Workbook

Sheet Ascendus DATA
A1: Customer Account: Name 1 | B1: Fiscal Year | C1: Posting Date | D1: Document Type | E1: Document Date | F1: Reference | G1: Document Currency Key | H1: Document Currency Value | I1: Company Code Currency Key | J1: Company Code Currency Value | K1: Text
A2: KUEHNE+NAGEL PVT. LTD. | B2: 2025 | C2: 45848 | D2: DG | E2: 45848 | F2: 256779421326 | G2: USD | H2: -70.8 | I2: INR | J2: -6088.85 | K2: Credit note raised against INV 256779414309
A3: KUEHNE+NAGEL PVT. LTD. | B3: 2025 | C3: 45848 | D3: DG | E3: 45848 | F3: 256779421327 | G3: USD | H3: -113.28 | I3: INR | J3: -9742.16 | K3: Credit note raised against INV 256779414309
A4: KUEHNE+NAGEL PVT. LTD. | B4: 2025 | C4: 45848 | D4: DG | E4: 45848 | F4: 256779421328 | G4: USD | H4: -242.75 | I4: INR | J4: -20876.66 | K4: Credit note raised against INV 256779414309
A5: KUEHNE+NAGEL PVT. LTD. | B5: 2025 | C5: 45904 | D5: DR | E5: 45904 | F5: 256779416909 | G5: USD | H5: 989.55 | I5: INR | J5: 86599.81 | K5: CODC Inbound chgs - 16-31 Aug 25
A6: KUEHNE+NAGEL PVT. LTD. | B6: 2025 | C6: 45904 | D6: DR | E6: 45904 | F6: 256779417134 | G6: USD | H6: 536.44 | I6: INR | J6: 46946.19 | K6: VAS - 16-31 Aug 25
A7: KUEHNE+NAGEL PVT. LTD. | B7: 2025 | C7: 45904 | D7: DR | E7: 45904 | F7: 256779417137 | G7: USD | H7: 409.79 | I7: INR | J7: 35862.5 | K7: WEIGHMENT - 16-31 Aug 25
A8: KUEHNE+NAGEL PVT. LTD. | B8: 2025 | C8: 45904 | D8: DR | E8: 45904 | F8: 256779417158 | G8: USD | H8: 110 | I8: INR | J8: 9626.58 | K8: Intra 16-31 Aug 25
A9: KUEHNE+NAGEL PVT. LTD. | B9: 2025 | C9: 45904 | D9: DR | E9: 45904 | F9: 256779417200 | G9: USD | H9: 100.74 | I9: INR | J9: 8816.19 | K9: Empty Lolo Chgs - 01 - 31 AUG 25
A10: KUEHNE+NAGEL PVT. LTD. | B10: 2025 | C10: 45904 | D10: DR | E10: 45904 | F10: 256779417238 | G10: USD | H10: 608.78 | I10: INR | J10: 53276.97 | K10: PORT SSR Chgs Aug 25
A11: KUEHNE+NAGEL PVT. LTD. | B11: 2025 | C11: 45904 | D11: DR | E11: 45904 | F11: 256779417250 | G11: USD | H11: 50 | I11: INR | J11: 4375.72 | K11: Scanning Chgs - 16 - 31 Aug 25
A12: KUEHNE+NAGEL PVT. LTD. | B12: 2025 | C12: 45904 | D12: DR | E12: 45904 | F12: 256779417257 | G12: USD | H12: 22.77 | I12: INR | J12: 1992.7 | K12: Bond Stamp Paper Chgs 01 - 31 Aug 25
A13: KUEHNE+NAGEL PVT. LTD. | B13: 2025 | C13: 45904 | D13: DR | E13: 45904 | F13: 256779417280 | G13: USD | H13: 249.98 | I13: INR | J13: 21876.83 | K13: LCL Chgs - 16 - 31 AUG 25
... A263: KUEHNE+NAGEL PVT. LTD. | B263: 2026 | C263: 46027 | D263: DR | E263: 46027 | F263: 256779440116 | G263: USD | H263: 498.28 | I263: INR | J263: 45215.49 | K263: LCL Chgs - 01 - 15 DEC 25
A264: KUEHNE+NAGEL PVT. LTD. | B264: 2026 | C264: 46030 | D264: DZ | E264: 46030 | G264: INR | H264: -719881.09 | I264: INR | J264: -719881.09
A265: KUEHNE+NAGEL PVT. LTD. | B265: 2026 | C265: 46031 | D265: DR | E265: 46031 | F265: 256779440126 | G265: USD | H265: 122.48 | I265: INR | J265: 11114.22 | K265: CODC Out chgs -1-15 Nov 25
A266: KUEHNE+NAGEL PVT. LTD. | B266: 2026 | C266: 46031 | D266: DR | E266: 46031 | F266: 256779440136 | G266: USD | H266: 27.81 | I266: INR | J266: 2523.57 | K266: Internet Activity Chgs - Dec 25
A267: KUEHNE+NAGEL PVT. LTD. | B267: 2026 | C267: 46028 | D267: DR | E267: 46028 | F267: 256779440150 | G267: USD | H267: 112.85 | I267: INR | J267: 10240.36 | K267: Empty Lolo Chgs - 01 - 31 DEC 25
A268: KUEHNE+NAGEL PVT. LTD. | B268: 2026 | C268: 46028 | D268: DR | E268: 46028 | F268: 256779440159 | G268: USD | H268: 160.22 | I268: INR | J268: 14538.87 | K268: PORT SSR Chgs Dec 25
A269: KUEHNE+NAGEL PVT. LTD. | B269: 2026 | C269: 46028 | D269: DR | E269: 46028 | F269: 256779440208 | G269: USD | H269: 650.12 | I269: INR | J269: 58993.93 | K269: LCL Chgs - 16 - 31 DEC 25
A270: KUEHNE+NAGEL PVT. LTD. | B270: 2026 | C270: 46034 | D270: DR | E270: 46034 | F270: 256779440227 | G270: USD | H270: 304.07 | I270: INR | J270: 27592.27 | K270: Outbound chgs - 16 - 31 Dec 25
A271: KUEHNE+NAGEL PVT. LTD. | B271: 2026 | C271: 46028 | D271: DR | E271: 46028 | F271: 256779440238 | G271: USD | H271: 1083.58 | I271: INR | J271: 98327.45 | K271: Unit Storage - 1-31 DEC 2025
A272: KUEHNE+NAGEL PVT. LTD. | B272: 2026 | C272: 46034 | D272: DR | E272: 46034 | F272: 256779440285 | G272: USD | H272: 535.29 | I272: INR | J272: 48573.9 | K272: VAS-Dec 25 - 16-31
A273: KUEHNE+NAGEL PVT. LTD. | B273: 2026 | C273: 46028 | D273: DR | E273: 46028 | F273: 256779440309 | G273: INR | H273: 200000 | I273: INR | J273: 200000 | K273: Fixed Storage Charges for January 2026
A274: KUEHNE+NAGEL PVT. LTD. | B274: 2026 | C274: 46028 | D274: DR | E274: 46028 | F274: 256779440310 | G274: INR | H274: 8000 | I274: INR | J274: 8000 | K274: Fixed Storage Charges for January 2026
A275: KUEHNE+NAGEL PVT. LTD. | B275: 2026 | C275: 46028 | D275: DR | E275: 46028 | F275: 256779440311 | G275: INR | H275: 4400 | I275: INR | J275: 4400 | K275: Fixed Storage Charges for January 2026
A276: KUEHNE+NAGEL PVT. LTD. | B276: 2026 | C276: 46035 | D276: DR | E276: 46035 | F276: 256779440363 | G276: USD | H276: 937.45 | I276: INR | J276: 85067.16 | K276: VAS - NOV 25,16-30
... A565: KUEHNE+NAGEL PVT. LTD. | B565: 2025 | C565: 45848 | D565: DR | E565: 45848 | F565: 256779415363 | G565: USD | H565: 3 | I565: INR | J565: 258 | K565: Outbound Handling for Aug 2024
A566: KUEHNE+NAGEL PVT. LTD. | B566: 2025 | C566: 45861 | D566: DZ | E566: 45861 | G566: USD | H566: 0 | I566: INR | J566: 0
A567: KUEHNE+NAGEL PVT. LTD. | B567: 2025 | C567: 45861 | D567: DZ | E567: 45861 | G567: USD | H567: 0 | I567: INR | J567: 0
A568: KUEHNE+NAGEL PVT. LTD. | B568: 2025 | C568: 45861 | D568: DZ | E568: 45861 | G568: USD | H568: 0 | I568: INR | J568: 0
A569: KUEHNE+NAGEL PVT. LTD. | B569: 2025 | C569: 45861 | D569: DZ | E569: 45861 | G569: USD | H569: 0 | I569: INR | J569: 0
A570: KUEHNE+NAGEL PVT. LTD. | B570: 2025 | C570: 45861 | D570: DZ | E570: 45861 | G570: USD | H570: 0 | I570: INR | J570: 0
A571: KUEHNE+NAGEL PVT. LTD. | B571: 2025 | C571: 45861 | D571: DZ | E571: 45861 | G571: USD | H571: 0 | I571: INR | J571: 0
A572: KUEHNE+NAGEL PVT. LTD. | B572: 2025 | C572: 45861 | D572: DZ | E572: 45861 | G572: USD | H572: 0 | I572: INR | J572: 0
A573: KUEHNE+NAGEL PVT. LTD. | B573: 2025 | C573: 45758 | D573: DA | E573: 45758 | G573: INR | H573: 1 | I573: INR | J573: 1 | K573: Overpayment
A574: KUEHNE+NAGEL PVT. LTD. | B574: 2025 | C574: 45758 | D574: DA | E574: 45758 | G574: INR | H574: -1 | I574: INR | J574: -1 | K574: Overpayment
A575: KUEHNE+NAGEL PVT. LTD. | B575: 2025 | C575: 45902 | D575: DY | E575: 45902 | G575: INR | H575: 212521.54 | I575: INR | J575: 208845.74
A576: KUEHNE+NAGEL PVT. LTD. | B576: 2025 | C576: 45902 | D576: DY | E576: 45902 | G576: INR | H576: -212521.54 | I576: INR | J576: -207607.52
A577: KUEHNE+NAGEL PVT. LTD. | B577: 2025 | C577: 45974 | D577: DZ | E577: 45974 | G577: USD | H577: 4603.48 | I577: INR | J577: 396450.85
A578: KUEHNE+NAGEL PVT. LTD. | B578: 2025 | C578: 45974 | D578: DZ | E578: 45974 | G578: USD | H578: 2.98 | I578: INR | J578: 262.21
A579: KUEHNE+NAGEL PVT. LTD. | B579: 2025 | C579: 45974 | D579: DZ | E579: 45974 | G579: USD | H579: -2.98 | I579: INR | J579: -262.21
A580: KUEHNE+NAGEL PVT. LTD. | B580: 2025 | C580: 45974 | D580: DZ | E580: 45974 | G580: USD | H580: 5558.96 | I580: INR | J580: 478086.37
A581: KUEHNE+NAGEL PVT. LTD. | B581: 2025 | C581: 45974 | D581: DZ | E581: 45974 | G581: USD | H581: -3891.99 | I581: INR | J581: -338298.81
A582: KUEHNE+NAGEL PVT. LTD. | B582: 2025 | C582: 45974 | D582: DZ | E582: 45974 | G582: USD | H582: -6270.45 | I582: INR | J582: -536832.3
A583: KUEHNE+NAGEL PVT. LTD. | B583: 2025 | C583: 45974 | D583: DZ | E583: 45974 | G583: INR | H583: 77508.99 | I583: INR | J583: 75771.03
A584: KUEHNE+NAGEL PVT. LTD. | B584: 2025 | C584: 45974 | D584: DZ | E584: 45974 | G584: INR | H584: -20130.78 | I584: INR | J584: -20130.78
A585: KUEHNE+NAGEL PVT. LTD. | B585: 2025 | C585: 45974 | D585: DZ | E585: 45974 | G585: INR | H585: -746.27 | I585: INR | J585: -746.27
A586: KUEHNE+NAGEL PVT. LTD. | B586: 2025 | C586: 45974 | D586: DZ | E586: 45974 | G586: INR | H586: -24772.95 | I586: INR | J586: -24772.95
... A591: KUEHNE+NAGEL PVT. LTD. | B591: 2025 | C591: 45987 | D591: DZ | E591: 45987 | G591: INR | H591: -1917961.2 | I591: INR | J591: -1917961.2
A592: KUEHNE+NAGEL PVT. LTD. | B592: 2025 | C592: 45744 | D592: XC | E592: 45701 | F592: 6779ZR25000004 | G592: INR | H592: 1 | I592: INR | J592: 1 | K592: Overpayment
A593: KUEHNE+NAGEL PVT. LTD. | B593: 2025 | C593: 45701 | D593: XC | E593: 45701 | F593: 6779ZP25000139 | G593: INR | H593: -1 | I593: INR | J593: -1 | K593: Overpayment
A594: KUEHNE+NAGEL PVT. LTD. | B594: 2025 | C594: 45764 | D594: DR | E594: 45764 | F594: 256779412140 | G594: INR | H594: 262.21 | I594: INR | J594: 262.21 | K594: Fixed Storage Charges for April 2025
A595: KUEHNE+NAGEL PVT. LTD. | B595: 2025 | C595: 45735 | D595: DR | E595: 45735 | F595: 246779413076 | G595: USD | H595: 466.37 | I595: INR | J595: 40430.2 | K595: Port SSR Charges - Shifting for Aug to Dec,24.
A596: KUEHNE+NAGEL PVT. LTD. | B596: 2025 | C596: 45787 | D596: DR | E596: 45787 | F596: 256779413147 | G596: INR | H596: 8000 | I596: INR | J596: 8000 | K596: Fixed Storage Charges fo MAY 2025
A597: KUEHNE+NAGEL PVT. LTD. | B597: 2025 | C597: 45818 | D597: DR | E597: 45818 | F597: 256779414359 | G597: INR | H597: 8000 | I597: INR | J597: 8000 | K597: Fixed Storage Charges fo JUNE 2025
A598: KUEHNE+NAGEL PVT. LTD. | B598: 2025 | C598: 45842 | D598: DR | E598: 45842 | F598: 256779414917 | G598: INR | H598: 8000 | I598: INR | J598: 8000 | K598: Fixed Storage Charges fo JULY 2025
A599: KUEHNE+NAGEL PVT. LTD. | B599: 2025 | C599: 45870 | D599: DR | E599: 45870 | F599: 256779416029 | G599: INR | H599: 8000 | I599: INR | J599: 8000 | K599: Fixed Storage Charges for August 2025
A600: KUEHNE+NAGEL PVT. LTD. | B600: 2025 | C600: 45904 | D600: DR | E600: 45904 | F600: 256779417349 | G600: INR | H600: 8000 | I600: INR | J600: 8000 | K600: Fixed Storage Charges for September 2025
A601: KUEHNE+NAGEL PVT. LTD. | B601: 2025 | C601: 45935 | D601: DR | E601: 45935 | F601: 256779417876 | G601: INR | H601: 8000 | I601: INR | J601: 8000 | K601: Fixed Storage Charges for October 2025
A602: KUEHNE+NAGEL PVT. LTD. | B602: 2025 | C602: 45966 | D602: DR | E602: 45966 | F602: 256779418778 | G602: INR | H602: 8000 | I602: INR | J602: 8000 | K602: Fixed Storage Charges for November 2025
A603: KUEHNE+NAGEL PVT. LTD. | B603: 2025 | C603: 45995 | D603: DR | E603: 45995 | F603: 256779419971 | G603: INR | H603: 8000 | I603: INR | J603: 8000 | K603: Fixed Storage Charges for December 2025
A604: KUEHNE+NAGEL PVT. LTD. | B604: 2025 | C604: 45787 | D604: DR | E604: 45787 | F604: 256779413148 | G604: INR | H604: 4400 | I604: INR | J604: 4400 | K604: Fixed Storage Charges fo MAY 2025
A605: KUEHNE+NAGEL PVT. LTD. | B605: 2025 | C605: 45818 | D605: DR | E605: 45818 | F605: 256779414360 | G605: INR | H605: 4400 | I605: INR | J605: 4400 | K605: Fixed Storage Charges fo JUNE 2025
... A707: KUEHNE+NAGEL PVT. LTD. | B707: 2025 | C707: 45733 | D707: DR | E707: 45733 | F707: 246779411738 | G707: USD | H707: 28.54 | I707: INR | J707: 2474.17 | K707: VAS Activity Charges for the month of October, 24

Sheet Summary 
A2: Reconciliation of Ledger as on 31st January 2026
A3: Particulars | B3: Amount
A4: Balance as per Kuehne Nagel Pvt Ltd | B4: =-[1]A023951!$H$1116 -> 1386783.8
A5: Add: TDS recorded by customer but not in our books | B5: 233116.04
A6: Less: Amount recorded by customer, but not in our books | B6: -165435.46 | C6: This is Foreign Exchange Gain/loss in customers books confirmed by Customer team in Meeting
A7: Add: Difference in INR amounts in both books due to exchange rate | B7: 51209.63 | C7: This is Foreign Exchange Gain/loss in customers books confirmed by Customer team in Meeting
A8: Add: Invoices / CN not recorded in customer books | B8: ='Invoices not in customer''s Book'!I142+'CN Not in Customer''s Books'!G147 -> 2942083.2 | C8: To be discussed with customer
A9: Less: Exchange gain loss recorded by customer | B9: -7126.86
A10: Add: Diffrence in Payment recorded in both books due to exchange gain/loss | B10: =SUM('Payment Reco'!E3:E20) -> 2110.18
A11: Add: Payments recorded in Feb by Ascendus | B11: =('Payment Reco'!E21+'Payment Reco'!E22) -> 1878132.8 | C11: Confirmed by Sushil over call
A12: Derived balance | B12: =SUM(B4:B11) -> 6320873.3
A13: Balance as per Ascendus | B13: =[2]Sheet1!$T$709 -> 6321328.8
A15: Difference | B15: =B12-B13-B14 -> -455.44

Sheet Biling Reco
A1: As per Customer | G1: As per Ascendus
A2: Years | B2: Item Date | C2: Debit Note | D2: Expense | E2: Foreign Exchange Diffrence | F2: Net Amount | G2: Years | H2: Document Date | I2: Credit | J2: Expense | K2: Net Amount | L2: Diffrence
A3: 2025 | B3: Jan | D3: -217492.45 | F3: =SUM(C3:E3) -> -217492.45 | G3: 2025 | H3: Jan | K3: =SUM(I3:J3) -> 0 | L3: =K3+F3 -> -217492.45
A4: 2025 | B4: Feb | D4: -1520432.9 | F4: =SUM(C4:E4) -> -1520432.9 | G4: 2025 | H4: Feb | J4: 1514515.3 | K4: =SUM(I4:J4) -> 1514515.3 | L4: =K4+F4 -> -5917.55
A5: 2025 | B5: Mar | C5: 21719.38 | D5: -1191118 | F5: =SUM(C5:E5) -> -1169398.7 | G5: 2025 | H5: Mar | J5: 1933380.6 | K5: =SUM(I5:J5) -> 1933380.6 | L5: =K5+F5 -> 763981.97
A6: 2025 | B6: Apr | D6: -2932698.5 | F6: =SUM(C6:E6) -> -2932698.5 | G6: 2025 | H6: Apr | J6: 2087965.7 | K6: =SUM(I6:J6) -> 2087965.7 | L6: =K6+F6 -> -844732.75
A7: 2025 | B7: May | D7: -1341898.7 | F7: =SUM(C7:E7) -> -1341898.7 | G7: 2025 | H7: May | I7: -595574.41 | J7: 1044919.9 | K7: =SUM(I7:J7) -> 449345.53 | L7: =K7+F7 -> -892553.19
A8: 2025 | B8: Jun | D8: -796400.32 | F8: =SUM(C8:E8) -> -796400.32 | G8: 2025 | H8: Jun | J8: 1761603.8 | K8: =SUM(I8:J8) -> 1761603.8 | L8: =K8+F8 -> 965203.51
A9: 2025 | B9: Jul | D9: -266105.72 | F9: =SUM(C9:E9) -> -266105.72 | G9: 2025 | H9: Jul | I9: -1464659.3 | J9: 2492881.5 | K9: =SUM(I9:J9) -> 1028222.2 | L9: =K9+F9 -> 762116.44
A10: 2025 | B10: Aug | D10: -937708 | F10: =SUM(C10:E10) -> -937708 | G10: 2025 | H10: Aug | I10: -170239.97 | J10: 1305423 | K10: =SUM(I10:J10) -> 1135183.1 | L10: =K10+F10 -> 197475.05
A11: 2025 | B11: Sep | C11: 16556.76 | D11: -673577.15 | F11: =SUM(C11:E11) -> -657020.39 | G11: 2025 | H11: Sep | J11: =1564779.07+1238.22 -> 1566017.3 | K11: =SUM(I11:J11) -> 1566017.3 | L11: =K11+F11 -> 908996.9
A12: 2025 | B12: Oct | D12: -1793002.9 | F12: =SUM(C12:E12) -> -1793002.9 | G12: 2025 | H12: Oct | I12: -8361.37 | J12: 1113806.7 | K12: =SUM(I12:J12) -> 1105445.3 | L12: =K12+F12 -> -687557.56
A13: 2025 | B13: Nov | D13: -80394.56 | F13: =SUM(C13:E13) -> -80394.56 | G13: 2025 | H13: Nov | I13: -405590.02 | J13: 1574052.7 | K13: =SUM(I13:J13) -> 1168462.7 | L13: =K13+F13 -> 1088068.1
A14: 2025 | B14: Dec | F14: =SUM(C14:E14) -> 0 | G14: 2025 | H14: Dec | J14: 282835.01 | K14: =SUM(I14:J14) -> 282835.01 | L14: =K14+F14 -> 282835.01
A15: 2026 | B15: Jan | E15: -45403 | F15: =SUM(C15:E15) -> -45403 | G15: 2026 | H15: Jan | I15: -52265.33 | J15: 831546.81 | K15: =SUM(I15:J15) -> 779281.48 | L15: =K15+F15 -> 733878.48
A16: Total | C16: =SUM(C3:C15) -> 38276.14 | D16: =SUM(D3:D15) -> -11750829 | E16: =SUM(E3:E15) -> -45403 | F16: =SUM(C16:E16) -> -11757956 | G16: Total | I16: =SUM(I3:I15) -> -2696690.4 | J16: =SUM(J3:J15) -> 17508948 | K16: =SUM(I16:J16) -> 14812258 | L16: =K16+F16 -> 3054302
D18: =J16+D16 -> 5758119.3

Sheet Payment Reco
A1: As per Customer ledger | C1: As per Ascendus | E1: Amount
A2: Date | B2: Amount | C2: Date | D2: Amount | J2: As per Customer ledger | K2: As per Ascendus
A3: 45827 | B3: 1760137.8 | C3: 45940 | D3: -1746430.2 | E3: =B3+D3 -> 13707.54 | F3: >>Exchange diffrence | H3: 2025 | I3: Jan
A4: 45859 | B4: 2396201.3 | C4: 45940 | D4: -2385234 | E4: =B4+D4 -> 10967.32 | F4: >>Exchange diffrence | H4: 2025 | I4: Feb
A5: 45859 | B5: 2396201.3 | E5: =B5+D5 -> 2396201.3 | H5: 2025 | I5: May
A6: 45869 | B6: -2396201.3 | E6: =B6+D6 -> -2396201.3 | H6: 2025 | I6: June | J6: =B3 -> 1760137.8
A7: 45954 | B7: 1721315.8 | C7: 45958 | D7: -1719090.9 | E7: =B7+D7 -> 2224.91 | F7: >>Exchange diffrence | H7: 2025 | I7: July | J7: =B4 -> 2396201.3
C8: 45974 | D8: 396450.85 | E8: =B8+D8 -> 396450.85 | H8: 2025 | I8: Aug
C9: 45974 | D9: 262.21 | E9: =B9+D9 -> 262.21 | H9: 2025 | I9: Sep
C10: 45974 | D10: -262.21 | E10: =B10+D10 -> -262.21 | H10: 2025 | I10: Oct | J10: 1721315.8 | K10: -5850755.1
C11: 45974 | D11: 478086.37 | E11: =B11+D11 -> 478086.37 | H11: 2025 | I11: Nov | J11: 1899719.6 | K11: -1920293.1
C12: 45974 | D12: -338298.81 | E12: =B12+D12 -> -338298.81 | H12: 2025 | I12: Dec | J12: 715665.04
C13: 45974 | D13: -536832.3 | E13: =B13+D13 -> -536832.3 | H13: 2026 | I13: Jan | J13: 1878132.8 | K13: -719881.09
C14: 45974 | D14: 75771.03 | E14: =B14+D14 -> 75771.03 | H14: Total | J14: =SUM(J3:J13) -> 10371172 | K14: =SUM(K3:K13) -> -8490929.3 | L14: =SUM(J14:K14) -> 1880243
C15: 45974 | D15: -20130.78 | E15: =B15+D15 -> -20130.78
C16: 45974 | D16: -746.27 | E16: =B16+D16 -> -746.27
C17: 45974 | D17: -24772.95 | E17: =B17+D17 -> -24772.95
C18: 45974 | D18: -31858.99 | E18: =B18+D18 -> -31858.99
A19: 45982 | B19: 1899719.6 | C19: 45987 | D19: -1917961.2 | E19: =B19+D19 -> -18241.69 | F19: >>Exchange diffrence
A20: 46014 | B20: 715665.04 | C20: 46030 | D20: -719881.09 | E20: =B20+D20 -> -4216.05 | F20: >>Exchange diffrence
A21: 46052 | B21: 1869680.8 | E21: =B21+D21 -> 1869680.8 | F21: >>payment not recorded in books
A22: 46053 | B22: 8452 | E22: =B22+D22 -> 8452 | F22: >>payment not recorded in books
B23: =SUM(B3:B22) -> 10371172 | D23: =SUM(D3:D21) -> -8490929.3 | E23: =SUM(E3:E22) -> 1880243

Sheet Pivot data
A3: Sum of LC Amount | D3: Ty
A4: Years | B4: Quarters | C4: Item Date | D4: A | E4: C | F4: I | G4: S
A5: 2025 | B5: Qtr1 | C5: Jan | F5: -217492.45
C6: Feb | F6: -1520432.9
C7: Mar | E7: 21719.38 | F7: -1191118
B8: Qtr2 | C8: Apr | F8: -2932698.5
C9: May | F9: -1341898.7
C10: Jun | D10: 1760137.8 | F10: -796400.32
B11: Qtr3 | C11: Jul | D11: 2396201.3 | F11: -266105.72
C12: Aug | F12: -937708
C13: Sep | E13: 16556.76 | F13: -673577.15
B14: Qtr4 | C14: Oct | D14: 1721315.8 | F14: -1793002.9
C15: Nov | D15: 1899719.6 | F15: -80394.56
C16: Dec | D16: 715665.04
A17: 2026 | B17: Qtr1 | C17: Jan | D17: 1878132.8 | G17: -45403

Sheet Invoices not in customer's Book
A1: Customer Account: Name 1 | B1: Fiscal Year | C1: Document Type | D1: Document Date | E1: Reference | F1: Document Currency Key | G1: Document Currency Value | H1: Company Code Currency Key | I1: Company Code Currency Value | J1: Text | K1: Amount In USD | L1: Amount In INR | M1: Diffrecnce
A2: KUEHNE+NAGEL PVT. LTD. | B2: 2025 | C2: DR | D2: 45719 | E2: 246779410482 | F2: USD | G2: 3.54 | H2: INR | I2: 306.89 | J2: Outbound Handling for Aug 2024 | K2: #N/A
A3: KUEHNE+NAGEL PVT. LTD. | B3: 2025 | C3: DR | D3: 45719 | E3: 246779410483 | F3: USD | G3: 3.54 | H3: INR | I3: 306.89 | J3: Outbound Handling for Aug 2024 | K3: #N/A
A4: KUEHNE+NAGEL PVT. LTD. | B4: 2025 | C4: DR | D4: 45730 | E4: 246779412207 | F4: USD | G4: 312.5 | H4: INR | I4: 27091.02 | J4: VAS Activity Charges for the month of August, 24 | K4: #N/A
A5: KUEHNE+NAGEL PVT. LTD. | B5: 2025 | C5: DR | D5: 45730 | E5: 246779412208 | F5: USD | G5: 23.35 | H5: INR | I5: 2024.24 | J5: VAS Activity Charges for the month of August, 24 | K5: #N/A
A6: KUEHNE+NAGEL PVT. LTD. | B6: 2025 | C6: DR | D6: 45730 | E6: 246779412197 | F6: USD | G6: 40.06 | H6: INR | I6: 3472.85 | J6: VAS Activity Charges for the month of August, 24 | K6: #N/A
A7: KUEHNE+NAGEL PVT. LTD. | B7: 2025 | C7: DR | D7: 45730 | E7: 246779412198 | F7: USD | G7: 249.55 | H7: INR | I7: 21633.8 | J7: VAS Activity Charges for the month of August, 24 | K7: #N/A
A8: KUEHNE+NAGEL PVT. LTD. | B8: 2025 | C8: DR | D8: 45730 | E8: 246779412199 | F8: USD | G8: 40.06 | H8: INR | I8: 3472.85 | J8: VAS Activity Charges for the month of August, 24 | K8: #N/A
A9: KUEHNE+NAGEL PVT. LTD. | B9: 2025 | C9: DR | D9: 45730 | E9: 246779412200 | F9: USD | G9: 45.79 | H9: INR | I9: 3969.59 | J9: VAS Activity Charges for the month of August, 24 | K9: #N/A
A10: KUEHNE+NAGEL PVT. LTD. | B10: 2025 | C10: DR | D10: 45730 | E10: 246779412202 | F10: USD | G10: 40.06 | H10: INR | I10: 3472.85 | J10: VAS Activity Charges for the month of August, 24 | K10: #N/A
A11: KUEHNE+NAGEL PVT. LTD. | B11: 2025 | C11: DR | D11: 45730 | E11: 246779412203 | F11: USD | G11: 28.62 | H11: INR | I11: 2481.1 | J11: VAS Activity Charges for the month of August, 24 | K11: #N/A
A12: KUEHNE+NAGEL PVT. LTD. | B12: 2025 | C12: DR | D12: 45730 | E12: 246779412204 | F12: USD | G12: 22.89 | H12: INR | I12: 1984.36 | J12: VAS Activity Charges for the month of August, 24 | K12: #N/A
A13: KUEHNE+NAGEL PVT. LTD. | B13: 2025 | C13: DR | D13: 45730 | E13: 246779412205 | F13: USD | G13: 114.46 | H13: INR | I13: 9922.68 | J13: VAS Activity Charges for the month of August, 24 | K13: #N/A
... A141: KUEHNE+NAGEL PVT. LTD. | B141: 2026 | C141: DR | D141: 46049 | E141: 256779440443 | F141: USD | G141: 18.41 | H141: INR | I141: 1670.58 | J141: VAS-1-15 Jan 2026 | K141: #N/A
I142: =SUM(I2:I141) -> 5638773.6
I143: -2696690.4
I144: =I142+I143 -> 2942083.2
I145: 3054302
I146: =I145-I144 -> 112218.79

Sheet CN Not in Customer's Books
A1: Document Type | B1: Document Date | C1: Reference | D1: Document Currency Key | E1: Document Currency Value | F1: Company Code Currency Key | G1: Company Code Currency Value | H1: Text
A2: DG | B2: 45848 | C2: 256779421326 | D2: USD | E2: -70.8 | F2: INR | G2: -6088.85 | H2: Credit note raised against INV 256779414309 | I2: =MID(H2,32,15) -> 256779414309 | J2: 256779414309
A3: DG | B3: 45848 | C3: 256779421327 | D3: USD | E3: -113.28 | F3: INR | G3: -9742.16 | H3: Credit note raised against INV 256779414309 | I3: =MID(H3,32,15) -> 256779414309 | J3: 256779414309
A4: DG | B4: 45848 | C4: 256779421328 | D4: USD | E4: -242.75 | F4: INR | G4: -20876.66 | H4: Credit note raised against INV 256779414309 | I4: =MID(H4,32,15) -> 256779414309 | J4: 256779414309
A5: DG | B5: 45964 | C5: 256779422067 | D5: USD | E5: -4608.8 | F5: INR | G5: -405590.02 | H5: CN issued against 256779417093 | I5: =MID(H5,18,15) -> 256779417093 | J5: 256779417093
A6: DG | B6: 45791 | C6: 256779420272 | D6: USD | E6: -40.06 | F6: INR | G6: -3472.85 | H6: Credit note against 246779412202 | I6: =MID(H6,20,15) -> 246779412202 | J6: 246779412202
A7: DG | B7: 45791 | C7: 256779420273 | D7: USD | E7: -28.62 | F7: INR | G7: -2481.1 | H7: Credit note against 246779412203 | I7: =MID(H7,20,15) -> 246779412203 | J7: 246779412203
A8: DG | B8: 45791 | C8: 256779420275 | D8: USD | E8: -114.46 | F8: INR | G8: -9922.68 | H8: Credit note against 246779412205 | I8: =MID(H8,20,15) -> 246779412205 | J8: 246779412205
A9: DG | B9: 45791 | C9: 256779420276 | D9: USD | E9: -68.68 | F9: INR | G9: -5953.96 | H9: Credit note against 246779412206 | I9: =MID(H9,20,15) -> 246779412206 | J9: 246779412206
A10: DG | B10: 45791 | C10: 256779420268 | D10: USD | E10: -249.55 | F10: INR | G10: -21633.8 | H10: Credit note against 246779412198 | I10: =MID(H10,20,15) -> 246779412198 | J10: 246779412198
A11: DG | B11: 45791 | C11: 256779420269 | D11: USD | E11: -40.06 | F11: INR | G11: -3472.85 | H11: Credit note against 246779412199 | I11: =MID(H11,20,15) -> 246779412199 | J11: 246779412199
A12: DG | B12: 45791 | C12: 256779420274 | D12: USD | E12: -22.89 | F12: INR | G12: -1984.36 | H12: Credit note against 246779412204 | I12: =MID(H12,20,15) -> 246779412204 | J12: 246779412204
A13: DG | B13: 45791 | C13: 256779420277 | D13: USD | E13: -312.5 | F13: INR | G13: -27091.02 | H13: Credit note against 246779412207 | I13: =MID(H13,20,15) -> 246779412207 | J13: 246779412207
A14: DG | B14: 45791 | C14: 256779420278 | D14: USD | E14: -23.35 | F14: INR | G14: -2024.24 | H14: Credit note against 246779412208 | I14: =MID(H14,20,15) -> 246779412208 | J14: 246779412208
A15: DG | B15: 45791 | C15: 256779420266 | D15: USD | E15: -57.23 | F15: INR | G15: -4961.34 | H15: Credit note against 246779412196 | I15: =MID(H15,20,15) -> 246779412196 | J15: 246779412196
A16: DG | B16: 45791 | C16: 256779420267 | D16: USD | E16: -40.06 | F16: INR | G16: -3472.85 | H16: Credit note against 246779412197 | I16: =MID(H16,20,15) -> 246779412197 | J16: 246779412197
A17: DG | B17: 45791 | C17: 256779420270 | D17: USD | E17: -45.79 | F17: INR | G17: -3969.59 | H17: Credit note against 246779412200 | I17: =MID(H17,20,15) -> 246779412200 | J17: 246779412200
... A20: DG | B20: 45791 | C20: 256779420526 | D20: USD | E20: -2286.24 | F20: INR | G20: -198724.14 | H20: Credit note against 256779410272 | I20: =MID(H20,20,15) -> 256779410272 | J20: 256779410272
A21: DG | B21: 45873 | C21: 256779421623 | D21: USD | E21: -608.41 | F21: INR | G21: -52323.67 | H21: Credit note raised against 256779415792 | I21: =MID(H21,28,15) -> 256779415792 | J21: 256779415792
A22: DG | B22: 45862 | C22: 256779421498 | D22: USD | E22: -95.24 | F22: INR | G22: -8190.7 | H22: Credit note raised against 256779414430 | I22: =MID(H22,28,15) -> 256779414430 | J22: 256779414430
A23: DG | B23: 45862 | C23: 256779421512 | D23: USD | E23: -2333.18 | F23: INR | G23: -200655.04 | H23: Credit note raised against 256779414445 | I23: =MID(H23,28,15) -> 256779414445 | J23: 256779414445
A24: DG | B24: 45800 | C24: 256779421106 | D24: USD | E24: -707.71 | F24: INR | G24: -60851.52 | H24: Credit Note against 256779413161 | I24: =MID(H24,20,15) -> 256779413161 | J24: 256779413161
A25: DG | B25: 45800 | C25: 256779421109 | D25: USD | E25: -3.78 | F25: INR | G25: -325.02 | H25: Credit Note against 256779413169 | I25: =MID(H25,20,15) -> 256779413169 | J25: 256779413169
A26: DG | B26: 45890 | C26: 256779421698 | D26: USD | E26: -30 | F26: INR | G26: -2580.9 | H26: CN ISSUED TOWARDS BILL NO.256779415304 | I26: =MID(H26,27,15) -> 256779415304 | J26: 256779415304
A27: DG | B27: 45890 | C27: 256779421699 | D27: USD | E27: -30 | F27: INR | G27: -2580.9 | H27: CN ISSUED TOWARDS BILL NO.256779415305 | I27: =MID(H27,27,15) -> 256779415305 | J27: 256779415305
A28: DG | B28: 45890 | C28: 256779421700 | D28: USD | E28: -30 | F28: INR | G28: -2580.9 | H28: CN ISSUED TOWARDS BILL NO.256779415306 | I28: =MID(H28,27,15) -> 256779415306 | J28: 256779415306
A29: DG | B29: 45890 | C29: 256779421701 | D29: USD | E29: -30 | F29: INR | G29: -2580.9 | H29: CN ISSUED TOWARDS BILL NO.256779415307 | I29: =MID(H29,27,15) -> 256779415307 | J29: 256779415307
A30: DG | B30: 45890 | C30: 256779421702 | D30: USD | E30: -30 | F30: INR | G30: -2580.9 | H30: CN ISSUED TOWARDS BILL NO.256779415308 | I30: =MID(H30,27,15) -> 256779415308 | J30: 256779415308
A31: DG | B31: 45890 | C31: 256779421703 | D31: USD | E31: -27.39 | F31: INR | G31: -2356.36 | H31: CN ISSUED TOWARDS BILL NO.256779415339 | I31: =MID(H31,27,15) -> 256779415339 | J31: 256779415339
A32: DG | B32: 45890 | C32: 256779421705 | D32: USD | E32: -212.5 | F32: INR | G32: -18281.4 | H32: CN ISSUED TOWARDS BILL NO.256779415321 | I32: =MID(H32,27,15) -> 256779415321 | J32: 256779415321
A33: DG | B33: 45890 | C33: 256779421706 | D33: USD | E33: -362.02 | F33: INR | G33: -31144.62 | H33: CN ISSUED TOWARDS BILL NO.256779415374 | I33: =MID(H33,27,15) -> 256779415374 | J33: 256779415374
A34: DG | B34: 45890 | C34: 256779421707 | D34: USD | E34: -228.75 | F34: INR | G34: -19679.39 | H34: CN ISSUED TOWARDS BILL NO.246779414662 | I34: =MID(H34,27,15) -> 246779414662 | J34: 246779414662
A35: DG | B35: 45890 | C35: 256779421708 | D35: USD | E35: -281.5 | F35: INR | G35: -24217.48 | H35: CN ISSUED TOWARDS BILL NO.256779415365 | I35: =MID(H35,27,15) -> 256779415365 | J35: 256779415365
A36: DG | B36: 45799 | C36: 256779420844 | D36: INR | E36: -262.21 | F36: INR | G36: -262.21 | H36: Credit Note against 256779412140 | I36: =MID(H36,20,15) -> 256779412140 | J36: 256779412140
A37: DG | B37: 45799 | C37: 256779420845 | D37: USD | E37: -466.37 | F37: INR | G37: -40430.2 | H37: Credit Note against 246779413076 | I37: =MID(H37,20,15) -> 246779413076 | J37: 246779413076
A38: DG | B38: 46027 | C38: 256779422164 | D38: USD | E38: -562.38 | F38: INR | G38: -51032.13 | H38: Credit note for Duplicate invoice -256779418489 | I38: =MID(H38,36,15) -> 256779418489 | J38: 256779418489
A39: DG | B39: 46027 | C39: 256779422170 | D39: USD | E39: -13.59 | F39: INR | G39: -1233.2 | H39: Credit note for Duplicate invoice -256779418495 | I39: =MID(H39,36,15) -> 256779418495 | J39: 256779418495
A40: DG | B40: 45848 | C40: 256779421222 | D40: USD | E40: -295 | F40: INR | G40: -25370.2 | H40: Credit note raised against INV 256779411867 | I40: =MID(H40,32,15) -> 256779411867 | J40: 256779411867
A41: DG | B41: 45848 | C41: 256779421223 | D41: USD | E41: -28.32 | F41: INR | G41: -2435.54 | H41: Credit note raised against INV 246779414057 | I41: =MID(H41,32,15) -> 246779414057 | J41: 246779414057
A42: DG | B42: 45848 | C42: 256779421224 | D42: USD | E42: -28.32 | F42: INR | G42: -2435.54 | H42: Credit note raised against INV 256779411091 | I42: =MID(H42,32,15) -> 256779411091 | J42: 256779411091
A43: DG | B43: 45848 | C43: 256779421225 | D43: USD | E43: -28.32 | F43: INR | G43: -2435.54 | H43: Credit note raised against INV 256779411092 | I43: =MID(H43,32,15) -> 256779411092 | J43: 256779411092
A44: DG | B44: 45848 | C44: 256779421226 | D44: USD | E44: -28.32 | F44: INR | G44: -2435.54 | H44: Credit note raised against INV 256779411093 | I44: =MID(H44,32,15) -> 256779411093 | J44: 256779411093
A45: DG | B45: 45848 | C45: 256779421227 | D45: USD | E45: -28.32 | F45: INR | G45: -2435.54 | H45: Credit note raised against INV 256779411094 | I45: =MID(H45,32,15) -> 256779411094 | J45: 256779411094
A46: DG | B46: 45848 | C46: 256779421228 | D46: USD | E46: -28.32 | F46: INR | G46: -2435.54 | H46: Credit note raised against INV 256779411095 | I46: =MID(H46,32,15) -> 256779411095 | J46: 256779411095
A47: DG | B47: 45848 | C47: 256779421229 | D47: USD | E47: -28.32 | F47: INR | G47: -2435.54 | H47: Credit note raised against INV 256779411096 | I47: =MID(H47,32,15) -> 256779411096 | J47: 256779411096
A48: DG | B48: 45848 | C48: 256779421230 | D48: USD | E48: -28.32 | F48: INR | G48: -2435.54 | H48: Credit note raised against INV 256779411098 | I48: =MID(H48,32,15) -> 256779411098 | J48: 256779411098
A49: DG | B49: 45848 | C49: 256779421231 | D49: USD | E49: -28.32 | F49: INR | G49: -2435.54 | H49: Credit note raised against INV 256779411099 | I49: =MID(H49,32,15) -> 256779411099 | J49: 256779411099
A50: DG | B50: 45848 | C50: 256779421232 | D50: USD | E50: -28.32 | F50: INR | G50: -2435.54 | H50: Credit note raised against INV 256779411100 | I50: =MID(H50,32,15) -> 256779411100 | J50: 256779411100
A51: DG | B51: 45848 | C51: 256779421233 | D51: USD | E51: -28.32 | F51: INR | G51: -2435.54 | H51: Credit note raised against INV 256779411101 | I51: =MID(H51,32,15) -> 256779411101 | J51: 256779411101
... A142: DG | B142: 45848 | C142: 256779421325 | D142: USD | E142: -236 | F142: INR | G142: -20296.16 | H142: Credit note raised against INV 256779414309 | I142: =MID(H142,32,15) -> 256779414309 | J142: 256779414309
A143: DG | B143: 45947 | C143: 256779422006 | D143: USD | E143: -94.81 | F143: INR | G143: -8361.37 | H143: Credit note raised against 256779418068 | I143: =MID(H143,28,15) -> 256779418068 | J143: 256779418068
A144: DG | B144: 45848 | C144: 256779421236 | D144: USD | E144: -118 | F144: INR | G144: -10148.08 | H144: Credit note raised against INV 256779411097 | I144: =MID(H144,32,15) -> 256779411097 | J144: 256779411097
A145: DG | B145: 45890 | C145: 256779421697 | D145: USD | E145: -100 | F145: INR | G145: -8603.01 | H145: CN ISSUED TOWARDS BILL NO.256779415303 | I145: =MID(H145,27,15) -> 256779415303 | J145: 256779415303
A146: DG | B146: 45890 | C146: 256779421704 | D146: USD | E146: -8.48 | F146: INR | G146: -729.54 | H146: CN ISSUED TOWARDS BILL NO.256779415349 | I146: =MID(H146,27,15) -> 256779415349 | J146: 256779415349
G147: =SUM(G2:G146) -> -2696690.4

Sheet Foreign Exchange difference
A1: Ty | B1: Item# | C1: Item Date | D1: FC Amount | E1: LC Amount | F1: Particular | G1: Due Date | H1: CCY | I1: VC Period | J1: VC Seq | K1: VC Date | L1: Tx. Type | M1: Company Code
A2: C | B2: 246779411409_R | C2: 45730 | D2: 249.55 | E2: 21721.43 | F2: NO EXCHANGE RATE | H2: USD | I2: 45839 | M2: 53826350
A3: C | B3: 246779411409_R | C3: 45730 | D3: 0 | E3: -2.05 | F3: C: ASCENDAS27 P: Matching | H3: USD | I3: 45839 | M3: 54969548
A4: C | B4: 256779417580_R | C4: 45918 | D4: 184.38 | E4: 184.38 | H4: USD | I4: 46023 | M4: 68208016
A5: S | B5: 2830735 | C5: 46053 | D5: 0 | E5: -7756 | F5: Exchange rate diference for JUN'25 USD 20175.95 | H5: INR | I5: 46023 | M5: 68369723
A6: S | B6: 2830736 | C6: 46053 | D6: 0 | E6: -15004 | F6: Exchange rate diference for JUL'25 USD 27632.46 | H6: INR | I6: 46023 | M6: 68369723
A7: S | B7: 2830738 | C7: 46053 | D7: 0 | E7: -17437 | F7: Exchange rate diference for NOV'25 USD 21525.94 | H7: INR | I7: 46023 | M7: 68369723
A8: S | B8: 2830739 | C8: 46053 | D8: 0 | E8: -5206 | F8: Exchange rate diference for DEC'25 USD 8027.22 | H8: INR | I8: 46023 | M8: 68369723
A9: C | B9: 256779417580_R | C9: 45918 | D9: -3.69 | E9: -3.69 | F9: C: ASCENDAS27 P: A023951 C 256779 | H9: USD | I9: 46023 | M9: 68389624
A10: C | B10: 256779417580_R | C10: 45918 | D10: 0 | E10: 16376.07 | F10: C: ASCENDAS27 P: Matching | H10: USD | I10: 46023 | M10: 68459189
E11: =SUM(E2:E10) -> -7126.86

Sheet Ascendus
A1: Customer Account: Name 1 | B1: Fiscal Year | C1: Document Type | D1: Document Date | E1: Reference | F1: Document Currency Key | G1: Document Currency Value | H1: Company Code Currency Key | I1: Company Code Currency Value | J1: Text | K1: Amount In USD | L1: Amount In INR | M1: Diffrecnce
A2: KUEHNE+NAGEL PVT. LTD. | B2: 2025 | C2: DG | D2: 45848 | E2: 256779421326 | F2: USD | G2: -70.8 | H2: INR | I2: -6088.85 | J2: Credit note raised against INV 256779414309 | K2: {=VLOOKUP(E2,[1]A023951!D$1:H$1114,{3,5},0)} -> #N/A
A3: KUEHNE+NAGEL PVT. LTD. | B3: 2025 | C3: DG | D3: 45848 | E3: 256779421327 | F3: USD | G3: -113.28 | H3: INR | I3: -9742.16 | J3: Credit note raised against INV 256779414309 | K3: {=VLOOKUP(E3,[1]A023951!D$1:H$1114,{3,5},0)} -> #N/A
A4: KUEHNE+NAGEL PVT. LTD. | B4: 2025 | C4: DG | D4: 45848 | E4: 256779421328 | F4: USD | G4: -242.75 | H4: INR | I4: -20876.66 | J4: Credit note raised against INV 256779414309 | K4: {=VLOOKUP(E4,[1]A023951!D$1:H$1114,{3,5},0)} -> #N/A
A5: KUEHNE+NAGEL PVT. LTD. | B5: 2025 | C5: DR | D5: 45904 | E5: 256779416909 | F5: USD | G5: 989.55 | H5: INR | I5: 86599.81 | J5: CODC Inbound chgs - 16-31 Aug 25 | K5: {=VLOOKUP(E5,[1]A023951!D$1:H$1114,{3,5},0)} -> -989.55 | L5: -87733 | M5: =I5+L5 -> -1133.19
A6: KUEHNE+NAGEL PVT. LTD. | B6: 2025 | C6: DR | D6: 45904 | E6: 256779417134 | F6: USD | G6: 536.44 | H6: INR | I6: 46946.19 | J6: VAS - 16-31 Aug 25 | K6: {=VLOOKUP(E6,[1]A023951!D$1:H$1114,{3,5},0)} -> -536.44 | L6: -47020 | M6: =I6+L6 -> -73.81
A7: KUEHNE+NAGEL PVT. LTD. | B7: 2025 | C7: DR | D7: 45904 | E7: 256779417137 | F7: USD | G7: 409.79 | H7: INR | I7: 35862.5 | J7: WEIGHMENT - 16-31 Aug 25 | K7: {=VLOOKUP(E7,[1]A023951!D$1:H$1114,{3,5},0)} -> -409.79 | L7: -35918.88 | M7: =I7+L7 -> -56.38
A8: KUEHNE+NAGEL PVT. LTD. | B8: 2025 | C8: DR | D8: 45904 | E8: 256779417158 | F8: USD | G8: 110 | H8: INR | I8: 9626.58 | J8: Intra 16-31 Aug 25 | K8: {=VLOOKUP(E8,[1]A023951!D$1:H$1114,{3,5},0)} -> -110 | L8: -9641.71 | M8: =I8+L8 -> -15.13
A9: KUEHNE+NAGEL PVT. LTD. | B9: 2025 | C9: DR | D9: 45904 | E9: 256779417200 | F9: USD | G9: 100.74 | H9: INR | I9: 8816.19 | J9: Empty Lolo Chgs - 01 - 31 AUG 25 | K9: {=VLOOKUP(E9,[1]A023951!D$1:H$1114,{3,5},0)} -> -100.74 | L9: -8830.05 | M9: =I9+L9 -> -13.86
A10: KUEHNE+NAGEL PVT. LTD. | B10: 2025 | C10: DR | D10: 45904 | E10: 256779417238 | F10: USD | G10: 608.78 | H10: INR | I10: 53276.97 | J10: PORT SSR Chgs Aug 25 | K10: {=VLOOKUP(E10,[1]A023951!D$1:H$1114,{3,5},0)} -> -608.78 | L10: -53360.74 | M10: =I10+L10 -> -83.77
A11: KUEHNE+NAGEL PVT. LTD. | B11: 2025 | C11: DR | D11: 45904 | E11: 256779417250 | F11: USD | G11: 50 | H11: INR | I11: 4375.72 | J11: Scanning Chgs - 16 - 31 Aug 25 | K11: {=VLOOKUP(E11,[1]A023951!D$1:H$1114,{3,5},0)} -> #N/A
A12: KUEHNE+NAGEL PVT. LTD. | B12: 2025 | C12: DR | D12: 45904 | E12: 256779417257 | F12: USD | G12: 22.77 | H12: INR | I12: 1992.7 | J12: Bond Stamp Paper Chgs 01 - 31 Aug 25 | K12: {=VLOOKUP(E12,[1]A023951!D$1:H$1114,{3,5},0)} -> -22.77 | L12: -1995.83 | M12: =I12+L12 -> -3.13
A13: KUEHNE+NAGEL PVT. LTD. | B13: 2025 | C13: DR | D13: 45904 | E13: 256779417280 | F13: USD | G13: 249.98 | H13: INR | I13: 21876.83 | J13: LCL Chgs - 16 - 31 AUG 25 | K13: {=VLOOKUP(E13,[1]A023951!D$1:H$1114,{3,5},0)} -> -249.98 | L13: -21911.23 | M13: =I13+L13 -> -34.4
A14: KUEHNE+NAGEL PVT. LTD. | B14: 2025 | C14: DR | D14: 45904 | E14: 256779417317 | F14: USD | G14: 170.85 | H14: INR | I14: 14951.82 | J14: Outbound chgs - 16 - 31 Aug 25 | K14: {=VLOOKUP(E14,[1]A023951!D$1:H$1114,{3,5},0)} -> -170.85 | L14: -14975.33 | M14: =I14+L14 -> -23.51
A15: KUEHNE+NAGEL PVT. LTD. | B15: 2025 | C15: DR | D15: 45842 | E15: 256779414859 | F15: USD | G15: 318.47 | H15: INR | I15: 27388.63 | J15: LCL Chgs - 16 - 30 JUN 25 | K15: {=VLOOKUP(E15,[1]A023951!D$1:H$1114,{3,5},0)} -> -318.47 | L15: -27385.08 | M15: =I15+L15 -> 3.55
A16: KUEHNE+NAGEL PVT. LTD. | B16: 2025 | C16: DR | D16: 45842 | E16: 256779415012 | F16: USD | G16: 184.3 | H16: INR | I16: 15849.92 | J16: Outbound chgs - 16 - 30 Jun 25 | K16: {=VLOOKUP(E16,[1]A023951!D$1:H$1114,{3,5},0)} -> -184 | L16: -15822.07 | M16: =I16+L16 -> 27.85
A17: KUEHNE+NAGEL PVT. LTD. | B17: 2025 | C17: DR | D17: 45842 | E17: 256779415208 | F17: USD | G17: 183.43 | H17: INR | I17: 15775.1 | J17: Unit Storage - 1-30 June 25 | K17: {=VLOOKUP(E17,[1]A023951!D$1:H$1114,{3,5},0)} -> -183.43 | L17: -16228.05 | M17: =I17+L17 -> -452.95
A18: KUEHNE+NAGEL PVT. LTD. | B18: 2025 | C18: DR | D18: 45842 | E18: 256779415209 | F18: USD | G18: 63.26 | H18: INR | I18: 5440.4 | J18: Unit Storage - 1-30 June 25 | K18: {=VLOOKUP(E18,[1]A023951!D$1:H$1114,{3,5},0)} -> -63.26 | L18: -5596.61 | M18: =I18+L18 -> -156.21
A19: KUEHNE+NAGEL PVT. LTD. | B19: 2025 | C19: DR | D19: 45842 | E19: 256779415210 | F19: USD | G19: 9629.63 | H19: INR | I19: 828154.63 | J19: Unit Storage - 1-30 June 25 | K19: {=VLOOKUP(E19,[1]A023951!D$1:H$1114,{3,5},0)} -> -9629.63 | L19: -851933.37 | M19: =I19+L19 -> -23778.74
A20: KUEHNE+NAGEL PVT. LTD. | B20: 2025 | C20: DR | D20: 45842 | E20: 256779415261 | F20: USD | G20: 292.96 | H20: INR | I20: 25194.76 | J20: VAS - 16-30 June 25 | K20: {=VLOOKUP(E20,[1]A023951!D$1:H$1114,{3,5},0)} -> -292.26 | L20: -25131.29 | M20: =I20+L20 -> 63.47
A21: KUEHNE+NAGEL PVT. LTD. | B21: 2025 | C21: DR | D21: 45842 | E21: 256779415270 | F21: USD | G21: 420.86 | H21: INR | I21: 36194.24 | J21: Weighment- 16-30 June 25 | K21: {=VLOOKUP(E21,[1]A023951!D$1:H$1114,{3,5},0)} -> -420.86 | L21: -37233.48 | M21: =I21+L21 -> -1039.24
A22: KUEHNE+NAGEL PVT. LTD. | B22: 2025 | C22: DR | D22: 45966 | E22: 256779418816 | F22: USD | G22: 891 | H22: INR | I22: 78411.02 | J22: VAS-16 -31 Oct 25 | K22: {=VLOOKUP(E22,[1]A023951!D$1:H$1114,{3,5},0)} -> #N/A
A23: KUEHNE+NAGEL PVT. LTD. | B23: 2025 | C23: DR | D23: 45966 | E23: 256779418872 | F23: USD | G23: 5939.04 | H23: INR | I23: 522655.65 | J23: Unit Storage - 1-31 Oct 2025 | K23: {=VLOOKUP(E23,[1]A023951!D$1:H$1114,{3,5},0)} -> #N/A
A24: KUEHNE+NAGEL PVT. LTD. | B24: 2025 | C24: DR | D24: 45966 | E24: 256779418892 | F24: USD | G24: 1683.97 | H24: INR | I24: 148195.07 | J24: CODC Inbound chgs - 16-31 Oct 25 | K24: {=VLOOKUP(E24,[1]A023951!D$1:H$1114,{3,5},0)} -> -1683.97 | L24: -148614.68 | M24: =I24+L24 -> -419.61
A25: KUEHNE+NAGEL PVT. LTD. | B25: 2025 | C25: DR | D25: 45966 | E25: 256779418904 | F25: USD | G25: 1273.92 | H25: INR | I25: 112109.28 | J25: CODC Out chgs -16-31 Oct 25 | K25: {=VLOOKUP(E25,[1]A023951!D$1:H$1114,{3,5},0)} -> -1273.92 | L25: -112426.72 | M25: =I25+L25 -> -317.44
A26: KUEHNE+NAGEL PVT. LTD. | B26: 2025 | C26: DR | D26: 45966 | E26: 256779419165 | F26: USD | G26: 191.57 | H26: INR | I26: 16858.81 | J26: Outbound chgs - 16 - 31 Oct 25 | K26: {=VLOOKUP(E26,[1]A023951!D$1:H$1114,{3,5},0)} -> -191.57 | L26: -16906.55 | M26: =I26+L26 -> -47.74
A27: KUEHNE+NAGEL PVT. LTD. | B27: 2025 | C27: DR | D27: 45966 | E27: 256779419192 | F27: USD | G27: 171.87 | H27: INR | I27: 15125.14 | J27: Empty Lolo Chgs - 01 - 31 OCT 25 | K27: {=VLOOKUP(E27,[1]A023951!D$1:H$1114,{3,5},0)} -> -171.87 | L27: -15167.97 | M27: =I27+L27 -> -42.83
A28: KUEHNE+NAGEL PVT. LTD. | B28: 2025 | C28: DR | D28: 45966 | E28: 256779419211 | F28: USD | G28: 28.18 | H28: INR | I28: 2479.94 | J28: Internet Activity Chgs - Oct 25 | K28: {=VLOOKUP(E28,[1]A023951!D$1:H$1114,{3,5},0)} -> -28.18 | L28: -2486.96 | M28: =I28+L28 -> -7.02
A29: KUEHNE+NAGEL PVT. LTD. | B29: 2025 | C29: DR | D29: 45966 | E29: 256779419222 | F29: USD | G29: 3537 | H29: INR | I29: 311267.99 | J29: PORT SSR Chgs Oct 25 | K29: {=VLOOKUP(E29,[1]A023951!D$1:H$1114,{3,5},0)} -> #N/A
A30: KUEHNE+NAGEL PVT. LTD. | B30: 2025 | C30: DR | D30: 45964 | E30: 256779419122 | F30: USD | G30: 670.42 | H30: INR | I30: 58999.23 | J30: LCL Chgs - 16 - 31 OCT 25 | K30: {=VLOOKUP(E30,[1]A023951!D$1:H$1114,{3,5},0)} -> -670.42 | L30: -59439.1 | M30: =I30+L30 -> -439.87
A31: KUEHNE+NAGEL PVT. LTD. | B31: 2025 | C31: DG | D31: 45964 | E31: 256779422067 | F31: USD | G31: -4608.8 | H31: INR | I31: -405590.02 | J31: CN issued against 256779417093 | K31: {=VLOOKUP(E31,[1]A023951!D$1:H$1114,{3,5},0)} -> #N/A
A32: KUEHNE+NAGEL PVT. LTD. | B32: 2025 | C32: DR | D32: 45877 | E32: 256779416096 | F32: USD | G32: 7386.34 | H32: INR | I32: 635447.72 | J32: Unit Storage - 1-31 July 25 | K32: {=VLOOKUP(E32,[1]A023951!D$1:H$1114,{3,5},0)} -> -7386.34 | L32: -639885.33 | M32: =I32+L32 -> -4437.61
A33: KUEHNE+NAGEL PVT. LTD. | B33: 2025 | C33: DR | D33: 45877 | E33: 256779416137 | F33: USD | G33: 55.28 | H33: INR | I33: 4755.75 | J33: Empty Lolo Chgs - 01 - 31 JUL 25 | K33: {=VLOOKUP(E33,[1]A023951!D$1:H$1114,{3,5},0)} -> -55 | L33: -4764.7 | M33: =I33+L33 -> -8.95
A34: KUEHNE+NAGEL PVT. LTD. | B34: 2025 | C34: DR | D34: 45877 | E34: 256779416169 | F34: USD | G34: 256.97 | H34: INR | I34: 22107.16 | J34: LCL Chgs - 16 - 31 JUL 25 | K34: {=VLOOKUP(E34,[1]A023951!D$1:H$1114,{3,5},0)} -> -257 | L34: -22264.14 | M34: =I34+L34 -> -156.98
A35: KUEHNE+NAGEL PVT. LTD. | B35: 2025 | C35: DR | D35: 45877 | E35: 256779416214 | F35: USD | G35: 212.34 | H35: INR | I35: 18267.64 | J35: Outbound chgs - 16 - 31 Jul 25 | K35: {=VLOOKUP(E35,[1]A023951!D$1:H$1114,{3,5},0)} -> -212 | L35: -18365.75 | M35: =I35+L35 -> -98.11
A36: KUEHNE+NAGEL PVT. LTD. | B36: 2025 | C36: DR | D36: 45877 | E36: 256779416255 | F36: USD | G36: 392.28 | H36: INR | I36: 33747.9 | J36: CODC Out chgs - 16 - 31 Jul 25 | K36: {=VLOOKUP(E36,[1]A023951!D$1:H$1114,{3,5},0)} -> -392 | L36: -33959.32 | M36: =I36+L36 -> -211.42
A37: KUEHNE+NAGEL PVT. LTD. | B37: 2025 | C37: DR | D37: 45877 | E37: 256779416442 | F37: USD | G37: 1053.34 | H37: INR | I37: 90618.97 | J37: VAS 16-31 July 25 | K37: {=VLOOKUP(E37,[1]A023951!D$1:H$1114,{3,5},0)} -> -1053 | L37: -91222.35 | M37: =I37+L37 -> -603.38
A38: KUEHNE+NAGEL PVT. LTD. | B38: 2025 | C38: DR | D38: 45877 | E38: 256779416454 | F38: USD | G38: 411.19 | H38: INR | I38: 35374.73 | J38: Weighment - 16-31 July 25 | K38: {=VLOOKUP(E38,[1]A023951!D$1:H$1114,{3,5},0)} -> -411 | L38: -35605.3 | M38: =I38+L38 -> -230.57
A39: KUEHNE+NAGEL PVT. LTD. | B39: 2025 | C39: DR | D39: 45812 | E39: 256779414156 | F39: USD | G39: 83.66 | H39: INR | I39: 7152.16 | J39: CODC Inbound chgs - 16 - 31 May 25 | K39: {=VLOOKUP(E39,[1]A023951!D$1:H$1114,{3,5},0)} -> #N/A
A40: KUEHNE+NAGEL PVT. LTD. | B40: 2025 | C40: DR | D40: 45812 | E40: 256779414173 | F40: USD | G40: 2668.72 | H40: INR | I40: 228150.95 | J40: PORT SSR Chgs - 16 - 31 May 25 | K40: {=VLOOKUP(E40,[1]A023951!D$1:H$1114,{3,5},0)} -> #N/A
A41: KUEHNE+NAGEL PVT. LTD. | B41: 2025 | C41: DR | D41: 45812 | E41: 256779414206 | F41: USD | G41: 201.33 | H41: INR | I41: 17211.86 | J41: Outbound chgs - 16 - 31 MAY 25 | K41: {=VLOOKUP(E41,[1]A023951!D$1:H$1114,{3,5},0)} -> #N/A
A42: KUEHNE+NAGEL PVT. LTD. | B42: 2025 | C42: DR | D42: 45812 | E42: 256779414260 | F42: USD | G42: 130.93 | H42: INR | I42: 11193.31 | J42: Detention Chgs - 01 - 15 MAY 25 | K42: {=VLOOKUP(E42,[1]A023951!D$1:H$1114,{3,5},0)} -> #N/A
A43: KUEHNE+NAGEL PVT. LTD. | B43: 2025 | C43: DR | D43: 45812 | E43: 256779414271 | F43: USD | G43: 967.68 | H43: INR | I43: 82727.72 | J43: Empty Lolo Chgs - 01 - 31 MAY 25 | K43: {=VLOOKUP(E43,[1]A023951!D$1:H$1114,{3,5},0)} -> #N/A
A44: KUEHNE+NAGEL PVT. LTD. | B44: 2025 | C44: DR | D44: 45812 | E44: 256779414309 | F44: USD | G44: 662.83 | H44: INR | I44: 56665.85 | J44: Transportation In Chgs - 16-31 MAY 25 | K44: {=VLOOKUP(E44,[1]A023951!D$1:H$1114,{3,5},0)} -> #N/A
A45: KUEHNE+NAGEL PVT. LTD. | B45: 2025 | C45: DG | D45: 45791 | E45: 256779420272 | F45: USD | G45: -40.06 | H45: INR | I45: -3472.85 | J45: Credit note against 246779412202 | K45: {=VLOOKUP(E45,[1]A023951!D$1:H$1114,{3,5},0)} -> #N/A
A46: KUEHNE+NAGEL PVT. LTD. | B46: 2025 | C46: DG | D46: 45791 | E46: 256779420273 | F46: USD | G46: -28.62 | H46: INR | I46: -2481.1 | J46: Credit note against 246779412203 | K46: {=VLOOKUP(E46,[1]A023951!D$1:H$1114,{3,5},0)} -> #N/A
A47: KUEHNE+NAGEL PVT. LTD. | B47: 2025 | C47: DG | D47: 45791 | E47: 256779420275 | F47: USD | G47: -114.46 | H47: INR | I47: -9922.68 | J47: Credit note against 246779412205 | K47: {=VLOOKUP(E47,[1]A023951!D$1:H$1114,{3,5},0)} -> #N/A
A48: KUEHNE+NAGEL PVT. LTD. | B48: 2025 | C48: DG | D48: 45791 | E48: 256779420276 | F48: USD | G48: -68.68 | H48: INR | I48: -5953.96 | J48: Credit note against 246779412206 | K48: {=VLOOKUP(E48,[1]A023951!D$1:H$1114,{3,5},0)} -> #N/A
A49: KUEHNE+NAGEL PVT. LTD. | B49: 2025 | C49: DG | D49: 45791 | E49: 256779420268 | F49: USD | G49: -249.55 | H49: INR | I49: -21633.8 | J49: Credit note against 246779412198 | K49: {=VLOOKUP(E49,[1]A023951!D$1:H$1114,{3,5},0)} -> #N/A
A50: KUEHNE+NAGEL PVT. LTD. | B50: 2025 | C50: DG | D50: 45791 | E50: 256779420269 | F50: USD | G50: -40.06 | H50: INR | I50: -3472.85 | J50: Credit note against 246779412199 | K50: {=VLOOKUP(E50,[1]A023951!D$1:H$1114,{3,5},0)} -> #N/A
... A62: KUEHNE+NAGEL PVT. LTD. | B62: 2025 | C62: DR | D62: 45793 | E62: 256779413348 | F62: USD | G62: 138.82 | H62: INR | I62: 11936.26 | J62: Outbound chgs - 16 - 30 Apr 25 | K62: {=VLOOKUP(E62,[1]A023951!D$1:H$1114,{3,5},0)} -> #N/A
A63: KUEHNE+NAGEL PVT. LTD. | B63: 2025 | C63: DR | D63: 46000 | E63: 256779419995 | F63: USD | G63: 187.19 | H63: INR | I63: 16603.78 | J63: CODC LCL Chgs -16-30 Nov 25 | K63: {=VLOOKUP(E63,[1]A023951!D$1:H$1114,{3,5},0)} -> -187.19 | L63: -16688.88 | M63: =I63+L63 -> -85.1
A64: KUEHNE+NAGEL PVT. LTD. | B64: 2025 | C64: DR | D64: 45805 | E64: 256779413908 | F64: USD | G64: 3200.83 | H64: INR | I64: 275219.21 | J64: Storage Chgs - 01 - 31 Apr 25 | K64: {=VLOOKUP(E64,[1]A023951!D$1:H$1114,{3,5},0)} -> -3200.83 | L64: -273269.16 | M64: =I64+L64 -> 1950.05
A65: KUEHNE+NAGEL PVT. LTD. | B65: 2025 | C65: DR | D65: 45856 | E65: 256779415426 | F65: USD | G65: 464.73 | H65: INR | I65: 39967.09 | J65: PORT SSR Chgs Apr & May 25 | K65: {=VLOOKUP(E65,[1]A023951!D$1:H$1114,{3,5},0)} -> -464.73 | L65: -39961.91 | M65: =I65+L65 -> 5.18
A66: KUEHNE+NAGEL PVT. LTD. | B66: 2025 | C66: DR | D66: 45856 | E66: 256779415442 | F66: USD | G66: 1.59 | H66: INR | I66: 136.74 | J66: CODC Inbound Chgs - 01 - 15 July 25 | K66: {=VLOOKUP(E66,[1]A023951!D$1:H$1114,{3,5},0)} -> -1.59 | L66: -136.72 | M66: =I66+L66 -> 0.02
A67: KUEHNE+NAGEL PVT. LTD. | B67: 2025 | C67: DR | D67: 45856 | E67: 256779415453 | F67: USD | G67: 293.46 | H67: INR | I67: 25237.76 | J67: CODC Out chgs - 01 - 15 July 25 | K67: {=VLOOKUP(E67,[1]A023951!D$1:H$1114,{3,5},0)} -> -293.46 | L67: -25234.48 | M67: =I67+L67 -> 3.28
A68: KUEHNE+NAGEL PVT. LTD. | B68: 2025 | C68: DR | D68: 45856 | E68: 256779415474 | F68: USD | G68: 608.41 | H68: INR | I68: 52323.67 | J68: Transportation In Chgs - 01 - 15 JUL 25 | K68: {=VLOOKUP(E68,[1]A023951!D$1:H$1114,{3,5},0)} -> -608.41 | L68: -52316.88 | M68: =I68+L68 -> 6.79
A69: KUEHNE+NAGEL PVT. LTD. | B69: 2025 | C69: DR | D69: 45856 | E69: 256779415517 | F69: USD | G69: 116.74 | H69: INR | I69: 10039.72 | J69: Outbound chgs - 01 - 15 Jul 25 | K69: {=VLOOKUP(E69,[1]A023951!D$1:H$1114,{3,5},0)} -> -116.74 | L69: -10038.42 | M69: =I69+L69 -> 1.3
A70: KUEHNE+NAGEL PVT. LTD. | B70: 2025 | C70: DR | D70: 45856 | E70: 256779415792 | F70: USD | G70: 608.41 | H70: INR | I70: 52323.67 | J70: Transportation In Chgs - 01 - 15 JUL 25 | K70: {=VLOOKUP(E70,[1]A023951!D$1:H$1114,{3,5},0)} -> #N/A
A71: KUEHNE+NAGEL PVT. LTD. | B71: 2025 | C71: DR | D71: 45729 | E71: 246779411312 | F71: USD | G71: 27 | H71: INR | I71: 2340.66 | J71: Scanning Charges for the month of October, 2024 | K71: {=VLOOKUP(E71,[1]A023951!D$1:H$1114,{3,5},0)} -> -27 | L71: -2350.15 | M71: =I71+L71 -> -9.49
A72: KUEHNE+NAGEL PVT. LTD. | B72: 2025 | C72: DR | D72: 45736 | E72: 246779413730 | F72: USD | G72: 3.2 | H72: INR | I72: 277.41 | J72: Outbound Handling charges for Jan 2025 | K72: {=VLOOKUP(E72,[1]A023951!D$1:H$1114,{3,5},0)} -> -3.2 | L72: -278.54 | M72: =I72+L72 -> -1.13
A73: KUEHNE+NAGEL PVT. LTD. | B73: 2025 | C73: DR | D73: 45736 | E73: 246779413747 | F73: USD | G73: 2.74 | H73: INR | I73: 237.53 | J73: Outbound Handling charges for Feb 2025 | K73: {=VLOOKUP(E73,[1]A023951!D$1:H$1114,{3,5},0)} -> -2.74 | L73: -238.5 | M73: =I73+L73 -> -0.97
A74: KUEHNE+NAGEL PVT. LTD. | B74: 2025 | C74: DR | D74: 45736 | E74: 246779413815 | F74: USD | G74: 50 | H74: INR | I74: 4334.56 | J74: Scanning Charges for the month of Feb 2025 | K74: {=VLOOKUP(E74,[1]A023951!D$1:H$1114,{3,5},0)} -> -50 | L74: -4352.12 | M74: =I74+L74 -> -17.56
A75: KUEHNE+NAGEL PVT. LTD. | B75: 2025 | C75: DR | D75: 45736 | E75: 246779413920 | F75: USD | G75: 22.5 | H75: INR | I75: 1950.55 | J75: Outbound Handling charges for Feb 2025 | K75: {=VLOOKUP(E75,[1]A023951!D$1:H$1114,{3,5},0)} -> -22.5 | L75: -1958.45 | M75: =I75+L75 -> -7.9
A76: KUEHNE+NAGEL PVT. LTD. | B76: 2025 | C76: DR | D76: 45736 | E76: 246779413936 | F76: USD | G76: 27.5 | H76: INR | I76: 2384.01 | J76: Outbound Handling charges for Feb 2025 | K76: {=VLOOKUP(E76,[1]A023951!D$1:H$1114,{3,5},0)} -> -27.5 | L76: -2393.67 | M76: =I76+L76 -> -9.66
A77: KUEHNE+NAGEL PVT. LTD. | B77: 2025 | C77: DR | D77: 45736 | E77: 246779413941 | F77: USD | G77: 30 | H77: INR | I77: 2600.74 | J77: Outbound Handling charges for Feb 2025 | K77: {=VLOOKUP(E77,[1]A023951!D$1:H$1114,{3,5},0)} -> -30 | L77: -2611.27 | M77: =I77+L77 -> -10.53
A78: KUEHNE+NAGEL PVT. LTD. | B78: 2025 | C78: DR | D78: 45736 | E78: 246779414384 | F78: USD | G78: 182.5 | H78: INR | I78: 15821.15 | J78: Inbound Handling charges for Nov 2024 | K78: {=VLOOKUP(E78,[1]A023951!D$1:H$1114,{3,5},0)} -> -182.5 | L78: -15885.24 | M78: =I78+L78 -> -64.09
A79: KUEHNE+NAGEL PVT. LTD. | B79: 2025 | C79: DR | D79: 45736 | E79: 246779414385 | F79: USD | G79: 240 | H79: INR | I79: 20805.9 | J79: LCL Movement Charges for Nov 2024 | K79: {=VLOOKUP(E79,[1]A023951!D$1:H$1114,{3,5},0)} -> -240 | L79: -20890.18 | M79: =I79+L79 -> -84.28
A80: KUEHNE+NAGEL PVT. LTD. | B80: 2025 | C80: DR | D80: 45736 | E80: 246779414057 | F80: USD | G80: 43.07 | H80: INR | I80: 3733.79 | J80: Inbound Handling charges for Jan 2025 | K80: {=VLOOKUP(E80,[1]A023951!D$1:H$1114,{3,5},0)} -> #N/A
A81: KUEHNE+NAGEL PVT. LTD. | B81: 2025 | C81: DR | D81: 45736 | E81: 246779414058 | F81: USD | G81: 398.23 | H81: INR | I81: 34523.06 | J81: Inbound Handling charges for Jan 2025 | K81: {=VLOOKUP(E81,[1]A023951!D$1:H$1114,{3,5},0)} -> #N/A
A82: KUEHNE+NAGEL PVT. LTD. | B82: 2025 | C82: DR | D82: 45736 | E82: 246779414120 | F82: USD | G82: 250.75 | H82: INR | I82: 21737.83 | J82: Inbound Handling charges for Sep 2024 | K82: {=VLOOKUP(E82,[1]A023951!D$1:H$1114,{3,5},0)} -> #N/A
A83: KUEHNE+NAGEL PVT. LTD. | B83: 2025 | C83: DR | D83: 45736 | E83: 246779414121 | F83: USD | G83: 226.56 | H83: INR | I83: 19640.77 | J83: LCL charges for Sep 2024 | K83: {=VLOOKUP(E83,[1]A023951!D$1:H$1114,{3,5},0)} -> #N/A
A84: KUEHNE+NAGEL PVT. LTD. | B84: 2025 | C84: DR | D84: 45736 | E84: 246779414122 | F84: USD | G84: 35.4 | H84: INR | I84: 3068.87 | J84: Cy-WH Destuff charges for Sep 2024 | K84: {=VLOOKUP(E84,[1]A023951!D$1:H$1114,{3,5},0)} -> #N/A
A85: KUEHNE+NAGEL PVT. LTD. | B85: 2025 | C85: DR | D85: 45736 | E85: 246779414204 | F85: USD | G85: 249.87 | H85: INR | I85: 21661.55 | J85: Outbound Handling charges for Sep 2024 | K85: {=VLOOKUP(E85,[1]A023951!D$1:H$1114,{3,5},0)} -> #N/A
A86: KUEHNE+NAGEL PVT. LTD. | B86: 2025 | C86: DR | D86: 45736 | E86: 246779414460 | F86: USD | G86: 173.05 | H86: INR | I86: 15001.92 | J86: Inbound Handling charges for Jan 2025 | K86: {=VLOOKUP(E86,[1]A023951!D$1:H$1114,{3,5},0)} -> #N/A
A87: KUEHNE+NAGEL PVT. LTD. | B87: 2025 | C87: DR | D87: 45736 | E87: 246779414461 | F87: USD | G87: 226.56 | H87: INR | I87: 19640.77 | J87: LCL charges for Jan 2025 | K87: {=VLOOKUP(E87,[1]A023951!D$1:H$1114,{3,5},0)} -> #N/A
A88: KUEHNE+NAGEL PVT. LTD. | B88: 2025 | C88: DR | D88: 45736 | E88: 246779414525 | F88: USD | G88: 211.39 | H88: INR | I88: 18325.67 | J88: Inbound Handling charges for Feb 2025 | K88: {=VLOOKUP(E88,[1]A023951!D$1:H$1114,{3,5},0)} -> #N/A
A89: KUEHNE+NAGEL PVT. LTD. | B89: 2025 | C89: DR | D89: 45736 | E89: 246779414526 | F89: USD | G89: 141.6 | H89: INR | I89: 12275.48 | J89: LCL Movement Charges for Feb 2025 | K89: {=VLOOKUP(E89,[1]A023951!D$1:H$1114,{3,5},0)} -> #N/A
A90: KUEHNE+NAGEL PVT. LTD. | B90: 2025 | C90: DR | D90: 45736 | E90: 246779414527 | F90: USD | G90: 70.8 | H90: INR | I90: 6137.74 | J90: Empty transportation Charges for Feb 2025 | K90: {=VLOOKUP(E90,[1]A023951!D$1:H$1114,{3,5},0)} -> #N/A
A91: KUEHNE+NAGEL PVT. LTD. | B91: 2025 | C91: DR | D91: 45736 | E91: 246779414528 | F91: USD | G91: 236 | H91: INR | I91: 20459.14 | J91: Transportation Charges for Feb 2025 | K91: {=VLOOKUP(E91,[1]A023951!D$1:H$1114,{3,5},0)} -> #N/A
... A99: KUEHNE+NAGEL PVT. LTD. | B99: 2025 | C99: DR | D99: 45736 | E99: 246779414869 | F99: USD | G99: 35.4 | H99: INR | I99: 3068.87 | J99: Outbound Handling charges for Jan 2025 | K99: {=VLOOKUP(E99,[1]A023951!D$1:H$1114,{3,5},0)} -> #N/A
A100: KUEHNE+NAGEL PVT. LTD. | B100: 2025 | C100: DR | D100: 45736 | E100: 246779413889 | F100: USD | G100: 42.5 | H100: INR | I100: 3684.38 | J100: Outbound Handling charges for Feb 2025 | K100: {=VLOOKUP(E100,[1]A023951!D$1:H$1114,{3,5},0)} -> -42.5 | L100: -3699.3 | M100: =I100+L100 -> -14.92
A101: KUEHNE+NAGEL PVT. LTD. | B101: 2025 | C101: DR | D101: 45736 | E101: 246779414662 | F101: USD | G101: 275 | H101: INR | I101: 23840.1 | J101: Outbound Handling charges for Nov 2024 | K101: {=VLOOKUP(E101,[1]A023951!D$1:H$1114,{3,5},0)} -> -275 | L101: -23936.66 | M101: =I101+L101 -> -96.56
A102: KUEHNE+NAGEL PVT. LTD. | B102: 2025 | C102: DR | D102: 45736 | E102: 246779414663 | F102: USD | G102: 45 | H102: INR | I102: 3901.11 | J102: CY-MOVEMENT CHARGES for Nov 2024 | K102: {=VLOOKUP(E102,[1]A023951!D$1:H$1114,{3,5},0)} -> -45 | L102: -3916.91 | M102: =I102+L102 -> -15.8
A103: KUEHNE+NAGEL PVT. LTD. | B103: 2025 | C103: DR | D103: 45736 | E103: 246779414590 | F103: USD | G103: 300.49 | H103: INR | I103: 26049.86 | J103: Outbound Handling charges for Oct 2024 | K103: {=VLOOKUP(E103,[1]A023951!D$1:H$1114,{3,5},0)} -> #N/A
A104: KUEHNE+NAGEL PVT. LTD. | B104: 2025 | C104: DR | D104: 45736 | E104: 246779414726 | F104: USD | G104: 165.4 | H104: INR | I104: 14338.73 | J104: Outbound Handling charges for Jan 2025 | K104: {=VLOOKUP(E104,[1]A023951!D$1:H$1114,{3,5},0)} -> #N/A
A105: KUEHNE+NAGEL PVT. LTD. | B105: 2025 | C105: DR | D105: 45708 | E105: 246779410010 | F105: USD | G105: 2380.95 | H105: INR | I105: 205484.7 | J105: Fixed Rental charges for Aug 2024 | K105: {=VLOOKUP(E105,[1]A023951!D$1:H$1114,{3,5},0)} -> -2380.95 | L105: -206046.42 | M105: =I105+L105 -> -561.72
A106: KUEHNE+NAGEL PVT. LTD. | B106: 2025 | C106: DR | D106: 45708 | E106: 246779410030 | F106: USD | G106: 2380.95 | H106: INR | I106: 205484.7 | J106: Fixed Rental charges for Sept 2024 | K106: {=VLOOKUP(E106,[1]A023951!D$1:H$1114,{3,5},0)} -> -2380.95 | L106: -206046.42 | M106: =I106+L106 -> -561.72
A107: KUEHNE+NAGEL PVT. LTD. | B107: 2025 | C107: DR | D107: 45708 | E107: 246779410063 | F107: USD | G107: 95.24 | H107: INR | I107: 8219.56 | J107: Office space charges for Sept 2024 | K107: {=VLOOKUP(E107,[1]A023951!D$1:H$1114,{3,5},0)} -> -95.24 | L107: -8242.03 | M107: =I107+L107 -> -22.47
A108: KUEHNE+NAGEL PVT. LTD. | B108: 2025 | C108: DR | D108: 45708 | E108: 246779410064 | F108: USD | G108: 52.38 | H108: INR | I108: 4520.59 | J108: Utility charge- Electricity for Sept 2024 | K108: {=VLOOKUP(E108,[1]A023951!D$1:H$1114,{3,5},0)} -> -52.38 | L108: -4532.94 | M108: =I108+L108 -> -12.35
A109: KUEHNE+NAGEL PVT. LTD. | B109: 2025 | C109: DR | D109: 45708 | E109: 246779410080 | F109: USD | G109: 95.24 | H109: INR | I109: 8219.56 | J109: Office space charges - Aug, 2024 | K109: {=VLOOKUP(E109,[1]A023951!D$1:H$1114,{3,5},0)} -> -95.24 | L109: -8242.03 | M109: =I109+L109 -> -22.47
A110: KUEHNE+NAGEL PVT. LTD. | B110: 2025 | C110: DR | D110: 45708 | E110: 246779410098 | F110: USD | G110: 2380.95 | H110: INR | I110: 205484.7 | J110: Fixed Rental charges for Nov 2024 | K110: {=VLOOKUP(E110,[1]A023951!D$1:H$1114,{3,5},0)} -> -2380.95 | L110: -206046.42 | M110: =I110+L110 -> -561.72
A111: KUEHNE+NAGEL PVT. LTD. | B111: 2025 | C111: DR | D111: 45708 | E111: 246779410131 | F111: USD | G111: 95.24 | H111: INR | I111: 8219.56 | J111: Office space charges for Nov 2024 | K111: {=VLOOKUP(E111,[1]A023951!D$1:H$1114,{3,5},0)} -> -95.24 | L111: -8242.03 | M111: =I111+L111 -> -22.47
A112: KUEHNE+NAGEL PVT. LTD. | B112: 2025 | C112: DR | D112: 45708 | E112: 246779410132 | F112: USD | G112: 52.38 | H112: INR | I112: 4520.59 | J112: Utility charge- Electricity for Nov 2024 | K112: {=VLOOKUP(E112,[1]A023951!D$1:H$1114,{3,5},0)} -> -52.38 | L112: -4532.94 | M112: =I112+L112 -> -12.35
A113: KUEHNE+NAGEL PVT. LTD. | B113: 2025 | C113: DR | D113: 45708 | E113: 246779410141 | F113: USD | G113: 2380.95 | H113: INR | I113: 205484.7 | J113: Fixed Rental charges for Dec 2024 | K113: {=VLOOKUP(E113,[1]A023951!D$1:H$1114,{3,5},0)} -> -2380.95 | L113: -206046.42 | M113: =I113+L113 -> -561.72
A114: KUEHNE+NAGEL PVT. LTD. | B114: 2025 | C114: DR | D114: 45708 | E114: 246779410174 | F114: USD | G114: 95.24 | H114: INR | I114: 8219.56 | J114: Office space charges for Dec 2024 | K114: {=VLOOKUP(E114,[1]A023951!D$1:H$1114,{3,5},0)} -> -95.24 | L114: -8242.03 | M114: =I114+L114 -> -22.47
A115: KUEHNE+NAGEL PVT. LTD. | B115: 2025 | C115: DR | D115: 45708 | E115: 246779410175 | F115: USD | G115: 52.38 | H115: INR | I115: 4520.59 | J115: Utility charge- Electricity for Dec 2024 | K115: {=VLOOKUP(E115,[1]A023951!D$1:H$1114,{3,5},0)} -> -52.38 | L115: -4532.94 | M115: =I115+L115 -> -12.35
A116: KUEHNE+NAGEL PVT. LTD. | B116: 2025 | C116: DR | D116: 45708 | E116: 246779410184 | F116: USD | G116: 2333.18 | H116: INR | I116: 201361.97 | J116: Fixed Rental charges for Jan 2025 | K116: {=VLOOKUP(E116,[1]A023951!D$1:H$1114,{3,5},0)} -> -2333.18 | L116: -201912.42 | M116: =I116+L116 -> -550.45
... A124: KUEHNE+NAGEL PVT. LTD. | B124: 2025 | C124: DR | D124: 45708 | E124: 246779410227 | F124: USD | G124: 2286.24 | H124: INR | I124: 197310.88 | J124: Fixed Rental charges for Feb 2025 | K124: {=VLOOKUP(E124,[1]A023951!D$1:H$1114,{3,5},0)} -> -2286.24 | L124: -197850.25 | M124: =I124+L124 -> -539.37
A125: KUEHNE+NAGEL PVT. LTD. | B125: 2025 | C125: DR | D125: 45889 | E125: 256779416593 | F125: USD | G125: 810 | H125: INR | I125: 69684.4 | J125: Empty Cont Out Chgs - 16 - 31 Jul 25 | K125: {=VLOOKUP(E125,[1]A023951!D$1:H$1114,{3,5},0)} -> #N/A
...

Sheet Sheet12
A1: Customer Account: Name 1 | B1: Fiscal Year | C1: Document Type | D1: Document Date | E1: Entry Date | F1: Reference | G1: Document Currency Key | H1: Document Currency Value | I1: Company Code Currency Key | J1: Company Code Currency Value | K1: Text
A2: KUEHNE+NAGEL PVT. LTD. | B2: 2025 | C2: DR | D2: 45904 | E2: 45909 | F2: 256779417250 | G2: USD | H2: 50 | I2: INR | J2: 4375.72 | K2: Scanning Chgs - 16 - 31 Aug 25
A3: KUEHNE+NAGEL PVT. LTD. | B3: 2025 | C3: DR | D3: 45966 | E3: 45967 | F3: 256779418816 | G3: USD | H3: 891 | I3: INR | J3: 78411.02 | K3: VAS-16 -31 Oct 25
A4: KUEHNE+NAGEL PVT. LTD. | B4: 2025 | C4: DR | D4: 45966 | E4: 45967 | F4: 256779418872 | G4: USD | H4: 5939.04 | I4: INR | J4: 522655.65 | K4: Unit Storage - 1-31 Oct 2025
A5: KUEHNE+NAGEL PVT. LTD. | B5: 2025 | C5: DR | D5: 45966 | E5: 45968 | F5: 256779419222 | G5: USD | H5: 3537 | I5: INR | J5: 311267.99 | K5: PORT SSR Chgs Oct 25
A6: KUEHNE+NAGEL PVT. LTD. | B6: 2025 | C6: DR | D6: 45812 | E6: 45817 | F6: 256779414156 | G6: USD | H6: 83.66 | I6: INR | J6: 7152.16 | K6: CODC Inbound chgs - 16 - 31 May 25
A7: KUEHNE+NAGEL PVT. LTD. | B7: 2025 | C7: DR | D7: 45812 | E7: 45817 | F7: 256779414173 | G7: USD | H7: 2668.72 | I7: INR | J7: 228150.95 | K7: PORT SSR Chgs - 16 - 31 May 25
A8: KUEHNE+NAGEL PVT. LTD. | B8: 2025 | C8: DR | D8: 45812 | E8: 45817 | F8: 256779414206 | G8: USD | H8: 201.33 | I8: INR | J8: 17211.86 | K8: Outbound chgs - 16 - 31 MAY 25
A9: KUEHNE+NAGEL PVT. LTD. | B9: 2025 | C9: DR | D9: 45812 | E9: 45817 | F9: 256779414260 | G9: USD | H9: 130.93 | I9: INR | J9: 11193.31 | K9: Detention Chgs - 01 - 15 MAY 25
A10: KUEHNE+NAGEL PVT. LTD. | B10: 2025 | C10: DR | D10: 45812 | E10: 45817 | F10: 256779414271 | G10: USD | H10: 967.68 | I10: INR | J10: 82727.72 | K10: Empty Lolo Chgs - 01 - 31 MAY 25
A11: KUEHNE+NAGEL PVT. LTD. | B11: 2025 | C11: DR | D11: 45812 | E11: 45817 | F11: 256779414309 | G11: USD | H11: 662.83 | I11: INR | J11: 56665.85 | K11: Transportation In Chgs - 16-31 MAY 25
A12: KUEHNE+NAGEL PVT. LTD. | B12: 2025 | C12: DR | D12: 45793 | E12: 45800 | F12: 256779413280 | G12: USD | H12: 59 | I12: INR | J12: 5073.04 | K12: Scanning Chgs - 16 - 31 Apr 25
A13: KUEHNE+NAGEL PVT. LTD. | B13: 2025 | C13: DR | D13: 45793 | E13: 45800 | F13: 256779413308 | G13: USD | H13: 723.47 | I13: INR | J13: 62206.63 | K13: LCL Chgs - 16 - 30 Apr 25
... A141: KUEHNE+NAGEL PVT. LTD. | B141: 2025 | C141: DR | D141: 45719 | E141: 45719 | F141: 246779410483 | G141: USD | H141: 3.54 | I141: INR | J141: 306.89 | K141: Outbound Handling for Aug 2024

Sheet Sheet4

Sheet CUSTOMER DATA
E1: =SUBTOTAL(9,E3:E732) -> -11983945 | O1: =SUBTOTAL(9,O3:O732) -> 233116.04 | P1: =SUBTOTAL(9,P3:P732) -> -11750829 | R1: =SUBTOTAL(9,R3:R732) -> #N/A
A2: Ty | B2: Item# | C2: Item Date | D2: FC Amount | E2: LC Amount | F2: Particular | G2: Due Date | H2: CCY | I2: VC Period | J2: VC Seq | K2: VC Date | L2: Tx. Type | M2: Company Code | O2: TDS as per customer | P2: Customer balance | Q2: Vlookup | S2: Remarks
A3: I | B3: 256779413908 | C3: 45805 | D3: -3200.83 | E3: -273269.16 | G3: 27/06/2025 | H3: USD | I3: 45962 | J3: 1 | K3: 45991 | L3: 210 | M3: IN89 | N3: =O3/E3 -> -0.02000105 | O3: =VLOOKUP(B3,'Customer TDS'!A:D,4,0) -> 5465.67 | P3: =E3+O3 -> -267803.49 | Q3: =VLOOKUP(B3,Ascendus!E:I,5,0) -> 275219.21 | R3: =E3+Q3 -> 1950.05 | S3: Difference due to exchange rate
A4: I | B4: 256779413908 | C4: 45805 | D4: 0 | E4: -11858.12 | F4: C: ASCENDAS27 P: Matching | G4: 27/06/2025 | H4: USD | I4: 45962 | J4: 66 | K4: 45991 | L4: 271 | M4: IN89 | P4: =E4+O4 -> -11858.12 | S4: Amount recorded by customer but not in our books
A5: I | B5: 256779415989 | C5: 45863 | D5: -299.84 | E5: -25783.09 | G5: 24/08/2025 | H5: USD | I5: 45931 | J5: 1 | K5: 45959 | L5: 210 | M5: IN89 | N5: =O5/E5 -> -0.02001079 | O5: =VLOOKUP(B5,'Customer TDS'!A:D,4,0) -> 515.94 | P5: =E5+O5 -> -25267.15 | Q5: =VLOOKUP(B5,Ascendus!E:I,5,0) -> 25786.44 | R5: =E5+Q5 -> 3.35 | S5: Difference due to exchange rate
A6: I | B6: 256779416007 | C6: 45863 | D6: -421.15 | E6: -36214.48 | G6: 24/08/2025 | H6: USD | I6: 45931 | J6: 1 | K6: 45959 | L6: 210 | M6: IN89 | N6: =O6/E6 -> -0.019992832 | O6: =VLOOKUP(B6,'Customer TDS'!A:D,4,0) -> 724.03 | P6: =E6+O6 -> -35490.45 | Q6: =VLOOKUP(B6,Ascendus!E:I,5,0) -> 36219.18 | R6: =E6+Q6 -> 4.7 | S6: Difference due to exchange rate
A7: I | B7: 256779415989 | C7: 45863 | D7: 0 | E7: -664.99 | F7: C: ASCENDAS27 P: Matching | G7: 24/08/2025 | H7: USD | I7: 45931 | J7: 82 | K7: 45961 | L7: 271 | M7: IN89 | P7: =E7+O7 -> -664.99 | S7: Amount recorded by customer but not in our books
A8: I | B8: 256779416007 | C8: 45863 | D8: 0 | E8: -934.03 | F8: C: ASCENDAS27 P: Matching | G8: 24/08/2025 | H8: USD | I8: 45931 | J8: 84 | K8: 45961 | L8: 271 | M8: IN89 | P8: =E8+O8 -> -934.03 | S8: Amount recorded by customer but not in our books
A9: I | B9: 256779412776 | C9: 45771 | D9: -632.46 | E9: -54218.88 | G9: 24/05/2025 | H9: USD | I9: 45962 | J9: 1 | K9: 45991 | L9: 210 | M9: IN89 | N9: =O9/E9 -> -0.020001335 | O9: =VLOOKUP(B9,'Customer TDS'!A:D,4,0) -> 1084.45 | P9: =E9+O9 -> -53134.43 | Q9: =VLOOKUP(B9,Ascendus!E:I,5,0) -> 54974.57 | R9: =E9+Q9 -> 755.69 | S9: Difference due to exchange rate
A10: I | B10: 256779412776 | C10: 45771 | D10: 0 | E10: -2124.59 | F10: C: ASCENDAS27 P: Matching | G10: 24/05/2025 | H10: USD | I10: 45962 | J10: 58 | K10: 45991 | L10: 271 | M10: IN89 | P10: =E10+O10 -> -2124.59 | S10: Amount recorded by customer but not in our books
A11: I | B11: 256779417801 | C11: 45922 | D11: -4755.47 | E11: -416826.08 | G11: 22/10/2025 | H11: USD | I11: 45931 | J11: 1 | K11: 45959 | L11: 210 | M11: IN89 | N11: =O11/E11 -> -0.020000116 | O11: =VLOOKUP(B11,'Customer TDS'!A:D,4,0) -> 8336.57 | P11: =E11+O11 -> -408489.51 | Q11: =VLOOKUP(B11,Ascendus!E:I,5,0) -> 416171.77 | R11: =E11+Q11 -> -654.31 | S11: Difference due to exchange rate
A12: I | B12: 256779417801 | C12: 45922 | D12: 0 | E12: -2799.24 | F12: C: ASCENDAS27 P: Matching | G12: 22/10/2025 | H12: USD | I12: 45931 | J12: 64 | K12: 45961 | L12: 271 | M12: IN89 | P12: =E12+O12 -> -2799.24 | S12: Amount recorded by customer but not in our books
A13: I | B13: 256779417744 | C13: 45922 | D13: -870 | E13: -76257.17 | G13: 22/10/2025 | H13: USD | I13: 45962 | J13: 1 | K13: 45972 | L13: 210 | M13: IN89 | N13: =O13/E13 -> -0.019999955 | O13: =VLOOKUP(B13,'Customer TDS'!A:D,4,0) -> 1525.14 | P13: =E13+O13 -> -74732.03 | Q13: =VLOOKUP(B13,Ascendus!E:I,5,0) -> 76137.47 | R13: =E13+Q13 -> -119.7 | S13: Difference due to exchange rate
A14: I | B14: 256779412524 | C14: 45769 | D14: -36.5 | E14: -3129.03 | G14: 22/05/2025 | H14: USD | I14: 45809 | J14: 1 | K14: 45838 | L14: 210 | M14: IN89 | N14: =O14/E14 -> -0.019999808 | O14: =VLOOKUP(B14,'Customer TDS'!A:D,4,0) -> 62.58 | P14: =E14+O14 -> -3066.45 | Q14: =VLOOKUP(B14,Ascendus!E:I,5,0) -> 3172.65 | R14: =E14+Q14 -> 43.62 | S14: Difference due to exchange rate
A15: I | B15: 256779412529 | C15: 45769 | D15: -29.57 | E15: -2534.95 | G15: 22/05/2025 | H15: USD | I15: 45809 | J15: 1 | K15: 45838 | L15: 210 | M15: IN89 | N15: =O15/E15 -> -0.019953056 | O15: =VLOOKUP(B15,'Customer TDS'!A:D,4,0) -> 50.58 | P15: =E15+O15 -> -2484.37 | Q15: =VLOOKUP(B15,Ascendus!E:I,5,0) -> 2570.28 | R15: =E15+Q15 -> 35.33 | S15: Difference due to exchange rate
A16: I | B16: 256779412536 | C16: 45769 | D16: -37.02 | E16: -3173.61 | G16: 22/05/2025 | H16: USD | I16: 45809 | J16: 1 | K16: 45838 | L16: 210 | M16: IN89 | N16: =O16/E16 -> -0.019989854 | O16: =VLOOKUP(B16,'Customer TDS'!A:D,4,0) -> 63.44 | P16: =E16+O16 -> -3110.17 | Q16: =VLOOKUP(B16,Ascendus!E:I,5,0) -> 3217.85 | R16: =E16+Q16 -> 44.24 | S16: Difference due to exchange rate
A17: I | B17: 256779412537 | C17: 45769 | D17: -407.58 | E17: -34940.6 | G17: 22/05/2025 | H17: USD | I17: 45809 | J17: 1 | K17: 45838 | L17: 210 | M17: IN89 | N17: =O17/E17 -> -0.019995936 | O17: =VLOOKUP(B17,'Customer TDS'!A:D,4,0) -> 698.67 | P17: =E17+O17 -> -34241.93 | Q17: =VLOOKUP(B17,Ascendus!E:I,5,0) -> 35427.6 | R17: =E17+Q17 -> 487 | S17: Difference due to exchange rate
A18: I | B18: 256779412579 | C18: 45769 | D18: -57.6 | E18: -4937.87 | G18: 22/05/2025 | H18: USD | I18: 45809 | J18: 1 | K18: 45838 | L18: 210 | M18: IN89 | N18: =O18/E18 -> -0.019966099 | O18: =VLOOKUP(B18,'Customer TDS'!A:D,4,0) -> 98.59 | P18: =E18+O18 -> -4839.28 | Q18: =VLOOKUP(B18,Ascendus!E:I,5,0) -> 5006.7 | R18: =E18+Q18 -> 68.83 | S18: Difference due to exchange rate
A19: I | B19: 256779412586 | C19: 45769 | D19: -51.5 | E19: -4414.94 | G19: 22/05/2025 | H19: USD | I19: 45809 | J19: 1 | K19: 45838 | L19: 210 | M19: IN89 | N19: =O19/E19 -> -0.020000272 | O19: =VLOOKUP(B19,'Customer TDS'!A:D,4,0) -> 88.3 | P19: =E19+O19 -> -4326.64 | Q19: =VLOOKUP(B19,Ascendus!E:I,5,0) -> 4476.47 | R19: =E19+Q19 -> 61.53 | S19: Difference due to exchange rate
A20: I | B20: 256779412563 | C20: 45769 | D20: -27 | E20: -2314.63 | G20: 22/05/2025 | H20: USD | I20: 45809 | J20: 1 | K20: 45838 | L20: 210 | M20: IN89 | N20: =O20/E20 -> -0.019998877 | O20: =VLOOKUP(B20,'Customer TDS'!A:D,4,0) -> 46.29 | P20: =E20+O20 -> -2268.34 | Q20: =VLOOKUP(B20,Ascendus!E:I,5,0) -> 2346.89 | R20: =E20+Q20 -> 32.26 | S20: Difference due to exchange rate
A21: I | B21: 256779412576 | C21: 45769 | D21: -46 | E21: -3943.44 | G21: 22/05/2025 | H21: USD | I21: 45809 | J21: 1 | K21: 45838 | L21: 210 | M21: IN89 | N21: =O21/E21 -> -0.020000304 | O21: =VLOOKUP(B21,'Customer TDS'!A:D,4,0) -> 78.87 | P21: =E21+O21 -> -3864.57 | Q21: =VLOOKUP(B21,Ascendus!E:I,5,0) -> 3998.4 | R21: =E21+Q21 -> 54.96 | S21: Difference due to exchange rate
A22: I | B22: 256779412577 | C22: 45769 | D22: -46 | E22: -3943.44 | G22: 22/05/2025 | H22: USD | I22: 45809 | J22: 1 | K22: 45838 | L22: 210 | M22: IN89 | N22: =O22/E22 -> -0.020000304 | O22: =VLOOKUP(B22,'Customer TDS'!A:D,4,0) -> 78.87 | P22: =E22+O22 -> -3864.57 | Q22: =VLOOKUP(B22,Ascendus!E:I,5,0) -> 3998.4 | R22: =E22+Q22 -> 54.96 | S22: Difference due to exchange rate
A23: I | B23: 256779412580 | C23: 45769 | D23: -40.5 | E23: -3471.94 | G23: 22/05/2025 | H23: USD | I23: 45809 | J23: 1 | K23: 45838 | L23: 210 | M23: IN89 | N23: =O23/E23 -> -0.020000346 | O23: =VLOOKUP(B23,'Customer TDS'!A:D,4,0) -> 69.44 | P23: =E23+O23 -> -3402.5 | Q23: =VLOOKUP(B23,Ascendus!E:I,5,0) -> 3520.33 | R23: =E23+Q23 -> 48.39 | S23: Difference due to exchange rate
A24: I | B24: 256779412562 | C24: 45769 | D24: -54.65 | E24: -4684.98 | G24: 22/05/2025 | H24: USD | I24: 45809 | J24: 1 | K24: 45838 | L24: 210 | M24: IN89 | N24: =O24/E24 -> -0.019944589 | O24: =VLOOKUP(B24,'Customer TDS'!A:D,4,0) -> 93.44 | P24: =E24+O24 -> -4591.54 | Q24: =VLOOKUP(B24,Ascendus!E:I,5,0) -> 4750.28 | R24: =E24+Q24 -> 65.3 | S24: Difference due to exchange rate
... A28: I | B28: 256779412585 | C28: 45769 | D28: -48.75 | E28: -4179.19 | G28: 22/05/2025 | H28: USD | I28: 45809 | J28: 1 | K28: 45838 | L28: 210 | M28: IN89 | N28: =O28/E28 -> -0.020101981 | O28: =VLOOKUP(B28,'Customer TDS'!A:D,4,0) -> 84.01 | P28: =E28+O28 -> -4095.18 | Q28: =VLOOKUP(B28,Ascendus!E:I,5,0) -> 4237.44 | R28: =E28+Q28 -> 58.25 | S28: Difference due to exchange rate
A29: I | B29: 256779412583 | C29: 45769 | D29: -51.75 | E29: -4436.37 | G29: 22/05/2025 | H29: USD | I29: 45809 | J29: 1 | K29: 45838 | L29: 210 | M29: IN89 | P29: =E29+O29 -> -4436.37 | Q29: =VLOOKUP(B29,Ascendus!E:I,5,0) -> 4498.2 | R29: =E29+Q29 -> 61.83 | S29: Difference due to exchange rate
A30: I | B30: 256779412524 | C30: 45769 | D30: 0 | E30: -9.39 | F30: C: ASCENDAS27 P: Matching | G30: 22/05/2025 | H30: USD | I30: 45809 | J30: 14 | K30: 45838 | L30: 271 | M30: IN89 | P30: =E30+O30 -> -9.39 | S30: Amount recorded by customer but not in our books
A31: I | B31: 256779412529 | C31: 45769 | D31: 0 | E31: -7.61 | F31: C: ASCENDAS27 P: Matching | G31: 22/05/2025 | H31: USD | I31: 45809 | J31: 16 | K31: 45838 | L31: 271 | M31: IN89 | P31: =E31+O31 -> -7.61 | S31: Amount recorded by customer but not in our books
A32: I | B32: 256779412536 | C32: 45769 | D32: 0 | E32: -9.53 | F32: C: ASCENDAS27 P: Matching | G32: 22/05/2025 | H32: USD | I32: 45809 | J32: 18 | K32: 45838 | L32: 271 | M32: IN89 | P32: =E32+O32 -> -9.53 | S32: Amount recorded by customer but not in our books
A33: I | B33: 256779412537 | C33: 45769 | D33: 0 | E33: -104.86 | F33: C: ASCENDAS27 P: Matching | G33: 22/05/2025 | H33: USD | I33: 45809 | J33: 20 | K33: 45838 | L33: 271 | M33: IN89 | P33: =E33+O33 -> -104.86 | S33: Amount recorded by customer but not in our books
A34: I | B34: 256779412579 | C34: 45769 | D34: 0 | E34: -14.83 | F34: C: ASCENDAS27 P: Matching | G34: 22/05/2025 | H34: USD | I34: 45809 | J34: 22 | K34: 45838 | L34: 271 | M34: IN89 | P34: =E34+O34 -> -14.83 | S34: Amount recorded by customer but not in our books
A35: I | B35: 256779412586 | C35: 45769 | D35: 0 | E35: -13.25 | F35: C: ASCENDAS27 P: Matching | G35: 22/05/2025 | H35: USD | I35: 45809 | J35: 24 | K35: 45838 | L35: 271 | M35: IN89 | P35: =E35+O35 -> -13.25 | S35: Amount recorded by customer but not in our books
A36: I | B36: 256779412563 | C36: 45769 | D36: 0 | E36: -6.94 | F36: C: ASCENDAS27 P: Matching | G36: 22/05/2025 | H36: USD | I36: 45809 | J36: 48 | K36: 45838 | L36: 271 | M36: IN89 | P36: =E36+O36 -> -6.94 | S36: Amount recorded by customer but not in our books
A37: I | B37: 256779412576 | C37: 45769 | D37: 0 | E37: -11.84 | F37: C: ASCENDAS27 P: Matching | G37: 22/05/2025 | H37: USD | I37: 45809 | J37: 52 | K37: 45838 | L37: 271 | M37: IN89 | P37: =E37+O37 -> -11.84 | S37: Amount recorded by customer but not in our books
A38: I | B38: 256779412577 | C38: 45769 | D38: 0 | E38: -11.84 | F38: C: ASCENDAS27 P: Matching | G38: 22/05/2025 | H38: USD | I38: 45809 | J38: 54 | K38: 45838 | L38: 271 | M38: IN89 | P38: =E38+O38 -> -11.84 | S38: Amount recorded by customer but not in our books
A39: I | B39: 256779412580 | C39: 45769 | D39: 0 | E39: -10.42 | F39: C: ASCENDAS27 P: Matching | G39: 22/05/2025 | H39: USD | I39: 45809 | J39: 56 | K39: 45838 | L39: 271 | M39: IN89 | P39: =E39+O39 -> -10.42 | S39: Amount recorded by customer but not in our books
A40: I | B40: 256779412562 | C40: 45769 | D40: 0 | E40: -14.06 | F40: C: ASCENDAS27 P: Matching | G40: 22/05/2025 | H40: USD | I40: 45809 | J40: 66 | K40: 45838 | L40: 271 | M40: IN89 | P40: =E40+O40 -> -14.06 | S40: Amount recorded by customer but not in our books
A41: I | B41: 256779412564 | C41: 45769 | D41: 0 | E41: -14.2 | F41: C: ASCENDAS27 P: Matching | G41: 22/05/2025 | H41: USD | I41: 45809 | J41: 70 | K41: 45838 | L41: 271 | M41: IN89 | P41: =E41+O41 -> -14.2 | S41: Amount recorded by customer but not in our books
... A45: I | B45: 256779412583 | C45: 45769 | D45: 0 | E45: -13.59 | F45: C: ASCENDAS27 P: Matching | G45: 22/05/2025 | H45: USD | I45: 45809 | J45: 104 | K45: 45838 | L45: 271 | M45: IN89 | P45: =E45+O45 -> -13.59 | S45: Amount recorded by customer but not in our books
A46: I | B46: 256779418480 | C46: 45951 | D46: -13.59 | E46: -1204.88 | F46: USD CURRENCY | G46: 20/11/2025 | H46: USD | I46: 45992 | J46: 1 | K46: 46006 | L46: 210 | M46: IN89 | N46: =O46/E46 -> -0.019869199 | O46: =VLOOKUP(B46,'Customer TDS'!A:D,4,0) -> 23.94 | P46: =E46+O46 -> -1180.94 | Q46: =VLOOKUP(B46,Ascendus!E:I,5,0) -> 1198.51 | R46: =E46+Q46 -> -6.37 | S46: Difference due to exchange rate
A47: I | B47: 256779418474 | C47: 45951 | D47: -562.38 | E47: -49860.33 | F47: USD CURRENCY | G47: 20/11/2025 | H47: USD | I47: 46023 | J47: 1 | K47: 46050 | L47: 210 | M47: IN89 | N47: =O47/E47 -> -0.02000428 | O47: =VLOOKUP(B47,'Customer TDS'!A:D,4,0) -> 997.42 | P47: =E47+O47 -> -48862.91 | Q47: =VLOOKUP(B47,Ascendus!E:I,5,0) -> 49596.73 | R47: =E47+Q47 -> -263.6 | S47: Difference due to exchange rate
A48: I | B48: 256779418474 | C48: 45951 | D48: 0 | E48: -1591.62 | F48: C: ASCENDAS27 P: Matching | G48: 20/11/2025 | H48: USD | I48: 46023 | J48: 78 | K48: 46053 | L48: 271 | M48: IN89 | P48: =E48+O48 -> -1591.62 | S48: Amount recorded by customer but not in our books
A49: I | B49: 256779418474 | C49: 45951 | D49: 0 | E49: -14.27 | F49: C: ASCENDAS27 P: Matching | G49: 20/11/2025 | H49: USD | I49: 46023 | J49: 80 | K49: 46053 | L49: 271 | M49: IN89 | P49: =E49+O49 -> -14.27 | S49: Amount recorded by customer but not in our books
A50: I | B50: 256779418474 | C50: 45951 | D50: 0 | E50: -31.65 | F50: C: ASCENDAS27 P: Matching | G50: 20/11/2025 | H50: USD | I50: 46023 | J50: 82 | K50: 46053 | L50: 271 | M50: IN89 | P50: =E50+O50 -> -31.65 | S50: Amount recorded by customer but not in our books
A51: I | B51: 256779413393 | C51: 45798 | D51: -229.87 | E51: -19625.03 | G51: 20/06/2025 | H51: USD | I51: 45839 | J51: 1 | K51: 45968 | L51: 210 | M51: IN89 | P51: =E51+O51 -> -19625.03 | Q51: =VLOOKUP(B51,Ascendus!E:I,5,0) -> 19765.07 | R51: =E51+Q51 -> 140.04 | S51: Difference due to exchange rate
A52: I | B52: 256779413394 | C52: 45798 | D52: -218.17 | E52: -18626.15 | G52: 20/06/2025 | H52: USD | I52: 45839 | J52: 1 | K52: 45968 | L52: 210 | M52: IN89 | P52: =E52+O52 -> -18626.15 | Q52: =VLOOKUP(B52,Ascendus!E:I,5,0) -> 18759.06 | R52: =E52+Q52 -> 132.91 | S52: Difference due to exchange rate
A53: I | B53: 256779413403 | C53: 45798 | D53: -402.88 | E53: -34395.67 | G53: 20/06/2025 | H53: USD | I53: 45839 | J53: 1 | K53: 45968 | L53: 210 | M53: IN89 | P53: =E53+O53 -> -34395.67 | Q53: =VLOOKUP(B53,Ascendus!E:I,5,0) -> 34641.11 | R53: =E53+Q53 -> 245.44 | S53: Difference due to exchange rate
A54: I | B54: 256779413397 | C54: 45798 | D54: -229.87 | E54: -19625.03 | G54: 20/06/2025 | H54: USD | I54: 45839 | J54: 1 | K54: 45968 | L54: 210 | M54: IN89 | P54: =E54+O54 -> -19625.03 | Q54: =VLOOKUP(B54,Ascendus!E:I,5,0) -> 19765.07 | R54: =E54+Q54 -> 140.04 | S54: Difference due to exchange rate
A55: I | B55: 256779413398 | C55: 45798 | D55: -218.17 | E55: -18626.15 | G55: 20/06/2025 | H55: USD | I55: 45839 | J55: 1 | K55: 45968 | L55: 210 | M55: IN89 | P55: =E55+O55 -> -18626.15 | Q55: =VLOOKUP(B55,Ascendus!E:I,5,0) -> 18759.06 | R55: =E55+Q55 -> 132.91 | S55: Difference due to exchange rate
A56: I | B56: 256779413400 | C56: 45798 | D56: -218.17 | E56: -18626.15 | F56: USD CURRENCY | G56: 20/06/2025 | H56: USD | I56: 45839 | J56: 1 | K56: 45968 | L56: 210 | M56: IN89 | P56: =E56+O56 -> -18626.15 | Q56: =VLOOKUP(B56,Ascendus!E:I,5,0) -> 18759.06 | R56: =E56+Q56 -> 132.91 | S56: Difference due to exchange rate
A57: I | B57: 256779413402 | C57: 45798 | D57: -229.87 | E57: -19625.03 | G57: 20/06/2025 | H57: USD | I57: 45839 | J57: 1 | K57: 45968 | L57: 210 | M57: IN89 | P57: =E57+O57 -> -19625.03 | Q57: =VLOOKUP(B57,Ascendus!E:I,5,0) -> 19765.07 | R57: =E57+Q57 -> 140.04 | S57: Difference due to exchange rate
A58: I | B58: 256779413396 | C58: 45798 | D58: -218.17 | E58: -18626.15 | G58: 20/06/2025 | H58: USD | I58: 45839 | J58: 1 | K58: 45968 | L58: 210 | M58: IN89 | N58: =O58/E58 -> -0.019984269 | O58: =VLOOKUP(B58,'Customer TDS'!A:D,4,0) -> 372.23 | P58: =E58+O58 -> -18253.92 | Q58: =VLOOKUP(B58,Ascendus!E:I,5,0) -> 18759.06 | R58: =E58+Q58 -> 132.91 | S58: Difference due to exchange rate
A59: I | B59: 256779413401 | C59: 45798 | D59: -229.87 | E59: -19625.03 | G59: 20/06/2025 | H59: USD | I59: 45839 | J59: 1 | K59: 45968 | L59: 210 | M59: IN89 | N59: =O59/E59 -> -0.02001118 | O59: =VLOOKUP(B59,'Customer TDS'!A:D,4,0) -> 392.72 | P59: =E59+O59 -> -19232.31 | Q59: =VLOOKUP(B59,Ascendus!E:I,5,0) -> 19765.07 | R59: =E59+Q59 -> 140.04 | S59: Difference due to exchange rate
A60: I | B60: 256779413395 | C60: 45798 | D60: -264.98 | E60: -22622.53 | G60: 20/06/2025 | H60: USD | I60: 45839 | J60: 1 | K60: 45968 | L60: 210 | M60: IN89 | N60: =O60/E60 -> -0.0200013 | O60: =VLOOKUP(B60,'Customer TDS'!A:D,4,0) -> 452.48 | P60: =E60+O60 -> -22170.05 | Q60: =VLOOKUP(B60,Ascendus!E:I,5,0) -> 22783.96 | R60: =E60+Q60 -> 161.43 | S60: Difference due to exchange rate
A61: I | B61: 256779413399 | C61: 45798 | D61: -229.87 | E61: -19625.03 | G61: 20/06/2025 | H61: USD | I61: 45839 | J61: 1 | K61: 45968 | L61: 210 | M61: IN89 | N61: =O61/E61 -> -0.02001118 | O61: =VLOOKUP(B61,'Customer TDS'!A:D,4,0) -> 392.72 | P61: =E61+O61 -> -19232.31 | Q61: =VLOOKUP(B61,Ascendus!E:I,5,0) -> 19765.07 | R61: =E61+Q61 -> 140.04 | S61: Difference due to exchange rate
A62: I | B62: 256779413391 | C62: 45798 | D62: -253.29 | E62: -21624.5 | G62: 20/06/2025 | H62: USD | I62: 45901 | J62: 1 | K62: 45930 | L62: 210 | M62: IN89 | N62: =O62/E62 -> -0.020016648 | O62: =VLOOKUP(B62,'Customer TDS'!A:D,4,0) -> 432.85 | P62: =E62+O62 -> -21191.65 | Q62: =VLOOKUP(B62,Ascendus!E:I,5,0) -> 21778.81 | R62: =E62+Q62 -> 154.31 | S62: Difference due to exchange rate
A63: I | B63: 256779413392 | C63: 45798 | D63: -218.17 | E63: -18626.15 | G63: 20/06/2025 | H63: USD | I63: 45901 | J63: 1 | K63: 45930 | L63: 210 | M63: IN89 | N63: =O63/E63 -> -0.019984269 | O63: =VLOOKUP(B63,'Customer TDS'!A:D,4,0) -> 372.23 | P63: =E63+O63 -> -18253.92 | Q63: =VLOOKUP(B63,Ascendus!E:I,5,0) -> 18759.06 | R63: =E63+Q63 -> 132.91 | S63: Difference due to exchange rate
A64: I | B64: 256779413391 | C64: 45798 | D64: 0 | E64: -815.41 | F64: C: ASCENDAS27 P: Matching | G64: 20/06/2025 | H64: USD | I64: 45901 | J64: 64 | K64: 45930 | L64: 271 | M64: IN89 | P64: =E64+O64 -> -815.41 | S64: Amount recorded by customer but not in our books
A65: I | B65: 256779413392 | C65: 45798 | D65: 0 | E65: -702.37 | F65: C: ASCENDAS27 P: Matching | G65: 20/06/2025 | H65: USD | I65: 45901 | J65: 70 | K65: 45930 | L65: 271 | M65: IN89 | P65: =E65+O65 -> -702.37 | S65: Amount recorded by customer but not in our books
A66: I | B66: 256779412184 | C66: 45768 | D66: -93.23 | E66: -7992.33 | G66: 21/05/2025 | H66: USD | I66: 45809 | J66: 1 | K66: 45838 | L66: 210 | M66: IN89 | N66: =O66/E66 -> -0.019950377 | O66: =VLOOKUP(B66,'Customer TDS'!A:D,4,0) -> 159.45 | P66: =E66+O66 -> -7832.88 | Q66: =VLOOKUP(B66,Ascendus!E:I,5,0) -> 8000.07 | R66: =E66+Q66 -> 7.74 | S66: Difference due to exchange rate
A67: I | B67: 256779412185 | C67: 45768 | D67: -51.28 | E67: -4396.08 | G67: 21/05/2025 | H67: USD | I67: 45809 | J67: 1 | K67: 45838 | L67: 210 | M67: IN89 | N67: =O67/E67 -> -0.020086077 | O67: =VLOOKUP(B67,'Customer TDS'!A:D,4,0) -> 88.3 | P67: =E67+O67 -> -4307.78 | Q67: =VLOOKUP(B67,Ascendus!E:I,5,0) -> 4400.34 | R67: =E67+Q67 -> 4.26 | S67: Difference due to exchange rate
A68: I | B68: 256779412189 | C68: 45768 | D68: 0 | E68: -262.21 | G68: 21/05/2025 | H68: INR | I68: 45809 | J68: 1 | K68: 45838 | L68: 210 | M68: IN89 | N68: =O68/E68 -> -0.022882422 | O68: =VLOOKUP(B68,'Customer TDS'!A:D,4,0) -> 6 | P68: =E68+O68 -> -256.21 | Q68: =VLOOKUP(B68,Ascendus!E:I,5,0) -> 262.21 | R68: =E68+Q68 -> 0 | S68: Difference due to exchange rate
A69: I | B69: 256779412155 | C69: 45768 | D69: -2330.73 | E69: -199806.42 | G69: 21/05/2025 | H69: USD | I69: 45809 | J69: 1 | K69: 45838 | L69: 210 | M69: IN89 | N69: =O69/E69 -> -0.019998006 | O69: =VLOOKUP(B69,'Customer TDS'!A:D,4,0) -> 3995.73 | P69: =E69+O69 -> -195810.69 | Q69: =VLOOKUP(B69,Ascendus!E:I,5,0) -> 199999.94 | R69: =E69+Q69 -> 193.52 | S69: Difference due to exchange rate
A70: I | B70: 256779412184 | C70: 45768 | D70: 0 | E70: -23.98 | F70: C: ASCENDAS27 P: Matching | G70: 21/05/2025 | H70: USD | I70: 45809 | J70: 42 | K70: 45838 | L70: 271 | M70: IN89 | P70: =E70+O70 -> -23.98 | S70: Amount recorded by customer but not in our books
A71: I | B71: 256779412185 | C71: 45768 | D71: 0 | E71: -13.19 | F71: C: ASCENDAS27 P: Matching | G71: 21/05/2025 | H71: USD | I71: 45809 | J71: 46 | K71: 45838 | L71: 271 | M71: IN89 | P71: =E71+O71 -> -13.19 | S71: Amount recorded by customer but not in our books
A72: I | B72: 256779412155 | C72: 45768 | D72: 0 | E72: -599.67 | F72: C: ASCENDAS27 P: Matching | G72: 21/05/2025 | H72: USD | I72: 45809 | J72: 84 | K72: 45838 | L72: 271 | M72: IN89 | P72: =E72+O72 -> -599.67 | S72: Amount recorded by customer but not in our books
A73: I | B73: 256779419542 | C73: 45981 | D73: -409.4 | E73: -36130.6 | F73: USD CURRENCY- NO EXCHANGE RATE PROVIDED | G73: 20/12/2025 | H73: USD | I73: 45992 | J73: 1 | K73: 46006 | L73: 210 | M73: IN89 | N73: =O73/E73 -> -0.020004927 | O73: =VLOOKUP(B73,'Customer TDS'!A:D,4,0) -> 722.79 | P73: =E73+O73 -> -35407.81 | Q73: =VLOOKUP(B73,Ascendus!E:I,5,0) -> 36028.59 | R73: =E73+Q73 -> -102.01 | S73: Difference due to exchange rate
A74: I | B74: 256779419531 | C74: 45981 | D74: -417.77 | E74: -36869.28 | F74: USD CURRENCY | G74: 20/12/2025 | H74: USD | I74: 46023 | J74: 1 | K74: 46049 | L74: 210 | M74: IN89 | N74: =O74/E74 -> -0.020010968 | O74: =VLOOKUP(B74,'Customer TDS'!A:D,4,0) -> 737.79 | P74: =E74+O74 -> -36131.49 | Q74: =VLOOKUP(B74,Ascendus!E:I,5,0) -> 36765.18 | R74: =E74+Q74 -> -104.1 | S74: Difference due to exchange rate
A75: I | B75: 256779419620 | C75: 45981 | D75: -102.39 | E75: -9036.18 | F75: USD CURRENCY | G75: 20/12/2025 | H75: USD | I75: 46023 | J75: 1 | K75: 46049 | L75: 210 | M75: IN89 | N75: =O75/E75 -> -0.020021735 | O75: =VLOOKUP(B75,'Customer TDS'!A:D,4,0) -> 180.92 | P75: =E75+O75 -> -8855.26 | Q75: =VLOOKUP(B75,Ascendus!E:I,5,0) -> 9010.67 | R75: =E75+Q75 -> -25.51 | S75: Difference due to exchange rate
A76: I | B76: 256779418653 | C76: 45950 | D76: -170.68 | E76: -15132.4 | F76: USD CURRENCY | G76: 19/11/2025 | H76: USD | I76: 46023 | J76: 1 | K76: 46050 | L76: 210 | M76: IN89 | N76: =O76/E76 -> -0.019978985 | O76: =VLOOKUP(B76,'Customer TDS'!A:D,4,0) -> 302.33 | P76: =E76+O76 -> -14830.07 | Q76: =VLOOKUP(B76,Ascendus!E:I,5,0) -> 15052.4 | R76: =E76+Q76 -> -80 | S76: Difference due to exchange rate
A77: I | B77: 256779418653 | C77: 45950 | D77: 0 | E77: -166.44 | F77: C: ASCENDAS27 P: Matching | G77: 19/11/2025 | H77: USD | I77: 46023 | J77: 90 | K77: 46053 | L77: 271 | M77: IN89 | P77: =E77+O77 -> -166.44 | S77: Amount recorded by customer but not in our books
A78: I | B78: 256779418653 | C78: 45950 | D78: 0 | E78: -330.56 | F78: C: ASCENDAS27 P: Matching | G78: 19/11/2025 | H78: USD | I78: 46023 | J78: 92 | K78: 46053 | L78: 271 | M78: IN89 | P78: =E78+O78 -> -330.56 | S78: Amount recorded by customer but not in our books
A79: I | B79: 256779416869 | C79: 45889 | D79: -115.98 | E79: -10047.45 | F79: USD CURRENCY | G79: 19/09/2025 | H79: USD | I79: 46023 | J79: 1 | K79: 46050 | L79: 210 | M79: IN89 | N79: =O79/E79 -> -0.020003085 | O79: =VLOOKUP(B79,'Customer TDS'!A:D,4,0) -> 200.98 | P79: =E79+O79 -> -9846.47 | Q79: =VLOOKUP(B79,Ascendus!E:I,5,0) -> 9977.77 | R79: =E79+Q79 -> -69.68 | S79: Difference due to exchange rate
A80: I | B80: 256779416838 | C80: 45889 | D80: -685.03 | E80: -59344.77 | F80: USD CURRENCY | G80: 19/09/2025 | H80: USD | I80: 46023 | J80: 1 | K80: 46050 | L80: 210 | M80: IN89 | N80: =O80/E80 -> -0.019999066 | O80: =VLOOKUP(B80,'Customer TDS'!A:D,4,0) -> 1186.84 | P80: =E80+O80 -> -58157.93 | Q80: =VLOOKUP(B80,Ascendus!E:I,5,0) -> 58933.21 | R80: =E80+Q80 -> -411.56 | S80: Difference due to exchange rate
A81: I | B81: 256779416869 | C81: 45889 | D81: 0 | E81: -568.28 | F81: C: ASCENDAS27 P: Matching | G81: 19/09/2025 | H81: USD | I81: 46023 | J81: 84 | K81: 46053 | L81: 271 | M81: IN89 | P81: =E81+O81 -> -568.28 | S81: Amount recorded by customer but not in our books
A82: I | B82: 256779416838 | C82: 45889 | D82: 0 | E82: -3356.53 | F82: C: ASCENDAS27 P: Matching | G82: 19/09/2025 | H82: USD | I82: 46023 | J82: 88 | K82: 46053 | L82: 271 | M82: IN89 | P82: =E82+O82 -> -3356.53 | S82: Amount recorded by customer but not in our books
A83: I | B83: 246779414663 | C83: 45736 | D83: -45 | E83: -3916.91 | G83: 19/04/2025 | H83: USD | I83: 45809 | J83: 1 | K83: 45997 | L83: 210 | M83: IN89 | N83: =O83/E83 -> -0.02000046 | O83: =VLOOKUP(B83,'Customer TDS'!A:D,4,0) -> 78.34 | P83: =E83+O83 -> -3838.57 | Q83: =VLOOKUP(B83,Ascendus!E:I,5,0) -> 3901.11 | R83: =E83+Q83 -> -15.8 | S83: Difference due to exchange rate
A84: I | B84: 246779414662 | C84: 45736 | D84: -275 | E84: -23936.66 | G84: 19/04/2025 | H84: USD | I84: 45809 | J84: 1 | K84: 45997 | L84: 210 | M84: IN89 | N84: =O84/E84 -> -0.019999866 | O84: =VLOOKUP(B84,'Customer TDS'!A:D,4,0) -> 478.73 | P84: =E84+O84 -> -23457.93 | Q84: =VLOOKUP(B84,Ascendus!E:I,5,0) -> 23840.1 | R84: =E84+Q84 -> -96.56 | S84: Difference due to exchange rate
A85: I | B85: 246779414385 | C85: 45736 | D85: -240 | E85: -20890.18 | G85: 19/04/2025 | H85: USD | I85: 45809 | J85: 1 | K85: 45997 | L85: 210 | M85: IN89 | N85: =O85/E85 -> -0.019999828 | O85: =VLOOKUP(B85,'Customer TDS'!A:D,4,0) -> 417.8 | P85: =E85+O85 -> -20472.38 | Q85: =VLOOKUP(B85,Ascendus!E:I,5,0) -> 20805.9 | R85: =E85+Q85 -> -84.28 | S85: Difference due to exchange rate
A86: I | B86: 246779413730 | C86: 45736 | D86: -3.2 | E86: -278.54 | G86: 19/04/2025 | H86: USD | I86: 45809 | J86: 1 | K86: 45997 | L86: 210 | M86: IN89 | N86: =O86/E86 -> -0.018740576 | O86: =VLOOKUP(B86,'Customer TDS'!A:D,4,0) -> 5.22 | P86: =E86+O86 -> -273.32 | Q86: =VLOOKUP(B86,Ascendus!E:I,5,0) -> 277.41 | R86: =E86+Q86 -> -1.13 | S86: Difference due to exchange rate
A87: I | B87: 246779413936 | C87: 45736 | D87: -27.5 | E87: -2393.67 | G87: 19/04/2025 | H87: USD | I87: 45809 | J87: 1 | K87: 45838 | L87: 210 | M87: IN89 | N87: =O87/E87 -> -0.01999858 | O87: =VLOOKUP(B87,'Customer TDS'!A:D,4,0) -> 47.87 | P87: =E87+O87 -> -2345.8 | Q87: =VLOOKUP(B87,Ascendus!E:I,5,0) -> 2384.01 | R87: =E87+Q87 -> -9.66 | S87: Difference due to exchange rate
A88: I | B88: 246779413889 | C88: 45736 | D88: -42.5 | E88: -3699.3 | G88: 19/04/2025 | H88: USD | I88: 45809 | J88: 1 | K88: 45838 | L88: 210 | M88: IN89 | N88: =O88/E88 -> -0.020001081 | O88: =VLOOKUP(B88,'Customer TDS'!A:D,4,0) -> 73.99 | P88: =E88+O88 -> -3625.31 | Q88: =VLOOKUP(B88,Ascendus!E:I,5,0) -> 3684.38 | R88: =E88+Q88 -> -14.92 | S88: Difference due to exchange rate
A89: I | B89: 246779413920 | C89: 45736 | D89: -22.5 | E89: -1958.45 | G89: 19/04/2025 | H89: USD | I89: 45809 | J89: 1 | K89: 45838 | L89: 210 | M89: IN89 | N89: =O89/E89 -> -0.020000511 | O89: =VLOOKUP(B89,'Customer TDS'!A:D,4,0) -> 39.17 | P89: =E89+O89 -> -1919.28 | Q89: =VLOOKUP(B89,Ascendus!E:I,5,0) -> 1950.55 | R89: =E89+Q89 -> -7.9 | S89: Difference due to exchange rate
A90: I | B90: 246779413941 | C90: 45736 | D90: -30 | E90: -2611.27 | G90: 19/04/2025 | H90: USD | I90: 45809 | J90: 1 | K90: 45838 | L90: 210 | M90: IN89 | N90: =O90/E90 -> -0.020001762 | O90: =VLOOKUP(B90,'Customer TDS'!A:D,4,0) -> 52.23 | P90: =E90+O90 -> -2559.04 | Q90: =VLOOKUP(B90,Ascendus!E:I,5,0) -> 2600.74 | R90: =E90+Q90 -> -10.53 | S90: Difference due to exchange rate
A91: I | B91: 246779413815 | C91: 45736 | D91: -50 | E91: -4352.12 | G91: 19/04/2025 | H91: USD | I91: 45809 | J91: 1 | K91: 45838 | L91: 210 | M91: IN89 | N91: =O91/E91 -> -0.019999449 | O91: =VLOOKUP(B91,'Customer TDS'!A:D,4,0) -> 87.04 | P91: =E91+O91 -> -4265.08 | Q91: =VLOOKUP(B91,Ascendus!E:I,5,0) -> 4334.56 | R91: =E91+Q91 -> -17.56 | S91: Difference due to exchange rate
A92: I | B92: 246779414384 | C92: 45736 | D92: -182.5 | E92: -15885.24 | G92: 19/04/2025 | H92: USD | I92: 45809 | J92: 1 | K92: 45838 | L92: 210 | M92: IN89 | N92: =O92/E92 -> -0.019999698 | O92: =VLOOKUP(B92,'Customer TDS'!A:D,4,0) -> 317.7 | P92: =E92+O92 -> -15567.54 | Q92: =VLOOKUP(B92,Ascendus!E:I,5,0) -> 15821.15 | R92: =E92+Q92 -> -64.09 | S92: Difference due to exchange rate
A93: I | B93: 246779413936 | C93: 45736 | D93: 0 | E93: 28.38 | F93: C: ASCENDAS27 P: Matching | G93: 19/04/2025 | H93: USD | I93: 45809 | J93: 10 | K93: 45838 | L93: 271 | M93: IN89 | P93: =E93+O93 -> 28.38 | S93: Amount recorded by customer but not in our books
A94: I | B94: 246779413889 | C94: 45736 | D94: 0 | E94: 43.85 | F94: C: ASCENDAS27 P: Matching | G94: 19/04/2025 | H94: USD | I94: 45809 | J94: 28 | K94: 45838 | L94: 271 | M94: IN89 | P94: =E94+O94 -> 43.85 | S94: Amount recorded by customer but not in our books
A95: I | B95: 246779413920 | C95: 45736 | D95: 0 | E95: 23.21 | F95: C: ASCENDAS27 P: Matching | G95: 19/04/2025 | H95: USD | I95: 45809 | J95: 32 | K95: 45838 | L95: 271 | M95: IN89 | P95: =E95+O95 -> 23.21 | S95: Amount recorded by customer but not in our books
A96: I | B96: 246779413941 | C96: 45736 | D96: 0 | E96: 30.95 | F96: C: ASCENDAS27 P: Matching | G96: 19/04/2025 | H96: USD | I96: 45809 | J96: 36 | K96: 45838 | L96: 271 | M96: IN89 | P96: =E96+O96 -> 30.95 | S96: Amount recorded by customer but not in our books
A97: I | B97: 246779413815 | C97: 45736 | D97: 0 | E97: 51.59 | F97: C: ASCENDAS27 P: Matching | G97: 19/04/2025 | H97: USD | I97: 45809 | J97: 58 | K97: 45838 | L97: 271 | M97: IN89 | P97: =E97+O97 -> 51.59 | S97: Amount recorded by customer but not in our books
A98: I | B98: 246779414384 | C98: 45736 | D98: 0 | E98: 188.32 | F98: C: ASCENDAS27 P: Matching | G98: 19/04/2025 | H98: USD | I98: 45809 | J98: 88 | K98: 45838 | L98: 271 | M98: IN89 | P98: =E98+O98 -> 188.32 | S98: Amount recorded by customer but not in our books
A99: I | B99: 246779413747 | C99: 45736 | D99: -2.74 | E99: -238.5 | G99: 19/04/2025 | H99: USD | I99: 45901 | J99: 1 | K99: 45930 | L99: 210 | M99: IN89 | N99: =O99/E99 -> -0.018238994 | O99: =VLOOKUP(B99,'Customer TDS'!A:D,4,0) -> 4.35 | P99: =E99+O99 -> -234.15 | Q99: =VLOOKUP(B99,Ascendus!E:I,5,0) -> 237.53 | R99: =E99+Q99 -> -0.97 | S99: Difference due to exchange rate
A100: I | B100: 246779413747 | C100: 45736 | D100: 0 | E100: -4.34 | F100: C: ASCENDAS27 P: Matching | G100: 19/04/2025 | H100: USD | I100: 45901 | J100: 58 | K100: 45930 | L100: 271 | M100: IN89 | P100: =E100+O100 -> -4.34 | S100: Amount recorded by customer but not in our books
A101: I | B101: 246779410315 | C101: 45708 | D101: -2380.95 | E101: -207243.64 | G101: 22/03/2025 | H101: USD | I101: 45809 | J101: 1 | K101: 45997 | L101: 210 | M101: IN89 | N101: =O101/E101 -> -0.020000421 | O101: =VLOOKUP(B101,'Customer TDS'!A:D,4,0) -> 4144.96 | P101: =E101+O101 -> -203098.68 | Q101: =VLOOKUP(B101,Ascendus!E:I,5,0) -> 205484.7 | R101: =E101+Q101 -> -1758.94 | S101: Difference due to exchange rate
A102: I | B102: 246779410098 | C102: 45708 | D102: -2380.95 | E102: -206046.42 | G102: 22/03/2025 | H102: USD | I102: 45809 | J102: 1 | K102: 45997 | L102: 210 | M102: IN89 | N102: =O102/E102 -> -0.020000396 | O102: =VLOOKUP(B102,'Customer TDS'!A:D,4,0) -> 4121.01 | P102: =E102+O102 -> -201925.41 | Q102: =VLOOKUP(B102,Ascendus!E:I,5,0) -> 205484.7 | R102: =E102+Q102 -> -561.72 | S102: Difference due to exchange rate
A103: I | B103: 246779410132 | C103: 45708 | D103: -52.38 | E103: -4532.94 | G103: 22/03/2025 | H103: USD | I103: 45809 | J103: 1 | K103: 45997 | L103: 210 | M103: IN89 | N103: =O103/E103 -> -0.020046592 | O103: =VLOOKUP(B103,'Customer TDS'!A:D,4,0) -> 90.87 | P103: =E103+O103 -> -4442.07 | Q103: =VLOOKUP(B103,Ascendus!E:I,5,0) -> 4520.59 | R103: =E103+Q103 -> -12.35 | S103: Difference due to exchange rate
A104: I | B104: 246779410131 | C104: 45708 | D104: -95.24 | E104: -8242.03 | G104: 22/03/2025 | H104: USD | I104: 45809 | J104: 1 | K104: 45997 | L104: 210 | M104: IN89 | N104: =O104/E104 -> -0.019950182 | O104: =VLOOKUP(B104,'Customer TDS'!A:D,4,0) -> 164.43 | P104: =E104+O104 -> -8077.6 | Q104: =VLOOKUP(B104,Ascendus!E:I,5,0) -> 8219.56 | R104: =E104+Q104 -> -22.47 | S104: Difference due to exchange rate
A105: I | B105: 246779410312 | C105: 45708 | D105: -52.38 | E105: -4559.28 | G105: 22/03/2025 | H105: USD | I105: 45809 | J105: 1 | K105: 45997 | L105: 210 | M105: IN89 | N105: =O105/E105 -> -0.020044832 | O105: =VLOOKUP(B105,'Customer TDS'!A:D,4,0) -> 91.39 | P105: =E105+O105 -> -4467.89 | Q105: =VLOOKUP(B105,Ascendus!E:I,5,0) -> 4520.59 | R105: =E105+Q105 -> -38.69 | S105: Difference due to exchange rate
A106: I | B106: 246779410175 | C106: 45708 | D106: -52.38 | E106: -4532.94 | G106: 22/03/2025 | H106: USD | I106: 45809 | J106: 1 | K106: 45997 | L106: 210 | M106: IN89 | N106: =O106/E106 -> -0.020046592 | O106: =VLOOKUP(B106,'Customer TDS'!A:D,4,0) -> 90.87 | P106: =E106+O106 -> -4442.07 | Q106: =VLOOKUP(B106,Ascendus!E:I,5,0) -> 4520.59 | R106: =E106+Q106 -> -12.35 | S106: Difference due to exchange rate
...

Sheet Customer TDS
A2: Item# | B2: Item Date | C2: FC Amount | D2: LC Amount | E2: Particular | F2: Due Date | G2: CCY | H2: VC Period | I2: VC Seq | J2: VC Date | K2: Tx. Type | L2: Company Code
A3: 256779413908 | B3: 45805 | C3: 64.02 | D3: 5465.67 | E3: C: ASCENDAS27 P: A023951 I 256779413908 | F3: 27/06/2025 | G3: USD | H3: 45962 | I3: 1 | J3: 30/11/2025 | K3: 230 | L3: IN89
A4: 256779416007 | B4: 45863 | C4: 8.42 | D4: 724.03 | E4: C: ASCENDAS27 P: A023951 I 256779416007 | F4: 24/08/2025 | G4: USD | H4: 45931 | I4: 1 | J4: 29/10/2025 | K4: 230 | L4: IN89
A5: 256779415989 | B5: 45863 | C5: 6 | D5: 515.94 | E5: C: ASCENDAS27 P: A023951 I 256779415989 | F5: 24/08/2025 | G5: USD | H5: 45931 | I5: 1 | J5: 29/10/2025 | K5: 230 | L5: IN89
A6: 256779412776 | B6: 45771 | C6: 12.65 | D6: 1084.45 | E6: C: ASCENDAS27 P: A023951 I 256779412776 | F6: 24/05/2025 | G6: USD | H6: 45962 | I6: 1 | J6: 30/11/2025 | K6: 230 | L6: IN89
A7: 256779417801 | B7: 45922 | C7: 95.11 | D7: 8336.57 | E7: C: ASCENDAS27 P: A023951 I 256779417801 | F7: 22/10/2025 | G7: USD | H7: 45931 | I7: 1 | J7: 29/10/2025 | K7: 230 | L7: IN89
A8: 256779417744 | B8: 45922 | C8: 17.4 | D8: 1525.14 | E8: C: ASCENDAS27 P: A023951 I 256779417744 | F8: 22/10/2025 | G8: USD | H8: 45962 | I8: 1 | J8: 45972 | K8: 230 | L8: IN89
A9: 256779412577 | B9: 45769 | C9: 0.92 | D9: 78.87 | E9: C: ASCENDAS27 P: A023951 I 256779412577 | F9: 22/05/2025 | G9: USD | H9: 45809 | I9: 1 | J9: 30/06/2025 | K9: 230 | L9: IN89
A10: 256779412564 | B10: 45769 | C10: 1.1 | D10: 94.3 | E10: C: ASCENDAS27 P: A023951 I 256779412564 | F10: 22/05/2025 | G10: USD | H10: 45809 | I10: 1 | J10: 30/06/2025 | K10: 230 | L10: IN89
A11: 256779412529 | B11: 45769 | C11: 0.59 | D11: 50.58 | E11: C: ASCENDAS27 P: A023951 I 256779412529 | F11: 22/05/2025 | G11: USD | H11: 45809 | I11: 1 | J11: 30/06/2025 | K11: 230 | L11: IN89
A12: 256779412563 | B12: 45769 | C12: 0.54 | D12: 46.29 | E12: C: ASCENDAS27 P: A023951 I 256779412563 | F12: 22/05/2025 | G12: USD | H12: 45809 | I12: 1 | J12: 30/06/2025 | K12: 230 | L12: IN89
A13: 256779412570 | B13: 45769 | C13: 0.87 | D13: 74.58 | E13: C: ASCENDAS27 P: A023951 I 256779412570 | F13: 22/05/2025 | G13: USD | H13: 45809 | I13: 1 | J13: 30/06/2025 | K13: 230 | L13: IN89
A14: 256779412580 | B14: 45769 | C14: 0.81 | D14: 69.44 | E14: C: ASCENDAS27 P: A023951 I 256779412580 | F14: 22/05/2025 | G14: USD | H14: 45809 | I14: 1 | J14: 30/06/2025 | K14: 230 | L14: IN89
A15: 256779412581 | B15: 45769 | C15: 1.03 | D15: 88.3 | E15: C: ASCENDAS27 P: A023951 I 256779412581 | F15: 22/05/2025 | G15: USD | H15: 45809 | I15: 1 | J15: 30/06/2025 | K15: 230 | L15: IN89
A16: 256779412536 | B16: 45769 | C16: 0.74 | D16: 63.44 | E16: C: ASCENDAS27 P: A023951 I 256779412536 | F16: 22/05/2025 | G16: USD | H16: 45809 | I16: 1 | J16: 30/06/2025 | K16: 230 | L16: IN89
A17: 256779412576 | B17: 45769 | C17: 0.92 | D17: 78.87 | E17: C: ASCENDAS27 P: A023951 I 256779412576 | F17: 22/05/2025 | G17: USD | H17: 45809 | I17: 1 | J17: 30/06/2025 | K17: 230 | L17: IN89
A18: 256779412524 | B18: 45769 | C18: 0.73 | D18: 62.58 | E18: C: ASCENDAS27 P: A023951 I 256779412524 | F18: 22/05/2025 | G18: USD | H18: 45809 | I18: 1 | J18: 30/06/2025 | K18: 230 | L18: IN89
A19: 256779412537 | B19: 45769 | C19: 8.15 | D19: 698.67 | E19: C: ASCENDAS27 P: A023951 I 256779412537 | F19: 22/05/2025 | G19: USD | H19: 45809 | I19: 1 | J19: 30/06/2025 | K19: 230 | L19: IN89
A20: 256779412585 | B20: 45769 | C20: 0.98 | D20: 84.01 | E20: C: ASCENDAS27 P: A023951 I 256779412585 | F20: 22/05/2025 | G20: USD | H20: 45809 | I20: 1 | J20: 30/06/2025 | K20: 230 | L20: IN89
... A25: 256779418474 | B25: 45951 | C25: 11.25 | D25: 997.42 | E25: C: ASCENDAS27 P: A023951 I 256779418474 | F25: 20/11/2025 | G25: USD | H25: 46023 | I25: 1 | J25: 28/01/2026 | K25: 230 | L25: IN89
A26: 256779413396 | B26: 45798 | C26: 4.36 | D26: 372.23 | E26: C: ASCENDAS27 P: A023951 I 256779413396 | F26: 20/06/2025 | G26: USD | H26: 45839 | I26: 1 | J26: 45968 | K26: 230 | L26: IN89
A27: 256779413401 | B27: 45798 | C27: 4.6 | D27: 392.72 | E27: C: ASCENDAS27 P: A023951 I 256779413401 | F27: 20/06/2025 | G27: USD | H27: 45839 | I27: 1 | J27: 45968 | K27: 230 | L27: IN89
A28: 256779413395 | B28: 45798 | C28: 5.3 | D28: 452.48 | E28: C: ASCENDAS27 P: A023951 I 256779413395 | F28: 20/06/2025 | G28: USD | H28: 45839 | I28: 1 | J28: 45968 | K28: 230 | L28: IN89
A29: 256779413399 | B29: 45798 | C29: 4.6 | D29: 392.72 | E29: C: ASCENDAS27 P: A023951 I 256779413399 | F29: 20/06/2025 | G29: USD | H29: 45839 | I29: 1 | J29: 45968 | K29: 230 | L29: IN89
A30: 256779413391 | B30: 45798 | C30: 5.07 | D30: 432.85 | E30: C: ASCENDAS27 P: A023951 I 256779413391 | F30: 20/06/2025 | G30: USD | H30: 45901 | I30: 1 | J30: 30/09/2025 | K30: 230 | L30: IN89
A31: 256779413392 | B31: 45798 | C31: 4.36 | D31: 372.23 | E31: C: ASCENDAS27 P: A023951 I 256779413392 | F31: 20/06/2025 | G31: USD | H31: 45901 | I31: 1 | J31: 30/09/2025 | K31: 230 | L31: IN89
A32: 256779412189 | B32: 45768 | C32: 0 | D32: 6 | E32: C: ASCENDAS27 P: A023951 I 256779412189 | F32: 21/05/2025 | G32: INR | H32: 45809 | I32: 1 | J32: 30/06/2025 | K32: 230 | L32: IN89
A33: 256779412185 | B33: 45768 | C33: 1.03 | D33: 88.3 | E33: C: ASCENDAS27 P: A023951 I 256779412185 | F33: 21/05/2025 | G33: USD | H33: 45809 | I33: 1 | J33: 30/06/2025 | K33: 230 | L33: IN89
A34: 256779412184 | B34: 45768 | C34: 1.86 | D34: 159.45 | E34: C: ASCENDAS27 P: A023951 I 256779412184 | F34: 21/05/2025 | G34: USD | H34: 45809 | I34: 1 | J34: 30/06/2025 | K34: 230 | L34: IN89
A35: 256779412155 | B35: 45768 | C35: 46.61 | D35: 3995.73 | E35: C: ASCENDAS27 P: A023951 I 256779412155 | F35: 21/05/2025 | G35: USD | H35: 45809 | I35: 1 | J35: 30/06/2025 | K35: 230 | L35: IN89
A36: 256779419542 | B36: 45981 | C36: 8.19 | D36: 722.79 | E36: C: ASCENDAS27 P: A023951 I 256779419542 | F36: 20/12/2025 | G36: USD | H36: 45992 | I36: 1 | J36: 15/12/2025 | K36: 230 | L36: IN89
A37: 256779419620 | B37: 45981 | C37: 2.05 | D37: 180.92 | E37: C: ASCENDAS27 P: A023951 I 256779419620 | F37: 20/12/2025 | G37: USD | H37: 46023 | I37: 1 | J37: 27/01/2026 | K37: 230 | L37: IN89
A38: 256779419531 | B38: 45981 | C38: 8.36 | D38: 737.79 | E38: C: ASCENDAS27 P: A023951 I 256779419531 | F38: 20/12/2025 | G38: USD | H38: 46023 | I38: 1 | J38: 27/01/2026 | K38: 230 | L38: IN89
A39: 256779418653 | B39: 45950 | C39: 3.41 | D39: 302.33 | E39: C: ASCENDAS27 P: A023951 I 256779418653 | F39: 19/11/2025 | G39: USD | H39: 46023 | I39: 1 | J39: 28/01/2026 | K39: 230 | L39: IN89
A40: 256779416838 | B40: 45889 | C40: 13.7 | D40: 1186.84 | E40: C: ASCENDAS27 P: A023951 I 256779416838 | F40: 19/09/2025 | G40: USD | H40: 46023 | I40: 1 | J40: 28/01/2026 | K40: 230 | L40: IN89
A41: 256779416869 | B41: 45889 | C41: 2.32 | D41: 200.98 | E41: C: ASCENDAS27 P: A023951 I 256779416869 | F41: 19/09/2025 | G41: USD | H41: 46023 | I41: 1 | J41: 28/01/2026 | K41: 230 | L41: IN89
A42: 246779414663 | B42: 45736 | C42: 0.9 | D42: 78.34 | E42: C: ASCENDAS27 P: A023951 I 246779414663 | F42: 19/04/2025 | G42: USD | H42: 45809 | I42: 1 | J42: 45997 | K42: 230 | L42: IN89
A43: 246779414662 | B43: 45736 | C43: 5.5 | D43: 478.73 | E43: C: ASCENDAS27 P: A023951 I 246779414662 | F43: 19/04/2025 | G43: USD | H43: 45809 | I43: 1 | J43: 45997 | K43: 230 | L43: IN89
A44: 246779414385 | B44: 45736 | C44: 4.8 | D44: 417.8 | E44: C: ASCENDAS27 P: A023951 I 246779414385 | F44: 19/04/2025 | G44: USD | H44: 45809 | I44: 1 | J44: 45997 | K44: 230 | L44: IN89
A45: 246779413730 | B45: 45736 | C45: 0.06 | D45: 5.22 | E45: C: ASCENDAS27 P: A023951 I 246779413730 | F45: 19/04/2025 | G45: USD | H45: 45809 | I45: 1 | J45: 45997 | K45: 230 | L45: IN89
A46: 246779413815 | B46: 45736 | C46: 1 | D46: 87.04 | E46: C: ASCENDAS27 P: A023951 I 246779413815 | F46: 19/04/2025 | G46: USD | H46: 45809 | I46: 1 | J46: 30/06/2025 | K46: 230 | L46: IN89
A47: 246779413936 | B47: 45736 | C47: 0.55 | D47: 47.87 | E47: C: ASCENDAS27 P: A023951 I 246779413936 | F47: 19/04/2025 | G47: USD | H47: 45809 | I47: 1 | J47: 30/06/2025 | K47: 230 | L47: IN89
A48: 246779414384 | B48: 45736 | C48: 3.65 | D48: 317.7 | E48: C: ASCENDAS27 P: A023951 I 246779414384 | F48: 19/04/2025 | G48: USD | H48: 45809 | I48: 1 | J48: 30/06/2025 | K48: 230 | L48: IN89
A49: 246779413889 | B49: 45736 | C49: 0.85 | D49: 73.99 | E49: C: ASCENDAS27 P: A023951 I 246779413889 | F49: 19/04/2025 | G49: USD | H49: 45809 | I49: 1 | J49: 30/06/2025 | K49: 230 | L49: IN89
A50: 246779413920 | B50: 45736 | C50: 0.45 | D50: 39.17 | E50: C: ASCENDAS27 P: A023951 I 246779413920 | F50: 19/04/2025 | G50: USD | H50: 45809 | I50: 1 | J50: 30/06/2025 | K50: 230 | L50: IN89
A51: 246779413941 | B51: 45736 | C51: 0.6 | D51: 52.23 | E51: C: ASCENDAS27 P: A023951 I 246779413941 | F51: 19/04/2025 | G51: USD | H51: 45809 | I51: 1 | J51: 30/06/2025 | K51: 230 | L51: IN89
A52: 246779413747 | B52: 45736 | C52: 0.05 | D52: 4.35 | E52: C: ASCENDAS27 P: A023951 I 246779413747 | F52: 19/04/2025 | G52: USD | H52: 45901 | I52: 1 | J52: 30/09/2025 | K52: 230 | L52: IN89
A53: 246779410132 | B53: 45708 | C53: 1.05 | D53: 90.87 | E53: C: ASCENDAS27 P: A023951 I 246779410132 | F53: 22/03/2025 | G53: USD | H53: 45809 | I53: 1 | J53: 45997 | K53: 230 | L53: IN89
A54: 246779410098 | B54: 45708 | C54: 47.62 | D54: 4121.01 | E54: C: ASCENDAS27 P: A023951 I 246779410098 | F54: 22/03/2025 | G54: USD | H54: 45809 | I54: 1 | J54: 45997 | K54: 230 | L54: IN89
A55: 246779410131 | B55: 45708 | C55: 1.9 | D55: 164.43 | E55: C: ASCENDAS27 P: A023951 I 246779410131 | F55: 22/03/2025 | G55: USD | H55: 45809 | I55: 1 | J55: 45997 | K55: 230 | L55: IN89
A56: 246779410315 | B56: 45708 | C56: 47.62 | D56: 4144.96 | E56: C: ASCENDAS27 P: A023951 I 246779410315 | F56: 22/03/2025 | G56: USD | H56: 45809 | I56: 1 | J56: 45997 | K56: 230 | L56: IN89
A57: 246779410312 | B57: 45708 | C57: 1.05 | D57: 91.39 | E57: C: ASCENDAS27 P: A023951 I 246779410312 | F57: 22/03/2025 | G57: USD | H57: 45809 | I57: 1 | J57: 45997 | K57: 230 | L57: IN89
A58: 246779410218 | B58: 45708 | C58: 1.03 | D58: 89.14 | E58: C: ASCENDAS27 P: A023951 I 246779410218 | F58: 22/03/2025 | G58: USD | H58: 45809 | I58: 1 | J58: 45997 | K58: 230 | L58: IN89
A59: 246779410175 | B59: 45708 | C59: 1.05 | D59: 90.87 | E59: C: ASCENDAS27 P: A023951 I 246779410175 | F59: 22/03/2025 | G59: USD | H59: 45809 | I59: 1 | J59: 45997 | K59: 230 | L59: IN89
A60: 246779410141 | B60: 45708 | C60: 47.62 | D60: 4121.01 | E60: C: ASCENDAS27 P: A023951 I 246779410141 | F60: 22/03/2025 | G60: USD | H60: 45809 | I60: 1 | J60: 45997 | K60: 230 | L60: IN89
A61: 246779410184 | B61: 45708 | C61: 46.66 | D61: 4037.94 | E61: C: ASCENDAS27 P: A023951 I 246779410184 | F61: 22/03/2025 | G61: USD | H61: 45809 | I61: 1 | J61: 45997 | K61: 230 | L61: IN89
A62: 246779410217 | B62: 45708 | C62: 1.87 | D62: 161.83 | E62: C: ASCENDAS27 P: A023951 I 246779410217 | F62: 22/03/2025 | G62: USD | H62: 45809 | I62: 1 | J62: 45997 | K62: 230 | L62: IN89
A63: 246779410174 | B63: 45708 | C63: 1.9 | D63: 164.43 | E63: C: ASCENDAS27 P: A023951 I 246779410174 | F63: 22/03/2025 | G63: USD | H63: 45809 | I63: 1 | J63: 45997 | K63: 230 | L63: IN89
A64: 246779410227 | B64: 45708 | C64: 45.72 | D64: 3956.59 | E64: C: ASCENDAS27 P: A023951 I 246779410227 | F64: 22/03/2025 | G64: USD | H64: 45809 | I64: 1 | J64: 26/06/2025 | K64: 230 | L64: IN89
A65: 246779410064 | B65: 45708 | C65: 1.05 | D65: 90.87 | E65: C: ASCENDAS27 P: A023951 I 246779410064 | F65: 22/03/2025 | G65: USD | H65: 45809 | I65: 1 | J65: 30/06/2025 | K65: 230 | L65: IN89
A66: 246779410030 | B66: 45708 | C66: 47.62 | D66: 4121.01 | E66: C: ASCENDAS27 P: A023951 I 246779410030 | F66: 22/03/2025 | G66: USD | H66: 45809 | I66: 1 | J66: 30/06/2025 | K66: 230 | L66: IN89
A67: 246779410063 | B67: 45708 | C67: 1.9 | D67: 164.43 | E67: C: ASCENDAS27 P: A023951 I 246779410063 | F67: 22/03/2025 | G67: USD | H67: 45809 | I67: 1 | J67: 30/06/2025 | K67: 230 | L67: IN89
A68: 246779410260 | B68: 45708 | C68: 1.83 | D68: 158.37 | E68: C: ASCENDAS27 P: A023951 I 246779410260 | F68: 22/03/2025 | G68: USD | H68: 45809 | I68: 1 | J68: 30/06/2025 | K68: 230 | L68: IN89
A69: 246779410010 | B69: 45708 | C69: 47.62 | D69: 4121.01 | E69: C: ASCENDAS27 P: A023951 I 246779410010 | F69: 22/03/2025 | G69: USD | H69: 45809 | I69: 1 | J69: 30/06/2025 | K69: 230 | L69: IN89
A70: 246779410080 | B70: 45708 | C70: 1.9 | D70: 164.43 | E70: C: ASCENDAS27 P: A023951 I 246779410080 | F70: 22/03/2025 | G70: USD | H70: 45809 | I70: 1 | J70: 30/06/2025 | K70: 230 | L70: IN89
A71: 246779410261 | B71: 45708 | C71: 1.01 | D71: 87.4 | E71: C: ASCENDAS27 P: A023951 I 246779410261 | F71: 22/03/2025 | G71: USD | H71: 45809 | I71: 1 | J71: 30/06/2025 | K71: 230 | L71: IN89
A72: 246779410311 | B72: 45708 | C72: 1.9 | D72: 164.43 | E72: C: ASCENDAS27 P: A023951 I 246779410311 | F72: 22/03/2025 | G72: USD | H72: 45901 | I72: 1 | J72: 30/09/2025 | K72: 230 | L72: IN89
A73: 256779415769 | B73: 45857 | C73: 4.7 | D73: 404.15 | E73: C: ASCENDAS27 P: A023951 I 256779415769 | F73: 18/08/2025 | G73: USD | H73: 46023 | I73: 1 | J73: 23/01/2026 | K73: 230 | L73: IN89
A74: 256779414741 | B74: 45827 | C74: 11.6 | D74: 986.74 | E74: C: ASCENDAS27 P: A023951 I 256779414741 | F74: 19/07/2025 | G74: USD | H74: 45992 | I74: 1 | J74: 31/12/2025 | K74: 230 | L74: IN89
A75: 246779413202 | B75: 45735 | C75: 0.78 | D75: 67.5 | E75: C: ASCENDAS27 P: A023951 I 246779413202 | F75: 18/04/2025 | G75: USD | H75: 45809 | I75: 1 | J75: 45997 | K75: 230 | L75: IN89
A76: 246779413024 | B76: 45735 | C76: 1.01 | D76: 87.91 | E76: C: ASCENDAS27 P: A023951 I 246779413024 | F76: 18/04/2025 | G76: USD | H76: 45809 | I76: 1 | J76: 30/06/2025 | K76: 230 | L76: IN89
A77: 246779412994 | B77: 45735 | C77: 45.95 | D77: 3999.6 | E77: C: ASCENDAS27 P: A023951 I 246779412994 | F77: 18/04/2025 | G77: USD | H77: 45809 | I77: 1 | J77: 30/06/2025 | K77: 230 | L77: IN89
A78: 246779413023 | B78: 45735 | C78: 1.84 | D78: 160.16 | E78: C: ASCENDAS27 P: A023951 I 246779413023 | F78: 18/04/2025 | G78: USD | H78: 45809 | I78: 1 | J78: 30/06/2025 | K78: 230 | L78: IN89
A79: 246779410081 | B79: 45707 | C79: 1.05 | D79: 90.87 | E79: C: ASCENDAS27 P: A023951 I 246779410081 | F79: 21/03/2025 | G79: USD | H79: 45809 | I79: 1 | J79: 30/06/2025 | K79: 230 | L79: IN89
A80: 256779418433 | B80: 45948 | C80: 7.03 | D80: 623.28 | E80: C: ASCENDAS27 P: A023951 I 256779418433 | F80: 17/11/2025 | G80: USD | H80: 45992 | I80: 1 | J80: 15/12/2025 | K80: 230 | L80: IN89
A81: 256779418424 | B81: 45948 | C81: 26.69 | D81: 2366.32 | E81: C: ASCENDAS27 P: A023951 I 256779418424 | F81: 17/11/2025 | G81: USD | H81: 45992 | I81: 1 | J81: 15/12/2025 | K81: 230 | L81: IN89
A82: 256779417597 | B82: 45918 | C82: 21.1 | D82: 1849.46 | E82: C: ASCENDAS27 P: A023951 I 256779417597 | F82: 18/10/2025 | G82: USD | H82: 45931 | I82: 1 | J82: 29/10/2025 | K82: 230 | L82: IN89
A83: 256779417580 | B83: 45918 | C83: 3.69 | D83: 3.69 | E83: C: ASCENDAS27 P: A023951 I 256779417580 | F83: 18/10/2025 | G83: USD | H83: 45962 | I83: 1 | J83: 45972 | K83: 230 | L83: IN89
A84: 256779417517 | B84: 45918 | C84: 0.09 | D84: 7.89 | E84: C: ASCENDAS27 P: A023951 I 256779417517 | F84: 18/10/2025 | G84: USD | H84: 45962 | I84: 1 | J84: 45972 | K84: 230 | L84: IN89
A85: 256779417557 | B85: 45918 | C85: 14.52 | D85: 1272.71 | E85: C: ASCENDAS27 P: A023951 I 256779417557 | F85: 18/10/2025 | G85: USD | H85: 45962 | I85: 1 | J85: 45972 | K85: 230 | L85: IN89
A86: 256779417580_D | B86: 45918 | C86: 3.69 | D86: 323.44 | E86: C: ASCENDAS27 P: A023951 I 256779417580_D | F86: 18/10/2025 | G86: USD | H86: 46023 | I86: 1 | J86: 31/01/2026 | K86: 230 | L86: IN89
A87: 256779415474 | B87: 45856 | C87: 12.17 | D87: 1046.49 | E87: C: ASCENDAS27 P: A023951 I 256779415474 | F87: 17/08/2025 | G87: USD | H87: 45931 | I87: 1 | J87: 29/10/2025 | K87: 230 | L87: IN89
A88: 256779415442 | B88: 45856 | C88: 0.03 | D88: 2.58 | E88: C: ASCENDAS27 P: A023951 I 256779415442 | F88: 17/08/2025 | G88: USD | H88: 45931 | I88: 1 | J88: 29/10/2025 | K88: 230 | L88: IN89
A89: 256779415453 | B89: 45856 | C89: 5.87 | D89: 504.76 | E89: C: ASCENDAS27 P: A023951 I 256779415453 | F89: 17/08/2025 | G89: USD | H89: 45931 | I89: 1 | J89: 29/10/2025 | K89: 230 | L89: IN89
A90: 256779415517 | B90: 45856 | C90: 2.33 | D90: 200.36 | E90: C: ASCENDAS27 P: A023951 I 256779415517 | F90: 17/08/2025 | G90: USD | H90: 45931 | I90: 1 | J90: 29/10/2025 | K90: 230 | L90: IN89
A91: 256779415426 | B91: 45856 | C91: 9.29 | D91: 798.84 | E91: C: ASCENDAS27 P: A023951 I 256779415426 | F91: 17/08/2025 | G91: USD | H91: 45931 | I91: 1 | J91: 29/10/2025 | K91: 230 | L91: IN89
A92: 256779414431 | B92: 45826 | C92: 1.05 | D92: 89.32 | E92: C: ASCENDAS27 P: A023951 I 256779414431 | F92: 18/07/2025 | G92: USD | H92: 45962 | I92: 1 | J92: 30/11/2025 | K92: 230 | L92: IN89
A93: 246779411742 | B93: 45733 | C93: 0.47 | D93: 40.91 | E93: C: ASCENDAS27 P: A023951 I 246779411742 | F93: 16/04/2025 | G93: USD | H93: 45809 | I93: 1 | J93: 45967 | K93: 230 | L93: IN89
A94: 246779411601 | B94: 45733 | C94: 0.47 | D94: 40.91 | E94: C: ASCENDAS27 P: A023951 I 246779411601 | F94: 16/04/2025 | G94: USD | H94: 45809 | I94: 1 | J94: 45997 | K94: 230 | L94: IN89
A95: 246779411717 | B95: 45733 | C95: 0.91 | D95: 79.21 | E95: C: ASCENDAS27 P: A023951 I 246779411717 | F95: 16/04/2025 | G95: USD | H95: 45809 | I95: 1 | J95: 45997 | K95: 230 | L95: IN89
A96: 246779411913 | B96: 45733 | C96: 0.57 | D96: 49.61 | E96: C: ASCENDAS27 P: A023951 I 246779411913 | F96: 16/04/2025 | G96: USD | H96: 45809 | I96: 1 | J96: 45997 | K96: 230 | L96: IN89
A97: 246779411740 | B97: 45733 | C97: 0.46 | D97: 40.04 | E97: C: ASCENDAS27 P: A023951 I 246779411740 | F97: 16/04/2025 | G97: USD | H97: 45809 | I97: 1 | J97: 45997 | K97: 230 | L97: IN89
A98: 246779412111 | B98: 45733 | C98: 8.41 | D98: 732.03 | E98: C: ASCENDAS27 P: A023951 I 246779412111 | F98: 16/04/2025 | G98: USD | H98: 45809 | I98: 1 | J98: 45997 | K98: 230 | L98: IN89
A99: 246779411722 | B99: 45733 | C99: 0.8 | D99: 69.63 | E99: C: ASCENDAS27 P: A023951 I 246779411722 | F99: 16/04/2025 | G99: USD | H99: 45809 | I99: 1 | J99: 45997 | K99: 230 | L99: IN89
A100: 246779412041 | B100: 45733 | C100: 0.67 | D100: 58.32 | E100: C: ASCENDAS27 P: A023951 I 246779412041 | F100: 16/04/2025 | G100: USD | H100: 45809 | I100: 1 | J100: 45997 | K100: 230 | L100: IN89
A101: 246779411898 | B101: 45733 | C101: 0.14 | D101: 12.19 | E101: C: ASCENDAS27 P: A023951 I 246779411898 | F101: 16/04/2025 | G101: USD | H101: 45809 | I101: 1 | J101: 45997 | K101: 230 | L101: IN89
A102: 246779411729 | B102: 45733 | C102: 0.69 | D102: 60.06 | E102: C: ASCENDAS27 P: A023951 I 246779411729 | F102: 16/04/2025 | G102: USD | H102: 45809 | I102: 1 | J102: 45997 | K102: 230 | L102: IN89
A103: 246779411737 | B103: 45733 | C103: 0.57 | D103: 49.61 | E103: C: ASCENDAS27 P: A023951 I 246779411737 | F103: 16/04/2025 | G103: USD | H103: 45809 | I103: 1 | J103: 45997 | K103: 230 | L103: IN89
A104: 246779411595 | B104: 45733 | C104: 1.03 | D104: 89.65 | E104: C: ASCENDAS27 P: A023951 I 246779411595 | F104: 16/04/2025 | G104: USD | H104: 45809 | I104: 1 | J104: 45997 | K104: 230 | L104: IN89
... A167: 246779412035 | B167: 45733 | C167: 1.46 | D167: 127.08 | E167: C: ASCENDAS27 P: A023951 I 246779412035 | F167: 16/04/2025 | G167: USD | H167: 45809 | I167: 1 | J167: 45997 | K167: 230 | L167: IN89
...

Sheet Customer P matching
B2: Item# | C2: Item Date | D2: FC Amount | E2: LC Amount | F2: Particular | G2: Due Date | H2: CCY | I2: VC Period | J2: VC Seq | K2: VC Date | L2: Tx. Type | M2: Company Code
B3: 256779413908 | C3: 45805 | D3: 0 | E3: -11858.12 | F3: C: ASCENDAS27 P: Matching | G3: 27/06/2025 | H3: USD | I3: 45962 | J3: 66 | K3: 30/11/2025 | L3: 271 | M3: IN89
B4: 256779415989 | C4: 45863 | D4: 0 | E4: -664.99 | F4: C: ASCENDAS27 P: Matching | G4: 24/08/2025 | H4: USD | I4: 45931 | J4: 82 | K4: 31/10/2025 | L4: 271 | M4: IN89
B5: 256779416007 | C5: 45863 | D5: 0 | E5: -934.03 | F5: C: ASCENDAS27 P: Matching | G5: 24/08/2025 | H5: USD | I5: 45931 | J5: 84 | K5: 31/10/2025 | L5: 271 | M5: IN89
B6: 256779412776 | C6: 45771 | D6: 0 | E6: -2124.59 | F6: C: ASCENDAS27 P: Matching | G6: 24/05/2025 | H6: USD | I6: 45962 | J6: 58 | K6: 30/11/2025 | L6: 271 | M6: IN89
B7: 256779417801 | C7: 45922 | D7: 0 | E7: -2799.24 | F7: C: ASCENDAS27 P: Matching | G7: 22/10/2025 | H7: USD | I7: 45931 | J7: 64 | K7: 31/10/2025 | L7: 271 | M7: IN89
B8: 256779412524 | C8: 45769 | D8: 0 | E8: -9.39 | F8: C: ASCENDAS27 P: Matching | G8: 22/05/2025 | H8: USD | I8: 45809 | J8: 14 | K8: 30/06/2025 | L8: 271 | M8: IN89
B9: 256779412529 | C9: 45769 | D9: 0 | E9: -7.61 | F9: C: ASCENDAS27 P: Matching | G9: 22/05/2025 | H9: USD | I9: 45809 | J9: 16 | K9: 30/06/2025 | L9: 271 | M9: IN89
B10: 256779412536 | C10: 45769 | D10: 0 | E10: -9.53 | F10: C: ASCENDAS27 P: Matching | G10: 22/05/2025 | H10: USD | I10: 45809 | J10: 18 | K10: 30/06/2025 | L10: 271 | M10: IN89
B11: 256779412537 | C11: 45769 | D11: 0 | E11: -104.86 | F11: C: ASCENDAS27 P: Matching | G11: 22/05/2025 | H11: USD | I11: 45809 | J11: 20 | K11: 30/06/2025 | L11: 271 | M11: IN89
B12: 256779412579 | C12: 45769 | D12: 0 | E12: -14.83 | F12: C: ASCENDAS27 P: Matching | G12: 22/05/2025 | H12: USD | I12: 45809 | J12: 22 | K12: 30/06/2025 | L12: 271 | M12: IN89
B13: 256779412586 | C13: 45769 | D13: 0 | E13: -13.25 | F13: C: ASCENDAS27 P: Matching | G13: 22/05/2025 | H13: USD | I13: 45809 | J13: 24 | K13: 30/06/2025 | L13: 271 | M13: IN89
B14: 256779412563 | C14: 45769 | D14: 0 | E14: -6.94 | F14: C: ASCENDAS27 P: Matching | G14: 22/05/2025 | H14: USD | I14: 45809 | J14: 48 | K14: 30/06/2025 | L14: 271 | M14: IN89
... B57: 256779417597 | C57: 45918 | D57: 0 | E57: -621.04 | F57: C: ASCENDAS27 P: Matching | G57: 18/10/2025 | H57: USD | I57: 45931 | J57: 68 | K57: 31/10/2025 | L57: 271 | M57: IN89
B58: 256779417580_D | C58: 45918 | D58: 0 | E58: -718.94 | F58: C: ASCENDAS27 P: Matching | G58: 18/10/2025 | H58: USD | I58: 46023 | J58: 104 | K58: 31/01/2026 | L58: 271 | M58: IN89
B59: 256779415442 | C59: 45856 | D59: 0 | E59: -3.53 | F59: C: ASCENDAS27 P: Matching | G59: 17/08/2025 | H59: USD | I59: 45931 | J59: 66 | K59: 31/10/2025 | L59: 271 | M59: IN89
B60: 256779415426 | C60: 45856 | D60: 0 | E60: -1030.68 | F60: C: ASCENDAS27 P: Matching | G60: 17/08/2025 | H60: USD | I60: 45931 | J60: 70 | K60: 31/10/2025 | L60: 271 | M60: IN89
B61: 256779415517 | C61: 45856 | D61: 0 | E61: -258.92 | F61: C: ASCENDAS27 P: Matching | G61: 17/08/2025 | H61: USD | I61: 45931 | J61: 72 | K61: 31/10/2025 | L61: 271 | M61: IN89
B62: 256779415453 | C62: 45856 | D62: 0 | E62: -650.84 | F62: C: ASCENDAS27 P: Matching | G62: 17/08/2025 | H62: USD | I62: 45931 | J62: 74 | K62: 31/10/2025 | L62: 271 | M62: IN89
B63: 256779415474 | C63: 45856 | D63: 0 | E63: -1349.32 | F63: C: ASCENDAS27 P: Matching | G63: 17/08/2025 | H63: USD | I63: 45931 | J63: 76 | K63: 31/10/2025 | L63: 271 | M63: IN89
B64: 256779414431 | C64: 45826 | D64: 0 | E64: -209.97 | F64: C: ASCENDAS27 P: Matching | G64: 18/07/2025 | H64: USD | I64: 45962 | J64: 60 | K64: 30/11/2025 | L64: 271 | M64: IN89
B65: 246779411973 | C65: 45733 | D65: 0 | E65: 439.66 | F65: C: ASCENDAS27 P: Matching | G65: 16/04/2025 | H65: USD | I65: 45809 | J65: 4 | K65: 30/06/2025 | L65: 271 | M65: IN89
B66: 246779412033 | C66: 45733 | D66: 0 | E66: 23.13 | F66: C: ASCENDAS27 P: Matching | G66: 16/04/2025 | H66: USD | I66: 45809 | J66: 6 | K66: 30/06/2025 | L66: 271 | M66: IN89
B67: 246779412047 | C67: 45733 | D67: 0 | E67: 28.93 | F67: C: ASCENDAS27 P: Matching | G67: 16/04/2025 | H67: USD | I67: 45809 | J67: 86 | K67: 30/06/2025 | L67: 271 | M67: IN89
B68: 246779411908 | C68: 45733 | D68: 0 | E68: 29.32 | F68: C: ASCENDAS27 P: Matching | G68: 16/04/2025 | H68: USD | I68: 45809 | J68: 94 | K68: 30/06/2025 | L68: 271 | M68: IN89
B69: 246779411730 | C69: 45733 | D69: 0 | E69: -23.64 | F69: C: ASCENDAS27 P: Matching | G69: 16/04/2025 | H69: USD | I69: 45962 | J69: 52 | K69: 30/11/2025 | L69: 271 | M69: IN89
B70: 246779411789 | C70: 45733 | D70: 0 | E70: -886.24 | F70: C: ASCENDAS27 P: Matching | G70: 16/04/2025 | H70: USD | I70: 45962 | J70: 54 | K70: 30/11/2025 | L70: 271 | M70: IN89
... B92: 256779411463 | C92: 45762 | D92: 0 | E92: -40.25 | F92: C: ASCENDAS27 P: Matching | G92: 15/05/2025 | H92: USD | I92: 46023 | J92: 50 | K92: 31/01/2026 | L92: 271 | M92: IN89
B93: 256779415389 | C93: 45937 | D93: 0 | E93: -31.68 | F93: C: ASCENDAS27 P: Matching | G93: 45908 | H93: USD | I93: 45901 | J93: 6 | K93: 30/09/2025 | L93: 271 | M93: IN89
B94: 256779415346 | C94: 45937 | D94: 0 | E94: -3.24 | F94: C: ASCENDAS27 P: Matching | G94: 45908 | H94: USD | I94: 45901 | J94: 8 | K94: 30/09/2025 | L94: 271 | M94: IN89
B95: 256779415350 | C95: 45937 | D95: 0 | E95: -4.17 | F95: C: ASCENDAS27 P: Matching | G95: 45908 | H95: USD | I95: 45901 | J95: 10 | K95: 30/09/2025 | L95: 271 | M95: IN89
B96: 256779415316 | C96: 45937 | D96: 0 | E96: -11.14 | F96: C: ASCENDAS27 P: Matching | G96: 45908 | H96: USD | I96: 45901 | J96: 12 | K96: 30/09/2025 | L96: 271 | M96: IN89
B97: 256779415355 | C97: 45937 | D97: 0 | E97: -3.97 | F97: C: ASCENDAS27 P: Matching | G97: 45908 | H97: USD | I97: 45901 | J97: 14 | K97: 30/09/2025 | L97: 271 | M97: IN89
B98: 256779415303 | C98: 45937 | D98: 0 | E98: -18.57 | F98: C: ASCENDAS27 P: Matching | G98: 45908 | H98: USD | I98: 45901 | J98: 18 | K98: 30/09/2025 | L98: 271 | M98: IN89
B99: 256779415333 | C99: 45937 | D99: 0 | E99: -4.17 | F99: C: ASCENDAS27 P: Matching | G99: 45908 | H99: USD | I99: 45901 | J99: 20 | K99: 30/09/2025 | L99: 271 | M99: IN89
B100: 256779415304 | C100: 45937 | D100: 0 | E100: -5.57 | F100: C: ASCENDAS27 P: Matching | G100: 45908 | H100: USD | I100: 45901 | J100: 22 | K100: 30/09/2025 | L100: 271 | M100: IN89
B101: 256779415377 | C101: 45937 | D101: 0 | E101: -9.29 | F101: C: ASCENDAS27 P: Matching | G101: 45908 | H101: USD | I101: 45901 | J101: 24 | K101: 30/09/2025 | L101: 271 | M101: IN89
B102: 256779415298 | C102: 45937 | D102: 0 | E102: -4.46 | F102: C: ASCENDAS27 P: Matching | G102: 45908 | H102: USD | I102: 45901 | J102: 28 | K102: 30/09/2025 | L102: 271 | M102: IN89
B103: 256779415380 | C103: 45937 | D103: 0 | E103: -37.14 | F103: C: ASCENDAS27 P: Matching | G103: 45908 | H103: USD | I103: 45901 | J103: 30 | K103: 30/09/2025 | L103: 271 | M103: IN89
B104: 256779415341 | C104: 45937 | D104: 0 | E104: -2.78 | F104: C: ASCENDAS27 P: Matching | G104: 45908 | H104: USD | I104: 45901 | J104: 32 | K104: 30/09/2025 | L104: 271 | M104: IN89
... B316: 256779413931 | C316: 45694 | D316: 0 | E316: -1584.45 | F316: C: ASCENDAS27 P: Matching | G316: 45695 | H316: USD | I316: 45962 | J316: 62 | K316: 30/11/2025 | L316: 271 | M316: IN89
B317: 256779416028 | C317: 45665 | D317: 0 | E317: -7426.8 | F317: C: ASCENDAS27 P: Matching | G317: 31/08/2025 | H317: USD | I317: 45992 | J317: 54 | K317: 31/12/2025 | L317: 271 | M317: IN89
B318: 256779416029 | C318: 45665 | D318: 0 | E318: -297.06 | F318: C: ASCENDAS27 P: Matching | G318: 31/08/2025 | H318: USD | I318: 45992 | J318: 56 | K318: 31/12/2025 | L318: 271 | M318: IN89
B319: 256779416030 | C319: 45665 | D319: 0 | E319: -163.38 | F319: C: ASCENDAS27 P: Matching | G319: 31/08/2025 | H319: USD | I319: 45992 | J319: 58 | K319: 31/12/2025 | L319: 271 | M319: IN89

Sheet Pivot
A3: Sum of Company Code Currency Value | D3: Document Type
A4: Years | B4: Quarters | C4: Document Date | D4: DA | E4: DG | F4: DR | G4: DY | H4: DZ | I4: XC
A5: 2025 | B5: Qtr1 | C5: Feb | F5: 1514515.3 | I5: 0
C6: Mar | F6: 1933380.6
B7: Qtr2 | C7: Apr | D7: 0 | F7: 2087965.7
C8: May | E8: -595574.41 | F8: 1044919.9
C9: Jun | F9: 1761603.8
B10: Qtr3 | C10: Jul | E10: -1464659.3 | F10: 2492881.5 | H10: 0
C11: Aug | E11: -170239.97 | F11: 1305423
C12: Sep | F12: 1564779.1 | G12: 1238.22
B13: Qtr4 | C13: Oct | E13: -8361.37 | F13: 1113806.7 | H13: -5850755.1
C14: Nov | E14: -405590.02 | F14: 1574052.7 | H14: -1920293.1
C15: Dec | F15: 282835.01
A16: 2026 | B16: Qtr1 | C16: Jan | E16: -52265.33 | F16: 831546.81 | H16: -719881.09

Sheet 26AS Reco
