Workbook

Sheet Summary
A1: Reconciliation of Ledger as on 31st January 2026
A2: Particulars | B2: Amount
A3: Balance as per Shah TC Exim LLP | B3: =-'Customer Data'!L279 -> 13295.313
A4: Add: TDS recorded by customer but not in our books | B4: ='TDS Deducted'!O1-'Payment Reco Updated'!M19 -> 4115.9928 | C4: >> to be knocked against Payment
A5: Add: Invoices / CN not recorded in customer books | B5: ='Invoice not in Customer books'!I1 -> 7523.3641 | C5: >> to be confirmed by customer
A6: Add: Bank Charges and Foreign Exchange gain/loss | B6: =-('Payment Reco Updated'!L19+'Payment Reco Updated'!N19) -> 226.32 | C6: >> to be confirmed by CL team
A7: Less: Invoices under recorded in Ascendus books | B7: ='Difference in Invoice Amount'!M4 -> -96.0148 | C7: >> to be confirmed by CL team
A8: Less: Invoices in Customers books and not in Ascendus books | B8: =-'Customer Data Vlookup'!S11 -> -131.5718 | C8: >> to be confirmed by CL team
A9: Derived balance | B9: =SUM(B3:B8) -> 24933.403
A10: Balance as per Ascendus | B10: ='Ascendus Data'!G1 -> 25229.422
A12: Difference | B12: =B9-B10-B11 -> -296.0188

Sheet Payment Reco Updated
A1: Document Date | B1: Remarks | C1: Ref No | D1: Debit (FC) | E1: Payment Date | F1: Currency | G1: Recd Amount | H1: UTR Details | I1: Clearing Document | J1: Document Header Text | K1: Document Currency Value | L1: Bank Charges | M1: TDS | N1: Foreign Exchange Gain/Loss | O1: Remark
A2: 45876 | B2: Outgoing Payments - VD0304,Being payment done against USD 1007 | C2: 003MISC252190104 | D2: 1007.818 | E2: 45877 | F2: USD | G2: 986.32 | H2: 8681446219FS | I2: 1400000864 | J2: 8681446219FS | K2: -1102.02 | L2: =D2-G2 -> 21.498 | M2: 94.2 | N2: =-(K2+G2+M2) -> 21.5
A3: 45959 | B3: Outgoing Payments - VD0304,Being payment done against USD 1752 | C3: 003MISC253020092 | D3: 1752.7656 | E3: 45960 | F3: USD | G3: 1731.27 | H3: 2169049302JS | I3: Not Yet Cleared | J3: T54SWIC278972 | K3: -1731.27 | L3: =D3-G3 -> 21.4956 | M3: =K3+G3 -> 0 | N3: =-(K3+G3+M3) -> 0 | O3: To Be Cleared
A4: 45961 | B4: Outgoing Payments - VD0304,Being $1989 | C4: 003MISC253040153 | D4: 1989.9404 | E4: 45964 | F4: USD | G4: 1968.44 | H4: 2225660304JS | I4: Not Yet Cleared | J4: T54SWIC279192 | K4: -1968.44 | L4: =D4-G4 -> 21.5004 | M4: =K4+G4 -> 0 | N4: =-(K4+G4+M4) -> 0 | O4: To Be Cleared
A5: 46022 | B5: Outgoing Payments - VD0304,Being $2328 | C5: 003MISC253650039 | D5: 2368.203 | E5: 46024 | F5: USD | G5: 2346.7 | H5: T54SWIC285279 | I5: 1400002372 | J5: T54SWIC285279 | K5: -2517.26 | L5: =D5-G5 -> 21.503 | M5: 184.34 | N5: =-(K5+G5+M5) -> -13.78
A6: 45910 | B6: Outgoing Payments - VD0304,Being payment done against USD 2954 | C6: 003MISC252530130 | D6: 2954.3362 | E6: 45911 | F6: USD | G6: 2932.84 | H6: 4568362253FS | I6: Not Yet Cleared | J6: 4568362253FS | K6: -2932.84 | L6: =D6-G6 -> 21.4962 | M6: =K6+G6 -> 0 | N6: =-(K6+G6+M6) -> 0 | O6: To Be Cleared
A7: 45813 | B7: Outgoing Payments - VD0304,Being Amount paid to ascendas against bank ref | C7: 003MISC251560102 | D7: 3167.4752 | E7: 45814 | F7: USD | G7: 3145.98 | H7: 8113643156FS | I7: Not Yet Cleared | J7: 8113643156FS | K7: -3145.98 | L7: =D7-G7 -> 21.4952 | M7: =K7+G7 -> 0 | N7: =-(K7+G7+M7) -> 0 | O7: To Be Cleared
A8: 45813 | B8: Outgoing Payments - VD0304, Being Amount paid to ascendas against bank ref | C8: 003MISC251560088 | D8: 3529.5558 | E8: 45814 | F8: USD | G8: 3508.06 | H8: 9422978156FS | I8: Not Yet Cleared | J8: 9422978156FS | K8: -3508.06 | L8: =D8-G8 -> 21.4958 | M8: =K8+G8 -> 0 | N8: =-(K8+G8+M8) -> 0 | O8: To Be Cleared
A9: 45813 | B9: Outgoing Payments - VD0304,Being Amount paid to ascendas against bank ref | C9: 003MISC251560090 | D9: 3685.2032 | E9: 45814 | F9: USD | G9: 3663.7 | H9: 1810304156FS | I9: Not Yet Cleared | J9: T54SWIC264904 | K9: -3663.7 | L9: =D9-G9 -> 21.5032 | M9: =K9+G9 -> 0 | N9: =-(K9+G9+M9) -> 0 | O9: To Be Cleared
A10: 45856 | B10: Outgoing Payments - VD0304,Being payment done against USD 3798 | C10: 003MISC251990131 | D10: 3742.0478 | E10: 45859 | F10: USD | G10: 3777.49 | H10: 1984476199FS | I10: Not Yet Cleared | J10: T54SWIC268990 | K10: -3777.49 | L10: =D10-G10 -> -35.4422 | M10: =K10+G10 -> 0 | N10: =-(K10+G10+M10) -> 0 | O10: To Be Cleared
A11: 45821 | B11: Outgoing Payments - VD0304,Being Amount paid to ascendas against bank ref | C11: 003FT01251640038 | D11: 4224.8172 | E11: 45824 | F11: USD | G11: 4228.22 | H11: 4989824164FS | I11: Not Yet Cleared | J11: 4989824164FS | K11: -4228.22 | L11: =D11+D12-G11 -> -0.002 | M11: =K11+G11 -> 0 | N11: =-(K11+G11+M11) -> 0 | O11: To Be Cleared
A12: 45821 | B12: Being $3.4008 less paid in this bill because in summary sheet 2% tds deduscted instead of 10% | C12: HDFC Bank - INR | D12: 3.4008 | L12: 0 | N12: =-(K12+G12+M12) -> 0
A13: 45910 | B13: Outgoing Payments - VD0304,Being payment done against USD 4740 | C13: 003MISC252530128 | D13: 4740.77 | E13: 45911 | F13: USD | G13: 4719.25 | H13: 0758767253FS | I13: Not Yet Cleared | J13: 0758767253FS | K13: -4719.25 | L13: =D13-G13 -> 21.52 | M13: =K13+G13 -> 0 | N13: =-(K13+G13+M13) -> 0 | O13: To Be Cleared
A14: 45877 | B14: Outgoing Payments - VD0304,Being payment done against USD 4800 | C14: 003MISC252200121 | D14: 4800.3366 | E14: 45880 | F14: USD | G14: 4778.84 | H14: 0798436220FS | I14: 1400000854 | K14: -5138.35 | L14: =D14-G14 -> 21.4966 | M14: 338 | N14: =-(K14+G14+M14) -> 21.51
A15: 45916 | B15: Outgoing Payments - VD0304,Being payment done against USD 5041 | C15: 003MISC252590125 | D15: 5041.56 | E15: 45918 | F15: USD | G15: 8339.84 | H15: 5940256259FS | I15: Not Yet Cleared | J15: 5940256259FS | K15: -8339.84 | L15: =D15+D16-G15 -> 29.488 | M15: =K15+G15 -> 0 | N15: =-(K15+G15+M15) -> 0 | O15: To Be Cleared
A16: 45916 | B16: Outgoing Payments - VD0304,Being payment done against USD 3327 | C16: 003MISC252590125 | D16: 3327.768 | L16: 0 | N16: =-(K16+G16+M16) -> 0
A17: 45961 | B17: Outgoing Payments - VD0304,Being $10502 | C17: 003MISC253040148 | D17: 10502.163 | E17: 45964 | F17: USD | G17: 10455.66 | H17: 2220942304JS | I17: Not Yet Cleared | J17: T54SWIC279194 | K17: -10455.66 | L17: =D17-G17 -> 46.5028 | M17: =K17+G17 -> 0 | N17: =-(K17+G17+M17) -> 0 | O17: To Be Cleared
A18: 45821 | B18: Outgoing Payments - VD0304,Being Amount paid to ascendas against bank ref | C18: 003FT01251640051 | D18: 12549.359 | E18: 45824 | F18: USD | G18: 12549.36 | H18: 1171852164FS | I18: Not Yet Cleared | J18: 1171852164FS | K18: -12549.36 | L18: =D18-G18 -> -0.0006 | M18: =K18+G18 -> 0 | N18: =-(K18+G18+M18) -> 0 | O18: To Be Cleared
D19: =SUM(D2:D18) -> 69387.52 | G19: =SUM(G2:G18) -> 69131.97 | K19: =SUM(K2:K18) -> -69777.74 | L19: =-SUM(L2:L18) -> -255.55 | M19: =SUM(M2:M18) -> 616.54 | N19: =SUM(N2:N18) -> 29.23
G23: =K19+D19 -> -390.22

Sheet Ascendus Data
F1: 25229.422 | G1: =SUBTOTAL(9,G3:G317) -> 25229.422 | I1: =SUBTOTAL(9,I3:I317) -> 4171298.9
A2: Document Number | B2: Document Type | C2: Document Date | D2: Reference | E2: Document Currency Key | F2: Document Currency Value | G2: USD Value | H2: Company Code Currency Key | I2: Company Code Currency Value | K2: Gross Amount | L2: Net Amount | M2: Diffrence | N2: Rate | O2: Text
A3: 1400001110 | B3: DY | C3: 45902 | E3: INR | F3: 603848.88 | G3: =F3/87 -> 6940.7917 | H3: INR | I3: 595243.31 | J3: {=_xlfn.XLOOKUP(D3,'Customer Data Vlookup'!$L:$L,'Customer Data Vlookup'!$M:$N,,0)} -> #N/A
A4: 1400001110 | B4: DY | C4: 45902 | E4: INR | F4: -603848.88 | G4: =F4/87 -> -6940.7917 | H4: INR | I4: -599760.56 | J4: {=_xlfn.XLOOKUP(D4,'Customer Data Vlookup'!$L:$L,'Customer Data Vlookup'!$M:$N,,0)} -> #N/A
A5: 1400000854 | B5: DZ | C5: 45887 | E5: USD | F5: -700.45 | G5: =F5 -> -700.45 | H5: INR | I5: -60884.42 | J5: {=_xlfn.XLOOKUP(D5,'Customer Data Vlookup'!$L:$L,'Customer Data Vlookup'!$M:$N,,0)} -> #N/A
A6: 1400001231 | B6: DZ | C6: 45931 | E6: USD | F6: -4719.25 | G6: =F6 -> -4719.25 | H6: INR | I6: -413002 | J6: {=_xlfn.XLOOKUP(D6,'Customer Data Vlookup'!$L:$L,'Customer Data Vlookup'!$M:$N,,0)} -> #N/A
A7: 1400000977 | B7: DZ | C7: 45890 | E7: USD | F7: -3663.7 | G7: =F7 -> -3663.7 | H7: INR | I7: -313212.57 | J7: {=_xlfn.XLOOKUP(D7,'Customer Data Vlookup'!$L:$L,'Customer Data Vlookup'!$M:$N,,0)} -> #N/A
A8: 1400000990 | B8: DZ | C8: 45890 | E8: USD | F8: -3777.49 | G8: =F8 -> -3777.49 | H8: INR | I8: -324866.67 | J8: {=_xlfn.XLOOKUP(D8,'Customer Data Vlookup'!$L:$L,'Customer Data Vlookup'!$M:$N,,0)} -> #N/A
A9: 1400000126 | B9: DZ | C9: 45832 | E9: USD | F9: -3663.7 | G9: =F9 -> -3663.7 | H9: INR | I9: -3663.7 | J9: {=_xlfn.XLOOKUP(D9,'Customer Data Vlookup'!$L:$L,'Customer Data Vlookup'!$M:$N,,0)} -> #N/A
A10: 1400000127 | B10: DZ | C10: 45832 | E10: USD | F10: -3508.06 | G10: =F10 -> -3508.06 | H10: INR | I10: -3508.06 | J10: {=_xlfn.XLOOKUP(D10,'Customer Data Vlookup'!$L:$L,'Customer Data Vlookup'!$M:$N,,0)} -> #N/A
A11: 1400000128 | B11: DZ | C11: 45832 | E11: USD | F11: -3145.98 | G11: =F11 -> -3145.98 | H11: INR | I11: -3145.98 | J11: {=_xlfn.XLOOKUP(D11,'Customer Data Vlookup'!$L:$L,'Customer Data Vlookup'!$M:$N,,0)} -> #N/A
A12: 1400000133 | B12: DZ | C12: 45832 | E12: USD | F12: -12549.36 | G12: =F12 -> -12549.36 | H12: INR | I12: -12549.36 | J12: {=_xlfn.XLOOKUP(D12,'Customer Data Vlookup'!$L:$L,'Customer Data Vlookup'!$M:$N,,0)} -> #N/A
A13: 1400000134 | B13: DZ | C13: 45832 | E13: USD | F13: -4228.22 | G13: =F13 -> -4228.22 | H13: INR | I13: -4228.22 | J13: {=_xlfn.XLOOKUP(D13,'Customer Data Vlookup'!$L:$L,'Customer Data Vlookup'!$M:$N,,0)} -> #N/A
A14: 1400000149 | B14: DZ | C14: 45832 | E14: USD | F14: 3663.7 | G14: =F14 -> 3663.7 | H14: INR | I14: 3663.7 | J14: {=_xlfn.XLOOKUP(D14,'Customer Data Vlookup'!$L:$L,'Customer Data Vlookup'!$M:$N,,0)} -> #N/A
A15: 1400000854 | B15: DZ | C15: 45887 | E15: USD | F15: -4437.9 | G15: =F15 -> -4437.9 | H15: INR | I15: -383425.92 | J15: {=_xlfn.XLOOKUP(D15,'Customer Data Vlookup'!$L:$L,'Customer Data Vlookup'!$M:$N,,0)} -> #N/A
A16: 1400000864 | B16: DZ | C16: 45888 | E16: USD | F16: -1102.02 | G16: =F16 -> -1102.02 | H16: INR | I16: -94695.18 | J16: {=_xlfn.XLOOKUP(D16,'Customer Data Vlookup'!$L:$L,'Customer Data Vlookup'!$M:$N,,0)} -> #N/A | O16: 8681446219FS
A17: 1400001221 | B17: DZ | C17: 45924 | E17: USD | F17: -2932.84 | G17: =F17 -> -2932.84 | H17: INR | I17: -256665.53 | J17: {=_xlfn.XLOOKUP(D17,'Customer Data Vlookup'!$L:$L,'Customer Data Vlookup'!$M:$N,,0)} -> #N/A
A18: 1400001598 | B18: DZ | C18: 45964 | E18: USD | F18: -1731.27 | G18: =F18 -> -1731.27 | H18: INR | I18: -152682.03 | J18: {=_xlfn.XLOOKUP(D18,'Customer Data Vlookup'!$L:$L,'Customer Data Vlookup'!$M:$N,,0)} -> #N/A
A19: 1400001618 | B19: DZ | C19: 45972 | E19: USD | F19: -1968.44 | G19: =F19 -> -1968.44 | H19: INR | I19: -173229.39 | J19: {=_xlfn.XLOOKUP(D19,'Customer Data Vlookup'!$L:$L,'Customer Data Vlookup'!$M:$N,,0)} -> #N/A
A20: 1400001620 | B20: DZ | C20: 45972 | E20: USD | F20: -8339.84 | G20: =F20 -> -8339.84 | H20: INR | I20: -729855.51 | J20: {=_xlfn.XLOOKUP(D20,'Customer Data Vlookup'!$L:$L,'Customer Data Vlookup'!$M:$N,,0)} -> #N/A
A21: 1400001622 | B21: DZ | C21: 45972 | E21: USD | F21: -10455.66 | G21: =F21 -> -10455.66 | H21: INR | I21: -920133.52 | J21: {=_xlfn.XLOOKUP(D21,'Customer Data Vlookup'!$L:$L,'Customer Data Vlookup'!$M:$N,,0)} -> #N/A
A22: 1400000213 | B22: DY | C22: 45842 | D22: KNOCK OFF ENTRY | E22: USD | F22: 0 | G22: =F22 -> 0 | H22: INR | I22: 0 | J22: {=_xlfn.XLOOKUP(D22,'Customer Data Vlookup'!$L:$L,'Customer Data Vlookup'!$M:$N,,0)} -> #N/A
A23: 1400000214 | B23: DY | C23: 45842 | D23: KNOCK OFF ENTRY | E23: USD | F23: 1166.59 | G23: =F23 -> 1166.59 | H23: INR | I23: 101402.13 | J23: {=_xlfn.XLOOKUP(D23,'Customer Data Vlookup'!$L:$L,'Customer Data Vlookup'!$M:$N,,0)} -> #N/A
A24: 1400000214 | B24: DY | C24: 45842 | D24: KNOCK OFF ENTRY | E24: USD | F24: -1166.59 | G24: =F24 -> -1166.59 | H24: INR | I24: -101402.13 | J24: {=_xlfn.XLOOKUP(D24,'Customer Data Vlookup'!$L:$L,'Customer Data Vlookup'!$M:$N,,0)} -> #N/A
A25: 1400000215 | B25: DY | C25: 45842 | D25: KNOCK OFF ENTRY | E25: USD | F25: 1143.12 | G25: =F25 -> 1143.12 | H25: INR | I25: 99362.07 | J25: {=_xlfn.XLOOKUP(D25,'Customer Data Vlookup'!$L:$L,'Customer Data Vlookup'!$M:$N,,0)} -> #N/A
A26: 1400000215 | B26: DY | C26: 45842 | D26: KNOCK OFF ENTRY | E26: USD | F26: -1143.12 | G26: =F26 -> -1143.12 | H26: INR | I26: -99362.07 | J26: {=_xlfn.XLOOKUP(D26,'Customer Data Vlookup'!$L:$L,'Customer Data Vlookup'!$M:$N,,0)} -> #N/A
A27: 1800008260 | B27: DR | C27: 45787 | D27: 256779413144 | E27: INR | F27: 100000 | G27: =L27/0.9 -> 1163.0111 | H27: INR | I27: 100000 | J27: {=_xlfn.XLOOKUP(D27,'Customer Data Vlookup'!$L:$L,'Customer Data Vlookup'!$M:$N,,0)} -> 0 | K27: 1046.71 | L27: =K27-J27 -> 1046.71 | M27: =G27-L27 -> 116.30111 | N27: =M27/G27 -> 0.1 | O27: Fixed Storage Charges fo MAY 2025
A28: 1800009592 | B28: DR | C28: 45818 | D28: 256779414356 | E28: INR | F28: 100000 | G28: =L28/0.9 -> 1169.72 | H28: INR | I28: 100000 | J28: {=_xlfn.XLOOKUP(D28,'Customer Data Vlookup'!$L:$L,'Customer Data Vlookup'!$M:$N,,0)} -> 0 | K28: 1052.748 | L28: =K28-J28 -> 1052.748 | M28: =G28-L28 -> 116.972 | N28: =M28/G28 -> 0.1 | O28: Fixed Storage Charges fo JUNE 2025
A29: 1800010154 | B29: DR | C29: 45842 | D29: 256779414914 | E29: INR | F29: 100000 | G29: =L29/0.9 -> 1162.78 | H29: INR | I29: 100000 | J29: {=_xlfn.XLOOKUP(D29,'Customer Data Vlookup'!$L:$L,'Customer Data Vlookup'!$M:$N,,0)} -> 0 | K29: 1046.502 | L29: =K29-J29 -> 1046.502 | M29: =G29-L29 -> 116.278 | N29: =M29/G29 -> 0.1 | O29: Fixed Storage Charges fo JULY 2025
A30: 1800011360 | B30: DR | C30: 45870 | D30: 256779416026 | E30: INR | F30: 100000 | G30: =L30/0.9 -> 1162.3778 | H30: INR | I30: 100000 | J30: {=_xlfn.XLOOKUP(D30,'Customer Data Vlookup'!$L:$L,'Customer Data Vlookup'!$M:$N,,0)} -> 0 | K30: 1046.14 | L30: =K30-J30 -> 1046.14 | M30: =G30-L30 -> 116.23778 | N30: =M30/G30 -> 0.1 | O30: Fixed Storage Charges for August 2025
A31: 1800012712 | B31: DR | C31: 45904 | D31: 256779417346 | E31: INR | F31: 100000 | G31: =L31/0.9 -> 1142.67 | H31: INR | I31: 100000 | J31: {=_xlfn.XLOOKUP(D31,'Customer Data Vlookup'!$L:$L,'Customer Data Vlookup'!$M:$N,,0)} -> 0 | K31: 1028.403 | L31: =K31-J31 -> 1028.403 | M31: =G31-L31 -> 114.267 | N31: =M31/G31 -> 0.1 | O31: Fixed Storage Charges for September 2025
A32: 1800014235 | B32: DR | C32: 45966 | D32: 256779418775 | E32: INR | F32: 100000 | G32: =L32/0.9 -> 1136.32 | H32: INR | I32: 100000 | J32: {=_xlfn.XLOOKUP(D32,'Customer Data Vlookup'!$L:$L,'Customer Data Vlookup'!$M:$N,,0)} -> 0 | K32: 1022.688 | L32: =K32-J32 -> 1022.688 | M32: =G32-L32 -> 113.632 | N32: =M32/G32 -> 0.1 | O32: Fixed Storage Charges for November 2025
A33: 1800015484 | B33: DR | C33: 45995 | D33: 256779419968 | E33: INR | F33: 100000 | G33: =L33/0.9 -> 1127.39 | H33: INR | I33: 100000 | J33: {=_xlfn.XLOOKUP(D33,'Customer Data Vlookup'!$L:$L,'Customer Data Vlookup'!$M:$N,,0)} -> 0 | K33: 1014.651 | L33: =K33-J33 -> 1014.651 | M33: =G33-L33 -> 112.739 | N33: =M33/G33 -> 0.1 | O33: Fixed Storage Charges for December 2025
A34: 1800008261 | B34: DR | C34: 45787 | D34: 256779413145 | E34: INR | F34: 35000 | G34: =L34/0.9 -> 407.05 | H34: INR | I34: 35000 | J34: {=_xlfn.XLOOKUP(D34,'Customer Data Vlookup'!$L:$L,'Customer Data Vlookup'!$M:$N,,0)} -> 0 | K34: 366.345 | L34: =K34-J34 -> 366.345 | M34: =G34-L34 -> 40.705 | N34: =M34/G34 -> 0.1 | O34: Fixed Storage Charges fo MAY 2025
A35: 1800009593 | B35: DR | C35: 45818 | D35: 256779414357 | E35: INR | F35: 35000 | G35: =L35/0.9 -> 409.4 | H35: INR | I35: 35000 | J35: {=_xlfn.XLOOKUP(D35,'Customer Data Vlookup'!$L:$L,'Customer Data Vlookup'!$M:$N,,0)} -> 0 | K35: 368.46 | L35: =K35-J35 -> 368.46 | M35: =G35-L35 -> 40.94 | N35: =M35/G35 -> 0.1 | O35: Fixed Storage Charges fo JUNE 2025
A36: 1800010155 | B36: DR | C36: 45842 | D36: 256779414915 | E36: INR | F36: 35000 | G36: =L36/0.9 -> 443.14511 | H36: INR | I36: 35000 | J36: {=_xlfn.XLOOKUP(D36,'Customer Data Vlookup'!$L:$L,'Customer Data Vlookup'!$M:$N,,0)} -> 0 | K36: 398.8306 | L36: =K36-J36 -> 398.8306 | M36: =G36-L36 -> 44.314511 | N36: =M36/G36 -> 0.1 | O36: Fixed Storage Charges fo JULY 2025
A37: 1800011361 | B37: DR | C37: 45870 | D37: 256779416027 | E37: INR | F37: 35000 | G37: =L37/0.9 -> 442.98889 | H37: INR | I37: 35000 | J37: {=_xlfn.XLOOKUP(D37,'Customer Data Vlookup'!$L:$L,'Customer Data Vlookup'!$M:$N,,0)} -> 0 | K37: 398.69 | L37: =K37-J37 -> 398.69 | M37: =G37-L37 -> 44.298889 | N37: =M37/G37 -> 0.1 | O37: Fixed Storage Charges for August 2025
A38: 1800012713 | B38: DR | C38: 45904 | D38: 256779417347 | E38: INR | F38: 35000 | G38: =L38/0.9 -> 399.93 | H38: INR | I38: 35000 | J38: {=_xlfn.XLOOKUP(D38,'Customer Data Vlookup'!$L:$L,'Customer Data Vlookup'!$M:$N,,0)} -> 0 | K38: 359.937 | L38: =K38-J38 -> 359.937 | M38: =G38-L38 -> 39.993 | N38: =M38/G38 -> 0.1 | O38: Fixed Storage Charges for September 2025
... A40: 1800015485 | B40: DR | C40: 45995 | D40: 256779419969 | E40: INR | F40: 35000 | G40: =L40/0.9 -> 429.66467 | H40: INR | I40: 35000 | J40: {=_xlfn.XLOOKUP(D40,'Customer Data Vlookup'!$L:$L,'Customer Data Vlookup'!$M:$N,,0)} -> 0 | K40: 386.6982 | L40: =K40-J40 -> 386.6982 | M40: =G40-L40 -> 42.966467 | N40: =M40/G40 -> 0.1 | O40: Fixed Mangement FEE for December 2025
A41: 1600002145 | B41: DG | C41: 45890 | D41: 256779421709 | E41: INR | F41: -200000 | G41: =F41/87 -> -2298.8506 | H41: INR | I41: -200000 | J41: {=_xlfn.XLOOKUP(D41,'Customer Data Vlookup'!$L:$L,'Customer Data Vlookup'!$M:$N,,0)} -> #N/A | O41: CN issued towards D & D
A42: 1800012258 | B42: DR | C42: 45883 | D42: 256779416887 | E42: INR | F42: 200000 | G42: =F42/87 -> 2298.8506 | H42: INR | I42: 200000 | J42: {=_xlfn.XLOOKUP(D42,'Customer Data Vlookup'!$L:$L,'Customer Data Vlookup'!$M:$N,,0)} -> #N/A | O42: DN issued towards D & D 256779421709
A43: 1800002451 | B43: DR | C43: 45733 | D43: 246779412116 | E43: USD | F43: 100 | G43: =F43 -> 100 | H43: INR | I43: 8669.13 | J43: {=_xlfn.XLOOKUP(D43,'Customer Data Vlookup'!$L:$L,'Customer Data Vlookup'!$M:$N,,0)} -> 0 | K43: 98 | L43: =K43-J43 -> 98 | M43: =F43-L43 -> 2 | N43: =M43/F43 -> 0.02 | O43: Intra Unit Transfer Charges Month Of December,2024
A44: 1800002454 | B44: DR | C44: 45733 | D44: 246779412119 | E44: USD | F44: 100 | G44: =F44 -> 100 | H44: INR | I44: 8669.13 | J44: {=_xlfn.XLOOKUP(D44,'Customer Data Vlookup'!$L:$L,'Customer Data Vlookup'!$M:$N,,0)} -> 0 | K44: 98 | L44: =K44-J44 -> 98 | M44: =F44-L44 -> 2 | N44: =M44/F44 -> 0.02 | O44: Intra Unit Transfer Charges Month Of December,2024
A45: 1800002456 | B45: DR | C45: 45733 | D45: 246779412121 | E45: USD | F45: 100 | G45: =F45 -> 100 | H45: INR | I45: 8669.13 | J45: {=_xlfn.XLOOKUP(D45,'Customer Data Vlookup'!$L:$L,'Customer Data Vlookup'!$M:$N,,0)} -> 0 | K45: 98 | L45: =K45-J45 -> 98 | M45: =F45-L45 -> 2 | N45: =M45/F45 -> 0.02 | O45: Intra Unit Transfer Charges Month Of December,2024
A46: 1800008348 | B46: DR | C46: 45787 | D46: 256779413231 | E46: USD | F46: 100 | G46: =F46 -> 100 | H46: INR | I46: 8598.37 | J46: {=_xlfn.XLOOKUP(D46,'Customer Data Vlookup'!$L:$L,'Customer Data Vlookup'!$M:$N,,0)} -> 0 | K46: 98 | L46: =K46-J46 -> 98 | M46: =F46-L46 -> 2 | N46: =M46/F46 -> 0.02 | O46: Intra Unit Transfer 16-30 April 25
A47: 1800009077 | B47: DR | C47: 45797 | D47: 256779413841 | E47: USD | F47: 100 | G47: =F47 -> 100 | H47: INR | I47: 8598.37 | J47: {=_xlfn.XLOOKUP(D47,'Customer Data Vlookup'!$L:$L,'Customer Data Vlookup'!$M:$N,,0)} -> 0 | K47: 98 | L47: =K47-J47 -> 98 | M47: =F47-L47 -> 2 | N47: =M47/F47 -> 0.02 | O47: Unit to Unit, 1-15 May 25
A48: 1800009083 | B48: DR | C48: 45797 | D48: 256779413847 | E48: USD | F48: 100 | G48: =F48 -> 100 | H48: INR | I48: 8598.37 | J48: {=_xlfn.XLOOKUP(D48,'Customer Data Vlookup'!$L:$L,'Customer Data Vlookup'!$M:$N,,0)} -> 0 | K48: 98 | L48: =K48-J48 -> 98 | M48: =F48-L48 -> 2 | N48: =M48/F48 -> 0.02 | O48: Unit to Unit, 1-15 May 25
A49: 1800009084 | B49: DR | C49: 45797 | D49: 256779413848 | E49: USD | F49: 100 | G49: =F49 -> 100 | H49: INR | I49: 8598.37 | J49: {=_xlfn.XLOOKUP(D49,'Customer Data Vlookup'!$L:$L,'Customer Data Vlookup'!$M:$N,,0)} -> 0 | K49: 98 | L49: =K49-J49 -> 98 | M49: =F49-L49 -> 2 | N49: =M49/F49 -> 0.02 | O49: Unit to Unit, 1-15 May 25
A50: 1800011280 | B50: DR | C50: 45863 | D50: 256779416012 | E50: USD | F50: 100 | G50: =F50 -> 100 | H50: INR | I50: 8600.07 | J50: {=_xlfn.XLOOKUP(D50,'Customer Data Vlookup'!$L:$L,'Customer Data Vlookup'!$M:$N,,0)} -> 0 | K50: 98 | L50: =K50-J50 -> 98 | M50: =F50-L50 -> 2 | N50: =M50/F50 -> 0.02 | O50: Unit to Unit 16-31 May 25
A51: 1800001850 | B51: DR | C51: 45730 | D51: 246779411515 | E51: USD | F51: 100 | G51: =F51 -> 100 | H51: INR | I51: 8669.13 | J51: {=_xlfn.XLOOKUP(D51,'Customer Data Vlookup'!$L:$L,'Customer Data Vlookup'!$M:$N,,0)} -> 0 | K51: 98 | L51: =K51-J51 -> 98 | M51: =F51-L51 -> 2 | N51: =M51/F51 -> 0.02 | O51: Intra Unit Transfer Charges Month Of August,2024
A52: 1800009967 | B52: DR | C52: 45827 | D52: 256779414731 | E52: USD | F52: 100 | G52: =F52 -> 100 | H52: INR | I52: 8549.08 | J52: {=_xlfn.XLOOKUP(D52,'Customer Data Vlookup'!$L:$L,'Customer Data Vlookup'!$M:$N,,0)} -> #N/A | O52: Unit to Unit 1-15 June 25
A53: 1800009968 | B53: DR | C53: 45827 | D53: 256779414732 | E53: USD | F53: 100 | G53: =F53 -> 100 | H53: INR | I53: 8549.08 | J53: {=_xlfn.XLOOKUP(D53,'Customer Data Vlookup'!$L:$L,'Customer Data Vlookup'!$M:$N,,0)} -> #N/A | O53: Unit to Unit 1-15 June 25
A54: 1800009969 | B54: DR | C54: 45827 | D54: 256779414733 | E54: USD | F54: 100 | G54: =F54 -> 100 | H54: INR | I54: 8549.08 | J54: {=_xlfn.XLOOKUP(D54,'Customer Data Vlookup'!$L:$L,'Customer Data Vlookup'!$M:$N,,0)} -> #N/A | O54: Unit to Unit 1-15 June 25
A55: 1800009970 | B55: DR | C55: 45827 | D55: 256779414734 | E55: USD | F55: 100 | G55: =F55 -> 100 | H55: INR | I55: 8549.08 | J55: {=_xlfn.XLOOKUP(D55,'Customer Data Vlookup'!$L:$L,'Customer Data Vlookup'!$M:$N,,0)} -> #N/A | O55: Unit to Unit 1-15 June 25
A56: 1800009971 | B56: DR | C56: 45827 | D56: 256779414735 | E56: USD | F56: 100 | G56: =F56 -> 100 | H56: INR | I56: 8549.08 | J56: {=_xlfn.XLOOKUP(D56,'Customer Data Vlookup'!$L:$L,'Customer Data Vlookup'!$M:$N,,0)} -> 0 | K56: 90 | L56: =K56-J56 -> 90 | M56: =F56-L56 -> 10 | N56: =M56/F56 -> 0.1 | O56: Unit to Unit 1-15 June 25
A57: 1800012780 | B57: DR | C57: 45917 | D57: 256779417434 | E57: USD | F57: 100 | G57: =F57 -> 100 | H57: INR | I57: 8751.43 | J57: {=_xlfn.XLOOKUP(D57,'Customer Data Vlookup'!$L:$L,'Customer Data Vlookup'!$M:$N,,0)} -> 0 | K57: 98 | L57: =K57-J57 -> 98 | M57: =F57-L57 -> 2 | N57: =M57/F57 -> 0.02 | O57: Intra SEZ -1-15 Sept-25
A58: 1800013748 | B58: DR | C58: 45937 | D58: 256779418169 | E58: USD | F58: 100 | G58: =F58 -> 100 | H58: INR | I58: 8819.08 | J58: {=_xlfn.XLOOKUP(D58,'Customer Data Vlookup'!$L:$L,'Customer Data Vlookup'!$M:$N,,0)} -> #N/A | O58: Intra - SEZ-16-30 Sept 25
A59: 1800013749 | B59: DR | C59: 45937 | D59: 256779418170 | E59: USD | F59: 100 | G59: =F59 -> 100 | H59: INR | I59: 8819.08 | J59: {=_xlfn.XLOOKUP(D59,'Customer Data Vlookup'!$L:$L,'Customer Data Vlookup'!$M:$N,,0)} -> 0 | K59: 98 | L59: =K59-J59 -> 98 | M59: =F59-L59 -> 2 | N59: =M59/F59 -> 0.02 | O59: Intra - SEZ-16-30 Sept 25
A60: 1800000374 | B60: DR | C60: 45716 | D60: 246779410343 | E60: USD | F60: 1700 | G60: =F60 -> 1700 | H60: INR | I60: 146716.22 | J60: {=_xlfn.XLOOKUP(D60,'Customer Data Vlookup'!$L:$L,'Customer Data Vlookup'!$M:$N,,0)} -> #N/A | O60: CY Longstanding container Ground Rent charges for
A61: 1800000381 | B61: DR | C61: 45716 | D61: 246779410350 | E61: USD | F61: 1750 | G61: =F61 -> 1750 | H61: INR | I61: 151031.41 | J61: {=_xlfn.XLOOKUP(D61,'Customer Data Vlookup'!$L:$L,'Customer Data Vlookup'!$M:$N,,0)} -> #N/A | O61: CY Longstanding container Ground Rent charges for
A62: 1800000387 | B62: DR | C62: 45716 | D62: 246779410356 | E62: USD | F62: 1750 | G62: =F62 -> 1750 | H62: INR | I62: 151031.41 | J62: {=_xlfn.XLOOKUP(D62,'Customer Data Vlookup'!$L:$L,'Customer Data Vlookup'!$M:$N,,0)} -> #N/A | O62: CY Longstanding container Ground Rent charges for
A63: 1800000393 | B63: DR | C63: 45716 | D63: 246779410362 | E63: USD | F63: 1700 | G63: =F63 -> 1700 | H63: INR | I63: 146716.22 | J63: {=_xlfn.XLOOKUP(D63,'Customer Data Vlookup'!$L:$L,'Customer Data Vlookup'!$M:$N,,0)} -> #N/A | O63: CY Longstanding container Ground Rent charges for
A64: 1800000931 | B64: DR | C64: 45722 | D64: 246779410871 | E64: USD | F64: 42.51 | G64: =F64 -> 42.51 | H64: INR | I64: 3685.25 | J64: {=_xlfn.XLOOKUP(D64,'Customer Data Vlookup'!$L:$L,'Customer Data Vlookup'!$M:$N,,0)} -> 0 | K64: 38.259 | L64: =K64-J64 -> 38.259 | M64: =F64-L64 -> 4.251 | N64: =M64/F64 -> 0.1 | O64: Storage Charges for the month of November, 2024 Ex
A65: 1800000953 | B65: DR | C65: 45722 | D65: 246779410893 | E65: USD | F65: 177.18 | G65: =F65 -> 177.18 | H65: INR | I65: 15359.96 | J65: {=_xlfn.XLOOKUP(D65,'Customer Data Vlookup'!$L:$L,'Customer Data Vlookup'!$M:$N,,0)} -> 0 | K65: 159.462 | L65: =K65-J65 -> 159.462 | M65: =F65-L65 -> 17.718 | N65: =M65/F65 -> 0.1 | O65: Storage Charges for the month of December, 2024 Ex
A66: 1600002439 | B66: DG | C66: 45943 | D66: 256779421983 | E66: USD | F66: -930.14 | G66: =F66 -> -930.14 | H66: INR | I66: -82029.76 | J66: {=_xlfn.XLOOKUP(D66,'Customer Data Vlookup'!$L:$L,'Customer Data Vlookup'!$M:$N,,0)} -> #N/A | O66: CN issued against 256779418011
A67: 1800000414 | B67: DR | C67: 45719 | D67: 246779410376 | E67: USD | F67: 711.35 | G67: =F67 -> 711.35 | H67: INR | I67: 61667.83 | J67: {=_xlfn.XLOOKUP(D67,'Customer Data Vlookup'!$L:$L,'Customer Data Vlookup'!$M:$N,,0)} -> 0 | K67: 640.215 | L67: =K67-J67 -> 640.215 | M67: =F67-L67 -> 71.135 | N67: =M67/F67 -> 0.1 | O67: Storage Charges for the month of August, 2024
A68: 1800000439 | B68: DR | C68: 45719 | D68: 246779410401 | E68: USD | F68: 1298.96 | G68: =F68 -> 1298.96 | H68: INR | I68: 112608.48 | J68: {=_xlfn.XLOOKUP(D68,'Customer Data Vlookup'!$L:$L,'Customer Data Vlookup'!$M:$N,,0)} -> 0 | K68: 1169.064 | L68: =K68-J68 -> 1169.064 | M68: =F68-L68 -> 129.896 | N68: =M68/F68 -> 0.1 | O68: Storage for the month of Sept 2024
A69: 1800000463 | B69: DR | C69: 45719 | D69: 246779410425 | E69: USD | F69: 1687.21 | G69: =F69 -> 1687.21 | H69: INR | I69: 146266.36 | J69: {=_xlfn.XLOOKUP(D69,'Customer Data Vlookup'!$L:$L,'Customer Data Vlookup'!$M:$N,,0)} -> 0 | K69: 1518.489 | L69: =K69-J69 -> 1518.489 | M69: =F69-L69 -> 168.721 | N69: =M69/F69 -> 0.1 | O69: Storage for the month of Oct 2024
A70: 1800001956 | B70: DR | C70: 45733 | D70: 246779411621 | E70: USD | F70: 444.04 | G70: =F70 -> 444.04 | H70: INR | I70: 38494.39 | J70: {=_xlfn.XLOOKUP(D70,'Customer Data Vlookup'!$L:$L,'Customer Data Vlookup'!$M:$N,,0)} -> 0 | K70: 435.1592 | L70: =K70-J70 -> 435.1592 | M70: =F70-L70 -> 8.8808 | N70: =M70/F70 -> 0.02 | O70: VAS Activity Charges for the month of September, 2
A71: 1800002095 | B71: DR | C71: 45733 | D71: 246779411760 | E71: USD | F71: 520.17 | G71: =F71 -> 520.17 | H71: INR | I71: 45094.19 | J71: {=_xlfn.XLOOKUP(D71,'Customer Data Vlookup'!$L:$L,'Customer Data Vlookup'!$M:$N,,0)} -> 0 | K71: 509.7666 | L71: =K71-J71 -> 509.7666 | M71: =F71-L71 -> 10.4034 | N71: =M71/F71 -> 0.02 | O71: VAS Activity Charges for the month of October, 24
A72: 1800002401 | B72: DR | C72: 45733 | D72: 246779412066 | E72: USD | F72: 66.5 | G72: =F72 -> 66.5 | H72: INR | I72: 5764.97 | J72: {=_xlfn.XLOOKUP(D72,'Customer Data Vlookup'!$L:$L,'Customer Data Vlookup'!$M:$N,,0)} -> 0 | K72: 65.17 | L72: =K72-J72 -> 65.17 | M72: =F72-L72 -> 1.33 | N72: =M72/F72 -> 0.02 | O72: VAS Activity Charges for the month of December, 24
A73: 1800002272 | B73: DR | C73: 45733 | D73: 246779411937 | E73: USD | F73: 7.27 | G73: =F73 -> 7.27 | H73: INR | I73: 630.25 | J73: {=_xlfn.XLOOKUP(D73,'Customer Data Vlookup'!$L:$L,'Customer Data Vlookup'!$M:$N,,0)} -> 0 | K73: 7.1246 | L73: =K73-J73 -> 7.1246 | M73: =F73-L73 -> 0.1454 | N73: =M73/F73 -> 0.02 | O73: VAS Activity Charges for the month of November, 24
A74: 1800002273 | B74: DR | C74: 45733 | D74: 246779411938 | E74: USD | F74: 53.26 | G74: =F74 -> 53.26 | H74: INR | I74: 4617.18 | J74: {=_xlfn.XLOOKUP(D74,'Customer Data Vlookup'!$L:$L,'Customer Data Vlookup'!$M:$N,,0)} -> 0 | K74: 52.1948 | L74: =K74-J74 -> 52.1948 | M74: =F74-L74 -> 1.0652 | N74: =M74/F74 -> 0.02 | O74: VAS Activity Charges for the month of November, 24
A75: 1800002274 | B75: DR | C75: 45733 | D75: 246779411939 | E75: USD | F75: 23.08 | G75: =F75 -> 23.08 | H75: INR | I75: 2000.83 | J75: {=_xlfn.XLOOKUP(D75,'Customer Data Vlookup'!$L:$L,'Customer Data Vlookup'!$M:$N,,0)} -> 0 | K75: 22.6184 | L75: =K75-J75 -> 22.6184 | M75: =F75-L75 -> 0.4616 | N75: =M75/F75 -> 0.02 | O75: VAS Activity Charges for the month of November, 24
A76: 1800002275 | B76: DR | C76: 45733 | D76: 246779411940 | E76: USD | F76: 52.73 | G76: =F76 -> 52.73 | H76: INR | I76: 4571.23 | J76: {=_xlfn.XLOOKUP(D76,'Customer Data Vlookup'!$L:$L,'Customer Data Vlookup'!$M:$N,,0)} -> 0 | K76: 51.6754 | L76: =K76-J76 -> 51.6754 | M76: =F76-L76 -> 1.0546 | N76: =M76/F76 -> 0.02 | O76: VAS Activity Charges for the month of November, 24
A77: 1800002276 | B77: DR | C77: 45733 | D77: 246779411941 | E77: USD | F77: 76.02 | G77: =F77 -> 76.02 | H77: INR | I77: 6590.27 | J77: {=_xlfn.XLOOKUP(D77,'Customer Data Vlookup'!$L:$L,'Customer Data Vlookup'!$M:$N,,0)} -> 0 | K77: 74.4996 | L77: =K77-J77 -> 74.4996 | M77: =F77-L77 -> 1.5204 | N77: =M77/F77 -> 0.02 | O77: VAS Activity Charges for the month of November, 24
A78: 1800006261 | B78: DR | C78: 45762 | D78: 256779411152 | E78: USD | F78: 164.38 | G78: =F78 -> 164.38 | H78: INR | I78: 14288.21 | J78: {=_xlfn.XLOOKUP(D78,'Customer Data Vlookup'!$L:$L,'Customer Data Vlookup'!$M:$N,,0)} -> 0 | K78: 161.09 | L78: =K78-J78 -> 161.09 | M78: =F78-L78 -> 3.29 | N78: =M78/F78 -> 0.0200146 | O78: Empty Transportation August 2024
... A104: 1800006694 | B104: DR | C104: 45762 | D104: 256779411585 | E104: USD | F104: 7.81 | G104: =F104 -> 7.81 | H104: INR | I104: 678.86 | J104: {=_xlfn.XLOOKUP(D104,'Customer Data Vlookup'!$L:$L,'Customer Data Vlookup'!$M:$N,,0)} -> 0 | K104: 7.65 | L104: =K104-J104 -> 7.65 | M104: =F104-L104 -> 0.16 | N104: =M104/F104 -> 0.020486556 | O104: Outbound Handling Charges Aug 2024
A105: 1600002472 | B105: DG | C105: 45947 | D105: 256779422014 | E105: USD | F105: -136.48 | G105: =F105 -> -136.48 | H105: INR | I105: -12036.28 | J105: {=_xlfn.XLOOKUP(D105,'Customer Data Vlookup'!$L:$L,'Customer Data Vlookup'!$M:$N,,0)} -> #N/A | O105: Credit note raised against 256779418076
A106: 1800006996 | B106: DR | C106: 45763 | D106: 256779411887 | E106: USD | F106: 71.22 | G106: =F106 -> 71.22 | H106: INR | I106: 6190.57 | J106: {=_xlfn.XLOOKUP(D106,'Customer Data Vlookup'!$L:$L,'Customer Data Vlookup'!$M:$N,,0)} -> 0 | K106: 69.7956 | L106: =K106-J106 -> 69.7956 | M106: =F106-L106 -> 1.4244 | N106: =M106/F106 -> 0.02 | O106: Outbound Handling charges for Dec 2024
A107: 1800007093 | B107: DR | C107: 45763 | D107: 256779411984 | E107: USD | F107: 39.54 | G107: =F107 -> 39.54 | H107: INR | I107: 3436.89 | J107: {=_xlfn.XLOOKUP(D107,'Customer Data Vlookup'!$L:$L,'Customer Data Vlookup'!$M:$N,,0)} -> 0 | K107: 38.7492 | L107: =K107-J107 -> 38.7492 | M107: =F107-L107 -> 0.7908 | N107: =M107/F107 -> 0.02 | O107: CAAU5283880-Port SSR Shifting Mar 2025. Exch rate
A108: 1800007129 | B108: DR | C108: 45763 | D108: 256779412020 | E108: USD | F108: 85.21 | G108: =F108 -> 85.21 | H108: INR | I108: 7406.61 | J108: {=_xlfn.XLOOKUP(D108,'Customer Data Vlookup'!$L:$L,'Customer Data Vlookup'!$M:$N,,0)} -> 0 | K108: 83.5058 | L108: =K108-J108 -> 83.5058 | M108: =F108-L108 -> 1.7042 | N108: =M108/F108 -> 0.02 | O108: VAS Activity - Jan 25, Ex Rate. 86.64
A109: 1800007210 | B109: DR | C109: 45763 | D109: 256779412101 | E109: USD | F109: 171.71 | G109: =F109 -> 171.71 | H109: INR | I109: 14925.35 | J109: {=_xlfn.XLOOKUP(D109,'Customer Data Vlookup'!$L:$L,'Customer Data Vlookup'!$M:$N,,0)} -> 0 | K109: 168.28 | L109: =K109-J109 -> 168.28 | M109: =F109-L109 -> 3.43 | N109: =M109/F109 -> 0.01997554 | O109: VAS Activity - Mar 25, 16-31, Ex Rate. 85.58
A110: 1800007235 | B110: DR | C110: 45763 | D110: 256779412126 | E110: USD | F110: 500.58 | G110: =F110 -> 500.58 | H110: INR | I110: 43511.32 | J110: {=_xlfn.XLOOKUP(D110,'Customer Data Vlookup'!$L:$L,'Customer Data Vlookup'!$M:$N,,0)} -> 0 | K110: 450.522 | L110: =K110-J110 -> 450.522 | M110: =F110-L110 -> 50.058 | N110: =M110/F110 -> 0.1 | O110: Storage Charges Mar, 25 Exch Rate 85.58
A111: 1800011264 | B111: DR | C111: 45863 | D111: 256779415996 | E111: USD | F111: 755.58 | G111: =F111 -> 755.58 | H111: INR | I111: 64980.39 | J111: {=_xlfn.XLOOKUP(D111,'Customer Data Vlookup'!$L:$L,'Customer Data Vlookup'!$M:$N,,0)} -> 0 | K111: 740.47 | L111: =K111-J111 -> 740.47 | M111: =F111-L111 -> 15.11 | N111: =M111/F111 -> 0.019997882 | O111: VAS 16-31 May 25 Ex.85.48
A112: 1800001581 | B112: DR | C112: 45730 | D112: 246779412238 | E112: USD | F112: 945.75 | G112: =F112 -> 945.75 | H112: INR | I112: 81988.26 | J112: {=_xlfn.XLOOKUP(D112,'Customer Data Vlookup'!$L:$L,'Customer Data Vlookup'!$M:$N,,0)} -> 0 | K112: 0 | L112: =K112-J112 -> 0 | M112: =F112-L112 -> 945.75 | N112: =M112/F112 -> 1 | O112: VAS Activity Charges for the month of August, 24
A113: 1800001784 | B113: DR | C113: 45730 | D113: 246779411449 | E113: USD | F113: 945.75 | G113: =F113 -> 945.75 | H113: INR | I113: 81988.26 | J113: {=_xlfn.XLOOKUP(D113,'Customer Data Vlookup'!$L:$L,'Customer Data Vlookup'!$M:$N,,0)} -> 0 | K113: 926.835 | L113: =K113-J113 -> 926.835 | M113: =F113-L113 -> 18.915 | N113: =M113/F113 -> 0.02 | O113: VAS Activity Charges for the month of August, 24
A114: 1600002155 | B114: DG | C114: 45883 | D114: 256779421715 | E114: USD | F114: -2324.77 | G114: =F114 -> -2324.77 | H114: INR | I114: -200000.24 | J114: {=_xlfn.XLOOKUP(D114,'Customer Data Vlookup'!$L:$L,'Customer Data Vlookup'!$M:$N,,0)} -> 2092.293 | K114: 0 | L114: =J114 -> 2092.293 | M114: =F114+L114 -> -232.477 | N114: =M114/F114 -> 0.1 | O114: CN issued towards D & D
A115: 1800012461 | B115: DR | C115: 45904 | D115: 256779417161 | E115: USD | F115: 787.95 | G115: =F115 -> 787.95 | H115: INR | I115: 68956.92 | J115: {=_xlfn.XLOOKUP(D115,'Customer Data Vlookup'!$L:$L,'Customer Data Vlookup'!$M:$N,,0)} -> 0 | K115: 772.191 | L115: =K115-J115 -> 772.191 | M115: =F115-L115 -> 15.759 | N115: =M115/F115 -> 0.02 | O115: VAS -16-31 Aug 25
A116: 1800012559 | B116: DR | C116: 45904 | D116: 256779417178 | E116: USD | F116: 1560 | G116: =F116 -> 1560 | H116: INR | I116: 136522.35 | J116: {=_xlfn.XLOOKUP(D116,'Customer Data Vlookup'!$L:$L,'Customer Data Vlookup'!$M:$N,,0)} -> 0 | K116: 1528.8 | L116: =K116-J116 -> 1528.8 | M116: =F116-L116 -> 31.2 | N116: =M116/F116 -> 0.02 | O116: CY Refer Pluging Chgs - 01 - 31 May 25
A117: 1800012560 | B117: DR | C117: 45904 | D117: 256779417179 | E117: USD | F117: 1560 | G117: =F117 -> 1560 | H117: INR | I117: 136522.35 | J117: {=_xlfn.XLOOKUP(D117,'Customer Data Vlookup'!$L:$L,'Customer Data Vlookup'!$M:$N,,0)} -> 0 | K117: 1528.8 | L117: =K117-J117 -> 1528.8 | M117: =F117-L117 -> 31.2 | N117: =M117/F117 -> 0.02 | O117: CY Refer Pluging Chgs - 01 - 30 Jun 25
A118: 1800012561 | B118: DR | C118: 45904 | D118: 256779417180 | E118: USD | F118: 1799.1 | G118: =F118 -> 1799.1 | H118: INR | I118: 157447.03 | J118: {=_xlfn.XLOOKUP(D118,'Customer Data Vlookup'!$L:$L,'Customer Data Vlookup'!$M:$N,,0)} -> 0 | K118: 1748.15 | L118: =K118-J118 -> 1748.15 | M118: =F118-L118 -> 50.95 | N118: =M118/F118 -> 0.028319715 | O118: CY Ground rent Chgs - 01 - 31 July 25
A119: 1800012562 | B119: DR | C119: 45904 | D119: 256779417181 | E119: USD | F119: 1812 | G119: =F119 -> 1812 | H119: INR | I119: 158575.97 | J119: {=_xlfn.XLOOKUP(D119,'Customer Data Vlookup'!$L:$L,'Customer Data Vlookup'!$M:$N,,0)} -> 0 | K119: 1759.76 | L119: =K119-J119 -> 1759.76 | M119: =F119-L119 -> 52.24 | N119: =M119/F119 -> 0.028830022 | O119: CY Ground rent Chgs - 01 - 31 Aug 25
A120: 1800012619 | B120: DR | C120: 45904 | D120: 256779417206 | E120: USD | F120: 152.28 | G120: =F120 -> 152.28 | H120: INR | I120: 13326.68 | J120: {=_xlfn.XLOOKUP(D120,'Customer Data Vlookup'!$L:$L,'Customer Data Vlookup'!$M:$N,,0)} -> 0 | K120: 149.2344 | L120: =K120-J120 -> 149.2344 | M120: =F120-L120 -> 3.0456 | N120: =M120/F120 -> 0.02 | O120: Empty Lolo Chgs - 01 - 31 AUG 25
A121: 1800012587 | B121: DR | C121: 45904 | D121: 256779417245 | E121: USD | F121: 83.89 | G121: =F121 -> 83.89 | H121: INR | I121: 7341.58 | J121: {=_xlfn.XLOOKUP(D121,'Customer Data Vlookup'!$L:$L,'Customer Data Vlookup'!$M:$N,,0)} -> 0 | K121: 82.2122 | L121: =K121-J121 -> 82.2122 | M121: =F121-L121 -> 1.6778 | N121: =M121/F121 -> 0.02 | O121: PORT SSR Chgs Aug 25
A122: 1800012647 | B122: DR | C122: 45904 | D122: 256779417287 | E122: USD | F122: 410.58 | G122: =F122 -> 410.58 | H122: INR | I122: 35931.63 | J122: {=_xlfn.XLOOKUP(D122,'Customer Data Vlookup'!$L:$L,'Customer Data Vlookup'!$M:$N,,0)} -> 0 | K122: 402.3684 | L122: =K122-J122 -> 402.3684 | M122: =F122-L122 -> 8.2116 | N122: =M122/F122 -> 0.02 | O122: Transportation In Chgs - 16 - 31 AUG 25
A123: 1800012685 | B123: DR | C123: 45904 | D123: 256779417325 | E123: USD | F123: 97.84 | G123: =F123 -> 97.84 | H123: INR | I123: 8562.4 | J123: {=_xlfn.XLOOKUP(D123,'Customer Data Vlookup'!$L:$L,'Customer Data Vlookup'!$M:$N,,0)} -> 0 | K123: 95.8832 | L123: =K123-J123 -> 95.8832 | M123: =F123-L123 -> 1.9568 | N123: =M123/F123 -> 0.02 | O123: Outbound chgs - 16 - 31 Aug 25
A124: 1600002212 | B124: DG | C124: 45904 | D124: 256779421767 | E124: USD | F124: -60 | G124: =F124 -> -60 | H124: INR | I124: -5250.86 | J124: {=_xlfn.XLOOKUP(D124,'Customer Data Vlookup'!$L:$L,'Customer Data Vlookup'!$M:$N,,0)} -> #N/A | O124: CN Issued towards bill no. 256779417178
A125: 1600002213 | B125: DG | C125: 45904 | D125: 256779421768 | E125: USD | F125: -60 | G125: =F125 -> -60 | H125: INR | I125: -5250.86 | J125: {=_xlfn.XLOOKUP(D125,'Customer Data Vlookup'!$L:$L,'Customer Data Vlookup'!$M:$N,,0)} -> #N/A | O125: CN Issued towards bill no. 256779417179
A126: 1600002214 | B126: DG | C126: 45904 | D126: 256779421769 | E126: USD | F126: -62 | G126: =F126 -> -62 | H126: INR | I126: -5425.89 | J126: {=_xlfn.XLOOKUP(D126,'Customer Data Vlookup'!$L:$L,'Customer Data Vlookup'!$M:$N,,0)} -> #N/A | O126: CN Issued towards bill no. 256779417180
...

Sheet Payment Reco
A2: As per Customer | E2: As per Ascendus
A3: Document Date | B3: Remarks | C3: Offset Acct Name | D3: Amount | E3: Document Type | F3: Document Date | G3: Document Currency Key | H3: Document Currency Value
A4: 45813 | B4: Outgoing Payments - VD0304, Being Amount paid to ascendas against bank ref. no-003MISC251560088 dated 5-6-2025. | C4: YES BANK - 038784600000486 - CC A/c(SGE) | D4: 3529.5558 | E4: DZ | F4: 45832 | G4: USD | H4: 3663.7
A5: 45813 | B5: Outgoing Payments - VD0304,Being Amount paid to ascendas against bank ref. no-003MISC251560102 dated 5-6-2025. | C5: YES BANK - 038784600000486 - CC A/c(SGE) | D5: 3167.4752 | E5: DZ | F5: 45832 | G5: USD | H5: 3508.06
A6: 45813 | B6: Outgoing Payments - VD0304,Being Amount paid to ascendas against bank ref. no-003MISC251560090 dated 5-6-2025. | C6: YES BANK - 038784600000486 - CC A/c(SGE) | D6: 3685.2032 | E6: DZ | F6: 45832 | G6: USD | H6: 3145.98
A7: 45821 | B7: Outgoing Payments - VD0304,Being Amount paid to ascendas against bank ref. no-003FT01251640051 dated 13-6-2025. | C7: HDFC Bank - INR | D7: 12549.359 | E7: DZ | F7: 45832 | G7: USD | H7: 12549.36
A8: 45821 | B8: Outgoing Payments - VD0304,Being Amount paid to ascendas against bank ref. no-003FT01251640038 dated 13-6-2025. | C8: HDFC Bank - INR | E8: DZ | F8: 45832 | G8: USD | H8: 4228.22
A9: 45821 | B9: Reverse Entry for Payment No. 7360143 | C9: HDFC Bank - INR | E9: DZ | F9: 45887 | G9: USD | H9: 700.45
A10: 45821 | B10: Outgoing Payments - VD0304,Being Amount paid to ascendas against bank ref. no-003FT01251640038 dated 13-6-2025. | C10: HDFC Bank - INR | D10: 4127.955 | E10: DZ | F10: 45887 | G10: USD | H10: 4437.9
A11: 45821 | B11: Being $3.4008 less paid in this bill because in summary sheet 2% tds deduscted instead of 10% | C11: HDFC Bank - INR | D11: 3.4008 | E11: DZ | F11: 45888 | G11: USD | H11: 1102.02
A12: 45821 | B12: Reverse Entry for Payment No. 7360144 | C12: HDFC Bank - INR | D12: -4127.955 | E12: DZ | F12: 45890 | G12: USD | H12: 3777.49
A13: 45821 | B13: Outgoing Payments - VD0304,Being Amount paid to ascendas against bank ref. no-003FT01251640038 dated 13-6-2025. | C13: HDFC Bank - INR | D13: 4224.8172 | E13: DZ | F13: 46029 | G13: USD | H13: 986.48
A14: 45856 | B14: Outgoing Payments - VD0304,Being payment done against USD 3798.9858 ASCENDAS PANVEL FTWZ PRIVATE LIMITED, Bank ref no.- 003MISC251990131 dated-18-07-2025. | C14: YES BANK - USD | D14: 3742.0478 | E14: DZ | F14: 45924 | G14: USD | H14: 2932.84
A15: 45876 | B15: Outgoing Payments - VD0304,Being payment done against USD 1007.82 ASCENDAS PANVEL FTWZ PRIVATE LIMITED, Bank ref no.- 003MISC252190104 dated-07-08-2025. | C15: YES BANK - USD | D15: 1007.818 | H15: 0
A16: 45877 | B16: Outgoing Payments - VD0304,Being payment done against USD 4800.34 ASCENDAS PANVEL FTWZ PRIVATE LIMITED, Bank ref no.- 003MISC252200121 dated-08-08-2025. | C16: YES BANK - USD | D16: 4800.3366 | E16: DZ | F16: 45931 | G16: USD | H16: 4719.25
A17: 45910 | B17: Outgoing Payments - VD0304,Being payment done against USD 2954.34 ASCENDAS PANVEL FTWZ PRIVATE LIMITED, Bank ref no.- 003MISC252530130 dated-10-09-2025. | C17: YES BANK - USD | D17: 2954.3362 | E17: DZ | F17: 45964 | G17: USD | H17: 1731.27
A18: 45910 | B18: Outgoing Payments - VD0304,Being payment done against USD 4740.75 ASCENDAS PANVEL FTWZ PRIVATE LIMITED, Bank ref no.- 003MISC252530128 dated-10-09-2025. | C18: YES BANK - USD | D18: 4740.77 | E18: DZ | F18: 45972 | G18: USD | H18: 1968.44
A19: 45916 | B19: Outgoing Payments - VD0304,Being payment done against USD 5041.57 ASCENDAS PANVEL FTWZ PRIVATE LIMITED, Bank ref no.- 003MISC252590125 dated-16-09-2025. | C19: YES BANK - USD | D19: 5041.56 | E19: DZ | F19: 45972 | G19: USD | H19: 8339.84
A20: 45916 | B20: Outgoing Payments - VD0304,Being payment done against USD 3327.77 ASCENDAS PANVEL FTWZ PRIVATE LIMITED, Bank ref no.- 003MISC252590125 dated-16-09-2025. | C20: YES BANK - USD | D20: 3327.768 | E20: DZ | F20: 45972 | G20: USD | H20: 10455.66
A21: 45959 | B21: Outgoing Payments - VD0304,Being payment done against USD 1752.77 ASCENDAS PANVEL FTWZ PRIVATE LIMITED, Bank ref no.- 003MISC253020092 dated-29-10-2025. | C21: YES BANK - USD | D21: 1752.7656 | H21: 0
A22: 45961 | B22: Outgoing Payments - VD0304,Being $1989.94 paid to ASCENDAS PANVEL FTWZ PRIVATE LIMITED against bank ref. no.-003MISC253040153 dated-31-10-2025. | C22: YES BANK - USD | D22: 1989.9404 | H22: 0
A23: 45961 | B23: Outgoing Payments - VD0304,Being $10502.1628 paid to ASCENDAS PANVEL FTWZ PRIVATE LIMITED against bank ref. no.-003MISC253040148 dated-31-10-2025. | C23: YES BANK - USD | D23: 10502.163 | E23: DZ | F23: 46029 | G23: USD | H23: 1530.78
A24: 46022 | B24: Outgoing Payments - VD0304,Being $2328.2000 paid to ASCENDAS PANVEL FTWZ PRIVATE LIMITED against bank ref. no.-003MISC253650039 dated-31-12-2025. | C24: Yes Bank (Dollar) | D24: 2368.203 | H24: 0
D25: =SUM(D4:D24) -> 69387.52 | H25: =SUM(H4:H24) -> 69777.74 | I25: =D25-H25 -> -390.22

Sheet Difference in Invoice Amount
A1: Document Number | B1: Document Type | C1: Document Date | D1: Reference | E1: Document Currency Key | F1: Document Currency Value | G1: USD Value | H1: Company Code Currency Key | I1: Company Code Currency Value | J1: Vlookup | K1: Gross Amount | L1: Net Amount | M1: Diffrence | N1: Rate | O1: Text
A2: 1800001581 | B2: DR | C2: 45730 | D2: 246779412238 | E2: USD | F2: 945.75 | G2: 945.75 | H2: INR | I2: 81988.26 | J2: 0 | K2: 0 | L2: 0 | M2: 945.75 | N2: 1 | O2: VAS Activity Charges for the month of August, 24
A3: 1800000282 | B3: DR | C3: 45708 | D3: 246779410209 | E3: USD | F3: 408.31 | G3: 408.31 | H3: INR | I3: 35238.65 | J3: 0 | K3: 1450.0748 | L3: 1450.0748 | M3: -1041.7648 | N3: -2.5514065 | O3: Management Fees for Jan 2025
M4: =SUM(M2:M3) -> -96.0148

Sheet Invoice not in Customer books
G1: =SUBTOTAL(9,G3:G38) -> 23952.404 | H1: ='CN not in Customer Books'!G21 -> -16429.04 | I1: =G1+H1 -> 7523.3641
A2: Document Number | B2: Document Type | C2: Document Date | D2: Reference | E2: Document Currency Key | F2: Document Currency Value | G2: USD Value | H2: Company Code Currency Key | I2: Company Code Currency Value | J2: Text
A3: 1800009967 | B3: DR | C3: 45827 | D3: 256779414731 | E3: USD | F3: 100 | G3: 100 | H3: INR | I3: 8549.08 | J3: Unit to Unit 1-15 June 25 | K3: =_xlfn.XLOOKUP(D3,'CN not in Customer Books'!$K:$K,'CN not in Customer Books'!$G:$G,,0) -> #N/A
A4: 1800009968 | B4: DR | C4: 45827 | D4: 256779414732 | E4: USD | F4: 100 | G4: 100 | H4: INR | I4: 8549.08 | J4: Unit to Unit 1-15 June 25 | K4: =_xlfn.XLOOKUP(D4,'CN not in Customer Books'!$K:$K,'CN not in Customer Books'!$G:$G,,0) -> #N/A
A5: 1800009969 | B5: DR | C5: 45827 | D5: 256779414733 | E5: USD | F5: 100 | G5: 100 | H5: INR | I5: 8549.08 | J5: Unit to Unit 1-15 June 25 | K5: =_xlfn.XLOOKUP(D5,'CN not in Customer Books'!$K:$K,'CN not in Customer Books'!$G:$G,,0) -> #N/A
A6: 1800009970 | B6: DR | C6: 45827 | D6: 256779414734 | E6: USD | F6: 100 | G6: 100 | H6: INR | I6: 8549.08 | J6: Unit to Unit 1-15 June 25 | K6: =_xlfn.XLOOKUP(D6,'CN not in Customer Books'!$K:$K,'CN not in Customer Books'!$G:$G,,0) -> #N/A
A7: 1800013748 | B7: DR | C7: 45937 | D7: 256779418169 | E7: USD | F7: 100 | G7: 100 | H7: INR | I7: 8819.08 | J7: Intra - SEZ-16-30 Sept 25 | K7: =_xlfn.XLOOKUP(D7,'CN not in Customer Books'!$K:$K,'CN not in Customer Books'!$G:$G,,0) -> #N/A
A8: 1800000374 | B8: DR | C8: 45716 | D8: 246779410343 | E8: USD | F8: 1700 | G8: 1700 | H8: INR | I8: 146716.22 | J8: CY Longstanding container Ground Rent charges for | K8: =_xlfn.XLOOKUP(D8,'CN not in Customer Books'!$K:$K,'CN not in Customer Books'!$G:$G,,0) -> #N/A
A9: 1800000381 | B9: DR | C9: 45716 | D9: 246779410350 | E9: USD | F9: 1750 | G9: 1750 | H9: INR | I9: 151031.41 | J9: CY Longstanding container Ground Rent charges for | K9: =_xlfn.XLOOKUP(D9,'CN not in Customer Books'!$K:$K,'CN not in Customer Books'!$G:$G,,0) -> #N/A
A10: 1800000387 | B10: DR | C10: 45716 | D10: 246779410356 | E10: USD | F10: 1750 | G10: 1750 | H10: INR | I10: 151031.41 | J10: CY Longstanding container Ground Rent charges for | K10: =_xlfn.XLOOKUP(D10,'CN not in Customer Books'!$K:$K,'CN not in Customer Books'!$G:$G,,0) -> #N/A
A11: 1800000393 | B11: DR | C11: 45716 | D11: 246779410362 | E11: USD | F11: 1700 | G11: 1700 | H11: INR | I11: 146716.22 | J11: CY Longstanding container Ground Rent charges for | K11: =_xlfn.XLOOKUP(D11,'CN not in Customer Books'!$K:$K,'CN not in Customer Books'!$G:$G,,0) -> #N/A
A12: 1800011800 | B12: DR | C12: 45877 | D12: 256779416103 | E12: USD | F12: 50 | G12: 50 | H12: INR | I12: 4301.51 | J12: Scanning Chgs - 16 - 31 Jul 25 | K12: =_xlfn.XLOOKUP(D12,'CN not in Customer Books'!$K:$K,'CN not in Customer Books'!$G:$G,,0) -> #N/A
A13: 1800011042 | B13: DR | C13: 45856 | D13: 256779415802 | E13: USD | F13: 860.97 | G13: 860.97 | H13: INR | I13: 74044 | J13: Transportation In Chgs - 01 - 15 JUL 25 | K13: =_xlfn.XLOOKUP(D13,'CN not in Customer Books'!$K:$K,'CN not in Customer Books'!$G:$G,,0) -> #N/A
A14: 1800005020 | B14: DR | C14: 45736 | D14: 246779414888 | E14: USD | F14: 10.91 | G14: 10.91 | H14: INR | I14: 945.8 | J14: Outbound Handling charges for Jan 2025 | K14: =_xlfn.XLOOKUP(D14,'CN not in Customer Books'!$K:$K,'CN not in Customer Books'!$G:$G,,0) -> #N/A
... A38: 1800017178 | B38: DR | C38: 46055 | D38: 256779440457 | E38: USD | F38: 938.8 | G38: 938.8 | H38: INR | I38: 84806.69 | J38: Unit Storage - 1-30 Sept 2025 | K38: =_xlfn.XLOOKUP(D38,'CN not in Customer Books'!$K:$K,'CN not in Customer Books'!$G:$G,,0) -> #N/A

Sheet CN not in Customer Books
A2: Document Number | B2: Document Type | C2: Document Date | D2: Reference | E2: Document Currency Key | F2: Document Currency Value | G2: USD Value | H2: Company Code Currency Key | I2: Company Code Currency Value | J2: Text
A3: 1600002439 | B3: DG | C3: 45943 | D3: 256779421983 | E3: USD | F3: -930.14 | G3: -930.14 | H3: INR | I3: -82029.76 | J3: CN issued against 256779418011 | K3: 256779418011 | L3: =_xlfn.XLOOKUP(K3,'Invoice not in Customer books'!$D:$D,'Invoice not in Customer books'!$G:$G,,0) -> #N/A
A4: 1600002212 | B4: DG | C4: 45904 | D4: 256779421767 | E4: USD | F4: -60 | G4: -60 | H4: INR | I4: -5250.86 | J4: CN Issued towards bill no. 256779417178 | K4: 256779417178 | L4: =_xlfn.XLOOKUP(K4,'Invoice not in Customer books'!$D:$D,'Invoice not in Customer books'!$G:$G,,0) -> #N/A
A5: 1600002213 | B5: DG | C5: 45904 | D5: 256779421768 | E5: USD | F5: -60 | G5: -60 | H5: INR | I5: -5250.86 | J5: CN Issued towards bill no. 256779417179 | K5: 256779417179 | L5: =_xlfn.XLOOKUP(K5,'Invoice not in Customer books'!$D:$D,'Invoice not in Customer books'!$G:$G,,0) -> #N/A
A6: 1600002214 | B6: DG | C6: 45904 | D6: 256779421769 | E6: USD | F6: -62 | G6: -62 | H6: INR | I6: -5425.89 | J6: CN Issued towards bill no. 256779417180 | K6: 256779417180 | L6: =_xlfn.XLOOKUP(K6,'Invoice not in Customer books'!$D:$D,'Invoice not in Customer books'!$G:$G,,0) -> #N/A
A7: 1600002215 | B7: DG | C7: 45904 | D7: 256779421770 | E7: USD | F7: -62 | G7: -62 | H7: INR | I7: -5425.89 | J7: CN Issued towards bill no. 256779417181 | K7: 256779417181 | L7: =_xlfn.XLOOKUP(K7,'Invoice not in Customer books'!$D:$D,'Invoice not in Customer books'!$G:$G,,0) -> #N/A
A8: 1600001539 | B8: DG | C8: 45842 | D8: 256779421172 | E8: USD | F8: -1700 | G8: -1700 | H8: INR | I8: -146201.14 | J8: CN against 256779410006 | K8: 256779410006 | L8: =_xlfn.XLOOKUP(K8,'Invoice not in Customer books'!$D:$D,'Invoice not in Customer books'!$G:$G,,0) -> #N/A
A9: 1600001540 | B9: DG | C9: 45842 | D9: 256779421173 | E9: USD | F9: -1750 | G9: -1750 | H9: INR | I9: -150501.17 | J9: CN against 256779410012 | K9: 256779410012 | L9: =_xlfn.XLOOKUP(K9,'Invoice not in Customer books'!$D:$D,'Invoice not in Customer books'!$G:$G,,0) -> #N/A
A10: 1600001541 | B10: DG | C10: 45842 | D10: 256779421174 | E10: USD | F10: -1700 | G10: -1700 | H10: INR | I10: -146201.14 | J10: CN against 256779410015 | K10: 256779410015 | L10: =_xlfn.XLOOKUP(K10,'Invoice not in Customer books'!$D:$D,'Invoice not in Customer books'!$G:$G,,0) -> #N/A
A11: 1600001542 | B11: DG | C11: 45842 | D11: 256779421175 | E11: USD | F11: -1750 | G11: -1750 | H11: INR | I11: -150501.17 | J11: CN against 256779410224 | K11: 256779410224 | L11: =_xlfn.XLOOKUP(K11,'Invoice not in Customer books'!$D:$D,'Invoice not in Customer books'!$G:$G,,0) -> #N/A
A12: 1600000596 | B12: DG | C12: 45791 | D12: 256779420305 | E12: USD | F12: -945.75 | G12: -945.75 | H12: INR | I12: -81988.26 | J12: Credit note against 246779412238 | K12: 246779412238 | L12: =_xlfn.XLOOKUP(K12,'Invoice not in Customer books'!$D:$D,'Invoice not in Customer books'!$G:$G,,0) -> #N/A
A13: 1600001839 | B13: DG | C13: 45862 | D13: 256779421459 | E13: USD | F13: -1700 | G13: -1700 | H13: INR | I13: -146201.14 | J13: Credit note raised against 256779410006 | K13: 256779410006 | L13: =_xlfn.XLOOKUP(K13,'Invoice not in Customer books'!$D:$D,'Invoice not in Customer books'!$G:$G,,0) -> #N/A
A14: 1600001840 | B14: DG | C14: 45862 | D14: 256779421460 | E14: USD | F14: -1750 | G14: -1750 | H14: INR | I14: -150501.17 | J14: Credit note raised against 256779410012 | K14: 256779410012 | L14: =_xlfn.XLOOKUP(K14,'Invoice not in Customer books'!$D:$D,'Invoice not in Customer books'!$G:$G,,0) -> #N/A
... A20: 1600002771 | B20: DG | C20: 46055 | D20: 256779422241 | E20: USD | F20: -87.28 | G20: -87.28 | H20: INR | I20: -7884.46 | J20: CN issued against - 256779417082 | K20: 256779417082 | L20: =_xlfn.XLOOKUP(K20,'Invoice not in Customer books'!$D:$D,'Invoice not in Customer books'!$G:$G,,0) -> #N/A
G21: =SUM(G3:G20) -> -16429.04

Sheet TDS Deducted
M1: =SUM(M3:M211) -> 4692.5328 | N1: =SUBTOTAL(9,N3:N211) -> 40 | O1: =M1+N1 -> 4732.5328
A2: Document Number | B2: Document Type | C2: Document Date | D2: Reference | E2: Document Currency Key | F2: Document Currency Value | G2: USD Value | H2: Company Code Currency Key | I2: Company Code Currency Value | J2: Vlookup | K2: Gross Amount | L2: Net Amount | M2: Diffrence | N2: Additional TDS | O2: Rate | P2: Text | R2: Ref. 2 (Header) | S2: Document Date | T2: Remarks | U2: Offset Acct Name | V2: Debit (FC) | W2: Credit (FC)
A3: 1800008260 | B3: DR | C3: 45787 | D3: 256779413144 | E3: INR | F3: 100000 | G3: 1163.0111 | H3: INR | I3: 100000 | J3: 0 | K3: 1046.71 | L3: 1046.71 | M3: 116.30111 | N3: =_xlfn.XLOOKUP(D3,$R:$R,$V:$V,0,0) -> 0 | O3: 0.1 | P3: Fixed Storage Charges fo MAY 2025 | R3: 246779413797 | S3: 45736 | T3: Being TDS deduction on 246779413797 ascendas | U3: Tds Payable- 94Ib - Rent | V3: 20
A4: 1800009592 | B4: DR | C4: 45818 | D4: 256779414356 | E4: INR | F4: 100000 | G4: 1169.72 | H4: INR | I4: 100000 | J4: 0 | K4: 1052.748 | L4: 1052.748 | M4: 116.972 | N4: =_xlfn.XLOOKUP(D4,$R:$R,$V:$V,0,0) -> 0 | O4: 0.1 | P4: Fixed Storage Charges fo JUNE 2025 | S4: 45736 | T4: Being TDS deduction on 246779413797 ascendas | U4: Tds Payable- 94Ib - Rent | W4: 20
A5: 1800010154 | B5: DR | C5: 45842 | D5: 256779414914 | E5: INR | F5: 100000 | G5: 1162.78 | H5: INR | I5: 100000 | J5: 0 | K5: 1046.502 | L5: 1046.502 | M5: 116.278 | N5: =_xlfn.XLOOKUP(D5,$R:$R,$V:$V,0,0) -> 0 | O5: 0.1 | P5: Fixed Storage Charges fo JULY 2025 | S5: 45736 | T5: Being TDS deduction on 246779413797 ascendas(Reversal) - 7619 | U5: Tds Payable- 94Ib - Rent | V5: -20
A6: 1800011360 | B6: DR | C6: 45870 | D6: 256779416026 | E6: INR | F6: 100000 | G6: 1162.3778 | H6: INR | I6: 100000 | J6: 0 | K6: 1046.14 | L6: 1046.14 | M6: 116.23778 | N6: =_xlfn.XLOOKUP(D6,$R:$R,$V:$V,0,0) -> 0 | O6: 0.1 | P6: Fixed Storage Charges for August 2025 | R6: 246779413808 | S6: 45736 | T6: Being TDS deduction on 246779413808 ascendas | U6: Tds Payable- 94Ib - Rent | V6: 20
A7: 1800012712 | B7: DR | C7: 45904 | D7: 256779417346 | E7: INR | F7: 100000 | G7: 1142.67 | H7: INR | I7: 100000 | J7: 0 | K7: 1028.403 | L7: 1028.403 | M7: 114.267 | N7: =_xlfn.XLOOKUP(D7,$R:$R,$V:$V,0,0) -> 0 | O7: 0.1 | P7: Fixed Storage Charges for September 2025 | S7: 45736 | T7: Being TDS deduction on 246779413797 ascendas | U7: Tds Payable- 94Ib - Rent | V7: 20
A8: 1800014235 | B8: DR | C8: 45966 | D8: 256779418775 | E8: INR | F8: 100000 | G8: 1136.32 | H8: INR | I8: 100000 | J8: 0 | K8: 1022.688 | L8: 1022.688 | M8: 113.632 | N8: =_xlfn.XLOOKUP(D8,$R:$R,$V:$V,0,0) -> 0 | O8: 0.1 | P8: Fixed Storage Charges for November 2025 | S8: 45736 | T8: Being TDS deduction on 246779413797 ascendas(Reversal) - 7646 | U8: Tds Payable- 94Ib - Rent | W8: -20
A9: 1800015484 | B9: DR | C9: 45995 | D9: 256779419968 | E9: INR | F9: 100000 | G9: 1127.39 | H9: INR | I9: 100000 | J9: 0 | K9: 1014.651 | L9: 1014.651 | M9: 112.739 | N9: =_xlfn.XLOOKUP(D9,$R:$R,$V:$V,0,0) -> 0 | O9: 0.1 | P9: Fixed Storage Charges for December 2025
A10: 1800008261 | B10: DR | C10: 45787 | D10: 256779413145 | E10: INR | F10: 35000 | G10: 407.05 | H10: INR | I10: 35000 | J10: 0 | K10: 366.345 | L10: 366.345 | M10: 40.705 | N10: =_xlfn.XLOOKUP(D10,$R:$R,$V:$V,0,0) -> 0 | O10: 0.1 | P10: Fixed Storage Charges fo MAY 2025
A11: 1800009593 | B11: DR | C11: 45818 | D11: 256779414357 | E11: INR | F11: 35000 | G11: 409.4 | H11: INR | I11: 35000 | J11: 0 | K11: 368.46 | L11: 368.46 | M11: 40.94 | N11: =_xlfn.XLOOKUP(D11,$R:$R,$V:$V,0,0) -> 0 | O11: 0.1 | P11: Fixed Storage Charges fo JUNE 2025
A12: 1800010155 | B12: DR | C12: 45842 | D12: 256779414915 | E12: INR | F12: 35000 | G12: 443.14511 | H12: INR | I12: 35000 | J12: 0 | K12: 398.8306 | L12: 398.8306 | M12: 44.314511 | N12: =_xlfn.XLOOKUP(D12,$R:$R,$V:$V,0,0) -> 0 | O12: 0.1 | P12: Fixed Storage Charges fo JULY 2025
A13: 1800011361 | B13: DR | C13: 45870 | D13: 256779416027 | E13: INR | F13: 35000 | G13: 442.98889 | H13: INR | I13: 35000 | J13: 0 | K13: 398.69 | L13: 398.69 | M13: 44.298889 | N13: =_xlfn.XLOOKUP(D13,$R:$R,$V:$V,0,0) -> 0 | O13: 0.1 | P13: Fixed Storage Charges for August 2025
A14: 1800012713 | B14: DR | C14: 45904 | D14: 256779417347 | E14: INR | F14: 35000 | G14: 399.93 | H14: INR | I14: 35000 | J14: 0 | K14: 359.937 | L14: 359.937 | M14: 39.993 | N14: =_xlfn.XLOOKUP(D14,$R:$R,$V:$V,0,0) -> 0 | O14: 0.1 | P14: Fixed Storage Charges for September 2025
A15: 1800014236 | B15: DR | C15: 45966 | D15: 256779418776 | E15: INR | F15: 35000 | G15: 433.062 | H15: INR | I15: 35000 | J15: 0 | K15: 389.7558 | L15: 389.7558 | M15: 43.3062 | N15: =_xlfn.XLOOKUP(D15,$R:$R,$V:$V,0,0) -> 0 | O15: 0.1 | P15: Fixed Storage Charges for November 2025
A16: 1800015485 | B16: DR | C16: 45995 | D16: 256779419969 | E16: INR | F16: 35000 | G16: 429.66467 | H16: INR | I16: 35000 | J16: 0 | K16: 386.6982 | L16: 386.6982 | M16: 42.966467 | N16: =_xlfn.XLOOKUP(D16,$R:$R,$V:$V,0,0) -> 0 | O16: 0.1 | P16: Fixed Mangement FEE for December 2025
A17: 1800002451 | B17: DR | C17: 45733 | D17: 246779412116 | E17: USD | F17: 100 | G17: 100 | H17: INR | I17: 8669.13 | J17: 0 | K17: 98 | L17: 98 | M17: 2 | N17: =_xlfn.XLOOKUP(D17,$R:$R,$V:$V,0,0) -> 0 | O17: 0.02 | P17: Intra Unit Transfer Charges Month Of December,2024
A18: 1800002454 | B18: DR | C18: 45733 | D18: 246779412119 | E18: USD | F18: 100 | G18: 100 | H18: INR | I18: 8669.13 | J18: 0 | K18: 98 | L18: 98 | M18: 2 | N18: =_xlfn.XLOOKUP(D18,$R:$R,$V:$V,0,0) -> 0 | O18: 0.02 | P18: Intra Unit Transfer Charges Month Of December,2024
A19: 1800002456 | B19: DR | C19: 45733 | D19: 246779412121 | E19: USD | F19: 100 | G19: 100 | H19: INR | I19: 8669.13 | J19: 0 | K19: 98 | L19: 98 | M19: 2 | N19: =_xlfn.XLOOKUP(D19,$R:$R,$V:$V,0,0) -> 0 | O19: 0.02 | P19: Intra Unit Transfer Charges Month Of December,2024
A20: 1800008348 | B20: DR | C20: 45787 | D20: 256779413231 | E20: USD | F20: 100 | G20: 100 | H20: INR | I20: 8598.37 | J20: 0 | K20: 98 | L20: 98 | M20: 2 | N20: =_xlfn.XLOOKUP(D20,$R:$R,$V:$V,0,0) -> 0 | O20: 0.02 | P20: Intra Unit Transfer 16-30 April 25
... A75: 1800001784 | B75: DR | C75: 45730 | D75: 246779411449 | E75: USD | F75: 945.75 | G75: 945.75 | H75: INR | I75: 81988.26 | J75: 0 | K75: 926.835 | L75: 926.835 | M75: 18.915 | N75: =_xlfn.XLOOKUP(D75,$R:$R,$V:$V,0,0) -> 0 | O75: 0.02 | P75: VAS Activity Charges for the month of August, 24
A76: 1600002155 | B76: DG | C76: 45883 | D76: 256779421715 | E76: USD | F76: -2324.77 | G76: -2324.77 | H76: INR | I76: -200000.24 | J76: 2092.293 | K76: 0 | L76: 2092.293 | M76: =G76+L76 -> -232.477 | O76: 0.1 | P76: CN issued towards D & D
A77: 1800012461 | B77: DR | C77: 45904 | D77: 256779417161 | E77: USD | F77: 787.95 | G77: 787.95 | H77: INR | I77: 68956.92 | J77: 0 | K77: 772.191 | L77: 772.191 | M77: 15.759 | N77: =_xlfn.XLOOKUP(D77,$R:$R,$V:$V,0,0) -> 0 | O77: 0.02 | P77: VAS -16-31 Aug 25
A78: 1800012559 | B78: DR | C78: 45904 | D78: 256779417178 | E78: USD | F78: 1560 | G78: 1560 | H78: INR | I78: 136522.35 | J78: 0 | K78: 1528.8 | L78: 1528.8 | M78: 31.2 | N78: =_xlfn.XLOOKUP(D78,$R:$R,$V:$V,0,0) -> 0 | O78: 0.02 | P78: CY Refer Pluging Chgs - 01 - 31 May 25
A79: 1800012560 | B79: DR | C79: 45904 | D79: 256779417179 | E79: USD | F79: 1560 | G79: 1560 | H79: INR | I79: 136522.35 | J79: 0 | K79: 1528.8 | L79: 1528.8 | M79: 31.2 | N79: =_xlfn.XLOOKUP(D79,$R:$R,$V:$V,0,0) -> 0 | O79: 0.02 | P79: CY Refer Pluging Chgs - 01 - 30 Jun 25
A80: 1800012561 | B80: DR | C80: 45904 | D80: 256779417180 | E80: USD | F80: 1799.1 | G80: 1799.1 | H80: INR | I80: 157447.03 | J80: 0 | K80: 1748.15 | L80: 1748.15 | M80: 50.95 | N80: =_xlfn.XLOOKUP(D80,$R:$R,$V:$V,0,0) -> 0 | O80: 0.028319715 | P80: CY Ground rent Chgs - 01 - 31 July 25
A81: 1800012562 | B81: DR | C81: 45904 | D81: 256779417181 | E81: USD | F81: 1812 | G81: 1812 | H81: INR | I81: 158575.97 | J81: 0 | K81: 1759.76 | L81: 1759.76 | M81: 52.24 | N81: =_xlfn.XLOOKUP(D81,$R:$R,$V:$V,0,0) -> 0 | O81: 0.028830022 | P81: CY Ground rent Chgs - 01 - 31 Aug 25
A82: 1800012619 | B82: DR | C82: 45904 | D82: 256779417206 | E82: USD | F82: 152.28 | G82: 152.28 | H82: INR | I82: 13326.68 | J82: 0 | K82: 149.2344 | L82: 149.2344 | M82: 3.0456 | N82: =_xlfn.XLOOKUP(D82,$R:$R,$V:$V,0,0) -> 0 | O82: 0.02 | P82: Empty Lolo Chgs - 01 - 31 AUG 25
A83: 1800012587 | B83: DR | C83: 45904 | D83: 256779417245 | E83: USD | F83: 83.89 | G83: 83.89 | H83: INR | I83: 7341.58 | J83: 0 | K83: 82.2122 | L83: 82.2122 | M83: 1.6778 | N83: =_xlfn.XLOOKUP(D83,$R:$R,$V:$V,0,0) -> 0 | O83: 0.02 | P83: PORT SSR Chgs Aug 25
A84: 1800012647 | B84: DR | C84: 45904 | D84: 256779417287 | E84: USD | F84: 410.58 | G84: 410.58 | H84: INR | I84: 35931.63 | J84: 0 | K84: 402.3684 | L84: 402.3684 | M84: 8.2116 | N84: =_xlfn.XLOOKUP(D84,$R:$R,$V:$V,0,0) -> 0 | O84: 0.02 | P84: Transportation In Chgs - 16 - 31 AUG 25
A85: 1800012685 | B85: DR | C85: 45904 | D85: 256779417325 | E85: USD | F85: 97.84 | G85: 97.84 | H85: INR | I85: 8562.4 | J85: 0 | K85: 95.8832 | L85: 95.8832 | M85: 1.9568 | N85: =_xlfn.XLOOKUP(D85,$R:$R,$V:$V,0,0) -> 0 | O85: 0.02 | P85: Outbound chgs - 16 - 31 Aug 25
A86: 1800010008 | B86: DR | C86: 45842 | D86: 256779414772 | E86: USD | F86: 220 | G86: 220 | H86: INR | I86: 18920.15 | J86: 0 | K86: 215.6 | L86: 215.6 | M86: 4.4 | N86: =_xlfn.XLOOKUP(D86,$R:$R,$V:$V,0,0) -> 0 | O86: 0.02 | P86: Transportation In Chgs - 01 - 15 Jun 25
A87: 1800010066 | B87: DR | C87: 45842 | D87: 256779414830 | E87: USD | F87: 142.32 | G87: 142.32 | H87: INR | I87: 12239.62 | J87: 0 | K87: 139.4736 | L87: 139.4736 | M87: 2.8464 | N87: =_xlfn.XLOOKUP(D87,$R:$R,$V:$V,0,0) -> 0 | O87: 0.02 | P87: Outbound chgs - 01 - 15 Jun 25
A88: 1800010119 | B88: DR | C88: 45842 | D88: 256779414879 | E88: USD | F88: 1663.92 | G88: 1663.92 | H88: INR | I88: 143098.23 | J88: 0 | K88: 1627.5448 | L88: 1627.5448 | M88: 36.3752 | N88: =_xlfn.XLOOKUP(D88,$R:$R,$V:$V,0,0) -> 0 | O88: 0.021861147 | P88: Transportation In Chgs - 16 - 30 JUN 25
... A211: 1800013479 | B211: DR | C211: 45935 | D211: 256779418095 | E211: USD | F211: 850 | G211: 850 | H211: INR | I211: 74962.15 | J211: 0 | K211: 825 | L211: 825 | M211: 25 | N211: =_xlfn.XLOOKUP(D211,$R:$R,$V:$V,0,0) -> 0 | O211: 0.029411765 | P211: CY Ground rent Chgs - 16 - 30 Sep 25

Sheet Sheet2
A3: Sum of USD Value | D3: Document Type | I3: Sum of USD Value | K3: Document Type
A4: Years | B4: Quarters | C4: Document Date | D4: DG | E4: DR | F4: DY | G4: DZ | I4: Years | J4: Document Date | K4: DG | L4: DR | M4: DZ | O4: Years | P4: Document Date | Q4: Sum of Debit (FC) | R4: Sum of Credit (FC)
A5: 2025 | B5: Qtr1 | C5: Feb | E5: 19803.86 | I5: 2025 | J5: Feb | L5: 19803.86 | O5: 2025 | P5: Feb | R5: 12293.713
C6: Mar | E6: 14823.47 | I6: 2025 | J6: Mar | L6: 14823.47 | O6: 2025 | P6: Mar | Q6: 40 | R6: 12720.29
B7: Qtr2 | C7: Apr | E7: 13418.32 | I7: 2025 | J7: Apr | L7: 13418.32 | O7: 2025 | P7: Apr | Q7: 80 | R7: 9784.916
C8: May | D8: -3255.46 | E8: 3894.3411 | I8: 2025 | J8: May | K8: -3255.46 | L8: 3894.3411 | O8: 2025 | P8: May | R8: 3363.296
C9: Jun | E9: 8129.42 | G9: -23431.62 | I9: 2025 | J9: Jun | L9: 8129.42 | M9: -23431.62 | O9: 2025 | P9: Jun | Q9: 27159.812 | R9: 4339.4726
B10: Qtr3 | C10: Jul | D10: -17406.03 | E10: 9114.5951 | F10: 0 | I10: 2025 | J10: Jul | K10: -17406.03 | L10: 9114.5951 | O10: 2025 | P10: Jul | Q10: 3742.0478 | R10: 7944.713
C11: Aug | D11: -4623.6206 | E11: 20154.677 | G11: -13681.56 | I11: 2025 | J11: Aug | K11: -4623.6206 | L11: 20154.677 | M11: -13681.56 | O11: 2025 | P11: Aug | Q11: 7900.4476 | R11: 9099.6876
C12: Sep | D12: -504.79 | E12: 13032.36 | F12: 0 | G12: -2932.84 | I12: 2025 | J12: Sep | K12: -504.79 | L12: 13032.36 | M12: -2932.84 | O12: 2025 | P12: Sep | Q12: 16064.434 | R12: 10508.427
B13: Qtr4 | C13: Oct | D13: -1066.62 | E13: 5834.0484 | G13: -4719.25 | I13: 2025 | J13: Oct | K13: -1066.62 | L13: 5834.0484 | M13: -4719.25 | O13: 2025 | P13: Oct | Q13: 14244.869 | R13: 6997.0412
C14: Nov | E14: 5099.432 | G14: -22495.21 | I14: 2025 | J14: Nov | L14: 5099.432 | M14: -22495.21 | O14: 2025 | P14: Nov | R14: 4796.2152
C15: Dec | E15: 2704.5547 | I15: 2025 | J15: Dec | L15: 2704.5547 | O15: 2025 | P15: Dec | Q15: 2368.203 | R15: 2517.8992
A16: 2026 | B16: Qtr1 | C16: Jan | E16: 5424.9541 | G16: -2517.26 | I16: 2026 | J16: Jan | L16: 5424.9541 | M16: -2517.26 | O16: 2026 | P16: Jan | R16: 825.474
C17: Feb | D17: -509.15 | E17: 938.8 | I17: 2026 | J17: Feb | K17: -509.15 | L17: 938.8 | Q17: =SUM(Q5:Q16) -> 71599.813 | R17: =SUM(R5:R16) -> 85191.145
K18: =SUM(K5:K17) -> -27365.671 | L18: =SUM(L5:L17) -> 122372.83 | M18: =SUM(M5:M17) -> -69777.74

Sheet Customer Data Vlookup
A1: Ref. 2 (Header) | B1: Document Date | C1: Remarks | D1: Offset Acct Name | E1: Debit (LC) | F1: Credit (LC) | G1: Cumulative Balance (LC) | H1: Debit (FC) | I1: Credit (FC) | J1: Cumulative Balance (FC) | L1: Ref. 2 (Header) | M1: Sum of Debit (FC) | N1: Sum of Credit (FC) | O1: vlookup | R1: Ref. 2 (Header) | S1: Sum of Credit (FC) | T1: vlookup
A2: 1002 | B2: 45940 | C2: A/P Credit Memo - Cancellation - VD0304 | D2: Reefer Plug In | F2: 2520.8598 | G2: -1156227.5 | I2: 28.8 | J2: -2529.6996 | L2: 1002 | N2: 28.8 | O2: =VLOOKUP(L2,'Ascendus Data'!$D$3:$F$317,3,0) -> #N/A | R2: 7360257 | S2: -58.8 | T2: #N/A
A3: 1003 | B3: 45940 | C3: A/P Credit Memo - Cancellation - VD0304 | D3: Reefer Plug In | F3: 2520.8598 | G3: -1158748.3 | I3: 28.8 | J3: -3579.6306 | L3: 1003 | N3: 28.8 | O3: =VLOOKUP(L3,'Ascendus Data'!$D$3:$F$317,3,0) -> #N/A | R3: 7360258 | S3: -58.8 | T3: #N/A
A4: 1004 | B4: 45940 | C4: A/P Credit Memo - Cancellation - VD0304 | D4: Reefer Plug In | F4: 2604.8885 | G4: -1161353.2 | I4: 29.76 | J4: -2978.5984 | L4: 1004 | N4: 29.76 | O4: =VLOOKUP(L4,'Ascendus Data'!$D$3:$F$317,3,0) -> #N/A | R4: 7360259 | S4: -60.76 | T4: #N/A
A5: 1005 | B5: 45940 | C5: A/P Credit Memo - Cancellation - VD0304 | D5: Reefer Plug In | F5: 138252.1 | G5: -1153706.6 | I5: 1579.76 | J5: -2970.4056 | L5: 1005 | N5: 1579.76 | O5: =VLOOKUP(L5,'Ascendus Data'!$D$3:$F$317,3,0) -> #N/A | R5: 7360262 | S5: -60.76 | T5: #N/A
A6: 1008 | B6: 45941 | C6: A/P Credit Memo - Cancellation - VD0304 | D6: Reefer Plug In | F6: 5250.8598 | G6: -1261566.9 | I6: 60 | J6: -3378.7422 | L6: 1008 | N6: 60 | O6: =VLOOKUP(L6,'Ascendus Data'!$D$3:$F$317,3,0) -> #N/A | R6: 246779414731 | S6: 90 | T6: #N/A
A7: 7360257 | B7: 45904 | C7: A/P Credit Memos - VD0304 | D7: Reefer Plug In | F7: -2520.8598 | G7: -1108837.9 | I7: -28.8 | J7: -4450.1742 | L7: 7360257 | N7: -87.6 | O7: =VLOOKUP(L7,'Ascendus Data'!$D$3:$F$317,3,0) -> #N/A | R7: 246779414732 | S7: 90 | T7: #N/A
A8: 7360257 | B8: 45904 | C8: A/P Credit Memos - VD0304 | D8: Reefer Plug In | F8: -5145.8598 | G8: -1251275.1 | I8: -58.8 | J8: -4526.7318 | L8: 7360258 | N8: -147.6 | O8: =VLOOKUP(L8,'Ascendus Data'!$D$3:$F$317,3,0) -> #N/A | R8: 246779414733 | S8: 90 | T8: #N/A
A9: 7360258 | B9: 45904 | C9: A/P Credit Memos - VD0304 | D9: Reefer Plug In | F9: -2520.8598 | G9: -1111358.8 | I9: -28.8 | J9: -4935.0684 | L9: 7360259 | N9: -90.52 | O9: =VLOOKUP(L9,'Ascendus Data'!$D$3:$F$317,3,0) -> #N/A | R9: 246779414734 | S9: 90 | T9: #N/A
A10: 7360258 | B10: 45904 | C10: A/P Credit Memos - VD0304 | D10: Reefer Plug In | F10: -5250.8598 | G10: -1256316 | I10: -60 | J10: -4986.7438 | L10: 7360262 | N10: -1640.52 | O10: =VLOOKUP(L10,'Ascendus Data'!$D$3:$F$317,3,0) -> #N/A | R10: 256779414888 | S10: 10.6918 | T10: #N/A
A11: 7360258 | B11: 45904 | C11: A/P Credit Memos - VD0304 | D11: Reefer Plug In | F11: -5145.8598 | G11: -1256421 | I11: -58.8 | J11: -6705.7438 | L11: 7360566 | M11: 1752.7656 | O11: =VLOOKUP(L11,'Ascendus Data'!$D$3:$F$317,3,0) -> #N/A | S11: =SUM(S2:S10) -> 131.5718 | T11: #N/A
A12: 7360259 | B12: 45904 | C12: A/P Credit Memos - VD0304 | D12: Reefer Plug In | F12: -2604.8885 | G12: -1106233 | I12: -29.76 | J12: -6780.2434 | L12: 246779410055 | N12: 408.3366 | O12: =VLOOKUP(L12,'Ascendus Data'!$D$3:$F$317,3,0) -> 416.67
A13: 7360259 | B13: 45904 | C13: A/P Credit Memos - VD0304 | D13: Reefer Plug In | F13: -5316.8885 | G13: -1245958.3 | I13: -60.76 | J13: -6760.2434 | L13: 246779410009 | N13: 1071.432 | O13: =VLOOKUP(L13,'Ascendus Data'!$D$3:$F$317,3,0) -> 1190.48
A14: 7360262 | B14: 45904 | C14: A/P Credit Memos - VD0304 | D14: Reefer Plug In | F14: -138252.1 | G14: -967980.94 | I14: -1579.76 | J14: -6809.2434 | L14: 246779410029 | N14: 1071.432 | O14: =VLOOKUP(L14,'Ascendus Data'!$D$3:$F$317,3,0) -> 1190.48
A15: 7360262 | B15: 45904 | C15: A/P Credit Memos - VD0304 | D15: Reefer Plug In | F15: -5316.8885 | G15: -1261566.9 | I15: -60.76 | J15: -6861.4382 | L15: 246779410077 | N15: 408.3366 | O15: =VLOOKUP(L15,'Ascendus Data'!$D$3:$F$317,3,0) -> 416.67
B16: 45959 | C16: Outgoing Payments - VD0304,Being payment done against USD 1752.77 ASCENDAS PANVEL FTWZ PRIVATE LIMITED, Bank ref no.- 003MISC253020092 dated-29-10-2025. | D16: YES BANK - USD | E16: 153004.1 | G16: -1092954.2 | H16: 1752.7656 | J16: -6917.5628 | L16: 246779410097 | N16: 1071.432 | O16: =VLOOKUP(L16,'Ascendus Data'!$D$3:$F$317,3,0) -> 1190.48
A17: 246779410009 | B17: 45707 | C17: A/P Invoices - VD0304 | D17: Rent - Ascendas | F17: 91693.278 | G17: -1027809.8 | I17: 1071.432 | J17: -6940.1812 | L17: 246779410123 | N17: 408.3366 | O17: =VLOOKUP(L17,'Ascendus Data'!$D$3:$F$317,3,0) -> 416.67
A18: 246779410029 | B18: 45708 | C18: A/P Invoices - VD0304 | D18: Rent - Ascendas | F18: 91693.278 | G18: -1575456.3 | I18: 1071.432 | J18: -6981.5568 | L18: 246779410140 | N18: 1071.432 | O18: =VLOOKUP(L18,'Ascendus Data'!$D$3:$F$317,3,0) -> 1190.48
A19: 246779410055 | B19: 45708 | C19: A/P Invoices - VD0304 | D19: Management Fees (Ascendas) | F19: 34945.619 | G19: -1610402 | I19: 408.3366 | J19: -7070.5996 | L19: 246779410166 | N19: 408.3366 | O19: =VLOOKUP(L19,'Ascendus Data'!$D$3:$F$317,3,0) -> 416.67
A20: 246779410077 | B20: 45708 | C20: A/P Invoices - VD0304 | D20: Management Fees (Ascendas) | F20: 34945.619 | G20: -1062755.5 | I20: 408.3366 | J20: -7166.0516 | L20: 246779410209 | N20: 1450.0748 | O20: =VLOOKUP(L20,'Ascendus Data'!$D$3:$F$317,3,0) -> 408.31
A21: 246779410097 | B21: 45708 | C21: A/P Invoices - VD0304 | D21: Rent - Ascendas | F21: 91693.278 | G21: -380845.89 | I21: 1071.432 | J21: -7196.2356 | L21: 246779410226 | N21: 1028.808 | O21: =VLOOKUP(L21,'Ascendus Data'!$D$3:$F$317,3,0) -> 1143.12
A22: 246779410123 | B22: 45708 | C22: A/P Invoices - VD0304 | D22: Management Fees (Ascendas) | F22: 34945.619 | G22: -422343.02 | I22: 408.3366 | J22: -7203.125 | L22: 246779410252 | N22: 392.0882 | O22: =VLOOKUP(L22,'Ascendus Data'!$D$3:$F$317,3,0) -> 400.09
A23: 246779410140 | B23: 45708 | C23: A/P Invoices - VD0304 | D23: Rent - Ascendas | F23: 91693.278 | G23: -797615.56 | I23: 1071.432 | J23: -7210.2496 | L23: 246779410276 | N23: 1071.432 | O23: =VLOOKUP(L23,'Ascendus Data'!$D$3:$F$317,3,0) -> 1190.48
A24: 246779410166 | B24: 45708 | C24: A/P Invoices - VD0304 | D24: Management Fees (Ascendas) | F24: 34945.619 | G24: -705922.29 | I24: 408.3366 | J24: -7220.9414 | L24: 246779410308 | N24: 408.3366 | O24: =VLOOKUP(L24,'Ascendus Data'!$D$3:$F$317,3,0) -> 416.67
A25: 246779410209 | B25: 45708 | C25: A/P Invoices - VD0304 | D25: Rent - Ascendas | F25: 89852.772 | G25: -306344.44 | I25: 1049.931 | J25: -7223.411 | L25: 246779410324 | N25: 1575 | O25: =VLOOKUP(L25,'Ascendus Data'!$D$3:$F$317,3,0) -> 1750
A26: 246779410209 | B26: 45708 | C26: A/P Invoices - VD0304 | D26: Management Fees (Ascendas) | F26: 34244.17 | G26: -254207 | I26: 400.1438 | J26: -7255.1434 | L26: 246779410376 | N26: 640.215 | O26: =VLOOKUP(L26,'Ascendus Data'!$D$3:$F$317,3,0) -> 711.35
A27: 246779410226 | B27: 45708 | C27: A/P Invoices - VD0304 | D27: Rent - Ascendas | F27: 88045.21 | G27: -885660.77 | I27: 1028.808 | J27: -7298.2634 | L27: 246779410401 | N27: 1169.064 | O27: =VLOOKUP(L27,'Ascendus Data'!$D$3:$F$317,3,0) -> 1298.96
A28: 246779410252 | B28: 45708 | C28: A/P Invoices - VD0304 | D28: Management Fees (Ascendas) | F28: 33554.702 | G28: -670976.67 | I28: 392.0882 | J28: -7363.4334 | L28: 246779410425 | N28: 1518.489 | O28: =VLOOKUP(L28,'Ascendus Data'!$D$3:$F$317,3,0) -> 1687.21
... A35: 246779410871 | B35: 45722 | C35: A/P Invoices - VD0304 | D35: Rent - Ascendas | F35: 3274.0058 | G35: -1778306.5 | I35: 38.259 | J35: -10348.923 | L35: 246779411515 | N35: 98 | O35: =VLOOKUP(L35,'Ascendus Data'!$D$3:$F$317,3,0) -> 100
A36: 246779410871 | B36: 45821 | C36: Being $3.4008 less paid in this bill because in summary sheet 2% tds deduscted instead of 10% | D36: HDFC Bank - INR | E36: 290.9044 | G36: -675841.21 | H36: 3.4008 | J36: -10858.69 | L36: 246779411621 | N36: 435.1592 | O36: =VLOOKUP(L36,'Ascendus Data'!$D$3:$F$317,3,0) -> 444.04
A37: 246779410893 | B37: 45722 | C37: A/P Invoices - VD0304 | D37: Rent - Ascendas | F37: 13647.064 | G37: -1775032.5 | I37: 159.462 | J37: -10863.002 | L37: 246779411760 | N37: 509.7666 | O37: =VLOOKUP(L37,'Ascendus Data'!$D$3:$F$317,3,0) -> 520.17
A38: 246779411279 | B38: 45729 | C38: A/P Invoices - VD0304 | D38: Vos Miscellaneous Charges | F38: 2935.3 | G38: -1613337.3 | I38: 34.3 | J38: -10938.501 | L38: 246779411937 | N38: 7.1246 | O38: =VLOOKUP(L38,'Ascendus Data'!$D$3:$F$317,3,0) -> 7.27
A39: 246779411301 | B39: 45729 | C39: A/P Invoices - VD0304 | D39: Vos Miscellaneous Charges | F39: 7129.3 | G39: -1329744.4 | I39: 83.3 | J39: -12009.933 | L39: 246779411938 | N39: 52.1948 | O39: =VLOOKUP(L39,'Ascendus Data'!$D$3:$F$317,3,0) -> 53.26
A40: 246779411315 | B40: 45729 | C40: A/P Invoices - VD0304 | D40: Vos Miscellaneous Charges | F40: 2935.3 | G40: -1332679.7 | I40: 34.3 | J40: -12418.27 | L40: 246779411939 | N40: 22.6184 | O40: =VLOOKUP(L40,'Ascendus Data'!$D$3:$F$317,3,0) -> 23.08
A41: 246779411449 | B41: 45730 | C41: A/P Invoices - VD0304 | D41: Vos Miscellaneous Charges | F41: 79318.285 | G41: -1142073.7 | I41: 926.835 | J41: -13345.105 | L41: 246779411940 | N41: 51.6754 | O41: =VLOOKUP(L41,'Ascendus Data'!$D$3:$F$317,3,0) -> 52.73
A42: 246779411515 | B42: 45730 | C42: A/P Invoices - VD0304 | D42: Vos Miscellaneous Charges | F42: 8387 | G42: -1815791.5 | I42: 98 | J42: -14271.94 | L42: 246779411941 | N42: 74.4996 | O42: =VLOOKUP(L42,'Ascendus Data'!$D$3:$F$317,3,0) -> 76.02
A43: 246779411621 | B43: 45733 | C43: A/P Invoices - VD0304 | D43: Vos Miscellaneous Charges | F43: 37240.943 | G43: -1322615.1 | I43: 435.1592 | J43: -14464.784 | L43: 246779412066 | N43: 65.17 | O43: =VLOOKUP(L43,'Ascendus Data'!$D$3:$F$317,3,0) -> 66.5
A44: 246779411760 | B44: 45733 | C44: A/P Invoices - VD0304 | D44: Vos Miscellaneous Charges | F44: 43626.149 | G44: -929286.92 | I44: 509.7666 | J44: -15019.572 | L44: 246779412116 | N44: 98 | O44: =VLOOKUP(L44,'Ascendus Data'!$D$3:$F$317,3,0) -> 100
A45: 246779411937 | B45: 45733 | C45: A/P Invoices - VD0304 | D45: Vos Miscellaneous Charges | F45: 610.1666 | G45: -592005 | I45: 7.1246 | J45: -15454.731 | L45: 246779412119 | N45: 98 | O45: =VLOOKUP(L45,'Ascendus Data'!$D$3:$F$317,3,0) -> 100
A46: 246779411938 | B46: 45733 | C46: A/P Invoices - VD0304 | D46: Vos Miscellaneous Charges | F46: 4466.9908 | G46: -587201.84 | I46: 52.1948 | J46: -15538.031 | L46: 246779412121 | N46: 98 | O46: =VLOOKUP(L46,'Ascendus Data'!$D$3:$F$317,3,0) -> 100
A47: 246779411939 | B47: 45733 | C47: A/P Invoices - VD0304 | D47: Vos Miscellaneous Charges | F47: 1935.1864 | G47: -593940.19 | I47: 22.6184 | J47: -15572.331 | L47: 246779412238 | N47: 0 | O47: =VLOOKUP(L47,'Ascendus Data'!$D$3:$F$317,3,0) -> 945.75
A48: 246779411940 | B48: 45733 | C48: A/P Invoices - VD0304 | D48: Vos Miscellaneous Charges | F48: 4422.6334 | G48: -426765.65 | I48: 51.6754 | J48: -15621.331 | L48: 246779412981 | N48: 1033.767 | O48: =VLOOKUP(L48,'Ascendus Data'!$D$3:$F$317,3,0) -> 1148.63
... A77: 256779414731 | B77: 45827 | C77: A/P Invoices - VD0304 | D77: Rent - Ascendas | F77: 7725 | G77: -1018413.6 | I77: 90 | J77: -26911.76 | L77: 246779414890 | N77: 43.12 | O77: =VLOOKUP(L77,'Ascendus Data'!$D$3:$F$317,3,0) -> 44
A78: 256779414732 | B78: 45827 | C78: A/P Invoices - VD0304 | D78: Rent - Ascendas | F78: 7725 | G78: -1010688.6 | I78: 90 | J78: -26967.571 | L78: 256779410006 | M78: 20 | N78: 1670 | O78: =VLOOKUP(L78,'Ascendus Data'!$D$3:$F$317,3,0) -> 1700
A79: 256779414733 | B79: 45827 | C79: A/P Invoices - VD0304 | D79: Rent - Ascendas | F79: 7725 | G79: -1002963.6 | I79: 90 | J79: -23438.015 | L79: 256779410012 | M79: 20 | N79: 1719 | O79: =VLOOKUP(L79,'Ascendus Data'!$D$3:$F$317,3,0) -> 1750
A80: 256779414734 | B80: 45827 | C80: A/P Invoices - VD0304 | D80: Rent - Ascendas | F80: 7725 | G80: -995238.64 | I80: 90 | J80: -20270.54 | L80: 256779410015 | M80: 20 | N80: 1670 | O80: =VLOOKUP(L80,'Ascendus Data'!$D$3:$F$317,3,0) -> 1700
A81: 246779414735 | B81: 45736 | C81: A/P Invoices - VD0304 | D81: Handeling & Agency Charges | F81: 8168.492 | G81: -613269.67 | I81: 95.452 | J81: -16585.337 | L81: 256779410136 | N81: 9.653 | O81: =VLOOKUP(L81,'Ascendus Data'!$D$3:$F$317,3,0) -> 9.85
A82: 246779414886 | B82: 45736 | C82: A/P Invoices - VD0304 | D82: Handeling & Agency Charges | F82: 2582.864 | G82: -615852.53 | I82: 30.184 | J82: -17035.859 | L82: 256779410224 | M82: 20 | N82: 1719 | O82: =VLOOKUP(L82,'Ascendus Data'!$D$3:$F$317,3,0) -> 1750
A83: 246779414887 | B83: 45736 | C83: A/P Invoices - VD0304 | D83: Handeling & Agency Charges | F83: 610.1666 | G83: -617052.33 | I83: 7.1246 | J83: -17215.859 | L83: 256779411152 | N83: 161.09 | O83: =VLOOKUP(L83,'Ascendus Data'!$D$3:$F$317,3,0) -> 164.38
A84: 246779414889 | B84: 45736 | C84: A/P Invoices - VD0304 | D84: Handeling & Agency Charges | F84: 211.6616 | G84: -618178.67 | I84: 2.4696 | J84: -17313.859 | L84: 256779411153 | N84: 26.01 | O84: =VLOOKUP(L84,'Ascendus Data'!$D$3:$F$317,3,0) -> 26.54
A85: 246779414890 | B85: 45736 | C85: A/P Invoices - VD0304 | D85: Handeling & Agency Charges | F85: 3690.52 | G85: -624585.27 | I85: 43.12 | J85: -17411.859 | L85: 256779411154 | N85: 82.57 | O85: =VLOOKUP(L85,'Ascendus Data'!$D$3:$F$317,3,0) -> 84.26
A86: 256779410006 | B86: 45750 | C86: A/P Invoices - VD0304 | D86: Rent - Ascendas | F86: 143269 | G86: -1819439.9 | I86: 1670 | J86: -17805.074 | L86: 256779411155 | N86: 36.16 | O86: =VLOOKUP(L86,'Ascendus Data'!$D$3:$F$317,3,0) -> 36.9
A87: 256779410006 | B87: 45750 | C87: Being TDS entry passed for the ground rent charges against bill no. 256779410006 dated 03-04-2025. | D87: Tds Payable- 94Ib - Rent | E87: 1715.8 | G87: -1817724.1 | H87: 20 | J87: -17903.074 | L87: 256779411156 | N87: 19.83 | O87: =VLOOKUP(L87,'Ascendus Data'!$D$3:$F$317,3,0) -> 20.23
A88: 256779410012 | B88: 45750 | C88: A/P Invoices - VD0304 | D88: Rent - Ascendas | F88: 147473.5 | G88: -1965197.6 | I88: 1719 | J88: -18302.797 | L88: 256779411157 | N88: 113.99 | O88: =VLOOKUP(L88,'Ascendus Data'!$D$3:$F$317,3,0) -> 116.32
A89: 256779410012 | B89: 45750 | C89: BEing Ground Rent Charges tds booked against bill no 256779410012 dated 03-04-2025. | D89: Tds Payable- 94Ib - Rent | E89: 1715.8 | G89: -2105035 | H89: 20 | J89: -19351.63 | L89: 256779411565 | N89: 21.56 | O89: =VLOOKUP(L89,'Ascendus Data'!$D$3:$F$317,3,0) -> 22
A90: 256779410015 | B90: 45750 | C90: A/P Invoices - VD0304 | D90: Rent - Ascendas | F90: 143269 | G90: -2108466.6 | I90: 1670 | J90: -19449.63 | L90: 256779411566 | N90: 4.31 | O90: =VLOOKUP(L90,'Ascendus Data'!$D$3:$F$317,3,0) -> 4.4
A91: 256779410015 | B91: 45750 | C91: Being Ground rent charges tds booked against bill no. 256779410015 dated 03-04-2025. | D91: Tds Payable- 94Ib - Rent | E91: 1715.8 | G91: -2106750.8 | H91: 20 | J91: -19488.379 | L91: 256779411567 | N91: 5.72 | O91: =VLOOKUP(L91,'Ascendus Data'!$D$3:$F$317,3,0) -> 5.84
A92: 256779410136 | B92: 45750 | C92: A/P Invoices - VD0304 | D92: Inbound & Outbound Handling | F92: 838.374 | G92: -896611.71 | I92: 9.653 | J92: -19493.21 | L92: 256779411568 | N92: 0.78 | O92: =VLOOKUP(L92,'Ascendus Data'!$D$3:$F$317,3,0) -> 0.8
A93: 256779410224 | B93: 45750 | C93: A/P Invoices - VD0304 | D93: Ground Rent (Container) | F93: 146940 | G93: -2290181.3 | I93: 1719 | J93: -19578.666 | L93: 256779411569 | N93: 13.57 | O93: =VLOOKUP(L93,'Ascendus Data'!$D$3:$F$317,3,0) -> 13.85
A94: 256779410224 | B94: 45750 | C94: Being tds deduction for rent against bill no.-256779410224 dated-03-04-2025. | D94: Tds Payable- 94Ib - Rent | E94: 1709.6 | G94: -2288471.7 | H94: 20 | J94: -21248.666 | L94: 256779411570 | N94: 17.79 | O94: =VLOOKUP(L94,'Ascendus Data'!$D$3:$F$317,3,0) -> 18.15
A95: 256779411152 | B95: 45762 | C95: A/P Invoices - VD0304 | D95: Empty Return - Outward | F95: 13942.089 | G95: -736955.3 | I95: 161.09 | J95: -21228.666 | L95: 256779411571 | N95: 20.93 | O95: =VLOOKUP(L95,'Ascendus Data'!$D$3:$F$317,3,0) -> 21.36
A96: 256779411153 | B96: 45762 | C96: A/P Invoices - VD0304 | D96: LCL CHARGES | F96: 2251.037 | G96: -739206.34 | I96: 26.01 | J96: -22947.666 | L96: 256779411572 | N96: 1.93 | O96: =VLOOKUP(L96,'Ascendus Data'!$D$3:$F$317,3,0) -> 1.97
A97: 256779411154 | B97: 45762 | C97: A/P Invoices - VD0304 | D97: LCL CHARGES | F97: 7146.703 | G97: -746353.04 | I97: 82.57 | J97: -24617.666 | L97: 256779411573 | N97: 23.73 | O97: =VLOOKUP(L97,'Ascendus Data'!$D$3:$F$317,3,0) -> 24.21
A98: 256779411155 | B98: 45762 | C98: A/P Invoices - VD0304 | D98: Inbound & Outbound Handling | F98: 3129.695 | G98: -749482.73 | I98: 36.16 | J98: -24597.666 | L98: 256779411574 | N98: 14.41 | O98: =VLOOKUP(L98,'Ascendus Data'!$D$3:$F$317,3,0) -> 14.7
A99: 256779411156 | B99: 45762 | C99: A/P Invoices - VD0304 | D99: Inbound & Outbound Handling | F99: 1715.9065 | G99: -751198.64 | I99: 19.83 | J99: -24577.666 | L99: 256779411575 | N99: 21.903 | O99: =VLOOKUP(L99,'Ascendus Data'!$D$3:$F$317,3,0) -> 22.35
A100: 256779411157 | B100: 45762 | C100: A/P Invoices - VD0304 | D100: Inbound & Outbound Handling | F100: 9866.496 | G100: -761065.14 | I100: 113.99 | J100: -12028.307 | L100: 256779411576 | N100: 21.09 | O100: =VLOOKUP(L100,'Ascendus Data'!$D$3:$F$317,3,0) -> 21.52
A101: 256779411565 | B101: 45762 | C101: A/P Invoices - VD0304 | D101: Inbound & Outbound Handling | F101: 1866.1 | G101: -762931.24 | I101: 21.56 | J101: -12028.307 | L101: 256779411577 | N101: 1.51 | O101: =VLOOKUP(L101,'Ascendus Data'!$D$3:$F$317,3,0) -> 1.54
A102: 256779411566 | B102: 45762 | C102: A/P Invoices - VD0304 | D102: Inbound & Outbound Handling | F102: 372.82 | G102: -763304.06 | I102: 4.31 | J102: -12028.307 | L102: 256779411578 | N102: 7.05 | O102: =VLOOKUP(L102,'Ascendus Data'!$D$3:$F$317,3,0) -> 7.19
A103: 256779411567 | B103: 45762 | C103: A/P Invoices - VD0304 | D103: Inbound & Outbound Handling | F103: 495.452 | G103: -763799.51 | I103: 5.72 | J103: -7900.3518 | L103: 256779411579 | N103: 4.75 | O103: =VLOOKUP(L103,'Ascendus Data'!$D$3:$F$317,3,0) -> 4.85
A104: 256779411568 | B104: 45762 | C104: A/P Invoices - VD0304 | D104: Inbound & Outbound Handling | F104: 68.24 | G104: -763867.75 | I104: 0.78 | J104: -7896.951 | L104: 256779411580 | N104: 21.32 | O104: =VLOOKUP(L104,'Ascendus Data'!$D$3:$F$317,3,0) -> 21.76
A105: 256779411569 | B105: 45762 | C105: A/P Invoices - VD0304 | D105: Inbound & Outbound Handling | F105: 1174.7175 | G105: -765042.47 | I105: 13.57 | J105: -12024.906 | L105: 256779411581 | N105: 2.16 | O105: =VLOOKUP(L105,'Ascendus Data'!$D$3:$F$317,3,0) -> 2.2
A106: 256779411570 | B106: 45762 | C106: A/P Invoices - VD0304 | D106: Inbound & Outbound Handling | F106: 1539.8825 | G106: -766582.35 | I106: 17.79 | J106: -7800.0888 | L106: 256779411582 | N106: 1.09 | O106: =VLOOKUP(L106,'Ascendus Data'!$D$3:$F$317,3,0) -> 1.11
... A224: 256779418621 | B224: 45950 | C224: A/P Invoices - VD0304 | D224: Ground Rent (Container) | F224: 7937 | G224: -337748.42 | I224: 90 | J224: -14419.828 | L224: 256779419992 | N224: 121.6278 | O224: =VLOOKUP(L224,'Ascendus Data'!$D$3:$F$317,3,0) -> 124.11
A225: 256779418633 | B225: 45950 | C225: A/P Invoices - VD0304 | D225: Vos Miscellaneous Charges | F225: 3024.65 | G225: -340773.07 | I225: 34.3 | J225: -14359.828 | L225: 256779421715 | M225: 2092.293 | O225: =VLOOKUP(L225,'Ascendus Data'!$D$3:$F$317,3,0) -> -2324.77
A226: 256779418663 | B226: 45950 | C226: A/P Invoices - VD0304 | D226: Transportation (Inbound) | F226: 25400.159 | G226: -366173.22 | I226: 288.0122 | J226: -14419.828 | L226: 256779440052 | N226: 822.093 | O226: =VLOOKUP(L226,'Ascendus Data'!$D$3:$F$317,3,0) -> 846.77
A227: 256779418703 | B227: 45950 | C227: A/P Invoices - VD0304 | D227: Inbound & Outbound Handling | F227: 849.9077 | G227: -420917.84 | I227: 9.6334 | J227: -14361.028 | L227: 256779440081 | N227: 3.381 | O227: =VLOOKUP(L227,'Ascendus Data'!$D$3:$F$317,3,0) -> 3.45
A228: 256779418775 | B228: 45966 | C228: A/P Invoices - VD0304 | D228: Rent - Ascendas | F228: 89996.16 | G228: -593079.99 | I228: 1022.688 | J228: -14302.228 | L228: (blank) | M228: 67671.354 | N228: 0 | O228: =VLOOKUP(L228,'Ascendus Data'!$D$3:$F$317,3,0) -> #N/A
A229: 256779418776 | B229: 45966 | C229: A/P Invoices - VD0304 | D229: Management Fees (Ascendas) | F229: 34299.828 | G229: -627379.82 | I229: 389.7558 | J229: -14241.468 | M229: =SUBTOTAL(9,M2:M228) -> 71596.412 | N229: =SUBTOTAL(9,N2:N228) -> 85191.145 | O229: =SUBTOTAL(9,O2:O228) -> #N/A
A230: 256779418820 | B230: 45966 | C230: A/P Invoices - VD0304 | D230: Vos Miscellaneous Charges | F230: 30281.44 | G230: -420067.94 | I230: 344.1074 | J230: -12488.702
A231: 256779418876 | B231: 45966 | C231: A/P Invoices - VD0304 | D231: Rent - Ascendas | F231: 59082.889 | G231: -1485534 | I231: 671.373 | J231: -13509.222
A232: 256779419077 | B232: 45966 | C232: A/P Invoices - VD0304 | D232: Ground Rent (Container) | F232: 7920 | G232: -434091.83 | I232: 90 | J232: -13898.155
A233: 256779419077 | B233: 45966 | C233: A/P Invoices - VD0304 | D233: Reefer Plug In | F233: 68992 | G233: -503083.83 | I233: 784 | J233: -13988.155
A234: 256779419130 | B234: 45964 | C234: A/P Invoices - VD0304 | D234: LCL CHARGES | F234: 4545.48 | G234: -426171.83 | I234: 51.6558 | J234: -14723.155
A235: 256779419174 | B235: 45966 | C235: A/P Invoices - VD0304 | D235: Inbound & Outbound Handling | F235: 708.5078 | G235: -421626.35 | I235: 8.0458 | J235: -14856.905
A236: 256779419200 | B236: 45966 | C236: A/P Invoices - VD0304 | D236: Vos Miscellaneous Charges | F236: 13131.454 | G236: -1186951.7 | I236: 149.2148 | J236: -12866.965
A237: 256779419232 | B237: 45966 | C237: A/P Invoices - VD0304 | D237: Vos Miscellaneous Charges | F237: 2233.4737 | G237: -1173820.3 | I237: 25.1762 | J237: -2364.8022
A238: 256779419558 | B238: 45981 | C238: A/P Invoices - VD0304 | D238: Ground Rent (Container) | F238: 7920.339 | G238: -886072.43 | I238: 90 | J238: -2392.3892
A239: 256779419558 | B239: 45981 | C239: A/P Invoices - VD0304 | D239: Reefer Plug In | F239: 64682.543 | G239: -950754.97 | I239: 735 | J239: -2717.2592
A240: 256779419590 | B240: 45981 | C240: A/P Invoices - VD0304 | D240: Inbound & Outbound Handling | F240: 28590.124 | G240: -748463.94 | I240: 324.87 | J240: -3004.6932
A241: 256779419630 | B241: 45981 | C241: A/P Invoices - VD0304 | D241: Inbound & Outbound Handling | F241: 9709.4216 | G241: -637089.24 | I241: 110.3284 | J241: -3739.6932
... A248: 256779419992 | B248: 45997 | C248: A/P Invoices - VD0304 | D248: Vos Miscellaneous Charges | F248: 10788.574 | G248: -1197740.3 | I248: 121.6278 | J248: -4773.5018
A249: 256779421715 | B249: 45883 | C249: Being debit note recieved from Ascendas Panvel FTWZ Private Limited against debit note no-256779421715 dated-14-08-2025. | D249: Rent - Ascendas | E249: 179999.97 | G249: -1096682.8 | H249: 2092.293 | J249: -4781.5476
A250: 256779440052 | B250: 46027 | C250: A/P Invoices - VD0304 | D250: Ground Rent (Container) | F250: 7902.9098 | G250: -1104585.7 | I250: 87.093 | J250: -4833.2034
A251: 256779440052 | B251: 46027 | C251: A/P Invoices - VD0304 | D251: Reefer Plug In | F251: 66694 | G251: -1171279.7 | I251: 735 | J251: -4923.2034
A252: 256779440081 | B252: 46027 | C252: A/P Invoices - VD0304 | D252: Inbound & Outbound Handling | F252: 307.053 | G252: -1171586.8 | I252: 3.381 | J252: -5707.2034
B253: 45736 | C253: Being TDS deduction on 246779413797 ascendas | D253: Tds Payable- 94Ib - Rent | E253: 1711.6 | G253: -578541.85 | H253: 20 | J253: -6729.8914
B254: 45736 | C254: Being TDS deduction on 246779413797 ascendas | D254: Tds Payable- 94Ib - Rent | F254: 1711.6 | G254: -635710.36 | I254: 20 | J254: -7119.6472
B255: 45736 | C255: Being TDS deduction on 246779413797 ascendas(Reversal) - 7619 | D255: Tds Payable- 94Ib - Rent | E255: -1711.6 | G255: -637421.96 | H255: -20 | J255: -7229.9756
B256: 45736 | C256: Being TDS deduction on 246779413808 ascendas | D256: Tds Payable- 94Ib - Rent | E256: 1711.6 | G256: -1471183.1 | H256: 20 | J256: -7339.1476
B257: 45736 | C257: Being TDS deduction on 246779413797 ascendas | D257: Tds Payable- 94Ib - Rent | E257: 1711.6 | G257: -1854196.3 | H257: 20 | J257: -7429.1476
...

Sheet Sheet3
A3: Years | B3: Quarters | C3: Document Date | D3: Sum of Debit (FC) | E3: Sum of Credit (FC)
A4: 2025 | B4: Qtr1 | C4: Feb | E4: 12293.713
C5: Mar | D5: 40 | E5: 12720.29
B6: Qtr2 | C6: Apr | D6: 80 | E6: 9784.916
C7: May | E7: 3363.296
C8: Jun | D8: 27159.812 | E8: 4339.4726
B9: Qtr3 | C9: Jul | D9: 3742.0478 | E9: 7944.713
C10: Aug | D10: 7900.4476 | E10: 9099.6876
C11: Sep | D11: 16064.434 | E11: 10508.427
B12: Qtr4 | C12: Oct | D12: 14244.869 | E12: 6997.0412
C13: Nov | E13: 4796.2152
C14: Dec | D14: 2368.203 | E14: 2517.8992
A15: 2026 | B15: Qtr1 | C15: Jan | E15: 825.474

Sheet Updated Ascendus ledger
A1: Cleared Item | B1: Company Code | C1: Customer | D1: Customer Account: Name 1 | E1: Fiscal Year | F1: Posting period | G1: Posting Date | H1: Document Number | I1: Document Type | J1: Document Date | K1: Entry Date | L1: Document Header Text | M1: Reference | N1: G/L Account | O1: G/L Account: Short Text | P1: Special G/L Ind. | Q1: Posting Key | R1: Document Currency Key | S1: Document Currency Value | T1: Company Code Currency Key | U1: Company Code Currency Value | V1: Tax Code | W1: Profit Center | X1: Trading Partner No. | Y1: Assignment | Z1: Item | AG1: Text | AH1: Reference Key 1 | AI1: Reference Key 2 | AJ1: Reference Key 3 | AK1: Baseline Payment Dte | AL1: Clearing Date | AM1: Clearing Document
A2: Selected | B2: 6779 | C2: 100222372 | D2: SHAH TC GLOBAL EXIM LLP | E2: 2025 | F2: 9 | G2: 45902 | H2: 1400001110 | I2: DY | J2: 45902 | K2: 45902 | N2: 212100 | O2: Trade Debtors (Ctrl) | Q2: 08 | R2: INR | S2: 6940.7917 | T2: INR | U2: 595243.31 | W2: 6779224500 | Z2: 1 | AD2: =_xlfn.XLOOKUP(M2,'Customer Data Vlookup'!$R:$R,'Customer Data Vlookup'!$S:$S,,0) -> #N/A | AK2: 45902 | AL2: 45902 | AM2: 1400001110
A3: Selected | B3: 6779 | C3: 100222372 | D3: SHAH TC GLOBAL EXIM LLP | E3: 2025 | F3: 9 | G3: 45902 | H3: 1400001110 | I3: DY | J3: 45902 | K3: 45902 | N3: 212100 | O3: Trade Debtors (Ctrl) | Q3: 15 | R3: INR | S3: -6940.7917 | T3: INR | U3: -599760.56 | W3: 6779224500 | Z3: 2 | AD3: =_xlfn.XLOOKUP(M3,'Customer Data Vlookup'!$R:$R,'Customer Data Vlookup'!$S:$S,,0) -> #N/A | AK3: 45902 | AL3: 45902 | AM3: 1400001110
A4: Selected | B4: 6779 | C4: 100222372 | D4: SHAH TC GLOBAL EXIM LLP | E4: 2025 | F4: 8 | G4: 45887 | H4: 1400000854 | I4: DZ | J4: 45887 | K4: 45887 | N4: 212100 | O4: Trade Debtors (Ctrl) | Q4: 15 | R4: USD | S4: -700.45 | T4: INR | U4: -60884.42 | Z4: 4 | AD4: =_xlfn.XLOOKUP(M4,'Customer Data Vlookup'!$R:$R,'Customer Data Vlookup'!$S:$S,,0) -> #N/A | AK4: 45887 | AL4: 45887 | AM4: 1400000854
A5: Not Selected | B5: 6779 | C5: 100222372 | D5: SHAH TC GLOBAL EXIM LLP | E5: 2025 | F5: 10 | G5: 45931 | H5: 1400001231 | I5: DZ | J5: 45931 | K5: 45925 | L5: 0758767253FS | N5: 212100 | O5: Trade Debtors (Ctrl) | Q5: 15 | R5: USD | S5: -4719.25 | T5: INR | U5: -413002 | W5: 6779220000 | Z5: 2 | AD5: =_xlfn.XLOOKUP(M5,'Customer Data Vlookup'!$R:$R,'Customer Data Vlookup'!$S:$S,,0) -> #N/A | AK5: 45931
A6: Not Selected | B6: 6779 | C6: 100222372 | D6: SHAH TC GLOBAL EXIM LLP | E6: 2025 | F6: 8 | G6: 45890 | H6: 1400000977 | I6: DZ | J6: 45890 | K6: 45890 | L6: T54SWIC264904 | N6: 212100 | O6: Trade Debtors (Ctrl) | Q6: 15 | R6: USD | S6: -3663.7 | T6: INR | U6: -313212.57 | W6: 6779220000 | Z6: 2 | AD6: =_xlfn.XLOOKUP(M6,'Customer Data Vlookup'!$R:$R,'Customer Data Vlookup'!$S:$S,,0) -> #N/A | AK6: 45890
A7: Selected | B7: 6779 | C7: 100222372 | D7: SHAH TC GLOBAL EXIM LLP | E7: 2025 | F7: 7 | G7: 45839 | H7: 1400000126 | I7: DZ | J7: 45832 | K7: 45832 | L7: 1810304156FS | N7: 212100 | O7: Trade Debtors (Ctrl) | Q7: 15 | R7: USD | S7: -3663.7 | T7: INR | U7: -3663.7 | W7: 6779220000 | Z7: 2 | AD7: =_xlfn.XLOOKUP(M7,'Customer Data Vlookup'!$R:$R,'Customer Data Vlookup'!$S:$S,,0) -> #N/A | AK7: 45832 | AL7: 45839 | AM7: 1400000149
A8: Not Selected | B8: 6779 | C8: 100222372 | D8: SHAH TC GLOBAL EXIM LLP | E8: 2025 | F8: 7 | G8: 45839 | H8: 1400000128 | I8: DZ | J8: 45832 | K8: 45832 | L8: 8113643156FS | N8: 212100 | O8: Trade Debtors (Ctrl) | Q8: 15 | R8: USD | S8: -3145.98 | T8: INR | U8: -3145.98 | W8: 6779220000 | Z8: 2 | AD8: =_xlfn.XLOOKUP(M8,'Customer Data Vlookup'!$R:$R,'Customer Data Vlookup'!$S:$S,,0) -> #N/A | AK8: 45832
A9: Not Selected | B9: 6779 | C9: 100222372 | D9: SHAH TC GLOBAL EXIM LLP | E9: 2025 | F9: 7 | G9: 45839 | H9: 1400000133 | I9: DZ | J9: 45832 | K9: 45832 | L9: 1171852164FS | N9: 212100 | O9: Trade Debtors (Ctrl) | Q9: 15 | R9: USD | S9: -12549.36 | T9: INR | U9: -12549.36 | W9: 6779220000 | Z9: 2 | AD9: =_xlfn.XLOOKUP(M9,'Customer Data Vlookup'!$R:$R,'Customer Data Vlookup'!$S:$S,,0) -> #N/A | AK9: 45832
A10: Not Selected | B10: 6779 | C10: 100222372 | D10: SHAH TC GLOBAL EXIM LLP | E10: 2025 | F10: 7 | G10: 45839 | H10: 1400000134 | I10: DZ | J10: 45832 | K10: 45832 | L10: 4989824164FS | N10: 212100 | O10: Trade Debtors (Ctrl) | Q10: 15 | R10: USD | S10: -4228.22 | T10: INR | U10: -4228.22 | W10: 6779220000 | Z10: 2 | AD10: =_xlfn.XLOOKUP(M10,'Customer Data Vlookup'!$R:$R,'Customer Data Vlookup'!$S:$S,,0) -> #N/A | AK10: 45832
A11: Selected | B11: 6779 | C11: 100222372 | D11: SHAH TC GLOBAL EXIM LLP | E11: 2025 | F11: 7 | G11: 45839 | H11: 1400000149 | I11: DZ | J11: 45832 | K11: 45835 | L11: 1810304156FS | N11: 212100 | O11: Trade Debtors (Ctrl) | Q11: 05 | R11: USD | S11: 3663.7 | T11: INR | U11: 3663.7 | W11: 6779220000 | Z11: 2 | AD11: =_xlfn.XLOOKUP(M11,'Customer Data Vlookup'!$R:$R,'Customer Data Vlookup'!$S:$S,,0) -> #N/A | AK11: 45832 | AL11: 45839 | AM11: 1400000149
A12: Selected | B12: 6779 | C12: 100222372 | D12: SHAH TC GLOBAL EXIM LLP | E12: 2025 | F12: 8 | G12: 45887 | H12: 1400000854 | I12: DZ | J12: 45887 | K12: 45887 | N12: 212100 | O12: Trade Debtors (Ctrl) | Q12: 15 | R12: USD | S12: -4437.9 | T12: INR | U12: -383425.92 | W12: 6779224500 | Z12: 3 | AD12: =_xlfn.XLOOKUP(M12,'Customer Data Vlookup'!$R:$R,'Customer Data Vlookup'!$S:$S,,0) -> #N/A | AK12: 45887 | AL12: 45887 | AM12: 1400000854
A13: Selected | B13: 6779 | C13: 100222372 | D13: SHAH TC GLOBAL EXIM LLP | E13: 2025 | F13: 8 | G13: 45888 | H13: 1400000864 | I13: DZ | J13: 45888 | K13: 45888 | L13: 8681446219FS | N13: 212100 | O13: Trade Debtors (Ctrl) | Q13: 15 | R13: USD | S13: -1102.02 | T13: INR | U13: -94695.18 | W13: 6779224500 | Z13: 4 | AD13: =_xlfn.XLOOKUP(M13,'Customer Data Vlookup'!$R:$R,'Customer Data Vlookup'!$S:$S,,0) -> #N/A | AG13: 8681446219FS | AK13: 45888 | AL13: 45888 | AM13: 1400000864
A14: Not Selected | B14: 6779 | C14: 100222372 | D14: SHAH TC GLOBAL EXIM LLP | E14: 2025 | F14: 9 | G14: 45924 | H14: 1400001221 | I14: DZ | J14: 45924 | K14: 45924 | L14: 4568362253FS | N14: 212100 | O14: Trade Debtors (Ctrl) | Q14: 15 | R14: USD | S14: -2932.84 | T14: INR | U14: -256665.53 | W14: 6779220000 | Z14: 2 | AD14: =_xlfn.XLOOKUP(M14,'Customer Data Vlookup'!$R:$R,'Customer Data Vlookup'!$S:$S,,0) -> #N/A | AK14: 45924
A15: Not Selected | B15: 6779 | C15: 100222372 | D15: SHAH TC GLOBAL EXIM LLP | E15: 2025 | F15: 11 | G15: 45964 | H15: 1400001598 | I15: DZ | J15: 45964 | K15: 45964 | L15: T54SWIC278972 | N15: 212100 | O15: Trade Debtors (Ctrl) | Q15: 15 | R15: USD | S15: -1731.27 | T15: INR | U15: -152682.03 | W15: 6779220000 | Z15: 2 | AD15: =_xlfn.XLOOKUP(M15,'Customer Data Vlookup'!$R:$R,'Customer Data Vlookup'!$S:$S,,0) -> #N/A | AK15: 45964
A16: Not Selected | B16: 6779 | C16: 100222372 | D16: SHAH TC GLOBAL EXIM LLP | E16: 2025 | F16: 11 | G16: 45972 | H16: 1400001618 | I16: DZ | J16: 45972 | K16: 45972 | L16: T54SWIC279192 | N16: 212100 | O16: Trade Debtors (Ctrl) | Q16: 15 | R16: USD | S16: -1968.44 | T16: INR | U16: -173229.39 | W16: 6779220000 | Z16: 2 | AD16: =_xlfn.XLOOKUP(M16,'Customer Data Vlookup'!$R:$R,'Customer Data Vlookup'!$S:$S,,0) -> #N/A | AK16: 45972
A17: Not Selected | B17: 6779 | C17: 100222372 | D17: SHAH TC GLOBAL EXIM LLP | E17: 2025 | F17: 11 | G17: 45972 | H17: 1400001620 | I17: DZ | J17: 45972 | K17: 45972 | L17: 5940256259FS | N17: 212100 | O17: Trade Debtors (Ctrl) | Q17: 15 | R17: USD | S17: -8339.84 | T17: INR | U17: -729855.51 | W17: 6779220000 | Z17: 2 | AD17: =_xlfn.XLOOKUP(M17,'Customer Data Vlookup'!$R:$R,'Customer Data Vlookup'!$S:$S,,0) -> #N/A | AK17: 45972
A18: Not Selected | B18: 6779 | C18: 100222372 | D18: SHAH TC GLOBAL EXIM LLP | E18: 2025 | F18: 11 | G18: 45972 | H18: 1400001622 | I18: DZ | J18: 45972 | K18: 45972 | L18: T54SWIC279194 | N18: 212100 | O18: Trade Debtors (Ctrl) | Q18: 15 | R18: USD | S18: -10455.66 | T18: INR | U18: -920133.52 | W18: 6779220000 | Z18: 2 | AD18: =_xlfn.XLOOKUP(M18,'Customer Data Vlookup'!$R:$R,'Customer Data Vlookup'!$S:$S,,0) -> #N/A | AK18: 45972
A19: Selected | B19: 6779 | C19: 100222372 | D19: SHAH TC GLOBAL EXIM LLP | E19: 2025 | F19: 7 | G19: 45842 | H19: 1400000213 | I19: DY | J19: 45842 | K19: 45842 | L19: NA | M19: KNOCK OFF ENTRY | N19: 212100 | O19: Trade Debtors (Ctrl) | Q19: 15 | R19: USD | S19: 0 | T19: INR | U19: 0 | W19: 6779224500 | Z19: 1 | AD19: =_xlfn.XLOOKUP(M19,'Customer Data Vlookup'!$R:$R,'Customer Data Vlookup'!$S:$S,,0) -> #N/A | AK19: 45842 | AL19: 45842 | AM19: 1400000213
A20: Selected | B20: 6779 | C20: 100222372 | D20: SHAH TC GLOBAL EXIM LLP | E20: 2025 | F20: 7 | G20: 45842 | H20: 1400000214 | I20: DY | J20: 45842 | K20: 45842 | L20: NA | M20: KNOCK OFF ENTRY | N20: 212100 | O20: Trade Debtors (Ctrl) | Q20: 08 | R20: USD | S20: 1166.59 | T20: INR | U20: 101402.13 | W20: 6779224500 | Z20: 1 | AD20: =_xlfn.XLOOKUP(M20,'Customer Data Vlookup'!$R:$R,'Customer Data Vlookup'!$S:$S,,0) -> #N/A | AK20: 45842 | AL20: 45842 | AM20: 1400000214
A21: Selected | B21: 6779 | C21: 100222372 | D21: SHAH TC GLOBAL EXIM LLP | E21: 2025 | F21: 7 | G21: 45842 | H21: 1400000214 | I21: DY | J21: 45842 | K21: 45842 | L21: NA | M21: KNOCK OFF ENTRY | N21: 212100 | O21: Trade Debtors (Ctrl) | Q21: 15 | R21: USD | S21: -1166.59 | T21: INR | U21: -101402.13 | W21: 6779224500 | Z21: 2 | AD21: =_xlfn.XLOOKUP(M21,'Customer Data Vlookup'!$R:$R,'Customer Data Vlookup'!$S:$S,,0) -> #N/A | AK21: 45842 | AL21: 45842 | AM21: 1400000214
A22: Selected | B22: 6779 | C22: 100222372 | D22: SHAH TC GLOBAL EXIM LLP | E22: 2025 | F22: 7 | G22: 45842 | H22: 1400000215 | I22: DY | J22: 45842 | K22: 45842 | L22: NA | M22: KNOCK OFF ENTRY | N22: 212100 | O22: Trade Debtors (Ctrl) | Q22: 08 | R22: USD | S22: 1143.12 | T22: INR | U22: 99362.07 | W22: 6779224500 | Z22: 1 | AD22: =_xlfn.XLOOKUP(M22,'Customer Data Vlookup'!$R:$R,'Customer Data Vlookup'!$S:$S,,0) -> #N/A | AK22: 45842 | AL22: 45842 | AM22: 1400000215
A23: Selected | B23: 6779 | C23: 100222372 | D23: SHAH TC GLOBAL EXIM LLP | E23: 2025 | F23: 7 | G23: 45842 | H23: 1400000215 | I23: DY | J23: 45842 | K23: 45842 | L23: NA | M23: KNOCK OFF ENTRY | N23: 212100 | O23: Trade Debtors (Ctrl) | Q23: 15 | R23: USD | S23: -1143.12 | T23: INR | U23: -99362.07 | W23: 6779224500 | Z23: 2 | AD23: =_xlfn.XLOOKUP(M23,'Customer Data Vlookup'!$R:$R,'Customer Data Vlookup'!$S:$S,,0) -> #N/A | AK23: 45842 | AL23: 45842 | AM23: 1400000215
A24: Not Selected | B24: 6779 | C24: 100222372 | D24: SHAH TC GLOBAL EXIM LLP | E24: 2025 | F24: 5 | G24: 45787 | H24: 1800008260 | I24: DR | J24: 45787 | K24: 45791 | L24: NA | M24: 256779413144 | N24: 212100 | O24: Trade Debtors (Ctrl) | Q24: 01 | R24: INR | S24: 1163.0111 | T24: INR | U24: 100000 | V24: O0 | W24: 6779224500 | Y24: NA | Z24: 1 | AD24: =_xlfn.XLOOKUP(M24,'Customer Data Vlookup'!$R:$R,'Customer Data Vlookup'!$S:$S,,0) -> #N/A | AG24: Fixed Storage Charges fo MAY 2025 | AK24: 45787
A25: Not Selected | B25: 6779 | C25: 100222372 | D25: SHAH TC GLOBAL EXIM LLP | E25: 2025 | F25: 7 | G25: 45842 | H25: 1800010154 | I25: DR | J25: 45842 | K25: 45847 | L25: NA | M25: 256779414914 | N25: 212100 | O25: Trade Debtors (Ctrl) | Q25: 01 | R25: INR | S25: 1169.72 | T25: INR | U25: 100000 | V25: O0 | W25: 6779224500 | Y25: NA | Z25: 1 | AD25: =_xlfn.XLOOKUP(M25,'Customer Data Vlookup'!$R:$R,'Customer Data Vlookup'!$S:$S,,0) -> #N/A | AG25: Fixed Storage Charges fo JULY 2025 | AK25: 45842
A26: Not Selected | B26: 6779 | C26: 100222372 | D26: SHAH TC GLOBAL EXIM LLP | E26: 2025 | F26: 8 | G26: 45870 | H26: 1800011360 | I26: DR | J26: 45870 | K26: 45873 | L26: NA | M26: 256779416026 | N26: 212100 | O26: Trade Debtors (Ctrl) | Q26: 01 | R26: INR | S26: 1162.78 | T26: INR | U26: 100000 | V26: O0 | W26: 6779224500 | Y26: NA | Z26: 1 | AD26: =_xlfn.XLOOKUP(M26,'Customer Data Vlookup'!$R:$R,'Customer Data Vlookup'!$S:$S,,0) -> #N/A | AG26: Fixed Storage Charges for August 2025 | AK26: 45870
A27: Not Selected | B27: 6779 | C27: 100222372 | D27: SHAH TC GLOBAL EXIM LLP | E27: 2025 | F27: 9 | G27: 45904 | H27: 1800012712 | I27: DR | J27: 45904 | K27: 45909 | L27: NA | M27: 256779417346 | N27: 212100 | O27: Trade Debtors (Ctrl) | Q27: 01 | R27: INR | S27: 1162.3778 | T27: INR | U27: 100000 | V27: O0 | W27: 6779224500 | Y27: 2097261 | Z27: 1 | AD27: =_xlfn.XLOOKUP(M27,'Customer Data Vlookup'!$R:$R,'Customer Data Vlookup'!$S:$S,,0) -> #N/A | AG27: Fixed Storage Charges for September 2025 | AK27: 45904
A28: Not Selected | B28: 6779 | C28: 100222372 | D28: SHAH TC GLOBAL EXIM LLP | E28: 2025 | F28: 11 | G28: 45966 | H28: 1800014235 | I28: DR | J28: 45966 | K28: 45966 | L28: NA | M28: 256779418775 | N28: 212100 | O28: Trade Debtors (Ctrl) | Q28: 01 | R28: INR | S28: 1142.67 | T28: INR | U28: 100000 | V28: O0 | W28: 6779224500 | Y28: 2123158 | Z28: 1 | AD28: =_xlfn.XLOOKUP(M28,'Customer Data Vlookup'!$R:$R,'Customer Data Vlookup'!$S:$S,,0) -> #N/A | AG28: Fixed Storage Charges for November 2025 | AK28: 45966
A29: Not Selected | B29: 6779 | C29: 100222372 | D29: SHAH TC GLOBAL EXIM LLP | E29: 2025 | F29: 12 | G29: 45995 | H29: 1800015484 | I29: DR | J29: 45995 | K29: 46000 | L29: NA | M29: 256779419968 | N29: 212100 | O29: Trade Debtors (Ctrl) | Q29: 01 | R29: INR | S29: 1136.32 | T29: INR | U29: 100000 | V29: O0 | W29: 6779224500 | Y29: 2139804 | Z29: 1 | AD29: =_xlfn.XLOOKUP(M29,'Customer Data Vlookup'!$R:$R,'Customer Data Vlookup'!$S:$S,,0) -> #N/A | AG29: Fixed Storage Charges for December 2025 | AK29: 45995
A30: Not Selected | B30: 6779 | C30: 100222372 | D30: SHAH TC GLOBAL EXIM LLP | E30: 2025 | F30: 5 | G30: 45787 | H30: 1800008261 | I30: DR | J30: 45787 | K30: 45791 | L30: NA | M30: 256779413145 | N30: 212100 | O30: Trade Debtors (Ctrl) | Q30: 01 | R30: INR | S30: 1127.39 | T30: INR | U30: 35000 | V30: O0 | W30: 6779224500 | Y30: NA | Z30: 1 | AD30: =_xlfn.XLOOKUP(M30,'Customer Data Vlookup'!$R:$R,'Customer Data Vlookup'!$S:$S,,0) -> #N/A | AG30: Fixed Storage Charges fo MAY 2025 | AK30: 45787
A31: Not Selected | B31: 6779 | C31: 100222372 | D31: SHAH TC GLOBAL EXIM LLP | E31: 2025 | F31: 7 | G31: 45842 | H31: 1800010155 | I31: DR | J31: 45842 | K31: 45847 | L31: NA | M31: 256779414915 | N31: 212100 | O31: Trade Debtors (Ctrl) | Q31: 01 | R31: INR | S31: 407.05 | T31: INR | U31: 35000 | V31: O0 | W31: 6779224500 | Y31: NA | Z31: 1 | AD31: =_xlfn.XLOOKUP(M31,'Customer Data Vlookup'!$R:$R,'Customer Data Vlookup'!$S:$S,,0) -> #N/A | AG31: Fixed Storage Charges fo JULY 2025 | AK31: 45842
A32: Not Selected | B32: 6779 | C32: 100222372 | D32: SHAH TC GLOBAL EXIM LLP | E32: 2025 | F32: 8 | G32: 45870 | H32: 1800011361 | I32: DR | J32: 45870 | K32: 45873 | L32: NA | M32: 256779416027 | N32: 212100 | O32: Trade Debtors (Ctrl) | Q32: 01 | R32: INR | S32: 409.4 | T32: INR | U32: 35000 | V32: O0 | W32: 6779224500 | Y32: NA | Z32: 1 | AD32: =_xlfn.XLOOKUP(M32,'Customer Data Vlookup'!$R:$R,'Customer Data Vlookup'!$S:$S,,0) -> #N/A | AG32: Fixed Storage Charges for August 2025 | AK32: 45870
A33: Not Selected | B33: 6779 | C33: 100222372 | D33: SHAH TC GLOBAL EXIM LLP | E33: 2025 | F33: 9 | G33: 45904 | H33: 1800012713 | I33: DR | J33: 45904 | K33: 45909 | L33: NA | M33: 256779417347 | N33: 212100 | O33: Trade Debtors (Ctrl) | Q33: 01 | R33: INR | S33: 443.14511 | T33: INR | U33: 35000 | V33: O0 | W33: 6779224500 | Y33: 2097261 | Z33: 1 | AD33: =_xlfn.XLOOKUP(M33,'Customer Data Vlookup'!$R:$R,'Customer Data Vlookup'!$S:$S,,0) -> #N/A | AG33: Fixed Storage Charges for September 2025 | AK33: 45904
A34: Not Selected | B34: 6779 | C34: 100222372 | D34: SHAH TC GLOBAL EXIM LLP | E34: 2025 | F34: 11 | G34: 45966 | H34: 1800014236 | I34: DR | J34: 45966 | K34: 45966 | L34: NA | M34: 256779418776 | N34: 212100 | O34: Trade Debtors (Ctrl) | Q34: 01 | R34: INR | S34: 442.98889 | T34: INR | U34: 35000 | V34: O0 | W34: 6779224500 | Y34: 2123158 | Z34: 1 | AD34: =_xlfn.XLOOKUP(M34,'Customer Data Vlookup'!$R:$R,'Customer Data Vlookup'!$S:$S,,0) -> #N/A | AG34: Fixed Storage Charges for November 2025 | AK34: 45966
A35: Not Selected | B35: 6779 | C35: 100222372 | D35: SHAH TC GLOBAL EXIM LLP | E35: 2025 | F35: 12 | G35: 45995 | H35: 1800015485 | I35: DR | J35: 45995 | K35: 46000 | L35: NA | M35: 256779419969 | N35: 212100 | O35: Trade Debtors (Ctrl) | Q35: 01 | R35: INR | S35: 399.93 | T35: INR | U35: 35000 | V35: O0 | W35: 6779224500 | Y35: 2139804 | Z35: 1 | AD35: =_xlfn.XLOOKUP(M35,'Customer Data Vlookup'!$R:$R,'Customer Data Vlookup'!$S:$S,,0) -> #N/A | AG35: Fixed Mangement FEE for December 2025 | AK35: 45995
... A41: Not Selected | B41: 6779 | C41: 100222372 | D41: SHAH TC GLOBAL EXIM LLP | E41: 2025 | F41: 5 | G41: 45787 | H41: 1800008348 | I41: DR | J41: 45787 | K41: 45792 | L41: NA | M41: 256779413231 | N41: 212100 | O41: Trade Debtors (Ctrl) | Q41: 01 | R41: USD | S41: 100 | T41: INR | U41: 8598.37 | V41: O0 | W41: 6779224500 | Y41: NA | Z41: 1 | AD41: =_xlfn.XLOOKUP(M41,'Customer Data Vlookup'!$R:$R,'Customer Data Vlookup'!$S:$S,,0) -> #N/A | AG41: Intra Unit Transfer 16-30 April 25 | AK41: 45787
A42: Not Selected | B42: 6779 | C42: 100222372 | D42: SHAH TC GLOBAL EXIM LLP | E42: 2025 | F42: 5 | G42: 45797 | H42: 1800009077 | I42: DR | J42: 45797 | K42: 45805 | L42: NA | M42: 256779413841 | N42: 212100 | O42: Trade Debtors (Ctrl) | Q42: 01 | R42: USD | S42: 100 | T42: INR | U42: 8598.37 | V42: O0 | W42: 6779224500 | Z42: 1 | AD42: =_xlfn.XLOOKUP(M42,'Customer Data Vlookup'!$R:$R,'Customer Data Vlookup'!$S:$S,,0) -> #N/A | AG42: Unit to Unit, 1-15 May 25 | AK42: 45797
A43: Not Selected | B43: 6779 | C43: 100222372 | D43: SHAH TC GLOBAL EXIM LLP | E43: 2025 | F43: 5 | G43: 45797 | H43: 1800009083 | I43: DR | J43: 45797 | K43: 45805 | L43: NA | M43: 256779413847 | N43: 212100 | O43: Trade Debtors (Ctrl) | Q43: 01 | R43: USD | S43: 100 | T43: INR | U43: 8598.37 | V43: O0 | W43: 6779224500 | Z43: 1 | AD43: =_xlfn.XLOOKUP(M43,'Customer Data Vlookup'!$R:$R,'Customer Data Vlookup'!$S:$S,,0) -> #N/A | AG43: Unit to Unit, 1-15 May 25 | AK43: 45797
A44: Not Selected | B44: 6779 | C44: 100222372 | D44: SHAH TC GLOBAL EXIM LLP | E44: 2025 | F44: 5 | G44: 45797 | H44: 1800009084 | I44: DR | J44: 45797 | K44: 45805 | L44: NA | M44: 256779413848 | N44: 212100 | O44: Trade Debtors (Ctrl) | Q44: 01 | R44: USD | S44: 100 | T44: INR | U44: 8598.37 | V44: O0 | W44: 6779224500 | Z44: 1 | AD44: =_xlfn.XLOOKUP(M44,'Customer Data Vlookup'!$R:$R,'Customer Data Vlookup'!$S:$S,,0) -> #N/A | AG44: Unit to Unit, 1-15 May 25 | AK44: 45797
A45: Not Selected | B45: 6779 | C45: 100222372 | D45: SHAH TC GLOBAL EXIM LLP | E45: 2025 | F45: 7 | G45: 45863 | H45: 1800011280 | I45: DR | J45: 45863 | K45: 45863 | L45: NA | M45: 256779416012 | N45: 212100 | O45: Trade Debtors (Ctrl) | Q45: 01 | R45: USD | S45: 100 | T45: INR | U45: 8600.07 | V45: O0 | W45: 6779224500 | Z45: 1 | AD45: =_xlfn.XLOOKUP(M45,'Customer Data Vlookup'!$R:$R,'Customer Data Vlookup'!$S:$S,,0) -> #N/A | AG45: Unit to Unit 16-31 May 25 | AK45: 45863
A46: Selected | B46: 6779 | C46: 100222372 | D46: SHAH TC GLOBAL EXIM LLP | E46: 2025 | F46: 3 | G46: 45730 | H46: 1800001850 | I46: DR | J46: 45730 | K46: 45733 | L46: NA | M46: 246779411515 | N46: 212100 | O46: Trade Debtors (Ctrl) | Q46: 01 | R46: USD | S46: 100 | T46: INR | U46: 8669.13 | V46: O0 | W46: 6779224500 | Y46: NA | Z46: 1 | AD46: =_xlfn.XLOOKUP(M46,'Customer Data Vlookup'!$R:$R,'Customer Data Vlookup'!$S:$S,,0) -> #N/A | AG46: Intra Unit Transfer Charges Month Of August,2024 | AK46: 45730 | AL46: 45887 | AM46: 1400000854
A47: Selected | B47: 6779 | C47: 100222372 | D47: SHAH TC GLOBAL EXIM LLP | E47: 2025 | F47: 6 | G47: 45827 | H47: 1800009967 | I47: DR | J47: 45827 | K47: 45829 | L47: NA | M47: 256779414731 | N47: 212100 | O47: Trade Debtors (Ctrl) | Q47: 01 | R47: USD | S47: 100 | T47: INR | U47: 8549.08 | V47: O0 | W47: 6779224500 | Y47: NA | Z47: 1 | AD47: =_xlfn.XLOOKUP(M47,'Customer Data Vlookup'!$R:$R,'Customer Data Vlookup'!$S:$S,,0) -> #N/A | AG47: Unit to Unit 1-15 June 25 | AK47: 45827 | AL47: 45888 | AM47: 1400000864
A48: Selected | B48: 6779 | C48: 100222372 | D48: SHAH TC GLOBAL EXIM LLP | E48: 2025 | F48: 6 | G48: 45827 | H48: 1800009968 | I48: DR | J48: 45827 | K48: 45829 | L48: NA | M48: 256779414732 | N48: 212100 | O48: Trade Debtors (Ctrl) | Q48: 01 | R48: USD | S48: 100 | T48: INR | U48: 8549.08 | V48: O0 | W48: 6779224500 | Y48: NA | Z48: 1 | AD48: =_xlfn.XLOOKUP(M48,'Customer Data Vlookup'!$R:$R,'Customer Data Vlookup'!$S:$S,,0) -> #N/A | AG48: Unit to Unit 1-15 June 25 | AK48: 45827 | AL48: 45888 | AM48: 1400000864
A49: Selected | B49: 6779 | C49: 100222372 | D49: SHAH TC GLOBAL EXIM LLP | E49: 2025 | F49: 6 | G49: 45827 | H49: 1800009969 | I49: DR | J49: 45827 | K49: 45829 | L49: NA | M49: 256779414733 | N49: 212100 | O49: Trade Debtors (Ctrl) | Q49: 01 | R49: USD | S49: 100 | T49: INR | U49: 8549.08 | V49: O0 | W49: 6779224500 | Y49: NA | Z49: 1 | AD49: =_xlfn.XLOOKUP(M49,'Customer Data Vlookup'!$R:$R,'Customer Data Vlookup'!$S:$S,,0) -> #N/A | AG49: Unit to Unit 1-15 June 25 | AK49: 45827 | AL49: 45888 | AM49: 1400000864
A50: Selected | B50: 6779 | C50: 100222372 | D50: SHAH TC GLOBAL EXIM LLP | E50: 2025 | F50: 6 | G50: 45827 | H50: 1800009970 | I50: DR | J50: 45827 | K50: 45829 | L50: NA | M50: 256779414734 | N50: 212100 | O50: Trade Debtors (Ctrl) | Q50: 01 | R50: USD | S50: 100 | T50: INR | U50: 8549.08 | V50: O0 | W50: 6779224500 | Y50: NA | Z50: 1 | AD50: =_xlfn.XLOOKUP(M50,'Customer Data Vlookup'!$R:$R,'Customer Data Vlookup'!$S:$S,,0) -> #N/A | AG50: Unit to Unit 1-15 June 25 | AK50: 45827 | AL50: 45888 | AM50: 1400000864
A51: Selected | B51: 6779 | C51: 100222372 | D51: SHAH TC GLOBAL EXIM LLP | E51: 2025 | F51: 6 | G51: 45827 | H51: 1800009971 | I51: DR | J51: 45827 | K51: 45829 | L51: NA | M51: 256779414735 | N51: 212100 | O51: Trade Debtors (Ctrl) | Q51: 01 | R51: USD | S51: 100 | T51: INR | U51: 8549.08 | V51: O0 | W51: 6779224500 | Y51: NA | Z51: 1 | AD51: =_xlfn.XLOOKUP(M51,'Customer Data Vlookup'!$R:$R,'Customer Data Vlookup'!$S:$S,,0) -> #N/A | AG51: Unit to Unit 1-15 June 25 | AK51: 45827 | AL51: 45888 | AM51: 1400000864
A52: Not Selected | B52: 6779 | C52: 100222372 | D52: SHAH TC GLOBAL EXIM LLP | E52: 2025 | F52: 9 | G52: 45917 | H52: 1800012780 | I52: DR | J52: 45917 | K52: 45922 | L52: NA | M52: 256779417434 | N52: 212100 | O52: Trade Debtors (Ctrl) | Q52: 01 | R52: USD | S52: 100 | T52: INR | U52: 8751.43 | V52: O0 | W52: 6779224500 | Y52: 2102531 | Z52: 1 | AD52: =_xlfn.XLOOKUP(M52,'Customer Data Vlookup'!$R:$R,'Customer Data Vlookup'!$S:$S,,0) -> #N/A | AG52: Intra SEZ -1-15 Sept-25 | AK52: 45917
A53: Not Selected | B53: 6779 | C53: 100222372 | D53: SHAH TC GLOBAL EXIM LLP | E53: 2025 | F53: 10 | G53: 45937 | H53: 1800013748 | I53: DR | J53: 45937 | K53: 45939 | L53: NA | M53: 256779418169 | N53: 212100 | O53: Trade Debtors (Ctrl) | Q53: 01 | R53: USD | S53: 100 | T53: INR | U53: 8819.08 | V53: O0 | W53: 6779224500 | Y53: 2110802 | Z53: 1 | AD53: =_xlfn.XLOOKUP(M53,'Customer Data Vlookup'!$R:$R,'Customer Data Vlookup'!$S:$S,,0) -> #N/A | AG53: Intra - SEZ-16-30 Sept 25 | AK53: 45937
A54: Not Selected | B54: 6779 | C54: 100222372 | D54: SHAH TC GLOBAL EXIM LLP | E54: 2025 | F54: 10 | G54: 45937 | H54: 1800013749 | I54: DR | J54: 45937 | K54: 45939 | L54: NA | M54: 256779418170 | N54: 212100 | O54: Trade Debtors (Ctrl) | Q54: 01 | R54: USD | S54: 100 | T54: INR | U54: 8819.08 | V54: O0 | W54: 6779224500 | Y54: 2110802 | Z54: 1 | AD54: =_xlfn.XLOOKUP(M54,'Customer Data Vlookup'!$R:$R,'Customer Data Vlookup'!$S:$S,,0) -> #N/A | AG54: Intra - SEZ-16-30 Sept 25 | AK54: 45937
A55: Not Selected | B55: 6779 | C55: 100222372 | D55: SHAH TC GLOBAL EXIM LLP | E55: 2025 | F55: 2 | G55: 45716 | H55: 1800000374 | I55: DR | J55: 45716 | K55: 45716 | L55: NA | M55: 246779410343 | N55: 212100 | O55: Trade Debtors (Ctrl) | Q55: 01 | R55: USD | S55: 1700 | T55: INR | U55: 146716.22 | V55: O0 | W55: 6779224500 | Y55: NA | Z55: 1 | AD55: =_xlfn.XLOOKUP(M55,'Customer Data Vlookup'!$R:$R,'Customer Data Vlookup'!$S:$S,,0) -> #N/A | AG55: CY Longstanding container Ground Rent charges for | AK55: 45716
A56: Not Selected | B56: 6779 | C56: 100222372 | D56: SHAH TC GLOBAL EXIM LLP | E56: 2025 | F56: 2 | G56: 45716 | H56: 1800000381 | I56: DR | J56: 45716 | K56: 45716 | L56: NA | M56: 246779410350 | N56: 212100 | O56: Trade Debtors (Ctrl) | Q56: 01 | R56: USD | S56: 1750 | T56: INR | U56: 151031.41 | V56: O0 | W56: 6779224500 | Y56: NA | Z56: 1 | AD56: =_xlfn.XLOOKUP(M56,'Customer Data Vlookup'!$R:$R,'Customer Data Vlookup'!$S:$S,,0) -> #N/A | AG56: CY Longstanding container Ground Rent charges for | AK56: 45716
A57: Not Selected | B57: 6779 | C57: 100222372 | D57: SHAH TC GLOBAL EXIM LLP | E57: 2025 | F57: 2 | G57: 45716 | H57: 1800000387 | I57: DR | J57: 45716 | K57: 45716 | L57: NA | M57: 246779410356 | N57: 212100 | O57: Trade Debtors (Ctrl) | Q57: 01 | R57: USD | S57: 1750 | T57: INR | U57: 151031.41 | V57: O0 | W57: 6779224500 | Y57: NA | Z57: 1 | AD57: =_xlfn.XLOOKUP(M57,'Customer Data Vlookup'!$R:$R,'Customer Data Vlookup'!$S:$S,,0) -> #N/A | AG57: CY Longstanding container Ground Rent charges for | AK57: 45716
A58: Not Selected | B58: 6779 | C58: 100222372 | D58: SHAH TC GLOBAL EXIM LLP | E58: 2025 | F58: 2 | G58: 45716 | H58: 1800000393 | I58: DR | J58: 45716 | K58: 45716 | L58: NA | M58: 246779410362 | N58: 212100 | O58: Trade Debtors (Ctrl) | Q58: 01 | R58: USD | S58: 1700 | T58: INR | U58: 146716.22 | V58: O0 | W58: 6779224500 | Y58: NA | Z58: 1 | AD58: =_xlfn.XLOOKUP(M58,'Customer Data Vlookup'!$R:$R,'Customer Data Vlookup'!$S:$S,,0) -> #N/A | AG58: CY Longstanding container Ground Rent charges for | AK58: 45716
A59: Not Selected | B59: 6779 | C59: 100222372 | D59: SHAH TC GLOBAL EXIM LLP | E59: 2025 | F59: 3 | G59: 45722 | H59: 1800000931 | I59: DR | J59: 45722 | K59: 45722 | L59: NA | M59: 246779410871 | N59: 212100 | O59: Trade Debtors (Ctrl) | Q59: 01 | R59: USD | S59: 42.51 | T59: INR | U59: 3685.25 | V59: O0 | W59: 6779224500 | Y59: NA | Z59: 1 | AD59: =_xlfn.XLOOKUP(M59,'Customer Data Vlookup'!$R:$R,'Customer Data Vlookup'!$S:$S,,0) -> #N/A | AG59: Storage Charges for the month of November, 2024 Ex | AK59: 45722
A60: Not Selected | B60: 6779 | C60: 100222372 | D60: SHAH TC GLOBAL EXIM LLP | E60: 2025 | F60: 3 | G60: 45722 | H60: 1800000953 | I60: DR | J60: 45722 | K60: 45722 | L60: NA | M60: 246779410893 | N60: 212100 | O60: Trade Debtors (Ctrl) | Q60: 01 | R60: USD | S60: 177.18 | T60: INR | U60: 15359.96 | V60: O0 | W60: 6779224500 | Y60: NA | Z60: 1 | AD60: =_xlfn.XLOOKUP(M60,'Customer Data Vlookup'!$R:$R,'Customer Data Vlookup'!$S:$S,,0) -> #N/A | AG60: Storage Charges for the month of December, 2024 Ex | AK60: 45722
A61: Not Selected | B61: 6779 | C61: 100222372 | D61: SHAH TC GLOBAL EXIM LLP | E61: 2025 | F61: 10 | G61: 45943 | H61: 1600002439 | I61: DG | J61: 45943 | K61: 45944 | L61: NA | M61: 256779421983 | N61: 212100 | O61: Trade Debtors (Ctrl) | Q61: 11 | R61: USD | S61: -930.14 | T61: INR | U61: -82029.76 | V61: O0 | W61: 6779224500 | Y61: 2112591 | Z61: 1 | AD61: =_xlfn.XLOOKUP(M61,'Customer Data Vlookup'!$R:$R,'Customer Data Vlookup'!$S:$S,,0) -> #N/A | AG61: CN issued against 256779418011 | AK61: 45943
A62: Not Selected | B62: 6779 | C62: 100222372 | D62: SHAH TC GLOBAL EXIM LLP | E62: 2025 | F62: 3 | G62: 45719 | H62: 1800000414 | I62: DR | J62: 45719 | K62: 45719 | L62: NA | M62: 246779410376 | N62: 212100 | O62: Trade Debtors (Ctrl) | Q62: 01 | R62: USD | S62: 711.35 | T62: INR | U62: 61667.83 | V62: O0 | W62: 6779224500 | Y62: NA | Z62: 1 | AD62: =_xlfn.XLOOKUP(M62,'Customer Data Vlookup'!$R:$R,'Customer Data Vlookup'!$S:$S,,0) -> #N/A | AG62: Storage Charges for the month of August, 2024 | AK62: 45719
A63: Not Selected | B63: 6779 | C63: 100222372 | D63: SHAH TC GLOBAL EXIM LLP | E63: 2025 | F63: 3 | G63: 45719 | H63: 1800000439 | I63: DR | J63: 45719 | K63: 45719 | L63: NA | M63: 246779410401 | N63: 212100 | O63: Trade Debtors (Ctrl) | Q63: 01 | R63: USD | S63: 1298.96 | T63: INR | U63: 112608.48 | V63: O0 | W63: 6779224500 | Y63: NA | Z63: 1 | AD63: =_xlfn.XLOOKUP(M63,'Customer Data Vlookup'!$R:$R,'Customer Data Vlookup'!$S:$S,,0) -> #N/A | AG63: Storage for the month of Sept 2024 | AK63: 45719
... A72: Not Selected | B72: 6779 | C72: 100222372 | D72: SHAH TC GLOBAL EXIM LLP | E72: 2025 | F72: 3 | G72: 45733 | H72: 1800002276 | I72: DR | J72: 45733 | K72: 45734 | L72: NA | M72: 246779411941 | N72: 212100 | O72: Trade Debtors (Ctrl) | Q72: 01 | R72: USD | S72: 76.02 | T72: INR | U72: 6590.27 | V72: O0 | W72: 6779224500 | Y72: NA | Z72: 1 | AD72: =_xlfn.XLOOKUP(M72,'Customer Data Vlookup'!$R:$R,'Customer Data Vlookup'!$S:$S,,0) -> #N/A | AG72: VAS Activity Charges for the month of November, 24 | AK72: 45733
A73: Selected | B73: 6779 | C73: 100222372 | D73: SHAH TC GLOBAL EXIM LLP | E73: 2025 | F73: 4 | G73: 45762 | H73: 1800006261 | I73: DR | J73: 45762 | K73: 45763 | L73: NA | M73: 256779411152 | N73: 212100 | O73: Trade Debtors (Ctrl) | Q73: 01 | R73: USD | S73: 164.38 | T73: INR | U73: 14288.21 | V73: O0 | Y73: NA | Z73: 1 | AD73: =_xlfn.XLOOKUP(M73,'Customer Data Vlookup'!$R:$R,'Customer Data Vlookup'!$S:$S,,0) -> #N/A | AG73: Empty Transportation August 2024 | AK73: 45762 | AL73: 45887 | AM73: 1400000854
A74: Selected | B74: 6779 | C74: 100222372 | D74: SHAH TC GLOBAL EXIM LLP | E74: 2025 | F74: 4 | G74: 45762 | H74: 1800006262 | I74: DR | J74: 45762 | K74: 45763 | L74: NA | M74: 256779411153 | N74: 212100 | O74: Trade Debtors (Ctrl) | Q74: 01 | R74: USD | S74: 26.54 | T74: INR | U74: 2306.91 | V74: O0 | Y74: NA | Z74: 1 | AD74: =_xlfn.XLOOKUP(M74,'Customer Data Vlookup'!$R:$R,'Customer Data Vlookup'!$S:$S,,0) -> #N/A | AG74: LCL Charges August 2024 | AK74: 45762 | AL74: 45887 | AM74: 1400000854
A75: Selected | B75: 6779 | C75: 100222372 | D75: SHAH TC GLOBAL EXIM LLP | E75: 2025 | F75: 4 | G75: 45762 | H75: 1800006263 | I75: DR | J75: 45762 | K75: 45763 | L75: NA | M75: 256779411154 | N75: 212100 | O75: Trade Debtors (Ctrl) | Q75: 01 | R75: USD | S75: 84.26 | T75: INR | U75: 7324.03 | V75: O0 | Y75: NA | Z75: 1 | AD75: =_xlfn.XLOOKUP(M75,'Customer Data Vlookup'!$R:$R,'Customer Data Vlookup'!$S:$S,,0) -> #N/A | AG75: LCL Charges August 2024 | AK75: 45762 | AL75: 45887 | AM75: 1400000854
A76: Selected | B76: 6779 | C76: 100222372 | D76: SHAH TC GLOBAL EXIM LLP | E76: 2025 | F76: 4 | G76: 45762 | H76: 1800006264 | I76: DR | J76: 45762 | K76: 45763 | L76: NA | M76: 256779411155 | N76: 212100 | O76: Trade Debtors (Ctrl) | Q76: 01 | R76: USD | S76: 36.9 | T76: INR | U76: 3207.42 | V76: O0 | Y76: NA | Z76: 1 | AD76: =_xlfn.XLOOKUP(M76,'Customer Data Vlookup'!$R:$R,'Customer Data Vlookup'!$S:$S,,0) -> #N/A | AG76: Inbound Handling for August 24 | AK76: 45762 | AL76: 45887 | AM76: 1400000854
A77: Selected | B77: 6779 | C77: 100222372 | D77: SHAH TC GLOBAL EXIM LLP | E77: 2025 | F77: 4 | G77: 45762 | H77: 1800006265 | I77: DR | J77: 45762 | K77: 45763 | L77: NA | M77: 256779411156 | N77: 212100 | O77: Trade Debtors (Ctrl) | Q77: 01 | R77: USD | S77: 20.23 | T77: INR | U77: 1758.43 | V77: O0 | Y77: NA | Z77: 1 | AD77: =_xlfn.XLOOKUP(M77,'Customer Data Vlookup'!$R:$R,'Customer Data Vlookup'!$S:$S,,0) -> #N/A | AG77: Inbound Handling for August 24 | AK77: 45762 | AL77: 45887 | AM77: 1400000854
A78: Selected | B78: 6779 | C78: 100222372 | D78: SHAH TC GLOBAL EXIM LLP | E78: 2025 | F78: 4 | G78: 45762 | H78: 1800006266 | I78: DR | J78: 45762 | K78: 45763 | L78: NA | M78: 256779411157 | N78: 212100 | O78: Trade Debtors (Ctrl) | Q78: 01 | R78: USD | S78: 116.32 | T78: INR | U78: 10110.75 | V78: O0 | Y78: NA | Z78: 1 | AD78: =_xlfn.XLOOKUP(M78,'Customer Data Vlookup'!$R:$R,'Customer Data Vlookup'!$S:$S,,0) -> #N/A | AG78: Inbound Handling for August 24 | AK78: 45762 | AL78: 45887 | AM78: 1400000854
A79: Selected | B79: 6779 | C79: 100222372 | D79: SHAH TC GLOBAL EXIM LLP | E79: 2025 | F79: 4 | G79: 45762 | H79: 1800006674 | I79: DR | J79: 45762 | K79: 45763 | L79: NA | M79: 256779411565 | N79: 212100 | O79: Trade Debtors (Ctrl) | Q79: 01 | R79: USD | S79: 22 | T79: INR | U79: 1912.28 | V79: O0 | Y79: NA | Z79: 1 | AD79: =_xlfn.XLOOKUP(M79,'Customer Data Vlookup'!$R:$R,'Customer Data Vlookup'!$S:$S,,0) -> #N/A | AG79: Outbound Handling Charges Aug 2024 | AK79: 45762 | AL79: 45887 | AM79: 1400000854
A80: Selected | B80: 6779 | C80: 100222372 | D80: SHAH TC GLOBAL EXIM LLP | E80: 2025 | F80: 4 | G80: 45762 | H80: 1800006675 | I80: DR | J80: 45762 | K80: 45763 | L80: NA | M80: 256779411566 | N80: 212100 | O80: Trade Debtors (Ctrl) | Q80: 01 | R80: USD | S80: 4.4 | T80: INR | U80: 382.46 | V80: O0 | Y80: NA | Z80: 1 | AD80: =_xlfn.XLOOKUP(M80,'Customer Data Vlookup'!$R:$R,'Customer Data Vlookup'!$S:$S,,0) -> #N/A | AG80: Outbound Handling Charges Aug 2024 | AK80: 45762 | AL80: 45887 | AM80: 1400000854
A81: Selected | B81: 6779 | C81: 100222372 | D81: SHAH TC GLOBAL EXIM LLP | E81: 2025 | F81: 4 | G81: 45762 | H81: 1800006676 | I81: DR | J81: 45762 | K81: 45763 | L81: NA | M81: 256779411567 | N81: 212100 | O81: Trade Debtors (Ctrl) | Q81: 01 | R81: USD | S81: 5.84 | T81: INR | U81: 507.62 | V81: O0 | Y81: NA | Z81: 1 | AD81: =_xlfn.XLOOKUP(M81,'Customer Data Vlookup'!$R:$R,'Customer Data Vlookup'!$S:$S,,0) -> #N/A | AG81: Outbound Handling Charges Aug 2024 | AK81: 45762 | AL81: 45887 | AM81: 1400000854
A82: Selected | B82: 6779 | C82: 100222372 | D82: SHAH TC GLOBAL EXIM LLP | E82: 2025 | F82: 4 | G82: 45762 | H82: 1800006677 | I82: DR | J82: 45762 | K82: 45763 | L82: NA | M82: 256779411568 | N82: 212100 | O82: Trade Debtors (Ctrl) | Q82: 01 | R82: USD | S82: 0.8 | T82: INR | U82: 69.54 | V82: O0 | Y82: NA | Z82: 1 | AD82: =_xlfn.XLOOKUP(M82,'Customer Data Vlookup'!$R:$R,'Customer Data Vlookup'!$S:$S,,0) -> #N/A | AG82: Outbound Handling Charges Aug 2024 | AK82: 45762 | AL82: 45887 | AM82: 1400000854
A83: Selected | B83: 6779 | C83: 100222372 | D83: SHAH TC GLOBAL EXIM LLP | E83: 2025 | F83: 4 | G83: 45762 | H83: 1800006678 | I83: DR | J83: 45762 | K83: 45763 | L83: NA | M83: 256779411569 | N83: 212100 | O83: Trade Debtors (Ctrl) | Q83: 01 | R83: USD | S83: 13.85 | T83: INR | U83: 1203.87 | V83: O0 | Y83: NA | Z83: 1 | AD83: =_xlfn.XLOOKUP(M83,'Customer Data Vlookup'!$R:$R,'Customer Data Vlookup'!$S:$S,,0) -> #N/A | AG83: Outbound Handling Charges Aug 2024 | AK83: 45762 | AL83: 45887 | AM83: 1400000854
A84: Selected | B84: 6779 | C84: 100222372 | D84: SHAH TC GLOBAL EXIM LLP | E84: 2025 | F84: 4 | G84: 45762 | H84: 1800006679 | I84: DR | J84: 45762 | K84: 45763 | L84: NA | M84: 256779411570 | N84: 212100 | O84: Trade Debtors (Ctrl) | Q84: 01 | R84: USD | S84: 18.15 | T84: INR | U84: 1577.63 | V84: O0 | Y84: NA | Z84: 1 | AD84: =_xlfn.XLOOKUP(M84,'Customer Data Vlookup'!$R:$R,'Customer Data Vlookup'!$S:$S,,0) -> #N/A | AG84: Outbound Handling Charges Aug 2024 | AK84: 45762 | AL84: 45887 | AM84: 1400000854
... A99: Selected | B99: 6779 | C99: 100222372 | D99: SHAH TC GLOBAL EXIM LLP | E99: 2025 | F99: 4 | G99: 45762 | H99: 1800006694 | I99: DR | J99: 45762 | K99: 45763 | L99: NA | M99: 256779411585 | N99: 212100 | O99: Trade Debtors (Ctrl) | Q99: 01 | R99: USD | S99: 7.81 | T99: INR | U99: 678.86 | V99: O0 | Y99: NA | Z99: 1 | AD99: =_xlfn.XLOOKUP(M99,'Customer Data Vlookup'!$R:$R,'Customer Data Vlookup'!$S:$S,,0) -> #N/A | AG99: Outbound Handling Charges Aug 2024 | AK99: 45762 | AL99: 45887 | AM99: 1400000854
A100: Not Selected | B100: 6779 | C100: 100222372 | D100: SHAH TC GLOBAL EXIM LLP | E100: 2025 | F100: 10 | G100: 45947 | H100: 1600002472 | I100: DG | J100: 45947 | K100: 45953 | L100: NA | M100: 256779422014 | N100: 212100 | O100: Trade Debtors (Ctrl) | Q100: 11 | R100: USD | S100: -136.48 | T100: INR | U100: -12036.28 | V100: O0 | W100: 6779224500 | Y100: 2117487 | Z100: 1 | AD100: =_xlfn.XLOOKUP(M100,'Customer Data Vlookup'!$R:$R,'Customer Data Vlookup'!$S:$S,,0) -> #N/A | AG100: Credit note raised against 256779418076 | AK100: 45947
A101: Not Selected | B101: 6779 | C101: 100222372 | D101: SHAH TC GLOBAL EXIM LLP | E101: 2025 | F101: 4 | G101: 45763 | H101: 1800006996 | I101: DR | J101: 45763 | K101: 45764 | L101: NA | M101: 256779411887 | N101: 212100 | O101: Trade Debtors (Ctrl) | Q101: 01 | R101: USD | S101: 71.22 | T101: INR | U101: 6190.57 | V101: O0 | W101: 6779224500 | Y101: NA | Z101: 1 | AD101: =_xlfn.XLOOKUP(M101,'Customer Data Vlookup'!$R:$R,'Customer Data Vlookup'!$S:$S,,0) -> #N/A | AG101: Outbound Handling charges for Dec 2024 | AK101: 45763
A102: Not Selected | B102: 6779 | C102: 100222372 | D102: SHAH TC GLOBAL EXIM LLP | E102: 2025 | F102: 4 | G102: 45763 | H102: 1800007093 | I102: DR | J102: 45763 | K102: 45764 | L102: NA | M102: 256779411984 | N102: 212100 | O102: Trade Debtors (Ctrl) | Q102: 01 | R102: USD | S102: 39.54 | T102: INR | U102: 3436.89 | V102: O0 | W102: 6779224500 | Y102: NA | Z102: 1 | AD102: =_xlfn.XLOOKUP(M102,'Customer Data Vlookup'!$R:$R,'Customer Data Vlookup'!$S:$S,,0) -> #N/A | AG102: CAAU5283880-Port SSR Shifting Mar 2025. Exch rate | AK102: 45763
A103: Not Selected | B103: 6779 | C103: 100222372 | D103: SHAH TC GLOBAL EXIM LLP | E103: 2025 | F103: 4 | G103: 45763 | H103: 1800007129 | I103: DR | J103: 45763 | K103: 45764 | L103: NA | M103: 256779412020 | N103: 212100 | O103: Trade Debtors (Ctrl) | Q103: 01 | R103: USD | S103: 85.21 | T103: INR | U103: 7406.61 | V103: O0 | W103: 6779224500 | Y103: NA | Z103: 1 | AD103: =_xlfn.XLOOKUP(M103,'Customer Data Vlookup'!$R:$R,'Customer Data Vlookup'!$S:$S,,0) -> #N/A | AG103: VAS Activity - Jan 25, Ex Rate. 86.64 | AK103: 45763
A104: Not Selected | B104: 6779 | C104: 100222372 | D104: SHAH TC GLOBAL EXIM LLP | E104: 2025 | F104: 4 | G104: 45763 | H104: 1800007210 | I104: DR | J104: 45763 | K104: 45764 | L104: NA | M104: 256779412101 | N104: 212100 | O104: Trade Debtors (Ctrl) | Q104: 01 | R104: USD | S104: 171.71 | T104: INR | U104: 14925.35 | V104: O0 | W104: 6779224500 | Y104: NA | Z104: 1 | AD104: =_xlfn.XLOOKUP(M104,'Customer Data Vlookup'!$R:$R,'Customer Data Vlookup'!$S:$S,,0) -> #N/A | AG104: VAS Activity - Mar 25, 16-31, Ex Rate. 85.58 | AK104: 45763
A105: Not Selected | B105: 6779 | C105: 100222372 | D105: SHAH TC GLOBAL EXIM LLP | E105: 2025 | F105: 4 | G105: 45763 | H105: 1800007235 | I105: DR | J105: 45763 | K105: 45764 | L105: NA | M105: 256779412126 | N105: 212100 | O105: Trade Debtors (Ctrl) | Q105: 01 | R105: USD | S105: 500.58 | T105: INR | U105: 43511.32 | V105: O0 | W105: 6779224500 | Y105: NA | Z105: 1 | AD105: =_xlfn.XLOOKUP(M105,'Customer Data Vlookup'!$R:$R,'Customer Data Vlookup'!$S:$S,,0) -> #N/A | AG105: Storage Charges Mar, 25 Exch Rate 85.58 | AK105: 45763
A106: Not Selected | B106: 6779 | C106: 100222372 | D106: SHAH TC GLOBAL EXIM LLP | E106: 2025 | F106: 7 | G106: 45863 | H106: 1800011264 | I106: DR | J106: 45863 | K106: 45863 | L106: NA | M106: 256779415996 | N106: 212100 | O106: Trade Debtors (Ctrl) | Q106: 01 | R106: USD | S106: 755.58 | T106: INR | U106: 64980.39 | V106: O0 | W106: 6779224500 | Y106: NA | Z106: 1 | AD106: =_xlfn.XLOOKUP(M106,'Customer Data Vlookup'!$R:$R,'Customer Data Vlookup'!$S:$S,,0) -> #N/A | AG106: VAS 16-31 May 25 Ex.85.48 | AK106: 45863
A107: Selected | B107: 6779 | C107: 100222372 | D107: SHAH TC GLOBAL EXIM LLP | E107: 2025 | F107: 3 | G107: 45730 | H107: 1800001581 | I107: DR | J107: 45730 | K107: 45735 | L107: NA | M107: 246779412238 | N107: 212100 | O107: Trade Debtors (Ctrl) | Q107: 01 | R107: USD | S107: 945.75 | T107: INR | U107: 81988.26 | V107: O0 | W107: 6779224500 | Y107: NA | Z107: 1 | AD107: =_xlfn.XLOOKUP(M107,'Customer Data Vlookup'!$R:$R,'Customer Data Vlookup'!$S:$S,,0) -> #N/A | AG107: VAS Activity Charges for the month of August, 24 | AK107: 45730 | AL107: 45842 | AM107: 1400000213
A108: Selected | B108: 6779 | C108: 100222372 | D108: SHAH TC GLOBAL EXIM LLP | E108: 2025 | F108: 3 | G108: 45730 | H108: 1800001784 | I108: DR | J108: 45730 | K108: 45733 | L108: NA | M108: 246779411449 | N108: 212100 | O108: Trade Debtors (Ctrl) | Q108: 01 | R108: USD | S108: 945.75 | T108: INR | U108: 81988.26 | V108: O0 | W108: 6779224500 | Y108: NA | Z108: 1 | AD108: =_xlfn.XLOOKUP(M108,'Customer Data Vlookup'!$R:$R,'Customer Data Vlookup'!$S:$S,,0) -> #N/A | AG108: VAS Activity Charges for the month of August, 24 | AK108: 45730 | AL108: 45887 | AM108: 1400000854
A109: Not Selected | B109: 6779 | C109: 100222372 | D109: SHAH TC GLOBAL EXIM LLP | E109: 2025 | F109: 8 | G109: 45883 | H109: 1600002155 | I109: DG | J109: 45883 | K109: 45891 | L109: NA | M109: 256779421715 | N109: 212100 | O109: Trade Debtors (Ctrl) | Q109: 11 | R109: USD | S109: -2324.77 | T109: INR | U109: -200000.24 | V109: O0 | W109: 6779224500 | Y109: NA | Z109: 1 | AD109: =_xlfn.XLOOKUP(M109,'Customer Data Vlookup'!$R:$R,'Customer Data Vlookup'!$S:$S,,0) -> #N/A | AG109: CN issued towards D & D | AK109: 45883
A110: Not Selected | B110: 6779 | C110: 100222372 | D110: SHAH TC GLOBAL EXIM LLP | E110: 2025 | F110: 9 | G110: 45904 | H110: 1800012461 | I110: DR | J110: 45904 | K110: 45909 | L110: NA | M110: 256779417161 | N110: 212100 | O110: Trade Debtors (Ctrl) | Q110: 01 | R110: USD | S110: 787.95 | T110: INR | U110: 68956.92 | V110: O0 | W110: 6779224500 | Y110: NA | Z110: 1 | AD110: =_xlfn.XLOOKUP(M110,'Customer Data Vlookup'!$R:$R,'Customer Data Vlookup'!$S:$S,,0) -> #N/A | AG110: VAS -16-31 Aug 25 | AK110: 45904
A111: Not Selected | B111: 6779 | C111: 100222372 | D111: SHAH TC GLOBAL EXIM LLP | E111: 2025 | F111: 9 | G111: 45904 | H111: 1800012559 | I111: DR | J111: 45904 | K111: 45909 | L111: NA | M111: 256779417178 | N111: 212100 | O111: Trade Debtors (Ctrl) | Q111: 01 | R111: USD | S111: 1560 | T111: INR | U111: 136522.35 | V111: O0 | W111: 6779224500 | Y111: NA | Z111: 1 | AD111: =_xlfn.XLOOKUP(M111,'Customer Data Vlookup'!$R:$R,'Customer Data Vlookup'!$S:$S,,0) -> #N/A | AG111: CY Refer Pluging Chgs - 01 - 31 May 25 | AK111: 45904
A112: Not Selected | B112: 6779 | C112: 100222372 | D112: SHAH TC GLOBAL EXIM LLP | E112: 2025 | F112: 9 | G112: 45904 | H112: 1800012560 | I112: DR | J112: 45904 | K112: 45909 | L112: NA | M112: 256779417179 | N112: 212100 | O112: Trade Debtors (Ctrl) | Q112: 01 | R112: USD | S112: 1560 | T112: INR | U112: 136522.35 | V112: O0 | W112: 6779224500 | Y112: NA | Z112: 1 | AD112: =_xlfn.XLOOKUP(M112,'Customer Data Vlookup'!$R:$R,'Customer Data Vlookup'!$S:$S,,0) -> #N/A | AG112: CY Refer Pluging Chgs - 01 - 30 Jun 25 | AK112: 45904
A113: Not Selected | B113: 6779 | C113: 100222372 | D113: SHAH TC GLOBAL EXIM LLP | E113: 2025 | F113: 9 | G113: 45904 | H113: 1800012561 | I113: DR | J113: 45904 | K113: 45909 | L113: NA | M113: 256779417180 | N113: 212100 | O113: Trade Debtors (Ctrl) | Q113: 01 | R113: USD | S113: 1799.1 | T113: INR | U113: 157447.03 | V113: O0 | W113: 6779224500 | Y113: NA | Z113: 1 | AD113: =_xlfn.XLOOKUP(M113,'Customer Data Vlookup'!$R:$R,'Customer Data Vlookup'!$S:$S,,0) -> #N/A | AG113: CY Ground rent Chgs - 01 - 31 July 25 | AK113: 45904
A114: Not Selected | B114: 6779 | C114: 100222372 | D114: SHAH TC GLOBAL EXIM LLP | E114: 2025 | F114: 9 | G114: 45904 | H114: 1800012562 | I114: DR | J114: 45904 | K114: 45909 | L114: NA | M114: 256779417181 | N114: 212100 | O114: Trade Debtors (Ctrl) | Q114: 01 | R114: USD | S114: 1812 | T114: INR | U114: 158575.97 | V114: O0 | W114: 6779224500 | Y114: NA | Z114: 1 | AD114: =_xlfn.XLOOKUP(M114,'Customer Data Vlookup'!$R:$R,'Customer Data Vlookup'!$S:$S,,0) -> #N/A | AG114: CY Ground rent Chgs - 01 - 31 Aug 25 | AK114: 45904
A115: Not Selected | B115: 6779 | C115: 100222372 | D115: SHAH TC GLOBAL EXIM LLP | E115: 2025 | F115: 9 | G115: 45904 | H115: 1800012619 | I115: DR | J115: 45904 | K115: 45909 | L115: NA | M115: 256779417206 | N115: 212100 | O115: Trade Debtors (Ctrl) | Q115: 01 | R115: USD | S115: 152.28 | T115: INR | U115: 13326.68 | V115: O0 | W115: 6779224500 | Y115: NA | Z115: 1 | AD115: =_xlfn.XLOOKUP(M115,'Customer Data Vlookup'!$R:$R,'Customer Data Vlookup'!$S:$S,,0) -> #N/A | AG115: Empty Lolo Chgs - 01 - 31 AUG 25 | AK115: 45904
A116: Not Selected | B116: 6779 | C116: 100222372 | D116: SHAH TC GLOBAL EXIM LLP | E116: 2025 | F116: 9 | G116: 45904 | H116: 1800012587 | I116: DR | J116: 45904 | K116: 45909 | L116: NA | M116: 256779417245 | N116: 212100 | O116: Trade Debtors (Ctrl) | Q116: 01 | R116: USD | S116: 83.89 | T116: INR | U116: 7341.58 | V116: O0 | W116: 6779224500 | Y116: NA | Z116: 1 | AD116: =_xlfn.XLOOKUP(M116,'Customer Data Vlookup'!$R:$R,'Customer Data Vlookup'!$S:$S,,0) -> #N/A | AG116: PORT SSR Chgs Aug 25 | AK116: 45904
A117: Not Selected | B117: 6779 | C117: 100222372 | D117: SHAH TC GLOBAL EXIM LLP | E117: 2025 | F117: 9 | G117: 45904 | H117: 1800012647 | I117: DR | J117: 45904 | K117: 45909 | L117: NA | M117: 256779417287 | N117: 212100 | O117: Trade Debtors (Ctrl) | Q117: 01 | R117: USD | S117: 410.58 | T117: INR | U117: 35931.63 | V117: O0 | W117: 6779224500 | Y117: NA | Z117: 1 | AD117: =_xlfn.XLOOKUP(M117,'Customer Data Vlookup'!$R:$R,'Customer Data Vlookup'!$S:$S,,0) -> #N/A | AG117: Transportation In Chgs - 16 - 31 AUG 25 | AK117: 45904
A118: Not Selected | B118: 6779 | C118: 100222372 | D118: SHAH TC GLOBAL EXIM LLP | E118: 2025 | F118: 9 | G118: 45904 | H118: 1800012685 | I118: DR | J118: 45904 | K118: 45909 | L118: NA | M118: 256779417325 | N118: 212100 | O118: Trade Debtors (Ctrl) | Q118: 01 | R118: USD | S118: 97.84 | T118: INR | U118: 8562.4 | V118: O0 | W118: 6779224500 | Y118: 2096996 | Z118: 1 | AD118: =_xlfn.XLOOKUP(M118,'Customer Data Vlookup'!$R:$R,'Customer Data Vlookup'!$S:$S,,0) -> #N/A | AG118: Outbound chgs - 16 - 31 Aug 25 | AK118: 45904
A119: Not Selected | B119: 6779 | C119: 100222372 | D119: SHAH TC GLOBAL EXIM LLP | E119: 2025 | F119: 9 | G119: 45904 | H119: 1600002212 | I119: DG | J119: 45904 | K119: 45915 | L119: NA | M119: 256779421767 | N119: 212100 | O119: Trade Debtors (Ctrl) | Q119: 11 | R119: USD | S119: -60 | T119: INR | U119: -5250.86 | V119: O0 | W119: 6779224500 | Y119: 2100473 | Z119: 1 | AD119: =_xlfn.XLOOKUP(M119,'Customer Data Vlookup'!$R:$R,'Customer Data Vlookup'!$S:$S,,0) -> #N/A | AG119: CN Issued towards bill no. 256779417178 | AK119: 45904
A120: Not Selected | B120: 6779 | C120: 100222372 | D120: SHAH TC GLOBAL EXIM LLP | E120: 2025 | F120: 9 | G120: 45904 | H120: 1600002213 | I120: DG | J120: 45904 | K120: 45915 | L120: NA | M120: 256779421768 | N120: 212100 | O120: Trade Debtors (Ctrl) | Q120: 11 | R120: USD | S120: -60 | T120: INR | U120: -5250.86 | V120: O0 | W120: 6779224500 | Y120: 2100473 | Z120: 1 | AD120: =_xlfn.XLOOKUP(M120,'Customer Data Vlookup'!$R:$R,'Customer Data Vlookup'!$S:$S,,0) -> #N/A | AG120: CN Issued towards bill no. 256779417179 | AK120: 45904
... A131: Not Selected | B131: 6779 | C131: 100222372 | D131: SHAH TC GLOBAL EXIM LLP | E131: 2025 | F131: 7 | G131: 45842 | H131: 1800010436 | I131: DR | J131: 45842 | K131: 45847 | L131: NA | M131: 256779415196 | N131: 212100 | O131: Trade Debtors (Ctrl) | Q131: 01 | R131: USD | S131: 17.48 | T131: INR | U131: 1503.29 | V131: O0 | W131: 6779224500 | Y131: NA | Z131: 1 | AD131: =_xlfn.XLOOKUP(M131,'Customer Data Vlookup'!$R:$R,'Customer Data Vlookup'!$S:$S,,0) -> #N/A | AG131: Unit Storage - 1-30 June 25 | AK131: 45842
A132: Not Selected | B132: 6779 | C132: 100222372 | D132: SHAH TC GLOBAL EXIM LLP | E132: 2025 | F132: 7 | G132: 45842 | H132: 1800010504 | I132: DR | J132: 45842 | K132: 45847 | L132: NA | M132: 256779415264 | N132: 212100 | O132: Trade Debtors (Ctrl) | Q132: 01 | R132: USD | S132: 926.11 | T132: INR | U132: 79646.08 | V132: O0 | W132: 6779224500 | Z132: 1 | AD132: =_xlfn.XLOOKUP(M132,'Customer Data Vlookup'!$R:$R,'Customer Data Vlookup'!$S:$S,,0) -> #N/A | AG132: VAS - 16-30 June 25 | AK132: 45842
A133: Selected | B133: 6779 | C133: 100222372 | D133: SHAH TC GLOBAL EXIM LLP | E133: 2025 | F133: 7 | G133: 45842 | H133: 1600001539 | I133: DG | J133: 45842 | K133: 45846 | L133: NA | M133: 256779421172 | N133: 212100 | O133: Trade Debtors (Ctrl) | Q133: 11 | R133: USD | S133: -1700 | T133: INR | U133: -146201.14 | V133: O0 | W133: 6779224500 | Y133: NA | Z133: 1 | AD133: =_xlfn.XLOOKUP(M133,'Customer Data Vlookup'!$R:$R,'Customer Data Vlookup'!$S:$S,,0) -> #N/A | AG133: CN against 256779410006 | AK133: 45842 | AL133: 45902 | AM133: 1400001110
A134: Selected | B134: 6779 | C134: 100222372 | D134: SHAH TC GLOBAL EXIM LLP | E134: 2025 | F134: 7 | G134: 45842 | H134: 1600001540 | I134: DG | J134: 45842 | K134: 45846 | L134: NA | M134: 256779421173 | N134: 212100 | O134: Trade Debtors (Ctrl) | Q134: 11 | R134: USD | S134: -1750 | T134: INR | U134: -150501.17 | V134: O0 | W134: 6779224500 | Y134: NA | Z134: 1 | AD134: =_xlfn.XLOOKUP(M134,'Customer Data Vlookup'!$R:$R,'Customer Data Vlookup'!$S:$S,,0) -> #N/A | AG134: CN against 256779410012 | AK134: 45842 | AL134: 45902 | AM134: 1400001110
A135: Selected | B135: 6779 | C135: 100222372 | D135: SHAH TC GLOBAL EXIM LLP | E135: 2025 | F135: 7 | G135: 45842 | H135: 1600001541 | I135: DG | J135: 45842 | K135: 45846 | L135: NA | M135: 256779421174 | N135: 212100 | O135: Trade Debtors (Ctrl) | Q135: 11 | R135: USD | S135: -1700 | T135: INR | U135: -146201.14 | V135: O0 | W135: 6779224500 | Y135: NA | Z135: 1 | AD135: =_xlfn.XLOOKUP(M135,'Customer Data Vlookup'!$R:$R,'Customer Data Vlookup'!$S:$S,,0) -> #N/A | AG135: CN against 256779410015 | AK135: 45842 | AL135: 45902 | AM135: 1400001110
A136: Selected | B136: 6779 | C136: 100222372 | D136: SHAH TC GLOBAL EXIM LLP | E136: 2025 | F136: 7 | G136: 45842 | H136: 1600001542 | I136: DG | J136: 45842 | K136: 45846 | L136: NA | M136: 256779421175 | N136: 212100 | O136: Trade Debtors (Ctrl) | Q136: 11 | R136: USD | S136: -1750 | T136: INR | U136: -150501.17 | V136: O0 | W136: 6779224500 | Y136: NA | Z136: 1 | AD136: =_xlfn.XLOOKUP(M136,'Customer Data Vlookup'!$R:$R,'Customer Data Vlookup'!$S:$S,,0) -> #N/A | AG136: CN against 256779410224 | AK136: 45842 | AL136: 45902 | AM136: 1400001110
A137: Not Selected | B137: 6779 | C137: 100222372 | D137: SHAH TC GLOBAL EXIM LLP | E137: 2025 | F137: 11 | G137: 45966 | H137: 1800014283 | I137: DR | J137: 45966 | K137: 45967 | L137: NA | M137: 256779418820 | N137: 212100 | O137: Trade Debtors (Ctrl) | Q137: 01 | R137: USD | S137: 351.13 | T137: INR | U137: 30900.63 | V137: O0 | W137: 6779224500 | Y137: 2123387 | Z137: 1 | AD137: =_xlfn.XLOOKUP(M137,'Customer Data Vlookup'!$R:$R,'Customer Data Vlookup'!$S:$S,,0) -> #N/A | AG137: VAS-16 -31 Oct 25 | AK137: 45966
...

Sheet Customer Data
A1: Ref. 2 (Header) | B1: Document Date | C1: Series | D1: Doc. No. | E1: Remarks | F1: Offset Acct Name | G1: Debit (LC) | H1: Credit (LC) | I1: Cumulative Balance (LC) | J1: Debit (FC) | K1: Credit (FC) | L1: Cumulative Balance (FC) | M1: Balance Due (FC) | N1: Branch Name | O1: Vlookup | P1: Diff | Q1: Remarks
A2: 246779410009 | B2: 45707 | C2: BOS2425M | D2: PU 7350308 | E2: A/P Invoices - VD0304 | F2: Rent - Ascendas | H2: 91693.278 | I2: -1027809.8 | K2: 1071.432 | L2: -12009.933 | M2: 0 | N2: Shah TC Global Exim LLP - Mumbai | R2: =L2+K2 -> -10938.501
A3: 246779410276 | B3: 45708 | C3: BOS2425M | D3: PU 7350273 | E3: A/P Invoices - VD0304 | F3: Rent - Ascendas | H3: 91693.278 | I3: -216491.67 | K3: 1071.432 | L3: -2529.6996 | M3: 0 | N3: Shah TC Global Exim LLP - Mumbai
A4: 246779410209 | B4: 45708 | C4: BOS2425M | D4: PU 7350274 | E4: A/P Invoices - VD0304 | F4: Rent - Ascendas | H4: 89852.772 | I4: -306344.44 | K4: 1049.931 | L4: -3579.6306 | M4: 0 | N4: Shah TC Global Exim LLP - Mumbai
A5: 246779414604 | B5: 45708 | C5: BOS2425M | D5: PU 7350275 | E5: A/P Invoices - VD0304 | F5: Handeling & Agency Charges | H5: 38416.775 | I5: -254908.44 | K5: 448.8988 | L5: -2978.5984 | M5: 0 | N5: Shah TC Global Exim LLP - Mumbai
A6: 246779410209 | B6: 45708 | C6: BOS2425M | D6: PU 7350276 | E6: A/P Invoices - VD0304 | F6: Management Fees (Ascendas) | H6: 34244.17 | I6: -254207 | K6: 400.1438 | L6: -2970.4056 | M6: 0 | N6: Shah TC Global Exim LLP - Mumbai
A7: 246779410308 | B7: 45708 | C7: BOS2425M | D7: PU 7350277 | E7: A/P Invoices - VD0304 | F7: Management Fees (Ascendas) | H7: 34945.619 | I7: -289152.61 | K7: 408.3366 | L7: -3378.7422 | M7: 0 | N7: Shah TC Global Exim LLP - Mumbai
A8: 246779410097 | B8: 45708 | C8: BOS2425M | D8: PU 7350278 | E8: A/P Invoices - VD0304 | F8: Rent - Ascendas | H8: 91693.278 | I8: -380845.89 | K8: 1071.432 | L8: -4450.1742 | M8: 0 | N8: Shah TC Global Exim LLP - Mumbai
A9: 246779410123 | B9: 45708 | C9: BOS2425M | D9: PU 7350280 | E9: A/P Invoices - VD0304 | F9: Management Fees (Ascendas) | H9: 34945.619 | I9: -422343.02 | K9: 408.3366 | L9: -4935.0684 | M9: 0 | N9: Shah TC Global Exim LLP - Mumbai
A10: 246779410252 | B10: 45708 | C10: BOS2425M | D10: PU 7350301 | E10: A/P Invoices - VD0304 | F10: Management Fees (Ascendas) | H10: 33554.702 | I10: -670976.67 | K10: 392.0882 | L10: -7840.3468 | M10: 0 | N10: Shah TC Global Exim LLP - Mumbai
A11: 246779410166 | B11: 45708 | C11: BOS2425M | D11: PU 7350302 | E11: A/P Invoices - VD0304 | F11: Management Fees (Ascendas) | H11: 34945.619 | I11: -705922.29 | K11: 408.3366 | L11: -8248.6834 | M11: 0 | N11: Shah TC Global Exim LLP - Mumbai
A12: 246779410140 | B12: 45708 | C12: BOS2425M | D12: PU 7350303 | E12: A/P Invoices - VD0304 | F12: Rent - Ascendas | H12: 91693.278 | I12: -797615.56 | K12: 1071.432 | L12: -9320.1154 | M12: 0 | N12: Shah TC Global Exim LLP - Mumbai
A13: 246779410226 | B13: 45708 | C13: BOS2425M | D13: PU 7350304 | E13: A/P Invoices - VD0304 | F13: Rent - Ascendas | H13: 88045.21 | I13: -885660.77 | K13: 1028.808 | L13: -10348.923 | M13: 0 | N13: Shah TC Global Exim LLP - Mumbai
A14: 246779410077 | B14: 45708 | C14: BOS2425M | D14: PU 7350309 | E14: A/P Invoices - VD0304 | F14: Management Fees (Ascendas) | H14: 34945.619 | I14: -1062755.5 | K14: 408.3366 | L14: -12418.27 | M14: 0 | N14: Shah TC Global Exim LLP - Mumbai
... A44: 246779413797 | B44: 45736 | C44: BOS2425M | D44: PU 7350282 | E44: A/P Invoices - VD0304 | F44: Ground Rent (Container) | H44: 147112 | I44: -573877.65 | K44: 1719 | L44: -6705.7438 | M44: 0 | N44: Shah TC Global Exim LLP - Mumbai
B45: 45736 | C45: JRN2425M | D45: JE 7353113 | E45: Being TDS deduction on 246779413797 ascendas | F45: Tds Payable- 94Ib - Rent | G45: 1711.6 | I45: -578541.85 | J45: 20 | L45: -6760.2434 | M45: 0 | N45: Shah TC Global Exim LLP - Mumbai
A46: 246779413828 | B46: 45736 | C46: BOS2425M | D46: PU 7350284 | E46: A/P Invoices - VD0304 | F46: Vos Miscellaneous Charges | H46: 4193 | I46: -582734.85 | K46: 49 | L46: -6809.2434 | M46: 0 | N46: Shah TC Global Exim LLP - Mumbai
A47: 246779414468 | B47: 45736 | C47: BOS2425M | D47: PU 7350289 | E47: A/P Invoices - VD0304 | F47: Handeling & Agency Charges | H47: 7734.1876 | I47: -597481.38 | K47: 90.3756 | L47: -6981.5568 | M47: 0 | N47: Shah TC Global Exim LLP - Mumbai
A48: 246779414682 | B48: 45736 | C48: BOS2425M | D48: PU 7350290 | E48: A/P Invoices - VD0304 | F48: Handeling & Agency Charges | H48: 7619.7988 | I48: -605101.18 | K48: 89.0428 | L48: -7070.5996 | M48: 0 | N48: Shah TC Global Exim LLP - Mumbai
A49: 246779414735 | B49: 45736 | C49: BOS2425M | D49: PU 7350291 | E49: A/P Invoices - VD0304 | F49: Handeling & Agency Charges | H49: 8168.492 | I49: -613269.67 | K49: 95.452 | L49: -7166.0516 | M49: 0 | N49: Shah TC Global Exim LLP - Mumbai
A50: 246779414886 | B50: 45736 | C50: BOS2425M | D50: PU 7350292 | E50: A/P Invoices - VD0304 | F50: Handeling & Agency Charges | H50: 2582.864 | I50: -615852.53 | K50: 30.184 | L50: -7196.2356 | M50: 0 | N50: Shah TC Global Exim LLP - Mumbai
A51: 246779414397 | B51: 45736 | C51: BOS2425M | D51: PU 7350293 | E51: A/P Invoices - VD0304 | F51: Handeling & Agency Charges | H51: 589.6274 | I51: -616442.16 | K51: 6.8894 | L51: -7203.125 | M51: 0 | N51: Shah TC Global Exim LLP - Mumbai
A52: 246779414887 | B52: 45736 | C52: BOS2425M | D52: PU 7350294 | E52: A/P Invoices - VD0304 | F52: Handeling & Agency Charges | H52: 610.1666 | I52: -617052.33 | K52: 7.1246 | L52: -7210.2496 | M52: 0 | N52: Shah TC Global Exim LLP - Mumbai
A53: 256779414888 | B53: 45736 | C53: BOS2425M | D53: PU 7350295 | E53: A/P Invoices - VD0304 | F53: Handeling & Agency Charges | H53: 914.6778 | I53: -617967 | K53: 10.6918 | L53: -7220.9414 | M53: 0 | N53: Shah TC Global Exim LLP - Mumbai
A54: 246779414889 | B54: 45736 | C54: BOS2425M | D54: PU 7350296 | E54: A/P Invoices - VD0304 | F54: Handeling & Agency Charges | H54: 211.6616 | I54: -618178.67 | K54: 2.4696 | L54: -7223.411 | M54: 0 | N54: Shah TC Global Exim LLP - Mumbai
A55: 246779414398 | B55: 45736 | C55: BOS2425M | D55: PU 7350297 | E55: A/P Invoices - VD0304 | F55: Handeling & Agency Charges | H55: 2716.0804 | I55: -620894.75 | K55: 31.7324 | L55: -7255.1434 | M55: 0 | N55: Shah TC Global Exim LLP - Mumbai
A56: 246779414890 | B56: 45736 | C56: BOS2425M | D56: PU 7350298 | E56: A/P Invoices - VD0304 | F56: Handeling & Agency Charges | H56: 3690.52 | I56: -624585.27 | K56: 43.12 | L56: -7298.2634 | M56: 0 | N56: Shah TC Global Exim LLP - Mumbai
B57: 45736 | C57: JRN2425M | D57: JE 7353132 | E57: Being TDS deduction on 246779413797 ascendas | F57: Tds Payable- 94Ib - Rent | H57: 1711.6 | I57: -635710.36 | K57: 20 | L57: -7428.2586 | M57: 0 | N57: Shah TC Global Exim LLP - Mumbai
B58: 45736 | C58: JRN2425M | D58: JE 7353133 | E58: Being TDS deduction on 246779413797 ascendas(Reversal) - 7619 | F58: Tds Payable- 94Ib - Rent | G58: -1711.6 | I58: -637421.96 | J58: -20 | L58: -7448.2586 | M58: 0 | N58: Shah TC Global Exim LLP - Mumbai
A59: 246779413905 | B59: 45736 | C59: BOS2425M | D59: PU 7350306 | E59: A/P Invoices - VD0304 | F59: Handeling & Agency Charges | H59: 368.552 | I59: -929655.47 | K59: 4.312 | L59: -10863.002 | M59: 0 | N59: Shah TC Global Exim LLP - Mumbai
A60: 246779414399 | B60: 45736 | C60: BOS2425M | D60: PU 7350307 | E60: A/P Invoices - VD0304 | F60: Handeling & Agency Charges | H60: 6461.0832 | I60: -936116.56 | K60: 75.4992 | L60: -10938.501 | M60: 0 | N60: Shah TC Global Exim LLP - Mumbai
A61: 246779414222 | B61: 45736 | C61: BOS2425M | D61: PU 7350312 | E61: A/P Invoices - VD0304 | F61: Handeling & Agency Charges | H61: 16503.432 | I61: -1237895.5 | K61: 192.8444 | L61: -14464.784 | M61: 0 | N61: Shah TC Global Exim LLP - Mumbai
A62: 246779414143 | B62: 45736 | C62: BOS2425M | D62: PU 7350313 | E62: A/P Invoices - VD0304 | F62: Handeling & Agency Charges | H62: 47478.694 | I62: -1285374.2 | K62: 554.7878 | L62: -15019.572 | M62: 0 | N62: Shah TC Global Exim LLP - Mumbai
A63: 246779413817 | B63: 45736 | C63: BOS2425M | D63: PU 7350317 | E63: A/P Invoices - VD0304 | F63: Vos Miscellaneous Charges | H63: 4193 | I63: -1336872.7 | K63: 49 | L63: -15621.331 | M63: 0 | N63: Shah TC Global Exim LLP - Mumbai
A64: 246779414146 | B64: 45736 | C64: BOS2425M | D64: PU 7350318 | E64: A/P Invoices - VD0304 | F64: Ground Rent (Container) | H64: 1489.973 | I64: -1338362.7 | K64: 17.415 | L64: -15638.746 | M64: 0 | N64: Shah TC Global Exim LLP - Mumbai
A65: 246779413808 | B65: 45736 | C65: BOS2425M | D65: PU 7350319 | E65: A/P Invoices - VD0304 | F65: Ground Rent (Container) | H65: 134532 | I65: -1472894.7 | K65: 1572 | L65: -17210.746 | M65: 0 | N65: Shah TC Global Exim LLP - Mumbai
B66: 45736 | C66: JRN2425M | D66: JE 7353155 | E66: Being TDS deduction on 246779413808 ascendas | F66: Tds Payable- 94Ib - Rent | G66: 1711.6 | I66: -1471183.1 | J66: 20 | L66: -17190.746 | M66: 0 | N66: Shah TC Global Exim LLP - Mumbai
A67: 246779414145 | B67: 45736 | C67: BOS2425M | D67: PU 7350320 | E67: A/P Invoices - VD0304 | F67: Reefer Plug In | H67: 12580 | I67: -1483763.1 | K67: 147 | L67: -17337.746 | M67: 0 | N67: Shah TC Global Exim LLP - Mumbai
A68: 246779414144 | B68: 45736 | C68: BOS2425M | D68: PU 7350330 | E68: A/P Invoices - VD0304 | F68: LCL CHARGES | H68: 10567.08 | I68: -1790630.5 | K68: 123.48 | L68: -20923.485 | M68: 0 | N68: Shah TC Global Exim LLP - Mumbai
B69: 45736 | C69: JRN2425M | D69: JE 7353198 | E69: Being TDS deduction on 246779413797 ascendas | F69: Tds Payable- 94Ib - Rent | G69: 1711.6 | I69: -1854196.3 | J69: 20 | L69: -21666.235 | M69: 0 | N69: Shah TC Global Exim LLP - Mumbai
B70: 45736 | C70: JRN2425M | D70: JE 7353199 | E70: Being TDS deduction on 246779413797 ascendas(Reversal) - 7646 | F70: Tds Payable- 94Ib - Rent | H70: -1711.6 | I70: -1852484.7 | K70: -20 | L70: -21646.235 | M70: 0 | N70: Shah TC Global Exim LLP - Mumbai
A71: 246779414318 | B71: 45737 | C71: BOS2425M | D71: PU 7350300 | E71: A/P Invoices - VD0304 | F71: Handeling & Agency Charges | H71: 3836.4292 | I71: -633998.76 | K71: 44.8252 | L71: -7408.2586 | M71: 0 | N71: Shah TC Global Exim LLP - Mumbai
A72: 246779412238 | B72: 45747 | C72: CL2425M | D72: PU 300025 | E72: A/P Invoice - Cancellation - VD0304 | F72: Vos Miscellaneous Charges | H72: -79318.285 | I72: -1855753.7 | K72: -926.835 | L72: -21684.435 | M72: 0 | N72: Shah TC Global Exim LLP - Mumbai
A73: 256779410224 | B73: 45750 | C73: BOS2526M | D73: PU 7360034 | E73: A/P Invoices - VD0304 | F73: Ground Rent (Container) | H73: 146940 | I73: -2290181.3 | K73: 1719 | L73: -26762.798 | M73: 0 | N73: Shah TC Global Exim LLP - Mumbai
A74: 256779410224 | B74: 45750 | C74: JRN2526M | D74: JE 7360255 | E74: Being tds deduction for rent against bill no.-256779410224 dated-03-04-2025. | F74: Tds Payable- 94Ib - Rent | G74: 1709.6 | I74: -2288471.7 | J74: 20 | L74: -26742.798 | M74: 0 | N74: Shah TC Global Exim LLP - Mumbai
A75: 256779410006 | B75: 45750 | C75: BOS2526M | D75: PU 7360052 | E75: A/P Invoices - VD0304 | F75: Rent - Ascendas | H75: 143269 | I75: -1819439.9 | K75: 1670 | L75: -21248.666 | M75: 0 | N75: Shah TC Global Exim LLP - Mumbai
A76: 256779410006 | B76: 45750 | C76: JRN2526M | D76: JE 7360300 | E76: Being TDS entry passed for the ground rent charges against bill no. 256779410006 dated 03-04-2025. | F76: Tds Payable- 94Ib - Rent | G76: 1715.8 | I76: -1817724.1 | J76: 20 | L76: -21228.666 | M76: 0 | N76: Shah TC Global Exim LLP - Mumbai
A77: 256779410012 | B77: 45750 | C77: BOS2526M | D77: PU 7360053 | E77: A/P Invoices - VD0304 | F77: Rent - Ascendas | H77: 147473.5 | I77: -1965197.6 | K77: 1719 | L77: -22947.666 | M77: 0 | N77: Shah TC Global Exim LLP - Mumbai
A78: 256779410015 | B78: 45750 | C78: BOS2526M | D78: PU 7360054 | E78: A/P Invoices - VD0304 | F78: Rent - Ascendas | H78: 143269 | I78: -2108466.6 | K78: 1670 | L78: -24617.666 | M78: 0 | N78: Shah TC Global Exim LLP - Mumbai
A79: 256779410015 | B79: 45750 | C79: JRN2526M | D79: JE 7360303 | E79: Being Ground rent charges tds booked against bill no. 256779410015 dated 03-04-2025. | F79: Tds Payable- 94Ib - Rent | G79: 1715.8 | I79: -2106750.8 | J79: 20 | L79: -24597.666 | M79: 0 | N79: Shah TC Global Exim LLP - Mumbai
A80: 256779410012 | B80: 45750 | C80: JRN2526M | D80: JE 7360304 | E80: BEing Ground Rent Charges tds booked against bill no 256779410012 dated 03-04-2025. | F80: Tds Payable- 94Ib - Rent | G80: 1715.8 | I80: -2105035 | J80: 20 | L80: -24577.666 | M80: 0 | N80: Shah TC Global Exim LLP - Mumbai
A81: 256779410136 | B81: 45750 | C81: BOS2526M | D81: PU 7360171 | E81: A/P Invoices - VD0304 | F81: Inbound & Outbound Handling | H81: 838.374 | I81: -896611.71 | K81: 9.653 | L81: -10447.436 | M81: 0 | N81: Shah TC Global Exim LLP - Mumbai
A82: 256779411152 | B82: 45762 | C82: BOS2526M | D82: PU 7360133 | E82: A/P Invoices - VD0304 | F82: Empty Return - Outward | H82: 13942.089 | I82: -736955.3 | K82: 161.09 | L82: -8607.1788 | M82: 0 | N82: Shah TC Global Exim LLP - Mumbai
A83: 256779411153 | B83: 45762 | C83: BOS2526M | D83: PU 7360134 | E83: A/P Invoices - VD0304 | F83: LCL CHARGES | H83: 2251.037 | I83: -739206.34 | K83: 26.01 | L83: -8633.1888 | M83: 0 | N83: Shah TC Global Exim LLP - Mumbai
A84: 256779411154 | B84: 45762 | C84: BOS2526M | D84: PU 7360135 | E84: A/P Invoices - VD0304 | F84: LCL CHARGES | H84: 7146.703 | I84: -746353.04 | K84: 82.57 | L84: -8715.7588 | M84: 0 | N84: Shah TC Global Exim LLP - Mumbai
A85: 256779411155 | B85: 45762 | C85: BOS2526M | D85: PU 7360136 | E85: A/P Invoices - VD0304 | F85: Inbound & Outbound Handling | H85: 3129.695 | I85: -749482.73 | K85: 36.16 | L85: -8751.9188 | M85: 0 | N85: Shah TC Global Exim LLP - Mumbai
A86: 256779411156 | B86: 45762 | C86: BOS2526M | D86: PU 7360137 | E86: A/P Invoices - VD0304 | F86: Inbound & Outbound Handling | H86: 1715.9065 | I86: -751198.64 | K86: 19.83 | L86: -8771.7488 | M86: 0 | N86: Shah TC Global Exim LLP - Mumbai
A87: 256779411157 | B87: 45762 | C87: BOS2526M | D87: PU 7360138 | E87: A/P Invoices - VD0304 | F87: Inbound & Outbound Handling | H87: 9866.496 | I87: -761065.14 | K87: 113.99 | L87: -8885.7388 | M87: 0 | N87: Shah TC Global Exim LLP - Mumbai
A88: 256779411565 | B88: 45762 | C88: BOS2526M | D88: PU 7360139 | E88: A/P Invoices - VD0304 | F88: Inbound & Outbound Handling | H88: 1866.1 | I88: -762931.24 | K88: 21.56 | L88: -8907.2988 | M88: 0 | N88: Shah TC Global Exim LLP - Mumbai
A89: 256779411566 | B89: 45762 | C89: BOS2526M | D89: PU 7360140 | E89: A/P Invoices - VD0304 | F89: Inbound & Outbound Handling | H89: 372.82 | I89: -763304.06 | K89: 4.31 | L89: -8911.6088 | M89: 0 | N89: Shah TC Global Exim LLP - Mumbai
A90: 256779411567 | B90: 45762 | C90: BOS2526M | D90: PU 7360141 | E90: A/P Invoices - VD0304 | F90: Inbound & Outbound Handling | H90: 495.452 | I90: -763799.51 | K90: 5.72 | L90: -8917.3288 | M90: 0 | N90: Shah TC Global Exim LLP - Mumbai
A91: 256779411568 | B91: 45762 | C91: BOS2526M | D91: PU 7360142 | E91: A/P Invoices - VD0304 | F91: Inbound & Outbound Handling | H91: 68.24 | I91: -763867.75 | K91: 0.78 | L91: -8918.1088 | M91: 0 | N91: Shah TC Global Exim LLP - Mumbai
A92: 256779411569 | B92: 45762 | C92: BOS2526M | D92: PU 7360143 | E92: A/P Invoices - VD0304 | F92: Inbound & Outbound Handling | H92: 1174.7175 | I92: -765042.47 | K92: 13.57 | L92: -8931.6788 | M92: 0 | N92: Shah TC Global Exim LLP - Mumbai
... A134: 256779414217 | B134: 45812 | C134: BOS2526M | D134: PU 7360170 | E134: A/P Invoices - VD0304 | F134: Inbound & Outbound Handling | H134: 6106.6384 | I134: -895773.34 | K134: 70.3248 | L134: -10437.783 | M134: 0 | N134: Shah TC Global Exim LLP - Mumbai
B135: 45813 | C135: OPY2526M | D135: PS 7360069 | E135: Outgoing Payments - VD0304, Being Amount paid to ascendas against bank ref. no-003MISC251560088 dated 5-6-2025. | F135: YES BANK - 038784600000486 - CC A/c(SGE) | G135: 302049.55 | I135: -2005635.8 | J135: 3529.5558 | L135: -23438.015 | M135: 0 | N135: Shah TC Global Exim LLP - Mumbai
B136: 45813 | C136: OPY2526M | D136: PS 7360072 | E136: Outgoing Payments - VD0304,Being Amount paid to ascendas against bank ref. no-003MISC251560102 dated 5-6-2025. | F136: YES BANK - 038784600000486 - CC A/c(SGE) | G136: 271057.81 | I136: -1734578 | J136: 3167.4752 | L136: -20270.54 | M136: 0 | N136: Shah TC Global Exim LLP - Mumbai
B137: 45813 | C137: OPY2526M | D137: PS 7360074 | E137: Outgoing Payments - VD0304,Being Amount paid to ascendas against bank ref. no-003MISC251560090 dated 5-6-2025. | F137: YES BANK - 038784600000486 - CC A/c(SGE) | G137: 315203.35 | I137: -1419374.7 | J137: 3685.2032 | L137: -16585.337 | M137: 0 | N137: Shah TC Global Exim LLP - Mumbai
A138: 256779413185 | B138: 45815 | C138: BOS2526M | D138: PU 7360040 | E138: A/P Invoices - VD0304 | F138: Ground Rent (Container) | H138: 15442 | I138: -1473467.4 | K138: 180 | L138: -17215.859 | M138: 0 | N138: Shah TC Global Exim LLP - Mumbai
A139: 256779414240 | B139: 45815 | C139: BOS2526M | D139: PU 7360085 | E139: A/P Invoices - VD0304 | F139: Rent - Ascendas | H139: 103047.89 | I139: -770580.1 | K139: 1205.1 | L139: -9005.1888 | M139: 0 | N139: Shah TC Global Exim LLP - Mumbai
A140: 256779414357 | B140: 45818 | C140: BOS2526M | D140: PU 7360086 | E140: A/P Invoices - VD0304 | F140: Rent - Ascendas | H140: 31506.794 | I140: -802086.89 | K140: 368.46 | L140: -9373.6488 | M140: 0 | N140: Shah TC Global Exim LLP - Mumbai
A141: 256779414356 | B141: 45818 | C141: BOS2526M | D141: PU 7360087 | E141: A/P Invoices - VD0304 | F141: Rent - Ascendas | H141: 90020.757 | I141: -892107.65 | K141: 1052.748 | L141: -10426.397 | M141: 0 | N141: Shah TC Global Exim LLP - Mumbai
B142: 45821 | C142: OPY2526M | D142: PS 7360113 | E142: Outgoing Payments - VD0304,Being Amount paid to ascendas against bank ref. no-003FT01251640051 dated 13-6-2025. | F142: HDFC Bank - INR | G142: 1075024.8 | I142: -1030010.2 | J142: 12549.359 | L142: -12028.307 | M142: 0 | N142: Shah TC Global Exim LLP - Mumbai
B143: 45821 | C143: OPY2526M | D143: PS 7360143 | E143: Outgoing Payments - VD0304,Being Amount paid to ascendas against bank ref. no-003FT01251640038 dated 13-6-2025. | F143: HDFC Bank - INR | G143: 353878.05 | I143: -676132.12 | L143: -12028.307 | N143: Shah TC Global Exim LLP - Mumbai
B144: 45821 | C144: OPY2526M | D144: PS 7360143 | E144: Reverse Entry for Payment No. 7360143 | F144: HDFC Bank - INR | G144: -353878.05 | I144: -1030010.2 | L144: -12028.307 | N144: Shah TC Global Exim LLP - Mumbai
B145: 45821 | C145: OPY2526M | D145: PS 7360144 | E145: Outgoing Payments - VD0304,Being Amount paid to ascendas against bank ref. no-003FT01251640038 dated 13-6-2025. | F145: HDFC Bank - INR | G145: 353878.05 | I145: -676132.12 | J145: 4127.955 | L145: -7900.3518 | M145: 0 | N145: Shah TC Global Exim LLP - Mumbai
A146: 246779410871 | B146: 45821 | C146: JRN2526M | D146: JE 7360530 | E146: Being $3.4008 less paid in this bill because in summary sheet 2% tds deduscted instead of 10% | F146: HDFC Bank - INR | G146: 290.9044 | I146: -675841.21 | J146: 3.4008 | L146: -7896.951 | M146: 3.4008 | N146: Shah TC Global Exim LLP - Mumbai
B147: 45821 | C147: OPY2526M | D147: PS 7360144 | E147: Reverse Entry for Payment No. 7360144 | F147: HDFC Bank - INR | G147: -353878.05 | I147: -1029719.3 | J147: -4127.955 | L147: -12024.906 | M147: 0 | N147: Shah TC Global Exim LLP - Mumbai
B148: 45821 | C148: OPY2526M | D148: PS 7360145 | E148: Outgoing Payments - VD0304,Being Amount paid to ascendas against bank ref. no-003FT01251640038 dated 13-6-2025. | F148: HDFC Bank - INR | G148: 362187.05 | I148: -667532.21 | J148: 4224.8172 | L148: -7800.0888 | M148: 0 | N148: Shah TC Global Exim LLP - Mumbai
A149: 256779414341 | B149: 45821 | C149: BOS2526M | D149: PU 7360113 | E149: A/P Invoices - VD0304 | F149: Vos Miscellaneous Charges | H149: 16823 | I149: -1035236.6 | K149: 196 | L149: -12098.137 | M149: 0 | N149: Shah TC Global Exim LLP - Mumbai
A150: 256779414317 | B150: 45827 | C150: BOS2526M | D150: PU 7360091 | E150: A/P Invoices - VD0304 | F150: Vos Miscellaneous Charges | H150: 58444.239 | I150: -987513.64 | K150: 683.4814 | L150: -11542.137 | M150: 0 | N150: Shah TC Global Exim LLP - Mumbai
A151: 246779414733 | B151: 45827 | C151: BOS2526M | D151: PU 7360106 | E151: A/P Invoices - VD0304 | F151: Rent - Ascendas | H151: 7725 | I151: -1002963.6 | K151: 90 | L151: -11722.137 | M151: 0 | N151: Shah TC Global Exim LLP - Mumbai
A152: 246779414732 | B152: 45827 | C152: BOS2526M | D152: PU 7360107 | E152: A/P Invoices - VD0304 | F152: Rent - Ascendas | H152: 7725 | I152: -1010688.6 | K152: 90 | L152: -11812.137 | M152: 0 | N152: Shah TC Global Exim LLP - Mumbai
A153: 246779414731 | B153: 45827 | C153: BOS2526M | D153: PU 7360108 | E153: A/P Invoices - VD0304 | F153: Rent - Ascendas | H153: 7725 | I153: -1018413.6 | K153: 90 | L153: -11902.137 | M153: 0 | N153: Shah TC Global Exim LLP - Mumbai
A154: 246779414734 | B154: 45827 | C154: BOS2526M | D154: PU 7360109 | E154: A/P Invoices - VD0304 | F154: Rent - Ascendas | H154: 7725 | I154: -995238.64 | K154: 90 | L154: -11632.137 | M154: 0 | N154: Shah TC Global Exim LLP - Mumbai
A155: 256779414735 | B155: 45827 | C155: BOS2526M | D155: PU 7360124 | E155: A/P Invoices - VD0304 | F155: Rent - Ascendas | H155: 7758 | I155: -723013.21 | K155: 90 | L155: -8446.0888 | M155: 0 | N155: Shah TC Global Exim LLP - Mumbai
A156: 256779414772 | B156: 45842 | C156: BOS2526M | D156: PU 7360163 | E156: A/P Invoices - VD0304 | F156: Transportation (Inbound) | H156: 18722.8 | I156: -801147.96 | K156: 215.6 | L156: -9348.1218 | M156: 0 | N156: Shah TC Global Exim LLP - Mumbai
A157: 256779414956 | B157: 45842 | C157: BOS2526M | D157: PU 7360164 | E157: A/P Invoices - VD0304 | F157: Empty Return - Outward | H157: 4255 | I157: -805402.96 | K157: 49 | L157: -9397.1218 | M157: 0 | N157: Shah TC Global Exim LLP - Mumbai
A158: 256779414957 | B158: 45842 | C158: BOS2526M | D158: PU 7360165 | E158: A/P Invoices - VD0304 | F158: Empty Return - Outward | H158: 4255 | I158: -809657.96 | K158: 49 | L158: -9446.1218 | M158: 0 | N158: Shah TC Global Exim LLP - Mumbai
A159: 256779414830 | B159: 45842 | C159: BOS2526M | D159: PU 7360166 | E159: A/P Invoices - VD0304 | F159: Inbound & Outbound Handling | H159: 12112.069 | I159: -821770.03 | K159: 139.4736 | L159: -9585.5954 | M159: 0 | N159: Shah TC Global Exim LLP - Mumbai
A160: 256779415017 | B160: 45842 | C160: BOS2526M | D160: PU 7360167 | E160: A/P Invoices - VD0304 | F160: Inbound & Outbound Handling | H160: 29722.738 | I160: -851492.77 | K160: 342.2748 | L160: -9927.8702 | M160: 0 | N160: Shah TC Global Exim LLP - Mumbai
... A168: 256779414915 | B168: 45852 | C168: BOS2526M | D168: PU 7360253 | E168: A/P Invoices - VD0304 | F168: Vos Miscellaneous Charges | H168: 34299.693 | I168: -368034.94 | K168: 398.8306 | L168: -4204.0632 | M168: 0 | N168: Shah TC Global Exim LLP - Mumbai
B169: 45856 | C169: OPY2526M | D169: PS 7360316 | E169: Outgoing Payments - VD0304,Being payment done against USD 3798.9858 ASCENDAS PANVEL FTWZ PRIVATE LIMITED, Bank ref no.- 003MISC251990131 dated-18-07-2025. | F169: YES BANK - USD | G169: 319981.43 | I169: -715255.21 | J169: 3742.0478 | L169: -8356.0888 | M169: 0 | N169: Shah TC Global Exim LLP - Mumbai
B170: 45856 | C170: OPY2526M | D170: PS 7360316 | E170: Reverse Entry for Payment No. 7360316 | F170: YES BANK - USD | G170: -319981.43 | I170: -1035236.6 | J170: -3742.0478 | L170: -12098.137 | M170: 0 | N170: Shah TC Global Exim LLP - Mumbai
B171: 45856 | C171: OPY2526M | D171: PS 7360331 | E171: Outgoing Payments - VD0304,Being payment done against USD 3798.9858 ASCENDAS PANVEL FTWZ PRIVATE LIMITED, Bank ref no.- 003MISC251990131 dated-18-07-2025. | F171: YES BANK - USD | G171: 319981.43 | I171: -715255.21 | J171: 3742.0478 | L171: -8356.0888 | M171: 0 | N171: Shah TC Global Exim LLP - Mumbai
A172: 256779415482 | B172: 45856 | C172: BOS2526M | D172: PU 7360197 | E172: A/P Invoices - VD0304 | F172: Transportation (Inbound) | H172: 71830.686 | I172: -769876.53 | K172: 824.79 | L172: -8919.8334 | M172: 0 | N172: Shah TC Global Exim LLP - Mumbai
A173: 256779415482 | B173: 45856 | C173: BOS2526M | D173: PU 7360198 | E173: A/P Invoices - VD0304 | F173: Ground Rent (Container) | H173: 1516.1915 | I173: -771392.72 | K173: 17.42 | L173: -8937.2534 | M173: 0 | N173: Shah TC Global Exim LLP - Mumbai
A174: 256779415701 | B174: 45856 | C174: BOS2526M | D174: PU 7360199 | E174: A/P Invoices - VD0304 | F174: Transportation (Inbound) | H174: 56058.2 | I174: -827450.92 | K174: 646.8 | L174: -9584.0534 | M174: 0 | N174: Shah TC Global Exim LLP - Mumbai
A175: 256779415432 | B175: 45856 | C175: BOS2526M | D175: PU 7360201 | E175: A/P Invoices - VD0304 | F175: Vos Miscellaneous Charges | H175: 25195.789 | I175: -861140.71 | K175: 290.71 | L175: -9972.7634 | M175: 0 | N175: Shah TC Global Exim LLP - Mumbai
A176: 256779415524 | B176: 45856 | C176: BOS2526M | D176: PU 7360255 | E176: A/P Invoices - VD0304 | F176: Inbound & Outbound Handling | H176: 6162.369 | I176: -382588.71 | K176: 71.6576 | L176: -4371.604 | M176: 0 | N176: Shah TC Global Exim LLP - Mumbai
A177: 256779415996 | B177: 45863 | C177: BOS2526M | D177: PU 7360196 | E177: A/P Invoices - VD0304 | F177: Vos Miscellaneous Charges | H177: 63294.978 | I177: -698045.84 | K177: 740.47 | L177: -8095.0434 | M177: 0 | N177: Shah TC Global Exim LLP - Mumbai
...

Sheet Sheet4
H1: =SUBTOTAL(9,H3:H301) -> 3504414.2 | J1: =SUBTOTAL(9,J3:J301) -> #REF!
A2: Document Number | B2: Document Type | C2: Document Date | D2: Reference | E2: Document Currency Key | F2: Document Currency Value | G2: Company Code Currency Key | H2: Company Code Currency Value | I2: Text | J2: Vlookup
A3: 1600000042 | B3: DA | C3: 45758 | E3: INR | F3: 1 | G3: INR | H3: 1 | I3: Overpayment | J3: =VLOOKUP(D3,#REF!,8,0) -> #REF!
A4: 1600000042 | B4: DA | C4: 45758 | E4: INR | F4: -1 | G4: INR | H4: -1 | I4: Overpayment | J4: =VLOOKUP(D4,#REF!,8,0) -> #REF!
A5: 1400001110 | B5: DY | C5: 45902 | E5: INR | F5: 603848.88 | G5: INR | H5: 595243.31 | J5: =VLOOKUP(D5,#REF!,8,0) -> #REF!
A6: 1400001110 | B6: DY | C6: 45902 | E6: INR | F6: -603848.88 | G6: INR | H6: -599760.56 | J6: =VLOOKUP(D6,#REF!,8,0) -> #REF!
A7: 1400000854 | B7: DZ | C7: 45887 | E7: USD | F7: -700.45 | G7: INR | H7: -60884.42 | J7: =VLOOKUP(D7,#REF!,8,0) -> #REF!
A8: 1400001231 | B8: DZ | C8: 45931 | E8: USD | F8: -4719.25 | G8: INR | H8: -413002 | J8: =VLOOKUP(D8,#REF!,8,0) -> #REF!
A9: 1400000977 | B9: DZ | C9: 45890 | E9: USD | F9: -3663.7 | G9: INR | H9: -313212.57 | J9: =VLOOKUP(D9,#REF!,8,0) -> #REF!
A10: 1400000990 | B10: DZ | C10: 45890 | E10: USD | F10: -3777.49 | G10: INR | H10: -324866.67 | J10: =VLOOKUP(D10,#REF!,8,0) -> #REF!
A11: 1400000126 | B11: DZ | C11: 45832 | E11: USD | F11: -3663.7 | G11: INR | H11: -3663.7 | J11: =VLOOKUP(D11,#REF!,8,0) -> #REF!
A12: 1400000127 | B12: DZ | C12: 45832 | E12: USD | F12: -3508.06 | G12: INR | H12: -3508.06 | J12: =VLOOKUP(D12,#REF!,8,0) -> #REF!
A13: 1400000128 | B13: DZ | C13: 45832 | E13: USD | F13: -3145.98 | G13: INR | H13: -3145.98 | J13: =VLOOKUP(D13,#REF!,8,0) -> #REF!
A14: 1400000133 | B14: DZ | C14: 45832 | E14: USD | F14: -12549.36 | G14: INR | H14: -12549.36 | J14: =VLOOKUP(D14,#REF!,8,0) -> #REF!
A15: 1400000134 | B15: DZ | C15: 45832 | E15: USD | F15: -4228.22 | G15: INR | H15: -4228.22 | J15: =VLOOKUP(D15,#REF!,8,0) -> #REF!
A16: 1400000149 | B16: DZ | C16: 45832 | E16: USD | F16: 3663.7 | G16: INR | H16: 3663.7 | J16: =VLOOKUP(D16,#REF!,8,0) -> #REF!
A17: 1400000854 | B17: DZ | C17: 45887 | E17: USD | F17: -4437.9 | G17: INR | H17: -383425.92 | J17: =VLOOKUP(D17,#REF!,8,0) -> #REF!
A18: 1400000864 | B18: DZ | C18: 45888 | E18: USD | F18: -1102.02 | G18: INR | H18: -94695.18 | I18: 8681446219FS | J18: =VLOOKUP(D18,#REF!,8,0) -> #REF!
A19: 1400001221 | B19: DZ | C19: 45924 | E19: USD | F19: -2932.84 | G19: INR | H19: -256665.53 | J19: =VLOOKUP(D19,#REF!,8,0) -> #REF!
A20: 1400001598 | B20: DZ | C20: 45964 | E20: USD | F20: -1731.27 | G20: INR | H20: -152682.03 | J20: =VLOOKUP(D20,#REF!,8,0) -> #REF!
A21: 1400001618 | B21: DZ | C21: 45972 | E21: USD | F21: -1968.44 | G21: INR | H21: -173229.39 | J21: =VLOOKUP(D21,#REF!,8,0) -> #REF!
A22: 1400001620 | B22: DZ | C22: 45972 | E22: USD | F22: -8339.84 | G22: INR | H22: -729855.51 | J22: =VLOOKUP(D22,#REF!,8,0) -> #REF!
A23: 1400001622 | B23: DZ | C23: 45972 | E23: USD | F23: -10455.66 | G23: INR | H23: -920133.52 | J23: =VLOOKUP(D23,#REF!,8,0) -> #REF!
A24: 1400000213 | B24: DY | C24: 45842 | D24: KNOCK OFF ENTRY | E24: USD | F24: 0 | G24: INR | H24: 0 | J24: =VLOOKUP(D24,#REF!,8,0) -> #REF!
A25: 1400000214 | B25: DY | C25: 45842 | D25: KNOCK OFF ENTRY | E25: USD | F25: 1166.59 | G25: INR | H25: 101402.13 | J25: =VLOOKUP(D25,#REF!,8,0) -> #REF!
A26: 1400000214 | B26: DY | C26: 45842 | D26: KNOCK OFF ENTRY | E26: USD | F26: -1166.59 | G26: INR | H26: -101402.13 | J26: =VLOOKUP(D26,#REF!,8,0) -> #REF!
A27: 1400000215 | B27: DY | C27: 45842 | D27: KNOCK OFF ENTRY | E27: USD | F27: 1143.12 | G27: INR | H27: 99362.07 | J27: =VLOOKUP(D27,#REF!,8,0) -> #REF!
A28: 1400000215 | B28: DY | C28: 45842 | D28: KNOCK OFF ENTRY | E28: USD | F28: -1143.12 | G28: INR | H28: -99362.07 | J28: =VLOOKUP(D28,#REF!,8,0) -> #REF!
A29: 1800008260 | B29: DR | C29: 45787 | D29: 256779413144 | E29: INR | F29: 100000 | G29: INR | H29: 100000 | I29: Fixed Storage Charges fo MAY 2025 | J29: =VLOOKUP(D29,#REF!,8,0) -> #REF! | K29: =H29-J29 -> #REF! | L29: =K29/H29 -> #REF!
A30: 1800009592 | B30: DR | C30: 45818 | D30: 256779414356 | E30: INR | F30: 100000 | G30: INR | H30: 100000 | I30: Fixed Storage Charges fo JUNE 2025 | J30: =VLOOKUP(D30,#REF!,8,0) -> #REF! | K30: =H30-J30 -> #REF! | L30: =K30/H30 -> #REF!
A31: 1800010154 | B31: DR | C31: 45842 | D31: 256779414914 | E31: INR | F31: 100000 | G31: INR | H31: 100000 | I31: Fixed Storage Charges fo JULY 2025 | J31: =VLOOKUP(D31,#REF!,8,0) -> #REF! | K31: =H31-J31 -> #REF! | L31: =K31/H31 -> #REF!
A32: 1800011360 | B32: DR | C32: 45870 | D32: 256779416026 | E32: INR | F32: 100000 | G32: INR | H32: 100000 | I32: Fixed Storage Charges for August 2025 | J32: =VLOOKUP(D32,#REF!,8,0) -> #REF! | K32: =H32-J32 -> #REF! | L32: =K32/H32 -> #REF!
A33: 1800012712 | B33: DR | C33: 45904 | D33: 256779417346 | E33: INR | F33: 100000 | G33: INR | H33: 100000 | I33: Fixed Storage Charges for September 2025 | J33: =VLOOKUP(D33,#REF!,8,0) -> #REF! | K33: =H33-J33 -> #REF! | L33: =K33/H33 -> #REF!
A34: 1800014235 | B34: DR | C34: 45966 | D34: 256779418775 | E34: INR | F34: 100000 | G34: INR | H34: 100000 | I34: Fixed Storage Charges for November 2025 | J34: =VLOOKUP(D34,#REF!,8,0) -> #REF! | K34: =H34-J34 -> #REF! | L34: =K34/H34 -> #REF!
A35: 1800015484 | B35: DR | C35: 45995 | D35: 256779419968 | E35: INR | F35: 100000 | G35: INR | H35: 100000 | I35: Fixed Storage Charges for December 2025 | J35: =VLOOKUP(D35,#REF!,8,0) -> #REF! | K35: =H35-J35 -> #REF! | L35: =K35/H35 -> #REF!
A36: 1800008261 | B36: DR | C36: 45787 | D36: 256779413145 | E36: INR | F36: 35000 | G36: INR | H36: 35000 | I36: Fixed Storage Charges fo MAY 2025 | J36: =VLOOKUP(D36,#REF!,8,0) -> #REF! | K36: =H36-J36 -> #REF! | L36: =K36/H36 -> #REF!
A37: 1800009593 | B37: DR | C37: 45818 | D37: 256779414357 | E37: INR | F37: 35000 | G37: INR | H37: 35000 | I37: Fixed Storage Charges fo JUNE 2025 | J37: =VLOOKUP(D37,#REF!,8,0) -> #REF! | K37: =H37-J37 -> #REF! | L37: =K37/H37 -> #REF!
A38: 1800010155 | B38: DR | C38: 45842 | D38: 256779414915 | E38: INR | F38: 35000 | G38: INR | H38: 35000 | I38: Fixed Storage Charges fo JULY 2025 | J38: =VLOOKUP(D38,#REF!,8,0) -> #REF! | K38: =H38-J38 -> #REF! | L38: =K38/H38 -> #REF!
A39: 1800011361 | B39: DR | C39: 45870 | D39: 256779416027 | E39: INR | F39: 35000 | G39: INR | H39: 35000 | I39: Fixed Storage Charges for August 2025 | J39: =VLOOKUP(D39,#REF!,8,0) -> #REF! | K39: =H39-J39 -> #REF! | L39: =K39/H39 -> #REF!
A40: 1800012713 | B40: DR | C40: 45904 | D40: 256779417347 | E40: INR | F40: 35000 | G40: INR | H40: 35000 | I40: Fixed Storage Charges for September 2025 | J40: =VLOOKUP(D40,#REF!,8,0) -> #REF! | K40: =H40-J40 -> #REF! | L40: =K40/H40 -> #REF!
... A42: 1800015485 | B42: DR | C42: 45995 | D42: 256779419969 | E42: INR | F42: 35000 | G42: INR | H42: 35000 | I42: Fixed Mangement FEE for December 2025 | J42: =VLOOKUP(D42,#REF!,8,0) -> #REF! | K42: =H42-J42 -> #REF! | L42: =K42/H42 -> #REF!
A43: 1600002145 | B43: DG | C43: 45890 | D43: 256779421709 | E43: INR | F43: -200000 | G43: INR | H43: -200000 | I43: CN issued towards D & D | J43: =VLOOKUP(D43,#REF!,8,0) -> #REF!
A44: 1800012258 | B44: DR | C44: 45883 | D44: 256779416887 | E44: INR | F44: 200000 | G44: INR | H44: 200000 | I44: DN issued towards D & D 256779421709 | J44: =VLOOKUP(D44,#REF!,8,0) -> #REF!
A45: 1800002451 | B45: DR | C45: 45733 | D45: 246779412116 | E45: USD | F45: 100 | G45: INR | H45: 8669.13 | I45: Intra Unit Transfer Charges Month Of December,2024 | J45: =VLOOKUP(D45,#REF!,8,0) -> #REF! | K45: =H45-J45 -> #REF! | L45: =K45/H45 -> #REF!
A46: 1800002454 | B46: DR | C46: 45733 | D46: 246779412119 | E46: USD | F46: 100 | G46: INR | H46: 8669.13 | I46: Intra Unit Transfer Charges Month Of December,2024 | J46: =VLOOKUP(D46,#REF!,8,0) -> #REF! | K46: =H46-J46 -> #REF! | L46: =K46/H46 -> #REF!
A47: 1800002456 | B47: DR | C47: 45733 | D47: 246779412121 | E47: USD | F47: 100 | G47: INR | H47: 8669.13 | I47: Intra Unit Transfer Charges Month Of December,2024 | J47: =VLOOKUP(D47,#REF!,8,0) -> #REF! | K47: =H47-J47 -> #REF! | L47: =K47/H47 -> #REF!
A48: 1800008348 | B48: DR | C48: 45787 | D48: 256779413231 | E48: USD | F48: 100 | G48: INR | H48: 8598.37 | I48: Intra Unit Transfer 16-30 April 25 | J48: =VLOOKUP(D48,#REF!,8,0) -> #REF! | K48: =H48-J48 -> #REF! | L48: =K48/H48 -> #REF!
A49: 1800009077 | B49: DR | C49: 45797 | D49: 256779413841 | E49: USD | F49: 100 | G49: INR | H49: 8598.37 | I49: Unit to Unit, 1-15 May 25 | J49: =VLOOKUP(D49,#REF!,8,0) -> #REF! | K49: =H49-J49 -> #REF! | L49: =K49/H49 -> #REF!
A50: 1800009083 | B50: DR | C50: 45797 | D50: 256779413847 | E50: USD | F50: 100 | G50: INR | H50: 8598.37 | I50: Unit to Unit, 1-15 May 25 | J50: =VLOOKUP(D50,#REF!,8,0) -> #REF! | K50: =H50-J50 -> #REF! | L50: =K50/H50 -> #REF!
A51: 1800009084 | B51: DR | C51: 45797 | D51: 256779413848 | E51: USD | F51: 100 | G51: INR | H51: 8598.37 | I51: Unit to Unit, 1-15 May 25 | J51: =VLOOKUP(D51,#REF!,8,0) -> #REF! | K51: =H51-J51 -> #REF! | L51: =K51/H51 -> #REF!
A52: 1800011280 | B52: DR | C52: 45863 | D52: 256779416012 | E52: USD | F52: 100 | G52: INR | H52: 8600.07 | I52: Unit to Unit 16-31 May 25 | J52: =VLOOKUP(D52,#REF!,8,0) -> #REF! | K52: =H52-J52 -> #REF! | L52: =K52/H52 -> #REF!
A53: 1800001850 | B53: DR | C53: 45730 | D53: 246779411515 | E53: USD | F53: 100 | G53: INR | H53: 8669.13 | I53: Intra Unit Transfer Charges Month Of August,2024 | J53: =VLOOKUP(D53,#REF!,8,0) -> #REF! | K53: =H53-J53 -> #REF! | L53: =K53/H53 -> #REF!
A54: 1800009967 | B54: DR | C54: 45827 | D54: 256779414731 | E54: USD | F54: 100 | G54: INR | H54: 8549.08 | I54: Unit to Unit 1-15 June 25 | J54: =VLOOKUP(D54,#REF!,8,0) -> #REF!
A55: 1800009968 | B55: DR | C55: 45827 | D55: 256779414732 | E55: USD | F55: 100 | G55: INR | H55: 8549.08 | I55: Unit to Unit 1-15 June 25 | J55: =VLOOKUP(D55,#REF!,8,0) -> #REF!
A56: 1800009969 | B56: DR | C56: 45827 | D56: 256779414733 | E56: USD | F56: 100 | G56: INR | H56: 8549.08 | I56: Unit to Unit 1-15 June 25 | J56: =VLOOKUP(D56,#REF!,8,0) -> #REF!
A57: 1800009970 | B57: DR | C57: 45827 | D57: 256779414734 | E57: USD | F57: 100 | G57: INR | H57: 8549.08 | I57: Unit to Unit 1-15 June 25 | J57: =VLOOKUP(D57,#REF!,8,0) -> #REF!
A58: 1800009971 | B58: DR | C58: 45827 | D58: 256779414735 | E58: USD | F58: 100 | G58: INR | H58: 8549.08 | I58: Unit to Unit 1-15 June 25 | J58: =VLOOKUP(D58,#REF!,8,0) -> #REF! | K58: =H58-J58 -> #REF! | L58: =K58/H58 -> #REF!
A59: 1800012780 | B59: DR | C59: 45917 | D59: 256779417434 | E59: USD | F59: 100 | G59: INR | H59: 8751.43 | I59: Intra SEZ -1-15 Sept-25 | J59: =VLOOKUP(D59,#REF!,8,0) -> #REF! | K59: =H59-J59 -> #REF! | L59: =K59/H59 -> #REF!
A60: 1800013748 | B60: DR | C60: 45937 | D60: 256779418169 | E60: USD | F60: 100 | G60: INR | H60: 8819.08 | I60: Intra - SEZ-16-30 Sept 25 | J60: =VLOOKUP(D60,#REF!,8,0) -> #REF!
A61: 1800013749 | B61: DR | C61: 45937 | D61: 256779418170 | E61: USD | F61: 100 | G61: INR | H61: 8819.08 | I61: Intra - SEZ-16-30 Sept 25 | J61: =VLOOKUP(D61,#REF!,8,0) -> #REF! | K61: =H61-J61 -> #REF! | L61: =K61/H61 -> #REF!
A62: 1800000374 | B62: DR | C62: 45716 | D62: 246779410343 | E62: USD | F62: 1700 | G62: INR | H62: 146716.22 | I62: CY Longstanding container Ground Rent charges for | J62: =VLOOKUP(D62,#REF!,8,0) -> #REF!
A63: 1800000381 | B63: DR | C63: 45716 | D63: 246779410350 | E63: USD | F63: 1750 | G63: INR | H63: 151031.41 | I63: CY Longstanding container Ground Rent charges for | J63: =VLOOKUP(D63,#REF!,8,0) -> #REF!
A64: 1800000387 | B64: DR | C64: 45716 | D64: 246779410356 | E64: USD | F64: 1750 | G64: INR | H64: 151031.41 | I64: CY Longstanding container Ground Rent charges for | J64: =VLOOKUP(D64,#REF!,8,0) -> #REF!
A65: 1800000393 | B65: DR | C65: 45716 | D65: 246779410362 | E65: USD | F65: 1700 | G65: INR | H65: 146716.22 | I65: CY Longstanding container Ground Rent charges for | J65: =VLOOKUP(D65,#REF!,8,0) -> #REF!
A66: 1800000931 | B66: DR | C66: 45722 | D66: 246779410871 | E66: USD | F66: 42.51 | G66: INR | H66: 3685.25 | I66: Storage Charges for the month of November, 2024 Ex | J66: =VLOOKUP(D66,#REF!,8,0) -> #REF! | K66: =H66-J66 -> #REF! | L66: =K66/H66 -> #REF!
A67: 1800000953 | B67: DR | C67: 45722 | D67: 246779410893 | E67: USD | F67: 177.18 | G67: INR | H67: 15359.96 | I67: Storage Charges for the month of December, 2024 Ex | J67: =VLOOKUP(D67,#REF!,8,0) -> #REF! | K67: =H67-J67 -> #REF! | L67: =K67/H67 -> #REF!
A68: 1600002439 | B68: DG | C68: 45943 | D68: 256779421983 | E68: USD | F68: -930.14 | G68: INR | H68: -82029.76 | I68: CN issued against 256779418011 | J68: =VLOOKUP(D68,#REF!,8,0) -> #REF!
A69: 1800000414 | B69: DR | C69: 45719 | D69: 246779410376 | E69: USD | F69: 711.35 | G69: INR | H69: 61667.83 | I69: Storage Charges for the month of August, 2024 | J69: =VLOOKUP(D69,#REF!,8,0) -> #REF! | K69: =H69-J69 -> #REF! | L69: =K69/H69 -> #REF!
A70: 1800000439 | B70: DR | C70: 45719 | D70: 246779410401 | E70: USD | F70: 1298.96 | G70: INR | H70: 112608.48 | I70: Storage for the month of Sept 2024 | J70: =VLOOKUP(D70,#REF!,8,0) -> #REF! | K70: =H70-J70 -> #REF! | L70: =K70/H70 -> #REF!
A71: 1800000463 | B71: DR | C71: 45719 | D71: 246779410425 | E71: USD | F71: 1687.21 | G71: INR | H71: 146266.36 | I71: Storage for the month of Oct 2024 | J71: =VLOOKUP(D71,#REF!,8,0) -> #REF! | K71: =H71-J71 -> #REF! | L71: =K71/H71 -> #REF!
A72: 1800001956 | B72: DR | C72: 45733 | D72: 246779411621 | E72: USD | F72: 444.04 | G72: INR | H72: 38494.39 | I72: VAS Activity Charges for the month of September, 2 | J72: =VLOOKUP(D72,#REF!,8,0) -> #REF! | K72: =H72-J72 -> #REF! | L72: =K72/H72 -> #REF!
A73: 1800002095 | B73: DR | C73: 45733 | D73: 246779411760 | E73: USD | F73: 520.17 | G73: INR | H73: 45094.19 | I73: VAS Activity Charges for the month of October, 24 | J73: =VLOOKUP(D73,#REF!,8,0) -> #REF! | K73: =H73-J73 -> #REF! | L73: =K73/H73 -> #REF!
A74: 1800002401 | B74: DR | C74: 45733 | D74: 246779412066 | E74: USD | F74: 66.5 | G74: INR | H74: 5764.97 | I74: VAS Activity Charges for the month of December, 24 | J74: =VLOOKUP(D74,#REF!,8,0) -> #REF! | K74: =H74-J74 -> #REF! | L74: =K74/H74 -> #REF!
A75: 1800002272 | B75: DR | C75: 45733 | D75: 246779411937 | E75: USD | F75: 7.27 | G75: INR | H75: 630.25 | I75: VAS Activity Charges for the month of November, 24 | J75: =VLOOKUP(D75,#REF!,8,0) -> #REF! | K75: =H75-J75 -> #REF! | L75: =K75/H75 -> #REF!
A76: 1800002273 | B76: DR | C76: 45733 | D76: 246779411938 | E76: USD | F76: 53.26 | G76: INR | H76: 4617.18 | I76: VAS Activity Charges for the month of November, 24 | J76: =VLOOKUP(D76,#REF!,8,0) -> #REF! | K76: =H76-J76 -> #REF! | L76: =K76/H76 -> #REF!
A77: 1800002274 | B77: DR | C77: 45733 | D77: 246779411939 | E77: USD | F77: 23.08 | G77: INR | H77: 2000.83 | I77: VAS Activity Charges for the month of November, 24 | J77: =VLOOKUP(D77,#REF!,8,0) -> #REF! | K77: =H77-J77 -> #REF! | L77: =K77/H77 -> #REF!
A78: 1800002275 | B78: DR | C78: 45733 | D78: 246779411940 | E78: USD | F78: 52.73 | G78: INR | H78: 4571.23 | I78: VAS Activity Charges for the month of November, 24 | J78: =VLOOKUP(D78,#REF!,8,0) -> #REF! | K78: =H78-J78 -> #REF! | L78: =K78/H78 -> #REF!
A79: 1800002276 | B79: DR | C79: 45733 | D79: 246779411941 | E79: USD | F79: 76.02 | G79: INR | H79: 6590.27 | I79: VAS Activity Charges for the month of November, 24 | J79: =VLOOKUP(D79,#REF!,8,0) -> #REF! | K79: =H79-J79 -> #REF! | L79: =K79/H79 -> #REF!
A80: 1800006261 | B80: DR | C80: 45762 | D80: 256779411152 | E80: USD | F80: 164.38 | G80: INR | H80: 14288.21 | I80: Empty Transportation August 2024 | J80: =VLOOKUP(D80,#REF!,8,0) -> #REF! | K80: =H80-J80 -> #REF! | L80: =K80/H80 -> #REF!
... A106: 1800006694 | B106: DR | C106: 45762 | D106: 256779411585 | E106: USD | F106: 7.81 | G106: INR | H106: 678.86 | I106: Outbound Handling Charges Aug 2024 | J106: =VLOOKUP(D106,#REF!,8,0) -> #REF! | K106: =H106-J106 -> #REF! | L106: =K106/H106 -> #REF!
A107: 1600002472 | B107: DG | C107: 45947 | D107: 256779422014 | E107: USD | F107: -136.48 | G107: INR | H107: -12036.28 | I107: Credit note raised against 256779418076 | J107: =VLOOKUP(D107,#REF!,8,0) -> #REF!
A108: 1800006996 | B108: DR | C108: 45763 | D108: 256779411887 | E108: USD | F108: 71.22 | G108: INR | H108: 6190.57 | I108: Outbound Handling charges for Dec 2024 | J108: =VLOOKUP(D108,#REF!,8,0) -> #REF! | K108: =H108-J108 -> #REF! | L108: =K108/H108 -> #REF!
A109: 1800007093 | B109: DR | C109: 45763 | D109: 256779411984 | E109: USD | F109: 39.54 | G109: INR | H109: 3436.89 | I109: CAAU5283880-Port SSR Shifting Mar 2025. Exch rate | J109: =VLOOKUP(D109,#REF!,8,0) -> #REF! | K109: =H109-J109 -> #REF! | L109: =K109/H109 -> #REF!
A110: 1800007129 | B110: DR | C110: 45763 | D110: 256779412020 | E110: USD | F110: 85.21 | G110: INR | H110: 7406.61 | I110: VAS Activity - Jan 25, Ex Rate. 86.64 | J110: =VLOOKUP(D110,#REF!,8,0) -> #REF! | K110: =H110-J110 -> #REF! | L110: =K110/H110 -> #REF!
A111: 1800007210 | B111: DR | C111: 45763 | D111: 256779412101 | E111: USD | F111: 171.71 | G111: INR | H111: 14925.35 | I111: VAS Activity - Mar 25, 16-31, Ex Rate. 85.58 | J111: =VLOOKUP(D111,#REF!,8,0) -> #REF! | K111: =H111-J111 -> #REF! | L111: =K111/H111 -> #REF!
A112: 1800007235 | B112: DR | C112: 45763 | D112: 256779412126 | E112: USD | F112: 500.58 | G112: INR | H112: 43511.32 | I112: Storage Charges Mar, 25 Exch Rate 85.58 | J112: =VLOOKUP(D112,#REF!,8,0) -> #REF! | K112: =H112-J112 -> #REF! | L112: =K112/H112 -> #REF!
A113: 1800011264 | B113: DR | C113: 45863 | D113: 256779415996 | E113: USD | F113: 755.58 | G113: INR | H113: 64980.39 | I113: VAS 16-31 May 25 Ex.85.48 | J113: =VLOOKUP(D113,#REF!,8,0) -> #REF! | K113: =H113-J113 -> #REF! | L113: =K113/H113 -> #REF!
A114: 1800001581 | B114: DR | C114: 45730 | D114: 246779412238 | E114: USD | F114: 945.75 | G114: INR | H114: 81988.26 | I114: VAS Activity Charges for the month of August, 24 | J114: =VLOOKUP(D114,#REF!,8,0) -> #REF! | K114: =H114-J114 -> #REF! | L114: =K114/H114 -> #REF!
A115: 1800001784 | B115: DR | C115: 45730 | D115: 246779411449 | E115: USD | F115: 945.75 | G115: INR | H115: 81988.26 | I115: VAS Activity Charges for the month of August, 24 | J115: =VLOOKUP(D115,#REF!,8,0) -> #REF! | K115: =H115-J115 -> #REF! | L115: =K115/H115 -> #REF!
A116: 1800012461 | B116: DR | C116: 45904 | D116: 256779417161 | E116: USD | F116: 787.95 | G116: INR | H116: 68956.92 | I116: VAS -16-31 Aug 25 | J116: =VLOOKUP(D116,#REF!,8,0) -> #REF! | K116: =H116-J116 -> #REF! | L116: =K116/H116 -> #REF!
A117: 1800012559 | B117: DR | C117: 45904 | D117: 256779417178 | E117: USD | F117: 1560 | G117: INR | H117: 136522.35 | I117: CY Refer Pluging Chgs - 01 - 31 May 25 | J117: =VLOOKUP(D117,#REF!,8,0) -> #REF! | K117: =H117-J117 -> #REF! | L117: =K117/H117 -> #REF!
A118: 1800012560 | B118: DR | C118: 45904 | D118: 256779417179 | E118: USD | F118: 1560 | G118: INR | H118: 136522.35 | I118: CY Refer Pluging Chgs - 01 - 30 Jun 25 | J118: =VLOOKUP(D118,#REF!,8,0) -> #REF! | K118: =H118-J118 -> #REF! | L118: =K118/H118 -> #REF!
A119: 1800012561 | B119: DR | C119: 45904 | D119: 256779417180 | E119: USD | F119: 1799.1 | G119: INR | H119: 157447.03 | I119: CY Ground rent Chgs - 01 - 31 July 25 | J119: =VLOOKUP(D119,#REF!,8,0) -> #REF! | K119: =H119-J119 -> #REF! | L119: =K119/H119 -> #REF!
... A123: 1800012685 | B123: DR | C123: 45904 | D123: 256779417325 | E123: USD | F123: 97.84 | G123: INR | H123: 8562.4 | I123: Outbound chgs - 16 - 31 Aug 25 | J123: =VLOOKUP(D123,#REF!,8,0) -> #REF! | K123: =H123-J123 -> #REF! | L123: =K123/H123 -> #REF!
A124: 1600002212 | B124: DG | C124: 45904 | D124: 256779421767 | E124: USD | F124: -60 | G124: INR | H124: -5250.86 | I124: CN Issued towards bill no. 256779417178 | J124: =VLOOKUP(D124,#REF!,8,0) -> #REF!
A125: 1600002213 | B125: DG | C125: 45904 | D125: 256779421768 | E125: USD | F125: -60 | G125: INR | H125: -5250.86 | I125: CN Issued towards bill no. 256779417179 | J125: =VLOOKUP(D125,#REF!,8,0) -> #REF!
A126: 1600002214 | B126: DG | C126: 45904 | D126: 256779421769 | E126: USD | F126: -62 | G126: INR | H126: -5425.89 | I126: CN Issued towards bill no. 256779417180 | J126: =VLOOKUP(D126,#REF!,8,0) -> #REF!
A127: 1600002215 | B127: DG | C127: 45904 | D127: 256779421770 | E127: USD | F127: -62 | G127: INR | H127: -5425.89 | I127: CN Issued towards bill no. 256779417181 | J127: =VLOOKUP(D127,#REF!,8,0) -> #REF!
A128: 1800010008 | B128: DR | C128: 45842 | D128: 256779414772 | E128: USD | F128: 220 | G128: INR | H128: 18920.15 | I128: Transportation In Chgs - 01 - 15 Jun 25 | J128: =VLOOKUP(D128,#REF!,8,0) -> #REF! | K128: =H128-J128 -> #REF! | L128: =K128/H128 -> #REF!
A129: 1800010066 | B129: DR | C129: 45842 | D129: 256779414830 | E129: USD | F129: 142.32 | G129: INR | H129: 12239.62 | I129: Outbound chgs - 01 - 15 Jun 25 | J129: =VLOOKUP(D129,#REF!,8,0) -> #REF! | K129: =H129-J129 -> #REF! | L129: =K129/H129 -> #REF!
...

Sheet Sheet1
C2: Our Ledger | P2: Customer Ledger
D3: =SUBTOTAL(9,D5:D17) -> 0 | E3: =SUBTOTAL(9,E5:E17) -> -2363520.3 | F3: =SUBTOTAL(9,F5:F17) -> 10607419 | G3: =SUBTOTAL(9,G5:G17) -> -4517.25 | H3: =SUBTOTAL(9,H5:H17) -> -4068082.8 | I3: =SUBTOTAL(9,I5:I17) -> 0 | J3: =SUBTOTAL(9,J5:J17) -> 4171298.9 | P3: =SUBTOTAL(9,P5:P16) -> 6183010.3 | Q3: =SUBTOTAL(9,Q5:Q16) -> 7380750.6 | R3: =SUBTOTAL(9,R5:R16) -> 1197740.3
A4: Years | B4: Quarters | C4: Document Date | D4: DA | E4: DG | F4: DR | G4: DY | H4: DZ | I4: XC | J4: Net Balance | M4: Years | N4: Quarters | O4: Document Date | P4: Sum of Debit (LC) | Q4: Sum of Credit (LC) | R4: Net Balance
A5: 2025 | B5: Qtr1 | C5: Feb | F5: 1709145.6 | I5: 0 | J5: =SUM(D5:I5) -> 1709145.6 | M5: 2025 | N5: Qtr1 | O5: Feb | Q5: 1176894.5 | R5: =Q5-P5 -> 1176894.5
A6: 2025 | B6: Qtr1 | C6: Mar | F6: 1285065.3 | J6: =SUM(D6:I6) -> 1285065.3 | M6: 2025 | N6: Qtr1 | O6: Mar | P6: 3423.2 | Q6: 963804.11 | R6: =Q6-P6 -> 960380.91
A7: 2025 | B7: Qtr2 | C7: Apr | D7: 0 | F7: 1164595.6 | J7: =SUM(D7:I7) -> 1164595.6 | M7: 2025 | N7: Qtr2 | O7: Apr | P7: 6857 | Q7: 965734.79 | R7: =Q7-P7 -> 958877.79
A8: 2025 | B8: Qtr2 | C8: May | E8: -282752.46 | F8: 334850.19 | J8: =SUM(D8:I8) -> 52097.73 | M8: 2025 | N8: Qtr2 | O8: May | Q8: 314121.81 | R8: =Q8-P8 -> 314121.81
A9: 2025 | B9: Qtr2 | C9: Jun | F9: 694990.26 | H9: -23431.62 | J9: =SUM(D9:I9) -> 671558.64 | M9: 2025 | N9: Qtr2 | O9: Jun | P9: 2325813.5 | Q9: 383274.06 | R9: =Q9-P9 -> -1942539.4
A10: 2025 | B10: Qtr3 | C10: Jul | E10: -1496930.2 | F10: 780750.66 | G10: 0 | J10: =SUM(D10:I10) -> -716179.58 | M10: 2025 | N10: Qtr3 | O10: Jul | P10: 319981.43 | Q10: 525725.73 | R10: =Q10-P10 -> 205744.3
A11: 2025 | B11: Qtr3 | C11: Aug | E11: -400000.24 | F11: 1732789.2 | H11: -1177084.8 | J11: =SUM(D11:I11) -> 155704.22 | M11: 2025 | N11: Qtr3 | O11: Aug | P11: 677925.27 | Q11: 795781.75 | R11: =Q11-P11 -> 117856.48
A12: 2025 | B12: Qtr3 | C12: Sep | E12: -43777.19 | F12: 1140119.5 | G12: -4517.25 | H12: -256665.53 | J12: =SUM(D12:I12) -> 835159.5 | M12: 2025 | N12: Qtr3 | O12: Sep | P12: 1393909.6 | Q12: 931531.18 | R12: =Q12-P12 -> -462378.42
A13: 2025 | B13: Qtr4 | C13: Oct | E13: -94066.04 | F13: 511397.34 | H13: -413002 | J13: =SUM(D13:I13) -> 4329.3 | M13: 2025 | N13: Qtr4 | O13: Oct | P13: 1246249.2 | Q13: 603623.76 | R13: =Q13-P13 -> -642625.4
A14: 2025 | B14: Qtr4 | C14: Nov | F14: 445656.37 | H14: -1975900.5 | J14: =SUM(D14:I14) -> -1530244.1 | M14: 2025 | N14: Qtr4 | O14: Nov | Q14: 456392.14 | R14: =Q14-P14 -> 456392.14
A15: 2025 | B15: Qtr4 | C15: Dec | F15: 236783.41 | J15: =SUM(D15:I15) -> 236783.41 | M15: 2025 | N15: Qtr4 | O15: Dec | P15: 208851.16 | Q15: 188962.82 | R15: =Q15-P15 -> -19888.34
A16: 2026 | B16: Qtr1 | C16: Jan | F16: 486469.03 | H16: -221998.43 | J16: =SUM(D16:I16) -> 264470.6 | M16: 2026 | N16: Qtr1 | O16: Jan | Q16: 74903.963 | R16: =Q16-P16 -> 74903.963
A17: 2026 | B17: Qtr1 | C17: Feb | E17: -45994.17 | F17: 84806.69 | J17: =SUM(D17:I17) -> 38812.52
