Workbook

Sheet Summary
A2: Reconciliation of Ledger as on 31st January 2026
A3: Particulars | B3: Amount
A4: Balance as per Barnet India Pvt Ltd | B4: ='Customer data'!P188 -> 1917316.7
A5: Add: TDS recorded by customer but not in our books | B5: ='TDS data'!J1 -> 298205
A6: Add: Credit Note in Customer's Books | B6: ='Credit Note in customers books'!L5 -> 397146.74
A7: Less: Difference in Invoice value in customers books | B7: =-'Difference in Invoice value '!L8 -> -5055.6602
A8: Less: Duplicate CN in Ascendus Books | B8: ='Duplicate CN in Ascenudes Books'!H3 -> -7510.05
A9: less: Difference in Payment recorded in Ascendus books | B9: =Sheet5!G15 -> -464928.21
A10: Derived balance | B10: =SUM(B4:B9) -> 2135174.6
A11: Balance as per Ascendus | B11: ='Ascendus Data'!U337 -> 2135174.6
A13: Difference | B13: =B10-B11-B12 -> -0.006391603

Sheet Sheet5
A2: Years | B2: Date | C2: Company Code Currency Value | D2: Years | E2: Date | F2: Sum of AMOUNT PAID
A3: 2025 | B3: Mar | C3: 0 | D3: 2025 | E3: Mar | F3: 267943.73 | G3: =C3+F3 -> 267943.73
A4: 2025 | B4: Apr | C4: -291173.73 | D4: 2025 | E4: Apr | F4: 0 | G4: =C4+F4 -> -291173.73
A5: 2025 | B5: May | C5: 0 | D5: 2025 | E5: May | F5: 112111.95 | G5: =C5+F5 -> 112111.95
A6: 2025 | B6: Jun | C6: -341000 | D6: 2025 | E6: Jun | F6: 905889.53 | G6: =C6+F6 -> 564889.53
A7: 2025 | B7: Jul | C7: 0 | D7: 2025 | E7: Jul | F7: 475086.94 | G7: =C7+F7 -> 475086.94
A8: 2025 | B8: Aug | C8: 0 | D8: 2025 | E8: Aug | F8: 602275.11 | G8: =C8+F8 -> 602275.11
A9: 2025 | B9: Sep | C9: 0 | D9: 2025 | E9: Sep | F9: 124189.23 | G9: =C9+F9 -> 124189.23
A10: 2025 | B10: Oct | C10: -1805272.2 | D10: 2025 | E10: Oct | F10: 663652.5 | G10: =C10+F10 -> -1141619.7
A11: 2025 | B11: Nov | C11: -1129444.9 | D11: 2025 | E11: Nov | F11: 0 | G11: =C11+F11 -> -1129444.9
A12: 2025 | B12: Dec | C12: -422946.17 | D12: 2025 | E12: Dec | F12: 375012.8 | G12: =C12+F12 -> -47933.368
A13: 2026 | B13: Jan | C13: -1253.01 | D13: 2026 | E13: Jan | F13: 0 | G13: =C13+F13 -> -1253.01
A14: 2026 | B14: Feb | C14: -31395.72 | D14: 2026 | E14: Feb | F14: 31395.717 | G14: =C14+F14 -> -0.0034348
C15: =SUM(C3:C14) -> -4022485.7 | F15: =SUM(F3:F14) -> 3557557.5 | G15: =SUM(G3:G14) -> -464928.21

Sheet Sheet3
A1: As per Customer
A2: Date | B2: AMOUNT PAID | C2: UTR NO/REMARK | E2: Years | F2: Quarters | G2: Date | H2: Sum of AMOUNT PAID
A3: 45728 | B3: 69973.16 | C3: HDFCN52025031215974606 | E3: 2025 | F3: Qtr1 | G3: Mar | H3: 267943.73
A4: 45728 | B4: 28756.3 | C4: HDFCN52025031215976413 | F4: Qtr2 | G4: May | H4: 112111.95
A5: 45728 | B5: 97112.2 | C5: HDFCN52025031215974609 | G5: Jun | H5: 905889.53
A6: 45740 | B6: 11330.33 | C6: HDFCN52025032433793860 | F6: Qtr3 | G6: Jul | H6: 475086.94
A7: 45740 | B7: 18128.12 | C7: HDFCN52025032433793867 | G7: Aug | H7: 602275.11
A8: 45740 | B8: 18128.12 | C8: HDFCN52025032433793886 | G8: Sep | H8: 124189.23
A9: 45740 | B9: 4532.53 | C9: HDFCN52025032433793875 | F9: Qtr4 | G9: Oct | H9: 663652.5
A10: 45740 | B10: 15450.44 | C10: HDFCN52025032433791996 | G10: Dec | H10: 375012.8
A11: 45740 | B11: 4532.53 | C11: HDFCN52025032433791993 | E11: 2026 | F11: Qtr1 | G11: Feb | H11: 31395.717
A12: 45791 | B12: 28538.08 | C12: HDFCN52025051435275414
A13: 45791 | B13: 24143.251 | C13: HDFCN52025051435275414
A14: 45791 | B14: 6746.2081 | C14: HDFCN52025051435275414 | E14: Years | F14: Quarters | G14: Date | H14: Sum of AMOUNT PAID
A15: 45791 | B15: 11040.068 | C15: HDFCN52025051435275414 | E15: 2025 | F15: Qtr1 | G15: Mar | H15: 267943.73
A16: 45791 | B16: 24143.251 | C16: HDFCN52025051435275414 | F16: Qtr2 | G16: May | H16: 112111.95
A17: 45791 | B17: 11040.068 | C17: HDFCN52025051435275414 | G17: Jun | H17: 905889.53
A18: 45791 | B18: 6461.02 | C18: HDFCN52025051435275414 | F18: Qtr3 | G18: Jul | H18: 475086.94
A19: 45813 | B19: 2186.2831 | C19: HDFCN52025060575568983 | G19: Aug | H19: 602275.11
A20: 45813 | B20: 3566.69 | C20: HDFCN52025060575568983 | G20: Sep | H20: 124189.23
A21: 45813 | B21: 8026.5902 | C21: HDFCN52025060575568983 | F21: Qtr4 | G21: Oct | H21: 663652.5
A22: 45813 | B22: 2293.664 | C22: HDFCN52025060575568983 | G22: Dec | H22: 375012.8
A23: 45813 | B23: 3670.0624 | C23: HDFCN52025060575568983 | E23: 2026 | F23: Qtr1 | G23: Feb | H23: 31395.717
A24: 45813 | B24: 8026.5902 | C24: HDFCN52025060575568983
A25: 45813 | B25: 2293.664 | C25: HDFCN52025060575568983
A26: 45813 | B26: 3670.0624 | C26: HDFCN52025060575568983
A27: 45813 | B27: 16052.314 | C27: HDFCN52025060575568983
A28: 45813 | B28: 4587.328 | C28: HDFCN52025060575568983
A29: 45813 | B29: 7340.1249 | C29: HDFCN52025060575568983
A30: 45813 | B30: 15921.62 | C30: HDFCN52025060575568983
A31: 45813 | B31: 15921.62 | C31: HDFCN52025060575568983
A32: 45813 | B32: 57739.158 | C32: HDFCN52025060575568983
A33: 45813 | B33: 4339.1605 | C33: HDFCN52025060575568983
A34: 45813 | B34: 3551.3531 | C34: HDFCN52025060575568983
A35: 45813 | B35: 341000 | C35: HDFCN52025060575565670
... A92: 46067 | B92: 971.66757 | C92: HDFCH00806112854

Sheet Sheet4
A1: Document Type | B1: Document Date | C1: Company Code Currency Value | D1: Text | I1: Years | J1: Quarters | K1: Document Date | L1: Sum of Company Code Currency Value
A2: DZ | B2: 45772 | C2: -77748.16 | D2: HDFCN52025031215974606 | I2: 2025 | J2: Qtr2 | K2: Apr | L2: -291173.73
A3: DZ | B3: 45772 | C3: -31951.3 | D3: HDFCN52025031215976413 | K3: Jun | L3: -341000
A4: DZ | B4: 45772 | C4: -107902.2 | D4: HDFCN52025031215974609 | J4: Qtr3 | K4: Aug | L4: 0
A5: DZ | B5: 45772 | C5: -11561.33 | D5: HDFCN52025032433793860 | K5: Sep | L5: 0
A6: DZ | B6: 45772 | C6: -18498.12 | D6: HDFCN52025032433793867 | J6: Qtr4 | K6: Oct | L6: -1805272.2
A7: DZ | B7: 45772 | C7: -18498.12 | D7: HDFCN52025032433793886 | K7: Nov | L7: -1129444.9
A8: DZ | B8: 45772 | C8: -4624.53 | D8: HDFCN52025032433793875 | K8: Dec | L8: -422946.17
A9: DZ | B9: 45772 | C9: -15765.44 | D9: HDFCN52025032433791996 | I9: 2026 | J9: Qtr1 | K9: Jan | L9: -1253.01
A10: DZ | B10: 45772 | C10: -4624.53 | D10: HDFCN52025032433791993 | K10: Feb | L10: -31395.72
A11: DZ | B11: 45832 | C11: -341000
A12: DZ | B12: 45832 | C12: -112111.95
A13: DZ | B13: 45832 | C13: 112111.95
A14: DZ | B14: 45832 | C14: 159186.29
A15: DZ | B15: 45832 | C15: -159186.29
A16: DZ | B16: 45890 | C16: 179293.83
A17: DZ | B17: 45890 | C17: -179293.83
A18: DZ | B18: 45890 | C18: 475086.94
A19: DZ | B19: 45890 | C19: -475086.94
A20: DZ | B20: 45908 | C20: 495157.4
A21: DZ | B21: 45908 | C21: -495157.4
A22: DZ | B22: 45908 | C22: 107117.71
... A28: DZ | B28: 45938 | C28: -339060.54
A29: DZ | B29: 45946 | C29: 2932.62 | D29: HDFCH00465695692
A30: DZ | B30: 45946 | C30: -492209.06 | D30: HDFCN52025082227307462
A31: DZ | B31: 45946 | C31: -139776.58 | D31: HDFCH00465695692
A32: DZ | B32: 45946 | C32: -2932.62
A33: DZ | B33: 45946 | C33: -116988.95 | D33: HDFCN52025051435275414
A34: DZ | B34: 45946 | C34: -646935.77 | D34: HDFCN52025100205721894
A35: DZ | B35: 45946 | C35: -182952.83 | D35: HDFCN52025062512710909
A36: DZ | B36: 45972 | C36: -324591.96
A37: DZ | B37: 45979 | C37: -8051.51 | D37: HDFCN52025060575568983
A38: DZ | B38: 45979 | C38: -109304.71 | D38: HDFCN52025082733046460
A39: DZ | B39: 45979 | C39: -159622.78 | D39: HDFCN52025060575568983
A40: DZ | B40: 45979 | C40: -50734.53 | D40: HDFCN52025072369906032
A41: DZ | B41: 45979 | C41: -477139.41 | D41: HDFCN52025072369906032
A42: DZ | B42: 46007 | C42: -66620.79 | D42: G15K40FCKGJH
A43: DZ | B43: 46007 | C43: -296024
A44: DZ | B44: 46007 | C44: -30866.77 | D44: G15K40FCKGJH
A45: DZ | B45: 46007 | C45: -14531.11
A46: DZ | B46: 46011 | C46: -14903.5
A47: DZ | B47: 46030 | C47: 14531.11
A48: DZ | B48: 46030 | C48: 14903.5
A49: DZ | B49: 46030 | C49: 14531.11
A50: DZ | B50: 46030 | C50: -30687.62
A51: DZ | B51: 46030 | C51: -14531.11
A52: DZ | B52: 46070 | C52: -30424.05
A53: DZ | B53: 46070 | C53: -971.67

Sheet Payment Reco Updated
A2: As Per Bank Details | D2: As per Ascendus ledger | G2: Reco
A3: Payment Date | B3: Recd Amount | C3: Bank Reference | D3: Clearing Documents | E3: Document Header Text | F3: Sum of Company Code Currency Value | G3: TDS | H3: Difference | I3: Reasons
A4: 45933 | B4: 324591.96 | C4: HDFCN52025100308494407 | D4: Not Yet Cleared | E4: HDFCN52025100308494407 | F4: -324591.96 | G4: =_xlfn.XLOOKUP(D4,Sheet8!$D:$D,Sheet8!$E:$E,0,0) -> 0 | H4: =B4+F4+G4 -> 0 | I4: Documents Not Yet Cleared
A5: 45933 | B5: 339060.54 | C5: HDFCN52025100205721894 | D5: 1400001455 | E5: HDFCN52025100205721894 | F5: -646935.77 | G5: =_xlfn.XLOOKUP(D5,Sheet8!$D:$D,Sheet8!$E:$E,0,0) -> 57796 | H5: =B5+F5+G5 -> -250079.23 | I5: Part Payment Cleared
A6: 45896 | B6: 107117.71 | C6: HDFCN52025082733046460 | D6: 1400001956 | E6: HDFCN52025082733046460 | F6: -109304.71 | G6: =_xlfn.XLOOKUP(D6,Sheet8!$D:$D,Sheet8!$E:$E,0,0) -> 2187 | H6: =B6+F6+G6 -> 0
A7: 45891 | B7: 495157.4 | C7: HDFCN52025082227307462 | D7: 1400001452 | E7: HDFCN52025082227307462 | F7: -492209.06 | G7: =_xlfn.XLOOKUP(D7,Sheet8!$D:$D,Sheet8!$E:$E,0,0) -> 9843 | H7: =B7+F7+G7 -> 12791.34 | I7: Foreign exchange Gain/Loss
D8: 1400001453 | F8: -2932.62 | H8: =B8+F8+G8 -> -2932.62 | I8: Not In Bank
D9: 1400001453 | E9: HDFCH00465695692 | F9: -136843.96 | G9: =_xlfn.XLOOKUP(D9,Sheet8!$D:$D,Sheet8!$E:$E,0,0) -> 2796 | H9: =B9+F9+G9 -> -134047.96 | I9: Not In Bank
A10: 45861 | B10: 475086.94 | C10: HDFCN52025072369906032 | D10: 1400001972 | E10: HDFCN52025072369906032 | F10: -477139.41 | G10: =_xlfn.XLOOKUP(D10,Sheet8!$D:$D,Sheet8!$E:$E,0,0) -> 47714 | H10: =B10+F10+G10 -> 45661.53
D11: 1400001971 | E11: HDFCN52025072369906032 | F11: -50734.53 | G11: =_xlfn.XLOOKUP(D11,Sheet8!$D:$D,Sheet8!$E:$E,0,0) -> 5073 | H11: =B11+F11+G11 -> -45661.53
A12: 45833 | B12: 179293.83 | C12: HDFCN52025062512710909 | D12: 1400001456 | E12: HDFCN52025062512710909 | F12: -182952.83 | G12: =_xlfn.XLOOKUP(D12,Sheet8!$D:$D,Sheet8!$E:$E,0,0) -> 3659 | H12: =B12+F12+G12 -> 0
A13: 45822 | B13: 226409 | C13: HDFCN52025061495304800 | D13: Not Yet Cleared | E13: HDFCN52025061495304800 | F13: -226409 | G13: =_xlfn.XLOOKUP(D13,Sheet8!$D:$D,Sheet8!$E:$E,0,0) -> 0 | H13: =B13+F13+G13 -> 0 | I13: Documents Not Yet Cleared
A14: 45813 | B14: 159186.29 | C14: HDFCN52025060575568983 | D14: 1400001961 | E14: HDFCN52025060575568983 | F14: -167674.29 | G14: =_xlfn.XLOOKUP(D14,Sheet8!$D:$D,Sheet8!$E:$E,0,0) -> 8488 | H14: =B14+F14+G14 -> 0
A15: 45813 | B15: 341000 | C15: HDFCN52025060575565670 | D15: Not Yet Cleared | E15: HDFCN52025060575565670 | F15: -341000 | G15: =_xlfn.XLOOKUP(D15,Sheet8!$D:$D,Sheet8!$E:$E,0,0) -> 0 | H15: =B15+F15+G15 -> 0 | I15: Documents Not Yet Cleared
A16: 45791 | B16: 112111.95 | C16: HDFCN52025051435275414 | D16: 1400001454 | E16: HDFCN52025051435275414 | F16: -116988.95 | G16: =_xlfn.XLOOKUP(D16,Sheet8!$D:$D,Sheet8!$E:$E,0,0) -> 4877 | H16: =B16+F16+G16 -> 0
A17: 45740 | B17: 18128.12 | C17: HDFCN52025032433793886 | D17: 1400000012 | E17: HDFCN52025032433793886 | F17: -18498.12 | G17: =_xlfn.XLOOKUP(D17,Sheet8!$D:$D,Sheet8!$E:$E,0,0) -> 370 | H17: =B17+F17+G17 -> 0
A18: 45740 | B18: 4532.53 | C18: HDFCN52025032433793875 | D18: 1400000013 | E18: HDFCN52025032433793875 | F18: -4624.53 | G18: =_xlfn.XLOOKUP(D18,Sheet8!$D:$D,Sheet8!$E:$E,0,0) -> 92 | H18: =B18+F18+G18 -> 0
A19: 45740 | B19: 18128.12 | C19: HDFCN52025032433793867 | D19: 1400000011 | E19: HDFCN52025032433793867 | F19: -18498.12 | G19: =_xlfn.XLOOKUP(D19,Sheet8!$D:$D,Sheet8!$E:$E,0,0) -> 370 | H19: =B19+F19+G19 -> 0
A20: 45740 | B20: 11330.33 | C20: HDFCN52025032433793860 | D20: 1400000010 | E20: HDFCN52025032433793860 | F20: -11561.33 | G20: =_xlfn.XLOOKUP(D20,Sheet8!$D:$D,Sheet8!$E:$E,0,0) -> 231 | H20: =B20+F20+G20 -> 0
A21: 45740 | B21: 15450.44 | C21: HDFCN52025032433791996 | D21: 1400000014 | E21: HDFCN52025032433791996 | F21: -15765.44 | G21: =_xlfn.XLOOKUP(D21,Sheet8!$D:$D,Sheet8!$E:$E,0,0) -> 315 | H21: =B21+F21+G21 -> 0
A22: 45740 | B22: 4532.53 | C22: HDFCN52025032433791993 | D22: 1400000015 | E22: HDFCN52025032433791993 | F22: -4624.53 | G22: =_xlfn.XLOOKUP(D22,Sheet8!$D:$D,Sheet8!$E:$E,0,0) -> 92 | H22: =B22+F22+G22 -> 0
A23: 45728 | B23: 28756.3 | C23: HDFCN52025031215976413 | D23: 1400000008 | E23: HDFCN52025031215976413 | F23: -31951.3 | G23: =_xlfn.XLOOKUP(D23,Sheet8!$D:$D,Sheet8!$E:$E,0,0) -> 3195 | H23: =B23+F23+G23 -> 0
A24: 45728 | B24: 97112.2 | C24: HDFCN52025031215974609 | D24: 1400000009 | E24: HDFCN52025031215974609 | F24: -107902.2 | G24: =_xlfn.XLOOKUP(D24,Sheet8!$D:$D,Sheet8!$E:$E,0,0) -> 10790 | H24: =B24+F24+G24 -> 0
A25: 45728 | B25: 69973.16 | C25: HDFCN52025031215974606 | D25: 1400000007 | E25: HDFCN52025031215974606 | F25: -77748.16 | G25: =_xlfn.XLOOKUP(D25,Sheet8!$D:$D,Sheet8!$E:$E,0,0) -> 7775 | H25: =B25+F25+G25 -> 0
A26: 46069 | B26: 30424.05 | C26: H3YKFZWVB0GN | D26: Not Yet Cleared | E26: H3YKFZWVB0GN | F26: -30424.05 | G26: =_xlfn.XLOOKUP(D26,Sheet8!$D:$D,Sheet8!$E:$E,0,0) -> 0 | H26: =B26+F26+G26 -> 0 | I26: Documents Not Yet Cleared
A27: 46069 | B27: 971.67 | C27: H2PMXC728CY0 | D27: Not Yet Cleared | E27: H2PMXC728CY0 | F27: -971.67 | G27: =_xlfn.XLOOKUP(D27,Sheet8!$D:$D,Sheet8!$E:$E,0,0) -> 0 | H27: =B27+F27+G27 -> 0 | I27: Documents Not Yet Cleared
A28: 46006 | B28: 14903.5 | C28: G90RGJ9HVGZQ | D28: Not Yet Cleared | E28: G15K40FCKGJH | F28: -296024 | G28: =_xlfn.XLOOKUP(D29,Sheet8!$D:$D,Sheet8!$E:$E,0,0) -> 0 | H28: =B29+F28+G28 -> 64085.3 | I28: Documents Not Yet Cleared
A29: 45993 | B29: 360109.3 | C29: G15K40FCKGJH | D29: Not Yet Cleared | E29: G15K40FCKGJH | F29: -97487.56 | G29: =_xlfn.XLOOKUP(D30,Sheet8!$D:$D,Sheet8!$E:$E,0,0) -> 4539 | H29: =B30+F29+G29 -> -92948.56 | I29: =G29/F29 -> -0.046559787
D30: 1400002197 | E30: G15K40FCKGJH+G90RGJ9HVGZQ | F30: =-14531.11-16156.51 -> -30687.62 | G30: =_xlfn.XLOOKUP(D31,Sheet8!$D:$D,Sheet8!$E:$E,0,0) -> 614 | H30: =B31+F30+G30 -> -30073.62 | I30: =G30/F30 -> -0.020008068
D31: 1400002389

Sheet Sheet8
A3: Row Labels | B3: Sum of TDS | D3: Row Labels | E3: Sum of TDS
A4: 1400000007 | B4: 7775 | D4: 1400000007 | E4: 7775
A5: 1400000008 | B5: 3195 | D5: 1400000008 | E5: 3195
A6: 1400000009 | B6: 10790 | D6: 1400000009 | E6: 10790
A7: 1400000010 | B7: 231 | D7: 1400000010 | E7: 231
A8: 1400000011 | B8: 370 | D8: 1400000011 | E8: 370
A9: 1400000012 | B9: 370 | D9: 1400000012 | E9: 370
A10: 1400000013 | B10: 92 | D10: 1400000013 | E10: 92
A11: 1400000014 | B11: 315 | D11: 1400000014 | E11: 315
A12: 1400000015 | B12: 92 | D12: 1400000015 | E12: 92
A13: 1400000293 | D13: 1400000293
A14: 1400000294 | D14: 1400000294
A15: 1400000295 | D15: 1400000295
A16: 1400000296 | D16: 1400000296
A17: 1400000297 | D17: 1400000297
A18: 1400000298 | D18: 1400000298
A19: 1400000299 | D19: 1400000299
A20: 1400000300 | D20: 1400000300
A21: 1400000301 | D21: 1400000301
A22: 1400000302 | D22: 1400000302
A23: 1400000303 | D23: 1400000303
A24: 1400000304 | D24: 1400000304
... A65: 1400001451 | D65: 1400001451
A66: 1400001452 | B66: 9843 | D66: 1400001452 | E66: 9843
A67: 1400001453 | B67: 2796 | D67: 1400001453 | E67: 2796
A68: 1400001454 | B68: 4877 | D68: 1400001454 | E68: 4877
A69: 1400001455 | B69: 57796 | D69: 1400001455 | E69: 57796
A70: 1400001456 | B70: 3659 | D70: 1400001456 | E70: 3659
A71: 1400001458 | D71: 1400001458
A72: 1400001468 | D72: 1400001468
A73: 1400001956 | B73: 2187 | D73: 1400001956 | E73: 2187
A74: 1400001961 | B74: 8488 | D74: 1400001961 | E74: 8488
A75: 1400001971 | B75: 5073 | D75: 1400001971 | E75: 5073
A76: 1400001972 | B76: 47714 | D76: 1400001972 | E76: 47714
A77: 1400001988 | D77: 1400001988
A78: 1400001989 | D78: 1400001989
A79: 1400001993 | D79: 1400001993
A80: 1400002197 | B80: 4539 | D80: 1400002197 | E80: 4539
A81: 1400002388 | D81: 1400002388
A82: 1400002389 | B82: 614 | D82: 1400002389 | E82: 614
A83: 1600000159 | D83: 1600000159
A84: 1600000160 | D84: 1600000160
A85: 1600000161 | D85: 1600000161
B86: 127389 | D86: TDS Not Booked | E86: 127389
A87: Grand Total | B87: 298205 | D87: Grand Total | E87: 298205

Sheet Ascendus Data
AK1: =SUBTOTAL(9,AK148:AK334) -> 0.005074
A2: Cleared Item | B2: Company Code | C2: Customer | D2: Customer Account: Name 1 | E2: Fiscal Year | F2: Posting period | G2: Posting Date | H2: Document Number | I2: Document Type | J2: Document Date | K2: Entry Date | L2: Document Header Text | M2: Reference | N2: G/L Account | O2: G/L Account: Short Text | P2: Special G/L Ind. | Q2: Posting Key | R2: Document Currency Key | S2: Document Currency Value | T2: Company Code Currency Key | U2: Company Code Currency Value | V2: Tax Code | W2: Profit Center | X2: Trading Partner No. | Y2: Assignment | Z2: Item | AA2: Text | AB2: Reference Key 1 | AC2: Reference Key 2 | AD2: Reference Key 3 | AE2: Baseline Payment Dte | AF2: Clearing Date | AG2: Clearing Documents | AH2: Gross Amount | AI2: TDS | AJ2: Net Amount | AK2: Difference | AL2: Rate | AO2: Payment reference as per customer
A3: Selected | B3: 6779 | C3: 100222397 | D3: BARNET INDIA PRIVATE LIMITED | E3: 2025 | F3: 9 | G3: 46070 | H3: 1400002720 | I3: DZ | J3: 46070 | K3: 46070 | L3: H3YKFZWVB0GN | M3: 2173609 | N3: 212100 | O3: Trade Debtors (Ctrl) | Q3: 15 | R3: INR | S3: -30424.05 | T3: INR | U3: -30424.05 | W3: 6779220000 | Z3: 2 | AE3: 46070 | AH3: {=VLOOKUP(M3,'Customer data Vlookup'!$B$3:$H$127,{2,3},0)} -> #N/A | AO3: =VLOOKUP(M3,'Customer data'!F:P,11,0) -> #N/A
A4: Selected | B4: 6779 | C4: 100222397 | D4: BARNET INDIA PRIVATE LIMITED | E4: 2025 | F4: 12 | G4: 46070 | H4: 1400002721 | I4: DZ | J4: 46070 | K4: 46070 | L4: H2PMXC728CY0 | M4: 2173609 | N4: 212100 | O4: Trade Debtors (Ctrl) | Q4: 15 | R4: INR | S4: -971.67 | T4: INR | U4: -971.67 | W4: 6779220000 | Z4: 2 | AE4: 46070 | AH4: {=VLOOKUP(M4,'Customer data Vlookup'!$B$3:$H$127,{2,3},0)} -> #N/A | AO4: =VLOOKUP(M4,'Customer data'!F:P,11,0) -> #N/A
A5: Selected | B5: 6779 | C5: 100222397 | D5: BARNET INDIA PRIVATE LIMITED | E5: 2025 | F5: 10 | G5: 46065 | H5: 1800017510 | I5: DR | J5: 46065 | K5: 46069 | L5: NA | M5: 256779451324 | N5: 212100 | O5: Trade Debtors (Ctrl) | Q5: 01 | R5: USD | S5: 384.56 | T5: INR | U5: 34739.3 | V5: O0 | W5: 6779224501 | Y5: 2172711 | Z5: 1 | AA5: Unit Storage 1-31 Jan 2026 | AE5: 46065 | AH5: {=VLOOKUP(M5,'Customer data Vlookup'!$B$3:$H$127,{2,3},0)} -> 34739.305 | AI5: 3474 | AJ5: =AH5-AI5 -> 31265.305 | AK5: =U5-AH5 -> -0.004512 | AL5: =AI5/U5 -> 0.10000202 | AO5: =VLOOKUP(M5,'Customer data'!F:P,11,0) -> Not Approved
A6: Selected | B6: 6779 | C6: 100222397 | D6: BARNET INDIA PRIVATE LIMITED | E6: 2025 | F6: 11 | G6: 46064 | H6: 1800017704 | I6: DR | J6: 46064 | K6: 46069 | L6: 2173095 | M6: 256779451520 | N6: 212100 | O6: Trade Debtors (Ctrl) | Q6: 01 | R6: USD | S6: 61.04 | T6: INR | U6: 5514.06 | V6: O0 | W6: 6779224501 | Y6: NA | Z6: 1 | AA6: LCL Chgs - 16 - 31 JAN 26 | AE6: 46064 | AH6: {=VLOOKUP(M6,'Customer data Vlookup'!$B$3:$H$127,{2,3},0)} -> 5514.0606 | AI6: 111 | AJ6: =AH6-AI6 -> 5403.0606 | AK6: =U6-AH6 -> -0.000608 | AL6: =AI6/U6 -> 0.020130358 | AO6: =VLOOKUP(M6,'Customer data'!F:P,11,0) -> Not Approved
A7: Not Selected | B7: 6779 | C7: 100222397 | D7: BARNET INDIA PRIVATE LIMITED | E7: 2025 | F7: 10 | G7: 46030 | H7: 1400002388 | I7: DZ | J7: 46030 | K7: 46030 | L7: G15K40FCKGJH | N7: 212100 | O7: Trade Debtors (Ctrl) | Q7: 08 | R7: INR | S7: 14531.11 | T7: INR | U7: 14531.11 | W7: 6779220000 | Z7: 2 | AE7: 46030 | AF7: 46030 | AG7: 1400002388 | AH7: {=VLOOKUP(M7,'Customer data Vlookup'!$B$3:$H$127,{2,3},0)} -> #N/A | AO7: =VLOOKUP(M7,'Customer data'!F:P,11,0) -> #N/A
A8: Selected | B8: 6779 | C8: 100222397 | D8: BARNET INDIA PRIVATE LIMITED | E8: 2025 | F8: 11 | G8: 46030 | H8: 1400002389 | I8: DZ | J8: 46030 | K8: 46030 | L8: G90RGJ9HVGZQ | N8: 212100 | O8: Trade Debtors (Ctrl) | Q8: 08 | R8: INR | S8: 14903.5 | T8: INR | U8: 14903.5 | W8: 6779220000 | Z8: 3 | AE8: 46030 | AF8: 46030 | AG8: 1400002389 | AH8: {=VLOOKUP(M8,'Customer data Vlookup'!$B$3:$H$127,{2,3},0)} -> #N/A | AO8: =VLOOKUP(M8,'Customer data'!F:P,11,0) -> #N/A
A9: Selected | B9: 6779 | C9: 100222397 | D9: BARNET INDIA PRIVATE LIMITED | E9: 2025 | F9: 11 | G9: 46030 | H9: 1400002389 | I9: DZ | J9: 46030 | K9: 46030 | L9: G90RGJ9HVGZQ | N9: 212100 | O9: Trade Debtors (Ctrl) | Q9: 08 | R9: INR | S9: 14531.11 | T9: INR | U9: 14531.11 | W9: 6779224500 | Z9: 4 | AE9: 46030 | AF9: 46030 | AG9: 1400002389 | AH9: {=VLOOKUP(M9,'Customer data Vlookup'!$B$3:$H$127,{2,3},0)} -> #N/A | AO9: =VLOOKUP(M9,'Customer data'!F:P,11,0) -> #N/A
A10: Selected | B10: 6779 | C10: 100222397 | D10: BARNET INDIA PRIVATE LIMITED | E10: 2025 | F10: 11 | G10: 46030 | H10: 1400002389 | I10: DZ | J10: 46030 | K10: 46030 | L10: G90RGJ9HVGZQ | N10: 212100 | O10: Trade Debtors (Ctrl) | Q10: 15 | R10: INR | S10: -31650.87 | T10: INR | U10: -30687.62 | W10: 6779224500 | Z10: 5 | AE10: 46030 | AF10: 46030 | AG10: 1400002389 | AH10: {=VLOOKUP(M10,'Customer data Vlookup'!$B$3:$H$127,{2,3},0)} -> #N/A | AO10: =VLOOKUP(M10,'Customer data'!F:P,11,0) -> #N/A
A11: Selected | B11: 6779 | C11: 100222397 | D11: BARNET INDIA PRIVATE LIMITED | E11: 2025 | F11: 11 | G11: 46030 | H11: 1400002388 | I11: DZ | J11: 46030 | K11: 46030 | L11: G15K40FCKGJH | N11: 212100 | O11: Trade Debtors (Ctrl) | Q11: 15 | R11: INR | S11: -14531.11 | T11: INR | U11: -14531.11 | W11: 6779224500 | Y11: NA | Z11: 1 | AE11: 46030 | AF11: 46030 | AG11: 1400002389 | AH11: {=VLOOKUP(M11,'Customer data Vlookup'!$B$3:$H$127,{2,3},0)} -> #N/A | AO11: =VLOOKUP(M11,'Customer data'!F:P,11,0) -> #N/A
A12: Selected | B12: 6779 | C12: 100222397 | D12: BARNET INDIA PRIVATE LIMITED | E12: 2025 | F12: 10 | G12: 46028 | H12: 1800016266 | I12: DR | J12: 46028 | K12: 46031 | L12: 2158342 | M12: 256779440152 | N12: 212100 | O12: Trade Debtors (Ctrl) | Q12: 01 | R12: USD | S12: 246.17 | T12: INR | U12: 22338.24 | V12: O0 | W12: 6779224500 | Y12: NA | Z12: 1 | AA12: PORT SSR Chgs Dec 25 | AE12: 46028 | AH12: {=VLOOKUP(M12,'Customer data Vlookup'!$B$3:$H$127,{2,3},0)} -> 22338.239 | AI12: 447 | AJ12: =AH12-AI12 -> 21891.239 | AK12: =U12-AH12 -> 0.0012262 | AL12: =AI12/U12 -> 0.020010529 | AO12: =VLOOKUP(M12,'Customer data'!F:P,11,0) -> Not Approved
A13: Selected | B13: 6779 | C13: 100222397 | D13: BARNET INDIA PRIVATE LIMITED | E13: 2025 | F13: 8 | G13: 46028 | H13: 1800016352 | I13: DR | J13: 46028 | K13: 46034 | L13: 2158411 | M13: 256779440242 | N13: 212100 | O13: Trade Debtors (Ctrl) | Q13: 01 | R13: USD | S13: 881.6 | T13: INR | U13: 79999.15 | V13: O0 | W13: 6779224500 | Y13: NA | Z13: 1 | AA13: Unit Storage - 1-31 DEC 2025 | AE13: 46028 | AH13: {=VLOOKUP(M13,'Customer data Vlookup'!$B$3:$H$127,{2,3},0)} -> 79999.152 | AI13: 8000 | AJ13: =AH13-AI13 -> 71999.152 | AK13: =U13-AH13 -> -0.002224 | AL13: =AI13/U13 -> 0.10000106 | AO13: =VLOOKUP(M13,'Customer data'!F:P,11,0) -> Not Approved
A14: Selected | B14: 6779 | C14: 100222397 | D14: BARNET INDIA PRIVATE LIMITED | E14: 2025 | F14: 11 | G14: 46027 | H14: 1800016064 | I14: DR | J14: 46027 | K14: 46027 | L14: 2156406 | M14: 256779440106 | N14: 212100 | O14: Trade Debtors (Ctrl) | Q14: 01 | R14: USD | S14: 700 | T14: INR | U14: 63520.2 | V14: O0 | W14: 6779224500 | Y14: NA | Z14: 1 | AA14: Transportation IN Chgs - 01 - 15 DEC 25 | AE14: 46027 | AH14: {=VLOOKUP(M14,'Customer data Vlookup'!$B$3:$H$127,{2,3},0)} -> 63520.198 | AI14: 1270 | AJ14: =AH14-AI14 -> 62250.198 | AK14: =U14-AH14 -> 0.002 | AL14: =AI14/U14 -> 0.01999364 | AO14: =VLOOKUP(M14,'Customer data'!F:P,11,0) -> Not Approved
A15: Selected | B15: 6779 | C15: 100222397 | D15: BARNET INDIA PRIVATE LIMITED | E15: 2025 | F15: 8 | G15: 46024 | H15: 1800015679 | I15: DR | J15: 46024 | K15: 46024 | L15: NA | M15: 256779440012 | N15: 212100 | O15: Trade Debtors (Ctrl) | Q15: 01 | R15: USD | S15: 182.78 | T15: INR | U15: 16586.03 | V15: O0 | W15: 6779224500 | Y15: 2139799 | Z15: 1 | AA15: Unit Storage - 1-30 Nov 2025 | AE15: 46024 | AH15: {=VLOOKUP(M15,'Customer data Vlookup'!$B$3:$H$127,{2,3},0)} -> 33172.062 | AI15: 3318 | AJ15: =AH15-AI15 -> 29854.062 | AK15: =U15-AH15 -> -16586.032 | AL15: =AI15/U15 -> 0.20004787 | AO15: =VLOOKUP(M15,'Customer data'!F:P,11,0) -> Not Approved
A16: Selected | B16: 6779 | C16: 100222397 | D16: BARNET INDIA PRIVATE LIMITED | E16: 2025 | F16: 10 | G16: 46024 | H16: 1800015717 | I16: DR | J16: 46024 | K16: 46024 | L16: NA | M16: 256779440046 | N16: 212100 | O16: Trade Debtors (Ctrl) | Q16: 01 | R16: USD | S16: 50 | T16: INR | U16: 4537.16 | V16: O0 | W16: 6779224500 | Y16: 2139808 | Z16: 1 | AA16: Scanning Chgs - 16 - 30 Nov 25 | AE16: 46024 | AH16: {=VLOOKUP(M16,'Customer data Vlookup'!$B$3:$H$127,{2,3},0)} -> 9074.314 | AI16: 182 | AJ16: =AH16-AI16 -> 8892.314 | AK16: =U16-AH16 -> -4537.154 | AL16: =AI16/U16 -> 0.040113199 | AO16: =VLOOKUP(M16,'Customer data'!F:P,11,0) -> Not Approved
A17: Selected | B17: 6779 | C17: 100222397 | D17: BARNET INDIA PRIVATE LIMITED | E17: 2025 | F17: 9 | G17: 46011 | H17: 1400002237 | I17: DZ | J17: 46011 | K17: 46011 | L17: G90RGJ9HVGZQ | N17: 212100 | O17: Trade Debtors (Ctrl) | Q17: 15 | R17: INR | S17: -14903.5 | T17: INR | U17: -14903.5 | W17: 6779220000 | Z17: 2 | AE17: 46011 | AF17: 46030 | AG17: 1400002389 | AH17: {=VLOOKUP(M17,'Customer data Vlookup'!$B$3:$H$127,{2,3},0)} -> #N/A | AO17: =VLOOKUP(M17,'Customer data'!F:P,11,0) -> #N/A
A18: Selected | B18: 6779 | C18: 100222397 | D18: BARNET INDIA PRIVATE LIMITED | E18: 2025 | F18: 10 | G18: 46007 | H18: 1400002197 | I18: DZ | J18: 46007 | K18: 46007 | L18: G15K40FCKGJH | N18: 212100 | O18: Trade Debtors (Ctrl) | Q18: 15 | R18: INR | S18: -67082.14 | T18: INR | U18: -66620.79 | W18: 6779224500 | Z18: 5 | AA18: G15K40FCKGJH | AE18: 46007 | AF18: 46007 | AG18: 1400002197 | AH18: {=VLOOKUP(M18,'Customer data Vlookup'!$B$3:$H$127,{2,3},0)} -> #N/A | AO18: =VLOOKUP(M18,'Customer data'!F:P,11,0) -> #N/A
A19: Selected | B19: 6779 | C19: 100222397 | D19: BARNET INDIA PRIVATE LIMITED | E19: 2025 | F19: 10 | G19: 46007 | H19: 1400002197 | I19: DZ | J19: 46007 | K19: 46007 | L19: G15K40FCKGJH | N19: 212100 | O19: Trade Debtors (Ctrl) | Q19: 15 | R19: INR | S19: -31045.05 | T19: INR | U19: -30866.77 | W19: 6779224501 | Z19: 4 | AA19: G15K40FCKGJH | AE19: 46007 | AF19: 46007 | AG19: 1400002197 | AH19: {=VLOOKUP(M19,'Customer data Vlookup'!$B$3:$H$127,{2,3},0)} -> #N/A | AO19: =VLOOKUP(M19,'Customer data'!F:P,11,0) -> #N/A
A20: Selected | B20: 6779 | C20: 100222397 | D20: BARNET INDIA PRIVATE LIMITED | E20: 2025 | F20: 10 | G20: 46007 | H20: 1400002198 | I20: DZ | J20: 46007 | K20: 46007 | L20: G15K40FCKGJH | N20: 212100 | O20: Trade Debtors (Ctrl) | Q20: 15 | R20: INR | S20: -14531.11 | T20: INR | U20: -14531.11 | W20: 6779220000 | Z20: 2 | AE20: 46007 | AF20: 46030 | AG20: 1400002388 | AH20: {=VLOOKUP(M20,'Customer data Vlookup'!$B$3:$H$127,{2,3},0)} -> #N/A | AO20: =VLOOKUP(M20,'Customer data'!F:P,11,0) -> #N/A
A21: Selected | B21: 6779 | C21: 100222397 | D21: BARNET INDIA PRIVATE LIMITED | E21: 2025 | F21: 10 | G21: 46007 | H21: 1400002197 | I21: DZ | J21: 46007 | K21: 46007 | L21: G15K40FCKGJH | N21: 212100 | O21: Trade Debtors (Ctrl) | Q21: 15 | R21: INR | S21: -296024 | T21: INR | U21: -296024 | W21: 6779224500 | Y21: NA | Z21: 3 | AE21: 46007 | AH21: {=VLOOKUP(M21,'Customer data Vlookup'!$B$3:$H$127,{2,3},0)} -> #N/A | AO21: =VLOOKUP(M21,'Customer data'!F:P,11,0) -> #N/A
A22: Selected | B22: 6779 | C22: 100222397 | D22: BARNET INDIA PRIVATE LIMITED | E22: 2025 | F22: 10 | G22: 45999 | H22: 1800015381 | I22: DR | J22: 45999 | K22: 46000 | L22: NA | M22: 256779419830 | N22: 212100 | O22: Trade Debtors (Ctrl) | Q22: 01 | R22: USD | S22: 11.18 | T22: INR | U22: 991.67 | V22: O0 | W22: 6779224500 | Y22: 2140080 | Z22: 1 | AA22: Bond Stamp Paper Chgs Nov 25 | AE22: 45999 | AH22: {=VLOOKUP(M22,'Customer data Vlookup'!$B$3:$H$127,{2,3},0)} -> 991.66757 | AI22: 20 | AJ22: =AH22-AI22 -> 971.66757 | AK22: =U22-AH22 -> 0.0024348 | AL22: =AI22/U22 -> 0.020167999 | AO22: =VLOOKUP(M22,'Customer data'!F:P,11,0) -> HDFCH00806112854
A23: Selected | B23: 6779 | C23: 100222397 | D23: BARNET INDIA PRIVATE LIMITED | E23: 2025 | F23: 10 | G23: 45996 | H23: 1800015349 | I23: DR | J23: 45996 | K23: 46000 | L23: NA | M23: 256779419798 | N23: 212100 | O23: Trade Debtors (Ctrl) | Q23: 01 | R23: USD | S23: 350 | T23: INR | U23: 31045.05 | V23: O0 | W23: 6779224500 | Y23: 2140069 | Z23: 1 | AA23: Transportation In Chgs - 16 - 30 Nov 25 | AE23: 45996 | AH23: {=VLOOKUP(M23,'Customer data Vlookup'!$B$3:$H$127,{2,3},0)} -> 31045.049 | AI23: 621 | AJ23: =AH23-AI23 -> 30424.049 | AK23: =U23-AH23 -> 0.001 | AL23: =AI23/U23 -> 0.020003189 | AO23: =VLOOKUP(M23,'Customer data'!F:P,11,0) -> HDFCH00806112855
A24: Selected | B24: 6779 | C24: 100222397 | D24: BARNET INDIA PRIVATE LIMITED | E24: 2025 | F24: 10 | G24: 45979 | H24: 1400001956 | I24: DZ | J24: 45979 | K24: 45979 | L24: HDFCN52025082733046460 | N24: 212100 | O24: Trade Debtors (Ctrl) | Q24: 15 | R24: INR | S24: -109304.71 | T24: INR | U24: -109304.71 | W24: 6779224500 | Z24: 3 | AA24: HDFCN52025082733046460 | AE24: 45979 | AF24: 45979 | AG24: 1400001956 | AH24: {=VLOOKUP(M24,'Customer data Vlookup'!$B$3:$H$127,{2,3},0)} -> #N/A | AO24: =VLOOKUP(M24,'Customer data'!F:P,11,0) -> #N/A
A25: Selected | B25: 6779 | C25: 100222397 | D25: BARNET INDIA PRIVATE LIMITED | E25: 2025 | F25: 9 | G25: 45979 | H25: 1400001961 | I25: DZ | J25: 45979 | K25: 45979 | L25: HDFCN52025060575568983 | N25: 212100 | O25: Trade Debtors (Ctrl) | Q25: 15 | R25: INR | S25: -8051.51 | T25: INR | U25: -8051.51 | W25: 6779224500 | Z25: 5 | AA25: HDFCN52025060575568983 | AE25: 45979 | AF25: 45979 | AG25: 1400001961 | AH25: {=VLOOKUP(M25,'Customer data Vlookup'!$B$3:$H$127,{2,3},0)} -> #N/A | AO25: =VLOOKUP(M25,'Customer data'!F:P,11,0) -> #N/A
A26: Selected | B26: 6779 | C26: 100222397 | D26: BARNET INDIA PRIVATE LIMITED | E26: 2025 | F26: 11 | G26: 45979 | H26: 1400001961 | I26: DZ | J26: 45979 | K26: 45979 | L26: HDFCN52025060575568983 | N26: 212100 | O26: Trade Debtors (Ctrl) | Q26: 15 | R26: INR | S26: -159132.62 | T26: INR | U26: -159622.78 | W26: 6779224500 | Z26: 4 | AA26: HDFCN52025060575568983 | AE26: 45979 | AF26: 45979 | AG26: 1400001961 | AH26: {=VLOOKUP(M26,'Customer data Vlookup'!$B$3:$H$127,{2,3},0)} -> #N/A | AO26: =VLOOKUP(M26,'Customer data'!F:P,11,0) -> #N/A
A27: Selected | B27: 6779 | C27: 100222397 | D27: BARNET INDIA PRIVATE LIMITED | E27: 2025 | F27: 9 | G27: 45979 | H27: 1400001971 | I27: DZ | J27: 45979 | K27: 45979 | L27: HDFCN52025072369906032 | N27: 212100 | O27: Trade Debtors (Ctrl) | Q27: 15 | R27: INR | S27: -50196.87 | T27: INR | U27: -50734.53 | W27: 6779224500 | Z27: 4 | AA27: HDFCN52025072369906032 | AE27: 45979 | AF27: 45979 | AG27: 1400001971 | AH27: {=VLOOKUP(M27,'Customer data Vlookup'!$B$3:$H$127,{2,3},0)} -> #N/A | AO27: =VLOOKUP(M27,'Customer data'!F:P,11,0) -> #N/A
A28: Not Selected | B28: 6779 | C28: 100222397 | D28: BARNET INDIA PRIVATE LIMITED | E28: 2025 | F28: 7 | G28: 45979 | H28: 1400001972 | I28: DZ | J28: 45979 | K28: 45979 | L28: HDFCN52025072369906032 | N28: 212100 | O28: Trade Debtors (Ctrl) | Q28: 15 | R28: INR | S28: -477139.41 | T28: INR | U28: -477139.41 | W28: 6779224500 | Z28: 3 | AA28: HDFCN52025072369906032 | AE28: 45979 | AF28: 45979 | AG28: 1400001972 | AH28: {=VLOOKUP(M28,'Customer data Vlookup'!$B$3:$H$127,{2,3},0)} -> #N/A | AO28: =VLOOKUP(M28,'Customer data'!F:P,11,0) -> #N/A
A29: Selected | B29: 6779 | C29: 100222397 | D29: BARNET INDIA PRIVATE LIMITED | E29: 2025 | F29: 7 | G29: 45972 | H29: 1400001627 | I29: DZ | J29: 45972 | K29: 45972 | L29: HDFCN52025100308494407 | N29: 212100 | O29: Trade Debtors (Ctrl) | Q29: 15 | R29: INR | S29: -324591.96 | T29: INR | U29: -324591.96 | W29: 6779220000 | Z29: 2 | AE29: 45972 | AH29: {=VLOOKUP(M29,'Customer data Vlookup'!$B$3:$H$127,{2,3},0)} -> #N/A | AO29: =VLOOKUP(M29,'Customer data'!F:P,11,0) -> #N/A
A30: Selected | B30: 6779 | C30: 100222397 | D30: BARNET INDIA PRIVATE LIMITED | E30: 2025 | F30: 10 | G30: 45966 | H30: 1800014545 | I30: DR | J30: 45966 | K30: 45967 | L30: NA | M30: 256779418877 | N30: 212100 | O30: Trade Debtors (Ctrl) | Q30: 01 | R30: USD | S30: 367.84 | T30: INR | U30: 32371.17 | V30: O0 | W30: 6779224500 | Y30: 2123390 | Z30: 1 | AA30: Unit Storage - 1-31 Oct 2025 | AE30: 45966 | AF30: 46007 | AG30: 1400002197 | AH30: {=VLOOKUP(M30,'Customer data Vlookup'!$B$3:$H$127,{2,3},0)} -> 32371.167 | AI30: 3237 | AJ30: =AH30-AI30 -> 29134.167 | AK30: =U30-AH30 -> 0.0030224 | AL30: =AI30/U30 -> 0.099996386 | AO30: =VLOOKUP(M30,'Customer data'!F:P,11,0) -> HDFCH00646925098
A31: Selected | B31: 6779 | C31: 100222397 | D31: BARNET INDIA PRIVATE LIMITED | E31: 2025 | F31: 11 | G31: 45966 | H31: 1800014715 | I31: DR | J31: 45966 | K31: 45968 | L31: 2123630 | M31: 256779419216 | N31: 212100 | O31: Trade Debtors (Ctrl) | Q31: 01 | R31: USD | S31: 27.17 | T31: INR | U31: 2391.05 | V31: O0 | W31: 6779224500 | Y31: NA | Z31: 1 | AA31: PORT SSR Chgs Oct 25 | AE31: 45966 | AF31: 46007 | AG31: 1400002197 | AH31: {=VLOOKUP(M31,'Customer data Vlookup'!$B$3:$H$127,{2,3},0)} -> 2391.0521 | AI31: 48 | AJ31: =AH31-AI31 -> 2343.0521 | AK31: =U31-AH31 -> -0.0021063 | AL31: =AI31/U31 -> 0.020074863 | AO31: =VLOOKUP(M31,'Customer data'!F:P,11,0) -> HDFCH00646925098
A32: Selected | B32: 6779 | C32: 100222397 | D32: BARNET INDIA PRIVATE LIMITED | E32: 2025 | F32: 7 | G32: 45966 | H32: 1800014737 | I32: DR | J32: 45966 | K32: 45968 | L32: NA | M32: 256779419240 | N32: 212100 | O32: Trade Debtors (Ctrl) | Q32: 01 | R32: USD | S32: 11.27 | T32: INR | U32: 991.8 | V32: O0 | W32: 6779224500 | Y32: 2123648 | Z32: 1 | AA32: Bond Stamp Paper Chgs Oct 25 | AE32: 45966 | AF32: 46007 | AG32: 1400002197 | AH32: {=VLOOKUP(M32,'Customer data Vlookup'!$B$3:$H$127,{2,3},0)} -> 991.79821 | AI32: 20 | AJ32: =AH32-AI32 -> 971.79821 | AK32: =U32-AH32 -> 0.0017947 | AL32: =AI32/U32 -> 0.020165356 | AO32: =VLOOKUP(M32,'Customer data'!F:P,11,0) -> HDFCH00646925098
A33: Selected | B33: 6779 | C33: 100222397 | D33: BARNET INDIA PRIVATE LIMITED | E33: 2025 | F33: 10 | G33: 45950 | H33: 1800013820 | I33: DR | J33: 45950 | K33: 45951 | L33: NA | M33: 256779418638 | N33: 212100 | O33: Trade Debtors (Ctrl) | Q33: 01 | R33: USD | S33: 350 | T33: INR | U33: 30866.77 | V33: O0 | W33: 6779224500 | Y33: 2114881 | Z33: 1 | AA33: Transportation In Chgs - 01 - 15 OCT 25 | AE33: 45950 | AF33: 46007 | AG33: 1400002197 | AH33: {=VLOOKUP(M33,'Customer data Vlookup'!$B$3:$H$127,{2,3},0)} -> 30866.769 | AI33: 617 | AJ33: =AH33-AI33 -> 30249.769 | AK33: =U33-AH33 -> 0.0005 | AL33: =AI33/U33 -> 0.019989134 | AO33: =VLOOKUP(M33,'Customer data'!F:P,11,0) -> HDFCH00646925098
A34: Selected | B34: 6779 | C34: 100222397 | D34: BARNET INDIA PRIVATE LIMITED | E34: 2025 | F34: 10 | G34: 45946 | H34: 1400001452 | I34: DZ | J34: 45946 | K34: 45946 | L34: HDFCN52025082227307462 | N34: 212100 | O34: Trade Debtors (Ctrl) | Q34: 15 | R34: INR | S34: -492224.78 | T34: INR | U34: -492209.06 | W34: 6779224500 | Z34: 3 | AA34: HDFCN52025082227307462 | AE34: 45946 | AF34: 45946 | AG34: 1400001452 | AH34: {=VLOOKUP(M34,'Customer data Vlookup'!$B$3:$H$127,{2,3},0)} -> #N/A | AO34: =VLOOKUP(M34,'Customer data'!F:P,11,0) -> #N/A
A35: Selected | B35: 6779 | C35: 100222397 | D35: BARNET INDIA PRIVATE LIMITED | E35: 2025 | F35: 4 | G35: 45946 | H35: 1400001453 | I35: DZ | J35: 45946 | K35: 45946 | L35: HDFCH00465695692 | N35: 212100 | O35: Trade Debtors (Ctrl) | Q35: 08 | R35: INR | S35: 2932.62 | T35: INR | U35: 2932.62 | W35: 6779224500 | Z35: 4 | AA35: HDFCH00465695692 | AE35: 45946 | AF35: 45946 | AG35: 1400001453 | AH35: {=VLOOKUP(M35,'Customer data Vlookup'!$B$3:$H$127,{2,3},0)} -> #N/A | AO35: =VLOOKUP(M35,'Customer data'!F:P,11,0) -> #N/A
A36: Selected | B36: 6779 | C36: 100222397 | D36: BARNET INDIA PRIVATE LIMITED | E36: 2025 | F36: 4 | G36: 45946 | H36: 1400001453 | I36: DZ | J36: 45946 | K36: 45946 | L36: HDFCH00465695692 | N36: 212100 | O36: Trade Debtors (Ctrl) | Q36: 15 | R36: INR | S36: -142188.03 | T36: INR | U36: -139776.58 | W36: 6779224500 | Z36: 5 | AA36: HDFCH00465695692 | AE36: 45946 | AF36: 45946 | AG36: 1400001453 | AH36: {=VLOOKUP(M36,'Customer data Vlookup'!$B$3:$H$127,{2,3},0)} -> #N/A | AO36: =VLOOKUP(M36,'Customer data'!F:P,11,0) -> #N/A
A37: Selected | B37: 6779 | C37: 100222397 | D37: BARNET INDIA PRIVATE LIMITED | E37: 2025 | F37: 4 | G37: 45946 | H37: 1400001452 | I37: DZ | J37: 45946 | K37: 45946 | L37: HDFCN52025082227307462 | N37: 212100 | O37: Trade Debtors (Ctrl) | Q37: 15 | R37: INR | S37: -2932.62 | T37: INR | U37: -2932.62 | W37: 6779224500 | Y37: NA | Z37: 2 | AE37: 45946 | AF37: 45946 | AG37: 1400001453 | AH37: {=VLOOKUP(M37,'Customer data Vlookup'!$B$3:$H$127,{2,3},0)} -> #N/A | AO37: =VLOOKUP(M37,'Customer data'!F:P,11,0) -> #N/A
A38: Selected | B38: 6779 | C38: 100222397 | D38: BARNET INDIA PRIVATE LIMITED | E38: 2025 | F38: 4 | G38: 45946 | H38: 1400001454 | I38: DZ | J38: 45946 | K38: 45946 | L38: HDFCN52025051435275414 | N38: 212100 | O38: Trade Debtors (Ctrl) | Q38: 15 | R38: INR | S38: -115726.32 | T38: INR | U38: -116988.95 | Z38: 4 | AA38: HDFCN52025051435275414 | AE38: 45946 | AF38: 45946 | AG38: 1400001454 | AH38: {=VLOOKUP(M38,'Customer data Vlookup'!$B$3:$H$127,{2,3},0)} -> #N/A | AO38: =VLOOKUP(M38,'Customer data'!F:P,11,0) -> #N/A
A39: Selected | B39: 6779 | C39: 100222397 | D39: BARNET INDIA PRIVATE LIMITED | E39: 2025 | F39: 4 | G39: 45946 | H39: 1400001455 | I39: DZ | J39: 45946 | K39: 45946 | L39: HDFCN52025100205721894 | N39: 212100 | O39: Trade Debtors (Ctrl) | Q39: 15 | R39: INR | S39: -659505.58 | T39: INR | U39: -646935.77 | W39: 6779224500 | Z39: 4 | AA39: HDFCN52025100205721894 | AE39: 45946 | AF39: 45946 | AG39: 1400001455 | AH39: {=VLOOKUP(M39,'Customer data Vlookup'!$B$3:$H$127,{2,3},0)} -> #N/A | AO39: =VLOOKUP(M39,'Customer data'!F:P,11,0) -> #N/A
A40: Selected | B40: 6779 | C40: 100222397 | D40: BARNET INDIA PRIVATE LIMITED | E40: 2025 | F40: 4 | G40: 45946 | H40: 1400001456 | I40: DZ | J40: 45946 | K40: 45946 | L40: HDFCN52025062512710909 | N40: 212100 | O40: Trade Debtors (Ctrl) | Q40: 15 | R40: USD | S40: -2140.03 | T40: INR | U40: -182952.83 | W40: 6779224500 | Z40: 3 | AA40: HDFCN52025062512710909 | AE40: 45946 | AF40: 45946 | AG40: 1400001456 | AH40: {=VLOOKUP(M40,'Customer data Vlookup'!$B$3:$H$127,{2,3},0)} -> #N/A | AO40: =VLOOKUP(M40,'Customer data'!F:P,11,0) -> #N/A
A41: Selected | B41: 6779 | C41: 100222397 | D41: BARNET INDIA PRIVATE LIMITED | E41: 2025 | F41: 4 | G41: 45938 | H41: 1400001468 | I41: DZ | J41: 45938 | K41: 45946 | L41: HDFCN52025100205721894 | N41: 212100 | O41: Trade Debtors (Ctrl) | Q41: 05 | R41: INR | S41: 339060.54 | T41: INR | U41: 339060.54 | W41: 6779220000 | Z41: 2 | AE41: 45938 | AF41: 45938 | AG41: 1400001468 | AH41: {=VLOOKUP(M41,'Customer data Vlookup'!$B$3:$H$127,{2,3},0)} -> #N/A | AO41: =VLOOKUP(M41,'Customer data'!F:P,11,0) -> #N/A
A42: Selected | B42: 6779 | C42: 100222397 | D42: BARNET INDIA PRIVATE LIMITED | E42: 2025 | F42: 4 | G42: 45938 | H42: 1400001367 | I42: DZ | J42: 45938 | K42: 45938 | L42: HDFCN52025100205721894 | N42: 212100 | O42: Trade Debtors (Ctrl) | Q42: 15 | R42: INR | S42: -339060.54 | T42: INR | U42: -339060.54 | W42: 6779220000 | Z42: 2 | AE42: 45938 | AF42: 45938 | AG42: 1400001468 | AH42: {=VLOOKUP(M42,'Customer data Vlookup'!$B$3:$H$127,{2,3},0)} -> #N/A | AO42: =VLOOKUP(M42,'Customer data'!F:P,11,0) -> #N/A
A43: Selected | B43: 6779 | C43: 100222397 | D43: BARNET INDIA PRIVATE LIMITED | E43: 2025 | F43: 4 | G43: 45935 | H43: 1800013318 | I43: DR | J43: 45935 | K43: 45937 | L43: NA | M43: 256779417914 | N43: 212100 | O43: Trade Debtors (Ctrl) | Q43: 01 | R43: USD | S43: 350 | T43: INR | U43: 30866.77 | V43: O0 | W43: 6779224501 | Y43: NA | Z43: 1 | AA43: Transportation In Chgs - 16 - 30 SEP 25 | AE43: 45935 | AF43: 46007 | AG43: 1400002197 | AH43: {=VLOOKUP(M43,'Customer data Vlookup'!$B$3:$H$127,{2,3},0)} -> 30866.769 | AI43: 617 | AJ43: =AH43-AI43 -> 30249.769 | AK43: =U43-AH43 -> 0.0005 | AL43: =AI43/U43 -> 0.019989134 | AO43: =VLOOKUP(M43,'Customer data'!F:P,11,0) -> HDFCH00646925098
A44: Not Selected | B44: 6779 | C44: 100222397 | D44: BARNET INDIA PRIVATE LIMITED | E44: 2025 | F44: 12 | G44: 45931 | H44: 1400001329 | I44: DZ | J44: 45931 | K44: 45931 | L44: HDFCN52025061495304800 | N44: 212100 | O44: Trade Debtors (Ctrl) | Q44: 15 | R44: INR | S44: -226409 | T44: INR | U44: -226409 | W44: 6779220000 | Z44: 2 | AE44: 45931 | AH44: {=VLOOKUP(M44,'Customer data Vlookup'!$B$3:$H$127,{2,3},0)} -> #N/A | AO44: =VLOOKUP(M44,'Customer data'!F:P,11,0) -> #N/A
A45: Selected | B45: 6779 | C45: 100222397 | D45: BARNET INDIA PRIVATE LIMITED | E45: 2025 | F45: 12 | G45: 45918 | H45: 1400001206 | I45: DY | J45: 45918 | K45: 45918 | N45: 212100 | O45: Trade Debtors (Ctrl) | Q45: 15 | R45: INR | S45: 0 | T45: INR | U45: 0 | W45: 6779224500 | Z45: 1 | AE45: 45918 | AF45: 45918 | AG45: 1400001206 | AH45: {=VLOOKUP(M45,'Customer data Vlookup'!$B$3:$H$127,{2,3},0)} -> #N/A | AO45: =VLOOKUP(M45,'Customer data'!F:P,11,0) -> #N/A
A46: Not Selected | B46: 6779 | C46: 100222397 | D46: BARNET INDIA PRIVATE LIMITED | E46: 2025 | F46: 11 | G46: 45917 | H46: 1800013170 | I46: DR | J46: 45917 | K46: 45923 | L46: NA | M46: 256779417777 | N46: 212100 | O46: Trade Debtors (Ctrl) | Q46: 01 | R46: USD | S46: 50.34 | T46: INR | U46: 4405.47 | V46: O0 | W46: 6779224500 | Y46: 2102586 | Z46: 1 | AA46: VAS Activity - Feb 25, Ex Rate. 87.40 | AE46: 45917 | AF46: 45946 | AG46: 1400001455 | AH46: {=VLOOKUP(M46,'Customer data Vlookup'!$B$3:$H$127,{2,3},0)} -> 4405.4714 | AI46: 88 | AJ46: =AH46-AI46 -> 4317.4714 | AK46: =U46-AH46 -> -0.0013722 | AL46: =AI46/U46 -> 0.019975167 | AO46: =VLOOKUP(M46,'Customer data'!F:P,11,0) -> HDFCN52025100205721894
A47: Selected | B47: 6779 | C47: 100222397 | D47: BARNET INDIA PRIVATE LIMITED | E47: 2025 | F47: 7 | G47: 45946 | H47: 1400001449 | I47: DZ | J47: 45912 | K47: 45946 | L47: HDFCN52025090553870975 | N47: 212100 | O47: Trade Debtors (Ctrl) | Q47: 05 | R47: INR | S47: 124189.23 | T47: INR | U47: 124189.23 | W47: 6779220000 | Z47: 2 | AE47: 45912 | AF47: 45946 | AG47: 1400001449 | AH47: {=VLOOKUP(M47,'Customer data Vlookup'!$B$3:$H$127,{2,3},0)} -> #N/A | AO47: =VLOOKUP(M47,'Customer data'!F:P,11,0) -> #N/A
A48: Selected | B48: 6779 | C48: 100222397 | D48: BARNET INDIA PRIVATE LIMITED | E48: 2025 | F48: 7 | G48: 45912 | H48: 1400001173 | I48: DZ | J48: 45912 | K48: 45912 | L48: HDFCN52025090553870975 | N48: 212100 | O48: Trade Debtors (Ctrl) | Q48: 15 | R48: INR | S48: -124189.23 | T48: INR | U48: -124189.23 | W48: 6779220000 | Z48: 2 | AE48: 45912 | AF48: 45946 | AG48: 1400001449 | AH48: {=VLOOKUP(M48,'Customer data Vlookup'!$B$3:$H$127,{2,3},0)} -> #N/A | AO48: =VLOOKUP(M48,'Customer data'!F:P,11,0) -> #N/A
A49: Selected | B49: 6779 | C49: 100222397 | D49: BARNET INDIA PRIVATE LIMITED | E49: 2025 | F49: 7 | G49: 45946 | H49: 1400001450 | I49: DZ | J49: 45908 | K49: 45946 | N49: 212100 | O49: Trade Debtors (Ctrl) | Q49: 05 | R49: INR | S49: 495157.4 | T49: INR | U49: 495157.4 | W49: 6779220000 | Z49: 2 | AE49: 45908 | AF49: 45946 | AG49: 1400001450 | AH49: {=VLOOKUP(M49,'Customer data Vlookup'!$B$3:$H$127,{2,3},0)} -> #N/A | AO49: =VLOOKUP(M49,'Customer data'!F:P,11,0) -> #N/A
A50: Selected | B50: 6779 | C50: 100222397 | D50: BARNET INDIA PRIVATE LIMITED | E50: 2025 | F50: 7 | G50: 45908 | H50: 1400001142 | I50: DZ | J50: 45908 | K50: 45908 | N50: 212100 | O50: Trade Debtors (Ctrl) | Q50: 15 | R50: INR | S50: -495157.4 | T50: INR | U50: -495157.4 | W50: 6779220000 | Z50: 2 | AE50: 45908 | AF50: 45946 | AG50: 1400001450 | AH50: {=VLOOKUP(M50,'Customer data Vlookup'!$B$3:$H$127,{2,3},0)} -> #N/A | AO50: =VLOOKUP(M50,'Customer data'!F:P,11,0) -> #N/A
A51: Selected | B51: 6779 | C51: 100222397 | D51: BARNET INDIA PRIVATE LIMITED | E51: 2025 | F51: 7 | G51: 45985 | H51: 1400001988 | I51: DZ | J51: 45908 | K51: 45985 | L51: HDFCN52025082733046460 | N51: 212100 | O51: Trade Debtors (Ctrl) | Q51: 05 | R51: INR | S51: 107117.71 | T51: INR | U51: 107117.71 | W51: 6779220000 | Z51: 2 | AE51: 45908 | AF51: 45985 | AG51: 1400001988 | AH51: {=VLOOKUP(M51,'Customer data Vlookup'!$B$3:$H$127,{2,3},0)} -> #N/A | AO51: =VLOOKUP(M51,'Customer data'!F:P,11,0) -> #N/A
A52: Selected | B52: 6779 | C52: 100222397 | D52: BARNET INDIA PRIVATE LIMITED | E52: 2025 | F52: 7 | G52: 45908 | H52: 1400001145 | I52: DZ | J52: 45908 | K52: 45908 | L52: HDFCN52025082733046460 | N52: 212100 | O52: Trade Debtors (Ctrl) | Q52: 15 | R52: INR | S52: -107117.71 | T52: INR | U52: -107117.71 | W52: 6779220000 | Z52: 2 | AE52: 45908 | AF52: 45985 | AG52: 1400001988 | AH52: {=VLOOKUP(M52,'Customer data Vlookup'!$B$3:$H$127,{2,3},0)} -> #N/A | AO52: =VLOOKUP(M52,'Customer data'!F:P,11,0) -> #N/A
A53: Selected | B53: 6779 | C53: 100222397 | D53: BARNET INDIA PRIVATE LIMITED | E53: 2025 | F53: 7 | G53: 45906 | H53: 1800012483 | I53: DR | J53: 45906 | K53: 45909 | L53: NA | M53: 256779417091 | N53: 212100 | O53: Trade Debtors (Ctrl) | Q53: 01 | R53: USD | S53: 1598.28 | T53: INR | U53: 139872.4 | V53: O0 | W53: 6779224500 | Y53: NA | Z53: 1 | AA53: Unit-Storage-1-31 Aug 25 | AE53: 45906 | AF53: 45946 | AG53: 1400001455 | AH53: {=VLOOKUP(M53,'Customer data Vlookup'!$B$3:$H$127,{2,3},0)} -> 139872.4 | AI53: 13987 | AJ53: =AH53-AI53 -> 125885.4 | AK53: =U53-AH53 -> -0.0033524 | AL53: =AI53/U53 -> 0.099998284 | AO53: =VLOOKUP(M53,'Customer data'!F:P,11,0) -> HDFCN52025100205721894
A54: Selected | B54: 6779 | C54: 100222397 | D54: BARNET INDIA PRIVATE LIMITED | E54: 2025 | F54: 7 | G54: 45904 | H54: 1800012439 | I54: DR | J54: 45904 | K54: 45909 | L54: NA | M54: 256779417139 | N54: 212100 | O54: Trade Debtors (Ctrl) | Q54: 01 | R54: USD | S54: 25.04 | T54: INR | U54: 2191.36 | V54: O0 | W54: 6779224500 | Y54: NA | Z54: 1 | AA54: VAS -16-31 Aug 25 | AE54: 45904 | AF54: 45946 | AG54: 1400001455 | AH54: {=VLOOKUP(M54,'Customer data Vlookup'!$B$3:$H$127,{2,3},0)} -> 2191.3588 | AI54: 44 | AJ54: =AH54-AI54 -> 2147.3588 | AK54: =U54-AH54 -> 0.0011768 | AL54: =AI54/U54 -> 0.020078855 | AO54: =VLOOKUP(M54,'Customer data'!F:P,11,0) -> HDFCN52025100205721894
A55: Selected | B55: 6779 | C55: 100222397 | D55: BARNET INDIA PRIVATE LIMITED | E55: 2025 | F55: 7 | G55: 45904 | H55: 1800012440 | I55: DR | J55: 45904 | K55: 45909 | L55: NA | M55: 256779417140 | N55: 212100 | O55: Trade Debtors (Ctrl) | Q55: 01 | R55: USD | S55: 20.49 | T55: INR | U55: 1793.17 | V55: O0 | W55: 6779224500 | Y55: NA | Z55: 1 | AA55: WEIGHMENT -16-31 Aug 25 | AE55: 45904 | AF55: 45946 | AG55: 1400001455 | AH55: {=VLOOKUP(M55,'Customer data Vlookup'!$B$3:$H$127,{2,3},0)} -> 1793.1686 | AI55: 36 | AJ55: =AH55-AI55 -> 1757.1686 | AK55: =U55-AH55 -> 0.0013783 | AL55: =AI55/U55 -> 0.020076178 | AO55: =VLOOKUP(M55,'Customer data'!F:P,11,0) -> HDFCN52025100205721894
A56: Selected | B56: 6779 | C56: 100222397 | D56: BARNET INDIA PRIVATE LIMITED | E56: 2025 | F56: 7 | G56: 45904 | H56: 1800012572 | I56: DR | J56: 45904 | K56: 45909 | L56: NA | M56: 256779417191 | N56: 212100 | O56: Trade Debtors (Ctrl) | Q56: 01 | R56: USD | S56: 8.88 | T56: INR | U56: 777.13 | V56: O0 | W56: 6779224500 | Y56: NA | Z56: 1 | AA56: Detention Chgs - 01 - 31 AUG 25 | AE56: 45904 | AF56: 45946 | AG56: 1400001455 | AH56: {=VLOOKUP(M56,'Customer data Vlookup'!$B$3:$H$127,{2,3},0)} -> 777.12725 | AI56: 16 | AJ56: =AH56-AI56 -> 761.12725 | AK56: =U56-AH56 -> 0.0027496 | AL56: =AI56/U56 -> 0.020588576 | AO56: =VLOOKUP(M56,'Customer data'!F:P,11,0) -> HDFCN52025100205721894
A57: Selected | B57: 6779 | C57: 100222397 | D57: BARNET INDIA PRIVATE LIMITED | E57: 2025 | F57: 7 | G57: 45904 | H57: 1800012577 | I57: DR | J57: 45904 | K57: 45909 | L57: NA | M57: 256779417235 | N57: 212100 | O57: Trade Debtors (Ctrl) | Q57: 01 | R57: USD | S57: 412 | T57: INR | U57: 36055.9 | V57: O0 | W57: 6779224500 | Y57: NA | Z57: 1 | AA57: PORT SSR Chgs Aug 25 | AE57: 45904 | AF57: 45946 | AG57: 1400001455 | AH57: {=VLOOKUP(M57,'Customer data Vlookup'!$B$3:$H$127,{2,3},0)} -> 36055.904 | AI57: 721 | AJ57: =AH57-AI57 -> 35334.904 | AK57: =U57-AH57 -> -0.00396 | AL57: =AI57/U57 -> 0.019996727 | AO57: =VLOOKUP(M57,'Customer data'!F:P,11,0) -> HDFCN52025100205721894
A58: Selected | B58: 6779 | C58: 100222397 | D58: BARNET INDIA PRIVATE LIMITED | E58: 2025 | F58: 7 | G58: 45904 | H58: 1800012627 | I58: DR | J58: 45904 | K58: 45909 | L58: NA | M58: 256779417267 | N58: 212100 | O58: Trade Debtors (Ctrl) | Q58: 01 | R58: USD | S58: 164.68 | T58: INR | U58: 14411.86 | V58: O0 | W58: 6779224500 | Y58: NA | Z58: 1 | AA58: Cy - WH destuff - 16 - 31 AUG 25 | AE58: 45904 | AF58: 45946 | AG58: 1400001455 | AH58: {=VLOOKUP(M58,'Customer data Vlookup'!$B$3:$H$127,{2,3},0)} -> 14411.86 | AI58: 288 | AJ58: =AH58-AI58 -> 14123.86 | AK58: =U58-AH58 -> 0.0001356 | AL58: =AI58/U58 -> 0.019983541 | AO58: =VLOOKUP(M58,'Customer data'!F:P,11,0) -> HDFCN52025100205721894
A59: Selected | B59: 6779 | C59: 100222397 | D59: BARNET INDIA PRIVATE LIMITED | E59: 2025 | F59: 7 | G59: 45904 | H59: 1800012657 | I59: DR | J59: 45904 | K59: 45909 | L59: NA | M59: 256779417297 | N59: 212100 | O59: Trade Debtors (Ctrl) | Q59: 01 | R59: USD | S59: 137.68 | T59: INR | U59: 12048.97 | V59: O0 | W59: 6779224500 | Y59: 2096996 | Z59: 1 | AA59: Outbound chgs - 16 - 31 Aug 25 | AE59: 45904 | AF59: 45946 | AG59: 1400001455 | AH59: {=VLOOKUP(M59,'Customer data Vlookup'!$B$3:$H$127,{2,3},0)} -> 12048.973 | AI59: 241 | AJ59: =AH59-AI59 -> 11807.973 | AK59: =U59-AH59 -> -0.0029544 | AL59: =AI59/U59 -> 0.02000171 | AO59: =VLOOKUP(M59,'Customer data'!F:P,11,0) -> HDFCN52025100205721894
A60: Selected | B60: 6779 | C60: 100222397 | D60: BARNET INDIA PRIVATE LIMITED | E60: 2025 | F60: 7 | G60: 45946 | H60: 1400001458 | I60: DZ | J60: 45890 | K60: 45946 | L60: CT68PKL3P93Q | N60: 212100 | O60: Trade Debtors (Ctrl) | Q60: 05 | R60: INR | S60: 179293.83 | T60: INR | U60: 179293.83 | W60: 6779220000 | Z60: 2 | AE60: 45890 | AF60: 45946 | AG60: 1400001458 | AH60: {=VLOOKUP(M60,'Customer data Vlookup'!$B$3:$H$127,{2,3},0)} -> #N/A | AO60: =VLOOKUP(M60,'Customer data'!F:P,11,0) -> #N/A
A61: Selected | B61: 6779 | C61: 100222397 | D61: BARNET INDIA PRIVATE LIMITED | E61: 2025 | F61: 7 | G61: 45890 | H61: 1400000898 | I61: DZ | J61: 45890 | K61: 45890 | L61: CT68PKL3P93Q | N61: 212100 | O61: Trade Debtors (Ctrl) | Q61: 15 | R61: INR | S61: -179293.83 | T61: INR | U61: -179293.83 | W61: 6779220000 | Z61: 2 | AE61: 45890 | AF61: 45946 | AG61: 1400001458 | AH61: {=VLOOKUP(M61,'Customer data Vlookup'!$B$3:$H$127,{2,3},0)} -> #N/A | AO61: =VLOOKUP(M61,'Customer data'!F:P,11,0) -> #N/A
A62: Selected | B62: 6779 | C62: 100222397 | D62: BARNET INDIA PRIVATE LIMITED | E62: 2025 | F62: 7 | G62: 45985 | H62: 1400001989 | I62: DZ | J62: 45890 | K62: 45985 | L62: D2WMGTC7VB6Y | N62: 212100 | O62: Trade Debtors (Ctrl) | Q62: 05 | R62: INR | S62: 475086.94 | T62: INR | U62: 475086.94 | W62: 6779220000 | Z62: 2 | AE62: 45890 | AF62: 45985 | AG62: 1400001989 | AH62: {=VLOOKUP(M62,'Customer data Vlookup'!$B$3:$H$127,{2,3},0)} -> #N/A | AO62: =VLOOKUP(M62,'Customer data'!F:P,11,0) -> #N/A
A63: Selected | B63: 6779 | C63: 100222397 | D63: BARNET INDIA PRIVATE LIMITED | E63: 2025 | F63: 7 | G63: 45890 | H63: 1400000962 | I63: DZ | J63: 45890 | K63: 45890 | L63: D2WMGTC7VB6Y | N63: 212100 | O63: Trade Debtors (Ctrl) | Q63: 15 | R63: INR | S63: -475086.94 | T63: INR | U63: -475086.94 | W63: 6779220000 | Z63: 2 | AE63: 45890 | AF63: 45985 | AG63: 1400001989 | AH63: {=VLOOKUP(M63,'Customer data Vlookup'!$B$3:$H$127,{2,3},0)} -> #N/A | AO63: =VLOOKUP(M63,'Customer data'!F:P,11,0) -> #N/A
A64: Selected | B64: 6779 | C64: 100222397 | D64: BARNET INDIA PRIVATE LIMITED | E64: 2025 | F64: 7 | G64: 45889 | H64: 1800012165 | I64: DR | J64: 45889 | K64: 45891 | L64: NA | M64: 256779416810 | N64: 212100 | O64: Trade Debtors (Ctrl) | Q64: 01 | R64: USD | S64: 20.57 | T64: INR | U64: 1769.64 | V64: O0 | W64: 6779224500 | Y64: NA | Z64: 1 | AA64: Weighment-Aug 25- 1-15 | AE64: 45889 | AF64: 45946 | AG64: 1400001455 | AH64: {=VLOOKUP(M64,'Customer data Vlookup'!$B$3:$H$127,{2,3},0)} -> 1769.6396 | AI64: 35 | AJ64: =AH64-AI64 -> 1734.6396 | AK64: =U64-AH64 -> 0.0004316 | AL64: =AI64/U64 -> 0.019778034 | AO64: =VLOOKUP(M64,'Customer data'!F:P,11,0) -> HDFCN52025100205721894
A65: Selected | B65: 6779 | C65: 100222397 | D65: BARNET INDIA PRIVATE LIMITED | E65: 2025 | F65: 7 | G65: 45889 | H65: 1800012193 | I65: DR | J65: 45889 | K65: 45891 | L65: NA | M65: 256779416855 | N65: 212100 | O65: Trade Debtors (Ctrl) | Q65: 01 | R65: USD | S65: 137.68 | T65: INR | U65: 11844.63 | V65: O0 | W65: 6779224500 | Y65: NA | Z65: 1 | AA65: Outbound chgs - 01 - 15 Aug 25 | AE65: 45889 | AF65: 45946 | AG65: 1400001455 | AH65: {=VLOOKUP(M65,'Customer data Vlookup'!$B$3:$H$127,{2,3},0)} -> 8128.1257 | AI65: 163 | AJ65: =AH65-AI65 -> 7965.1257 | AK65: =U65-AH65 -> 3716.5043 | AL65: =AI65/U65 -> 0.01376151 | AO65: =VLOOKUP(M65,'Customer data'!F:P,11,0) -> HDFCN52025100205721894
A66: Selected | B66: 6779 | C66: 100222397 | D66: BARNET INDIA PRIVATE LIMITED | E66: 2025 | F66: 7 | G66: 45889 | H66: 1800012229 | I66: DR | J66: 45889 | K66: 45891 | L66: NA | M66: 256779416825 | N66: 212100 | O66: Trade Debtors (Ctrl) | Q66: 01 | R66: USD | S66: 3850 | T66: INR | U66: 331215.96 | V66: O0 | W66: 6779224500 | Y66: NA | Z66: 1 | AA66: Transportation In Chgs - 01 - 15 AUG 25 | AE66: 45889 | AH66: {=VLOOKUP(M66,'Customer data Vlookup'!$B$3:$H$127,{2,3},0)} -> 331215.96 | AI66: 6624 | AJ66: =AH66-AI66 -> 324591.96 | AK66: =U66-AH66 -> -0.002 | AL66: =AI66/U66 -> 0.019999036 | AO66: =VLOOKUP(M66,'Customer data'!F:P,11,0) -> HDFCN52025100308494407
A67: Selected | B67: 6779 | C67: 100222397 | D67: BARNET INDIA PRIVATE LIMITED | E67: 2025 | F67: 7 | G67: 45888 | H67: 1800011930 | I67: DR | J67: 45888 | K67: 45888 | L67: NA | M67: 256779416579 | N67: 212100 | O67: Trade Debtors (Ctrl) | Q67: 01 | R67: USD | S67: 270 | T67: INR | U67: 23228.13 | V67: O0 | W67: 6779224500 | Y67: NA | Z67: 1 | AA67: Empty Cont Out Chgs - 16 - 31 Jul 25 | AE67: 45888 | AF67: 45946 | AG67: 1400001452 | AH67: {=VLOOKUP(M67,'Customer data Vlookup'!$B$3:$H$127,{2,3},0)} -> 23228.132 | AI67: 465 | AJ67: =AH67-AI67 -> 22763.132 | AK67: =U67-AH67 -> -0.0024 | AL67: =AI67/U67 -> 0.020018831 | AO67: =VLOOKUP(M67,'Customer data'!F:P,11,0) -> HDFCN52025082227307462
A68: Selected | B68: 6779 | C68: 100222397 | D68: BARNET INDIA PRIVATE LIMITED | E68: 2025 | F68: 7 | G68: 45877 | H68: 1800011587 | I68: DR | J68: 45877 | K68: 45877 | L68: NA | M68: 256779416437 | N68: 212100 | O68: Trade Debtors (Ctrl) | Q68: 01 | R68: USD | S68: 150.77 | T68: INR | U68: 12970.76 | V68: O0 | W68: 6779224500 | Y68: NA | Z68: 1 | AA68: VAS 16-31 July 25 | AE68: 45877 | AF68: 45946 | AG68: 1400001452 | AH68: {=VLOOKUP(M68,'Customer data Vlookup'!$B$3:$H$127,{2,3},0)} -> 12970.761 | AI68: 259 | AJ68: =AH68-AI68 -> 12711.761 | AK68: =U68-AH68 -> -0.0011924 | AL68: =AI68/U68 -> 0.01996799 | AO68: =VLOOKUP(M68,'Customer data'!F:P,11,0) -> HDFCN52025082227307462
A69: Selected | B69: 6779 | C69: 100222397 | D69: BARNET INDIA PRIVATE LIMITED | E69: 2025 | F69: 7 | G69: 45877 | H69: 1800011600 | I69: DR | J69: 45877 | K69: 45877 | L69: NA | M69: 256779416450 | N69: 212100 | O69: Trade Debtors (Ctrl) | Q69: 01 | R69: USD | S69: 123.36 | T69: INR | U69: 10612.68 | V69: O0 | W69: 6779224500 | Y69: NA | Z69: 1 | AA69: Weighment - 16-31 July 25 | AE69: 45877 | AF69: 45946 | AG69: 1400001452 | AH69: {=VLOOKUP(M69,'Customer data Vlookup'!$B$3:$H$127,{2,3},0)} -> 10612.676 | AI69: 212 | AJ69: =AH69-AI69 -> 10400.676 | AK69: =U69-AH69 -> 0.0043968 | AL69: =AI69/U69 -> 0.019976104 | AO69: =VLOOKUP(M69,'Customer data'!F:P,11,0) -> HDFCN52025082227307462
A70: Selected | B70: 6779 | C70: 100222397 | D70: BARNET INDIA PRIVATE LIMITED | E70: 2025 | F70: 7 | G70: 45877 | H70: 1800011763 | I70: DR | J70: 45877 | K70: 45877 | L70: NA | M70: 256779416154 | N70: 212100 | O70: Trade Debtors (Ctrl) | Q70: 01 | R70: USD | S70: 1143.61 | T70: INR | U70: 98384.91 | V70: O0 | W70: 6779224500 | Y70: NA | Z70: 1 | AA70: Cy - WH destuff - 16 - 31 JUL 25 | AE70: 45877 | AF70: 45946 | AG70: 1400001452 | AH70: {=VLOOKUP(M70,'Customer data Vlookup'!$B$3:$H$127,{2,3},0)} -> 98384.906 | AI70: 1967 | AJ70: =AH70-AI70 -> 96417.906 | AK70: =U70-AH70 -> 0.0044668 | AL70: =AI70/U70 -> 0.019992903 | AO70: =VLOOKUP(M70,'Customer data'!F:P,11,0) -> HDFCN52025082227307462
A71: Selected | B71: 6779 | C71: 100222397 | D71: BARNET INDIA PRIVATE LIMITED | E71: 2025 | F71: 7 | G71: 45877 | H71: 1800011764 | I71: DR | J71: 45877 | K71: 45877 | L71: NA | M71: 256779416155 | N71: 212100 | O71: Trade Debtors (Ctrl) | Q71: 01 | R71: USD | S71: 3500 | T71: INR | U71: 301105.42 | V71: O0 | W71: 6779224500 | Y71: NA | Z71: 1 | AA71: Transportation In Chgs - 16 - 31 JUL 25 | AE71: 45877 | AF71: 45946 | AG71: 1400001452 | AH71: {=VLOOKUP(M71,'Customer data Vlookup'!$B$3:$H$127,{2,3},0)} -> 301105.42 | AI71: 6022 | AJ71: =AH71-AI71 -> 295083.42 | AK71: =U71-AH71 -> 0 | AL71: =AI71/U71 -> 0.01999964 | AO71: =VLOOKUP(M71,'Customer data'!F:P,11,0) -> HDFCN52025082227307462
A72: Selected | B72: 6779 | C72: 100222397 | D72: BARNET INDIA PRIVATE LIMITED | E72: 2025 | F72: 7 | G72: 45877 | H72: 1800011675 | I72: DR | J72: 45877 | K72: 45877 | L72: NA | M72: 256779416193 | N72: 212100 | O72: Trade Debtors (Ctrl) | Q72: 01 | R72: USD | S72: 1624.74 | T72: INR | U72: 139776.58 | V72: O0 | W72: 6779224500 | Y72: NA | Z72: 1 | AA72: Outbound chgs - 16 - 31 Jul 25 | AE72: 45877 | AF72: 45946 | AG72: 1400001453 | AH72: {=VLOOKUP(M72,'Customer data Vlookup'!$B$3:$H$127,{2,3},0)} -> 139776.58 | AI72: 2796 | AJ72: =AH72-AI72 -> 136980.58 | AK72: =U72-AH72 -> 0.0028312 | AL72: =AI72/U72 -> 0.020003351 | AO72: =VLOOKUP(M72,'Customer data'!F:P,11,0) -> HDFCN52025082227307462
A73: Selected | B73: 6779 | C73: 100222397 | D73: BARNET INDIA PRIVATE LIMITED | E73: 2025 | F73: 7 | G73: 45877 | H73: 1800011663 | I73: DR | J73: 45877 | K73: 45877 | L73: NA | M73: 256779416093 | N73: 212100 | O73: Trade Debtors (Ctrl) | Q73: 01 | R73: USD | S73: 4902.53 | T73: INR | U73: 421765.24 | V73: O0 | W73: 6779224500 | Y73: NA | Z73: 1 | AA73: Unit Storage - 1-31 July 25 | AE73: 45877 | AF73: 45946 | AG73: 1400001455 | AH73: {=VLOOKUP(M73,'Customer data Vlookup'!$B$3:$H$127,{2,3},0)} -> 421765.24 | AI73: 42177 | AJ73: =AH73-AI73 -> 379588.24 | AK73: =U73-AH73 -> -0.0042036 | AL73: =AI73/U73 -> 0.10000113 | AO73: =VLOOKUP(M73,'Customer data'!F:P,11,0) -> HDFCN52025100205721894
A74: Selected | B74: 6779 | C74: 100222397 | D74: BARNET INDIA PRIVATE LIMITED | E74: 2025 | F74: 7 | G74: 45877 | H74: 1800011821 | I74: DR | J74: 45877 | K74: 45877 | L74: NA | M74: 256779416130 | N74: 212100 | O74: Trade Debtors (Ctrl) | Q74: 01 | R74: USD | S74: 323.47 | T74: INR | U74: 27828.16 | V74: O0 | W74: 6779224500 | Y74: NA | Z74: 1 | AA74: Empty Lolo Chgs - 01 - 31 JUL 25 | AE74: 45877 | AF74: 45979 | AG74: 1400001956 | AH74: {=VLOOKUP(M74,'Customer data Vlookup'!$B$3:$H$127,{2,3},0)} -> 27828.163 | AI74: 557 | AJ74: =AH74-AI74 -> 27271.163 | AK74: =U74-AH74 -> -0.0029164 | AL74: =AI74/U74 -> 0.020015696 | AO74: =VLOOKUP(M74,'Customer data'!F:P,11,0) -> HDFCN52025082733046460
A75: Selected | B75: 6779 | C75: 100222397 | D75: BARNET INDIA PRIVATE LIMITED | E75: 2025 | F75: 7 | G75: 45877 | H75: 1800011849 | I75: DR | J75: 45877 | K75: 45877 | L75: NA | M75: 256779416500 | N75: 212100 | O75: Trade Debtors (Ctrl) | Q75: 01 | R75: USD | S75: 947.07 | T75: INR | U75: 81476.55 | V75: O0 | W75: 6779224500 | Y75: NA | Z75: 1 | AA75: PORT SSR Chgs July 25 | AE75: 45877 | AF75: 45979 | AG75: 1400001956 | AH75: {=VLOOKUP(M75,'Customer data Vlookup'!$B$3:$H$127,{2,3},0)} -> 81476.546 | AI75: 1630 | AJ75: =AH75-AI75 -> 79846.546 | AK75: =U75-AH75 -> 0.0042516 | AL75: =AI75/U75 -> 0.020005756 | AO75: =VLOOKUP(M75,'Customer data'!F:P,11,0) -> HDFCN52025082733046460
A76: Selected | B76: 6779 | C76: 100222397 | D76: BARNET INDIA PRIVATE LIMITED | E76: 2025 | F76: 7 | G76: 45877 | H76: 1800011813 | I76: DR | J76: 45877 | K76: 45877 | L76: NA | M76: 256779416122 | N76: 212100 | O76: Trade Debtors (Ctrl) | Q76: 01 | R76: USD | S76: 700 | T76: INR | U76: 60221.08 | V76: O0 | W76: 6779224500 | Y76: NA | Z76: 1 | AA76: Transportation In Chgs - 16 - 31 Jul 25 | AE76: 45877 | AH76: {=VLOOKUP(M76,'Customer data Vlookup'!$B$3:$H$127,{2,3},0)} -> 60221.084 | AI76: 1204 | AJ76: =AH76-AI76 -> 59017.084 | AK76: =U76-AH76 -> -0.004 | AL76: =AI76/U76 -> 0.019992999 | AO76: =VLOOKUP(M76,'Customer data'!F:P,11,0) -> Not Approved
A77: Selected | B77: 6779 | C77: 100222397 | D77: BARNET INDIA PRIVATE LIMITED | E77: 2025 | F77: 7 | G77: 45862 | H77: 1600001818 | I77: DG | J77: 45862 | K77: 45862 | L77: NA | M77: 256779421438 | N77: 212100 | O77: Trade Debtors (Ctrl) | Q77: 11 | R77: USD | S77: -356.83 | T77: INR | U77: -30681.56 | V77: O0 | W77: 6779224500 | Y77: NA | Z77: 1 | AA77: Credit Note raised against 256779413869 | AE77: 45862 | AF77: 45918 | AG77: 1400001206 | AH77: {=VLOOKUP(M77,'Customer data Vlookup'!$B$3:$H$127,{2,3},0)} -> #N/A | AO77: =VLOOKUP(M77,'Customer data'!F:P,11,0) -> #N/A
A78: Selected | B78: 6779 | C78: 100222397 | D78: BARNET INDIA PRIVATE LIMITED | E78: 2025 | F78: 7 | G78: 45862 | H78: 1800011189 | I78: DR | J78: 45862 | K78: 45862 | L78: NA | M78: 256779415941 | N78: 212100 | O78: Trade Debtors (Ctrl) | Q78: 01 | R78: USD | S78: 356.83 | T78: INR | U78: 30687.62 | V78: O0 | W78: 6779224500 | Y78: NA | Z78: 1 | AA78: Transportation In Chgs - 01 -15 MAY 25 | AE78: 45862 | AF78: 46030 | AG78: 1400002389 | AH78: {=VLOOKUP(M78,'Customer data Vlookup'!$B$3:$H$127,{2,3},0)} -> 30687.619 | AI78: 614 | AJ78: =AH78-AI78 -> 30073.619 | AK78: =U78-AH78 -> 0.0009239 | AL78: =AI78/U78 -> 0.020008068 | AO78: HDFCH00646925098 &HDFCH00676798572
A79: Selected | B79: 6779 | C79: 100222397 | D79: BARNET INDIA PRIVATE LIMITED | E79: 2025 | F79: 7 | G79: 45856 | H79: 1400000293 | I79: DY | J79: 45856 | K79: 45856 | L79: NA | M79: KNOCK OFF ENTRY | N79: 212100 | O79: Trade Debtors (Ctrl) | Q79: 15 | R79: USD | S79: 0 | T79: INR | U79: 0 | W79: 6779224500 | Z79: 1 | AE79: 45856 | AF79: 45856 | AG79: 1400000293 | AH79: {=VLOOKUP(M79,'Customer data Vlookup'!$B$3:$H$127,{2,3},0)} -> #N/A | AO79: =VLOOKUP(M79,'Customer data'!F:P,11,0) -> #N/A
A80: Selected | B80: 6779 | C80: 100222397 | D80: BARNET INDIA PRIVATE LIMITED | E80: 2025 | F80: 7 | G80: 45856 | H80: 1400000294 | I80: DY | J80: 45856 | K80: 45856 | L80: NA | M80: KNOCK OFF ENTRY | N80: 212100 | O80: Trade Debtors (Ctrl) | Q80: 15 | R80: USD | S80: 0 | T80: INR | U80: 0 | W80: 6779224500 | Z80: 1 | AE80: 45856 | AF80: 45856 | AG80: 1400000294 | AH80: {=VLOOKUP(M80,'Customer data Vlookup'!$B$3:$H$127,{2,3},0)} -> #N/A | AO80: =VLOOKUP(M80,'Customer data'!F:P,11,0) -> #N/A
A81: Selected | B81: 6779 | C81: 100222397 | D81: BARNET INDIA PRIVATE LIMITED | E81: 2025 | F81: 7 | G81: 45856 | H81: 1400000295 | I81: DY | J81: 45856 | K81: 45856 | L81: NA | M81: KNOCK OFF ENTRY | N81: 212100 | O81: Trade Debtors (Ctrl) | Q81: 15 | R81: USD | S81: 0 | T81: INR | U81: 0 | W81: 6779224500 | Z81: 1 | AE81: 45856 | AF81: 45856 | AG81: 1400000295 | AH81: {=VLOOKUP(M81,'Customer data Vlookup'!$B$3:$H$127,{2,3},0)} -> #N/A | AO81: =VLOOKUP(M81,'Customer data'!F:P,11,0) -> #N/A
A82: Selected | B82: 6779 | C82: 100222397 | D82: BARNET INDIA PRIVATE LIMITED | E82: 2025 | F82: 7 | G82: 45856 | H82: 1400000296 | I82: DY | J82: 45856 | K82: 45856 | L82: NA | M82: KNOCK OFF ENTRY | N82: 212100 | O82: Trade Debtors (Ctrl) | Q82: 15 | R82: USD | S82: 0 | T82: INR | U82: 0 | W82: 6779224500 | Z82: 1 | AE82: 45856 | AF82: 45856 | AG82: 1400000296 | AH82: {=VLOOKUP(M82,'Customer data Vlookup'!$B$3:$H$127,{2,3},0)} -> #N/A | AO82: =VLOOKUP(M82,'Customer data'!F:P,11,0) -> #N/A
A83: Selected | B83: 6779 | C83: 100222397 | D83: BARNET INDIA PRIVATE LIMITED | E83: 2025 | F83: 7 | G83: 45856 | H83: 1400000297 | I83: DY | J83: 45856 | K83: 45856 | L83: NA | M83: KNOCK OFF ENTRY | N83: 212100 | O83: Trade Debtors (Ctrl) | Q83: 15 | R83: USD | S83: 0 | T83: INR | U83: 0 | W83: 6779224500 | Z83: 1 | AE83: 45856 | AF83: 45856 | AG83: 1400000297 | AH83: {=VLOOKUP(M83,'Customer data Vlookup'!$B$3:$H$127,{2,3},0)} -> #N/A | AO83: =VLOOKUP(M83,'Customer data'!F:P,11,0) -> #N/A
A84: Selected | B84: 6779 | C84: 100222397 | D84: BARNET INDIA PRIVATE LIMITED | E84: 2025 | F84: 7 | G84: 45856 | H84: 1400000298 | I84: DY | J84: 45856 | K84: 45856 | L84: NA | M84: KNOCK OFF ENTRY | N84: 212100 | O84: Trade Debtors (Ctrl) | Q84: 15 | R84: USD | S84: 0 | T84: INR | U84: 0 | W84: 6779224500 | Z84: 1 | AE84: 45856 | AF84: 45856 | AG84: 1400000298 | AH84: {=VLOOKUP(M84,'Customer data Vlookup'!$B$3:$H$127,{2,3},0)} -> #N/A | AO84: =VLOOKUP(M84,'Customer data'!F:P,11,0) -> #N/A
A85: Selected | B85: 6779 | C85: 100222397 | D85: BARNET INDIA PRIVATE LIMITED | E85: 2025 | F85: 7 | G85: 45856 | H85: 1400000299 | I85: DY | J85: 45856 | K85: 45856 | L85: NA | M85: KNOCK OFF ENTRY | N85: 212100 | O85: Trade Debtors (Ctrl) | Q85: 15 | R85: USD | S85: 0 | T85: INR | U85: 0 | W85: 6779224500 | Z85: 1 | AE85: 45856 | AF85: 45856 | AG85: 1400000299 | AH85: {=VLOOKUP(M85,'Customer data Vlookup'!$B$3:$H$127,{2,3},0)} -> #N/A | AO85: =VLOOKUP(M85,'Customer data'!F:P,11,0) -> #N/A
A86: Selected | B86: 6779 | C86: 100222397 | D86: BARNET INDIA PRIVATE LIMITED | E86: 2025 | F86: 7 | G86: 45856 | H86: 1400000300 | I86: DY | J86: 45856 | K86: 45856 | L86: NA | M86: KNOCK OFF ENTRY | N86: 212100 | O86: Trade Debtors (Ctrl) | Q86: 15 | R86: USD | S86: 0 | T86: INR | U86: 0 | W86: 6779224500 | Z86: 1 | AE86: 45856 | AF86: 45856 | AG86: 1400000300 | AH86: {=VLOOKUP(M86,'Customer data Vlookup'!$B$3:$H$127,{2,3},0)} -> #N/A | AO86: =VLOOKUP(M86,'Customer data'!F:P,11,0) -> #N/A
A87: Selected | B87: 6779 | C87: 100222397 | D87: BARNET INDIA PRIVATE LIMITED | E87: 2025 | F87: 7 | G87: 45856 | H87: 1400000301 | I87: DY | J87: 45856 | K87: 45856 | L87: NA | M87: KNOCK OFF ENTRY | N87: 212100 | O87: Trade Debtors (Ctrl) | Q87: 15 | R87: USD | S87: 0 | T87: INR | U87: 0 | W87: 6779224500 | Z87: 1 | AE87: 45856 | AF87: 45856 | AG87: 1400000301 | AH87: {=VLOOKUP(M87,'Customer data Vlookup'!$B$3:$H$127,{2,3},0)} -> #N/A | AO87: =VLOOKUP(M87,'Customer data'!F:P,11,0) -> #N/A
A88: Selected | B88: 6779 | C88: 100222397 | D88: BARNET INDIA PRIVATE LIMITED | E88: 2025 | F88: 7 | G88: 45856 | H88: 1400000302 | I88: DY | J88: 45856 | K88: 45856 | L88: NA | M88: KNOCK OFF ENTRY | N88: 212100 | O88: Trade Debtors (Ctrl) | Q88: 15 | R88: USD | S88: 0 | T88: INR | U88: 0 | W88: 6779224500 | Z88: 1 | AE88: 45856 | AF88: 45856 | AG88: 1400000302 | AH88: {=VLOOKUP(M88,'Customer data Vlookup'!$B$3:$H$127,{2,3},0)} -> #N/A | AO88: =VLOOKUP(M88,'Customer data'!F:P,11,0) -> #N/A
A89: Selected | B89: 6779 | C89: 100222397 | D89: BARNET INDIA PRIVATE LIMITED | E89: 2025 | F89: 7 | G89: 45856 | H89: 1400000303 | I89: DY | J89: 45856 | K89: 45856 | L89: NA | M89: KNOCK OFF ENTRY | N89: 212100 | O89: Trade Debtors (Ctrl) | Q89: 15 | R89: USD | S89: 0 | T89: INR | U89: 0 | W89: 6779224500 | Z89: 1 | AE89: 45856 | AF89: 45856 | AG89: 1400000303 | AH89: {=VLOOKUP(M89,'Customer data Vlookup'!$B$3:$H$127,{2,3},0)} -> #N/A | AO89: =VLOOKUP(M89,'Customer data'!F:P,11,0) -> #N/A
A90: Selected | B90: 6779 | C90: 100222397 | D90: BARNET INDIA PRIVATE LIMITED | E90: 2025 | F90: 7 | G90: 45856 | H90: 1400000304 | I90: DY | J90: 45856 | K90: 45856 | L90: NA | M90: KNOCK OFF ENTRY | N90: 212100 | O90: Trade Debtors (Ctrl) | Q90: 15 | R90: USD | S90: 0 | T90: INR | U90: 0 | W90: 6779224500 | Z90: 1 | AE90: 45856 | AF90: 45856 | AG90: 1400000304 | AH90: {=VLOOKUP(M90,'Customer data Vlookup'!$B$3:$H$127,{2,3},0)} -> #N/A | AO90: =VLOOKUP(M90,'Customer data'!F:P,11,0) -> #N/A
... A128: Not Selected | B128: 6779 | C128: 100222397 | D128: BARNET INDIA PRIVATE LIMITED | E128: 2025 | F128: 3 | G128: 45856 | H128: 1400000342 | I128: DY | J128: 45856 | K128: 45856 | L128: NA | M128: KNOCK OFF ENTRY | N128: 212100 | O128: Trade Debtors (Ctrl) | Q128: 15 | R128: USD | S128: 0 | T128: INR | U128: 0 | W128: 6779224500 | Z128: 1 | AE128: 45856 | AF128: 45856 | AG128: 1400000342 | AH128: {=VLOOKUP(M128,'Customer data Vlookup'!$B$3:$H$127,{2,3},0)} -> #N/A | AO128: =VLOOKUP(M128,'Customer data'!F:P,11,0) -> #N/A
A129: Not Selected | B129: 6779 | C129: 100222397 | D129: BARNET INDIA PRIVATE LIMITED | E129: 2025 | F129: 3 | G129: 45856 | H129: 1800010755 | I129: DR | J129: 45856 | K129: 45859 | L129: NA | M129: 256779415417 | N129: 212100 | O129: Trade Debtors (Ctrl) | Q129: 01 | R129: USD | S129: 449.63 | T129: INR | U129: 38668.48 | V129: O0 | W129: 6779224500 | Y129: NA | Z129: 1 | AA129: PORT SSR Chgs Apr to June 25 | AE129: 45856 | AF129: 45946 | AG129: 1400001452 | AH129: {=VLOOKUP(M129,'Customer data Vlookup'!$B$3:$H$127,{2,3},0)} -> 38668.481 | AI129: 773 | AJ129: =AH129-AI129 -> 37895.481 | AK129: =U129-AH129 -> -0.0012521 | AL129: =AI129/U129 -> 0.019990442 | AO129: =VLOOKUP(M129,'Customer data'!F:P,11,0) -> HDFCN52025082227307462
A130: Not Selected | B130: 6779 | C130: 100222397 | D130: BARNET INDIA PRIVATE LIMITED | E130: 2025 | F130: 3 | G130: 45842 | H130: 1800010507 | I130: DR | J130: 45842 | K130: 45847 | L130: NA | M130: 256779415267 | N130: 212100 | O130: Trade Debtors (Ctrl) | Q130: 01 | R130: USD | S130: 84.17 | T130: INR | U130: 7238.68 | V130: O0 | W130: 6779224500 | Z130: 1 | AA130: Weighment- 16-30 June 25 | AE130: 45842 | AF130: 45946 | AG130: 1400001452 | AH130: {=VLOOKUP(M130,'Customer data Vlookup'!$B$3:$H$127,{2,3},0)} -> 7238.6764 | AI130: 145 | AJ130: =AH130-AI130 -> 7093.6764 | AK130: =U130-AH130 -> 0.0036061 | AL130: =AI130/U130 -> 0.020031276 | AO130: =VLOOKUP(M130,'Customer data'!F:P,11,0) -> HDFCN52025082227307462
A131: Not Selected | B131: 6779 | C131: 100222397 | D131: BARNET INDIA PRIVATE LIMITED | E131: 2025 | F131: 3 | G131: 45842 | H131: 1800010021 | I131: DR | J131: 45842 | K131: 45845 | L131: NA | M131: 256779414785 | N131: 212100 | O131: Trade Debtors (Ctrl) | Q131: 01 | R131: USD | S131: 3262.49 | T131: INR | U131: 280576.33 | V131: O0 | W131: 6779224500 | Y131: NA | Z131: 1 | AA131: Transportation In Chgs - 01 - 15 JUN 25 | AE131: 45842 | AH131: {=VLOOKUP(M131,'Customer data Vlookup'!$B$3:$H$127,{2,3},0)} -> 280576.33 | AI131: 5613 | AJ131: =AH131-AI131 -> 274963.33 | AK131: =U131-AH131 -> 0.0041317 | AL131: =AI131/U131 -> 0.020005251 | AO131: =VLOOKUP(M131,'Customer data'!F:P,11,0) -> Not Approved
A132: Not Selected | B132: 6779 | C132: 100222397 | D132: BARNET INDIA PRIVATE LIMITED | E132: 2025 | F132: 3 | G132: 45842 | H132: 1800010045 | I132: DR | J132: 45842 | K132: 45845 | L132: NA | M132: 256779414809 | N132: 212100 | O132: Trade Debtors (Ctrl) | Q132: 01 | R132: USD | S132: 1980.46 | T132: INR | U132: 170320.89 | V132: O0 | W132: 6779224500 | Y132: NA | Z132: 1 | AA132: Outbound chgs - 01 - 15 Jun 25 | AE132: 45842 | AH132: {=VLOOKUP(M132,'Customer data Vlookup'!$B$3:$H$127,{2,3},0)} -> 170320.89 | AI132: 3406 | AJ132: =AH132-AI132 -> 166914.89 | AK132: =U132-AH132 -> 0.0030918 | AL132: =AI132/U132 -> 0.019997547 | AO132: =VLOOKUP(M132,'Customer data'!F:P,11,0) -> Not Approved
A133: Not Selected | B133: 6779 | C133: 100222397 | D133: BARNET INDIA PRIVATE LIMITED | E133: 2025 | F133: 3 | G133: 45842 | H133: 1800010091 | I133: DR | J133: 45842 | K133: 45847 | L133: NA | M133: 256779414851 | N133: 212100 | O133: Trade Debtors (Ctrl) | Q133: 01 | R133: USD | S133: 139.58 | T133: INR | U133: 12003.97 | V133: O0 | W133: 6779224500 | Y133: NA | Z133: 1 | AA133: Detention Chgs - 16 - 30 JUN 25 | AE133: 45842 | AH133: {=VLOOKUP(M133,'Customer data Vlookup'!$B$3:$H$127,{2,3},0)} -> 12003.974 | AI133: 240 | AJ133: =AH133-AI133 -> 11763.974 | AK133: =U133-AH133 -> -0.0035186 | AL133: =AI133/U133 -> 0.019993386 | AO133: =VLOOKUP(M133,'Customer data'!F:P,11,0) -> Not Approved
A134: Selected | B134: 6779 | C134: 100222397 | D134: BARNET INDIA PRIVATE LIMITED | E134: 2025 | F134: 4 | G134: 45842 | H134: 1800010106 | I134: DR | J134: 45842 | K134: 45847 | L134: NA | M134: 256779414866 | N134: 212100 | O134: Trade Debtors (Ctrl) | Q134: 01 | R134: USD | S134: 3691.03 | T134: INR | U134: 317431.05 | V134: O0 | W134: 6779224500 | Y134: NA | Z134: 1 | AA134: Transportation In Chgs - 16 - 30 JUN 25 | AE134: 45842 | AH134: {=VLOOKUP(M134,'Customer data Vlookup'!$B$3:$H$127,{2,3},0)} -> 317431.05 | AI134: 6349 | AJ134: =AH134-AI134 -> 311082.05 | AK134: =U134-AH134 -> -0.0029901 | AL134: =AI134/U134 -> 0.020001194 | AO134: =VLOOKUP(M134,'Customer data'!F:P,11,0) -> Not Approved
A135: Selected | B135: 6779 | C135: 100222397 | D135: BARNET INDIA PRIVATE LIMITED | E135: 2025 | F135: 3 | G135: 45842 | H135: 1800010238 | I135: DR | J135: 45842 | K135: 45847 | L135: NA | M135: 256779414998 | N135: 212100 | O135: Trade Debtors (Ctrl) | Q135: 01 | R135: USD | S135: 1752.33 | T135: INR | U135: 150701.55 | V135: O0 | W135: 6779224500 | Y135: NA | Z135: 1 | AA135: Outbound chgs - 16 - 30 Jun 25 | AE135: 45842 | AH135: {=VLOOKUP(M135,'Customer data Vlookup'!$B$3:$H$127,{2,3},0)} -> 150701.55 | AI135: 3013 | AJ135: =AH135-AI135 -> 147688.55 | AK135: =U135-AH135 -> -0.0040611 | AL135: =AI135/U135 -> 0.019993159 | AO135: =VLOOKUP(M135,'Customer data'!F:P,11,0) -> Not Approved
A136: Selected | B136: 6779 | C136: 100222397 | D136: BARNET INDIA PRIVATE LIMITED | E136: 2025 | F136: 3 | G136: 45842 | H136: 1800010271 | I136: DR | J136: 45842 | K136: 45847 | L136: NA | M136: 256779415031 | N136: 212100 | O136: Trade Debtors (Ctrl) | Q136: 01 | R136: USD | S136: 14.09 | T136: INR | U136: 1211.75 | V136: O0 | W136: 6779224500 | Y136: NA | Z136: 1 | AA136: PORT SSR Chgs June 25 | AE136: 45842 | AH136: {=VLOOKUP(M136,'Customer data Vlookup'!$B$3:$H$127,{2,3},0)} -> 1211.7494 | AI136: 24 | AJ136: =AH136-AI136 -> 1187.7494 | AK136: =U136-AH136 -> 0.0005597 | AL136: =AI136/U136 -> 0.019806066 | AO136: =VLOOKUP(M136,'Customer data'!F:P,11,0) -> Not Approved
A137: Selected | B137: 6779 | C137: 100222397 | D137: BARNET INDIA PRIVATE LIMITED | E137: 2025 | F137: 7 | G137: 45842 | H137: 1800010445 | I137: DR | J137: 45842 | K137: 45847 | L137: NA | M137: 256779415205 | N137: 212100 | O137: Trade Debtors (Ctrl) | Q137: 01 | R137: USD | S137: 5120.2 | T137: INR | U137: 440340.63 | V137: O0 | W137: 6779224500 | Y137: NA | Z137: 1 | AA137: Unit Storage - 1-30 June 25 | AE137: 45842 | AG137: 1400002197 | AH137: {=VLOOKUP(M137,'Customer data Vlookup'!$B$3:$H$127,{2,3},0)} -> 440340.63 | AI137: 44034 | AJ137: =AH137-AI137 -> 396306.63 | AK137: =U137-AH137 -> -0.00053399999 | AL137: =AI137/U137 -> 0.099999857 | AO137: =VLOOKUP(M137,'Customer data'!F:P,11,0) -> HDFCH00646925098
...

Sheet Customer data
A1: Sr.No. | B1: Particulars | C1: Bill Amt in USD | D1: Month- service Received | E1: Date | F1: INV NO | G1: EX.RATE | H1: INVOICE AMT | I1: TDS | J1: TDS AMOUNT | K1: AMT PAYABLE | L1: AMOUNT DEDUCTED | M1: AMOUNT PAID | O1: Date | P1: UTR NO/REMARK | Q1: MONTH-INV Received &BOOKED | R1: REMARK
A2: 1 | B2: Storage Charges 1st Aug to 31st Aug 2024 | C2: 960.64 | D2: August, 2024 | E2: 45698 | F2: 6779IV124000167 | G2: 87.5858 | H2: 84138.423 | I2: 0.1 | J2: =ROUND(H2*I2,0) -> 8414 | K2: =H2-J2 -> 75724.423 | M2: =K2 -> 75724.423 | N2: =SUM(L2:M2) -> 75724.423 | O2: 45861 | P2: HDFCN52025072369906032 | Q2: 45717
A3: 2 | B3: LCL Charges | C3: 132 | D3: August, 2024 | E3: 45698 | F3: 6779IV124000168 | G3: 87.5858 | H3: 11561.326 | I3: 0.02 | J3: =ROUND(H3*I3,0) -> 231 | K3: =H3-J3 -> 11330.326 | M3: 11330.33 | N3: =SUM(L3:M3) -> 11330.33 | O3: 45740 | P3: HDFCN52025032433793860 | Q3: 45717
A4: 3 | B4: Inbound Handling Charges | C4: 472.38 | D4: August, 2024 | E4: 45698 | F4: 6779IV124000169 | G4: 87.5858 | H4: 41373.78 | I4: 0.02 | J4: =ROUND(H4*I4,0) -> 827 | K4: =H4-J4 -> 40546.78 | N4: =SUM(L4:M4) -> 0 | P4: Not Approved | Q4: 45717
A5: 4 | B5: Lolo Charges | C5: 432 | D5: August, 2024 | E5: 45698 | F5: 6779IV124000170 | G5: 87.5858 | H5: 37837.066 | I5: 0.02 | J5: =ROUND(H5*I5,0) -> 757 | K5: =H5-J5 -> 37080.066 | N5: =SUM(L5:M5) -> 0 | P5: Not Approved | Q5: 45717
A6: 5 | B6: Outbound Handling Charges | C6: 472.38 | D6: August, 2024 | E6: 45698 | F6: 6779IV124000171 | G6: 87.5858 | H6: 41373.78 | I6: 0.02 | J6: =ROUND(H6*I6,0) -> 827 | K6: =H6-J6 -> 40546.78 | N6: =SUM(L6:M6) -> 0 | P6: Not Approved | Q6: 45717
A7: 6 | B7: VAS Activity Charges | C7: 125.59113 | D7: August, 2024 | E7: 45698 | F7: 6779IV124000172 | G7: 87.5858 | H7: 11000 | I7: 0.02 | J7: =ROUND(H7*I7,0) -> 220 | K7: =H7-J7 -> 10780 | M7: =K7 -> 10780 | N7: =SUM(L7:M7) -> 10780 | O7: 45822 | P7: HDFCN52025061495304800 | Q7: 45717
A8: 7 | B8: Storage Charges 1st Sep to 30th Sep 2024 | C8: 1495.68 | D8: September, 2024 | E8: 45698 | F8: 6779IV124000173 | G8: 87.5858 | H8: 131000.33 | I8: 0.1 | J8: =ROUND(H8*I8,0) -> 13100 | K8: =H8-J8 -> 117900.33 | M8: =K8 -> 117900.33 | N8: =SUM(L8:M8) -> 117900.33 | O8: 45861 | P8: HDFCN52025072369906032 | Q8: 45717
A9: 8 | B9: LCL Charges | C9: 211.2 | D9: September, 2024 | E9: 45698 | F9: 6779IV124000174 | G9: 87.5858 | H9: 18498.121 | I9: 0.02 | J9: =ROUND(H9*I9,0) -> 370 | K9: =H9-J9 -> 18128.121 | M9: 18128.12 | N9: =SUM(L9:M9) -> 18128.12 | O9: 45740 | P9: HDFCN52025032433793867 | Q9: 45717
A10: 9 | B10: Inbound Handling Charges | C10: 755.808 | D10: September, 2024 | E10: 45698 | F10: 6779IV124000175 | G10: 87.5858 | H10: 66198.048 | I10: 0.02 | J10: =ROUND(H10*I10,0) -> 1324 | K10: =H10-J10 -> 64874.048 | N10: =SUM(L10:M10) -> 0 | P10: Not Approved | Q10: 45717
A11: 10 | B11: Lolo Charges | C11: 475.2 | D11: September, 2024 | E11: 45698 | F11: 6779IV124000176 | G11: 87.5858 | H11: 41620.772 | I11: 0.02 | J11: =ROUND(H11*I11,0) -> 832 | K11: =H11-J11 -> 40788.772 | N11: =SUM(L11:M11) -> 0 | P11: Not Approved | Q11: 45717
A12: 11 | B12: Outbound Handling Charges | C12: 283.428 | D12: September, 2024 | E12: 45698 | F12: 6779IV124000177 | G12: 87.5858 | H12: 24824.268 | I12: 0.02 | J12: =ROUND(H12*I12,0) -> 496 | K12: =H12-J12 -> 24328.268 | N12: =SUM(L12:M12) -> 0 | P12: Not Approved | Q12: 45717
A13: 12 | B13: CY Movement Charges | C13: 81 | D13: September, 2024 | E13: 45698 | F13: 6779IV124000178 | G13: 87.5858 | H13: 7094.4498 | I13: 0.02 | J13: =ROUND(H13*I13,0) -> 142 | K13: =H13-J13 -> 6952.4498 | N13: =SUM(L13:M13) -> 0 | P13: Not Approved | Q13: 45717
A14: 13 | B14: VAS Activity Charges | C14: 150.70936 | D14: September, 2024 | E14: 45698 | F14: 6779IV124000179 | G14: 87.5858 | H14: 13200 | I14: 0.02 | J14: =ROUND(H14*I14,0) -> 264 | K14: =H14-J14 -> 12936 | L14: 6468 | M14: 6468 | N14: =SUM(L14:M14) -> 12936 | O14: 45822 | P14: HDFCN52025061495304800 | Q14: 45717 | R14: CREDIT NOTE AWAITED
A15: 14 | B15: Storage Charges 1st Oct to 31st Oct 2024 | C15: 2991.36 | D15: October, 2024 | E15: 45698 | F15: 6779IV124000180 | G15: 87.5858 | H15: 262000.66 | I15: 0.1 | J15: =ROUND(H15*I15,0) -> 26200 | K15: =H15-J15 -> 235800.66 | M15: =K15 -> 235800.66 | N15: =SUM(L15:M15) -> 235800.66 | O15: 45861 | P15: HDFCN52025072369906032 | Q15: 45717
A16: 15 | B16: LCL Charges | C16: 211.2 | D16: October, 2024 | E16: 45698 | F16: 6779IV124000181 | G16: 87.5858 | H16: 18498.121 | I16: 0.02 | J16: =ROUND(H16*I16,0) -> 370 | K16: =H16-J16 -> 18128.121 | M16: 18128.12 | N16: =SUM(L16:M16) -> 18128.12 | O16: 45740 | P16: HDFCN52025032433793886 | Q16: 45717
A17: 16 | B17: Inbound Handling Charges | C17: 755.808 | D17: October, 2024 | E17: 45698 | F17: 6779IV124000182 | G17: 87.5858 | H17: 66198.048 | I17: 0.02 | J17: =ROUND(H17*I17,0) -> 1324 | K17: =H17-J17 -> 64874.048 | N17: =SUM(L17:M17) -> 0 | P17: Not Approved | Q17: 45717
A18: 17 | B18: Lolo Charges | C18: 691.2 | D18: October, 2024 | E18: 45698 | F18: 6779IV124000183 | G18: 87.5858 | H18: 60539.305 | I18: 0.02 | J18: =ROUND(H18*I18,0) -> 1211 | K18: =H18-J18 -> 59328.305 | N18: =SUM(L18:M18) -> 0 | P18: Not Approved | Q18: 45717
A19: 18 | B19: CY Movement Charges | C19: 216 | D19: October, 2024 | E19: 45698 | F19: 6779IV124000184 | G19: 87.5858 | H19: 18918.533 | I19: 0.02 | J19: =ROUND(H19*I19,0) -> 378 | K19: =H19-J19 -> 18540.533 | N19: =SUM(L19:M19) -> 0 | P19: Not Approved | Q19: 45717
A20: 19 | B20: Outbound Handling Charges | C20: 755.808 | D20: October, 2024 | E20: 45698 | F20: 6779IV124000185 | G20: 87.5858 | H20: 66198.048 | I20: 0.02 | J20: =ROUND(H20*I20,0) -> 1324 | K20: =H20-J20 -> 64874.048 | N20: =SUM(L20:M20) -> 0 | P20: Not Approved | Q20: 45717
A21: 20 | B21: Storage Charges 1st Nov to 30th Nov 2024 | C21: 887.68 | D21: November, 2024 | E21: 45698 | F21: 6779IV124000186 | G21: 87.5858 | H21: 77748.163 | I21: 0.1 | J21: =ROUND(H21*I21,0) -> 7775 | K21: =H21-J21 -> 69973.163 | M21: 69973.16 | N21: =SUM(L21:M21) -> 69973.16 | O21: 45728 | P21: HDFCN52025031215974606 | Q21: 45717
A22: 21 | B22: CY Movement Charges | C22: 162 | D22: November, 2024 | E22: 45698 | F22: 6779IV124000187 | G22: 87.5858 | H22: 14188.9 | I22: 0.02 | J22: =ROUND(H22*I22,0) -> 284 | K22: =H22-J22 -> 13904.9 | N22: =SUM(L22:M22) -> 0 | P22: Not Approved | Q22: 45717
A23: 22 | B23: Outbound Handling Charges | C23: 566.856 | D23: November, 2024 | E23: 45698 | F23: 6779IV124000188 | G23: 87.5858 | H23: 49648.536 | I23: 0.02 | J23: =ROUND(H23*I23,0) -> 993 | K23: =H23-J23 -> 48655.536 | N23: =SUM(L23:M23) -> 0 | P23: Not Approved | Q23: 45717
A24: 23 | B24: Lolo Charges | C24: 259.2 | D24: November, 2024 | E24: 45698 | F24: 6779IV124000189 | G24: 87.5858 | H24: 22702.239 | I24: 0.02 | J24: =ROUND(H24*I24,0) -> 454 | K24: =H24-J24 -> 22248.239 | N24: =SUM(L24:M24) -> 0 | P24: Not Approved | Q24: 45717
A25: 24 | B25: Storage Charges 1st Dec to 31st Dec 2024 | C25: 364.8 | D25: December, 2024 | E25: 45698 | F25: 6779IV124000190 | G25: 87.5858 | H25: 31951.3 | I25: 0.1 | J25: =ROUND(H25*I25,0) -> 3195 | K25: =H25-J25 -> 28756.3 | M25: 28756.3 | N25: =SUM(L25:M25) -> 28756.3 | O25: 45728 | P25: HDFCN52025031215976413 | Q25: 45717
A26: 25 | B26: LCL Charges | C26: 52.8 | D26: December, 2024 | E26: 45698 | F26: 6779IV124000191 | G26: 87.5858 | H26: 4624.5302 | I26: 0.02 | J26: =ROUND(H26*I26,0) -> 92 | K26: =H26-J26 -> 4532.5302 | M26: 4532.53 | N26: =SUM(L26:M26) -> 4532.53 | O26: 45740 | P26: HDFCN52025032433793875 | Q26: 45717
A27: 26 | B27: Inbound Handling Charges | C27: 188.952 | D27: December, 2024 | E27: 45698 | F27: 6779IV124000192 | G27: 87.5858 | H27: 16549.512 | I27: 0.02 | J27: =ROUND(H27*I27,0) -> 331 | K27: =H27-J27 -> 16218.512 | N27: =SUM(L27:M27) -> 0 | P27: Not Approved | Q27: 45717
A28: 27 | B28: Lolo Charges | C28: 172.8 | D28: December, 2024 | E28: 45698 | F28: 6779IV124000193 | G28: 87.5858 | H28: 15134.826 | I28: 0.02 | J28: =ROUND(H28*I28,0) -> 303 | K28: =H28-J28 -> 14831.826 | N28: =SUM(L28:M28) -> 0 | P28: Not Approved | Q28: 45717
A29: 28 | B29: CY Movement Charges | C29: 54 | D29: December, 2024 | E29: 45698 | F29: 6779IV124000194 | G29: 87.5858 | H29: 4729.6332 | I29: 0.02 | J29: =ROUND(H29*I29,0) -> 95 | K29: =H29-J29 -> 4634.6332 | N29: =SUM(L29:M29) -> 0 | P29: Not Approved | Q29: 45717
A30: 29 | B30: Outbound Handling Charges | C30: 188.952 | D30: December, 2024 | E30: 45698 | F30: 6779IV124000195 | G30: 87.5858 | H30: 16549.512 | I30: 0.02 | J30: =ROUND(H30*I30,0) -> 331 | K30: =H30-J30 -> 16218.512 | N30: =SUM(L30:M30) -> 0 | P30: Not Approved | Q30: 45717
A31: 30 | B31: Storage Charges 1st Jan to 31st Jan 2025 | C31: 1231.96 | D31: January, 2025 | E31: 45698 | F31: 6779IV124000196 | G31: 87.5858 | H31: 107902.2 | I31: 0.1 | J31: =ROUND(H31*I31,0) -> 10790 | K31: =H31-J31 -> 97112.202 | M31: 97112.2 | N31: =SUM(L31:M31) -> 97112.2 | O31: 45728 | P31: HDFCN52025031215974609 | Q31: 45717
A32: 31 | B32: Transportation Inbound | C32: 180 | D32: January, 2025 | E32: 45698 | F32: 6779IV124000197 | G32: 87.5858 | H32: 15765.444 | I32: 0.02 | J32: =ROUND(H32*I32,0) -> 315 | K32: =H32-J32 -> 15450.444 | M32: 15450.44 | N32: =SUM(L32:M32) -> 15450.44 | O32: 45740 | P32: HDFCN52025032433791996 | Q32: 45717
A33: 32 | B33: CY Destuff Charges | C33: 27 | D33: January, 2025 | E33: 45698 | F33: 6779IV124000198 | G33: 87.5858 | H33: 2364.8166 | I33: 0.02 | J33: =ROUND(H33*I33,0) -> 47 | K33: =H33-J33 -> 2317.8166 | N33: =SUM(L33:M33) -> 0 | P33: Not Approved | Q33: 45717
A34: 33 | B34: Empty Movement Charges | C34: 180 | D34: January, 2025 | E34: 45698 | F34: 6779IV124000199 | G34: 87.5858 | H34: 15765.444 | I34: 0.02 | J34: =ROUND(H34*I34,0) -> 315 | K34: =H34-J34 -> 15450.444 | N34: =SUM(L34:M34) -> 0 | P34: Not Approved | Q34: 45717
A35: 34 | B35: LCL Charges | C35: 52.8 | D35: January, 2025 | E35: 45698 | F35: 6779IV124000200 | G35: 87.5858 | H35: 4624.5302 | I35: 0.02 | J35: =ROUND(H35*I35,0) -> 92 | K35: =H35-J35 -> 4532.5302 | M35: 4532.53 | N35: =SUM(L35:M35) -> 4532.53 | O35: 45740 | P35: HDFCN52025032433791993 | Q35: 45717
A36: 35 | B36: Inbound Handling Charges | C36: 252.932 | D36: January, 2025 | E36: 45698 | F36: 6779IV124000201 | G36: 87.5858 | H36: 22153.252 | I36: 0.02 | J36: =ROUND(H36*I36,0) -> 443 | K36: =H36-J36 -> 21710.252 | N36: =SUM(L36:M36) -> 0 | P36: Not Approved | Q36: 45717
A37: 36 | B37: Loose Unloading Charges | C37: 31.99 | D37: January, 2025 | E37: 45698 | F37: 6779IV124000202 | G37: 87.5858 | H37: 2801.8697 | I37: 0.02 | J37: =ROUND(H37*I37,0) -> 56 | K37: =H37-J37 -> 2745.8697 | N37: =SUM(L37:M37) -> 0 | P37: Not Approved | Q37: 45717
A38: 37 | B38: Lolo Charges | C38: 129.6 | D38: January, 2025 | E38: 45698 | F38: 6779IV124000203 | G38: 87.5858 | H38: 11351.12 | I38: 0.02 | J38: =ROUND(H38*I38,0) -> 227 | K38: =H38-J38 -> 11124.12 | N38: =SUM(L38:M38) -> 0 | P38: Not Approved | Q38: 45717
A39: 38 | B39: Outbound Handling Charges | C39: 63.98 | D39: January, 2025 | E39: 45698 | F39: 6779IV124000204 | G39: 87.5858 | H39: 5603.7395 | I39: 0.02 | J39: =ROUND(H39*I39,0) -> 112 | K39: =H39-J39 -> 5491.7395 | N39: =SUM(L39:M39) -> 0 | P39: Not Approved | Q39: 45717
A40: 39 | B40: Loose Loading Charges | C40: 31.99 | D40: January, 2025 | E40: 45698 | F40: 6779IV124000205 | G40: 87.5858 | H40: 2801.8697 | I40: 0.02 | J40: =ROUND(H40*I40,0) -> 56 | K40: =H40-J40 -> 2745.8697 | N40: =SUM(L40:M40) -> 0 | P40: Not Approved | Q40: 45717
A41: 40 | B41: Storage Charges Feb, 25 | C41: 364.8 | D41: February, 2025 | E41: 45751 | F41: 256779410800 | G41: 86.92182 | H41: 31709.08 | I41: 0.1 | J41: =ROUND(H41*I41,0) -> 3171 | K41: =H41-J41 -> 28538.08 | M41: 28538.08 | N41: =SUM(L41:M41) -> 28538.08 | O41: 45791 | P41: HDFCN52025051435275414 | Q41: 45717
A42: 41 | B42: VAS Activity - Feb 25, Ex Rate.87.40 | C42: 25.17 | D42: February, 2025 | E42: 45763 | F42: 256779412037 | G42: 86.92182 | H42: 2187.8222 | I42: 0.02 | J42: =ROUND(H42*I42,0) -> 44 | K42: =H42-J42 -> 2143.8222 | N42: =SUM(L42:M42) -> 0 | P42: Not Approved | Q42: 45717
A43: 42 | B43: Inbound Handling charges for Mar 2025 | C43: 283.43 | D43: March, 2025 | E43: 45750 | F43: 256779410039 | G43: 86.92182 | H43: 24636.251 | I43: 0.02 | J43: =ROUND(H43*I43,0) -> 493 | K43: =H43-J43 -> 24143.251 | M43: =K43 -> 24143.251 | N43: =SUM(L43:M43) -> 24143.251 | O43: 45791 | P43: HDFCN52025051435275414 | Q43: 45717
A44: 43 | B44: LCL charges for Mar 2025 | C44: 79.2 | D44: March, 2025 | E44: 45750 | F44: 256779410040 | G44: 86.92182 | H44: 6884.2081 | I44: 0.02 | J44: =ROUND(H44*I44,0) -> 138 | K44: =H44-J44 -> 6746.2081 | M44: =K44 -> 6746.2081 | N44: =SUM(L44:M44) -> 6746.2081 | O44: 45791 | P44: HDFCN52025051435275414 | Q44: 45717
A45: 44 | B45: LOLO charges for Mar 2025 | C45: 129.6 | D45: March, 2025 | E45: 45750 | F45: 256779410041 | G45: 86.92182 | H45: 11265.068 | I45: 0.02 | J45: =ROUND(H45*I45,0) -> 225 | K45: =H45-J45 -> 11040.068 | M45: =K45 -> 11040.068 | N45: =SUM(L45:M45) -> 11040.068 | O45: 45791 | P45: HDFCN52025051435275414 | Q45: 45717
A46: 45 | B46: Empty Cont. Outbound charges for Mar 2025 | C46: 270 | D46: March, 2025 | E46: 45750 | F46: 256779410042 | G46: 86.92182 | H46: 23468.891 | I46: 0.02 | J46: =ROUND(H46*I46,0) -> 469 | K46: =H46-J46 -> 22999.891 | N46: =SUM(L46:M46) -> 0 | P46: Not Approved | Q46: 45717
A47: 46 | B47: Cy-WH Destuff charges for Mar 2025 | C47: 283.43 | D47: March, 2025 | E47: 45750 | F47: 256779410102 | G47: 86.92182 | H47: 24636.251 | I47: 0.02 | J47: =ROUND(H47*I47,0) -> 493 | K47: =H47-J47 -> 24143.251 | M47: =K47 -> 24143.251 | N47: =SUM(L47:M47) -> 24143.251 | O47: 45791 | P47: HDFCN52025051435275414 | Q47: 45717
A48: 47 | B48: Inbound Handling charges for Mar 2025 Exch. Rate 8 | C48: 81 | D48: March, 2025 | E48: 45750 | F48: 256779410103 | G48: 86.92182 | H48: 7040.6674 | I48: 0.02 | J48: =ROUND(H48*I48,0) -> 141 | K48: =H48-J48 -> 6899.6674 | N48: =SUM(L48:M48) -> 0 | P48: Not Approved | Q48: 45717
A49: 48 | B49: Gate in charges for Mar 2025 Exch. Rate 87.01 | C49: 129.6 | D49: March, 2025 | E49: 45750 | F49: 256779410104 | G49: 86.92182 | H49: 11265.068 | I49: 0.02 | J49: =ROUND(H49*I49,0) -> 225 | K49: =H49-J49 -> 11040.068 | M49: =K49 -> 11040.068 | N49: =SUM(L49:M49) -> 11040.068 | O49: 45791 | P49: HDFCN52025051435275414 | Q49: 45717
A50: 49 | B50: VAS Activity -1 -15 Mar 25, Ex Rate. 87.01 | C50: 75.85 | D50: March, 2025 | E50: 45750 | F50: 256779410183 | G50: 86.92182 | H50: 6593.02 | I50: 0.02 | J50: =ROUND(H50*I50,0) -> 132 | K50: =H50-J50 -> 6461.02 | M50: =K50 -> 6461.02 | N50: =SUM(L50:M50) -> 6461.02 | O50: 45791 | P50: HDFCN52025051435275414 | Q50: 45717
A51: 50 | B51: Storage Charges Mar, 25 | C51: 583.68 | D51: March, 2025 | E51: 45763 | F51: 256779412122 | G51: 86.92182 | H51: 50734.528 | I51: 0.1 | J51: =ROUND(H51*I51,0) -> 5073 | K51: =H51-J51 -> 45661.528 | M51: =K51 -> 45661.528 | N51: =SUM(L51:M51) -> 45661.528 | O51: 45861 | P51: HDFCN52025072369906032 | Q51: 45717
A52: 51 | B52: Outbound Handling Charges Aug 2024 | C52: 188.95 | D52: August, 2024 | E52: 45763 | F52: 256779411261 | G52: 86.92182 | H52: 16423.878 | I52: 0.02 | J52: =ROUND(H52*I52,0) -> 328 | K52: =H52-J52 -> 16095.878 | N52: =SUM(L52:M52) -> 0 | P52: Not Approved | Q52: 45717
A53: 52 | B53: Lolo Charges Aug 2024 | C53: 86.4 | D53: August, 2024 | E53: 45763 | F53: 256779411261 | G53: 86.92182 | H53: 7510.0452 | I53: 0.02 | J53: =ROUND(H53*I53,0) -> 150 | K53: =H53-J53 -> 7360.0452 | N53: =SUM(L53:M53) -> 0 | P53: Not Approved | Q53: 45717
A54: 53 | B54: Outbound Handling Charges Aug 2024 | C54: 94.48 | D54: August, 2024 | E54: 45763 | F54: 256779411258 | G54: 86.92182 | H54: 8212.3736 | I54: 0.02 | J54: =ROUND(H54*I54,0) -> 164 | K54: =H54-J54 -> 8048.3736 | N54: =SUM(L54:M54) -> 0 | P54: Not Approved | Q54: 45717
A55: 54 | B55: Lolo Charges Aug 2024 | C55: 43.2 | D55: August, 2024 | E55: 45763 | F55: 256779411258 | G55: 86.92182 | H55: 3755.0226 | I55: 0.02 | J55: =ROUND(H55*I55,0) -> 75 | K55: =H55-J55 -> 3680.0226 | N55: =SUM(L55:M55) -> 0 | P55: Not Approved | Q55: 45717
A56: 55 | B56: Outbound Handling Charges Aug 2024 | C56: 94.48 | D56: August, 2024 | E56: 45763 | F56: 256779411259 | G56: 86.92182 | H56: 8212.3736 | I56: 0.02 | J56: =ROUND(H56*I56,0) -> 164 | K56: =H56-J56 -> 8048.3736 | N56: =SUM(L56:M56) -> 0 | P56: Not Approved | Q56: 45717
A57: 56 | B57: Lolo Charges Aug 2024 | C57: 43.2 | D57: August, 2024 | E57: 45763 | F57: 256779411259 | G57: 86.92182 | H57: 3755.0226 | I57: 0.02 | J57: =ROUND(H57*I57,0) -> 75 | K57: =H57-J57 -> 3680.0226 | N57: =SUM(L57:M57) -> 0 | P57: Not Approved | Q57: 45717
A58: 57 | B58: Outbound Handling Charges Aug 2024 | C58: 94.48 | D58: August, 2024 | E58: 45763 | F58: 256779411260 | G58: 86.92182 | H58: 8212.3736 | I58: 0.02 | J58: =ROUND(H58*I58,0) -> 164 | K58: =H58-J58 -> 8048.3736 | N58: =SUM(L58:M58) -> 0 | P58: Not Approved | Q58: 45717
A59: 58 | B59: Lolo Charges Aug 2024 | C59: 43.2 | D59: August, 2024 | E59: 45763 | F59: 256779411260 | G59: 86.92182 | H59: 3755.0226 | I59: 0.02 | J59: =ROUND(H59*I59,0) -> 75 | K59: =H59-J59 -> 3680.0226 | N59: =SUM(L59:M59) -> 0 | P59: Not Approved | Q59: 45717
A60: 59 | B60: LCL Charges August 2024 | C60: 26.4 | D60: August, 2024 | E60: 45762 | F60: 256779411010 | G60: 86.92182 | H60: 2294.736 | I60: 0.02 | J60: =ROUND(H60*I60,0) -> 46 | K60: =H60-J60 -> 2248.736 | N60: =SUM(L60:M60) -> 0 | P60: Not Approved | Q60: 45717
A61: 60 | B61: Inbound Handling for August 24 | C61: 94.48 | D61: August, 2024 | E61: 45762 | F61: 256779411010 | G61: 86.92182 | H61: 8212.3736 | I61: 0.02 | J61: =ROUND(H61*I61,0) -> 164 | K61: =H61-J61 -> 8048.3736 | N61: =SUM(L61:M61) -> 0 | P61: Not Approved | Q61: 45717
A62: 61 | B62: Lolo Charges for Aug 2024 | C62: 43.2 | D62: August, 2024 | E62: 45762 | F62: 256779411010 | G62: 86.92182 | H62: 3755.0226 | I62: 0.02 | J62: =ROUND(H62*I62,0) -> 75 | K62: =H62-J62 -> 3680.0226 | N62: =SUM(L62:M62) -> 0 | P62: Not Approved | Q62: 45717
A63: 62 | B63: LCL Charges August 2024 | C63: 26.4 | D63: August, 2024 | E63: 45762 | F63: 256779411007 | G63: 86.92182 | H63: 2294.736 | I63: 0.02 | J63: =ROUND(H63*I63,0) -> 46 | K63: =H63-J63 -> 2248.736 | N63: =SUM(L63:M63) -> 0 | P63: Not Approved | Q63: 45717
... A85: 84 | B85: LOLO chgs - 01 - 15 Apr 25 | C85: 43.2 | D85: April, 2025 | E85: 45770 | F85: 256779412903 | G85: 86.972692 | H85: 3757.2203 | I85: 0.02 | J85: =ROUND(H85*I85,0) -> 75 | K85: =H85-J85 -> 3682.2203 | N85: =SUM(L85:M85) -> 0 | P85: Not Approved | Q85: 45748
A86: 85 | B86: VAS - 16-30 April 25, Ex.Rate-85.05 | C86: 51.73 | D86: April, 2025 | E86: 45787 | F86: 256779413234 | G86: 85.9837 | H86: 4447.9368 | I86: 0.02 | J86: =ROUND(H86*I86,0) -> 89 | K86: =H86-J86 -> 4358.9368 | M86: =K86 -> 4358.9368 | N86: =SUM(L86:M86) -> 4358.9368 | O86: 45821 | P86: HDFCN52025061495304800 | Q86: 45778
A87: 86 | B87: VAS 1-15 April-25,Ex.Rate-85.69 | C87: 25.67 | D87: April, 2025 | E87: 45771 | F87: 256779412766 | G87: 86.92182 | H87: 2231.2831 | I87: 0.02 | J87: =ROUND(H87*I87,0) -> 45 | K87: =H87-J87 -> 2186.2831 | M87: =K87 -> 2186.2831 | N87: =SUM(L87:M87) -> 2186.2831 | O87: 45813 | P87: HDFCN52025060575568983 | Q87: 45778
A88: 87 | B88: Weighment-16-30 April25, Ex.Rate-85.05 | C88: 42.33 | D88: April, 2025 | E88: 45787 | F88: 256779413248 | G88: 85.9837 | H88: 3639.69 | I88: 0.02 | J88: =ROUND(H88*I88,0) -> 73 | K88: =H88-J88 -> 3566.69 | M88: =K88 -> 3566.69 | N88: =SUM(L88:M88) -> 3566.69 | O88: 45813 | P88: HDFCN52025060575568983 | Q88: 45778
A89: 88 | B89: Outbound Handling charges for Feb 2025 | C89: 94.48 | D89: February, 2025 | E89: 45736 | F89: 246779413959 | G89: 86.69126 | H89: 8190.5902 | I89: 0.02 | J89: =ROUND(H89*I89,0) -> 164 | K89: =H89-J89 -> 8026.5902 | M89: =K89 -> 8026.5902 | N89: =SUM(L89:M89) -> 8026.5902 | O89: 45813 | P89: HDFCN52025060575568983 | Q89: 45778
A90: 89 | B90: CY-Movement Charges for Feb 2025 | C90: 27 | D90: February, 2025 | E90: 45736 | F90: 246779413959 | G90: 86.69126 | H90: 2340.664 | I90: 0.02 | J90: =ROUND(H90*I90,0) -> 47 | K90: =H90-J90 -> 2293.664 | M90: =K90 -> 2293.664 | N90: =SUM(L90:M90) -> 2293.664 | O90: 45813 | P90: HDFCN52025060575568983 | Q90: 45778
A91: 90 | B91: LOLO Charges for Feb 2025 | C91: 43.2 | D91: February, 2025 | E91: 45736 | F91: 246779413959 | G91: 86.69126 | H91: 3745.0624 | I91: 0.02 | J91: =ROUND(H91*I91,0) -> 75 | K91: =H91-J91 -> 3670.0624 | M91: =K91 -> 3670.0624 | N91: =SUM(L91:M91) -> 3670.0624 | O91: 45813 | P91: HDFCN52025060575568983 | Q91: 45778
A92: 91 | B92: Outbound Handling charges for Feb 2025 | C92: 94.48 | D92: February, 2025 | E92: 45736 | F92: 246779413960 | G92: 86.69126 | H92: 8190.5902 | I92: 0.02 | J92: =ROUND(H92*I92,0) -> 164 | K92: =H92-J92 -> 8026.5902 | M92: =K92 -> 8026.5902 | N92: =SUM(L92:M92) -> 8026.5902 | O92: 45813 | P92: HDFCN52025060575568983 | Q92: 45778
A93: 92 | B93: CY-Movement Charges for Feb 2025 | C93: 27 | D93: February, 2025 | E93: 45736 | F93: 246779413960 | G93: 86.69126 | H93: 2340.664 | I93: 0.02 | J93: =ROUND(H93*I93,0) -> 47 | K93: =H93-J93 -> 2293.664 | M93: =K93 -> 2293.664 | N93: =SUM(L93:M93) -> 2293.664 | O93: 45813 | P93: HDFCN52025060575568983 | Q93: 45778
A94: 93 | B94: LOLO Charges for Feb 2025 | C94: 43.2 | D94: February, 2025 | E94: 45736 | F94: 246779413960 | G94: 86.69126 | H94: 3745.0624 | I94: 0.02 | J94: =ROUND(H94*I94,0) -> 75 | K94: =H94-J94 -> 3670.0624 | M94: =K94 -> 3670.0624 | N94: =SUM(L94:M94) -> 3670.0624 | O94: 45813 | P94: HDFCN52025060575568983 | Q94: 45778
A95: 94 | B95: Outbound Handling charges for Feb 2025 | C95: 188.95 | D95: February, 2025 | E95: 45736 | F95: 246779413963 | G95: 86.69126 | H95: 16380.314 | I95: 0.02 | J95: =ROUND(H95*I95,0) -> 328 | K95: =H95-J95 -> 16052.314 | M95: =K95 -> 16052.314 | N95: =SUM(L95:M95) -> 16052.314 | O95: 45813 | P95: HDFCN52025060575568983 | Q95: 45778
A96: 95 | B96: CY-Movement Charges for Feb 2025 | C96: 54 | D96: February, 2025 | E96: 45736 | F96: 246779413963 | G96: 86.69126 | H96: 4681.328 | I96: 0.02 | J96: =ROUND(H96*I96,0) -> 94 | K96: =H96-J96 -> 4587.328 | M96: =K96 -> 4587.328 | N96: =SUM(L96:M96) -> 4587.328 | O96: 45813 | P96: HDFCN52025060575568983 | Q96: 45778
A97: 96 | B97: LOLO Charges for Feb 2025 | C97: 86.4 | D97: February, 2025 | E97: 45736 | F97: 246779413963 | G97: 86.69126 | H97: 7490.1249 | I97: 0.02 | J97: =ROUND(H97*I97,0) -> 150 | K97: =H97-J97 -> 7340.1249 | M97: =K97 -> 7340.1249 | N97: =SUM(L97:M97) -> 7340.1249 | O97: 45813 | P97: HDFCN52025060575568983 | Q97: 45778
... A113: 112 | B113: LOLO chgs - 16-31 MAY 25 ( BOE2030748 ) | C113: 259.2 | D113: May,2025 | E113: 45812 | F113: 256779414296 | G113: 85.49078 | H113: 22159.21 | I113: 0.02 | J113: =ROUND(H113*I113,0) -> 443 | K113: =H113-J113 -> 21716.21 | M113: =K113 -> 21716.21 | N113: =SUM(L113:M113) -> 21716.21 | O113: 45833 | P113: HDFCN52025062512710909 | Q113: 45809
A114: 113 | B114: Transportation In Chgs - 01 - 15 JUN 25 | C114: 1440 | D114: June,2025 | E114: 45842 | F114: 256779414785 | G114: 86.00067 | H114: 123840.96 | I114: 0.02 | J114: =ROUND(H114*I114,0) -> 2477 | K114: =H114-J114 -> 121363.96 | N114: =SUM(L114:M114) -> 0 | P114: Not Approved | Q114: 45839
A115: 114 | B115: CY - WH destuff Chgs - 01 - 15 JUN 25 | C115: 216 | D115: June,2025 | E115: 45842 | F115: 256779414785 | G115: 86.00067 | H115: 18576.145 | I115: 0.02 | J115: =ROUND(H115*I115,0) -> 372 | K115: =H115-J115 -> 18204.145 | N115: =SUM(L115:M115) -> 0 | P115: Not Approved | Q115: 45839
A116: 115 | B116: Inbound chgs - 01 - 15 JUN 25 | C116: 1088.09 | D116: June,2025 | E116: 45842 | F116: 256779414785 | G116: 86.00067 | H116: 93576.469 | I116: 0.02 | J116: =ROUND(H116*I116,0) -> 1872 | K116: =H116-J116 -> 91704.469 | N116: =SUM(L116:M116) -> 0 | P116: Not Approved | Q116: 45839
A117: 116 | B117: LOLO chgs - 01 - 15 JUN 25 | C117: 518.4 | D117: June,2025 | E117: 45842 | F117: 256779414785 | G117: 86.00067 | H117: 44582.747 | I117: 0.02 | J117: =ROUND(H117*I117,0) -> 892 | K117: =H117-J117 -> 43690.747 | N117: =SUM(L117:M117) -> 0 | P117: Not Approved | Q117: 45839
A118: 117 | B118: Outbound chgs - 01 - 15 Jun 25 | C118: 1350.66 | D118: June,2025 | E118: 45842 | F118: 256779414809 | G118: 86.00067 | H118: 116157.66 | I118: 0.02 | J118: =ROUND(H118*I118,0) -> 2323 | K118: =H118-J118 -> 113834.66 | N118: =SUM(L118:M118) -> 0 | P118: Not Approved | Q118: 45839
A119: 118 | B119: Loose chgs - 01 - 15 Jun 25 | C119: 25 | D119: June,2025 | E119: 45842 | F119: 256779414809 | G119: 86.00067 | H119: 2150.0167 | I119: 0.02 | J119: =ROUND(H119*I119,0) -> 43 | K119: =H119-J119 -> 2107.0167 | N119: =SUM(L119:M119) -> 0 | P119: Not Approved | Q119: 45839
A120: 119 | B120: LOLO chgs - 01 - 15 Jun 25 | C120: 604.8 | D120: June,2025 | E120: 45842 | F120: 256779414809 | G120: 86.00067 | H120: 52013.205 | I120: 0.02 | J120: =ROUND(H120*I120,0) -> 1040 | K120: =H120-J120 -> 50973.205 | N120: =SUM(L120:M120) -> 0 | P120: Not Approved | Q120: 45839
A121: 120 | B121: Transportation Out chgs - 16 - 30 Jun 25 WH 09 | C121: 720 | D121: June,2025 | E121: 45842 | F121: 256779414998 | G121: 86.00067 | H121: 61920.482 | I121: 0.02 | J121: =ROUND(H121*I121,0) -> 1238 | K121: =H121-J121 -> 60682.482 | N121: =SUM(L121:M121) -> 0 | P121: Not Approved | Q121: 45839
A122: 121 | B122: CY - CY chgs - 16 - 30 Jun 25 WH 09 | C122: 108 | D122: June,2025 | E122: 45842 | F122: 256779414998 | G122: 86.00067 | H122: 9288.0724 | I122: 0.02 | J122: =ROUND(H122*I122,0) -> 186 | K122: =H122-J122 -> 9102.0724 | N122: =SUM(L122:M122) -> 0 | P122: Not Approved | Q122: 45839
A123: 122 | B123: Empty Cont In chgs - 16 - 30 Jun 25 WH 09 | C123: 360 | D123: June,2025 | E123: 45842 | F123: 256779414998 | G123: 86.00067 | H123: 30960.241 | I123: 0.02 | J123: =ROUND(H123*I123,0) -> 619 | K123: =H123-J123 -> 30341.241 | N123: =SUM(L123:M123) -> 0 | P123: Not Approved | Q123: 45839
A124: 123 | B124: Outbound chgs - 16 - 30 Jun 25 WH 09 | C124: 377.9 | D124: June,2025 | E124: 45842 | F124: 256779414998 | G124: 86.00067 | H124: 32499.653 | I124: 0.02 | J124: =ROUND(H124*I124,0) -> 650 | K124: =H124-J124 -> 31849.653 | N124: =SUM(L124:M124) -> 0 | P124: Not Approved | Q124: 45839
A125: 124 | B125: Loose chgs - 16 - 30 Jun 25 WH 09 | C125: 13.63 | D125: June,2025 | E125: 45842 | F125: 256779414998 | G125: 86.00067 | H125: 1172.1891 | I125: 0.02 | J125: =ROUND(H125*I125,0) -> 23 | K125: =H125-J125 -> 1149.1891 | N125: =SUM(L125:M125) -> 0 | P125: Not Approved | Q125: 45839
... A133: 132 | B133: Empty Cont Out chgs - 16 - 30 JUN 25 WH09 | C133: 630 | D133: June,2025 | E133: 45842 | F133: 256779414866 | G133: 86.00067 | H133: 54180.422 | I133: 0.02 | J133: =ROUND(H133*I133,0) -> 1084 | K133: =H133-J133 -> 53096.422 | N133: =SUM(L133:M133) -> 0 | P133: Not Approved | Q133: 45839
A134: 133 | B134: Unit Storage - 1-30 June 25 | C134: 5120.2 | D134: June,2025 | E134: 45842 | F134: 256779415205 | G134: 86.00067 | H134: 440340.63 | I134: 0.1 | J134: =ROUND(H134*I134,0) -> 44034 | K134: =H134-J134 -> 396306.63 | L134: 144316 | M134: =K134-L134 -> 251990.63 | N134: =SUM(L134:M134) -> 396306.63 | O134: 45993 | P134: HDFCH00646925098 | Q134: 45839 | R134: CREDIT NOTE AWAITED
A135: 134 | B135: PORT SSR Chgs Apr to June 25 | C135: 449.63 | D135: June,2025 | E135: 45856 | F135: 256779415417 | G135: 86.00067 | H135: 38668.481 | I135: 0.02 | J135: =ROUND(H135*I135,0) -> 773 | K135: =H135-J135 -> 37895.481 | M135: =K135 -> 37895.481 | N135: =SUM(L135:M135) -> 37895.481 | O135: 45891 | P135: HDFCN52025082227307462 | Q135: 45839
A136: 135 | B136: Weighment- 16-30 June 25 | C136: 84.17 | D136: June,2025 | E136: 45842 | F136: 256779415267 | G136: 86.00067 | H136: 7238.6764 | I136: 0.02 | J136: =ROUND(H136*I136,0) -> 145 | K136: =H136-J136 -> 7093.6764 | M136: =K136 -> 7093.6764 | N136: =SUM(L136:M136) -> 7093.6764 | O136: 45891 | P136: HDFCN52025082227307462 | Q136: 45839
A137: 136 | B137: Transportation In Chgs - 01 -15 MAY 25 | C137: 180 | D137: May,2025 | E137: 45863 | F137: 256779415941 | G137: 86.00067 | H137: 15480.121 | I137: 0.02 | J137: =ROUND(H137*I137,0) -> 310 | K137: =H137-J137 -> 15170.121 | M137: =K137-L137 -> 15170.121 | N137: =SUM(L137:M137) -> 15170.121 | O137: 45993 | P137: HDFCH00646925098 | Q137: 45839
A138: 137 | B138: Inbound chgs - 01-15 MAY 25 | C138: 133.63 | D138: May,2025 | E138: 45863 | F138: 256779415941 | G138: 86.00067 | H138: 11492.27 | I138: 0.02 | J138: =ROUND(H138*I138,0) -> 230 | K138: =H138-J138 -> 11262.27 | M138: =K138-L138 -> 11262.27 | N138: =SUM(L138:M138) -> 11262.27 | O138: 46006 | P138: HDFCH00676798572 | Q138: 45839
A139: 138 | B139: LOLO chgs - 01-15 MAY 25 | C139: 43.2 | D139: May,2025 | E139: 45863 | F139: 256779415941 | G139: 86.00067 | H139: 3715.2289 | I139: 0.02 | J139: =ROUND(H139*I139,0) -> 74 | K139: =H139-J139 -> 3641.2289 | M139: =K139-L139 -> 3641.2289 | N139: =SUM(L139:M139) -> 3641.2289 | O139: 46006 | P139: HDFCH00676798572 | Q139: 45839
A140: 139 | B140: Unit Storage - 1-31 July 25 | C140: 4902.53 | D140: July,25 | E140: 45877 | F140: 256779416093 | G140: 86.03012 | H140: 421765.24 | I140: 0.1 | J140: =ROUND(H140*I140,0) -> 42177 | K140: =H140-J140 -> 379588.24 | L140: 246362.73 | M140: =K140-L140 -> 133225.51 | N140: =SUM(L140:M140) -> 379588.24 | O140: 45932 | P140: HDFCN52025100205721894 | Q140: 45870 | R140: CREDIT NOTE AWAITED
A141: 140 | B141: Transportation In Chgs - 16 - 31 Jul 25 | C141: 700 | D141: July,25 | E141: 45877 | F141: 256779416122 | G141: 86.03012 | H141: 60221.084 | I141: 0.02 | J141: =ROUND(H141*I141,0) -> 1204 | K141: =H141-J141 -> 59017.084 | N141: =SUM(L141:M141) -> 0 | P141: Not Approved | Q141: 45870
A142: 141 | B142: Empty Lolo Chgs - 01 - 31 JUL 25 | C142: 323.47 | D142: July,25 | E142: 45877 | F142: 256779416130 | G142: 86.03012 | H142: 27828.163 | I142: 0.02 | J142: =ROUND(H142*I142,0) -> 557 | K142: =H142-J142 -> 27271.163 | M142: =K142 -> 27271.163 | N142: =SUM(L142:M142) -> 27271.163 | O142: 45896 | P142: HDFCN52025082733046460 | Q142: 45870
A143: 142 | B143: Cy - WH destuff - 16 - 31 JUL 25 | C143: 189 | D143: July,25 | E143: 45877 | F143: 256779416154 | G143: 86.03012 | H143: 16259.693 | I143: 0.02 | J143: =ROUND(H143*I143,0) -> 325 | K143: =H143-J143 -> 15934.693 | M143: =K143 -> 15934.693 | N143: =SUM(L143:M143) -> 15934.693 | O143: 45891 | P143: HDFCN52025082227307462 | Q143: 45870
...

Sheet Paym Updated
A1: Document Number | B1: Document Type | C1: Document Date | D1: Document Header Text | E1: Company Code Currency Key | F1: Company Code Currency Value | G1: Text | H1: Clearing Documents | J1: Clearing Documents | K1: Document Header Text | L1: Sum of Company Code Currency Value
A2: 1400000007 | B2: DZ | C2: 45772 | D2: HDFCN52025031215974606 | E2: INR | F2: -77748.16 | G2: HDFCN52025031215974606 | H2: 1400000007 | J2: 1400000007 | K2: HDFCN52025031215974606 | L2: -77748.16
A3: 1400000008 | B3: DZ | C3: 45772 | D3: HDFCN52025031215976413 | E3: INR | F3: -31951.3 | G3: HDFCN52025031215976413 | H3: 1400000008 | J3: 1400000008 | K3: HDFCN52025031215976413 | L3: -31951.3
A4: 1400000009 | B4: DZ | C4: 45772 | D4: HDFCN52025031215974609 | E4: INR | F4: -107902.2 | G4: HDFCN52025031215974609 | H4: 1400000009 | J4: 1400000009 | K4: HDFCN52025031215974609 | L4: -107902.2
A5: 1400000010 | B5: DZ | C5: 45772 | D5: HDFCN52025032433793860 | E5: INR | F5: -11561.33 | G5: HDFCN52025032433793860 | H5: 1400000010 | J5: 1400000010 | K5: HDFCN52025032433793860 | L5: -11561.33
A6: 1400000011 | B6: DZ | C6: 45772 | D6: HDFCN52025032433793867 | E6: INR | F6: -18498.12 | G6: HDFCN52025032433793867 | H6: 1400000011 | J6: 1400000011 | K6: HDFCN52025032433793867 | L6: -18498.12
A7: 1400000012 | B7: DZ | C7: 45772 | D7: HDFCN52025032433793886 | E7: INR | F7: -18498.12 | G7: HDFCN52025032433793886 | H7: 1400000012 | J7: 1400000012 | K7: HDFCN52025032433793886 | L7: -18498.12
A8: 1400000013 | B8: DZ | C8: 45772 | D8: HDFCN52025032433793875 | E8: INR | F8: -4624.53 | G8: HDFCN52025032433793875 | H8: 1400000013 | J8: 1400000013 | K8: HDFCN52025032433793875 | L8: -4624.53
A9: 1400000014 | B9: DZ | C9: 45772 | D9: HDFCN52025032433791996 | E9: INR | F9: -15765.44 | G9: HDFCN52025032433791996 | H9: 1400000014 | J9: 1400000014 | K9: HDFCN52025032433791996 | L9: -15765.44
A10: 1400000015 | B10: DZ | C10: 45772 | D10: HDFCN52025032433791993 | E10: INR | F10: -4624.53 | G10: HDFCN52025032433791993 | H10: 1400000015 | J10: 1400000015 | K10: HDFCN52025032433791993 | L10: -4624.53
A11: 1400001449 | B11: DZ | C11: 45912 | D11: HDFCN52025090553870975 | E11: INR | F11: 124189.23 | H11: 1400001449 | J11: 1400001449 | K11: HDFCN52025090553870975 | L11: 0
A12: 1400001173 | B12: DZ | C12: 45912 | D12: HDFCN52025090553870975 | E12: INR | F12: -124189.23 | H12: 1400001449 | J12: 1400001450 | L12: 0
A13: 1400001450 | B13: DZ | C13: 45908 | E13: INR | F13: 495157.4 | H13: 1400001450 | J13: 1400001451 | K13: HDFCN52025051435275414 | L13: 0
A14: 1400001142 | B14: DZ | C14: 45908 | E14: INR | F14: -495157.4 | H14: 1400001450 | J14: 1400001452 | K14: HDFCN52025082227307462 | L14: -492209.06
A15: 1400000063 | B15: DZ | C15: 45832 | D15: HDFCN52025051435275414 | E15: INR | F15: -112111.95 | H15: 1400001451 | J15: 1400001453 | K15: HDFCN52025082227307462 | L15: -2932.62
A16: 1400001451 | B16: DZ | C16: 45832 | D16: HDFCN52025051435275414 | E16: INR | F16: 112111.95 | H16: 1400001451 | K16: HDFCH00465695692 | L16: -136843.96
A17: 1400001452 | B17: DZ | C17: 45946 | D17: HDFCN52025082227307462 | E17: INR | F17: -492209.06 | G17: HDFCN52025082227307462 | H17: 1400001452 | J17: 1400001454 | K17: HDFCN52025051435275414 | L17: -116988.95
A18: 1400001453 | B18: DZ | C18: 45946 | D18: HDFCH00465695692 | E18: INR | F18: 2932.62 | G18: HDFCH00465695692 | H18: 1400001453 | J18: 1400001455 | K18: HDFCN52025100205721894 | L18: -646935.77
A19: 1400001453 | B19: DZ | C19: 45946 | D19: HDFCH00465695692 | E19: INR | F19: -139776.58 | G19: HDFCH00465695692 | H19: 1400001453 | J19: 1400001456 | K19: HDFCN52025062512710909 | L19: -182952.83
A20: 1400001452 | B20: DZ | C20: 45946 | D20: HDFCN52025082227307462 | E20: INR | F20: -2932.62 | H20: 1400001453 | J20: 1400001458 | K20: CT68PKL3P93Q | L20: 0
A21: 1400001454 | B21: DZ | C21: 45946 | D21: HDFCN52025051435275414 | E21: INR | F21: -116988.95 | G21: HDFCN52025051435275414 | H21: 1400001454 | J21: 1400001468 | K21: HDFCN52025100205721894 | L21: 0
A22: 1400001455 | B22: DZ | C22: 45946 | D22: HDFCN52025100205721894 | E22: INR | F22: -646935.77 | G22: HDFCN52025100205721894 | H22: 1400001455 | J22: 1400001956 | K22: HDFCN52025082733046460 | L22: -109304.71
A23: 1400001456 | B23: DZ | C23: 45946 | D23: HDFCN52025062512710909 | E23: INR | F23: -182952.83 | G23: HDFCN52025062512710909 | H23: 1400001456 | J23: 1400001961 | K23: HDFCN52025060575568983 | L23: -167674.29
A24: 1400001458 | B24: DZ | C24: 45890 | D24: CT68PKL3P93Q | E24: INR | F24: 179293.83 | H24: 1400001458 | J24: 1400001971 | K24: HDFCN52025072369906032 | L24: -50734.53
A25: 1400000898 | B25: DZ | C25: 45890 | D25: CT68PKL3P93Q | E25: INR | F25: -179293.83 | H25: 1400001458 | J25: 1400001972 | K25: HDFCN52025072369906032 | L25: -477139.41
A26: 1400001468 | B26: DZ | C26: 45938 | D26: HDFCN52025100205721894 | E26: INR | F26: 339060.54 | H26: 1400001468 | J26: 1400001988 | K26: HDFCN52025082733046460 | L26: 0
A27: 1400001367 | B27: DZ | C27: 45938 | D27: HDFCN52025100205721894 | E27: INR | F27: -339060.54 | H27: 1400001468 | J27: 1400001989 | K27: D2WMGTC7VB6Y | L27: 0
A28: 1400001956 | B28: DZ | C28: 45979 | D28: HDFCN52025082733046460 | E28: INR | F28: -109304.71 | G28: HDFCN52025082733046460 | H28: 1400001956 | J28: 1400001993 | K28: HDFCN52025060575568983 | L28: 0
A29: 1400001961 | B29: DZ | C29: 45979 | D29: HDFCN52025060575568983 | E29: INR | F29: -8051.51 | G29: HDFCN52025060575568983 | H29: 1400001961 | J29: 1400002197 | K29: G15K40FCKGJH | L29: -97487.56
A30: 1400001961 | B30: DZ | C30: 45979 | D30: HDFCN52025060575568983 | E30: INR | F30: -159622.78 | G30: HDFCN52025060575568983 | H30: 1400001961 | J30: 1400002388 | K30: G15K40FCKGJH | L30: 0
A31: 1400001971 | B31: DZ | C31: 45979 | D31: HDFCN52025072369906032 | E31: INR | F31: -50734.53 | G31: HDFCN52025072369906032 | H31: 1400001971 | J31: 1400002389 | K31: G90RGJ9HVGZQ | L31: -16156.51
A32: 1400001972 | B32: DZ | C32: 45979 | D32: HDFCN52025072369906032 | E32: INR | F32: -477139.41 | G32: HDFCN52025072369906032 | H32: 1400001972 | K32: G15K40FCKGJH | L32: -14531.11
A33: 1400001988 | B33: DZ | C33: 45908 | D33: HDFCN52025082733046460 | E33: INR | F33: 107117.71 | H33: 1400001988 | K33: HDFCN52025100308494407 | L33: -324591.96
A34: 1400001145 | B34: DZ | C34: 45908 | D34: HDFCN52025082733046460 | E34: INR | F34: -107117.71 | H34: 1400001988 | K34: HDFCN52025061495304800 | L34: -226409
A35: 1400001989 | B35: DZ | C35: 45890 | D35: D2WMGTC7VB6Y | E35: INR | F35: 475086.94 | H35: 1400001989 | K35: HDFCN52025060575565670 | L35: -341000
A36: 1400000962 | B36: DZ | C36: 45890 | D36: D2WMGTC7VB6Y | E36: INR | F36: -475086.94 | H36: 1400001989 | K36: H3YKFZWVB0GN | L36: -30424.05
A37: 1400001993 | B37: DZ | C37: 45832 | D37: HDFCN52025060575568983 | E37: INR | F37: 159186.29 | H37: 1400001993 | K37: H2PMXC728CY0 | L37: -971.67
A38: 1400000115 | B38: DZ | C38: 45832 | D38: HDFCN52025060575568983 | E38: INR | F38: -159186.29 | H38: 1400001993 | K38: G15K40FCKGJH | L38: -296024
A39: 1400002197 | B39: DZ | C39: 46007 | D39: G15K40FCKGJH | E39: INR | F39: -66620.79 | G39: G15K40FCKGJH | H39: 1400002197
A40: 1400002197 | B40: DZ | C40: 46007 | D40: G15K40FCKGJH | E40: INR | F40: -30866.77 | G40: G15K40FCKGJH | H40: 1400002197
A41: 1400002388 | B41: DZ | C41: 46030 | D41: G15K40FCKGJH | E41: INR | F41: 14531.11 | H41: 1400002388
A42: 1400002198 | B42: DZ | C42: 46007 | D42: G15K40FCKGJH | E42: INR | F42: -14531.11 | H42: 1400002388
A43: 1400002389 | B43: DZ | C43: 46030 | D43: G90RGJ9HVGZQ | E43: INR | F43: 14903.5 | H43: 1400002389
A44: 1400002389 | B44: DZ | C44: 46030 | D44: G90RGJ9HVGZQ | E44: INR | F44: 14531.11 | H44: 1400002389
A45: 1400002389 | B45: DZ | C45: 46030 | D45: G90RGJ9HVGZQ | E45: INR | F45: -30687.62 | H45: 1400002389
A46: 1400002237 | B46: DZ | C46: 46011 | D46: G90RGJ9HVGZQ | E46: INR | F46: -14903.5 | H46: 1400002389
A47: 1400002388 | B47: DZ | C47: 46030 | D47: G15K40FCKGJH | E47: INR | F47: -14531.11 | H47: 1400002389
A48: 1400001329 | B48: DZ | C48: 45931 | D48: HDFCN52025061495304800 | E48: INR | F48: -226409
A49: 1400000113 | B49: DZ | C49: 45832 | D49: HDFCN52025060575565670 | E49: INR | F49: -341000
A50: 1400002197 | B50: DZ | C50: 46007 | D50: G15K40FCKGJH | E50: INR | F50: -296024
A51: 1400001627 | B51: DZ | C51: 45972 | D51: HDFCN52025100308494407 | E51: INR | F51: -324591.96
A52: 1400002720 | B52: DZ | C52: 46070 | D52: H3YKFZWVB0GN | E52: INR | F52: -30424.05
A53: 1400002721 | B53: DZ | C53: 46070 | D53: H2PMXC728CY0 | E53: INR | F53: -971.67

Sheet Payment Reco
B1: =SUBTOTAL(9,B4:B93) -> 3557557.5 | D1: =B1+G1 -> -464928.21 | G1: =SUBTOTAL(9,G4:G55) -> -4022485.7 | M1: =SUM(M4:M31) -> 3557557.1
A2: As per Customer | E2: As per Ascendus Ledger | J2: As per Ascendus Bank Details
A3: Date | B3: AMOUNT PAID | C3: UTR NO/REMARK | E3: Document Type | F3: Document Date | G3: Company Code Currency Value | H3: Text | J3: Payment Date | K3: Customer Name | L3: Currency | M3: Recd Amount | N3: Bank Reference
A4: 45728 | B4: 69973.16 | C4: HDFCN52025031215974606 | E4: DZ | F4: 45772 | G4: -77748.16 | H4: HDFCN52025031215974606 | J4: 45728 | K4: BARNET INDIA PRIVATE LIMITED | L4: INR | M4: 97112.2 | N4: HDFCN52025031215974609
A5: 45728 | B5: 28756.3 | C5: HDFCN52025031215976413 | E5: DZ | F5: 45772 | G5: -31951.3 | H5: HDFCN52025031215976413 | J5: 45728 | K5: BARNET INDIA PRIVATE LIMITED | L5: INR | M5: 28756.3 | N5: HDFCN52025031215976413
A6: 45728 | B6: 97112.2 | C6: HDFCN52025031215974609 | E6: DZ | F6: 45772 | G6: -107902.2 | H6: HDFCN52025031215974609 | J6: 45728 | K6: BARNET INDIA PRIVATE LIMITED | L6: INR | M6: 69973.16 | N6: HDFCN52025031215974606
A7: 45740 | B7: 11330.33 | C7: HDFCN52025032433793860 | E7: DZ | F7: 45772 | G7: -11561.33 | H7: HDFCN52025032433793860 | J7: 45740 | K7: BARNET INDIA PRIVATE LIMITED | L7: INR | M7: 18128.12 | N7: HDFCN52025032433793867
A8: 45740 | B8: 18128.12 | C8: HDFCN52025032433793867 | E8: DZ | F8: 45772 | G8: -18498.12 | H8: HDFCN52025032433793867 | J8: 45740 | K8: BARNET INDIA PRIVATE LIMITED | L8: INR | M8: 15450.44 | N8: HDFCN52025032433791996
A9: 45740 | B9: 18128.12 | C9: HDFCN52025032433793886 | E9: DZ | F9: 45772 | G9: -18498.12 | H9: HDFCN52025032433793886 | J9: 45740 | K9: BARNET INDIA PRIVATE LIMITED | L9: INR | M9: 11330.33 | N9: HDFCN52025032433793860
A10: 45740 | B10: 4532.53 | C10: HDFCN52025032433793875 | E10: DZ | F10: 45772 | G10: -4624.53 | H10: HDFCN52025032433793875 | J10: 45740 | K10: BARNET INDIA PRIVATE LIMITED | L10: INR | M10: 4532.53 | N10: HDFCN52025032433791993
A11: 45740 | B11: 15450.44 | C11: HDFCN52025032433791996 | E11: DZ | F11: 45772 | G11: -15765.44 | H11: HDFCN52025032433791996 | J11: 45740 | K11: BARNET INDIA PRIVATE LIMITED | L11: INR | M11: 18128.12 | N11: HDFCN52025032433793886
A12: 45740 | B12: 4532.53 | C12: HDFCN52025032433791993 | E12: DZ | F12: 45772 | G12: -4624.53 | H12: HDFCN52025032433791993 | J12: 45740 | K12: BARNET INDIA PRIVATE LIMITED | L12: INR | M12: 4532.53 | N12: HDFCN52025032433793875
A13: 45791 | B13: 28538.08 | C13: HDFCN52025051435275414 | E13: DZ | F13: 45832 | G13: -341000 | J13: 45813 | K13: BARNET INDIA PRIVATE LIMITED | L13: INR | M13: 341000 | N13: HDFCN52025060575565670
A14: 45791 | B14: 24143.251 | C14: HDFCN52025051435275414 | E14: DZ | F14: 45931 | G14: -226409 | J14: 45822 | K14: BARNET INDIA PRIVATE LIMITED | L14: INR | M14: 226409 | N14: HDFCN52025061495304800
A15: 45791 | B15: 6746.2081 | C15: HDFCN52025051435275414 | E15: DZ | F15: 45946 | G15: -492209.06 | H15: HDFCN52025082227307462 | J15: 45791 | K15: BARNET INDIA PRIVATE LIMITED | L15: INR | M15: 112111.95 | N15: HDFCN52025051435275414
A16: 45791 | B16: 11040.068 | C16: HDFCN52025051435275414 | E16: DZ | F16: 45946 | G16: -139776.58 | H16: HDFCH00465695692
A17: 45791 | B17: 24143.251 | C17: HDFCN52025051435275414 | E17: DZ | F17: 45946 | G17: -116988.95 | H17: HDFCN52025051435275414 | J17: 45813 | K17: BARNET INDIA PRIVATE LIMITED | L17: INR | M17: 159186.29 | N17: HDFCN52025060575568983
A18: 45791 | B18: 11040.068 | C18: HDFCN52025051435275414 | E18: DZ | F18: 45946 | G18: -646935.77 | H18: HDFCN52025100205721894 | J18: 45833 | K18: BARNET INDIA PRIVATE LIMITED | L18: INR | M18: 179293.83 | N18: HDFCN52025062512710909
A19: 45791 | B19: 6461.02 | C19: HDFCN52025051435275414 | E19: DZ | F19: 45946 | G19: -182952.83 | H19: HDFCN52025062512710909 | J19: 45861 | K19: BARNET INDIA PRIVATE LIMITED | L19: INR | M19: 475086.94 | N19: HDFCN52025072369906032
A20: 45813 | B20: 2186.2831 | C20: HDFCN52025060575568983 | E20: DZ | F20: 45972 | G20: -324591.96 | J20: 45933 | K20: BARNET INDIA PRIVATE LIMITED | L20: INR | M20: 324591.96 | N20: HDFCN52025100308494407
A21: 45813 | B21: 3566.69 | C21: HDFCN52025060575568983 | E21: DZ | F21: 45979 | G21: -8051.51 | H21: HDFCN52025060575568983
A22: 45813 | B22: 8026.5902 | C22: HDFCN52025060575568983 | E22: DZ | F22: 45979 | G22: -109304.71 | H22: HDFCN52025082733046460 | J22: 45891 | K22: BARNET INDIA PRIVATE LIMITED | L22: INR | M22: 495157.4 | N22: HDFCN52025082227307462
A23: 45813 | B23: 2293.664 | C23: HDFCN52025060575568983 | E23: DZ | F23: 45979 | G23: -159622.78 | H23: HDFCN52025060575568983 | J23: 45896 | K23: BARNET INDIA PRIVATE LIMITED | L23: INR | M23: 107117.71 | N23: HDFCN52025082733046460
A24: 45813 | B24: 3670.0624 | C24: HDFCN52025060575568983 | E24: DZ | F24: 45979 | G24: -50734.53 | H24: HDFCN52025072369906032 | J24: 45905 | K24: BARNET INDIA PRIVATE LIMITED | L24: INR | M24: 124189.23 | N24: HDFCN52025090553870975
A25: 45813 | B25: 8026.5902 | E25: DZ | F25: 45979 | G25: -477139.41 | H25: HDFCN52025072369906032 | J25: 45933 | K25: BARNET INDIA PRIVATE LIMITED | L25: INR | M25: 339060.54 | N25: HDFCN52025100205721894
A26: 45813 | B26: 2293.664 | C26: HDFCN52025060575568983 | E26: DZ | F26: 46007 | G26: -66620.79 | H26: G15K40FCKGJH
A27: 45813 | B27: 3670.0624 | C27: HDFCN52025060575568983 | E27: DZ | F27: 46007 | G27: -296024 | J27: 45993 | K27: BARNET INDIA PRIVATE LIMITED | L27: INR | M27: 360109.3 | N27: G15K40FCKGJH
A28: 45813 | B28: 16052.314 | C28: HDFCN52025060575568983 | E28: DZ | F28: 46007 | G28: -30866.77 | H28: G15K40FCKGJH | J28: 46006 | K28: BARNET INDIA PRIVATE LIMITED | L28: INR | M28: 14903.5 | N28: G90RGJ9HVGZQ
A29: 45813 | B29: 4587.328 | C29: HDFCN52025060575568983 | E29: DZ | F29: 46030 | G29: -30687.62
A30: 45813 | B30: 7340.1249 | C30: HDFCN52025060575568983 | E30: DZ | F30: 46070 | G30: -30424.05 | J30: 46069 | K30: BARNET INDIA PRIVATE LIMITED | L30: INR | M30: 30424.05 | N30: H3YKFZWVB0GN
A31: 45813 | B31: 15921.62 | C31: HDFCN52025060575568983 | E31: DZ | F31: 46070 | G31: -971.67 | J31: 46069 | K31: BARNET INDIA PRIVATE LIMITED | L31: INR | M31: 971.67 | N31: H2PMXC728CY0
A32: 45813 | B32: 15921.62 | C32: HDFCN52025060575568983 | E32: DZ | F32: 45832 | G32: -112111.95
A33: 45813 | B33: 57739.158 | C33: HDFCN52025060575568983 | E33: DZ | F33: 45832 | G33: 112111.95
A34: 45813 | B34: 4339.1605 | C34: HDFCN52025060575568983 | E34: DZ | F34: 45832 | G34: 159186.29
A35: 45813 | B35: 3551.3531 | C35: HDFCN52025060575568983 | E35: DZ | F35: 45832 | G35: -159186.29
A36: 45813 | B36: 341000 | C36: HDFCN52025060575565670 | E36: DZ | F36: 45890 | G36: 179293.83
A37: 45821 | B37: 4358.9368 | C37: HDFCN52025061495304800 | E37: DZ | F37: 45890 | G37: -179293.83
A38: 45822 | B38: 10780 | C38: HDFCN52025061495304800 | E38: DZ | F38: 45890 | G38: 475086.94
A39: 45822 | B39: 6468 | C39: HDFCN52025061495304800 | E39: DZ | F39: 45890 | G39: -475086.94
A40: 45822 | B40: 4208.8858 | C40: HDFCN52025061495304800 | E40: DZ | F40: 45908 | G40: 495157.4
A41: 45822 | B41: 8897.8787 | C41: HDFCN52025061495304800 | E41: DZ | F41: 45908 | G41: -495157.4
A42: 45822 | B42: 31843.24 | C42: HDFCN52025061495304800 | E42: DZ | F42: 45908 | G42: 107117.71
A43: 45822 | B43: 14560.983 | C43: HDFCN52025061495304800 | E43: DZ | F43: 45908 | G43: -107117.71
... A54: 45861 | B54: 45661.528 | C54: HDFCN52025072369906032 | E54: DZ | F54: 45946 | G54: -2932.62
A55: 45891 | B55: 37895.481 | C55: HDFCN52025082227307462 | E55: DZ | F55: 45946 | G55: 2932.62 | H55: HDFCH00465695692
A56: 45891 | B56: 7093.6764 | C56: HDFCN52025082227307462
A57: 45891 | B57: 15934.693 | C57: HDFCN52025082227307462
A58: 45891 | B58: 295083.42 | C58: HDFCN52025082227307462
A59: 45891 | B59: 93274.563 | C59: HDFCN52025082227307462
A60: 45891 | B60: 12711.761 | C60: HDFCN52025082227307462
A61: 45891 | B61: 10400.676 | C61: HDFCN52025082227307462
A62: 45891 | B62: 22763.132 | C62: HDFCN52025082227307462
A63: 45896 | B63: 27271.163 | C63: HDFCN52025082733046460
A64: 45896 | B64: 79846.546 | C64: HDFCN52025082733046460
A65: 45905 | B65: 54987.705 | C65: HDFCN52025090553870975
A66: 45905 | B66: 25495.508 | C66: HDFCN52025090553870975
A67: 45905 | B67: 43706.014 | C67: HDFCN52025090553870975
... A93: 46067 | B93: 971.66757 | C93: HDFCH00806112854

Sheet TDS data
J1: =SUBTOTAL(9,J3:J186) -> 298205
A2: Sr.No. | B2: Particulars | C2: Bill Amt in USD | D2: Month- service Received | E2: Date | F2: INV NO | G2: EX.RATE | H2: INVOICE AMT | I2: TDS | J2: TDS AMOUNT
A3: 1 | B3: Storage Charges 1st Aug to 31st Aug 2024 | C3: 960.64 | D3: August, 2024 | E3: 45698 | F3: 6779IV124000167 | G3: 87.5858 | H3: 84138.423 | I3: 0.1 | J3: =ROUND(H3*I3,0) -> 8414
A4: 2 | B4: LCL Charges | C4: 132 | D4: August, 2024 | E4: 45698 | F4: 6779IV124000168 | G4: 87.5858 | H4: 11561.326 | I4: 0.02 | J4: =ROUND(H4*I4,0) -> 231
A5: 3 | B5: Inbound Handling Charges | C5: 472.38 | D5: August, 2024 | E5: 45698 | F5: 6779IV124000169 | G5: 87.5858 | H5: 41373.78 | I5: 0.02 | J5: =ROUND(H5*I5,0) -> 827
A6: 4 | B6: Lolo Charges | C6: 432 | D6: August, 2024 | E6: 45698 | F6: 6779IV124000170 | G6: 87.5858 | H6: 37837.066 | I6: 0.02 | J6: =ROUND(H6*I6,0) -> 757
A7: 5 | B7: Outbound Handling Charges | C7: 472.38 | D7: August, 2024 | E7: 45698 | F7: 6779IV124000171 | G7: 87.5858 | H7: 41373.78 | I7: 0.02 | J7: =ROUND(H7*I7,0) -> 827
A8: 6 | B8: VAS Activity Charges | C8: 125.59113 | D8: August, 2024 | E8: 45698 | F8: 6779IV124000172 | G8: 87.5858 | H8: 11000 | I8: 0.02 | J8: =ROUND(H8*I8,0) -> 220
A9: 7 | B9: Storage Charges 1st Sep to 30th Sep 2024 | C9: 1495.68 | D9: September, 2024 | E9: 45698 | F9: 6779IV124000173 | G9: 87.5858 | H9: 131000.33 | I9: 0.1 | J9: =ROUND(H9*I9,0) -> 13100
A10: 8 | B10: LCL Charges | C10: 211.2 | D10: September, 2024 | E10: 45698 | F10: 6779IV124000174 | G10: 87.5858 | H10: 18498.121 | I10: 0.02 | J10: =ROUND(H10*I10,0) -> 370
A11: 9 | B11: Inbound Handling Charges | C11: 755.808 | D11: September, 2024 | E11: 45698 | F11: 6779IV124000175 | G11: 87.5858 | H11: 66198.048 | I11: 0.02 | J11: =ROUND(H11*I11,0) -> 1324
A12: 10 | B12: Lolo Charges | C12: 475.2 | D12: September, 2024 | E12: 45698 | F12: 6779IV124000176 | G12: 87.5858 | H12: 41620.772 | I12: 0.02 | J12: =ROUND(H12*I12,0) -> 832
A13: 11 | B13: Outbound Handling Charges | C13: 283.428 | D13: September, 2024 | E13: 45698 | F13: 6779IV124000177 | G13: 87.5858 | H13: 24824.268 | I13: 0.02 | J13: =ROUND(H13*I13,0) -> 496
A14: 12 | B14: CY Movement Charges | C14: 81 | D14: September, 2024 | E14: 45698 | F14: 6779IV124000178 | G14: 87.5858 | H14: 7094.4498 | I14: 0.02 | J14: =ROUND(H14*I14,0) -> 142
... A86: 84 | B86: LOLO chgs - 01 - 15 Apr 25 | C86: 43.2 | D86: April, 2025 | E86: 45770 | F86: 256779412903 | G86: 86.972692 | H86: 3757.2203 | I86: 0.02 | J86: =ROUND(H86*I86,0) -> 75
A87: 85 | B87: VAS - 16-30 April 25, Ex.Rate-85.05 | C87: 51.73 | D87: April, 2025 | E87: 45787 | F87: 256779413234 | G87: 85.9837 | H87: 4447.9368 | I87: 0.02 | J87: =ROUND(H87*I87,0) -> 89
A88: 86 | B88: VAS 1-15 April-25,Ex.Rate-85.69 | C88: 25.67 | D88: April, 2025 | E88: 45771 | F88: 256779412766 | G88: 86.92182 | H88: 2231.2831 | I88: 0.02 | J88: =ROUND(H88*I88,0) -> 45
A89: 87 | B89: Weighment-16-30 April25, Ex.Rate-85.05 | C89: 42.33 | D89: April, 2025 | E89: 45787 | F89: 256779413248 | G89: 85.9837 | H89: 3639.69 | I89: 0.02 | J89: =ROUND(H89*I89,0) -> 73
A90: 88 | B90: Outbound Handling charges for Feb 2025 | C90: 94.48 | D90: February, 2025 | E90: 45736 | F90: 246779413959 | G90: 86.69126 | H90: 8190.5902 | I90: 0.02 | J90: =ROUND(H90*I90,0) -> 164
A91: 89 | B91: CY-Movement Charges for Feb 2025 | C91: 27 | D91: February, 2025 | E91: 45736 | F91: 246779413959 | G91: 86.69126 | H91: 2340.664 | I91: 0.02 | J91: =ROUND(H91*I91,0) -> 47
A92: 90 | B92: LOLO Charges for Feb 2025 | C92: 43.2 | D92: February, 2025 | E92: 45736 | F92: 246779413959 | G92: 86.69126 | H92: 3745.0624 | I92: 0.02 | J92: =ROUND(H92*I92,0) -> 75
A93: 91 | B93: Outbound Handling charges for Feb 2025 | C93: 94.48 | D93: February, 2025 | E93: 45736 | F93: 246779413960 | G93: 86.69126 | H93: 8190.5902 | I93: 0.02 | J93: =ROUND(H93*I93,0) -> 164
A94: 92 | B94: CY-Movement Charges for Feb 2025 | C94: 27 | D94: February, 2025 | E94: 45736 | F94: 246779413960 | G94: 86.69126 | H94: 2340.664 | I94: 0.02 | J94: =ROUND(H94*I94,0) -> 47
A95: 93 | B95: LOLO Charges for Feb 2025 | C95: 43.2 | D95: February, 2025 | E95: 45736 | F95: 246779413960 | G95: 86.69126 | H95: 3745.0624 | I95: 0.02 | J95: =ROUND(H95*I95,0) -> 75
A96: 94 | B96: Outbound Handling charges for Feb 2025 | C96: 188.95 | D96: February, 2025 | E96: 45736 | F96: 246779413963 | G96: 86.69126 | H96: 16380.314 | I96: 0.02 | J96: =ROUND(H96*I96,0) -> 328
A97: 95 | B97: CY-Movement Charges for Feb 2025 | C97: 54 | D97: February, 2025 | E97: 45736 | F97: 246779413963 | G97: 86.69126 | H97: 4681.328 | I97: 0.02 | J97: =ROUND(H97*I97,0) -> 94
A98: 96 | B98: LOLO Charges for Feb 2025 | C98: 86.4 | D98: February, 2025 | E98: 45736 | F98: 246779413963 | G98: 86.69126 | H98: 7490.1249 | I98: 0.02 | J98: =ROUND(H98*I98,0) -> 150
... A114: 112 | B114: LOLO chgs - 16-31 MAY 25 ( BOE2030748 ) | C114: 259.2 | D114: May,2025 | E114: 45812 | F114: 256779414296 | G114: 85.49078 | H114: 22159.21 | I114: 0.02 | J114: =ROUND(H114*I114,0) -> 443
A115: 113 | B115: Transportation In Chgs - 01 - 15 JUN 25 | C115: 1440 | D115: June,2025 | E115: 45842 | F115: 256779414785 | G115: 86.00067 | H115: 123840.96 | I115: 0.02 | J115: =ROUND(H115*I115,0) -> 2477
A116: 114 | B116: CY - WH destuff Chgs - 01 - 15 JUN 25 | C116: 216 | D116: June,2025 | E116: 45842 | F116: 256779414785 | G116: 86.00067 | H116: 18576.145 | I116: 0.02 | J116: =ROUND(H116*I116,0) -> 372
A117: 115 | B117: Inbound chgs - 01 - 15 JUN 25 | C117: 1088.09 | D117: June,2025 | E117: 45842 | F117: 256779414785 | G117: 86.00067 | H117: 93576.469 | I117: 0.02 | J117: =ROUND(H117*I117,0) -> 1872
A118: 116 | B118: LOLO chgs - 01 - 15 JUN 25 | C118: 518.4 | D118: June,2025 | E118: 45842 | F118: 256779414785 | G118: 86.00067 | H118: 44582.747 | I118: 0.02 | J118: =ROUND(H118*I118,0) -> 892
A119: 117 | B119: Outbound chgs - 01 - 15 Jun 25 | C119: 1350.66 | D119: June,2025 | E119: 45842 | F119: 256779414809 | G119: 86.00067 | H119: 116157.66 | I119: 0.02 | J119: =ROUND(H119*I119,0) -> 2323
A120: 118 | B120: Loose chgs - 01 - 15 Jun 25 | C120: 25 | D120: June,2025 | E120: 45842 | F120: 256779414809 | G120: 86.00067 | H120: 2150.0167 | I120: 0.02 | J120: =ROUND(H120*I120,0) -> 43
A121: 119 | B121: LOLO chgs - 01 - 15 Jun 25 | C121: 604.8 | D121: June,2025 | E121: 45842 | F121: 256779414809 | G121: 86.00067 | H121: 52013.205 | I121: 0.02 | J121: =ROUND(H121*I121,0) -> 1040
A122: 120 | B122: Transportation Out chgs - 16 - 30 Jun 25 WH 09 | C122: 720 | D122: June,2025 | E122: 45842 | F122: 256779414998 | G122: 86.00067 | H122: 61920.482 | I122: 0.02 | J122: =ROUND(H122*I122,0) -> 1238
A123: 121 | B123: CY - CY chgs - 16 - 30 Jun 25 WH 09 | C123: 108 | D123: June,2025 | E123: 45842 | F123: 256779414998 | G123: 86.00067 | H123: 9288.0724 | I123: 0.02 | J123: =ROUND(H123*I123,0) -> 186
A124: 122 | B124: Empty Cont In chgs - 16 - 30 Jun 25 WH 09 | C124: 360 | D124: June,2025 | E124: 45842 | F124: 256779414998 | G124: 86.00067 | H124: 30960.241 | I124: 0.02 | J124: =ROUND(H124*I124,0) -> 619
A125: 123 | B125: Outbound chgs - 16 - 30 Jun 25 WH 09 | C125: 377.9 | D125: June,2025 | E125: 45842 | F125: 256779414998 | G125: 86.00067 | H125: 32499.653 | I125: 0.02 | J125: =ROUND(H125*I125,0) -> 650
A126: 124 | B126: Loose chgs - 16 - 30 Jun 25 WH 09 | C126: 13.63 | D126: June,2025 | E126: 45842 | F126: 256779414998 | G126: 86.00067 | H126: 1172.1891 | I126: 0.02 | J126: =ROUND(H126*I126,0) -> 23
A127: 125 | B127: LOLO chgs - 16 - 30 Jun 25 WH 09 | C127: 172.8 | D127: June,2025 | E127: 45842 | F127: 256779414998 | G127: 86.00067 | H127: 14860.916 | I127: 0.02 | J127: =ROUND(H127*I127,0) -> 297
A128: 126 | B128: PORT SSR Chgs June 25 | C128: 14.09 | D128: June,2025 | E128: 45842 | F128: 256779415031 | G128: 86.00067 | H128: 1211.7494 | I128: 0.02 | J128: =ROUND(H128*I128,0) -> 24
A129: 127 | B129: Detention Chgs - 16 - 30 JUN 25 | C129: 139.58 | D129: June,2025 | E129: 45842 | F129: 256779414851 | G129: 86.00067 | H129: 12003.974 | I129: 0.02 | J129: =ROUND(H129*I129,0) -> 240
A130: 128 | B130: Transportation In Chgs - 16 - 30 JUN 25 WH09 | C130: 1620 | D130: June,2025 | E130: 45842 | F130: 256779414866 | G130: 86.00067 | H130: 139321.09 | I130: 0.02 | J130: =ROUND(H130*I130,0) -> 2786
A131: 129 | B131: CY - WH destuff Chgs - 16 - 30 JUN 25 WH09 | C131: 243 | D131: June,2025 | E131: 45842 | F131: 256779414866 | G131: 86.00067 | H131: 20898.163 | I131: 0.02 | J131: =ROUND(H131*I131,0) -> 418
A132: 130 | B132: Inbound chgs - 16 - 30 JUN 25 WH09 | C132: 809.23 | D132: June,2025 | E132: 45842 | F132: 256779414866 | G132: 86.00067 | H132: 69594.322 | I132: 0.02 | J132: =ROUND(H132*I132,0) -> 1392
A133: 131 | B133: LOLO chgs - 16 - 30 JUN 25 WH09 | C133: 388.8 | D133: June,2025 | E133: 45842 | F133: 256779414866 | G133: 86.00067 | H133: 33437.06 | I133: 0.02 | J133: =ROUND(H133*I133,0) -> 669
... A180: 178 | B180: Unit Storage - 1-31 DEC 2025 | C180: 881.6 | D180: December, 2025 | E180: 46028 | F180: 256779440242 | G180: 90.74314 | H180: 79999.152 | I180: 0.1 | J180: =ROUND(H180*I180,0) -> 8000
A181: 179 | B181: Unit Storage - 1-30 Nov 2025 | C181: 182.78 | D181: November, 2025 | E181: 46024 | F181: 256779440012 | G181: 90.74314 | H181: =C181*G181 -> 16586.031 | I181: 0.1 | J181: =ROUND(H181*I181,0) -> 1659
A182: 180 | B182: Scanning Chgs - 16 - 30 Nov 25 | C182: 50 | D182: November, 2025 | E182: 46024 | F182: 256779440046 | G182: 90.74314 | H182: =C182*G182 -> 4537.157 | I182: 0.02 | J182: =ROUND(H182*I182,0) -> 91
A183: 181 | B183: LCL Chgs - 16 - 31 JAN 26 ( WH 09 ) | C183: 26.4 | D183: January, 2026 | E183: 46064 | F183: 256779451520 | G183: 90.3352 | H183: =C183*G183 -> 2384.8493 | I183: 0.02 | J183: =ROUND(H183*I183,0) -> 48
A184: 182 | B184: Inbound chgs - 16 - 31 JAN 26 ( WH 09 ) | C184: 23.09 | D184: January, 2026 | E184: 46064 | F184: 256779451520 | G184: 90.3352 | H184: =C184*G184 -> 2085.8398 | I184: 0.02 | J184: =ROUND(H184*I184,0) -> 42
A185: 183 | B185: Loose chgs - 16 - 31 JAN 26 ( WH 09 ) | C185: 11.55 | D185: January, 2026 | E185: 46064 | F185: 256779451520 | G185: 90.3352 | H185: =C185*G185 -> 1043.3716 | I185: 0.02 | J185: =ROUND(H185*I185,0) -> 21
A186: 184 | B186: Unit Storage 1-31 Jan 2026 | C186: 384.56 | D186: January, 2026 | E186: 46065 | F186: 256779451324 | G186: 90.3352 | H186: =C186*G186 -> 34739.305 | I186: 0.1 | J186: =ROUND(H186*I186,0) -> 3474

Sheet Sheet2
A1: Document Type | B1: Document Date | C1: Reference | D1: Document Currency Key | E1: Document Currency Value | F1: Company Code Currency Key | G1: Company Code Currency Value | H1: Text | J1: Particulars | K1: Bill Amt in USD | L1: Date | M1: INV NO | N1: EX.RATE | O1: INVOICE AMT | P1: TDS | Q1: TDS AMOUNT | R1: AMT PAYABLE
A2: XB | B2: 45733 | C2: 6779IV124000198 | D2: INR | E2: 2364.82 | F2: INR | G2: 2364.82 | H2: CY Destuff Charges. USD 27 @ INR 87.59 per USD - G | J2: CY Destuff Charges | K2: 27 | L2: 45698 | M2: 6779IV124000198 | N2: 87.5858 | O2: 2364.8166 | P2: 0.02 | Q2: =ROUND(O2*P2,0) -> 47 | R2: =O2-Q2 -> 2317.8166
A3: XB | B3: 45733 | C3: 6779IV124000202 | D3: INR | E3: 2801.87 | F3: INR | G3: 2801.87 | H3: Loose Unloading Charges. USD 31.99 @ INR 87.59 per | J3: Loose Unloading Charges | K3: 31.99 | L3: 45698 | M3: 6779IV124000202 | N3: 87.5858 | O3: 2801.8697 | P3: 0.02 | Q3: =ROUND(O3*P3,0) -> 56 | R3: =O3-Q3 -> 2745.8697
A4: XB | B4: 45733 | C4: 6779IV124000205 | D4: INR | E4: 2801.87 | F4: INR | G4: 2801.87 | H4: Loose Loading Charges. USD 31.99 @ INR 87.59 per U | J4: Loose Loading Charges | K4: 31.99 | L4: 45698 | M4: 6779IV124000205 | N4: 87.5858 | O4: 2801.8697 | P4: 0.02 | Q4: =ROUND(O4*P4,0) -> 56 | R4: =O4-Q4 -> 2745.8697
A5: XB | B5: 45733 | C5: 6779IV124000191 | D5: INR | E5: 4624.53 | F5: INR | G5: 4624.53 | H5: LCL Charges. USD 52.8 @ INR 87.59 per USD - GST eI | J5: LCL Charges | K5: 52.8 | L5: 45698 | M5: 6779IV124000191 | N5: 87.5858 | O5: 4624.5302 | P5: 0.02 | Q5: =ROUND(O5*P5,0) -> 92 | R5: =O5-Q5 -> 4532.5302
A6: XB | B6: 45733 | C6: 6779IV124000200 | D6: INR | E6: 4624.53 | F6: INR | G6: 4624.53 | H6: LCL Charges. USD 52.8 @ INR 87.59 per USD - GST eI | J6: LCL Charges | K6: 52.8 | L6: 45698 | M6: 6779IV124000200 | N6: 87.5858 | O6: 4624.5302 | P6: 0.02 | Q6: =ROUND(O6*P6,0) -> 92 | R6: =O6-Q6 -> 4532.5302
A7: XB | B7: 45733 | C7: 6779IV124000194 | D7: INR | E7: 4729.63 | F7: INR | G7: 4729.63 | H7: CY Movement Charges. USD 54 @ INR 87.59 per USD - | J7: CY Movement Charges | K7: 54 | L7: 45698 | M7: 6779IV124000194 | N7: 87.5858 | O7: 4729.6332 | P7: 0.02 | Q7: =ROUND(O7*P7,0) -> 95 | R7: =O7-Q7 -> 4634.6332
A8: XB | B8: 45733 | C8: 6779IV124000204 | D8: INR | E8: 5603.74 | F8: INR | G8: 5603.74 | H8: Outbound Handling Charges. USD 63.98 @ INR 87.59 p | J8: Outbound Handling Charges | K8: 63.98 | L8: 45698 | M8: 6779IV124000204 | N8: 87.5858 | O8: 5603.7395 | P8: 0.02 | Q8: =ROUND(O8*P8,0) -> 112 | R8: =O8-Q8 -> 5491.7395
A9: XB | B9: 45733 | C9: 6779IV124000178 | D9: INR | E9: 7094.45 | F9: INR | G9: 7094.45 | H9: CY Movement Charges. USD 81 @ INR 87.59 per USD - | J9: CY Movement Charges | K9: 81 | L9: 45698 | M9: 6779IV124000178 | N9: 87.5858 | O9: 7094.4498 | P9: 0.02 | Q9: =ROUND(O9*P9,0) -> 142 | R9: =O9-Q9 -> 6952.4498
A10: XB | B10: 45733 | C10: 6779IV124000172 | D10: INR | E10: 11000 | F10: INR | G10: 11000 | H10: VAS Activity Charges. USD 125.59 @ INR 87.59 per U | J10: VAS Activity Charges | K10: 125.59113 | L10: 45698 | M10: 6779IV124000172 | N10: 87.5858 | O10: 11000 | P10: 0.02 | Q10: =ROUND(O10*P10,0) -> 220 | R10: =O10-Q10 -> 10780
A11: XB | B11: 45733 | C11: 6779IV124000203 | D11: INR | E11: 11351.12 | F11: INR | G11: 11351.12 | H11: Lolo Charges. USD 129.6 @ INR 87.59 per USD - GST | J11: Lolo Charges | K11: 129.6 | L11: 45698 | M11: 6779IV124000203 | N11: 87.5858 | O11: 11351.12 | P11: 0.02 | Q11: =ROUND(O11*P11,0) -> 227 | R11: =O11-Q11 -> 11124.12
A12: XB | B12: 45733 | C12: 6779IV124000168 | D12: INR | E12: 11561.33 | F12: INR | G12: 11561.33 | H12: LCL Charges. USD 132 @ INR 87.59 per USD - GST eIn | J12: LCL Charges | K12: 132 | L12: 45698 | M12: 6779IV124000168 | N12: 87.5858 | O12: 11561.326 | P12: 0.02 | Q12: =ROUND(O12*P12,0) -> 231 | R12: =O12-Q12 -> 11330.326
A13: XB | B13: 45733 | C13: 6779IV124000179 | D13: INR | E13: 13200 | F13: INR | G13: 13200 | H13: VAS Activity Charges. USD 150.71 @ INR 87.59 per U | J13: VAS Activity Charges | K13: 150.70936 | L13: 45698 | M13: 6779IV124000179 | N13: 87.5858 | O13: 13200 | P13: 0.02 | Q13: =ROUND(O13*P13,0) -> 264 | R13: =O13-Q13 -> 12936
... A40: XB | B40: 45733 | C40: 6779IV124000180 | D40: INR | E40: 262000.66 | F40: INR | G40: 262000.66 | H40: Storage Charges 1st Oct to 31st Oct 2024. USD 2991 | J40: Storage Charges 1st Oct to 31st Oct 2024 | K40: 2991.36 | L40: 45698 | M40: 6779IV124000180 | N40: 87.5858 | O40: 262000.66 | P40: 0.1 | Q40: =ROUND(O40*P40,0) -> 26200 | R40: =O40-Q40 -> 235800.66

Sheet Duplicate CN in Ascenudes Books
A2: Document Number | B2: Document Type | C2: Document Date | D2: Reference | E2: Document Currency Key | F2: Document Currency Value | G2: Company Code Currency Key | H2: Company Code Currency Value | I2: Text | J2: Invoice Value | K2: Remarks
A3: 1600000820 | B3: DG | C3: 45791 | D3: 256779420529 | E3: USD | F3: -86.4 | G3: INR | H3: -7510.05 | I3: Credit note against 256779411760 | J3: 256779411760 | K3: Duplicate CN in Ascendus

Sheet Difference in Invoice value  
A3: Document Number | B3: Document Type | C3: Document Date | D3: Reference | E3: Document Currency Key | F3: Document Currency Value | G3: Company Code Currency Key | H3: Company Code Currency Value | I3: Text | J3: Gross Amount | K3: TDS | L3: Difference | M3: Rate | N3: Remarks
A4: 1800012193 | B4: DR | C4: 45889 | D4: 256779416855 | E4: USD | F4: 137.68 | G4: INR | H4: 11844.63 | I4: Outbound chgs - 01 - 15 Aug 25 | J4: {=VLOOKUP(D4,'Customer data Vlookup'!$B:$E,{2,3},0)} -> 8128.1257 | K4: 163 | L4: =J4-H4 -> -3716.5043 | M4: =K4/H4 -> 0.01376151 | N4: Under reporting of invoice Value
A5: 1800009485 | B5: DR | C5: 45815 | D5: 256779414249 | E5: USD | F5: 2032.81 | G5: INR | H5: 173786.51 | I5: Unit storage -1-31 May 25 | J5: {=VLOOKUP(D5,'Customer data Vlookup'!$B:$E,{2,3},0)} -> 161435.49 | K5: 16144 | L5: =J5-H5 -> -12351.022 | M5: =K5/H5 -> 0.092895588 | N5: Under reporting of invoice Value
A6: 1800015679 | B6: DR | C6: 46024 | D6: 256779440012 | E6: USD | F6: 182.78 | G6: INR | H6: 16586.03 | I6: Unit Storage - 1-30 Nov 2025 | J6: {=VLOOKUP(D6,'Customer data Vlookup'!$B:$E,{2,3},0)} -> 33172.062 | K6: 3318 | L6: =J6-H6 -> 16586.032 | M6: =K6/H6 -> 0.20004787 | N6: Duplicate Invoice In customers Books
A7: 1800015717 | B7: DR | C7: 46024 | D7: 256779440046 | E7: USD | F7: 50 | G7: INR | H7: 4537.16 | I7: Scanning Chgs - 16 - 30 Nov 25 | J7: {=VLOOKUP(D7,'Customer data Vlookup'!$B:$E,{2,3},0)} -> 9074.314 | K7: 182 | L7: =J7-H7 -> 4537.154 | M7: =K7/H7 -> 0.040113199 | N7: Duplicate Invoice In customers Books
L8: =SUM(L4:L7) -> 5055.6602

Sheet Credit Note in customers books
A1: Sr.No. | B1: Particulars | C1: Bill Amt in USD | D1: Month- service Received | E1: Date | F1: INV NO | G1: EX.RATE | H1: INVOICE AMT | I1: TDS | J1: TDS AMOUNT | K1: AMT PAYABLE | L1: AMOUNT DEDUCTED/Credit note | M1: AMOUNT PAID | O1: Date | P1: UTR NO/REMARK | Q1: MONTH-INV Received &BOOKED | R1: REMARK
A2: 13 | B2: VAS Activity Charges | C2: 150.70936 | D2: September, 2024 | E2: 45698 | F2: 6779IV124000179 | G2: 87.5858 | H2: 13200 | I2: 0.02 | J2: 264 | K2: 12936 | L2: 6468 | M2: 6468 | N2: 12936 | O2: 45822 | P2: HDFCN52025061495304800 | Q2: 45717 | R2: CREDIT NOTE AWAITED
A3: 133 | B3: Unit Storage - 1-30 June 25 | C3: 5120.2 | D3: June,2025 | E3: 45842 | F3: 256779415205 | G3: 86.00067 | H3: 440340.63 | I3: 0.1 | J3: 44034 | K3: 396306.63 | L3: 144316 | M3: 251990.63 | N3: 396306.63 | O3: 45993 | P3: HDFCH00646925098 | Q3: 45839 | R3: CREDIT NOTE AWAITED
A4: 139 | B4: Unit Storage - 1-31 July 25 | C4: 4902.53 | D4: July,25 | E4: 45877 | F4: 256779416093 | G4: 86.03012 | H4: 421765.24 | I4: 0.1 | J4: 42177 | K4: 379588.24 | L4: 246362.73 | M4: 133225.51 | N4: 379588.24 | O4: 45932 | P4: HDFCN52025100205721894 | Q4: 45870 | R4: CREDIT NOTE AWAITED
L5: =SUM(L2:L4) -> 397146.74

Sheet Customer data Vlookup
B3: INV NO | C3: INVOICE AMT | D3: TDS AMOUNT | E3: AMT PAYABLE | F3: AMOUNT DEDUCTED | G3: AMOUNT PAID | H3: Total Payment | J3: =SUBTOTAL(9,J4:J127) -> 5055.6538
B4: 246779413959 | C4: 14276.317 | D4: 286 | E4: 13990.317 | G4: 13990.317 | H4: =SUM(F4:G4) -> 13990.317 | I4: =_xlfn.XLOOKUP(B4,'Ascendus Data'!$M:$M,'Ascendus Data'!$U:$U,0,0) -> 14276.32 | J4: =C4-I4 -> -0.0033032
B5: 246779413960 | C5: 14276.317 | D5: 286 | E5: 13990.317 | G5: 13990.317 | H5: =SUM(F5:G5) -> 13990.317 | I5: =_xlfn.XLOOKUP(B5,'Ascendus Data'!$M:$M,'Ascendus Data'!$U:$U,0,0) -> 14276.32 | J5: =C5-I5 -> -0.0033032
B6: 246779413963 | C6: 28551.766 | D6: 572 | E6: 27979.766 | G6: 27979.766 | H6: =SUM(F6:G6) -> 27979.766 | I6: =_xlfn.XLOOKUP(B6,'Ascendus Data'!$M:$M,'Ascendus Data'!$U:$U,0,0) -> 28551.77 | J6: =C6-I6 -> -0.003519
B7: 256779410039 | C7: 24636.251 | D7: 493 | E7: 24143.251 | G7: 24143.251 | H7: =SUM(F7:G7) -> 24143.251 | I7: =_xlfn.XLOOKUP(B7,'Ascendus Data'!$M:$M,'Ascendus Data'!$U:$U,0,0) -> 24636.25 | J7: =C7-I7 -> 0.0014426
B8: 256779410040 | C8: 6884.2081 | D8: 138 | E8: 6746.2081 | G8: 6746.2081 | H8: =SUM(F8:G8) -> 6746.2081 | I8: =_xlfn.XLOOKUP(B8,'Ascendus Data'!$M:$M,'Ascendus Data'!$U:$U,0,0) -> 6884.21 | J8: =C8-I8 -> -0.001856
B9: 256779410041 | C9: 11265.068 | D9: 225 | E9: 11040.068 | G9: 11040.068 | H9: =SUM(F9:G9) -> 11040.068 | I9: =_xlfn.XLOOKUP(B9,'Ascendus Data'!$M:$M,'Ascendus Data'!$U:$U,0,0) -> 11265.07 | J9: =C9-I9 -> -0.002128
B10: 256779410042 | C10: 23468.891 | D10: 469 | E10: 22999.891 | H10: =SUM(F10:G10) -> 0 | I10: =_xlfn.XLOOKUP(B10,'Ascendus Data'!$M:$M,'Ascendus Data'!$U:$U,0,0) -> 23468.89 | J10: =C10-I10 -> 0.0014
B11: 256779410102 | C11: 24636.251 | D11: 493 | E11: 24143.251 | G11: 24143.251 | H11: =SUM(F11:G11) -> 24143.251 | I11: =_xlfn.XLOOKUP(B11,'Ascendus Data'!$M:$M,'Ascendus Data'!$U:$U,0,0) -> 24636.25 | J11: =C11-I11 -> 0.0014426
B12: 256779410103 | C12: 7040.6674 | D12: 141 | E12: 6899.6674 | H12: =SUM(F12:G12) -> 0 | I12: =_xlfn.XLOOKUP(B12,'Ascendus Data'!$M:$M,'Ascendus Data'!$U:$U,0,0) -> 7040.67 | J12: =C12-I12 -> -0.00258
B13: 256779410104 | C13: 11265.068 | D13: 225 | E13: 11040.068 | G13: 11040.068 | H13: =SUM(F13:G13) -> 11040.068 | I13: =_xlfn.XLOOKUP(B13,'Ascendus Data'!$M:$M,'Ascendus Data'!$U:$U,0,0) -> 11265.07 | J13: =C13-I13 -> -0.002128
B14: 256779410183 | C14: 6593.02 | D14: 132 | E14: 6461.02 | G14: 6461.02 | H14: =SUM(F14:G14) -> 6461.02 | I14: =_xlfn.XLOOKUP(B14,'Ascendus Data'!$M:$M,'Ascendus Data'!$U:$U,0,0) -> 6593.02 | J14: =C14-I14 -> 4.6999999e-05
B15: 256779410800 | C15: 31709.08 | D15: 3171 | E15: 28538.08 | G15: 28538.08 | H15: =SUM(F15:G15) -> 28538.08 | I15: =_xlfn.XLOOKUP(B15,'Ascendus Data'!$M:$M,'Ascendus Data'!$U:$U,0,0) -> 31709.08 | J15: =C15-I15 -> -6.4000003e-05
B16: 256779411007 | C16: 14262.132 | D16: 285 | E16: 13977.132 | H16: =SUM(F16:G16) -> 0 | I16: =_xlfn.XLOOKUP(B16,'Ascendus Data'!$M:$M,'Ascendus Data'!$U:$U,0,0) -> 14262.13 | J16: =C16-I16 -> 0.0022256
B17: 256779411008 | C17: 28523.395 | D17: 570 | E17: 27953.395 | H17: =SUM(F17:G17) -> 0 | I17: =_xlfn.XLOOKUP(B17,'Ascendus Data'!$M:$M,'Ascendus Data'!$U:$U,0,0) -> 28523.4 | J17: =C17-I17 -> -0.004767
B18: 256779411009 | C18: 14262.132 | D18: 285 | E18: 13977.132 | H18: =SUM(F18:G18) -> 0 | I18: =_xlfn.XLOOKUP(B18,'Ascendus Data'!$M:$M,'Ascendus Data'!$U:$U,0,0) -> 14262.13 | J18: =C18-I18 -> 0.0022256
B19: 256779411010 | C19: 14262.132 | D19: 285 | E19: 13977.132 | H19: =SUM(F19:G19) -> 0 | I19: =_xlfn.XLOOKUP(B19,'Ascendus Data'!$M:$M,'Ascendus Data'!$U:$U,0,0) -> 14262.13 | J19: =C19-I19 -> 0.0022256
B20: 256779411258 | C20: 11967.396 | D20: 239 | E20: 11728.396 | H20: =SUM(F20:G20) -> 0 | I20: =_xlfn.XLOOKUP(B20,'Ascendus Data'!$M:$M,'Ascendus Data'!$U:$U,0,0) -> 11967.4 | J20: =C20-I20 -> -0.0038224
B21: 256779411259 | C21: 11967.396 | D21: 239 | E21: 11728.396 | H21: =SUM(F21:G21) -> 0 | I21: =_xlfn.XLOOKUP(B21,'Ascendus Data'!$M:$M,'Ascendus Data'!$U:$U,0,0) -> 11967.4 | J21: =C21-I21 -> -0.0038224
B22: 256779411260 | C22: 11967.396 | D22: 239 | E22: 11728.396 | H22: =SUM(F22:G22) -> 0 | I22: =_xlfn.XLOOKUP(B22,'Ascendus Data'!$M:$M,'Ascendus Data'!$U:$U,0,0) -> 11967.4 | J22: =C22-I22 -> -0.0038224
B23: 256779411261 | C23: 23933.923 | D23: 478 | E23: 23455.923 | H23: =SUM(F23:G23) -> 0 | I23: =_xlfn.XLOOKUP(B23,'Ascendus Data'!$M:$M,'Ascendus Data'!$U:$U,0,0) -> 23933.92 | J23: =C23-I23 -> 0.003137
B24: 256779412037 | C24: 2187.8222 | D24: 44 | E24: 2143.8222 | H24: =SUM(F24:G24) -> 0 | I24: =_xlfn.XLOOKUP(B24,'Ascendus Data'!$M:$M,'Ascendus Data'!$U:$U,0,0) -> 2187.82 | J24: =C24-I24 -> 0.0022094
B25: 256779412122 | C25: 50734.528 | D25: 5073 | E25: 45661.528 | G25: 45661.528 | H25: =SUM(F25:G25) -> 45661.528 | I25: =_xlfn.XLOOKUP(B25,'Ascendus Data'!$M:$M,'Ascendus Data'!$U:$U,0,0) -> 50734.53 | J25: =C25-I25 -> -0.0021024
B26: 256779412598 | C26: 118253.66 | D26: 2365 | E26: 115888.66 | H26: =SUM(F26:G26) -> 0 | I26: =_xlfn.XLOOKUP(B26,'Ascendus Data'!$M:$M,'Ascendus Data'!$U:$U,0,0) -> 118253.66 | J26: =C26-I26 -> -0.0007628
B27: 256779412630 | C27: 46282.392 | D27: 925 | E27: 45357.392 | H27: =SUM(F27:G27) -> 0 | I27: =_xlfn.XLOOKUP(B27,'Ascendus Data'!$M:$M,'Ascendus Data'!$U:$U,0,0) -> 46282.39 | J27: =C27-I27 -> 0.0022772
B28: 256779412766 | C28: 2231.2831 | D28: 45 | E28: 2186.2831 | G28: 2186.2831 | H28: =SUM(F28:G28) -> 2186.2831 | I28: =_xlfn.XLOOKUP(B28,'Ascendus Data'!$M:$M,'Ascendus Data'!$U:$U,0,0) -> 2231.28 | J28: =C28-I28 -> 0.0031194
B29: 256779412875 | C29: 50525.92 | D29: 1010 | E29: 49515.92 | H29: =SUM(F29:G29) -> 0 | I29: =_xlfn.XLOOKUP(B29,'Ascendus Data'!$M:$M,'Ascendus Data'!$U:$U,0,0) -> 50525.92 | J29: =C29-I29 -> 0
B30: 256779412903 | C30: 13376.4 | D30: 267 | E30: 13109.4 | H30: =SUM(F30:G30) -> 0 | I30: =_xlfn.XLOOKUP(B30,'Ascendus Data'!$M:$M,'Ascendus Data'!$U:$U,0,0) -> 13376.4 | J30: =C30-I30 -> 0
B31: 256779413234 | C31: 4447.9368 | D31: 89 | E31: 4358.9368 | G31: 4358.9368 | H31: =SUM(F31:G31) -> 4358.9368 | I31: =_xlfn.XLOOKUP(B31,'Ascendus Data'!$M:$M,'Ascendus Data'!$U:$U,0,0) -> 4447.94 | J31: =C31-I31 -> -0.003199
B32: 256779413248 | C32: 3639.69 | D32: 73 | E32: 3566.69 | G32: 3566.69 | H32: =SUM(F32:G32) -> 3566.69 | I32: =_xlfn.XLOOKUP(B32,'Ascendus Data'!$M:$M,'Ascendus Data'!$U:$U,0,0) -> 3639.69 | J32: =C32-I32 -> 2.1e-05
B33: 256779413262 | C33: 4294.8858 | D33: 86 | E33: 4208.8858 | G33: 4208.8858 | H33: =SUM(F33:G33) -> 4208.8858 | I33: =_xlfn.XLOOKUP(B33,'Ascendus Data'!$M:$M,'Ascendus Data'!$U:$U,0,0) -> 4294.89 | J33: =C33-I33 -> -0.004185
B34: 256779413294 | C34: 56431.102 | D34: 1129 | E34: 55302.102 | G34: 55302.102 | H34: =SUM(F34:G34) -> 55302.102 | I34: =_xlfn.XLOOKUP(B34,'Ascendus Data'!$M:$M,'Ascendus Data'!$U:$U,0,0) -> 56431.1 | J34: =C34-I34 -> 0.00231
B35: 256779413331 | C35: 16246.62 | D35: 325 | E35: 15921.62 | G35: 15921.62 | H35: =SUM(F35:G35) -> 15921.62 | I35: =_xlfn.XLOOKUP(B35,'Ascendus Data'!$M:$M,'Ascendus Data'!$U:$U,0,0) -> 16246.62 | J35: =C35-I35 -> 0.000115
B36: 256779413466 | C36: 16246.62 | D36: 325 | E36: 15921.62 | G36: 15921.62 | H36: =SUM(F36:G36) -> 15921.62 | I36: =_xlfn.XLOOKUP(B36,'Ascendus Data'!$M:$M,'Ascendus Data'!$U:$U,0,0) -> 16246.62 | J36: =C36-I36 -> 0.000115
B37: 256779413830 | C37: 4428.1605 | D37: 89 | E37: 4339.1605 | G37: 4339.1605 | H37: =SUM(F37:G37) -> 4339.1605 | I37: =_xlfn.XLOOKUP(B37,'Ascendus Data'!$M:$M,'Ascendus Data'!$U:$U,0,0) -> 4428.16 | J37: =C37-I37 -> 0.00055
B38: 256779413838 | C38: 3623.3531 | D38: 72 | E38: 3551.3531 | G38: 3551.3531 | H38: =SUM(F38:G38) -> 3551.3531 | I38: =_xlfn.XLOOKUP(B38,'Ascendus Data'!$M:$M,'Ascendus Data'!$U:$U,0,0) -> 3623.35 | J38: =C38-I38 -> 0.003118
B39: 256779413906 | C39: 64154.158 | D39: 6415 | E39: 57739.158 | G39: 57739.158 | H39: =SUM(F39:G39) -> 57739.158 | I39: =_xlfn.XLOOKUP(B39,'Ascendus Data'!$M:$M,'Ascendus Data'!$U:$U,0,0) -> 64154.16 | J39: =C39-I39 -> -0.001756
B40: 256779414249 | C40: 161435.49 | D40: 16144 | E40: 145291.49 | G40: 145291.49 | H40: =SUM(F40:G40) -> 145291.49 | I40: =_xlfn.XLOOKUP(B40,'Ascendus Data'!$M:$M,'Ascendus Data'!$U:$U,0,0) -> 173786.51 | J40: =C40-I40 -> -12351.022
B41: 256779414282 | C41: 4274.539 | D41: 85 | E41: 4189.539 | G41: 4189.539 | H41: =SUM(F41:G41) -> 4189.539 | I41: =_xlfn.XLOOKUP(B41,'Ascendus Data'!$M:$M,'Ascendus Data'!$U:$U,0,0) -> 4274.54 | J41: =C41-I41 -> -0.001
B42: 256779414296 | C42: 178678.29 | D42: 3574 | E42: 175104.29 | G42: 175104.29 | H42: =SUM(F42:G42) -> 175104.29 | I42: =_xlfn.XLOOKUP(B42,'Ascendus Data'!$M:$M,'Ascendus Data'!$U:$U,0,0) -> 178678.29 | J42: =C42-I42 -> 0.0049234
B43: 256779414785 | C43: 280576.33 | D43: 5613 | E43: 274963.33 | H43: =SUM(F43:G43) -> 0 | I43: =_xlfn.XLOOKUP(B43,'Ascendus Data'!$M:$M,'Ascendus Data'!$U:$U,0,0) -> 280576.33 | J43: =C43-I43 -> -0.0041317
B44: 256779414809 | C44: 170320.89 | D44: 3406 | E44: 166914.89 | H44: =SUM(F44:G44) -> 0 | I44: =_xlfn.XLOOKUP(B44,'Ascendus Data'!$M:$M,'Ascendus Data'!$U:$U,0,0) -> 170320.89 | J44: =C44-I44 -> -0.0030918
B45: 256779414851 | C45: 12003.974 | D45: 240 | E45: 11763.974 | H45: =SUM(F45:G45) -> 0 | I45: =_xlfn.XLOOKUP(B45,'Ascendus Data'!$M:$M,'Ascendus Data'!$U:$U,0,0) -> 12003.97 | J45: =C45-I45 -> 0.0035186
B46: 256779414866 | C46: 317431.05 | D46: 6349 | E46: 311082.05 | H46: =SUM(F46:G46) -> 0 | I46: =_xlfn.XLOOKUP(B46,'Ascendus Data'!$M:$M,'Ascendus Data'!$U:$U,0,0) -> 317431.05 | J46: =C46-I46 -> 0.0029901
B47: 256779414998 | C47: 150701.55 | D47: 3013 | E47: 147688.55 | H47: =SUM(F47:G47) -> 0 | I47: =_xlfn.XLOOKUP(B47,'Ascendus Data'!$M:$M,'Ascendus Data'!$U:$U,0,0) -> 150701.55 | J47: =C47-I47 -> 0.0040611
B48: 256779415031 | C48: 1211.7494 | D48: 24 | E48: 1187.7494 | H48: =SUM(F48:G48) -> 0 | I48: =_xlfn.XLOOKUP(B48,'Ascendus Data'!$M:$M,'Ascendus Data'!$U:$U,0,0) -> 1211.75 | J48: =C48-I48 -> -0.0005597
B49: 256779415205 | C49: 440340.63 | D49: 44034 | E49: 396306.63 | F49: 144316 | G49: 251990.63 | H49: =SUM(F49:G49) -> 396306.63 | I49: =_xlfn.XLOOKUP(B49,'Ascendus Data'!$M:$M,'Ascendus Data'!$U:$U,0,0) -> 440340.63 | J49: =C49-I49 -> 0.00053399999
B50: 256779415254 | C50: 8847.7489 | D50: 177 | E50: 8670.7489 | H50: =SUM(F50:G50) -> 0 | I50: =_xlfn.XLOOKUP(B50,'Ascendus Data'!$M:$M,'Ascendus Data'!$U:$U,0,0) -> 8847.75 | J50: =C50-I50 -> -0.0010704
B51: 256779415267 | C51: 7238.6764 | D51: 145 | E51: 7093.6764 | G51: 7093.6764 | H51: =SUM(F51:G51) -> 7093.6764 | I51: =_xlfn.XLOOKUP(B51,'Ascendus Data'!$M:$M,'Ascendus Data'!$U:$U,0,0) -> 7238.68 | J51: =C51-I51 -> -0.0036061
B52: 256779415417 | C52: 38668.481 | D52: 773 | E52: 37895.481 | G52: 37895.481 | H52: =SUM(F52:G52) -> 37895.481 | I52: =_xlfn.XLOOKUP(B52,'Ascendus Data'!$M:$M,'Ascendus Data'!$U:$U,0,0) -> 38668.48 | J52: =C52-I52 -> 0.0012521
B53: 256779415941 | C53: 30687.619 | D53: 614 | E53: 30073.619 | G53: 30073.619 | H53: =SUM(F53:G53) -> 30073.619 | I53: =_xlfn.XLOOKUP(B53,'Ascendus Data'!$M:$M,'Ascendus Data'!$U:$U,0,0) -> 30687.62 | J53: =C53-I53 -> -0.0009239
B54: 256779416093 | C54: 421765.24 | D54: 42177 | E54: 379588.24 | F54: 246362.73 | G54: 133225.51 | H54: =SUM(F54:G54) -> 379588.24 | I54: =_xlfn.XLOOKUP(B54,'Ascendus Data'!$M:$M,'Ascendus Data'!$U:$U,0,0) -> 421765.24 | J54: =C54-I54 -> 0.0042036
B55: 256779416122 | C55: 60221.084 | D55: 1204 | E55: 59017.084 | H55: =SUM(F55:G55) -> 0 | I55: =_xlfn.XLOOKUP(B55,'Ascendus Data'!$M:$M,'Ascendus Data'!$U:$U,0,0) -> 60221.08 | J55: =C55-I55 -> 0.004
B56: 256779416130 | C56: 27828.163 | D56: 557 | E56: 27271.163 | G56: 27271.163 | H56: =SUM(F56:G56) -> 27271.163 | I56: =_xlfn.XLOOKUP(B56,'Ascendus Data'!$M:$M,'Ascendus Data'!$U:$U,0,0) -> 27828.16 | J56: =C56-I56 -> 0.0029164
B57: 256779416154 | C57: 98384.906 | D57: 1967 | E57: 96417.906 | G57: 96417.906 | H57: =SUM(F57:G57) -> 96417.906 | I57: =_xlfn.XLOOKUP(B57,'Ascendus Data'!$M:$M,'Ascendus Data'!$U:$U,0,0) -> 98384.91 | J57: =C57-I57 -> -0.0044668
B58: 256779416155 | C58: 301105.42 | D58: 6022 | E58: 295083.42 | G58: 295083.42 | H58: =SUM(F58:G58) -> 295083.42 | I58: =_xlfn.XLOOKUP(B58,'Ascendus Data'!$M:$M,'Ascendus Data'!$U:$U,0,0) -> 301105.42 | J58: =C58-I58 -> 0
B59: 256779416193 | C59: 139776.58 | D59: 2796 | E59: 136980.58 | G59: 136980.58 | H59: =SUM(F59:G59) -> 136980.58 | I59: =_xlfn.XLOOKUP(B59,'Ascendus Data'!$M:$M,'Ascendus Data'!$U:$U,0,0) -> 139776.58 | J59: =C59-I59 -> -0.0028312
B60: 256779416437 | C60: 12970.761 | D60: 259 | E60: 12711.761 | G60: 12711.761 | H60: =SUM(F60:G60) -> 12711.761 | I60: =_xlfn.XLOOKUP(B60,'Ascendus Data'!$M:$M,'Ascendus Data'!$U:$U,0,0) -> 12970.76 | J60: =C60-I60 -> 0.0011924
B61: 256779416450 | C61: 10612.676 | D61: 212 | E61: 10400.676 | G61: 10400.676 | H61: =SUM(F61:G61) -> 10400.676 | I61: =_xlfn.XLOOKUP(B61,'Ascendus Data'!$M:$M,'Ascendus Data'!$U:$U,0,0) -> 10612.68 | J61: =C61-I61 -> -0.0043968
B62: 256779416500 | C62: 81476.546 | D62: 1630 | E62: 79846.546 | G62: 79846.546 | H62: =SUM(F62:G62) -> 79846.546 | I62: =_xlfn.XLOOKUP(B62,'Ascendus Data'!$M:$M,'Ascendus Data'!$U:$U,0,0) -> 81476.55 | J62: =C62-I62 -> -0.0042516
B63: 256779416579 | C63: 23228.132 | D63: 465 | E63: 22763.132 | G63: 22763.132 | H63: =SUM(F63:G63) -> 22763.132 | I63: =_xlfn.XLOOKUP(B63,'Ascendus Data'!$M:$M,'Ascendus Data'!$U:$U,0,0) -> 23228.13 | J63: =C63-I63 -> 0.0024
B64: 256779416810 | C64: 1769.6396 | D64: 35 | E64: 1734.6396 | F64: 0 | G64: 1734.6396 | H64: =SUM(F64:G64) -> 1734.6396 | I64: =_xlfn.XLOOKUP(B64,'Ascendus Data'!$M:$M,'Ascendus Data'!$U:$U,0,0) -> 1769.64 | J64: =C64-I64 -> -0.0004316
B65: 256779416825 | C65: 331215.96 | D65: 6624 | E65: 324591.96 | F65: 0 | G65: 324591.96 | H65: =SUM(F65:G65) -> 324591.96 | I65: =_xlfn.XLOOKUP(B65,'Ascendus Data'!$M:$M,'Ascendus Data'!$U:$U,0,0) -> 331215.96 | J65: =C65-I65 -> 0.002
B66: 256779416855 | C66: 8128.1257 | D66: 163 | E66: 7965.1257 | F66: 0 | G66: 7965.1257 | H66: =SUM(F66:G66) -> 7965.1257 | I66: =_xlfn.XLOOKUP(B66,'Ascendus Data'!$M:$M,'Ascendus Data'!$U:$U,0,0) -> 11844.63 | J66: =C66-I66 -> -3716.5043
B67: 256779417091 | C67: 139872.4 | D67: 13987 | E67: 125885.4 | F67: 0 | G67: 125885.4 | H67: =SUM(F67:G67) -> 125885.4 | I67: =_xlfn.XLOOKUP(B67,'Ascendus Data'!$M:$M,'Ascendus Data'!$U:$U,0,0) -> 139872.4 | J67: =C67-I67 -> 0.0033524
B68: 256779417139 | C68: 2191.3588 | D68: 44 | E68: 2147.3588 | F68: 0 | G68: 2147.3588 | H68: =SUM(F68:G68) -> 2147.3588 | I68: =_xlfn.XLOOKUP(B68,'Ascendus Data'!$M:$M,'Ascendus Data'!$U:$U,0,0) -> 2191.36 | J68: =C68-I68 -> -0.0011768
B69: 256779417140 | C69: 1793.1686 | D69: 36 | E69: 1757.1686 | F69: 0 | G69: 1757.1686 | H69: =SUM(F69:G69) -> 1757.1686 | I69: =_xlfn.XLOOKUP(B69,'Ascendus Data'!$M:$M,'Ascendus Data'!$U:$U,0,0) -> 1793.17 | J69: =C69-I69 -> -0.0013783
B70: 256779417191 | C70: 777.12725 | D70: 16 | E70: 761.12725 | F70: 0 | G70: 761.12725 | H70: =SUM(F70:G70) -> 761.12725 | I70: =_xlfn.XLOOKUP(B70,'Ascendus Data'!$M:$M,'Ascendus Data'!$U:$U,0,0) -> 777.13 | J70: =C70-I70 -> -0.0027496
B71: 256779417235 | C71: 36055.904 | D71: 721 | E71: 35334.904 | F71: 0 | G71: 35334.904 | H71: =SUM(F71:G71) -> 35334.904 | I71: =_xlfn.XLOOKUP(B71,'Ascendus Data'!$M:$M,'Ascendus Data'!$U:$U,0,0) -> 36055.9 | J71: =C71-I71 -> 0.00396
B72: 256779417267 | C72: 14411.86 | D72: 288 | E72: 14123.86 | F72: 0 | G72: 14123.86 | H72: =SUM(F72:G72) -> 14123.86 | I72: =_xlfn.XLOOKUP(B72,'Ascendus Data'!$M:$M,'Ascendus Data'!$U:$U,0,0) -> 14411.86 | J72: =C72-I72 -> -0.0001356
B73: 256779417297 | C73: 12048.973 | D73: 241 | E73: 11807.973 | F73: 0 | G73: 11807.973 | H73: =SUM(F73:G73) -> 11807.973 | I73: =_xlfn.XLOOKUP(B73,'Ascendus Data'!$M:$M,'Ascendus Data'!$U:$U,0,0) -> 12048.97 | J73: =C73-I73 -> 0.0029544
B74: 256779417777 | C74: 4405.4714 | D74: 88 | E74: 4317.4714 | F74: 0 | G74: 4317.4714 | H74: =SUM(F74:G74) -> 4317.4714 | I74: =_xlfn.XLOOKUP(B74,'Ascendus Data'!$M:$M,'Ascendus Data'!$U:$U,0,0) -> 4405.47 | J74: =C74-I74 -> 0.0013722
B75: 256779417914 | C75: 30866.769 | D75: 617 | E75: 30249.769 | F75: 0 | G75: 30249.769 | H75: =SUM(F75:G75) -> 30249.769 | I75: =_xlfn.XLOOKUP(B75,'Ascendus Data'!$M:$M,'Ascendus Data'!$U:$U,0,0) -> 30866.77 | J75: =C75-I75 -> -0.0005
... B81: 256779419830 | C81: 991.66757 | D81: 20 | E81: 971.66757 | F81: 0 | G81: 971.66757 | H81: =SUM(F81:G81) -> 971.66757 | I81: =_xlfn.XLOOKUP(B81,'Ascendus Data'!$M:$M,'Ascendus Data'!$U:$U,0,0) -> 991.67 | J81: =C81-I81 -> -0.0024348
B82: 256779440012 | C82: 33172.062 | D82: 3318 | E82: 29854.062 | H82: =SUM(F82:G82) -> 0 | I82: =_xlfn.XLOOKUP(B82,'Ascendus Data'!$M:$M,'Ascendus Data'!$U:$U,0,0) -> 16586.03 | J82: =C82-I82 -> 16586.032
B83: 256779440046 | C83: 9074.314 | D83: 182 | E83: 8892.314 | H83: =SUM(F83:G83) -> 0 | I83: =_xlfn.XLOOKUP(B83,'Ascendus Data'!$M:$M,'Ascendus Data'!$U:$U,0,0) -> 4537.16 | J83: =C83-I83 -> 4537.154
B84: 256779440106 | C84: 63520.198 | D84: 1270 | E84: 62250.198 | H84: =SUM(F84:G84) -> 0 | I84: =_xlfn.XLOOKUP(B84,'Ascendus Data'!$M:$M,'Ascendus Data'!$U:$U,0,0) -> 63520.2 | J84: =C84-I84 -> -0.002
B85: 256779440152 | C85: 22338.239 | D85: 447 | E85: 21891.239 | H85: =SUM(F85:G85) -> 0 | I85: =_xlfn.XLOOKUP(B85,'Ascendus Data'!$M:$M,'Ascendus Data'!$U:$U,0,0) -> 22338.24 | J85: =C85-I85 -> -0.0012262
B86: 256779440242 | C86: 79999.152 | D86: 8000 | E86: 71999.152 | H86: =SUM(F86:G86) -> 0 | I86: =_xlfn.XLOOKUP(B86,'Ascendus Data'!$M:$M,'Ascendus Data'!$U:$U,0,0) -> 79999.15 | J86: =C86-I86 -> 0.002224
B87: 256779451324 | C87: 34739.305 | D87: 3474 | E87: 31265.305 | H87: =SUM(F87:G87) -> 0 | I87: =_xlfn.XLOOKUP(B87,'Ascendus Data'!$M:$M,'Ascendus Data'!$U:$U,0,0) -> 34739.3 | J87: =C87-I87 -> 0.004512
B88: 256779451520 | C88: 5514.0606 | D88: 111 | E88: 5403.0606 | H88: =SUM(F88:G88) -> 0 | I88: =_xlfn.XLOOKUP(B88,'Ascendus Data'!$M:$M,'Ascendus Data'!$U:$U,0,0) -> 5514.06 | J88: =C88-I88 -> 0.000608
B89: 6779IV124000167 | C89: 84138.423 | D89: 8414 | E89: 75724.423 | G89: 75724.423 | H89: =SUM(F89:G89) -> 75724.423 | I89: =_xlfn.XLOOKUP(B89,'Ascendus Data'!$M:$M,'Ascendus Data'!$U:$U,0,0) -> 84138.42 | J89: =C89-I89 -> 0.002912
B90: 6779IV124000168 | C90: 11561.326 | D90: 231 | E90: 11330.326 | G90: 11330.33 | H90: =SUM(F90:G90) -> 11330.33 | I90: =_xlfn.XLOOKUP(B90,'Ascendus Data'!$M:$M,'Ascendus Data'!$U:$U,0,0) -> 11561.33 | J90: =C90-I90 -> -0.0044
B91: 6779IV124000169 | C91: 41373.78 | D91: 827 | E91: 40546.78 | H91: =SUM(F91:G91) -> 0 | I91: =_xlfn.XLOOKUP(B91,'Ascendus Data'!$M:$M,'Ascendus Data'!$U:$U,0,0) -> 41373.78 | J91: =C91-I91 -> 0.000204
B92: 6779IV124000170 | C92: 37837.066 | D92: 757 | E92: 37080.066 | H92: =SUM(F92:G92) -> 0 | I92: =_xlfn.XLOOKUP(B92,'Ascendus Data'!$M:$M,'Ascendus Data'!$U:$U,0,0) -> 37837.07 | J92: =C92-I92 -> -0.0044
B93: 6779IV124000171 | C93: 41373.78 | D93: 827 | E93: 40546.78 | H93: =SUM(F93:G93) -> 0 | I93: =_xlfn.XLOOKUP(B93,'Ascendus Data'!$M:$M,'Ascendus Data'!$U:$U,0,0) -> 41373.78 | J93: =C93-I93 -> 0.000204
B94: 6779IV124000172 | C94: 11000 | D94: 220 | E94: 10780 | G94: 10780 | H94: =SUM(F94:G94) -> 10780 | I94: =_xlfn.XLOOKUP(B94,'Ascendus Data'!$M:$M,'Ascendus Data'!$U:$U,0,0) -> 11000 | J94: =C94-I94 -> 0
B95: 6779IV124000173 | C95: 131000.33 | D95: 13100 | E95: 117900.33 | G95: 117900.33 | H95: =SUM(F95:G95) -> 117900.33 | I95: =_xlfn.XLOOKUP(B95,'Ascendus Data'!$M:$M,'Ascendus Data'!$U:$U,0,0) -> 131000.33 | J95: =C95-I95 -> -0.00065599999
B96: 6779IV124000174 | C96: 18498.121 | D96: 370 | E96: 18128.121 | G96: 18128.12 | H96: =SUM(F96:G96) -> 18128.12 | I96: =_xlfn.XLOOKUP(B96,'Ascendus Data'!$M:$M,'Ascendus Data'!$U:$U,0,0) -> 18498.12 | J96: =C96-I96 -> 0.00096
B97: 6779IV124000175 | C97: 66198.048 | D97: 1324 | E97: 64874.048 | H97: =SUM(F97:G97) -> 0 | I97: =_xlfn.XLOOKUP(B97,'Ascendus Data'!$M:$M,'Ascendus Data'!$U:$U,0,0) -> 66198.05 | J97: =C97-I97 -> -0.0016736
B98: 6779IV124000176 | C98: 41620.772 | D98: 832 | E98: 40788.772 | H98: =SUM(F98:G98) -> 0 | I98: =_xlfn.XLOOKUP(B98,'Ascendus Data'!$M:$M,'Ascendus Data'!$U:$U,0,0) -> 41620.77 | J98: =C98-I98 -> 0.00216
B99: 6779IV124000177 | C99: 24824.268 | D99: 496 | E99: 24328.268 | H99: =SUM(F99:G99) -> 0 | I99: =_xlfn.XLOOKUP(B99,'Ascendus Data'!$M:$M,'Ascendus Data'!$U:$U,0,0) -> 24824.27 | J99: =C99-I99 -> -0.0018776
B100: 6779IV124000178 | C100: 7094.4498 | D100: 142 | E100: 6952.4498 | H100: =SUM(F100:G100) -> 0 | I100: =_xlfn.XLOOKUP(B100,'Ascendus Data'!$M:$M,'Ascendus Data'!$U:$U,0,0) -> 7094.45 | J100: =C100-I100 -> -0.0002
B101: 6779IV124000179 | C101: 13200 | D101: 264 | E101: 12936 | F101: 6468 | G101: 6468 | H101: =SUM(F101:G101) -> 12936 | I101: =_xlfn.XLOOKUP(B101,'Ascendus Data'!$M:$M,'Ascendus Data'!$U:$U,0,0) -> 13200 | J101: =C101-I101 -> 0
B102: 6779IV124000180 | C102: 262000.66 | D102: 26200 | E102: 235800.66 | G102: 235800.66 | H102: =SUM(F102:G102) -> 235800.66 | I102: =_xlfn.XLOOKUP(B102,'Ascendus Data'!$M:$M,'Ascendus Data'!$U:$U,0,0) -> 262000.66 | J102: =C102-I102 -> -0.0013120001
B103: 6779IV124000181 | C103: 18498.121 | D103: 370 | E103: 18128.121 | G103: 18128.12 | H103: =SUM(F103:G103) -> 18128.12 | I103: =_xlfn.XLOOKUP(B103,'Ascendus Data'!$M:$M,'Ascendus Data'!$U:$U,0,0) -> 18498.12 | J103: =C103-I103 -> 0.00096
B104: 6779IV124000182 | C104: 66198.048 | D104: 1324 | E104: 64874.048 | H104: =SUM(F104:G104) -> 0 | I104: =_xlfn.XLOOKUP(B104,'Ascendus Data'!$M:$M,'Ascendus Data'!$U:$U,0,0) -> 66198.05 | J104: =C104-I104 -> -0.0016736
B105: 6779IV124000183 | C105: 60539.305 | D105: 1211 | E105: 59328.305 | H105: =SUM(F105:G105) -> 0 | I105: =_xlfn.XLOOKUP(B105,'Ascendus Data'!$M:$M,'Ascendus Data'!$U:$U,0,0) -> 60539.3 | J105: =C105-I105 -> 0.00496
B106: 6779IV124000184 | C106: 18918.533 | D106: 378 | E106: 18540.533 | H106: =SUM(F106:G106) -> 0 | I106: =_xlfn.XLOOKUP(B106,'Ascendus Data'!$M:$M,'Ascendus Data'!$U:$U,0,0) -> 18918.53 | J106: =C106-I106 -> 0.0028
B107: 6779IV124000185 | C107: 66198.048 | D107: 1324 | E107: 64874.048 | H107: =SUM(F107:G107) -> 0 | I107: =_xlfn.XLOOKUP(B107,'Ascendus Data'!$M:$M,'Ascendus Data'!$U:$U,0,0) -> 66198.05 | J107: =C107-I107 -> -0.0016736
...
