Workbook

Sheet Summary
A2: Reconciliation of Ledger as on 31st January 2026
A3: Particulars | B3: Amount in USD
A4: Balance as per Siddhartha Logistics | B4: ='Customer ledger'!E158 -> 6201.493
A5: Add: TDS to be booked in Ascendus books | B5: =TDS!F154+'Payment Reco'!H8 -> 2559.2659
A6: Less: Difference in Payment recorded in both books | B6: ='Payment Reco'!I8 -> 50
A7: Add: CN and Invoices not in customer Books | B7: ='Invoices not in Customer books'!G8 -> 163.76
A8: Derived balance | B8: =SUM(B4:B7) -> 8974.5189
A9: Balance as per Ascent | B9: ='Ascendus Ledger'!K202 -> 8974.5146
A10: Difference | B10: =B8-B9 -> 0.0042622589

Sheet Invoices not in Customer books
A1: Document Number | B1: Document Type | C1: Document Date | D1: Reference | E1: Document Currency Value | F1: Company Code Currency Value | G1: Converted Value | H1: Text | I1: Remarks | J1: Status
A2: 1800001617 | B2: DR | C2: 45730 | D2: 246779412274 | E2: 100 | F2: 8669.13 | G2: 100 | H2: Intra Unit Transfer Charges Month Of August,2024 | I2: =_xlfn.XLOOKUP(D2,'Invoice Not in Customer Book'!$F:$F,'Invoice Not in Customer Book'!$N:$N,,0) -> Credit Note to be passed as discussed with CL team | J2: Done
A3: 1800013511 | B3: DR | C3: 45935 | D3: 256779418401 | E3: 62.52 | F3: 5513.69 | G3: 62.52 | H3: PORT SSR Chgs Sep 25 | I3: =_xlfn.XLOOKUP(D3,'Invoice Not in Customer Book'!$F:$F,'Invoice Not in Customer Book'!$N:$N,,0) -> to be accounted by siddhartha | J3: Pending
A4: 1800014290 | B4: DR | C4: 45966 | D4: 256779418827 | E4: 60.86 | F4: 5355.89 | G4: 60.86 | H4: WEIGHTMENT-16 -31 Oct 25 | I4: =_xlfn.XLOOKUP(D4,'Invoice Not in Customer Book'!$F:$F,'Invoice Not in Customer Book'!$N:$N,,0) -> Credit Note to be passed as discussed with CL team | J4: Done
A5: 1800013760 | B5: DR | C5: 45937 | D5: 256779418181 | E5: 49.33 | F5: 4350.45 | G5: 49.33 | H5: VAS-16-30 Sept 25 | I5: =_xlfn.XLOOKUP(D5,'Invoice Not in Customer Book'!$F:$F,'Invoice Not in Customer Book'!$N:$N,,0) -> Credit Note to be passed as discussed with CL team | J5: Done
A6: 1600002686 | B6: DG | C6: 46027 | D6: 256779422156 | E6: =G6 -> -59.62 | F6: -5410.11 | G6: -59.62 | H6: 256779418354 | I6: =_xlfn.XLOOKUP(D6,'Invoice Not in Customer Book'!$F:$F,'Invoice Not in Customer Book'!$N:$N,,0) -> #N/A | J6: Pending
A7: 1600002687 | B7: DG | C7: 46027 | D7: 256779422157 | E7: =G7 -> -49.33 | F7: -4476.36 | G7: -49.33 | H7: 256779418354 | I7: =_xlfn.XLOOKUP(D7,'Invoice Not in Customer Book'!$F:$F,'Invoice Not in Customer Book'!$N:$N,,0) -> #N/A | J7: Pending
G8: =SUM(G2:G7) -> 163.76

Sheet Ascendus Ledger
A1: Document Number | B1: Document Type | C1: Document Date | D1: Entry Date | E1: Document Header Text | F1: Reference | G1: Document Currency Key | H1: Document Currency Value | I1: Company Code Currency Key | J1: Company Code Currency Value | K1: Converted Value | L1: Xlookup | M1: TDS | N1: Text | O1: Clearing Document
A2: 1800000035 | B2: DR | C2: 45708 | D2: 45708 | E2: NA | F2: 246779410007 | G2: USD | H2: 1190.48 | I2: INR | J2: 102742.78 | K2: =_xlfn.XLOOKUP(F2,'[1]Ascendus data working'!$B:$B,'[1]Ascendus data working'!$F:$F,,0) -> 1190.48 | L2: =_xlfn.XLOOKUP(F2,'Customer ledger'!$A:$A,'Customer ledger'!$D:$D,,0) -> 1071.43 | M2: =K2-L2 -> 119.05 | N2: Fixed Rental charges for Aug 2024 | O2: 1400000805
A3: 1800000079 | B3: DR | C3: 45708 | D3: 45709 | E3: NA | F3: 246779410274 | G3: USD | H3: 1190.48 | I3: INR | J3: 102742.78 | K3: =_xlfn.XLOOKUP(F3,'[1]Ascendus data working'!$B:$B,'[1]Ascendus data working'!$F:$F,,0) -> 1190.48 | L3: =_xlfn.XLOOKUP(F3,'Customer ledger'!$A:$A,'Customer ledger'!$D:$D,,0) -> 1071.43 | M3: =K3-L3 -> 119.05 | N3: Fixed Rental charges for Oct 2024 | O3: 1400000805
A4: 1800000099 | B4: DR | C4: 45708 | D4: 45708 | E4: NA | F4: 246779410027 | G4: USD | H4: 1190.48 | I4: INR | J4: 102742.78 | K4: =_xlfn.XLOOKUP(F4,'[1]Ascendus data working'!$B:$B,'[1]Ascendus data working'!$F:$F,,0) -> 1190.48 | L4: =_xlfn.XLOOKUP(F4,'Customer ledger'!$A:$A,'Customer ledger'!$D:$D,,0) -> 1071.43 | M4: =K4-L4 -> 119.05 | N4: Fixed Rental charges for Sept 2024 | O4: 1400000805
A5: 1800000168 | B5: DR | C5: 45708 | D5: 45708 | E5: NA | F5: 246779410095 | G5: USD | H5: 1190.48 | I5: INR | J5: 102742.78 | K5: =_xlfn.XLOOKUP(F5,'[1]Ascendus data working'!$B:$B,'[1]Ascendus data working'!$F:$F,,0) -> 1190.48 | L5: =_xlfn.XLOOKUP(F5,'Customer ledger'!$A:$A,'Customer ledger'!$D:$D,,0) -> 1071.43 | M5: =K5-L5 -> 119.05 | N5: Fixed Rental charges for Nov 2024 | O5: 1400000805
A6: 1800000211 | B6: DR | C6: 45708 | D6: 45708 | E6: NA | F6: 246779410138 | G6: USD | H6: 1190.48 | I6: INR | J6: 102742.78 | K6: =_xlfn.XLOOKUP(F6,'[1]Ascendus data working'!$B:$B,'[1]Ascendus data working'!$F:$F,,0) -> 1190.48 | L6: =_xlfn.XLOOKUP(F6,'Customer ledger'!$A:$A,'Customer ledger'!$D:$D,,0) -> 1071.43 | M6: =K6-L6 -> 119.05 | N6: Fixed Rental charges for Dec 2024 | O6: 1400000805
A7: 1800000254 | B7: DR | C7: 45708 | D7: 45708 | E7: NA | F7: 246779410181 | G7: USD | H7: 1166.59 | I7: INR | J7: 100680.99 | K7: =_xlfn.XLOOKUP(F7,'[1]Ascendus data working'!$B:$B,'[1]Ascendus data working'!$F:$F,,0) -> 1166.59 | L7: =_xlfn.XLOOKUP(F7,'Customer ledger'!$A:$A,'Customer ledger'!$D:$D,,0) -> 1049.93 | M7: =K7-L7 -> 116.66 | N7: Fixed Rental charges for Jan 2025 | O7: 1400000805
A8: 1800000297 | B8: DR | C8: 45708 | D8: 45708 | E8: NA | F8: 246779410224 | G8: USD | H8: 1143.12 | I8: INR | J8: 98655.44 | K8: =_xlfn.XLOOKUP(F8,'[1]Ascendus data working'!$B:$B,'[1]Ascendus data working'!$F:$F,,0) -> 1143.12 | L8: =_xlfn.XLOOKUP(F8,'Customer ledger'!$A:$A,'Customer ledger'!$D:$D,,0) -> 1028.81 | M8: =K8-L8 -> 114.31 | N8: Fixed Rental charges for Feb 2025 | O8: 1400000805
A9: 1800000406 | B9: DR | C9: 45719 | D9: 45719 | E9: NA | F9: 246779410368 | G9: USD | H9: 356.43 | I9: INR | J9: 30899.37 | K9: =_xlfn.XLOOKUP(F9,'[1]Ascendus data working'!$B:$B,'[1]Ascendus data working'!$F:$F,,0) -> 356.43 | L9: =_xlfn.XLOOKUP(F9,'Customer ledger'!$A:$A,'Customer ledger'!$D:$D,,0) -> 320.78 | M9: =K9-L9 -> 35.65 | N9: Storage Charges for the month of August, 2024
A10: 1800000675 | B10: DR | C10: 45719 | D10: 45720 | E10: NA | F10: 246779410615 | G10: USD | H10: 9 | I10: INR | J10: 780.22 | K10: =_xlfn.XLOOKUP(F10,'[1]Ascendus data working'!$B:$B,'[1]Ascendus data working'!$F:$F,,0) -> 9 | L10: =_xlfn.XLOOKUP(F10,'Customer ledger'!$A:$A,'Customer ledger'!$D:$D,,0) -> 8.81 | M10: =K10-L10 -> 0.19 | N10: Outbound Handling for Sep 2024
A11: 1800000432 | B11: DR | C11: 45719 | D11: 45719 | E11: NA | F11: 246779410394 | G11: USD | H11: 505.86 | I11: INR | J11: 43853.64 | K11: =_xlfn.XLOOKUP(F11,'[1]Ascendus data working'!$B:$B,'[1]Ascendus data working'!$F:$F,,0) -> 505.86 | L11: =_xlfn.XLOOKUP(F11,'Customer ledger'!$A:$A,'Customer ledger'!$D:$D,,0) -> 455.27 | M11: =K11-L11 -> 50.59 | N11: Storage for the month of Sep 2024 Exch Rate 83.79
A12: 1800000456 | B12: DR | C12: 45719 | D12: 45719 | E12: NA | F12: 246779410418 | G12: USD | H12: 562.6 | I12: INR | J12: 48772.5 | K12: =_xlfn.XLOOKUP(F12,'[1]Ascendus data working'!$B:$B,'[1]Ascendus data working'!$F:$F,,0) -> 562.6 | L12: =_xlfn.XLOOKUP(F12,'Customer ledger'!$A:$A,'Customer ledger'!$D:$D,,0) -> 506.34 | M12: =K12-L12 -> 56.26 | N12: Storage for the month of Oct 2024
A13: 1800000559 | B13: DR | C13: 45719 | D13: 45719 | E13: NA | F13: 246779410509 | G13: USD | H13: 29.25 | I13: INR | J13: 2535.72 | K13: =_xlfn.XLOOKUP(F13,'[1]Ascendus data working'!$B:$B,'[1]Ascendus data working'!$F:$F,,0) -> 29.25 | L13: =_xlfn.XLOOKUP(F13,'Customer ledger'!$A:$A,'Customer ledger'!$D:$D,,0) -> 28.66 | M13: =K13-L13 -> 0.59 | N13: Outbound Handling for Aug 2024
A14: 1800000560 | B14: DR | C14: 45719 | D14: 45719 | E14: NA | F14: 246779410510 | G14: USD | H14: 194.9 | I14: INR | J14: 16896.13 | K14: =_xlfn.XLOOKUP(F14,'[1]Ascendus data working'!$B:$B,'[1]Ascendus data working'!$F:$F,,0) -> 194.9 | L14: =_xlfn.XLOOKUP(F14,'Customer ledger'!$A:$A,'Customer ledger'!$D:$D,,0) -> 191 | M14: =K14-L14 -> 3.9 | N14: Outbound Handling for Aug 2024
A15: 1800000561 | B15: DR | C15: 45719 | D15: 45719 | E15: NA | F15: 246779410511 | G15: USD | H15: 13.91 | I15: INR | J15: 1205.88 | K15: =_xlfn.XLOOKUP(F15,'[1]Ascendus data working'!$B:$B,'[1]Ascendus data working'!$F:$F,,0) -> 13.91 | L15: =_xlfn.XLOOKUP(F15,'Customer ledger'!$A:$A,'Customer ledger'!$D:$D,,0) -> 13.63 | M15: =K15-L15 -> 0.28 | N15: Outbound Handling for Aug 2024
A16: 1800000674 | B16: DR | C16: 45719 | D16: 45720 | E16: NA | F16: 246779410614 | G16: USD | H16: 2.25 | I16: INR | J16: 195.06 | K16: =_xlfn.XLOOKUP(F16,'[1]Ascendus data working'!$B:$B,'[1]Ascendus data working'!$F:$F,,0) -> 2.25 | L16: =_xlfn.XLOOKUP(F16,'Customer ledger'!$A:$A,'Customer ledger'!$D:$D,,0) -> 2.2 | M16: =K16-L16 -> 0.05 | N16: Outbound Handling for Sep 2024
A17: 1800000754 | B17: DR | C17: 45720 | D17: 45720 | E17: NA | F17: 246779410694 | G17: USD | H17: 59.36 | I17: INR | J17: 5145.99 | K17: =_xlfn.XLOOKUP(F17,'[1]Ascendus data working'!$B:$B,'[1]Ascendus data working'!$F:$F,,0) -> 59.36 | L17: =_xlfn.XLOOKUP(F17,'Customer ledger'!$A:$A,'Customer ledger'!$D:$D,,0) -> 58.17 | M17: =K17-L17 -> 1.19 | N17: Outbound Handling for Oct 2024
A18: 1800000915 | B18: DR | C18: 45720 | D18: 45721 | E18: NA | F18: 246779410856 | G18: USD | H18: 18.32 | I18: INR | J18: 1588.18 | K18: =_xlfn.XLOOKUP(F18,'[1]Ascendus data working'!$B:$B,'[1]Ascendus data working'!$F:$F,,0) -> 18.32 | L18: =_xlfn.XLOOKUP(F18,'Customer ledger'!$A:$A,'Customer ledger'!$D:$D,,0) -> 17.95 | M18: =K18-L18 -> 0.37 | N18: Outbound Handling for Dec 2024
A19: 1800000948 | B19: DR | C19: 45722 | D19: 45722 | E19: NA | F19: 246779410888 | G19: USD | H19: 446.38 | I19: INR | J19: 38697.24 | K19: =_xlfn.XLOOKUP(F19,'[1]Ascendus data working'!$B:$B,'[1]Ascendus data working'!$F:$F,,0) -> 446.38 | L19: =_xlfn.XLOOKUP(F19,'Customer ledger'!$A:$A,'Customer ledger'!$D:$D,,0) -> 401.74 | M19: =K19-L19 -> 44.64 | N19: Storage Charges for the month of December, 2024 Ex
A20: 1800000925 | B20: DR | C20: 45722 | D20: 45722 | E20: NA | F20: 246779410865 | G20: USD | H20: 412.11 | I20: INR | J20: 35726.34 | K20: =_xlfn.XLOOKUP(F20,'[1]Ascendus data working'!$B:$B,'[1]Ascendus data working'!$F:$F,,0) -> 412.11 | L20: =_xlfn.XLOOKUP(F20,'Customer ledger'!$A:$A,'Customer ledger'!$D:$D,,0) -> 370.9 | M20: =K20-L20 -> 41.21 | N20: Storage Charges for the month of November, 2024 Ex
... A35: 1800001791 | B35: DR | C35: 45730 | D35: 45733 | E35: NA | F35: 246779411456 | G35: USD | H35: 4.77 | I35: INR | J35: 413.52 | K35: =_xlfn.XLOOKUP(F35,'[1]Ascendus data working'!$B:$B,'[1]Ascendus data working'!$F:$F,,0) -> 4.77 | L35: =_xlfn.XLOOKUP(F35,'Customer ledger'!$A:$A,'Customer ledger'!$D:$D,,0) -> #N/A | M35: =K35-L35 -> #N/A | N35: VAS Activity Charges for the month of August, 24
A36: 1800001583 | B36: DR | C36: 45730 | D36: 45735 | E36: NA | F36: 246779412240 | G36: USD | H36: 2.86 | I36: INR | J36: 247.94 | K36: =_xlfn.XLOOKUP(F36,'[1]Ascendus data working'!$B:$B,'[1]Ascendus data working'!$F:$F,,0) -> 2.86 | L36: =_xlfn.XLOOKUP(F36,'Customer ledger'!$A:$A,'Customer ledger'!$D:$D,,0) -> 2.8 | M36: =K36-L36 -> 0.06 | N36: VAS Activity Charges for the month of August, 24 | O36: 1400000797
A37: 1800001584 | B37: DR | C37: 45730 | D37: 45735 | E37: NA | F37: 246779412241 | G37: USD | H37: 0.95 | I37: INR | J37: 82.36 | K37: =_xlfn.XLOOKUP(F37,'[1]Ascendus data working'!$B:$B,'[1]Ascendus data working'!$F:$F,,0) -> 0.95 | L37: =_xlfn.XLOOKUP(F37,'Customer ledger'!$A:$A,'Customer ledger'!$D:$D,,0) -> #N/A | M37: =K37-L37 -> #N/A | N37: VAS Activity Charges for the month of August, 24 | O37: 1400000797
A38: 1800001585 | B38: DR | C38: 45730 | D38: 45735 | E38: NA | F38: 246779412242 | G38: USD | H38: 4.77 | I38: INR | J38: 413.52 | K38: =_xlfn.XLOOKUP(F38,'[1]Ascendus data working'!$B:$B,'[1]Ascendus data working'!$F:$F,,0) -> 4.77 | L38: =_xlfn.XLOOKUP(F38,'Customer ledger'!$A:$A,'Customer ledger'!$D:$D,,0) -> 4.67 | M38: =K38-L38 -> 0.1 | N38: VAS Activity Charges for the month of August, 24 | O38: 1400000797
A39: 1800001586 | B39: DR | C39: 45730 | D39: 45735 | E39: NA | F39: 246779412243 | G39: USD | H39: 1.91 | I39: INR | J39: 165.58 | K39: =_xlfn.XLOOKUP(F39,'[1]Ascendus data working'!$B:$B,'[1]Ascendus data working'!$F:$F,,0) -> 1.91 | L39: =_xlfn.XLOOKUP(F39,'Customer ledger'!$A:$A,'Customer ledger'!$D:$D,,0) -> 1.87 | M39: =K39-L39 -> 0.04 | N39: VAS Activity Charges for the month of August, 24 | O39: 1400000797
A40: 1800001587 | B40: DR | C40: 45730 | D40: 45735 | E40: NA | F40: 246779412244 | G40: USD | H40: 1.91 | I40: INR | J40: 165.58 | K40: =_xlfn.XLOOKUP(F40,'[1]Ascendus data working'!$B:$B,'[1]Ascendus data working'!$F:$F,,0) -> 1.91 | L40: =_xlfn.XLOOKUP(F40,'Customer ledger'!$A:$A,'Customer ledger'!$D:$D,,0) -> 1.87 | M40: =K40-L40 -> 0.04 | N40: VAS Activity Charges for the month of August, 24 | O40: 1400000797
A41: 1800001588 | B41: DR | C41: 45730 | D41: 45735 | E41: NA | F41: 246779412245 | G41: USD | H41: 4.77 | I41: INR | J41: 413.52 | K41: =_xlfn.XLOOKUP(F41,'[1]Ascendus data working'!$B:$B,'[1]Ascendus data working'!$F:$F,,0) -> 4.77 | L41: =_xlfn.XLOOKUP(F41,'Customer ledger'!$A:$A,'Customer ledger'!$D:$D,,0) -> 4.68 | M41: =K41-L41 -> 0.09 | N41: VAS Activity Charges for the month of August, 24 | O41: 1400000797
A42: 1800001957 | B42: DR | C42: 45733 | D42: 45733 | E42: NA | F42: 246779411622 | G42: USD | H42: 3.82 | I42: INR | J42: 331.16 | K42: =_xlfn.XLOOKUP(F42,'[1]Ascendus data working'!$B:$B,'[1]Ascendus data working'!$F:$F,,0) -> 3.82 | L42: =_xlfn.XLOOKUP(F42,'Customer ledger'!$A:$A,'Customer ledger'!$D:$D,,0) -> 3.74 | M42: =K42-L42 -> 0.08 | N42: VAS Activity Charges for the month of September, 2
A43: 1800001958 | B43: DR | C43: 45733 | D43: 45733 | E43: NA | F43: 246779411623 | G43: USD | H43: 1.91 | I43: INR | J43: 165.58 | K43: =_xlfn.XLOOKUP(F43,'[1]Ascendus data working'!$B:$B,'[1]Ascendus data working'!$F:$F,,0) -> 1.91 | L43: =_xlfn.XLOOKUP(F43,'Customer ledger'!$A:$A,'Customer ledger'!$D:$D,,0) -> 1.87 | M43: =K43-L43 -> 0.04 | N43: VAS Activity Charges for the month of September, 2
A44: 1800003125 | B44: DR | C44: 45735 | D44: 45736 | E44: NA | F44: 246779412992 | G44: USD | H44: 1148.63 | I44: INR | J44: 99576.18 | K44: =_xlfn.XLOOKUP(F44,'[1]Ascendus data working'!$B:$B,'[1]Ascendus data working'!$F:$F,,0) -> 1148.63 | L44: =_xlfn.XLOOKUP(F44,'Customer ledger'!$A:$A,'Customer ledger'!$D:$D,,0) -> 1033.77 | M44: =K44-L44 -> 114.86 | N44: Fixed Storage Charges for Mar 2025
A45: 1800004097 | B45: DR | C45: 45736 | D45: 45737 | E45: NA | F45: 246779413953 | G45: USD | H45: 3 | I45: INR | J45: 260.07 | K45: =_xlfn.XLOOKUP(F45,'[1]Ascendus data working'!$B:$B,'[1]Ascendus data working'!$F:$F,,0) -> 3 | L45: =_xlfn.XLOOKUP(F45,'Customer ledger'!$A:$A,'Customer ledger'!$D:$D,,0) -> 2.94 | M45: =K45-L45 -> 0.06 | N45: Outbound Handling charges for Feb 2025
A46: 1800004357 | B46: DR | C46: 45736 | D46: 45737 | E46: NA | F46: 246779414225 | G46: USD | H46: 13.5 | I46: INR | J46: 1170.33 | K46: =_xlfn.XLOOKUP(F46,'[1]Ascendus data working'!$B:$B,'[1]Ascendus data working'!$F:$F,,0) -> 13.5 | L46: =_xlfn.XLOOKUP(F46,'Customer ledger'!$A:$A,'Customer ledger'!$D:$D,,0) -> 13.23 | M46: =K46-L46 -> 0.27 | N46: Outbound Handling charges for Sep 2024
A47: 1800004532 | B47: DR | C47: 45736 | D47: 45737 | E47: NA | F47: 246779414400 | G47: USD | H47: 80.95 | I47: INR | J47: 7017.66 | K47: =_xlfn.XLOOKUP(F47,'[1]Ascendus data working'!$B:$B,'[1]Ascendus data working'!$F:$F,,0) -> 80.95 | L47: =_xlfn.XLOOKUP(F47,'Customer ledger'!$A:$A,'Customer ledger'!$D:$D,,0) -> 79.33 | M47: =K47-L47 -> 1.62 | N47: Inbound Handling charges for Nov 2024
A48: 1800004533 | B48: DR | C48: 45736 | D48: 45737 | E48: NA | F48: 246779414401 | G48: USD | H48: 15 | I48: INR | J48: 1300.37 | K48: =_xlfn.XLOOKUP(F48,'[1]Ascendus data working'!$B:$B,'[1]Ascendus data working'!$F:$F,,0) -> 15 | L48: =_xlfn.XLOOKUP(F48,'Customer ledger'!$A:$A,'Customer ledger'!$D:$D,,0) -> 14.7 | M48: =K48-L48 -> 0.3 | N48: LCL Movement Charges for Nov 2024
A49: 1800004870 | B49: DR | C49: 45736 | D49: 45737 | E49: NA | F49: 246779414738 | G49: USD | H49: 2.25 | I49: INR | J49: 195.06 | K49: =_xlfn.XLOOKUP(F49,'[1]Ascendus data working'!$B:$B,'[1]Ascendus data working'!$F:$F,,0) -> 2.25 | L49: =_xlfn.XLOOKUP(F49,'Customer ledger'!$A:$A,'Customer ledger'!$D:$D,,0) -> 2.2 | M49: =K49-L49 -> 0.05 | N49: Outbound Handling charges for Jan 2025
A50: 1800004871 | B50: DR | C50: 45736 | D50: 45737 | E50: NA | F50: 246779414739 | G50: USD | H50: 0.75 | I50: INR | J50: 65.02 | K50: =_xlfn.XLOOKUP(F50,'[1]Ascendus data working'!$B:$B,'[1]Ascendus data working'!$F:$F,,0) -> 0.75 | L50: =_xlfn.XLOOKUP(F50,'Customer ledger'!$A:$A,'Customer ledger'!$D:$D,,0) -> 0.73 | M50: =K50-L50 -> 0.02 | N50: Loose Loading Handling charges for Jan 2025
A51: 1800004926 | B51: DR | C51: 45736 | D51: 45737 | E51: NA | F51: 246779414794 | G51: USD | H51: 2.25 | I51: INR | J51: 195.06 | K51: =_xlfn.XLOOKUP(F51,'[1]Ascendus data working'!$B:$B,'[1]Ascendus data working'!$F:$F,,0) -> 2.25 | L51: =_xlfn.XLOOKUP(F51,'Customer ledger'!$A:$A,'Customer ledger'!$D:$D,,0) -> 2.2 | M51: =K51-L51 -> 0.05 | N51: Outbound Handling charges for Feb 2025
A52: 1800004927 | B52: DR | C52: 45736 | D52: 45737 | E52: NA | F52: 246779414795 | G52: USD | H52: 0.75 | I52: INR | J52: 65.02 | K52: =_xlfn.XLOOKUP(F52,'[1]Ascendus data working'!$B:$B,'[1]Ascendus data working'!$F:$F,,0) -> 0.75 | L52: =_xlfn.XLOOKUP(F52,'Customer ledger'!$A:$A,'Customer ledger'!$D:$D,,0) -> 0.73 | M52: =K52-L52 -> 0.02 | N52: Loose handling Charges for Feb 2025
A53: 1800004739 | B53: DR | C53: 45736 | D53: 45737 | E53: NA | F53: 246779414607 | G53: USD | H53: 2.25 | I53: INR | J53: 195.06 | K53: =_xlfn.XLOOKUP(F53,'[1]Ascendus data working'!$B:$B,'[1]Ascendus data working'!$F:$F,,0) -> 2.25 | L53: =_xlfn.XLOOKUP(F53,'Customer ledger'!$A:$A,'Customer ledger'!$D:$D,,0) -> 2.2 | M53: =K53-L53 -> 0.05 | N53: Outbound Handling charges for Oct 2024
... A56: 1800005192 | B56: DR | C56: 45750 | D56: 45752 | E56: NA | F56: 256779410138 | G56: USD | H56: 1.5 | I56: INR | J56: 130.38 | K56: =_xlfn.XLOOKUP(F56,'[1]Ascendus data working'!$B:$B,'[1]Ascendus data working'!$F:$F,,0) -> 1.5 | L56: =_xlfn.XLOOKUP(F56,'Customer ledger'!$A:$A,'Customer ledger'!$D:$D,,0) -> 1.47 | M56: =K56-L56 -> 0.03 | N56: Loose loading Handling charges for Mar 25
A57: 1800005336 | B57: DR | C57: 45750 | D57: 45752 | E57: NA | F57: 256779410228 | G57: USD | H57: 1166.59 | I57: INR | J57: 101402.13 | K57: =_xlfn.XLOOKUP(F57,'[1]Ascendus data working'!$B:$B,'[1]Ascendus data working'!$F:$F,,0) -> 1166.59 | L57: =_xlfn.XLOOKUP(F57,'Customer ledger'!$A:$A,'Customer ledger'!$D:$D,,0) -> #N/A | M57: =K57-L57 -> #N/A | N57: Fixed Rental charges for Jan 2025 | O57: 1400000797
A58: 1800005377 | B58: DR | C58: 45750 | D58: 45752 | E58: NA | F58: 256779410269 | G58: USD | H58: 1143.12 | I58: INR | J58: 99362.07 | K58: =_xlfn.XLOOKUP(F58,'[1]Ascendus data working'!$B:$B,'[1]Ascendus data working'!$F:$F,,0) -> 1143.12 | L58: =_xlfn.XLOOKUP(F58,'Customer ledger'!$A:$A,'Customer ledger'!$D:$D,,0) -> #N/A | M58: =K58-L58 -> #N/A | N58: Fixed Rental charges for Feb 2025 | O58: 1400000797
A59: 1800005899 | B59: DR | C59: 45751 | D59: 45752 | E59: NA | F59: 256779410791 | G59: USD | H59: 441.2 | I59: INR | J59: 38349.91 | K59: =_xlfn.XLOOKUP(F59,'[1]Ascendus data working'!$B:$B,'[1]Ascendus data working'!$F:$F,,0) -> 441.2 | L59: =_xlfn.XLOOKUP(F59,'Customer ledger'!$A:$A,'Customer ledger'!$D:$D,,0) -> 397.08 | M59: =K59-L59 -> 44.12 | N59: Storage Charges Feb, 25 Exch Rate 87.4
A60: 1800005916 | B60: DR | C60: 45751 | D60: 45752 | E60: NA | F60: 256779410807 | G60: USD | H60: 742.7 | I60: INR | J60: 64556.84 | K60: =_xlfn.XLOOKUP(F60,'[1]Ascendus data working'!$B:$B,'[1]Ascendus data working'!$F:$F,,0) -> 742.7 | L60: =_xlfn.XLOOKUP(F60,'Customer ledger'!$A:$A,'Customer ledger'!$D:$D,,0) -> 668.43 | M60: =K60-L60 -> 74.27 | N60: Storage Charges Jan, 25 Exch Rate 86.64
A61: 1800006269 | B61: DR | C61: 45762 | D61: 45763 | E61: NA | F61: 256779411160 | G61: USD | H61: 18.38 | I61: INR | J61: 1597.62 | K61: =_xlfn.XLOOKUP(F61,'[1]Ascendus data working'!$B:$B,'[1]Ascendus data working'!$F:$F,,0) -> 18.38 | L61: =_xlfn.XLOOKUP(F61,'Customer ledger'!$A:$A,'Customer ledger'!$D:$D,,0) -> 18.01 | M61: =K61-L61 -> 0.37 | N61: LCL Charges August 2024
A62: 1800006270 | B62: DR | C62: 45762 | D62: 45763 | E62: NA | F62: 256779411161 | G62: USD | H62: 46.76 | I62: INR | J62: 4064.46 | K62: =_xlfn.XLOOKUP(F62,'[1]Ascendus data working'!$B:$B,'[1]Ascendus data working'!$F:$F,,0) -> 46.76 | L62: =_xlfn.XLOOKUP(F62,'Customer ledger'!$A:$A,'Customer ledger'!$D:$D,,0) -> 45.82 | M62: =K62-L62 -> 0.94 | N62: Inbound Handling for August 24
A63: 1800006271 | B63: DR | C63: 45762 | D63: 45763 | E63: NA | F63: 256779411162 | G63: USD | H63: 35.25 | I63: INR | J63: 3063.99 | K63: =_xlfn.XLOOKUP(F63,'[1]Ascendus data working'!$B:$B,'[1]Ascendus data working'!$F:$F,,0) -> 35.25 | L63: =_xlfn.XLOOKUP(F63,'Customer ledger'!$A:$A,'Customer ledger'!$D:$D,,0) -> 34.54 | M63: =K63-L63 -> 0.71 | N63: LCL Charges August 2024
A64: 1800006272 | B64: DR | C64: 45762 | D64: 45763 | E64: NA | F64: 256779411163 | G64: USD | H64: 24 | I64: INR | J64: 2086.12 | K64: =_xlfn.XLOOKUP(F64,'[1]Ascendus data working'!$B:$B,'[1]Ascendus data working'!$F:$F,,0) -> 24 | L64: =_xlfn.XLOOKUP(F64,'Customer ledger'!$A:$A,'Customer ledger'!$D:$D,,0) -> 23.52 | M64: =K64-L64 -> 0.48 | N64: LCL Charges August 2024
A65: 1800006273 | B65: DR | C65: 45762 | D65: 45763 | E65: NA | F65: 256779411164 | G65: USD | H65: 33 | I65: INR | J65: 2868.42 | K65: =_xlfn.XLOOKUP(F65,'[1]Ascendus data working'!$B:$B,'[1]Ascendus data working'!$F:$F,,0) -> 33 | L65: =_xlfn.XLOOKUP(F65,'Customer ledger'!$A:$A,'Customer ledger'!$D:$D,,0) -> 32.34 | M65: =K65-L65 -> 0.66 | N65: LCL Charges August 2024
A66: 1800006696 | B66: DR | C66: 45762 | D66: 45763 | E66: NA | F66: 256779411587 | G66: USD | H66: 2.25 | I66: INR | J66: 195.57 | K66: =_xlfn.XLOOKUP(F66,'[1]Ascendus data working'!$B:$B,'[1]Ascendus data working'!$F:$F,,0) -> 2.25 | L66: =_xlfn.XLOOKUP(F66,'Customer ledger'!$A:$A,'Customer ledger'!$D:$D,,0) -> 2.2 | M66: =K66-L66 -> 0.05 | N66: Outbound Handling Charges Aug 2024
A67: 1800006697 | B67: DR | C67: 45762 | D67: 45763 | E67: NA | F67: 256779411588 | G67: USD | H67: 2.25 | I67: INR | J67: 195.57 | K67: =_xlfn.XLOOKUP(F67,'[1]Ascendus data working'!$B:$B,'[1]Ascendus data working'!$F:$F,,0) -> 2.25 | L67: =_xlfn.XLOOKUP(F67,'Customer ledger'!$A:$A,'Customer ledger'!$D:$D,,0) -> 2.2 | M67: =K67-L67 -> 0.05 | N67: Outbound Handling Charges Aug 2024
A68: 1800006698 | B68: DR | C68: 45762 | D68: 45763 | E68: NA | F68: 256779411589 | G68: USD | H68: 3.38 | I68: INR | J68: 293.8 | K68: =_xlfn.XLOOKUP(F68,'[1]Ascendus data working'!$B:$B,'[1]Ascendus data working'!$F:$F,,0) -> 3.38 | L68: =_xlfn.XLOOKUP(F68,'Customer ledger'!$A:$A,'Customer ledger'!$D:$D,,0) -> 3.31 | M68: =K68-L68 -> 0.07 | N68: Outbound Handling Charges Aug 2024
A69: 1800006699 | B69: DR | C69: 45762 | D69: 45763 | E69: NA | F69: 256779411590 | G69: USD | H69: 2.25 | I69: INR | J69: 195.57 | K69: =_xlfn.XLOOKUP(F69,'[1]Ascendus data working'!$B:$B,'[1]Ascendus data working'!$F:$F,,0) -> 2.25 | L69: =_xlfn.XLOOKUP(F69,'Customer ledger'!$A:$A,'Customer ledger'!$D:$D,,0) -> 2.2 | M69: =K69-L69 -> 0.05 | N69: Outbound Handling Charges Aug 2024
A70: 1800006700 | B70: DR | C70: 45762 | D70: 45763 | E70: NA | F70: 256779411591 | G70: USD | H70: 3 | I70: INR | J70: 260.77 | K70: =_xlfn.XLOOKUP(F70,'[1]Ascendus data working'!$B:$B,'[1]Ascendus data working'!$F:$F,,0) -> 3 | L70: =_xlfn.XLOOKUP(F70,'Customer ledger'!$A:$A,'Customer ledger'!$D:$D,,0) -> 2.94 | M70: =K70-L70 -> 0.06 | N70: Outbound Handling Charges Aug 2024
... A87: 1800008258 | B87: DR | C87: 45787 | D87: 45791 | E87: NA | F87: 256779413142 | G87: USD | H87: 100000 | I87: INR | J87: 100000 | K87: =_xlfn.XLOOKUP(F87,'[1]Ascendus data working'!$B:$B,'[1]Ascendus data working'!$F:$F,,0) -> 1162.7907 | L87: =_xlfn.XLOOKUP(F87,'Customer ledger'!$A:$A,'Customer ledger'!$D:$D,,0) -> 1046.71 | M87: =K87-L87 -> 116.0807 | N87: Fixed Storage Charges fo MAY 2025
A88: 1600000602 | B88: DG | C88: 45791 | D88: 45793 | E88: NA | F88: 256779420311 | G88: USD | H88: -1.91 | I88: INR | J88: -165.58 | K88: =_xlfn.XLOOKUP(F88,'[1]Ascendus data working'!$B:$B,'[1]Ascendus data working'!$F:$F,,0) -> -1.91 | L88: =_xlfn.XLOOKUP(F88,'Customer ledger'!$A:$A,'Customer ledger'!$D:$D,,0) -> #N/A | M88: =K88-L88 -> #N/A | N88: Credit note against 246779412244 | O88: 1400000797
A89: 1600000598 | B89: DG | C89: 45791 | D89: 45793 | E89: NA | F89: 256779420307 | G89: USD | H89: -2.86 | I89: INR | J89: -247.94 | K89: =_xlfn.XLOOKUP(F89,'[1]Ascendus data working'!$B:$B,'[1]Ascendus data working'!$F:$F,,0) -> -2.86 | L89: =_xlfn.XLOOKUP(F89,'Customer ledger'!$A:$A,'Customer ledger'!$D:$D,,0) -> #N/A | M89: =K89-L89 -> #N/A | N89: Credit note against 246779412240 | O89: 1400000797
A90: 1600000599 | B90: DG | C90: 45791 | D90: 45793 | E90: NA | F90: 256779420308 | G90: USD | H90: -0.95 | I90: INR | J90: -82.36 | K90: =_xlfn.XLOOKUP(F90,'[1]Ascendus data working'!$B:$B,'[1]Ascendus data working'!$F:$F,,0) -> -0.95 | L90: =_xlfn.XLOOKUP(F90,'Customer ledger'!$A:$A,'Customer ledger'!$D:$D,,0) -> #N/A | M90: =K90-L90 -> #N/A | N90: Credit note against 246779412241 | O90: 1400000797
A91: 1600000600 | B91: DG | C91: 45791 | D91: 45793 | E91: NA | F91: 256779420309 | G91: USD | H91: -4.77 | I91: INR | J91: -413.52 | K91: =_xlfn.XLOOKUP(F91,'[1]Ascendus data working'!$B:$B,'[1]Ascendus data working'!$F:$F,,0) -> -4.77 | L91: =_xlfn.XLOOKUP(F91,'Customer ledger'!$A:$A,'Customer ledger'!$D:$D,,0) -> #N/A | M91: =K91-L91 -> #N/A | N91: Credit note against 246779412242 | O91: 1400000797
A92: 1600000601 | B92: DG | C92: 45791 | D92: 45793 | E92: NA | F92: 256779420310 | G92: USD | H92: -1.91 | I92: INR | J92: -165.58 | K92: =_xlfn.XLOOKUP(F92,'[1]Ascendus data working'!$B:$B,'[1]Ascendus data working'!$F:$F,,0) -> -1.91 | L92: =_xlfn.XLOOKUP(F92,'Customer ledger'!$A:$A,'Customer ledger'!$D:$D,,0) -> #N/A | M92: =K92-L92 -> #N/A | N92: Credit note against 246779412243 | O92: 1400000797
A93: 1600000603 | B93: DG | C93: 45791 | D93: 45793 | E93: NA | F93: 256779420312 | G93: USD | H93: -4.77 | I93: INR | J93: -413.52 | K93: =_xlfn.XLOOKUP(F93,'[1]Ascendus data working'!$B:$B,'[1]Ascendus data working'!$F:$F,,0) -> -4.77 | L93: =_xlfn.XLOOKUP(F93,'Customer ledger'!$A:$A,'Customer ledger'!$D:$D,,0) -> #N/A | M93: =K93-L93 -> #N/A | N93: Credit note against 246779412245 | O93: 1400000797
A94: 1600000780 | B94: DG | C94: 45791 | D94: 45793 | E94: NA | F94: 256779420489 | G94: USD | H94: -1166.59 | I94: INR | J94: -101402.13 | K94: =_xlfn.XLOOKUP(F94,'[1]Ascendus data working'!$B:$B,'[1]Ascendus data working'!$F:$F,,0) -> -1166.59 | L94: =_xlfn.XLOOKUP(F94,'Customer ledger'!$A:$A,'Customer ledger'!$D:$D,,0) -> #N/A | M94: =K94-L94 -> #N/A | N94: Credit note against 256779410228 | O94: 1400000797
A95: 1600000814 | B95: DG | C95: 45791 | D95: 45793 | E95: NA | F95: 256779420523 | G95: USD | H95: -1143.12 | I95: INR | J95: -99362.07 | K95: =_xlfn.XLOOKUP(F95,'[1]Ascendus data working'!$B:$B,'[1]Ascendus data working'!$F:$F,,0) -> -1143.12 | L95: =_xlfn.XLOOKUP(F95,'Customer ledger'!$A:$A,'Customer ledger'!$D:$D,,0) -> #N/A | M95: =K95-L95 -> #N/A | N95: Credit note against 256779410269 | O95: 1400000797
A96: 1800008504 | B96: DR | C96: 45793 | D96: 45800 | E96: NA | F96: 256779413272 | G96: USD | H96: 25.28 | I96: INR | J96: 2173.67 | K96: =_xlfn.XLOOKUP(F96,'[1]Ascendus data working'!$B:$B,'[1]Ascendus data working'!$F:$F,,0) -> 25.28 | L96: =_xlfn.XLOOKUP(F96,'Customer ledger'!$A:$A,'Customer ledger'!$D:$D,,0) -> 24.77 | M96: =K96-L96 -> 0.51 | N96: Empty Lolo Chgs - 01 - 31 Apr 25
A97: 1800008597 | B97: DR | C97: 45793 | D97: 45800 | E97: NA | F97: 256779413361 | G97: USD | H97: 3 | I97: INR | J97: 257.95 | K97: =_xlfn.XLOOKUP(F97,'[1]Ascendus data working'!$B:$B,'[1]Ascendus data working'!$F:$F,,0) -> 3 | L97: =_xlfn.XLOOKUP(F97,'Customer ledger'!$A:$A,'Customer ledger'!$D:$D,,0) -> 2.94 | M97: =K97-L97 -> 0.06 | N97: Outbound chgs - 16 - 30 Apr 25
A98: 1800008726 | B98: DR | C98: 45797 | D98: 45805 | E98: NA | F98: 256779413490 | G98: USD | H98: 3 | I98: INR | J98: 257.95 | K98: =_xlfn.XLOOKUP(F98,'[1]Ascendus data working'!$B:$B,'[1]Ascendus data working'!$F:$F,,0) -> 3 | L98: =_xlfn.XLOOKUP(F98,'Customer ledger'!$A:$A,'Customer ledger'!$D:$D,,0) -> 2.94 | M98: =K98-L98 -> 0.06 | N98: Outbound chgs - 01 - 15 MAY 25
A99: 1800009129 | B99: DR | C99: 45805 | D99: 45805 | E99: NA | F99: 256779413893 | G99: USD | H99: 797.57 | I99: INR | J99: 68578.02 | K99: =_xlfn.XLOOKUP(F99,'[1]Ascendus data working'!$B:$B,'[1]Ascendus data working'!$F:$F,,0) -> 797.57 | L99: =_xlfn.XLOOKUP(F99,'Customer ledger'!$A:$A,'Customer ledger'!$D:$D,,0) -> 717.81 | M99: =K99-L99 -> 79.76 | N99: Storage Chgs - 01 - 31 Apr 25
A100: 1800009239 | B100: DR | C100: 45812 | D100: 45817 | E100: NA | F100: 256779414003 | G100: USD | H100: 807.39 | I100: INR | J100: 69024.4 | K100: =_xlfn.XLOOKUP(F100,'[1]Ascendus data working'!$B:$B,'[1]Ascendus data working'!$F:$F,,0) -> 807.39 | L100: =_xlfn.XLOOKUP(F100,'Customer ledger'!$A:$A,'Customer ledger'!$D:$D,,0) -> 726.65 | M100: =K100-L100 -> 80.74 | N100: Storage- Aug-24,
A101: 1800009240 | B101: DR | C101: 45812 | D101: 45817 | E101: NA | F101: 256779414004 | G101: USD | H101: 808.16 | I101: INR | J101: 69090.23 | K101: =_xlfn.XLOOKUP(F101,'[1]Ascendus data working'!$B:$B,'[1]Ascendus data working'!$F:$F,,0) -> 808.16 | L101: =_xlfn.XLOOKUP(F101,'Customer ledger'!$A:$A,'Customer ledger'!$D:$D,,0) -> 727.34 | M101: =K101-L101 -> 80.82 | N101: Storage- Sept-24,
A102: 1800009241 | B102: DR | C102: 45812 | D102: 45817 | E102: NA | F102: 256779414005 | G102: USD | H102: 805.28 | I102: INR | J102: 68844.02 | K102: =_xlfn.XLOOKUP(F102,'[1]Ascendus data working'!$B:$B,'[1]Ascendus data working'!$F:$F,,0) -> 805.28 | L102: =_xlfn.XLOOKUP(F102,'Customer ledger'!$A:$A,'Customer ledger'!$D:$D,,0) -> 724.75 | M102: =K102-L102 -> 80.53 | N102: Storage - Oct-24,
A103: 1800009242 | B103: DR | C103: 45812 | D103: 45817 | E103: NA | F103: 256779414006 | G103: USD | H103: 801.47 | I103: INR | J103: 68518.3 | K103: =_xlfn.XLOOKUP(F103,'[1]Ascendus data working'!$B:$B,'[1]Ascendus data working'!$F:$F,,0) -> 801.47 | L103: =_xlfn.XLOOKUP(F103,'Customer ledger'!$A:$A,'Customer ledger'!$D:$D,,0) -> 721.32 | M103: =K103-L103 -> 80.15 | N103: Storage- Nov-24,
A104: 1800009243 | B104: DR | C104: 45812 | D104: 45817 | E104: NA | F104: 256779414007 | G104: USD | H104: 790.89 | I104: INR | J104: 67613.8 | K104: =_xlfn.XLOOKUP(F104,'[1]Ascendus data working'!$B:$B,'[1]Ascendus data working'!$F:$F,,0) -> 790.89 | L104: =_xlfn.XLOOKUP(F104,'Customer ledger'!$A:$A,'Customer ledger'!$D:$D,,0) -> 711.8 | M104: =K104-L104 -> 79.09 | N104: Storage- Dec-24,
A105: 1800009470 | B105: DR | C105: 45815 | D105: 45817 | E105: NA | F105: 256779414234 | G105: USD | H105: 925.23 | I105: INR | J105: 79098.63 | K105: =_xlfn.XLOOKUP(F105,'[1]Ascendus data working'!$B:$B,'[1]Ascendus data working'!$F:$F,,0) -> 925.23 | L105: =_xlfn.XLOOKUP(F105,'Customer ledger'!$A:$A,'Customer ledger'!$D:$D,,0) -> 832.7 | M105: =K105-L105 -> 92.53 | N105: Unit storage -1-31 May 25
A106: 1800009590 | B106: DR | C106: 45818 | D106: 45825 | E106: NA | F106: 256779414354 | G106: USD | H106: 100000 | I106: INR | J106: 100000 | K106: =_xlfn.XLOOKUP(F106,'[1]Ascendus data working'!$B:$B,'[1]Ascendus data working'!$F:$F,,0) -> 1169.5906 | L106: =_xlfn.XLOOKUP(F106,'Customer ledger'!$A:$A,'Customer ledger'!$D:$D,,0) -> 1052.75 | M106: =K106-L106 -> 116.84064 | N106: Fixed Storage Charges fo JUNE 2025
A107: 1800009671 | B107: DR | C107: 45826 | D107: 45827 | E107: NA | F107: 256779414435 | G107: USD | H107: 1190.48 | I107: INR | J107: 101775.06 | K107: =_xlfn.XLOOKUP(F107,'[1]Ascendus data working'!$B:$B,'[1]Ascendus data working'!$F:$F,,0) -> 1190.48 | L107: =_xlfn.XLOOKUP(F107,'Customer ledger'!$A:$A,'Customer ledger'!$D:$D,,0) -> #N/A | M107: =K107-L107 -> #N/A | N107: Fixed Rental charges for Dec 2024 | O107: 1400001107
A108: 1800010152 | B108: DR | C108: 45842 | D108: 45847 | E108: NA | F108: 256779414912 | G108: USD | H108: 100000 | I108: INR | J108: 100000 | K108: =_xlfn.XLOOKUP(F108,'[1]Ascendus data working'!$B:$B,'[1]Ascendus data working'!$F:$F,,0) -> 1162.7907 | L108: =_xlfn.XLOOKUP(F108,'Customer ledger'!$A:$A,'Customer ledger'!$D:$D,,0) -> 1046.5 | M108: =K108-L108 -> 116.2907 | N108: Fixed Storage Charges fo JULY 2025
A109: 1800010069 | B109: DR | C109: 45842 | D109: 45845 | E109: NA | F109: 256779414833 | G109: USD | H109: 3 | I109: INR | J109: 258 | K109: =_xlfn.XLOOKUP(F109,'[1]Ascendus data working'!$B:$B,'[1]Ascendus data working'!$F:$F,,0) -> 3 | L109: =_xlfn.XLOOKUP(F109,'Customer ledger'!$A:$A,'Customer ledger'!$D:$D,,0) -> 2.94 | M109: =K109-L109 -> 0.06 | N109: Outbound chgs - 01 - 15 Jun 25
A110: 1800010430 | B110: DR | C110: 45842 | D110: 45847 | E110: NA | F110: 256779415190 | G110: USD | H110: 690.7 | I110: INR | J110: 59400.66 | K110: =_xlfn.XLOOKUP(F110,'[1]Ascendus data working'!$B:$B,'[1]Ascendus data working'!$F:$F,,0) -> 690.7 | L110: =_xlfn.XLOOKUP(F110,'Customer ledger'!$A:$A,'Customer ledger'!$D:$D,,0) -> 621.63 | M110: =K110-L110 -> 69.07 | N110: Unit Storage - 1-30 June 25
A111: 1800010701 | B111: DR | C111: 45856 | D111: 45859 | E111: NA | F111: 256779415485 | G111: USD | H111: 17.25 | I111: INR | J111: 1483.51 | K111: =_xlfn.XLOOKUP(F111,'[1]Ascendus data working'!$B:$B,'[1]Ascendus data working'!$F:$F,,0) -> 17.25 | L111: =_xlfn.XLOOKUP(F111,'Customer ledger'!$A:$A,'Customer ledger'!$D:$D,,0) -> 16.9 | M111: =K111-L111 -> 0.35 | N111: LCL chgs - 01 - 15 JUL 25
A112: 1800010749 | B112: DR | C112: 45856 | D112: 45859 | E112: NA | F112: 256779415533 | G112: USD | H112: 21.75 | I112: INR | J112: 1870.51 | K112: =_xlfn.XLOOKUP(F112,'[1]Ascendus data working'!$B:$B,'[1]Ascendus data working'!$F:$F,,0) -> 21.75 | L112: =_xlfn.XLOOKUP(F112,'Customer ledger'!$A:$A,'Customer ledger'!$D:$D,,0) -> 21.31 | M112: =K112-L112 -> 0.44 | N112: Outbound chgs - 01 - 15 Jul 25
A113: 1800010706 | B113: DR | C113: 45856 | D113: 45859 | E113: NA | F113: 256779415490 | G113: USD | H113: 17.25 | I113: INR | J113: 1483.51 | K113: =_xlfn.XLOOKUP(F113,'[1]Ascendus data working'!$B:$B,'[1]Ascendus data working'!$F:$F,,0) -> 17.25 | L113: =_xlfn.XLOOKUP(F113,'Customer ledger'!$A:$A,'Customer ledger'!$D:$D,,0) -> #N/A | M113: =K113-L113 -> #N/A | N113: LCL chgs - 01 - 15 JUL 25 | O113: 1400001904
A114: 1800011045 | B114: DR | C114: 45856 | D114: 45859 | E114: NA | F114: 256779415805 | G114: USD | H114: 17.25 | I114: INR | J114: 1483.51 | K114: =_xlfn.XLOOKUP(F114,'[1]Ascendus data working'!$B:$B,'[1]Ascendus data working'!$F:$F,,0) -> 17.25 | L114: =_xlfn.XLOOKUP(F114,'Customer ledger'!$A:$A,'Customer ledger'!$D:$D,,0) -> #N/A | M114: =K114-L114 -> #N/A | N114: LCL chgs - 01 - 15 JUL 25 | O114: 1400001904
A115: 1800011050 | B115: DR | C115: 45856 | D115: 45859 | E115: NA | F115: 256779415810 | G115: USD | H115: 17.25 | I115: INR | J115: 1483.51 | K115: =_xlfn.XLOOKUP(F115,'[1]Ascendus data working'!$B:$B,'[1]Ascendus data working'!$F:$F,,0) -> 17.25 | L115: =_xlfn.XLOOKUP(F115,'Customer ledger'!$A:$A,'Customer ledger'!$D:$D,,0) -> #N/A | M115: =K115-L115 -> #N/A | N115: LCL chgs - 01 - 15 JUL 25 | O115: 1400001904
A116: 1800011012 | B116: DR | C116: 45857 | D116: 45859 | E116: NA | F116: 256779415772 | G116: USD | H116: 59.43 | I116: INR | J116: 5111.02 | K116: =_xlfn.XLOOKUP(F116,'[1]Ascendus data working'!$B:$B,'[1]Ascendus data working'!$F:$F,,0) -> 59.43 | L116: =_xlfn.XLOOKUP(F116,'Customer ledger'!$A:$A,'Customer ledger'!$D:$D,,0) -> 58.24 | M116: =K116-L116 -> 1.19 | N116: VAS - 1-15 July 25
A117: 1400000797 | B117: DY | C117: 45861 | D117: 45861 | G117: USD | H117: 198636.61 | I117: INR | J117: 200764.2 | K117: =H117 -> 198636.61 | L117: =_xlfn.XLOOKUP(F117,'Customer ledger'!$A:$A,'Customer ledger'!$D:$D,,0) -> #N/A | M117: =K117-L117 -> #N/A | O117: 1400000797
A118: 1400000797 | B118: DY | C118: 45861 | D118: 45861 | G118: USD | H118: -198636.61 | I118: INR | J118: -200764.2 | K118: =H118 -> -198636.61 | L118: =_xlfn.XLOOKUP(F118,'Customer ledger'!$A:$A,'Customer ledger'!$D:$D,,0) -> #N/A | M118: =K118-L118 -> #N/A | O118: 1400000797
A119: 1400000805 | B119: DZ | C119: 45862 | D119: 45862 | E119: 0105357143FC | G119: USD | H119: -8262.11 | I119: INR | J119: -713050.33 | K119: =H119 -> -8262.11 | L119: =_xlfn.XLOOKUP(F119,'Customer ledger'!$A:$A,'Customer ledger'!$D:$D,,0) -> #N/A | M119: =K119-L119 -> #N/A | N119: 0105357143FC | O119: 1400000805
A120: 1600001882 | B120: DG | C120: 45862 | D120: 45862 | E120: NA | F120: 256779421502 | G120: USD | H120: -1190.48 | I120: INR | J120: -102382.08 | K120: =_xlfn.XLOOKUP(F120,'[1]Ascendus data working'!$B:$B,'[1]Ascendus data working'!$F:$F,,0) -> -1190.48 | L120: =_xlfn.XLOOKUP(F120,'Customer ledger'!$A:$A,'Customer ledger'!$D:$D,,0) -> #N/A | M120: =K120-L120 -> #N/A | N120: Credit note raised against 256779414435 | O120: 1400001107
A121: 1800011358 | B121: DR | C121: 45870 | D121: 45873 | E121: NA | F121: 256779416024 | G121: USD | H121: 100000 | I121: INR | J121: 100000 | K121: =_xlfn.XLOOKUP(F121,'[1]Ascendus data working'!$B:$B,'[1]Ascendus data working'!$F:$F,,0) -> 1162.7907 | L121: =_xlfn.XLOOKUP(F121,'Customer ledger'!$A:$A,'Customer ledger'!$D:$D,,0) -> 1046.14 | M121: =K121-L121 -> 116.6507 | N121: Fixed Storage Charges for August 2025
A122: 1600002012 | B122: DG | C122: 45873 | D122: 45873 | E122: NA | F122: 256779421588 | G122: USD | H122: -17.25 | I122: INR | J122: -1483.51 | K122: =_xlfn.XLOOKUP(F122,'[1]Ascendus data working'!$B:$B,'[1]Ascendus data working'!$F:$F,,0) -> -17.25 | L122: =_xlfn.XLOOKUP(F122,'Customer ledger'!$A:$A,'Customer ledger'!$D:$D,,0) -> #N/A | M122: =K122-L122 -> #N/A | N122: Credit note raised against 256779415490 | O122: 1400001904
A123: 1600002057 | B123: DG | C123: 45873 | D123: 45873 | E123: NA | F123: 256779421633 | G123: USD | H123: -17.25 | I123: INR | J123: -1483.51 | K123: =_xlfn.XLOOKUP(F123,'[1]Ascendus data working'!$B:$B,'[1]Ascendus data working'!$F:$F,,0) -> -17.25 | L123: =_xlfn.XLOOKUP(F123,'Customer ledger'!$A:$A,'Customer ledger'!$D:$D,,0) -> #N/A | M123: =K123-L123 -> #N/A | N123: Credit note raised against 256779415805 | O123: 1400001904
A124: 1600002062 | B124: DG | C124: 45873 | D124: 45873 | E124: NA | F124: 256779421638 | G124: USD | H124: -17.25 | I124: INR | J124: -1483.51 | K124: =_xlfn.XLOOKUP(F124,'[1]Ascendus data working'!$B:$B,'[1]Ascendus data working'!$F:$F,,0) -> -17.25 | L124: =_xlfn.XLOOKUP(F124,'Customer ledger'!$A:$A,'Customer ledger'!$D:$D,,0) -> #N/A | M124: =K124-L124 -> #N/A | N124: Credit note raised against 256779415810 | O124: 1400001904
A125: 1800011652 | B125: DR | C125: 45877 | D125: 45877 | E125: NA | F125: 256779416082 | G125: USD | H125: 759.67 | I125: INR | J125: 65354.5 | K125: =_xlfn.XLOOKUP(F125,'[1]Ascendus data working'!$B:$B,'[1]Ascendus data working'!$F:$F,,0) -> 759.67 | L125: =_xlfn.XLOOKUP(F125,'Customer ledger'!$A:$A,'Customer ledger'!$D:$D,,0) -> 683.7 | M125: =K125-L125 -> 75.97 | N125: Unit Storage - 1-31 July 25
A126: 1800011791 | B126: DR | C126: 45877 | D126: 45877 | E126: NA | F126: 256779416182 | G126: USD | H126: 18 | I126: INR | J126: 1548.54 | K126: =_xlfn.XLOOKUP(F126,'[1]Ascendus data working'!$B:$B,'[1]Ascendus data working'!$F:$F,,0) -> 18 | L126: =_xlfn.XLOOKUP(F126,'Customer ledger'!$A:$A,'Customer ledger'!$D:$D,,0) -> 17.64 | M126: =K126-L126 -> 0.36 | N126: LCL chgs - 16 - 31 JUL 25
A127: 1800011710 | B127: DR | C127: 45877 | D127: 45877 | E127: NA | F127: 256779416228 | G127: USD | H127: 3 | I127: INR | J127: 258.09 | K127: =_xlfn.XLOOKUP(F127,'[1]Ascendus data working'!$B:$B,'[1]Ascendus data working'!$F:$F,,0) -> 3 | L127: =_xlfn.XLOOKUP(F127,'Customer ledger'!$A:$A,'Customer ledger'!$D:$D,,0) -> 2.94 | M127: =K127-L127 -> 0.06 | N127: Outbound chgs - 16 - 31 Jul 25
A128: 1800011396 | B128: DR | C128: 45877 | D128: 45877 | E128: NA | F128: 256779416246 | G128: USD | H128: 70.95 | I128: INR | J128: 6103.84 | K128: =_xlfn.XLOOKUP(F128,'[1]Ascendus data working'!$B:$B,'[1]Ascendus data working'!$F:$F,,0) -> 70.95 | L128: =_xlfn.XLOOKUP(F128,'Customer ledger'!$A:$A,'Customer ledger'!$D:$D,,0) -> 69.54 | M128: =K128-L128 -> 1.41 | N128: CODC LCL Chgs - 16 - 31 Jul 25
A129: 1800011407 | B129: DR | C129: 45877 | D129: 45877 | E129: NA | F129: 256779416257 | G129: USD | H129: 22.87 | I129: INR | J129: 1967.51 | K129: =_xlfn.XLOOKUP(F129,'[1]Ascendus data working'!$B:$B,'[1]Ascendus data working'!$F:$F,,0) -> 22.87 | L129: =_xlfn.XLOOKUP(F129,'Customer ledger'!$A:$A,'Customer ledger'!$D:$D,,0) -> 22.42 | M129: =K129-L129 -> 0.45 | N129: CODC Out chgs - 16 - 31 Jul 25
A130: 1800011596 | B130: DR | C130: 45877 | D130: 45877 | E130: NA | F130: 256779416446 | G130: USD | H130: 2.28 | I130: INR | J130: 196.15 | K130: =_xlfn.XLOOKUP(F130,'[1]Ascendus data working'!$B:$B,'[1]Ascendus data working'!$F:$F,,0) -> 2.28 | L130: =_xlfn.XLOOKUP(F130,'Customer ledger'!$A:$A,'Customer ledger'!$D:$D,,0) -> 2.23 | M130: =K130-L130 -> 0.05 | N130: VAS 16-31 July 25
A131: 1800012069 | B131: DR | C131: 45889 | D131: 45891 | E131: NA | F131: 256779416604 | G131: USD | H131: 17.31 | I131: INR | J131: 1489.18 | K131: =_xlfn.XLOOKUP(F131,'[1]Ascendus data working'!$B:$B,'[1]Ascendus data working'!$F:$F,,0) -> 17.31 | L131: =_xlfn.XLOOKUP(F131,'Customer ledger'!$A:$A,'Customer ledger'!$D:$D,,0) -> 16.96 | M131: =K131-L131 -> 0.35 | N131: CODC LCL Chgs - 1-15 Aug 25
A132: 1800012178 | B132: DR | C132: 45889 | D132: 45891 | E132: NA | F132: 256779416616 | G132: USD | H132: 63.65 | I132: INR | J132: 5475.82 | K132: =_xlfn.XLOOKUP(F132,'[1]Ascendus data working'!$B:$B,'[1]Ascendus data working'!$F:$F,,0) -> 63.65 | L132: =_xlfn.XLOOKUP(F132,'Customer ledger'!$A:$A,'Customer ledger'!$D:$D,,0) -> 62.38 | M132: =K132-L132 -> 1.27 | N132: CODC Out chgs - 1-15 Aug 25
...

Sheet CL Ledger
A1: Cleared Item | B1: Company Code | C1: Customer | D1: Customer Account: Name 1 | E1: Fiscal Year | F1: Posting period | G1: Posting Date | H1: Document Number | I1: Document Type | J1: Document Date | K1: Entry Date | L1: Document Header Text | M1: Reference | N1: G/L Account | O1: G/L Account: Short Text | P1: Special G/L Ind. | Q1: Posting Key | R1: Document Currency Key | S1: Document Currency Value | T1: Company Code Currency Key | U1: Company Code Currency Value | V1: Tax Code | W1: Profit Center | X1: Trading Partner No. | Y1: Assignment | Z1: Item | AB1: Text | AC1: Reference Key 1 | AD1: Reference Key 2 | AE1: Reference Key 3 | AF1: Baseline Payment Dte | AG1: Clearing Date | AH1: Clearing Document
A2: Selected | B2: 6779 | C2: 100222345 | D2: SIDDHARTHA LOGISTICS FTWZ PRIVATE | E2: 2025 | F2: 9 | G2: 45902 | H2: 1400001107 | I2: DY | J2: 45902 | K2: 45902 | N2: 212100 | O2: Trade Debtors (Ctrl) | Q2: 08 | R2: USD | S2: 104184.06 | T2: INR | U2: 102382.08 | W2: 6779224500 | Z2: 1 | AA2: =U2 -> 102382.08 | AF2: 45902 | AG2: 45902 | AH2: 1400001107
A3: Selected | B3: 6779 | C3: 100222345 | D3: SIDDHARTHA LOGISTICS FTWZ PRIVATE | E3: 2025 | F3: 9 | G3: 45902 | H3: 1400001107 | I3: DY | J3: 45902 | K3: 45902 | N3: 212100 | O3: Trade Debtors (Ctrl) | Q3: 15 | R3: USD | S3: -104184.06 | T3: INR | U3: -101775.06 | W3: 6779224500 | Z3: 2 | AA3: =U3 -> -101775.06 | AF3: 45902 | AG3: 45902 | AH3: 1400001107
A4: Selected | B4: 6779 | C4: 100222345 | D4: SIDDHARTHA LOGISTICS FTWZ PRIVATE | E4: 2025 | F4: 7 | G4: 45861 | H4: 1400000797 | I4: DY | J4: 45861 | K4: 45861 | N4: 212100 | O4: Trade Debtors (Ctrl) | Q4: 08 | R4: USD | S4: 198636.61 | T4: INR | U4: 200764.2 | W4: 6779224500 | Z4: 1 | AA4: =U4 -> 200764.2 | AF4: 45861 | AG4: 45861 | AH4: 1400000797
A5: Selected | B5: 6779 | C5: 100222345 | D5: SIDDHARTHA LOGISTICS FTWZ PRIVATE | E5: 2025 | F5: 7 | G5: 45861 | H5: 1400000797 | I5: DY | J5: 45861 | K5: 45861 | N5: 212100 | O5: Trade Debtors (Ctrl) | Q5: 15 | R5: USD | S5: -198636.61 | T5: INR | U5: -200764.2 | W5: 6779224500 | Z5: 2 | AA5: =U5 -> -200764.2 | AF5: 45861 | AG5: 45861 | AH5: 1400000797
A6: Not Selected | B6: 6779 | C6: 100222345 | D6: SIDDHARTHA LOGISTICS FTWZ PRIVATE | E6: 2025 | F6: 8 | G6: 45891 | H6: 1400001003 | I6: DZ | J6: 45891 | K6: 45891 | L6: 0099542199FC | N6: 212100 | O6: Trade Debtors (Ctrl) | Q6: 15 | R6: USD | S6: -4582.99 | T6: INR | U6: -394140.21 | W6: 6779220000 | Z6: 2 | AA6: =S6 -> -4582.99 | AF6: 45891
A7: Selected | B7: 6779 | C7: 100222345 | D7: SIDDHARTHA LOGISTICS FTWZ PRIVATE | E7: 2025 | F7: 7 | G7: 45862 | H7: 1400000805 | I7: DZ | J7: 45862 | K7: 45862 | L7: 0105357143FC | N7: 212100 | O7: Trade Debtors (Ctrl) | Q7: 15 | R7: USD | S7: -8262.11 | T7: INR | U7: -713050.33 | W7: 6779224500 | Z7: 3 | AA7: =S7 -> -8262.11 | AB7: 0105357143FC | AF7: 45862 | AG7: 45862 | AH7: 1400000805
A8: Not Selected | B8: 6779 | C8: 100222345 | D8: SIDDHARTHA LOGISTICS FTWZ PRIVATE | E8: 2025 | F8: 10 | G8: 45955 | H8: 1400001512 | I8: DZ | J8: 45955 | K8: 45955 | L8: T54SWIC277314 | N8: 212100 | O8: Trade Debtors (Ctrl) | Q8: 15 | R8: USD | S8: -4875.15 | T8: INR | U8: -429943.23 | W8: 6779220000 | Z8: 2 | AA8: =S8 -> -4875.15 | AF8: 45955
A9: Selected | B9: 6779 | C9: 100222345 | D9: SIDDHARTHA LOGISTICS FTWZ PRIVATE | E9: 2025 | F9: 11 | G9: 45976 | H9: 1400001904 | I9: DY | J9: 45976 | K9: 45976 | L9: NA | M9: KNOCK OFF ENTRY | N9: 212100 | O9: Trade Debtors (Ctrl) | Q9: 08 | R9: USD | S9: 0 | T9: INR | U9: 0 | W9: 6779224500 | Z9: 1 | AA9: =S9 -> 0 | AF9: 45976 | AG9: 45976 | AH9: 1400001904
A10: Selected | B10: 6779 | C10: 100222345 | D10: SIDDHARTHA LOGISTICS FTWZ PRIVATE | E10: 2025 | F10: 11 | G10: 45976 | H10: 1400001905 | I10: DY | J10: 45976 | K10: 45976 | L10: NA | M10: KNOCK OFF ENTRY | N10: 212100 | O10: Trade Debtors (Ctrl) | Q10: 08 | R10: USD | S10: 879.2 | T10: INR | U10: 77537.33 | W10: 6779224500 | Z10: 4 | AA10: =S10 -> 879.2 | AF10: 45976 | AG10: 45976 | AH10: 1400001905
A11: Not Selected | B11: 6779 | C11: 100222345 | D11: SIDDHARTHA LOGISTICS FTWZ PRIVATE | E11: 2025 | F11: 11 | G11: 45976 | H11: 1400001905 | I11: DY | J11: 45976 | K11: 45976 | L11: NA | M11: KNOCK OFF ENTRY | N11: 212100 | O11: Trade Debtors (Ctrl) | Q11: 15 | R11: USD | S11: -111.25 | T11: INR | U11: -9790.38 | W11: 6779224500 | Y11: NA | Z11: 1 | AA11: =S11 -> -111.25 | AF11: 45976
A12: Not Selected | B12: 6779 | C12: 100222345 | D12: SIDDHARTHA LOGISTICS FTWZ PRIVATE | E12: 2025 | F12: 11 | G12: 45976 | H12: 1400001905 | I12: DY | J12: 45976 | K12: 45976 | L12: NA | M12: KNOCK OFF ENTRY | N12: 212100 | O12: Trade Debtors (Ctrl) | Q12: 15 | R12: USD | S12: -376.4 | T12: INR | U12: -33124.48 | W12: 6779224500 | Y12: NA | Z12: 2 | AA12: =S12 -> -376.4 | AF12: 45976
A13: Not Selected | B13: 6779 | C13: 100222345 | D13: SIDDHARTHA LOGISTICS FTWZ PRIVATE | E13: 2025 | F13: 11 | G13: 45976 | H13: 1400001905 | I13: DY | J13: 45976 | K13: 45976 | L13: NA | M13: KNOCK OFF ENTRY | N13: 212100 | O13: Trade Debtors (Ctrl) | Q13: 15 | R13: USD | S13: -391.55 | T13: INR | U13: -34457.73 | W13: 6779224500 | Y13: NA | Z13: 3 | AA13: =S13 -> -391.55 | AF13: 45976
A14: Not Selected | B14: 6779 | C14: 100222345 | D14: SIDDHARTHA LOGISTICS FTWZ PRIVATE | E14: 2025 | F14: 5 | G14: 45787 | H14: 1800008258 | I14: DR | J14: 45787 | K14: 45791 | L14: NA | M14: 256779413142 | N14: 212100 | O14: Trade Debtors (Ctrl) | Q14: 01 | R14: USD | S14: 100000 | T14: INR | U14: 100000 | V14: O0 | W14: 6779224500 | Y14: NA | Z14: 1 | AA14: =_xlfn.XLOOKUP(M14,'[1]TDS To Be Booked'!$D:$D,'[1]TDS To Be Booked'!$K:$K,,0) -> 1163.0111 | AB14: Fixed Storage Charges fo MAY 2025 | AF14: 45787
A15: Not Selected | B15: 6779 | C15: 100222345 | D15: SIDDHARTHA LOGISTICS FTWZ PRIVATE | E15: 2025 | F15: 6 | G15: 45818 | H15: 1800009590 | I15: DR | J15: 45818 | K15: 45825 | L15: NA | M15: 256779414354 | N15: 212100 | O15: Trade Debtors (Ctrl) | Q15: 01 | R15: USD | S15: 100000 | T15: INR | U15: 100000 | V15: O0 | W15: 6779224500 | Y15: NA | Z15: 1 | AA15: =_xlfn.XLOOKUP(M15,'[1]TDS To Be Booked'!$D:$D,'[1]TDS To Be Booked'!$K:$K,,0) -> 1169.7222 | AB15: Fixed Storage Charges fo JUNE 2025 | AF15: 45818
A16: Not Selected | B16: 6779 | C16: 100222345 | D16: SIDDHARTHA LOGISTICS FTWZ PRIVATE | E16: 2025 | F16: 7 | G16: 45842 | H16: 1800010152 | I16: DR | J16: 45842 | K16: 45847 | L16: NA | M16: 256779414912 | N16: 212100 | O16: Trade Debtors (Ctrl) | Q16: 01 | R16: USD | S16: 100000 | T16: INR | U16: 100000 | V16: O0 | W16: 6779224500 | Y16: NA | Z16: 1 | AA16: =_xlfn.XLOOKUP(M16,'[1]TDS To Be Booked'!$D:$D,'[1]TDS To Be Booked'!$K:$K,,0) -> 1162.7778 | AB16: Fixed Storage Charges fo JULY 2025 | AF16: 45842
A17: Not Selected | B17: 6779 | C17: 100222345 | D17: SIDDHARTHA LOGISTICS FTWZ PRIVATE | E17: 2025 | F17: 8 | G17: 45870 | H17: 1800011358 | I17: DR | J17: 45870 | K17: 45873 | L17: NA | M17: 256779416024 | N17: 212100 | O17: Trade Debtors (Ctrl) | Q17: 01 | R17: USD | S17: 100000 | T17: INR | U17: 100000 | V17: O0 | W17: 6779224500 | Y17: NA | Z17: 1 | AA17: =_xlfn.XLOOKUP(M17,'[1]TDS To Be Booked'!$D:$D,'[1]TDS To Be Booked'!$K:$K,,0) -> 1162.3778 | AB17: Fixed Storage Charges for August 2025 | AF17: 45870
A18: Not Selected | B18: 6779 | C18: 100222345 | D18: SIDDHARTHA LOGISTICS FTWZ PRIVATE | E18: 2025 | F18: 9 | G18: 45904 | H18: 1800012710 | I18: DR | J18: 45904 | K18: 45909 | L18: NA | M18: 256779417344 | N18: 212100 | O18: Trade Debtors (Ctrl) | Q18: 01 | R18: USD | S18: 100000 | T18: INR | U18: 100000 | V18: O0 | W18: 6779224500 | Y18: 2097261 | Z18: 1 | AA18: =_xlfn.XLOOKUP(M18,'[1]TDS To Be Booked'!$D:$D,'[1]TDS To Be Booked'!$K:$K,,0) -> 1142.6667 | AB18: Fixed Storage Charges for September 2025 | AF18: 45904
A19: Not Selected | B19: 6779 | C19: 100222345 | D19: SIDDHARTHA LOGISTICS FTWZ PRIVATE | E19: 2025 | F19: 10 | G19: 45935 | H19: 1800013251 | I19: DR | J19: 45935 | K19: 45937 | L19: NA | M19: 256779417871 | N19: 212100 | O19: Trade Debtors (Ctrl) | Q19: 01 | R19: USD | S19: 100000 | T19: INR | U19: 100000 | V19: O0 | W19: 6779224500 | Y19: 2110507 | Z19: 1 | AA19: =_xlfn.XLOOKUP(M19,'[1]TDS To Be Booked'!$D:$D,'[1]TDS To Be Booked'!$K:$K,,0) -> 1133.9111 | AB19: Fixed Storage Charges for October 2025 | AF19: 45935
A20: Not Selected | B20: 6779 | C20: 100222345 | D20: SIDDHARTHA LOGISTICS FTWZ PRIVATE | E20: 2025 | F20: 11 | G20: 45966 | H20: 1800014233 | I20: DR | J20: 45966 | K20: 45966 | L20: NA | M20: 256779418773 | N20: 212100 | O20: Trade Debtors (Ctrl) | Q20: 01 | R20: USD | S20: 100000 | T20: INR | U20: 100000 | V20: O0 | W20: 6779224500 | Y20: 2123158 | Z20: 1 | AA20: =_xlfn.XLOOKUP(M20,'[1]TDS To Be Booked'!$D:$D,'[1]TDS To Be Booked'!$K:$K,,0) -> 1136.3222 | AB20: Fixed Storage Charges for November 2025 | AF20: 45966
A21: Not Selected | B21: 6779 | C21: 100222345 | D21: SIDDHARTHA LOGISTICS FTWZ PRIVATE | E21: 2025 | F21: 12 | G21: 45995 | H21: 1800015482 | I21: DR | J21: 45995 | K21: 46000 | L21: NA | M21: 256779419966 | N21: 212100 | O21: Trade Debtors (Ctrl) | Q21: 01 | R21: USD | S21: 100000 | T21: INR | U21: 100000 | V21: O0 | W21: 6779224500 | Y21: 2139804 | Z21: 1 | AA21: =_xlfn.XLOOKUP(M21,'[1]TDS To Be Booked'!$D:$D,'[1]TDS To Be Booked'!$K:$K,,0) -> 1127.3889 | AB21: Fixed Storage Charges for December 2025 | AF21: 45995
A22: Not Selected | B22: 6779 | C22: 100222345 | D22: SIDDHARTHA LOGISTICS FTWZ PRIVATE | E22: 2025 | F22: 3 | G22: 45730 | H22: 1800001820 | I22: DR | J22: 45730 | K22: 45733 | L22: NA | M22: 246779411485 | N22: 212100 | O22: Trade Debtors (Ctrl) | Q22: 01 | R22: USD | S22: 100 | T22: INR | U22: 8669.13 | V22: O0 | W22: 6779224500 | Y22: NA | Z22: 1 | AA22: =S22 -> 100 | AB22: Intra Unit Transfer Charges Month Of August,2024 | AF22: 45730
A23: Not Selected | B23: 6779 | C23: 100222345 | D23: SIDDHARTHA LOGISTICS FTWZ PRIVATE | E23: 2025 | F23: 3 | G23: 45730 | H23: 1800001617 | I23: DR | J23: 45730 | K23: 45735 | L23: NA | M23: 246779412274 | N23: 212100 | O23: Trade Debtors (Ctrl) | Q23: 01 | R23: USD | S23: 100 | T23: INR | U23: 8669.13 | V23: O0 | W23: 6779224500 | Y23: NA | Z23: 1 | AA23: =S23 -> 100 | AB23: Intra Unit Transfer Charges Month Of August,2024 | AF23: 45730
A24: Not Selected | B24: 6779 | C24: 100222345 | D24: SIDDHARTHA LOGISTICS FTWZ PRIVATE | E24: 2025 | F24: 3 | G24: 45720 | H24: 1800000754 | I24: DR | J24: 45720 | K24: 45720 | L24: NA | M24: 246779410694 | N24: 212100 | O24: Trade Debtors (Ctrl) | Q24: 01 | R24: USD | S24: 59.36 | T24: INR | U24: 5145.99 | V24: O0 | W24: 6779224500 | Y24: NA | Z24: 1 | AA24: =S24 -> 59.36 | AB24: Outbound Handling for Oct 2024 | AF24: 45720
A25: Not Selected | B25: 6779 | C25: 100222345 | D25: SIDDHARTHA LOGISTICS FTWZ PRIVATE | E25: 2025 | F25: 3 | G25: 45720 | H25: 1800000915 | I25: DR | J25: 45720 | K25: 45721 | L25: NA | M25: 246779410856 | N25: 212100 | O25: Trade Debtors (Ctrl) | Q25: 01 | R25: USD | S25: 18.32 | T25: INR | U25: 1588.18 | V25: O0 | W25: 6779224500 | Y25: NA | Z25: 1 | AA25: =S25 -> 18.32 | AB25: Outbound Handling for Dec 2024 | AF25: 45720
A26: Not Selected | B26: 6779 | C26: 100222345 | D26: SIDDHARTHA LOGISTICS FTWZ PRIVATE | E26: 2025 | F26: 4 | G26: 45751 | H26: 1800005899 | I26: DR | J26: 45751 | K26: 45752 | L26: NA | M26: 256779410791 | N26: 212100 | O26: Trade Debtors (Ctrl) | Q26: 01 | R26: USD | S26: 441.2 | T26: INR | U26: 38349.91 | V26: O0 | Y26: NA | Z26: 1 | AA26: =S26 -> 441.2 | AB26: Storage Charges Feb, 25 Exch Rate 87.4 | AF26: 45751
A27: Not Selected | B27: 6779 | C27: 100222345 | D27: SIDDHARTHA LOGISTICS FTWZ PRIVATE | E27: 2025 | F27: 4 | G27: 45751 | H27: 1800005916 | I27: DR | J27: 45751 | K27: 45752 | L27: NA | M27: 256779410807 | N27: 212100 | O27: Trade Debtors (Ctrl) | Q27: 01 | R27: USD | S27: 742.7 | T27: INR | U27: 64556.84 | V27: O0 | Y27: NA | Z27: 1 | AA27: =S27 -> 742.7 | AB27: Storage Charges Jan, 25 Exch Rate 86.64 | AF27: 45751
A28: Not Selected | B28: 6779 | C28: 100222345 | D28: SIDDHARTHA LOGISTICS FTWZ PRIVATE | E28: 2025 | F28: 3 | G28: 45722 | H28: 1800000948 | I28: DR | J28: 45722 | K28: 45722 | L28: NA | M28: 246779410888 | N28: 212100 | O28: Trade Debtors (Ctrl) | Q28: 01 | R28: USD | S28: 446.38 | T28: INR | U28: 38697.24 | V28: O0 | W28: 6779224500 | Y28: NA | Z28: 1 | AA28: =S28 -> 446.38 | AB28: Storage Charges for the month of December, 2024 Ex | AF28: 45722
A29: Not Selected | B29: 6779 | C29: 100222345 | D29: SIDDHARTHA LOGISTICS FTWZ PRIVATE | E29: 2025 | F29: 3 | G29: 45722 | H29: 1800000925 | I29: DR | J29: 45722 | K29: 45722 | L29: NA | M29: 246779410865 | N29: 212100 | O29: Trade Debtors (Ctrl) | Q29: 01 | R29: USD | S29: 412.11 | T29: INR | U29: 35726.34 | V29: O0 | W29: 6779224500 | Y29: NA | Z29: 1 | AA29: =S29 -> 412.11 | AB29: Storage Charges for the month of November, 2024 Ex | AF29: 45722
A30: Not Selected | B30: 6779 | C30: 100222345 | D30: SIDDHARTHA LOGISTICS FTWZ PRIVATE | E30: 2025 | F30: 3 | G30: 45722 | H30: 1800001035 | I30: DR | J30: 45722 | K30: 45722 | L30: NA | M30: 246779410975 | N30: 212100 | O30: Trade Debtors (Ctrl) | Q30: 01 | R30: USD | S30: 28.91 | T30: INR | U30: 2506.24 | V30: O0 | W30: 6779224500 | Y30: NA | Z30: 1 | AA30: =S30 -> 28.91 | AB30: Inbound Handling charges for Aug 2024 | AF30: 45722
A31: Not Selected | B31: 6779 | C31: 100222345 | D31: SIDDHARTHA LOGISTICS FTWZ PRIVATE | E31: 2025 | F31: 3 | G31: 45722 | H31: 1800001036 | I31: DR | J31: 45722 | K31: 45722 | L31: NA | M31: 246779410976 | N31: 212100 | O31: Trade Debtors (Ctrl) | Q31: 01 | R31: USD | S31: 24 | T31: INR | U31: 2080.59 | V31: O0 | W31: 6779224500 | Y31: NA | Z31: 1 | AA31: =S31 -> 24 | AB31: Inbound Handling charges for Aug 2024 | AF31: 45722
A32: Not Selected | B32: 6779 | C32: 100222345 | D32: SIDDHARTHA LOGISTICS FTWZ PRIVATE | E32: 2025 | F32: 3 | G32: 45722 | H32: 1800001120 | I32: DR | J32: 45722 | K32: 45723 | L32: NA | M32: 246779411056 | N32: 212100 | O32: Trade Debtors (Ctrl) | Q32: 01 | R32: USD | S32: 59.36 | T32: INR | U32: 5145.99 | V32: O0 | W32: 6779224500 | Y32: NA | Z32: 1 | AA32: =S32 -> 59.36 | AB32: Inbound Handling charges for Sep 2024 | AF32: 45722
A33: Not Selected | B33: 6779 | C33: 100222345 | D33: SIDDHARTHA LOGISTICS FTWZ PRIVATE | E33: 2025 | F33: 3 | G33: 45722 | H33: 1800001121 | I33: DR | J33: 45722 | K33: 45723 | L33: NA | M33: 246779411057 | N33: 212100 | O33: Trade Debtors (Ctrl) | Q33: 01 | R33: USD | S33: 67.67 | T33: INR | U33: 5866.4 | V33: O0 | W33: 6779224500 | Y33: NA | Z33: 1 | AA33: =S33 -> 67.67 | AB33: Inbound Handling charges for Sep 2024 | AF33: 45722
A34: Not Selected | B34: 6779 | C34: 100222345 | D34: SIDDHARTHA LOGISTICS FTWZ PRIVATE | E34: 2025 | F34: 3 | G34: 45722 | H34: 1800001321 | I34: DR | J34: 45722 | K34: 45723 | L34: NA | M34: 246779411190 | N34: 212100 | O34: Trade Debtors (Ctrl) | Q34: 01 | R34: USD | S34: 17.25 | T34: INR | U34: 1495.42 | V34: O0 | W34: 6779224500 | Y34: NA | Z34: 1 | AA34: =S34 -> 17.25 | AB34: Inbound Handling charges for Nov 2024 | AF34: 45722
A35: Not Selected | B35: 6779 | C35: 100222345 | D35: SIDDHARTHA LOGISTICS FTWZ PRIVATE | E35: 2025 | F35: 3 | G35: 45722 | H35: 1800001322 | I35: DR | J35: 45722 | K35: 45723 | L35: NA | M35: 246779411191 | N35: 212100 | O35: Trade Debtors (Ctrl) | Q35: 01 | R35: USD | S35: 26.15 | T35: INR | U35: 2266.98 | V35: O0 | W35: 6779224500 | Y35: NA | Z35: 1 | AA35: =S35 -> 26.15 | AB35: Inbound Handling charges for Nov 2024 | AF35: 45722
A36: Not Selected | B36: 6779 | C36: 100222345 | D36: SIDDHARTHA LOGISTICS FTWZ PRIVATE | E36: 2025 | F36: 3 | G36: 45722 | H36: 1800001384 | I36: DR | J36: 45722 | K36: 45723 | L36: NA | M36: 246779411253 | N36: 212100 | O36: Trade Debtors (Ctrl) | Q36: 01 | R36: USD | S36: 20 | T36: INR | U36: 1733.83 | V36: O0 | W36: 6779224500 | Y36: NA | Z36: 1 | AA36: =S36 -> 20 | AB36: Inbound Handling charges for Dec 2024 | AF36: 45722
A37: Not Selected | B37: 6779 | C37: 100222345 | D37: SIDDHARTHA LOGISTICS FTWZ PRIVATE | E37: 2025 | F37: 10 | G37: 45943 | H37: 1600002430 | I37: DG | J37: 45943 | K37: 45944 | L37: NA | M37: 256779421974 | N37: 212100 | O37: Trade Debtors (Ctrl) | Q37: 11 | R37: USD | S37: -435.91 | T37: INR | U37: -38443.24 | V37: O0 | W37: 6779224500 | Y37: 2112576 | Z37: 1 | AA37: =S37 -> -435.91 | AB37: CN issued against 246779410865 | AF37: 45943
A38: Not Selected | B38: 6779 | C38: 100222345 | D38: SIDDHARTHA LOGISTICS FTWZ PRIVATE | E38: 2025 | F38: 10 | G38: 45943 | H38: 1600002431 | I38: DG | J38: 45943 | K38: 45944 | L38: NA | M38: 256779421975 | N38: 212100 | O38: Trade Debtors (Ctrl) | Q38: 11 | R38: USD | S38: -447.05 | T38: INR | U38: -39425.68 | V38: O0 | W38: 6779224500 | Y38: 2112576 | Z38: 1 | AA38: =S38 -> -447.05 | AB38: CN issued against 246779410888 | AF38: 45943
A39: Selected | B39: 6779 | C39: 100222345 | D39: SIDDHARTHA LOGISTICS FTWZ PRIVATE | E39: 2025 | F39: 10 | G39: 45943 | H39: 1600002438 | I39: DG | J39: 45943 | K39: 45944 | L39: NA | M39: 256779421982 | N39: 212100 | O39: Trade Debtors (Ctrl) | Q39: 11 | R39: USD | S39: -480.02 | T39: INR | U39: -42333.33 | V39: O0 | W39: 6779224500 | Y39: 2112591 | Z39: 1 | AA39: =S39 -> -480.02 | AB39: CN issued against 256779418012 | AF39: 45943 | AG39: 45976 | AH39: 1400001904
A40: Selected | B40: 6779 | C40: 100222345 | D40: SIDDHARTHA LOGISTICS FTWZ PRIVATE | E40: 2025 | F40: 10 | G40: 45943 | H40: 1600002432 | I40: DG | J40: 45943 | K40: 45944 | L40: NA | M40: 256779421976 | N40: 212100 | O40: Trade Debtors (Ctrl) | Q40: 11 | R40: USD | S40: -111.25 | T40: INR | U40: -9811.22 | V40: O0 | W40: 6779224500 | Y40: 2112576 | Z40: 1 | AA40: =S40 -> -111.25 | AB40: CN issued against 246779410368 | AF40: 45943 | AG40: 45976 | AH40: 1400001905
A41: Selected | B41: 6779 | C41: 100222345 | D41: SIDDHARTHA LOGISTICS FTWZ PRIVATE | E41: 2025 | F41: 10 | G41: 45943 | H41: 1600002433 | I41: DG | J41: 45943 | K41: 45944 | L41: NA | M41: 256779421977 | N41: 212100 | O41: Trade Debtors (Ctrl) | Q41: 11 | R41: USD | S41: -376.4 | T41: INR | U41: -33195.01 | V41: O0 | W41: 6779224500 | Y41: 2112576 | Z41: 1 | AA41: =S41 -> -376.4 | AB41: CN issued against 246779410394 | AF41: 45943 | AG41: 45976 | AH41: 1400001905
A42: Selected | B42: 6779 | C42: 100222345 | D42: SIDDHARTHA LOGISTICS FTWZ PRIVATE | E42: 2025 | F42: 10 | G42: 45943 | H42: 1600002434 | I42: DG | J42: 45943 | K42: 45944 | L42: NA | M42: 256779421978 | N42: 212100 | O42: Trade Debtors (Ctrl) | Q42: 11 | R42: USD | S42: -391.55 | T42: INR | U42: -34531.1 | V42: O0 | W42: 6779224500 | Y42: 2112576 | Z42: 1 | AA42: =S42 -> -391.55 | AB42: CN issued against 246779410418 | AF42: 45943 | AG42: 45976 | AH42: 1400001905
A43: Not Selected | B43: 6779 | C43: 100222345 | D43: SIDDHARTHA LOGISTICS FTWZ PRIVATE | E43: 2025 | F43: 3 | G43: 45719 | H43: 1800000406 | I43: DR | J43: 45719 | K43: 45719 | L43: NA | M43: 246779410368 | N43: 212100 | O43: Trade Debtors (Ctrl) | Q43: 01 | R43: USD | S43: 356.43 | T43: INR | U43: 30899.37 | V43: O0 | W43: 6779224500 | Y43: NA | Z43: 1 | AA43: =S43 -> 356.43 | AB43: Storage Charges for the month of August, 2024 | AF43: 45719
A44: Not Selected | B44: 6779 | C44: 100222345 | D44: SIDDHARTHA LOGISTICS FTWZ PRIVATE | E44: 2025 | F44: 3 | G44: 45719 | H44: 1800000675 | I44: DR | J44: 45719 | K44: 45720 | L44: NA | M44: 246779410615 | N44: 212100 | O44: Trade Debtors (Ctrl) | Q44: 01 | R44: USD | S44: 9 | T44: INR | U44: 780.22 | V44: O0 | W44: 6779224500 | Y44: NA | Z44: 1 | AA44: =S44 -> 9 | AB44: Outbound Handling for Sep 2024 | AF44: 45719
A45: Not Selected | B45: 6779 | C45: 100222345 | D45: SIDDHARTHA LOGISTICS FTWZ PRIVATE | E45: 2025 | F45: 3 | G45: 45719 | H45: 1800000432 | I45: DR | J45: 45719 | K45: 45719 | L45: NA | M45: 246779410394 | N45: 212100 | O45: Trade Debtors (Ctrl) | Q45: 01 | R45: USD | S45: 505.86 | T45: INR | U45: 43853.64 | V45: O0 | W45: 6779224500 | Y45: NA | Z45: 1 | AA45: =S45 -> 505.86 | AB45: Storage for the month of Sep 2024 Exch Rate 83.79 | AF45: 45719
A46: Not Selected | B46: 6779 | C46: 100222345 | D46: SIDDHARTHA LOGISTICS FTWZ PRIVATE | E46: 2025 | F46: 3 | G46: 45719 | H46: 1800000456 | I46: DR | J46: 45719 | K46: 45719 | L46: NA | M46: 246779410418 | N46: 212100 | O46: Trade Debtors (Ctrl) | Q46: 01 | R46: USD | S46: 562.6 | T46: INR | U46: 48772.5 | V46: O0 | W46: 6779224500 | Y46: NA | Z46: 1 | AA46: =S46 -> 562.6 | AB46: Storage for the month of Oct 2024 | AF46: 45719
A47: Not Selected | B47: 6779 | C47: 100222345 | D47: SIDDHARTHA LOGISTICS FTWZ PRIVATE | E47: 2025 | F47: 3 | G47: 45719 | H47: 1800000559 | I47: DR | J47: 45719 | K47: 45719 | L47: NA | M47: 246779410509 | N47: 212100 | O47: Trade Debtors (Ctrl) | Q47: 01 | R47: USD | S47: 29.25 | T47: INR | U47: 2535.72 | V47: O0 | W47: 6779224500 | Y47: NA | Z47: 1 | AA47: =S47 -> 29.25 | AB47: Outbound Handling for Aug 2024 | AF47: 45719
A48: Not Selected | B48: 6779 | C48: 100222345 | D48: SIDDHARTHA LOGISTICS FTWZ PRIVATE | E48: 2025 | F48: 3 | G48: 45719 | H48: 1800000560 | I48: DR | J48: 45719 | K48: 45719 | L48: NA | M48: 246779410510 | N48: 212100 | O48: Trade Debtors (Ctrl) | Q48: 01 | R48: USD | S48: 194.9 | T48: INR | U48: 16896.13 | V48: O0 | W48: 6779224500 | Y48: NA | Z48: 1 | AA48: =S48 -> 194.9 | AB48: Outbound Handling for Aug 2024 | AF48: 45719
A49: Not Selected | B49: 6779 | C49: 100222345 | D49: SIDDHARTHA LOGISTICS FTWZ PRIVATE | E49: 2025 | F49: 3 | G49: 45719 | H49: 1800000561 | I49: DR | J49: 45719 | K49: 45719 | L49: NA | M49: 246779410511 | N49: 212100 | O49: Trade Debtors (Ctrl) | Q49: 01 | R49: USD | S49: 13.91 | T49: INR | U49: 1205.88 | V49: O0 | W49: 6779224500 | Y49: NA | Z49: 1 | AA49: =S49 -> 13.91 | AB49: Outbound Handling for Aug 2024 | AF49: 45719
A50: Not Selected | B50: 6779 | C50: 100222345 | D50: SIDDHARTHA LOGISTICS FTWZ PRIVATE | E50: 2025 | F50: 3 | G50: 45719 | H50: 1800000674 | I50: DR | J50: 45719 | K50: 45720 | L50: NA | M50: 246779410614 | N50: 212100 | O50: Trade Debtors (Ctrl) | Q50: 01 | R50: USD | S50: 2.25 | T50: INR | U50: 195.06 | V50: O0 | W50: 6779224500 | Y50: NA | Z50: 1 | AA50: =S50 -> 2.25 | AB50: Outbound Handling for Sep 2024 | AF50: 45719
A51: Not Selected | B51: 6779 | C51: 100222345 | D51: SIDDHARTHA LOGISTICS FTWZ PRIVATE | E51: 2025 | F51: 3 | G51: 45733 | H51: 1800001957 | I51: DR | J51: 45733 | K51: 45733 | L51: NA | M51: 246779411622 | N51: 212100 | O51: Trade Debtors (Ctrl) | Q51: 01 | R51: USD | S51: 3.82 | T51: INR | U51: 331.16 | V51: O0 | W51: 6779224500 | Y51: NA | Z51: 1 | AA51: =S51 -> 3.82 | AB51: VAS Activity Charges for the month of September, 2 | AF51: 45733
A52: Not Selected | B52: 6779 | C52: 100222345 | D52: SIDDHARTHA LOGISTICS FTWZ PRIVATE | E52: 2025 | F52: 3 | G52: 45733 | H52: 1800001958 | I52: DR | J52: 45733 | K52: 45733 | L52: NA | M52: 246779411623 | N52: 212100 | O52: Trade Debtors (Ctrl) | Q52: 01 | R52: USD | S52: 1.91 | T52: INR | U52: 165.58 | V52: O0 | W52: 6779224500 | Y52: NA | Z52: 1 | AA52: =S52 -> 1.91 | AB52: VAS Activity Charges for the month of September, 2 | AF52: 45733
A53: Not Selected | B53: 6779 | C53: 100222345 | D53: SIDDHARTHA LOGISTICS FTWZ PRIVATE | E53: 2025 | F53: 11 | G53: 45980 | H53: 1800014864 | I53: DR | J53: 45980 | K53: 45982 | L53: NA | M53: 256779419365 | N53: 212100 | O53: Trade Debtors (Ctrl) | Q53: 01 | R53: USD | S53: 292.99 | T53: INR | U53: 25784.11 | V53: O0 | W53: 6779224500 | Y53: 2128982 | Z53: 1 | AA53: =S53 -> 292.99 | AB53: MH43CE4486(ONEU1505971) Without de-stuffing Invoic | AF53: 45980
A54: Not Selected | B54: 6779 | C54: 100222345 | D54: SIDDHARTHA LOGISTICS FTWZ PRIVATE | E54: 2025 | F54: 4 | G54: 45762 | H54: 1800006269 | I54: DR | J54: 45762 | K54: 45763 | L54: NA | M54: 256779411160 | N54: 212100 | O54: Trade Debtors (Ctrl) | Q54: 01 | R54: USD | S54: 18.38 | T54: INR | U54: 1597.62 | V54: O0 | Y54: NA | Z54: 1 | AA54: =S54 -> 18.38 | AB54: LCL Charges August 2024 | AF54: 45762
A55: Not Selected | B55: 6779 | C55: 100222345 | D55: SIDDHARTHA LOGISTICS FTWZ PRIVATE | E55: 2025 | F55: 4 | G55: 45762 | H55: 1800006270 | I55: DR | J55: 45762 | K55: 45763 | L55: NA | M55: 256779411161 | N55: 212100 | O55: Trade Debtors (Ctrl) | Q55: 01 | R55: USD | S55: 46.76 | T55: INR | U55: 4064.46 | V55: O0 | Y55: NA | Z55: 1 | AA55: =S55 -> 46.76 | AB55: Inbound Handling for August 24 | AF55: 45762
A56: Not Selected | B56: 6779 | C56: 100222345 | D56: SIDDHARTHA LOGISTICS FTWZ PRIVATE | E56: 2025 | F56: 4 | G56: 45762 | H56: 1800006271 | I56: DR | J56: 45762 | K56: 45763 | L56: NA | M56: 256779411162 | N56: 212100 | O56: Trade Debtors (Ctrl) | Q56: 01 | R56: USD | S56: 35.25 | T56: INR | U56: 3063.99 | V56: O0 | Y56: NA | Z56: 1 | AA56: =S56 -> 35.25 | AB56: LCL Charges August 2024 | AF56: 45762
A57: Not Selected | B57: 6779 | C57: 100222345 | D57: SIDDHARTHA LOGISTICS FTWZ PRIVATE | E57: 2025 | F57: 4 | G57: 45762 | H57: 1800006272 | I57: DR | J57: 45762 | K57: 45763 | L57: NA | M57: 256779411163 | N57: 212100 | O57: Trade Debtors (Ctrl) | Q57: 01 | R57: USD | S57: 24 | T57: INR | U57: 2086.12 | V57: O0 | Y57: NA | Z57: 1 | AA57: =S57 -> 24 | AB57: LCL Charges August 2024 | AF57: 45762
A58: Not Selected | B58: 6779 | C58: 100222345 | D58: SIDDHARTHA LOGISTICS FTWZ PRIVATE | E58: 2025 | F58: 4 | G58: 45762 | H58: 1800006273 | I58: DR | J58: 45762 | K58: 45763 | L58: NA | M58: 256779411164 | N58: 212100 | O58: Trade Debtors (Ctrl) | Q58: 01 | R58: USD | S58: 33 | T58: INR | U58: 2868.42 | V58: O0 | Y58: NA | Z58: 1 | AA58: =S58 -> 33 | AB58: LCL Charges August 2024 | AF58: 45762
A59: Not Selected | B59: 6779 | C59: 100222345 | D59: SIDDHARTHA LOGISTICS FTWZ PRIVATE | E59: 2025 | F59: 4 | G59: 45762 | H59: 1800006696 | I59: DR | J59: 45762 | K59: 45763 | L59: NA | M59: 256779411587 | N59: 212100 | O59: Trade Debtors (Ctrl) | Q59: 01 | R59: USD | S59: 2.25 | T59: INR | U59: 195.57 | V59: O0 | Y59: NA | Z59: 1 | AA59: =S59 -> 2.25 | AB59: Outbound Handling Charges Aug 2024 | AF59: 45762
A60: Not Selected | B60: 6779 | C60: 100222345 | D60: SIDDHARTHA LOGISTICS FTWZ PRIVATE | E60: 2025 | F60: 4 | G60: 45762 | H60: 1800006697 | I60: DR | J60: 45762 | K60: 45763 | L60: NA | M60: 256779411588 | N60: 212100 | O60: Trade Debtors (Ctrl) | Q60: 01 | R60: USD | S60: 2.25 | T60: INR | U60: 195.57 | V60: O0 | Y60: NA | Z60: 1 | AA60: =S60 -> 2.25 | AB60: Outbound Handling Charges Aug 2024 | AF60: 45762
A61: Not Selected | B61: 6779 | C61: 100222345 | D61: SIDDHARTHA LOGISTICS FTWZ PRIVATE | E61: 2025 | F61: 4 | G61: 45762 | H61: 1800006698 | I61: DR | J61: 45762 | K61: 45763 | L61: NA | M61: 256779411589 | N61: 212100 | O61: Trade Debtors (Ctrl) | Q61: 01 | R61: USD | S61: 3.38 | T61: INR | U61: 293.8 | V61: O0 | Y61: NA | Z61: 1 | AA61: =S61 -> 3.38 | AB61: Outbound Handling Charges Aug 2024 | AF61: 45762
A62: Not Selected | B62: 6779 | C62: 100222345 | D62: SIDDHARTHA LOGISTICS FTWZ PRIVATE | E62: 2025 | F62: 4 | G62: 45762 | H62: 1800006699 | I62: DR | J62: 45762 | K62: 45763 | L62: NA | M62: 256779411590 | N62: 212100 | O62: Trade Debtors (Ctrl) | Q62: 01 | R62: USD | S62: 2.25 | T62: INR | U62: 195.57 | V62: O0 | Y62: NA | Z62: 1 | AA62: =S62 -> 2.25 | AB62: Outbound Handling Charges Aug 2024 | AF62: 45762
A63: Not Selected | B63: 6779 | C63: 100222345 | D63: SIDDHARTHA LOGISTICS FTWZ PRIVATE | E63: 2025 | F63: 4 | G63: 45762 | H63: 1800006700 | I63: DR | J63: 45762 | K63: 45763 | L63: NA | M63: 256779411591 | N63: 212100 | O63: Trade Debtors (Ctrl) | Q63: 01 | R63: USD | S63: 3 | T63: INR | U63: 260.77 | V63: O0 | Y63: NA | Z63: 1 | AA63: =S63 -> 3 | AB63: Outbound Handling Charges Aug 2024 | AF63: 45762
A64: Not Selected | B64: 6779 | C64: 100222345 | D64: SIDDHARTHA LOGISTICS FTWZ PRIVATE | E64: 2025 | F64: 4 | G64: 45762 | H64: 1800006701 | I64: DR | J64: 45762 | K64: 45763 | L64: NA | M64: 256779411592 | N64: 212100 | O64: Trade Debtors (Ctrl) | Q64: 01 | R64: USD | S64: 9.59 | T64: INR | U64: 833.58 | V64: O0 | Y64: NA | Z64: 1 | AA64: =S64 -> 9.59 | AB64: Outbound Handling Charges Aug 2024 | AF64: 45762
A65: Not Selected | B65: 6779 | C65: 100222345 | D65: SIDDHARTHA LOGISTICS FTWZ PRIVATE | E65: 2025 | F65: 4 | G65: 45762 | H65: 1800006702 | I65: DR | J65: 45762 | K65: 45763 | L65: NA | M65: 256779411593 | N65: 212100 | O65: Trade Debtors (Ctrl) | Q65: 01 | R65: USD | S65: 3 | T65: INR | U65: 260.77 | V65: O0 | Y65: NA | Z65: 1 | AA65: =S65 -> 3 | AB65: Outbound Handling Charges Aug 2024 | AF65: 45762
... A69: Not Selected | B69: 6779 | C69: 100222345 | D69: SIDDHARTHA LOGISTICS FTWZ PRIVATE | E69: 2025 | F69: 4 | G69: 45762 | H69: 1800006706 | I69: DR | J69: 45762 | K69: 45763 | L69: NA | M69: 256779411597 | N69: 212100 | O69: Trade Debtors (Ctrl) | Q69: 01 | R69: USD | S69: 19.95 | T69: INR | U69: 1734.09 | V69: O0 | Y69: NA | Z69: 1 | AA69: =S69 -> 19.95 | AB69: Outbound Handling Charges Aug 2024 | AF69: 45762
A70: Not Selected | B70: 6779 | C70: 100222345 | D70: SIDDHARTHA LOGISTICS FTWZ PRIVATE | E70: 2025 | F70: 4 | G70: 45763 | H70: 1800006920 | I70: DR | J70: 45763 | K70: 45764 | L70: NA | M70: 256779411811 | N70: 212100 | O70: Trade Debtors (Ctrl) | Q70: 01 | R70: USD | S70: 3.24 | T70: INR | U70: 281.63 | V70: O0 | W70: 6779224500 | Y70: NA | Z70: 1 | AA70: =S70 -> 3.24 | AB70: Inbound Handling charges for Dec 2024 | AF70: 45763
A71: Not Selected | B71: 6779 | C71: 100222345 | D71: SIDDHARTHA LOGISTICS FTWZ PRIVATE | E71: 2025 | F71: 4 | G71: 45763 | H71: 1800006921 | I71: DR | J71: 45763 | K71: 45764 | L71: NA | M71: 256779411812 | N71: 212100 | O71: Trade Debtors (Ctrl) | Q71: 01 | R71: USD | S71: 15 | T71: INR | U71: 1303.83 | V71: O0 | W71: 6779224500 | Y71: NA | Z71: 1 | AA71: =S71 -> 15 | AB71: LCL charges for Dec 2024 | AF71: 45763
A72: Not Selected | B72: 6779 | C72: 100222345 | D72: SIDDHARTHA LOGISTICS FTWZ PRIVATE | E72: 2025 | F72: 4 | G72: 45763 | H72: 1800006999 | I72: DR | J72: 45763 | K72: 45764 | L72: NA | M72: 256779411890 | N72: 212100 | O72: Trade Debtors (Ctrl) | Q72: 01 | R72: USD | S72: 24.75 | T72: INR | U72: 2151.32 | V72: O0 | W72: 6779224500 | Y72: NA | Z72: 1 | AA72: =S72 -> 24.75 | AB72: Outbound Handling charges for Dec 2024 | AF72: 45763
A73: Not Selected | B73: 6779 | C73: 100222345 | D73: SIDDHARTHA LOGISTICS FTWZ PRIVATE | E73: 2025 | F73: 4 | G73: 45763 | H73: 1800007000 | I73: DR | J73: 45763 | K73: 45764 | L73: NA | M73: 256779411891 | N73: 212100 | O73: Trade Debtors (Ctrl) | Q73: 01 | R73: USD | S73: 2.25 | T73: INR | U73: 195.57 | V73: O0 | W73: 6779224500 | Y73: NA | Z73: 1 | AA73: =S73 -> 2.25 | AB73: Loose loading Handling charges for Dec 2024 | AF73: 45763
A74: Not Selected | B74: 6779 | C74: 100222345 | D74: SIDDHARTHA LOGISTICS FTWZ PRIVATE | E74: 2025 | F74: 4 | G74: 45763 | H74: 1800007212 | I74: DR | J74: 45763 | K74: 45764 | L74: NA | M74: 256779412103 | N74: 212100 | O74: Trade Debtors (Ctrl) | Q74: 01 | R74: USD | S74: 42.53 | T74: INR | U74: 3696.79 | V74: O0 | W74: 6779224500 | Y74: NA | Z74: 1 | AA74: =S74 -> 42.53 | AB74: VAS Activity - Mar 25, 16-31, Ex Rate. 85.58 | AF74: 45763
A75: Not Selected | B75: 6779 | C75: 100222345 | D75: SIDDHARTHA LOGISTICS FTWZ PRIVATE | E75: 2025 | F75: 4 | G75: 45763 | H75: 1800007222 | I75: DR | J75: 45763 | K75: 45764 | L75: NA | M75: 256779412113 | N75: 212100 | O75: Trade Debtors (Ctrl) | Q75: 01 | R75: USD | S75: 827.48 | T75: INR | U75: 71926.07 | V75: O0 | W75: 6779224500 | Y75: NA | Z75: 1 | AA75: =S75 -> 827.48 | AB75: Storage Charges Mar, 25 Exch Rate 85.58 | AF75: 45763
A76: Not Selected | B76: 6779 | C76: 100222345 | D76: SIDDHARTHA LOGISTICS FTWZ PRIVATE | E76: 2025 | F76: 3 | G76: 45730 | H76: 1800001786 | I76: DR | J76: 45730 | K76: 45733 | L76: NA | M76: 246779411451 | N76: 212100 | O76: Trade Debtors (Ctrl) | Q76: 01 | R76: USD | S76: 2.86 | T76: INR | U76: 247.94 | V76: O0 | W76: 6779224500 | Y76: NA | Z76: 1 | AA76: =S76 -> 2.86 | AB76: VAS Activity Charges for the month of August, 24 | AF76: 45730
A77: Not Selected | B77: 6779 | C77: 100222345 | D77: SIDDHARTHA LOGISTICS FTWZ PRIVATE | E77: 2025 | F77: 3 | G77: 45730 | H77: 1800001787 | I77: DR | J77: 45730 | K77: 45733 | L77: NA | M77: 246779411452 | N77: 212100 | O77: Trade Debtors (Ctrl) | Q77: 01 | R77: USD | S77: 0.95 | T77: INR | U77: 82.36 | V77: O0 | W77: 6779224500 | Y77: NA | Z77: 1 | AA77: =S77 -> 0.95 | AB77: VAS Activity Charges for the month of August, 24 | AF77: 45730
A78: Not Selected | B78: 6779 | C78: 100222345 | D78: SIDDHARTHA LOGISTICS FTWZ PRIVATE | E78: 2025 | F78: 3 | G78: 45730 | H78: 1800001788 | I78: DR | J78: 45730 | K78: 45733 | L78: NA | M78: 246779411453 | N78: 212100 | O78: Trade Debtors (Ctrl) | Q78: 01 | R78: USD | S78: 4.77 | T78: INR | U78: 413.52 | V78: O0 | W78: 6779224500 | Y78: NA | Z78: 1 | AA78: =S78 -> 4.77 | AB78: VAS Activity Charges for the month of August, 24 | AF78: 45730
A79: Not Selected | B79: 6779 | C79: 100222345 | D79: SIDDHARTHA LOGISTICS FTWZ PRIVATE | E79: 2025 | F79: 3 | G79: 45730 | H79: 1800001789 | I79: DR | J79: 45730 | K79: 45733 | L79: NA | M79: 246779411454 | N79: 212100 | O79: Trade Debtors (Ctrl) | Q79: 01 | R79: USD | S79: 1.91 | T79: INR | U79: 165.58 | V79: O0 | W79: 6779224500 | Y79: NA | Z79: 1 | AA79: =S79 -> 1.91 | AB79: VAS Activity Charges for the month of August, 24 | AF79: 45730
A80: Not Selected | B80: 6779 | C80: 100222345 | D80: SIDDHARTHA LOGISTICS FTWZ PRIVATE | E80: 2025 | F80: 3 | G80: 45730 | H80: 1800001790 | I80: DR | J80: 45730 | K80: 45733 | L80: NA | M80: 246779411455 | N80: 212100 | O80: Trade Debtors (Ctrl) | Q80: 01 | R80: USD | S80: 1.91 | T80: INR | U80: 165.58 | V80: O0 | W80: 6779224500 | Y80: NA | Z80: 1 | AA80: =S80 -> 1.91 | AB80: VAS Activity Charges for the month of August, 24 | AF80: 45730
A81: Not Selected | B81: 6779 | C81: 100222345 | D81: SIDDHARTHA LOGISTICS FTWZ PRIVATE | E81: 2025 | F81: 3 | G81: 45730 | H81: 1800001791 | I81: DR | J81: 45730 | K81: 45733 | L81: NA | M81: 246779411456 | N81: 212100 | O81: Trade Debtors (Ctrl) | Q81: 01 | R81: USD | S81: 4.77 | T81: INR | U81: 413.52 | V81: O0 | W81: 6779224500 | Y81: NA | Z81: 1 | AA81: =S81 -> 4.77 | AB81: VAS Activity Charges for the month of August, 24 | AF81: 45730
A82: Selected | B82: 6779 | C82: 100222345 | D82: SIDDHARTHA LOGISTICS FTWZ PRIVATE | E82: 2025 | F82: 3 | G82: 45730 | H82: 1800001583 | I82: DR | J82: 45730 | K82: 45735 | L82: NA | M82: 246779412240 | N82: 212100 | O82: Trade Debtors (Ctrl) | Q82: 01 | R82: USD | S82: 2.86 | T82: INR | U82: 247.94 | V82: O0 | W82: 6779224500 | Y82: NA | Z82: 1 | AA82: =S82 -> 2.86 | AB82: VAS Activity Charges for the month of August, 24 | AF82: 45730 | AG82: 45861 | AH82: 1400000797
A83: Selected | B83: 6779 | C83: 100222345 | D83: SIDDHARTHA LOGISTICS FTWZ PRIVATE | E83: 2025 | F83: 3 | G83: 45730 | H83: 1800001584 | I83: DR | J83: 45730 | K83: 45735 | L83: NA | M83: 246779412241 | N83: 212100 | O83: Trade Debtors (Ctrl) | Q83: 01 | R83: USD | S83: 0.95 | T83: INR | U83: 82.36 | V83: O0 | W83: 6779224500 | Y83: NA | Z83: 1 | AA83: =S83 -> 0.95 | AB83: VAS Activity Charges for the month of August, 24 | AF83: 45730 | AG83: 45861 | AH83: 1400000797
A84: Selected | B84: 6779 | C84: 100222345 | D84: SIDDHARTHA LOGISTICS FTWZ PRIVATE | E84: 2025 | F84: 3 | G84: 45730 | H84: 1800001585 | I84: DR | J84: 45730 | K84: 45735 | L84: NA | M84: 246779412242 | N84: 212100 | O84: Trade Debtors (Ctrl) | Q84: 01 | R84: USD | S84: 4.77 | T84: INR | U84: 413.52 | V84: O0 | W84: 6779224500 | Y84: NA | Z84: 1 | AA84: =S84 -> 4.77 | AB84: VAS Activity Charges for the month of August, 24 | AF84: 45730 | AG84: 45861 | AH84: 1400000797
A85: Selected | B85: 6779 | C85: 100222345 | D85: SIDDHARTHA LOGISTICS FTWZ PRIVATE | E85: 2025 | F85: 3 | G85: 45730 | H85: 1800001586 | I85: DR | J85: 45730 | K85: 45735 | L85: NA | M85: 246779412243 | N85: 212100 | O85: Trade Debtors (Ctrl) | Q85: 01 | R85: USD | S85: 1.91 | T85: INR | U85: 165.58 | V85: O0 | W85: 6779224500 | Y85: NA | Z85: 1 | AA85: =S85 -> 1.91 | AB85: VAS Activity Charges for the month of August, 24 | AF85: 45730 | AG85: 45861 | AH85: 1400000797
A86: Selected | B86: 6779 | C86: 100222345 | D86: SIDDHARTHA LOGISTICS FTWZ PRIVATE | E86: 2025 | F86: 3 | G86: 45730 | H86: 1800001587 | I86: DR | J86: 45730 | K86: 45735 | L86: NA | M86: 246779412244 | N86: 212100 | O86: Trade Debtors (Ctrl) | Q86: 01 | R86: USD | S86: 1.91 | T86: INR | U86: 165.58 | V86: O0 | W86: 6779224500 | Y86: NA | Z86: 1 | AA86: =S86 -> 1.91 | AB86: VAS Activity Charges for the month of August, 24 | AF86: 45730 | AG86: 45861 | AH86: 1400000797
A87: Selected | B87: 6779 | C87: 100222345 | D87: SIDDHARTHA LOGISTICS FTWZ PRIVATE | E87: 2025 | F87: 3 | G87: 45730 | H87: 1800001588 | I87: DR | J87: 45730 | K87: 45735 | L87: NA | M87: 246779412245 | N87: 212100 | O87: Trade Debtors (Ctrl) | Q87: 01 | R87: USD | S87: 4.77 | T87: INR | U87: 413.52 | V87: O0 | W87: 6779224500 | Y87: NA | Z87: 1 | AA87: =S87 -> 4.77 | AB87: VAS Activity Charges for the month of August, 24 | AF87: 45730 | AG87: 45861 | AH87: 1400000797
A88: Not Selected | B88: 6779 | C88: 100222345 | D88: SIDDHARTHA LOGISTICS FTWZ PRIVATE | E88: 2025 | F88: 9 | G88: 45904 | H88: 1800012276 | I88: DR | J88: 45904 | K88: 45908 | L88: NA | M88: 256779416912 | N88: 212100 | O88: Trade Debtors (Ctrl) | Q88: 01 | R88: USD | S88: 44.96 | T88: INR | U88: 3934.64 | V88: O0 | W88: 6779224500 | Y88: NA | Z88: 1 | AA88: =S88 -> 44.96 | AB88: CODC LCL Chgs - 16-31 Aug 25 | AF88: 45904
A89: Not Selected | B89: 6779 | C89: 100222345 | D89: SIDDHARTHA LOGISTICS FTWZ PRIVATE | E89: 2025 | F89: 9 | G89: 45904 | H89: 1800012287 | I89: DR | J89: 45904 | K89: 45908 | L89: NA | M89: 256779416949 | N89: 212100 | O89: Trade Debtors (Ctrl) | Q89: 01 | R89: USD | S89: 30.16 | T89: INR | U89: 2639.43 | V89: O0 | W89: 6779224500 | Y89: NA | Z89: 1 | AA89: =S89 -> 30.16 | AB89: CODC Out chgs -16-31 Aug 25 | AF89: 45904
A90: Not Selected | B90: 6779 | C90: 100222345 | D90: SIDDHARTHA LOGISTICS FTWZ PRIVATE | E90: 2025 | F90: 9 | G90: 45904 | H90: 1800012532 | I90: DR | J90: 45904 | K90: 45909 | L90: NA | M90: 256779417136 | N90: 212100 | O90: Trade Debtors (Ctrl) | Q90: 01 | R90: USD | S90: 1.71 | T90: INR | U90: 149.65 | V90: O0 | W90: 6779224500 | Y90: NA | Z90: 1 | AA90: =S90 -> 1.71 | AB90: VAS - 16-31 Aug 25 | AF90: 45904
A91: Not Selected | B91: 6779 | C91: 100222345 | D91: SIDDHARTHA LOGISTICS FTWZ PRIVATE | E91: 2025 | F91: 9 | G91: 45904 | H91: 1800012462 | I91: DR | J91: 45904 | K91: 45909 | L91: NA | M91: 256779417162 | N91: 212100 | O91: Trade Debtors (Ctrl) | Q91: 01 | R91: USD | S91: 44.74 | T91: INR | U91: 3915.39 | V91: O0 | W91: 6779224500 | Y91: NA | Z91: 1 | AA91: =S91 -> 44.74 | AB91: VAS -16-31 Aug 25 | AF91: 45904
A92: Not Selected | B92: 6779 | C92: 100222345 | D92: SIDDHARTHA LOGISTICS FTWZ PRIVATE | E92: 2025 | F92: 9 | G92: 45904 | H92: 1800012688 | I92: DR | J92: 45904 | K92: 45909 | L92: NA | M92: 256779417328 | N92: 212100 | O92: Trade Debtors (Ctrl) | Q92: 01 | R92: USD | S92: 2.25 | T92: INR | U92: 196.91 | V92: O0 | W92: 6779224500 | Y92: 2096996 | Z92: 1 | AA92: =S92 -> 2.25 | AB92: Outbound chgs - 16 - 31 Aug 25 | AF92: 45904
A93: Not Selected | B93: 6779 | C93: 100222345 | D93: SIDDHARTHA LOGISTICS FTWZ PRIVATE | E93: 2025 | F93: 7 | G93: 45842 | H93: 1800010069 | I93: DR | J93: 45842 | K93: 45845 | L93: NA | M93: 256779414833 | N93: 212100 | O93: Trade Debtors (Ctrl) | Q93: 01 | R93: USD | S93: 3 | T93: INR | U93: 258 | V93: O0 | W93: 6779224500 | Y93: NA | Z93: 1 | AA93: =S93 -> 3 | AB93: Outbound chgs - 01 - 15 Jun 25 | AF93: 45842
A94: Not Selected | B94: 6779 | C94: 100222345 | D94: SIDDHARTHA LOGISTICS FTWZ PRIVATE | E94: 2025 | F94: 7 | G94: 45842 | H94: 1800010430 | I94: DR | J94: 45842 | K94: 45847 | L94: NA | M94: 256779415190 | N94: 212100 | O94: Trade Debtors (Ctrl) | Q94: 01 | R94: USD | S94: 690.7 | T94: INR | U94: 59400.66 | V94: O0 | W94: 6779224500 | Y94: NA | Z94: 1 | AA94: =S94 -> 690.7 | AB94: Unit Storage - 1-30 June 25 | AF94: 45842
A95: Not Selected | B95: 6779 | C95: 100222345 | D95: SIDDHARTHA LOGISTICS FTWZ PRIVATE | E95: 2025 | F95: 11 | G95: 45966 | H95: 1800014284 | I95: DR | J95: 45966 | K95: 45967 | L95: NA | M95: 256779418821 | N95: 212100 | O95: Trade Debtors (Ctrl) | Q95: 01 | R95: USD | S95: 49.59 | T95: INR | U95: 4364.09 | V95: O0 | W95: 6779224500 | Y95: 2123387 | Z95: 1 | AA95: =S95 -> 49.59 | AB95: VAS-16 -31 Oct 25 | AF95: 45966
A96: Not Selected | B96: 6779 | C96: 100222345 | D96: SIDDHARTHA LOGISTICS FTWZ PRIVATE | E96: 2025 | F96: 11 | G96: 45966 | H96: 1800014290 | I96: DR | J96: 45966 | K96: 45967 | L96: NA | M96: 256779418827 | N96: 212100 | O96: Trade Debtors (Ctrl) | Q96: 01 | R96: USD | S96: 60.86 | T96: INR | U96: 5355.89 | V96: O0 | W96: 6779224500 | Y96: 2123387 | Z96: 1 | AA96: =S96 -> 60.86 | AB96: WEIGHTMENT-16 -31 Oct 25 | AF96: 45966
A97: Not Selected | B97: 6779 | C97: 100222345 | D97: SIDDHARTHA LOGISTICS FTWZ PRIVATE | E97: 2025 | F97: 11 | G97: 45966 | H97: 1800014538 | I97: DR | J97: 45966 | K97: 45967 | L97: NA | M97: 256779418870 | N97: 212100 | O97: Trade Debtors (Ctrl) | Q97: 01 | R97: USD | S97: 493.91 | T97: INR | U97: 43465.75 | V97: O0 | W97: 6779224500 | Y97: 2123390 | Z97: 1 | AA97: =S97 -> 493.91 | AB97: Unit Storage - 1-31 Oct 2025 | AF97: 45966
A98: Not Selected | B98: 6779 | C98: 100222345 | D98: SIDDHARTHA LOGISTICS FTWZ PRIVATE | E98: 2025 | F98: 11 | G98: 45966 | H98: 1800014270 | I98: DR | J98: 45966 | K98: 45967 | L98: NA | M98: 256779418945 | N98: 212100 | O98: Trade Debtors (Ctrl) | Q98: 01 | R98: USD | S98: 293.04 | T98: INR | U98: 25788.51 | V98: O0 | W98: 6779224500 | Y98: NA | Z98: 1 | AA98: =S98 -> 293.04 | AB98: ONEU5912276 Without de-stuffing | AF98: 45966
A99: Not Selected | B99: 6779 | C99: 100222345 | D99: SIDDHARTHA LOGISTICS FTWZ PRIVATE | E99: 2025 | F99: 11 | G99: 45966 | H99: 1800014271 | I99: DR | J99: 45966 | K99: 45967 | L99: NA | M99: 256779418946 | N99: 212100 | O99: Trade Debtors (Ctrl) | Q99: 01 | R99: USD | S99: 293.04 | T99: INR | U99: 25788.51 | V99: O0 | W99: 6779224500 | Y99: NA | Z99: 1 | AA99: =S99 -> 293.04 | AB99: UACU6030817 Without de-stuffing | AF99: 45966
... A114: Not Selected | B114: 6779 | C114: 100222345 | D114: SIDDHARTHA LOGISTICS FTWZ PRIVATE | E114: 2025 | F114: 6 | G114: 45812 | H114: 1800009243 | I114: DR | J114: 45812 | K114: 45817 | L114: NA | M114: 256779414007 | N114: 212100 | O114: Trade Debtors (Ctrl) | Q114: 01 | R114: USD | S114: 790.89 | T114: INR | U114: 67613.8 | V114: O0 | W114: 6779224500 | Y114: NA | Z114: 1 | AA114: =S114 -> 790.89 | AB114: Storage- Dec-24, | AF114: 45812
A115: Selected | B115: 6779 | C115: 100222345 | D115: SIDDHARTHA LOGISTICS FTWZ PRIVATE | E115: 2025 | F115: 5 | G115: 45791 | H115: 1600000602 | I115: DG | J115: 45791 | K115: 45793 | L115: NA | M115: 256779420311 | N115: 212100 | O115: Trade Debtors (Ctrl) | Q115: 11 | R115: USD | S115: -1.91 | T115: INR | U115: -165.58 | V115: O0 | W115: 6779224500 | Y115: NA | Z115: 1 | AA115: =S115 -> -1.91 | AB115: Credit note against 246779412244 | AF115: 45791 | AG115: 45861 | AH115: 1400000797
A116: Selected | B116: 6779 | C116: 100222345 | D116: SIDDHARTHA LOGISTICS FTWZ PRIVATE | E116: 2025 | F116: 5 | G116: 45791 | H116: 1600000598 | I116: DG | J116: 45791 | K116: 45793 | L116: NA | M116: 256779420307 | N116: 212100 | O116: Trade Debtors (Ctrl) | Q116: 11 | R116: USD | S116: -2.86 | T116: INR | U116: -247.94 | V116: O0 | W116: 6779224500 | Y116: NA | Z116: 1 | AA116: =S116 -> -2.86 | AB116: Credit note against 246779412240 | AF116: 45791 | AG116: 45861 | AH116: 1400000797
A117: Selected | B117: 6779 | C117: 100222345 | D117: SIDDHARTHA LOGISTICS FTWZ PRIVATE | E117: 2025 | F117: 5 | G117: 45791 | H117: 1600000599 | I117: DG | J117: 45791 | K117: 45793 | L117: NA | M117: 256779420308 | N117: 212100 | O117: Trade Debtors (Ctrl) | Q117: 11 | R117: USD | S117: -0.95 | T117: INR | U117: -82.36 | V117: O0 | W117: 6779224500 | Y117: NA | Z117: 1 | AA117: =S117 -> -0.95 | AB117: Credit note against 246779412241 | AF117: 45791 | AG117: 45861 | AH117: 1400000797
...

Sheet TDS
F1: =SUM(F3:F153) -> 3385.1759
A2: Invoice No | B2: Invoice Date | C2: Debit (USD) | D2: Credit (USD) | E2: Xlookup | F2: TDS | G2: Rate
A3: 246779410007 | B3: 45708 | D3: 1071.43 | E3: =_xlfn.XLOOKUP(A3,'CL Ledger'!$M:$M,'CL Ledger'!$AA:$AA,,0) -> 1190.48 | F3: =E3-D3 -> 119.05 | G3: =F3/E3 -> 0.10000168
A4: 246779410138 | B4: 45708 | D4: 1071.43 | E4: =_xlfn.XLOOKUP(A4,'CL Ledger'!$M:$M,'CL Ledger'!$AA:$AA,,0) -> 1190.48 | F4: =E4-D4 -> 119.05 | G4: =F4/E4 -> 0.10000168
A5: 246779410095 | B5: 45708 | D5: 1071.43 | E5: =_xlfn.XLOOKUP(A5,'CL Ledger'!$M:$M,'CL Ledger'!$AA:$AA,,0) -> 1190.48 | F5: =E5-D5 -> 119.05 | G5: =F5/E5 -> 0.10000168
A6: 246779410274 | B6: 45708 | D6: 1071.43 | E6: =_xlfn.XLOOKUP(A6,'CL Ledger'!$M:$M,'CL Ledger'!$AA:$AA,,0) -> 1190.48 | F6: =E6-D6 -> 119.05 | G6: =F6/E6 -> 0.10000168
A7: 246779410027 | B7: 45708 | D7: 1071.43 | E7: =_xlfn.XLOOKUP(A7,'CL Ledger'!$M:$M,'CL Ledger'!$AA:$AA,,0) -> 1190.48 | F7: =E7-D7 -> 119.05 | G7: =F7/E7 -> 0.10000168
A8: 246779410181 | B8: 45708 | D8: 1049.93 | E8: =_xlfn.XLOOKUP(A8,'CL Ledger'!$M:$M,'CL Ledger'!$AA:$AA,,0) -> 1166.59 | F8: =E8-D8 -> 116.66 | G8: =F8/E8 -> 0.10000086
A9: 246779410224 | B9: 45708 | D9: 1028.81 | E9: =_xlfn.XLOOKUP(A9,'CL Ledger'!$M:$M,'CL Ledger'!$AA:$AA,,0) -> 1143.12 | F9: =E9-D9 -> 114.31 | G9: =F9/E9 -> 0.09999825
A10: 246779410614 | B10: 45719 | D10: 2.2 | E10: =_xlfn.XLOOKUP(A10,'CL Ledger'!$M:$M,'CL Ledger'!$AA:$AA,,0) -> 2.25 | F10: =E10-D10 -> 0.05 | G10: =F10/E10 -> 0.022222222
A11: 246779410615 | B11: 45719 | D11: 8.81 | E11: =_xlfn.XLOOKUP(A11,'CL Ledger'!$M:$M,'CL Ledger'!$AA:$AA,,0) -> 9 | F11: =E11-D11 -> 0.19 | G11: =F11/E11 -> 0.021111111
A12: 246779410511 | B12: 45719 | D12: 13.63 | E12: =_xlfn.XLOOKUP(A12,'CL Ledger'!$M:$M,'CL Ledger'!$AA:$AA,,0) -> 13.91 | F12: =E12-D12 -> 0.28 | G12: =F12/E12 -> 0.020129403
A13: 246779410510 | B13: 45719 | D13: 191 | E13: =_xlfn.XLOOKUP(A13,'CL Ledger'!$M:$M,'CL Ledger'!$AA:$AA,,0) -> 194.9 | F13: =E13-D13 -> 3.9 | G13: =F13/E13 -> 0.020010262
A14: 246779410368 | B14: 45719 | D14: 320.78 | E14: =_xlfn.XLOOKUP(A14,'CL Ledger'!$M:$M,'CL Ledger'!$AA:$AA,,0) -> 356.43 | F14: =E14-D14 -> 35.65 | G14: =F14/E14 -> 0.10001964
... A153: 256779422210 | B153: 46053 | D153: -22.64 | E153: =_xlfn.XLOOKUP(A153,'CL Ledger'!$M:$M,'CL Ledger'!$AA:$AA,,0) -> -22.64 | F153: =E153-D153 -> 0 | G153: =F153/E153 -> 0
D154: =SUM(D3:D153) -> 33836.943 | E154: =SUM(E3:E153) -> 37222.119 | F154: =SUM(F3:F153)+0.31 -> 3385.4859

Sheet Customer ledger
A2: Invoice No | B2: Invoice Dt | C2: Debit (USD) | D2: Credit (USD) | E2: Xlookup | F2: TDS | G2: Rate
A3: 246779410007 | B3: 45708 | D3: 1071.43 | E3: =_xlfn.XLOOKUP(A3,'CL Ledger'!$M:$M,'CL Ledger'!$AA:$AA,,0) -> 1190.48 | F3: =E3-D3 -> 119.05 | G3: =F3/E3 -> 0.10000168
A4: 246779410138 | B4: 45708 | D4: 1071.43 | E4: =_xlfn.XLOOKUP(A4,'CL Ledger'!$M:$M,'CL Ledger'!$AA:$AA,,0) -> 1190.48 | F4: =E4-D4 -> 119.05 | G4: =F4/E4 -> 0.10000168
A5: 246779410095 | B5: 45708 | D5: 1071.43 | E5: =_xlfn.XLOOKUP(A5,'CL Ledger'!$M:$M,'CL Ledger'!$AA:$AA,,0) -> 1190.48 | F5: =E5-D5 -> 119.05 | G5: =F5/E5 -> 0.10000168
A6: 246779410274 | B6: 45708 | D6: 1071.43 | E6: =_xlfn.XLOOKUP(A6,'CL Ledger'!$M:$M,'CL Ledger'!$AA:$AA,,0) -> 1190.48 | F6: =E6-D6 -> 119.05 | G6: =F6/E6 -> 0.10000168
A7: 246779410027 | B7: 45708 | D7: 1071.43 | E7: =_xlfn.XLOOKUP(A7,'CL Ledger'!$M:$M,'CL Ledger'!$AA:$AA,,0) -> 1190.48 | F7: =E7-D7 -> 119.05 | G7: =F7/E7 -> 0.10000168
A8: 246779410181 | B8: 45708 | D8: 1049.93 | E8: =_xlfn.XLOOKUP(A8,'CL Ledger'!$M:$M,'CL Ledger'!$AA:$AA,,0) -> 1166.59 | F8: =E8-D8 -> 116.66 | G8: =F8/E8 -> 0.10000086
A9: 246779410224 | B9: 45708 | D9: 1028.81 | E9: =_xlfn.XLOOKUP(A9,'CL Ledger'!$M:$M,'CL Ledger'!$AA:$AA,,0) -> 1143.12 | F9: =E9-D9 -> 114.31 | G9: =F9/E9 -> 0.09999825
A10: 246779410614 | B10: 45719 | D10: 2.2 | E10: =_xlfn.XLOOKUP(A10,'CL Ledger'!$M:$M,'CL Ledger'!$AA:$AA,,0) -> 2.25 | F10: =E10-D10 -> 0.05 | G10: =F10/E10 -> 0.022222222
A11: 246779410615 | B11: 45719 | D11: 8.81 | E11: =_xlfn.XLOOKUP(A11,'CL Ledger'!$M:$M,'CL Ledger'!$AA:$AA,,0) -> 9 | F11: =E11-D11 -> 0.19 | G11: =F11/E11 -> 0.021111111
A12: 246779410511 | B12: 45719 | D12: 13.63 | E12: =_xlfn.XLOOKUP(A12,'CL Ledger'!$M:$M,'CL Ledger'!$AA:$AA,,0) -> 13.91 | F12: =E12-D12 -> 0.28 | G12: =F12/E12 -> 0.020129403
A13: 246779410510 | B13: 45719 | D13: 191 | E13: =_xlfn.XLOOKUP(A13,'CL Ledger'!$M:$M,'CL Ledger'!$AA:$AA,,0) -> 194.9 | F13: =E13-D13 -> 3.9 | G13: =F13/E13 -> 0.020010262
A14: 246779410368 | B14: 45719 | D14: 320.78 | E14: =_xlfn.XLOOKUP(A14,'CL Ledger'!$M:$M,'CL Ledger'!$AA:$AA,,0) -> 356.43 | F14: =E14-D14 -> 35.65 | G14: =F14/E14 -> 0.10001964
... A153: 256779422210 | B153: 46053 | D153: -22.64 | E153: =_xlfn.XLOOKUP(A153,'CL Ledger'!$M:$M,'CL Ledger'!$AA:$AA,,0) -> -22.64 | F153: =E153-D153 -> 0 | G153: =F153/E153 -> 0
A154: Outgoing payment | B154: 45800 | C154: 7435.89
A155: Outgoing payment | B155: 45856 | C155: 4602.99
A156: Outgoing payment | B156: 45945 | C156: 4875.15
A157: Outgoing payment | B157: 46053 | C157: 10721.42
C158: =SUM(C3:C157) -> 27635.45 | D158: =SUM(D3:D157) -> 33836.943 | E158: =D158-C158 -> 6201.493

Sheet Invoice Not in Customer Book
A1: Document Number | B1: Document Type | C1: Document Date | D1: Entry Date | E1: Document Header Text | F1: Reference | G1: Document Currency Key | H1: Document Currency Value | I1: Company Code Currency Key | J1: Company Code Currency Value | K1: Text | L1: Remark | M1: Remarks | N1: Action Points
A2: 1800001617 | B2: DR | C2: 45730 | D2: 45735 | E2: NA | F2: 246779412274 | G2: USD | H2: 100 | I2: INR | J2: 8669.13 | K2: Intra Unit Transfer Charges Month Of August,2024 | L2: We had given 2 invoices against BOE No. 7000274, and we accepted invoice 246779411485. | M2: Credit Note to be passed after verification by billing team | N2: Credit Note to be passed as discussed with CL team
A3: 1800000559 | B3: DR | C3: 45719 | D3: 45719 | E3: NA | F3: 246779410509 | G3: USD | H3: 29.25 | I3: INR | J3: 2535.72 | K3: Outbound Handling for Aug 2024 | L3: you have made an Invoice of Handling Charges 13 Plt instead of 4 Plt. | M3: CRM team will handle | N3: to be accounted by siddhartha
A4: 1800006698 | B4: DR | C4: 45762 | D4: 45763 | E4: NA | F4: 256779411589 | G4: USD | H4: 3.38 | I4: INR | J4: 293.8 | K4: Outbound Handling Charges Aug 2024 | L4: Handling Charges CBM Rate is 2.25 but you have Handling Charges CBM Rate is 3.24 | M4: CRM team will handle | N4: To be discussed with customer that the rate is charged as per agreemant for HAZ goods
A5: 1800001791 | B5: DR | C5: 45730 | D5: 45733 | E5: NA | F5: 246779411456 | G5: USD | H5: 4.77 | I5: INR | J5: 413.52 | K5: VAS Activity Charges for the month of August, 24 | L5: Duplicated invoice | M5: Credit Note to be passed after verification by billing team | N5: Credit Note to be passed as discussed with CL team
A6: 1800012462 | B6: DR | C6: 45904 | D6: 45909 | E6: NA | F6: 256779417162 | G6: USD | H6: 44.74 | I6: INR | J6: 3915.39 | K6: VAS -16-31 Aug 25 | L6: The VAS charges are incorrect. | M6: Invoice to changed by CRM team | N6: Credit Note to be passed as discussed with CL team
A7: 1800014290 | B7: DR | C7: 45966 | D7: 45967 | E7: NA | F7: 256779418827 | G7: USD | H7: 60.86 | I7: INR | J7: 5355.89 | K7: WEIGHTMENT-16 -31 Oct 25 | L7: These specific charges are not included in our existing contract. | N7: Credit Note to be passed as discussed with CL team
A8: 1800004532 | B8: DR | C8: 45736 | D8: 45737 | E8: NA | F8: 246779414400 | G8: USD | H8: 80.95 | I8: INR | J8: 7017.66 | K8: Inbound Handling charges for Nov 2024 | L8: Handling Charges CBM Rate is 2.25 but you have Handling Charges CBM Rate is 3.24 | M8: CRM team will handle | N8: To be discussed with customer that the rate is charged as per agreemant for HAZ goods
A9: 1800004533 | B9: DR | C9: 45736 | D9: 45737 | E9: NA | F9: 246779414401 | G9: USD | H9: 15 | I9: INR | J9: 1300.37 | K9: LCL Movement Charges for Nov 2024 | M9: Amount in Invoice to be verified by biling team | N9: to be accounted by siddhartha
A10: 1800013760 | B10: DR | C10: 45937 | D10: 45939 | E10: NA | F10: 256779418181 | G10: USD | H10: 49.33 | I10: INR | J10: 4350.45 | K10: VAS-16-30 Sept 25 | L10: This is to inform you that MHE charges have already been applied in Invoice Nos. 256779418354 and 256779418342. However, the same MHE charges have been included again in Invoice No. 256779418181. | M10: to be accounted by siddhartha after CBM rate issue is solved | N10: Credit Note to be passed as discussed with CL team
A11: 1800009470 | B11: DR | C11: 45815 | D11: 45817 | E11: NA | F11: 256779414234 | G11: USD | H11: 925.23 | I11: INR | J11: 79098.63 | K11: Unit storage -1-31 May 25 | L11: Credit Note Pending | M11: mail summary will be sent by Siddhartha team ,Credit Note to be passed after verification by billing team | N11: Credit Note to be passed as discussed with CL team | O11: 149 | P11: 22.64
A12: 1800013511 | B12: DR | C12: 45935 | D12: 45940 | E12: NA | F12: 256779418401 | G12: USD | H12: 62.52 | I12: INR | J12: 5513.69 | K12: PORT SSR Chgs Sep 25 | L12: These specific charges are not included in our existing contract. | M12: to be accounted by siddhartha | N12: to be accounted by siddhartha
H13: =SUM(H2:H12) -> 1376.03 | J13: =SUBTOTAL(9,J2:J12) -> 118464.25

Sheet Payment Reco
A2: As per Customer | D2: As per Ascendus
A3: Payment Date | B3: Particulars | C3: Amount | D3: Particulars | E3: Date | G3: Amount | H3: TDS | I3: Bank Charges
A4: 45800 | B4: Outgoing payment | C4: 7435.89 | D4: DZ | E4: 45862 | F4: USD | G4: -8262.11 | H4: =C4+G4 -> -826.22
A5: 45856 | B5: Outgoing payment | C5: 4602.99 | D5: DZ | E5: 45891 | F5: USD | G5: -4582.99 | I5: =C5+G5 -> 20
A6: 45945 | B6: Outgoing payment | C6: 4875.15 | D6: DZ | E6: 45955 | F6: USD | G6: -4875.15 | I6: =C6+G6 -> 0
B7: Outgoing payment | C7: 10721.42 | D7: DZ | E7: 46050 | F7: USD | G7: -10691.42 | I7: =C7+G7 -> 30
C8: =SUM(C4:C7) -> 27635.45 | G8: =SUM(G4:G7) -> -28411.67 | H8: =SUM(H4:H7) -> -826.22 | I8: =SUM(I5:I7) -> 50
