Workbook

Sheet Ascendus DATA
A1: Customer Account: Name 1 | B1: Fiscal Year | C1: Posting Date | D1: Document Type | E1: Document Date | F1: Reference | G1: Document Currency Key | H1: Document Currency Value | I1: Company Code Currency Key | J1: Company Code Currency Value | K1: Text
A2: KUEHNE+NAGEL PVT. LTD. | B2: 2025 | C2: 45848 | D2: DG | E2: 45848 | F2: 256779421326 | G2: USD | H2: -70.8 | I2: INR | J2: -6088.85 | K2: Credit note raised against INV 256779414309
A3: KUEHNE+NAGEL PVT. LTD. | B3: 2025 | C3: 45848 | D3: DG | E3: 45848 | F3: 256779421327 | G3: USD | H3: -113.28 | I3: INR | J3: -9742.16 | K3: Credit note raised against INV 256779414309
A4: KUEHNE+NAGEL PVT. LTD. | B4: 2025 | C4: 45848 | D4: DG | E4: 45848 | F4: 256779421328 | G4: USD | H4: -242.75 | I4: INR | J4: -20876.66 | K4: Credit note raised against INV 256779414309
A5: KUEHNE+NAGEL PVT. LTD. | B5: 2025 | C5: 45904 | D5: DR | E5: 45904 | F5: 256779416909 | G5: USD | H5: 989.55 | I5: INR | J5: 86599.81 | K5: CODC Inbound chgs - 16-31 Aug 25
A6: KUEHNE+NAGEL PVT. LTD. | B6: 2025 | C6: 45904 | D6: DR | E6: 45904 | F6: 256779417134 | G6: USD | H6: 536.44 | I6: INR | J6: 46946.19 | K6: VAS - 16-31 Aug 25
A7: KUEHNE+NAGEL PVT. LTD. | B7: 2025 | C7: 45904 | D7: DR | E7: 45904 | F7: 256779417137 | G7: USD | H7: 409.79 | I7: INR | J7: 35862.5 | K7: WEIGHMENT - 16-31 Aug 25
A8: KUEHNE+NAGEL PVT. LTD. | B8: 2025 | C8: 45904 | D8: DR | E8: 45904 | F8: 256779417158 | G8: USD | H8: 110 | I8: INR | J8: 9626.58 | K8: Intra 16-31 Aug 25
A9: KUEHNE+NAGEL PVT. LTD. | B9: 2025 | C9: 45904 | D9: DR | E9: 45904 | F9: 256779417200 | G9: USD | H9: 100.74 | I9: INR | J9: 8816.19 | K9: Empty Lolo Chgs - 01 - 31 AUG 25
A10: KUEHNE+NAGEL PVT. LTD. | B10: 2025 | C10: 45904 | D10: DR | E10: 45904 | F10: 256779417238 | G10: USD | H10: 608.78 | I10: INR | J10: 53276.97 | K10: PORT SSR Chgs Aug 25
A11: KUEHNE+NAGEL PVT. LTD. | B11: 2025 | C11: 45904 | D11: DR | E11: 45904 | F11: 256779417250 | G11: USD | H11: 50 | I11: INR | J11: 4375.72 | K11: Scanning Chgs - 16 - 31 Aug 25
A12: KUEHNE+NAGEL PVT. LTD. | B12: 2025 | C12: 45904 | D12: DR | E12: 45904 | F12: 256779417257 | G12: USD | H12: 22.77 | I12: INR | J12: 1992.7 | K12: Bond Stamp Paper Chgs 01 - 31 Aug 25
A13: KUEHNE+NAGEL PVT. LTD. | B13: 2025 | C13: 45904 | D13: DR | E13: 45904 | F13: 256779417280 | G13: USD | H13: 249.98 | I13: INR | J13: 21876.83 | K13: LCL Chgs - 16 - 31 AUG 25
... A263: KUEHNE+NAGEL PVT. LTD. | B263: 2026 | C263: 46027 | D263: DR | E263: 46027 | F263: 256779440116 | G263: USD | H263: 498.28 | I263: INR | J263: 45215.49 | K263: LCL Chgs - 01 - 15 DEC 25
A264: KUEHNE+NAGEL PVT. LTD. | B264: 2026 | C264: 46030 | D264: DZ | E264: 46030 | G264: INR | H264: -719881.09 | I264: INR | J264: -719881.09
A265: KUEHNE+NAGEL PVT. LTD. | B265: 2026 | C265: 46031 | D265: DR | E265: 46031 | F265: 256779440126 | G265: USD | H265: 122.48 | I265: INR | J265: 11114.22 | K265: CODC Out chgs -1-15 Nov 25
A266: KUEHNE+NAGEL PVT. LTD. | B266: 2026 | C266: 46031 | D266: DR | E266: 46031 | F266: 256779440136 | G266: USD | H266: 27.81 | I266: INR | J266: 2523.57 | K266: Internet Activity Chgs - Dec 25
A267: KUEHNE+NAGEL PVT. LTD. | B267: 2026 | C267: 46028 | D267: DR | E267: 46028 | F267: 256779440150 | G267: USD | H267: 112.85 | I267: INR | J267: 10240.36 | K267: Empty Lolo Chgs - 01 - 31 DEC 25
A268: KUEHNE+NAGEL PVT. LTD. | B268: 2026 | C268: 46028 | D268: DR | E268: 46028 | F268: 256779440159 | G268: USD | H268: 160.22 | I268: INR | J268: 14538.87 | K268: PORT SSR Chgs Dec 25
A269: KUEHNE+NAGEL PVT. LTD. | B269: 2026 | C269: 46028 | D269: DR | E269: 46028 | F269: 256779440208 | G269: USD | H269: 650.12 | I269: INR | J269: 58993.93 | K269: LCL Chgs - 16 - 31 DEC 25
A270: KUEHNE+NAGEL PVT. LTD. | B270: 2026 | C270: 46034 | D270: DR | E270: 46034 | F270: 256779440227 | G270: USD | H270: 304.07 | I270: INR | J270: 27592.27 | K270: Outbound chgs - 16 - 31 Dec 25
A271: KUEHNE+NAGEL PVT. LTD. | B271: 2026 | C271: 46028 | D271: DR | E271: 46028 | F271: 256779440238 | G271: USD | H271: 1083.58 | I271: INR | J271: 98327.45 | K271: Unit Storage - 1-31 DEC 2025
A272: KUEHNE+NAGEL PVT. LTD. | B272: 2026 | C272: 46034 | D272: DR | E272: 46034 | F272: 256779440285 | G272: USD | H272: 535.29 | I272: INR | J272: 48573.9 | K272: VAS-Dec 25 - 16-31
A273: KUEHNE+NAGEL PVT. LTD. | B273: 2026 | C273: 46028 | D273: DR | E273: 46028 | F273: 256779440309 | G273: INR | H273: 200000 | I273: INR | J273: 200000 | K273: Fixed Storage Charges for January 2026
A274: KUEHNE+NAGEL PVT. LTD. | B274: 2026 | C274: 46028 | D274: DR | E274: 46028 | F274: 256779440310 | G274: INR | H274: 8000 | I274: INR | J274: 8000 | K274: Fixed Storage Charges for January 2026
A275: KUEHNE+NAGEL PVT. LTD. | B275: 2026 | C275: 46028 | D275: DR | E275: 46028 | F275: 256779440311 | G275: INR | H275: 4400 | I275: INR | J275: 4400 | K275: Fixed Storage Charges for January 2026
A276: KUEHNE+NAGEL PVT. LTD. | B276: 2026 | C276: 46035 | D276: DR | E276: 46035 | F276: 256779440363 | G276: USD | H276: 937.45 | I276: INR | J276: 85067.16 | K276: VAS - NOV 25,16-30
... A565: KUEHNE+NAGEL PVT. LTD. | B565: 2025 | C565: 45848 | D565: DR | E565: 45848 | F565: 256779415363 | G565: USD | H565: 3 | I565: INR | J565: 258 | K565: Outbound Handling for Aug 2024
A566: KUEHNE+NAGEL PVT. LTD. | B566: 2025 | C566: 45861 | D566: DZ | E566: 45861 | G566: USD | H566: 0 | I566: INR | J566: 0
A567: KUEHNE+NAGEL PVT. LTD. | B567: 2025 | C567: 45861 | D567: DZ | E567: 45861 | G567: USD | H567: 0 | I567: INR | J567: 0
A568: KUEHNE+NAGEL PVT. LTD. | B568: 2025 | C568: 45861 | D568: DZ | E568: 45861 | G568: USD | H568: 0 | I568: INR | J568: 0
A569: KUEHNE+NAGEL PVT. LTD. | B569: 2025 | C569: 45861 | D569: DZ | E569: 45861 | G569: USD | H569: 0 | I569: INR | J569: 0
A570: KUEHNE+NAGEL PVT. LTD. | B570: 2025 | C570: 45861 | D570: DZ | E570: 45861 | G570: USD | H570: 0 | I570: INR | J570: 0
A571: KUEHNE+NAGEL PVT. LTD. | B571: 2025 | C571: 45861 | D571: DZ | E571: 45861 | G571: USD | H571: 0 | I571: INR | J571: 0
A572: KUEHNE+NAGEL PVT. LTD. | B572: 2025 | C572: 45861 | D572: DZ | E572: 45861 | G572: USD | H572: 0 | I572: INR | J572: 0
A573: KUEHNE+NAGEL PVT. LTD. | B573: 2025 | C573: 45758 | D573: DA | E573: 45758 | G573: INR | H573: 1 | I573: INR | J573: 1 | K573: Overpayment
A574: KUEHNE+NAGEL PVT. LTD. | B574: 2025 | C574: 45758 | D574: DA | E574: 45758 | G574: INR | H574: -1 | I574: INR | J574: -1 | K574: Overpayment
A575: KUEHNE+NAGEL PVT. LTD. | B575: 2025 | C575: 45902 | D575: DY | E575: 45902 | G575: INR | H575: 212521.54 | I575: INR | J575: 208845.74
A576: KUEHNE+NAGEL PVT. LTD. | B576: 2025 | C576: 45902 | D576: DY | E576: 45902 | G576: INR | H576: -212521.54 | I576: INR | J576: -207607.52
A577: KUEHNE+NAGEL PVT. LTD. | B577: 2025 | C577: 45974 | D577: DZ | E577: 45974 | G577: USD | H577: 4603.48 | I577: INR | J577: 396450.85
A578: KUEHNE+NAGEL PVT. LTD. | B578: 2025 | C578: 45974 | D578: DZ | E578: 45974 | G578: USD | H578: 2.98 | I578: INR | J578: 262.21
A579: KUEHNE+NAGEL PVT. LTD. | B579: 2025 | C579: 45974 | D579: DZ | E579: 45974 | G579: USD | H579: -2.98 | I579: INR | J579: -262.21
A580: KUEHNE+NAGEL PVT. LTD. | B580: 2025 | C580: 45974 | D580: DZ | E580: 45974 | G580: USD | H580: 5558.96 | I580: INR | J580: 478086.37
A581: KUEHNE+NAGEL PVT. LTD. | B581: 2025 | C581: 45974 | D581: DZ | E581: 45974 | G581: USD | H581: -3891.99 | I581: INR | J581: -338298.81
A582: KUEHNE+NAGEL PVT. LTD. | B582: 2025 | C582: 45974 | D582: DZ | E582: 45974 | G582: USD | H582: -6270.45 | I582: INR | J582: -536832.3
A583: KUEHNE+NAGEL PVT. LTD. | B583: 2025 | C583: 45974 | D583: DZ | E583: 45974 | G583: INR | H583: 77508.99 | I583: INR | J583: 75771.03
A584: KUEHNE+NAGEL PVT. LTD. | B584: 2025 | C584: 45974 | D584: DZ | E584: 45974 | G584: INR | H584: -20130.78 | I584: INR | J584: -20130.78
A585: KUEHNE+NAGEL PVT. LTD. | B585: 2025 | C585: 45974 | D585: DZ | E585: 45974 | G585: INR | H585: -746.27 | I585: INR | J585: -746.27
A586: KUEHNE+NAGEL PVT. LTD. | B586: 2025 | C586: 45974 | D586: DZ | E586: 45974 | G586: INR | H586: -24772.95 | I586: INR | J586: -24772.95
... A591: KUEHNE+NAGEL PVT. LTD. | B591: 2025 | C591: 45987 | D591: DZ | E591: 45987 | G591: INR | H591: -1917961.2 | I591: INR | J591: -1917961.2
A592: KUEHNE+NAGEL PVT. LTD. | B592: 2025 | C592: 45744 | D592: XC | E592: 45701 | F592: 6779ZR25000004 | G592: INR | H592: 1 | I592: INR | J592: 1 | K592: Overpayment
A593: KUEHNE+NAGEL PVT. LTD. | B593: 2025 | C593: 45701 | D593: XC | E593: 45701 | F593: 6779ZP25000139 | G593: INR | H593: -1 | I593: INR | J593: -1 | K593: Overpayment
A594: KUEHNE+NAGEL PVT. LTD. | B594: 2025 | C594: 45764 | D594: DR | E594: 45764 | F594: 256779412140 | G594: INR | H594: 262.21 | I594: INR | J594: 262.21 | K594: Fixed Storage Charges for April 2025
A595: KUEHNE+NAGEL PVT. LTD. | B595: 2025 | C595: 45735 | D595: DR | E595: 45735 | F595: 246779413076 | G595: USD | H595: 466.37 | I595: INR | J595: 40430.2 | K595: Port SSR Charges - Shifting for Aug to Dec,24.
A596: KUEHNE+NAGEL PVT. LTD. | B596: 2025 | C596: 45787 | D596: DR | E596: 45787 | F596: 256779413147 | G596: INR | H596: 8000 | I596: INR | J596: 8000 | K596: Fixed Storage Charges fo MAY 2025
A597: KUEHNE+NAGEL PVT. LTD. | B597: 2025 | C597: 45818 | D597: DR | E597: 45818 | F597: 256779414359 | G597: INR | H597: 8000 | I597: INR | J597: 8000 | K597: Fixed Storage Charges fo JUNE 2025
A598: KUEHNE+NAGEL PVT. LTD. | B598: 2025 | C598: 45842 | D598: DR | E598: 45842 | F598: 256779414917 | G598: INR | H598: 8000 | I598: INR | J598: 8000 | K598: Fixed Storage Charges fo JULY 2025
A599: KUEHNE+NAGEL PVT. LTD. | B599: 2025 | C599: 45870 | D599: DR | E599: 45870 | F599: 256779416029 | G599: INR | H599: 8000 | I599: INR | J599: 8000 | K599: Fixed Storage Charges for August 2025
A600: KUEHNE+NAGEL PVT. LTD. | B600: 2025 | C600: 45904 | D600: DR | E600: 45904 | F600: 256779417349 | G600: INR | H600: 8000 | I600: INR | J600: 8000 | K600: Fixed Storage Charges for September 2025
A601: KUEHNE+NAGEL PVT. LTD. | B601: 2025 | C601: 45935 | D601: DR | E601: 45935 | F601: 256779417876 | G601: INR | H601: 8000 | I601: INR | J601: 8000 | K601: Fixed Storage Charges for October 2025
A602: KUEHNE+NAGEL PVT. LTD. | B602: 2025 | C602: 45966 | D602: DR | E602: 45966 | F602: 256779418778 | G602: INR | H602: 8000 | I602: INR | J602: 8000 | K602: Fixed Storage Charges for November 2025
A603: KUEHNE+NAGEL PVT. LTD. | B603: 2025 | C603: 45995 | D603: DR | E603: 45995 | F603: 256779419971 | G603: INR | H603: 8000 | I603: INR | J603: 8000 | K603: Fixed Storage Charges for December 2025
A604: KUEHNE+NAGEL PVT. LTD. | B604: 2025 | C604: 45787 | D604: DR | E604: 45787 | F604: 256779413148 | G604: INR | H604: 4400 | I604: INR | J604: 4400 | K604: Fixed Storage Charges fo MAY 2025
A605: KUEHNE+NAGEL PVT. LTD. | B605: 2025 | C605: 45818 | D605: DR | E605: 45818 | F605: 256779414360 | G605: INR | H605: 4400 | I605: INR | J605: 4400 | K605: Fixed Storage Charges fo JUNE 2025
... A707: KUEHNE+NAGEL PVT. LTD. | B707: 2025 | C707: 45733 | D707: DR | E707: 45733 | F707: 246779411738 | G707: USD | H707: 28.54 | I707: INR | J707: 2474.17 | K707: VAS Activity Charges for the month of October, 24

Sheet Summary 
A2: Reconciliation of Ledger as on 31st January 2026
A3: Particulars | B3: Amount
A4: Balance as per Kuehne Nagel Pvt Ltd | B4: =-'CUSTOMER DATA'!Y1 -> -10371172
A5: Add: TDS recorded by customer but not in our books | B5: ='CUSTOMER DATA'!X1 -> 0
A6: Add: Corrections to be done by customer | B6: ='Corrections to be done by custo'!AB1 -> 102752.19
A7: Less: Amount recorded by customer, but not in our books due to exchange gain | B7: -111936.53
A8: Less: Difference in INR amounts in both books due to exchange rate | B8: =-63698.83-45403 -> -109101.83
A9: Add: Invoices / CN not recorded in customer books | B9: ='Invoices not in customer''s Book'!H20 -> 1181419.2 | C9: To be discussed with customer
A10: Add: Payments recorded in Feb by Ascendus | B10: =('Payment Reco'!E21+'Payment Reco'!E22) -> 1878132.8 | C10: Confirmed by Sushil over call
A11: Derived balance | B11: =SUM(B4:B10) -> -7429906.4
A12: Balance as per Ascendus | B12: =[1]Sheet1!$T$709 -> 6321328.8
A14: Difference | B14: =B11-B12-B13 -> -13751235

Sheet Corrections to be done by custo
AB1: =SUM(AB3:AB5) -> 102752.19
A2: Creditor Code | B2: Creditor | C2: Ty | D2: Item# | E2: Item Date | F2: CCY | G2: FC Amount | H2: Settled FC Amount | I2: LC Amount | J2: Particular | K2: Due Date | L2: Last Sett. Date | M2: Job# | N2: VC Period | O2: VC# | P2: VC Seq | Q2: VC Date | R2: Tx. Type | S2: Reference | T2: Full Name | U2: Settled LC Amount | X2: TDS | Y2: Net balance | Z2: Remarks | AA2: vlookup | AB2: Difference
A3: A023951 | B3: A023951 | C3: I | D3: 256779410262 | E3: 45750 | F3: INR | G3: - | H3: - | I3: -93.33 | J3: NO EXCHANGE RATE | K3: 45780 | L3: 45939 | M3: - | N3: 45809 | O3: 51171858 | P3: 1 | Q3: 45820 | R3: 210 | S3: 1.55e+16 | T3: Ascendas Panvel FTWZ Private Limited | U3: 2 | W3: -0.021429337 | X3: 2 | Y3: -91.33 | Z3: Customer recorded USD amount in INR amount. Customer needs to correct | AA3: 8112.41 | AB3: 8019.08
A4: A023951 | B4: A023951 | C4: I | D4: 256779410263 | E4: 45750 | F4: INR | G4: - | H4: - | I4: -51.33 | J4: NO EXCHANGE RATE | K4: 45780 | L4: 45939 | M4: - | N4: 45809 | O4: 51171949 | P4: 1 | Q4: 45820 | R4: 210 | S4: 1.55e+16 | T4: Ascendas Panvel FTWZ Private Limited | U4: 2 | W4: -0.038963569 | X4: 2 | Y4: -49.33 | Z4: Customer recorded USD amount in INR amount. Customer needs to correct | AA4: 4461.7 | AB4: 4410.37
A5: A023951 | B5: A023951 | C5: I | D5: 256779412012 | E5: 45763 | F5: INR | G5: - | H5: - | I5: -1051.22 | J5: NO EXCHANGE RATE | K5: 45793 | L5: 45820 | M5: - | N5: 45809 | O5: 51171953 | P5: 1 | Q5: 45820 | R5: 210 | S5: 1.55e+16 | T5: Ascendas Panvel FTWZ Private Limited | U5: 22 | W5: -0.020928065 | X5: 22 | Y5: -1029.22 | Z5: Customer recorded USD amount in INR amount. Customer needs to correct | AA5: 91373.96 | AB5: 90322.74

Sheet Biling Reco
A1: As per Customer | G1: As per Ascendus
A2: Years | B2: Item Date | C2: Debit Note | D2: Expense | E2: Foreign Exchange Diffrence | F2: Net Amount | G2: Years | H2: Document Date | I2: Credit | J2: Expense | K2: Net Amount | L2: Diffrence
A3: 2025 | B3: Jan | D3: -217492.45 | F3: =SUM(C3:E3) -> -217492.45 | G3: 2025 | H3: Jan | K3: =SUM(I3:J3) -> 0 | L3: =K3+F3 -> -217492.45
A4: 2025 | B4: Feb | D4: -1520432.9 | F4: =SUM(C4:E4) -> -1520432.9 | G4: 2025 | H4: Feb | J4: 1514515.3 | K4: =SUM(I4:J4) -> 1514515.3 | L4: =K4+F4 -> -5917.55
A5: 2025 | B5: Mar | C5: 21719.38 | D5: -1191118 | F5: =SUM(C5:E5) -> -1169398.7 | G5: 2025 | H5: Mar | J5: 1933380.6 | K5: =SUM(I5:J5) -> 1933380.6 | L5: =K5+F5 -> 763981.97
A6: 2025 | B6: Apr | D6: -2932698.5 | F6: =SUM(C6:E6) -> -2932698.5 | G6: 2025 | H6: Apr | J6: 2087965.7 | K6: =SUM(I6:J6) -> 2087965.7 | L6: =K6+F6 -> -844732.75
A7: 2025 | B7: May | D7: -1341898.7 | F7: =SUM(C7:E7) -> -1341898.7 | G7: 2025 | H7: May | I7: -595574.41 | J7: 1044919.9 | K7: =SUM(I7:J7) -> 449345.53 | L7: =K7+F7 -> -892553.19
A8: 2025 | B8: Jun | D8: -796400.32 | F8: =SUM(C8:E8) -> -796400.32 | G8: 2025 | H8: Jun | J8: 1761603.8 | K8: =SUM(I8:J8) -> 1761603.8 | L8: =K8+F8 -> 965203.51
A9: 2025 | B9: Jul | D9: -266105.72 | F9: =SUM(C9:E9) -> -266105.72 | G9: 2025 | H9: Jul | I9: -1464659.3 | J9: 2492881.5 | K9: =SUM(I9:J9) -> 1028222.2 | L9: =K9+F9 -> 762116.44
A10: 2025 | B10: Aug | D10: -937708 | F10: =SUM(C10:E10) -> -937708 | G10: 2025 | H10: Aug | I10: -170239.97 | J10: 1305423 | K10: =SUM(I10:J10) -> 1135183.1 | L10: =K10+F10 -> 197475.05
A11: 2025 | B11: Sep | C11: 16556.76 | D11: -673577.15 | F11: =SUM(C11:E11) -> -657020.39 | G11: 2025 | H11: Sep | J11: =1564779.07+1238.22 -> 1566017.3 | K11: =SUM(I11:J11) -> 1566017.3 | L11: =K11+F11 -> 908996.9
A12: 2025 | B12: Oct | D12: -1793002.9 | F12: =SUM(C12:E12) -> -1793002.9 | G12: 2025 | H12: Oct | I12: -8361.37 | J12: 1113806.7 | K12: =SUM(I12:J12) -> 1105445.3 | L12: =K12+F12 -> -687557.56
A13: 2025 | B13: Nov | D13: -80394.56 | F13: =SUM(C13:E13) -> -80394.56 | G13: 2025 | H13: Nov | I13: -405590.02 | J13: 1574052.7 | K13: =SUM(I13:J13) -> 1168462.7 | L13: =K13+F13 -> 1088068.1
A14: 2025 | B14: Dec | F14: =SUM(C14:E14) -> 0 | G14: 2025 | H14: Dec | J14: 282835.01 | K14: =SUM(I14:J14) -> 282835.01 | L14: =K14+F14 -> 282835.01
A15: 2026 | B15: Jan | E15: -45403 | F15: =SUM(C15:E15) -> -45403 | G15: 2026 | H15: Jan | I15: -52265.33 | J15: 831546.81 | K15: =SUM(I15:J15) -> 779281.48 | L15: =K15+F15 -> 733878.48
A16: Total | C16: =SUM(C3:C15) -> 38276.14 | D16: =SUM(D3:D15) -> -11750829 | E16: =SUM(E3:E15) -> -45403 | F16: =SUM(C16:E16) -> -11757956 | G16: Total | I16: =SUM(I3:I15) -> -2696690.4 | J16: =SUM(J3:J15) -> 17508948 | K16: =SUM(I16:J16) -> 14812258 | L16: =K16+F16 -> 3054302
D18: =J16+D16 -> 5758119.3

Sheet Payment Reco
A1: As per Customer ledger | C1: As per Ascendus | E1: Amount
A2: Date | B2: Amount | C2: Date | D2: Amount | J2: As per Customer ledger | K2: As per Ascendus
A3: 45827 | B3: 1760137.8 | C3: 45940 | D3: -1746430.2 | E3: =B3+D3 -> 13707.54 | F3: >>Exchange diffrence | H3: 2025 | I3: Jan
A4: 45859 | B4: 2396201.3 | C4: 45940 | D4: -2385234 | E4: =B4+D4 -> 10967.32 | F4: >>Exchange diffrence | H4: 2025 | I4: Feb
A5: 45859 | B5: 2396201.3 | E5: =B5+D5 -> 2396201.3 | H5: 2025 | I5: May
A6: 45869 | B6: -2396201.3 | E6: =B6+D6 -> -2396201.3 | H6: 2025 | I6: June | J6: =B3 -> 1760137.8
A7: 45954 | B7: 1721315.8 | C7: 45958 | D7: -1719090.9 | E7: =B7+D7 -> 2224.91 | F7: >>Exchange diffrence | H7: 2025 | I7: July | J7: =B4 -> 2396201.3
C8: 45974 | D8: 396450.85 | E8: =B8+D8 -> 396450.85 | H8: 2025 | I8: Aug
C9: 45974 | D9: 262.21 | E9: =B9+D9 -> 262.21 | H9: 2025 | I9: Sep
C10: 45974 | D10: -262.21 | E10: =B10+D10 -> -262.21 | H10: 2025 | I10: Oct | J10: 1721315.8 | K10: -5850755.1
C11: 45974 | D11: 478086.37 | E11: =B11+D11 -> 478086.37 | H11: 2025 | I11: Nov | J11: 1899719.6 | K11: -1920293.1
C12: 45974 | D12: -338298.81 | E12: =B12+D12 -> -338298.81 | H12: 2025 | I12: Dec | J12: 715665.04
C13: 45974 | D13: -536832.3 | E13: =B13+D13 -> -536832.3 | H13: 2026 | I13: Jan | J13: 1878132.8 | K13: -719881.09
C14: 45974 | D14: 75771.03 | E14: =B14+D14 -> 75771.03 | H14: Total | J14: =SUM(J3:J13) -> 10371172 | K14: =SUM(K3:K13) -> -8490929.3 | L14: =SUM(J14:K14) -> 1880243
C15: 45974 | D15: -20130.78 | E15: =B15+D15 -> -20130.78
C16: 45974 | D16: -746.27 | E16: =B16+D16 -> -746.27
C17: 45974 | D17: -24772.95 | E17: =B17+D17 -> -24772.95
C18: 45974 | D18: -31858.99 | E18: =B18+D18 -> -31858.99
A19: 45982 | B19: 1899719.6 | C19: 45987 | D19: -1917961.2 | E19: =B19+D19 -> -18241.69 | F19: >>Exchange diffrence
A20: 46014 | B20: 715665.04 | C20: 46030 | D20: -719881.09 | E20: =B20+D20 -> -4216.05 | F20: >>Exchange diffrence
A21: 46052 | B21: 1869680.8 | E21: =B21+D21 -> 1869680.8 | F21: >>payment not recorded in books
A22: 46053 | B22: 8452 | E22: =B22+D22 -> 8452 | F22: >>payment not recorded in books
B23: =SUM(B3:B22) -> 10371172 | D23: =SUM(D3:D21) -> -8490929.3 | E23: =SUM(E3:E22) -> 1880243

Sheet Pivot data
A3: Sum of LC Amount | D3: Ty
A4: Years | B4: Quarters | C4: Item Date | D4: A | E4: C | F4: I | G4: S
A5: 2025 | B5: Qtr1 | C5: Jan | F5: -217492.45
C6: Feb | F6: -1520432.9
C7: Mar | E7: 21719.38 | F7: -1191118
B8: Qtr2 | C8: Apr | F8: -2932698.5
C9: May | F9: -1341898.7
C10: Jun | D10: 1760137.8 | F10: -796400.32
B11: Qtr3 | C11: Jul | D11: 2396201.3 | F11: -266105.72
C12: Aug | F12: -937708
C13: Sep | E13: 16556.76 | F13: -673577.15
B14: Qtr4 | C14: Oct | D14: 1721315.8 | F14: -1793002.9
C15: Nov | D15: 1899719.6 | F15: -80394.56
C16: Dec | D16: 715665.04
A17: 2026 | B17: Qtr1 | C17: Jan | D17: 1878132.8 | G17: -45403

Sheet Invoices not in customer's Book
A1: Document Number | B1: Document Type | C1: Document Date | D1: Reference | E1: Document Currency Key | F1: Document Currency Value | G1: Company Code Currency Key | H1: Company Code Currency Value | I1: Assignment | J1: Item | K1: Text | L1: Clearing Document | N1: Remarks from customers
A2: 1800013764 | B2: DR | C2: 45937 | D2: 256779418185 | E2: USD | F2: 405.44 | G2: INR | H2: 35756.07 | I2: 2110802 | J2: 1 | K2: Weighment-16-30 Sept 25 | N2: Invoice under booking
A3: 1800009489 | B3: DR | C3: 45815 | D3: 256779414253 | E3: USD | F3: 9947.26 | G3: INR | H3: 850399.02 | I3: NA | J3: 1 | K3: Unit storage -1-31 May 25 | N3: Invoice under booking
A4: 1800015955 | B4: DR | C4: 46027 | D4: 256779440078 | E4: USD | F4: 78.75 | G4: INR | H4: 7146.02 | I4: NA | J4: 1 | K4: Outbound chgs - 01 - 15 Dec 25 | N4: Invoice not received
A5: 1800016933 | B5: DR | C5: 46043 | D5: 256779440381 | E5: USD | F5: 6.79 | G5: INR | H5: 616.15 | I5: NA | J5: 1 | K5: CODC Out chgs -1-15 JAN 26 | N5: Invoice not received
A6: 1800016874 | B6: DR | C6: 46043 | D6: 256779440388 | E6: USD | F6: 57.29 | G6: INR | H6: 5198.67 | I6: 2163060 | J6: 1 | K6: CODC LCL Chgs -1-15 JAN 26 | N6: Invoice not received
A7: 1800017058 | B7: DR | C7: 46045 | D7: 256779440411 | E7: USD | F7: 554.49 | G7: INR | H7: 50316.16 | I7: NA | J7: 1 | K7: LCL Chgs - 01 - 15 JAN 26 | N7: Invoice not received
A8: 1800017100 | B8: DR | C8: 46045 | D8: 256779440427 | E8: USD | F8: 44.06 | G8: INR | H8: 3998.14 | I8: NA | J8: 1 | K8: Outbound chgs - 01 - 15 JAN 26 | N8: Invoice not received
A9: 1800017150 | B9: DR | C9: 46049 | D9: 256779440443 | E9: USD | F9: 18.41 | G9: INR | H9: 1670.58 | I9: NA | J9: 1 | K9: VAS-1-15 Jan 2026 | N9: Invoice not received
A10: 1800014279 | B10: DR | C10: 45966 | D10: 256779418816 | E10: USD | F10: 891 | G10: INR | H10: 78411.02 | I10: 2123387 | J10: 1 | K10: VAS-16 -31 Oct 25 | N10: Invoice under booking
A11: 1800010603 | B11: DR | C11: 45848 | D11: 256779415363 | E11: USD | F11: 3 | G11: INR | H11: 258 | I11: NA | J11: 1 | K11: Outbound Handling for Aug 2024 | N11: Invoice under booking
A12: 1800011944 | B12: DR | C12: 45889 | D12: 256779416593 | E12: USD | F12: 810 | G12: INR | H12: 69684.4 | I12: NA | J12: 1 | K12: Empty Cont Out Chgs - 16 - 31 Jul 25 | N12: Invoice under booking
A13: 1800012156 | B13: DR | C13: 45889 | D13: 256779416801 | E13: USD | F13: 110 | G13: INR | H13: 9463.31 | I13: NA | J13: 1 | K13: INTRA-Aug 25- 1-15 | N13: Invoice under booking
... A15: 1800012182 | B15: DR | C15: 45889 | D15: 256779416814 | E15: USD | F15: 230 | G15: INR | H15: 19786.93 | I15: NA | J15: 1 | K15: Transportation In Chgs - 01 - 15 Aug 25 | N15: Invoice under booking
A16: 1800009071 | B16: DR | C16: 45797 | D16: 256779413835 | E16: USD | F16: 206.02 | G16: INR | H16: 17714.36 | J16: 1 | K16: VAS -1-15 May 25, Ex.rate 85.43 | N16: Invoice not received
A17: 1800005928 | B17: DR | C17: 45751 | D17: 256779410819 | E17: USD | F17: 1913.97 | G17: INR | H17: 166365.76 | I17: NA | J17: 1 | K17: Storage Charges Jan, 25 | N17: Invoice under booking
H18: =SUM(H2:H17) -> 1338202.7
H19: -156783.44
H20: =H18+H19 -> 1181419.2

Sheet CN Not in Customer's Books
A1: Document Number | B1: Document Type | C1: Document Date | D1: Reference | E1: Document Currency Key | F1: Document Currency Value | G1: Company Code Currency Key | H1: Company Code Currency Value | I1: Assignment | J1: Item | K1: Text | L1: Clearing Document | N1: Remarks from customers
A2: 1600001670 | B2: DG | C2: 45848 | D2: 256779421302 | E2: USD | F2: -3.54 | G2: INR | H2: -304.44 | I2: NA | J2: 1 | K2: Credit note raised against INV 246779410665 | L2: 1400001815 | N2: CN not received
A3: 1600001590 | B3: DG | C3: 45848 | D3: 256779421222 | E3: USD | F3: -295 | G3: INR | H3: -25370.2 | I3: NA | J3: 1 | K3: Credit note raised against INV 256779411867 | L3: 1400001815 | N3: CN not received
A4: 1600001607 | B4: DG | C4: 45848 | D4: 256779421239 | E4: USD | F4: -35.4 | G4: INR | H4: -3044.42 | I4: NA | J4: 1 | K4: Credit note raised against INV 256779411466 | L4: 1400001815 | N4: CN not received
A5: 1600001608 | B5: DG | C5: 45848 | D5: 256779421240 | E5: USD | F5: -35.4 | G5: INR | H5: -3044.42 | I5: NA | J5: 1 | K5: Credit note raised against INV 256779411467 | L5: 1400001815 | N5: CN not received
A6: 1600001648 | B6: DG | C6: 45848 | D6: 256779421280 | E6: USD | F6: -23.6 | G6: INR | H6: -2029.62 | I6: NA | J6: 1 | K6: Credit note raised against INV 256779411463 | L6: 1400001815 | N6: CN not received
A7: 1600001650 | B7: DG | C7: 45848 | D7: 256779421282 | E7: USD | F7: -32.45 | G7: INR | H7: -2790.72 | I7: NA | J7: 1 | K7: Credit note raised against INV 256779411465 | L7: 1400001815 | N7: CN not received
A8: 1600001651 | B8: DG | C8: 45848 | D8: 256779421283 | E8: USD | F8: -26.55 | G8: INR | H8: -2283.32 | I8: NA | J8: 1 | K8: Credit note raised against INV 256779411468 | L8: 1400001815 | N8: CN not received
A9: 1600002133 | B9: DG | C9: 45890 | D9: 256779421698 | E9: USD | F9: -30 | G9: INR | H9: -2580.9 | I9: NA | J9: 1 | K9: CN ISSUED TOWARDS BILL NO.256779415304 | L9: 1400001815 | N9: CN under booking
A10: 1600002134 | B10: DG | C10: 45890 | D10: 256779421699 | E10: USD | F10: -30 | G10: INR | H10: -2580.9 | I10: NA | J10: 1 | K10: CN ISSUED TOWARDS BILL NO.256779415305 | L10: 1400001815 | N10: CN under booking
A11: 1600002135 | B11: DG | C11: 45890 | D11: 256779421700 | E11: USD | F11: -30 | G11: INR | H11: -2580.9 | I11: NA | J11: 1 | K11: CN ISSUED TOWARDS BILL NO.256779415306 | L11: 1400001815 | N11: CN under booking
A12: 1600002136 | B12: DG | C12: 45890 | D12: 256779421701 | E12: USD | F12: -30 | G12: INR | H12: -2580.9 | I12: NA | J12: 1 | K12: CN ISSUED TOWARDS BILL NO.256779415307 | L12: 1400001815 | N12: CN under booking
A13: 1600002137 | B13: DG | C13: 45890 | D13: 256779421702 | E13: USD | F13: -30 | G13: INR | H13: -2580.9 | I13: NA | J13: 1 | K13: CN ISSUED TOWARDS BILL NO.256779415308 | L13: 1400001815 | N13: CN under booking
... A20: 1600002139 | B20: DG | C20: 45890 | D20: 256779421704 | E20: USD | F20: -8.48 | G20: INR | H20: -729.54 | I20: NA | J20: 1 | K20: CN ISSUED TOWARDS BILL NO.256779415349 | L20: 1400001816 | N20: CN under booking
H21: =SUM(H2:H20) -> -156783.44 | I21: =MID(H21,28,15)
I22: =MID(H22,28,15)
I23: =MID(H23,28,15)
I24: =MID(H24,20,15)
I25: =MID(H25,20,15)
I26: =MID(H26,27,15)
I27: =MID(H27,27,15)
I28: =MID(H28,27,15)
I29: =MID(H29,27,15)
I30: =MID(H30,27,15)
I31: =MID(H31,27,15)
I32: =MID(H32,27,15)
I33: =MID(H33,27,15)
I34: =MID(H34,27,15)
I35: =MID(H35,27,15)
I36: =MID(H36,20,15)
I37: =MID(H37,20,15)
I38: =MID(H38,36,15)
I39: =MID(H39,36,15)
I40: =MID(H40,32,15)
I41: =MID(H41,32,15)
I42: =MID(H42,32,15)
I43: =MID(H43,32,15)
I44: =MID(H44,32,15)
I45: =MID(H45,32,15)
I46: =MID(H46,32,15)
I47: =MID(H47,32,15)
I48: =MID(H48,32,15)
I49: =MID(H49,32,15)
I50: =MID(H50,32,15)
I51: =MID(H51,32,15)
... I142: =MID(H142,32,15)
I143: =MID(H143,28,15)
I144: =MID(H144,32,15)
I145: =MID(H145,27,15)
I146: =MID(H146,27,15)
G147: =SUM(G2:G146) -> 0

Sheet Foreign Exchange difference
A1: Ty | B1: Item# | C1: Item Date | D1: FC Amount | E1: LC Amount | F1: Particular | G1: Due Date | H1: CCY | I1: VC Period | J1: VC Seq | K1: VC Date | L1: Tx. Type | M1: Company Code
A2: C | B2: 246779411409_R | C2: 45730 | D2: 249.55 | E2: 21721.43 | F2: NO EXCHANGE RATE | H2: USD | I2: 45839 | M2: 53826350
A3: C | B3: 246779411409_R | C3: 45730 | D3: 0 | E3: -2.05 | F3: C: ASCENDAS27 P: Matching | H3: USD | I3: 45839 | M3: 54969548
A4: C | B4: 256779417580_R | C4: 45918 | D4: 184.38 | E4: 184.38 | H4: USD | I4: 46023 | M4: 68208016
A5: S | B5: 2830735 | C5: 46053 | D5: 0 | E5: -7756 | F5: Exchange rate diference for JUN'25 USD 20175.95 | H5: INR | I5: 46023 | M5: 68369723
A6: S | B6: 2830736 | C6: 46053 | D6: 0 | E6: -15004 | F6: Exchange rate diference for JUL'25 USD 27632.46 | H6: INR | I6: 46023 | M6: 68369723
A7: S | B7: 2830738 | C7: 46053 | D7: 0 | E7: -17437 | F7: Exchange rate diference for NOV'25 USD 21525.94 | H7: INR | I7: 46023 | M7: 68369723
A8: S | B8: 2830739 | C8: 46053 | D8: 0 | E8: -5206 | F8: Exchange rate diference for DEC'25 USD 8027.22 | H8: INR | I8: 46023 | M8: 68369723
A9: C | B9: 256779417580_R | C9: 45918 | D9: -3.69 | E9: -3.69 | F9: C: ASCENDAS27 P: A023951 C 256779 | H9: USD | I9: 46023 | M9: 68389624
A10: C | B10: 256779417580_R | C10: 45918 | D10: 0 | E10: 16376.07 | F10: C: ASCENDAS27 P: Matching | H10: USD | I10: 46023 | M10: 68459189
E11: =SUM(E2:E10) -> -7126.86

Sheet Ascendus
A1: Customer Account: Name 1 | B1: Fiscal Year | C1: Document Type | D1: Document Date | E1: Reference | F1: Document Currency Key | G1: Document Currency Value | H1: Company Code Currency Key | I1: Company Code Currency Value | J1: Text | K1: Amount In USD | L1: Amount In INR | M1: Diffrecnce
A2: KUEHNE+NAGEL PVT. LTD. | B2: 2025 | C2: DG | D2: 45848 | E2: 256779421326 | F2: USD | G2: -70.8 | H2: INR | I2: -6088.85 | J2: Credit note raised against INV 256779414309 | K2: {=VLOOKUP(E2,[2]A023951!D$1:H$1114,{3,5},0)} -> #N/A
A3: KUEHNE+NAGEL PVT. LTD. | B3: 2025 | C3: DG | D3: 45848 | E3: 256779421327 | F3: USD | G3: -113.28 | H3: INR | I3: -9742.16 | J3: Credit note raised against INV 256779414309 | K3: {=VLOOKUP(E3,[2]A023951!D$1:H$1114,{3,5},0)} -> #N/A
A4: KUEHNE+NAGEL PVT. LTD. | B4: 2025 | C4: DG | D4: 45848 | E4: 256779421328 | F4: USD | G4: -242.75 | H4: INR | I4: -20876.66 | J4: Credit note raised against INV 256779414309 | K4: {=VLOOKUP(E4,[2]A023951!D$1:H$1114,{3,5},0)} -> #N/A
A5: KUEHNE+NAGEL PVT. LTD. | B5: 2025 | C5: DR | D5: 45904 | E5: 256779416909 | F5: USD | G5: 989.55 | H5: INR | I5: 86599.81 | J5: CODC Inbound chgs - 16-31 Aug 25 | K5: {=VLOOKUP(E5,[2]A023951!D$1:H$1114,{3,5},0)} -> -989.55 | L5: -87733 | M5: =I5+L5 -> -1133.19
A6: KUEHNE+NAGEL PVT. LTD. | B6: 2025 | C6: DR | D6: 45904 | E6: 256779417134 | F6: USD | G6: 536.44 | H6: INR | I6: 46946.19 | J6: VAS - 16-31 Aug 25 | K6: {=VLOOKUP(E6,[2]A023951!D$1:H$1114,{3,5},0)} -> -536.44 | L6: -47020 | M6: =I6+L6 -> -73.81
A7: KUEHNE+NAGEL PVT. LTD. | B7: 2025 | C7: DR | D7: 45904 | E7: 256779417137 | F7: USD | G7: 409.79 | H7: INR | I7: 35862.5 | J7: WEIGHMENT - 16-31 Aug 25 | K7: {=VLOOKUP(E7,[2]A023951!D$1:H$1114,{3,5},0)} -> -409.79 | L7: -35918.88 | M7: =I7+L7 -> -56.38
A8: KUEHNE+NAGEL PVT. LTD. | B8: 2025 | C8: DR | D8: 45904 | E8: 256779417158 | F8: USD | G8: 110 | H8: INR | I8: 9626.58 | J8: Intra 16-31 Aug 25 | K8: {=VLOOKUP(E8,[2]A023951!D$1:H$1114,{3,5},0)} -> -110 | L8: -9641.71 | M8: =I8+L8 -> -15.13
A9: KUEHNE+NAGEL PVT. LTD. | B9: 2025 | C9: DR | D9: 45904 | E9: 256779417200 | F9: USD | G9: 100.74 | H9: INR | I9: 8816.19 | J9: Empty Lolo Chgs - 01 - 31 AUG 25 | K9: {=VLOOKUP(E9,[2]A023951!D$1:H$1114,{3,5},0)} -> -100.74 | L9: -8830.05 | M9: =I9+L9 -> -13.86
A10: KUEHNE+NAGEL PVT. LTD. | B10: 2025 | C10: DR | D10: 45904 | E10: 256779417238 | F10: USD | G10: 608.78 | H10: INR | I10: 53276.97 | J10: PORT SSR Chgs Aug 25 | K10: {=VLOOKUP(E10,[2]A023951!D$1:H$1114,{3,5},0)} -> -608.78 | L10: -53360.74 | M10: =I10+L10 -> -83.77
A11: KUEHNE+NAGEL PVT. LTD. | B11: 2025 | C11: DR | D11: 45904 | E11: 256779417250 | F11: USD | G11: 50 | H11: INR | I11: 4375.72 | J11: Scanning Chgs - 16 - 31 Aug 25 | K11: {=VLOOKUP(E11,[2]A023951!D$1:H$1114,{3,5},0)} -> #N/A
A12: KUEHNE+NAGEL PVT. LTD. | B12: 2025 | C12: DR | D12: 45904 | E12: 256779417257 | F12: USD | G12: 22.77 | H12: INR | I12: 1992.7 | J12: Bond Stamp Paper Chgs 01 - 31 Aug 25 | K12: {=VLOOKUP(E12,[2]A023951!D$1:H$1114,{3,5},0)} -> -22.77 | L12: -1995.83 | M12: =I12+L12 -> -3.13
A13: KUEHNE+NAGEL PVT. LTD. | B13: 2025 | C13: DR | D13: 45904 | E13: 256779417280 | F13: USD | G13: 249.98 | H13: INR | I13: 21876.83 | J13: LCL Chgs - 16 - 31 AUG 25 | K13: {=VLOOKUP(E13,[2]A023951!D$1:H$1114,{3,5},0)} -> -249.98 | L13: -21911.23 | M13: =I13+L13 -> -34.4
A14: KUEHNE+NAGEL PVT. LTD. | B14: 2025 | C14: DR | D14: 45904 | E14: 256779417317 | F14: USD | G14: 170.85 | H14: INR | I14: 14951.82 | J14: Outbound chgs - 16 - 31 Aug 25 | K14: {=VLOOKUP(E14,[2]A023951!D$1:H$1114,{3,5},0)} -> -170.85 | L14: -14975.33 | M14: =I14+L14 -> -23.51
A15: KUEHNE+NAGEL PVT. LTD. | B15: 2025 | C15: DR | D15: 45842 | E15: 256779414859 | F15: USD | G15: 318.47 | H15: INR | I15: 27388.63 | J15: LCL Chgs - 16 - 30 JUN 25 | K15: {=VLOOKUP(E15,[2]A023951!D$1:H$1114,{3,5},0)} -> -318.47 | L15: -27385.08 | M15: =I15+L15 -> 3.55
A16: KUEHNE+NAGEL PVT. LTD. | B16: 2025 | C16: DR | D16: 45842 | E16: 256779415012 | F16: USD | G16: 184.3 | H16: INR | I16: 15849.92 | J16: Outbound chgs - 16 - 30 Jun 25 | K16: {=VLOOKUP(E16,[2]A023951!D$1:H$1114,{3,5},0)} -> -184 | L16: -15822.07 | M16: =I16+L16 -> 27.85
A17: KUEHNE+NAGEL PVT. LTD. | B17: 2025 | C17: DR | D17: 45842 | E17: 256779415208 | F17: USD | G17: 183.43 | H17: INR | I17: 15775.1 | J17: Unit Storage - 1-30 June 25 | K17: {=VLOOKUP(E17,[2]A023951!D$1:H$1114,{3,5},0)} -> -183.43 | L17: -16228.05 | M17: =I17+L17 -> -452.95
A18: KUEHNE+NAGEL PVT. LTD. | B18: 2025 | C18: DR | D18: 45842 | E18: 256779415209 | F18: USD | G18: 63.26 | H18: INR | I18: 5440.4 | J18: Unit Storage - 1-30 June 25 | K18: {=VLOOKUP(E18,[2]A023951!D$1:H$1114,{3,5},0)} -> -63.26 | L18: -5596.61 | M18: =I18+L18 -> -156.21
A19: KUEHNE+NAGEL PVT. LTD. | B19: 2025 | C19: DR | D19: 45842 | E19: 256779415210 | F19: USD | G19: 9629.63 | H19: INR | I19: 828154.63 | J19: Unit Storage - 1-30 June 25 | K19: {=VLOOKUP(E19,[2]A023951!D$1:H$1114,{3,5},0)} -> -9629.63 | L19: -851933.37 | M19: =I19+L19 -> -23778.74
A20: KUEHNE+NAGEL PVT. LTD. | B20: 2025 | C20: DR | D20: 45842 | E20: 256779415261 | F20: USD | G20: 292.96 | H20: INR | I20: 25194.76 | J20: VAS - 16-30 June 25 | K20: {=VLOOKUP(E20,[2]A023951!D$1:H$1114,{3,5},0)} -> -292.26 | L20: -25131.29 | M20: =I20+L20 -> 63.47
A21: KUEHNE+NAGEL PVT. LTD. | B21: 2025 | C21: DR | D21: 45842 | E21: 256779415270 | F21: USD | G21: 420.86 | H21: INR | I21: 36194.24 | J21: Weighment- 16-30 June 25 | K21: {=VLOOKUP(E21,[2]A023951!D$1:H$1114,{3,5},0)} -> -420.86 | L21: -37233.48 | M21: =I21+L21 -> -1039.24
A22: KUEHNE+NAGEL PVT. LTD. | B22: 2025 | C22: DR | D22: 45966 | E22: 256779418816 | F22: USD | G22: 891 | H22: INR | I22: 78411.02 | J22: VAS-16 -31 Oct 25 | K22: {=VLOOKUP(E22,[2]A023951!D$1:H$1114,{3,5},0)} -> #N/A
A23: KUEHNE+NAGEL PVT. LTD. | B23: 2025 | C23: DR | D23: 45966 | E23: 256779418872 | F23: USD | G23: 5939.04 | H23: INR | I23: 522655.65 | J23: Unit Storage - 1-31 Oct 2025 | K23: {=VLOOKUP(E23,[2]A023951!D$1:H$1114,{3,5},0)} -> #N/A
A24: KUEHNE+NAGEL PVT. LTD. | B24: 2025 | C24: DR | D24: 45966 | E24: 256779418892 | F24: USD | G24: 1683.97 | H24: INR | I24: 148195.07 | J24: CODC Inbound chgs - 16-31 Oct 25 | K24: {=VLOOKUP(E24,[2]A023951!D$1:H$1114,{3,5},0)} -> -1683.97 | L24: -148614.68 | M24: =I24+L24 -> -419.61
A25: KUEHNE+NAGEL PVT. LTD. | B25: 2025 | C25: DR | D25: 45966 | E25: 256779418904 | F25: USD | G25: 1273.92 | H25: INR | I25: 112109.28 | J25: CODC Out chgs -16-31 Oct 25 | K25: {=VLOOKUP(E25,[2]A023951!D$1:H$1114,{3,5},0)} -> -1273.92 | L25: -112426.72 | M25: =I25+L25 -> -317.44
A26: KUEHNE+NAGEL PVT. LTD. | B26: 2025 | C26: DR | D26: 45966 | E26: 256779419165 | F26: USD | G26: 191.57 | H26: INR | I26: 16858.81 | J26: Outbound chgs - 16 - 31 Oct 25 | K26: {=VLOOKUP(E26,[2]A023951!D$1:H$1114,{3,5},0)} -> -191.57 | L26: -16906.55 | M26: =I26+L26 -> -47.74
A27: KUEHNE+NAGEL PVT. LTD. | B27: 2025 | C27: DR | D27: 45966 | E27: 256779419192 | F27: USD | G27: 171.87 | H27: INR | I27: 15125.14 | J27: Empty Lolo Chgs - 01 - 31 OCT 25 | K27: {=VLOOKUP(E27,[2]A023951!D$1:H$1114,{3,5},0)} -> -171.87 | L27: -15167.97 | M27: =I27+L27 -> -42.83
A28: KUEHNE+NAGEL PVT. LTD. | B28: 2025 | C28: DR | D28: 45966 | E28: 256779419211 | F28: USD | G28: 28.18 | H28: INR | I28: 2479.94 | J28: Internet Activity Chgs - Oct 25 | K28: {=VLOOKUP(E28,[2]A023951!D$1:H$1114,{3,5},0)} -> -28.18 | L28: -2486.96 | M28: =I28+L28 -> -7.02
A29: KUEHNE+NAGEL PVT. LTD. | B29: 2025 | C29: DR | D29: 45966 | E29: 256779419222 | F29: USD | G29: 3537 | H29: INR | I29: 311267.99 | J29: PORT SSR Chgs Oct 25 | K29: {=VLOOKUP(E29,[2]A023951!D$1:H$1114,{3,5},0)} -> #N/A
A30: KUEHNE+NAGEL PVT. LTD. | B30: 2025 | C30: DR | D30: 45964 | E30: 256779419122 | F30: USD | G30: 670.42 | H30: INR | I30: 58999.23 | J30: LCL Chgs - 16 - 31 OCT 25 | K30: {=VLOOKUP(E30,[2]A023951!D$1:H$1114,{3,5},0)} -> -670.42 | L30: -59439.1 | M30: =I30+L30 -> -439.87
A31: KUEHNE+NAGEL PVT. LTD. | B31: 2025 | C31: DG | D31: 45964 | E31: 256779422067 | F31: USD | G31: -4608.8 | H31: INR | I31: -405590.02 | J31: CN issued against 256779417093 | K31: {=VLOOKUP(E31,[2]A023951!D$1:H$1114,{3,5},0)} -> #N/A
A32: KUEHNE+NAGEL PVT. LTD. | B32: 2025 | C32: DR | D32: 45877 | E32: 256779416096 | F32: USD | G32: 7386.34 | H32: INR | I32: 635447.72 | J32: Unit Storage - 1-31 July 25 | K32: {=VLOOKUP(E32,[2]A023951!D$1:H$1114,{3,5},0)} -> -7386.34 | L32: -639885.33 | M32: =I32+L32 -> -4437.61
A33: KUEHNE+NAGEL PVT. LTD. | B33: 2025 | C33: DR | D33: 45877 | E33: 256779416137 | F33: USD | G33: 55.28 | H33: INR | I33: 4755.75 | J33: Empty Lolo Chgs - 01 - 31 JUL 25 | K33: {=VLOOKUP(E33,[2]A023951!D$1:H$1114,{3,5},0)} -> -55 | L33: -4764.7 | M33: =I33+L33 -> -8.95
A34: KUEHNE+NAGEL PVT. LTD. | B34: 2025 | C34: DR | D34: 45877 | E34: 256779416169 | F34: USD | G34: 256.97 | H34: INR | I34: 22107.16 | J34: LCL Chgs - 16 - 31 JUL 25 | K34: {=VLOOKUP(E34,[2]A023951!D$1:H$1114,{3,5},0)} -> -257 | L34: -22264.14 | M34: =I34+L34 -> -156.98
A35: KUEHNE+NAGEL PVT. LTD. | B35: 2025 | C35: DR | D35: 45877 | E35: 256779416214 | F35: USD | G35: 212.34 | H35: INR | I35: 18267.64 | J35: Outbound chgs - 16 - 31 Jul 25 | K35: {=VLOOKUP(E35,[2]A023951!D$1:H$1114,{3,5},0)} -> -212 | L35: -18365.75 | M35: =I35+L35 -> -98.11
A36: KUEHNE+NAGEL PVT. LTD. | B36: 2025 | C36: DR | D36: 45877 | E36: 256779416255 | F36: USD | G36: 392.28 | H36: INR | I36: 33747.9 | J36: CODC Out chgs - 16 - 31 Jul 25 | K36: {=VLOOKUP(E36,[2]A023951!D$1:H$1114,{3,5},0)} -> -392 | L36: -33959.32 | M36: =I36+L36 -> -211.42
A37: KUEHNE+NAGEL PVT. LTD. | B37: 2025 | C37: DR | D37: 45877 | E37: 256779416442 | F37: USD | G37: 1053.34 | H37: INR | I37: 90618.97 | J37: VAS 16-31 July 25 | K37: {=VLOOKUP(E37,[2]A023951!D$1:H$1114,{3,5},0)} -> -1053 | L37: -91222.35 | M37: =I37+L37 -> -603.38
A38: KUEHNE+NAGEL PVT. LTD. | B38: 2025 | C38: DR | D38: 45877 | E38: 256779416454 | F38: USD | G38: 411.19 | H38: INR | I38: 35374.73 | J38: Weighment - 16-31 July 25 | K38: {=VLOOKUP(E38,[2]A023951!D$1:H$1114,{3,5},0)} -> -411 | L38: -35605.3 | M38: =I38+L38 -> -230.57
A39: KUEHNE+NAGEL PVT. LTD. | B39: 2025 | C39: DR | D39: 45812 | E39: 256779414156 | F39: USD | G39: 83.66 | H39: INR | I39: 7152.16 | J39: CODC Inbound chgs - 16 - 31 May 25 | K39: {=VLOOKUP(E39,[2]A023951!D$1:H$1114,{3,5},0)} -> #N/A
A40: KUEHNE+NAGEL PVT. LTD. | B40: 2025 | C40: DR | D40: 45812 | E40: 256779414173 | F40: USD | G40: 2668.72 | H40: INR | I40: 228150.95 | J40: PORT SSR Chgs - 16 - 31 May 25 | K40: {=VLOOKUP(E40,[2]A023951!D$1:H$1114,{3,5},0)} -> #N/A
A41: KUEHNE+NAGEL PVT. LTD. | B41: 2025 | C41: DR | D41: 45812 | E41: 256779414206 | F41: USD | G41: 201.33 | H41: INR | I41: 17211.86 | J41: Outbound chgs - 16 - 31 MAY 25 | K41: {=VLOOKUP(E41,[2]A023951!D$1:H$1114,{3,5},0)} -> #N/A
A42: KUEHNE+NAGEL PVT. LTD. | B42: 2025 | C42: DR | D42: 45812 | E42: 256779414260 | F42: USD | G42: 130.93 | H42: INR | I42: 11193.31 | J42: Detention Chgs - 01 - 15 MAY 25 | K42: {=VLOOKUP(E42,[2]A023951!D$1:H$1114,{3,5},0)} -> #N/A
A43: KUEHNE+NAGEL PVT. LTD. | B43: 2025 | C43: DR | D43: 45812 | E43: 256779414271 | F43: USD | G43: 967.68 | H43: INR | I43: 82727.72 | J43: Empty Lolo Chgs - 01 - 31 MAY 25 | K43: {=VLOOKUP(E43,[2]A023951!D$1:H$1114,{3,5},0)} -> #N/A
A44: KUEHNE+NAGEL PVT. LTD. | B44: 2025 | C44: DR | D44: 45812 | E44: 256779414309 | F44: USD | G44: 662.83 | H44: INR | I44: 56665.85 | J44: Transportation In Chgs - 16-31 MAY 25 | K44: {=VLOOKUP(E44,[2]A023951!D$1:H$1114,{3,5},0)} -> #N/A
A45: KUEHNE+NAGEL PVT. LTD. | B45: 2025 | C45: DG | D45: 45791 | E45: 256779420272 | F45: USD | G45: -40.06 | H45: INR | I45: -3472.85 | J45: Credit note against 246779412202 | K45: {=VLOOKUP(E45,[2]A023951!D$1:H$1114,{3,5},0)} -> #N/A
A46: KUEHNE+NAGEL PVT. LTD. | B46: 2025 | C46: DG | D46: 45791 | E46: 256779420273 | F46: USD | G46: -28.62 | H46: INR | I46: -2481.1 | J46: Credit note against 246779412203 | K46: {=VLOOKUP(E46,[2]A023951!D$1:H$1114,{3,5},0)} -> #N/A
A47: KUEHNE+NAGEL PVT. LTD. | B47: 2025 | C47: DG | D47: 45791 | E47: 256779420275 | F47: USD | G47: -114.46 | H47: INR | I47: -9922.68 | J47: Credit note against 246779412205 | K47: {=VLOOKUP(E47,[2]A023951!D$1:H$1114,{3,5},0)} -> #N/A
A48: KUEHNE+NAGEL PVT. LTD. | B48: 2025 | C48: DG | D48: 45791 | E48: 256779420276 | F48: USD | G48: -68.68 | H48: INR | I48: -5953.96 | J48: Credit note against 246779412206 | K48: {=VLOOKUP(E48,[2]A023951!D$1:H$1114,{3,5},0)} -> #N/A
A49: KUEHNE+NAGEL PVT. LTD. | B49: 2025 | C49: DG | D49: 45791 | E49: 256779420268 | F49: USD | G49: -249.55 | H49: INR | I49: -21633.8 | J49: Credit note against 246779412198 | K49: {=VLOOKUP(E49,[2]A023951!D$1:H$1114,{3,5},0)} -> #N/A
A50: KUEHNE+NAGEL PVT. LTD. | B50: 2025 | C50: DG | D50: 45791 | E50: 256779420269 | F50: USD | G50: -40.06 | H50: INR | I50: -3472.85 | J50: Credit note against 246779412199 | K50: {=VLOOKUP(E50,[2]A023951!D$1:H$1114,{3,5},0)} -> #N/A
... A62: KUEHNE+NAGEL PVT. LTD. | B62: 2025 | C62: DR | D62: 45793 | E62: 256779413348 | F62: USD | G62: 138.82 | H62: INR | I62: 11936.26 | J62: Outbound chgs - 16 - 30 Apr 25 | K62: {=VLOOKUP(E62,[2]A023951!D$1:H$1114,{3,5},0)} -> #N/A
A63: KUEHNE+NAGEL PVT. LTD. | B63: 2025 | C63: DR | D63: 46000 | E63: 256779419995 | F63: USD | G63: 187.19 | H63: INR | I63: 16603.78 | J63: CODC LCL Chgs -16-30 Nov 25 | K63: {=VLOOKUP(E63,[2]A023951!D$1:H$1114,{3,5},0)} -> -187.19 | L63: -16688.88 | M63: =I63+L63 -> -85.1
A64: KUEHNE+NAGEL PVT. LTD. | B64: 2025 | C64: DR | D64: 45805 | E64: 256779413908 | F64: USD | G64: 3200.83 | H64: INR | I64: 275219.21 | J64: Storage Chgs - 01 - 31 Apr 25 | K64: {=VLOOKUP(E64,[2]A023951!D$1:H$1114,{3,5},0)} -> -3200.83 | L64: -273269.16 | M64: =I64+L64 -> 1950.05
A65: KUEHNE+NAGEL PVT. LTD. | B65: 2025 | C65: DR | D65: 45856 | E65: 256779415426 | F65: USD | G65: 464.73 | H65: INR | I65: 39967.09 | J65: PORT SSR Chgs Apr & May 25 | K65: {=VLOOKUP(E65,[2]A023951!D$1:H$1114,{3,5},0)} -> -464.73 | L65: -39961.91 | M65: =I65+L65 -> 5.18
A66: KUEHNE+NAGEL PVT. LTD. | B66: 2025 | C66: DR | D66: 45856 | E66: 256779415442 | F66: USD | G66: 1.59 | H66: INR | I66: 136.74 | J66: CODC Inbound Chgs - 01 - 15 July 25 | K66: {=VLOOKUP(E66,[2]A023951!D$1:H$1114,{3,5},0)} -> -1.59 | L66: -136.72 | M66: =I66+L66 -> 0.02
A67: KUEHNE+NAGEL PVT. LTD. | B67: 2025 | C67: DR | D67: 45856 | E67: 256779415453 | F67: USD | G67: 293.46 | H67: INR | I67: 25237.76 | J67: CODC Out chgs - 01 - 15 July 25 | K67: {=VLOOKUP(E67,[2]A023951!D$1:H$1114,{3,5},0)} -> -293.46 | L67: -25234.48 | M67: =I67+L67 -> 3.28
A68: KUEHNE+NAGEL PVT. LTD. | B68: 2025 | C68: DR | D68: 45856 | E68: 256779415474 | F68: USD | G68: 608.41 | H68: INR | I68: 52323.67 | J68: Transportation In Chgs - 01 - 15 JUL 25 | K68: {=VLOOKUP(E68,[2]A023951!D$1:H$1114,{3,5},0)} -> -608.41 | L68: -52316.88 | M68: =I68+L68 -> 6.79
A69: KUEHNE+NAGEL PVT. LTD. | B69: 2025 | C69: DR | D69: 45856 | E69: 256779415517 | F69: USD | G69: 116.74 | H69: INR | I69: 10039.72 | J69: Outbound chgs - 01 - 15 Jul 25 | K69: {=VLOOKUP(E69,[2]A023951!D$1:H$1114,{3,5},0)} -> -116.74 | L69: -10038.42 | M69: =I69+L69 -> 1.3
A70: KUEHNE+NAGEL PVT. LTD. | B70: 2025 | C70: DR | D70: 45856 | E70: 256779415792 | F70: USD | G70: 608.41 | H70: INR | I70: 52323.67 | J70: Transportation In Chgs - 01 - 15 JUL 25 | K70: {=VLOOKUP(E70,[2]A023951!D$1:H$1114,{3,5},0)} -> #N/A
A71: KUEHNE+NAGEL PVT. LTD. | B71: 2025 | C71: DR | D71: 45729 | E71: 246779411312 | F71: USD | G71: 27 | H71: INR | I71: 2340.66 | J71: Scanning Charges for the month of October, 2024 | K71: {=VLOOKUP(E71,[2]A023951!D$1:H$1114,{3,5},0)} -> -27 | L71: -2350.15 | M71: =I71+L71 -> -9.49
A72: KUEHNE+NAGEL PVT. LTD. | B72: 2025 | C72: DR | D72: 45736 | E72: 246779413730 | F72: USD | G72: 3.2 | H72: INR | I72: 277.41 | J72: Outbound Handling charges for Jan 2025 | K72: {=VLOOKUP(E72,[2]A023951!D$1:H$1114,{3,5},0)} -> -3.2 | L72: -278.54 | M72: =I72+L72 -> -1.13
A73: KUEHNE+NAGEL PVT. LTD. | B73: 2025 | C73: DR | D73: 45736 | E73: 246779413747 | F73: USD | G73: 2.74 | H73: INR | I73: 237.53 | J73: Outbound Handling charges for Feb 2025 | K73: {=VLOOKUP(E73,[2]A023951!D$1:H$1114,{3,5},0)} -> -2.74 | L73: -238.5 | M73: =I73+L73 -> -0.97
A74: KUEHNE+NAGEL PVT. LTD. | B74: 2025 | C74: DR | D74: 45736 | E74: 246779413815 | F74: USD | G74: 50 | H74: INR | I74: 4334.56 | J74: Scanning Charges for the month of Feb 2025 | K74: {=VLOOKUP(E74,[2]A023951!D$1:H$1114,{3,5},0)} -> -50 | L74: -4352.12 | M74: =I74+L74 -> -17.56
A75: KUEHNE+NAGEL PVT. LTD. | B75: 2025 | C75: DR | D75: 45736 | E75: 246779413920 | F75: USD | G75: 22.5 | H75: INR | I75: 1950.55 | J75: Outbound Handling charges for Feb 2025 | K75: {=VLOOKUP(E75,[2]A023951!D$1:H$1114,{3,5},0)} -> -22.5 | L75: -1958.45 | M75: =I75+L75 -> -7.9
A76: KUEHNE+NAGEL PVT. LTD. | B76: 2025 | C76: DR | D76: 45736 | E76: 246779413936 | F76: USD | G76: 27.5 | H76: INR | I76: 2384.01 | J76: Outbound Handling charges for Feb 2025 | K76: {=VLOOKUP(E76,[2]A023951!D$1:H$1114,{3,5},0)} -> -27.5 | L76: -2393.67 | M76: =I76+L76 -> -9.66
A77: KUEHNE+NAGEL PVT. LTD. | B77: 2025 | C77: DR | D77: 45736 | E77: 246779413941 | F77: USD | G77: 30 | H77: INR | I77: 2600.74 | J77: Outbound Handling charges for Feb 2025 | K77: {=VLOOKUP(E77,[2]A023951!D$1:H$1114,{3,5},0)} -> -30 | L77: -2611.27 | M77: =I77+L77 -> -10.53
A78: KUEHNE+NAGEL PVT. LTD. | B78: 2025 | C78: DR | D78: 45736 | E78: 246779414384 | F78: USD | G78: 182.5 | H78: INR | I78: 15821.15 | J78: Inbound Handling charges for Nov 2024 | K78: {=VLOOKUP(E78,[2]A023951!D$1:H$1114,{3,5},0)} -> -182.5 | L78: -15885.24 | M78: =I78+L78 -> -64.09
A79: KUEHNE+NAGEL PVT. LTD. | B79: 2025 | C79: DR | D79: 45736 | E79: 246779414385 | F79: USD | G79: 240 | H79: INR | I79: 20805.9 | J79: LCL Movement Charges for Nov 2024 | K79: {=VLOOKUP(E79,[2]A023951!D$1:H$1114,{3,5},0)} -> -240 | L79: -20890.18 | M79: =I79+L79 -> -84.28
A80: KUEHNE+NAGEL PVT. LTD. | B80: 2025 | C80: DR | D80: 45736 | E80: 246779414057 | F80: USD | G80: 43.07 | H80: INR | I80: 3733.79 | J80: Inbound Handling charges for Jan 2025 | K80: {=VLOOKUP(E80,[2]A023951!D$1:H$1114,{3,5},0)} -> #N/A
A81: KUEHNE+NAGEL PVT. LTD. | B81: 2025 | C81: DR | D81: 45736 | E81: 246779414058 | F81: USD | G81: 398.23 | H81: INR | I81: 34523.06 | J81: Inbound Handling charges for Jan 2025 | K81: {=VLOOKUP(E81,[2]A023951!D$1:H$1114,{3,5},0)} -> #N/A
A82: KUEHNE+NAGEL PVT. LTD. | B82: 2025 | C82: DR | D82: 45736 | E82: 246779414120 | F82: USD | G82: 250.75 | H82: INR | I82: 21737.83 | J82: Inbound Handling charges for Sep 2024 | K82: {=VLOOKUP(E82,[2]A023951!D$1:H$1114,{3,5},0)} -> #N/A
A83: KUEHNE+NAGEL PVT. LTD. | B83: 2025 | C83: DR | D83: 45736 | E83: 246779414121 | F83: USD | G83: 226.56 | H83: INR | I83: 19640.77 | J83: LCL charges for Sep 2024 | K83: {=VLOOKUP(E83,[2]A023951!D$1:H$1114,{3,5},0)} -> #N/A
A84: KUEHNE+NAGEL PVT. LTD. | B84: 2025 | C84: DR | D84: 45736 | E84: 246779414122 | F84: USD | G84: 35.4 | H84: INR | I84: 3068.87 | J84: Cy-WH Destuff charges for Sep 2024 | K84: {=VLOOKUP(E84,[2]A023951!D$1:H$1114,{3,5},0)} -> #N/A
A85: KUEHNE+NAGEL PVT. LTD. | B85: 2025 | C85: DR | D85: 45736 | E85: 246779414204 | F85: USD | G85: 249.87 | H85: INR | I85: 21661.55 | J85: Outbound Handling charges for Sep 2024 | K85: {=VLOOKUP(E85,[2]A023951!D$1:H$1114,{3,5},0)} -> #N/A
A86: KUEHNE+NAGEL PVT. LTD. | B86: 2025 | C86: DR | D86: 45736 | E86: 246779414460 | F86: USD | G86: 173.05 | H86: INR | I86: 15001.92 | J86: Inbound Handling charges for Jan 2025 | K86: {=VLOOKUP(E86,[2]A023951!D$1:H$1114,{3,5},0)} -> #N/A
A87: KUEHNE+NAGEL PVT. LTD. | B87: 2025 | C87: DR | D87: 45736 | E87: 246779414461 | F87: USD | G87: 226.56 | H87: INR | I87: 19640.77 | J87: LCL charges for Jan 2025 | K87: {=VLOOKUP(E87,[2]A023951!D$1:H$1114,{3,5},0)} -> #N/A
A88: KUEHNE+NAGEL PVT. LTD. | B88: 2025 | C88: DR | D88: 45736 | E88: 246779414525 | F88: USD | G88: 211.39 | H88: INR | I88: 18325.67 | J88: Inbound Handling charges for Feb 2025 | K88: {=VLOOKUP(E88,[2]A023951!D$1:H$1114,{3,5},0)} -> #N/A
A89: KUEHNE+NAGEL PVT. LTD. | B89: 2025 | C89: DR | D89: 45736 | E89: 246779414526 | F89: USD | G89: 141.6 | H89: INR | I89: 12275.48 | J89: LCL Movement Charges for Feb 2025 | K89: {=VLOOKUP(E89,[2]A023951!D$1:H$1114,{3,5},0)} -> #N/A
A90: KUEHNE+NAGEL PVT. LTD. | B90: 2025 | C90: DR | D90: 45736 | E90: 246779414527 | F90: USD | G90: 70.8 | H90: INR | I90: 6137.74 | J90: Empty transportation Charges for Feb 2025 | K90: {=VLOOKUP(E90,[2]A023951!D$1:H$1114,{3,5},0)} -> #N/A
A91: KUEHNE+NAGEL PVT. LTD. | B91: 2025 | C91: DR | D91: 45736 | E91: 246779414528 | F91: USD | G91: 236 | H91: INR | I91: 20459.14 | J91: Transportation Charges for Feb 2025 | K91: {=VLOOKUP(E91,[2]A023951!D$1:H$1114,{3,5},0)} -> #N/A
... A99: KUEHNE+NAGEL PVT. LTD. | B99: 2025 | C99: DR | D99: 45736 | E99: 246779414869 | F99: USD | G99: 35.4 | H99: INR | I99: 3068.87 | J99: Outbound Handling charges for Jan 2025 | K99: {=VLOOKUP(E99,[2]A023951!D$1:H$1114,{3,5},0)} -> #N/A
A100: KUEHNE+NAGEL PVT. LTD. | B100: 2025 | C100: DR | D100: 45736 | E100: 246779413889 | F100: USD | G100: 42.5 | H100: INR | I100: 3684.38 | J100: Outbound Handling charges for Feb 2025 | K100: {=VLOOKUP(E100,[2]A023951!D$1:H$1114,{3,5},0)} -> -42.5 | L100: -3699.3 | M100: =I100+L100 -> -14.92
A101: KUEHNE+NAGEL PVT. LTD. | B101: 2025 | C101: DR | D101: 45736 | E101: 246779414662 | F101: USD | G101: 275 | H101: INR | I101: 23840.1 | J101: Outbound Handling charges for Nov 2024 | K101: {=VLOOKUP(E101,[2]A023951!D$1:H$1114,{3,5},0)} -> -275 | L101: -23936.66 | M101: =I101+L101 -> -96.56
A102: KUEHNE+NAGEL PVT. LTD. | B102: 2025 | C102: DR | D102: 45736 | E102: 246779414663 | F102: USD | G102: 45 | H102: INR | I102: 3901.11 | J102: CY-MOVEMENT CHARGES for Nov 2024 | K102: {=VLOOKUP(E102,[2]A023951!D$1:H$1114,{3,5},0)} -> -45 | L102: -3916.91 | M102: =I102+L102 -> -15.8
A103: KUEHNE+NAGEL PVT. LTD. | B103: 2025 | C103: DR | D103: 45736 | E103: 246779414590 | F103: USD | G103: 300.49 | H103: INR | I103: 26049.86 | J103: Outbound Handling charges for Oct 2024 | K103: {=VLOOKUP(E103,[2]A023951!D$1:H$1114,{3,5},0)} -> #N/A
A104: KUEHNE+NAGEL PVT. LTD. | B104: 2025 | C104: DR | D104: 45736 | E104: 246779414726 | F104: USD | G104: 165.4 | H104: INR | I104: 14338.73 | J104: Outbound Handling charges for Jan 2025 | K104: {=VLOOKUP(E104,[2]A023951!D$1:H$1114,{3,5},0)} -> #N/A
A105: KUEHNE+NAGEL PVT. LTD. | B105: 2025 | C105: DR | D105: 45708 | E105: 246779410010 | F105: USD | G105: 2380.95 | H105: INR | I105: 205484.7 | J105: Fixed Rental charges for Aug 2024 | K105: {=VLOOKUP(E105,[2]A023951!D$1:H$1114,{3,5},0)} -> -2380.95 | L105: -206046.42 | M105: =I105+L105 -> -561.72
A106: KUEHNE+NAGEL PVT. LTD. | B106: 2025 | C106: DR | D106: 45708 | E106: 246779410030 | F106: USD | G106: 2380.95 | H106: INR | I106: 205484.7 | J106: Fixed Rental charges for Sept 2024 | K106: {=VLOOKUP(E106,[2]A023951!D$1:H$1114,{3,5},0)} -> -2380.95 | L106: -206046.42 | M106: =I106+L106 -> -561.72
A107: KUEHNE+NAGEL PVT. LTD. | B107: 2025 | C107: DR | D107: 45708 | E107: 246779410063 | F107: USD | G107: 95.24 | H107: INR | I107: 8219.56 | J107: Office space charges for Sept 2024 | K107: {=VLOOKUP(E107,[2]A023951!D$1:H$1114,{3,5},0)} -> -95.24 | L107: -8242.03 | M107: =I107+L107 -> -22.47
A108: KUEHNE+NAGEL PVT. LTD. | B108: 2025 | C108: DR | D108: 45708 | E108: 246779410064 | F108: USD | G108: 52.38 | H108: INR | I108: 4520.59 | J108: Utility charge- Electricity for Sept 2024 | K108: {=VLOOKUP(E108,[2]A023951!D$1:H$1114,{3,5},0)} -> -52.38 | L108: -4532.94 | M108: =I108+L108 -> -12.35
A109: KUEHNE+NAGEL PVT. LTD. | B109: 2025 | C109: DR | D109: 45708 | E109: 246779410080 | F109: USD | G109: 95.24 | H109: INR | I109: 8219.56 | J109: Office space charges - Aug, 2024 | K109: {=VLOOKUP(E109,[2]A023951!D$1:H$1114,{3,5},0)} -> -95.24 | L109: -8242.03 | M109: =I109+L109 -> -22.47
A110: KUEHNE+NAGEL PVT. LTD. | B110: 2025 | C110: DR | D110: 45708 | E110: 246779410098 | F110: USD | G110: 2380.95 | H110: INR | I110: 205484.7 | J110: Fixed Rental charges for Nov 2024 | K110: {=VLOOKUP(E110,[2]A023951!D$1:H$1114,{3,5},0)} -> -2380.95 | L110: -206046.42 | M110: =I110+L110 -> -561.72
A111: KUEHNE+NAGEL PVT. LTD. | B111: 2025 | C111: DR | D111: 45708 | E111: 246779410131 | F111: USD | G111: 95.24 | H111: INR | I111: 8219.56 | J111: Office space charges for Nov 2024 | K111: {=VLOOKUP(E111,[2]A023951!D$1:H$1114,{3,5},0)} -> -95.24 | L111: -8242.03 | M111: =I111+L111 -> -22.47
A112: KUEHNE+NAGEL PVT. LTD. | B112: 2025 | C112: DR | D112: 45708 | E112: 246779410132 | F112: USD | G112: 52.38 | H112: INR | I112: 4520.59 | J112: Utility charge- Electricity for Nov 2024 | K112: {=VLOOKUP(E112,[2]A023951!D$1:H$1114,{3,5},0)} -> -52.38 | L112: -4532.94 | M112: =I112+L112 -> -12.35
A113: KUEHNE+NAGEL PVT. LTD. | B113: 2025 | C113: DR | D113: 45708 | E113: 246779410141 | F113: USD | G113: 2380.95 | H113: INR | I113: 205484.7 | J113: Fixed Rental charges for Dec 2024 | K113: {=VLOOKUP(E113,[2]A023951!D$1:H$1114,{3,5},0)} -> -2380.95 | L113: -206046.42 | M113: =I113+L113 -> -561.72
A114: KUEHNE+NAGEL PVT. LTD. | B114: 2025 | C114: DR | D114: 45708 | E114: 246779410174 | F114: USD | G114: 95.24 | H114: INR | I114: 8219.56 | J114: Office space charges for Dec 2024 | K114: {=VLOOKUP(E114,[2]A023951!D$1:H$1114,{3,5},0)} -> -95.24 | L114: -8242.03 | M114: =I114+L114 -> -22.47
A115: KUEHNE+NAGEL PVT. LTD. | B115: 2025 | C115: DR | D115: 45708 | E115: 246779410175 | F115: USD | G115: 52.38 | H115: INR | I115: 4520.59 | J115: Utility charge- Electricity for Dec 2024 | K115: {=VLOOKUP(E115,[2]A023951!D$1:H$1114,{3,5},0)} -> -52.38 | L115: -4532.94 | M115: =I115+L115 -> -12.35
A116: KUEHNE+NAGEL PVT. LTD. | B116: 2025 | C116: DR | D116: 45708 | E116: 246779410184 | F116: USD | G116: 2333.18 | H116: INR | I116: 201361.97 | J116: Fixed Rental charges for Jan 2025 | K116: {=VLOOKUP(E116,[2]A023951!D$1:H$1114,{3,5},0)} -> -2333.18 | L116: -201912.42 | M116: =I116+L116 -> -550.45
... A124: KUEHNE+NAGEL PVT. LTD. | B124: 2025 | C124: DR | D124: 45708 | E124: 246779410227 | F124: USD | G124: 2286.24 | H124: INR | I124: 197310.88 | J124: Fixed Rental charges for Feb 2025 | K124: {=VLOOKUP(E124,[2]A023951!D$1:H$1114,{3,5},0)} -> -2286.24 | L124: -197850.25 | M124: =I124+L124 -> -539.37
A125: KUEHNE+NAGEL PVT. LTD. | B125: 2025 | C125: DR | D125: 45889 | E125: 256779416593 | F125: USD | G125: 810 | H125: INR | I125: 69684.4 | J125: Empty Cont Out Chgs - 16 - 31 Jul 25 | K125: {=VLOOKUP(E125,[2]A023951!D$1:H$1114,{3,5},0)} -> #N/A
...

Sheet Sheet12
A1: Customer Account: Name 1 | B1: Fiscal Year | C1: Document Type | D1: Document Date | E1: Entry Date | F1: Reference | G1: Document Currency Key | H1: Document Currency Value | I1: Company Code Currency Key | J1: Company Code Currency Value | K1: Text
A2: KUEHNE+NAGEL PVT. LTD. | B2: 2025 | C2: DR | D2: 45904 | E2: 45909 | F2: 256779417250 | G2: USD | H2: 50 | I2: INR | J2: 4375.72 | K2: Scanning Chgs - 16 - 31 Aug 25
A3: KUEHNE+NAGEL PVT. LTD. | B3: 2025 | C3: DR | D3: 45966 | E3: 45967 | F3: 256779418816 | G3: USD | H3: 891 | I3: INR | J3: 78411.02 | K3: VAS-16 -31 Oct 25
A4: KUEHNE+NAGEL PVT. LTD. | B4: 2025 | C4: DR | D4: 45966 | E4: 45967 | F4: 256779418872 | G4: USD | H4: 5939.04 | I4: INR | J4: 522655.65 | K4: Unit Storage - 1-31 Oct 2025
A5: KUEHNE+NAGEL PVT. LTD. | B5: 2025 | C5: DR | D5: 45966 | E5: 45968 | F5: 256779419222 | G5: USD | H5: 3537 | I5: INR | J5: 311267.99 | K5: PORT SSR Chgs Oct 25
A6: KUEHNE+NAGEL PVT. LTD. | B6: 2025 | C6: DR | D6: 45812 | E6: 45817 | F6: 256779414156 | G6: USD | H6: 83.66 | I6: INR | J6: 7152.16 | K6: CODC Inbound chgs - 16 - 31 May 25
A7: KUEHNE+NAGEL PVT. LTD. | B7: 2025 | C7: DR | D7: 45812 | E7: 45817 | F7: 256779414173 | G7: USD | H7: 2668.72 | I7: INR | J7: 228150.95 | K7: PORT SSR Chgs - 16 - 31 May 25
A8: KUEHNE+NAGEL PVT. LTD. | B8: 2025 | C8: DR | D8: 45812 | E8: 45817 | F8: 256779414206 | G8: USD | H8: 201.33 | I8: INR | J8: 17211.86 | K8: Outbound chgs - 16 - 31 MAY 25
A9: KUEHNE+NAGEL PVT. LTD. | B9: 2025 | C9: DR | D9: 45812 | E9: 45817 | F9: 256779414260 | G9: USD | H9: 130.93 | I9: INR | J9: 11193.31 | K9: Detention Chgs - 01 - 15 MAY 25
A10: KUEHNE+NAGEL PVT. LTD. | B10: 2025 | C10: DR | D10: 45812 | E10: 45817 | F10: 256779414271 | G10: USD | H10: 967.68 | I10: INR | J10: 82727.72 | K10: Empty Lolo Chgs - 01 - 31 MAY 25
A11: KUEHNE+NAGEL PVT. LTD. | B11: 2025 | C11: DR | D11: 45812 | E11: 45817 | F11: 256779414309 | G11: USD | H11: 662.83 | I11: INR | J11: 56665.85 | K11: Transportation In Chgs - 16-31 MAY 25
A12: KUEHNE+NAGEL PVT. LTD. | B12: 2025 | C12: DR | D12: 45793 | E12: 45800 | F12: 256779413280 | G12: USD | H12: 59 | I12: INR | J12: 5073.04 | K12: Scanning Chgs - 16 - 31 Apr 25
A13: KUEHNE+NAGEL PVT. LTD. | B13: 2025 | C13: DR | D13: 45793 | E13: 45800 | F13: 256779413308 | G13: USD | H13: 723.47 | I13: INR | J13: 62206.63 | K13: LCL Chgs - 16 - 30 Apr 25
... A141: KUEHNE+NAGEL PVT. LTD. | B141: 2025 | C141: DR | D141: 45719 | E141: 45719 | F141: 246779410483 | G141: USD | H141: 3.54 | I141: INR | J141: 306.89 | K141: Outbound Handling for Aug 2024

Sheet Sheet4

Sheet CUSTOMER DATA
I1: =SUBTOTAL(9,I3:I751) -> 10371172 | X1: =SUBTOTAL(9,X3:X751) -> 0 | Y1: =SUBTOTAL(9,Y3:Y751) -> 10371172 | AB1: =SUBTOTAL(9,AB3:AB751) -> 0
A2: Creditor Code | B2: Creditor | C2: Ty | D2: Item# | E2: Item Date | F2: CCY | G2: FC Amount | H2: Settled FC Amount | I2: LC Amount | J2: Particular | K2: Due Date | L2: Last Sett. Date | M2: Job# | N2: VC Period | O2: VC# | P2: VC Seq | Q2: VC Date | R2: Tx. Type | S2: Reference | T2: Full Name | U2: Settled LC Amount | X2: TDS | Y2: Net balance | Z2: Remarks | AA2: vlookup | AB2: Difference
A3: A023951 | B3: A023951 | C3: I | D3: 246779411742 | E3: 45733 | F3: USD | G3: -23.27 | H3: 23.27 | I3: -2025.48 | J3: NO EXCHANGE RATE | K3: 45763 | L3: 45838 | M3: - | N3: 45809 | O3: 51127398 | P3: 1 | Q3: 45819 | R3: 210 | S3: 1.55e+16 | T3: Ascendas Panvel FTWZ Private Limited | U3: 2025.48 | W3: =X3/I3 -> -0.020197682 | X3: =VLOOKUP(D3,'[3]Customer TDS'!D:I,6,0) -> 40.91 | Y3: =I3+X3 -> -1984.57 | Z3: Diff due to exchange gain/loss | AA3: =VLOOKUP(D3,'Ascendus DATA'!$F:$J,5,0) -> 2017.31 | AB3: =I3+AA3 -> -8.17
A4: A023951 | B4: A023951 | C4: I | D4: 246779411737 | E4: 45733 | F4: USD | G4: -28.54 | H4: 28.54 | I4: -2484.19 | K4: 45763 | L4: 45838 | M4: - | N4: 45809 | O4: 51158463 | P4: 1 | Q4: 45820 | R4: 210 | S4: 1.55e+16 | T4: Ascendas Panvel FTWZ Private Limited | U4: 2484.19 | W4: =X4/I4 -> -0.019970292 | X4: =VLOOKUP(D4,'[3]Customer TDS'!D:I,6,0) -> 49.61 | Y4: =I4+X4 -> -2434.58 | Z4: Diff due to exchange gain/loss | AA4: =VLOOKUP(D4,'Ascendus DATA'!$F:$J,5,0) -> 2474.17 | AB4: =I4+AA4 -> -10.02
A5: A023951 | B5: A023951 | C5: I | D5: 246779411734 | E5: 45733 | F5: USD | G5: -22.83 | H5: 22.83 | I5: -1987.18 | K5: 45763 | L5: 45838 | M5: - | N5: 45809 | O5: 51158465 | P5: 1 | Q5: 45820 | R5: 210 | S5: 1.55e+16 | T5: Ascendas Panvel FTWZ Private Limited | U5: 1987.18 | W5: =X5/I5 -> -0.020149156 | X5: =VLOOKUP(D5,'[3]Customer TDS'!D:I,6,0) -> 40.04 | Y5: =I5+X5 -> -1947.14 | Z5: Diff due to exchange gain/loss | AA5: =VLOOKUP(D5,'Ascendus DATA'!$F:$J,5,0) -> 1979.16 | AB5: =I5+AA5 -> -8.02
A6: A023951 | B6: A023951 | C6: I | D6: 246779411732 | E6: 45733 | F6: USD | G6: -28.54 | H6: 28.54 | I6: -2484.19 | K6: 45763 | L6: 45838 | M6: - | N6: 45809 | O6: 51158468 | P6: 1 | Q6: 45820 | R6: 210 | S6: 1.55e+16 | T6: Ascendas Panvel FTWZ Private Limited | U6: 2484.19 | W6: =X6/I6 -> -0.019970292 | X6: =VLOOKUP(D6,'[3]Customer TDS'!D:I,6,0) -> 49.61 | Y6: =I6+X6 -> -2434.58 | Z6: Diff due to exchange gain/loss | AA6: =VLOOKUP(D6,'Ascendus DATA'!$F:$J,5,0) -> 2474.17 | AB6: =I6+AA6 -> -10.02
A7: A023951 | B7: A023951 | C7: I | D7: 246779411729 | E7: 45733 | F7: USD | G7: -34.25 | H7: 34.25 | I7: -2981.2 | J7: NO EXCHANGE RATE | K7: 45763 | L7: 45838 | M7: - | N7: 45809 | O7: 51158469 | P7: 1 | Q7: 45820 | R7: 210 | S7: 1.55e+16 | T7: Ascendas Panvel FTWZ Private Limited | U7: 2981.2 | W7: =X7/I7 -> -0.02014625 | X7: =VLOOKUP(D7,'[3]Customer TDS'!D:I,6,0) -> 60.06 | Y7: =I7+X7 -> -2921.14 | Z7: Diff due to exchange gain/loss | AA7: =VLOOKUP(D7,'Ascendus DATA'!$F:$J,5,0) -> 2969.18 | AB7: =I7+AA7 -> -12.02
A8: A023951 | B8: A023951 | C8: I | D8: 246779411724 | E8: 45733 | F8: USD | G8: -68.5 | H8: 68.5 | I8: -5962.41 | K8: 45763 | L8: 45838 | M8: - | N8: 45809 | O8: 51158473 | P8: 1 | Q8: 45820 | R8: 210 | S8: 1.55e+16 | T8: Ascendas Panvel FTWZ Private Limited | U8: 5962.41 | W8: =X8/I8 -> -0.020000302 | X8: =VLOOKUP(D8,'[3]Customer TDS'!D:I,6,0) -> 119.25 | Y8: =I8+X8 -> -5843.16 | Z8: Diff due to exchange gain/loss | AA8: =VLOOKUP(D8,'Ascendus DATA'!$F:$J,5,0) -> 5938.35 | AB8: =I8+AA8 -> -24.06
A9: A023951 | B9: A023951 | C9: I | D9: 246779411721 | E9: 45733 | F9: USD | G9: -525.63 | H9: 525.63 | I9: -45752.1 | K9: 45763 | L9: 45838 | M9: - | N9: 45809 | O9: 51158475 | P9: 1 | Q9: 45820 | R9: 210 | S9: 1.55e+16 | T9: Ascendas Panvel FTWZ Private Limited | U9: 45752.1 | W9: =X9/I9 -> -0.019995148 | X9: =VLOOKUP(D9,'[3]Customer TDS'!D:I,6,0) -> 914.82 | Y9: =I9+X9 -> -44837.28 | Z9: Diff due to exchange gain/loss | AA9: =VLOOKUP(D9,'Ascendus DATA'!$F:$J,5,0) -> 45567.53 | AB9: =I9+AA9 -> -184.57
A10: A023951 | B10: A023951 | C10: I | D10: 246779411741 | E10: 45733 | F10: USD | G10: -240 | H10: 240 | I10: -20890.18 | K10: 45763 | L10: 45838 | M10: - | N10: 45809 | O10: 51158478 | P10: 1 | Q10: 45820 | R10: 210 | S10: 1.55e+16 | T10: Ascendas Panvel FTWZ Private Limited | U10: 20890.18 | W10: =X10/I10 -> -0.019999828 | X10: =VLOOKUP(D10,'[3]Customer TDS'!D:I,6,0) -> 417.8 | Y10: =I10+X10 -> -20472.38 | Z10: Diff due to exchange gain/loss | AA10: =VLOOKUP(D10,'Ascendus DATA'!$F:$J,5,0) -> 20805.9 | AB10: =I10+AA10 -> -84.28
A11: A023951 | B11: A023951 | C11: I | D11: 246779410315 | E11: 45708 | F11: USD | G11: -2380.95 | H11: 2380.95 | I11: -207243.64 | K11: 45738 | L11: 45838 | M11: - | N11: 45809 | O11: 51158482 | P11: 1 | Q11: 45820 | R11: 210 | S11: 1.55e+16 | T11: Ascendas Panvel FTWZ Private Limited | U11: 207243.64 | W11: =X11/I11 -> -0.020000421 | X11: =VLOOKUP(D11,'[3]Customer TDS'!D:I,6,0) -> 4144.96 | Y11: =I11+X11 -> -203098.68 | Z11: Diff due to exchange gain/loss | AA11: =VLOOKUP(D11,'Ascendus DATA'!$F:$J,5,0) -> 205484.7 | AB11: =I11+AA11 -> -1758.94
A12: A023951 | B12: A023951 | C12: I | D12: 246779411735 | E12: 45733 | F12: USD | G12: -479.25 | H12: 479.25 | I12: -41715.08 | K12: 45763 | L12: 45838 | M12: - | N12: 45809 | O12: 51158483 | P12: 1 | Q12: 45820 | R12: 210 | S12: 1.55e+16 | T12: Ascendas Panvel FTWZ Private Limited | U12: 41715.08 | W12: =X12/I12 -> -0.020010509 | X12: =VLOOKUP(D12,'[3]Customer TDS'!D:I,6,0) -> 834.74 | Y12: =I12+X12 -> -40880.34 | Z12: Diff due to exchange gain/loss | AA12: =VLOOKUP(D12,'Ascendus DATA'!$F:$J,5,0) -> 41546.79 | AB12: =I12+AA12 -> -168.29
A13: A023951 | B13: A023951 | C13: I | D13: 246779411733 | E13: 45733 | F13: USD | G13: -17.12 | H13: 17.12 | I13: -1490.17 | K13: 45763 | L13: 45838 | M13: - | N13: 45809 | O13: 51158487 | P13: 1 | Q13: 45820 | R13: 210 | S13: 1.55e+16 | T13: Ascendas Panvel FTWZ Private Limited | U13: 1490.17 | W13: =X13/I13 -> -0.019856795 | X13: =VLOOKUP(D13,'[3]Customer TDS'!D:I,6,0) -> 29.59 | Y13: =I13+X13 -> -1460.58 | Z13: Diff due to exchange gain/loss | AA13: =VLOOKUP(D13,'Ascendus DATA'!$F:$J,5,0) -> 1484.15 | AB13: =I13+AA13 -> -6.02
A14: A023951 | B14: A023951 | C14: I | D14: 246779411727 | E14: 45733 | F14: USD | G14: -17.12 | H14: 17.12 | I14: -1490.17 | K14: 45763 | L14: 45838 | M14: - | N14: 45809 | O14: 51158492 | P14: 1 | Q14: 45820 | R14: 210 | S14: 1.55e+16 | T14: Ascendas Panvel FTWZ Private Limited | U14: 1490.17 | W14: =X14/I14 -> -0.019856795 | X14: =VLOOKUP(D14,'[3]Customer TDS'!D:I,6,0) -> 29.59 | Y14: =I14+X14 -> -1460.58 | Z14: Diff due to exchange gain/loss | AA14: =VLOOKUP(D14,'Ascendus DATA'!$F:$J,5,0) -> 1484.15 | AB14: =I14+AA14 -> -6.02
A15: A023951 | B15: A023951 | C15: I | D15: 246779411726 | E15: 45733 | F15: USD | G15: -28.54 | H15: 28.54 | I15: -2484.19 | K15: 45763 | L15: 45838 | M15: - | N15: 45809 | O15: 51158494 | P15: 1 | Q15: 45820 | R15: 210 | S15: 1.55e+16 | T15: Ascendas Panvel FTWZ Private Limited | U15: 2484.19 | W15: =X15/I15 -> -0.019970292 | X15: =VLOOKUP(D15,'[3]Customer TDS'!D:I,6,0) -> 49.61 | Y15: =I15+X15 -> -2434.58 | Z15: Diff due to exchange gain/loss | AA15: =VLOOKUP(D15,'Ascendus DATA'!$F:$J,5,0) -> 2474.17 | AB15: =I15+AA15 -> -10.02
A16: A023951 | B16: A023951 | C16: I | D16: 246779411720 | E16: 45733 | F16: USD | G16: -17.12 | H16: 17.12 | I16: -1490.17 | K16: 45763 | L16: 45838 | M16: - | N16: 45809 | O16: 51158497 | P16: 1 | Q16: 45820 | R16: 210 | S16: 1.55e+16 | T16: Ascendas Panvel FTWZ Private Limited | U16: 1490.17 | W16: =X16/I16 -> -0.019856795 | X16: =VLOOKUP(D16,'[3]Customer TDS'!D:I,6,0) -> 29.59 | Y16: =I16+X16 -> -1460.58 | Z16: Diff due to exchange gain/loss | AA16: =VLOOKUP(D16,'Ascendus DATA'!$F:$J,5,0) -> 1484.15 | AB16: =I16+AA16 -> -6.02
A17: A023951 | B17: A023951 | C17: I | D17: 246779411718 | E17: 45733 | F17: USD | G17: -22.95 | H17: 22.95 | I17: -1997.62 | K17: 45763 | L17: 45838 | M17: - | N17: 45809 | O17: 51158499 | P17: 1 | Q17: 45820 | R17: 210 | S17: 1.55e+16 | T17: Ascendas Panvel FTWZ Private Limited | U17: 1997.62 | W17: =X17/I17 -> -0.020043852 | X17: =VLOOKUP(D17,'[3]Customer TDS'!D:I,6,0) -> 40.04 | Y17: =I17+X17 -> -1957.58 | Z17: Diff due to exchange gain/loss | AA17: =VLOOKUP(D17,'Ascendus DATA'!$F:$J,5,0) -> 1989.56 | AB17: =I17+AA17 -> -8.06
A18: A023951 | B18: A023951 | C18: I | D18: 246779411637 | E18: 45733 | F18: USD | G18: -429.65 | H18: 429.65 | I18: -37397.77 | K18: 45763 | L18: 45838 | M18: - | N18: 45809 | O18: 51158500 | P18: 1 | Q18: 45820 | R18: 210 | S18: 1.55e+16 | T18: Ascendas Panvel FTWZ Private Limited | U18: 37397.77 | W18: =X18/I18 -> -0.019992903 | X18: =VLOOKUP(D18,'[3]Customer TDS'!D:I,6,0) -> 747.69 | Y18: =I18+X18 -> -36650.08 | Z18: Diff due to exchange gain/loss | AA18: =VLOOKUP(D18,'Ascendus DATA'!$F:$J,5,0) -> 37246.9 | AB18: =I18+AA18 -> -150.87
A19: A023951 | B19: A023951 | C19: I | D19: 246779411717 | E19: 45733 | F19: USD | G19: -45.67 | H19: 45.67 | I19: -3975.23 | K19: 45763 | L19: 45838 | M19: - | N19: 45809 | O19: 51158502 | P19: 1 | Q19: 45820 | R19: 210 | S19: 1.55e+16 | T19: Ascendas Panvel FTWZ Private Limited | U19: 3975.23 | W19: =X19/I19 -> -0.019925891 | X19: =VLOOKUP(D19,'[3]Customer TDS'!D:I,6,0) -> 79.21 | Y19: =I19+X19 -> -3896.02 | Z19: Diff due to exchange gain/loss | AA19: =VLOOKUP(D19,'Ascendus DATA'!$F:$J,5,0) -> 3959.19 | AB19: =I19+AA19 -> -16.04
... A23: A023951 | B23: A023951 | C23: I | D23: 246779411597 | E23: 45733 | F23: USD | G23: -57.29 | H23: 57.29 | I23: -4986.66 | K23: 45763 | L23: 45838 | M23: - | N23: 45809 | O23: 51158507 | P23: 1 | Q23: 45820 | R23: 210 | S23: 1.55e+16 | T23: Ascendas Panvel FTWZ Private Limited | U23: 4986.66 | W23: =X23/I23 -> -0.020073556 | X23: =VLOOKUP(D23,'[3]Customer TDS'!D:I,6,0) -> 100.1 | Y23: =I23+X23 -> -4886.56 | Z23: Diff due to exchange gain/loss | AA23: =VLOOKUP(D23,'Ascendus DATA'!$F:$J,5,0) -> 4966.54 | AB23: =I23+AA23 -> -20.12
A24: A023951 | B24: A023951 | C24: I | D24: 246779411739 | E24: 45733 | F24: USD | G24: -34.25 | H24: 34.25 | I24: -2981.2 | J24: NO EXCHANGE RATE | K24: 45763 | L24: 45838 | M24: - | N24: 45809 | O24: 51158508 | P24: 1 | Q24: 45820 | R24: 210 | S24: 1.55e+16 | T24: Ascendas Panvel FTWZ Private Limited | U24: 2981.2 | W24: =X24/I24 -> -0.02014625 | X24: =VLOOKUP(D24,'[3]Customer TDS'!D:I,6,0) -> 60.06 | Y24: =I24+X24 -> -2921.14 | Z24: Diff due to exchange gain/loss | AA24: =VLOOKUP(D24,'Ascendus DATA'!$F:$J,5,0) -> 2969.18 | AB24: =I24+AA24 -> -12.02
A25: A023951 | B25: A023951 | C25: I | D25: 246779411914 | E25: 45733 | F25: USD | G25: -260 | H25: 260 | I25: -22631.03 | K25: 45763 | L25: 45838 | M25: - | N25: 45809 | O25: 51158509 | P25: 1 | Q25: 45820 | R25: 210 | S25: 1.55e+16 | T25: Ascendas Panvel FTWZ Private Limited | U25: 22631.03 | W25: =X25/I25 -> -0.019999973 | X25: =VLOOKUP(D25,'[3]Customer TDS'!D:I,6,0) -> 452.62 | Y25: =I25+X25 -> -22178.41 | Z25: Diff due to exchange gain/loss | AA25: =VLOOKUP(D25,'Ascendus DATA'!$F:$J,5,0) -> 22539.73 | AB25: =I25+AA25 -> -91.3
A26: A023951 | B26: A023951 | C26: I | D26: 246779411596 | E26: 45733 | F26: USD | G26: -74.47 | H26: 74.47 | I26: -6482.05 | K26: 45763 | L26: 45838 | M26: - | N26: 45809 | O26: 51158510 | P26: 1 | Q26: 45820 | R26: 210 | S26: 1.55e+16 | T26: Ascendas Panvel FTWZ Private Limited | U26: 6482.05 | W26: =X26/I26 -> -0.020007559 | X26: =VLOOKUP(D26,'[3]Customer TDS'!D:I,6,0) -> 129.69 | Y26: =I26+X26 -> -6352.36 | Z26: Diff due to exchange gain/loss | AA26: =VLOOKUP(D26,'Ascendus DATA'!$F:$J,5,0) -> 6455.9 | AB26: =I26+AA26 -> -26.15
A27: A023951 | B27: A023951 | C27: I | D27: 246779411738 | E27: 45733 | F27: USD | G27: -28.54 | H27: 28.54 | I27: -2484.19 | K27: 45763 | L27: 45838 | M27: - | N27: 45809 | O27: 51158511 | P27: 1 | Q27: 45820 | R27: 210 | S27: 1.55e+16 | T27: Ascendas Panvel FTWZ Private Limited | U27: 2484.19 | W27: =X27/I27 -> -0.019970292 | X27: =VLOOKUP(D27,'[3]Customer TDS'!D:I,6,0) -> 49.61 | Y27: =I27+X27 -> -2434.58 | Z27: Diff due to exchange gain/loss | AA27: =VLOOKUP(D27,'Ascendus DATA'!$F:$J,5,0) -> 2474.17 | AB27: =I27+AA27 -> -10.02
A28: A023951 | B28: A023951 | C28: I | D28: 246779412040 | E28: 45733 | F28: USD | G28: -16.82 | H28: 16.82 | I28: -1464.05 | J28: NO EXCHANGE RATE / 14 DAYS OLDER | K28: 45763 | L28: 45838 | M28: - | N28: 45809 | O28: 51158513 | P28: 1 | Q28: 45820 | R28: 210 | S28: 1.55e+16 | T28: Ascendas Panvel FTWZ Private Limited | U28: 1464.05 | W28: =X28/I28 -> -0.020211058 | X28: =VLOOKUP(D28,'[3]Customer TDS'!D:I,6,0) -> 29.59 | Y28: =I28+X28 -> -1434.46 | Z28: Diff due to exchange gain/loss | AA28: =VLOOKUP(D28,'Ascendus DATA'!$F:$J,5,0) -> 1458.15 | AB28: =I28+AA28 -> -5.9
A29: A023951 | B29: A023951 | C29: I | D29: 246779411736 | E29: 45733 | F29: USD | G29: -22.83 | H29: 22.83 | I29: -1987.18 | K29: 45763 | L29: 45838 | M29: - | N29: 45809 | O29: 51158514 | P29: 1 | Q29: 45820 | R29: 210 | S29: 1.55e+16 | T29: Ascendas Panvel FTWZ Private Limited | U29: 1987.18 | W29: =X29/I29 -> -0.020149156 | X29: =VLOOKUP(D29,'[3]Customer TDS'!D:I,6,0) -> 40.04 | Y29: =I29+X29 -> -1947.14 | Z29: Diff due to exchange gain/loss | AA29: =VLOOKUP(D29,'Ascendus DATA'!$F:$J,5,0) -> 1979.16 | AB29: =I29+AA29 -> -8.02
A30: A023951 | B30: A023951 | C30: I | D30: 246779411899 | E30: 45733 | F30: USD | G30: -62.49 | H30: 62.49 | I30: -5439.28 | K30: 45763 | L30: 45838 | M30: - | N30: 45809 | O30: 51158516 | P30: 1 | Q30: 45820 | R30: 210 | S30: 1.55e+16 | T30: Ascendas Panvel FTWZ Private Limited | U30: 5439.28 | W30: =X30/I30 -> -0.020002647 | X30: =VLOOKUP(D30,'[3]Customer TDS'!D:I,6,0) -> 108.8 | Y30: =I30+X30 -> -5330.48 | Z30: Diff due to exchange gain/loss | AA30: =VLOOKUP(D30,'Ascendus DATA'!$F:$J,5,0) -> 5417.34 | AB30: =I30+AA30 -> -21.94
A31: A023951 | B31: A023951 | C31: I | D31: 246779411896 | E31: 45733 | F31: USD | G31: -39.77 | H31: 39.77 | I31: -3461.68 | K31: 45763 | L31: 45838 | M31: - | N31: 45809 | O31: 51158519 | P31: 1 | Q31: 45820 | R31: 210 | S31: 1.55e+16 | T31: Ascendas Panvel FTWZ Private Limited | U31: 3461.68 | W31: =X31/I31 -> -0.020114511 | X31: =VLOOKUP(D31,'[3]Customer TDS'!D:I,6,0) -> 69.63 | Y31: =I31+X31 -> -3392.05 | Z31: Diff due to exchange gain/loss | AA31: =VLOOKUP(D31,'Ascendus DATA'!$F:$J,5,0) -> 3447.71 | AB31: =I31+AA31 -> -13.97
A32: A023951 | B32: A023951 | C32: I | D32: 246779411902 | E32: 45733 | F32: USD | G32: -2.13 | H32: 2.13 | I32: -185.4 | K32: 45763 | L32: 45838 | M32: - | N32: 45809 | O32: 51158521 | P32: 1 | Q32: 45820 | R32: 210 | S32: 1.55e+16 | T32: Ascendas Panvel FTWZ Private Limited | U32: 185.4 | W32: =X32/I32 -> -0.018770227 | X32: =VLOOKUP(D32,'[3]Customer TDS'!D:I,6,0) -> 3.48 | Y32: =I32+X32 -> -181.92 | Z32: Diff due to exchange gain/loss | AA32: =VLOOKUP(D32,'Ascendus DATA'!$F:$J,5,0) -> 184.65 | AB32: =I32+AA32 -> -0.75
A33: A023951 | B33: A023951 | C33: I | D33: 246779411723 | E33: 45733 | F33: USD | G33: -45.67 | H33: 45.67 | I33: -3975.23 | J33: NO EXCHANGE RATE | K33: 45763 | L33: 45838 | M33: - | N33: 45809 | O33: 51158523 | P33: 1 | Q33: 45820 | R33: 210 | S33: 1.55e+16 | T33: Ascendas Panvel FTWZ Private Limited | U33: 3975.23 | W33: =X33/I33 -> -0.019925891 | X33: =VLOOKUP(D33,'[3]Customer TDS'!D:I,6,0) -> 79.21 | Y33: =I33+X33 -> -3896.02 | Z33: Diff due to exchange gain/loss | AA33: =VLOOKUP(D33,'Ascendus DATA'!$F:$J,5,0) -> 3959.19 | AB33: =I33+AA33 -> -16.04
A34: A023951 | B34: A023951 | C34: I | D34: 246779411722 | E34: 45733 | F34: USD | G34: -39.96 | H34: 39.96 | I34: -3478.21 | K34: 45763 | L34: 45838 | M34: - | N34: 45809 | O34: 51158526 | P34: 1 | Q34: 45820 | R34: 210 | S34: 1.55e+16 | T34: Ascendas Panvel FTWZ Private Limited | U34: 3478.21 | W34: =X34/I34 -> -0.020018918 | X34: =VLOOKUP(D34,'[3]Customer TDS'!D:I,6,0) -> 69.63 | Y34: =I34+X34 -> -3408.58 | Z34: Diff due to exchange gain/loss | AA34: =VLOOKUP(D34,'Ascendus DATA'!$F:$J,5,0) -> 3464.18 | AB34: =I34+AA34 -> -14.03
A35: A023951 | B35: A023951 | C35: I | D35: 246779411907 | E35: 45733 | F35: USD | G35: -17.04 | H35: 17.04 | I35: -1483.2 | K35: 45763 | L35: 45838 | M35: - | N35: 45809 | O35: 51158529 | P35: 1 | Q35: 45820 | R35: 210 | S35: 1.55e+16 | T35: Ascendas Panvel FTWZ Private Limited | U35: 1483.2 | W35: =X35/I35 -> -0.019950108 | X35: =VLOOKUP(D35,'[3]Customer TDS'!D:I,6,0) -> 29.59 | Y35: =I35+X35 -> -1453.61 | Z35: Diff due to exchange gain/loss | AA35: =VLOOKUP(D35,'Ascendus DATA'!$F:$J,5,0) -> 1477.22 | AB35: =I35+AA35 -> -5.98
A36: A023951 | B36: A023951 | C36: I | D36: 246779411909 | E36: 45733 | F36: USD | G36: -28.41 | H36: 28.41 | I36: -2472.88 | K36: 45763 | L36: 45838 | M36: - | N36: 45809 | O36: 51158531 | P36: 1 | Q36: 45820 | R36: 210 | S36: 1.55e+16 | T36: Ascendas Panvel FTWZ Private Limited | U36: 2472.88 | W36: =X36/I36 -> -0.020061629 | X36: =VLOOKUP(D36,'[3]Customer TDS'!D:I,6,0) -> 49.61 | Y36: =I36+X36 -> -2423.27 | Z36: Diff due to exchange gain/loss | AA36: =VLOOKUP(D36,'Ascendus DATA'!$F:$J,5,0) -> 2462.9 | AB36: =I36+AA36 -> -9.98
A37: A023951 | B37: A023951 | C37: I | D37: 246779411600 | E37: 45733 | F37: USD | G37: -2.6 | H37: 2.6 | I37: -226.31 | K37: 45763 | L37: 45838 | M37: - | N37: 45809 | O37: 51158533 | P37: 1 | Q37: 45820 | R37: 210 | S37: 1.55e+16 | T37: Ascendas Panvel FTWZ Private Limited | U37: 226.31 | W37: =X37/I37 -> -0.019221422 | X37: =VLOOKUP(D37,'[3]Customer TDS'!D:I,6,0) -> 4.35 | Y37: =I37+X37 -> -221.96 | Z37: Diff due to exchange gain/loss | AA37: =VLOOKUP(D37,'Ascendus DATA'!$F:$J,5,0) -> 225.4 | AB37: =I37+AA37 -> -0.91
A38: A023951 | B38: A023951 | C38: I | D38: 246779410436 | E38: 45719 | F38: USD | G38: -1332.41 | H38: 1332.41 | I38: -115976.18 | K38: 45749 | L38: 45838 | M38: - | N38: 45809 | O38: 51158534 | P38: 1 | Q38: 45820 | R38: 210 | S38: 1.55e+16 | T38: Ascendas Panvel FTWZ Private Limited | U38: 115976.18 | W38: =X38/I38 -> -0.020001349 | X38: =VLOOKUP(D38,'[3]Customer TDS'!D:I,6,0) -> 2319.68 | Y38: =I38+X38 -> -113656.5 | Z38: Diff due to exchange gain/loss | AA38: =VLOOKUP(D38,'Ascendus DATA'!$F:$J,5,0) -> 115508.3 | AB38: =I38+AA38 -> -467.88
A39: A023951 | B39: A023951 | C39: I | D39: 246779411595 | E39: 45733 | F39: USD | G39: -51.56 | H39: 51.56 | I39: -4487.91 | K39: 45763 | L39: 45838 | M39: - | N39: 45809 | O39: 51158535 | P39: 1 | Q39: 45820 | R39: 210 | S39: 1.55e+16 | T39: Ascendas Panvel FTWZ Private Limited | U39: 4487.91 | W39: =X39/I39 -> -0.019975891 | X39: =VLOOKUP(D39,'[3]Customer TDS'!D:I,6,0) -> 89.65 | Y39: =I39+X39 -> -4398.26 | Z39: Diff due to exchange gain/loss | AA39: =VLOOKUP(D39,'Ascendus DATA'!$F:$J,5,0) -> 4469.8 | AB39: =I39+AA39 -> -18.11
A40: A023951 | B40: A023951 | C40: I | D40: 246779414663 | E40: 45736 | F40: USD | G40: -45 | H40: 45 | I40: -3916.91 | K40: 45766 | L40: 45838 | M40: - | N40: 45809 | O40: 51158536 | P40: 1 | Q40: 45820 | R40: 210 | S40: 1.55e+16 | T40: Ascendas Panvel FTWZ Private Limited | U40: 3916.91 | W40: =X40/I40 -> -0.02000046 | X40: =VLOOKUP(D40,'[3]Customer TDS'!D:I,6,0) -> 78.34 | Y40: =I40+X40 -> -3838.57 | Z40: Diff due to exchange gain/loss | AA40: =VLOOKUP(D40,'Ascendus DATA'!$F:$J,5,0) -> 3901.11 | AB40: =I40+AA40 -> -15.8
A41: A023951 | B41: A023951 | C41: I | D41: 246779411594 | E41: 45733 | F41: USD | G41: -17.19 | H41: 17.19 | I41: -1496.26 | K41: 45763 | L41: 45838 | M41: - | N41: 45809 | O41: 51158537 | P41: 1 | Q41: 45820 | R41: 210 | S41: 1.55e+16 | T41: Ascendas Panvel FTWZ Private Limited | U41: 1496.26 | W41: =X41/I41 -> -0.019775975 | X41: =VLOOKUP(D41,'[3]Customer TDS'!D:I,6,0) -> 29.59 | Y41: =I41+X41 -> -1466.67 | Z41: Diff due to exchange gain/loss | AA41: =VLOOKUP(D41,'Ascendus DATA'!$F:$J,5,0) -> 1490.22 | AB41: =I41+AA41 -> -6.04
A42: A023951 | B42: A023951 | C42: I | D42: 246779410098 | E42: 45708 | F42: USD | G42: -2380.95 | H42: 2380.95 | I42: -206046.42 | K42: 45738 | L42: 45838 | M42: - | N42: 45809 | O42: 51158538 | P42: 1 | Q42: 45820 | R42: 210 | S42: 1.55e+16 | T42: Ascendas Panvel FTWZ Private Limited | U42: 206046.42 | W42: =X42/I42 -> -0.020000396 | X42: =VLOOKUP(D42,'[3]Customer TDS'!D:I,6,0) -> 4121.01 | Y42: =I42+X42 -> -201925.41 | Z42: Diff due to exchange gain/loss | AA42: =VLOOKUP(D42,'Ascendus DATA'!$F:$J,5,0) -> 205484.7 | AB42: =I42+AA42 -> -561.72
A43: A023951 | B43: A023951 | C43: I | D43: 246779411599 | E43: 45733 | F43: USD | G43: -37.95 | H43: 37.95 | I43: -3303.26 | K43: 45763 | L43: 45838 | M43: - | N43: 45809 | O43: 51158539 | P43: 1 | Q43: 45820 | R43: 210 | S43: 1.55e+16 | T43: Ascendas Panvel FTWZ Private Limited | U43: 3303.26 | W43: =X43/I43 -> -0.020025672 | X43: =VLOOKUP(D43,'[3]Customer TDS'!D:I,6,0) -> 66.15 | Y43: =I43+X43 -> -3237.11 | Z43: Diff due to exchange gain/loss | AA43: =VLOOKUP(D43,'Ascendus DATA'!$F:$J,5,0) -> 3289.93 | AB43: =I43+AA43 -> -13.33
A44: A023951 | B44: A023951 | C44: I | D44: 246779410132 | E44: 45708 | F44: USD | G44: -52.38 | H44: 52.38 | I44: -4532.94 | K44: 45738 | L44: 45838 | M44: - | N44: 45809 | O44: 51158540 | P44: 1 | Q44: 45820 | R44: 210 | S44: 1.55e+16 | T44: Ascendas Panvel FTWZ Private Limited | U44: 4532.94 | W44: =X44/I44 -> -0.020046592 | X44: =VLOOKUP(D44,'[3]Customer TDS'!D:I,6,0) -> 90.87 | Y44: =I44+X44 -> -4442.07 | Z44: Diff due to exchange gain/loss | AA44: =VLOOKUP(D44,'Ascendus DATA'!$F:$J,5,0) -> 4520.59 | AB44: =I44+AA44 -> -12.35
A45: A023951 | B45: A023951 | C45: I | D45: 246779410413 | E45: 45719 | F45: USD | G45: -694.12 | H45: 694.12 | I45: -60417.88 | K45: 45749 | L45: 45838 | M45: - | N45: 45809 | O45: 51158541 | P45: 1 | Q45: 45820 | R45: 210 | S45: 1.55e+16 | T45: Ascendas Panvel FTWZ Private Limited | U45: 60417.88 | W45: =X45/I45 -> -0.019996564 | X45: =VLOOKUP(D45,'[3]Customer TDS'!D:I,6,0) -> 1208.15 | Y45: =I45+X45 -> -59209.73 | Z45: Diff due to exchange gain/loss | AA45: =VLOOKUP(D45,'Ascendus DATA'!$F:$J,5,0) -> 60174.14 | AB45: =I45+AA45 -> -243.74
... A54: A023951 | B54: A023951 | C54: I | D54: 246779411915 | E54: 45733 | F54: USD | G54: -23.17 | H54: 23.17 | I54: -2016.77 | K54: 45763 | L54: 45838 | M54: - | N54: 45809 | O54: 51158550 | P54: 1 | Q54: 45820 | R54: 210 | S54: 1.55e+16 | T54: Ascendas Panvel FTWZ Private Limited | U54: 2016.77 | W54: =X54/I54 -> -0.019853528 | X54: =VLOOKUP(D54,'[3]Customer TDS'!D:I,6,0) -> 40.04 | Y54: =I54+X54 -> -1976.73 | Z54: Diff due to exchange gain/loss | AA54: =VLOOKUP(D54,'Ascendus DATA'!$F:$J,5,0) -> 2008.64 | AB54: =I54+AA54 -> -8.13
A55: A023951 | B55: A023951 | C55: I | D55: 246779412041 | E55: 45733 | F55: USD | G55: -33.64 | H55: 33.64 | I55: -2928.11 | J55: NO EXCHANGE RATE / 14 DAYS OLDER | K55: 45763 | L55: 45838 | M55: - | N55: 45809 | O55: 51158551 | P55: 1 | Q55: 45820 | R55: 210 | S55: 1.55e+16 | T55: Ascendas Panvel FTWZ Private Limited | U55: 2928.11 | W55: =X55/I55 -> -0.019917285 | X55: =VLOOKUP(D55,'[3]Customer TDS'!D:I,6,0) -> 58.32 | Y55: =I55+X55 -> -2869.79 | Z55: Diff due to exchange gain/loss | AA55: =VLOOKUP(D55,'Ascendus DATA'!$F:$J,5,0) -> 2916.29 | AB55: =I55+AA55 -> -11.82
A56: A023951 | B56: A023951 | C56: I | D56: 246779411900 | E56: 45733 | F56: USD | G56: -73.85 | H56: 73.85 | I56: -6428.08 | K56: 45763 | L56: 45838 | M56: - | N56: 45809 | O56: 51158552 | P56: 1 | Q56: 45820 | R56: 210 | S56: 1.55e+16 | T56: Ascendas Panvel FTWZ Private Limited | U56: 6428.08 | W56: =X56/I56 -> -0.020040199 | X56: =VLOOKUP(D56,'[3]Customer TDS'!D:I,6,0) -> 128.82 | Y56: =I56+X56 -> -6299.26 | Z56: Diff due to exchange gain/loss | AA56: =VLOOKUP(D56,'Ascendus DATA'!$F:$J,5,0) -> 6402.15 | AB56: =I56+AA56 -> -25.93
A57: A023951 | B57: A023951 | C57: I | D57: 246779412048 | E57: 45733 | F57: USD | G57: -22.78 | H57: 22.78 | I57: -1982.83 | K57: 45763 | L57: 45838 | M57: - | N57: 45809 | O57: 51158554 | P57: 1 | Q57: 45820 | R57: 210 | S57: 1.55e+16 | T57: Ascendas Panvel FTWZ Private Limited | U57: 1982.83 | W57: =X57/I57 -> -0.02019336 | X57: =VLOOKUP(D57,'[3]Customer TDS'!D:I,6,0) -> 40.04 | Y57: =I57+X57 -> -1942.79 | Z57: Diff due to exchange gain/loss | AA57: =VLOOKUP(D57,'Ascendus DATA'!$F:$J,5,0) -> 1974.83 | AB57: =I57+AA57 -> -8
A58: A023951 | B58: A023951 | C58: I | D58: 246779411903 | E58: 45733 | F58: USD | G58: -3.55 | H58: 3.55 | I58: -309 | K58: 45763 | L58: 45838 | M58: - | N58: 45809 | O58: 51158555 | P58: 1 | Q58: 45820 | R58: 210 | S58: 1.55e+16 | T58: Ascendas Panvel FTWZ Private Limited | U58: 309 | W58: =X58/I58 -> -0.019708738 | X58: =VLOOKUP(D58,'[3]Customer TDS'!D:I,6,0) -> 6.09 | Y58: =I58+X58 -> -302.91 | Z58: Diff due to exchange gain/loss | AA58: =VLOOKUP(D58,'Ascendus DATA'!$F:$J,5,0) -> 307.75 | AB58: =I58+AA58 -> -1.25
A59: A023951 | B59: A023951 | C59: I | D59: 246779411910 | E59: 45733 | F59: USD | G59: -28.41 | H59: 28.41 | I59: -2472.88 | K59: 45763 | L59: 45838 | M59: - | N59: 45809 | O59: 51158556 | P59: 1 | Q59: 45820 | R59: 210 | S59: 1.55e+16 | T59: Ascendas Panvel FTWZ Private Limited | U59: 2472.88 | W59: =X59/I59 -> -0.020061629 | X59: =VLOOKUP(D59,'[3]Customer TDS'!D:I,6,0) -> 49.61 | Y59: =I59+X59 -> -2423.27 | Z59: Diff due to exchange gain/loss | AA59: =VLOOKUP(D59,'Ascendus DATA'!$F:$J,5,0) -> 2462.9 | AB59: =I59+AA59 -> -9.98
A60: A023951 | B60: A023951 | C60: I | D60: 246779411598 | E60: 45733 | F60: USD | G60: -91.66 | H60: 91.66 | I60: -7978.31 | K60: 45763 | L60: 45838 | M60: - | N60: 45809 | O60: 51158557 | P60: 1 | Q60: 45820 | R60: 210 | S60: 1.55e+16 | T60: Ascendas Panvel FTWZ Private Limited | U60: 7978.31 | W60: =X60/I60 -> -0.019965381 | X60: =VLOOKUP(D60,'[3]Customer TDS'!D:I,6,0) -> 159.29 | Y60: =I60+X60 -> -7819.02 | Z60: Diff due to exchange gain/loss | AA60: =VLOOKUP(D60,'Ascendus DATA'!$F:$J,5,0) -> 7946.12 | AB60: =I60+AA60 -> -32.19
A61: A023951 | B61: A023951 | C61: I | D61: 246779411593 | E61: 45733 | F61: USD | G61: -40.1 | H61: 40.1 | I61: -3490.4 | K61: 45763 | L61: 45838 | M61: - | N61: 45809 | O61: 51158558 | P61: 1 | Q61: 45820 | R61: 210 | S61: 1.55e+16 | T61: Ascendas Panvel FTWZ Private Limited | U61: 3490.4 | W61: =X61/I61 -> -0.019949003 | X61: =VLOOKUP(D61,'[3]Customer TDS'!D:I,6,0) -> 69.63 | Y61: =I61+X61 -> -3420.77 | Z61: Diff due to exchange gain/loss | AA61: =VLOOKUP(D61,'Ascendus DATA'!$F:$J,5,0) -> 3476.32 | AB61: =I61+AA61 -> -14.08
A62: A023951 | B62: A023951 | C62: I | D62: 246779412045 | E62: 45733 | F62: USD | G62: -230 | H62: 230 | I62: -20019.76 | J62: NO EXCHANGE RATE / 14 DAYS OLDER | K62: 45763 | L62: 45838 | M62: - | N62: 45809 | O62: 51158560 | P62: 1 | Q62: 45820 | R62: 210 | S62: 1.55e+16 | T62: Ascendas Panvel FTWZ Private Limited | U62: 20019.76 | W62: =X62/I62 -> -0.02000024 | X62: =VLOOKUP(D62,'[3]Customer TDS'!D:I,6,0) -> 400.4 | Y62: =I62+X62 -> -19619.36 | Z62: Diff due to exchange gain/loss | AA62: =VLOOKUP(D62,'Ascendus DATA'!$F:$J,5,0) -> 19938.99 | AB62: =I62+AA62 -> -80.77
A63: A023951 | B63: A023951 | C63: I | D63: 246779412042 | E63: 45733 | F63: USD | G63: -16.82 | H63: 16.82 | I63: -1464.05 | J63: NO EXCHANGE RATE / 14 DAYS OLDER | K63: 45763 | L63: 45838 | M63: - | N63: 45809 | O63: 51158561 | P63: 1 | Q63: 45820 | R63: 210 | S63: 1.55e+16 | T63: Ascendas Panvel FTWZ Private Limited | U63: 1464.05 | W63: =X63/I63 -> -0.020211058 | X63: =VLOOKUP(D63,'[3]Customer TDS'!D:I,6,0) -> 29.59 | Y63: =I63+X63 -> -1434.46 | Z63: Diff due to exchange gain/loss | AA63: =VLOOKUP(D63,'Ascendus DATA'!$F:$J,5,0) -> 1458.15 | AB63: =I63+AA63 -> -5.9
A64: A023951 | B64: A023951 | C64: I | D64: 246779412038 | E64: 45733 | F64: USD | G64: -33.64 | H64: 33.64 | I64: -2928.11 | J64: NO EXCHANGE RATE / 14 DAYS OLDER | K64: 45763 | L64: 45838 | M64: - | N64: 45809 | O64: 51158562 | P64: 1 | Q64: 45820 | R64: 210 | S64: 1.55e+16 | T64: Ascendas Panvel FTWZ Private Limited | U64: 2928.11 | W64: =X64/I64 -> -0.019917285 | X64: =VLOOKUP(D64,'[3]Customer TDS'!D:I,6,0) -> 58.32 | Y64: =I64+X64 -> -2869.79 | Z64: Diff due to exchange gain/loss | AA64: =VLOOKUP(D64,'Ascendus DATA'!$F:$J,5,0) -> 2916.29 | AB64: =I64+AA64 -> -11.82
A65: A023951 | B65: A023951 | C65: I | D65: 246779410312 | E65: 45708 | F65: USD | G65: -52.38 | H65: 52.38 | I65: -4559.28 | K65: 45738 | L65: 45838 | M65: - | N65: 45809 | O65: 51160045 | P65: 1 | Q65: 45820 | R65: 210 | S65: 1.55e+16 | T65: Ascendas Panvel FTWZ Private Limited | U65: 4559.28 | W65: =X65/I65 -> -0.020044832 | X65: =VLOOKUP(D65,'[3]Customer TDS'!D:I,6,0) -> 91.39 | Y65: =I65+X65 -> -4467.89 | Z65: Diff due to exchange gain/loss | AA65: =VLOOKUP(D65,'Ascendus DATA'!$F:$J,5,0) -> 4520.59 | AB65: =I65+AA65 -> -38.69
A66: A023951 | B66: A023951 | C66: I | D66: 246779411901 | E66: 45733 | F66: USD | G66: -12.78 | H66: 12.78 | I66: -1112.4 | K66: 45763 | L66: 45838 | M66: - | N66: 45809 | O66: 51160046 | P66: 1 | Q66: 45820 | R66: 210 | S66: 1.55e+16 | T66: Ascendas Panvel FTWZ Private Limited | U66: 1112.4 | W66: =X66/I66 -> -0.020343402 | X66: =VLOOKUP(D66,'[3]Customer TDS'!D:I,6,0) -> 22.63 | Y66: =I66+X66 -> -1089.77 | Z66: Diff due to exchange gain/loss | AA66: =VLOOKUP(D66,'Ascendus DATA'!$F:$J,5,0) -> 1107.91 | AB66: =I66+AA66 -> -4.49
A67: A023951 | B67: A023951 | C67: I | D67: 246779411906 | E67: 45733 | F67: USD | G67: -34.09 | H67: 34.09 | I67: -2967.28 | K67: 45763 | L67: 45838 | M67: - | N67: 45809 | O67: 51160048 | P67: 1 | Q67: 45820 | R67: 210 | S67: 1.55e+16 | T67: Ascendas Panvel FTWZ Private Limited | U67: 2967.28 | W67: =X67/I67 -> -0.019947561 | X67: =VLOOKUP(D67,'[3]Customer TDS'!D:I,6,0) -> 59.19 | Y67: =I67+X67 -> -2908.09 | Z67: Diff due to exchange gain/loss | AA67: =VLOOKUP(D67,'Ascendus DATA'!$F:$J,5,0) -> 2955.31 | AB67: =I67+AA67 -> -11.97
A68: A023951 | B68: A023951 | C68: I | D68: 246779411911 | E68: 45733 | F68: USD | G68: -29.83 | H68: 29.83 | I68: -2596.48 | K68: 45763 | L68: 45838 | M68: - | N68: 45809 | O68: 51160049 | P68: 1 | Q68: 45820 | R68: 210 | S68: 1.55e+16 | T68: Ascendas Panvel FTWZ Private Limited | U68: 2596.48 | W68: =X68/I68 -> -0.020115695 | X68: =VLOOKUP(D68,'[3]Customer TDS'!D:I,6,0) -> 52.23 | Y68: =I68+X68 -> -2544.25 | Z68: Diff due to exchange gain/loss | AA68: =VLOOKUP(D68,'Ascendus DATA'!$F:$J,5,0) -> 2586 | AB68: =I68+AA68 -> -10.48
A69: A023951 | B69: A023951 | C69: I | D69: 246779411731 | E69: 45733 | F69: USD | G69: -22.83 | H69: 22.83 | I69: -1987.18 | K69: 45763 | L69: 45838 | M69: - | N69: 45809 | O69: 51160057 | P69: 1 | Q69: 45820 | R69: 210 | S69: 1.55e+16 | T69: Ascendas Panvel FTWZ Private Limited | U69: 1987.18 | W69: =X69/I69 -> -0.020149156 | X69: =VLOOKUP(D69,'[3]Customer TDS'!D:I,6,0) -> 40.04 | Y69: =I69+X69 -> -1947.14 | Z69: Diff due to exchange gain/loss | AA69: =VLOOKUP(D69,'Ascendus DATA'!$F:$J,5,0) -> 1979.16 | AB69: =I69+AA69 -> -8.02
A70: A023951 | B70: A023951 | C70: I | D70: 246779414662 | E70: 45736 | F70: USD | G70: -275 | H70: 275 | I70: -23936.66 | K70: 45766 | L70: 45838 | M70: - | N70: 45809 | O70: 51160060 | P70: 1 | Q70: 45820 | R70: 210 | S70: 1.55e+16 | T70: Ascendas Panvel FTWZ Private Limited | U70: 23936.66 | W70: =X70/I70 -> -0.019999866 | X70: =VLOOKUP(D70,'[3]Customer TDS'!D:I,6,0) -> 478.73 | Y70: =I70+X70 -> -23457.93 | Z70: Diff due to exchange gain/loss | AA70: =VLOOKUP(D70,'Ascendus DATA'!$F:$J,5,0) -> 23840.1 | AB70: =I70+AA70 -> -96.56
A71: A023951 | B71: A023951 | C71: I | D71: 246779411725 | E71: 45733 | F71: USD | G71: -22.83 | H71: 22.83 | I71: -1987.18 | K71: 45763 | L71: 45838 | M71: - | N71: 45809 | O71: 51160062 | P71: 1 | Q71: 45820 | R71: 210 | S71: 1.55e+16 | T71: Ascendas Panvel FTWZ Private Limited | U71: 1987.18 | W71: =X71/I71 -> -0.020149156 | X71: =VLOOKUP(D71,'[3]Customer TDS'!D:I,6,0) -> 40.04 | Y71: =I71+X71 -> -1947.14 | Z71: Diff due to exchange gain/loss | AA71: =VLOOKUP(D71,'Ascendus DATA'!$F:$J,5,0) -> 1979.16 | AB71: =I71+AA71 -> -8.02
A72: A023951 | B72: A023951 | C72: I | D72: 246779411905 | E72: 45733 | F72: USD | G72: -7.1 | H72: 7.1 | I72: -618 | K72: 45763 | L72: 45838 | M72: - | N72: 45809 | O72: 51160065 | P72: 1 | Q72: 45820 | R72: 210 | S72: 1.55e+16 | T72: Ascendas Panvel FTWZ Private Limited | U72: 618 | W72: =X72/I72 -> -0.019724919 | X72: =VLOOKUP(D72,'[3]Customer TDS'!D:I,6,0) -> 12.19 | Y72: =I72+X72 -> -605.81 | Z72: Diff due to exchange gain/loss | AA72: =VLOOKUP(D72,'Ascendus DATA'!$F:$J,5,0) -> 615.51 | AB72: =I72+AA72 -> -2.49
A73: A023951 | B73: A023951 | C73: I | D73: 246779411719 | E73: 45733 | F73: USD | G73: -28.54 | H73: 28.54 | I73: -2484.19 | K73: 45763 | L73: 45838 | M73: - | N73: 45809 | O73: 51160075 | P73: 1 | Q73: 45820 | R73: 210 | S73: 1.55e+16 | T73: Ascendas Panvel FTWZ Private Limited | U73: 2484.19 | W73: =X73/I73 -> -0.019970292 | X73: =VLOOKUP(D73,'[3]Customer TDS'!D:I,6,0) -> 49.61 | Y73: =I73+X73 -> -2434.58 | Z73: Diff due to exchange gain/loss | AA73: =VLOOKUP(D73,'Ascendus DATA'!$F:$J,5,0) -> 2474.17 | AB73: =I73+AA73 -> -10.02
A74: A023951 | B74: A023951 | C74: I | D74: 246779411312 | E74: 45729 | F74: USD | G74: -27 | H74: 27 | I74: -2350.15 | K74: 45759 | L74: 45838 | M74: - | N74: 45809 | O74: 51160078 | P74: 1 | Q74: 45820 | R74: 210 | S74: 1.55e+16 | T74: Ascendas Panvel FTWZ Private Limited | U74: 2350.15 | W74: =X74/I74 -> -0.019998723 | X74: =VLOOKUP(D74,'[3]Customer TDS'!D:I,6,0) -> 47 | Y74: =I74+X74 -> -2303.15 | Z74: Diff due to exchange gain/loss | AA74: =VLOOKUP(D74,'Ascendus DATA'!$F:$J,5,0) -> 2340.66 | AB74: =I74+AA74 -> -9.49
A75: A023951 | B75: A023951 | C75: I | D75: 246779414385 | E75: 45736 | F75: USD | G75: -240 | H75: 240 | I75: -20890.18 | K75: 45766 | L75: 45838 | M75: - | N75: 45809 | O75: 51162142 | P75: 1 | Q75: 45820 | R75: 210 | S75: 1.55e+16 | T75: Ascendas Panvel FTWZ Private Limited | U75: 20890.18 | W75: =X75/I75 -> -0.019999828 | X75: =VLOOKUP(D75,'[3]Customer TDS'!D:I,6,0) -> 417.8 | Y75: =I75+X75 -> -20472.38 | Z75: Diff due to exchange gain/loss | AA75: =VLOOKUP(D75,'Ascendus DATA'!$F:$J,5,0) -> 20805.9 | AB75: =I75+AA75 -> -84.28
A76: A023951 | B76: A023951 | C76: I | D76: 246779411728 | E76: 45733 | F76: USD | G76: -11.42 | H76: 11.42 | I76: -994.02 | K76: 45763 | L76: 45838 | M76: - | N76: 45809 | O76: 51162161 | P76: 1 | Q76: 45820 | R76: 210 | S76: 1.55e+16 | T76: Ascendas Panvel FTWZ Private Limited | U76: 994.02 | W76: =X76/I76 -> -0.02014044 | X76: =VLOOKUP(D76,'[3]Customer TDS'!D:I,6,0) -> 20.02 | Y76: =I76+X76 -> -974 | Z76: Diff due to exchange gain/loss | AA76: =VLOOKUP(D76,'Ascendus DATA'!$F:$J,5,0) -> 990.01 | AB76: =I76+AA76 -> -4.01
... A91: A023951 | B91: A023951 | C91: I | D91: 246779411417 | E91: 45730 | F91: USD | G91: -68.68 | H91: 68.68 | I91: -5978.07 | K91: 45760 | L91: 45838 | M91: - | N91: 45809 | O91: 51171830 | P91: 1 | Q91: 45820 | R91: 210 | S91: 1.55e+16 | T91: Ascendas Panvel FTWZ Private Limited | U91: 5978.07 | W91: =X91/I91 -> -0.01994791 | X91: =VLOOKUP(D91,'[3]Customer TDS'!D:I,6,0) -> 119.25 | Y91: =I91+X91 -> -5858.82 | Z91: Diff due to exchange gain/loss | AA91: =VLOOKUP(D91,'Ascendus DATA'!$F:$J,5,0) -> 5953.96 | AB91: =I91+AA91 -> -24.11
A92: A023951 | B92: A023951 | C92: I | D92: 246779410217 | E92: 45708 | F92: USD | G92: -93.33 | H92: 93.33 | I92: -8076.74 | J92: NO EXCHANGE RATE | K92: 45738 | L92: 45838 | M92: - | N92: 45809 | O92: 51171835 | P92: 1 | Q92: 45820 | R92: 210 | S92: 1.55e+16 | T92: Ascendas Panvel FTWZ Private Limited | U92: 8076.74 | W92: =X92/I92 -> -0.020036549 | X92: =VLOOKUP(D92,'[3]Customer TDS'!D:I,6,0) -> 161.83 | Y92: =I92+X92 -> -7914.91 | Z92: Diff due to exchange gain/loss | AA92: =VLOOKUP(D92,'Ascendus DATA'!$F:$J,5,0) -> 8054.72 | AB92: =I92+AA92 -> -22.02
A93: A023951 | B93: A023951 | C93: I | D93: 246779410218 | E93: 45708 | F93: USD | G93: -51.33 | H93: 51.33 | I93: -4442.08 | K93: 45738 | L93: 45838 | M93: - | N93: 45809 | O93: 51171840 | P93: 1 | Q93: 45820 | R93: 210 | S93: 1.55e+16 | T93: Ascendas Panvel FTWZ Private Limited | U93: 4442.08 | W93: =X93/I93 -> -0.020067176 | X93: =VLOOKUP(D93,'[3]Customer TDS'!D:I,6,0) -> 89.14 | Y93: =I93+X93 -> -4352.94 | Z93: Diff due to exchange gain/loss | AA93: =VLOOKUP(D93,'Ascendus DATA'!$F:$J,5,0) -> 4429.97 | AB93: =I93+AA93 -> -12.11
A94: A023951 | B94: A023951 | C94: I | D94: 256779410818 | E94: 45751 | F94: INR | G94: - | H94: - | I94: -1231.96 | J94: NO EXCHANGE RATE | K94: 45781 | L94: 45961 | M94: - | N94: 45809 | O94: 51171847 | P94: 1 | Q94: 45820 | R94: 210 | S94: 1.55e+16 | T94: Ascendas Panvel FTWZ Private Limited | U94: 457.29 | W94: =X94/I94 -> -0.020292867 | X94: =VLOOKUP(D94,'[3]Customer TDS'!D:I,6,0) -> 25 | Y94: =I94+X94 -> -1206.96 | Z94: Amount recorded by customer but not in our books | AA94: =VLOOKUP(D94,'Ascendus DATA'!$F:$J,5,0) -> #N/A
A95: A023951 | B95: A023951 | C95: I | D95: 246779411419 | E95: 45730 | F95: USD | G95: -23.35 | H95: 23.35 | I95: -2032.44 | K95: 45760 | L95: 45838 | M95: - | N95: 45809 | O95: 51171848 | P95: 1 | Q95: 45820 | R95: 210 | S95: 1.55e+16 | T95: Ascendas Panvel FTWZ Private Limited | U95: 2032.44 | W95: =X95/I95 -> -0.020128515 | X95: =VLOOKUP(D95,'[3]Customer TDS'!D:I,6,0) -> 40.91 | Y95: =I95+X95 -> -1991.53 | Z95: Diff due to exchange gain/loss | AA95: =VLOOKUP(D95,'Ascendus DATA'!$F:$J,5,0) -> 2024.24 | AB95: =I95+AA95 -> -8.2
A96: A023951 | B96: A023951 | C96: I | D96: 246779413202 | E96: 45735 | F96: USD | G96: -39.06 | H96: 39.06 | I96: -3380.24 | K96: 45765 | L96: 45838 | M96: - | N96: 45809 | O96: 51171856 | P96: 1 | Q96: 45820 | R96: 210 | S96: 1.55e+16 | T96: Ascendas Panvel FTWZ Private Limited | U96: 3380.24 | W96: =X96/I96 -> -0.019968996 | X96: =VLOOKUP(D96,'[3]Customer TDS'!D:I,6,0) -> 67.5 | Y96: =I96+X96 -> -3312.74 | Z96: Diff due to exchange gain/loss | AA96: =VLOOKUP(D96,'Ascendus DATA'!$F:$J,5,0) -> 3386.16 | AB96: =I96+AA96 -> 5.92
A97: A023951 | B97: A023951 | C97: I | D97: 256779410262 | E97: 45750 | F97: INR | G97: - | H97: - | I97: -93.33 | J97: NO EXCHANGE RATE | K97: 45780 | L97: 45939 | M97: - | N97: 45809 | O97: 51171858 | P97: 1 | Q97: 45820 | R97: 210 | S97: 1.55e+16 | T97: Ascendas Panvel FTWZ Private Limited | U97: 2 | W97: =X97/I97 -> -0.021429337 | X97: =VLOOKUP(D97,'[3]Customer TDS'!D:I,6,0) -> 2 | Y97: =I97+X97 -> -91.33 | Z97: Customer recorded USD amount in INR amount. Customer needs to correct | AA97: =VLOOKUP(D97,'Ascendus DATA'!$F:$J,5,0) -> 8112.41 | AB97: =I97+AA97 -> 8019.08
A98: A023951 | B98: A023951 | C98: I | D98: 246779412037 | E98: 45733 | F98: USD | G98: -44.85 | H98: 44.85 | I98: -3903.85 | J98: NO EXCHANGE RATE / 14 DAYS OLDER | K98: 45763 | L98: 45838 | M98: - | N98: 45809 | O98: 51171868 | P98: 1 | Q98: 45820 | R98: 210 | S98: 1.55e+16 | T98: Ascendas Panvel FTWZ Private Limited | U98: 3903.85 | W98: =X98/I98 -> -0.020067369 | X98: =VLOOKUP(D98,'[3]Customer TDS'!D:I,6,0) -> 78.34 | Y98: =I98+X98 -> -3825.51 | Z98: Diff due to exchange gain/loss | AA98: =VLOOKUP(D98,'Ascendus DATA'!$F:$J,5,0) -> 3888.1 | AB98: =I98+AA98 -> -15.75
A99: A023951 | B99: A023951 | C99: I | D99: 246779412032 | E99: 45733 | F99: USD | G99: -33.64 | H99: 33.64 | I99: -2928.11 | K99: 45763 | L99: 45838 | M99: - | N99: 45809 | O99: 51171871 | P99: 1 | Q99: 45820 | R99: 210 | S99: 1.55e+16 | T99: Ascendas Panvel FTWZ Private Limited | U99: 2928.11 | W99: =X99/I99 -> -0.019917285 | X99: =VLOOKUP(D99,'[3]Customer TDS'!D:I,6,0) -> 58.32 | Y99: =I99+X99 -> -2869.79 | Z99: Diff due to exchange gain/loss | AA99: =VLOOKUP(D99,'Ascendus DATA'!$F:$J,5,0) -> 2916.29 | AB99: =I99+AA99 -> -11.82
A100: A023951 | B100: A023951 | C100: I | D100: 246779412030 | E100: 45733 | F100: USD | G100: -16.82 | H100: 16.82 | I100: -1464.05 | K100: 45763 | L100: 45838 | M100: - | N100: 45809 | O100: 51171874 | P100: 1 | Q100: 45820 | R100: 210 | S100: 1.55e+16 | T100: Ascendas Panvel FTWZ Private Limited | U100: 1464.05 | W100: =X100/I100 -> -0.020211058 | X100: =VLOOKUP(D100,'[3]Customer TDS'!D:I,6,0) -> 29.59 | Y100: =I100+X100 -> -1434.46 | Z100: Diff due to exchange gain/loss | AA100: =VLOOKUP(D100,'Ascendus DATA'!$F:$J,5,0) -> 1458.15 | AB100: =I100+AA100 -> -5.9
A101: A023951 | B101: A023951 | C101: I | D101: 246779410904 | E101: 45722 | F101: USD | G101: -1665.82 | H101: 1665.82 | I101: -144997 | K101: 45752 | L101: 45838 | M101: - | N101: 45809 | O101: 51171876 | P101: 1 | Q101: 45820 | R101: 210 | S101: 1.55e+16 | T101: Ascendas Panvel FTWZ Private Limited | U101: 144997 | W101: =X101/I101 -> -0.020002138 | X101: =VLOOKUP(D101,'[3]Customer TDS'!D:I,6,0) -> 2900.25 | Y101: =I101+X101 -> -142096.75 | Z101: Diff due to exchange gain/loss | AA101: =VLOOKUP(D101,'Ascendus DATA'!$F:$J,5,0) -> 144412.03 | AB101: =I101+AA101 -> -584.97
A102: A023951 | B102: A023951 | C102: I | D102: 246779410174 | E102: 45708 | F102: USD | G102: -95.24 | H102: 95.24 | I102: -8242.03 | K102: 45738 | L102: 45838 | M102: - | N102: 45809 | O102: 51171884 | P102: 1 | Q102: 45820 | R102: 210 | S102: 1.55e+16 | T102: Ascendas Panvel FTWZ Private Limited | U102: 8242.03 | W102: =X102/I102 -> -0.019950182 | X102: =VLOOKUP(D102,'[3]Customer TDS'!D:I,6,0) -> 164.43 | Y102: =I102+X102 -> -8077.6 | Z102: Diff due to exchange gain/loss | AA102: =VLOOKUP(D102,'Ascendus DATA'!$F:$J,5,0) -> 8219.56 | AB102: =I102+AA102 -> -22.47
A103: A023951 | B103: A023951 | C103: I | D103: 256779411468 | E103: 45762 | F103: USD | G103: -26.55 | H103: 26.55 | I103: -2276.05 | K103: 45792 | L103: 45838 | M103: - | N103: 45809 | O103: 51171893 | P103: 1 | Q103: 45820 | R103: 210 | S103: 1.55e+16 | T103: Ascendas Panvel FTWZ Private Limited | U103: 2276.05 | W103: =X103/I103 -> -0.019964412 | X103: =VLOOKUP(D103,'[3]Customer TDS'!D:I,6,0) -> 45.44 | Y103: =I103+X103 -> -2230.61 | Z103: Diff due to exchange gain/loss | AA103: =VLOOKUP(D103,'Ascendus DATA'!$F:$J,5,0) -> 2307.77 | AB103: =I103+AA103 -> 31.72
A104: A023951 | B104: A023951 | C104: I | D104: 246779410389 | E104: 45719 | F104: USD | G104: -542.08 | H104: 542.08 | I104: -47183.95 | J104: NO EXCHANGE RATE | K104: 45749 | L104: 45838 | M104: - | N104: 45809 | O104: 51171905 | P104: 1 | Q104: 45820 | R104: 210 | S104: 1.55e+16 | T104: Ascendas Panvel FTWZ Private Limited | U104: 47183.95 | W104: =X104/I104 -> -0.019997054 | X104: =VLOOKUP(D104,'[3]Customer TDS'!D:I,6,0) -> 943.54 | Y104: =I104+X104 -> -46240.41 | Z104: Diff due to exchange gain/loss | AA104: =VLOOKUP(D104,'Ascendus DATA'!$F:$J,5,0) -> 46993.6 | AB104: =I104+AA104 -> -190.35
A105: A023951 | B105: A023951 | C105: I | D105: 246779411409 | E105: 45730 | F105: USD | G105: -249.55 | H105: 249.55 | I105: -21721.43 | J105: NO EXCHANGE RATE | K105: 45760 | L105: 45838 | M105: - | N105: 45809 | O105: 51171913 | P105: 1 | Q105: 45820 | R105: 210 | S105: 1.55e+16 | T105: Ascendas Panvel FTWZ Private Limited | U105: 21721.43 | W105: =X105/I105 -> -0.039991842 | X105: 868.68 | Y105: =I105+X105 -> -20852.75 | Z105: Diff due to exchange gain/loss | AA105: =VLOOKUP(D105,'Ascendus DATA'!$F:$J,5,0) -> 21633.8 | AB105: =I105+AA105 -> -87.63
A106: A023951 | B106: A023951 | C106: I | D106: 246779411408 | E106: 45730 | F106: USD | G106: -40.06 | H106: 40.06 | I106: -3486.92 | K106: 45760 | L106: 45838 | M106: - | N106: 45809 | O106: 51171919 | P106: 1 | Q106: 45820 | R106: 210 | S106: 1.55e+16 | T106: Ascendas Panvel FTWZ Private Limited | U106: 3486.92 | W106: =X106/I106 -> -0.019968912 | X106: =VLOOKUP(D106,'[3]Customer TDS'!D:I,6,0) -> 69.63 | Y106: =I106+X106 -> -3417.29 | Z106: Diff due to exchange gain/loss | AA106: =VLOOKUP(D106,'Ascendus DATA'!$F:$J,5,0) -> 3472.85 | AB106: =I106+AA106 -> -14.07
A107: A023951 | B107: A023951 | C107: I | D107: 246779411411 | E107: 45730 | F107: USD | G107: -45.79 | H107: 45.79 | I107: -3985.67 | K107: 45760 | L107: 45838 | M107: - | N107: 45809 | O107: 51171925 | P107: 1 | Q107: 45820 | R107: 210 | S107: 1.55e+16 | T107: Ascendas Panvel FTWZ Private Limited | U107: 3985.67 | W107: =X107/I107 -> -0.02009198 | X107: =VLOOKUP(D107,'[3]Customer TDS'!D:I,6,0) -> 80.08 | Y107: =I107+X107 -> -3905.59 | Z107: Diff due to exchange gain/loss | AA107: =VLOOKUP(D107,'Ascendus DATA'!$F:$J,5,0) -> 3969.59 | AB107: =I107+AA107 -> -16.08
A108: A023951 | B108: A023951 | C108: I | D108: 246779411412 | E108: 45730 | F108: USD | G108: -20.03 | H108: 20.03 | I108: -1743.46 | K108: 45760 | L108: 45838 | M108: - | N108: 45809 | O108: 51171929 | P108: 1 | Q108: 45820 | R108: 210 | S108: 1.55e+16 | T108: Ascendas Panvel FTWZ Private Limited | U108: 1743.46 | W108: =X108/I108 -> -0.01997178 | X108: =VLOOKUP(D108,'[3]Customer TDS'!D:I,6,0) -> 34.82 | Y108: =I108+X108 -> -1708.64 | Z108: Diff due to exchange gain/loss | AA108: =VLOOKUP(D108,'Ascendus DATA'!$F:$J,5,0) -> 1736.43 | AB108: =I108+AA108 -> -7.03
A109: A023951 | B109: A023951 | C109: I | D109: 246779411416 | E109: 45730 | F109: USD | G109: -114.46 | H109: 114.46 | I109: -9962.87 | K109: 45760 | L109: 45838 | M109: - | N109: 45809 | O109: 51171933 | P109: 1 | Q109: 45820 | R109: 210 | S109: 1.55e+16 | T109: Ascendas Panvel FTWZ Private Limited | U109: 9962.87 | W109: =X109/I109 -> -0.020007287 | X109: =VLOOKUP(D109,'[3]Customer TDS'!D:I,6,0) -> 199.33 | Y109: =I109+X109 -> -9763.54 | Z109: Diff due to exchange gain/loss | AA109: =VLOOKUP(D109,'Ascendus DATA'!$F:$J,5,0) -> 9922.68 | AB109: =I109+AA109 -> -40.19
A110: A023951 | B110: A023951 | C110: I | D110: 246779411418 | E110: 45730 | F110: USD | G110: -312.5 | H110: 312.5 | I110: -27200.75 | K110: 45760 | L110: 45838 | M110: - | N110: 45809 | O110: 51171937 | P110: 1 | Q110: 45820 | R110: 210 | S110: 1.55e+16 | T110: Ascendas Panvel FTWZ Private Limited | U110: 27200.75 | W110: =X110/I110 -> -0.020000184 | X110: =VLOOKUP(D110,'[3]Customer TDS'!D:I,6,0) -> 544.02 | Y110: =I110+X110 -> -26656.73 | Z110: Diff due to exchange gain/loss | AA110: =VLOOKUP(D110,'Ascendus DATA'!$F:$J,5,0) -> 27091.02 | AB110: =I110+AA110 -> -109.73
A111: A023951 | B111: A023951 | C111: I | D111: 246779410184 | E111: 45708 | F111: USD | G111: -2333.18 | H111: 2333.18 | I111: -201912.42 | J111: NO EXCHANGE RATE | K111: 45738 | L111: 45838 | M111: - | N111: 45809 | O111: 51171940 | P111: 1 | Q111: 45820 | R111: 210 | S111: 1.55e+16 | T111: Ascendas Panvel FTWZ Private Limited | U111: 201912.42 | W111: =X111/I111 -> -0.019998473 | X111: =VLOOKUP(D111,'[3]Customer TDS'!D:I,6,0) -> 4037.94 | Y111: =I111+X111 -> -197874.48 | Z111: Diff due to exchange gain/loss | AA111: =VLOOKUP(D111,'Ascendus DATA'!$F:$J,5,0) -> 201361.97 | AB111: =I111+AA111 -> -550.45
A112: A023951 | B112: A023951 | C112: I | D112: 246779413730 | E112: 45736 | F112: USD | G112: -3.2 | H112: 3.2 | I112: -278.54 | K112: 45766 | L112: 45838 | M112: - | N112: 45809 | O112: 51171944 | P112: 1 | Q112: 45820 | R112: 210 | S112: 1.55e+16 | T112: Ascendas Panvel FTWZ Private Limited | U112: 278.54 | W112: =X112/I112 -> -0.018740576 | X112: =VLOOKUP(D112,'[3]Customer TDS'!D:I,6,0) -> 5.22 | Y112: =I112+X112 -> -273.32 | Z112: Diff due to exchange gain/loss | AA112: =VLOOKUP(D112,'Ascendus DATA'!$F:$J,5,0) -> 277.41 | AB112: =I112+AA112 -> -1.13
A113: A023951 | B113: A023951 | C113: I | D113: 256779410263 | E113: 45750 | F113: INR | G113: - | H113: - | I113: -51.33 | J113: NO EXCHANGE RATE | K113: 45780 | L113: 45939 | M113: - | N113: 45809 | O113: 51171949 | P113: 1 | Q113: 45820 | R113: 210 | S113: 1.55e+16 | T113: Ascendas Panvel FTWZ Private Limited | U113: 2 | W113: =X113/I113 -> -0.038963569 | X113: =VLOOKUP(D113,'[3]Customer TDS'!D:I,6,0) -> 2 | Y113: =I113+X113 -> -49.33 | Z113: Customer recorded USD amount in INR amount. Customer needs to correct | AA113: =VLOOKUP(D113,'Ascendus DATA'!$F:$J,5,0) -> 4461.7 | AB113: =I113+AA113 -> 4410.37
A114: A023951 | B114: A023951 | C114: I | D114: 256779412012 | E114: 45763 | F114: INR | G114: - | H114: - | I114: -1051.22 | J114: NO EXCHANGE RATE | K114: 45793 | L114: 45820 | M114: - | N114: 45809 | O114: 51171953 | P114: 1 | Q114: 45820 | R114: 210 | S114: 1.55e+16 | T114: Ascendas Panvel FTWZ Private Limited | U114: 22 | W114: =X114/I114 -> -0.020928065 | X114: =VLOOKUP(D114,'[3]Customer TDS'!D:I,6,0) -> 22 | Y114: =I114+X114 -> -1029.22 | Z114: Customer recorded USD amount in INR amount. Customer needs to correct | AA114: =VLOOKUP(D114,'Ascendus DATA'!$F:$J,5,0) -> 91373.96 | AB114: =I114+AA114 -> 90322.74
A115: A023951 | B115: A023951 | C115: I | D115: 246779412035 | E115: 45733 | F115: USD | G115: -72.88 | H115: 72.88 | I115: -6343.65 | K115: 45763 | L115: 45838 | M115: - | N115: 45809 | O115: 51173807 | P115: 1 | Q115: 45820 | R115: 210 | S115: 1.55e+16 | T115: Ascendas Panvel FTWZ Private Limited | U115: 6343.65 | W115: =X115/I115 -> -0.020032631 | X115: =VLOOKUP(D115,'[3]Customer TDS'!D:I,6,0) -> 127.08 | Y115: =I115+X115 -> -6216.57 | Z115: Diff due to exchange gain/loss | AA115: =VLOOKUP(D115,'Ascendus DATA'!$F:$J,5,0) -> 6318.06 | AB115: =I115+AA115 -> -25.59
A116: A023951 | B116: A023951 | C116: I | D116: 246779412031 | E116: 45733 | F116: USD | G116: -28.03 | H116: 28.03 | I116: -2439.8 | J116: NO EXCHANGE RATE / 14 DAYS OLDER | K116: 45763 | L116: 45838 | M116: - | N116: 45809 | O116: 51173809 | P116: 1 | Q116: 45820 | R116: 210 | S116: 1.55e+16 | T116: Ascendas Panvel FTWZ Private Limited | U116: 2439.8 | W116: =X116/I116 -> -0.019977047 | X116: =VLOOKUP(D116,'[3]Customer TDS'!D:I,6,0) -> 48.74 | Y116: =I116+X116 -> -2391.06 | Z116: Diff due to exchange gain/loss | AA116: =VLOOKUP(D116,'Ascendus DATA'!$F:$J,5,0) -> 2429.96 | AB116: =I116+AA116 -> -9.84
A117: A023951 | B117: A023951 | C117: I | D117: 246779412029 | E117: 45733 | F117: USD | G117: -22.42 | H117: 22.42 | I117: -1951.49 | K117: 45763 | L117: 45838 | M117: - | N117: 45809 | O117: 51173811 | P117: 1 | Q117: 45820 | R117: 210 | S117: 1.55e+16 | T117: Ascendas Panvel FTWZ Private Limited | U117: 1951.49 | W117: =X117/I117 -> -0.020071843 | X117: =VLOOKUP(D117,'[3]Customer TDS'!D:I,6,0) -> 39.17 | Y117: =I117+X117 -> -1912.32 | Z117: Diff due to exchange gain/loss | AA117: =VLOOKUP(D117,'Ascendus DATA'!$F:$J,5,0) -> 1943.62 | AB117: =I117+AA117 -> -7.87
A118: A023951 | B118: A023951 | C118: I | D118: 246779410227 | E118: 45708 | F118: USD | G118: -2286.24 | H118: 2286.24 | I118: -197850.25 | K118: 45738 | L118: 45869 | M118: - | N118: 45809 | O118: 52235128 | P118: 1 | Q118: 45834 | R118: 210 | S118: 1.55e+16 | T118: Ascendas Panvel FTWZ Private Limited | U118: 197850.25 | W118: =X118/I118 -> -0.019997902 | X118: =VLOOKUP(D118,'[3]Customer TDS'!D:I,6,0) -> 3956.59 | Y118: =I118+X118 -> -193893.66 | Z118: Diff due to exchange gain/loss | AA118: =VLOOKUP(D118,'Ascendus DATA'!$F:$J,5,0) -> 197310.88 | AB118: =I118+AA118 -> -539.37
A119: A023951 | B119: A023951 | C119: A | D119: 2439105 | E119: 45827 | F119: INR | G119: - | H119: - | I119: 1760137.8 | J119: Outwards remit C-A023951 USD20175.95@87.24 | K119: 45827 | L119: 45869 | M119: - | N119: 45809 | O119: 52421432 | P119: 1 | Q119: 45827 | R119: 400 | S119: Outwards remit C-A02 | T119: Ascendas Panvel FTWZ Private Limited | U119: -1760137.8 | Y119: =I119+X119 -> 1760137.8
A120: A023951 | B120: A023951 | C120: I | D120: 246779411973 | E120: 45733 | F120: USD | G120: -426.09 | H120: 426.09 | I120: -37087.9 | K120: 45763 | L120: 45869 | M120: - | N120: 45809 | O120: 52538488 | P120: 1 | Q120: 45838 | R120: 210 | S120: 1.55e+16 | T120: Ascendas Panvel FTWZ Private Limited | U120: 37087.9 | W120: =X120/I120 -> -0.01999574 | X120: =VLOOKUP(D120,'[3]Customer TDS'!D:I,6,0) -> 741.6 | Y120: =I120+X120 -> -36346.3 | Z120: Diff due to exchange gain/loss | AA120: =VLOOKUP(D120,'Ascendus DATA'!$F:$J,5,0) -> 36938.28 | AB120: =I120+AA120 -> -149.62
A121: A023951 | B121: A023951 | C121: I | D121: 246779412033 | E121: 45733 | F121: USD | G121: -22.42 | H121: 22.42 | I121: -1951.49 | K121: 45763 | L121: 45869 | M121: - | N121: 45809 | O121: 52538490 | P121: 1 | Q121: 45838 | R121: 210 | S121: 1.55e+16 | T121: Ascendas Panvel FTWZ Private Limited | U121: 1951.49 | W121: =X121/I121 -> -0.020071843 | X121: =VLOOKUP(D121,'[3]Customer TDS'!D:I,6,0) -> 39.17 | Y121: =I121+X121 -> -1912.32 | Z121: Diff due to exchange gain/loss | AA121: =VLOOKUP(D121,'Ascendus DATA'!$F:$J,5,0) -> 1943.62 | AB121: =I121+AA121 -> -7.87
A122: A023951 | B122: A023951 | C122: I | D122: 246779410260 | E122: 45708 | F122: USD | G122: -91.45 | H122: 91.45 | I122: -7914.04 | K122: 45738 | L122: 45869 | M122: - | N122: 45809 | O122: 52538802 | P122: 1 | Q122: 45838 | R122: 210 | S122: 1.55e+16 | T122: Ascendas Panvel FTWZ Private Limited | U122: 7914.04 | W122: =X122/I122 -> -0.020011271 | X122: =VLOOKUP(D122,'[3]Customer TDS'!D:I,6,0) -> 158.37 | Y122: =I122+X122 -> -7755.67 | Z122: Diff due to exchange gain/loss | AA122: =VLOOKUP(D122,'Ascendus DATA'!$F:$J,5,0) -> 7892.47 | AB122: =I122+AA122 -> -21.57
A123: A023951 | B123: A023951 | C123: I | D123: 246779413936 | E123: 45736 | F123: USD | G123: -27.5 | H123: 27.5 | I123: -2393.67 | K123: 45766 | L123: 45869 | M123: - | N123: 45809 | O123: 52538807 | P123: 1 | Q123: 45838 | R123: 210 | S123: 1.55e+16 | T123: Ascendas Panvel FTWZ Private Limited | U123: 2393.67 | W123: =X123/I123 -> -0.01999858 | X123: =VLOOKUP(D123,'[3]Customer TDS'!D:I,6,0) -> 47.87 | Y123: =I123+X123 -> -2345.8 | Z123: Diff due to exchange gain/loss | AA123: =VLOOKUP(D123,'Ascendus DATA'!$F:$J,5,0) -> 2384.01 | AB123: =I123+AA123 -> -9.66
A124: A023951 | B124: A023951 | C124: I | D124: 256779410801 | E124: 45751 | F124: USD | G124: -2829.48 | H124: 2829.48 | I124: -242562.74 | K124: 45781 | L124: 45869 | M124: - | N124: 45809 | O124: 52538812 | P124: 1 | Q124: 45838 | R124: 210 | S124: 1.55e+16 | T124: Ascendas Panvel FTWZ Private Limited | U124: 242562.74 | W124: =X124/I124 -> -0.020000145 | X124: =VLOOKUP(D124,'[3]Customer TDS'!D:I,6,0) -> 4851.29 | Y124: =I124+X124 -> -237711.45 | Z124: Diff due to exchange gain/loss | AA124: =VLOOKUP(D124,'Ascendus DATA'!$F:$J,5,0) -> 245943.55 | AB124: =I124+AA124 -> 3380.81
A125: A023951 | B125: A023951 | C125: I | D125: 256779412524 | E125: 45769 | F125: USD | G125: -36.5 | H125: 36.5 | I125: -3129.03 | K125: 45799 | L125: 45869 | M125: - | N125: 45809 | O125: 52538816 | P125: 1 | Q125: 45838 | R125: 210 | S125: 1.55e+16 | T125: Ascendas Panvel FTWZ Private Limited | U125: 3129.03 | W125: =X125/I125 -> -0.019999808 | X125: =VLOOKUP(D125,'[3]Customer TDS'!D:I,6,0) -> 62.58 | Y125: =I125+X125 -> -3066.45 | Z125: Diff due to exchange gain/loss | AA125: =VLOOKUP(D125,'Ascendus DATA'!$F:$J,5,0) -> 3172.65 | AB125: =I125+AA125 -> 43.62
...

Sheet Customer TDS
A2: Creditor Code | B2: Creditor | C2: Ty | D2: Item# | E2: Item Date | F2: CCY | G2: FC Amount | H2: Settled FC Amount | I2: LC Amount | J2: Particular | K2: Due Date | L2: Last Sett. Date | M2: Job# | N2: VC Period | O2: VC# | P2: VC Seq | Q2: VC Date | R2: Tx. Type | S2: Reference | T2: Full Name | U2: Settled LC Amount
A3: A023951 | B3: A023951 | C3: I | D3: 246779411742 | E3: 45733 | F3: USD | G3: 0.47 | H3: - | I3: 40.91 | J3: C: ASCENDAS27 P: A023951 I 246779411742 | K3: 45763 | M3: - | N3: 45809 | O3: 51127447 | P3: 1 | Q3: 45819 | R3: 230 | T3: Ascendas Panvel FTWZ Private Limited | U3: 0
A4: A023951 | B4: A023951 | C4: I | D4: 246779411601 | E4: 45733 | F4: USD | G4: 0.47 | H4: - | I4: 40.91 | J4: C: ASCENDAS27 P: A023951 I 246779411601 | K4: 45763 | M4: - | N4: 45809 | O4: 51162689 | P4: 1 | Q4: 45820 | R4: 230 | T4: Ascendas Panvel FTWZ Private Limited | U4: 0
A5: A023951 | B5: A023951 | C5: I | D5: 246779411717 | E5: 45733 | F5: USD | G5: 0.91 | H5: - | I5: 79.21 | J5: C: ASCENDAS27 P: A023951 I 246779411717 | K5: 45763 | M5: - | N5: 45809 | O5: 51162692 | P5: 1 | Q5: 45820 | R5: 230 | T5: Ascendas Panvel FTWZ Private Limited | U5: 0
A6: A023951 | B6: A023951 | C6: I | D6: 246779411913 | E6: 45733 | F6: USD | G6: 0.57 | H6: - | I6: 49.61 | J6: C: ASCENDAS27 P: A023951 I 246779411913 | K6: 45763 | M6: - | N6: 45809 | O6: 51162693 | P6: 1 | Q6: 45820 | R6: 230 | T6: Ascendas Panvel FTWZ Private Limited | U6: 0
A7: A023951 | B7: A023951 | C7: I | D7: 246779411740 | E7: 45733 | F7: USD | G7: 0.46 | H7: - | I7: 40.04 | J7: C: ASCENDAS27 P: A023951 I 246779411740 | K7: 45763 | M7: - | N7: 45809 | O7: 51162694 | P7: 1 | Q7: 45820 | R7: 230 | T7: Ascendas Panvel FTWZ Private Limited | U7: 0
A8: A023951 | B8: A023951 | C8: I | D8: 246779412111 | E8: 45733 | F8: USD | G8: 8.41 | H8: - | I8: 732.03 | J8: C: ASCENDAS27 P: A023951 I 246779412111 | K8: 45763 | M8: - | N8: 45809 | O8: 51162695 | P8: 1 | Q8: 45820 | R8: 230 | T8: Ascendas Panvel FTWZ Private Limited | U8: 0
A9: A023951 | B9: A023951 | C9: I | D9: 246779411722 | E9: 45733 | F9: USD | G9: 0.8 | H9: - | I9: 69.63 | J9: C: ASCENDAS27 P: A023951 I 246779411722 | K9: 45763 | M9: - | N9: 45809 | O9: 51162698 | P9: 1 | Q9: 45820 | R9: 230 | T9: Ascendas Panvel FTWZ Private Limited | U9: 0
A10: A023951 | B10: A023951 | C10: I | D10: 246779412041 | E10: 45733 | F10: USD | G10: 0.67 | H10: - | I10: 58.32 | J10: C: ASCENDAS27 P: A023951 I 246779412041 | K10: 45763 | M10: - | N10: 45809 | O10: 51162699 | P10: 1 | Q10: 45820 | R10: 230 | T10: Ascendas Panvel FTWZ Private Limited | U10: 0
A11: A023951 | B11: A023951 | C11: I | D11: 246779411898 | E11: 45733 | F11: USD | G11: 0.14 | H11: - | I11: 12.19 | J11: C: ASCENDAS27 P: A023951 I 246779411898 | K11: 45763 | M11: - | N11: 45809 | O11: 51162700 | P11: 1 | Q11: 45820 | R11: 230 | T11: Ascendas Panvel FTWZ Private Limited | U11: 0
A12: A023951 | B12: A023951 | C12: I | D12: 246779411729 | E12: 45733 | F12: USD | G12: 0.69 | H12: - | I12: 60.06 | J12: C: ASCENDAS27 P: A023951 I 246779411729 | K12: 45763 | M12: - | N12: 45809 | O12: 51162702 | P12: 1 | Q12: 45820 | R12: 230 | T12: Ascendas Panvel FTWZ Private Limited | U12: 0
A13: A023951 | B13: A023951 | C13: I | D13: 246779411737 | E13: 45733 | F13: USD | G13: 0.57 | H13: - | I13: 49.61 | J13: C: ASCENDAS27 P: A023951 I 246779411737 | K13: 45763 | M13: - | N13: 45809 | O13: 51162703 | P13: 1 | Q13: 45820 | R13: 230 | T13: Ascendas Panvel FTWZ Private Limited | U13: 0
A14: A023951 | B14: A023951 | C14: I | D14: 246779411595 | E14: 45733 | F14: USD | G14: 1.03 | H14: - | I14: 89.65 | J14: C: ASCENDAS27 P: A023951 I 246779411595 | K14: 45763 | M14: - | N14: 45809 | O14: 51162704 | P14: 1 | Q14: 45820 | R14: 230 | T14: Ascendas Panvel FTWZ Private Limited | U14: 0
... A78: A023951 | B78: A023951 | C78: I | D78: 246779411912 | E78: 45733 | F78: USD | G78: 0.23 | H78: - | I78: 20.02 | J78: C: ASCENDAS27 P: A023951 I 246779411912 | K78: 45763 | M78: - | N78: 45809 | O78: 51165565 | P78: 1 | Q78: 45820 | R78: 230 | T78: Ascendas Panvel FTWZ Private Limited | U78: 0
A79: A023951 | B79: A023951 | C79: I | D79: 256779410818 | E79: 45751 | F79: INR | G79: - | H79: - | I79: 25 | J79: C: ASCENDAS27 P: A023951 I 256779410818 | K79: 45781 | M79: - | N79: 45809 | O79: 51174451 | P79: 1 | Q79: 45820 | R79: 230 | T79: Ascendas Panvel FTWZ Private Limited | U79: 0
A80: A023951 | B80: A023951 | C80: I | D80: 246779412032 | E80: 45733 | F80: USD | G80: 0.67 | H80: - | I80: 58.32 | J80: C: ASCENDAS27 P: A023951 I 246779412032 | K80: 45763 | M80: - | N80: 45809 | O80: 51174461 | P80: 1 | Q80: 45820 | R80: 230 | T80: Ascendas Panvel FTWZ Private Limited | U80: 0
A81: A023951 | B81: A023951 | C81: I | D81: 246779411414 | E81: 45730 | F81: USD | G81: 0.57 | H81: - | I81: 49.61 | J81: C: ASCENDAS27 P: A023951 I 246779411414 | K81: 45760 | M81: - | N81: 45809 | O81: 51174466 | P81: 1 | Q81: 45820 | R81: 230 | T81: Ascendas Panvel FTWZ Private Limited | U81: 0
A82: A023951 | B82: A023951 | C82: I | D82: 246779410218 | E82: 45708 | F82: USD | G82: 1.03 | H82: - | I82: 89.14 | J82: C: ASCENDAS27 P: A023951 I 246779410218 | K82: 45738 | M82: - | N82: 45809 | O82: 51174468 | P82: 1 | Q82: 45820 | R82: 230 | T82: Ascendas Panvel FTWZ Private Limited | U82: 0
A83: A023951 | B83: A023951 | C83: I | D83: 246779410175 | E83: 45708 | F83: USD | G83: 1.05 | H83: - | I83: 90.87 | J83: C: ASCENDAS27 P: A023951 I 246779410175 | K83: 45738 | M83: - | N83: 45809 | O83: 51174473 | P83: 1 | Q83: 45820 | R83: 230 | T83: Ascendas Panvel FTWZ Private Limited | U83: 0
A84: A023951 | B84: A023951 | C84: I | D84: 246779411408 | E84: 45730 | F84: USD | G84: 0.8 | H84: - | I84: 69.63 | J84: C: ASCENDAS27 P: A023951 I 246779411408 | K84: 45760 | M84: - | N84: 45809 | O84: 51174475 | P84: 1 | Q84: 45820 | R84: 230 | T84: Ascendas Panvel FTWZ Private Limited | U84: 0
A85: A023951 | B85: A023951 | C85: I | D85: 246779410904 | E85: 45722 | F85: USD | G85: 33.32 | H85: - | I85: 2900.25 | J85: C: ASCENDAS27 P: A023951 I 246779410904 | K85: 45752 | M85: - | N85: 45809 | O85: 51174476 | P85: 1 | Q85: 45820 | R85: 230 | T85: Ascendas Panvel FTWZ Private Limited | U85: 0
A86: A023951 | B86: A023951 | C86: I | D86: 246779411413 | E86: 45730 | F86: USD | G86: 0.8 | H86: - | I86: 69.63 | J86: C: ASCENDAS27 P: A023951 I 246779411413 | K86: 45760 | M86: - | N86: 45809 | O86: 51174480 | P86: 1 | Q86: 45820 | R86: 230 | T86: Ascendas Panvel FTWZ Private Limited | U86: 0
A87: A023951 | B87: A023951 | C87: I | D87: 246779411410 | E87: 45730 | F87: USD | G87: 0.8 | H87: - | I87: 69.63 | J87: C: ASCENDAS27 P: A023951 I 246779411410 | K87: 45760 | M87: - | N87: 45809 | O87: 51174492 | P87: 1 | Q87: 45820 | R87: 230 | T87: Ascendas Panvel FTWZ Private Limited | U87: 0
A88: A023951 | B88: A023951 | C88: I | D88: 246779410826 | E88: 45720 | F88: USD | G88: 0.06 | H88: - | I88: 5.22 | J88: C: ASCENDAS27 P: A023951 I 246779410826 | K88: 45750 | M88: - | N88: 45809 | O88: 51174506 | P88: 1 | Q88: 45820 | R88: 230 | T88: Ascendas Panvel FTWZ Private Limited | U88: 0
A89: A023951 | B89: A023951 | C89: I | D89: 246779412037 | E89: 45733 | F89: USD | G89: 0.9 | H89: - | I89: 78.34 | J89: C: ASCENDAS27 P: A023951 I 246779412037 | K89: 45763 | M89: - | N89: 45809 | O89: 51174508 | P89: 1 | Q89: 45820 | R89: 230 | T89: Ascendas Panvel FTWZ Private Limited | U89: 0
A90: A023951 | B90: A023951 | C90: I | D90: 246779412030 | E90: 45733 | F90: USD | G90: 0.34 | H90: - | I90: 29.59 | J90: C: ASCENDAS27 P: A023951 I 246779412030 | K90: 45763 | M90: - | N90: 45809 | O90: 51174511 | P90: 1 | Q90: 45820 | R90: 230 | T90: Ascendas Panvel FTWZ Private Limited | U90: 0
A91: A023951 | B91: A023951 | C91: I | D91: 256779411468 | E91: 45762 | F91: USD | G91: 0.53 | H91: - | I91: 45.44 | J91: C: ASCENDAS27 P: A023951 I 256779411468 | K91: 45792 | M91: - | N91: 45809 | O91: 51174512 | P91: 1 | Q91: 45820 | R91: 230 | T91: Ascendas Panvel FTWZ Private Limited | U91: 0
... A94: A023951 | B94: A023951 | C94: I | D94: 246779411411 | E94: 45730 | F94: USD | G94: 0.92 | H94: - | I94: 80.08 | J94: C: ASCENDAS27 P: A023951 I 246779411411 | K94: 45760 | M94: - | N94: 45809 | O94: 51174525 | P94: 1 | Q94: 45820 | R94: 230 | T94: Ascendas Panvel FTWZ Private Limited | U94: 0
A95: A023951 | B95: A023951 | C95: I | D95: 256779410262 | E95: 45750 | F95: INR | G95: - | H95: - | I95: 2 | J95: C: ASCENDAS27 P: A023951 I 256779410262 | K95: 45780 | M95: - | N95: 45809 | O95: 51174527 | P95: 1 | Q95: 45820 | R95: 230 | T95: Ascendas Panvel FTWZ Private Limited | U95: 0
A96: A023951 | B96: A023951 | C96: I | D96: 246779413202 | E96: 45735 | F96: USD | G96: 0.78 | H96: - | I96: 67.5 | J96: C: ASCENDAS27 P: A023951 I 246779413202 | K96: 45765 | M96: - | N96: 45809 | O96: 51174535 | P96: 1 | Q96: 45820 | R96: 230 | T96: Ascendas Panvel FTWZ Private Limited | U96: 0
A97: A023951 | B97: A023951 | C97: I | D97: 246779411418 | E97: 45730 | F97: USD | G97: 6.25 | H97: - | I97: 544.02 | J97: C: ASCENDAS27 P: A023951 I 246779411418 | K97: 45760 | M97: - | N97: 45809 | O97: 51174544 | P97: 1 | Q97: 45820 | R97: 230 | T97: Ascendas Panvel FTWZ Private Limited | U97: 0
A98: A023951 | B98: A023951 | C98: I | D98: 256779412012 | E98: 45763 | F98: INR | G98: - | H98: - | I98: 22 | J98: C: ASCENDAS27 P: A023951 I 256779412012 | K98: 45793 | M98: - | N98: 45809 | O98: 51174545 | P98: 1 | Q98: 45820 | R98: 230 | T98: Ascendas Panvel FTWZ Private Limited | U98: 0
A99: A023951 | B99: A023951 | C99: I | D99: 246779412034 | E99: 45733 | F99: USD | G99: 0.67 | H99: - | I99: 58.32 | J99: C: ASCENDAS27 P: A023951 I 246779412034 | K99: 45763 | M99: - | N99: 45809 | O99: 51174548 | P99: 1 | Q99: 45820 | R99: 230 | T99: Ascendas Panvel FTWZ Private Limited | U99: 0
A100: A023951 | B100: A023951 | C100: I | D100: 246779412039 | E100: 45733 | F100: USD | G100: 1.12 | H100: - | I100: 97.49 | J100: C: ASCENDAS27 P: A023951 I 246779412039 | K100: 45763 | M100: - | N100: 45809 | O100: 51174549 | P100: 1 | Q100: 45820 | R100: 230 | T100: Ascendas Panvel FTWZ Private Limited | U100: 0
A101: A023951 | B101: A023951 | C101: I | D101: 246779413730 | E101: 45736 | F101: USD | G101: 0.06 | H101: - | I101: 5.22 | J101: C: ASCENDAS27 P: A023951 I 246779413730 | K101: 45766 | M101: - | N101: 45809 | O101: 51174564 | P101: 1 | Q101: 45820 | R101: 230 | T101: Ascendas Panvel FTWZ Private Limited | U101: 0
A102: A023951 | B102: A023951 | C102: I | D102: 246779411415 | E102: 45730 | F102: USD | G102: 0.46 | H102: - | I102: 40.04 | J102: C: ASCENDAS27 P: A023951 I 246779411415 | K102: 45760 | M102: - | N102: 45809 | O102: 51174566 | P102: 1 | Q102: 45820 | R102: 230 | T102: Ascendas Panvel FTWZ Private Limited | U102: 0
A103: A023951 | B103: A023951 | C103: I | D103: 246779410141 | E103: 45708 | F103: USD | G103: 47.62 | H103: - | I103: 4121.01 | J103: C: ASCENDAS27 P: A023951 I 246779410141 | K103: 45738 | M103: - | N103: 45809 | O103: 51174570 | P103: 1 | Q103: 45820 | R103: 230 | T103: Ascendas Panvel FTWZ Private Limited | U103: 0
A104: A023951 | B104: A023951 | C104: I | D104: 246779410184 | E104: 45708 | F104: USD | G104: 46.66 | H104: - | I104: 4037.94 | J104: C: ASCENDAS27 P: A023951 I 246779410184 | K104: 45738 | M104: - | N104: 45809 | O104: 51174572 | P104: 1 | Q104: 45820 | R104: 230 | T104: Ascendas Panvel FTWZ Private Limited | U104: 0
A105: A023951 | B105: A023951 | C105: I | D105: 246779411419 | E105: 45730 | F105: USD | G105: 0.47 | H105: - | I105: 40.91 | J105: C: ASCENDAS27 P: A023951 I 246779411419 | K105: 45760 | M105: - | N105: 45809 | O105: 51174577 | P105: 1 | Q105: 45820 | R105: 230 | T105: Ascendas Panvel FTWZ Private Limited | U105: 0
A106: A023951 | B106: A023951 | C106: I | D106: 246779410389 | E106: 45719 | F106: USD | G106: 10.84 | H106: - | I106: 943.54 | J106: C: ASCENDAS27 P: A023951 I 246779410389 | K106: 45749 | M106: - | N106: 45809 | O106: 51174586 | P106: 1 | Q106: 45820 | R106: 230 | T106: Ascendas Panvel FTWZ Private Limited | U106: 0
A107: A023951 | B107: A023951 | C107: I | D107: 246779411417 | E107: 45730 | F107: USD | G107: 1.37 | H107: - | I107: 119.25 | J107: C: ASCENDAS27 P: A023951 I 246779411417 | K107: 45760 | M107: - | N107: 45809 | O107: 51174588 | P107: 1 | Q107: 45820 | R107: 230 | T107: Ascendas Panvel FTWZ Private Limited | U107: 0
A108: A023951 | B108: A023951 | C108: I | D108: 246779411407 | E108: 45730 | F108: USD | G108: 1.14 | H108: - | I108: 99.23 | J108: C: ASCENDAS27 P: A023951 I 246779411407 | K108: 45760 | M108: - | N108: 45809 | O108: 51174590 | P108: 1 | Q108: 45820 | R108: 230 | T108: Ascendas Panvel FTWZ Private Limited | U108: 0
A109: A023951 | B109: A023951 | C109: I | D109: 246779412036 | E109: 45733 | F109: USD | G109: 0.56 | H109: - | I109: 48.74 | J109: C: ASCENDAS27 P: A023951 I 246779412036 | K109: 45763 | M109: - | N109: 45809 | O109: 51174595 | P109: 1 | Q109: 45820 | R109: 230 | T109: Ascendas Panvel FTWZ Private Limited | U109: 0
A110: A023951 | B110: A023951 | C110: I | D110: 246779411412 | E110: 45730 | F110: USD | G110: 0.4 | H110: - | I110: 34.82 | J110: C: ASCENDAS27 P: A023951 I 246779411412 | K110: 45760 | M110: - | N110: 45809 | O110: 51174596 | P110: 1 | Q110: 45820 | R110: 230 | T110: Ascendas Panvel FTWZ Private Limited | U110: 0
A111: A023951 | B111: A023951 | C111: I | D111: 246779412028 | E111: 45733 | F111: USD | G111: 0.56 | H111: - | I111: 48.74 | J111: C: ASCENDAS27 P: A023951 I 246779412028 | K111: 45763 | M111: - | N111: 45809 | O111: 51174600 | P111: 1 | Q111: 45820 | R111: 230 | T111: Ascendas Panvel FTWZ Private Limited | U111: 0
A112: A023951 | B112: A023951 | C112: I | D112: 256779410263 | E112: 45750 | F112: INR | G112: - | H112: - | I112: 2 | J112: C: ASCENDAS27 P: A023951 I 256779410263 | K112: 45780 | M112: - | N112: 45809 | O112: 51174603 | P112: 1 | Q112: 45820 | R112: 230 | T112: Ascendas Panvel FTWZ Private Limited | U112: 0
A113: A023951 | B113: A023951 | C113: I | D113: 246779410217 | E113: 45708 | F113: USD | G113: 1.87 | H113: - | I113: 161.83 | J113: C: ASCENDAS27 P: A023951 I 246779410217 | K113: 45738 | M113: - | N113: 45809 | O113: 51174605 | P113: 1 | Q113: 45820 | R113: 230 | T113: Ascendas Panvel FTWZ Private Limited | U113: 0
A114: A023951 | B114: A023951 | C114: I | D114: 246779410174 | E114: 45708 | F114: USD | G114: 1.9 | H114: - | I114: 164.43 | J114: C: ASCENDAS27 P: A023951 I 246779410174 | K114: 45738 | M114: - | N114: 45809 | O114: 51174608 | P114: 1 | Q114: 45820 | R114: 230 | T114: Ascendas Panvel FTWZ Private Limited | U114: 0
A115: A023951 | B115: A023951 | C115: I | D115: 246779412031 | E115: 45733 | F115: USD | G115: 0.56 | H115: - | I115: 48.74 | J115: C: ASCENDAS27 P: A023951 I 246779412031 | K115: 45763 | M115: - | N115: 45809 | O115: 51175460 | P115: 1 | Q115: 45820 | R115: 230 | T115: Ascendas Panvel FTWZ Private Limited | U115: 0
A116: A023951 | B116: A023951 | C116: I | D116: 246779412029 | E116: 45733 | F116: USD | G116: 0.45 | H116: - | I116: 39.17 | J116: C: ASCENDAS27 P: A023951 I 246779412029 | K116: 45763 | M116: - | N116: 45809 | O116: 51175471 | P116: 1 | Q116: 45820 | R116: 230 | T116: Ascendas Panvel FTWZ Private Limited | U116: 0
A117: A023951 | B117: A023951 | C117: I | D117: 246779412035 | E117: 45733 | F117: USD | G117: 1.46 | H117: - | I117: 127.08 | J117: C: ASCENDAS27 P: A023951 I 246779412035 | K117: 45763 | M117: - | N117: 45809 | O117: 51175472 | P117: 1 | Q117: 45820 | R117: 230 | T117: Ascendas Panvel FTWZ Private Limited | U117: 0
A118: A023951 | B118: A023951 | C118: I | D118: 246779410227 | E118: 45708 | F118: USD | G118: 45.72 | H118: - | I118: 3956.59 | J118: C: ASCENDAS27 P: A023951 I 246779410227 | K118: 45738 | M118: - | N118: 45809 | O118: 52235689 | P118: 1 | Q118: 45834 | R118: 230 | T118: Ascendas Panvel FTWZ Private Limited | U118: 0
A119: A023951 | B119: A023951 | C119: I | D119: 256779412053 | E119: 45763 | F119: USD | G119: 19.72 | H119: - | I119: 1690.54 | J119: C: ASCENDAS27 P: A023951 I 256779412053 | K119: 45793 | M119: - | N119: 45809 | O119: 52543946 | P119: 1 | Q119: 45838 | R119: 230 | T119: Ascendas Panvel FTWZ Private Limited | U119: 0
A120: A023951 | B120: A023951 | C120: I | D120: 246779410064 | E120: 45708 | F120: USD | G120: 1.05 | H120: - | I120: 90.87 | J120: C: ASCENDAS27 P: A023951 I 246779410064 | K120: 45738 | M120: - | N120: 45809 | O120: 52543948 | P120: 1 | Q120: 45838 | R120: 230 | T120: Ascendas Panvel FTWZ Private Limited | U120: 0
A121: A023951 | B121: A023951 | C121: I | D121: 246779410030 | E121: 45708 | F121: USD | G121: 47.62 | H121: - | I121: 4121.01 | J121: C: ASCENDAS27 P: A023951 I 246779410030 | K121: 45738 | M121: - | N121: 45809 | O121: 52543953 | P121: 1 | Q121: 45838 | R121: 230 | T121: Ascendas Panvel FTWZ Private Limited | U121: 0
A122: A023951 | B122: A023951 | C122: I | D122: 256779411969 | E122: 45763 | F122: USD | G122: 1.58 | H122: - | I122: 135.45 | J122: C: ASCENDAS27 P: A023951 I 256779411969 | K122: 45793 | M122: - | N122: 45809 | O122: 52543954 | P122: 1 | Q122: 45838 | R122: 230 | T122: Ascendas Panvel FTWZ Private Limited | U122: 0
A123: A023951 | B123: A023951 | C123: I | D123: 256779412189 | E123: 45768 | F123: INR | G123: - | H123: - | I123: 6 | J123: C: ASCENDAS27 P: A023951 I 256779412189 | K123: 45798 | M123: - | N123: 45809 | O123: 52543957 | P123: 1 | Q123: 45838 | R123: 230 | T123: Ascendas Panvel FTWZ Private Limited | U123: 0
A124: A023951 | B124: A023951 | C124: I | D124: 246779410063 | E124: 45708 | F124: USD | G124: 1.9 | H124: - | I124: 164.43 | J124: C: ASCENDAS27 P: A023951 I 246779410063 | K124: 45738 | M124: - | N124: 45809 | O124: 52543959 | P124: 1 | Q124: 45838 | R124: 230 | T124: Ascendas Panvel FTWZ Private Limited | U124: 0
A125: A023951 | B125: A023951 | C125: I | D125: 256779410196 | E125: 45750 | F125: USD | G125: 4.93 | H125: - | I125: 422.63 | J125: C: ASCENDAS27 P: A023951 I 256779410196 | K125: 45780 | M125: - | N125: 45809 | O125: 52543961 | P125: 1 | Q125: 45838 | R125: 230 | T125: Ascendas Panvel FTWZ Private Limited | U125: 0
A126: A023951 | B126: A023951 | C126: I | D126: 256779412185 | E126: 45768 | F126: USD | G126: 1.03 | H126: - | I126: 88.3 | J126: C: ASCENDAS27 P: A023951 I 256779412185 | K126: 45798 | M126: - | N126: 45809 | O126: 52543962 | P126: 1 | Q126: 45838 | R126: 230 | T126: Ascendas Panvel FTWZ Private Limited | U126: 0
A127: A023951 | B127: A023951 | C127: I | D127: 256779412092 | E127: 45763 | F127: USD | G127: 5.78 | H127: - | I127: 495.5 | J127: C: ASCENDAS27 P: A023951 I 256779412092 | K127: 45793 | M127: - | N127: 45809 | O127: 52543964 | P127: 1 | Q127: 45838 | R127: 230 | T127: Ascendas Panvel FTWZ Private Limited | U127: 0
A128: A023951 | B128: A023951 | C128: I | D128: 256779412577 | E128: 45769 | F128: USD | G128: 0.92 | H128: - | I128: 78.87 | J128: C: ASCENDAS27 P: A023951 I 256779412577 | K128: 45799 | M128: - | N128: 45809 | O128: 52543974 | P128: 1 | Q128: 45838 | R128: 230 | T128: Ascendas Panvel FTWZ Private Limited | U128: 0
A129: A023951 | B129: A023951 | C129: I | D129: 246779413024 | E129: 45735 | F129: USD | G129: 1.01 | H129: - | I129: 87.91 | J129: C: ASCENDAS27 P: A023951 I 246779413024 | K129: 45765 | M129: - | N129: 45809 | O129: 52543977 | P129: 1 | Q129: 45838 | R129: 230 | T129: Ascendas Panvel FTWZ Private Limited | U129: 0
A130: A023951 | B130: A023951 | C130: I | D130: 256779412564 | E130: 45769 | F130: USD | G130: 1.1 | H130: - | I130: 94.3 | J130: C: ASCENDAS27 P: A023951 I 256779412564 | K130: 45799 | M130: - | N130: 45809 | O130: 52543978 | P130: 1 | Q130: 45838 | R130: 230 | T130: Ascendas Panvel FTWZ Private Limited | U130: 0
A131: A023951 | B131: A023951 | C131: I | D131: 246779413815 | E131: 45736 | F131: USD | G131: 1 | H131: - | I131: 87.04 | J131: C: ASCENDAS27 P: A023951 I 246779413815 | K131: 45766 | M131: - | N131: 45809 | O131: 52543983 | P131: 1 | Q131: 45838 | R131: 230 | T131: Ascendas Panvel FTWZ Private Limited | U131: 0
A132: A023951 | B132: A023951 | C132: I | D132: 246779410260 | E132: 45708 | F132: USD | G132: 1.83 | H132: - | I132: 158.37 | J132: C: ASCENDAS27 P: A023951 I 246779410260 | K132: 45738 | M132: - | N132: 45809 | O132: 52543989 | P132: 1 | Q132: 45838 | R132: 230 | T132: Ascendas Panvel FTWZ Private Limited | U132: 0
A133: A023951 | B133: A023951 | C133: I | D133: 256779412123 | E133: 45763 | F133: USD | G133: 66.36 | H133: - | I133: 5688.84 | J133: C: ASCENDAS27 P: A023951 I 256779412123 | K133: 45793 | M133: - | N133: 45809 | O133: 52543991 | P133: 1 | Q133: 45838 | R133: 230 | T133: Ascendas Panvel FTWZ Private Limited | U133: 0
A134: A023951 | B134: A023951 | C134: I | D134: 256779412529 | E134: 45769 | F134: USD | G134: 0.59 | H134: - | I134: 50.58 | J134: C: ASCENDAS27 P: A023951 I 256779412529 | K134: 45799 | M134: - | N134: 45809 | O134: 52543995 | P134: 1 | Q134: 45838 | R134: 230 | T134: Ascendas Panvel FTWZ Private Limited | U134: 0
A135: A023951 | B135: A023951 | C135: I | D135: 256779410303 | E135: 45750 | F135: USD | G135: 1.83 | H135: - | I135: 156.88 | J135: C: ASCENDAS27 P: A023951 I 256779410303 | K135: 45780 | M135: - | N135: 45809 | O135: 52543997 | P135: 1 | Q135: 45838 | R135: 230 | T135: Ascendas Panvel FTWZ Private Limited | U135: 0
... A173: A023951 | B173: A023951 | C173: I | D173: 256779413399 | E173: 45798 | F173: USD | G173: 4.6 | H173: - | I173: 392.72 | J173: C: ASCENDAS27 P: A023951 I 256779413399 | K173: 45828 | M173: - | N173: 45839 | O173: 53373894 | P173: 1 | Q173: 45849 | R173: 230 | T173: Ascendas Panvel FTWZ Private Limited | U173: 0
A174: A023951 | B174: A023951 | C174: I | D174: 246779411409_D | E174: 45730 | F174: USD | G174: 4.99 | H174: - | I174: 434.34 | J174: C: ASCENDAS27 P: A023951 I 246779411409_D | K174: 45760 | M174: - | N174: 45839 | O174: 54042034 | P174: 1 | Q174: 45860 | R174: 230 | T174: Ascendas Panvel FTWZ Private Limited | U174: 0
A175: A023951 | B175: A023951 | C175: I | D175: 256779415317 | E175: 45848 | F175: USD | G175: 4 | H175: - | I175: 353.88 | J175: C: ASCENDAS27 P: A023951 I 256779415317 | K175: 45878 | M175: - | N175: 45901 | O175: 59299159 | P175: 1 | Q175: 45930 | R175: 230 | T175: Ascendas Panvel FTWZ Private Limited | U175: 0
A176: A023951 | B176: A023951 | C176: I | D176: 256779415346 | E176: 45848 | F176: USD | G176: 0.35 | H176: - | I176: 30.96 | J176: C: ASCENDAS27 P: A023951 I 256779415346 | K176: 45878 | M176: - | N176: 45901 | O176: 59299161 | P176: 1 | Q176: 45930 | R176: 230 | T176: Ascendas Panvel FTWZ Private Limited | U176: 0
A177: A023951 | B177: A023951 | C177: I | D177: 256779415339 | E177: 45848 | F177: USD | G177: 0.55 | H177: - | I177: 48.66 | J177: C: ASCENDAS27 P: A023951 I 256779415339 | K177: 45878 | M177: - | N177: 45901 | O177: 59299163 | P177: 1 | Q177: 45930 | R177: 230 | T177: Ascendas Panvel FTWZ Private Limited | U177: 0
A178: A023951 | B178: A023951 | C178: I | D178: 256779415371 | E178: 45848 | F178: USD | G178: 0.87 | H178: - | I178: 76.97 | J178: C: ASCENDAS27 P: A023951 I 256779415371 | K178: 45878 | M178: - | N178: 45901 | O178: 59299165 | P178: 1 | Q178: 45930 | R178: 230 | T178: Ascendas Panvel FTWZ Private Limited | U178: 0
A179: A023951 | B179: A023951 | C179: I | D179: 256779415338 | E179: 45848 | F179: USD | G179: 0.25 | H179: - | I179: 22.12 | J179: C: ASCENDAS27 P: A023951 I 256779415338 | K179: 45878 | M179: - | N179: 45901 | O179: 59299166 | P179: 1 | Q179: 45930 | R179: 230 | T179: Ascendas Panvel FTWZ Private Limited | U179: 0
A180: A023951 | B180: A023951 | C180: I | D180: 256779413391 | E180: 45798 | F180: USD | G180: 5.07 | H180: - | I180: 432.85 | J180: C: ASCENDAS27 P: A023951 I 256779413391 | K180: 45828 | M180: - | N180: 45901 | O180: 59299168 | P180: 1 | Q180: 45930 | R180: 230 | T180: Ascendas Panvel FTWZ Private Limited | U180: 0
A181: A023951 | B181: A023951 | C181: I | D181: 256779415359 | E181: 45848 | F181: USD | G181: 4 | H181: - | I181: 353.88 | J181: C: ASCENDAS27 P: A023951 I 256779415359 | K181: 45878 | M181: - | N181: 45901 | O181: 59299170 | P181: 1 | Q181: 45930 | R181: 230 | T181: Ascendas Panvel FTWZ Private Limited | U181: 0
A182: A023951 | B182: A023951 | C182: I | D182: 256779415381 | E182: 45848 | F182: USD | G182: 1.2 | H182: - | I182: 106.16 | J182: C: ASCENDAS27 P: A023951 I 256779415381 | K182: 45878 | M182: - | N182: 45901 | O182: 59299171 | P182: 1 | Q182: 45930 | R182: 230 | T182: Ascendas Panvel FTWZ Private Limited | U182: 0
A183: A023951 | B183: A023951 | C183: I | D183: 256779415391 | E183: 45848 | F183: USD | G183: 16.4 | H183: - | I183: 1450.91 | J183: C: ASCENDAS27 P: A023951 I 256779415391 | K183: 45878 | M183: - | N183: 45901 | O183: 59299173 | P183: 1 | Q183: 45930 | R183: 230 | T183: Ascendas Panvel FTWZ Private Limited | U183: 0
A184: A023951 | B184: A023951 | C184: I | D184: 256779415358 | E184: 45848 | F184: USD | G184: 1.92 | H184: - | I184: 169.86 | J184: C: ASCENDAS27 P: A023951 I 256779415358 | K184: 45878 | M184: - | N184: 45901 | O184: 59299174 | P184: 1 | Q184: 45930 | R184: 230 | T184: Ascendas Panvel FTWZ Private Limited | U184: 0
A185: A023951 | B185: A023951 | C185: I | D185: 256779415305 | E185: 45848 | F185: USD | G185: 0.6 | H185: - | I185: 53.08 | J185: C: ASCENDAS27 P: A023951 I 256779415305 | K185: 45878 | M185: - | N185: 45901 | O185: 59299176 | P185: 1 | Q185: 45930 | R185: 230 | T185: Ascendas Panvel FTWZ Private Limited | U185: 0
A186: A023951 | B186: A023951 | C186: I | D186: 256779415345 | E186: 45848 | F186: USD | G186: 0.5 | H186: - | I186: 44.24 | J186: C: ASCENDAS27 P: A023951 I 256779415345 | K186: 45878 | M186: - | N186: 45901 | O186: 59299178 | P186: 1 | Q186: 45930 | R186: 230 | T186: Ascendas Panvel FTWZ Private Limited | U186: 0
... A315: A023951 | B315: A023951 | C315: I | D315: 256779416137 | E315: 45877 | F315: USD | G315: 1.1 | H315: - | I315: 95.29 | J315: C: ASCENDAS27 P: A023951 I 256779416137 | K315: 45907 | M315: - | N315: 45962 | O315: 63135770 | P315: 1 | Q315: 45985 | R315: 230 | T315: Ascendas Panvel FTWZ Private Limited | U315: 0
A316: A023951 | B316: A023951 | C316: I | D316: 256779413972 | E316: 45810 | F316: INR | G316: - | H316: - | I316: 6 | J316: C: ASCENDAS27 P: A023951 I 256779413972 | K316: 45840 | M316: - | N316: 45962 | O316: 63776333 | P316: 1 | Q316: 45991 | R316: 230 | T316: Ascendas Panvel FTWZ Private Limited | U316: 0
A317: A023951 | B317: A023951 | C317: I | D317: 256779413148 | E317: 45787 | F317: INR | G317: - | H317: - | I317: 88 | J317: C: ASCENDAS27 P: A023951 I 256779413148 | K317: 45817 | M317: - | N317: 45962 | O317: 63776339 | P317: 1 | Q317: 45991 | R317: 230 | T317: Ascendas Panvel FTWZ Private Limited | U317: 0
A318: A023951 | B318: A023951 | C318: I | D318: 256779413146 | E318: 45787 | F318: INR | G318: - | H318: - | I318: 4000 | J318: C: ASCENDAS27 P: A023951 I 256779413146 | K318: 45817 | M318: - | N318: 45962 | O318: 63776347 | P318: 1 | Q318: 45991 | R318: 230 | T318: Ascendas Panvel FTWZ Private Limited | U318: 0
A319: A023951 | B319: A023951 | C319: I | D319: 256779413147 | E319: 45787 | F319: INR | G319: - | H319: - | I319: 160 | J319: C: ASCENDAS27 P: A023951 I 256779413147 | K319: 45817 | M319: - | N319: 45962 | O319: 63776349 | P319: 1 | Q319: 45991 | R319: 230 | T319: Ascendas Panvel FTWZ Private Limited | U319: 0
A320: A023951 | B320: A023951 | C320: I | D320: 246779411789 | E320: 45733 | F320: USD | G320: 8.56 | H320: - | I320: 745.08 | J320: C: ASCENDAS27 P: A023951 I 246779411789 | K320: 45763 | M320: - | N320: 45962 | O320: 63776358 | P320: 1 | Q320: 45991 | R320: 230 | T320: Ascendas Panvel FTWZ Private Limited | U320: 0
A321: A023951 | B321: A023951 | C321: I | D321: 256779413250 | E321: 45787 | F321: USD | G321: 8.47 | H321: - | I321: 723.12 | J321: C: ASCENDAS27 P: A023951 I 256779413250 | K321: 45817 | M321: - | N321: 45962 | O321: 63776370 | P321: 1 | Q321: 45991 | R321: 230 | T321: Ascendas Panvel FTWZ Private Limited | U321: 0
A322: A023951 | B322: A023951 | C322: I | D322: 256779413240 | E322: 45787 | F322: USD | G322: 8.48 | H322: - | I322: 723.98 | J322: C: ASCENDAS27 P: A023951 I 256779413240 | K322: 45817 | M322: - | N322: 45962 | O322: 63776371 | P322: 1 | Q322: 45991 | R322: 230 | T322: Ascendas Panvel FTWZ Private Limited | U322: 0
A323: A023951 | B323: A023951 | C323: I | D323: 256779412776 | E323: 45771 | F323: USD | G323: 12.65 | H323: - | I323: 1084.45 | J323: C: ASCENDAS27 P: A023951 I 256779412776 | K323: 45801 | M323: - | N323: 45962 | O323: 63776375 | P323: 1 | Q323: 45991 | R323: 230 | T323: Ascendas Panvel FTWZ Private Limited | U323: 0
A324: A023951 | B324: A023951 | C324: I | D324: 246779411730 | E324: 45733 | F324: USD | G324: 0.23 | H324: - | I324: 20.02 | J324: C: ASCENDAS27 P: A023951 I 246779411730 | K324: 45763 | M324: - | N324: 45962 | O324: 63776378 | P324: 1 | Q324: 45991 | R324: 230 | T324: Ascendas Panvel FTWZ Private Limited | U324: 0
A325: A023951 | B325: A023951 | C325: I | D325: 256779414431 | E325: 45826 | F325: USD | G325: 1.05 | H325: - | I325: 89.32 | J325: C: ASCENDAS27 P: A023951 I 256779414431 | K325: 45856 | M325: - | N325: 45962 | O325: 63776383 | P325: 1 | Q325: 45991 | R325: 230 | T325: Ascendas Panvel FTWZ Private Limited | U325: 0
A326: A023951 | B326: A023951 | C326: I | D326: 256779413931 | E326: 45810 | F326: USD | G326: 7.9 | H326: - | I326: 672.01 | J326: C: ASCENDAS27 P: A023951 I 256779413931 | K326: 45840 | M326: - | N326: 45962 | O326: 63776391 | P326: 1 | Q326: 45991 | R326: 230 | T326: Ascendas Panvel FTWZ Private Limited | U326: 0
A327: A023951 | B327: A023951 | C327: I | D327: 256779413908 | E327: 45805 | F327: USD | G327: 64.02 | H327: - | I327: 5465.67 | J327: C: ASCENDAS27 P: A023951 I 256779413908 | K327: 45835 | M327: - | N327: 45962 | O327: 63776634 | P327: 1 | Q327: 45991 | R327: 230 | T327: Ascendas Panvel FTWZ Private Limited | U327: 0
A328: A023951 | B328: A023951 | C328: I | D328: 256779417971 | E328: 45935 | F328: USD | G328: 1.9 | H328: - | I328: 168.45 | J328: C: ASCENDAS27 P: A023951 I 256779417971 | K328: 45965 | M328: - | N328: 45992 | O328: 64690005 | P328: 1 | Q328: 46005 | R328: 230 | T328: Ascendas Panvel FTWZ Private Limited | U328: 0
A329: A023951 | B329: A023951 | C329: I | D329: 256779411465 | E329: 45762 | F329: USD | G329: 0.65 | H329: - | I329: 55.72 | J329: C: ASCENDAS27 P: A023951 I 256779411465 | K329: 45792 | M329: - | N329: 45992 | O329: 64790171 | P329: 1 | Q329: 46006 | R329: 230 | T329: Ascendas Panvel FTWZ Private Limited | U329: 0
A330: A023951 | B330: A023951 | C330: I | D330: 256779417317 | E330: 45904 | F330: USD | G330: 3.42 | H330: - | I330: 299.77 | J330: C: ASCENDAS27 P: A023951 I 256779417317 | K330: 45934 | M330: - | N330: 45992 | O330: 64790190 | P330: 1 | Q330: 46006 | R330: 230 | T330: Ascendas Panvel FTWZ Private Limited | U330: 0
A331: A023951 | B331: A023951 | C331: I | D331: 256779416030 | E331: 45870 | F331: USD | G331: 1.02 | H331: - | I331: 88.36 | J331: C: ASCENDAS27 P: A023951 I 256779416030 | K331: 45900 | M331: - | N331: 45992 | O331: 64790199 | P331: 1 | Q331: 46006 | R331: 230 | T331: Ascendas Panvel FTWZ Private Limited | U331: 0
...

Sheet Customer P matching
B2: Item# | C2: Item Date | D2: FC Amount | E2: LC Amount | F2: Particular | G2: Due Date | H2: CCY | I2: VC Period | J2: VC Seq | K2: VC Date | L2: Tx. Type | M2: Company Code
B3: 256779413908 | C3: 45805 | D3: 0 | E3: -11858.12 | F3: C: ASCENDAS27 P: Matching | G3: 27/06/2025 | H3: USD | I3: 45962 | J3: 66 | K3: 30/11/2025 | L3: 271 | M3: IN89
B4: 256779415989 | C4: 45863 | D4: 0 | E4: -664.99 | F4: C: ASCENDAS27 P: Matching | G4: 24/08/2025 | H4: USD | I4: 45931 | J4: 82 | K4: 31/10/2025 | L4: 271 | M4: IN89
B5: 256779416007 | C5: 45863 | D5: 0 | E5: -934.03 | F5: C: ASCENDAS27 P: Matching | G5: 24/08/2025 | H5: USD | I5: 45931 | J5: 84 | K5: 31/10/2025 | L5: 271 | M5: IN89
B6: 256779412776 | C6: 45771 | D6: 0 | E6: -2124.59 | F6: C: ASCENDAS27 P: Matching | G6: 24/05/2025 | H6: USD | I6: 45962 | J6: 58 | K6: 30/11/2025 | L6: 271 | M6: IN89
B7: 256779417801 | C7: 45922 | D7: 0 | E7: -2799.24 | F7: C: ASCENDAS27 P: Matching | G7: 22/10/2025 | H7: USD | I7: 45931 | J7: 64 | K7: 31/10/2025 | L7: 271 | M7: IN89
B8: 256779412524 | C8: 45769 | D8: 0 | E8: -9.39 | F8: C: ASCENDAS27 P: Matching | G8: 22/05/2025 | H8: USD | I8: 45809 | J8: 14 | K8: 30/06/2025 | L8: 271 | M8: IN89
B9: 256779412529 | C9: 45769 | D9: 0 | E9: -7.61 | F9: C: ASCENDAS27 P: Matching | G9: 22/05/2025 | H9: USD | I9: 45809 | J9: 16 | K9: 30/06/2025 | L9: 271 | M9: IN89
B10: 256779412536 | C10: 45769 | D10: 0 | E10: -9.53 | F10: C: ASCENDAS27 P: Matching | G10: 22/05/2025 | H10: USD | I10: 45809 | J10: 18 | K10: 30/06/2025 | L10: 271 | M10: IN89
B11: 256779412537 | C11: 45769 | D11: 0 | E11: -104.86 | F11: C: ASCENDAS27 P: Matching | G11: 22/05/2025 | H11: USD | I11: 45809 | J11: 20 | K11: 30/06/2025 | L11: 271 | M11: IN89
B12: 256779412579 | C12: 45769 | D12: 0 | E12: -14.83 | F12: C: ASCENDAS27 P: Matching | G12: 22/05/2025 | H12: USD | I12: 45809 | J12: 22 | K12: 30/06/2025 | L12: 271 | M12: IN89
B13: 256779412586 | C13: 45769 | D13: 0 | E13: -13.25 | F13: C: ASCENDAS27 P: Matching | G13: 22/05/2025 | H13: USD | I13: 45809 | J13: 24 | K13: 30/06/2025 | L13: 271 | M13: IN89
B14: 256779412563 | C14: 45769 | D14: 0 | E14: -6.94 | F14: C: ASCENDAS27 P: Matching | G14: 22/05/2025 | H14: USD | I14: 45809 | J14: 48 | K14: 30/06/2025 | L14: 271 | M14: IN89
... B57: 256779417597 | C57: 45918 | D57: 0 | E57: -621.04 | F57: C: ASCENDAS27 P: Matching | G57: 18/10/2025 | H57: USD | I57: 45931 | J57: 68 | K57: 31/10/2025 | L57: 271 | M57: IN89
B58: 256779417580_D | C58: 45918 | D58: 0 | E58: -718.94 | F58: C: ASCENDAS27 P: Matching | G58: 18/10/2025 | H58: USD | I58: 46023 | J58: 104 | K58: 31/01/2026 | L58: 271 | M58: IN89
B59: 256779415442 | C59: 45856 | D59: 0 | E59: -3.53 | F59: C: ASCENDAS27 P: Matching | G59: 17/08/2025 | H59: USD | I59: 45931 | J59: 66 | K59: 31/10/2025 | L59: 271 | M59: IN89
B60: 256779415426 | C60: 45856 | D60: 0 | E60: -1030.68 | F60: C: ASCENDAS27 P: Matching | G60: 17/08/2025 | H60: USD | I60: 45931 | J60: 70 | K60: 31/10/2025 | L60: 271 | M60: IN89
B61: 256779415517 | C61: 45856 | D61: 0 | E61: -258.92 | F61: C: ASCENDAS27 P: Matching | G61: 17/08/2025 | H61: USD | I61: 45931 | J61: 72 | K61: 31/10/2025 | L61: 271 | M61: IN89
B62: 256779415453 | C62: 45856 | D62: 0 | E62: -650.84 | F62: C: ASCENDAS27 P: Matching | G62: 17/08/2025 | H62: USD | I62: 45931 | J62: 74 | K62: 31/10/2025 | L62: 271 | M62: IN89
B63: 256779415474 | C63: 45856 | D63: 0 | E63: -1349.32 | F63: C: ASCENDAS27 P: Matching | G63: 17/08/2025 | H63: USD | I63: 45931 | J63: 76 | K63: 31/10/2025 | L63: 271 | M63: IN89
B64: 256779414431 | C64: 45826 | D64: 0 | E64: -209.97 | F64: C: ASCENDAS27 P: Matching | G64: 18/07/2025 | H64: USD | I64: 45962 | J64: 60 | K64: 30/11/2025 | L64: 271 | M64: IN89
B65: 246779411973 | C65: 45733 | D65: 0 | E65: 439.66 | F65: C: ASCENDAS27 P: Matching | G65: 16/04/2025 | H65: USD | I65: 45809 | J65: 4 | K65: 30/06/2025 | L65: 271 | M65: IN89
B66: 246779412033 | C66: 45733 | D66: 0 | E66: 23.13 | F66: C: ASCENDAS27 P: Matching | G66: 16/04/2025 | H66: USD | I66: 45809 | J66: 6 | K66: 30/06/2025 | L66: 271 | M66: IN89
B67: 246779412047 | C67: 45733 | D67: 0 | E67: 28.93 | F67: C: ASCENDAS27 P: Matching | G67: 16/04/2025 | H67: USD | I67: 45809 | J67: 86 | K67: 30/06/2025 | L67: 271 | M67: IN89
B68: 246779411908 | C68: 45733 | D68: 0 | E68: 29.32 | F68: C: ASCENDAS27 P: Matching | G68: 16/04/2025 | H68: USD | I68: 45809 | J68: 94 | K68: 30/06/2025 | L68: 271 | M68: IN89
B69: 246779411730 | C69: 45733 | D69: 0 | E69: -23.64 | F69: C: ASCENDAS27 P: Matching | G69: 16/04/2025 | H69: USD | I69: 45962 | J69: 52 | K69: 30/11/2025 | L69: 271 | M69: IN89
B70: 246779411789 | C70: 45733 | D70: 0 | E70: -886.24 | F70: C: ASCENDAS27 P: Matching | G70: 16/04/2025 | H70: USD | I70: 45962 | J70: 54 | K70: 30/11/2025 | L70: 271 | M70: IN89
... B92: 256779411463 | C92: 45762 | D92: 0 | E92: -40.25 | F92: C: ASCENDAS27 P: Matching | G92: 15/05/2025 | H92: USD | I92: 46023 | J92: 50 | K92: 31/01/2026 | L92: 271 | M92: IN89
B93: 256779415389 | C93: 45937 | D93: 0 | E93: -31.68 | F93: C: ASCENDAS27 P: Matching | G93: 45908 | H93: USD | I93: 45901 | J93: 6 | K93: 30/09/2025 | L93: 271 | M93: IN89
B94: 256779415346 | C94: 45937 | D94: 0 | E94: -3.24 | F94: C: ASCENDAS27 P: Matching | G94: 45908 | H94: USD | I94: 45901 | J94: 8 | K94: 30/09/2025 | L94: 271 | M94: IN89
B95: 256779415350 | C95: 45937 | D95: 0 | E95: -4.17 | F95: C: ASCENDAS27 P: Matching | G95: 45908 | H95: USD | I95: 45901 | J95: 10 | K95: 30/09/2025 | L95: 271 | M95: IN89
B96: 256779415316 | C96: 45937 | D96: 0 | E96: -11.14 | F96: C: ASCENDAS27 P: Matching | G96: 45908 | H96: USD | I96: 45901 | J96: 12 | K96: 30/09/2025 | L96: 271 | M96: IN89
B97: 256779415355 | C97: 45937 | D97: 0 | E97: -3.97 | F97: C: ASCENDAS27 P: Matching | G97: 45908 | H97: USD | I97: 45901 | J97: 14 | K97: 30/09/2025 | L97: 271 | M97: IN89
B98: 256779415303 | C98: 45937 | D98: 0 | E98: -18.57 | F98: C: ASCENDAS27 P: Matching | G98: 45908 | H98: USD | I98: 45901 | J98: 18 | K98: 30/09/2025 | L98: 271 | M98: IN89
B99: 256779415333 | C99: 45937 | D99: 0 | E99: -4.17 | F99: C: ASCENDAS27 P: Matching | G99: 45908 | H99: USD | I99: 45901 | J99: 20 | K99: 30/09/2025 | L99: 271 | M99: IN89
B100: 256779415304 | C100: 45937 | D100: 0 | E100: -5.57 | F100: C: ASCENDAS27 P: Matching | G100: 45908 | H100: USD | I100: 45901 | J100: 22 | K100: 30/09/2025 | L100: 271 | M100: IN89
B101: 256779415377 | C101: 45937 | D101: 0 | E101: -9.29 | F101: C: ASCENDAS27 P: Matching | G101: 45908 | H101: USD | I101: 45901 | J101: 24 | K101: 30/09/2025 | L101: 271 | M101: IN89
B102: 256779415298 | C102: 45937 | D102: 0 | E102: -4.46 | F102: C: ASCENDAS27 P: Matching | G102: 45908 | H102: USD | I102: 45901 | J102: 28 | K102: 30/09/2025 | L102: 271 | M102: IN89
B103: 256779415380 | C103: 45937 | D103: 0 | E103: -37.14 | F103: C: ASCENDAS27 P: Matching | G103: 45908 | H103: USD | I103: 45901 | J103: 30 | K103: 30/09/2025 | L103: 271 | M103: IN89
B104: 256779415341 | C104: 45937 | D104: 0 | E104: -2.78 | F104: C: ASCENDAS27 P: Matching | G104: 45908 | H104: USD | I104: 45901 | J104: 32 | K104: 30/09/2025 | L104: 271 | M104: IN89
... B316: 256779413931 | C316: 45694 | D316: 0 | E316: -1584.45 | F316: C: ASCENDAS27 P: Matching | G316: 45695 | H316: USD | I316: 45962 | J316: 62 | K316: 30/11/2025 | L316: 271 | M316: IN89
B317: 256779416028 | C317: 45665 | D317: 0 | E317: -7426.8 | F317: C: ASCENDAS27 P: Matching | G317: 31/08/2025 | H317: USD | I317: 45992 | J317: 54 | K317: 31/12/2025 | L317: 271 | M317: IN89
B318: 256779416029 | C318: 45665 | D318: 0 | E318: -297.06 | F318: C: ASCENDAS27 P: Matching | G318: 31/08/2025 | H318: USD | I318: 45992 | J318: 56 | K318: 31/12/2025 | L318: 271 | M318: IN89
B319: 256779416030 | C319: 45665 | D319: 0 | E319: -163.38 | F319: C: ASCENDAS27 P: Matching | G319: 31/08/2025 | H319: USD | I319: 45992 | J319: 58 | K319: 31/12/2025 | L319: 271 | M319: IN89

Sheet Pivot
A3: Sum of Company Code Currency Value | D3: Document Type
A4: Years | B4: Quarters | C4: Document Date | D4: DA | E4: DG | F4: DR | G4: DY | H4: DZ | I4: XC
A5: 2025 | B5: Qtr1 | C5: Feb | F5: 1514515.3 | I5: 0
C6: Mar | F6: 1933380.6
B7: Qtr2 | C7: Apr | D7: 0 | F7: 2087965.7
C8: May | E8: -595574.41 | F8: 1044919.9
C9: Jun | F9: 1761603.8
B10: Qtr3 | C10: Jul | E10: -1464659.3 | F10: 2492881.5 | H10: 0
C11: Aug | E11: -170239.97 | F11: 1305423
C12: Sep | F12: 1564779.1 | G12: 1238.22
B13: Qtr4 | C13: Oct | E13: -8361.37 | F13: 1113806.7 | H13: -5850755.1
C14: Nov | E14: -405590.02 | F14: 1574052.7 | H14: -1920293.1
C15: Dec | F15: 282835.01
A16: 2026 | B16: Qtr1 | C16: Jan | E16: -52265.33 | F16: 831546.81 | H16: -719881.09

Sheet 26AS Reco
