Workbook

Sheet Summary
A3: Reconciliation of Ledger as on 31st January 2026
A4: Particulars | B4: Amount in USD
A5: Balance as per Ashland | B5: ='Customer Data'!F192 -> 0
A6: Add: Invoices not recorded in customer books | B6: ='Invoices Not in customer books'!F30 -> 34851.14
A7: Less: Invoice not recorded in Ascendus Books | B7: ='invoice not in Ascendus Books'!E41 -> 0
A8: Add: CN not recorded in Ascendus Books | B8: ='CN not in Ascendus Books'!F2 -> 16009
A9: Add: Diffrence in Payment recorded in both books | B9: ='Payment Reco'!L14 -> 44897.47
A10: Add: Diffrence in Invoice Amount in both Books | B10: ='Diffrence in Customer Books'!Q11 -> 49.5
A11: Less: Duplicate CN in Ascendus Books | B11: ='Duplicate CN in Ascendus Books'!F2 -> -131.74
A12: Derived balance | B12: =SUM(B5:B11) -> 95675.37
A13: Balance as per Ascent | B13: ='Ascendus data'!T296 -> 95447.7
A15: Difference | B15: =B12-B13 -> 227.67

Sheet Invoice No Ref
A1: Ascendus Ledger | F1: Customer Ledger
A2: Document Type | B2: Document Date | C2: Reference | D2: Document Currency Value | E2: Text | F2: Document Type | G2: Document Number | H2: Document Date | I2: Reference | J2: Amount in doc. curr. | K2: Text
A3: DR | B3: 45763 | C3: 256779411831 | D3: 23.6 | E3: CY - CY charges for Dec 2024 | F3: KR | G3: 1900008140 | H3: 45702 | I3: 6779IV124000270 | J3: -23.6 | K3: CY Movement Charges-Dec24
A4: DR | B4: 45736 | C4: 246779414629 | D4: 23.6 | E4: CY-MOVEMENT CHARGES for Nov 2024 | F4: KR | G4: 1900008127 | H4: 45702 | I4: 6779IV124000261 | J4: -23.6 | K4: CY Movement Charges-Nov24
A5: DR | B5: 45737 | C5: 246779414251 | D5: 28.32 | E5: LCL Movement Charges for Oct 2024 | F5: KR | G5: 1900008134 | H5: 45702 | I5: 6779IV124000251 | J5: -28.32 | K5: LCL Charges-Oct24
A6: DR | B6: 45737 | C6: 246779414252 | D6: 70.8 | E6: CY-MOVEMENT CHARGES for Oct 2024 | F6: KR | G6: 1900008133 | H6: 45702 | I6: 6779IV124000250 | J6: -70.8 | K6: CY Destuff Charges-Oct24
A7: DR | B7: 45729 | C7: 246779411330 | D7: 85 | E7: Scanning Charges for the month of December, 2024 | F7: KR | G7: 1900008142 | H7: 45702 | I7: 6779IV124000273 | J7: -85 | K7: Scanning Charges- Dec24
A8: DR | B8: 45736 | C8: 246779414554 | D8: 94.4 | E8: CY-MOVEMENT CHARGES for Oct 2024 | F8: KR | G8: 1900008136 | H8: 45702 | I8: 6779IV124000253 | J8: -94.4 | K8: CY Movement Charges-oct24
A9: DR | B9: 45736 | C9: 246779414343 | D9: 118 | E9: CY-MOVEMENT CHARGES for Nov 2024 | F9: KR | G9: 1900008125 | H9: 45702 | I9: 6779IV124000258 | J9: -118 | K9: CY Destuff Charges-Nov24
A10: DR | B10: 45736 | C10: 246779414424 | D10: 118 | E10: Cy-WH Destuff charges for Jan 2025 | F10: KR | G10: 1900008144 | H10: 45702 | I10: 6779IV124000276 | J10: -118 | K10: CY Destuff Charges-Jan25
A11: DR | B11: 45729 | C11: 246779411319 | D11: 120 | E11: Scanning Charges for the month of November, 2024 | F11: KR | G11: 1900008129 | H11: 45702 | I11: 6779IV124000264 | J11: -120 | K11: Scanning Charges-Nov24
A12: DR | B12: 45729 | C12: 246779411305 | D12: 135 | E12: Scanning Charges for the month of October, 2024 | F12: KR | G12: 1900008124 | H12: 45702 | I12: 6779IV124000256 | J12: -135 | K12: Scanning Charges-Oct24
A13: DR | B13: 45763 | C13: 256779411746 | D13: 141.6 | E13: Cy-WH Destuff charges for Dec 2024 | F13: KR | G13: 1900008130 | H13: 45702 | I13: 6779IV124000267 | J13: -141.6 | K13: CY Destuff Charges-Dec24
A14: DR | B14: 45736 | C14: 246779414079 | D14: 169.92 | E14: LCL charges for Sep 2024 | F14: KR | G14: 1900008117 | H14: 45702 | I14: 6779IV124000244 | J14: -169.92 | K14: LCL Charges-Sep24
... A38: DR | B38: 45734 | C38: 246779412401 | D38: 23761.19 | E38: Storage charges for OCT 2024 | F38: RE | G38: 5100012795 | H38: 45702 | I38: 6779IV124000249 | J38: -23761.19 | K38: Storage Charges Oct24
A39: DR | B39: 45736 | C39: 246779413820 | D39: 354 | E39: Scanning Charges for the month of Jan 2025 | F39: KR | H39: 45702 | I39: 6779IV124000285 | J39: -200 | K39: Scanning Charges-Jan25

Sheet Payment Reco
A1: As Per Customer ledger | E1: As Per Bank Details | J1: As per Ascendus Ledger
A2: Document Date | B2: Reference | C2: Document currency | D2: Amount in doc. curr. | E2: Customer Code | F2: Payment Date | G2: Currency | H2: Recd Amount | I2: UTR Details | J2: Clearing Doc No | K2: Amount | L2: Difference | M2: Remarks
A3: 45751 | B3: Payment | C3: USD | D3: 123978.28 | E3: 100222426 | F3: 45751 | G3: USD | H3: 123953.28 | I3: 2.0250403e+15 | K3: -123953.28 | L3: =K3+D3 -> 25 | M3: Difference Due to Bank Charges
A4: 46097 | B4: Payment | C4: USD | D4: 44872.17 | E4: 100222426 | F4: 46097 | G4: USD | H4: 44847.17 | I4: T54SWIC292175 | L4: =K4+D4 -> 44872.17 | M4: Payment Not in Books
A5: 46015 | B5: Payment | C5: USD | D5: 37332.98 | E5: 100222426 | F5: 46015 | G5: USD | H5: 37307.98 | I5: T54SWIC284726 | J5: 1400002336 | K5: -37332.98 | L5: =K5+D5 -> 0
A6: 45884 | B6: Payment | C6: USD | D6: 34635.14 | E6: 100222426 | F6: 45887 | G6: USD | H6: 34610.14 | I6: 2.0250814e+15 | J6: 1400002466 | K6: -34635.14 | L6: =K6+D6 -> 0
A7: 45925 | B7: Payment | C7: USD | D7: 29536.15 | E7: 100222426 | F7: 45925 | G7: USD | H7: 29511.15 | I7: 2.0250924e+15 | J7: 1400002445 | K7: -29535.85 | L7: =K7+D7 -> 0.3
A8: 45975 | B8: Payment | C8: USD | D8: 22973.48 | E8: 100222426 | F8: 45975 | G8: USD | H8: 22948.48 | I8: 2.0251113e+15 | J8: 1400002448 | K8: -22973.48 | L8: =K8+D8 -> 0
A9: 45833 | B9: Payment | C9: USD | D9: 19783.53 | E9: 100222426 | F9: 45833 | G9: USD | H9: 19758.53 | I9: 2.0250624e+15 | J9: 1400000284 | K9: -19783.53 | L9: =K9+D9 -> 0
A10: 45824 | B10: Payment | C10: USD | D10: 19172.47 | E10: 100222426 | F10: 45824 | G10: USD | H10: 19147.47 | I10: 2.0250616e+15 | J10: 1400002443 | K10: -19172.47 | L10: =K10+D10 -> 0
A11: 45945 | B11: Payment | C11: USD | D11: 8309.99 | E11: 100222426 | F11: 45945 | G11: USD | H11: 8284.99 | I11: 2.0251014e+15 | J11: 1400002446 | K11: -8309.99 | L11: =K11+D11 -> 0
A12: 45915 | B12: Payment | C12: USD | D12: 6750.14 | E12: 100222426 | F12: 45915 | G12: USD | H12: 6725.14 | I12: 2.0250915e+15 | J12: 1400002444 | K12: -6750.14 | L12: =K12+D12 -> 0
A13: 45954 | B13: Payment | C13: USD | D13: 79.94 | E13: 100222426 | F13: 45954 | G13: USD | H13: 79.94 | I13: 2.0251023e+15 | J13: 1400002447 | K13: -79.94 | L13: =K13+D13 -> 0
L14: =SUM(L3:L13) -> 44897.47

Sheet Invoices Not in customer books
A3: Document Number | B3: Document Type | C3: Document Date | D3: Reference | E3: Document Currency Key | F3: Document Currency Value | G3: Text
A4: 1800012797 | B4: DR | C4: 45920 | D4: 256779417478 | E4: USD | F4: 1002.2 | G4: BOE handling charges
A5: 1800003244 | B5: DR | C5: 45735 | D5: 246779413111 | E5: USD | F5: 13.77 | G5: CMAU8274168-Port SSR Storage Jan 2025. Exch rate -
A6: 1800006828 | B6: DR | C6: 45763 | D6: 256779411719 | E6: USD | F6: 488.03 | G6: CY Longstanding Transportation chgs for 31 MAR 202
A7: 1800003944 | B7: DR | C7: 45736 | D7: 246779413973 | E7: USD | F7: 123.56 | G7: Detention Charges for JAN 2025 Exch. Rate 86.60
A8: 1800016238 | B8: DR | C8: 46028 | D8: 256779450410 | E8: USD | F8: 833.03 | G8: Empty Lolo Chgs - 01 - 31 DEC 25
A9: 1800003245 | B9: DR | C9: 45735 | D9: 246779413112 | E9: USD | F9: 13.77 | G9: GATU4442400-Port SSR Storage Jan 2025. Exch rate -
A10: 1800006854 | B10: DR | C10: 45763 | D10: 256779411745 | E10: USD | F10: 169.92 | G10: Loose Unloading charges for Dec 2024
A11: 1800003241 | B11: DR | C11: 45735 | D11: 246779413108 | E11: USD | F11: 78.12 | G11: ONEU1598927-Port SSR Shifting Jan 2025. Exch rate
A12: 1800003242 | B12: DR | C12: 45735 | D12: 246779413109 | E12: USD | F12: 166.09 | G12: ONEU1598927-Port SSR Storage Jan 2025. Exch rate -
A13: 1800003243 | B13: DR | C13: 45735 | D13: 246779413110 | E13: USD | F13: 76.72 | G13: ONEU1598927-Port SSR Storage Jan 2025. Exch rate -
A14: 1800016374 | B14: DR | C14: 46034 | D14: 256779450541 | E14: USD | F14: 1568.64 | G14: Outbound chgs - 16 - 31 Dec 25
A15: 1800013204 | B15: DR | C15: 45924 | D15: 256779417820 | E15: USD | F15: 131.74 | G15: Port SSR Charges - Shifting for Aug to Dec,24. Exc
... A29: 1800017223 | B29: DR | C29: 46059 | D29: 256779451053 | E29: USD | F29: 27.18 | G29: Weighment -1-15 Oct 2025
F30: =SUM(F4:F29) -> 34851.14

Sheet CN not in Ascendus Books
A1: Document Type | B1: Document Number | C1: Document Date | D1: Reference | E1: Document currency | F1: Amount in doc. curr. | G1: Text
A2: KG | B2: 1700001171 | C2: 45729 | D2: ASCEN20250102 | E2: USD | F2: 16009 | G2: CN against detention-Aug24-Dec24

Sheet Sheet1
A1: Text | B1: Reference | C1: Sum of Document Currency Value
A2: BOE handling charges | B2: 256779417478 | C2: 1002.2
A3: CMAU8274168-Port SSR Storage Jan 2025. Exch rate - | B3: 246779413111 | C3: 13.77
A4: CY Destuff Charges August 2024 | B4: 256779410983 | C4: 392.35
B5: 256779410984 | C5: 200.6
B6: 256779410985 | C6: 106.2
B7: 256779410986 | C7: 82.6
B8: 256779410988 | C8: 330.4
B9: 256779410989 | C9: 82.6
B10: 256779410990 | C10: 194.7
A11: CY Longstanding Transportation chgs for 31 MAR 202 | B11: 256779411719 | C11: 488.03
A12: Detention Charges for JAN 2025 Exch. Rate 86.60 | B12: 246779413973 | C12: 123.56
A13: Empty Lolo Chgs - 01 - 31 DEC 25 | B13: 256779450410 | C13: 833.03
A14: GATU4442400-Port SSR Storage Jan 2025. Exch rate - | B14: 246779413112 | C14: 13.77
A15: Inbound Handling charges for Jan 2025 | B15: 246779414012 | C15: 72.89
B16: 246779414013 | C16: 81.04
B17: 246779414419 | C17: 1003.1
A18: Loose Unloading charges for Dec 2024 | B18: 256779411745 | C18: 169.92
A19: ONEU1598927-Port SSR Shifting Jan 2025. Exch rate | B19: 246779413108 | C19: 78.12
A20: ONEU1598927-Port SSR Storage Jan 2025. Exch rate - | B20: 246779413109 | C20: 166.09
B21: 246779413110 | C21: 76.72
A22: Outbound chgs - 16 - 31 Dec 25 | B22: 256779450541 | C22: 1568.64
A23: Outbound Handling Charges Aug 2024 | B23: 256779411213 | C23: 66.08
B24: 256779411214 | C24: 11.8
B25: 256779411215 | C25: 46.87
B26: 256779411216 | C26: 91.45
B27: 256779411217 | C27: 91.45
B28: 256779411218 | C28: 110.7
B29: 256779411219 | C29: 35.4
B30: 256779411220 | C30: 44.25
B31: 256779411221 | C31: 2.95
B32: 256779411222 | C32: 105.43
B33: 256779411223 | C33: 85.55
B34: 256779411224 | C34: 54.47
B35: 256779411225 | C35: 66
... B43: 256779411233 | C43: 20.96
A44: Outbound Handling charges for Jan 2025 | B44: 246779414704 | C44: 768.32
B45: 246779414803 | C45: 17.7
B46: 246779414804 | C46: 109.15
B47: 246779414805 | C47: 8.85
B48: 246779414806 | C48: 203.55
B49: 246779414807 | C49: 9.4
A50: Port SSR Charges - Shifting for Aug to Dec,24. Exc | B50: 256779417820 | C50: 131.74
A51: PORT SSR Chgs Apr to June 25 | B51: 256779415415 | C51: 340.75
A52: PORT SSR Chgs Dec 25 | B52: 256779450428 | C52: 832.95
A53: Storage -WH 09- 1-31 DEC 25 | B53: 256779450686 | C53: 12105.53
B54: 256779450687 | C54: 7220.11
A55: Transportation In Charges August 2024 | B55: 256779410987 | C55: 223.67
A56: Transportation In Chgs - 16 - 31 Dec 25 | B56: 256779450460 | C56: 587.32
B57: 256779450509 | C57: 7819.18
A58: Transportation Inbound charges for Dec 2024 | B58: 256779410206 | C58: 346.96
A59: VAS -1-15 Oct 2025 | B59: 256779451039 | C59: 59.58
A60: VAS - Weighment-1-15 Jan 2026 | B60: 256779451016 | C60: 26.61
A61: VAS- 1-31 Aug-24, | B61: 256779414841 | C61: 165.16
A62: VAS 16-31 May 25 Ex.85.48 | B62: 256779415973 | C62: 448.06
A63: VAS Activity - Jan 25, Ex Rate. 86.64 | B63: 256779411994 | C63: 146.81
A64: VAS Activity Charges for the month of December, 24 | B64: 246779411997 | C64: 23.36
B65: 246779411998 | C65: 25.69
B66: 246779411999 | C66: 6.42
A67: VAS Activity Charges for the month of November, 24 | B67: 246779411865 | C67: 17.75
B68: 246779411866 | C68: 17.75
B69: 246779411867 | C69: 23.67
B70: 246779411868 | C70: 14.2
B71: 246779411869 | C71: 11.84
B72: 246779411870 | C72: 1.18
B73: 246779411871 | C73: 17.75
B74: 246779411872 | C74: 18.94
B75: 246779411873 | C75: 16.57
A76: VAS Activity Charges for the month of October, 24 | B76: 246779411658 | C76: 149.84
B77: 246779411659 | C77: 17.84
B78: 246779411660 | C78: 11.89
B79: 246779411661 | C79: 0.95
B80: 246779411662 | C80: 6.54
B81: 246779411663 | C81: 66.6
A82: VAS Activity Charges for the month of September, 2 | B82: 246779411543 | C82: 17.9
B83: 246779411544 | C83: 17.9
B84: 246779411545 | C84: 38.19
A85: VAS DEC 25 -1-15 | B85: 256779450142 | C85: 69.28
A86: VAS-1-15 Jan 2026 | B86: 256779451000 | C86: 285.36
A87: VAS-Dec 25 - 16-31 | B87: 256779450704 | C87: 16.68
A88: Weighment -1-15 Oct 2025 | B88: 256779451053 | C88: 27.18

Sheet Sheet2
A1: As Per Customer | G1: As per CL
A2: Document Type | B2: Document Number | C2: Document Date | D2: Reference | E2: Amount in doc. curr. | F2: Text | G2: Text | H2: Reference | I2: Sum of Document Currency Value
A3: KR | B3: 1900008119 | C3: 45702 | D3: 6779IV124000236 | E3: -236 | F3: CY Destuff Charges-Aug24 | G3: CY Destuff Charges August 2024 | H3: 256779410983 to 256779410990 | I3: 1389.45 | J3: =I3+E3 -> 1153.45 | K3: =J3/E3 -> -4.8875
A4: KR | B4: 1900008161 | C4: 45702 | D4: 6779IV124000279 | E4: -1100.39 | F4: Inbound Handling Charges-Jan25 | G4: Inbound Handling charges for Jan 2025 | H4: 246779414012/246779414013/246779414019 | I4: 1157.03 | J4: =I4+E4 -> 56.64 | K4: =J4/E4 -> -0.05147266
A5: KR | B5: 1900008165 | C5: 45702 | D5: 6779IV124000239 | E5: -1142.99 | F5: Outbound Handling Charges-Aug24 | G5: Outbound Handling Charges Aug 2024 | H5: 256779411213 To 256779411233 | I5: 1166.59 | J5: =I5+E5 -> 23.6 | K5: =J5/E5 -> -0.0206476
A6: KR | B6: 1900008160 | C6: 45702 | D6: 6779IV124000282 | E6: -1093.36 | F6: Outbound Handling Charges-Jan25 | G6: Outbound Handling charges for Jan 2025 | I6: 1116.97 | J6: =I6+E6 -> 23.61 | K6: =J6/E6 -> -0.021593986
A7: KR | B7: 1900008118 | C7: 45702 | D7: 6779IV124000235 | E7: -141.07 | F7: Transportation Inbound charges-Aug24 | G7: Transportation In Charges August 2024 | I7: 223.67 | J7: =I7+E7 -> 82.6 | K7: =J7/E7 -> -0.58552492
A8: KR | B8: 1900008150 | C8: 45702 | D8: 6779IV124000284 | E8: -219.71 | F8: VAS Activity Charges -Jan25 | G8: VAS Activity - Jan 25, Ex Rate. 86.64 | I8: 146.81 | J8: =I8+E8 -> -72.9 | K8: =J8/E8 -> 0.33180101
A9: KR | B9: 1900008141 | C9: 45702 | D9: 6779IV124000272 | E9: -54.67 | F9: VAS Activity Charges-Dec24 | G9: VAS Activity Charges for the month of December, 24 | I9: 55.47 | J9: =I9+E9 -> 0.8 | K9: =J9/E9 -> -0.014633254
A10: KR | B10: 1900008128 | C10: 45702 | D10: 6779IV124000263 | E10: -135.81 | F10: VAS Activity Charges-Nov24 | G10: VAS Activity Charges for the month of November, 24 | I10: 139.65 | J10: =I10+E10 -> 3.84 | K10: =J10/E10 -> -0.028274796
A11: KR | B11: 1900008137 | C11: 45702 | D11: 6779IV124000255 | E11: -245.49 | F11: VAS Activity Charges-Oct24 | G11: VAS Activity Charges for the month of October, 24 | I11: 253.66 | J11: =I11+E11 -> 8.17 | K11: =J11/E11 -> -0.033280378
A12: KR | B12: 1900008131 | C12: 45702 | D12: 6779IV124000247 | E12: -71.36 | F12: VAS Activity Charges-Sep24 | G12: VAS Activity Charges for the month of September, 2 | I12: 73.99 | J12: =I12+E12 -> 2.63 | K12: =J12/E12 -> -0.036855381
A13: KR | B13: 1900008121 | C13: 45702 | D13: 6779IV124000240 | E13: -165.16 | F13: VAS Activity Charges-Aug24 | G13: VAS- 1-31 Aug-24, | I13: 165.16 | J13: =I13+E13 -> 0 | K13: =J13/E13 -> 0

Sheet invoice not in Ascendus Books
A1: Document Type | B1: Document Number | C1: Document Date | D1: Reference | E1: Amount in doc. curr. | F1: Text
A2: KR | B2: 1900008146 | C2: 45702 | D2: 6779IV124000278 | E2: -226.56 | F2: LCL Charges-Jan25
A3: KR | B3: 1900008159 | C3: 45702 | D3: 6779IV124000237 | E3: -1236.05 | F3: Inbound Handling Charges-Aug24
A4: KR | B4: 1900008148 | C4: 45702 | D4: 6779IV124000281 | E4: -23.6 | F4: CY Movement Charges-Jan25
A5: KR | B5: 1900008120 | C5: 45702 | D5: 6779IV124000238 | E5: -23.6 | F5: CY Movement Charges-Aug24
E41: =SUM(E23:E40) -> 0

Sheet Duplicate CN in Ascendus Books
A1: Document Number | B1: Document Type | C1: Document Date | D1: Reference | E1: Document Currency Key | F1: Document Currency Value | G1: Company Code Currency Key | H1: Company Code Currency Value | I1: Text | J1: Clearing Document
A2: 1600002320 | B2: DG | C2: 45923 | D2: 246779413054 | E2: USD | F2: -131.74 | G2: INR | H2: -11420.71 | I2: Credit Note Raised against INV_246779413054

Sheet Diffrence in Customer Books
A1: Document Number | B1: Document Type | C1: Document Date | D1: Reference | E1: New Ref | F1: Document Currency Key | G1: Document Currency Value | H1: Vlookup | I1: Difference | J1: Text | K1: Document No | L1: Doc Type | M1: Date | N1: Difference invoice raised in Ascendus books | O1: Amount | P1: Particulars | Q1: Net Diffrence | R1: Remarks
A2: 1800003964 | B2: DR | C2: 45736 | D2: 246779413820 | E2: 6779IV124000285 | F2: USD | G2: 354 | H2: =_xlfn.XLOOKUP(E2,'Customer Data'!$D:$D,'Customer Data'!$H:$H,,0) -> -200 | I2: =G2+H2 -> 154 | J2: Scanning Charges for the month of Jan 2025 | Q2: =O2+I2 -> 154 | R2: UnderBooked in customer's Books
A3: 1800007300 | B3: DR | C3: 45768 | D3: 256779412191 | E3: 6779IV124000234 | F3: USD | G3: 19567.14 | H3: =_xlfn.XLOOKUP(E3,'Customer Data'!$D:$D,'Customer Data'!$H:$H,,0) -> -19671.64 | I3: =G3+H3 -> -104.5 | J3: Storage Charges for Aug 2024 | Q3: =O3+I3 -> -104.5 | R3: OverBooked in customer's Books
A4: 1800012322 | B4: DR | C4: 45904 | D4: 256779416958 | F4: USD | G4: 3624.71 | H4: =_xlfn.XLOOKUP(D4,'Customer Data'!$D:$D,'Customer Data'!$H:$H,,0) -> -6712.26 | I4: =G4+H4 -> -3087.55 | J4: WH 09- Storage - 16-31 Aug 25 | K4: 1800011946 | L4: DR | M4: 45889 | N4: 256779416698 | O4: 3087.55 | P4: Storage 1-15 Aug-25,WH-9 | Q4: =O4+I4 -> 0 | R4: Different invoice no in Ascendus books
A5: 1800012323 | B5: DR | C5: 45904 | D5: 256779416959 | F5: USD | G5: 2779.47 | H5: =_xlfn.XLOOKUP(D5,'Customer Data'!$D:$D,'Customer Data'!$H:$H,,0) -> -5587.13 | I5: =G5+H5 -> -2807.66 | J5: WH 09- Storage - 16-31 Aug 25 | K5: 1800011947 | L5: DR | M5: 45889 | N5: 256779416699 | O5: 2807.66 | P5: Storage 1-15 Aug-25,WH-9 | Q5: =O5+I5 -> 0 | R5: Different invoice no in Ascendus books
A6: 1800013655 | B6: DR | C6: 45936 | D6: 256779418216 | F6: USD | G6: 3984.09 | H6: =_xlfn.XLOOKUP(D6,'Customer Data'!$D:$D,'Customer Data'!$H:$H,,0) -> -8093.39 | I6: =G6+H6 -> -4109.3 | J6: Storage -WH 09- 16-30 Sep 25 | K6: 1800013001 | L6: DR | M6: 45918 | N6: 256779417627 | O6: 4109.3 | P6: Storage -WH 09- 1-15 Sep 25 | Q6: =O6+I6 -> 0 | R6: Different invoice no in Ascendus books
A7: 1800013656 | B7: DR | C7: 45936 | D7: 256779418217 | F7: USD | G7: 3863.82 | H7: =_xlfn.XLOOKUP(D7,'Customer Data'!$D:$D,'Customer Data'!$H:$H,,0) -> -6196.45 | I7: =G7+H7 -> -2332.63 | J7: Storage -WH 09- 16-30 Sep 25 | K7: 1800013002 | L7: DR | M7: 45918 | N7: 256779417628 | O7: 2332.63 | P7: Storage -WH 09- 1-15 Sep 25 | Q7: =O7+I7 -> 0 | R7: Different invoice no in Ascendus books
A8: 1800012498 | B8: DR | C8: 45904 | D8: 256779417102 | F8: USD | G8: 17.07 | H8: =_xlfn.XLOOKUP(D8,'Customer Data'!$D:$D,'Customer Data'!$H:$H,,0) -> -66.22 | I8: =G8+H8 -> -49.15 | J8: VAS -16-31 Aug 25 | K8: 1800012098 | L8: DR | M8: 45889 | N8: 256779416789 | O8: 49.15 | P8: VAS-Aug 25, 1-15 | Q8: =O8+I8 -> 0 | R8: Different invoice no in Ascendus books
A9: 1800013605 | B9: DR | C9: 45937 | D9: 256779418129 | F9: USD | G9: 82.72 | H9: =_xlfn.XLOOKUP(D9,'Customer Data'!$D:$D,'Customer Data'!$H:$H,,0) -> -122.94 | I9: =G9+H9 -> -40.22 | J9: VAS-16-30 Sept 25 | K9: 1800012828 | L9: DR | M9: 45917 | N9: 256779417462 | O9: 40.22 | P9: VAS -1-15 Sept-25 | Q9: =O9+I9 -> 0 | R9: Different invoice no in Ascendus books
A10: 1800008808 | B10: DR | C10: 45785 | D10: 256779413572 | F10: USD | G10: 5969.61 | H10: =_xlfn.XLOOKUP(D10,'Customer Data'!$D:$D,'Customer Data'!$H:$H,,0) -> -6237.23 | I10: =G10+H10 -> -267.62 | J10: Storage 16-30 April-25-WH09 | K10: 1800016812 | L10: DR | M10: 46036 | N10: 256779450748 | O10: 267.62 | P10: Storage -WH 09- 16-30 Apr 25 | Q10: =O10+I10 -> 0 | R10: Different invoice no in Ascendus books
Q11: =SUM(Q2:Q10) -> 49.5

Sheet Ascendus data
A1: Cleared Item | B1: Company Code | C1: Customer | D1: Customer Account: Name 1 | E1: Fiscal Year | F1: Posting period | G1: Posting Date | H1: Document Number | I1: Document Type | J1: Document Date | K1: Entry Date | L1: Document Header Text | M1: Reference | N1: G/L Account | O1: G/L Account: Short Text | P1: Special G/L Ind. | Q1: Posting Key | R1: New Ref | S1: Document Currency Key | T1: Document Currency Value | U1: Company Code Currency Key | V1: Company Code Currency Value | X1: Profit Center | Y1: Trading Partner No. | Z1: Assignment | AA1: Item | AB1: Vlookup | AC1: Difference | AD1: Text | AE1: Reference Key 1 | AF1: Reference Key 2 | AG1: Reference Key 3 | AH1: Baseline Payment Dte | AI1: Clearing Date | AJ1: Clearing Document
A2: Selected | B2: 6779 | C2: 100222426 | D2: ASHLAND SPECIALITY CHEMICAL | E2: 2025 | F2: 7 | G2: 45855 | H2: 1400000284 | I2: DZ | J2: 45855 | K2: 45855 | L2: 2025062400636248 | N2: 212100 | O2: Trade Debtors (Ctrl) | Q2: 15 | R2: =_xlfn.XLOOKUP(M2,'Invoice No Ref'!$C:$C,'Invoice No Ref'!$I:$I,,0) -> #N/A | S2: USD | T2: -3814.84 | U2: INR | V2: -331592.82 | W2: =V2/T2 -> 86.921816 | X2: 6779224500 | AA2: 4 | AB2: =_xlfn.XLOOKUP(R2,'Customer Data'!$D:$D,'Customer Data'!$F:$F,,0) -> #N/A | AD2: 2025062400636248 | AH2: 45855 | AI2: 45855 | AJ2: 1400000284
A3: Not Selected | B3: 6779 | C3: 100222426 | D3: ASHLAND SPECIALITY CHEMICAL | E3: 2025 | F3: 8 | G3: 45891 | H3: 1400000999 | I3: DZ | J3: 45891 | K3: 45891 | N3: 212100 | O3: Trade Debtors (Ctrl) | Q3: 15 | R3: =_xlfn.XLOOKUP(M3,'Invoice No Ref'!$C:$C,'Invoice No Ref'!$I:$I,,0) -> #N/A | S3: USD | T3: -123953.28 | U3: INR | V3: -10774245 | W3: =V3/T3 -> 86.92182 | X3: 6779220000 | AA3: 2 | AB3: =_xlfn.XLOOKUP(R3,'Customer Data'!$D:$D,'Customer Data'!$F:$F,,0) -> #N/A | AH3: 45891
A4: Selected | B4: 6779 | C4: 100222426 | D4: ASHLAND SPECIALITY CHEMICAL | E4: 2025 | F4: 7 | G4: 45855 | H4: 1400000284 | I4: DZ | J4: 45855 | K4: 45855 | L4: 2025062400636248 | N4: 212100 | O4: Trade Debtors (Ctrl) | Q4: 15 | R4: =_xlfn.XLOOKUP(M4,'Invoice No Ref'!$C:$C,'Invoice No Ref'!$I:$I,,0) -> #N/A | S4: USD | T4: -15968.69 | U4: INR | V4: -1388027.6 | W4: =V4/T4 -> 86.92182 | AA4: 3 | AB4: =_xlfn.XLOOKUP(R4,'Customer Data'!$D:$D,'Customer Data'!$F:$F,,0) -> #N/A | AD4: 2025062400636248 | AH4: 45855 | AI4: 45855 | AJ4: 1400000284
A5: Selected | B5: 6779 | C5: 100222426 | D5: ASHLAND SPECIALITY CHEMICAL | E5: 2025 | F5: 7 | G5: 45842 | H5: 1400000158 | I5: DY | J5: 45842 | K5: 45842 | L5: NA | M5: KNOCK OFF ENTRY | N5: 212100 | O5: Trade Debtors (Ctrl) | Q5: 15 | R5: =_xlfn.XLOOKUP(M5,'Invoice No Ref'!$C:$C,'Invoice No Ref'!$I:$I,,0) -> #N/A | S5: USD | T5: 0 | U5: INR | V5: 0 | W5: =V5/T5 -> #DIV/0! | X5: 6779224500 | AA5: 1 | AB5: =_xlfn.XLOOKUP(R5,'Customer Data'!$D:$D,'Customer Data'!$F:$F,,0) -> #N/A | AH5: 45842 | AI5: 45842 | AJ5: 1400000158
A6: Selected | B6: 6779 | C6: 100222426 | D6: ASHLAND SPECIALITY CHEMICAL | E6: 2025 | F6: 3 | G6: 45735 | H6: 1800003187 | I6: DR | J6: 45735 | K6: 45736 | L6: NA | M6: 246779413054 | N6: 212100 | O6: Trade Debtors (Ctrl) | Q6: 01 | R6: =_xlfn.XLOOKUP(M6,'Invoice No Ref'!$C:$C,'Invoice No Ref'!$I:$I,,0) -> #N/A | S6: USD | T6: 131.74 | U6: INR | V6: 11420.71 | W6: =V6/T6 -> 86.691286 | X6: 6779224500 | Z6: NA | AA6: 1 | AB6: =_xlfn.XLOOKUP(R6,'Customer Data'!$D:$D,'Customer Data'!$F:$F,,0) -> #N/A | AD6: Port SSR Charges - Shifting for Aug to Dec,24. | AH6: 45735 | AI6: 45842 | AJ6: 1400000158
A7: Selected | B7: 6779 | C7: 100222426 | D7: ASHLAND SPECIALITY CHEMICAL | E7: 2025 | F7: 11 | G7: 45976 | H7: 1400001878 | I7: DY | J7: 45976 | K7: 45976 | L7: NA | M7: KNOCK OFF ENTRY | N7: 212100 | O7: Trade Debtors (Ctrl) | Q7: 08 | R7: =_xlfn.XLOOKUP(M7,'Invoice No Ref'!$C:$C,'Invoice No Ref'!$I:$I,,0) -> #N/A | S7: USD | T7: 3981.8 | U7: INR | V7: 351158.01 | W7: =V7/T7 -> 88.190771 | X7: 6779224501 | AA7: 1 | AB7: =_xlfn.XLOOKUP(R7,'Customer Data'!$D:$D,'Customer Data'!$F:$F,,0) -> #N/A | AH7: 45976 | AI7: 45976 | AJ7: 1400001878
A8: Selected | B8: 6779 | C8: 100222426 | D8: ASHLAND SPECIALITY CHEMICAL | E8: 2025 | F8: 11 | G8: 45976 | H8: 1400001878 | I8: DY | J8: 45976 | K8: 45976 | L8: NA | M8: KNOCK OFF ENTRY | N8: 212100 | O8: Trade Debtors (Ctrl) | Q8: 15 | R8: =_xlfn.XLOOKUP(M8,'Invoice No Ref'!$C:$C,'Invoice No Ref'!$I:$I,,0) -> #N/A | S8: USD | T8: -3981.8 | U8: INR | V8: -351158.01 | W8: =V8/T8 -> 88.190771 | X8: 6779224501 | AA8: 2 | AB8: =_xlfn.XLOOKUP(R8,'Customer Data'!$D:$D,'Customer Data'!$F:$F,,0) -> #N/A | AH8: 45976 | AI8: 45976 | AJ8: 1400001878
A9: Not Selected | B9: 6779 | C9: 100222426 | D9: ASHLAND SPECIALITY CHEMICAL | E9: 2025 | F9: 3 | G9: 45736 | H9: 1800004475 | I9: DR | J9: 45736 | K9: 45737 | L9: NA | M9: 246779414343 | N9: 212100 | O9: Trade Debtors (Ctrl) | Q9: 01 | R9: =_xlfn.XLOOKUP(M9,'Invoice No Ref'!$C:$C,'Invoice No Ref'!$I:$I,,0) -> 6779IV124000258 | S9: USD | T9: 118 | U9: INR | V9: 10229.57 | W9: =V9/T9 -> 86.691271 | X9: 6779224500 | Z9: NA | AA9: 1 | AB9: =_xlfn.XLOOKUP(R9,'Customer Data'!$D:$D,'Customer Data'!$F:$F,,0) -> -118 | AC9: =AB9+T9 -> 0 | AD9: CY-MOVEMENT CHARGES for Nov 2024 | AH9: 45736
A10: Not Selected | B10: 6779 | C10: 100222426 | D10: ASHLAND SPECIALITY CHEMICAL | E10: 2025 | F10: 3 | G10: 45736 | H10: 1800004556 | I10: DR | J10: 45736 | K10: 45737 | L10: NA | M10: 246779414424 | N10: 212100 | O10: Trade Debtors (Ctrl) | Q10: 01 | R10: =_xlfn.XLOOKUP(M10,'Invoice No Ref'!$C:$C,'Invoice No Ref'!$I:$I,,0) -> 6779IV124000276 | S10: USD | T10: 118 | U10: INR | V10: 10229.57 | W10: =V10/T10 -> 86.691271 | X10: 6779224500 | Z10: NA | AA10: 1 | AB10: =_xlfn.XLOOKUP(R10,'Customer Data'!$D:$D,'Customer Data'!$F:$F,,0) -> -118 | AC10: =AB10+T10 -> 0 | AD10: Cy-WH Destuff charges for Jan 2025 | AH10: 45736
A11: Not Selected | B11: 6779 | C11: 100222426 | D11: ASHLAND SPECIALITY CHEMICAL | E11: 2025 | F11: 4 | G11: 45763 | H11: 1800006323 | I11: DR | J11: 45763 | K11: 45763 | L11: NA | M11: 256779411214 | N11: 212100 | O11: Trade Debtors (Ctrl) | Q11: 01 | R11: =_xlfn.XLOOKUP(M11,'Invoice No Ref'!$C:$C,'Invoice No Ref'!$I:$I,,0) -> #N/A | S11: USD | T11: 11.8 | U11: INR | V11: 1025.68 | W11: =V11/T11 -> 86.922034 | Z11: NA | AA11: 1 | AB11: =_xlfn.XLOOKUP(R11,'Customer Data'!$D:$D,'Customer Data'!$F:$F,,0) -> #N/A | AD11: Outbound Handling Charges Aug 2024 | AH11: 45763
A12: Not Selected | B12: 6779 | C12: 100222426 | D12: ASHLAND SPECIALITY CHEMICAL | E12: 2025 | F12: 3 | G12: 45736 | H12: 1800003964 | I12: DR | J12: 45736 | K12: 45737 | L12: NA | M12: 246779413820 | N12: 212100 | O12: Trade Debtors (Ctrl) | Q12: 01 | R12: =_xlfn.XLOOKUP(M12,'Invoice No Ref'!$C:$C,'Invoice No Ref'!$I:$I,,0) -> 6779IV124000285 | S12: USD | T12: 354 | U12: INR | V12: 30688.71 | W12: =V12/T12 -> 86.691271 | X12: 6779224500 | Z12: NA | AA12: 1 | AB12: =_xlfn.XLOOKUP(R12,'Customer Data'!$D:$D,'Customer Data'!$F:$F,,0) -> -200 | AC12: =AB12+T12 -> 154 | AD12: Scanning Charges for the month of Jan 2025 | AH12: 45736
A13: Not Selected | B13: 6779 | C13: 100222426 | D13: ASHLAND SPECIALITY CHEMICAL | E13: 2025 | F13: 4 | G13: 45751 | H13: 1800005708 | I13: DR | J13: 45751 | K13: 45752 | L13: NA | M13: 256779410600 | N13: 212100 | O13: Trade Debtors (Ctrl) | Q13: 01 | R13: =_xlfn.XLOOKUP(M13,'Invoice No Ref'!$C:$C,'Invoice No Ref'!$I:$I,,0) -> 6779IV124000274 | S13: USD | T13: 15887.63 | U13: INR | V13: 1380981.7 | W13: =V13/T13 -> 86.92182 | Z13: NA | AA13: 1 | AB13: =_xlfn.XLOOKUP(R13,'Customer Data'!$D:$D,'Customer Data'!$F:$F,,0) -> -15887.63 | AC13: =AB13+T13 -> 0 | AD13: Storage charges for Jan 2025 | AH13: 45751
A14: Not Selected | B14: 6779 | C14: 100222426 | D14: ASHLAND SPECIALITY CHEMICAL | E14: 2025 | F14: 3 | G14: 45733 | H14: 1800001878 | I14: DR | J14: 45733 | K14: 45733 | L14: NA | M14: 246779411543 | N14: 212100 | O14: Trade Debtors (Ctrl) | Q14: 01 | R14: =_xlfn.XLOOKUP(M14,'Invoice No Ref'!$C:$C,'Invoice No Ref'!$I:$I,,0) -> #N/A | S14: USD | T14: 17.9 | U14: INR | V14: 1551.77 | W14: =V14/T14 -> 86.691061 | X14: 6779224500 | Z14: NA | AA14: 1 | AB14: =_xlfn.XLOOKUP(R14,'Customer Data'!$D:$D,'Customer Data'!$F:$F,,0) -> #N/A | AD14: VAS Activity Charges for the month of September, 2 | AH14: 45733
A15: Not Selected | B15: 6779 | C15: 100222426 | D15: ASHLAND SPECIALITY CHEMICAL | E15: 2025 | F15: 3 | G15: 45733 | H15: 1800001879 | I15: DR | J15: 45733 | K15: 45733 | L15: NA | M15: 246779411544 | N15: 212100 | O15: Trade Debtors (Ctrl) | Q15: 01 | R15: =_xlfn.XLOOKUP(M15,'Invoice No Ref'!$C:$C,'Invoice No Ref'!$I:$I,,0) -> #N/A | S15: USD | T15: 17.9 | U15: INR | V15: 1551.77 | W15: =V15/T15 -> 86.691061 | X15: 6779224500 | Z15: NA | AA15: 1 | AB15: =_xlfn.XLOOKUP(R15,'Customer Data'!$D:$D,'Customer Data'!$F:$F,,0) -> #N/A | AD15: VAS Activity Charges for the month of September, 2 | AH15: 45733
A16: Not Selected | B16: 6779 | C16: 100222426 | D16: ASHLAND SPECIALITY CHEMICAL | E16: 2025 | F16: 3 | G16: 45733 | H16: 1800001880 | I16: DR | J16: 45733 | K16: 45733 | L16: NA | M16: 246779411545 | N16: 212100 | O16: Trade Debtors (Ctrl) | Q16: 01 | R16: =_xlfn.XLOOKUP(M16,'Invoice No Ref'!$C:$C,'Invoice No Ref'!$I:$I,,0) -> #N/A | S16: USD | T16: 38.19 | U16: INR | V16: 3310.74 | W16: =V16/T16 -> 86.69128 | X16: 6779224500 | Z16: NA | AA16: 1 | AB16: =_xlfn.XLOOKUP(R16,'Customer Data'!$D:$D,'Customer Data'!$F:$F,,0) -> #N/A | AD16: VAS Activity Charges for the month of September, 2 | AH16: 45733
A17: Not Selected | B17: 6779 | C17: 100222426 | D17: ASHLAND SPECIALITY CHEMICAL | E17: 2025 | F17: 3 | G17: 45733 | H17: 1800001993 | I17: DR | J17: 45733 | K17: 45734 | L17: NA | M17: 246779411658 | N17: 212100 | O17: Trade Debtors (Ctrl) | Q17: 01 | R17: =_xlfn.XLOOKUP(M17,'Invoice No Ref'!$C:$C,'Invoice No Ref'!$I:$I,,0) -> #N/A | S17: USD | T17: 149.84 | U17: INR | V17: 12989.82 | W17: =V17/T17 -> 86.691271 | X17: 6779224500 | Z17: NA | AA17: 1 | AB17: =_xlfn.XLOOKUP(R17,'Customer Data'!$D:$D,'Customer Data'!$F:$F,,0) -> #N/A | AD17: VAS Activity Charges for the month of October, 24 | AH17: 45733
A18: Not Selected | B18: 6779 | C18: 100222426 | D18: ASHLAND SPECIALITY CHEMICAL | E18: 2025 | F18: 3 | G18: 45733 | H18: 1800001994 | I18: DR | J18: 45733 | K18: 45734 | L18: NA | M18: 246779411659 | N18: 212100 | O18: Trade Debtors (Ctrl) | Q18: 01 | R18: =_xlfn.XLOOKUP(M18,'Invoice No Ref'!$C:$C,'Invoice No Ref'!$I:$I,,0) -> #N/A | S18: USD | T18: 17.84 | U18: INR | V18: 1546.57 | W18: =V18/T18 -> 86.691143 | X18: 6779224500 | Z18: NA | AA18: 1 | AB18: =_xlfn.XLOOKUP(R18,'Customer Data'!$D:$D,'Customer Data'!$F:$F,,0) -> #N/A | AD18: VAS Activity Charges for the month of October, 24 | AH18: 45733
A19: Not Selected | B19: 6779 | C19: 100222426 | D19: ASHLAND SPECIALITY CHEMICAL | E19: 2025 | F19: 3 | G19: 45733 | H19: 1800001995 | I19: DR | J19: 45733 | K19: 45734 | L19: NA | M19: 246779411660 | N19: 212100 | O19: Trade Debtors (Ctrl) | Q19: 01 | R19: =_xlfn.XLOOKUP(M19,'Invoice No Ref'!$C:$C,'Invoice No Ref'!$I:$I,,0) -> #N/A | S19: USD | T19: 11.89 | U19: INR | V19: 1030.76 | W19: =V19/T19 -> 86.691337 | X19: 6779224500 | Z19: NA | AA19: 1 | AB19: =_xlfn.XLOOKUP(R19,'Customer Data'!$D:$D,'Customer Data'!$F:$F,,0) -> #N/A | AD19: VAS Activity Charges for the month of October, 24 | AH19: 45733
A20: Not Selected | B20: 6779 | C20: 100222426 | D20: ASHLAND SPECIALITY CHEMICAL | E20: 2025 | F20: 3 | G20: 45733 | H20: 1800001996 | I20: DR | J20: 45733 | K20: 45734 | L20: NA | M20: 246779411661 | N20: 212100 | O20: Trade Debtors (Ctrl) | Q20: 01 | R20: =_xlfn.XLOOKUP(M20,'Invoice No Ref'!$C:$C,'Invoice No Ref'!$I:$I,,0) -> #N/A | S20: USD | T20: 0.95 | U20: INR | V20: 82.36 | W20: =V20/T20 -> 86.694737 | X20: 6779224500 | Z20: NA | AA20: 1 | AB20: =_xlfn.XLOOKUP(R20,'Customer Data'!$D:$D,'Customer Data'!$F:$F,,0) -> #N/A | AD20: VAS Activity Charges for the month of October, 24 | AH20: 45733
A21: Not Selected | B21: 6779 | C21: 100222426 | D21: ASHLAND SPECIALITY CHEMICAL | E21: 2025 | F21: 3 | G21: 45733 | H21: 1800001997 | I21: DR | J21: 45733 | K21: 45734 | L21: NA | M21: 246779411662 | N21: 212100 | O21: Trade Debtors (Ctrl) | Q21: 01 | R21: =_xlfn.XLOOKUP(M21,'Invoice No Ref'!$C:$C,'Invoice No Ref'!$I:$I,,0) -> #N/A | S21: USD | T21: 6.54 | U21: INR | V21: 566.96 | W21: =V21/T21 -> 86.691131 | X21: 6779224500 | Z21: NA | AA21: 1 | AB21: =_xlfn.XLOOKUP(R21,'Customer Data'!$D:$D,'Customer Data'!$F:$F,,0) -> #N/A | AD21: VAS Activity Charges for the month of October, 24 | AH21: 45733
A22: Not Selected | B22: 6779 | C22: 100222426 | D22: ASHLAND SPECIALITY CHEMICAL | E22: 2025 | F22: 3 | G22: 45733 | H22: 1800001998 | I22: DR | J22: 45733 | K22: 45734 | L22: NA | M22: 246779411663 | N22: 212100 | O22: Trade Debtors (Ctrl) | Q22: 01 | R22: =_xlfn.XLOOKUP(M22,'Invoice No Ref'!$C:$C,'Invoice No Ref'!$I:$I,,0) -> #N/A | S22: USD | T22: 66.6 | U22: INR | V22: 5773.64 | W22: =V22/T22 -> 86.691291 | X22: 6779224500 | Z22: NA | AA22: 1 | AB22: =_xlfn.XLOOKUP(R22,'Customer Data'!$D:$D,'Customer Data'!$F:$F,,0) -> #N/A | AD22: VAS Activity Charges for the month of October, 24 | AH22: 45733
A23: Not Selected | B23: 6779 | C23: 100222426 | D23: ASHLAND SPECIALITY CHEMICAL | E23: 2025 | F23: 3 | G23: 45733 | H23: 1800002200 | I23: DR | J23: 45733 | K23: 45734 | L23: NA | M23: 246779411865 | N23: 212100 | O23: Trade Debtors (Ctrl) | Q23: 01 | R23: =_xlfn.XLOOKUP(M23,'Invoice No Ref'!$C:$C,'Invoice No Ref'!$I:$I,,0) -> #N/A | S23: USD | T23: 17.75 | U23: INR | V23: 1538.77 | W23: =V23/T23 -> 86.691268 | X23: 6779224500 | Z23: NA | AA23: 1 | AB23: =_xlfn.XLOOKUP(R23,'Customer Data'!$D:$D,'Customer Data'!$F:$F,,0) -> #N/A | AD23: VAS Activity Charges for the month of November, 24 | AH23: 45733
A24: Not Selected | B24: 6779 | C24: 100222426 | D24: ASHLAND SPECIALITY CHEMICAL | E24: 2025 | F24: 3 | G24: 45733 | H24: 1800002201 | I24: DR | J24: 45733 | K24: 45734 | L24: NA | M24: 246779411866 | N24: 212100 | O24: Trade Debtors (Ctrl) | Q24: 01 | R24: =_xlfn.XLOOKUP(M24,'Invoice No Ref'!$C:$C,'Invoice No Ref'!$I:$I,,0) -> #N/A | S24: USD | T24: 17.75 | U24: INR | V24: 1538.77 | W24: =V24/T24 -> 86.691268 | X24: 6779224500 | Z24: NA | AA24: 1 | AB24: =_xlfn.XLOOKUP(R24,'Customer Data'!$D:$D,'Customer Data'!$F:$F,,0) -> #N/A | AD24: VAS Activity Charges for the month of November, 24 | AH24: 45733
A25: Not Selected | B25: 6779 | C25: 100222426 | D25: ASHLAND SPECIALITY CHEMICAL | E25: 2025 | F25: 3 | G25: 45733 | H25: 1800002206 | I25: DR | J25: 45733 | K25: 45734 | L25: NA | M25: 246779411871 | N25: 212100 | O25: Trade Debtors (Ctrl) | Q25: 01 | R25: =_xlfn.XLOOKUP(M25,'Invoice No Ref'!$C:$C,'Invoice No Ref'!$I:$I,,0) -> #N/A | S25: USD | T25: 17.75 | U25: INR | V25: 1538.77 | W25: =V25/T25 -> 86.691268 | X25: 6779224500 | Z25: NA | AA25: 1 | AB25: =_xlfn.XLOOKUP(R25,'Customer Data'!$D:$D,'Customer Data'!$F:$F,,0) -> #N/A | AD25: VAS Activity Charges for the month of November, 24 | AH25: 45733
... A34: Not Selected | B34: 6779 | C34: 100222426 | D34: ASHLAND SPECIALITY CHEMICAL | E34: 2025 | F34: 3 | G34: 45733 | H34: 1800002208 | I34: DR | J34: 45733 | K34: 45734 | L34: NA | M34: 246779411873 | N34: 212100 | O34: Trade Debtors (Ctrl) | Q34: 01 | R34: =_xlfn.XLOOKUP(M34,'Invoice No Ref'!$C:$C,'Invoice No Ref'!$I:$I,,0) -> #N/A | S34: USD | T34: 16.57 | U34: INR | V34: 1436.47 | W34: =V34/T34 -> 86.691008 | X34: 6779224500 | Z34: NA | AA34: 1 | AB34: =_xlfn.XLOOKUP(R34,'Customer Data'!$D:$D,'Customer Data'!$F:$F,,0) -> #N/A | AD34: VAS Activity Charges for the month of November, 24 | AH34: 45733
A35: Not Selected | B35: 6779 | C35: 100222426 | D35: ASHLAND SPECIALITY CHEMICAL | E35: 2025 | F35: 4 | G35: 45762 | H35: 1800006092 | I35: DR | J35: 45762 | K35: 45763 | L35: NA | M35: 256779410983 | N35: 212100 | O35: Trade Debtors (Ctrl) | Q35: 01 | R35: =_xlfn.XLOOKUP(M35,'Invoice No Ref'!$C:$C,'Invoice No Ref'!$I:$I,,0) -> #N/A | S35: USD | T35: 392.35 | U35: INR | V35: 34103.78 | W35: =V35/T35 -> 86.92183 | Z35: NA | AA35: 1 | AB35: =_xlfn.XLOOKUP(R35,'Customer Data'!$D:$D,'Customer Data'!$F:$F,,0) -> #N/A | AD35: CY Destuff Charges August 2024 | AH35: 45762
A36: Not Selected | B36: 6779 | C36: 100222426 | D36: ASHLAND SPECIALITY CHEMICAL | E36: 2025 | F36: 4 | G36: 45762 | H36: 1800006093 | I36: DR | J36: 45762 | K36: 45763 | L36: NA | M36: 256779410984 | N36: 212100 | O36: Trade Debtors (Ctrl) | Q36: 01 | R36: =_xlfn.XLOOKUP(M36,'Invoice No Ref'!$C:$C,'Invoice No Ref'!$I:$I,,0) -> #N/A | S36: USD | T36: 200.6 | U36: INR | V36: 17436.52 | W36: =V36/T36 -> 86.921834 | Z36: NA | AA36: 1 | AB36: =_xlfn.XLOOKUP(R36,'Customer Data'!$D:$D,'Customer Data'!$F:$F,,0) -> #N/A | AD36: CY Destuff Charges August 2024 | AH36: 45762
A37: Not Selected | B37: 6779 | C37: 100222426 | D37: ASHLAND SPECIALITY CHEMICAL | E37: 2025 | F37: 4 | G37: 45762 | H37: 1800006094 | I37: DR | J37: 45762 | K37: 45763 | L37: NA | M37: 256779410985 | N37: 212100 | O37: Trade Debtors (Ctrl) | Q37: 01 | R37: =_xlfn.XLOOKUP(M37,'Invoice No Ref'!$C:$C,'Invoice No Ref'!$I:$I,,0) -> #N/A | S37: USD | T37: 106.2 | U37: INR | V37: 9231.1 | W37: =V37/T37 -> 86.921846 | Z37: NA | AA37: 1 | AB37: =_xlfn.XLOOKUP(R37,'Customer Data'!$D:$D,'Customer Data'!$F:$F,,0) -> #N/A | AD37: CY Destuff Charges August 2024 | AH37: 45762
A38: Not Selected | B38: 6779 | C38: 100222426 | D38: ASHLAND SPECIALITY CHEMICAL | E38: 2025 | F38: 4 | G38: 45762 | H38: 1800006095 | I38: DR | J38: 45762 | K38: 45763 | L38: NA | M38: 256779410986 | N38: 212100 | O38: Trade Debtors (Ctrl) | Q38: 01 | R38: =_xlfn.XLOOKUP(M38,'Invoice No Ref'!$C:$C,'Invoice No Ref'!$I:$I,,0) -> #N/A | S38: USD | T38: 82.6 | U38: INR | V38: 7179.74 | W38: =V38/T38 -> 86.921792 | Z38: NA | AA38: 1 | AB38: =_xlfn.XLOOKUP(R38,'Customer Data'!$D:$D,'Customer Data'!$F:$F,,0) -> #N/A | AD38: CY Destuff Charges August 2024 | AH38: 45762
A39: Not Selected | B39: 6779 | C39: 100222426 | D39: ASHLAND SPECIALITY CHEMICAL | E39: 2025 | F39: 4 | G39: 45762 | H39: 1800006096 | I39: DR | J39: 45762 | K39: 45763 | L39: NA | M39: 256779410987 | N39: 212100 | O39: Trade Debtors (Ctrl) | Q39: 01 | R39: =_xlfn.XLOOKUP(M39,'Invoice No Ref'!$C:$C,'Invoice No Ref'!$I:$I,,0) -> #N/A | S39: USD | T39: 223.67 | U39: INR | V39: 19441.8 | W39: =V39/T39 -> 86.921804 | Z39: NA | AA39: 1 | AB39: =_xlfn.XLOOKUP(R39,'Customer Data'!$D:$D,'Customer Data'!$F:$F,,0) -> #N/A | AD39: Transportation In Charges August 2024 | AH39: 45762
A40: Not Selected | B40: 6779 | C40: 100222426 | D40: ASHLAND SPECIALITY CHEMICAL | E40: 2025 | F40: 4 | G40: 45762 | H40: 1800006097 | I40: DR | J40: 45762 | K40: 45763 | L40: NA | M40: 256779410988 | N40: 212100 | O40: Trade Debtors (Ctrl) | Q40: 01 | R40: =_xlfn.XLOOKUP(M40,'Invoice No Ref'!$C:$C,'Invoice No Ref'!$I:$I,,0) -> #N/A | S40: USD | T40: 330.4 | U40: INR | V40: 28718.97 | W40: =V40/T40 -> 86.921822 | Z40: NA | AA40: 1 | AB40: =_xlfn.XLOOKUP(R40,'Customer Data'!$D:$D,'Customer Data'!$F:$F,,0) -> #N/A | AD40: CY Destuff Charges August 2024 | AH40: 45762
A41: Not Selected | B41: 6779 | C41: 100222426 | D41: ASHLAND SPECIALITY CHEMICAL | E41: 2025 | F41: 4 | G41: 45762 | H41: 1800006098 | I41: DR | J41: 45762 | K41: 45763 | L41: NA | M41: 256779410989 | N41: 212100 | O41: Trade Debtors (Ctrl) | Q41: 01 | R41: =_xlfn.XLOOKUP(M41,'Invoice No Ref'!$C:$C,'Invoice No Ref'!$I:$I,,0) -> #N/A | S41: USD | T41: 82.6 | U41: INR | V41: 7179.74 | W41: =V41/T41 -> 86.921792 | Z41: NA | AA41: 1 | AB41: =_xlfn.XLOOKUP(R41,'Customer Data'!$D:$D,'Customer Data'!$F:$F,,0) -> #N/A | AD41: CY Destuff Charges August 2024 | AH41: 45762
A42: Not Selected | B42: 6779 | C42: 100222426 | D42: ASHLAND SPECIALITY CHEMICAL | E42: 2025 | F42: 4 | G42: 45762 | H42: 1800006099 | I42: DR | J42: 45762 | K42: 45763 | L42: NA | M42: 256779410990 | N42: 212100 | O42: Trade Debtors (Ctrl) | Q42: 01 | R42: =_xlfn.XLOOKUP(M42,'Invoice No Ref'!$C:$C,'Invoice No Ref'!$I:$I,,0) -> #N/A | S42: USD | T42: 194.7 | U42: INR | V42: 16923.68 | W42: =V42/T42 -> 86.921828 | Z42: NA | AA42: 1 | AB42: =_xlfn.XLOOKUP(R42,'Customer Data'!$D:$D,'Customer Data'!$F:$F,,0) -> #N/A | AD42: CY Destuff Charges August 2024 | AH42: 45762
A43: Selected | B43: 6779 | C43: 100222426 | D43: ASHLAND SPECIALITY CHEMICAL | E43: 2025 | F43: 10 | G43: 45947 | H43: 1600002447 | I43: DG | J43: 45947 | K43: 45953 | L43: NA | M43: 256779421989 | N43: 212100 | O43: Trade Debtors (Ctrl) | Q43: 11 | R43: =_xlfn.XLOOKUP(M43,'Invoice No Ref'!$C:$C,'Invoice No Ref'!$I:$I,,0) -> #N/A | S43: USD | T43: -3981.8 | U43: INR | V43: -351158.01 | W43: =V43/T43 -> 88.190771 | X43: 6779224501 | Z43: 2117487 | AA43: 1 | AB43: =_xlfn.XLOOKUP(R43,'Customer Data'!$D:$D,'Customer Data'!$F:$F,,0) -> #N/A | AD43: Credit note raised against 256779418050 | AH43: 45947 | AI43: 45976 | AJ43: 1400001878
A44: Not Selected | B44: 6779 | C44: 100222426 | D44: ASHLAND SPECIALITY CHEMICAL | E44: 2025 | F44: 4 | G44: 45763 | H44: 1800006828 | I44: DR | J44: 45763 | K44: 45764 | L44: NA | M44: 256779411719 | N44: 212100 | O44: Trade Debtors (Ctrl) | Q44: 01 | R44: =_xlfn.XLOOKUP(M44,'Invoice No Ref'!$C:$C,'Invoice No Ref'!$I:$I,,0) -> #N/A | S44: USD | T44: 488.03 | U44: INR | V44: 42420.46 | W44: =V44/T44 -> 86.921829 | X44: 6779224500 | Z44: NA | AA44: 1 | AB44: =_xlfn.XLOOKUP(R44,'Customer Data'!$D:$D,'Customer Data'!$F:$F,,0) -> #N/A | AD44: CY Longstanding Transportation chgs for 31 MAR 202 | AH44: 45763
A45: Not Selected | B45: 6779 | C45: 100222426 | D45: ASHLAND SPECIALITY CHEMICAL | E45: 2025 | F45: 4 | G45: 45763 | H45: 1800006853 | I45: DR | J45: 45763 | K45: 45764 | L45: NA | M45: 256779411744 | N45: 212100 | O45: Trade Debtors (Ctrl) | Q45: 01 | R45: =_xlfn.XLOOKUP(M45,'Invoice No Ref'!$C:$C,'Invoice No Ref'!$I:$I,,0) -> 6779IV124000269 | S45: USD | T45: 1015.85 | U45: INR | V45: 88299.53 | W45: =V45/T45 -> 86.921819 | X45: 6779224500 | Z45: NA | AA45: 1 | AB45: =_xlfn.XLOOKUP(R45,'Customer Data'!$D:$D,'Customer Data'!$F:$F,,0) -> -1015.85 | AC45: =AB45+T45 -> 0 | AD45: Inbound Handling charges for Dec 2024 | AH45: 45763
A46: Not Selected | B46: 6779 | C46: 100222426 | D46: ASHLAND SPECIALITY CHEMICAL | E46: 2025 | F46: 4 | G46: 45763 | H46: 1800006854 | I46: DR | J46: 45763 | K46: 45764 | L46: NA | M46: 256779411745 | N46: 212100 | O46: Trade Debtors (Ctrl) | Q46: 01 | R46: =_xlfn.XLOOKUP(M46,'Invoice No Ref'!$C:$C,'Invoice No Ref'!$I:$I,,0) -> #N/A | S46: USD | T46: 169.92 | U46: INR | V46: 14769.76 | W46: =V46/T46 -> 86.921846 | X46: 6779224500 | Z46: NA | AA46: 1 | AB46: =_xlfn.XLOOKUP(R46,'Customer Data'!$D:$D,'Customer Data'!$F:$F,,0) -> #N/A | AD46: Loose Unloading charges for Dec 2024 | AH46: 45763
A47: Not Selected | B47: 6779 | C47: 100222426 | D47: ASHLAND SPECIALITY CHEMICAL | E47: 2025 | F47: 4 | G47: 45763 | H47: 1800006855 | I47: DR | J47: 45763 | K47: 45764 | L47: NA | M47: 256779411746 | N47: 212100 | O47: Trade Debtors (Ctrl) | Q47: 01 | R47: =_xlfn.XLOOKUP(M47,'Invoice No Ref'!$C:$C,'Invoice No Ref'!$I:$I,,0) -> 6779IV124000267 | S47: USD | T47: 141.6 | U47: INR | V47: 12308.13 | W47: =V47/T47 -> 86.921822 | X47: 6779224500 | Z47: NA | AA47: 1 | AB47: =_xlfn.XLOOKUP(R47,'Customer Data'!$D:$D,'Customer Data'!$F:$F,,0) -> -141.6 | AC47: =AB47+T47 -> 0 | AD47: Cy-WH Destuff charges for Dec 2024 | AH47: 45763
A48: Not Selected | B48: 6779 | C48: 100222426 | D48: ASHLAND SPECIALITY CHEMICAL | E48: 2025 | F48: 4 | G48: 45763 | H48: 1800006939 | I48: DR | J48: 45763 | K48: 45764 | L48: NA | M48: 256779411830 | N48: 212100 | O48: Trade Debtors (Ctrl) | Q48: 01 | R48: =_xlfn.XLOOKUP(M48,'Invoice No Ref'!$C:$C,'Invoice No Ref'!$I:$I,,0) -> 6779IV124000271 | S48: USD | T48: 1362.36 | U48: INR | V48: 118418.81 | W48: =V48/T48 -> 86.921819 | X48: 6779224500 | Z48: NA | AA48: 1 | AB48: =_xlfn.XLOOKUP(R48,'Customer Data'!$D:$D,'Customer Data'!$F:$F,,0) -> -1362.36 | AC48: =AB48+T48 -> 0 | AD48: Outbound Handling charges for Dec 2024 | AH48: 45763
A49: Not Selected | B49: 6779 | C49: 100222426 | D49: ASHLAND SPECIALITY CHEMICAL | E49: 2025 | F49: 4 | G49: 45763 | H49: 1800006940 | I49: DR | J49: 45763 | K49: 45764 | L49: NA | M49: 256779411831 | N49: 212100 | O49: Trade Debtors (Ctrl) | Q49: 01 | R49: =_xlfn.XLOOKUP(M49,'Invoice No Ref'!$C:$C,'Invoice No Ref'!$I:$I,,0) -> 6779IV124000270 | S49: USD | T49: 23.6 | U49: INR | V49: 2051.35 | W49: =V49/T49 -> 86.92161 | X49: 6779224500 | Z49: NA | AA49: 1 | AB49: =_xlfn.XLOOKUP(R49,'Customer Data'!$D:$D,'Customer Data'!$F:$F,,0) -> -23.6 | AC49: =AB49+T49 -> 0 | AD49: CY - CY charges for Dec 2024 | AH49: 45763
A50: Not Selected | B50: 6779 | C50: 100222426 | D50: ASHLAND SPECIALITY CHEMICAL | E50: 2025 | F50: 4 | G50: 45763 | H50: 1800007103 | I50: DR | J50: 45763 | K50: 45764 | L50: NA | M50: 256779411994 | N50: 212100 | O50: Trade Debtors (Ctrl) | Q50: 01 | R50: =_xlfn.XLOOKUP(M50,'Invoice No Ref'!$C:$C,'Invoice No Ref'!$I:$I,,0) -> #N/A | S50: USD | T50: 146.81 | U50: INR | V50: 12760.99 | W50: =V50/T50 -> 86.921804 | X50: 6779224500 | Z50: NA | AA50: 1 | AB50: =_xlfn.XLOOKUP(R50,'Customer Data'!$D:$D,'Customer Data'!$F:$F,,0) -> #N/A | AD50: VAS Activity - Jan 25, Ex Rate. 86.64 | AH50: 45763
A51: Selected | B51: 6779 | C51: 100222426 | D51: ASHLAND SPECIALITY CHEMICAL | E51: 2025 | F51: 4 | G51: 45763 | H51: 1800006838 | I51: DR | J51: 45763 | K51: 45764 | L51: NA | M51: 256779411729 | N51: 212100 | O51: Trade Debtors (Ctrl) | Q51: 01 | S51: USD | T51: 51.12 | U51: INR | V51: 4443.44 | W51: =V51/T51 -> 86.921753 | X51: 6779224500 | Z51: NA | AA51: 1 | AB51: =_xlfn.XLOOKUP(M51,'Customer Data'!$D:$D,'Customer Data'!$H:$H,,0) -> -51.12 | AC51: =AB51+T51 -> 0 | AD51: Detention charges for 15 Mar 2025 | AH51: 45763 | AI51: 45855 | AJ51: 1400000284
A52: Selected | B52: 6779 | C52: 100222426 | D52: ASHLAND SPECIALITY CHEMICAL | E52: 2025 | F52: 4 | G52: 45763 | H52: 1800006843 | I52: DR | J52: 45763 | K52: 45764 | L52: NA | M52: 256779411734 | N52: 212100 | O52: Trade Debtors (Ctrl) | Q52: 01 | S52: USD | T52: 49.58 | U52: INR | V52: 4309.58 | W52: =V52/T52 -> 86.921743 | X52: 6779224500 | Z52: NA | AA52: 1 | AB52: =_xlfn.XLOOKUP(M52,'Customer Data'!$D:$D,'Customer Data'!$H:$H,,0) -> -49.58 | AC52: =AB52+T52 -> 0 | AD52: Empty Lolo chgs for 16 to 31 Mar 25 Exch. Rate 85. | AH52: 45763 | AI52: 45855 | AJ52: 1400000284
A53: Selected | B53: 6779 | C53: 100222426 | D53: ASHLAND SPECIALITY CHEMICAL | E53: 2025 | F53: 4 | G53: 45763 | H53: 1800007033 | I53: DR | J53: 45763 | K53: 45764 | L53: NA | M53: 256779411924 | N53: 212100 | O53: Trade Debtors (Ctrl) | Q53: 01 | S53: USD | T53: 13.94 | U53: INR | V53: 1211.69 | W53: =V53/T53 -> 86.921808 | X53: 6779224500 | Z53: NA | AA53: 1 | AB53: =_xlfn.XLOOKUP(M53,'Customer Data'!$D:$D,'Customer Data'!$H:$H,,0) -> -13.94 | AC53: =AB53+T53 -> 0 | AD53: FCIU6188174-Port SSR Shifting Mar 2025. Exch rate | AH53: 45763 | AI53: 45855 | AJ53: 1400000284
A54: Selected | B54: 6779 | C54: 100222426 | D54: ASHLAND SPECIALITY CHEMICAL | E54: 2025 | F54: 4 | G54: 45763 | H54: 1800007034 | I54: DR | J54: 45763 | K54: 45764 | L54: NA | M54: 256779411925 | N54: 212100 | O54: Trade Debtors (Ctrl) | Q54: 01 | S54: USD | T54: 3.48 | U54: INR | V54: 302.49 | W54: =V54/T54 -> 86.922414 | X54: 6779224500 | Z54: NA | AA54: 1 | AB54: =_xlfn.XLOOKUP(M54,'Customer Data'!$D:$D,'Customer Data'!$H:$H,,0) -> -3.48 | AC54: =AB54+T54 -> 0 | AD54: HPCU2278439-Port SSR Shifting Mar 2025. Exch rate | AH54: 45763 | AI54: 45855 | AJ54: 1400000284
A55: Selected | B55: 6779 | C55: 100222426 | D55: ASHLAND SPECIALITY CHEMICAL | E55: 2025 | F55: 4 | G55: 45763 | H55: 1800007035 | I55: DR | J55: 45763 | K55: 45764 | L55: NA | M55: 256779411926 | N55: 212100 | O55: Trade Debtors (Ctrl) | Q55: 01 | S55: USD | T55: 13.94 | U55: INR | V55: 1211.69 | W55: =V55/T55 -> 86.921808 | X55: 6779224500 | Z55: NA | AA55: 1 | AB55: =_xlfn.XLOOKUP(M55,'Customer Data'!$D:$D,'Customer Data'!$H:$H,,0) -> -13.94 | AC55: =AB55+T55 -> 0 | AD55: TCNU6507209-Port SSR Shifting Mar 2025. Exch rate | AH55: 45763 | AI55: 45855 | AJ55: 1400000284
A56: Selected | B56: 6779 | C56: 100222426 | D56: ASHLAND SPECIALITY CHEMICAL | E56: 2025 | F56: 4 | G56: 45763 | H56: 1800007188 | I56: DR | J56: 45763 | K56: 45764 | L56: NA | M56: 256779412079 | N56: 212100 | O56: Trade Debtors (Ctrl) | Q56: 01 | S56: USD | T56: 116.73 | U56: INR | V56: 10146.38 | W56: =V56/T56 -> 86.921785 | X56: 6779224500 | Z56: NA | AA56: 1 | AB56: =_xlfn.XLOOKUP(M56,'Customer Data'!$D:$D,'Customer Data'!$H:$H,,0) -> -116.73 | AC56: =AB56+T56 -> 0 | AD56: VAS Activity - Mar 25, 16-31, Ex Rate. 85.58 | AH56: 45763 | AI56: 45855 | AJ56: 1400000284
A57: Not Selected | B57: 6779 | C57: 100222426 | D57: ASHLAND SPECIALITY CHEMICAL | E57: 2025 | F57: 4 | G57: 45763 | H57: 1800006324 | I57: DR | J57: 45763 | K57: 45763 | L57: NA | M57: 256779411215 | N57: 212100 | O57: Trade Debtors (Ctrl) | Q57: 01 | R57: =_xlfn.XLOOKUP(M57,'Invoice No Ref'!$C:$C,'Invoice No Ref'!$I:$I,,0) -> #N/A | S57: USD | T57: 46.87 | U57: INR | V57: 4074.03 | W57: =V57/T57 -> 86.921912 | Z57: NA | AA57: 1 | AB57: =_xlfn.XLOOKUP(R57,'Customer Data'!$D:$D,'Customer Data'!$F:$F,,0) -> #N/A | AD57: Outbound Handling Charges Aug 2024 | AH57: 45763
A58: Not Selected | B58: 6779 | C58: 100222426 | D58: ASHLAND SPECIALITY CHEMICAL | E58: 2025 | F58: 4 | G58: 45763 | H58: 1800006330 | I58: DR | J58: 45763 | K58: 45763 | L58: NA | M58: 256779411221 | N58: 212100 | O58: Trade Debtors (Ctrl) | Q58: 01 | R58: =_xlfn.XLOOKUP(M58,'Invoice No Ref'!$C:$C,'Invoice No Ref'!$I:$I,,0) -> #N/A | S58: USD | T58: 2.95 | U58: INR | V58: 256.42 | W58: =V58/T58 -> 86.922034 | Z58: NA | AA58: 1 | AB58: =_xlfn.XLOOKUP(R58,'Customer Data'!$D:$D,'Customer Data'!$F:$F,,0) -> #N/A | AD58: Outbound Handling Charges Aug 2024 | AH58: 45763
A59: Not Selected | B59: 6779 | C59: 100222426 | D59: ASHLAND SPECIALITY CHEMICAL | E59: 2025 | F59: 4 | G59: 45763 | H59: 1800006332 | I59: DR | J59: 45763 | K59: 45763 | L59: NA | M59: 256779411223 | N59: 212100 | O59: Trade Debtors (Ctrl) | Q59: 01 | R59: =_xlfn.XLOOKUP(M59,'Invoice No Ref'!$C:$C,'Invoice No Ref'!$I:$I,,0) -> #N/A | S59: USD | T59: 85.55 | U59: INR | V59: 7436.16 | W59: =V59/T59 -> 86.9218 | Z59: NA | AA59: 1 | AB59: =_xlfn.XLOOKUP(R59,'Customer Data'!$D:$D,'Customer Data'!$F:$F,,0) -> #N/A | AD59: Outbound Handling Charges Aug 2024 | AH59: 45763
A60: Not Selected | B60: 6779 | C60: 100222426 | D60: ASHLAND SPECIALITY CHEMICAL | E60: 2025 | F60: 4 | G60: 45763 | H60: 1800006336 | I60: DR | J60: 45763 | K60: 45763 | L60: NA | M60: 256779411227 | N60: 212100 | O60: Trade Debtors (Ctrl) | Q60: 01 | R60: =_xlfn.XLOOKUP(M60,'Invoice No Ref'!$C:$C,'Invoice No Ref'!$I:$I,,0) -> #N/A | S60: USD | T60: 2.95 | U60: INR | V60: 256.42 | W60: =V60/T60 -> 86.922034 | Z60: NA | AA60: 1 | AB60: =_xlfn.XLOOKUP(R60,'Customer Data'!$D:$D,'Customer Data'!$F:$F,,0) -> #N/A | AD60: Outbound Handling Charges Aug 2024 | AH60: 45763
A61: Selected | B61: 6779 | C61: 100222426 | D61: ASHLAND SPECIALITY CHEMICAL | E61: 2025 | F61: 4 | G61: 45763 | H61: 1800005959 | I61: DR | J61: 45763 | K61: 45763 | L61: NA | M61: 256779410850 | N61: 212100 | O61: Trade Debtors (Ctrl) | Q61: 01 | S61: USD | T61: 6562.84 | U61: INR | V61: 570454 | W61: =V61/T61 -> 86.92182 | Z61: NA | AA61: 1 | AB61: =_xlfn.XLOOKUP(M61,'Customer Data'!$D:$D,'Customer Data'!$H:$H,,0) -> -6562.84 | AC61: =AB61+T61 -> 0 | AD61: Storage charges for March 2025 | AH61: 45763 | AI61: 45855 | AJ61: 1400000284
A62: Not Selected | B62: 6779 | C62: 100222426 | D62: ASHLAND SPECIALITY CHEMICAL | E62: 2025 | F62: 4 | G62: 45763 | H62: 1800006322 | I62: DR | J62: 45763 | K62: 45763 | L62: NA | M62: 256779411213 | N62: 212100 | O62: Trade Debtors (Ctrl) | Q62: 01 | R62: =_xlfn.XLOOKUP(M62,'Invoice No Ref'!$C:$C,'Invoice No Ref'!$I:$I,,0) -> #N/A | S62: USD | T62: 66.08 | U62: INR | V62: 5743.79 | W62: =V62/T62 -> 86.921762 | Z62: NA | AA62: 1 | AB62: =_xlfn.XLOOKUP(R62,'Customer Data'!$D:$D,'Customer Data'!$F:$F,,0) -> #N/A | AD62: Outbound Handling Charges Aug 2024 | AH62: 45763
A63: Not Selected | B63: 6779 | C63: 100222426 | D63: ASHLAND SPECIALITY CHEMICAL | E63: 2025 | F63: 4 | G63: 45763 | H63: 1800006325 | I63: DR | J63: 45763 | K63: 45763 | L63: NA | M63: 256779411216 | N63: 212100 | O63: Trade Debtors (Ctrl) | Q63: 01 | R63: =_xlfn.XLOOKUP(M63,'Invoice No Ref'!$C:$C,'Invoice No Ref'!$I:$I,,0) -> #N/A | S63: USD | T63: 91.45 | U63: INR | V63: 7949 | W63: =V63/T63 -> 86.921815 | Z63: NA | AA63: 1 | AB63: =_xlfn.XLOOKUP(R63,'Customer Data'!$D:$D,'Customer Data'!$F:$F,,0) -> #N/A | AD63: Outbound Handling Charges Aug 2024 | AH63: 45763
A64: Not Selected | B64: 6779 | C64: 100222426 | D64: ASHLAND SPECIALITY CHEMICAL | E64: 2025 | F64: 4 | G64: 45763 | H64: 1800006326 | I64: DR | J64: 45763 | K64: 45763 | L64: NA | M64: 256779411217 | N64: 212100 | O64: Trade Debtors (Ctrl) | Q64: 01 | R64: =_xlfn.XLOOKUP(M64,'Invoice No Ref'!$C:$C,'Invoice No Ref'!$I:$I,,0) -> #N/A | S64: USD | T64: 91.45 | U64: INR | V64: 7949 | W64: =V64/T64 -> 86.921815 | Z64: NA | AA64: 1 | AB64: =_xlfn.XLOOKUP(R64,'Customer Data'!$D:$D,'Customer Data'!$F:$F,,0) -> #N/A | AD64: Outbound Handling Charges Aug 2024 | AH64: 45763
A65: Not Selected | B65: 6779 | C65: 100222426 | D65: ASHLAND SPECIALITY CHEMICAL | E65: 2025 | F65: 4 | G65: 45763 | H65: 1800006327 | I65: DR | J65: 45763 | K65: 45763 | L65: NA | M65: 256779411218 | N65: 212100 | O65: Trade Debtors (Ctrl) | Q65: 01 | R65: =_xlfn.XLOOKUP(M65,'Invoice No Ref'!$C:$C,'Invoice No Ref'!$I:$I,,0) -> #N/A | S65: USD | T65: 110.7 | U65: INR | V65: 9622.25 | W65: =V65/T65 -> 86.921861 | Z65: NA | AA65: 1 | AB65: =_xlfn.XLOOKUP(R65,'Customer Data'!$D:$D,'Customer Data'!$F:$F,,0) -> #N/A | AD65: Outbound Handling Charges Aug 2024 | AH65: 45763
A66: Not Selected | B66: 6779 | C66: 100222426 | D66: ASHLAND SPECIALITY CHEMICAL | E66: 2025 | F66: 4 | G66: 45763 | H66: 1800006328 | I66: DR | J66: 45763 | K66: 45763 | L66: NA | M66: 256779411219 | N66: 212100 | O66: Trade Debtors (Ctrl) | Q66: 01 | R66: =_xlfn.XLOOKUP(M66,'Invoice No Ref'!$C:$C,'Invoice No Ref'!$I:$I,,0) -> #N/A | S66: USD | T66: 35.4 | U66: INR | V66: 3077.03 | W66: =V66/T66 -> 86.921751 | Z66: NA | AA66: 1 | AB66: =_xlfn.XLOOKUP(R66,'Customer Data'!$D:$D,'Customer Data'!$F:$F,,0) -> #N/A | AD66: Outbound Handling Charges Aug 2024 | AH66: 45763
A67: Not Selected | B67: 6779 | C67: 100222426 | D67: ASHLAND SPECIALITY CHEMICAL | E67: 2025 | F67: 4 | G67: 45763 | H67: 1800006329 | I67: DR | J67: 45763 | K67: 45763 | L67: NA | M67: 256779411220 | N67: 212100 | O67: Trade Debtors (Ctrl) | Q67: 01 | R67: =_xlfn.XLOOKUP(M67,'Invoice No Ref'!$C:$C,'Invoice No Ref'!$I:$I,,0) -> #N/A | S67: USD | T67: 44.25 | U67: INR | V67: 3846.29 | W67: =V67/T67 -> 86.921808 | Z67: NA | AA67: 1 | AB67: =_xlfn.XLOOKUP(R67,'Customer Data'!$D:$D,'Customer Data'!$F:$F,,0) -> #N/A | AD67: Outbound Handling Charges Aug 2024 | AH67: 45763
A68: Not Selected | B68: 6779 | C68: 100222426 | D68: ASHLAND SPECIALITY CHEMICAL | E68: 2025 | F68: 4 | G68: 45763 | H68: 1800006331 | I68: DR | J68: 45763 | K68: 45763 | L68: NA | M68: 256779411222 | N68: 212100 | O68: Trade Debtors (Ctrl) | Q68: 01 | R68: =_xlfn.XLOOKUP(M68,'Invoice No Ref'!$C:$C,'Invoice No Ref'!$I:$I,,0) -> #N/A | S68: USD | T68: 105.43 | U68: INR | V68: 9164.17 | W68: =V68/T68 -> 86.921844 | Z68: NA | AA68: 1 | AB68: =_xlfn.XLOOKUP(R68,'Customer Data'!$D:$D,'Customer Data'!$F:$F,,0) -> #N/A | AD68: Outbound Handling Charges Aug 2024 | AH68: 45763
A69: Not Selected | B69: 6779 | C69: 100222426 | D69: ASHLAND SPECIALITY CHEMICAL | E69: 2025 | F69: 4 | G69: 45763 | H69: 1800006333 | I69: DR | J69: 45763 | K69: 45763 | L69: NA | M69: 256779411224 | N69: 212100 | O69: Trade Debtors (Ctrl) | Q69: 01 | R69: =_xlfn.XLOOKUP(M69,'Invoice No Ref'!$C:$C,'Invoice No Ref'!$I:$I,,0) -> #N/A | S69: USD | T69: 54.47 | U69: INR | V69: 4734.63 | W69: =V69/T69 -> 86.921792 | Z69: NA | AA69: 1 | AB69: =_xlfn.XLOOKUP(R69,'Customer Data'!$D:$D,'Customer Data'!$F:$F,,0) -> #N/A | AD69: Outbound Handling Charges Aug 2024 | AH69: 45763
A70: Not Selected | B70: 6779 | C70: 100222426 | D70: ASHLAND SPECIALITY CHEMICAL | E70: 2025 | F70: 4 | G70: 45763 | H70: 1800006334 | I70: DR | J70: 45763 | K70: 45763 | L70: NA | M70: 256779411225 | N70: 212100 | O70: Trade Debtors (Ctrl) | Q70: 01 | R70: =_xlfn.XLOOKUP(M70,'Invoice No Ref'!$C:$C,'Invoice No Ref'!$I:$I,,0) -> #N/A | S70: USD | T70: 66 | U70: INR | V70: 5736.84 | W70: =V70/T70 -> 86.921818 | Z70: NA | AA70: 1 | AB70: =_xlfn.XLOOKUP(R70,'Customer Data'!$D:$D,'Customer Data'!$F:$F,,0) -> #N/A | AD70: Outbound Handling Charges Aug 2024 | AH70: 45763
A71: Not Selected | B71: 6779 | C71: 100222426 | D71: ASHLAND SPECIALITY CHEMICAL | E71: 2025 | F71: 4 | G71: 45763 | H71: 1800006335 | I71: DR | J71: 45763 | K71: 45763 | L71: NA | M71: 256779411226 | N71: 212100 | O71: Trade Debtors (Ctrl) | Q71: 01 | R71: =_xlfn.XLOOKUP(M71,'Invoice No Ref'!$C:$C,'Invoice No Ref'!$I:$I,,0) -> #N/A | S71: USD | T71: 112.1 | U71: INR | V71: 9743.94 | W71: =V71/T71 -> 86.921855 | Z71: NA | AA71: 1 | AB71: =_xlfn.XLOOKUP(R71,'Customer Data'!$D:$D,'Customer Data'!$F:$F,,0) -> #N/A | AD71: Outbound Handling Charges Aug 2024 | AH71: 45763
A72: Not Selected | B72: 6779 | C72: 100222426 | D72: ASHLAND SPECIALITY CHEMICAL | E72: 2025 | F72: 4 | G72: 45763 | H72: 1800006337 | I72: DR | J72: 45763 | K72: 45763 | L72: NA | M72: 256779411228 | N72: 212100 | O72: Trade Debtors (Ctrl) | Q72: 01 | R72: =_xlfn.XLOOKUP(M72,'Invoice No Ref'!$C:$C,'Invoice No Ref'!$I:$I,,0) -> #N/A | S72: USD | T72: 44.25 | U72: INR | V72: 3846.29 | W72: =V72/T72 -> 86.921808 | Z72: NA | AA72: 1 | AB72: =_xlfn.XLOOKUP(R72,'Customer Data'!$D:$D,'Customer Data'!$F:$F,,0) -> #N/A | AD72: Outbound Handling Charges Aug 2024 | AH72: 45763
A73: Not Selected | B73: 6779 | C73: 100222426 | D73: ASHLAND SPECIALITY CHEMICAL | E73: 2025 | F73: 4 | G73: 45763 | H73: 1800006338 | I73: DR | J73: 45763 | K73: 45763 | L73: NA | M73: 256779411229 | N73: 212100 | O73: Trade Debtors (Ctrl) | Q73: 01 | R73: =_xlfn.XLOOKUP(M73,'Invoice No Ref'!$C:$C,'Invoice No Ref'!$I:$I,,0) -> #N/A | S73: USD | T73: 103.25 | U73: INR | V73: 8974.68 | W73: =V73/T73 -> 86.92184 | Z73: NA | AA73: 1 | AB73: =_xlfn.XLOOKUP(R73,'Customer Data'!$D:$D,'Customer Data'!$F:$F,,0) -> #N/A | AD73: Outbound Handling Charges Aug 2024 | AH73: 45763
... A77: Not Selected | B77: 6779 | C77: 100222426 | D77: ASHLAND SPECIALITY CHEMICAL | E77: 2025 | F77: 4 | G77: 45763 | H77: 1800006342 | I77: DR | J77: 45763 | K77: 45763 | L77: NA | M77: 256779411233 | N77: 212100 | O77: Trade Debtors (Ctrl) | Q77: 01 | R77: =_xlfn.XLOOKUP(M77,'Invoice No Ref'!$C:$C,'Invoice No Ref'!$I:$I,,0) -> #N/A | S77: USD | T77: 20.96 | U77: INR | V77: 1821.88 | W77: =V77/T77 -> 86.921756 | Z77: NA | AA77: 1 | AB77: =_xlfn.XLOOKUP(R77,'Customer Data'!$D:$D,'Customer Data'!$F:$F,,0) -> #N/A | AD77: Outbound Handling Charges Aug 2024 | AH77: 45763
A78: Not Selected | B78: 6779 | C78: 100222426 | D78: ASHLAND SPECIALITY CHEMICAL | E78: 2025 | F78: 7 | G78: 45863 | H78: 1800011241 | I78: DR | J78: 45863 | K78: 45863 | L78: NA | M78: 256779415973 | N78: 212100 | O78: Trade Debtors (Ctrl) | Q78: 01 | R78: =_xlfn.XLOOKUP(M78,'Invoice No Ref'!$C:$C,'Invoice No Ref'!$I:$I,,0) -> #N/A | S78: USD | T78: 448.06 | U78: INR | V78: 38533.46 | W78: =V78/T78 -> 86.00067 | X78: 6779224501 | Z78: NA | AA78: 1 | AB78: =_xlfn.XLOOKUP(R78,'Customer Data'!$D:$D,'Customer Data'!$F:$F,,0) -> #N/A | AD78: VAS 16-31 May 25 Ex.85.48 | AH78: 45863
A79: Not Selected | B79: 6779 | C79: 100222426 | D79: ASHLAND SPECIALITY CHEMICAL | E79: 2025 | F79: 7 | G79: 45842 | H79: 1800010077 | I79: DR | J79: 45842 | K79: 45846 | L79: NA | M79: 256779414841 | N79: 212100 | O79: Trade Debtors (Ctrl) | Q79: 01 | R79: =_xlfn.XLOOKUP(M79,'Invoice No Ref'!$C:$C,'Invoice No Ref'!$I:$I,,0) -> #N/A | S79: USD | T79: 165.16 | U79: INR | V79: 14203.87 | W79: =V79/T79 -> 86.000666 | X79: 6779224500 | Z79: NA | AA79: 1 | AB79: =_xlfn.XLOOKUP(R79,'Customer Data'!$D:$D,'Customer Data'!$F:$F,,0) -> #N/A | AD79: VAS- 1-31 Aug-24, | AH79: 45842
A80: Not Selected | B80: 6779 | C80: 100222426 | D80: ASHLAND SPECIALITY CHEMICAL | E80: 2025 | F80: 11 | G80: 45966 | H80: 1800014423 | I80: DR | J80: 45966 | K80: 45967 | L80: NA | M80: 256779418940 | N80: 212100 | O80: Trade Debtors (Ctrl) | Q80: 01 | S80: USD | T80: 7238.59 | U80: INR | V80: 637020.46 | W80: =V80/T80 -> 88.00339 | X80: 6779224501 | Z80: 2123396 | AA80: 1 | AB80: =_xlfn.XLOOKUP(M80,'Customer Data'!$D:$D,'Customer Data'!$H:$H,,0) -> -7238.59 | AC80: =AB80+T80 -> 0 | AD80: Storage -WH 09- 16-31 OCT 25 | AH80: 45966
A81: Not Selected | B81: 6779 | C81: 100222426 | D81: ASHLAND SPECIALITY CHEMICAL | E81: 2025 | F81: 11 | G81: 45966 | H81: 1800014424 | I81: DR | J81: 45966 | K81: 45967 | L81: NA | M81: 256779418941 | N81: 212100 | O81: Trade Debtors (Ctrl) | Q81: 01 | S81: USD | T81: 7669.34 | U81: INR | V81: 674927.92 | W81: =V81/T81 -> 88.00339 | X81: 6779224501 | Z81: 2123396 | AA81: 1 | AB81: =_xlfn.XLOOKUP(M81,'Customer Data'!$D:$D,'Customer Data'!$H:$H,,0) -> -7669.34 | AC81: =AB81+T81 -> 0 | AD81: Storage -WH 09- 16-31 OCT 25 | AH81: 45966
A82: Not Selected | B82: 6779 | C82: 100222426 | D82: ASHLAND SPECIALITY CHEMICAL | E82: 2025 | F82: 7 | G82: 45856 | H82: 1800010753 | I82: DR | J82: 45856 | K82: 45859 | L82: NA | M82: 256779415415 | N82: 212100 | O82: Trade Debtors (Ctrl) | Q82: 01 | R82: =_xlfn.XLOOKUP(M82,'Invoice No Ref'!$C:$C,'Invoice No Ref'!$I:$I,,0) -> #N/A | S82: USD | T82: 340.75 | U82: INR | V82: 29304.73 | W82: =V82/T82 -> 86.000675 | X82: 6779224501 | Z82: NA | AA82: 1 | AB82: =_xlfn.XLOOKUP(R82,'Customer Data'!$D:$D,'Customer Data'!$F:$F,,0) -> #N/A | AD82: PORT SSR Chgs Apr to June 25 | AH82: 45856
A83: Not Selected | B83: 6779 | C83: 100222426 | D83: ASHLAND SPECIALITY CHEMICAL | E83: 2025 | F83: 3 | G83: 45729 | H83: 1800001388 | I83: DR | J83: 45729 | K83: 45731 | L83: NA | M83: 246779411256 | N83: 212100 | O83: Trade Debtors (Ctrl) | Q83: 01 | R83: =_xlfn.XLOOKUP(M83,'Invoice No Ref'!$C:$C,'Invoice No Ref'!$I:$I,,0) -> 6779IV124000241 | S83: USD | T83: 220 | U83: INR | V83: 19072.08 | W83: =V83/T83 -> 86.691273 | X83: 6779224500 | Z83: NA | AA83: 1 | AB83: =_xlfn.XLOOKUP(R83,'Customer Data'!$D:$D,'Customer Data'!$F:$F,,0) -> -220 | AC83: =AB83+T83 -> 0 | AD83: Scanning Charges for the month of August, 2024 | AH83: 45729
A84: Not Selected | B84: 6779 | C84: 100222426 | D84: ASHLAND SPECIALITY CHEMICAL | E84: 2025 | F84: 3 | G84: 45729 | H84: 1800001454 | I84: DR | J84: 45729 | K84: 45733 | L84: NA | M84: 246779411286 | N84: 212100 | O84: Trade Debtors (Ctrl) | Q84: 01 | R84: =_xlfn.XLOOKUP(M84,'Invoice No Ref'!$C:$C,'Invoice No Ref'!$I:$I,,0) -> 6779IV124000248 | S84: USD | T84: 670 | U84: INR | V84: 58083.14 | W84: =V84/T84 -> 86.691254 | X84: 6779224500 | Z84: NA | AA84: 1 | AB84: =_xlfn.XLOOKUP(R84,'Customer Data'!$D:$D,'Customer Data'!$F:$F,,0) -> -670 | AC84: =AB84+T84 -> 0 | AD84: Scanning Charges for the month of September, 2024 | AH84: 45729
A85: Not Selected | B85: 6779 | C85: 100222426 | D85: ASHLAND SPECIALITY CHEMICAL | E85: 2025 | F85: 3 | G85: 45729 | H85: 1800001441 | I85: DR | J85: 45729 | K85: 45733 | L85: NA | M85: 246779411305 | N85: 212100 | O85: Trade Debtors (Ctrl) | Q85: 01 | R85: =_xlfn.XLOOKUP(M85,'Invoice No Ref'!$C:$C,'Invoice No Ref'!$I:$I,,0) -> 6779IV124000256 | S85: USD | T85: 135 | U85: INR | V85: 11703.32 | W85: =V85/T85 -> 86.691259 | X85: 6779224500 | Z85: NA | AA85: 1 | AB85: =_xlfn.XLOOKUP(R85,'Customer Data'!$D:$D,'Customer Data'!$F:$F,,0) -> -135 | AC85: =AB85+T85 -> 0 | AD85: Scanning Charges for the month of October, 2024 | AH85: 45729
A86: Not Selected | B86: 6779 | C86: 100222426 | D86: ASHLAND SPECIALITY CHEMICAL | E86: 2025 | F86: 3 | G86: 45729 | H86: 1800001430 | I86: DR | J86: 45729 | K86: 45733 | L86: NA | M86: 246779411319 | N86: 212100 | O86: Trade Debtors (Ctrl) | Q86: 01 | R86: =_xlfn.XLOOKUP(M86,'Invoice No Ref'!$C:$C,'Invoice No Ref'!$I:$I,,0) -> 6779IV124000264 | S86: USD | T86: 120 | U86: INR | V86: 10402.95 | W86: =V86/T86 -> 86.69125 | X86: 6779224500 | Z86: NA | AA86: 1 | AB86: =_xlfn.XLOOKUP(R86,'Customer Data'!$D:$D,'Customer Data'!$F:$F,,0) -> -120 | AC86: =AB86+T86 -> 0 | AD86: Scanning Charges for the month of November, 2024 | AH86: 45729
A87: Not Selected | B87: 6779 | C87: 100222426 | D87: ASHLAND SPECIALITY CHEMICAL | E87: 2025 | F87: 3 | G87: 45729 | H87: 1800001417 | I87: DR | J87: 45729 | K87: 45733 | L87: NA | M87: 246779411330 | N87: 212100 | O87: Trade Debtors (Ctrl) | Q87: 01 | R87: =_xlfn.XLOOKUP(M87,'Invoice No Ref'!$C:$C,'Invoice No Ref'!$I:$I,,0) -> 6779IV124000273 | S87: USD | T87: 85 | U87: INR | V87: 7368.76 | W87: =V87/T87 -> 86.691294 | X87: 6779224500 | Z87: NA | AA87: 1 | AB87: =_xlfn.XLOOKUP(R87,'Customer Data'!$D:$D,'Customer Data'!$F:$F,,0) -> -85 | AC87: =AB87+T87 -> 0 | AD87: Scanning Charges for the month of December, 2024 | AH87: 45729
A88: Not Selected | B88: 6779 | C88: 100222426 | D88: ASHLAND SPECIALITY CHEMICAL | E88: 2025 | F88: 3 | G88: 45736 | H88: 1800003977 | I88: DR | J88: 45736 | K88: 45737 | L88: NA | M88: 246779413833 | N88: 212100 | O88: Trade Debtors (Ctrl) | Q88: 01 | R88: =_xlfn.XLOOKUP(M88,'Invoice No Ref'!$C:$C,'Invoice No Ref'!$I:$I,,0) -> 6779IV124000286 | S88: USD | T88: 346.96 | U88: INR | V88: 30078.4 | W88: =V88/T88 -> 86.691261 | X88: 6779224500 | Z88: NA | AA88: 1 | AB88: =_xlfn.XLOOKUP(R88,'Customer Data'!$D:$D,'Customer Data'!$F:$F,,0) -> -346.96 | AC88: =AB88+T88 -> 0 | AD88: Transportation Inbound Jan 25 | AH88: 45736
A89: Not Selected | B89: 6779 | C89: 100222426 | D89: ASHLAND SPECIALITY CHEMICAL | E89: 2025 | F89: 3 | G89: 45736 | H89: 1800003944 | I89: DR | J89: 45736 | K89: 45737 | L89: NA | M89: 246779413973 | N89: 212100 | O89: Trade Debtors (Ctrl) | Q89: 01 | R89: =_xlfn.XLOOKUP(M89,'Invoice No Ref'!$C:$C,'Invoice No Ref'!$I:$I,,0) -> #N/A | S89: USD | T89: 123.56 | U89: INR | V89: 10711.57 | W89: =V89/T89 -> 86.691243 | X89: 6779224500 | Z89: NA | AA89: 1 | AB89: =_xlfn.XLOOKUP(R89,'Customer Data'!$D:$D,'Customer Data'!$F:$F,,0) -> #N/A | AD89: Detention Charges for JAN 2025 Exch. Rate 86.60 | AH89: 45736
A90: Not Selected | B90: 6779 | C90: 100222426 | D90: ASHLAND SPECIALITY CHEMICAL | E90: 2025 | F90: 3 | G90: 45736 | H90: 1800004144 | I90: DR | J90: 45736 | K90: 45737 | L90: NA | M90: 246779414012 | N90: 212100 | O90: Trade Debtors (Ctrl) | Q90: 01 | R90: =_xlfn.XLOOKUP(M90,'Invoice No Ref'!$C:$C,'Invoice No Ref'!$I:$I,,0) -> #N/A | S90: USD | T90: 72.89 | U90: INR | V90: 6318.93 | W90: =V90/T90 -> 86.691316 | X90: 6779224500 | Z90: NA | AA90: 1 | AB90: =_xlfn.XLOOKUP(R90,'Customer Data'!$D:$D,'Customer Data'!$F:$F,,0) -> #N/A | AD90: Inbound Handling charges for Jan 2025 | AH90: 45736
A91: Not Selected | B91: 6779 | C91: 100222426 | D91: ASHLAND SPECIALITY CHEMICAL | E91: 2025 | F91: 3 | G91: 45736 | H91: 1800004210 | I91: DR | J91: 45736 | K91: 45737 | L91: NA | M91: 246779414078 | N91: 212100 | O91: Trade Debtors (Ctrl) | Q91: 01 | R91: =_xlfn.XLOOKUP(M91,'Invoice No Ref'!$C:$C,'Invoice No Ref'!$I:$I,,0) -> 6779IV124000245 | S91: USD | T91: 3021.49 | U91: INR | V91: 261936.78 | W91: =V91/T91 -> 86.691262 | X91: 6779224500 | Z91: NA | AA91: 1 | AB91: =_xlfn.XLOOKUP(R91,'Customer Data'!$D:$D,'Customer Data'!$F:$F,,0) -> -3021.49 | AC91: =AB91+T91 -> 0 | AD91: Inbound Handling charges for Sep 2024 | AH91: 45736
A92: Not Selected | B92: 6779 | C92: 100222426 | D92: ASHLAND SPECIALITY CHEMICAL | E92: 2025 | F92: 3 | G92: 45736 | H92: 1800004211 | I92: DR | J92: 45736 | K92: 45737 | L92: NA | M92: 246779414079 | N92: 212100 | O92: Trade Debtors (Ctrl) | Q92: 01 | R92: =_xlfn.XLOOKUP(M92,'Invoice No Ref'!$C:$C,'Invoice No Ref'!$I:$I,,0) -> 6779IV124000244 | S92: USD | T92: 169.92 | U92: INR | V92: 14730.58 | W92: =V92/T92 -> 86.691266 | X92: 6779224500 | Z92: NA | AA92: 1 | AB92: =_xlfn.XLOOKUP(R92,'Customer Data'!$D:$D,'Customer Data'!$F:$F,,0) -> -169.92 | AC92: =AB92+T92 -> 0 | AD92: LCL charges for Sep 2024 | AH92: 45736
A93: Not Selected | B93: 6779 | C93: 100222426 | D93: ASHLAND SPECIALITY CHEMICAL | E93: 2025 | F93: 3 | G93: 45736 | H93: 1800004212 | I93: DR | J93: 45736 | K93: 45737 | L93: NA | M93: 246779414080 | N93: 212100 | O93: Trade Debtors (Ctrl) | Q93: 01 | R93: =_xlfn.XLOOKUP(M93,'Invoice No Ref'!$C:$C,'Invoice No Ref'!$I:$I,,0) -> 6779IV124000243 | S93: USD | T93: 519.2 | U93: INR | V93: 45010.1 | W93: =V93/T93 -> 86.691256 | X93: 6779224500 | Z93: NA | AA93: 1 | AB93: =_xlfn.XLOOKUP(R93,'Customer Data'!$D:$D,'Customer Data'!$F:$F,,0) -> -519.2 | AC93: =AB93+T93 -> 0 | AD93: Cy-WH Destuff charges for Sep 2024 | AH93: 45736
A94: Not Selected | B94: 6779 | C94: 100222426 | D94: ASHLAND SPECIALITY CHEMICAL | E94: 2025 | F94: 3 | G94: 45736 | H94: 1800004473 | I94: DR | J94: 45736 | K94: 45737 | L94: NA | M94: 246779414341 | N94: 212100 | O94: Trade Debtors (Ctrl) | Q94: 01 | R94: =_xlfn.XLOOKUP(M94,'Invoice No Ref'!$C:$C,'Invoice No Ref'!$I:$I,,0) -> 6779IV124000260 | S94: USD | T94: 761.12 | U94: INR | V94: 65982.45 | W94: =V94/T94 -> 86.691258 | X94: 6779224500 | Z94: NA | AA94: 1 | AB94: =_xlfn.XLOOKUP(R94,'Customer Data'!$D:$D,'Customer Data'!$F:$F,,0) -> -761.12 | AC94: =AB94+T94 -> 0 | AD94: Inbound Handling charges for Nov 2024 | AH94: 45736
A95: Not Selected | B95: 6779 | C95: 100222426 | D95: ASHLAND SPECIALITY CHEMICAL | E95: 2025 | F95: 3 | G95: 45736 | H95: 1800004474 | I95: DR | J95: 45736 | K95: 45737 | L95: NA | M95: 246779414342 | N95: 212100 | O95: Trade Debtors (Ctrl) | Q95: 01 | R95: =_xlfn.XLOOKUP(M95,'Invoice No Ref'!$C:$C,'Invoice No Ref'!$I:$I,,0) -> 6779IV124000259 | S95: USD | T95: 198.24 | U95: INR | V95: 17185.68 | W95: =V95/T95 -> 86.691283 | X95: 6779224500 | Z95: NA | AA95: 1 | AB95: =_xlfn.XLOOKUP(R95,'Customer Data'!$D:$D,'Customer Data'!$F:$F,,0) -> -198.24 | AC95: =AB95+T95 -> 0 | AD95: LCL Movement Charges for Nov 2024 | AH95: 45736
A96: Not Selected | B96: 6779 | C96: 100222426 | D96: ASHLAND SPECIALITY CHEMICAL | E96: 2025 | F96: 3 | G96: 45736 | H96: 1800004551 | I96: DR | J96: 45736 | K96: 45737 | L96: NA | M96: 246779414419 | N96: 212100 | O96: Trade Debtors (Ctrl) | Q96: 01 | R96: =_xlfn.XLOOKUP(M96,'Invoice No Ref'!$C:$C,'Invoice No Ref'!$I:$I,,0) -> #N/A | S96: USD | T96: 1003.1 | U96: INR | V96: 86960 | W96: =V96/T96 -> 86.691257 | X96: 6779224500 | Z96: NA | AA96: 1 | AB96: =_xlfn.XLOOKUP(R96,'Customer Data'!$D:$D,'Customer Data'!$F:$F,,0) -> #N/A | AD96: Inbound Handling charges for Jan 2025 | AH96: 45736
A97: Not Selected | B97: 6779 | C97: 100222426 | D97: ASHLAND SPECIALITY CHEMICAL | E97: 2025 | F97: 3 | G97: 45736 | H97: 1800004552 | I97: DR | J97: 45736 | K97: 45737 | L97: NA | M97: 246779414420 | N97: 212100 | O97: Trade Debtors (Ctrl) | Q97: 01 | R97: =_xlfn.XLOOKUP(M97,'Invoice No Ref'!$C:$C,'Invoice No Ref'!$I:$I,,0) -> 6779IV124000280 | S97: USD | T97: 212.4 | U97: INR | V97: 18413.22 | W97: =V97/T97 -> 86.691243 | X97: 6779224500 | Z97: NA | AA97: 1 | AB97: =_xlfn.XLOOKUP(R97,'Customer Data'!$D:$D,'Customer Data'!$F:$F,,0) -> -212.4 | AC97: =AB97+T97 -> 0 | AD97: Loose Unloading charges for Jan 2025 | AH97: 45736
A98: Not Selected | B98: 6779 | C98: 100222426 | D98: ASHLAND SPECIALITY CHEMICAL | E98: 2025 | F98: 3 | G98: 45736 | H98: 1800004553 | I98: DR | J98: 45736 | K98: 45737 | L98: NA | M98: 246779414421 | N98: 212100 | O98: Trade Debtors (Ctrl) | Q98: 01 | R98: =_xlfn.XLOOKUP(M98,'Invoice No Ref'!$C:$C,'Invoice No Ref'!$I:$I,,0) -> 6779IV124000268 | S98: USD | T98: 169.92 | U98: INR | V98: 14730.58 | W98: =V98/T98 -> 86.691266 | X98: 6779224500 | Z98: NA | AA98: 1 | AB98: =_xlfn.XLOOKUP(R98,'Customer Data'!$D:$D,'Customer Data'!$F:$F,,0) -> -169.92 | AC98: =AB98+T98 -> 0 | AD98: LCL charges for Jan 2025 | AH98: 45736
A99: Not Selected | B99: 6779 | C99: 100222426 | D99: ASHLAND SPECIALITY CHEMICAL | E99: 2025 | F99: 3 | G99: 45736 | H99: 1800004554 | I99: DR | J99: 45736 | K99: 45737 | L99: NA | M99: 246779414422 | N99: 212100 | O99: Trade Debtors (Ctrl) | Q99: 01 | R99: =_xlfn.XLOOKUP(M99,'Invoice No Ref'!$C:$C,'Invoice No Ref'!$I:$I,,0) -> 6779IV124000275 | S99: USD | T99: 520.44 | U99: INR | V99: 45117.6 | W99: =V99/T99 -> 86.691261 | X99: 6779224500 | Z99: NA | AA99: 1 | AB99: =_xlfn.XLOOKUP(R99,'Customer Data'!$D:$D,'Customer Data'!$F:$F,,0) -> -520.44 | AC99: =AB99+T99 -> 0 | AD99: Transportation Inbound charges for Jan 2025 | AH99: 45736
A100: Not Selected | B100: 6779 | C100: 100222426 | D100: ASHLAND SPECIALITY CHEMICAL | E100: 2025 | F100: 3 | G100: 45736 | H100: 1800004555 | I100: DR | J100: 45736 | K100: 45737 | L100: NA | M100: 246779414423 | N100: 212100 | O100: Trade Debtors (Ctrl) | Q100: 01 | R100: =_xlfn.XLOOKUP(M100,'Invoice No Ref'!$C:$C,'Invoice No Ref'!$I:$I,,0) -> 6779IV124000277 | S100: USD | T100: 420 | U100: INR | V100: 36410.33 | W100: =V100/T100 -> 86.691262 | X100: 6779224500 | Z100: NA | AA100: 1 | AB100: =_xlfn.XLOOKUP(R100,'Customer Data'!$D:$D,'Customer Data'!$F:$F,,0) -> -420 | AC100: =AB100+T100 -> 0 | AD100: Empty Cont Outbound charges for Jan 2025 | AH100: 45736
A101: Not Selected | B101: 6779 | C101: 100222426 | D101: ASHLAND SPECIALITY CHEMICAL | E101: 2025 | F101: 3 | G101: 45736 | H101: 1800004935 | I101: DR | J101: 45736 | K101: 45737 | L101: NA | M101: 246779414803 | N101: 212100 | O101: Trade Debtors (Ctrl) | Q101: 01 | R101: =_xlfn.XLOOKUP(M101,'Invoice No Ref'!$C:$C,'Invoice No Ref'!$I:$I,,0) -> #N/A | S101: USD | T101: 17.7 | U101: INR | V101: 1534.44 | W101: =V101/T101 -> 86.691525 | X101: 6779224500 | Z101: NA | AA101: 1 | AB101: =_xlfn.XLOOKUP(R101,'Customer Data'!$D:$D,'Customer Data'!$F:$F,,0) -> #N/A | AD101: Outbound Handling charges for Jan 2025 | AH101: 45736
A102: Not Selected | B102: 6779 | C102: 100222426 | D102: ASHLAND SPECIALITY CHEMICAL | E102: 2025 | F102: 3 | G102: 45736 | H102: 1800004936 | I102: DR | J102: 45736 | K102: 45737 | L102: NA | M102: 246779414804 | N102: 212100 | O102: Trade Debtors (Ctrl) | Q102: 01 | R102: =_xlfn.XLOOKUP(M102,'Invoice No Ref'!$C:$C,'Invoice No Ref'!$I:$I,,0) -> #N/A | S102: USD | T102: 109.15 | U102: INR | V102: 9462.35 | W102: =V102/T102 -> 86.691251 | X102: 6779224500 | Z102: NA | AA102: 1 | AB102: =_xlfn.XLOOKUP(R102,'Customer Data'!$D:$D,'Customer Data'!$F:$F,,0) -> #N/A | AD102: Outbound Handling charges for Jan 2025 | AH102: 45736
A103: Not Selected | B103: 6779 | C103: 100222426 | D103: ASHLAND SPECIALITY CHEMICAL | E103: 2025 | F103: 3 | G103: 45736 | H103: 1800004937 | I103: DR | J103: 45736 | K103: 45737 | L103: NA | M103: 246779414805 | N103: 212100 | O103: Trade Debtors (Ctrl) | Q103: 01 | R103: =_xlfn.XLOOKUP(M103,'Invoice No Ref'!$C:$C,'Invoice No Ref'!$I:$I,,0) -> #N/A | S103: USD | T103: 8.85 | U103: INR | V103: 767.22 | W103: =V103/T103 -> 86.691525 | X103: 6779224500 | Z103: NA | AA103: 1 | AB103: =_xlfn.XLOOKUP(R103,'Customer Data'!$D:$D,'Customer Data'!$F:$F,,0) -> #N/A | AD103: Outbound Handling charges for Jan 2025 | AH103: 45736
A104: Not Selected | B104: 6779 | C104: 100222426 | D104: ASHLAND SPECIALITY CHEMICAL | E104: 2025 | F104: 3 | G104: 45736 | H104: 1800004938 | I104: DR | J104: 45736 | K104: 45737 | L104: NA | M104: 246779414806 | N104: 212100 | O104: Trade Debtors (Ctrl) | Q104: 01 | R104: =_xlfn.XLOOKUP(M104,'Invoice No Ref'!$C:$C,'Invoice No Ref'!$I:$I,,0) -> #N/A | S104: USD | T104: 203.55 | U104: INR | V104: 17646.01 | W104: =V104/T104 -> 86.69128 | X104: 6779224500 | Z104: NA | AA104: 1 | AB104: =_xlfn.XLOOKUP(R104,'Customer Data'!$D:$D,'Customer Data'!$F:$F,,0) -> #N/A | AD104: Outbound Handling charges for Jan 2025 | AH104: 45736
A105: Not Selected | B105: 6779 | C105: 100222426 | D105: ASHLAND SPECIALITY CHEMICAL | E105: 2025 | F105: 3 | G105: 45736 | H105: 1800004939 | I105: DR | J105: 45736 | K105: 45737 | L105: NA | M105: 246779414807 | N105: 212100 | O105: Trade Debtors (Ctrl) | Q105: 01 | R105: =_xlfn.XLOOKUP(M105,'Invoice No Ref'!$C:$C,'Invoice No Ref'!$I:$I,,0) -> #N/A | S105: USD | T105: 9.4 | U105: INR | V105: 814.9 | W105: =V105/T105 -> 86.691489 | X105: 6779224500 | Z105: NA | AA105: 1 | AB105: =_xlfn.XLOOKUP(R105,'Customer Data'!$D:$D,'Customer Data'!$F:$F,,0) -> #N/A | AD105: Outbound Handling charges for Jan 2025 | AH105: 45736
A106: Not Selected | B106: 6779 | C106: 100222426 | D106: ASHLAND SPECIALITY CHEMICAL | E106: 2025 | F106: 3 | G106: 45736 | H106: 1800004145 | I106: DR | J106: 45736 | K106: 45737 | L106: NA | M106: 246779414013 | N106: 212100 | O106: Trade Debtors (Ctrl) | Q106: 01 | R106: =_xlfn.XLOOKUP(M106,'Invoice No Ref'!$C:$C,'Invoice No Ref'!$I:$I,,0) -> #N/A | S106: USD | T106: 81.04 | U106: INR | V106: 7025.46 | W106: =V106/T106 -> 86.691264 | X106: 6779224500 | Z106: NA | AA106: 1 | AB106: =_xlfn.XLOOKUP(R106,'Customer Data'!$D:$D,'Customer Data'!$F:$F,,0) -> #N/A | AD106: Inbound Handling charges for Jan 2025 | AH106: 45736
A107: Not Selected | B107: 6779 | C107: 100222426 | D107: ASHLAND SPECIALITY CHEMICAL | E107: 2025 | F107: 3 | G107: 45736 | H107: 1800004306 | I107: DR | J107: 45736 | K107: 45737 | L107: NA | M107: 246779414174 | N107: 212100 | O107: Trade Debtors (Ctrl) | Q107: 01 | R107: =_xlfn.XLOOKUP(M107,'Invoice No Ref'!$C:$C,'Invoice No Ref'!$I:$I,,0) -> 6779IV124000246 | S107: USD | T107: 976.39 | U107: INR | V107: 84644.48 | W107: =V107/T107 -> 86.691261 | X107: 6779224500 | Z107: NA | AA107: 1 | AB107: =_xlfn.XLOOKUP(R107,'Customer Data'!$D:$D,'Customer Data'!$F:$F,,0) -> -976.39 | AC107: =AB107+T107 -> 0 | AD107: Outbound Handling charges for Sep 2024 | AH107: 45736
A108: Not Selected | B108: 6779 | C108: 100222426 | D108: ASHLAND SPECIALITY CHEMICAL | E108: 2025 | F108: 3 | G108: 45736 | H108: 1800004686 | I108: DR | J108: 45736 | K108: 45737 | L108: NA | M108: 246779414554 | N108: 212100 | O108: Trade Debtors (Ctrl) | Q108: 01 | R108: =_xlfn.XLOOKUP(M108,'Invoice No Ref'!$C:$C,'Invoice No Ref'!$I:$I,,0) -> 6779IV124000253 | S108: USD | T108: 94.4 | U108: INR | V108: 8183.65 | W108: =V108/T108 -> 86.691208 | X108: 6779224500 | Z108: NA | AA108: 1 | AB108: =_xlfn.XLOOKUP(R108,'Customer Data'!$D:$D,'Customer Data'!$F:$F,,0) -> -94.4 | AC108: =AB108+T108 -> 0 | AD108: CY-MOVEMENT CHARGES for Oct 2024 | AH108: 45736
A109: Not Selected | B109: 6779 | C109: 100222426 | D109: ASHLAND SPECIALITY CHEMICAL | E109: 2025 | F109: 3 | G109: 45736 | H109: 1800004687 | I109: DR | J109: 45736 | K109: 45737 | L109: NA | M109: 246779414555 | N109: 212100 | O109: Trade Debtors (Ctrl) | Q109: 01 | R109: =_xlfn.XLOOKUP(M109,'Invoice No Ref'!$C:$C,'Invoice No Ref'!$I:$I,,0) -> 6779IV124000254 | S109: USD | T109: 1548.45 | U109: INR | V109: 134237.08 | W109: =V109/T109 -> 86.691259 | X109: 6779224500 | Z109: NA | AA109: 1 | AB109: =_xlfn.XLOOKUP(R109,'Customer Data'!$D:$D,'Customer Data'!$F:$F,,0) -> -1548.45 | AC109: =AB109+T109 -> 0 | AD109: Outbound Handling charges for Oct 2024 | AH109: 45736
A110: Not Selected | B110: 6779 | C110: 100222426 | D110: ASHLAND SPECIALITY CHEMICAL | E110: 2025 | F110: 3 | G110: 45736 | H110: 1800004760 | I110: DR | J110: 45736 | K110: 45737 | L110: NA | M110: 246779414628 | N110: 212100 | O110: Trade Debtors (Ctrl) | Q110: 01 | R110: =_xlfn.XLOOKUP(M110,'Invoice No Ref'!$C:$C,'Invoice No Ref'!$I:$I,,0) -> 6779IV124000262 | S110: USD | T110: 1838.27 | U110: INR | V110: 159361.94 | W110: =V110/T110 -> 86.691259 | X110: 6779224500 | Z110: NA | AA110: 1 | AB110: =_xlfn.XLOOKUP(R110,'Customer Data'!$D:$D,'Customer Data'!$F:$F,,0) -> -1838.27 | AC110: =AB110+T110 -> 0 | AD110: Outbound Handling charges for Nov 2024 | AH110: 45736
A111: Not Selected | B111: 6779 | C111: 100222426 | D111: ASHLAND SPECIALITY CHEMICAL | E111: 2025 | F111: 3 | G111: 45736 | H111: 1800004761 | I111: DR | J111: 45736 | K111: 45737 | L111: NA | M111: 246779414629 | N111: 212100 | O111: Trade Debtors (Ctrl) | Q111: 01 | R111: =_xlfn.XLOOKUP(M111,'Invoice No Ref'!$C:$C,'Invoice No Ref'!$I:$I,,0) -> 6779IV124000261 | S111: USD | T111: 23.6 | U111: INR | V111: 2045.91 | W111: =V111/T111 -> 86.691102 | X111: 6779224500 | Z111: NA | AA111: 1 | AB111: =_xlfn.XLOOKUP(R111,'Customer Data'!$D:$D,'Customer Data'!$F:$F,,0) -> -23.6 | AC111: =AB111+T111 -> 0 | AD111: CY-MOVEMENT CHARGES for Nov 2024 | AH111: 45736
...

Sheet Customer Data
A1: Document Type | B1: Document Number | C1: Document Date | D1: Reference | E1: Document currency | F1: Amount in doc. curr. | G1: Local Currency | H1: Amount in local currency | I1: Vlookup | J1: Difference | K1: Clearing Document | L1: Clearing date | M1: Text
A2: KR | B2: 1900008116 | C2: 45702 | D2: 6779IV124000285 | E2: USD | F2: -200 | G2: USD | H2: -200 | I2: =_xlfn.XLOOKUP(D2,'Ascendus data'!$R:$R,'Ascendus data'!$T:$T,,0) -> 354 | J2: =H2+I2 -> 154 | K2: 2000002627 | L2: 45751 | M2: Scanning Charges-Jan25
A3: KR | B3: 1900008117 | C3: 45702 | D3: 6779IV124000244 | E3: USD | F3: -169.92 | G3: USD | H3: -169.92 | I3: =_xlfn.XLOOKUP(D3,'Ascendus data'!$R:$R,'Ascendus data'!$T:$T,,0) -> 169.92 | J3: =H3+I3 -> 0 | K3: 2000002627 | L3: 45751 | M3: LCL Charges-Sep24
A4: KR | B4: 1900008118 | C4: 45702 | D4: 6779IV124000235 | E4: USD | F4: -141.07 | G4: USD | H4: -141.07 | I4: =_xlfn.XLOOKUP(D4,'Ascendus data'!$R:$R,'Ascendus data'!$T:$T,,0) -> #N/A | J4: =H4+I4 -> #N/A | K4: 2000002627 | L4: 45751 | M4: Transportation Inbound charges-Aug24
A5: KR | B5: 1900008119 | C5: 45702 | D5: 6779IV124000236 | E5: USD | F5: -236 | G5: USD | H5: -236 | I5: =_xlfn.XLOOKUP(D5,'Ascendus data'!$R:$R,'Ascendus data'!$T:$T,,0) -> #N/A | J5: =H5+I5 -> #N/A | K5: 2000002627 | L5: 45751 | M5: CY Destuff Charges-Aug24
A6: KR | B6: 1900008120 | C6: 45702 | D6: 6779IV124000238 | E6: USD | F6: -23.6 | G6: USD | H6: -23.6 | I6: =_xlfn.XLOOKUP(D6,'Ascendus data'!$R:$R,'Ascendus data'!$T:$T,,0) -> #N/A | J6: =H6+I6 -> #N/A | K6: 2000002627 | L6: 45751 | M6: CY Movement Charges-Aug24
A7: KR | B7: 1900008121 | C7: 45702 | D7: 6779IV124000240 | E7: USD | F7: -165.16 | G7: USD | H7: -165.16 | I7: =_xlfn.XLOOKUP(D7,'Ascendus data'!$R:$R,'Ascendus data'!$T:$T,,0) -> #N/A | J7: =H7+I7 -> #N/A | K7: 2000002627 | L7: 45751 | M7: VAS Activity Charges-Aug24
A8: KR | B8: 1900008122 | C8: 45702 | D8: 6779IV124000241 | E8: USD | F8: -220 | G8: USD | H8: -220 | I8: =_xlfn.XLOOKUP(D8,'Ascendus data'!$R:$R,'Ascendus data'!$T:$T,,0) -> 220 | J8: =H8+I8 -> 0 | K8: 2000002627 | L8: 45751 | M8: Scanning Charges-Aug24
A9: KR | B9: 1900008123 | C9: 45702 | D9: 6779IV124000243 | E9: USD | F9: -519.2 | G9: USD | H9: -519.2 | I9: =_xlfn.XLOOKUP(D9,'Ascendus data'!$R:$R,'Ascendus data'!$T:$T,,0) -> 519.2 | J9: =H9+I9 -> 0 | K9: 2000002627 | L9: 45751 | M9: CY Destuff Charges-Sep24
A10: KR | B10: 1900008124 | C10: 45702 | D10: 6779IV124000256 | E10: USD | F10: -135 | G10: USD | H10: -135 | I10: =_xlfn.XLOOKUP(D10,'Ascendus data'!$R:$R,'Ascendus data'!$T:$T,,0) -> 135 | J10: =H10+I10 -> 0 | K10: 2000002627 | L10: 45751 | M10: Scanning Charges-Oct24
A11: KR | B11: 1900008125 | C11: 45702 | D11: 6779IV124000258 | E11: USD | F11: -118 | G11: USD | H11: -118 | I11: =_xlfn.XLOOKUP(D11,'Ascendus data'!$R:$R,'Ascendus data'!$T:$T,,0) -> 118 | J11: =H11+I11 -> 0 | K11: 2000002627 | L11: 45751 | M11: CY Destuff Charges-Nov24
A12: KR | B12: 1900008126 | C12: 45702 | D12: 6779IV124000260 | E12: USD | F12: -761.12 | G12: USD | H12: -761.12 | I12: =_xlfn.XLOOKUP(D12,'Ascendus data'!$R:$R,'Ascendus data'!$T:$T,,0) -> 761.12 | J12: =H12+I12 -> 0 | K12: 2000002627 | L12: 45751 | M12: Inbound Handling Charges-Nov24
A13: KR | B13: 1900008127 | C13: 45702 | D13: 6779IV124000261 | E13: USD | F13: -23.6 | G13: USD | H13: -23.6 | I13: =_xlfn.XLOOKUP(D13,'Ascendus data'!$R:$R,'Ascendus data'!$T:$T,,0) -> 23.6 | J13: =H13+I13 -> 0 | K13: 2000002627 | L13: 45751 | M13: CY Movement Charges-Nov24
... A54: KG | B54: 1700001171 | C54: 45729 | D54: ASCEN20250102 | E54: USD | F54: 16009 | G54: USD | H54: 16009 | I54: =_xlfn.XLOOKUP(D54,'Ascendus data'!$R:$R,'Ascendus data'!$T:$T,,0) -> #N/A | J54: =H54+I54 -> #N/A | K54: 2000002627 | L54: 45751 | M54: CN against detention-Aug24-Dec24
A55: ZP | B55: 2000002627 | C55: 45751 | D55: Payment | E55: USD | F55: 123978.28 | G55: USD | H55: 123978.28 | I55: =_xlfn.XLOOKUP(D55,'Ascendus data'!$R:$R,'Ascendus data'!$T:$T,,0) -> #N/A | J55: =H55+I55 -> #N/A
A56: KR | B56: 1900008240 | C56: 45735 | D56: 246779413236 | E56: USD | F56: -36.38 | G56: USD | H56: -36.38 | I56: =_xlfn.XLOOKUP(D56,'Ascendus data'!$M:$M,'Ascendus data'!$T:$T,,0) -> 36.38 | J56: =H56+I56 -> 0 | K56: 2000002693 | L56: 45824 | M56: SSR charges - Feb 25
A57: KR | B57: 1900008241 | C57: 45735 | D57: 246779413237 | E57: USD | F57: -27.3 | G57: USD | H57: -27.3 | I57: =_xlfn.XLOOKUP(D57,'Ascendus data'!$M:$M,'Ascendus data'!$T:$T,,0) -> 27.3 | J57: =H57+I57 -> 0 | K57: 2000002693 | L57: 45824 | M57: SSR charges - Feb 25
A58: KR | B58: 1900008242 | C58: 45735 | D58: 246779413238 | E58: USD | F58: -20.47 | G58: USD | H58: -20.47 | I58: =_xlfn.XLOOKUP(D58,'Ascendus data'!$M:$M,'Ascendus data'!$T:$T,,0) -> 20.47 | J58: =H58+I58 -> 0 | K58: 2000002693 | L58: 45824 | M58: SSR charges - Feb 25
A59: KR | B59: 1900008243 | C59: 45735 | D59: 246779413239 | E59: USD | F59: -68.24 | G59: USD | H59: -68.24 | I59: =_xlfn.XLOOKUP(D59,'Ascendus data'!$M:$M,'Ascendus data'!$T:$T,,0) -> 68.24 | J59: =H59+I59 -> 0 | K59: 2000002693 | L59: 45824 | M59: SSR charges - Feb 25
A60: KR | B60: 1900008244 | C60: 45736 | D60: 246779413638 | E60: USD | F60: -59.41 | G60: USD | H60: -59.41 | I60: =_xlfn.XLOOKUP(D60,'Ascendus data'!$M:$M,'Ascendus data'!$T:$T,,0) -> 59.41 | J60: =H60+I60 -> 0 | K60: 2000002693 | L60: 45824 | M60: Empty Lolo charges - Feb 25
A61: KR | B61: 1900008245 | C61: 45736 | D61: 246779413811 | E61: USD | F61: -200.6 | G61: USD | H61: -200.6 | I61: =_xlfn.XLOOKUP(D61,'Ascendus data'!$M:$M,'Ascendus data'!$T:$T,,0) -> 200.6 | J61: =H61+I61 -> 0 | K61: 2000002693 | L61: 45824 | M61: Scanning charges - Feb 25
A62: KR | B62: 1900008246 | C62: 45736 | D62: 246779414481 | E62: USD | F62: -42.48 | G62: USD | H62: -42.48 | I62: =_xlfn.XLOOKUP(D62,'Ascendus data'!$M:$M,'Ascendus data'!$T:$T,,0) -> 42.48 | J62: =H62+I62 -> 0 | K62: 2000002693 | L62: 45824 | M62: Handling charges- Feb 25
A63: KR | B63: 1900008247 | C63: 45736 | D63: 246779414482 | E63: USD | F63: -177 | G63: USD | H63: -177 | I63: =_xlfn.XLOOKUP(D63,'Ascendus data'!$M:$M,'Ascendus data'!$T:$T,,0) -> 177 | J63: =H63+I63 -> 0 | K63: 2000002693 | L63: 45824 | M63: Inbound Handling charges- Feb 25
A64: KR | B64: 1900008248 | C64: 45736 | D64: 246779414483 | E64: USD | F64: -23.6 | G64: USD | H64: -23.6 | I64: =_xlfn.XLOOKUP(D64,'Ascendus data'!$M:$M,'Ascendus data'!$T:$T,,0) -> 23.6 | J64: =H64+I64 -> 0 | K64: 2000002693 | L64: 45824 | M64: CY- Movement charges - Feb 25
A65: KR | B65: 1900008249 | C65: 45736 | D65: 246779414484 | E65: USD | F65: -173.48 | G65: USD | H65: -173.48 | I65: =_xlfn.XLOOKUP(D65,'Ascendus data'!$M:$M,'Ascendus data'!$T:$T,,0) -> 173.48 | J65: =H65+I65 -> 0 | K65: 2000002693 | L65: 45824 | M65: Transportation charges - Feb 25
A66: KR | B66: 1900008250 | C66: 45736 | D66: 246779414755 | E66: USD | F66: -419.36 | G66: USD | H66: -419.36 | I66: =_xlfn.XLOOKUP(D66,'Ascendus data'!$M:$M,'Ascendus data'!$T:$T,,0) -> 419.36 | J66: =H66+I66 -> 0 | K66: 2000002693 | L66: 45824 | M66: Outbound Handling charges- Feb 25
A67: KR | B67: 1900008251 | C67: 45736 | D67: 246779414756 | E67: USD | F67: -81.21 | G67: USD | H67: -81.21 | I67: =_xlfn.XLOOKUP(D67,'Ascendus data'!$M:$M,'Ascendus data'!$T:$T,,0) -> 81.21 | J67: =H67+I67 -> 0 | K67: 2000002693 | L67: 45824 | M67: Handling charges- Feb 25
... A78: KR | B78: 1900008262 | C78: 45736 | D78: 256779417737 | E78: USD | F78: -950.61 | G78: USD | H78: -950.61 | I78: =_xlfn.XLOOKUP(D78,'Ascendus data'!$M:$M,'Ascendus data'!$T:$T,,0) -> 950.61 | J78: =H78+I78 -> 0 | K78: 2000002693 | L78: 45824 | M78: Outbound Handling charges- Feb 25
A79: ZP | B79: 2000002693 | C79: 45824 | D79: Payment | E79: USD | F79: 19172.47 | G79: USD | H79: 19172.47 | I79: =_xlfn.XLOOKUP(D79,'Ascendus data'!$R:$R,'Ascendus data'!$T:$T,,0) -> #N/A | J79: =H79+I79 -> #N/A | K79: 2000002693 | L79: 45824
A80: KR | B80: 1900008270 | C80: 45763 | D80: 256779411925 | E80: USD | F80: -3.48 | G80: USD | H80: -3.48 | I80: =_xlfn.XLOOKUP(D80,'Ascendus data'!$M:$M,'Ascendus data'!$T:$T,,0) -> 3.48 | J80: =H80+I80 -> 0 | K80: 2000002708 | L80: 45833 | M80: HPCU2278439-Port SSR Shifting Mar 2025.
A81: KR | B81: 1900008271 | C81: 45763 | D81: 256779411926 | E81: USD | F81: -13.94 | G81: USD | H81: -13.94 | I81: =_xlfn.XLOOKUP(D81,'Ascendus data'!$M:$M,'Ascendus data'!$T:$T,,0) -> 13.94 | J81: =H81+I81 -> 0 | K81: 2000002708 | L81: 45833 | M81: TCNU6507209-Port SSR Shifting Mar 2025.
A82: KR | B82: 1900008272 | C82: 45763 | D82: 256779412079 | E82: USD | F82: -116.73 | G82: USD | H82: -116.73 | I82: =_xlfn.XLOOKUP(D82,'Ascendus data'!$M:$M,'Ascendus data'!$T:$T,,0) -> 116.73 | J82: =H82+I82 -> 0 | K82: 2000002708 | L82: 45833 | M82: VAS Activity
A83: KR | B83: 1900008273 | C83: 45750 | D83: 256779410026 | E83: USD | F83: -45.68 | G83: USD | H83: -45.68 | I83: =_xlfn.XLOOKUP(D83,'Ascendus data'!$M:$M,'Ascendus data'!$T:$T,,0) -> 45.68 | J83: =H83+I83 -> 0 | K83: 2000002708 | L83: 45833 | M83: Loose unloading charges Mar 2025
A84: KR | B84: 1900008274 | C84: 45750 | D84: 256779410027 | E84: USD | F84: -56.64 | G84: USD | H84: -56.64 | I84: =_xlfn.XLOOKUP(D84,'Ascendus data'!$M:$M,'Ascendus data'!$T:$T,,0) -> 56.64 | J84: =H84+I84 -> 0 | K84: 2000002708 | L84: 45833 | M84: LCL charges - March 2025
A85: KR | B85: 1900008275 | C85: 45750 | D85: 256779410028 | E85: USD | F85: -455.62 | G85: USD | H85: -455.62 | I85: =_xlfn.XLOOKUP(D85,'Ascendus data'!$M:$M,'Ascendus data'!$T:$T,,0) -> 455.62 | J85: =H85+I85 -> 0 | K85: 2000002708 | L85: 45833 | M85: Transportation Inbound charges- Mar 25
A86: KR | B86: 1900008276 | C86: 45750 | D86: 256779410029 | E86: USD | F86: -210 | G86: USD | H86: -210 | I86: =_xlfn.XLOOKUP(D86,'Ascendus data'!$M:$M,'Ascendus data'!$T:$T,,0) -> 210 | J86: =H86+I86 -> 0 | K86: 2000002708 | L86: 45833 | M86: Outbound charges- Mar 25
A87: KR | B87: 1900008277 | C87: 45750 | D87: 256779410030 | E87: USD | F87: -70.8 | G87: USD | H87: -70.8 | I87: =_xlfn.XLOOKUP(D87,'Ascendus data'!$M:$M,'Ascendus data'!$T:$T,,0) -> 70.8 | J87: =H87+I87 -> 0 | K87: 2000002708 | L87: 45833 | M87: CY - Destuff charges - March 2025
A88: KR | B88: 1900008278 | C88: 45750 | D88: 256779410097 | E88: USD | F88: -191.18 | G88: USD | H88: -191.18 | I88: =_xlfn.XLOOKUP(D88,'Ascendus data'!$M:$M,'Ascendus data'!$T:$T,,0) -> 191.18 | J88: =H88+I88 -> 0 | K88: 2000002708 | L88: 45833 | M88: Inbound Handling charges- Mar 25
A89: KR | B89: 1900008279 | C89: 45750 | D89: 256779410025 | E89: USD | F89: -407.28 | G89: USD | H89: -407.28 | I89: =_xlfn.XLOOKUP(D89,'Ascendus data'!$M:$M,'Ascendus data'!$T:$T,,0) -> 407.28 | J89: =H89+I89 -> 0 | K89: 2000002708 | L89: 45833 | M89: Inbound Handling charges- Mar 25
A90: KR | B90: 1900008280 | C90: 45750 | D90: 256779410180 | E90: USD | F90: -68.15 | G90: USD | H90: -68.15 | I90: =_xlfn.XLOOKUP(D90,'Ascendus data'!$M:$M,'Ascendus data'!$T:$T,,0) -> 68.15 | J90: =H90+I90 -> 0 | K90: 2000002708 | L90: 45833 | M90: VAS Activity Charges-Mar.25
A91: KR | B91: 1900008281 | C91: 45763 | D91: 256779411729 | E91: USD | F91: -51.12 | G91: USD | H91: -51.12 | I91: =_xlfn.XLOOKUP(D91,'Ascendus data'!$M:$M,'Ascendus data'!$T:$T,,0) -> 51.12 | J91: =H91+I91 -> 0 | K91: 2000002708 | L91: 45833 | M91: Detention charges - 15th March 25
... A98: KR | B98: 1900008290 | C98: 45769 | D98: 256779412594 | E98: USD | F98: -1779.06 | G98: USD | H98: -1779.06 | I98: =_xlfn.XLOOKUP(D98,'Ascendus data'!$M:$M,'Ascendus data'!$T:$T,,0) -> 1779.06 | J98: =H98+I98 -> 0 | K98: 2000002708 | L98: 45833 | M98: Inbound Handling charges
A99: ZP | B99: 2000002708 | C99: 45833 | D99: Payment | E99: USD | F99: 19783.53 | G99: USD | H99: 19783.53 | I99: =_xlfn.XLOOKUP(D99,'Ascendus data'!$R:$R,'Ascendus data'!$T:$T,,0) -> #N/A | J99: =H99+I99 -> #N/A | K99: 2000002708 | L99: 45833
A100: KR | B100: 1900008320 | C100: 45797 | D100: 256779413463 | E100: USD | F100: -297.43 | G100: USD | H100: -297.43 | I100: =_xlfn.XLOOKUP(D100,'Ascendus data'!$M:$M,'Ascendus data'!$T:$T,,0) -> 297.43 | J100: =H100+I100 -> 0 | K100: 2000002752 | L100: 45884 | M100: Outbound chgs&Loose chgs- 01 - 15 MAY 25
A101: KR | B101: 1900008321 | C101: 45797 | D101: 256779413820 | E101: USD | F101: -41.55 | G101: USD | H101: -41.55 | I101: =_xlfn.XLOOKUP(D101,'Ascendus data'!$M:$M,'Ascendus data'!$T:$T,,0) -> 41.55 | J101: =H101+I101 -> 0 | K101: 2000002752 | L101: 45884 | M101: VAS -1-15 May 25
A102: KR | B102: 1900008322 | C102: 45797 | D102: 256779413865 | E102: USD | F102: -452.8 | G102: USD | H102: -452.8 | I102: =_xlfn.XLOOKUP(D102,'Ascendus data'!$M:$M,'Ascendus data'!$T:$T,,0) -> 452.8 | J102: =H102+I102 -> 0 | K102: 2000002752 | L102: 45884 | M102: Transportation In Chgs - 01 -15 MAY 25
A103: KR | B103: 1900008323 | C103: 45812 | D103: 256779414168 | E103: USD | F103: -376.19 | G103: USD | H103: -376.19 | I103: =_xlfn.XLOOKUP(D103,'Ascendus data'!$M:$M,'Ascendus data'!$T:$T,,0) -> 376.19 | J103: =H103+I103 -> 0 | K103: 2000002752 | L103: 45884 | M103: PORT SSR Chgs - 16 - 31 May 25
A104: KR | B104: 1900008324 | C104: 45812 | D104: 256779414255 | E104: USD | F104: -520.44 | G104: USD | H104: -520.44 | I104: =_xlfn.XLOOKUP(D104,'Ascendus data'!$M:$M,'Ascendus data'!$T:$T,,0) -> 520.44 | J104: =H104+I104 -> 0 | K104: 2000002752 | L104: 45884 | M104: Transportation In Chgs - 16 - 31 May 25
A105: KR | B105: 1900008325 | C105: 45812 | D105: 256779414265 | E105: USD | F105: -149.11 | G105: USD | H105: -149.11 | I105: =_xlfn.XLOOKUP(D105,'Ascendus data'!$M:$M,'Ascendus data'!$T:$T,,0) -> 149.11 | J105: =H105+I105 -> 0 | K105: 2000002752 | L105: 45884 | M105: Empty Lolo Chgs - 01 - 31 MAY 25
A106: KR | B106: 1900008326 | C106: 45812 | D106: 256779414281 | E106: USD | F106: -59 | G106: USD | H106: -59 | I106: =_xlfn.XLOOKUP(D106,'Ascendus data'!$M:$M,'Ascendus data'!$T:$T,,0) -> 59 | J106: =H106+I106 -> 0 | K106: 2000002752 | L106: 45884 | M106: Scanning Chgs - 16 - 31 May 25
A107: KR | B107: 1900008327 | C107: 45770 | D107: 256779412687 | E107: USD | F107: -488.03 | G107: USD | H107: -488.03 | I107: =_xlfn.XLOOKUP(D107,'Ascendus data'!$M:$M,'Ascendus data'!$T:$T,,0) -> 488.03 | J107: =H107+I107 -> 0 | K107: 2000002752 | L107: 45884 | M107: Transportation In Chgs - 01 - 15 Apr 25
A108: KR | B108: 1900008328 | C108: 45770 | D108: 256779412871 | E108: USD | F108: -118.31 | G108: USD | H108: -118.31 | I108: =_xlfn.XLOOKUP(D108,'Ascendus data'!$M:$M,'Ascendus data'!$T:$T,,0) -> 118.31 | J108: =H108+I108 -> 0 | K108: 2000002752 | L108: 45884 | M108: Inbound chgs & LCL Chgs- 01 - 15 Apr 25
A109: KR | B109: 1900008329 | C109: 45770 | D109: 256779412872 | E109: USD | F109: -852.86 | G109: USD | H109: -852.86 | I109: =_xlfn.XLOOKUP(D109,'Ascendus data'!$M:$M,'Ascendus data'!$T:$T,,0) -> 852.86 | J109: =H109+I109 -> 0 | K109: 2000002752 | L109: 45884 | M109: Inbound chgs - 01 - 15 Apr 25
A110: KR | B110: 1900008330 | C110: 45770 | D110: 256779412900 | E110: USD | F110: -455.8 | G110: USD | H110: -455.8 | I110: =_xlfn.XLOOKUP(D110,'Ascendus data'!$M:$M,'Ascendus data'!$T:$T,,0) -> 455.8 | J110: =H110+I110 -> 0 | K110: 2000002752 | L110: 45884 | M110: Outbound chg & Loose chgs- 01 - 15 Apr 25
A111: KR | B111: 1900008331 | C111: 45787 | D111: 256779413223 | E111: USD | F111: -109.35 | G111: USD | H111: -109.35 | I111: =_xlfn.XLOOKUP(D111,'Ascendus data'!$M:$M,'Ascendus data'!$T:$T,,0) -> 109.35 | J111: =H111+I111 -> 0 | K111: 2000002752 | L111: 45884 | M111: VAS - 16-30 April 25
... A120: KR | B120: 1900008338 | C120: 45793 | D120: 256779413289 | E120: USD | F120: -3196.12 | G120: USD | H120: -3196.12 | I120: =_xlfn.XLOOKUP(D120,'Ascendus data'!$M:$M,'Ascendus data'!$T:$T,,0) -> 3196.12 | J120: =H120+I120 -> 0 | K120: 2000002752 | L120: 45884 | M120: Inbound chgs -16 - 30 Apr 25
A121: ZP | B121: 2000002752 | C121: 45884 | D121: Payment | E121: USD | F121: 34635.14 | G121: USD | H121: 34635.14 | I121: =_xlfn.XLOOKUP(D121,'Ascendus data'!$R:$R,'Ascendus data'!$T:$T,,0) -> #N/A | J121: =H121+I121 -> #N/A | K121: 2000002752 | L121: 45884
A122: RE | B122: 5100013131 | C122: 45813 | D122: 256779414082 | E122: USD | F122: -2321.64 | G122: USD | H122: -2321.64 | I122: =_xlfn.XLOOKUP(D122,'Ascendus data'!$M:$M,'Ascendus data'!$T:$T,,0) -> 2321.64 | J122: =H122+I122 -> 0 | K122: 2000002776 | L122: 45915 | M122: Storage 1-31 May-25
A123: KR | B123: 1900008359 | C123: 45842 | D123: 256779415231 | E123: USD | F123: -17.54 | G123: USD | H123: -17.54 | I123: =_xlfn.XLOOKUP(D123,'Ascendus data'!$M:$M,'Ascendus data'!$T:$T,,0) -> 17.54 | J123: =H123+I123 -> 0 | K123: 2000002776 | L123: 45915 | M123: VAS - 16-30 June 25
A124: KR | B124: 1900008360 | C124: 45827 | D124: 256779414727 | E124: USD | F124: -49.94 | G124: USD | H124: -49.94 | I124: =_xlfn.XLOOKUP(D124,'Ascendus data'!$M:$M,'Ascendus data'!$T:$T,,0) -> 49.94 | J124: =H124+I124 -> 0 | K124: 2000002776 | L124: 45915 | M124: VAS 1-15 June 25, Exch 86.10
A125: KR | B125: 1900008361 | C125: 45842 | D125: 256779414896 | E125: USD | F125: -182.09 | G125: USD | H125: -182.09 | I125: =_xlfn.XLOOKUP(D125,'Ascendus data'!$M:$M,'Ascendus data'!$T:$T,,0) -> 182.09 | J125: =H125+I125 -> 0 | K125: 2000002776 | L125: 45915 | M125: Empty Lolo Chgs - 01 - 30 JUN 25
A126: KR | B126: 1900008362 | C126: 45842 | D126: 256779415029 | E126: USD | F126: -56.41 | G126: USD | H126: -56.41 | I126: =_xlfn.XLOOKUP(D126,'Ascendus data'!$M:$M,'Ascendus data'!$T:$T,,0) -> 56.41 | J126: =H126+I126 -> 0 | K126: 2000002776 | L126: 45915 | M126: PORT SSR Chgs June 25
A127: KR | B127: 1900008363 | C127: 45842 | D127: 256779415042 | E127: USD | F127: -32.15 | G127: USD | H127: -32.15 | I127: =_xlfn.XLOOKUP(D127,'Ascendus data'!$M:$M,'Ascendus data'!$T:$T,,0) -> 32.15 | J127: =H127+I127 -> 0 | K127: 2000002776 | L127: 45915 | M127: Bond Stamp Paper Chgs
A128: KR | B128: 1900008365 | C128: 45842 | D128: 256779414994 | E128: USD | F128: -1081.83 | G128: USD | H128: -1081.83 | I128: =_xlfn.XLOOKUP(D128,'Ascendus data'!$M:$M,'Ascendus data'!$T:$T,,0) -> 1081.83 | J128: =H128+I128 -> 0 | K128: 2000002776 | L128: 45915 | M128: Outbound/Loose chgs 16-30 June 25
A129: KR | B129: 1900008366 | C129: 45842 | D129: 256779414864 | E129: USD | F129: -3008.54 | G129: USD | H129: -3008.54 | I129: =_xlfn.XLOOKUP(D129,'Ascendus data'!$M:$M,'Ascendus data'!$T:$T,,0) -> 3008.54 | J129: =H129+I129 -> 0 | K129: 2000002776 | L129: 45915 | M129: Transportation/inbound chgs 16-30 JUNE 25
A130: ZP | B130: 2000002776 | C130: 45915 | D130: Payment | E130: USD | F130: 6750.14 | G130: USD | H130: 6750.14 | I130: =_xlfn.XLOOKUP(D130,'Ascendus data'!$R:$R,'Ascendus data'!$T:$T,,0) -> #N/A | J130: =H130+I130 -> #N/A | K130: 2000002776 | L130: 45915
A131: KR | B131: 1900008385 | C131: 45877 | D131: 256779416099 | E131: USD | F131: -277.3 | G131: USD | H131: -277.3 | I131: =_xlfn.XLOOKUP(D131,'Ascendus data'!$M:$M,'Ascendus data'!$T:$T,,0) -> 277.3 | J131: =H131+I131 -> 0 | K131: 2000002790 | L131: 45925 | M131: Scanning Chgs - 16 - 31 Jul 25
A132: KR | B132: 1900008386 | C132: 45877 | D132: 256779416105 | E132: USD | F132: -46.6 | G132: USD | H132: -46.6 | I132: =_xlfn.XLOOKUP(D132,'Ascendus data'!$M:$M,'Ascendus data'!$T:$T,,0) -> 46.6 | J132: =H132+I132 -> 0 | K132: 2000002790 | L132: 45925 | M132: Detention Chgs - 01 - 31 JUL 25
A133: KR | B133: 1900008387 | C133: 45877 | D133: 256779416129 | E133: USD | F133: -160.55 | G133: USD | H133: -160.55 | I133: =_xlfn.XLOOKUP(D133,'Ascendus data'!$M:$M,'Ascendus data'!$T:$T,,0) -> 160.55 | J133: =H133+I133 -> 0 | K133: 2000002790 | L133: 45925 | M133: Empty Lolo Chgs - 01 - 31 JUL 25
A134: KR | B134: 1900008388 | C134: 45877 | D134: 256779416145 | E134: USD | F134: -188.46 | G134: USD | H134: -188.46 | I134: =_xlfn.XLOOKUP(D134,'Ascendus data'!$M:$M,'Ascendus data'!$T:$T,,0) -> 188.46 | J134: =H134+I134 -> 0 | K134: 2000002790 | L134: 45925 | M134: Bond Stamp Paper Chgs 16 - 31 Jul 25
A135: KR | B135: 1900008389 | C135: 45877 | D135: 256779416477 | E135: USD | F135: -45.69 | G135: USD | H135: -45.69 | I135: =_xlfn.XLOOKUP(D135,'Ascendus data'!$M:$M,'Ascendus data'!$T:$T,,0) -> 45.69 | J135: =H135+I135 -> 0 | K135: 2000002790 | L135: 45925 | M135: VAS 16-31 July 25
A136: KR | B136: 1900008390 | C136: 45877 | D136: 256779416498 | E136: USD | F136: -548.34 | G136: USD | H136: -548.34 | I136: =_xlfn.XLOOKUP(D136,'Ascendus data'!$M:$M,'Ascendus data'!$T:$T,,0) -> 548.34 | J136: =H136+I136 -> 0 | K136: 2000002790 | L136: 45925 | M136: PORT SSR Chgs July 25
A137: RE | B137: 5100013195 | C137: 45843 | D137: 256779415152 | E137: USD | F137: -9905.27 | G137: USD | H137: -9905.27 | I137: =_xlfn.XLOOKUP(D137,'Ascendus data'!$M:$M,'Ascendus data'!$T:$T,,0) -> 9905.27 | J137: =H137+I137 -> 0 | K137: 2000002790 | L137: 45925 | M137: Storage 01-30 June25
A138: RE | B138: 5100013199 | C138: 45877 | D138: 256779416302 | E138: USD | F138: -5299.43 | G138: USD | H138: -5299.43 | I138: =_xlfn.XLOOKUP(D138,'Ascendus data'!$M:$M,'Ascendus data'!$T:$T,,0) -> 5299.43 | J138: =H138+I138 -> 0 | K138: 2000002790 | L138: 45925 | M138: Storage 01-31 July25
A139: RE | B139: 5100013200 | C139: 45843 | D139: 256779415153 | E139: USD | F139: -4354.62 | G139: USD | H139: -4354.62 | I139: =_xlfn.XLOOKUP(D139,'Ascendus data'!$M:$M,'Ascendus data'!$T:$T,,0) -> 4354.62 | J139: =H139+I139 -> 0 | K139: 2000002790 | L139: 45925 | M139: Storage 01-30 June25
A140: RE | B140: 5100013203 | C140: 45877 | D140: 256779416301 | E140: USD | F140: -8709.89 | G140: USD | H140: -8709.89 | I140: =_xlfn.XLOOKUP(D140,'Ascendus data'!$M:$M,'Ascendus data'!$T:$T,,0) -> 8709.59 | J140: =H140+I140 -> -0.3 | K140: 2000002790 | L140: 45925 | M140: Storage 01-31 July25
A141: KR | B141: 1900008398 | C141: 45877 | D141: 256779416189 | E141: USD | F141: -2574.62 | G141: USD | H141: -2574.62 | I141: =_xlfn.XLOOKUP(D141,'Ascendus data'!$M:$M,'Ascendus data'!$T:$T,,0) -> 2574.62 | J141: =H141+I141 -> 0 | K141: 2000002809 | L141: 45945 | M141: Outbound chgs & Loose Chgs - 16 - 31 Jul 25
A142: KR | B142: 1900008399 | C142: 45877 | D142: 256779416151 | E142: USD | F142: -5735.37 | G142: USD | H142: -5735.37 | I142: =_xlfn.XLOOKUP(D142,'Ascendus data'!$M:$M,'Ascendus data'!$T:$T,,0) -> 5735.37 | J142: =H142+I142 -> 0 | K142: 2000002809 | L142: 45945 | M142: Transportation In Chgs - 16 - 31 JUL 25
A143: ZP | B143: 2000002790 | C143: 45925 | D143: Payment | E143: USD | F143: 29536.15 | G143: USD | H143: 29536.15 | I143: =_xlfn.XLOOKUP(D143,'Ascendus data'!$R:$R,'Ascendus data'!$T:$T,,0) -> #N/A | J143: =H143+I143 -> #N/A | K143: 2000002790 | L143: 45925
A144: KR | B144: 1900008420 | C144: 45889 | D144: 256779416792 | E144: USD | F144: -13.72 | G144: USD | H144: -13.72 | I144: =_xlfn.XLOOKUP(D144,'Ascendus data'!$M:$M,'Ascendus data'!$T:$T,,0) -> 13.72 | J144: =H144+I144 -> 0 | K144: 2000002815 | L144: 45954 | M144: Weighment-Aug 25, 1-31
A145: KR | B145: 1900008421 | C145: 45904 | D145: 256779417102 | E145: USD | F145: -66.22 | G145: USD | H145: -66.22 | I145: =_xlfn.XLOOKUP(D145,'Ascendus data'!$M:$M,'Ascendus data'!$T:$T,,0) -> 17.07 | J145: =H145+I145 -> -49.15 | K145: 2000002815 | L145: 45954 | M145: VAS -1-31 Aug 25
A146: ZP | B146: 2000002809 | C146: 45945 | D146: Payment | E146: USD | F146: 8309.99 | G146: USD | H146: 8309.99 | I146: =_xlfn.XLOOKUP(D146,'Ascendus data'!$R:$R,'Ascendus data'!$T:$T,,0) -> #N/A | J146: =H146+I146 -> #N/A | K146: 2000002809 | L146: 45945
A147: ZP | B147: 2000002815 | C147: 45954 | D147: Payment | E147: USD | F147: 79.94 | G147: USD | H147: 79.94 | I147: =_xlfn.XLOOKUP(D147,'Ascendus data'!$R:$R,'Ascendus data'!$T:$T,,0) -> #N/A | J147: =H147+I147 -> #N/A | K147: 2000002815 | L147: 45954
A148: KR | B148: 1900008431 | C148: 45904 | D148: 256779417254 | E148: USD | F148: -51.22 | G148: USD | H148: -51.22 | I148: =_xlfn.XLOOKUP(D148,'Ascendus data'!$M:$M,'Ascendus data'!$T:$T,,0) -> 51.22 | J148: =H148+I148 -> 0 | K148: 2000002840 | L148: 45975 | M148: Bond Stamp Paper Chgs 01 - 31 Aug 25
A149: KR | B149: 1900008432 | C149: 45904 | D149: 256779417249 | E149: USD | F149: -59 | G149: USD | H149: -59 | I149: =_xlfn.XLOOKUP(D149,'Ascendus data'!$M:$M,'Ascendus data'!$T:$T,,0) -> 59 | J149: =H149+I149 -> 0 | K149: 2000002840 | L149: 45975 | M149: Scanning Chgs - 16 - 31 Aug 25
A150: KR | B150: 1900008433 | C150: 45904 | D150: 256779417233 | E150: USD | F150: -710.32 | G150: USD | H150: -710.32 | I150: =_xlfn.XLOOKUP(D150,'Ascendus data'!$M:$M,'Ascendus data'!$T:$T,,0) -> 710.32 | J150: =H150+I150 -> 0 | K150: 2000002840 | L150: 45975 | M150: PORT SSR Chgs Aug 25
A151: KR | B151: 1900008434 | C151: 45904 | D151: 256779417193 | E151: USD | F151: -620.1 | G151: USD | H151: -620.1 | I151: =_xlfn.XLOOKUP(D151,'Ascendus data'!$M:$M,'Ascendus data'!$T:$T,,0) -> 620.1 | J151: =H151+I151 -> 0 | K151: 2000002840 | L151: 45975 | M151: Empty Lolo Chgs - 01 - 31 AUG 25
A152: KR | B152: 1900008435 | C152: 45904 | D152: 256779417189 | E152: USD | F152: -24.9 | G152: USD | H152: -24.9 | I152: =_xlfn.XLOOKUP(D152,'Ascendus data'!$M:$M,'Ascendus data'!$T:$T,,0) -> 24.9 | J152: =H152+I152 -> 0 | K152: 2000002840 | L152: 45975 | M152: Detention Chgs - 01 - 31 AUG 25
A153: KR | B153: 1900008436 | C153: 45904 | D153: 256779417294 | E153: USD | F153: -2063.13 | G153: USD | H153: -2063.13 | I153: =_xlfn.XLOOKUP(D153,'Ascendus data'!$M:$M,'Ascendus data'!$T:$T,,0) -> 2063.13 | J153: =H153+I153 -> 0 | K153: 2000002840 | L153: 45975 | M153: Outbound chgs - 16 - 31 Aug 25 WH 09
A154: KR | B154: 1900008437 | C154: 45904 | D154: 256779417265 | E154: USD | F154: -4958.09 | G154: USD | H154: -4958.09 | I154: =_xlfn.XLOOKUP(D154,'Ascendus data'!$M:$M,'Ascendus data'!$T:$T,,0) -> 4958.09 | J154: =H154+I154 -> 0 | K154: 2000002840 | L154: 45975 | M154: Transportation In Chgs - 16 - 31 AUG 25
A155: KR | B155: 1900008438 | C155: 45904 | D155: 256779417182 | E155: USD | F155: -985.4 | G155: USD | H155: -985.4 | I155: =_xlfn.XLOOKUP(D155,'Ascendus data'!$M:$M,'Ascendus data'!$T:$T,,0) -> 985.4 | J155: =H155+I155 -> 0 | K155: 2000002840 | L155: 45975 | M155: Transportation In Chgs - 16 - 31 Aug 25
A156: KR | B156: 1900008450 | C156: 45937 | D156: 256779418145 | E156: USD | F156: -54.06 | G156: USD | H156: -54.06 | I156: =_xlfn.XLOOKUP(D156,'Ascendus data'!$M:$M,'Ascendus data'!$T:$T,,0) -> 54.06 | J156: =H156+I156 -> 0 | K156: 2000002840 | L156: 45975 | M156: Weighment-16-30 Sept 25
A157: KR | B157: 1900008451 | C157: 45937 | D157: 256779418129 | E157: USD | F157: -122.94 | G157: USD | H157: -122.94 | I157: =_xlfn.XLOOKUP(D157,'Ascendus data'!$M:$M,'Ascendus data'!$T:$T,,0) -> 82.72 | J157: =H157+I157 -> -40.22 | K157: 2000002840 | L157: 45975 | M157: VAS-1-30 Sept 25
A158: KR | B158: 1900008452 | C158: 45938 | D158: 256779418096 | E158: USD | F158: -67.58 | G158: USD | H158: -67.58 | I158: =_xlfn.XLOOKUP(D158,'Ascendus data'!$M:$M,'Ascendus data'!$T:$T,,0) -> 67.58 | J158: =H158+I158 -> 0 | K158: 2000002840 | L158: 45975 | M158: Bond Stamp Paper Chgs 01 - 30 Sep 25
A159: KR | B159: 1900008453 | C159: 45935 | D159: 256779417882 | E159: USD | F159: -603.8 | G159: USD | H159: -603.8 | I159: =_xlfn.XLOOKUP(D159,'Ascendus data'!$M:$M,'Ascendus data'!$T:$T,,0) -> 603.8 | J159: =H159+I159 -> 0 | K159: 2000002840 | L159: 45975 | M159: Empty Lolo Chgs - 01 - 30 SEP 25
... A162: KR | B162: 1900008456 | C162: 45935 | D162: 256779417953 | E162: USD | F162: -3981.8 | G162: USD | H162: -3981.8 | I162: =_xlfn.XLOOKUP(D162,'Ascendus data'!$M:$M,'Ascendus data'!$T:$T,,0) -> 3981.8 | J162: =H162+I162 -> 0 | K162: 2000002840 | L162: 45975 | M162: Outbound chgs - 16 - 30 Sep 25
A163: ZP | B163: 2000002840 | C163: 45975 | D163: Payment | E163: USD | F163: 22973.48 | G163: USD | H163: 22973.48 | I163: =_xlfn.XLOOKUP(D163,'Ascendus data'!$R:$R,'Ascendus data'!$T:$T,,0) -> #N/A | J163: =H163+I163 -> #N/A | K163: 2000002840 | L163: 45975
A164: KR | B164: 1900008479 | C164: 45966 | D164: 256779419239 | E164: USD | F164: -67.62 | G164: USD | H164: -67.62 | I164: =_xlfn.XLOOKUP(D164,'Ascendus data'!$M:$M,'Ascendus data'!$T:$T,,0) -> 67.62 | J164: =H164+I164 -> 0 | K164: 2000002884 | L164: 46015 | M164: Bond Stamp Paper Chgs Oct 25
A165: KR | B165: 1900008480 | C165: 45966 | D165: 256779419214 | E165: USD | F165: -485.95 | G165: USD | H165: -485.95 | I165: =_xlfn.XLOOKUP(D165,'Ascendus data'!$M:$M,'Ascendus data'!$T:$T,,0) -> 485.95 | J165: =H165+I165 -> 0 | K165: 2000002884 | L165: 46015 | M165: PORT SSR Chgs Oct 25
A166: KR | B166: 1900008481 | C166: 45966 | D166: 256779419187 | E166: USD | F166: -503.26 | G166: USD | H166: -503.26 | I166: =_xlfn.XLOOKUP(D166,'Ascendus data'!$M:$M,'Ascendus data'!$T:$T,,0) -> 503.26 | J166: =H166+I166 -> 0 | K166: 2000002884 | L166: 46015 | M166: Empty Lolo Chgs - 01 - 31 OCT 25
...

Sheet Pivot - customer data
C4: Values | D4: Document Type
C5: Sum of Amount in doc. curr. | F5: Sum of Amount in local currency
A6: Months | B6: Document Date | C6: KG | D6: KR | E6: RE | F6: KG | G6: KR | H6: RE
A7: Feb | D7: -21923.99 | E7: -118063.29 | G7: -21923.99 | H7: -118063.29
A8: Mar | C8: 16009 | D8: -2280.14 | F8: 16009 | G8: -2280.14
A9: Apr | D9: -10761.47 | E9: -33703.42 | G9: -10761.47 | H9: -33703.42
A10: May | D10: -5481.61 | E10: -6237.23 | G10: -5481.61 | H10: -6237.23
A11: Jun | D11: -4841.19 | E11: -12657.66 | G11: -4841.19 | H11: -12657.66
A12: Jul | D12: -4378.56 | E12: -14259.89 | G12: -4378.56 | H12: -14259.89
A13: Aug | D13: -9590.65 | E13: -14009.32 | G13: -9590.65 | H13: -14009.32
A14: Sep | D14: -9538.38 | E14: -12299.39 | G14: -9538.38 | H14: -12299.39
A15: Oct | D15: -13501.32 | E15: -14289.84 | G15: -13501.32 | H15: -14289.84
A16: Nov | D16: -10743.75 | G16: -10743.75
B20: Sum of Amount in doc. curr.
A21: Months | B21: KG | C21: KR | D21: RE
A22: Feb | C22: -21923.99 | D22: -118063.29
A23: Mar | B23: 16009 | C23: -2280.14
A24: Apr | C24: -10761.47 | D24: -33703.42
A25: May | C25: -5481.61 | D25: -6237.23
A26: Jun | C26: -4841.19 | D26: -12657.66
A27: Jul | C27: -4378.56 | D27: -14259.89
A28: Aug | C28: -9590.65 | D28: -14009.32
A29: Sep | C29: -9538.38 | D29: -12299.39
A30: Oct | C30: -13501.32 | D30: -14289.84
A31: Nov | C31: -10743.75
A32: Total | B32: =SUM(B22:B31) -> 16009 | C32: =SUM(C22:C31) -> -93041.06 | D32: =SUM(D22:D31) -> -225520.04

Sheet Asendus Data
A1: Cleared/Open Items Symbol | B1: Document Number | C1: Invoice | D1: Document Type | E1: Document Date | F1: Special G/L Ind. | G1: Net Due Date Symbol | H1: Amount in Local Currency | I1: Local Currency | J1: Amount in USD | K1: Clearing Document | L1: Text | M1: Customer | N1: Posting Date | O1: Tax Code | P1: Processor | Q1: Contract Number | R1: G/L Account | S1: Vlookup
B2: 1400000999 | C2: #N/A | D2: DZ | E2: 45891 | H2: -10774245 | I2: INR | J2: #N/A | M2: 100222426 | N2: 45891 | R2: 212100
B3: 1800012797 | C3: 256779417478 | D3: DR | E3: 45920 | H3: 87706.86 | I3: INR | J3: 1002.2 | L3: BOE handling charges | M3: 100222426 | N3: 45920 | O3: O0 | R3: 212100
B4: 1600002320 | C4: 256779421875 | D4: DG | E4: 45923 | H4: -11420.71 | I4: INR | J4: -131.74 | L4: Credit Note Raised against INV_246779413054 | M4: 100222426 | N4: 45923 | O4: O0 | R4: 212100
B5: 1800013204 | C5: 256779417820 | D5: DR | E5: 45924 | H5: 11420.71 | I5: INR | J5: 131.74 | L5: Port SSR Charges - Shifting for Aug to Dec,24. Exc | M5: 100222426 | N5: 45924 | O5: O0 | R5: 212100
B6: 1800014423 | C6: 256779418940 | D6: DR | E6: 45966 | H6: 637020.46 | I6: INR | J6: 7238.59 | L6: Storage -WH 09- 16-31 OCT 25 | M6: 100222426 | N6: 45966 | O6: O0 | R6: 212100
B7: 1800014424 | C7: 256779418941 | D7: DR | E7: 45966 | H7: 674927.92 | I7: INR | J7: 7669.34 | L7: Storage -WH 09- 16-31 OCT 25 | M7: 100222426 | N7: 45966 | O7: O0 | R7: 212100
B8: 1800014902 | C8: 256779419451 | D8: DR | E8: 45981 | H8: 9074.03 | I8: INR | J8: 103.11 | L8: VAS-Nov 1-15, 2025 | M8: 100222426 | N8: 45981 | O8: O0 | R8: 212100
B9: 1800014910 | C9: 256779419459 | D9: DR | E9: 45981 | H9: 1189.81 | I9: INR | J9: 13.52 | L9: Weighment-Nov 1-15, 2025 | M9: 100222426 | N9: 45981 | O9: O0 | R9: 212100
B10: 1800015173 | C10: 256779419674 | D10: DR | E10: 45994 | H10: 790993.26 | I10: INR | J10: 8917.61 | L10: Storage -WH 09- 1-30 Nov 25 | M10: 100222426 | N10: 45994 | O10: O0 | R10: 212100
B11: 1800015174 | C11: 256779419675 | D11: DR | E11: 45994 | H11: 668445.14 | I11: INR | J11: 7536.01 | L11: Storage -WH 09- 1-30 Nov 25 | M11: 100222426 | N11: 45994 | O11: O0 | R11: 212100
B12: 1800015716 | C12: 256779450072 | D12: DR | E12: 46024 | H12: 10707.69 | I12: INR | J12: 118 | L12: Scanning Chgs - 16 - 30 Nov 25 | M12: 100222426 | N12: 46024 | O12: O0 | R12: 212100
B13: 1800015380 | C13: 256779419829 | D13: DR | E13: 45999 | H13: 4957.45 | I13: INR | J13: 55.89 | L13: Bond Stamp Paper Chgs Nov 25 | M13: 100222426 | N13: 45999 | O13: O0 | R13: 212100
B14: 1800015390 | C14: 256779419839 | D14: DR | E14: 45999 | H14: 726007.1 | I14: INR | J14: 3122.18 | L14: Transportation In Chgs - 16 - 30 NOV 25 | M14: 100222426 | N14: 45999 | O14: O0 | R14: 212100
... B137: 1800016811 | C137: 256779450747 | D137: DR | E137: 46034 | H137: 4260.39 | I137: INR | J137: 46.95 | L137: Weighment -NOV 25,16-30 | M137: 100222426 | N137: 46034 | O137: O0 | R137: 212100

Sheet Ascendus Pivot
C2: Sum of Document Currency Value | F2: Sum of Company Code Currency Value
A3: Years | B3: Document Date | C3: DG-Credit Note | D3: DR-Sales | E3: DZ-Payment | F3: DG-Credit Note | G3: DR-Sales | H3: DZ-Payment
A4: 2025 | B4: Feb
A5: 2025 | B5: Mar | D5: 63058.48 | G5: 5466619.1
A6: 2025 | B6: Apr | D6: 125751.78 | G6: 10930574
A7: 2025 | B7: May | C7: -473.94 | D7: 11457.67 | F7: -41086.47 | G7: 985172.85
A8: 2025 | B8: Jun | D8: 17599.15 | E8: -19376.22 | G8: 1504565.1 | H8: -1656776.5
A9: 2025 | B9: Jul | D9: 19661.85 | E9: -19783.53 | G9: 1690932.3 | H9: -1719620.4
A10: 2025 | B10: Aug | D10: 29638.91 | E10: -158563.42 | G10: 2549839 | H10: -13751759
A11: 2025 | B11: Sep | C11: -1082.33 | D11: 24505.42 | E11: -6725.14 | F11: -94610.97 | G11: 2144467 | H11: -588546.12
A12: 2025 | B12: Oct | C12: -3981.8 | D12: 25315.59 | E12: -38217.41 | F12: -351158.01 | G12: 2233401.4 | H12: -3349729
A13: 2025 | B13: Nov | C13: -171.1 | D13: 25800.22 | E13: -22948.48 | F13: -15057.37 | G13: 2270506.8 | H13: -2019544
A14: 2025 | B14: Dec | D14: 29373.84 | E14: -31.91 | G14: 2605463.7 | H14: -2830.42
A15: 2026 | B15: Jan | D15: 32187.51 | E15: -37482.68 | G15: 2920817.9 | H15: -3233319.9
A16: 2026 | B16: Feb | D16: 86.76 | G16: 7837.48
A17: Total | C17: =SUM(C4:C16) -> -5709.17 | D17: =SUM(D4:D16) -> 404437.18 | E17: =SUM(E4:E16) -> -303128.79 | F17: =SUM(F4:F16) -> -501912.82 | G17: =SUM(G5:G16) -> 35310196 | H17: =SUM(H5:H16) -> -26322126
