Workbook

Sheet Summary
A1: Particulars | B1: Amount in Rs.
A2: Balance as per Delight Logistic Pvt Ltd | B2: ='Customer Data'!F412 -> 896920.81
A3: Add: TDS To booked in Capital land's books | B3: =TDS!D1 -> 20804.91
A4: Less: TDS Already Booked in Capital land's Books | B4: =-'Payment Reco'!H6 -> -4599
A5: Add: Invoices / CN not recorded in customer books | B5: ='Invoices Not in customer books'!H39 -> 416781.42
A6: Less: Invoices not in Capital land's books | B6: =-'Invoices not in Ascendus books'!F5 -> -48765
A7: Derived balance | B7: =SUM(B2:B6) -> 1281143.1
A8: Balance as per Ascent | B8: ='Ascendus Data'!T114 -> 1270668.6
A9: Difference | B9: =B7-B8 -> 10474.54

Sheet Invoices Not in customer books
A3: Document Number | B3: Document Type | C3: Document Date | D3: Reference | E3: Document Currency Key | F3: Document Currency Value | G3: Company Code Currency Key | H3: Company Code Currency Value | I3: Text
A4: 1800012317 | B4: DR | C4: 45904 | D4: 256779416940 | E4: USD | F4: 1440.32 | G4: INR | H4: 126048.64 | I4: CODC Storage - 16-31 Aug 25
A5: 1800011529 | B5: DR | C5: 45877 | D5: 256779416379 | E5: USD | F5: 546.72 | G5: INR | H5: 47034.39 | I5: Storage 16-31 Jul 25-WH 03
A6: 1800005794 | B6: DR | C6: 45751 | D6: 256779410686 | E6: USD | F6: 447.59 | G6: INR | H6: 38905.34 | I6: Storage charges for Feb 2025
A7: 1800005668 | B7: DR | C7: 45751 | D7: 256779410560 | E7: USD | F7: 392.93 | G7: INR | H7: 34154.19 | I7: Storage charges for Jan 2025
A8: 1800011853 | B8: DR | C8: 45877 | D8: 256779416504 | E8: USD | F8: 269.8 | G8: INR | H8: 23210.93 | I8: PORT SSR Chgs July 25
A9: 1800005578 | B9: DR | C9: 45751 | D9: 256779410470 | E9: USD | F9: 206.48 | G9: INR | H9: 17947.62 | I9: Storage charges for March 2025
A10: 1800006043 | B10: DR | C10: 45763 | D10: 256779410934 | E10: USD | F10: 204.98 | G10: INR | H10: 17817.23 | I10: Storage charges for March 2025
A11: 1800011389 | B11: DR | C11: 45877 | D11: 256779416239 | E11: USD | F11: 132.4 | G11: INR | H11: 11390.39 | I11: CODC Transportation IN chgs - 16 - 31 Jul 25
A12: 1800008919 | B12: DR | C12: 45798 | D12: 256779413683 | E12: USD | F12: 112.44 | G12: INR | H12: 9668.01 | I12: Storage 1-15 May-25,WH-3
A13: 1800007596 | B13: DR | C13: 45769 | D13: 256779412487 | E13: USD | F13: 104.6 | G13: INR | H13: 9092.02 | I13: Inbound Handling charges for Feb 2025
A14: 1800011825 | B14: DR | C14: 45877 | D14: 256779416134 | E14: USD | F14: 102.45 | G14: INR | H14: 8813.79 | I14: Empty Lolo Chgs - 01 - 31 JUL 25
A15: 1800009285 | B15: DR | C15: 45813 | D15: 256779414049 | E15: USD | F15: 92.68 | G15: INR | H15: 7923.29 | I15: Storage 16-31 May-25,WH-3
... A38: 1800006806 | B38: DR | C38: 45763 | D38: 256779411697 | E38: USD | F38: 1.18 | G38: INR | H38: 102.57 | I38: Loose Unloading Charges Aug 24
H39: =SUM(H4:H38) -> 416781.42

Sheet Invoice no ref in cutomer books
H1: 716867.69
A2: Document Number | B2: Document Type | C2: Document Date | D2: Reference | E2: Document Currency Key | F2: Document Currency Value | G2: Company Code Currency Key | H2: Company Code Currency Value | I2: Text | J2: Date | K2: Particulars | L2: Transaction No. | M2: Credit (INR) | N2: TDS | O2: Rate
A3: 1800017085 | B3: DR | C3: 46045 | D3: 256779450977 | E3: USD | F3: 9.12 | G3: INR | H3: 827.58 | I3: Outbound chgs - 01 - 15 JAN 26 | J3: 46045 | K3: As per details | L3: PUR/MU/00014340 | M3: 828 | N3: 14 | O3: 0.016908213 | P3: =M3-H3 -> 0.42
A4: 1800017051 | B4: DR | C4: 46045 | D4: 256779450956 | E4: USD | F4: 70.09 | G4: INR | H4: 6360.19 | I4: LCL chgs - 01 - 15 JAN 26 | J4: 46045 | K4: As per details | L4: PUR/MU/00014342 | M4: 6360 | N4: 108 | O4: 0.016981132 | P4: =M4-H4 -> -0.19
A5: 1800016863 | B5: DR | C5: 46045 | D5: 256779450805 | E5: USD | F5: 112.56 | G5: INR | H5: 10214.05 | I5: Storage- CODC-1-15 JAN 26 | J5: 46045 | K5: As per details | L5: PUR/MU/00014338 | M5: 10214 | N5: 173 | O5: 0.016937537 | P5: =M5-H5 -> -0.05
A6: 1800016893 | B6: DR | C6: 46042 | D6: 256779450822 | E6: USD | F6: 489.12 | G6: INR | H6: 44384.28 | I6: Storage WH-03-1-15 Jan 26 | J6: 46042 | K6: As per details | L6: PUR/MU/00014343 | M6: 44384 | N6: 752 | O6: 0.016943043 | P6: =M6-H6 -> -0.28
A7: 1800016481 | B7: DR | C7: 46028 | D7: 256779450523 | E7: USD | F7: 41.18 | G7: INR | H7: 3736.8 | I7: LCL chgs - 16 - 31 DEC 25 | J7: 46028 | K7: As per details | L7: PUR/MU/00013442 | M7: 3737 | N7: 63 | O7: 0.016858443 | P7: =M7-H7 -> 0.2
A8: 1800016455 | B8: DR | C8: 46028 | D8: 256779450495 | E8: USD | F8: 120.07 | G8: INR | H8: 10895.53 | I8: Storage -CODC 16-31 DEC 25 | J8: 46065 | K8: As per details | L8: PUR/MU/00015442 | M8: 10846 | N8: 184 | O8: 0.01696478 | P8: =M8-H8 -> -49.53
A9: 1800016027 | B9: DR | C9: 46027 | D9: 256779450231 | E9: USD | F9: 112.56 | G9: INR | H9: 10214.05 | I9: Storage- CODC-1-15 DEC 25 | J9: 46027 | K9: As per details | L9: PUR/MU/00014303 | M9: 10214 | N9: 173 | O9: 0.016937537 | P9: =M9-H9 -> -0.05
A10: 1800016108 | B10: DR | C10: 46027 | D10: 256779450329 | E10: USD | F10: 463.66 | G10: INR | H10: 42073.96 | I10: Storage WH-03-1-15 DEC 25 | J10: 46027 | K10: As per details | L10: PUR/MU/00014306 | M10: 42074 | N10: 713 | O10: 0.016946333 | P10: =M10-H10 -> 0.04
A11: 1800015756 | B11: DR | C11: 46024 | D11: 256779450032 | E11: USD | F11: 475.1 | G11: INR | H11: 43112.07 | I11: Storage WH-03-16-30 Nov 25 | J11: 46024 | K11: As per details | L11: PUR/MU/00014312 | M11: 43112 | N11: 731 | O11: 0.016955836 | P11: =M11-H11 -> -0.07
A12: 1800015267 | B12: DR | C12: 45996 | D12: 256779419896 | E12: USD | F12: 7.08 | G12: INR | H12: 628 | I12: Outbound chgs - 16 - 30 Nov 25 | J12: 46039 | K12: As per details | L12: PUR/MU/00013152 | M12: 628 | N12: 11 | O12: 0.017515924 | P12: =M12-H12 -> 0
A13: 1800015335 | B13: DR | C13: 45995 | D13: 256779419781 | E13: USD | F13: 112.56 | G13: INR | H13: 9984.09 | I13: Storage -CODC 16-30 Nov 25 | J13: 46039 | K13: As per details | L13: PUR/MU/00013150 | M13: 9984 | N13: 169 | O13: 0.016927083 | P13: =M13-H13 -> -0.09
A14: 1800014656 | B14: DR | C14: 45966 | D14: 256779418961 | E14: USD | F14: 531.2 | G14: INR | H14: 46747.4 | I14: Storage WH-03-16-31 OCT 25 | J14: 45966 | K14: As per details | L14: PUR/MU/00011626 | M14: 46747.46 | N14: 0 | O14: 0 | P14: =M14-H14 -> 0.06
... A27: 1800013017 | B27: DR | C27: 45919 | D27: 256779417643 | E27: USD | F27: 503.06 | G27: INR | H27: 44024.96 | I27: Storage WH-03-1-15 Sep 25 | J27: 45990 | K27: As per details | L27: PUR/MU/00008475 | M27: 44047 | N27: 746 | O27: 0.016936454 | P27: =M27-H27 -> 22.04
P28: =SUM(P3:P27) -> 359.26

Sheet Customer Data
D1: =SUBTOTAL(9,D3:D411) -> 378627.12 | E1: =SUBTOTAL(9,E3:E411) -> 1275547.9 | F1: =SUBTOTAL(9,F3:F404) -> 20788.91
A2: Date | B2: Particulars | C2: Transaction No. | D2: Debit (INR) | E2: Credit (INR) | F2: TDS | G2: Rate | H2: Vender IN No
A3: 45719 | B3: As per details | C3: PUR/MU/031685 | D3: 0 | E3: 435 | F3: =_xlfn.XLOOKUP(C3,TDS!$C:$C,TDS!$D:$D,0,0) -> 8 | G3: =F3/E3 -> 0.018390805 | H3: =_xlfn.XLOOKUP(C3,'Customer Payments'!$C:$C,'Customer Payments'!$D:$D,,0) -> 246779410574 | I3: =_xlfn.XLOOKUP(H3,'Ascendus Data'!$L:$L,'Ascendus Data'!$T:$T,,0) -> 435.19
A4: 45719 | B4: Outbond Handling Charges Exp | 368.43 DR | C4: PUR/MU/031685 | D4: 0 | E4: 0
A5: 45719 | B5: IGST Receivable | 66.32 DR | C5: PUR/MU/031685 | D5: 0 | E5: 0
A6: 45719 | B6: Rounding off | 0.25 DR | C6: PUR/MU/031685 | D6: 0 | E6: 0
A7: 45719 | B7: TDS on Contractor(P) | C7: PUR/MU/031685 | D7: 8 | E7: 0
A8: 45733 | B8: As per details | C8: PUR/MU/031686 | D8: 0 | E8: 1670 | F8: =_xlfn.XLOOKUP(C8,TDS!$C:$C,TDS!$D:$D,0,0) -> 29 | G8: =F8/E8 -> 0.017365269 | H8: =_xlfn.XLOOKUP(C8,'Customer Payments'!$C:$C,'Customer Payments'!$D:$D,,0) -> 246779411950 | I8: =_xlfn.XLOOKUP(H8,'Ascendus Data'!$L:$L,'Ascendus Data'!$T:$T,,0) -> 1670.54
A9: 45733 | B9: IGST Receivable | 254.82 DR | C9: PUR/MU/031686 | D9: 0 | E9: 0
A10: 45733 | B10: Miscellaneous Expenses (IB-Mumbai Air Division) | 1,415.66 DR | C10: PUR/MU/031686 | D10: 0 | E10: 0
A11: 45733 | B11: Rounding off | 0.48 CR | C11: PUR/MU/031686 | D11: 0 | E11: 0
A12: 45733 | B12: TDS on Contractor(P) | C12: PUR/MU/031686 | D12: 29 | E12: 0
A13: 45735 | B13: As per details | C13: PUR/MU/031687 | D13: 0 | E13: 23969 | F13: =_xlfn.XLOOKUP(C13,TDS!$C:$C,TDS!$D:$D,0,0) -> 407 | G13: =F13/E13 -> 0.016980266 | H13: =_xlfn.XLOOKUP(C13,'Customer Payments'!$C:$C,'Customer Payments'!$D:$D,,0) -> 246779412626 | I13: =_xlfn.XLOOKUP(H13,'Ascendus Data'!$L:$L,'Ascendus Data'!$T:$T,,0) -> 23969.27
A14: 45735 | B14: Storage Charges Exp | 12,519.39 DR | C14: PUR/MU/031687 | D14: 0 | E14: 0
A15: 45735 | B15: Storage Charges Exp | 7,793.24 DR | C15: PUR/MU/031687 | D15: 0 | E15: 0
A16: 45735 | B16: IGST Receivable | 3,656.27 DR | C16: PUR/MU/031687 | D16: 0 | E16: 0
A17: 45735 | B17: Rounding off | 0.10 DR | C17: PUR/MU/031687 | D17: 0 | E17: 0
A18: 45735 | B18: TDS on Contractor(P) | C18: PUR/MU/031687 | D18: 407 | E18: 0
A19: 45735 | B19: As per details | C19: PUR/MU/031688 | D19: 0 | E19: 22007 | F19: =_xlfn.XLOOKUP(C19,TDS!$C:$C,TDS!$D:$D,0,0) -> 373 | G19: =F19/E19 -> 0.016949153 | H19: =_xlfn.XLOOKUP(C19,'Customer Payments'!$C:$C,'Customer Payments'!$D:$D,,0) -> 246779412712 | I19: =_xlfn.XLOOKUP(H19,'Ascendus Data'!$L:$L,'Ascendus Data'!$T:$T,,0) -> 22006.58
A20: 45735 | B20: Storage Charges Exp | 9,008.95 DR | C20: PUR/MU/031688 | D20: 0 | E20: 0
A21: 45735 | B21: Storage Charges Exp | 8,440.00 DR | C21: PUR/MU/031688 | D21: 0 | E21: 0
A22: 45735 | B22: Storage Charges Exp | 1,200.94 DR | C22: PUR/MU/031688 | D22: 0 | E22: 0
A23: 45735 | B23: IGST Receivable | 3,356.98 DR | C23: PUR/MU/031688 | D23: 0 | E23: 0
A24: 45735 | B24: Rounding off | 0.13 DR | C24: PUR/MU/031688 | D24: 0 | E24: 0
A25: 45735 | B25: TDS on Contractor(P) | C25: PUR/MU/031688 | D25: 373 | E25: 0
A26: 45735 | B26: As per details | C26: PUR/MU/031689 | D26: 0 | E26: 24537 | F26: =_xlfn.XLOOKUP(C26,TDS!$C:$C,TDS!$D:$D,0,0) -> 416 | G26: =F26/E26 -> 0.016953988 | H26: =_xlfn.XLOOKUP(C26,'Customer Payments'!$C:$C,'Customer Payments'!$D:$D,,0) -> 246779412785 | I26: =_xlfn.XLOOKUP(H26,'Ascendus Data'!$L:$L,'Ascendus Data'!$T:$T,,0) -> 24536.23
A27: 45735 | B27: Storage Charges Exp | 16,128.00 DR | C27: PUR/MU/031689 | D27: 0 | E27: 0
A28: 45735 | B28: Storage Charges Exp | 811.00 DR | C28: PUR/MU/031689 | D28: 0 | E28: 0
A29: 45735 | B29: IGST Receivable | 3,742.88 DR | C29: PUR/MU/031689 | D29: 0 | E29: 0
A30: 45735 | B30: Storage Charges Exp (IB-Mumbai Air Division) | 3,854.76 DR | C30: PUR/MU/031689 | D30: 0 | E30: 0
A31: 45735 | B31: Rounding off | 0.36 DR | C31: PUR/MU/031689 | D31: 0 | E31: 0
A32: 45735 | B32: TDS on Contractor(P) | C32: PUR/MU/031689 | D32: 416 | E32: 0
A33: 45735 | B33: As per details | C33: PUR/MU/031690 | D33: 0 | E33: 27677 | F33: =_xlfn.XLOOKUP(C33,TDS!$C:$C,TDS!$D:$D,0,0) -> 470 | G33: =F33/E33 -> 0.016981609 | H33: =_xlfn.XLOOKUP(C33,'Customer Payments'!$C:$C,'Customer Payments'!$D:$D,,0) -> 246779412863 | I33: =_xlfn.XLOOKUP(H33,'Ascendus Data'!$L:$L,'Ascendus Data'!$T:$T,,0) -> 27677.92
A34: 45735 | B34: Storage Charges Exp | 15,607.89 DR | C34: PUR/MU/031690 | D34: 0 | E34: 0
A35: 45735 | B35: IGST Receivable | 4,221.93 DR | C35: PUR/MU/031690 | D35: 0 | E35: 0
A36: 45735 | B36: Storage Charges Exp (IB-Mumbai Air Division) | 7,847.29 DR | C36: PUR/MU/031690 | D36: 0 | E36: 0
A37: 45735 | B37: Rounding off | 0.11 CR | C37: PUR/MU/031690 | D37: 0 | E37: 0
A38: 45735 | B38: TDS on Contractor(P) | C38: PUR/MU/031690 | D38: 470 | E38: 0
A39: 45735 | B39: As per details | C39: PUR/MU/031691 | D39: 0 | E39: 28600 | F39: =_xlfn.XLOOKUP(C39,TDS!$C:$C,TDS!$D:$D,0,0) -> 485 | G39: =F39/E39 -> 0.016958042 | H39: =_xlfn.XLOOKUP(C39,'Customer Payments'!$C:$C,'Customer Payments'!$D:$D,,0) -> 246779412934 | I39: =_xlfn.XLOOKUP(H39,'Ascendus Data'!$L:$L,'Ascendus Data'!$T:$T,,0) -> 28598.58
A40: 45735 | B40: Storage Charges Exp | 16,128.00 DR | C40: PUR/MU/031691 | D40: 0 | E40: 0
A41: 45735 | B41: IGST Receivable | 4,362.66 DR | C41: PUR/MU/031691 | D41: 0 | E41: 0
A42: 45735 | B42: Storage Charges Exp (IB-Mumbai Air Division) | 8,109.00 DR | C42: PUR/MU/031691 | D42: 0 | E42: 0
A43: 45735 | B43: Rounding off | 0.34 DR | C43: PUR/MU/031691 | D43: 0 | E43: 0
A44: 45735 | B44: TDS on Contractor(P) | C44: PUR/MU/031691 | D44: 485 | E44: 0
A45: 45735 | B45: As per details | C45: PUR/MU/031692 | D45: 0 | E45: 337 | F45: =_xlfn.XLOOKUP(C45,TDS!$C:$C,TDS!$D:$D,0,0) -> 6 | G45: =F45/E45 -> 0.017804154 | H45: =_xlfn.XLOOKUP(C45,'Customer Payments'!$C:$C,'Customer Payments'!$D:$D,,0) -> 246779413379 | I45: =_xlfn.XLOOKUP(H45,'Ascendus Data'!$L:$L,'Ascendus Data'!$T:$T,,0) -> 337.23
A46: 45735 | B46: Outbond Handling Charges Exp | 286.00 DR | C46: PUR/MU/031692 | D46: 0 | E46: 0
A47: 45735 | B47: IGST Receivable | 51.48 DR | C47: PUR/MU/031692 | D47: 0 | E47: 0
A48: 45735 | B48: Rounding off | 0.48 CR | C48: PUR/MU/031692 | D48: 0 | E48: 0
A49: 45735 | B49: TDS on Contractor(P) | C49: PUR/MU/031692 | D49: 6 | E49: 0
A50: 45736 | B50: As per details | C50: PUR/MU/031684 | D50: 0 | E50: 5930 | F50: =_xlfn.XLOOKUP(C50,TDS!$C:$C,TDS!$D:$D,0,0) -> 101 | G50: =F50/E50 -> 0.01703204 | H50: =_xlfn.XLOOKUP(C50,'Customer Payments'!$C:$C,'Customer Payments'!$D:$D,,0) -> 246779414768 | I50: =_xlfn.XLOOKUP(H50,'Ascendus Data'!$L:$L,'Ascendus Data'!$T:$T,,0) -> 5929.68
A51: 45736 | B51: Handling Charges Exp | 4,941.40 DR | C51: PUR/MU/031684 | D51: 0 | E51: 0
A52: 45736 | B52: Handling Charges Exp | 84.08 DR | C52: PUR/MU/031684 | D52: 0 | E52: 0
A53: 45736 | B53: IGST Receivable | 904.59 DR | C53: PUR/MU/031684 | D53: 0 | E53: 0
A54: 45736 | B54: Rounding off | 0.07 CR | C54: PUR/MU/031684 | D54: 0 | E54: 0
A55: 45736 | B55: TDS on Contractor(P) | C55: PUR/MU/031684 | D55: 101 | E55: 0
A56: 45736 | B56: As per details | C56: PUR/MU/031693 | D56: 0 | E56: 1166 | F56: =_xlfn.XLOOKUP(C56,TDS!$C:$C,TDS!$D:$D,0,0) -> 20 | G56: =F56/E56 -> 0.017152659 | H56: =_xlfn.XLOOKUP(C56,'Customer Payments'!$C:$C,'Customer Payments'!$D:$D,,0) -> 246779413500 | I56: =_xlfn.XLOOKUP(H56,'Ascendus Data'!$L:$L,'Ascendus Data'!$T:$T,,0) -> 1166
A57: 45736 | B57: IGST Receivable | 177.84 DR | C57: PUR/MU/031693 | D57: 0 | E57: 0
A58: 45736 | B58: Handling Charges Exp (IB-Mumbai Air Division) | 988.00 DR | C58: PUR/MU/031693 | D58: 0 | E58: 0
A59: 45736 | B59: Rounding off | 0.16 DR | C59: PUR/MU/031693 | D59: 0 | E59: 0
A60: 45736 | B60: TDS on Contractor(P) | C60: PUR/MU/031693 | D60: 20 | E60: 0
A61: 45736 | B61: As per details | C61: PUR/MU/031694 | D61: 0 | E61: 355 | F61: =_xlfn.XLOOKUP(C61,TDS!$C:$C,TDS!$D:$D,0,0) -> 7 | G61: =F61/E61 -> 0.01971831 | H61: =_xlfn.XLOOKUP(C61,'Customer Payments'!$C:$C,'Customer Payments'!$D:$D,,0) -> 246779414508 | I61: =_xlfn.XLOOKUP(H61,'Ascendus Data'!$L:$L,'Ascendus Data'!$T:$T,,0) -> 354.57
A62: 45736 | B62: IGST Receivable | 54.15 DR | C62: PUR/MU/031694 | D62: 0 | E62: 0
A63: 45736 | B63: Handling Charges Exp (IB-Mumbai Air Division) | 300.81 DR | C63: PUR/MU/031694 | D63: 0 | E63: 0
A64: 45736 | B64: Rounding off | 0.04 DR | C64: PUR/MU/031694 | D64: 0 | E64: 0
A65: 45736 | B65: TDS on Contractor(P) | C65: PUR/MU/031694 | D65: 7 | E65: 0
A66: 45736 | B66: As per details | C66: PUR/MU/031695 | D66: 0 | E66: 2836 | F66: =_xlfn.XLOOKUP(C66,TDS!$C:$C,TDS!$D:$D,0,0) -> 49 | G66: =F66/E66 -> 0.017277856 | H66: =_xlfn.XLOOKUP(C66,'Customer Payments'!$C:$C,'Customer Payments'!$D:$D,,0) -> 246779414509 | I66: =_xlfn.XLOOKUP(H66,'Ascendus Data'!$L:$L,'Ascendus Data'!$T:$T,,0) -> 2835.67
A67: 45736 | B67: IGST Receivable | 432.54 DR | C67: PUR/MU/031695 | D67: 0 | E67: 0
A68: 45736 | B68: Handling Charges Exp (IB-Mumbai Air Division) | 2,403.00 DR | C68: PUR/MU/031695 | D68: 0 | E68: 0
A69: 45736 | B69: Rounding off | 0.46 DR | C69: PUR/MU/031695 | D69: 0 | E69: 0
A70: 45736 | B70: TDS on Contractor(P) | C70: PUR/MU/031695 | D70: 49 | E70: 0
A71: 45750 | B71: As per details | C71: PUR/MU/002086 | D71: 0 | E71: 2063 | F71: =_xlfn.XLOOKUP(C71,TDS!$C:$C,TDS!$D:$D,0,0) -> 35 | G71: =F71/E71 -> 0.016965584 | H71: =_xlfn.XLOOKUP(C71,'Customer Payments'!$C:$C,'Customer Payments'!$D:$D,,0) -> 256779410187 | I71: =_xlfn.XLOOKUP(H71,'Ascendus Data'!$L:$L,'Ascendus Data'!$T:$T,,0) -> 2062.65
A72: 45750 | B72: Miscellaneous Expenses | 1,748.00 DR | C72: PUR/MU/002086 | D72: 0 | E72: 0
A73: 45750 | B73: IGST Receivable | 314.64 DR | C73: PUR/MU/002086 | D73: 0 | E73: 0
A74: 45750 | B74: Rounding off | 0.36 DR | C74: PUR/MU/002086 | D74: 0 | E74: 0
A75: 45750 | B75: TDS on Contractor(P) | C75: PUR/MU/002086 | D75: 35 | E75: 0
A76: 45769 | B76: As per details | C76: PUR/MU/002088 | D76: 0 | E76: 3199 | F76: =_xlfn.XLOOKUP(C76,TDS!$C:$C,TDS!$D:$D,0,0) -> 54 | G76: =F76/E76 -> 0.016880275 | H76: =_xlfn.XLOOKUP(C76,'Invoice no ref in cutomer books'!$L:$L,'Invoice no ref in cutomer books'!$D:$D,,0) -> 256779412497 | I76: =_xlfn.XLOOKUP(H76,'Ascendus Data'!$L:$L,'Ascendus Data'!$T:$T,,0) -> 3198.72
A77: 45769 | B77: IGST Receivable | 488.00 DR | C77: PUR/MU/002088 | D77: 0 | E77: 0
A78: 45769 | B78: Handling Charges Exp (IB-Mumbai Air Division) | 2,711.09 DR | C78: PUR/MU/002088 | D78: 0 | E78: 0
A79: 45769 | B79: Rounding off | 0.09 CR | C79: PUR/MU/002088 | D79: 0 | E79: 0
A80: 45769 | B80: TDS on Contractor(P) | C80: PUR/MU/002088 | D80: 54 | E80: 0
A81: 45769 | B81: As per details | C81: PUR/MU/002089 | D81: 0 | E81: 338 | F81: =_xlfn.XLOOKUP(C81,TDS!$C:$C,TDS!$D:$D,0,0) -> 6 | G81: =F81/E81 -> 0.017751479 | H81: =_xlfn.XLOOKUP(C81,'Customer Payments'!$C:$C,'Customer Payments'!$D:$D,,0) -> 256779412638 | I81: =_xlfn.XLOOKUP(H81,'Ascendus Data'!$L:$L,'Ascendus Data'!$T:$T,,0) -> 338.13
A82: 45769 | B82: Handling Charges Exp | 286.84 DR | C82: PUR/MU/002089 | D82: 0 | E82: 0
A83: 45769 | B83: IGST Receivable | 51.63 DR | C83: PUR/MU/002089 | D83: 0 | E83: 0
A84: 45769 | B84: Rounding off | 0.47 CR | C84: PUR/MU/002089 | D84: 0 | E84: 0
A85: 45769 | B85: TDS on Contractor(P) | C85: PUR/MU/002089 | D85: 6 | E85: 0
A86: 45770 | B86: As per details | C86: PUR/MU/002514 | D86: 0 | E86: 5993.35 | F86: =_xlfn.XLOOKUP(C86,TDS!$C:$C,TDS!$D:$D,0,0) -> 102 | G86: =F86/E86 -> 0.017018863 | H86: =_xlfn.XLOOKUP(C86,'Customer Payments'!$C:$C,'Customer Payments'!$D:$D,,0) -> 256779412910 | I86: =_xlfn.XLOOKUP(H86,'Ascendus Data'!$L:$L,'Ascendus Data'!$T:$T,,0) -> 5994.13
A87: 45770 | B87: Outbond Handling Charges Exp | 5,079.11 DR | C87: PUR/MU/002514 | D87: 0 | E87: 0
A88: 45770 | B88: IGST Receivable | 914.24 DR | C88: PUR/MU/002514 | D88: 0 | E88: 0
A89: 45770 | B89: TDS on Contractor(P) | C89: PUR/MU/002514 | D89: 102 | E89: 0
A90: 45770 | B90: As per details | C90: PUR/MU/002519 | D90: 0 | E90: 3384 | F90: =_xlfn.XLOOKUP(C90,TDS!$C:$C,TDS!$D:$D,0,0) -> 58 | G90: =F90/E90 -> 0.01713948 | H90: =_xlfn.XLOOKUP(C90,'Customer Payments'!$C:$C,'Customer Payments'!$D:$D,,0) -> 256779412880 | I90: =_xlfn.XLOOKUP(H90,'Ascendus Data'!$L:$L,'Ascendus Data'!$T:$T,,0) -> 3384.74
A91: 45770 | B91: Handling Charges Exp | 2,868.00 DR | C91: PUR/MU/002519 | D91: 0 | E91: 0
A92: 45770 | B92: IGST Receivable | 516.24 DR | C92: PUR/MU/002519 | D92: 0 | E92: 0
A93: 45770 | B93: Rounding off | 0.24 CR | C93: PUR/MU/002519 | D93: 0 | E93: 0
A94: 45770 | B94: TDS on Contractor(P) | C94: PUR/MU/002519 | D94: 58 | E94: 0
A95: 45797 | B95: As per details | C95: PUR/MU/002087 | D95: 0 | E95: 15086 | F95: =_xlfn.XLOOKUP(C95,TDS!$C:$C,TDS!$D:$D,0,0) -> 256 | G95: =F95/E95 -> 0.016969376 | H95: =_xlfn.XLOOKUP(C95,'Customer Payments'!$C:$C,'Customer Payments'!$D:$D,,0) -> 256779413875 | I95: =_xlfn.XLOOKUP(H95,'Ascendus Data'!$L:$L,'Ascendus Data'!$T:$T,,0) -> 15086.7
A96: 45797 | B96: Handling Charges Exp | 4,317.24 DR | C96: PUR/MU/002087 | D96: 0 | E96: 0
A97: 45797 | B97: Handling Charges Exp | 3,072.12 DR | C97: PUR/MU/002087 | D97: 0 | E97: 0
A98: 45797 | B98: Handling Charges Exp | 2,842.00 DR | C98: PUR/MU/002087 | D98: 0 | E98: 0
A99: 45797 | B99: IGST Receivable | 2,301.31 DR | C99: PUR/MU/002087 | D99: 0 | E99: 0
A100: 45797 | B100: Handling Charges Exp (IB-Mumbai Air Division) | 2,553.72 DR | C100: PUR/MU/002087 | D100: 0 | E100: 0
...

Sheet Invoices not in Ascendus books
A1: Date | B1: Particulars | C1: Transaction No. | D1: Credit (INR) | E1: TDS | F1: Rate
A2: 46076 | B2: As per details | C2: PUR/MU/00015781 | D2: 42919 | E2: 727 | F2: 0.016938885
A3: 46064 | B3: As per details | C3: PUR/MU/00015484 | D3: 4067 | E3: 69 | F3: 0.016965822
A4: 46064 | B4: As per details | C4: PUR/MU/00015482 | D4: 1779 | E4: 30 | F4: 0.016863406
D5: =SUM(D2:D4) -> 48765 | E5: =SUM(E2:E4) -> 826 | F5: =D5 -> 48765

Sheet TDS
D1: =SUBTOTAL(9,D3:D67)-'Invoices not in Ascendus books'!E5 -> 20804.91
A2: Date+A1:A2 | B2: Particulars | C2: Transaction No. | D2: Debit (INR) | E2: Credit (INR) | F2: Balance (INR)
A3: 45736 | B3: TDS on Contractor(P) | C3: PUR/MU/031695 | D3: 49 | E3: 0 | F3: -137148
A4: 45736 | B4: TDS on Contractor(P) | C4: PUR/MU/031694 | D4: 7 | E4: 0 | F4: -134361
A5: 45736 | B5: TDS on Contractor(P) | C5: PUR/MU/031693 | D5: 20 | E5: 0 | F5: -134013
A6: 45735 | B6: TDS on Contractor(P) | C6: PUR/MU/031692 | D6: 6 | E6: 0 | F6: -127038
A7: 45735 | B7: TDS on Contractor(P) | C7: PUR/MU/031691 | D7: 485 | E7: 0 | F7: -126707
A8: 45735 | B8: TDS on Contractor(P) | C8: PUR/MU/031690 | D8: 470 | E8: 0 | F8: -98592
A9: 45735 | B9: TDS on Contractor(P) | C9: PUR/MU/031689 | D9: 416 | E9: 0 | F9: -71385
A10: 45735 | B10: TDS on Contractor(P) | C10: PUR/MU/031688 | D10: 373 | E10: 0 | F10: -47264
A11: 45735 | B11: TDS on Contractor(P) | C11: PUR/MU/031687 | D11: 407 | E11: 0 | F11: -25630
A12: 45733 | B12: TDS on Contractor(P) | C12: PUR/MU/031686 | D12: 29 | E12: 0 | F12: -2068
A13: 45719 | B13: TDS on Contractor(P) | C13: PUR/MU/031685 | D13: 8 | E13: 0 | F13: -427
A14: 45736 | B14: TDS on Contractor(P) | C14: PUR/MU/031684 | D14: 101 | E14: 0 | F14: -132867
... A67: 45892 | B67: TDS on Contractor F Y 2025-26 | C67: JV/MU/001311 | D67: 8 | E67: 0 | F67: -359275.35

Sheet Sheet1
D1: 21630.91
A2: Date | B2: Particulars | C2: Transaction No. | D2: Debit (INR) | F2: Date | G2: Particulars | H2: Transaction No. | I2: Credit (INR) | J2: TDS | K2: Rate
A3: 45719 | B3: TDS on Contractor(P) | C3: PUR/MU/031685 | D3: 8 | F3: 45719 | G3: As per details | H3: PUR/MU/031685 | I3: 435 | J3: 8 | K3: 0.018390805 | L3: =J3-D3 -> 0
A4: 45733 | B4: TDS on Contractor(P) | C4: PUR/MU/031686 | D4: 29 | F4: 45733 | G4: As per details | H4: PUR/MU/031686 | I4: 1670 | J4: 29 | K4: 0.017365269 | L4: =J4-D4 -> 0
A5: 45735 | B5: TDS on Contractor(P) | C5: PUR/MU/031687 | D5: 407 | F5: 45735 | G5: As per details | H5: PUR/MU/031687 | I5: 23969 | J5: 407 | K5: 0.016980266 | L5: =J5-D5 -> 0
A6: 45735 | B6: TDS on Contractor(P) | C6: PUR/MU/031688 | D6: 373 | F6: 45735 | G6: As per details | H6: PUR/MU/031688 | I6: 22007 | J6: 373 | K6: 0.016949153 | L6: =J6-D6 -> 0
A7: 45735 | B7: TDS on Contractor(P) | C7: PUR/MU/031689 | D7: 416 | F7: 45735 | G7: As per details | H7: PUR/MU/031689 | I7: 24537 | J7: 416 | K7: 0.016953988 | L7: =J7-D7 -> 0
A8: 45735 | B8: TDS on Contractor(P) | C8: PUR/MU/031690 | D8: 470 | F8: 45735 | G8: As per details | H8: PUR/MU/031690 | I8: 27677 | J8: 470 | K8: 0.016981609 | L8: =J8-D8 -> 0
A9: 45735 | B9: TDS on Contractor(P) | C9: PUR/MU/031691 | D9: 485 | F9: 45735 | G9: As per details | H9: PUR/MU/031691 | I9: 28600 | J9: 485 | K9: 0.016958042 | L9: =J9-D9 -> 0
A10: 45735 | B10: TDS on Contractor(P) | C10: PUR/MU/031692 | D10: 6 | F10: 45735 | G10: As per details | H10: PUR/MU/031692 | I10: 337 | J10: 6 | K10: 0.017804154 | L10: =J10-D10 -> 0
A11: 45736 | B11: TDS on Contractor(P) | C11: PUR/MU/031684 | D11: 101 | F11: 45736 | G11: As per details | H11: PUR/MU/031684 | I11: 5930 | J11: 101 | K11: 0.01703204 | L11: =J11-D11 -> 0
A12: 45736 | B12: TDS on Contractor(P) | C12: PUR/MU/031693 | D12: 20 | F12: 45736 | G12: As per details | H12: PUR/MU/031693 | I12: 1166 | J12: 20 | K12: 0.017152659 | L12: =J12-D12 -> 0
A13: 45736 | B13: TDS on Contractor(P) | C13: PUR/MU/031694 | D13: 7 | F13: 45736 | G13: As per details | H13: PUR/MU/031694 | I13: 355 | J13: 7 | K13: 0.01971831 | L13: =J13-D13 -> 0
A14: 45736 | B14: TDS on Contractor(P) | C14: PUR/MU/031695 | D14: 49 | F14: 45736 | G14: As per details | H14: PUR/MU/031695 | I14: 2836 | J14: 49 | K14: 0.017277856 | L14: =J14-D14 -> 0
... A24: 45856 | B24: TDS on Contractor F Y 2025-26 | C24: PUR/MU/00005871 | D24: 1085 | F24: 45856 | G24: As per details | H24: PUR/MU/00005871 | I24: 64037 | J24: 1085 | K24: 0.01694333 | L24: =J24-D24 -> 0
F25: 45856 | G25: As per details | H25: PUR/MU/00006708 | I25: 2217 | J25: 0 | K25: 0 | L25: =J25-D25 -> 0
A26: 45857 | B26: TDS on Contractor F Y 2025-26 | C26: PUR/MU/00005872 | D26: 607 | F26: 45857 | G26: As per details | H26: PUR/MU/00005872 | I26: 35820 | J26: 607 | K26: 0.01694584 | L26: =J26-D26 -> 0
F27: 45857 | G27: As per details | H27: PUR/MU/00006706 | I27: 473 | J27: 0 | K27: 0 | L27: =J27-D27 -> 0
A28: 45889 | B28: TDS on Contractor F Y 2025-26 | C28: PUR/MU/00006901 | D28: 1600 | F28: 45889 | G28: As per details | H28: PUR/MU/00006901 | I28: 94396 | J28: 1600 | K28: 0.016949871 | L28: =J28-D28 -> 0
A29: 45889 | B29: TDS on Contractor F Y 2025-26 | C29: PUR/MU/00006902 | D29: 1969 | F29: 45889 | G29: As per details | H29: PUR/MU/00006902 | I29: 116166 | J29: 1969 | K29: 0.016949882 | L29: =J29-D29 -> 0
A30: 45889 | B30: TDS on Contractor F Y 2025-26 | C30: PUR/MU/00006903 | D30: 721 | F30: 45889 | G30: As per details | H30: PUR/MU/00006903 | I30: 42566 | J30: 721 | K30: 0.016938402 | L30: =J30-D30 -> 0
A31: 45889 | B31: TDS on Contractor F Y 2025-26 | C31: PUR/MU/00006906 | D31: 65 | F31: 45889 | G31: As per details | H31: PUR/MU/00006906 | I31: 3818 | J31: 65 | K31: 0.01702462 | L31: =J31-D31 -> 0
A32: 45889 | B32: TDS on Contractor F Y 2025-26 | C32: PUR/MU/00006909 | D32: 19 | F32: 45889 | G32: As per details | H32: PUR/MU/00006909 | I32: 1138 | J32: 19 | K32: 0.016695958 | L32: =J32-D32 -> 0
A33: 45892 | B33: TDS on Contractor F Y 2025-26 | C33: JV/MU/001311 | D33: 8 | L33: =J33-D33 -> -8
A34: 45892 | B34: TDS on Contractor F Y 2025-26 | C34: JV/MU/001312 | D34: 38 | L34: =J34-D34 -> -38
A35: 45936 | B35: TDS on Contractor F Y 2025-26 | C35: PUR/MU/00009570 | D35: 660 | F35: 45936 | G35: As per details | H35: PUR/MU/00009570 | I35: 38943 | J35: 660 | K35: 0.016947847 | L35: =J35-D35 -> 0
A36: 45937 | B36: TDS on Contractor F Y 2025-26 | C36: PUR/MU/00009566 | D36: 194 | F36: 45937 | G36: As per details | H36: PUR/MU/00009566 | I36: 11447 | J36: 194 | K36: 0.016947672 | L36: =J36-D36 -> 0
A37: 45937 | B37: TDS on Contractor F Y 2025-26 | C37: PUR/MU/00009567 | D37: 194 | F37: 45937 | G37: As per details | H37: PUR/MU/00009567 | I37: 11447 | J37: 194 | K37: 0.016947672 | L37: =J37-D37 -> 0
A38: 45948 | B38: TDS on Contractor F Y 2025-26 | C38: PUR/MU/00009572 | D38: 717 | F38: 45948 | G38: As per details | H38: PUR/MU/00009572 | I38: 42304 | J38: 717 | K38: 0.016948752 | L38: =J38-D38 -> 0
A39: 45950 | B39: TDS on Contractor F Y 2025-26 | C39: PUR/MU/00009574 | D39: 58 | F39: 45950 | G39: As per details | H39: PUR/MU/00009574 | I39: 3434 | J39: 58 | K39: 0.016889924 | L39: =J39-D39 -> 0
F40: 45966 | G40: As per details | H40: PUR/MU/00011621 | I40: 234.21 | J40: 0 | K40: 0 | L40: =J40-D40 -> 0
F41: 45966 | G41: As per details | H41: PUR/MU/00011626 | I41: 46747.46 | J41: 0 | K41: 0 | L41: =J41-D41 -> 0
A42: 45978 | B42: TDS on Contractor F Y 2025-26 | C42: PUR/MU/00008471 | D42: 4.69 | F42: 45978 | G42: As per details | H42: PUR/MU/00008471 | I42: 234.69 | J42: 4.69 | K42: 0.019983808 | L42: =J42-D42 -> 0
A43: 45979 | B43: TDS on Contractor F Y 2025-26 | C43: PUR/MU/00011012 | D43: 55 | F43: 45979 | G43: As per details | H43: PUR/MU/00011012 | I43: 3302 | J43: 55 | K43: 0.016656572 | L43: =J43-D43 -> 0
A44: 45980 | B44: TDS on Contractor F Y 2025-26 | C44: PUR/MU/00011010 | D44: 756 | F44: 45980 | G44: As per details | H44: PUR/MU/00011010 | I44: 44633 | J44: 756 | K44: 0.01693814 | L44: =J44-D44 -> 0
A45: 45981 | B45: TDS on Contractor F Y 2025-26 | C45: PUR/MU/00011011 | D45: 70.22 | F45: 45981 | G45: As per details | H45: PUR/MU/00011011 | I45: 3511.22 | J45: 70.22 | K45: 0.019998747 | L45: =J45-D45 -> 0
A46: 45981 | B46: TDS on Contractor F Y 2025-26 | C46: PUR/MU/00011013 | D46: 224 | F46: 45981 | G46: As per details | H46: PUR/MU/00011013 | I46: 13227 | J46: 224 | K46: 0.016935057 | L46: =J46-D46 -> 0
A47: 45981 | B47: TDS on Contractor F Y 2025-26 | C47: PUR/MU/00011014 | D47: 62 | F47: 45981 | G47: As per details | H47: PUR/MU/00011014 | I47: 3699 | J47: 62 | K47: 0.016761287 | L47: =J47-D47 -> 0
A48: 45981 | B48: TDS on Contractor F Y 2025-26 | C48: PUR/MU/00011015 | D48: 14 | F48: 45981 | G48: As per details | H48: PUR/MU/00011015 | I48: 870 | J48: 14 | K48: 0.016091954 | L48: =J48-D48 -> 0
A49: 45990 | B49: TDS on Contractor F Y 2025-26 | C49: PUR/MU/00008472 | D49: 119 | F49: 45990 | G49: As per details | H49: PUR/MU/00008472 | I49: 7066 | J49: 119 | K49: 0.016841211 | L49: =J49-D49 -> 0
A50: 45990 | B50: TDS on Contractor F Y 2025-26 | C50: PUR/MU/00008473 | D50: 2103 | F50: 45990 | G50: As per details | H50: PUR/MU/00008473 | I50: 124079 | J50: 2103 | K50: 0.016948879 | L50: =J50-D50 -> 0
A51: 45990 | B51: TDS on Contractor F Y 2025-26 | C51: PUR/MU/00008474 | D51: 127 | F51: 45990 | G51: As per details | H51: PUR/MU/00008474 | I51: 7520 | J51: 127 | K51: 0.016888298 | L51: =J51-D51 -> 0
A52: 45990 | B52: TDS on Contractor F Y 2025-26 | C52: PUR/MU/00008475 | D52: 746 | F52: 45990 | G52: As per details | H52: PUR/MU/00008475 | I52: 44047 | J52: 746 | K52: 0.016936454 | L52: =J52-D52 -> 0
A53: 46010 | B53: TDS on Contractor F Y 2025-26 | C53: JV/MU/002547 | D53: 4 | L53: =J53-D53 -> -4
A54: 46010 | B54: TDS on Contractor F Y 2025-26 | C54: JV/MU/002548 | D54: 792 | L54: =J54-D54 -> -792
A55: 46024 | B55: TDS on Contractor F Y 2025-26 | C55: PUR/MU/00014312 | D55: 731 | F55: 46024 | G55: As per details | H55: PUR/MU/00014312 | I55: 43112 | J55: 731 | K55: 0.016955836 | L55: =J55-D55 -> 0
A56: 46027 | B56: TDS on Contractor F Y 2025-26 | C56: PUR/MU/00014303 | D56: 173 | F56: 46027 | G56: As per details | H56: PUR/MU/00014303 | I56: 10214 | J56: 173 | K56: 0.016937537 | L56: =J56-D56 -> 0
A57: 46027 | B57: TDS on Contractor F Y 2025-26 | C57: PUR/MU/00014306 | D57: 713 | F57: 46027 | G57: As per details | H57: PUR/MU/00014306 | I57: 42074 | J57: 713 | K57: 0.016946333 | L57: =J57-D57 -> 0
A58: 46028 | B58: TDS on Contractor F Y 2025-26 | C58: PUR/MU/00013439 | D58: 184 | F58: 46028 | G58: As per details | H58: PUR/MU/00013439 | I58: 10895 | J58: 184 | K58: 0.016888481 | L58: =J58-D58 -> 0
A59: 46028 | B59: TDS on Contractor F Y 2025-26 | C59: PUR/MU/00013442 | D59: 63 | F59: 46028 | G59: As per details | H59: PUR/MU/00013442 | I59: 3737 | J59: 63 | K59: 0.016858443 | L59: =J59-D59 -> 0
A60: 46034 | B60: TDS on Contractor F Y 2025-26 | C60: PUR/MU/00013445 | D60: 779 | F60: 46034 | G60: As per details | H60: PUR/MU/00013445 | I60: 45945 | J60: 779 | K60: 0.016955055 | L60: =J60-D60 -> 0
A61: 46039 | B61: TDS on Contractor F Y 2025-26 | C61: PUR/MU/00013150 | D61: 169 | F61: 46039 | G61: As per details | H61: PUR/MU/00013150 | I61: 9984 | J61: 169 | K61: 0.016927083 | L61: =J61-D61 -> 0
A62: 46039 | B62: TDS on Contractor F Y 2025-26 | C62: PUR/MU/00013152 | D62: 11 | F62: 46039 | G62: As per details | H62: PUR/MU/00013152 | I62: 628 | J62: 11 | K62: 0.017515924 | L62: =J62-D62 -> 0
A63: 46042 | B63: TDS on Contractor F Y 2025-26 | C63: PUR/MU/00014343 | D63: 752 | F63: 46042 | G63: As per details | H63: PUR/MU/00014343 | I63: 44384 | J63: 752 | K63: 0.016943043 | L63: =J63-D63 -> 0
A64: 46045 | B64: TDS on Contractor F Y 2025-26 | C64: PUR/MU/00014338 | D64: 173 | F64: 46045 | G64: As per details | H64: PUR/MU/00014338 | I64: 10214 | J64: 173 | K64: 0.016937537 | L64: =J64-D64 -> 0
A65: 46045 | B65: TDS on Contractor F Y 2025-26 | C65: PUR/MU/00014340 | D65: 14 | F65: 46045 | G65: As per details | H65: PUR/MU/00014340 | I65: 828 | J65: 14 | K65: 0.016908213 | L65: =J65-D65 -> 0
A66: 46045 | B66: TDS on Contractor F Y 2025-26 | C66: PUR/MU/00014342 | D66: 108 | F66: 46045 | G66: As per details | H66: PUR/MU/00014342 | I66: 6360 | J66: 108 | K66: 0.016981132 | L66: =J66-D66 -> 0
... A71: 46076 | B71: TDS on Contractor F Y 2025-26 | C71: PUR/MU/00015781 | D71: 727 | F71: 46076 | G71: As per details | H71: PUR/MU/00015781 | I71: 42919 | J71: 727 | K71: 0.016938885 | L71: =J71-D71 -> 0

Sheet Payment Reco
A1: As Per Bank Details | E1: As per Ascendus Ledger | H1: Difference
A2: Payment Date | B2: Customer Name | C2: Recd Amount | D2: Bank Reference | E2: Text | F2: Clearing Document | G2: Sum of Company Code Currency Value | H2: TDS Booked | I2: Foreign Exchange Gain / Loss
A3: 45863 | B3: DELIGHT LOGISTICS PVT LTD | C3: 166588 | D3: HDFCN52025072572586434 | E3: HDFCN52025072572586434 | F3: 1400001167 | G3: -169468.91 | H3: 2880 | I3: =C3+G3+H3 -> -0.91
A4: 45904 | B4: DELIGHT LOGISTICS PVT LTD | C4: 102382 | D4: HDFCN52025090451794665 | E4: HDFCN52025090451794665 | F4: 1400001170 | G4: -104145.96 | H4: 1719 | I4: =C4+G4+H4 -> -44.96
A5: 46046 | B5: DELIGHT LOGISTICS PVT LTD | C5: 88026.11 | D5: GTTV1CW7JDGR | G5: -88026.11 | I5: =C5+G5+H5 -> 0
H6: =SUM(H3:H5) -> 4599 | I6: =SUM(I3:I5) -> -45.87

Sheet Customer Payments
A1: Delight Logistics Pvt. Ltd. Accounts Bills Payable as on date 14-Mar-2026
A2: Location | B2: Date | C2: Transaction No | D2: Vendor Inv No. | E2: Vendor Inv Date | F2: Bill Amount (INR) | G2: Payment Date | H2: Payment No. | I2: Payment Type | J2: Paid/Settled (INR) | K2: Total Paid/Settled (INR) | L2: =J2-K2 -> #VALUE! | M2: Overdue Days | N2: Remarks | O2: Reference No.
A3: Mumbai Sea Division | B3: 45719 | C3: PUR/MU/031685 | D3: 246779410574 | E3: 45719 | F3: 427 | G3: 45863 | H3: HDFC-3100P003931 | I3: TDS 2880 | J3: 427 | K3: 427 | L3: =J3-K3 -> 0 | M3: 144 | N3: tds 8 | O3: x
A4: Mumbai Sea Division | B4: 45733 | C4: PUR/MU/031686 | D4: 246779411950 | E4: 45733 | F4: 1641 | G4: 45863 | H4: HDFC-3100P003931 | I4: TDS 2880 | J4: 1641 | K4: 1641 | L4: =J4-K4 -> 0 | M4: 130 | N4: tds 29 | O4: AI/C/MU/241024829
A5: Mumbai Sea Division | B5: 45735 | C5: PUR/MU/031687 | D5: 246779412626 | E5: 45735 | F5: 23562 | G5: 45863 | H5: HDFC-3100P003931 | I5: TDS 2880 | J5: 23562 | K5: 23562 | L5: =J5-K5 -> 0 | M5: 128 | N5: tds 407 | O5: SE/C/MU/240532333,SI/C/MU/241113607
A6: Mumbai Sea Division | B6: 45735 | C6: PUR/MU/031689 | D6: 246779412785 | E6: 45735 | F6: 24121 | G6: 45863 | H6: HDFC-3100P003931 | I6: TDS 2880 | J6: 24121 | K6: 24121 | L6: =J6-K6 -> 0 | M6: 128 | N6: tds 416 | O6: AI/C/MU/241024829,SE/C/MU/240532333,SI/C/MU/241113607
A7: Mumbai Sea Division | B7: 45735 | C7: PUR/MU/031690 | D7: 246779412863 | E7: 45735 | F7: 27207 | G7: 45863 | H7: HDFC-3100P003931 | I7: TDS 2880 | J7: 27207 | K7: 27207 | L7: =J7-K7 -> 0 | M7: 128 | N7: tds 470 | O7: SE/C/MU/240532333,AI/C/MU/241024829
A8: Mumbai Sea Division | B8: 45735 | C8: PUR/MU/031691 | D8: 246779412934 | E8: 45735 | F8: 28115 | G8: 45863 | H8: HDFC-3100P003931 | I8: TDS 2880 | J8: 28115 | K8: 28115 | L8: =J8-K8 -> 0 | M8: 128 | N8: tds 485 | O8: SE/C/MU/240532333,AI/C/MU/241024829
A9: Mumbai Sea Division | B9: 45735 | C9: PUR/MU/031692 | D9: 246779413379 | E9: 45735 | F9: 331 | G9: 45863 | H9: HDFC-3100P003931 | I9: TDS 2880 | J9: 331 | K9: 331 | L9: =J9-K9 -> 0 | M9: 128 | N9: tds 6 | O9: SI/C/MU/241113607
A10: Mumbai Sea Division | B10: 45735 | C10: PUR/MU/031688 | D10: 246779412712 | E10: 45735 | F10: 21634 | G10: 45863 | H10: HDFC-3100P003931 | I10: TDS 2880 | J10: 21634 | K10: 21634 | L10: =J10-K10 -> 0 | M10: 128 | N10: tds 373 | O10: SE/C/MU/240532333,SI/C/MU/241113607,SI/C/MU/250315427
A11: Mumbai Sea Division | B11: 45736 | C11: PUR/MU/031684 | D11: 246779414768 | E11: 45736 | F11: 5829 | G11: 45863 | H11: HDFC-3100P003931 | I11: TDS 2880 | J11: 5829 | K11: 5829 | L11: =J11-K11 -> 0 | M11: 127 | N11: tds 101 | O11: SE/C/MU/250242306,SE/C/MU/250242692
A12: Mumbai Sea Division | B12: 45736 | C12: PUR/MU/031693 | D12: 246779413500 | E12: 45736 | F12: 1146 | G12: 45863 | H12: HDFC-3100P003931 | I12: TDS 2880 | J12: 1146 | K12: 1146 | L12: =J12-K12 -> 0 | M12: 127 | N12: tds 20 | O12: AI/C/MU/241024829
A13: Mumbai Sea Division | B13: 45736 | C13: PUR/MU/031694 | D13: 246779414508 | E13: 45736 | F13: 348 | G13: 45863 | H13: HDFC-3100P003931 | I13: TDS 2880 | J13: 348 | K13: 348 | L13: =J13-K13 -> 0 | M13: 127 | N13: tds 7 | O13: AI/C/MU/250228084
A14: Mumbai Sea Division | B14: 45736 | C14: PUR/MU/031695 | D14: 246779414509 | E14: 45736 | F14: 2787 | G14: 45863 | H14: HDFC-3100P003931 | I14: TDS 2880 | J14: 2787 | K14: 2787 | L14: =J14-K14 -> 0 | M14: 127 | N14: tds 49 | O14: AI/C/MU/250228084
... A30: Mumbai Sea Division | B30: 45950 | C30: PUR/MU/00009574 | D30: 256779418643 | E30: 45950 | F30: 3376 | G30: 46046 | H30: HDFC-3100P006799 | I30: Bank Payment | J30: 3376 | K30: 3376 | L30: =J30-K30 -> 0 | M30: 96 | N30: TDS 58 | O30: SI/C/MU/250913157
A31: Mumbai Sea Division | B31: 45966 | C31: PUR/MU/00011621 | D31: 256779418846 | E31: 45966 | F31: 234.21 | G31: 46046 | H31: HDFC-3100P006799 | I31: Bank Payment | J31: 234.21 | K31: 234.21 | L31: =J31-K31 -> 0 | M31: 80 | O31: SE/C/MU/251037875
A32: Mumbai Sea Division | B32: 45978 | C32: PUR/MU/00008471 | D32: 256779417464 | E32: 45917 | F32: 230 | G32: 46046 | H32: HDFC-3100P006799 | I32: Bank Payment | J32: 230 | K32: 230 | L32: =J32-K32 -> 0 | M32: 68 | N32: TDS 4 | O32: SE/C/MU/250936610
A33: Mumbai Sea Division | B33: 45979 | C33: PUR/MU/00011012 | D33: 256779419351 | E33: 45979 | F33: 3247 | G33: 46046 | H33: HDFC-3100P006799 | I33: Bank Payment | J33: 3247 | K33: 3247 | L33: =J33-K33 -> 0 | M33: 67 | N33: TDS 55 | O33: SI/C/MU/251013410
A34: Mumbai Sea Division | B34: 45980 | C34: PUR/MU/00011010 | D34: 256779419490 | E34: 45980 | F34: 43877 | G34: 46046 | H34: HDFC-3100P006799 | I34: Bank Payment | J34: 43877 | K34: 43877 | L34: =J34-K34 -> 0 | M34: 66 | N34: TDS 756 | O34: SI/C/MU/250611341,SI/C/MU/250611572,SI/C/MU/250712112,SI/C/MU/250913157,SI/C/MU/251013540
A35: Mumbai Sea Division | B35: 45981 | C35: PUR/MU/00011011 | D35: 256779419447 | E35: 45981 | F35: 3441 | G35: 46046 | H35: HDFC-3100P006799 | I35: Bank Payment | J35: 3441 | K35: 3441 | L35: =J35-K35 -> 0 | M35: 65 | N35: TDS 59 | O35: SE/C/MU/251038697/FORBES,SE/C/MU/250735020
A36: Mumbai Sea Division | B36: 45981 | C36: PUR/MU/00011013 | D36: 256779419526 | E36: 45981 | F36: 13003 | G36: 46046 | H36: HDFC-3100P006799 | I36: Bank Payment | J36: 13003 | K36: 13003 | L36: =J36-K36 -> 0 | M36: 65 | N36: TDS 224 | O36: SI/C/MU/251013410
A37: Mumbai Sea Division | B37: 45981 | C37: PUR/MU/00011014 | D37: 256779419571 | E37: 45981 | F37: 3637 | G37: 46046 | H37: HDFC-3100P006799 | I37: Bank Payment | J37: 3637 | K37: 3637 | L37: =J37-K37 -> 0 | M37: 65 | N37: TDS 62 | O37: SI/C/MU/251013540
A38: Mumbai Sea Division | B38: 45981 | C38: PUR/MU/00011015 | D38: 256779419609 | E38: 45981 | F38: 856 | G38: 46046 | H38: HDFC-3100P006799 | I38: Bank Payment | J38: 856 | K38: 856 | L38: =J38-K38 -> 0 | M38: 65 | N38: TDS 14 | O38: SE/C/MU/251038697/FORBES
B39: Total | F39: =SUM(F3:F38) -> 357042.56 | J39: =SUM(J3:J38) -> 354398.21 | K39: =SUM(K3:K38) -> 357042.21 | L39: =SUM(L3:L38) -> -2644

Sheet Ascendus Data
A1: Company Code | B1: Customer | C1: Customer Account: Name 1 | D1: Fiscal Year | E1: Posting period | F1: Posting Date | G1: Document Number | H1: Document Type | I1: Document Date | J1: Entry Date | K1: Document Header Text | L1: Reference | M1: G/L Account | N1: G/L Account: Short Text | O1: Special G/L Ind. | P1: Posting Key | Q1: Document Currency Key | R1: Document Currency Value | S1: Company Code Currency Key | T1: Company Code Currency Value | V1: Vlookup | W1: TDS | Y1: Assignment | Z1: Item | AB1: Text | AC1: Reference Key 1 | AD1: Reference Key 2 | AE1: Reference Key 3 | AF1: Baseline Payment Dte | AG1: Clearing Date | AH1: Clearing Document
A2: 6779 | B2: 100222335 | C2: DELIGHT LOGISTICS PRIVATE LIMITED | D2: 2025 | E2: 9 | F2: 45909 | G2: 1400001167 | H2: DZ | I2: 45909 | J2: 45909 | K2: HDFCN52025072572586434 | M2: 212100 | N2: Trade Debtors (Ctrl) | P2: 15 | Q2: INR | R2: -2040.8 | S2: INR | T2: -2062.65 | V2: {=_xlfn.XLOOKUP(L2,'Customer Data'!$H:$H,'Customer Data'!$E:$F,,0)} -> #N/A | Z2: 4 | AA2: =W2/T2 -> 0 | AB2: HDFCN52025072572586434 | AF2: 45909 | AG2: 45909 | AH2: 1400001167
A3: 6779 | B3: 100222335 | C3: DELIGHT LOGISTICS PRIVATE LIMITED | D3: 2025 | E3: 9 | F3: 45909 | G3: 1400001167 | H3: DZ | I3: 45909 | J3: 45909 | K3: HDFCN52025072572586434 | M3: 212100 | N3: Trade Debtors (Ctrl) | P3: 15 | Q3: INR | R3: -18175.38 | S3: INR | T3: -18171.8 | V3: {=_xlfn.XLOOKUP(L3,'Customer Data'!$H:$H,'Customer Data'!$E:$F,,0)} -> #N/A | Z3: 5 | AA3: =W3/T3 -> 0 | AB3: HDFCN52025072572586434 | AF3: 45909 | AG3: 45909 | AH3: 1400001167
A4: 6779 | B4: 100222335 | C4: DELIGHT LOGISTICS PRIVATE LIMITED | D4: 2025 | E4: 9 | F4: 45909 | G4: 1400001167 | H4: DZ | I4: 45909 | J4: 45909 | K4: HDFCN52025072572586434 | M4: 212100 | N4: Trade Debtors (Ctrl) | P4: 15 | Q4: INR | R4: -148020.05 | S4: INR | T4: -149234.46 | V4: {=_xlfn.XLOOKUP(L4,'Customer Data'!$H:$H,'Customer Data'!$E:$F,,0)} -> #N/A | Z4: 3 | AA4: =W4/T4 -> 0 | AB4: HDFCN52025072572586434 | AF4: 45909 | AG4: 45909 | AH4: 1400001167
A5: 6779 | B5: 100222335 | C5: DELIGHT LOGISTICS PRIVATE LIMITED | D5: 2025 | E5: 10 | F5: 45931 | G5: 1400001289 | H5: DZ | I5: 45890 | J5: 45926 | K5: D7GGNWPD499Z | M5: 212100 | N5: Trade Debtors (Ctrl) | P5: 5 | Q5: INR | R5: 166588 | S5: INR | T5: 166588 | V5: {=_xlfn.XLOOKUP(L5,'Customer Data'!$H:$H,'Customer Data'!$E:$F,,0)} -> #N/A | Z5: 2 | AA5: =W5/T5 -> 0 | AF5: 45890 | AG5: 45931 | AH5: 1400001289
A6: 6779 | B6: 100222335 | C6: DELIGHT LOGISTICS PRIVATE LIMITED | D6: 2025 | E6: 8 | F6: 45890 | G6: 1400000965 | H6: DZ | I6: 45890 | J6: 45890 | K6: D7GGNWPD499Z | M6: 212100 | N6: Trade Debtors (Ctrl) | P6: 15 | Q6: INR | R6: -166588 | S6: INR | T6: -166588 | V6: {=_xlfn.XLOOKUP(L6,'Customer Data'!$H:$H,'Customer Data'!$E:$F,,0)} -> #N/A | Z6: 2 | AA6: =W6/T6 -> 0 | AF6: 45890 | AG6: 45931 | AH6: 1400001289
A7: 6779 | B7: 100222335 | C7: DELIGHT LOGISTICS PRIVATE LIMITED | D7: 2025 | E7: 9 | F7: 45912 | G7: 1400001170 | H7: DZ | I7: 45912 | J7: 45912 | K7: HDFCN52025090451794665 | M7: 212100 | N7: Trade Debtors (Ctrl) | P7: 15 | Q7: INR | R7: -105978.98 | S7: INR | T7: -104145.96 | V7: {=_xlfn.XLOOKUP(L7,'Customer Data'!$H:$H,'Customer Data'!$E:$F,,0)} -> #N/A | Z7: 4 | AA7: =W7/T7 -> 0 | AB7: HDFCN52025090451794665 | AF7: 45912 | AG7: 45912 | AH7: 1400001170
A8: 6779 | B8: 100222335 | C8: DELIGHT LOGISTICS PRIVATE LIMITED | D8: 2025 | E8: 8 | F8: 45877 | G8: 1800011401 | H8: DR | I8: 45877 | J8: 45877 | K8: NA | L8: 256779416251 | M8: 212100 | N8: Trade Debtors (Ctrl) | P8: 1 | Q8: USD | R8: 13.86 | S8: INR | T8: 1192.38 | V8: {=_xlfn.XLOOKUP(L8,'Customer Data'!$H:$H,'Customer Data'!$E:$F,,0)} -> #N/A | Y8: NA | Z8: 1 | AA8: =W8/T8 -> 0 | AB8: CODC Out chgs - 16 - 31 Jul 25 | AF8: 45877 | AG8: 45976 | AH8: 1400001884
A9: 6779 | B9: 100222335 | C9: DELIGHT LOGISTICS PRIVATE LIMITED | D9: 2025 | E9: 11 | F9: 45976 | G9: 1400001884 | H9: DY | I9: 45976 | J9: 45976 | K9: NA | L9: KNOCK OFF ENTRY | M9: 212100 | N9: Trade Debtors (Ctrl) | P9: 8 | Q9: USD | R9: 0 | S9: INR | T9: 20.57 | V9: {=_xlfn.XLOOKUP(L9,'Customer Data'!$H:$H,'Customer Data'!$E:$F,,0)} -> #N/A | Z9: 1 | AA9: =W9/T9 -> 0 | AF9: 45976 | AG9: 45976 | AH9: 1400001884
A10: 6779 | B10: 100222335 | C10: DELIGHT LOGISTICS PRIVATE LIMITED | D10: 2025 | E10: 7 | F10: 45842 | G10: 1800010284 | H10: DR | I10: 45842 | J10: 45847 | K10: NA | L10: 256779415044 | M10: 212100 | N10: Trade Debtors (Ctrl) | P10: 1 | Q10: USD | R10: 7.59 | S10: INR | T10: 652.75 | V10: {=_xlfn.XLOOKUP(L10,'Customer Data'!$H:$H,'Customer Data'!$E:$F,,0)} -> 653 | W10: 11 | Y10: NA | Z10: 1 | AA10: =W10/T10 -> 0.016851781 | AB10: Bond Stamp Paper Chgs | AF10: 45842 | AG10: 45912 | AH10: 1400001170
A11: 6779 | B11: 100222335 | C11: DELIGHT LOGISTICS PRIVATE LIMITED | D11: 2025 | E11: 4 | F11: 45751 | G11: 1800005578 | H11: DR | I11: 45751 | J11: 45752 | K11: NA | L11: 256779410470 | M11: 212100 | N11: Trade Debtors (Ctrl) | P11: 1 | Q11: USD | R11: 206.48 | S11: INR | T11: 17947.62 | V11: {=_xlfn.XLOOKUP(L11,'Customer Data'!$H:$H,'Customer Data'!$E:$F,,0)} -> #N/A | Y11: NA | Z11: 1 | AA11: =W11/T11 -> 0 | AB11: Storage charges for March 2025 | AF11: 45751
A12: 6779 | B12: 100222335 | C12: DELIGHT LOGISTICS PRIVATE LIMITED | D12: 2025 | E12: 4 | F12: 45751 | G12: 1800005668 | H12: DR | I12: 45751 | J12: 45752 | K12: NA | L12: 256779410560 | M12: 212100 | N12: Trade Debtors (Ctrl) | P12: 1 | Q12: USD | R12: 392.93 | S12: INR | T12: 34154.19 | V12: {=_xlfn.XLOOKUP(L12,'Customer Data'!$H:$H,'Customer Data'!$E:$F,,0)} -> #N/A | Y12: NA | Z12: 1 | AA12: =W12/T12 -> 0 | AB12: Storage charges for Jan 2025 | AF12: 45751
A13: 6779 | B13: 100222335 | C13: DELIGHT LOGISTICS PRIVATE LIMITED | D13: 2025 | E13: 4 | F13: 45751 | G13: 1800005794 | H13: DR | I13: 45751 | J13: 45752 | K13: NA | L13: 256779410686 | M13: 212100 | N13: Trade Debtors (Ctrl) | P13: 1 | Q13: USD | R13: 447.59 | S13: INR | T13: 38905.34 | V13: {=_xlfn.XLOOKUP(L13,'Customer Data'!$H:$H,'Customer Data'!$E:$F,,0)} -> #N/A | Y13: NA | Z13: 1 | AA13: =W13/T13 -> 0 | AB13: Storage charges for Feb 2025 | AF13: 45751
A14: 6779 | B14: 100222335 | C14: DELIGHT LOGISTICS PRIVATE LIMITED | D14: 2025 | E14: 9 | F14: 45910 | G14: 1800012752 | H14: DR | I14: 45910 | J14: 45912 | K14: NA | L14: 256779417385 | M14: 212100 | N14: Trade Debtors (Ctrl) | P14: 1 | Q14: USD | R14: 16.35 | S14: INR | T14: 1430.86 | V14: {=_xlfn.XLOOKUP(L14,'Customer Data'!$H:$H,'Customer Data'!$E:$F,,0)} -> #N/A | Y14: NA | Z14: 1 | AA14: =W14/T14 -> 0 | AB14: CODC Out chgs - 16 - 31 Jul 25 | AF14: 45910
A15: 6779 | B15: 100222335 | C15: DELIGHT LOGISTICS PRIVATE LIMITED | D15: 2025 | E15: 9 | F15: 45910 | G15: 1600002205 | H15: DG | I15: 45910 | J15: 45912 | K15: NA | L15: 256779421760 | M15: 212100 | N15: Trade Debtors (Ctrl) | P15: 11 | Q15: USD | R15: -13.86 | S15: INR | T15: -1212.95 | V15: {=_xlfn.XLOOKUP(L15,'Customer Data'!$H:$H,'Customer Data'!$E:$F,,0)} -> #N/A | Y15: 2099674 | Z15: 1 | AA15: =W15/T15 -> 0 | AB15: CN issued against 256779416251 | AF15: 45910 | AG15: 45976 | AH15: 1400001884
A16: 6779 | B16: 100222335 | C16: DELIGHT LOGISTICS PRIVATE LIMITED | D16: 2025 | E16: 3 | F16: 45719 | G16: 1800000634 | H16: DR | I16: 45719 | J16: 45720 | K16: NA | L16: 246779410574 | M16: 212100 | N16: Trade Debtors (Ctrl) | P16: 1 | Q16: USD | R16: 5.02 | S16: INR | T16: 435.19 | V16: {=_xlfn.XLOOKUP(L16,'Customer Data'!$H:$H,'Customer Data'!$E:$F,,0)} -> 435 | W16: 8 | Y16: NA | Z16: 1 | AA16: =W16/T16 -> 0.018382775 | AB16: Outbound Handling for Sep 2024 | AF16: 45719 | AG16: 45909 | AH16: 1400001167
A17: 6779 | B17: 100222335 | C17: DELIGHT LOGISTICS PRIVATE LIMITED | D17: 2025 | E17: 3 | F17: 45733 | G17: 1800002285 | H17: DR | I17: 45733 | J17: 45734 | K17: NA | L17: 246779411950 | M17: 212100 | N17: Trade Debtors (Ctrl) | P17: 1 | Q17: USD | R17: 19.27 | S17: INR | T17: 1670.54 | V17: {=_xlfn.XLOOKUP(L17,'Customer Data'!$H:$H,'Customer Data'!$E:$F,,0)} -> 1670 | W17: 29 | Y17: NA | Z17: 1 | AA17: =W17/T17 -> 0.017359656 | AB17: VAS Activity Charges for the month of November, 24 | AF17: 45733 | AG17: 45909 | AH17: 1400001167
A18: 6779 | B18: 100222335 | C18: DELIGHT LOGISTICS PRIVATE LIMITED | D18: 2025 | E18: 9 | F18: 45917 | G18: 1800012830 | H18: DR | I18: 45917 | J18: 45922 | K18: NA | L18: 256779417464 | M18: 212100 | N18: Trade Debtors (Ctrl) | P18: 1 | Q18: USD | R18: 2.68 | S18: INR | T18: 234.54 | V18: {=_xlfn.XLOOKUP(L18,'Customer Data'!$H:$H,'Customer Data'!$E:$F,,0)} -> 234.69 | W18: 4.69 | Y18: 2102532 | Z18: 1 | AA18: =W18/T18 -> 0.019996589 | AB18: VAS -1-15 Sept-25 | AF18: 45917
A19: 6779 | B19: 100222335 | C19: DELIGHT LOGISTICS PRIVATE LIMITED | D19: 2025 | E19: 11 | F19: 45980 | G19: 1800014989 | H19: DR | I19: 45980 | J19: 45982 | K19: NA | L19: 256779419490 | M19: 212100 | N19: Trade Debtors (Ctrl) | P19: 1 | Q19: USD | R19: 507.18 | S19: INR | T19: 44633.56 | V19: {=_xlfn.XLOOKUP(L19,'Customer Data'!$H:$H,'Customer Data'!$E:$F,,0)} -> 44633 | W19: 756 | Y19: NA | Z19: 1 | AA19: =W19/T19 -> 0.016937927 | AB19: Storage WH-03-1-15 NOV 25 | AF19: 45980
A20: 6779 | B20: 100222335 | C20: DELIGHT LOGISTICS PRIVATE LIMITED | D20: 2025 | E20: 6 | F20: 45813 | G20: 1800009285 | H20: DR | I20: 45813 | J20: 45817 | K20: NA | L20: 256779414049 | M20: 212100 | N20: Trade Debtors (Ctrl) | P20: 1 | Q20: USD | R20: 92.68 | S20: INR | T20: 7923.29 | V20: {=_xlfn.XLOOKUP(L20,'Customer Data'!$H:$H,'Customer Data'!$E:$F,,0)} -> #N/A | Y20: NA | Z20: 1 | AA20: =W20/T20 -> 0 | AB20: Storage 16-31 May-25,WH-3 | AF20: 45813
A21: 6779 | B21: 100222335 | C21: DELIGHT LOGISTICS PRIVATE LIMITED | D21: 2025 | E21: 5 | F21: 45785 | G21: 1800008771 | H21: DR | I21: 45785 | J21: 45805 | K21: NA | L21: 256779413535 | M21: 212100 | N21: Trade Debtors (Ctrl) | P21: 1 | Q21: USD | R21: 81.77 | S21: INR | T21: 7030.89 | V21: {=_xlfn.XLOOKUP(L21,'Customer Data'!$H:$H,'Customer Data'!$E:$F,,0)} -> #N/A | Y21: NA | Z21: 1 | AA21: =W21/T21 -> 0 | AB21: Storage 16-30 April-25 | AF21: 45785
A22: 6779 | B22: 100222335 | C22: DELIGHT LOGISTICS PRIVATE LIMITED | D22: 2025 | E22: 4 | F22: 45763 | G22: 1800006043 | H22: DR | I22: 45763 | J22: 45763 | K22: NA | L22: 256779410934 | M22: 212100 | N22: Trade Debtors (Ctrl) | P22: 1 | Q22: USD | R22: 204.98 | S22: INR | T22: 17817.23 | V22: {=_xlfn.XLOOKUP(L22,'Customer Data'!$H:$H,'Customer Data'!$E:$F,,0)} -> #N/A | Y22: NA | Z22: 1 | AA22: =W22/T22 -> 0 | AB22: Storage charges for March 2025 | AF22: 45763
A23: 6779 | B23: 100222335 | C23: DELIGHT LOGISTICS PRIVATE LIMITED | D23: 2025 | E23: 4 | F23: 45763 | G23: 1800006794 | H23: DR | I23: 45763 | J23: 45763 | K23: NA | L23: 256779411685 | M23: 212100 | N23: Trade Debtors (Ctrl) | P23: 1 | Q23: USD | R23: 31.15 | S23: INR | T23: 2707.61 | V23: {=_xlfn.XLOOKUP(L23,'Customer Data'!$H:$H,'Customer Data'!$E:$F,,0)} -> #N/A | Y23: NA | Z23: 1 | AA23: =W23/T23 -> 0 | AB23: LCL Charges Aug 2024 | AF23: 45763
A24: 6779 | B24: 100222335 | C24: DELIGHT LOGISTICS PRIVATE LIMITED | D24: 2025 | E24: 4 | F24: 45763 | G24: 1800006795 | H24: DR | I24: 45763 | J24: 45763 | K24: NA | L24: 256779411686 | M24: 212100 | N24: Trade Debtors (Ctrl) | P24: 1 | Q24: USD | R24: 31.15 | S24: INR | T24: 2707.61 | V24: {=_xlfn.XLOOKUP(L24,'Customer Data'!$H:$H,'Customer Data'!$E:$F,,0)} -> #N/A | Y24: NA | Z24: 1 | AA24: =W24/T24 -> 0 | AB24: LCL Charges Aug 2024 | AF24: 45763
A25: 6779 | B25: 100222335 | C25: DELIGHT LOGISTICS PRIVATE LIMITED | D25: 2025 | E25: 4 | F25: 45763 | G25: 1800006802 | H25: DR | I25: 45763 | J25: 45763 | K25: NA | L25: 256779411693 | M25: 212100 | N25: Trade Debtors (Ctrl) | P25: 1 | Q25: USD | R25: 3.89 | S25: INR | T25: 338.13 | V25: {=_xlfn.XLOOKUP(L25,'Customer Data'!$H:$H,'Customer Data'!$E:$F,,0)} -> #N/A | Y25: NA | Z25: 1 | AA25: =W25/T25 -> 0 | AB25: Inbound Handling Charges Aug 24 | AF25: 45763
A26: 6779 | B26: 100222335 | C26: DELIGHT LOGISTICS PRIVATE LIMITED | D26: 2025 | E26: 4 | F26: 45763 | G26: 1800006803 | H26: DR | I26: 45763 | J26: 45763 | K26: NA | L26: 256779411694 | M26: 212100 | N26: Trade Debtors (Ctrl) | P26: 1 | Q26: USD | R26: 7.85 | S26: INR | T26: 682.34 | V26: {=_xlfn.XLOOKUP(L26,'Customer Data'!$H:$H,'Customer Data'!$E:$F,,0)} -> #N/A | Y26: NA | Z26: 1 | AA26: =W26/T26 -> 0 | AB26: Inbound Handling Charges Aug 24 | AF26: 45763
A27: 6779 | B27: 100222335 | C27: DELIGHT LOGISTICS PRIVATE LIMITED | D27: 2025 | E27: 4 | F27: 45763 | G27: 1800006810 | H27: DR | I27: 45763 | J27: 45763 | K27: NA | L27: 256779411701 | M27: 212100 | N27: Trade Debtors (Ctrl) | P27: 1 | Q27: USD | R27: 7.85 | S27: INR | T27: 682.34 | V27: {=_xlfn.XLOOKUP(L27,'Customer Data'!$H:$H,'Customer Data'!$E:$F,,0)} -> #N/A | Y27: NA | Z27: 1 | AA27: =W27/T27 -> 0 | AB27: Outbound Handling Charges Aug 24 | AF27: 45763
A28: 6779 | B28: 100222335 | C28: DELIGHT LOGISTICS PRIVATE LIMITED | D28: 2025 | E28: 4 | F28: 45763 | G28: 1800006806 | H28: DR | I28: 45763 | J28: 45763 | K28: NA | L28: 256779411697 | M28: 212100 | N28: Trade Debtors (Ctrl) | P28: 1 | Q28: USD | R28: 1.18 | S28: INR | T28: 102.57 | V28: {=_xlfn.XLOOKUP(L28,'Customer Data'!$H:$H,'Customer Data'!$E:$F,,0)} -> #N/A | Y28: NA | Z28: 1 | AA28: =W28/T28 -> 0 | AB28: Loose Unloading Charges Aug 24 | AF28: 45763
A29: 6779 | B29: 100222335 | C29: DELIGHT LOGISTICS PRIVATE LIMITED | D29: 2025 | E29: 4 | F29: 45763 | G29: 1800006809 | H29: DR | I29: 45763 | J29: 45763 | K29: NA | L29: 256779411700 | M29: 212100 | N29: Trade Debtors (Ctrl) | P29: 1 | Q29: USD | R29: 14.04 | S29: INR | T29: 1220.38 | V29: {=_xlfn.XLOOKUP(L29,'Customer Data'!$H:$H,'Customer Data'!$E:$F,,0)} -> #N/A | Y29: NA | Z29: 1 | AA29: =W29/T29 -> 0 | AB29: Outbound Handling Charges Aug 24 | AF29: 45763
A30: 6779 | B30: 100222335 | C30: DELIGHT LOGISTICS PRIVATE LIMITED | D30: 2025 | E30: 7 | F30: 45863 | G30: 1800011248 | H30: DR | I30: 45863 | J30: 45863 | K30: NA | L30: 256779415980 | M30: 212100 | N30: Trade Debtors (Ctrl) | P30: 1 | Q30: USD | R30: 11.04 | S30: INR | T30: 949.45 | V30: {=_xlfn.XLOOKUP(L30,'Customer Data'!$H:$H,'Customer Data'!$E:$F,,0)} -> #N/A | Y30: NA | Z30: 1 | AA30: =W30/T30 -> 0 | AB30: VAS 16-31 May 25 Ex.85.48 | AF30: 45863
A31: 6779 | B31: 100222335 | C31: DELIGHT LOGISTICS PRIVATE LIMITED | D31: 2025 | E31: 11 | F31: 45979 | G31: 1800014853 | H31: DR | I31: 45979 | J31: 45981 | K31: NA | L31: 256779419351 | M31: 212100 | N31: Trade Debtors (Ctrl) | P31: 1 | Q31: USD | R31: 37.52 | S31: INR | T31: 3301.89 | V31: {=_xlfn.XLOOKUP(L31,'Customer Data'!$H:$H,'Customer Data'!$E:$F,,0)} -> 3302 | W31: 55 | Y31: NA | Z31: 1 | AA31: =W31/T31 -> 0.016657127 | AB31: Storage- CODC-1-15 NOV 25 | AF31: 45979
A32: 6779 | B32: 100222335 | C32: DELIGHT LOGISTICS PRIVATE LIMITED | D32: 2025 | E32: 9 | F32: 45904 | G32: 1800012317 | H32: DR | I32: 45904 | J32: 45908 | K32: NA | L32: 256779416940 | M32: 212100 | N32: Trade Debtors (Ctrl) | P32: 1 | Q32: USD | R32: 1440.32 | S32: INR | T32: 126048.64 | V32: {=_xlfn.XLOOKUP(L32,'Customer Data'!$H:$H,'Customer Data'!$E:$F,,0)} -> #N/A | Y32: NA | Z32: 1 | AA32: =W32/T32 -> 0 | AB32: CODC Storage - 16-31 Aug 25 | AF32: 45904
A33: 6779 | B33: 100222335 | C33: DELIGHT LOGISTICS PRIVATE LIMITED | D33: 2025 | E33: 9 | F33: 45904 | G33: 1800012352 | H33: DR | I33: 45904 | J33: 45908 | K33: NA | L33: 256779416975 | M33: 212100 | N33: Trade Debtors (Ctrl) | P33: 1 | Q33: USD | R33: 523.35 | S33: INR | T33: 45800.62 | V33: {=_xlfn.XLOOKUP(L33,'Customer Data'!$H:$H,'Customer Data'!$E:$F,,0)} -> 45918 | W33: 778 | Y33: NA | Z33: 1 | AA33: =W33/T33 -> 0.01698667 | AB33: WH 03 - Storage 16-31 Aug 25 | AF33: 45904
A34: 6779 | B34: 100222335 | C34: DELIGHT LOGISTICS PRIVATE LIMITED | D34: 2025 | E34: 9 | F34: 45904 | G34: 1800012487 | H34: DR | I34: 45904 | J34: 45909 | K34: NA | L34: 256779417095 | M34: 212100 | N34: Trade Debtors (Ctrl) | P34: 1 | Q34: USD | R34: 8.06 | S34: INR | T34: 705.37 | V34: {=_xlfn.XLOOKUP(L34,'Customer Data'!$H:$H,'Customer Data'!$E:$F,,0)} -> #N/A | Y34: NA | Z34: 1 | AA34: =W34/T34 -> 0 | AB34: VAS - 16-31 Aug 25 | AF34: 45904
A35: 6779 | B35: 100222335 | C35: DELIGHT LOGISTICS PRIVATE LIMITED | D35: 2025 | E35: 7 | F35: 45842 | G35: 1800010324 | H35: DR | I35: 45842 | J35: 45847 | K35: NA | L35: 256779415084 | M35: 212100 | N35: Trade Debtors (Ctrl) | P35: 1 | Q35: USD | R35: 68.69 | S35: INR | T35: 5907.39 | V35: {=_xlfn.XLOOKUP(L35,'Customer Data'!$H:$H,'Customer Data'!$E:$F,,0)} -> #N/A | Y35: NA | Z35: 1 | AA35: =W35/T35 -> 0 | AB35: Storage 16-30 Jun 25-WH 03 | AF35: 45842
A36: 6779 | B36: 100222335 | C36: DELIGHT LOGISTICS PRIVATE LIMITED | D36: 2025 | E36: 7 | F36: 45842 | G36: 1800010247 | H36: DR | I36: 45842 | J36: 45847 | K36: NA | L36: 256779415007 | M36: 212100 | N36: Trade Debtors (Ctrl) | P36: 1 | Q36: USD | R36: 11.01 | S36: INR | T36: 946.87 | V36: {=_xlfn.XLOOKUP(L36,'Customer Data'!$H:$H,'Customer Data'!$E:$F,,0)} -> 947 | W36: 16 | Y36: NA | Z36: 1 | AA36: =W36/T36 -> 0.016897779 | AB36: Outbound chgs - 16 - 30 Jun 25 | AF36: 45842 | AG36: 45912 | AH36: 1400001170
A37: 6779 | B37: 100222335 | C37: DELIGHT LOGISTICS PRIVATE LIMITED | D37: 2025 | E37: 11 | F37: 45966 | G37: 1800014357 | H37: DR | I37: 45966 | J37: 45967 | K37: NA | L37: 256779418846 | M37: 212100 | N37: Trade Debtors (Ctrl) | P37: 1 | Q37: USD | R37: 2.66 | S37: INR | T37: 234.09 | V37: {=_xlfn.XLOOKUP(L37,'Customer Data'!$H:$H,'Customer Data'!$E:$F,,0)} -> 234.21 | W37: 0 | Y37: NA | Z37: 1 | AA37: =W37/T37 -> 0 | AB37: VAS-16 -31 Oct 25 | AF37: 45966
A38: 6779 | B38: 100222335 | C38: DELIGHT LOGISTICS PRIVATE LIMITED | D38: 2025 | E38: 11 | F38: 45966 | G38: 1800014656 | H38: DR | I38: 45966 | J38: 45967 | K38: NA | L38: 256779418961 | M38: 212100 | N38: Trade Debtors (Ctrl) | P38: 1 | Q38: USD | R38: 531.2 | S38: INR | T38: 46747.4 | V38: {=_xlfn.XLOOKUP(L38,'Customer Data'!$H:$H,'Customer Data'!$E:$F,,0)} -> 46747.46 | W38: 0 | Y38: NA | Z38: 1 | AA38: =W38/T38 -> 0 | AB38: Storage WH-03-16-31 OCT 25 | AF38: 45966
A39: 6779 | B39: 100222335 | C39: DELIGHT LOGISTICS PRIVATE LIMITED | D39: 2025 | E39: 8 | F39: 45877 | G39: 1800011768 | H39: DR | I39: 45877 | J39: 45877 | K39: NA | L39: 256779416159 | M39: 212100 | N39: Trade Debtors (Ctrl) | P39: 1 | Q39: USD | R39: 67.34 | S39: INR | T39: 5793.27 | V39: {=_xlfn.XLOOKUP(L39,'Customer Data'!$H:$H,'Customer Data'!$E:$F,,0)} -> #N/A | Y39: NA | Z39: 1 | AA39: =W39/T39 -> 0 | AB39: LCL Chgs - 16 - 31 JUL 25 | AF39: 45877
A40: 6779 | B40: 100222335 | C40: DELIGHT LOGISTICS PRIVATE LIMITED | D40: 2025 | E40: 8 | F40: 45877 | G40: 1800011630 | H40: DR | I40: 45877 | J40: 45877 | K40: NA | L40: 256779416480 | M40: 212100 | N40: Trade Debtors (Ctrl) | P40: 1 | Q40: USD | R40: 86.26 | S40: INR | T40: 7420.96 | V40: {=_xlfn.XLOOKUP(L40,'Customer Data'!$H:$H,'Customer Data'!$E:$F,,0)} -> #N/A | Y40: NA | Z40: 1 | AA40: =W40/T40 -> 0 | AB40: VAS 16-31 July 25 | AF40: 45877
A41: 6779 | B41: 100222335 | C41: DELIGHT LOGISTICS PRIVATE LIMITED | D41: 2025 | E41: 8 | F41: 45877 | G41: 1800011825 | H41: DR | I41: 45877 | J41: 45877 | K41: NA | L41: 256779416134 | M41: 212100 | N41: Trade Debtors (Ctrl) | P41: 1 | Q41: USD | R41: 102.45 | S41: INR | T41: 8813.79 | V41: {=_xlfn.XLOOKUP(L41,'Customer Data'!$H:$H,'Customer Data'!$E:$F,,0)} -> #N/A | Y41: NA | Z41: 1 | AA41: =W41/T41 -> 0 | AB41: Empty Lolo Chgs - 01 - 31 JUL 25 | AF41: 45877
A42: 6779 | B42: 100222335 | C42: DELIGHT LOGISTICS PRIVATE LIMITED | D42: 2025 | E42: 8 | F42: 45877 | G42: 1800011682 | H42: DR | I42: 45877 | J42: 45877 | K42: NA | L42: 256779416200 | M42: 212100 | N42: Trade Debtors (Ctrl) | P42: 1 | Q42: USD | R42: 36.19 | S42: INR | T42: 3113.43 | V42: {=_xlfn.XLOOKUP(L42,'Customer Data'!$H:$H,'Customer Data'!$E:$F,,0)} -> #N/A | Y42: NA | Z42: 1 | AA42: =W42/T42 -> 0 | AB42: Outbound chgs - 16 - 31 Jul 25 | AF42: 45877
A43: 6779 | B43: 100222335 | C43: DELIGHT LOGISTICS PRIVATE LIMITED | D43: 2025 | E43: 8 | F43: 45877 | G43: 1800011389 | H43: DR | I43: 45877 | J43: 45877 | K43: NA | L43: 256779416239 | M43: 212100 | N43: Trade Debtors (Ctrl) | P43: 1 | Q43: USD | R43: 132.4 | S43: INR | T43: 11390.39 | V43: {=_xlfn.XLOOKUP(L43,'Customer Data'!$H:$H,'Customer Data'!$E:$F,,0)} -> #N/A | Y43: NA | Z43: 1 | AA43: =W43/T43 -> 0 | AB43: CODC Transportation IN chgs - 16 - 31 Jul 25 | AF43: 45877
A44: 6779 | B44: 100222335 | C44: DELIGHT LOGISTICS PRIVATE LIMITED | D44: 2025 | E44: 8 | F44: 45877 | G44: 1800011445 | H44: DR | I44: 45877 | J44: 45877 | K44: NA | L44: 256779416295 | M44: 212100 | N44: Trade Debtors (Ctrl) | P44: 1 | Q44: USD | R44: 3.63 | S44: INR | T44: 312.29 | V44: {=_xlfn.XLOOKUP(L44,'Customer Data'!$H:$H,'Customer Data'!$E:$F,,0)} -> #N/A | Y44: NA | Z44: 1 | AA44: =W44/T44 -> 0 | AB44: CODC-Storage-16-31 Jul 25 | AF44: 45877
A45: 6779 | B45: 100222335 | C45: DELIGHT LOGISTICS PRIVATE LIMITED | D45: 2025 | E45: 8 | F45: 45877 | G45: 1800011529 | H45: DR | I45: 45877 | J45: 45877 | K45: NA | L45: 256779416379 | M45: 212100 | N45: Trade Debtors (Ctrl) | P45: 1 | Q45: USD | R45: 546.72 | S45: INR | T45: 47034.39 | V45: {=_xlfn.XLOOKUP(L45,'Customer Data'!$H:$H,'Customer Data'!$E:$F,,0)} -> #N/A | Y45: NA | Z45: 1 | AA45: =W45/T45 -> 0 | AB45: Storage 16-31 Jul 25-WH 03 | AF45: 45877
A46: 6779 | B46: 100222335 | C46: DELIGHT LOGISTICS PRIVATE LIMITED | D46: 2025 | E46: 8 | F46: 45877 | G46: 1800011853 | H46: DR | I46: 45877 | J46: 45877 | K46: NA | L46: 256779416504 | M46: 212100 | N46: Trade Debtors (Ctrl) | P46: 1 | Q46: USD | R46: 269.8 | S46: INR | T46: 23210.93 | V46: {=_xlfn.XLOOKUP(L46,'Customer Data'!$H:$H,'Customer Data'!$E:$F,,0)} -> #N/A | Y46: NA | Z46: 1 | AA46: =W46/T46 -> 0 | AB46: PORT SSR Chgs July 25 | AF46: 45877
A47: 6779 | B47: 100222335 | C47: DELIGHT LOGISTICS PRIVATE LIMITED | D47: 2025 | E47: 6 | F47: 45812 | G47: 1800009428 | H47: DR | I47: 45812 | J47: 45817 | K47: NA | L47: 256779414192 | M47: 212100 | N47: Trade Debtors (Ctrl) | P47: 1 | Q47: USD | R47: 15.64 | S47: INR | T47: 1337.08 | V47: {=_xlfn.XLOOKUP(L47,'Customer Data'!$H:$H,'Customer Data'!$E:$F,,0)} -> #N/A | Y47: NA | Z47: 1 | AA47: =W47/T47 -> 0 | AB47: Outbound chgs - 16 - 31 MAY 25 | AF47: 45812
A48: 6779 | B48: 100222335 | C48: DELIGHT LOGISTICS PRIVATE LIMITED | D48: 2025 | E48: 6 | F48: 45812 | G48: 1800009538 | H48: DR | I48: 45812 | J48: 45817 | K48: NA | L48: 256779414302 | M48: 212100 | N48: Trade Debtors (Ctrl) | P48: 1 | Q48: USD | R48: 35.04 | S48: INR | T48: 2995.6 | V48: {=_xlfn.XLOOKUP(L48,'Customer Data'!$H:$H,'Customer Data'!$E:$F,,0)} -> #N/A | Y48: NA | Z48: 1 | AA48: =W48/T48 -> 0 | AB48: LCL Chgs - 16-31 MAY 25 | AF48: 45812
A49: 6779 | B49: 100222335 | C49: DELIGHT LOGISTICS PRIVATE LIMITED | D49: 2025 | E49: 7 | F49: 45856 | G49: 1800010682 | H49: DR | I49: 45856 | J49: 45859 | K49: NA | L49: 256779415466 | M49: 212100 | N49: Trade Debtors (Ctrl) | P49: 1 | Q49: USD | R49: 744.61 | S49: INR | T49: 64036.96 | V49: {=_xlfn.XLOOKUP(L49,'Customer Data'!$H:$H,'Customer Data'!$E:$F,,0)} -> 64037 | W49: 1085 | Y49: NA | Z49: 1 | AA49: =W49/T49 -> 0.01694334 | AB49: Transportation In Chgs - 01 - 15 JUL 25 | AF49: 45856 | AG49: 45912 | AH49: 1400001170
A50: 6779 | B50: 100222335 | C50: DELIGHT LOGISTICS PRIVATE LIMITED | D50: 2025 | E50: 7 | F50: 45856 | G50: 1800010720 | H50: DR | I50: 45856 | J50: 45859 | K50: NA | L50: 256779415504 | M50: 212100 | N50: Trade Debtors (Ctrl) | P50: 1 | Q50: USD | R50: 25.78 | S50: INR | T50: 2217.1 | V50: {=_xlfn.XLOOKUP(L50,'Customer Data'!$H:$H,'Customer Data'!$E:$F,,0)} -> 2217 | W50: 0 | Y50: NA | Z50: 1 | AB50: Outbound chgs - 01 - 15 Jul 25 | AF50: 45856 | AG50: 45912 | AH50: 1400001170
A51: 6779 | B51: 100222335 | C51: DELIGHT LOGISTICS PRIVATE LIMITED | D51: 2025 | E51: 7 | F51: 45856 | G51: 1800010798 | H51: DR | I51: 45856 | J51: 45859 | K51: NA | L51: 256779415558 | M51: 212100 | N51: Trade Debtors (Ctrl) | P51: 1 | Q51: USD | R51: 20.63 | S51: INR | T51: 1774.19 | V51: {=_xlfn.XLOOKUP(L51,'Customer Data'!$H:$H,'Customer Data'!$E:$F,,0)} -> #N/A | Y51: NA | Z51: 1 | AA51: =W51/T51 -> 0 | AB51: Bond Stamp Paper Chgs - 01 to 15 JUL 25 | AF51: 45856 | AG51: 45976 | AH51: 1400001884
A52: 6779 | B52: 100222335 | C52: DELIGHT LOGISTICS PRIVATE LIMITED | D52: 2025 | E52: 7 | F52: 45856 | G52: 1800010962 | H52: DR | I52: 45856 | J52: 45859 | K52: NA | L52: 256779415722 | M52: 212100 | N52: Trade Debtors (Ctrl) | P52: 1 | Q52: USD | R52: 20.63 | S52: INR | T52: 1774.19 | V52: {=_xlfn.XLOOKUP(L52,'Customer Data'!$H:$H,'Customer Data'!$E:$F,,0)} -> #N/A | Y52: NA | Z52: 1 | AA52: =W52/T52 -> 0 | AB52: Bond Stamp Paper Chgs - 01 to 15 JUL 25 | AF52: 45856 | AG52: 45976 | AH52: 1400001884
A53: 6779 | B53: 100222335 | C53: DELIGHT LOGISTICS PRIVATE LIMITED | D53: 2025 | E53: 7 | F53: 45856 | G53: 1800011024 | H53: DR | I53: 45856 | J53: 45859 | K53: NA | L53: 256779415784 | M53: 212100 | N53: Trade Debtors (Ctrl) | P53: 1 | Q53: USD | R53: 744.61 | S53: INR | T53: 64036.96 | V53: {=_xlfn.XLOOKUP(L53,'Customer Data'!$H:$H,'Customer Data'!$E:$F,,0)} -> #N/A | Y53: NA | Z53: 1 | AA53: =W53/T53 -> 0 | AB53: Transportation In Chgs - 01 - 15 JUL 25 | AF53: 45856 | AG53: 45976 | AH53: 1400001884
A54: 6779 | B54: 100222335 | C54: DELIGHT LOGISTICS PRIVATE LIMITED | D54: 2025 | E54: 3 | F54: 45736 | G54: 1800003633 | H54: DR | I54: 45736 | J54: 45736 | K54: NA | L54: 246779413500 | M54: 212100 | N54: Trade Debtors (Ctrl) | P54: 1 | Q54: USD | R54: 13.45 | S54: INR | T54: 1166 | V54: {=_xlfn.XLOOKUP(L54,'Customer Data'!$H:$H,'Customer Data'!$E:$F,,0)} -> 1166 | W54: 20 | Y54: NA | Z54: 1 | AA54: =W54/T54 -> 0.017152659 | AB54: Inbound Handling charges for Oct 2024 | AF54: 45736 | AG54: 45909 | AH54: 1400001167
A55: 6779 | B55: 100222335 | C55: DELIGHT LOGISTICS PRIVATE LIMITED | D55: 2025 | E55: 3 | F55: 45736 | G55: 1800004640 | H55: DR | I55: 45736 | J55: 45737 | K55: NA | L55: 246779414508 | M55: 212100 | N55: Trade Debtors (Ctrl) | P55: 1 | Q55: USD | R55: 4.09 | S55: INR | T55: 354.57 | V55: {=_xlfn.XLOOKUP(L55,'Customer Data'!$H:$H,'Customer Data'!$E:$F,,0)} -> 355 | W55: 7 | Y55: NA | Z55: 1 | AA55: =W55/T55 -> 0.019742223 | AB55: Inbound Handling charges for Feb 2025 | AF55: 45736 | AG55: 45909 | AH55: 1400001167
A56: 6779 | B56: 100222335 | C56: DELIGHT LOGISTICS PRIVATE LIMITED | D56: 2025 | E56: 3 | F56: 45736 | G56: 1800004641 | H56: DR | I56: 45736 | J56: 45737 | K56: NA | L56: 246779414509 | M56: 212100 | N56: Trade Debtors (Ctrl) | P56: 1 | Q56: USD | R56: 32.71 | S56: INR | T56: 2835.67 | V56: {=_xlfn.XLOOKUP(L56,'Customer Data'!$H:$H,'Customer Data'!$E:$F,,0)} -> 2836 | W56: 49 | Y56: NA | Z56: 1 | AA56: =W56/T56 -> 0.017279867 | AB56: LCL Movement Charges for Feb 2025 | AF56: 45736 | AG56: 45909 | AH56: 1400001167
A57: 6779 | B57: 100222335 | C57: DELIGHT LOGISTICS PRIVATE LIMITED | D57: 2025 | E57: 3 | F57: 45736 | G57: 1800004900 | H57: DR | I57: 45736 | J57: 45737 | K57: NA | L57: 246779414768 | M57: 212100 | N57: Trade Debtors (Ctrl) | P57: 1 | Q57: USD | R57: 68.4 | S57: INR | T57: 5929.68 | V57: {=_xlfn.XLOOKUP(L57,'Customer Data'!$H:$H,'Customer Data'!$E:$F,,0)} -> 5930 | W57: 101 | Y57: NA | Z57: 1 | AA57: =W57/T57 -> 0.01703296 | AB57: Outbound Handling charges for Feb 2025 | AF57: 45736 | AG57: 45909 | AH57: 1400001167
A58: 6779 | B58: 100222335 | C58: DELIGHT LOGISTICS PRIVATE LIMITED | D58: 2025 | E58: 8 | F58: 45889 | G58: 1800012062 | H58: DR | I58: 45889 | J58: 45891 | K58: NA | L58: 256779416597 | M58: 212100 | N58: Trade Debtors (Ctrl) | P58: 1 | Q58: USD | R58: 1097.26 | S58: INR | T58: 94397.41 | V58: {=_xlfn.XLOOKUP(L58,'Customer Data'!$H:$H,'Customer Data'!$E:$F,,0)} -> 94396 | W58: 1600 | Y58: NA | Z58: 1 | AA58: =W58/T58 -> 0.016949618 | AB58: CODC LCL Chgs - 1-15 Aug 25 | AF58: 45889
A59: 6779 | B59: 100222335 | C59: DELIGHT LOGISTICS PRIVATE LIMITED | D59: 2025 | E59: 8 | F59: 45889 | G59: 1800011971 | H59: DR | I59: 45889 | J59: 45891 | K59: NA | L59: 256779416620 | M59: 212100 | N59: Trade Debtors (Ctrl) | P59: 1 | Q59: USD | R59: 1350.3 | S59: INR | T59: 116166.47 | V59: {=_xlfn.XLOOKUP(L59,'Customer Data'!$H:$H,'Customer Data'!$E:$F,,0)} -> 116166 | W59: 1969 | Y59: NA | Z59: 1 | AA59: =W59/T59 -> 0.016949813 | AB59: Storage 1-15 Aug-25 -CODC | AF59: 45889
A60: 6779 | B60: 100222335 | C60: DELIGHT LOGISTICS PRIVATE LIMITED | D60: 2025 | E60: 8 | F60: 45889 | G60: 1800012114 | H60: DR | I60: 45889 | J60: 45891 | K60: NA | L60: 256779416664 | M60: 212100 | N60: Trade Debtors (Ctrl) | P60: 1 | Q60: USD | R60: 494.79 | S60: INR | T60: 42566.84 | V60: {=_xlfn.XLOOKUP(L60,'Customer Data'!$H:$H,'Customer Data'!$E:$F,,0)} -> 42566 | W60: 721 | Y60: NA | Z60: 1 | AA60: =W60/T60 -> 0.016938067 | AB60: Storage 1-15 Aug-25,WH-3 | AF60: 45889
A61: 6779 | B61: 100222335 | C61: DELIGHT LOGISTICS PRIVATE LIMITED | D61: 2025 | E61: 8 | F61: 45889 | G61: 1800012235 | H61: DR | I61: 45889 | J61: 45891 | K61: NA | L61: 256779416831 | M61: 212100 | N61: Trade Debtors (Ctrl) | P61: 1 | Q61: USD | R61: 44.38 | S61: INR | T61: 3818.02 | V61: {=_xlfn.XLOOKUP(L61,'Customer Data'!$H:$H,'Customer Data'!$E:$F,,0)} -> 3818 | W61: 65 | Y61: NA | Z61: 1 | AA61: =W61/T61 -> 0.017024531 | AB61: LCL Chgs - 01 - 15 AUG 25 | AF61: 45889
A62: 6779 | B62: 100222335 | C62: DELIGHT LOGISTICS PRIVATE LIMITED | D62: 2025 | E62: 8 | F62: 45889 | G62: 1800012199 | H62: DR | I62: 45889 | J62: 45891 | K62: NA | L62: 256779416861 | M62: 212100 | N62: Trade Debtors (Ctrl) | P62: 1 | Q62: USD | R62: 13.23 | S62: INR | T62: 1138.18 | V62: {=_xlfn.XLOOKUP(L62,'Customer Data'!$H:$H,'Customer Data'!$E:$F,,0)} -> 1138 | W62: 19 | Y62: NA | Z62: 1 | AA62: =W62/T62 -> 0.016693317 | AB62: Outbound chgs - 01 - 15 Aug 25 | AF62: 45889
A63: 6779 | B63: 100222335 | C63: DELIGHT LOGISTICS PRIVATE LIMITED | D63: 2025 | E63: 5 | F63: 45797 | G63: 1800008709 | H63: DR | I63: 45797 | J63: 45805 | K63: NA | L63: 256779413473 | M63: 212100 | N63: Trade Debtors (Ctrl) | P63: 1 | Q63: USD | R63: 35.88 | S63: INR | T63: 3085.1 | V63: {=_xlfn.XLOOKUP(L63,'Customer Data'!$H:$H,'Customer Data'!$E:$F,,0)} -> 3085 | W63: 52 | Y63: NA | Z63: 1 | AA63: =W63/T63 -> 0.016855207 | AB63: Outbound chgs - 01 - 15 MAY 25 | AF63: 45797 | AG63: 45909 | AH63: 1400001167
A64: 6779 | B64: 100222335 | C64: DELIGHT LOGISTICS PRIVATE LIMITED | D64: 2025 | E64: 5 | F64: 45797 | G64: 1800009111 | H64: DR | I64: 45797 | J64: 45805 | K64: NA | L64: 256779413875 | M64: 212100 | N64: Trade Debtors (Ctrl) | P64: 1 | Q64: USD | R64: 175.46 | S64: INR | T64: 15086.7 | V64: {=_xlfn.XLOOKUP(L64,'Customer Data'!$H:$H,'Customer Data'!$E:$F,,0)} -> 15086 | W64: 256 | Y64: NA | Z64: 1 | AA64: =W64/T64 -> 0.016968588 | AB64: LCL Chgs - 01-15 MAY 25 | AF64: 45797 | AG64: 45909 | AH64: 1400001167
A65: 6779 | B65: 100222335 | C65: DELIGHT LOGISTICS PRIVATE LIMITED | D65: 2025 | E65: 8 | F65: 45873 | G65: 1600002017 | H65: DG | I65: 45873 | J65: 45873 | K65: NA | L65: 256779421593 | M65: 212100 | N65: Trade Debtors (Ctrl) | P65: 11 | Q65: USD | R65: -20.63 | S65: INR | T65: -1774.19 | V65: {=_xlfn.XLOOKUP(L65,'Customer Data'!$H:$H,'Customer Data'!$E:$F,,0)} -> #N/A | Y65: NA | Z65: 1 | AA65: =W65/T65 -> 0 | AB65: Credit note raised against 256779415558 | AF65: 45873 | AG65: 45976 | AH65: 1400001884
A66: 6779 | B66: 100222335 | C66: DELIGHT LOGISTICS PRIVATE LIMITED | D66: 2025 | E66: 8 | F66: 45873 | G66: 1600002031 | H66: DG | I66: 45873 | J66: 45873 | K66: NA | L66: 256779421607 | M66: 212100 | N66: Trade Debtors (Ctrl) | P66: 11 | Q66: USD | R66: -20.63 | S66: INR | T66: -1774.19 | V66: {=_xlfn.XLOOKUP(L66,'Customer Data'!$H:$H,'Customer Data'!$E:$F,,0)} -> #N/A | Y66: NA | Z66: 1 | AA66: =W66/T66 -> 0 | AB66: Credit note raised against 256779415722 | AF66: 45873 | AG66: 45976 | AH66: 1400001884
A67: 6779 | B67: 100222335 | C67: DELIGHT LOGISTICS PRIVATE LIMITED | D67: 2025 | E67: 8 | F67: 45873 | G67: 1600002040 | H67: DG | I67: 45873 | J67: 45873 | K67: NA | L67: 256779421616 | M67: 212100 | N67: Trade Debtors (Ctrl) | P67: 11 | Q67: USD | R67: -744.61 | S67: INR | T67: -64036.96 | V67: {=_xlfn.XLOOKUP(L67,'Customer Data'!$H:$H,'Customer Data'!$E:$F,,0)} -> #N/A | Y67: NA | Z67: 1 | AA67: =W67/T67 -> 0 | AB67: Credit note raised against 256779415784 | AF67: 45873 | AG67: 45976 | AH67: 1400001884
A68: 6779 | B68: 100222335 | C68: DELIGHT LOGISTICS PRIVATE LIMITED | D68: 2025 | E68: 4 | F68: 45750 | G68: 1800005295 | H68: DR | I68: 45750 | J68: 45752 | K68: NA | L68: 256779410187 | M68: 212100 | N68: Trade Debtors (Ctrl) | P68: 1 | Q68: USD | R68: 23.73 | S68: INR | T68: 2062.65 | V68: {=_xlfn.XLOOKUP(L68,'Customer Data'!$H:$H,'Customer Data'!$E:$F,,0)} -> 2063 | W68: 35 | Y68: NA | Z68: 1 | AA68: =W68/T68 -> 0.016968463 | AB68: VAS Activity -1 -15 Mar 25, Ex Rate. 87.01 | AF68: 45750 | AG68: 45909 | AH68: 1400001167
A69: 6779 | B69: 100222335 | C69: DELIGHT LOGISTICS PRIVATE LIMITED | D69: 2025 | E69: 10 | F69: 45950 | G69: 1800013825 | H69: DR | I69: 45950 | J69: 45951 | K69: NA | L69: 256779418643 | M69: 212100 | N69: Trade Debtors (Ctrl) | P69: 1 | Q69: USD | R69: 38.94 | S69: INR | T69: 3434.15 | V69: {=_xlfn.XLOOKUP(L69,'Customer Data'!$H:$H,'Customer Data'!$E:$F,,0)} -> 3434 | W69: 58 | Y69: 2114881 | Z69: 1 | AA69: =W69/T69 -> 0.016889187 | AB69: LCL Chgs - 01 - 15 OCT 25 | AF69: 45950
A70: 6779 | B70: 100222335 | C70: DELIGHT LOGISTICS PRIVATE LIMITED | D70: 2025 | E70: 12 | F70: 45995 | G70: 1800015335 | H70: DR | I70: 45995 | J70: 46000 | K70: NA | L70: 256779419781 | M70: 212100 | N70: Trade Debtors (Ctrl) | P70: 1 | Q70: USD | R70: 112.56 | S70: INR | T70: 9984.09 | V70: {=_xlfn.XLOOKUP(L70,'Customer Data'!$H:$H,'Customer Data'!$E:$F,,0)} -> 9984 | W70: 169 | Y70: NA | Z70: 1 | AA70: =W70/T70 -> 0.016926931 | AB70: Storage -CODC 16-30 Nov 25 | AF70: 45995
A71: 6779 | B71: 100222335 | C71: DELIGHT LOGISTICS PRIVATE LIMITED | D71: 2025 | E71: 8 | F71: 45888 | G71: 1800011920 | H71: DR | I71: 45888 | J71: 45888 | K71: NA | L71: 256779416570 | M71: 212100 | N71: Trade Debtors (Ctrl) | P71: 1 | Q71: USD | R71: 3.63 | S71: INR | T71: 312.29 | V71: {=_xlfn.XLOOKUP(L71,'Customer Data'!$H:$H,'Customer Data'!$E:$F,,0)} -> #N/A | Y71: NA | Z71: 1 | AA71: =W71/T71 -> 0 | AB71: Storage 16-31 Jul 25-CODC | AF71: 45888
A72: 6779 | B72: 100222335 | C72: DELIGHT LOGISTICS PRIVATE LIMITED | D72: 2025 | E72: 9 | F72: 45919 | G72: 1800013017 | H72: DR | I72: 45919 | J72: 45922 | K72: NA | L72: 256779417643 | M72: 212100 | N72: Trade Debtors (Ctrl) | P72: 1 | Q72: USD | R72: 503.06 | S72: INR | T72: 44024.96 | V72: {=_xlfn.XLOOKUP(L72,'Customer Data'!$H:$H,'Customer Data'!$E:$F,,0)} -> 44047 | W72: 746 | Y72: 2102534 | Z72: 1 | AA72: =W72/T72 -> 0.016944933 | AB72: Storage WH-03-1-15 Sep 25 | AF72: 45919
A73: 6779 | B73: 100222335 | C73: DELIGHT LOGISTICS PRIVATE LIMITED | D73: 2025 | E73: 5 | F73: 45798 | G73: 1800008919 | H73: DR | I73: 45798 | J73: 45805 | K73: NA | L73: 256779413683 | M73: 212100 | N73: Trade Debtors (Ctrl) | P73: 1 | Q73: USD | R73: 112.44 | S73: INR | T73: 9668.01 | V73: {=_xlfn.XLOOKUP(L73,'Customer Data'!$H:$H,'Customer Data'!$E:$F,,0)} -> #N/A | Y73: NA | Z73: 1 | AA73: =W73/T73 -> 0 | AB73: Storage 1-15 May-25,WH-3 | AF73: 45798
A74: 6779 | B74: 100222335 | C74: DELIGHT LOGISTICS PRIVATE LIMITED | D74: 2025 | E74: 4 | F74: 45771 | G74: 1800007894 | H74: DR | I74: 45771 | J74: 45773 | K74: NA | L74: 256779412785 | M74: 212100 | N74: Trade Debtors (Ctrl) | P74: 1 | Q74: USD | R74: 60.31 | S74: INR | T74: 5242.25 | V74: {=_xlfn.XLOOKUP(L74,'Customer Data'!$H:$H,'Customer Data'!$E:$F,,0)} -> #N/A | Y74: NA | Z74: 1 | AA74: =W74/T74 -> 0 | AB74: VAS 1-15 April-25,Ex.Rate-85.69 | AF74: 45771
A75: 6779 | B75: 100222335 | C75: DELIGHT LOGISTICS PRIVATE LIMITED | D75: 2025 | E75: 4 | F75: 45771 | G75: 1800007927 | H75: DR | I75: 45771 | J75: 45773 | K75: NA | L75: 256779412818 | M75: 212100 | N75: Trade Debtors (Ctrl) | P75: 1 | Q75: USD | R75: 86 | S75: INR | T75: 7475.28 | V75: {=_xlfn.XLOOKUP(L75,'Customer Data'!$H:$H,'Customer Data'!$E:$F,,0)} -> #N/A | Y75: NA | Z75: 1 | AA75: =W75/T75 -> 0 | AB75: Storage 1-15 April-25 | AF75: 45771
A76: 6779 | B76: 100222335 | C76: DELIGHT LOGISTICS PRIVATE LIMITED | D76: 2025 | E76: 6 | F76: 45826 | G76: 1800009856 | H76: DR | I76: 45826 | J76: 45829 | K76: NA | L76: 256779414620 | M76: 212100 | N76: Trade Debtors (Ctrl) | P76: 1 | Q76: USD | R76: 65.42 | S76: INR | T76: 5592.81 | V76: {=_xlfn.XLOOKUP(L76,'Customer Data'!$H:$H,'Customer Data'!$E:$F,,0)} -> #N/A | Y76: NA | Z76: 1 | AA76: =W76/T76 -> 0 | AB76: Storage 1-15 June-25,WH-3 | AF76: 45826
A77: 6779 | B77: 100222335 | C77: DELIGHT LOGISTICS PRIVATE LIMITED | D77: 2025 | E77: 3 | F77: 45735 | G77: 1800002759 | H77: DR | I77: 45735 | J77: 45735 | K77: NA | L77: 246779412626 | M77: 212100 | N77: Trade Debtors (Ctrl) | P77: 1 | Q77: USD | R77: 276.49 | S77: INR | T77: 23969.27 | V77: {=_xlfn.XLOOKUP(L77,'Customer Data'!$H:$H,'Customer Data'!$E:$F,,0)} -> 23969 | W77: 407 | Y77: NA | Z77: 1 | AA77: =W77/T77 -> 0.016980075 | AB77: Storage charges for Aug 2024 | AF77: 45735 | AG77: 45909 | AH77: 1400001167
A78: 6779 | B78: 100222335 | C78: DELIGHT LOGISTICS PRIVATE LIMITED | D78: 2025 | E78: 3 | F78: 45735 | G78: 1800002845 | H78: DR | I78: 45735 | J78: 45735 | K78: NA | L78: 246779412712 | M78: 212100 | N78: Trade Debtors (Ctrl) | P78: 1 | Q78: USD | R78: 253.85 | S78: INR | T78: 22006.58 | V78: {=_xlfn.XLOOKUP(L78,'Customer Data'!$H:$H,'Customer Data'!$E:$F,,0)} -> 22007 | W78: 373 | Y78: NA | Z78: 1 | AA78: =W78/T78 -> 0.016949476 | AB78: Storage charges for Sept 2024 | AF78: 45735 | AG78: 45909 | AH78: 1400001167
A79: 6779 | B79: 100222335 | C79: DELIGHT LOGISTICS PRIVATE LIMITED | D79: 2025 | E79: 3 | F79: 45735 | G79: 1800002918 | H79: DR | I79: 45735 | J79: 45735 | K79: NA | L79: 246779412785 | M79: 212100 | N79: Trade Debtors (Ctrl) | P79: 1 | Q79: USD | R79: 283.03 | S79: INR | T79: 24536.23 | V79: {=_xlfn.XLOOKUP(L79,'Customer Data'!$H:$H,'Customer Data'!$E:$F,,0)} -> 24537 | W79: 416 | Y79: NA | Z79: 1 | AA79: =W79/T79 -> 0.01695452 | AB79: Storage charges for Oct 2024 | AF79: 45735 | AG79: 45909 | AH79: 1400001167
A80: 6779 | B80: 100222335 | C80: DELIGHT LOGISTICS PRIVATE LIMITED | D80: 2025 | E80: 3 | F80: 45735 | G80: 1800002996 | H80: DR | I80: 45735 | J80: 45735 | K80: NA | L80: 246779412863 | M80: 212100 | N80: Trade Debtors (Ctrl) | P80: 1 | Q80: USD | R80: 319.27 | S80: INR | T80: 27677.92 | V80: {=_xlfn.XLOOKUP(L80,'Customer Data'!$H:$H,'Customer Data'!$E:$F,,0)} -> 27677 | W80: 470 | Y80: NA | Z80: 1 | AA80: =W80/T80 -> 0.016981045 | AB80: Storage charges for Nov 2024 | AF80: 45735 | AG80: 45909 | AH80: 1400001167
A81: 6779 | B81: 100222335 | C81: DELIGHT LOGISTICS PRIVATE LIMITED | D81: 2025 | E81: 3 | F81: 45735 | G81: 1800003067 | H81: DR | I81: 45735 | J81: 45735 | K81: NA | L81: 246779412934 | M81: 212100 | N81: Trade Debtors (Ctrl) | P81: 1 | Q81: USD | R81: 329.89 | S81: INR | T81: 28598.58 | V81: {=_xlfn.XLOOKUP(L81,'Customer Data'!$H:$H,'Customer Data'!$E:$F,,0)} -> 28600 | W81: 485 | Y81: NA | Z81: 1 | AA81: =W81/T81 -> 0.016958884 | AB81: Storage charges for Dec 2024 | AF81: 45735 | AG81: 45909 | AH81: 1400001167
A82: 6779 | B82: 100222335 | C82: DELIGHT LOGISTICS PRIVATE LIMITED | D82: 2025 | E82: 3 | F82: 45735 | G82: 1800003512 | H82: DR | I82: 45735 | J82: 45736 | K82: NA | L82: 246779413379 | M82: 212100 | N82: Trade Debtors (Ctrl) | P82: 1 | Q82: USD | R82: 3.89 | S82: INR | T82: 337.23 | V82: {=_xlfn.XLOOKUP(L82,'Customer Data'!$H:$H,'Customer Data'!$E:$F,,0)} -> 337 | W82: 6 | Y82: NA | Z82: 1 | AA82: =W82/T82 -> 0.017792011 | AB82: Outbound Handling charges for Oct 2024 | AF82: 45735 | AG82: 45909 | AH82: 1400001167
A83: 6779 | B83: 100222335 | C83: DELIGHT LOGISTICS PRIVATE LIMITED | D83: 2025 | E83: 11 | F83: 45981 | G83: 1800014898 | H83: DR | I83: 45981 | J83: 45982 | K83: NA | L83: 256779419447 | M83: 212100 | N83: Trade Debtors (Ctrl) | P83: 1 | Q83: USD | R83: 39.9 | S83: INR | T83: 3511.34 | V83: {=_xlfn.XLOOKUP(L83,'Customer Data'!$H:$H,'Customer Data'!$E:$F,,0)} -> 3511.22 | W83: 70.22 | Y83: 2130554 | Z83: 1 | AA83: =W83/T83 -> 0.019998063 | AB83: VAS-Nov 1-15, 2025 | AF83: 45981
A84: 6779 | B84: 100222335 | C84: DELIGHT LOGISTICS PRIVATE LIMITED | D84: 2025 | E84: 11 | F84: 45981 | G84: 1800015025 | H84: DR | I84: 45981 | J84: 45985 | K84: NA | L84: 256779419526 | M84: 212100 | N84: Trade Debtors (Ctrl) | P84: 1 | Q84: USD | R84: 150.29 | S84: INR | T84: 13226.03 | V84: {=_xlfn.XLOOKUP(L84,'Customer Data'!$H:$H,'Customer Data'!$E:$F,,0)} -> 13227 | W84: 224 | Y84: NA | Z84: 1 | AA84: =W84/T84 -> 0.016936299 | AB84: CODC LCL Chgs -1-15 Nov 25 | AF84: 45981
A85: 6779 | B85: 100222335 | C85: DELIGHT LOGISTICS PRIVATE LIMITED | D85: 2025 | E85: 11 | F85: 45981 | G85: 1800015058 | H85: DR | I85: 45981 | J85: 45985 | K85: NA | L85: 256779419571 | M85: 212100 | N85: Trade Debtors (Ctrl) | P85: 1 | Q85: USD | R85: 42.03 | S85: INR | T85: 3698.78 | V85: {=_xlfn.XLOOKUP(L85,'Customer Data'!$H:$H,'Customer Data'!$E:$F,,0)} -> 3699 | W85: 62 | Y85: 2130611 | Z85: 1 | AA85: =W85/T85 -> 0.016762284 | AB85: LCL Chgs - 01 - 15 NOV 25 | AF85: 45981
A86: 6779 | B86: 100222335 | C86: DELIGHT LOGISTICS PRIVATE LIMITED | D86: 2025 | E86: 11 | F86: 45981 | G86: 1800015110 | H86: DR | I86: 45981 | J86: 45985 | K86: NA | L86: 256779419609 | M86: 212100 | N86: Trade Debtors (Ctrl) | P86: 1 | Q86: USD | R86: 9.89 | S86: INR | T86: 870.35 | V86: {=_xlfn.XLOOKUP(L86,'Customer Data'!$H:$H,'Customer Data'!$E:$F,,0)} -> 870 | W86: 14 | Y86: 2130612 | Z86: 1 | AA86: =W86/T86 -> 0.016085483 | AB86: Outbound chgs - 01 - 15 Nov 25 | AF86: 45981
A87: 6779 | B87: 100222335 | C87: DELIGHT LOGISTICS PRIVATE LIMITED | D87: 2025 | E87: 4 | F87: 45769 | G87: 1800007596 | H87: DR | I87: 45769 | J87: 45770 | K87: NA | L87: 256779412487 | M87: 212100 | N87: Trade Debtors (Ctrl) | P87: 1 | Q87: USD | R87: 104.6 | S87: INR | T87: 9092.02 | V87: {=_xlfn.XLOOKUP(L87,'Customer Data'!$H:$H,'Customer Data'!$E:$F,,0)} -> #N/A | Y87: NA | Z87: 1 | AA87: =W87/T87 -> 0 | AB87: Inbound Handling charges for Feb 2025 | AF87: 45769
A88: 6779 | B88: 100222335 | C88: DELIGHT LOGISTICS PRIVATE LIMITED | D88: 2025 | E88: 4 | F88: 45769 | G88: 1800007606 | H88: DR | I88: 45769 | J88: 45770 | K88: NA | L88: 256779412497 | M88: 212100 | N88: Trade Debtors (Ctrl) | P88: 1 | Q88: USD | R88: 36.8 | S88: INR | T88: 3198.72 | V88: {=_xlfn.XLOOKUP(L88,'Customer Data'!$H:$H,'Customer Data'!$E:$F,,0)} -> 3199 | W88: 54 | Y88: NA | Z88: 1 | AA88: =W88/T88 -> 0.016881753 | AB88: Inbound Handling charges for Feb 2025 | AF88: 45769
A89: 6779 | B89: 100222335 | C89: DELIGHT LOGISTICS PRIVATE LIMITED | D89: 2025 | E89: 4 | F89: 45769 | G89: 1800007747 | H89: DR | I89: 45769 | J89: 45770 | K89: NA | L89: 256779412638 | M89: 212100 | N89: Trade Debtors (Ctrl) | P89: 1 | Q89: USD | R89: 3.89 | S89: INR | T89: 338.13 | V89: {=_xlfn.XLOOKUP(L89,'Customer Data'!$H:$H,'Customer Data'!$E:$F,,0)} -> 338 | W89: 6 | Y89: NA | Z89: 1 | AA89: =W89/T89 -> 0.017744654 | AB89: Outbound Handling charges for 31 Mar 25 | AF89: 45769 | AG89: 45909 | AH89: 1400001167
A90: 6779 | B90: 100222335 | C90: DELIGHT LOGISTICS PRIVATE LIMITED | D90: 2025 | E90: 9 | F90: 45918 | G90: 1800012968 | H90: DR | I90: 45918 | J90: 45922 | K90: NA | L90: 256779417503 | M90: 212100 | N90: Trade Debtors (Ctrl) | P90: 1 | Q90: USD | R90: 85.93 | S90: INR | T90: 7520.11 | V90: {=_xlfn.XLOOKUP(L90,'Customer Data'!$H:$H,'Customer Data'!$E:$F,,0)} -> 7520 | W90: 127 | Y90: 2102483 | Z90: 1 | AA90: =W90/T90 -> 0.016888051 | AB90: Outbound chgs - 01 - 15 Sep 25 | AF90: 45918
A91: 6779 | B91: 100222335 | C91: DELIGHT LOGISTICS PRIVATE LIMITED | D91: 2025 | E91: 9 | F91: 45918 | G91: 1800012905 | H91: DR | I91: 45918 | J91: 45922 | K91: NA | L91: 256779417544 | M91: 212100 | N91: Trade Debtors (Ctrl) | P91: 1 | Q91: USD | R91: 80.75 | S91: INR | T91: 7066.78 | V91: {=_xlfn.XLOOKUP(L91,'Customer Data'!$H:$H,'Customer Data'!$E:$F,,0)} -> 7066 | W91: 119 | Y91: 2102480 | Z91: 1 | AA91: =W91/T91 -> 0.016839353 | AB91: LCL Chgs - 01 - 15 SEP 25 | AF91: 45918
A92: 6779 | B92: 100222335 | C92: DELIGHT LOGISTICS PRIVATE LIMITED | D92: 2025 | E92: 9 | F92: 45918 | G92: 1800012896 | H92: DR | I92: 45918 | J92: 45922 | K92: NA | L92: 256779417623 | M92: 212100 | N92: Trade Debtors (Ctrl) | P92: 1 | Q92: USD | R92: 1417.82 | S92: INR | T92: 124079.57 | V92: {=_xlfn.XLOOKUP(L92,'Customer Data'!$H:$H,'Customer Data'!$E:$F,,0)} -> 124079 | W92: 2103 | Y92: 2102529 | Z92: 1 | AA92: =W92/T92 -> 0.016948801 | AB92: Storage -CODC 1-15 Sep 25 | AF92: 45918
A93: 6779 | B93: 100222335 | C93: DELIGHT LOGISTICS PRIVATE LIMITED | D93: 2025 | E93: 12 | F93: 45996 | G93: 1800015267 | H93: DR | I93: 45996 | J93: 46000 | K93: NA | L93: 256779419896 | M93: 212100 | N93: Trade Debtors (Ctrl) | P93: 1 | Q93: USD | R93: 7.08 | S93: INR | T93: 628 | V93: {=_xlfn.XLOOKUP(L93,'Customer Data'!$H:$H,'Customer Data'!$E:$F,,0)} -> 628 | W93: 11 | Y93: 2140088 | Z93: 1 | AA93: =W93/T93 -> 0.017515924 | AB93: Outbound chgs - 16 - 30 Nov 25 | AF93: 45996
A94: 6779 | B94: 100222335 | C94: DELIGHT LOGISTICS PRIVATE LIMITED | D94: 2025 | E94: 4 | F94: 45770 | G94: 1800007989 | H94: DR | I94: 45770 | J94: 45776 | K94: NA | L94: 256779412880 | M94: 212100 | N94: Trade Debtors (Ctrl) | P94: 1 | Q94: USD | R94: 38.94 | S94: INR | T94: 3384.74 | V94: {=_xlfn.XLOOKUP(L94,'Customer Data'!$H:$H,'Customer Data'!$E:$F,,0)} -> 3384 | W94: 58 | Y94: NA | Z94: 1 | AA94: =W94/T94 -> 0.017135733 | AB94: LCL Chgs - 01 - 15 Apr 25 | AF94: 45770 | AG94: 45909 | AH94: 1400001167
A95: 6779 | B95: 100222335 | C95: DELIGHT LOGISTICS PRIVATE LIMITED | D95: 2025 | E95: 4 | F95: 45770 | G95: 1800008019 | H95: DR | I95: 45770 | J95: 45776 | K95: NA | L95: 256779412910 | M95: 212100 | N95: Trade Debtors (Ctrl) | P95: 1 | Q95: USD | R95: 68.96 | S95: INR | T95: 5994.13 | V95: {=_xlfn.XLOOKUP(L95,'Customer Data'!$H:$H,'Customer Data'!$E:$F,,0)} -> 5993.35 | W95: 102 | Y95: NA | Z95: 1 | AA95: =W95/T95 -> 0.017016648 | AB95: Outbound chgs - 01 - 15 Apr 25 | AF95: 45770 | AG95: 45909 | AH95: 1400001167
A96: 6779 | B96: 100222335 | C96: DELIGHT LOGISTICS PRIVATE LIMITED | D96: 2025 | E96: 10 | F96: 45937 | G96: 1800013583 | H96: DR | I96: 45937 | J96: 45939 | K96: NA | L96: 256779418107 | M96: 212100 | N96: Trade Debtors (Ctrl) | P96: 1 | Q96: USD | R96: 129.8 | S96: INR | T96: 11447.16 | V96: {=_xlfn.XLOOKUP(L96,'Customer Data'!$H:$H,'Customer Data'!$E:$F,,0)} -> 11447 | W96: 194 | Y96: 2110803 | Z96: 1 | AA96: =W96/T96 -> 0.016947435 | AB96: Intra - SEZ-16-30 Sept 25 | AF96: 45937
A97: 6779 | B97: 100222335 | C97: DELIGHT LOGISTICS PRIVATE LIMITED | D97: 2025 | E97: 10 | F97: 45937 | G97: 1800013584 | H97: DR | I97: 45937 | J97: 45939 | K97: NA | L97: 256779418108 | M97: 212100 | N97: Trade Debtors (Ctrl) | P97: 1 | Q97: USD | R97: 129.8 | S97: INR | T97: 11447.16 | V97: {=_xlfn.XLOOKUP(L97,'Customer Data'!$H:$H,'Customer Data'!$E:$F,,0)} -> 11447 | W97: 194 | Y97: 2110803 | Z97: 1 | AA97: =W97/T97 -> 0.016947435 | AB97: Intra - SEZ-16-30 Sept 25 | AF97: 45937
A98: 6779 | B98: 100222335 | C98: DELIGHT LOGISTICS PRIVATE LIMITED | D98: 2025 | E98: 7 | F98: 45857 | G98: 1800010844 | H98: DR | I98: 45857 | J98: 45859 | K98: NA | L98: 256779415604 | M98: 212100 | N98: Trade Debtors (Ctrl) | P98: 1 | Q98: USD | R98: 416.5 | S98: INR | T98: 35819.28 | V98: {=_xlfn.XLOOKUP(L98,'Customer Data'!$H:$H,'Customer Data'!$E:$F,,0)} -> 35820 | W98: 607 | Y98: NA | Z98: 1 | AA98: =W98/T98 -> 0.016946181 | AB98: Storage 1-15 July-25,WH-3 | AF98: 45857 | AG98: 45912 | AH98: 1400001170
A99: 6779 | B99: 100222335 | C99: DELIGHT LOGISTICS PRIVATE LIMITED | D99: 2025 | E99: 7 | F99: 45857 | G99: 1800010973 | H99: DR | I99: 45857 | J99: 45859 | K99: NA | L99: 256779415733 | M99: 212100 | N99: Trade Debtors (Ctrl) | P99: 1 | Q99: USD | R99: 5.5 | S99: INR | T99: 473 | V99: {=_xlfn.XLOOKUP(L99,'Customer Data'!$H:$H,'Customer Data'!$E:$F,,0)} -> 473 | W99: 0 | Y99: NA | Z99: 1 | AA99: =W99/T99 -> 0 | AB99: VAS - 1-15 July 25 | AF99: 45857 | AG99: 45912 | AH99: 1400001170
A100: 6779 | B100: 100222335 | C100: DELIGHT LOGISTICS PRIVATE LIMITED | D100: 2025 | E100: 5 | F100: 45787 | G100: 1800008314 | H100: DR | I100: 45787 | J100: 45792 | K100: NA | L100: 256779413197 | M100: 212100 | N100: Trade Debtors (Ctrl) | P100: 1 | Q100: USD | R100: 8.32 | S100: INR | T100: 715.38 | V100: {=_xlfn.XLOOKUP(L100,'Customer Data'!$H:$H,'Customer Data'!$E:$F,,0)} -> #N/A | Y100: NA | Z100: 1 | AA100: =W100/T100 -> 0 | AB100: VAS - 16-30 April 25, Ex.Rate-85.05 | AF100: 45787
...
