Workbook

Sheet Summary
A1: Reconciliation of Ledger as on 31st January 2026
A2: Particulars | B2: Amount
A3: Balance as per Scope Chemicals Pvt Ltd | B3: =-'Customer Data'!E390 -> 1489274.5
A4: Add: TDS to be booked in Ascendus books | B4: =TDS!L2 -> 961633.58
A5: Add: Invoices & CN not recorded in customer books | B5: ='Invoice & CN not in Customers'!H1 -> 2304711.4
A6: Less: Difference of invoice value in both Books | B6: =-'Difference in Invoice Value'!L2 -> -72025.131
A7: Less: Knock off entries difference | B7: ='Foreign Exchnage Gain loss'!H31 -> -1093.08
A8: Derived balance | B8: =SUM(B3:B7) -> 4682501.3
A9: Balance as per Ascent | B9: ='Ascendus Data'!J479 -> 4683369.6
A11: Difference due to Foreign Exchange gain/loss | B11: =B8-B9-B10 -> -868.3137

Sheet TDS
L2: =SUBTOTAL(9,L4:L264) -> 961633.58
A3: Document Number | B3: Document Type | C3: Document Date | D3: Reference | E3: Document Currency Key | F3: Document Currency Value | G3: Company Code Currency Key | H3: Company Code Currency Value | I3: Debit | J3: Credit | K3: Net Amount | L3: TDS | M3: Rate | N3: Text
A4: 1800012476 | B4: DR | C4: 45906 | D4: 256779417084 | E4: USD | F4: 8832.14 | G4: INR | H4: 772938.81 | I4: 0 | J4: 695663.66 | K4: 695663.66 | L4: 77275.149 | M4: 0.099975765 | N4: Unit-Storage-1-31 Aug 25
A5: 1800013274 | B5: DR | C5: 45936 | D5: 256779418010 | E5: USD | F5: 8566.5 | G5: INR | H5: 755486.23 | I5: 0 | J5: 679906.74 | K5: 679906.74 | L5: 75579.489 | M5: 0.10004086 | N5: Unit Storage - 1-30 Sept 2025
A6: 1800000442 | B6: DR | C6: 45719 | D6: 246779410404 | E6: USD | F6: 7394.09 | G6: INR | H6: 641002.98 | I6: 0 | J6: 580687 | K6: 580687 | L6: 60315.98 | M6: 0.094096255 | N6: Storage for the month of Sept 2024
A7: 1800014537 | B7: DR | C7: 45966 | D7: 256779418869 | E7: USD | F7: 6685.47 | G7: INR | H7: 588344.02 | I7: 0 | J7: 529469.76 | K7: 529469.76 | L7: 58874.264 | M7: 0.10006775 | N7: Unit Storage - 1-31 Oct 2025
A8: 1800011658 | B8: DR | C8: 45877 | D8: 256779416088 | E8: USD | F8: 5977.6 | G8: INR | H8: 514253.65 | I8: 0 | J8: 462828 | K8: 462828 | L8: 51425.65 | M8: 0.10000055 | N8: Unit Storage - 1-31 July 25
A9: 1800000417 | B9: DR | C9: 45719 | D9: 246779410379 | E9: USD | F9: 5862.04 | G9: INR | H9: 508187.63 | I9: 0 | J9: 460370 | K9: 460370 | L9: 47817.63 | M9: 0.094094439 | N9: Storage Charges for the month of August, 2024
A10: 1800007226 | B10: DR | C10: 45763 | D10: 256779412117 | E10: USD | F10: 5415.85 | G10: INR | H10: 470755.54 | I10: 0 | J10: 417286 | K10: 417286 | L10: 53469.54 | M10: 0.11358239 | N10: Storage Charges Mar, 25
A11: 1800005904 | B11: DR | C11: 45751 | D11: 256779410795 | E11: USD | F11: 5005.59 | G11: INR | H11: 435094.99 | I11: 0 | J11: 384955 | K11: 384955 | L11: 50139.99 | M11: 0.11523918 | N11: Storage Charges Feb, 25
A12: 1800000956 | B12: DR | C12: 45722 | D12: 246779410896 | E12: USD | F12: 4556.4 | G12: INR | H12: 395000.06 | I12: 0 | J12: 357094 | K12: 357094 | L12: 37906.06 | M12: 0.095964694 | N12: Storage for the month of Dec 2024
A13: 1800009478 | B13: DR | C13: 45815 | D13: 256779414242 | E13: USD | F13: 4585.18 | G13: INR | H13: 391990.61 | I13: 0 | J13: 352792 | K13: 352792 | L13: 39198.61 | M13: 0.099998849 | N13: Unit storage -1-31 May 25
A14: 1800000466 | B14: DR | C14: 45719 | D14: 246779410428 | E14: USD | F14: 4332.22 | G14: INR | H14: 375565.61 | I14: 0 | J14: 340227 | K14: 340227 | L14: 35338.61 | M14: 0.094094371 | N14: Storage for the month of Oct 2024
A15: 1800005921 | B15: DR | C15: 45751 | D15: 256779410812 | E15: USD | F15: 4311.37 | G15: INR | H15: 374752.13 | I15: 0 | J15: 331566 | K15: 331566 | L15: 43186.13 | M15: 0.11523918 | N15: Storage Charges Jan, 25
... A137: 1800004273 | B137: DR | C137: 45736 | D137: 246779414141 | E137: USD | F137: 55 | G137: INR | H137: 4768.02 | I137: 0 | J137: 4652 | K137: 4652 | L137: 116.02 | M137: 0.024332952 | N137: Inbound Handling charges for Sep 2024
A138: 1800010215 | B138: DR | C138: 45842 | D138: 256779414975 | E138: USD | F138: 54.05 | G138: INR | H138: 4648.34 | I138: 0 | J138: 4562.3355 | K138: 4562.3355 | L138: 86.0045 | M138: 0.018502196
A139: 1800012684 | B139: DR | C139: 45904 | D139: 256779417324 | E139: USD | F139: 49.35 | G139: INR | H139: 4318.83 | I139: 0 | J139: 4231.3179 | K139: 4231.3179 | L139: 87.5121 | M139: 0.020262918 | N139: Outbound chgs - 16 - 31 Aug 25
A140: 1800008641 | B140: DR | C140: 45798 | D140: 256779413405 | E140: USD | F140: 47 | G140: INR | H140: 4041.23 | I140: 0 | J140: 3960 | K140: 3960 | L140: 81.23 | M140: 0.020100316 | N140: InKPI-CODC-1-15 May 25-BOE9862672
A141: 1800003760 | B141: DR | C141: 45736 | D141: 246779413627 | E141: USD | F141: 42.3 | G141: INR | H141: 3667.04 | I141: 0 | J141: 3578 | K141: 3578 | L141: 89.04 | M141: 0.024281164 | N141: Outbound Handling charges for Jan 2025
A142: 1800003870 | B142: DR | C142: 45736 | D142: 246779413738 | E142: USD | F142: 42.3 | G142: INR | H142: 3667.04 | I142: 0 | J142: 3603 | K142: 3603 | L142: 64.04 | M142: 0.017463676 | N142: Outbound Handling charges for Jan 2025
A143: 1800000750 | B143: DR | C143: 45720 | D143: 246779410690 | E143: USD | F143: 42.3 | G143: INR | H143: 3667.04 | I143: 0 | J143: 3622 | K143: 3622 | L143: 45.04 | M143: 0.012282386 | N143: Outbound Handling for Oct 2024
A144: 1800000815 | B144: DR | C144: 45720 | D144: 246779410755 | E144: USD | F144: 42.3 | G144: INR | H144: 3667.04 | I144: 0 | J144: 3594 | K144: 3594 | L144: 73.04 | M144: 0.019917972 | N144: Outbound Handling for Nov 2024
A145: 1800008360 | B145: DR | C145: 45787 | D145: 256779413243 | E145: USD | F145: 42.53 | G145: INR | H145: 3656.89 | I145: 0 | J145: 3623 | K145: 3623 | L145: 33.89 | M145: 0.0092674376 | N145: VAS - 16-30 April 25, Ex.Rate-85.05
A146: 1800012275 | B146: DR | C146: 45904 | D146: 256779416911 | E146: USD | F146: 40.85 | G146: INR | H146: 3574.96 | I146: 0 | J146: 3487.4461 | K146: 3487.4461 | L146: 87.5139 | M146: 0.024479686 | N146: CODC LCL Chgs - 16-31 Aug 25
A147: 1800000818 | B147: DR | C147: 45720 | D147: 246779410758 | E147: USD | F147: 37.6 | G147: INR | H147: 3259.59 | I147: 0 | J147: 3219 | K147: 3219 | L147: 40.59 | M147: 0.012452486 | N147: Outbound Handling for Nov 2024
A148: 1800000669 | B148: DR | C148: 45719 | D148: 246779410609 | E148: USD | F148: 37.6 | G148: INR | H148: 3259.59 | I148: 0 | J148: 3203 | K148: 3203 | L148: 56.59 | M148: 0.017361079 | N148: Outbound Handling for Sep 2024
A149: 1800014641 | B149: DR | C149: 45966 | D149: 256779418906 | E149: USD | F149: 35.25 | G149: INR | H149: 3102.12 | I149: 0 | J149: 3014.1161 | K149: 3014.1161 | L149: 88.0039 | M149: 0.028368954 | N149: CODC Out chgs -16-31 Oct 25
A150: 1800005309 | B150: DR | C150: 45750 | D150: 256779410201 | E150: USD | F150: 34.48 | G150: INR | H150: 2997.06 | I150: 0 | J150: 2937 | K150: 2937 | L150: 60.06 | M150: 0.020039639 | N150: VAS Activity -1 -15 Mar 25, Ex Rate. 87.01
... A156: 1800010118 | B156: DR | C156: 45842 | D156: 256779414878 | E156: USD | F156: 31.73 | G156: INR | H156: 2728.8 | I156: 0 | J156: 2642.8006 | K156: 2642.8006 | L156: 85.9994 | M156: 0.031515465 | N156: Inbound chgs - 16 - 30 JUN 25
A157: 1800010208 | B157: DR | C157: 45845 | D157: 256779414968 | E157: USD | F157: 31.58 | G157: INR | H157: 2715.9 | I157: 0 | J157: 2629.9005 | K157: 2629.9005 | L157: 85.9995 | M157: 0.031665194
A158: 1800011011 | B158: DR | C158: 45857 | D158: 256779415771 | E158: USD | F158: 30.76 | G158: INR | H158: 2645.38 | I158: 0 | J158: 2559.3799 | K158: 2559.3799 | L158: 86.0001 | M158: 0.032509545 | N158: VAS - 1-15 July 25
A159: 1800001259 | B159: DR | C159: 45722 | D159: 246779411128 | E159: USD | F159: 28.2 | G159: INR | H159: 2444.69 | I159: 0 | J159: 2406 | K159: 2406 | L159: 38.69 | M159: 0.015826137 | N159: Inbound Handling charges for Oct 2024
A160: 1800004449 | B160: DR | C160: 45737 | D160: 246779414317 | E160: USD | F160: 25 | G160: INR | H160: 2167.28 | I160: 0 | J160: 1907 | K160: 1907 | L160: 260.28 | M160: 0.12009523 | N160: Inbound Handling charges for Oct 2024
A161: 1800001316 | B161: DR | C161: 45722 | D161: 246779411185 | E161: USD | F161: 23.5 | G161: INR | H161: 2037.24 | I161: 0 | J161: 2004 | K161: 2004 | L161: 33.24 | M161: 0.016316192 | N161: Inbound Handling charges for Nov 2024
A162: 1800001317 | B162: DR | C162: 45722 | D162: 246779411186 | E162: USD | F162: 23.5 | G162: INR | H162: 2037.24 | I162: 0 | J162: 2004 | K162: 2004 | L162: 33.24 | M162: 0.016316192 | N162: Inbound Handling charges for Nov 2024
A163: 1800001318 | B163: DR | C163: 45722 | D163: 246779411187 | E163: USD | F163: 23.5 | G163: INR | H163: 2037.24 | I163: 0 | J163: 2004 | K163: 2004 | L163: 33.24 | M163: 0.016316192 | N163: Inbound Handling charges for Nov 2024
A164: 1800001319 | B164: DR | C164: 45722 | D164: 246779411188 | E164: USD | F164: 23.5 | G164: INR | H164: 2037.24 | I164: 0 | J164: 2004 | K164: 2004 | L164: 33.24 | M164: 0.016316192 | N164: Inbound Handling charges for Nov 2024
A165: 1800001320 | B165: DR | C165: 45722 | D165: 246779411189 | E165: USD | F165: 23.5 | G165: INR | H165: 2037.24 | I165: 0 | J165: 2004 | K165: 2004 | L165: 33.24 | M165: 0.016316192 | N165: Inbound Handling charges for Nov 2024
A166: 1800000545 | B166: DR | C166: 45719 | D166: 246779410495 | E166: USD | F166: 23.5 | G166: INR | H166: 2037.24 | I166: 0 | J166: 2009 | K166: 2009 | L166: 28.24 | M166: 0.013861892 | N166: Outbound Handling for Aug 2024
A167: 1800000552 | B167: DR | C167: 45719 | D167: 246779410502 | E167: USD | F167: 23.5 | G167: INR | H167: 2037.24 | I167: 0 | J167: 2009 | K167: 2009 | L167: 28.24 | M167: 0.013861892 | N167: Outbound Handling for Aug 2024
A168: 1800000665 | B168: DR | C168: 45719 | D168: 246779410605 | E168: USD | F168: 23.5 | G168: INR | H168: 2037.24 | I168: 0 | J168: 2009 | K168: 2009 | L168: 28.24 | M168: 0.013861892 | N168: Outbound Handling for Sep 2024
A169: 1800012603 | B169: DR | C169: 45904 | D169: 256779417261 | E169: USD | F169: 22.77 | G169: INR | H169: 1992.7 | I169: 0 | J169: 1992.7012 | K169: 1992.7012 | L169: -0.0012 | M169: -6.0219802e-07 | N169: Bond Stamp Paper Chgs 01 - 31 Aug 25
... A264: 1800010503 | B264: DR | C264: 45842 | D264: 256779415263 | E264: USD | F264: 2.34 | G264: INR | H264: 201.24 | I264: 0 | J264: 201.2416 | K264: 201.2416 | L264: -0.0016 | M264: -7.9507056e-06 | N264: VAS - 16-30 June 25

Sheet Ascendus Data
A2: Document Number | B2: Document Type | C2: Document Date | D2: Entry Date | E2: Document Header Text | F2: Reference | G2: Document Currency Key | H2: Document Currency Value | I2: Company Code Currency Key | J2: Company Code Currency Value | K2: Profit Center | L2: Assignment | M2: Debit | N2: Credit | O2: Net Amount | P2: TDS | Q2: Rate | R2: Text | S2: Clearing Date | T2: Clearing Document | U2: Invoice Reversed in books
A3: 1800012476 | B3: DR | C3: 45906 | D3: 45909 | E3: NA | F3: 256779417084 | G3: USD | H3: 8832.14 | I3: INR | J3: 772938.81 | K3: 6779224500 | L3: NA | M3: {=_xlfn.XLOOKUP(F3,'Customer Data Vlookup'!$L:$L,'Customer Data Vlookup'!$M:$N,,0)} -> 0 | N3: 695663.66 | O3: =N3-M3 -> 695663.66 | P3: =J3-O3 -> 77275.149 | Q3: =P3/J3 -> 0.099975765 | R3: Unit-Storage-1-31 Aug 25
A4: 1800013274 | B4: DR | C4: 45936 | D4: 45937 | E4: NA | F4: 256779418010 | G4: USD | H4: 8566.5 | I4: INR | J4: 755486.23 | K4: 6779224500 | L4: 2110511 | M4: {=_xlfn.XLOOKUP(F4,'Customer Data Vlookup'!$L:$L,'Customer Data Vlookup'!$M:$N,,0)} -> 0 | N4: 679906.74 | O4: =N4-M4 -> 679906.74 | P4: =J4-O4 -> 75579.489 | Q4: =P4/J4 -> 0.10004086 | R4: Unit Storage - 1-30 Sept 2025
A5: 1800016345 | B5: DR | C5: 46028 | D5: 46034 | E5: 2158411 | F5: 256779440235 | G5: USD | H5: 7267.85 | I5: INR | J5: 659507.53 | K5: 6779224500 | L5: NA | M5: {=_xlfn.XLOOKUP(F5,'Customer Data Vlookup'!$L:$L,'Customer Data Vlookup'!$M:$N,,0)} -> #N/A | O5: =N5-M5 -> #N/A | P5: =J5-O5 -> #N/A | Q5: =P5/J5 -> #N/A | R5: Unit Storage - 1-31 DEC 2025
A6: 1800000442 | B6: DR | C6: 45719 | D6: 45719 | E6: NA | F6: 246779410404 | G6: USD | H6: 7394.09 | I6: INR | J6: 641002.98 | K6: 6779224500 | L6: NA | M6: {=_xlfn.XLOOKUP(F6,'Customer Data Vlookup'!$L:$L,'Customer Data Vlookup'!$M:$N,,0)} -> 0 | N6: 580687 | O6: =N6-M6 -> 580687 | P6: =J6-O6 -> 60315.98 | Q6: =P6/J6 -> 0.094096255 | R6: Storage for the month of Sept 2024
A7: 1800015671 | B7: DR | C7: 46024 | D7: 46024 | E7: NA | F7: 256779440004 | G7: USD | H7: 7039.11 | I7: INR | J7: 638750.94 | K7: 6779224500 | L7: 2139799 | M7: {=_xlfn.XLOOKUP(F7,'Customer Data Vlookup'!$L:$L,'Customer Data Vlookup'!$M:$N,,0)} -> #N/A | O7: =N7-M7 -> #N/A | P7: =J7-O7 -> #N/A | Q7: =P7/J7 -> #N/A | R7: Unit Storage - 1-30 Nov 2025
A8: 1800014537 | B8: DR | C8: 45966 | D8: 45967 | E8: NA | F8: 256779418869 | G8: USD | H8: 6685.47 | I8: INR | J8: 588344.02 | K8: 6779224500 | L8: 2123390 | M8: {=_xlfn.XLOOKUP(F8,'Customer Data Vlookup'!$L:$L,'Customer Data Vlookup'!$M:$N,,0)} -> 0 | N8: 529469.76 | O8: =N8-M8 -> 529469.76 | P8: =J8-O8 -> 58874.264 | Q8: =P8/J8 -> 0.10006775 | R8: Unit Storage - 1-31 Oct 2025
A9: 1800011658 | B9: DR | C9: 45877 | D9: 45877 | E9: NA | F9: 256779416088 | G9: USD | H9: 5977.6 | I9: INR | J9: 514253.65 | K9: 6779224500 | L9: NA | M9: {=_xlfn.XLOOKUP(F9,'Customer Data Vlookup'!$L:$L,'Customer Data Vlookup'!$M:$N,,0)} -> 0 | N9: 462828 | O9: =N9-M9 -> 462828 | P9: =J9-O9 -> 51425.65 | Q9: =P9/J9 -> 0.10000055 | R9: Unit Storage - 1-31 July 25
A10: 1800000417 | B10: DR | C10: 45719 | D10: 45719 | E10: NA | F10: 246779410379 | G10: USD | H10: 5862.04 | I10: INR | J10: 508187.63 | K10: 6779224500 | L10: NA | M10: {=_xlfn.XLOOKUP(F10,'Customer Data Vlookup'!$L:$L,'Customer Data Vlookup'!$M:$N,,0)} -> 0 | N10: 460370 | O10: =N10-M10 -> 460370 | P10: =J10-O10 -> 47817.63 | Q10: =P10/J10 -> 0.094094439 | R10: Storage Charges for the month of August, 2024
A11: 1400001985 | B11: DZ | C11: 45972 | D11: 45985 | E11: PUNBR52025110118746241 | G11: INR | H11: 500000 | I11: INR | J11: 500000 | K11: 6779220000 | M11: {=_xlfn.XLOOKUP(F11,'Customer Data Vlookup'!$L:$L,'Customer Data Vlookup'!$M:$N,,0)} -> #N/A | O11: =N11-M11 -> #N/A | P11: =J11-O11 -> #N/A | Q11: =P11/J11 -> #N/A | S11: 45972 | T11: 1400001985 | U11: Yes
A12: 1800007226 | B12: DR | C12: 45763 | D12: 45764 | E12: NA | F12: 256779412117 | G12: USD | H12: 5415.85 | I12: INR | J12: 470755.54 | K12: 6779224500 | L12: NA | M12: {=_xlfn.XLOOKUP(F12,'Customer Data Vlookup'!$L:$L,'Customer Data Vlookup'!$M:$N,,0)} -> 0 | N12: 417286 | O12: =N12-M12 -> 417286 | P12: =J12-O12 -> 53469.54 | Q12: =P12/J12 -> 0.11358239 | R12: Storage Charges Mar, 25
A13: 1800005904 | B13: DR | C13: 45751 | D13: 45752 | E13: NA | F13: 256779410795 | G13: USD | H13: 5005.59 | I13: INR | J13: 435094.99 | L13: NA | M13: {=_xlfn.XLOOKUP(F13,'Customer Data Vlookup'!$L:$L,'Customer Data Vlookup'!$M:$N,,0)} -> 0 | N13: 384955 | O13: =N13-M13 -> 384955 | P13: =J13-O13 -> 50139.99 | Q13: =P13/J13 -> 0.11523918 | R13: Storage Charges Feb, 25
A14: 1800000956 | B14: DR | C14: 45722 | D14: 45722 | E14: NA | F14: 246779410896 | G14: USD | H14: 4556.4 | I14: INR | J14: 395000.06 | K14: 6779224500 | L14: NA | M14: {=_xlfn.XLOOKUP(F14,'Customer Data Vlookup'!$L:$L,'Customer Data Vlookup'!$M:$N,,0)} -> 0 | N14: 357094 | O14: =N14-M14 -> 357094 | P14: =J14-O14 -> 37906.06 | Q14: =P14/J14 -> 0.095964694 | R14: Storage for the month of Dec 2024
A15: 1800009478 | B15: DR | C15: 45815 | D15: 45817 | E15: NA | F15: 256779414242 | G15: USD | H15: 4585.18 | I15: INR | J15: 391990.61 | K15: 6779224500 | L15: NA | M15: {=_xlfn.XLOOKUP(F15,'Customer Data Vlookup'!$L:$L,'Customer Data Vlookup'!$M:$N,,0)} -> 0 | N15: 352792 | O15: =N15-M15 -> 352792 | P15: =J15-O15 -> 39198.61 | Q15: =P15/J15 -> 0.099998849 | R15: Unit storage -1-31 May 25
A16: 1800000466 | B16: DR | C16: 45719 | D16: 45719 | E16: NA | F16: 246779410428 | G16: USD | H16: 4332.22 | I16: INR | J16: 375565.61 | K16: 6779224500 | L16: NA | M16: {=_xlfn.XLOOKUP(F16,'Customer Data Vlookup'!$L:$L,'Customer Data Vlookup'!$M:$N,,0)} -> 0 | N16: 340227 | O16: =N16-M16 -> 340227 | P16: =J16-O16 -> 35338.61 | Q16: =P16/J16 -> 0.094094371 | R16: Storage for the month of Oct 2024
A17: 1800005921 | B17: DR | C17: 45751 | D17: 45752 | E17: NA | F17: 256779410812 | G17: USD | H17: 4311.37 | I17: INR | J17: 374752.13 | L17: NA | M17: {=_xlfn.XLOOKUP(F17,'Customer Data Vlookup'!$L:$L,'Customer Data Vlookup'!$M:$N,,0)} -> 0 | N17: 331566 | O17: =N17-M17 -> 331566 | P17: =J17-O17 -> 43186.13 | Q17: =P17/J17 -> 0.11523918 | R17: Storage Charges Jan, 25
A18: 1800009135 | B18: DR | C18: 45805 | D18: 45805 | E18: NA | F18: 256779413899 | G18: USD | H18: 4312.12 | I18: INR | J18: 370772.03 | K18: 6779224500 | L18: NA | M18: {=_xlfn.XLOOKUP(F18,'Customer Data Vlookup'!$L:$L,'Customer Data Vlookup'!$M:$N,,0)} -> 0 | N18: 333696 | O18: =N18-M18 -> 333696 | P18: =J18-O18 -> 37076.03 | Q18: =P18/J18 -> 0.099996836 | R18: Storage Chgs - 01 - 31 Apr 25
A19: 1400001901 | B19: DY | C19: 45976 | D19: 45976 | E19: NA | F19: KNOCK OFF ENTRY | G19: USD | H19: 3813.11 | I19: INR | J19: 331442.46 | K19: 6779224500 | M19: {=_xlfn.XLOOKUP(F19,'Customer Data Vlookup'!$L:$L,'Customer Data Vlookup'!$M:$N,,0)} -> #N/A | O19: =N19-M19 -> #N/A | P19: =J19-O19 -> #N/A | Q19: =P19/J19 -> #N/A | S19: 45976 | T19: 1400001901 | U19: Yes
A20: 1800010438 | B20: DR | C20: 45842 | D20: 45847 | E20: NA | F20: 256779415198 | G20: USD | H20: 3330.8 | I20: INR | J20: 286451.03 | K20: 6779224500 | L20: NA | M20: {=_xlfn.XLOOKUP(F20,'Customer Data Vlookup'!$L:$L,'Customer Data Vlookup'!$M:$N,,0)} -> 0 | N20: 257812.81 | O20: =N20-M20 -> 257812.81 | P20: =J20-O20 -> 28638.222 | Q20: =P20/J20 -> 0.099975977 | R20: Unit Storage - 1-30 June 25
A21: 1800000934 | B21: DR | C21: 45722 | D21: 45722 | E21: NA | F21: 246779410874 | G21: USD | H21: 3080 | I21: INR | J21: 267009.08 | K21: 6779224500 | L21: NA | M21: {=_xlfn.XLOOKUP(F21,'Customer Data Vlookup'!$L:$L,'Customer Data Vlookup'!$M:$N,,0)} -> 0 | N21: 241385 | O21: =N21-M21 -> 241385 | P21: =J21-O21 -> 25624.08 | Q21: =P21/J21 -> 0.095967073 | R21: Storage for the month of Nov 2024
A22: 1800010649 | B22: DR | C22: 45854 | D22: 45855 | E22: NA | F22: 256779415409 | G22: USD | H22: 1926.06 | I22: INR | J22: 166972.57 | K22: 6779224500 | L22: NA | M22: {=_xlfn.XLOOKUP(F22,'Customer Data Vlookup'!$L:$L,'Customer Data Vlookup'!$M:$N,,0)} -> #N/A | O22: =N22-M22 -> #N/A | P22: =J22-O22 -> #N/A | Q22: =P22/J22 -> #N/A | R22: Debit note Note raised against CN_256779421363 | S22: 45854 | T22: 1400000288 | U22: Yes
A23: 1800003928 | B23: DR | C23: 45736 | D23: 45736 | E23: NA | F23: 246779413796 | G23: USD | H23: 1926.06 | I23: INR | J23: 166972.57 | K23: 6779224500 | L23: NA | M23: {=_xlfn.XLOOKUP(F23,'Customer Data Vlookup'!$L:$L,'Customer Data Vlookup'!$M:$N,,0)} -> 0 | N23: 163631 | O23: =N23-M23 -> 163631 | P23: =J23-O23 -> 3341.57 | Q23: =P23/J23 -> 0.020012688 | R23: Ground Rent Jan 25
A24: 1400000288 | B24: DY | C24: 45854 | D24: 45855 | E24: NA | G24: USD | H24: 1926.06 | I24: INR | J24: 166972.57 | K24: 6779224500 | M24: {=_xlfn.XLOOKUP(F24,'Customer Data Vlookup'!$L:$L,'Customer Data Vlookup'!$M:$N,,0)} -> #N/A | O24: =N24-M24 -> #N/A | P24: =J24-O24 -> #N/A | Q24: =P24/J24 -> #N/A | S24: 45854 | T24: 1400000288 | U24: Yes
A25: 1800000371 | B25: DR | C25: 45716 | D25: 45716 | E25: NA | F25: 246779410340 | G25: USD | H25: 1863.55 | I25: INR | J25: 160831.19 | K25: 6779224500 | L25: NA | M25: {=_xlfn.XLOOKUP(F25,'Customer Data Vlookup'!$L:$L,'Customer Data Vlookup'!$M:$N,,0)} -> 0 | N25: 144772.57 | O25: =N25-M25 -> 144772.57 | P25: =J25-O25 -> 16058.625 | Q25: =P25/J25 -> 0.099847704 | R25: CY-CY Ground Rent charges for Dec 2024
A26: 1800005064 | B26: DR | C26: 45750 | D26: 45752 | E26: NA | F26: 256779410010 | G26: USD | H26: 1793.99 | I26: INR | J26: 155936.88 | L26: NA | M26: {=_xlfn.XLOOKUP(F26,'Customer Data Vlookup'!$L:$L,'Customer Data Vlookup'!$M:$N,,0)} -> 0 | N26: 140649 | O26: =N26-M26 -> 140649 | P26: =J26-O26 -> 15287.88 | Q26: =P26/J26 -> 0.098038899 | R26: CY Longstanding container Ground Rent charges for | S26: 45976 | T26: 1400001901 | U26: Yes
A27: 1800011863 | B27: DR | C27: 45877 | D27: 45877 | E27: NA | F27: 256779416514 | G27: USD | H27: 1804.03 | I27: INR | J27: 155200.92 | K27: 6779224500 | L27: NA | M27: {=_xlfn.XLOOKUP(F27,'Customer Data Vlookup'!$L:$L,'Customer Data Vlookup'!$M:$N,,0)} -> #N/A | O27: =N27-M27 -> #N/A | P27: =J27-O27 -> #N/A | Q27: =P27/J27 -> #N/A | R27: PORT SSR Chgs July 25
A28: 1800010646 | B28: DR | C28: 45854 | D28: 45855 | E28: NA | F28: 256779415406 | G28: USD | H28: 1793.99 | I28: INR | J28: 154827.9 | K28: 6779224500 | L28: NA | M28: {=_xlfn.XLOOKUP(F28,'Customer Data Vlookup'!$L:$L,'Customer Data Vlookup'!$M:$N,,0)} -> #N/A | O28: =N28-M28 -> #N/A | P28: =J28-O28 -> #N/A | Q28: =P28/J28 -> #N/A | R28: Debit note Note raised against CN_256779421358 | S28: 45854 | T28: 1400000285 | U28: Yes
A29: 1400000285 | B29: DY | C29: 45854 | D29: 45855 | E29: NA | G29: USD | H29: 1793.99 | I29: INR | J29: 154827.9 | K29: 6779224500 | M29: {=_xlfn.XLOOKUP(F29,'Customer Data Vlookup'!$L:$L,'Customer Data Vlookup'!$M:$N,,0)} -> #N/A | O29: =N29-M29 -> #N/A | P29: =J29-O29 -> #N/A | Q29: =P29/J29 -> #N/A | S29: 45854 | T29: 1400000285 | U29: Yes
A30: 1800000379 | B30: DR | C30: 45716 | D30: 45716 | E30: NA | F30: 246779410348 | G30: USD | H30: 1793.99 | I30: INR | J30: 154827.9 | K30: 6779224500 | L30: NA | M30: {=_xlfn.XLOOKUP(F30,'Customer Data Vlookup'!$L:$L,'Customer Data Vlookup'!$M:$N,,0)} -> 0 | N30: 151725 | O30: =N30-M30 -> 151725 | P30: =J30-O30 -> 3102.9 | Q30: =P30/J30 -> 0.020040962 | R30: CY Longstanding container Ground Rent charges for
A31: 1800001954 | B31: DR | C31: 45733 | D31: 45733 | E31: NA | F31: 246779411619 | G31: USD | H31: 1765.65 | I31: INR | J31: 153066.42 | K31: 6779224500 | L31: NA | M31: {=_xlfn.XLOOKUP(F31,'Customer Data Vlookup'!$L:$L,'Customer Data Vlookup'!$M:$N,,0)} -> 0 | N31: 143412 | O31: =N31-M31 -> 143412 | P31: =J31-O31 -> 9654.42 | Q31: =P31/J31 -> 0.063073403 | R31: VAS Activity Charges for the month of September, 2
A32: 1800011041 | B32: DR | C32: 45856 | D32: 45859 | E32: NA | F32: 256779415801 | G32: USD | H32: 1762.2 | I32: INR | J32: 151550.38 | K32: 6779224500 | L32: NA | M32: {=_xlfn.XLOOKUP(F32,'Customer Data Vlookup'!$L:$L,'Customer Data Vlookup'!$M:$N,,0)} -> 0 | N32: 148540.36 | O32: =N32-M32 -> 148540.36 | P32: =J32-O32 -> 3010.0228 | Q32: =P32/J32 -> 0.019861533 | R32: Inbound chgs - 01 - 15 JUL 25
A33: 1800013509 | B33: DR | C33: 45935 | D33: 45940 | E33: NA | F33: 256779418399 | G33: USD | H33: 1432.98 | I33: INR | J33: 126375.61 | K33: 6779224500 | L33: 2110981 | M33: {=_xlfn.XLOOKUP(F33,'Customer Data Vlookup'!$L:$L,'Customer Data Vlookup'!$M:$N,,0)} -> #N/A | O33: =N33-M33 -> #N/A | P33: =J33-O33 -> #N/A | Q33: =P33/J33 -> #N/A | R33: PORT SSR Chgs Sep 25
A34: 1800005328 | B34: DR | C34: 45750 | D34: 45752 | E34: NA | F34: 256779410220 | G34: USD | H34: 1314.12 | I34: INR | J34: 114225.7 | L34: NA | M34: {=_xlfn.XLOOKUP(F34,'Customer Data Vlookup'!$L:$L,'Customer Data Vlookup'!$M:$N,,0)} -> 0 | N34: 114223 | O34: =N34-M34 -> 114223 | P34: =J34-O34 -> 2.7 | Q34: =P34/J34 -> 2.3637413e-05 | R34: CY Longstanding container Ground Rent charges for | S34: 45976 | T34: 1400001901 | U34: Yes
A35: 1800000383 | B35: DR | C35: 45716 | D35: 45716 | E35: NA | F35: 246779410352 | G35: USD | H35: 1314.12 | I35: INR | J35: 113413.37 | K35: 6779224500 | L35: NA | M35: {=_xlfn.XLOOKUP(F35,'Customer Data Vlookup'!$L:$L,'Customer Data Vlookup'!$M:$N,,0)} -> 0 | N35: 102103.26 | O35: =N35-M35 -> 102103.26 | P35: =J35-O35 -> 11310.114 | Q35: =P35/J35 -> 0.099724697 | R35: CY Longstanding container Ground Rent charges for
A36: 1800001031 | B36: DR | C36: 45722 | D36: 45722 | E36: NA | F36: 246779410971 | G36: USD | H36: 1205.2 | I36: INR | J36: 104480.31 | K36: 6779224500 | L36: NA | M36: {=_xlfn.XLOOKUP(F36,'Customer Data Vlookup'!$L:$L,'Customer Data Vlookup'!$M:$N,,0)} -> 0 | N36: 36538 | O36: =N36-M36 -> 36538 | P36: =J36-O36 -> 67942.31 | Q36: =P36/J36 -> 0.65028817 | R36: Inbound Handling charges for Aug 2024
A37: 1800010130 | B37: DR | C37: 45842 | D37: 45847 | E37: NA | F37: 256779414890 | G37: USD | H37: 1180.8 | I37: INR | J37: 101549.59 | K37: 6779224500 | L37: NA | M37: {=_xlfn.XLOOKUP(F37,'Customer Data Vlookup'!$L:$L,'Customer Data Vlookup'!$M:$N,,0)} -> 0 | N37: 91401.512 | O37: =N37-M37 -> 91401.512 | P37: =J37-O37 -> 10148.078 | Q37: =P37/J37 -> 0.099932239 | R37: CY Ground rent Chgs - 01 - 30 June 25
A38: 1400001902 | B38: DY | C38: 45976 | D38: 45976 | E38: NA | F38: KNOCK OFF ENTRY | G38: USD | H38: 1117.66 | I38: INR | J38: 96798.99 | K38: 6779224500 | M38: {=_xlfn.XLOOKUP(F38,'Customer Data Vlookup'!$L:$L,'Customer Data Vlookup'!$M:$N,,0)} -> #N/A | O38: =N38-M38 -> #N/A | P38: =J38-O38 -> #N/A | Q38: =P38/J38 -> #N/A | S38: 45976 | T38: 1400001902 | U38: Yes
A39: 1800012646 | B39: DR | C39: 45904 | D39: 45909 | E39: NA | F39: 256779417286 | G39: USD | H39: 1050.9 | I39: INR | J39: 91968.81 | K39: 6779224500 | L39: NA | M39: {=_xlfn.XLOOKUP(F39,'Customer Data Vlookup'!$L:$L,'Customer Data Vlookup'!$M:$N,,0)} -> 0 | N39: 90131.008 | O39: =N39-M39 -> 90131.008 | P39: =J39-O39 -> 1837.8015 | Q39: =P39/J39 -> 0.019982878 | R39: Inbound chgs - 16 - 31 AUG 25
A40: 1400001112 | B40: DY | C40: 45902 | D40: 45902 | G40: INR | H40: 79944.34 | I40: INR | J40: 78561.62 | K40: 6779224500 | M40: {=_xlfn.XLOOKUP(F40,'Customer Data Vlookup'!$L:$L,'Customer Data Vlookup'!$M:$N,,0)} -> #N/A | O40: =N40-M40 -> #N/A | P40: =J40-O40 -> #N/A | Q40: =P40/J40 -> #N/A | S40: 45902 | T40: 1400001112 | U40: Yes
A41: 1800014013 | B41: DR | C41: 45950 | D41: 45951 | E41: NA | F41: 256779418620 | G41: USD | H41: 830.96 | I41: INR | J41: 73283 | K41: 6779224500 | L41: 2114877 | M41: {=_xlfn.XLOOKUP(F41,'Customer Data Vlookup'!$L:$L,'Customer Data Vlookup'!$M:$N,,0)} -> #N/A | O41: =N41-M41 -> #N/A | P41: =J41-O41 -> #N/A | Q41: =P41/J41 -> #N/A | R41: CY Ground rent Chgs - 01 - 15 Oct 25
A42: 1800014633 | B42: DR | C42: 45966 | D42: 45967 | E42: NA | F42: 256779419076 | G42: USD | H42: 799 | I42: INR | J42: 70314.71 | K42: 6779224500 | L42: 2123404 | M42: {=_xlfn.XLOOKUP(F42,'Customer Data Vlookup'!$L:$L,'Customer Data Vlookup'!$M:$N,,0)} -> 0 | N42: 63274.437 | O42: =N42-M42 -> 63274.437 | P42: =J42-O42 -> 7040.2726 | Q42: =P42/J42 -> 0.10012517 | R42: CY Ground rent Chgs - 16 - 31 Oct 25
A43: 1800013478 | B43: DR | C43: 45935 | D43: 45937 | E43: NA | F43: 256779418094 | G43: USD | H43: 771.74 | I43: INR | J43: 68060.34 | K43: 6779224500 | L43: 2110489 | M43: {=_xlfn.XLOOKUP(F43,'Customer Data Vlookup'!$L:$L,'Customer Data Vlookup'!$M:$N,,0)} -> 6791 | N43: 68060.655 | O43: =N43-M43 -> 61269.655 | P43: =J43-O43 -> 6790.6845 | Q43: =P43/J43 -> 0.099774472 | R43: CY Ground rent Chgs - 16 - 30 Sep 25
A44: 1800011787 | B44: DR | C44: 45877 | D44: 45877 | E44: NA | F44: 256779416178 | G44: USD | H44: 782.3 | I44: INR | J44: 67301.36 | K44: 6779224500 | L44: NA | M44: {=_xlfn.XLOOKUP(F44,'Customer Data Vlookup'!$L:$L,'Customer Data Vlookup'!$M:$N,,0)} -> 1351 | N44: 67557 | O44: =N44-M44 -> 66206 | P44: =J44-O44 -> 1095.36 | Q44: =P44/J44 -> 0.016275451 | R44: Inbound chgs - 16 - 31 JUL 25
A45: 1800012493 | B45: DR | C45: 45904 | D45: 45909 | E45: NA | F45: 256779417166 | G45: USD | H45: 760.25 | I45: INR | J45: 66532.77 | K45: 6779224500 | L45: NA | M45: {=_xlfn.XLOOKUP(F45,'Customer Data Vlookup'!$L:$L,'Customer Data Vlookup'!$M:$N,,0)} -> 0 | N45: 59881.68 | O45: =N45-M45 -> 59881.68 | P45: =J45-O45 -> 6651.0897 | Q45: =P45/J45 -> 0.099967124 | R45: CY - CY Grd Rent Chgs - 01 - 31 AUG 25
A46: 1800012554 | B46: DR | C46: 45904 | D46: 45909 | E46: NA | F46: 256779417173 | G46: USD | H46: 743.54 | I46: INR | J46: 65070.4 | K46: 6779224500 | L46: NA | M46: {=_xlfn.XLOOKUP(F46,'Customer Data Vlookup'!$L:$L,'Customer Data Vlookup'!$M:$N,,0)} -> 0 | N46: 58594.344 | O46: =N46-M46 -> 58594.344 | P46: =J46-O46 -> 6476.0555 | Q46: =P46/J46 -> 0.099523831 | R46: CY Ground rent Chgs - 01 - 31 Aug 25
A47: 1800015418 | B47: DR | C47: 45999 | D47: 46000 | E47: NA | F47: 256779419867 | G47: USD | H47: 703.51 | I47: INR | J47: 62401.44 | K47: 6779224500 | L47: 2140083 | M47: {=_xlfn.XLOOKUP(F47,'Customer Data Vlookup'!$L:$L,'Customer Data Vlookup'!$M:$N,,0)} -> 0 | N47: 61159.634 | O47: =N47-M47 -> 61159.634 | P47: =J47-O47 -> 1241.8065 | Q47: =P47/J47 -> 0.019900286 | R47: Gate IN Chgs - 01 - 15 NOV 25
A48: 1800005058 | B48: DR | C48: 45750 | D48: 45752 | E48: NA | F48: 256779410004 | G48: USD | H48: 705 | I48: INR | J48: 61279.88 | L48: NA | M48: {=_xlfn.XLOOKUP(F48,'Customer Data Vlookup'!$L:$L,'Customer Data Vlookup'!$M:$N,,0)} -> 0 | N48: 55272 | O48: =N48-M48 -> 55272 | P48: =J48-O48 -> 6007.88 | Q48: =P48/J48 -> 0.098040009 | R48: CY Longstanding container Ground Rent charges for | S48: 45976 | T48: 1400001901 | U48: Yes
A49: 1800010647 | B49: DR | C49: 45854 | D49: 45855 | E49: NA | F49: 256779415407 | G49: USD | H49: 705 | I49: INR | J49: 60844.08 | K49: 6779224500 | L49: NA | M49: {=_xlfn.XLOOKUP(F49,'Customer Data Vlookup'!$L:$L,'Customer Data Vlookup'!$M:$N,,0)} -> #N/A | O49: =N49-M49 -> #N/A | P49: =J49-O49 -> #N/A | Q49: =P49/J49 -> #N/A | R49: Debit note Note raised against CN_256779421359 | S49: 45854 | T49: 1400000286 | U49: Yes
A50: 1400000286 | B50: DY | C50: 45854 | D50: 45855 | E50: NA | G50: USD | H50: 705 | I50: INR | J50: 60844.08 | K50: 6779224500 | M50: {=_xlfn.XLOOKUP(F50,'Customer Data Vlookup'!$L:$L,'Customer Data Vlookup'!$M:$N,,0)} -> #N/A | O50: =N50-M50 -> #N/A | P50: =J50-O50 -> #N/A | Q50: =P50/J50 -> #N/A | S50: 45854 | T50: 1400000286 | U50: Yes
A51: 1800000391 | B51: DR | C51: 45716 | D51: 45716 | E51: NA | F51: 246779410360 | G51: USD | H51: 705 | I51: INR | J51: 60844.08 | K51: 6779224500 | L51: NA | M51: {=_xlfn.XLOOKUP(F51,'Customer Data Vlookup'!$L:$L,'Customer Data Vlookup'!$M:$N,,0)} -> 0 | N51: 59624 | O51: =N51-M51 -> 59624 | P51: =J51-O51 -> 1220.08 | Q51: =P51/J51 -> 0.020052567 | R51: CY Longstanding container Ground Rent charges for
A52: 1800012586 | B52: DR | C52: 45904 | D52: 45909 | E52: NA | F52: 256779417244 | G52: USD | H52: 685.41 | I52: INR | J52: 59983.2 | K52: 6779224500 | L52: NA | M52: {=_xlfn.XLOOKUP(F52,'Customer Data Vlookup'!$L:$L,'Customer Data Vlookup'!$M:$N,,0)} -> #N/A | O52: =N52-M52 -> #N/A | P52: =J52-O52 -> #N/A | Q52: =P52/J52 -> #N/A | R52: PORT SSR Chgs Aug 25
A53: 1800013382 | B53: DR | C53: 45935 | D53: 45937 | E53: NA | F53: 256779417978 | G53: USD | H53: 582.8 | I53: INR | J53: 51397.58 | K53: 6779224500 | L53: 2110504 | M53: {=_xlfn.XLOOKUP(F53,'Customer Data Vlookup'!$L:$L,'Customer Data Vlookup'!$M:$N,,0)} -> 1058 | N53: 51397.291 | O53: =N53-M53 -> 50339.291 | P53: =J53-O53 -> 1058.2885 | Q53: =P53/J53 -> 0.02059024 | R53: Outbound chgs - 16 - 30 Sep 25
A54: 1800013428 | B54: DR | C54: 45935 | D54: 45937 | E54: NA | F54: 256779418075 | G54: USD | H54: 582.8 | I54: INR | J54: 51397.58 | K54: 6779224500 | L54: 2110503 | M54: {=_xlfn.XLOOKUP(F54,'Customer Data Vlookup'!$L:$L,'Customer Data Vlookup'!$M:$N,,0)} -> 0 | N54: 1972 | O54: =N54-M54 -> 1972 | P54: =J54-O54 -> 49425.58 | Q54: =P54/J54 -> 0.96163243 | R54: Outbound chgs - 16 - 30 Sep 25 | S54: 45976 | T54: 1400001901 | U54: Yes
A55: 1800009171 | B55: DR | C55: 45810 | D55: 45810 | E55: NA | F55: 256779413935 | G55: USD | H55: 590.74 | I55: INR | J55: 50502.82 | K55: 6779224500 | L55: NA | M55: {=_xlfn.XLOOKUP(F55,'Customer Data Vlookup'!$L:$L,'Customer Data Vlookup'!$M:$N,,0)} -> #N/A | O55: =N55-M55 -> #N/A | P55: =J55-O55 -> #N/A | Q55: =P55/J55 -> #N/A | R55: Port SSR Charges - Shifting for Aug to D
A56: 1800009576 | B56: DR | C56: 45821 | D56: 45825 | E56: NA | F56: 256779414340 | G56: USD | H56: 586.09 | I56: INR | J56: 50105.29 | K56: 6779224500 | L56: NA | M56: {=_xlfn.XLOOKUP(F56,'Customer Data Vlookup'!$L:$L,'Customer Data Vlookup'!$M:$N,,0)} -> 0 | N56: 45061.335 | O56: =N56-M56 -> 45061.335 | P56: =J56-O56 -> 5043.9548 | Q56: =P56/J56 -> 0.10066711 | R56: CY Longstanding - March 25,16-31
A57: 1800000370 | B57: DR | C57: 45716 | D57: 45716 | E57: NA | F57: 246779410339 | G57: USD | H57: 575.75 | I57: INR | J57: 49689.33 | K57: 6779224500 | L57: NA | M57: {=_xlfn.XLOOKUP(F57,'Customer Data Vlookup'!$L:$L,'Customer Data Vlookup'!$M:$N,,0)} -> 0 | N57: 44681.825 | O57: =N57-M57 -> 44681.825 | P57: =J57-O57 -> 5007.505 | Q57: =P57/J57 -> 0.10077626 | R57: CY-CY Ground Rent charges for Nov 2024
A58: 1800012871 | B58: DR | C58: 45918 | D58: 45922 | E58: NA | F58: 256779417489 | G58: USD | H58: 533.92 | I58: INR | J58: 46725.65 | K58: 6779224500 | L58: 2102476 | M58: {=_xlfn.XLOOKUP(F58,'Customer Data Vlookup'!$L:$L,'Customer Data Vlookup'!$M:$N,,0)} -> 0 | N58: 42087.392 | O58: =N58-M58 -> 42087.392 | P58: =J58-O58 -> 4638.2584 | Q58: =P58/J58 -> 0.099265787 | R58: CY Ground rent Chgs - 01 - 15 Sep 25
A59: 1800013758 | B59: DR | C59: 45937 | D59: 45939 | E59: NA | F59: 256779418179 | G59: USD | H59: 528.99 | I59: INR | J59: 46652.04 | K59: 6779224500 | L59: 2110802 | M59: {=_xlfn.XLOOKUP(F59,'Customer Data Vlookup'!$L:$L,'Customer Data Vlookup'!$M:$N,,0)} -> #N/A | O59: =N59-M59 -> #N/A | P59: =J59-O59 -> #N/A | Q59: =P59/J59 -> #N/A | R59: VAS-16-30 Sept 25
A60: 1800010650 | B60: DR | C60: 45854 | D60: 45855 | E60: NA | F60: 256779415410 | G60: USD | H60: 531.9 | I60: INR | J60: 46111.08 | K60: 6779224500 | L60: NA | M60: {=_xlfn.XLOOKUP(F60,'Customer Data Vlookup'!$L:$L,'Customer Data Vlookup'!$M:$N,,0)} -> #N/A | O60: =N60-M60 -> #N/A | P60: =J60-O60 -> #N/A | Q60: =P60/J60 -> #N/A | R60: Debit note Note raised against CN_256779421366 | S60: 45854 | T60: 1400000289 | U60: Yes
A61: 1800003989 | B61: DR | C61: 45736 | D61: 45737 | E61: NA | F61: 246779413845 | G61: USD | H61: 531.9 | I61: INR | J61: 46111.08 | K61: 6779224500 | L61: NA | M61: {=_xlfn.XLOOKUP(F61,'Customer Data Vlookup'!$L:$L,'Customer Data Vlookup'!$M:$N,,0)} -> 0 | N61: 45188 | O61: =N61-M61 -> 45188 | P61: =J61-O61 -> 923.08 | Q61: =P61/J61 -> 0.020018616 | R61: Transportation Inbound Aug 24
A62: 1400000289 | B62: DY | C62: 45854 | D62: 45855 | E62: NA | G62: USD | H62: 531.9 | I62: INR | J62: 46111.08 | K62: 6779224500 | M62: {=_xlfn.XLOOKUP(F62,'Customer Data Vlookup'!$L:$L,'Customer Data Vlookup'!$M:$N,,0)} -> #N/A | O62: =N62-M62 -> #N/A | P62: =J62-O62 -> #N/A | Q62: =P62/J62 -> #N/A | S62: 45854 | T62: 1400000289 | U62: Yes
A63: 1800016282 | B63: DR | C63: 46028 | D63: 46031 | E63: 2158342 | F63: 256779440162 | G63: USD | H63: 505.46 | I63: INR | J63: 45867.03 | K63: 6779224500 | L63: NA | M63: {=_xlfn.XLOOKUP(F63,'Customer Data Vlookup'!$L:$L,'Customer Data Vlookup'!$M:$N,,0)} -> #N/A | O63: =N63-M63 -> #N/A | P63: =J63-O63 -> #N/A | Q63: =P63/J63 -> #N/A | R63: PORT SSR Chgs Dec 25
A64: 1800010651 | B64: DR | C64: 45854 | D64: 45855 | E64: NA | F64: 256779415411 | G64: USD | H64: 525 | I64: INR | J64: 45512.91 | K64: 6779224500 | L64: NA | M64: {=_xlfn.XLOOKUP(F64,'Customer Data Vlookup'!$L:$L,'Customer Data Vlookup'!$M:$N,,0)} -> #N/A | O64: =N64-M64 -> #N/A | P64: =J64-O64 -> #N/A | Q64: =P64/J64 -> #N/A | R64: Debit note Note raised against CN_256779421371 | S64: 45854 | T64: 1400000290 | U64: Yes
A65: 1800001410 | B65: DR | C65: 45729 | D65: 45731 | E65: NA | F65: 246779411278 | G65: USD | H65: 525 | I65: INR | J65: 45512.91 | K65: 6779224500 | L65: NA | M65: {=_xlfn.XLOOKUP(F65,'Customer Data Vlookup'!$L:$L,'Customer Data Vlookup'!$M:$N,,0)} -> 0 | N65: 44602 | O65: =N65-M65 -> 44602 | P65: =J65-O65 -> 910.91 | Q65: =P65/J65 -> 0.020014321 | R65: Scanning Charges for the month of August, 2024
A66: 1400000290 | B66: DY | C66: 45854 | D66: 45855 | E66: NA | F66: KNOCK OFF ENTRY | G66: USD | H66: 525 | I66: INR | J66: 45512.91 | K66: 6779224500 | M66: {=_xlfn.XLOOKUP(F66,'Customer Data Vlookup'!$L:$L,'Customer Data Vlookup'!$M:$N,,0)} -> #N/A | O66: =N66-M66 -> #N/A | P66: =J66-O66 -> #N/A | Q66: =P66/J66 -> #N/A | S66: 45854 | T66: 1400000290 | U66: Yes
A67: 1800016693 | B67: DR | C67: 46034 | D67: 46035 | E67: 2158638 | F67: 256779440282 | G67: USD | H67: 498.5 | I67: INR | J67: 45235.46 | K67: 6779224500 | L67: NA | M67: {=_xlfn.XLOOKUP(F67,'Customer Data Vlookup'!$L:$L,'Customer Data Vlookup'!$M:$N,,0)} -> #N/A | O67: =N67-M67 -> #N/A | P67: =J67-O67 -> #N/A | Q67: =P67/J67 -> #N/A | R67: VAS-Dec 25 - 16-31
A68: 1800007792 | B68: DR | C68: 45769 | D68: 45770 | E68: NA | F68: 256779412683 | G68: USD | H68: 517.64 | I68: INR | J68: 44994.21 | K68: 6779224500 | L68: NA | M68: {=_xlfn.XLOOKUP(F68,'Customer Data Vlookup'!$L:$L,'Customer Data Vlookup'!$M:$N,,0)} -> 0 | N68: 43195 | O68: =N68-M68 -> 43195 | P68: =J68-O68 -> 1799.21 | Q68: =P68/J68 -> 0.03998759 | R68: Outbound Handling charges for 31 Mar 25
A69: 1800015043 | B69: DR | C69: 45981 | D69: 45985 | E69: NA | F69: 256779419556 | G69: USD | H69: 502.5 | I69: INR | J69: 44221.7 | K69: 6779224500 | L69: 2130610 | M69: {=_xlfn.XLOOKUP(F69,'Customer Data Vlookup'!$L:$L,'Customer Data Vlookup'!$M:$N,,0)} -> 0 | N69: 39821.534 | O69: =N69-M69 -> 39821.534 | P69: =J69-O69 -> 4400.166 | Q69: =P69/J69 -> 0.099502416 | R69: CY Ground rent Chgs - 01 - 15 Nov 25
A70: 1800003221 | B70: DR | C70: 45735 | D70: 45736 | E70: NA | F70: 246779413088 | G70: USD | H70: 500.63 | I70: INR | J70: 43400.25 | K70: 6779224500 | L70: NA | M70: {=_xlfn.XLOOKUP(F70,'Customer Data Vlookup'!$L:$L,'Customer Data Vlookup'!$M:$N,,0)} -> #N/A | O70: =N70-M70 -> #N/A | P70: =J70-O70 -> #N/A | Q70: =P70/J70 -> #N/A | R70: Port SSR Charges - Shifting for Aug to Dec,24. | S70: 45842 | T70: 1400000248 | U70: Yes
A71: 1800009394 | B71: DR | C71: 45812 | D71: 45817 | E71: NA | F71: 256779414158 | G71: USD | H71: 498.55 | I71: INR | J71: 42621.43 | K71: 6779224500 | L71: NA | M71: {=_xlfn.XLOOKUP(F71,'Customer Data Vlookup'!$L:$L,'Customer Data Vlookup'!$M:$N,,0)} -> 0 | N71: 41769 | O71: =N71-M71 -> 41769 | P71: =J71-O71 -> 852.43 | Q71: =P71/J71 -> 0.020000033 | R71: CODC Inbound chgs - 16 - 31 May 25
A72: 1800015708 | B72: DR | C72: 46024 | D72: 46024 | E72: NA | F72: 256779440041 | G72: USD | H72: 456.75 | I72: INR | J72: 41446.93 | K72: 6779224500 | L72: 2139805 | M72: {=_xlfn.XLOOKUP(F72,'Customer Data Vlookup'!$L:$L,'Customer Data Vlookup'!$M:$N,,0)} -> 4174 | N72: 41446.745 | O72: =N72-M72 -> 37272.745 | P72: =J72-O72 -> 4174.185 | Q72: =P72/J72 -> 0.10071156 | R72: Fixed Storage Charges for December 2025
A73: 1800016623 | B73: DR | C73: 46028 | D73: 46035 | E73: NA | F73: 256779440332 | G73: USD | H73: 456.75 | I73: INR | J73: 41446.93 | K73: 6779224500 | L73: 2158673 | M73: {=_xlfn.XLOOKUP(F73,'Customer Data Vlookup'!$L:$L,'Customer Data Vlookup'!$M:$N,,0)} -> #N/A | O73: =N73-M73 -> #N/A | P73: =J73-O73 -> #N/A | Q73: =P73/J73 -> #N/A | R73: Fixed Storage Charges for January 2026
A74: 1800009411 | B74: DR | C74: 45812 | D74: 45817 | E74: NA | F74: 256779414175 | G74: USD | H74: 472.4 | I74: INR | J74: 40385.84 | K74: 6779224500 | L74: NA | M74: {=_xlfn.XLOOKUP(F74,'Customer Data Vlookup'!$L:$L,'Customer Data Vlookup'!$M:$N,,0)} -> #N/A | O74: =N74-M74 -> #N/A | P74: =J74-O74 -> #N/A | Q74: =P74/J74 -> #N/A | R74: PORT SSR Chgs - 16 - 31 May 25
A75: 1800013460 | B75: DR | C75: 45935 | D75: 45937 | E75: NA | F75: 256779418036 | G75: USD | H75: 456.75 | I75: INR | J75: 40281.13 | K75: 6779224500 | L75: 2110508 | M75: {=_xlfn.XLOOKUP(F75,'Customer Data Vlookup'!$L:$L,'Customer Data Vlookup'!$M:$N,,0)} -> 0 | N75: 36224.359 | O75: =N75-M75 -> 36224.359 | P75: =J75-O75 -> 4056.7712 | Q75: =P75/J75 -> 0.10071145 | R75: Fixed Storage Charges for October 2025
A76: 1800014263 | B76: DR | C76: 45966 | D76: 45966 | E76: NA | F76: 256779418802 | G76: USD | H76: 456.75 | I76: INR | J76: 40195.55 | K76: 6779224500 | L76: 2123159 | M76: {=_xlfn.XLOOKUP(F76,'Customer Data Vlookup'!$L:$L,'Customer Data Vlookup'!$M:$N,,0)} -> 4048 | N76: 40195.392 | O76: =N76-M76 -> 36147.392 | P76: =J76-O76 -> 4048.1576 | Q76: =P76/J76 -> 0.10071159 | R76: Fixed Storage Charges for November 2025
A77: 1800012739 | B77: DR | C77: 45904 | D77: 45909 | E77: NA | F77: 256779417373 | G77: USD | H77: 456.75 | I77: INR | J77: 39972.17 | K77: 6779224500 | L77: NA | M77: {=_xlfn.XLOOKUP(F77,'Customer Data Vlookup'!$L:$L,'Customer Data Vlookup'!$M:$N,,0)} -> 0 | N77: 33482.011 | O77: =N77-M77 -> 33482.011 | P77: =J77-O77 -> 6490.159 | Q77: =P77/J77 -> 0.16236694 | R77: Fixed Storage Charges for September 2025
A78: 1800005399 | B78: DR | C78: 45750 | D78: 45752 | E78: NA | F78: 256779410291 | G78: USD | H78: 456.75 | I78: INR | J78: 39701.54 | L78: NA | M78: {=_xlfn.XLOOKUP(F78,'Customer Data Vlookup'!$L:$L,'Customer Data Vlookup'!$M:$N,,0)} -> #N/A | O78: =N78-M78 -> #N/A | P78: =J78-O78 -> #N/A | Q78: =P78/J78 -> #N/A | R78: Fixed Rental charges for Feb 2025 | S78: 45842 | T78: 1400000246 | U78: Yes
A79: 1800005358 | B79: DR | C79: 45750 | D79: 45752 | E79: NA | F79: 256779410250 | G79: USD | H79: 456.75 | I79: INR | J79: 39701.54 | L79: NA | M79: {=_xlfn.XLOOKUP(F79,'Customer Data Vlookup'!$L:$L,'Customer Data Vlookup'!$M:$N,,0)} -> #N/A | O79: =N79-M79 -> #N/A | P79: =J79-O79 -> #N/A | Q79: =P79/J79 -> #N/A | R79: Fixed Rental charges for Jan 2025 | S79: 45842 | T79: 1400000247 | U79: Yes
A80: 1400000246 | B80: DY | C80: 45842 | D80: 45842 | E80: NA | F80: KNOCK OFF ENTRY | G80: USD | H80: 456.75 | I80: INR | J80: 39701.54 | K80: 6779224500 | M80: {=_xlfn.XLOOKUP(F80,'Customer Data Vlookup'!$L:$L,'Customer Data Vlookup'!$M:$N,,0)} -> #N/A | O80: =N80-M80 -> #N/A | P80: =J80-O80 -> #N/A | Q80: =P80/J80 -> #N/A | S80: 45842 | T80: 1400000246 | U80: Yes
A81: 1400000247 | B81: DY | C81: 45842 | D81: 45842 | E81: NA | F81: KNOCK OFF ENTRY | G81: USD | H81: 456.75 | I81: INR | J81: 39701.54 | K81: 6779224500 | M81: {=_xlfn.XLOOKUP(F81,'Customer Data Vlookup'!$L:$L,'Customer Data Vlookup'!$M:$N,,0)} -> #N/A | O81: =N81-M81 -> #N/A | P81: =J81-O81 -> #N/A | Q81: =P81/J81 -> #N/A | S81: 45842 | T81: 1400000247 | U81: Yes
A82: 1800003133 | B82: DR | C82: 45735 | D82: 45736 | E82: NA | F82: 246779413000 | G82: USD | H82: 456.75 | I82: INR | J82: 39596.23 | K82: 6779224500 | L82: NA | M82: {=_xlfn.XLOOKUP(F82,'Customer Data Vlookup'!$L:$L,'Customer Data Vlookup'!$M:$N,,0)} -> 0 | N82: 35488 | O82: =N82-M82 -> 35488 | P82: =J82-O82 -> 4108.23 | Q82: =P82/J82 -> 0.10375306 | R82: Fixed Storage Charges for Mar 2025
A83: 1800000121 | B83: DR | C83: 45708 | D83: 45708 | E83: NA | F83: 246779410049 | G83: USD | H83: 456.75 | I83: INR | J83: 39419.2 | K83: 6779224500 | L83: NA | M83: {=_xlfn.XLOOKUP(F83,'Customer Data Vlookup'!$L:$L,'Customer Data Vlookup'!$M:$N,,0)} -> 0 | N83: 35554.52 | O83: =N83-M83 -> 35554.52 | P83: =J83-O83 -> 3864.68 | Q83: =P83/J83 -> 0.098040549 | R83: Fixed Rental charges for Sept 2024
A84: 1800000032 | B84: DR | C84: 45708 | D84: 45708 | E84: NA | F84: 246779410072 | G84: USD | H84: 456.75 | I84: INR | J84: 39419.2 | K84: 6779224500 | L84: NA | M84: {=_xlfn.XLOOKUP(F84,'Customer Data Vlookup'!$L:$L,'Customer Data Vlookup'!$M:$N,,0)} -> 0 | N84: 35477 | O84: =N84-M84 -> 35477 | P84: =J84-O84 -> 3942.2 | Q84: =P84/J84 -> 0.1000071 | R84: Fixed Rental charges for Aug 2024
A85: 1800000190 | B85: DR | C85: 45708 | D85: 45708 | E85: NA | F85: 246779410117 | G85: USD | H85: 456.75 | I85: INR | J85: 39419.2 | K85: 6779224500 | L85: NA | M85: {=_xlfn.XLOOKUP(F85,'Customer Data Vlookup'!$L:$L,'Customer Data Vlookup'!$M:$N,,0)} -> 0 | N85: 35554.52 | O85: =N85-M85 -> 35554.52 | P85: =J85-O85 -> 3864.68 | Q85: =P85/J85 -> 0.098040549 | R85: Fixed Rental charges for Nov 2024
A86: 1800000233 | B86: DR | C86: 45708 | D86: 45708 | E86: NA | F86: 246779410160 | G86: USD | H86: 456.75 | I86: INR | J86: 39419.2 | K86: 6779224500 | L86: NA | M86: {=_xlfn.XLOOKUP(F86,'Customer Data Vlookup'!$L:$L,'Customer Data Vlookup'!$M:$N,,0)} -> 0 | N86: 35554.52 | O86: =N86-M86 -> 35554.52 | P86: =J86-O86 -> 3864.68 | Q86: =P86/J86 -> 0.098040549 | R86: Fixed Rental charges for Dec 2024
A87: 1800000276 | B87: DR | C87: 45708 | D87: 45708 | E87: NA | F87: 246779410203 | G87: USD | H87: 456.75 | I87: INR | J87: 39419.2 | K87: 6779224500 | L87: NA | M87: {=_xlfn.XLOOKUP(F87,'Customer Data Vlookup'!$L:$L,'Customer Data Vlookup'!$M:$N,,0)} -> 0 | N87: 35554.52 | O87: =N87-M87 -> 35554.52 | P87: =J87-O87 -> 3864.68 | Q87: =P87/J87 -> 0.098040549 | R87: Fixed Rental charges for Jan 2025
A88: 1800000319 | B88: DR | C88: 45708 | D88: 45708 | E88: NA | F88: 246779410246 | G88: USD | H88: 456.75 | I88: INR | J88: 39419.2 | K88: 6779224500 | L88: NA | M88: {=_xlfn.XLOOKUP(F88,'Customer Data Vlookup'!$L:$L,'Customer Data Vlookup'!$M:$N,,0)} -> 0 | N88: 35554.52 | O88: =N88-M88 -> 35554.52 | P88: =J88-O88 -> 3864.68 | Q88: =P88/J88 -> 0.098040549 | R88: Fixed Rental charges for Feb 2025
A89: 1800000150 | B89: DR | C89: 45708 | D89: 45709 | E89: NA | F89: 246779410303 | G89: USD | H89: 456.75 | I89: INR | J89: 39419.2 | K89: 6779224500 | L89: NA | M89: {=_xlfn.XLOOKUP(F89,'Customer Data Vlookup'!$L:$L,'Customer Data Vlookup'!$M:$N,,0)} -> 0 | N89: 35554.52 | O89: =N89-M89 -> 35554.52 | P89: =J89-O89 -> 3864.68 | Q89: =P89/J89 -> 0.098040549 | R89: Fixed Rental charges for Oct 2024
A90: 1800011345 | B90: DR | C90: 45870 | D90: 45873 | E90: NA | F90: 256779416054 | G90: USD | H90: 456.75 | I90: INR | J90: 39294.26 | K90: 6779224500 | L90: NA | M90: {=_xlfn.XLOOKUP(F90,'Customer Data Vlookup'!$L:$L,'Customer Data Vlookup'!$M:$N,,0)} -> 0 | N90: 35336.872 | O90: =N90-M90 -> 35336.872 | P90: =J90-O90 -> 3957.3882 | Q90: =P90/J90 -> 0.10071161 | R90: Fixed Storage Charges for August 2025
A91: 1800010184 | B91: DR | C91: 45842 | D91: 45847 | E91: NA | F91: 256779414944 | G91: USD | H91: 456.75 | I91: INR | J91: 39280.81 | K91: 6779224500 | L91: NA | M91: {=_xlfn.XLOOKUP(F91,'Customer Data Vlookup'!$L:$L,'Customer Data Vlookup'!$M:$N,,0)} -> 0 | N91: 35324.775 | O91: =N91-M91 -> 35324.775 | P91: =J91-O91 -> 3956.0348 | Q91: =P91/J91 -> 0.10071164 | R91: Fixed Storage Charges fo JULY 2025
A92: 1800013343 | B92: DR | C92: 45935 | D92: 45937 | E92: NA | F92: 256779417939 | G92: USD | H92: 445.35 | I92: INR | J92: 39275.76 | K92: 6779224500 | L92: NA | M92: {=_xlfn.XLOOKUP(F92,'Customer Data Vlookup'!$L:$L,'Customer Data Vlookup'!$M:$N,,0)} -> 0 | N92: 38482.043 | O92: =N92-M92 -> 38482.043 | P92: =J92-O92 -> 793.7175 | Q92: =P92/J92 -> 0.020208839 | R92: Inbound chgs - 16 - 30 SEP 25
A93: 1800008243 | B93: DR | C93: 45787 | D93: 45791 | E93: NA | F93: 256779413127 | G93: USD | H93: 456.75 | I93: INR | J93: 39273.05 | K93: 6779224500 | L93: NA | M93: {=_xlfn.XLOOKUP(F93,'Customer Data Vlookup'!$L:$L,'Customer Data Vlookup'!$M:$N,,0)} -> 0 | N93: 35097 | O93: =N93-M93 -> 35097 | P93: =J93-O93 -> 4176.05 | Q93: =P93/J93 -> 0.10633373 | R93: Fixed Storage Charges fo MAY 2025
A94: 1800007270 | B94: DR | C94: 45768 | D94: 45769 | E94: NA | F94: 256779412161 | G94: USD | H94: 456.75 | I94: INR | J94: 39193.72 | K94: 6779224500 | L94: NA | M94: {=_xlfn.XLOOKUP(F94,'Customer Data Vlookup'!$L:$L,'Customer Data Vlookup'!$M:$N,,0)} -> 0 | N94: 34962 | O94: =N94-M94 -> 34962 | P94: =J94-O94 -> 4231.72 | Q94: =P94/J94 -> 0.10796934 | R94: Fixed Storage Charges for April 2025
A95: 1800009695 | B95: DR | C95: 45826 | D95: 45827 | E95: NA | F95: 256779414459 | G95: USD | H95: 456.75 | I95: INR | J95: 39047.91 | K95: 6779224500 | L95: NA | M95: {=_xlfn.XLOOKUP(F95,'Customer Data Vlookup'!$L:$L,'Customer Data Vlookup'!$M:$N,,0)} -> #N/A | O95: =N95-M95 -> #N/A | P95: =J95-O95 -> #N/A | Q95: =P95/J95 -> #N/A | R95: Fixed Rental charges for Jan 2025 | S95: 45902 | T95: 1400001112 | U95: Yes
A96: 1800009712 | B96: DR | C96: 45826 | D96: 45827 | E96: NA | F96: 256779414476 | G96: USD | H96: 456.75 | I96: INR | J96: 39047.91 | K96: 6779224500 | L96: NA | M96: {=_xlfn.XLOOKUP(F96,'Customer Data Vlookup'!$L:$L,'Customer Data Vlookup'!$M:$N,,0)} -> #N/A | O96: =N96-M96 -> #N/A | P96: =J96-O96 -> #N/A | Q96: =P96/J96 -> #N/A | R96: Fixed Rental charges for Feb 2025 | S96: 45902 | T96: 1400001112 | U96: Yes
A97: 1800009622 | B97: DR | C97: 45818 | D97: 45825 | E97: NA | F97: 256779414386 | G97: USD | H97: 456.75 | I97: INR | J97: 39047.91 | K97: 6779224500 | L97: NA | M97: {=_xlfn.XLOOKUP(F97,'Customer Data Vlookup'!$L:$L,'Customer Data Vlookup'!$M:$N,,0)} -> 0 | N97: 35431 | O97: =N97-M97 -> 35431 | P97: =J97-O97 -> 3616.91 | Q97: =P97/J97 -> 0.092627493 | R97: Fixed Storage Charges fo JUNE 2025
A98: 1800015473 | B98: DR | C98: 45997 | D98: 46000 | E98: NA | F98: 256779419990 | G98: USD | H98: 429.75 | I98: INR | J98: 38118.89 | K98: 6779224500 | L98: 2140458 | M98: {=_xlfn.XLOOKUP(F98,'Customer Data Vlookup'!$L:$L,'Customer Data Vlookup'!$M:$N,,0)} -> #N/A | O98: =N98-M98 -> #N/A | P98: =J98-O98 -> #N/A | Q98: =P98/J98 -> #N/A | R98: PORT SSR Chgs Nov 25
A99: 1800004735 | B99: DR | C99: 45736 | D99: 45737 | E99: NA | F99: 246779414603 | G99: USD | H99: 412.38 | I99: INR | J99: 35749.74 | K99: 6779224500 | L99: NA | M99: {=_xlfn.XLOOKUP(F99,'Customer Data Vlookup'!$L:$L,'Customer Data Vlookup'!$M:$N,,0)} -> 0 | N99: 34760 | O99: =N99-M99 -> 34760 | P99: =J99-O99 -> 989.74 | Q99: =P99/J99 -> 0.027685236 | R99: Outbound Handling charges for Oct 2024
A100: 1800001468 | B100: DR | C100: 45729 | D100: 45733 | E100: NA | F100: 246779411300 | G100: USD | H100: 385 | I100: INR | J100: 33376.14 | K100: 6779224500 | L100: NA | M100: {=_xlfn.XLOOKUP(F100,'Customer Data Vlookup'!$L:$L,'Customer Data Vlookup'!$M:$N,,0)} -> 0 | N100: 33376 | O100: =N100-M100 -> 33376 | P100: =J100-O100 -> 0.14 | Q100: =P100/J100 -> 4.1946133e-06 | R100: Scanning Charges for the month of September, 2024 | S100: 45976 | T100: 1400001901 | U100: Yes
A101: 1800000364 | B101: DR | C101: 45716 | D101: 45716 | E101: NA | F101: 246779410333 | G101: USD | H101: 386.34 | I101: INR | J101: 33342.56 | K101: 6779224500 | L101: NA | M101: {=_xlfn.XLOOKUP(F101,'Customer Data Vlookup'!$L:$L,'Customer Data Vlookup'!$M:$N,,0)} -> 0 | N101: 29975.442 | O101: =N101-M101 -> 29975.442 | P101: =J101-O101 -> 3367.118 | Q101: =P101/J101 -> 0.10098559 | R101: CY-CY Ground Rent charges for Sept 2024
...

Sheet Difference in Invoice Value
L2: =SUBTOTAL(9,L4:L78) -> 72025.131
A3: Document Number | B3: Document Type | C3: Document Date | D3: Reference | E3: Document Currency Key | F3: Document Currency Value | G3: Company Code Currency Key | H3: Company Code Currency Value | I3: Debit | J3: Credit | K3: Net Amount | L3: Difference in Invoice Value | M3: Rate | N3: Text
A4: 1800001954 | B4: DR | C4: 45733 | D4: 246779411619 | E4: USD | F4: 1765.65 | G4: INR | H4: 153066.42 | I4: 0 | J4: 143412 | K4: 143412 | L4: 9654.42 | M4: 0.063073403 | N4: VAS Activity Charges for the month of September, 2
A5: 1800001031 | B5: DR | C5: 45722 | D5: 246779410971 | E5: USD | F5: 1205.2 | G5: INR | H5: 104480.31 | I5: 0 | J5: 36538 | K5: 36538 | L5: 67942.31 | M5: 0.65028817 | N5: Inbound Handling charges for Aug 2024
A6: 1800013428 | B6: DR | C6: 45935 | D6: 256779418075 | E6: USD | F6: 582.8 | G6: INR | H6: 51397.58 | I6: 0 | J6: 1972 | K6: 1972 | L6: 49425.58 | M6: 0.96163243 | N6: Outbound chgs - 16 - 30 Sep 25
A7: 1800007792 | B7: DR | C7: 45769 | D7: 256779412683 | E7: USD | F7: 517.64 | G7: INR | H7: 44994.21 | I7: 0 | J7: 43195 | K7: 43195 | L7: 1799.21 | M7: 0.03998759 | N7: Outbound Handling charges for 31 Mar 25
A8: 1800012739 | B8: DR | C8: 45904 | D8: 256779417373 | E8: USD | F8: 456.75 | G8: INR | H8: 39972.17 | I8: 0 | J8: 33482.011 | K8: 33482.011 | L8: 6490.159 | M8: 0.16236694 | N8: Fixed Storage Charges for September 2025
A9: 1800003783 | B9: DR | C9: 45736 | D9: 246779413705 | E9: USD | F9: 237.35 | G9: INR | H9: 20576.17 | I9: 0 | J9: 19429 | K9: 19429 | L9: 1147.17 | M9: 0.055752358 | N9: Ground Rent Feb 16-28
A10: 1800001426 | B10: DR | C10: 45729 | D10: 246779411339 | E10: USD | F10: 220 | G10: INR | H10: 19072.08 | I10: 0 | J10: 17857 | K10: 17857 | L10: 1215.08 | M10: 0.063709884 | N10: Scanning Charges for the month of December, 2024
A11: 1800009524 | B11: DR | C11: 45812 | D11: 256779414288 | E11: USD | F11: 190 | G11: INR | H11: 16243.25 | I11: 0 | J11: 17313 | K11: 17313 | L11: -1069.75 | M11: -0.065858126 | N11: Scanning Chgs - 16 - 31 May 25
A12: 1800007577 | B12: DR | C12: 45769 | D12: 256779412468 | E12: USD | F12: 169.2 | G12: INR | H12: 14707.17 | I12: 0 | J12: 14119 | K12: 14119 | L12: 588.17 | M12: 0.039992058 | N12: Inbound Handling charges for Feb 2025
A13: 1800001380 | B13: DR | C13: 45722 | D13: 246779411249 | E13: USD | F13: 169.2 | G13: INR | H13: 14668.16 | I13: 0 | J13: 13737 | K13: 13737 | L13: 931.16 | M13: 0.063481718 | N13: Inbound Handling charges for Dec 2024
A14: 1800001382 | B14: DR | C14: 45722 | D14: 246779411251 | E14: USD | F14: 126.9 | G14: INR | H14: 11001.12 | I14: 0 | J14: 1599 | K14: 1599 | L14: 9402.12 | M14: 0.85465116 | N14: Inbound Handling charges for Dec 2024
A15: 1800001450 | B15: DR | C15: 45729 | D15: 246779411314 | E15: USD | F15: 105 | G15: INR | H15: 9102.58 | I15: 0 | J15: 8522 | K15: 8522 | L15: 580.58 | M15: 0.063781917 | N15: Scanning Charges for the month of October, 2024
... A78: 1800000557 | B78: DR | C78: 45719 | D78: 246779410507 | E78: USD | F78: 2.35 | G78: INR | H78: 203.72 | I78: 0 | J78: 402 | K78: 402 | L78: -198.28 | M78: -0.97329668 | N78: Outbound Handling for Aug 2024

Sheet Invoice & CN not in Customers
H1: =SUBTOTAL(9,H3:H42) -> 2304711.4
A2: Document Number | B2: Document Type | C2: Document Date | D2: Reference | E2: Document Currency Key | F2: Document Currency Value | G2: Company Code Currency Key | H2: Company Code Currency Value | I2: Text
A3: 1800016345 | B3: DR | C3: 46028 | D3: 256779440235 | E3: USD | F3: 7267.85 | G3: INR | H3: 659507.53 | I3: Unit Storage - 1-31 DEC 2025
A4: 1800015671 | B4: DR | C4: 46024 | D4: 256779440004 | E4: USD | F4: 7039.11 | G4: INR | H4: 638750.94 | I4: Unit Storage - 1-30 Nov 2025
A5: 1800011863 | B5: DR | C5: 45877 | D5: 256779416514 | E5: USD | F5: 1804.03 | G5: INR | H5: 155200.92 | I5: PORT SSR Chgs July 25
A6: 1800013509 | B6: DR | C6: 45935 | D6: 256779418399 | E6: USD | F6: 1432.98 | G6: INR | H6: 126375.61 | I6: PORT SSR Chgs Sep 25
A7: 1800014013 | B7: DR | C7: 45950 | D7: 256779418620 | E7: USD | F7: 830.96 | G7: INR | H7: 73283 | I7: CY Ground rent Chgs - 01 - 15 Oct 25
A8: 1800012586 | B8: DR | C8: 45904 | D8: 256779417244 | E8: USD | F8: 685.41 | G8: INR | H8: 59983.2 | I8: PORT SSR Chgs Aug 25
A9: 1800009171 | B9: DR | C9: 45810 | D9: 256779413935 | E9: USD | F9: 590.74 | G9: INR | H9: 50502.82 | I9: Port SSR Charges - Shifting for Aug to D
A10: 1800013758 | B10: DR | C10: 45937 | D10: 256779418179 | E10: USD | F10: 528.99 | G10: INR | H10: 46652.04 | I10: VAS-16-30 Sept 25
A11: 1800016282 | B11: DR | C11: 46028 | D11: 256779440162 | E11: USD | F11: 505.46 | G11: INR | H11: 45867.03 | I11: PORT SSR Chgs Dec 25
A12: 1800016693 | B12: DR | C12: 46034 | D12: 256779440282 | E12: USD | F12: 498.5 | G12: INR | H12: 45235.46 | I12: VAS-Dec 25 - 16-31
A13: 1800016623 | B13: DR | C13: 46028 | D13: 256779440332 | E13: USD | F13: 456.75 | G13: INR | H13: 41446.93 | I13: Fixed Storage Charges for January 2026
A14: 1800009411 | B14: DR | C14: 45812 | D14: 256779414175 | E14: USD | F14: 472.4 | G14: INR | H14: 40385.84 | I14: PORT SSR Chgs - 16 - 31 May 25
... A42: 1600001816 | B42: DG | C42: 45862 | D42: 256779421436 | E42: USD | F42: -140 | G42: INR | H42: -12037.72 | I42: Credit Note raised against 256779413861

Sheet Foreign Exchnage Gain loss
A1: Document Number | B1: Document Type | C1: Document Date | D1: Reference | E1: Document Currency Key | F1: Document Currency Value | G1: Company Code Currency Key | H1: Company Code Currency Value | I1: Debit | J1: Credit | K1: Net Amount | L1: TDS | M1: Rate | N1: Text | O1: Clearing Document | P1: Invoice Reversed in books
A2: 1400001901 | B2: DY | C2: 45976 | D2: KNOCK OFF ENTRY | E2: USD | F2: 3813.11 | G2: INR | H2: 331442.46 | I2: #N/A | K2: #N/A | L2: #N/A | M2: #N/A | O2: 1400001901 | P2: Yes
A3: 1400000288 | B3: DY | C3: 45854 | E3: USD | F3: 1926.06 | G3: INR | H3: 166972.57 | I3: #N/A | K3: #N/A | L3: #N/A | M3: #N/A | O3: 1400000288 | P3: Yes
A4: 1400000285 | B4: DY | C4: 45854 | E4: USD | F4: 1793.99 | G4: INR | H4: 154827.9 | I4: #N/A | K4: #N/A | L4: #N/A | M4: #N/A | O4: 1400000285 | P4: Yes
A5: 1400001902 | B5: DY | C5: 45976 | D5: KNOCK OFF ENTRY | E5: USD | F5: 1117.66 | G5: INR | H5: 96798.99 | I5: #N/A | K5: #N/A | L5: #N/A | M5: #N/A | O5: 1400001902 | P5: Yes
A6: 1400001112 | B6: DY | C6: 45902 | E6: INR | F6: 79944.34 | G6: INR | H6: 78561.62 | I6: #N/A | K6: #N/A | L6: #N/A | M6: #N/A | O6: 1400001112 | P6: Yes
A7: 1400000286 | B7: DY | C7: 45854 | E7: USD | F7: 705 | G7: INR | H7: 60844.08 | I7: #N/A | K7: #N/A | L7: #N/A | M7: #N/A | O7: 1400000286 | P7: Yes
A8: 1400000289 | B8: DY | C8: 45854 | E8: USD | F8: 531.9 | G8: INR | H8: 46111.08 | I8: #N/A | K8: #N/A | L8: #N/A | M8: #N/A | O8: 1400000289 | P8: Yes
A9: 1400000290 | B9: DY | C9: 45854 | D9: KNOCK OFF ENTRY | E9: USD | F9: 525 | G9: INR | H9: 45512.91 | I9: #N/A | K9: #N/A | L9: #N/A | M9: #N/A | O9: 1400000290 | P9: Yes
A10: 1400000246 | B10: DY | C10: 45842 | D10: KNOCK OFF ENTRY | E10: USD | F10: 456.75 | G10: INR | H10: 39701.54 | I10: #N/A | K10: #N/A | L10: #N/A | M10: #N/A | O10: 1400000246 | P10: Yes
A11: 1400000247 | B11: DY | C11: 45842 | D11: KNOCK OFF ENTRY | E11: USD | F11: 456.75 | G11: INR | H11: 39701.54 | I11: #N/A | K11: #N/A | L11: #N/A | M11: #N/A | O11: 1400000247 | P11: Yes
A12: 1400000287 | B12: DY | C12: 45854 | E12: USD | F12: 216.2 | G12: INR | H12: 18742.65 | I12: #N/A | K12: #N/A | L12: #N/A | M12: #N/A | O12: 1400000287 | P12: Yes
A13: 1400000245 | B13: DY | C13: 45842 | D13: KNOCK OFF ENTRY | E13: USD | F13: 0 | G13: INR | H13: 0 | I13: #N/A | K13: #N/A | L13: #N/A | M13: #N/A | O13: 1400000245 | P13: Yes
A14: 1400000248 | B14: DY | C14: 45842 | D14: KNOCK OFF ENTRY | E14: USD | F14: 0 | G14: INR | H14: 0 | I14: #N/A | K14: #N/A | L14: #N/A | M14: #N/A | O14: 1400000248 | P14: Yes
A15: 1400001902 | B15: DY | C15: 45976 | D15: KNOCK OFF ENTRY | E15: USD | F15: -55.46 | G15: INR | H15: -4880.67 | I15: #N/A | K15: #N/A | L15: #N/A | M15: #N/A
A16: 1400001902 | B16: DY | C16: 45976 | D16: KNOCK OFF ENTRY | E16: USD | F16: -137.9 | G16: INR | H16: -12135.67 | I16: #N/A | K16: #N/A | L16: #N/A | M16: #N/A
A17: 1400001902 | B17: DY | C17: 45976 | D17: KNOCK OFF ENTRY | E17: USD | F17: -143.81 | G17: INR | H17: -12655.77 | I17: #N/A | K17: #N/A | L17: #N/A | M17: #N/A
A18: 1400001902 | B18: DY | C18: 45976 | D18: KNOCK OFF ENTRY | E18: USD | F18: -177.66 | G18: INR | H18: -15634.68 | I18: #N/A | K18: #N/A | L18: #N/A | M18: #N/A
A19: 1400001902 | B19: DY | C19: 45976 | D19: KNOCK OFF ENTRY | E19: USD | F19: -182.83 | G19: INR | H19: -16089.66 | I19: #N/A | K19: #N/A | L19: #N/A | M19: #N/A
A20: 1400000287 | B20: DY | C20: 45854 | E20: USD | F20: -216.2 | G20: INR | H20: -18742.65 | I20: #N/A | K20: #N/A | L20: #N/A | M20: #N/A | O20: 1400000287 | P20: Yes
A21: 1400001902 | B21: DY | C21: 45976 | D21: KNOCK OFF ENTRY | E21: USD | F21: -420 | G21: INR | H21: -36961.42 | I21: #N/A | K21: #N/A | L21: #N/A | M21: #N/A
A22: 1400000246 | B22: DY | C22: 45842 | D22: KNOCK OFF ENTRY | E22: USD | F22: -456.75 | G22: INR | H22: -39701.54 | I22: #N/A | K22: #N/A | L22: #N/A | M22: #N/A | O22: 1400000246 | P22: Yes
A23: 1400000247 | B23: DY | C23: 45842 | D23: KNOCK OFF ENTRY | E23: USD | F23: -456.75 | G23: INR | H23: -39701.54 | I23: #N/A | K23: #N/A | L23: #N/A | M23: #N/A | O23: 1400000247 | P23: Yes
A24: 1400000290 | B24: DY | C24: 45854 | D24: KNOCK OFF ENTRY | E24: USD | F24: -525 | G24: INR | H24: -45512.91 | I24: #N/A | K24: #N/A | L24: #N/A | M24: #N/A | O24: 1400000290 | P24: Yes
A25: 1400000289 | B25: DY | C25: 45854 | E25: USD | F25: -531.9 | G25: INR | H25: -46111.08 | I25: #N/A | K25: #N/A | L25: #N/A | M25: #N/A | O25: 1400000289 | P25: Yes
A26: 1400000286 | B26: DY | C26: 45854 | E26: USD | F26: -705 | G26: INR | H26: -60844.08 | I26: #N/A | K26: #N/A | L26: #N/A | M26: #N/A | O26: 1400000286 | P26: Yes
A27: 1400001112 | B27: DY | C27: 45902 | E27: INR | F27: -79944.34 | G27: INR | H27: -78095.82 | I27: #N/A | K27: #N/A | L27: #N/A | M27: #N/A | O27: 1400001112 | P27: Yes
A28: 1400000285 | B28: DY | C28: 45854 | E28: USD | F28: -1793.99 | G28: INR | H28: -154827.9 | I28: #N/A | K28: #N/A | L28: #N/A | M28: #N/A | O28: 1400000285 | P28: Yes
A29: 1400000288 | B29: DY | C29: 45854 | E29: USD | F29: -1926.06 | G29: INR | H29: -166972.57 | I29: #N/A | K29: #N/A | L29: #N/A | M29: #N/A | O29: 1400000288 | P29: Yes
A30: 1400001901 | B30: DY | C30: 45976 | D30: KNOCK OFF ENTRY | E30: USD | F30: -3813.11 | G30: INR | H30: -331442.46 | I30: #N/A | K30: #N/A | L30: #N/A | M30: #N/A | O30: 1400001901 | P30: Yes
H31: =SUM(H2:H30) -> -1093.08

Sheet Customer Data Vlookup
B1: =SUBTOTAL(9,B2:B360) -> 8842595.5 | C1: =SUBTOTAL(9,C2:C360) -> 10967816 | D1: =C1-B1 -> 2125220.5
A2: Posting Date | B2: Debit (INR) | C2: Credit (INR) | D2: Voucher Type | E2: Voucher Subtype | F2: Voucher No | G2: Against Account | H2: Against Voucher | I2: Supplier Invoice No | L2: Row Labels | M2: Sum of Debit (INR) | N2: Sum of Credit (INR)
A3: 2025-02-20 | B3: 0 | C3: 35554.52 | D3: Purchase Invoice | E3: Purchase Invoice | F3: PU/25/SLS/OT/1560 | G3: Fixed Storage Charges - ODC (Covered) - SLSIPL | H3: PU/25/SLS/OT/1560 | I3: 246779410049 | L3: 246779410049 | M3: 0 | N3: 35554.52
A4: 2025-02-20 | B4: 0 | C4: 35554.52 | D4: Purchase Invoice | E4: Purchase Invoice | F4: PU/25/SLS/OT/1561 | G4: Fixed Storage Charges - ODC (Covered) - SLSIPL | H4: PU/25/SLS/OT/1561 | I4: 246779410303 | L4: 246779410072 | M4: 0 | N4: 35477
A5: 2025-02-20 | B5: 0 | C5: 35554.52 | D5: Purchase Invoice | E5: Purchase Invoice | F5: PU/25/SLS/OT/1562 | G5: Fixed Storage Charges - ODC (Covered) - SLSIPL | H5: PU/25/SLS/OT/1562 | I5: 246779410117 | L5: 246779410117 | M5: 0 | N5: 35554.52
A6: 2025-02-20 | B6: 0 | C6: 35554.52 | D6: Purchase Invoice | E6: Purchase Invoice | F6: PU/25/SLS/OT/1563 | G6: Fixed Storage Charges - ODC (Covered) - SLSIPL | H6: PU/25/SLS/OT/1563 | I6: 246779410160 | L6: 246779410160 | M6: 0 | N6: 35554.52
A7: 2025-02-20 | B7: 0 | C7: 35554.52 | D7: Purchase Invoice | E7: Purchase Invoice | F7: PU/25/SLS/OT/1564 | G7: Fixed Storage Charges - ODC (Covered) - SLSIPL | H7: PU/25/SLS/OT/1564 | I7: 246779410203 | L7: 246779410203 | M7: 0 | N7: 35554.52
A8: 2025-02-20 | B8: 0 | C8: 35554.52 | D8: Purchase Invoice | E8: Purchase Invoice | F8: PU/25/SLS/OT/1565 | G8: Fixed Storage Charges - ODC (Covered) - SLSIPL | H8: PU/25/SLS/OT/1565 | I8: 246779410246 | L8: 246779410246 | M8: 0 | N8: 35554.52
A9: 2025-03-03 | B9: 0 | C9: 804 | D9: Purchase Invoice | E9: Purchase Invoice | F9: PU/25/SLS/OT/1672 | G9: Handling Charges - Outbound (Exp) - SLSIPL | H9: PU/25/SLS/OT/1672 | I9: 246779410613 | L9: 246779410303 | M9: 0 | N9: 35554.52
A10: 2025-03-03 | B10: 0 | C10: 1004 | D10: Purchase Invoice | E10: Purchase Invoice | F10: PU/25/SLS/OT/1673 | G10: Handling Charges - Outbound (Exp) - SLSIPL | H10: PU/25/SLS/OT/1673 | I10: 246779410612 | L10: 246779410327 | M10: 0 | N10: 16480.711
A11: 2025-03-03 | B11: 0 | C11: 402 | D11: Purchase Invoice | E11: Purchase Invoice | F11: PU/25/SLS/OT/1674 | G11: Handling Charges - Outbound (Exp) - SLSIPL | H11: PU/25/SLS/OT/1674 | I11: 246779410611 | L11: 246779410333 | M11: 0 | N11: 29975.442
A12: 2025-03-03 | B12: 0 | C12: 201 | D12: Purchase Invoice | E12: Purchase Invoice | F12: PU/25/SLS/OT/1675 | G12: Handling Charges - Outbound (Exp) - SLSIPL | H12: PU/25/SLS/OT/1675 | I12: 246779410610 | L12: 246779410338 | M12: 0 | N12: 13859.78
A13: 2025-03-03 | B13: 0 | C13: 804 | D13: Purchase Invoice | E13: Purchase Invoice | F13: PU/25/SLS/OT/1676 | G13: Handling Charges - Outbound (Exp) - SLSIPL | H13: PU/25/SLS/OT/1676 | I13: 246779410608 | L13: 246779410339 | M13: 0 | N13: 44681.825
A14: 2025-03-03 | B14: 0 | C14: 402 | D14: Purchase Invoice | E14: Purchase Invoice | F14: PU/25/SLS/OT/1677 | G14: Handling Charges - Outbound (Exp) - SLSIPL | H14: PU/25/SLS/OT/1677 | I14: 246779410607 | L14: 246779410340 | M14: 0 | N14: 144772.57
... A210: 2025-05-28 | B210: 0 | C210: 333696 | D210: Purchase Invoice | E210: Purchase Invoice | F210: PU/26/SLS/OT/0278 | G210: Storage Charges - Cargo - SLSIPL | H210: PU/26/SLS/OT/0278 | I210: 256779413899 | L210: 256779412468 | M210: 0 | N210: 14119
A211: 2025-05-30 | B211: 177773 | C211: 0 | D211: Payment Entry | E211: Pay | F211: BP/26/SLS/0192 | G211: 1395250393003 - Punjab National Bank - INR - SLSIPL | L211: 256779412613 | M211: 0 | N211: 3922
A212: 2025-06-04 | B212: 0 | C212: 9844 | D212: Purchase Invoice | E212: Purchase Invoice | F212: PU/26/SLS/OT/0358 | G212: Handling Charges - Outbound (Exp) - SLSIPL | H212: PU/26/SLS/OT/0358 | I212: 256779414165 | L212: 256779412655 | M212: 0 | N212: 2085
A213: 2025-06-04 | B213: 0 | C213: 8407 | D213: Purchase Invoice | E213: Purchase Invoice | F213: PU/26/SLS/OT/0360 | G213: Handling Charges - Outbound (Exp) - SLSIPL | H213: PU/26/SLS/OT/0360 | I213: 256779414216 | L213: 256779412675 | M213: 0 | N213: 1447
A214: 2025-06-04 | B214: 500946.52 | C214: 0 | D214: Payment Entry | E214: Pay | F214: BP/25/SLS/1225-1 | G214: 1395250393003 - Punjab National Bank - INR - SLSIPL | H214: PU/25/SLS/OT/1562, PU/25/SLS/OT/1720, PU/25/SLS/OT/1731, PU/25/SLS/OT/1721, PU/25/SLS/OT/1673 | L214: 256779412683 | M214: 0 | N214: 43195
A215: 2025-06-04 | B215: 0 | C215: 17313 | D215: Purchase Invoice | E215: Purchase Invoice | F215: PU/26/SLS/OT/0585 | G215: Scanning Charges - Inbound - SLSIPL | H215: PU/26/SLS/OT/0585 | I215: 256779414288 | L215: 256779412692 | M215: 0 | N215: 6084
A216: 2025-06-04 | B216: 0 | C216: 41769 | D216: Purchase Invoice | E216: Purchase Invoice | F216: PU/26/SLS/OT/0797 | G216: Handling Charges - Inbound (Exp) - SLSIPL,LCL Movment - Gate in Charge - SLSIPL,Transportation Charges Paid - SLSIPL,Eempty Container Return Charges Paid - SLSIPL | H216: PU/26/SLS/OT/0797 | I216: 256779414158 | L216: 256779412777 | M216: 0 | N216: 7981
A217: 2025-06-07 | B217: 0 | C217: 352792 | D217: Purchase Invoice | E217: Purchase Invoice | F217: PU/26/SLS/OT/0285 | G217: Storage Charges - Cargo - SLSIPL | H217: PU/26/SLS/OT/0285 | I217: 256779414242 | L217: 256779412926 | M217: 0 | N217: 1878
A218: 2025-06-10 | B218: 0 | C218: 35431 | D218: Purchase Invoice | E218: Purchase Invoice | F218: PU/26/SLS/OT/0357-1 | G218: Fixed Storage Charges - ODC (Covered) - SLSIPL | H218: PU/26/SLS/OT/0357-1 | I218: 256779414386 | L218: 256779412941 | M218: 0 | N218: 27408
A219: 2025-06-13 | B219: 700000 | C219: 0 | D219: Payment Entry | E219: Pay | F219: BP/26/SLS/0229 | G219: 1395250393003 - Punjab National Bank - INR - SLSIPL | L219: 256779412950 | M219: 0 | N219: 13211
A220: 2025-06-21 | B220: 700000 | C220: 0 | D220: Payment Entry | E220: Pay | F220: BP/26/SLS/0259 | G220: 1395250393003 - Punjab National Bank - INR - SLSIPL | L220: 256779413127 | M220: 0 | N220: 35097
A221: 2025-06-30 | B221: 700000 | C221: 0 | D221: Payment Entry | E221: Pay | F221: BP/26/SLS/0291 | G221: 1395250393003 - Punjab National Bank - INR - SLSIPL | L221: 256779413163 | M221: 0 | N221: 15927
A222: 2025-07-05 | B222: 700000 | C222: 0 | D222: Payment Entry | E222: Pay | F222: BP/26/SLS/0300 | G222: 1395250393003 - Punjab National Bank - INR - SLSIPL | L222: 256779413172 | M222: 0 | N222: 11810
A223: 2025-07-11 | B223: 700000 | C223: 0 | D223: Payment Entry | E223: Pay | F223: BP/26/SLS/0311 | G223: 1395250393003 - Punjab National Bank - INR - SLSIPL | L223: 256779413184 | M223: 0 | N223: 11723.018
A224: 2025-05-16 | B224: 0 | C224: 11797 | D224: Purchase Invoice | E224: Purchase Invoice | F224: PU/26/SLS/OT/0283 | G224: Container Scanning Paid - SLSIPL | H224: PU/26/SLS/OT/0283 | I224: 256779413283 | L224: 256779413243 | M224: 0 | N224: 3623
A225: 2025-04-23 | B225: 0 | C225: 6084 | D225: Purchase Invoice | E225: Purchase Invoice | F225: PU/26/SLS/OT/0586-1 | G225: Scanning Charges - Inbound - SLSIPL | H225: PU/26/SLS/OT/0586-1 | I225: 256779412692 | L225: 256779413283 | M225: 0 | N225: 11797
A226: 2025-04-16 | B226: 0 | C226: 12169 | D226: Purchase Invoice | E226: Purchase Invoice | F226: PU/26/SLS/OT/0587-1 | G226: Scanning Charges - Inbound - SLSIPL | H226: PU/26/SLS/OT/0587-1 | I226: 256779411917 | L226: 256779413357 | M226: 0 | N226: 1264
A227: 2025-04-03 | B227: 0 | C227: 114223 | D227: Purchase Invoice | E227: Purchase Invoice | F227: PU/26/SLS/OT/0611-1 | G227: Storage Charges - Cargo - SLSIPL | H227: PU/26/SLS/OT/0611-1 | I227: 256779410220 | L227: 256779413404 | M227: 0 | N227: 7129
A228: 2025-04-03 | B228: 0 | C228: 140649 | D228: Purchase Invoice | E228: Purchase Invoice | F228: PU/26/SLS/OT/0612 | G228: Storage Charges - Cargo - SLSIPL | H228: PU/26/SLS/OT/0612 | I228: 256779410010 | L228: 256779413405 | M228: 0 | N228: 3960
A229: 2025-04-03 | B229: 0 | C229: 55272 | D229: Purchase Invoice | E229: Purchase Invoice | F229: PU/26/SLS/OT/0613 | G229: Storage Charges - Cargo - SLSIPL | H229: PU/26/SLS/OT/0613 | I229: 256779410004 | L229: 256779413427 | M229: 0 | N229: 990
A230: 2025-04-01 | B230: 0 | C230: 45188 | D230: Purchase Invoice | E230: Purchase Invoice | F230: PU/26/SLS/OT/0588 | G230: Transportation Charges Paid - SLSIPL | H230: PU/26/SLS/OT/0588 | I230: 246779413845 | L230: 256779413428 | M230: 0 | N230: 990
A231: 2025-03-31 | B231: 0 | C231: 31723 | D231: Purchase Invoice | E231: Purchase Invoice | F231: PU/25/SLS/OT/1822 | G231: Container Scanning Paid - SLSIPL | H231: PU/25/SLS/OT/1822 | I231: 246779413827 | L231: 256779413429 | M231: 0 | N231: 601
A232: 2025-07-19 | B232: 700000 | C232: 0 | D232: Payment Entry | E232: Pay | F232: BP/26/SLS/0368 | G232: 1395250393003 - Punjab National Bank - INR - SLSIPL | L232: 256779413430 | M232: 0 | N232: 1201
A233: 2025-07-24 | B233: 0 | C233: 9368 | D233: Purchase Invoice | E233: Purchase Invoice | F233: PU/26/SLS/OT/0607 | G233: Handling Charges - Inbound (Exp) - SLSIPL | H233: PU/26/SLS/OT/0607 | I233: 256779415945 | L233: 256779413486 | M233: 0 | N233: 1054
A234: 2025-07-25 | B234: 350672 | C234: 0 | D234: Payment Entry | E234: Pay | F234: BP/26/SLS/0394 | G234: 1395250393003 - Punjab National Bank - INR - SLSIPL | L234: 256779413837 | M234: 0 | N234: 12177
A235: 2025-07-25 | B235: 0 | C235: 32007 | D235: Purchase Invoice | E235: Purchase Invoice | F235: PU/26/SLS/OT/0608 | G235: Storage Charges - Cargo - SLSIPL | H235: PU/26/SLS/OT/0608 | I235: 256779415967 | L235: 256779413899 | M235: 0 | N235: 333696
A236: 2025-07-25 | B236: 0 | C236: 9348 | D236: Purchase Invoice | E236: Purchase Invoice | F236: PU/26/SLS/OT/0609 | G236: Storage Charges - Cargo - SLSIPL | H236: PU/26/SLS/OT/0609 | I236: 256779415970 | L236: 256779414158 | M236: 0 | N236: 41769
A237: 2025-07-25 | B237: 0 | C237: 196 | D237: Purchase Invoice | E237: Purchase Invoice | F237: PU/26/SLS/OT/0610 | G237: VOS Activity Charges Paid - SLSIPL | H237: PU/26/SLS/OT/0610 | I237: 256779415995 | L237: 256779414165 | M237: 0 | N237: 9844
A238: 2025-03-31 | B238: 0 | C238: 18610 | D238: Purchase Invoice | E238: Purchase Invoice | F238: PU/25/SLS/OT/1821 | G238: Container Scanning Paid - SLSIPL | H238: PU/25/SLS/OT/1821 | I238: 246779413816 | L238: 256779414216 | M238: 0 | N238: 8407
A239: 2025-08-08 | B239: 0 | C239: 9124 | D239: Purchase Invoice | E239: Purchase Invoice | F239: PU/26/SLS/OT/0798 | G239: Handling Charges - Outbound (Exp) - SLSIPL | H239: PU/26/SLS/OT/0798 | I239: 256779416223 | L239: 256779414242 | M239: 0 | N239: 352792
A240: 2025-08-08 | B240: 0 | C240: 4755 | D240: Purchase Invoice | E240: Purchase Invoice | F240: PU/26/SLS/OT/0800 | G240: Handling Charges - Outbound (Exp) - SLSIPL | H240: PU/26/SLS/OT/0800 | I240: 256779416256 | L240: 256779414288 | M240: 0 | N240: 17313
A241: 2025-08-08 | B241: 0 | C241: 462828 | D241: Purchase Invoice | E241: Purchase Invoice | F241: PU/26/SLS/OT/0796 | G241: Storage Charges - SLSIPL | H241: PU/26/SLS/OT/0796 | I241: 256779416088 | L241: 256779414340 | M241: 0 | N241: 45061.335
A242: 2025-08-20 | B242: 0 | C242: 4790 | D242: Purchase Invoice | E242: Purchase Invoice | F242: PU/26/SLS/OT/0792 | G242: Handling Charges - Outbound (Exp) - SLSIPL,MHE Charges Paid - SLSIPL | H242: PU/26/SLS/OT/0792 | I242: 256779416615 | L242: 256779414386 | M242: 0 | N242: 35431
A243: 2025-08-20 | B243: 0 | C243: 6981 | D243: Purchase Invoice | E243: Purchase Invoice | F243: PU/26/SLS/OT/0793 | G243: VOS Activity Charges Paid - SLSIPL | H243: PU/26/SLS/OT/0793 | I243: 256779416809 | L243: 256779414743 | M243: 0 | N243: 6064.023
A244: 2025-08-20 | B244: 0 | C244: 971 | D244: Purchase Invoice | E244: Purchase Invoice | F244: PU/26/SLS/OT/0801 | G244: Loose Loading Handling - SLSIPL | H244: PU/26/SLS/OT/0801 | I244: 256779416878 | L244: 256779414748 | M244: 0 | N244: 1800.351
A245: 2025-08-20 | B245: 0 | C245: 11922 | D245: Purchase Invoice | E245: Purchase Invoice | F245: PU/26/SLS/OT/0795 | G245: Handling Charges - Inbound (Exp) - SLSIPL,Gate in Charges - Inbound - SLSIPL | H245: PU/26/SLS/OT/0795 | I245: 256779416844 | L245: 256779414758 | M245: 0 | N245: 14610.374
A246: 2025-08-20 | B246: 0 | C246: 1463 | D246: Purchase Invoice | E246: Purchase Invoice | F246: PU/26/SLS/OT/0794 | G246: LCL Movment - Gate in Charge - SLSIPL,Handling Charges - Inbound (Exp) - SLSIPL | H246: PU/26/SLS/OT/0794 | I246: 256779416603 | L246: 256779414768 | M246: 0 | N246: 1492.1116
... A252: 2025-03-31 | B252: 0 | C252: 20874 | D252: Purchase Invoice | E252: Purchase Invoice | F252: PU/25/SLS/OT/1820 | G252: Container Scanning Paid - SLSIPL | H252: PU/25/SLS/OT/1820 | I252: 246779411326 | L252: 256779414975 | M252: 0 | N252: 4562.3355
A253: 2025-10-09 | B253: 500000 | C253: 0 | D253: Payment Entry | E253: Pay | F253: BP/26/SLS/0710 | G253: 1395250393003 - Punjab National Bank - INR - SLSIPL | H253: PU/26/SLS/OT/0797, PU/26/SLS/OT/0357-1, PU/26/SLS/OT/0610, PU/26/SLS/OT/0796, PU/26/SLS/OT/0794 | L253: 256779415048 | M253: 0 | N253: 552.9843
A254: 2025-10-10 | B254: 108564 | C254: 0 | D254: Payment Entry | E254: Pay | F254: BP/26/SLS/0711 | G254: 1395250393003 - Punjab National Bank - INR - SLSIPL | H254: PU/26/SLS/OT/0797, PU/26/SLS/OT/0607, PU/26/SLS/OT/0608, PU/26/SLS/OT/0609, PU/26/SLS/OT/0798, PU/26/SLS/OT/0800, PU/26/SLS/OT/0792, PU/26/SLS/OT/0793, PU/26/SLS/OT/0795, PU/26/SLS/OT/0801 | L254: 256779415198 | M254: 0 | N254: 257812.81
A255: 2025-10-18 | B255: 500000 | C255: 0 | D255: Payment Entry | E255: Pay | F255: BP/26/SLS/0758 | G255: 1395250393003 - Punjab National Bank - INR - SLSIPL | L255: 256779415263 | M255: 0 | N255: 201.2416
A256: 2025-10-29 | B256: 300000 | C256: 0 | D256: Payment Entry | E256: Pay | F256: BP/26/SLS/0765 | G256: 1395250393003 - Punjab National Bank - INR - SLSIPL | L256: 256779415444 | M256: 0 | N256: 8342.065
A257: 2025-11-01 | B257: 500000 | C257: 0 | D257: Payment Entry | E257: Pay | F257: BP/26/SLS/0801 | G257: 1395250393003 - Punjab National Bank - INR - SLSIPL | L257: 256779415456 | M257: 0 | N257: 13522.745
A258: 2025-12-12 | B258: 0 | C258: 16480.711 | D258: Purchase Invoice | E258: Purchase Invoice | F258: PU/26/SLS/OT/1356 | G258: Storage Charges - Cargo - SLSIPL | H258: PU/26/SLS/OT/1356 | I258: 246779410327 | L258: 256779415771 | M258: 0 | N258: 2559.3799
A259: 2025-12-12 | B259: 0 | C259: 29975.442 | D259: Purchase Invoice | E259: Purchase Invoice | F259: PU/26/SLS/OT/1357 | G259: Storage Charges - Cargo - SLSIPL | H259: PU/26/SLS/OT/1357 | I259: 246779410333 | L259: 256779415801 | M259: 0 | N259: 148540.36
A260: 2025-12-12 | B260: 0 | C260: 144772.57 | D260: Purchase Invoice | E260: Purchase Invoice | F260: PU/26/SLS/OT/1358 | G260: Storage Charges - Cargo - SLSIPL | H260: PU/26/SLS/OT/1358 | I260: 246779410340 | L260: 256779415939 | M260: 0 | N260: 11782.092
A261: 2025-12-12 | B261: 0 | C261: 102103.26 | D261: Purchase Invoice | E261: Purchase Invoice | F261: PU/26/SLS/OT/1359 | G261: Storage Charges - Cargo - SLSIPL | H261: PU/26/SLS/OT/1359 | I261: 246779410352 | L261: 256779415945 | M261: 0 | N261: 9368
A262: 2025-12-12 | B262: 0 | C262: 13859.78 | D262: Purchase Invoice | E262: Purchase Invoice | F262: PU/26/SLS/OT/1360 | G262: Storage Charges - Cargo - SLSIPL | H262: PU/26/SLS/OT/1360 | I262: 246779410338 | L262: 256779415967 | M262: 0 | N262: 32007
A263: 2025-12-12 | B263: 0 | C263: 44681.825 | D263: Purchase Invoice | E263: Purchase Invoice | F263: PU/26/SLS/OT/1361 | G263: Storage Charges - Cargo - SLSIPL | H263: PU/26/SLS/OT/1361 | I263: 246779410339 | L263: 256779415970 | M263: 0 | N263: 9348
A264: 2025-12-12 | B264: 500000 | C264: 0 | D264: Payment Entry | E264: Pay | F264: BP/26/SLS/0958 | G264: 1395250393003 - Punjab National Bank - INR - SLSIPL | L264: 256779415995 | M264: 0 | N264: 196
A265: 2025-12-12 | B265: 0 | C265: 2053.9 | D265: Purchase Invoice | E265: Purchase Invoice | F265: PU/26/SLS/OT/1362-1 | G265: Handling Charges - Inbound (Exp) - SLSIPL | H265: PU/26/SLS/OT/1362-1 | I265: 256779411807 | L265: 256779416054 | M265: 0 | N265: 35336.872
A266: 2025-12-15 | B266: 0 | C266: 6064.023 | D266: Purchase Invoice | E266: Purchase Invoice | F266: PU/26/SLS/OT/1365 | G266: VOS Activity Charges Paid - SLSIPL | H266: PU/26/SLS/OT/1365 | I266: 256779414743 | L266: 256779416088 | M266: 0 | N266: 462828
A267: 2025-12-15 | B267: 0 | C267: 1800.351 | D267: Purchase Invoice | E267: Purchase Invoice | F267: PU/26/SLS/OT/1366-1 | G267: Weightment Charges Paid - SLSIPL | H267: PU/26/SLS/OT/1366-1 | I267: 256779414748 | L267: 256779416178 | M267: 1351 | N267: 67557
A268: 2025-12-15 | B268: 0 | C268: 14610.374 | D268: Purchase Invoice | E268: Purchase Invoice | F268: PU/26/SLS/OT/1367 | G268: Handling Charges - Outbound (Exp) - SLSIPL | H268: PU/26/SLS/OT/1367 | I268: 256779414758 | L268: 256779416223 | M268: 0 | N268: 9124
A269: 2025-12-15 | B269: 0 | C269: 45061.335 | D269: Purchase Invoice | E269: Purchase Invoice | F269: PU/26/SLS/OT/1368 | G269: Storage Charges - Cargo - SLSIPL | H269: PU/26/SLS/OT/1368 | I269: 256779414340 | L269: 256779416256 | M269: 0 | N269: 4755
A270: 2025-12-15 | B270: 0 | C270: 11782.092 | D270: Purchase Invoice | E270: Purchase Invoice | F270: PU/26/SLS/OT/1369-1 | G270: Container Scanning Paid - SLSIPL | H270: PU/26/SLS/OT/1369-1 | I270: 256779415939 | L270: 256779416444 | M270: 0 | N270: 9260.2821
A271: 2025-12-15 | B271: 0 | C271: 2559.3799 | D271: Purchase Invoice | E271: Purchase Invoice | F271: PU/26/SLS/OT/1370 | G271: VOS Activity Charges Paid - SLSIPL | H271: PU/26/SLS/OT/1370 | I271: 256779415771 | L271: 256779416538 | M271: 0 | N271: 27395.431
A272: 2025-12-15 | B272: 0 | C272: 148540.36 | D272: Purchase Invoice | E272: Purchase Invoice | F272: PU/26/SLS/OT/1371 | G272: Handling Charges - Inbound (Exp) - SLSIPL | H272: PU/26/SLS/OT/1371 | I272: 256779415801 | L272: 256779416544 | M272: 0 | N272: 23117.154
A273: 2025-12-15 | B273: 0 | C273: 13522.745 | D273: Purchase Invoice | E273: Purchase Invoice | F273: PU/26/SLS/OT/1376 | G273: Handling Charges - Outbound (Exp) - SLSIPL,MHE Charges Paid - SLSIPL | H273: PU/26/SLS/OT/1376 | I273: 256779415456 | L273: 256779416546 | M273: 0 | N273: 21929.078
A274: 2025-12-15 | B274: 0 | C274: 8342.065 | D274: Purchase Invoice | E274: Purchase Invoice | F274: PU/26/SLS/OT/1378 | G274: Transportation Charges Paid - SLSIPL,Handling Charges - Inbound (Exp) - SLSIPL | H274: PU/26/SLS/OT/1378 | I274: 256779415444 | L274: 256779416603 | M274: 0 | N274: 1463
A275: 2025-12-16 | B275: 0 | C275: 2629.9005 | D275: Purchase Invoice | E275: Purchase Invoice | F275: PU/26/SLS/OT/1379 | G275: MHE Charges Paid - SLSIPL,Handling Charges - Inbound (Exp) - SLSIPL | H275: PU/26/SLS/OT/1379 | I275: 256779414968 | L275: 256779416615 | M275: 0 | N275: 4790
A276: 2025-12-16 | B276: 0 | C276: 201.2416 | D276: Purchase Invoice | E276: Purchase Invoice | F276: PU/26/SLS/OT/1380 | G276: VOS Activity Charges Paid - SLSIPL | H276: PU/26/SLS/OT/1380 | I276: 256779415263 | L276: 256779416809 | M276: 0 | N276: 6981
... A333: 2025-12-29 | B333: 7320 | C333: 73283.168 | D333: Purchase Invoice | E333: Purchase Invoice | F333: PU/26/SLS/OT/1487 | G333: Storage Charges - Cargo - SLSIPL | H333: PU/26/SLS/OT/1487, PU/26/SLS/OT/1487 | I333: 246779418620 | L333: 256779440122 | M333: 181 | N333: 11185.421
A334: 2025-12-29 | B334: 500000 | C334: 0 | D334: Payment Entry | E334: Pay | F334: BP/26/SLS/1015 | G334: 1395250393003 - Punjab National Bank - INR - SLSIPL | L334: 256779440210 | M334: 181 | N334: 7063.8672
A335: 2025-12-29 | B335: 6 | C335: 306 | D335: Purchase Invoice | E335: Purchase Invoice | F335: PU/26/SLS/OT/1484-1 | G335: Weightment Charges Paid - SLSIPL | H335: PU/26/SLS/OT/1484-1, PU/26/SLS/OT/1484-1 | I335: 256779418492 | L335: 256779440383 | M335: 90 | N335: 4904.3774
A336: 2025-12-30 | B336: 176 | C336: 7046.061 | D336: Purchase Invoice | E336: Purchase Invoice | F336: PU/26/SLS/OT/1488 | G336: Handling Charges - Outbound (Exp) - SLSIPL | H336: PU/26/SLS/OT/1488, PU/26/SLS/OT/1488 | I336: 256779418437 | L336: 256779440392 | M336: 1089 | N336: 11313.937
A337: 2025-12-30 | B337: 88 | C337: 2901.2856 | D337: Purchase Invoice | E337: Purchase Invoice | F337: PU/26/SLS/OT/1489 | G337: Handling Charges - Inbound (Exp) - SLSIPL | H337: PU/26/SLS/OT/1489, PU/26/SLS/OT/1489 | I337: 256779418428 | L337: 256779440394 | M337: 1815 | N337: 18211.378
A338: 2025-12-30 | B338: 0 | C338: 1036.08 | D338: Purchase Invoice | E338: Purchase Invoice | F338: PU/26/SLS/OT/1490 | G338: Handling Charges - Outbound (Exp) - SLSIPL | H338: PU/26/SLS/OT/1490 | I338: 256779418351 | L338: 256779440413 | M338: 181 | N338: 8983.0846
A339: 2025-03-31 | B339: 0 | C339: 33376 | D339: Purchase Invoice | E339: Purchase Invoice | F339: PU/25/SLS/OT/1925 | G339: Container Scanning Paid - SLSIPL | H339: PU/25/SLS/OT/1925 | I339: 246779411300 | L339: 256779440429 | M339: 91 | N339: 6141.7526
A340: 2025-12-30 | B340: 88 | C340: 6173.1631 | D340: Purchase Invoice | E340: Purchase Invoice | F340: PU/26/SLS/OT/1493 | G340: Intra SEZ Trf Expenses - SLSIPL | H340: PU/26/SLS/OT/1493, PU/26/SLS/OT/1493 | I340: 256779418168 | L340: (blank) | M340: 8812706.5 | N340: 0
A341: 2025-12-30 | B341: 6791 | C341: 68060.655 | D341: Purchase Invoice | E341: Purchase Invoice | F341: PU/26/SLS/OT/1494 | G341: Storage Charges - Cargo - SLSIPL | H341: PU/26/SLS/OT/1494, PU/26/SLS/OT/1494 | I341: 256779418094
A342: 2025-12-30 | B342: 1058 | C342: 51397.291 | D342: Purchase Invoice | E342: Purchase Invoice | F342: PU/26/SLS/OT/1495 | G342: Handling Charges - Outbound (Exp) - SLSIPL | H342: PU/26/SLS/OT/1495, PU/26/SLS/OT/1495 | I342: 256779417978
A343: 2025-12-31 | B343: 1351 | C343: 67557 | D343: Purchase Invoice | E343: Purchase Invoice | F343: PU/26/SLS/OT/1394-2 | G343: Handling Charges - Inbound (Exp) - SLSIPL,Transportation Charges Paid - SLSIPL | H343: PU/26/SLS/OT/1394-2, PU/26/SLS/OT/1394-2 | I343: 256779416178
A344: 2025-07-31 | B344: 0 | C344: 44602 | D344: Purchase Invoice | E344: Purchase Invoice | F344: PU/26/SLS/OT/1009-1 | G344: Container Scanning Paid - SLSIPL | H344: PU/26/SLS/OT/1009-1 | I344: 246779411278
A345: 2025-04-01 | B345: 0 | C345: 59624 | D345: Purchase Invoice | E345: Purchase Invoice | F345: PU/26/SLS/OT/0591-1 | G345: Storage Charges - Cargo - SLSIPL | H345: PU/26/SLS/OT/0591-1 | I345: 246779410360
A346: 2025-07-11 | B346: 0 | C346: 151725 | D346: Purchase Invoice | E346: Purchase Invoice | F346: PU/26/SLS/OT/0415-1 | G346: Storage Charges - Cargo - SLSIPL | H346: PU/26/SLS/OT/0415-1 | I346: 246779410348
A347: 2026-01-16 | B347: 4174 | C347: 41446.745 | D347: Purchase Invoice | E347: Purchase Invoice | F347: PU/26/SLS/OT/1553 | G347: Storage Charges - SLSIPL | H347: PU/26/SLS/OT/1553, PU/26/SLS/OT/1553 | I347: 256779440041
A348: 2026-01-16 | B348: 0 | C348: 1066.231 | D348: Purchase Invoice | E348: Purchase Invoice | F348: PU/26/SLS/OT/1554 | G348: Handling Charges - Outbound (Exp) - SLSIPL | H348: PU/26/SLS/OT/1554 | I348: 256779440069
A349: 2026-01-23 | B349: 181 | C349: 8983.085 | D349: Purchase Invoice | E349: Purchase Invoice | F349: PU/26/SLS/OT/1538 | G349: Gate in Charges - Inbound - SLSIPL,Handling Charges - Inbound (Exp) - SLSIPL | H349: PU/26/SLS/OT/1538, PU/26/SLS/OT/1538 | I349: 256779440118
A350: 2026-01-28 | B350: 674751 | C350: 0 | D350: Payment Entry | E350: Pay | F350: BP/26/SLS/1165-1 | G350: 1395250393003 - Punjab National Bank - INR - SLSIPL | H350: PU/26/SLS/OT/1422
A351: 2026-02-04 | B351: 90 | C351: 4904.3774 | D351: Purchase Invoice | E351: Purchase Invoice | F351: PU/26/SLS/OT/1636 | G351: Handling Charges - Outbound (Exp) - SLSIPL,MHE CHARGES - SLSIPL | H351: PU/26/SLS/OT/1636, PU/26/SLS/OT/1636 | I351: 256779440383
A352: 2026-02-04 | B352: 181 | C352: 8983.0846 | D352: Purchase Invoice | E352: Purchase Invoice | F352: PU/26/SLS/OT/1637 | G352: Handling Charges - Outbound (Exp) - SLSIPL,Gate In Charges Paid - SLSIPL | H352: PU/26/SLS/OT/1637, PU/26/SLS/OT/1637 | I352: 256779440413
A353: 2026-02-04 | B353: 91 | C353: 6141.7526 | D353: Purchase Invoice | E353: Purchase Invoice | F353: PU/26/SLS/OT/1638 | G353: Handling Charges - Outbound (Exp) - SLSIPL | H353: PU/26/SLS/OT/1638, PU/26/SLS/OT/1638 | I353: 256779440429
A354: 2026-02-04 | B354: 1815 | C354: 18211.378 | D354: Purchase Invoice | E354: Purchase Invoice | F354: PU/26/SLS/OT/1639 | G354: Storage Charges - Cargo - SLSIPL | H354: PU/26/SLS/OT/1639, PU/26/SLS/OT/1639 | I354: 256779440394
A355: 2026-02-04 | B355: 1089 | C355: 11313.937 | D355: Purchase Invoice | E355: Purchase Invoice | F355: PU/26/SLS/OT/1640 | G355: Storage Charges - Cargo - SLSIPL,Gate In Charges Paid - SLSIPL | H355: PU/26/SLS/OT/1640, PU/26/SLS/OT/1640 | I355: 256779440392
A356: 2026-02-05 | B356: 181 | C356: 7063.8672 | D356: Purchase Invoice | E356: Purchase Invoice | F356: PU/26/SLS/OT/1643 | G356: Handling Charges - Inbound (Exp) - SLSIPL,Gate In Charges Paid - SLSIPL | H356: PU/26/SLS/OT/1643, PU/26/SLS/OT/1643 | I356: 256779440210
...

Sheet DN & CN in customer books
B1: 636449 | C1: 503
A2: Posting Date | B2: Debit (INR) | C2: Credit (INR) | D2: Voucher Subtype | E2: Voucher No | F2: Against Account | G2: Against Voucher | H2: Supplier Invoice No | I2: Supplier Invoice No
A3: 2025-07-16 | B3: 11798 | C3: 0 | D3: Credit Note | E3: SLS26/MF/DN/0013 | F3: Container Scanning Paid - SLSIPL | G3: PU/26/SLS/OT/0283 | H3: 256779413283 | J3: =_xlfn.XLOOKUP(H3,'Invoice & CN not in Customers'!$D:$D,'Invoice & CN not in Customers'!$H:$H,0,0) -> 0
A4: 2025-07-16 | B4: 140649 | C4: 0 | D4: Credit Note | E4: SLS26/MF/DN/0016 | F4: Storage Charges - Cargo - SLSIPL | G4: PU/26/SLS/OT/0612 | H4: 256779410010 | J4: =_xlfn.XLOOKUP(H4,'Invoice & CN not in Customers'!$D:$D,'Invoice & CN not in Customers'!$H:$H,0,0) -> 0
A5: 2025-07-16 | B5: 55272 | C5: 0 | D5: Credit Note | E5: SLS26/MF/DN/0017 | F5: Storage Charges - Cargo - SLSIPL | G5: PU/26/SLS/OT/0613 | H5: 256779410004 | J5: =_xlfn.XLOOKUP(H5,'Invoice & CN not in Customers'!$D:$D,'Invoice & CN not in Customers'!$H:$H,0,0) -> 0
A6: 2025-07-16 | B6: 4786 | C6: 0 | D6: Credit Note | E6: SLS26/MF/DN/0007-2 | F6: Storage Charges - Cargo - SLSIPL | G6: SLS26/MF/DN/0007-2 | H6: 256779421381 | J6: =_xlfn.XLOOKUP(H6,'Invoice & CN not in Customers'!$D:$D,'Invoice & CN not in Customers'!$H:$H,0,0) -> 0
A7: 2025-07-16 | B7: 11955 | C7: 0 | D7: Credit Note | E7: SLS26/MF/DN/0004-1 | F7: Transportation Charges Paid - SLSIPL | G7: PU/26/SLS/OT/0588 | H7: 246779413845 | J7: =_xlfn.XLOOKUP(H7,'Invoice & CN not in Customers'!$D:$D,'Invoice & CN not in Customers'!$H:$H,0,0) -> 0
A8: 2025-07-16 | B8: 12467 | C8: 0 | D8: Credit Note | E8: SLS26/MF/DN/0018-1 | F8: Storage Charges - Cargo - SLSIPL | G8: SLS26/MF/DN/0018-1 | H8: 256779421383 | J8: =_xlfn.XLOOKUP(H8,'Invoice & CN not in Customers'!$D:$D,'Invoice & CN not in Customers'!$H:$H,0,0) -> 0
A9: 2025-07-16 | B9: 6084 | C9: 0 | D9: Credit Note | E9: SLS26/MF/DN/0002-1 | F9: Scanning Charges - Inbound - SLSIPL | G9: SLS26/MF/DN/0002-1 | H9: 256779421376 | J9: =_xlfn.XLOOKUP(H9,'Invoice & CN not in Customers'!$D:$D,'Invoice & CN not in Customers'!$H:$H,0,0) -> 0
A10: 2025-07-16 | B10: 12169 | C10: 0 | D10: Credit Note | E10: SLS26/MF/DN/0003-1 | F10: Scanning Charges - Inbound - SLSIPL | G10: SLS26/MF/DN/0003-1 | H10: 256779421370 | J10: =_xlfn.XLOOKUP(H10,'Invoice & CN not in Customers'!$D:$D,'Invoice & CN not in Customers'!$H:$H,0,0) -> 0
A11: 2025-07-16 | B11: 114223 | C11: 0 | D11: Credit Note | E11: SLS26/MF/DN/0015-1 | F11: Storage Charges - Cargo - SLSIPL | G11: SLS26/MF/DN/0015-1 | H11: 256779421367 | J11: =_xlfn.XLOOKUP(H11,'Invoice & CN not in Customers'!$D:$D,'Invoice & CN not in Customers'!$H:$H,0,0) -> 0
A12: 2025-07-16 | B12: 31577 | C12: 0 | D12: Credit Note | E12: SLS26/MF/DN/0005-1 | F12: Storage Charges - Cargo - SLSIPL | G12: SLS26/MF/DN/0005-1 | H12: 256779421361 | J12: =_xlfn.XLOOKUP(H12,'Invoice & CN not in Customers'!$D:$D,'Invoice & CN not in Customers'!$H:$H,0,0) -> 0
A13: 2025-07-16 | B13: 17313 | C13: 330 | D13: Debit Note | E13: SLS26/MF/DN/0001-2 | F13: Scanning Charges - Inbound - SLSIPL | G13: SLS26/MF/DN/0001-2, SLS26/MF/DN/0001-2 | H13: 256779421379 | J13: =_xlfn.XLOOKUP(H13,'Invoice & CN not in Customers'!$D:$D,'Invoice & CN not in Customers'!$H:$H,0,0) -> 0
A14: 2025-07-16 | B14: 8696 | C14: 173 | D14: Debit Note | E14: SLS26/MF/DN/0010-1 | F14: Container Scanning Paid - SLSIPL | G14: SLS26/MF/DN/0010-1, SLS26/MF/DN/0010-1 | H14: 256779421373 | J14: =_xlfn.XLOOKUP(H14,'Invoice & CN not in Customers'!$D:$D,'Invoice & CN not in Customers'!$H:$H,0,0) -> 0
A15: 2025-07-16 | B15: 31723 | C15: 0 | D15: Credit Note | E15: SLS26/MF/DN/0009 | F15: Container Scanning Paid - SLSIPL | G15: PU/25/SLS/OT/1822 | H15: 246779413827 | J15: =_xlfn.XLOOKUP(H15,'Invoice & CN not in Customers'!$D:$D,'Invoice & CN not in Customers'!$H:$H,0,0) -> 0
A16: 2025-07-31 | B16: 15778 | C16: 0 | D16: Credit Note | E16: SLS26/MF/DN/0020-1 | F16: Storage Charges - Cargo - SLSIPL | G16: SLS26/MF/DN/0020-1 | H16: 246779410348 | I16: 256779421380 | J16: =_xlfn.XLOOKUP(H16,'Invoice & CN not in Customers'!$D:$D,'Invoice & CN not in Customers'!$H:$H,0,0) -> 0 | K16: =_xlfn.XLOOKUP(I16,'Invoice & CN not in Customers'!$D:$D,'Invoice & CN not in Customers'!$H:$H,0,0) -> 0
A17: 2025-07-31 | B17: 36410 | C17: 0 | D17: Credit Note | E17: SLS26/MF/DN/0022-1 | F17: Container Scanning Paid - SLSIPL | G17: SLS26/MF/DN/0022-1 | H17: 246779411278 | I17: 256779421385 | J17: =_xlfn.XLOOKUP(H17,'Invoice & CN not in Customers'!$D:$D,'Invoice & CN not in Customers'!$H:$H,0,0) -> 0 | K17: =_xlfn.XLOOKUP(I17,'Invoice & CN not in Customers'!$D:$D,'Invoice & CN not in Customers'!$H:$H,0,0) -> 0
A18: 2025-07-31 | B18: 15401 | C18: 0 | D18: Credit Note | E18: SLS26/MF/DN/0021-1 | F18: Fixed Storage Charges - ODC (Covered) - SLSIPL | G18: SLS26/MF/DN/0021-1 | H18: 256779421382 | I18: 246779413701 | J18: =_xlfn.XLOOKUP(H18,'Invoice & CN not in Customers'!$D:$D,'Invoice & CN not in Customers'!$H:$H,0,0) -> 0 | K18: =_xlfn.XLOOKUP(I18,'Invoice & CN not in Customers'!$D:$D,'Invoice & CN not in Customers'!$H:$H,0,0) -> 0
A19: 2025-07-16 | B19: 18611 | C19: 0 | D19: Credit Note | E19: SLS26/MF/DN/0008 | F19: Container Scanning Paid - SLSIPL | G19: PU/25/SLS/OT/1821 | H19: 246779413816 | J19: =_xlfn.XLOOKUP(H19,'Invoice & CN not in Customers'!$D:$D,'Invoice & CN not in Customers'!$H:$H,0,0) -> 0
A20: 2025-07-16 | B20: 19430 | C20: 0 | D20: Credit Note | E20: SLS26/MF/DN/0006 | F20: Storage Charges - Cargo - SLSIPL | G20: PU/26/SLS/OT/0590 | H20: 246779413705 | J20: =_xlfn.XLOOKUP(H20,'Invoice & CN not in Customers'!$D:$D,'Invoice & CN not in Customers'!$H:$H,0,0) -> 0
A21: 2025-07-16 | B21: 17857 | C21: 0 | D21: Credit Note | E21: SLS26/MF/DN/0011 | F21: Container Scanning Paid - SLSIPL | G21: PU/25/SLS/OT/1854 | H21: 246779411339 | J21: =_xlfn.XLOOKUP(H21,'Invoice & CN not in Customers'!$D:$D,'Invoice & CN not in Customers'!$H:$H,0,0) -> 0
A22: 2025-07-16 | B22: 20874 | C22: 0 | D22: Credit Note | E22: SLS26/MF/DN/0014 | F22: Container Scanning Paid - SLSIPL | G22: PU/25/SLS/OT/1820 | H22: 246779411326 | J22: =_xlfn.XLOOKUP(H22,'Invoice & CN not in Customers'!$D:$D,'Invoice & CN not in Customers'!$H:$H,0,0) -> 0
A23: 2025-07-31 | B23: 33376 | C23: 0 | D23: Credit Note | E23: SLS26/MF/DN/0019 | F23: Container Scanning Paid - SLSIPL | G23: PU/25/SLS/OT/1925 | H23: 246779411300 | J23: =_xlfn.XLOOKUP(H23,'Invoice & CN not in Customers'!$D:$D,'Invoice & CN not in Customers'!$H:$H,0,0) -> 0

Sheet DN Reversal with CN in customer
A1: Posting Date | B1: Debit (INR) | C1: Credit (INR) | D1: Voucher Type | E1: Voucher Subtype | F1: Voucher No | G1: Against Voucher | I1: Supplier Invoice No
A2: 2025-12-31 | B2: 453 | C2: 453 | D2: Journal Entry | E2: Debit Note | F2: SJ/25/GEA/1377 | G2: PU/26/SLS/OT/1422 | H2: SLS26/MF/DN/0001-2 | I2: 256779417084
A3: 2025-12-31 | B3: 16530 | C3: 16530 | D3: Journal Entry | E3: Debit Note | F3: SJ/25/GEA/1376 | G3: PU/26/SLS/OT/0585 | H3: SLS26/MF/DN/0001-2 | I3: 256779414288
A4: 2025-10-07 | B4: 6084 | C4: 6084 | D4: Journal Entry | E4: Debit Note | F4: SJ/25/GEA/1108 | G4: PU/26/SLS/OT/0586-1 | H4: SLS26/MF/DN/0002-1 | I4: 256779412692
A5: 2025-10-07 | B5: 12169 | C5: 12169 | D5: Journal Entry | E5: Debit Note | F5: SJ/25/GEA/1109 | G5: PU/26/SLS/OT/0587-1 | H5: SLS26/MF/DN/0003-1 | I5: 256779411917
A6: 2025-10-07 | B6: 114223 | C6: 114223 | D6: Journal Entry | E6: Debit Note | F6: SJ/25/GEA/1110 | G6: PU/26/SLS/OT/0611-1 | H6: SLS26/MF/DN/0015-1 | I6: 256779410220
A7: 2025-10-07 | B7: 12467 | C7: 12467 | D7: Journal Entry | E7: Debit Note | F7: SJ/25/GEA/1107 | G7: PU/26/SLS/OT/0614-1 | H7: SLS26/MF/DN/0018-1 | I7: 246779413796
A8: 2025-10-07 | B8: 31577 | C8: 31577 | D8: Journal Entry | E8: Debit Note | F8: SJ/25/GEA/1111 | G8: PU/26/SLS/OT/0589-2 | H8: SLS26/MF/DN/0005-1 | I8: 246779413702
A9: 2025-10-07 | B9: 15401 | C9: 15401 | D9: Journal Entry | E9: Debit Note | F9: SJ/25/GEA/1106 | G9: PU/26/SLS/OT/1008-1 | H9: SLS26/MF/DN/0021-1 | I9: 246779413701
A10: 2025-12-31 | B10: 8522 | C10: 8522 | D10: Journal Entry | E10: Debit Note | F10: SJ/25/GEA/1378 | G10: PU/25/SLS/OT/1856 | H10: SLS26/MF/DN/0010-1 | I10: 246779411314
A11: 2025-10-07 | B11: 36410 | C11: 36410 | D11: Journal Entry | E11: Debit Note | F11: SJ/25/GEA/1105 | G11: PU/26/SLS/OT/1009-1 | H11: SLS26/MF/DN/0022-1 | I11: 246779411278
A12: 2025-10-07 | B12: 4786 | C12: 4786 | D12: Journal Entry | E12: Debit Note | F12: SJ/25/GEA/1103 | G12: PU/26/SLS/OT/0591-1 | H12: SLS26/MF/DN/0007-2 | I12: 246779410360
A13: 2025-10-07 | B13: 15778 | C13: 15778 | D13: Journal Entry | E13: Debit Note | F13: SJ/25/GEA/1104 | G13: PU/26/SLS/OT/0415-1 | H13: SLS26/MF/DN/0020-1 | I13: 246779410348

Sheet Customer Data
A2: Posting Date | B2: Account | C2: Debit (INR) | D2: Credit (INR) | E2: Balance (INR) | F2: Voucher Type | G2: Voucher Subtype | H2: Voucher No | I2: Against Account | J2: Party Type | K2: Party | L2: Against Voucher | M2: Supplier Invoice No
A3: 2025-02-20 | B3: Sundry Creditors - SLSIPL | C3: 0 | D3: 35554.52 | E3: -35554.52 | F3: Purchase Invoice | G3: Purchase Invoice | H3: PU/25/SLS/OT/1560 | I3: Fixed Storage Charges - ODC (Covered) - SLSIPL | J3: Supplier | K3: Ascendas Panvel FTWZ Private Limited | L3: PU/25/SLS/OT/1560 | M3: 246779410049
A4: 2025-02-20 | B4: Sundry Creditors - SLSIPL | C4: 0 | D4: 35554.52 | E4: -71109.04 | F4: Purchase Invoice | G4: Purchase Invoice | H4: PU/25/SLS/OT/1561 | I4: Fixed Storage Charges - ODC (Covered) - SLSIPL | J4: Supplier | K4: Ascendas Panvel FTWZ Private Limited | L4: PU/25/SLS/OT/1561 | M4: 246779410303
A5: 2025-02-20 | B5: Sundry Creditors - SLSIPL | C5: 0 | D5: 35554.52 | E5: -106663.56 | F5: Purchase Invoice | G5: Purchase Invoice | H5: PU/25/SLS/OT/1562 | I5: Fixed Storage Charges - ODC (Covered) - SLSIPL | J5: Supplier | K5: Ascendas Panvel FTWZ Private Limited | L5: PU/25/SLS/OT/1562 | M5: 246779410117
A6: 2025-02-20 | B6: Sundry Creditors - SLSIPL | C6: 0 | D6: 35554.52 | E6: -142218.08 | F6: Purchase Invoice | G6: Purchase Invoice | H6: PU/25/SLS/OT/1563 | I6: Fixed Storage Charges - ODC (Covered) - SLSIPL | J6: Supplier | K6: Ascendas Panvel FTWZ Private Limited | L6: PU/25/SLS/OT/1563 | M6: 246779410160
A7: 2025-02-20 | B7: Sundry Creditors - SLSIPL | C7: 0 | D7: 35554.52 | E7: -177772.6 | F7: Purchase Invoice | G7: Purchase Invoice | H7: PU/25/SLS/OT/1564 | I7: Fixed Storage Charges - ODC (Covered) - SLSIPL | J7: Supplier | K7: Ascendas Panvel FTWZ Private Limited | L7: PU/25/SLS/OT/1564 | M7: 246779410203
A8: 2025-02-20 | B8: Sundry Creditors - SLSIPL | C8: 0 | D8: 35554.52 | E8: -213327.12 | F8: Purchase Invoice | G8: Purchase Invoice | H8: PU/25/SLS/OT/1565 | I8: Fixed Storage Charges - ODC (Covered) - SLSIPL | J8: Supplier | K8: Ascendas Panvel FTWZ Private Limited | L8: PU/25/SLS/OT/1565 | M8: 246779410246
A9: 2025-03-03 | B9: Sundry Creditors - SLSIPL | C9: 0 | D9: 804 | E9: -214131.12 | F9: Purchase Invoice | G9: Purchase Invoice | H9: PU/25/SLS/OT/1672 | I9: Handling Charges - Outbound (Exp) - SLSIPL | J9: Supplier | K9: Ascendas Panvel FTWZ Private Limited | L9: PU/25/SLS/OT/1672 | M9: 246779410613
A10: 2025-03-03 | B10: Sundry Creditors - SLSIPL | C10: 0 | D10: 1004 | E10: -215135.12 | F10: Purchase Invoice | G10: Purchase Invoice | H10: PU/25/SLS/OT/1673 | I10: Handling Charges - Outbound (Exp) - SLSIPL | J10: Supplier | K10: Ascendas Panvel FTWZ Private Limited | L10: PU/25/SLS/OT/1673 | M10: 246779410612
A11: 2025-03-03 | B11: Sundry Creditors - SLSIPL | C11: 0 | D11: 402 | E11: -215537.12 | F11: Purchase Invoice | G11: Purchase Invoice | H11: PU/25/SLS/OT/1674 | I11: Handling Charges - Outbound (Exp) - SLSIPL | J11: Supplier | K11: Ascendas Panvel FTWZ Private Limited | L11: PU/25/SLS/OT/1674 | M11: 246779410611
A12: 2025-03-03 | B12: Sundry Creditors - SLSIPL | C12: 0 | D12: 201 | E12: -215738.12 | F12: Purchase Invoice | G12: Purchase Invoice | H12: PU/25/SLS/OT/1675 | I12: Handling Charges - Outbound (Exp) - SLSIPL | J12: Supplier | K12: Ascendas Panvel FTWZ Private Limited | L12: PU/25/SLS/OT/1675 | M12: 246779410610
A13: 2025-03-03 | B13: Sundry Creditors - SLSIPL | C13: 0 | D13: 804 | E13: -216542.12 | F13: Purchase Invoice | G13: Purchase Invoice | H13: PU/25/SLS/OT/1676 | I13: Handling Charges - Outbound (Exp) - SLSIPL | J13: Supplier | K13: Ascendas Panvel FTWZ Private Limited | L13: PU/25/SLS/OT/1676 | M13: 246779410608
A14: 2025-03-03 | B14: Sundry Creditors - SLSIPL | C14: 0 | D14: 402 | E14: -216944.12 | F14: Purchase Invoice | G14: Purchase Invoice | H14: PU/25/SLS/OT/1677 | I14: Handling Charges - Outbound (Exp) - SLSIPL | J14: Supplier | K14: Ascendas Panvel FTWZ Private Limited | L14: PU/25/SLS/OT/1677 | M14: 246779410607
... A222: 2025-05-28 | B222: Sundry Creditors - SLSIPL | C222: 0 | D222: 333696 | E222: -5193789.1 | F222: Purchase Invoice | G222: Purchase Invoice | H222: PU/26/SLS/OT/0278 | I222: Storage Charges - Cargo - SLSIPL | J222: Supplier | K222: Ascendas Panvel FTWZ Private Limited | L222: PU/26/SLS/OT/0278 | M222: 256779413899
A223: 2025-05-30 | B223: Sundry Creditors - SLSIPL | C223: 177773 | D223: 0 | E223: -5016016.1 | F223: Payment Entry | G223: Pay | H223: BP/26/SLS/0192 | I223: 1395250393003 - Punjab National Bank - INR - SLSIPL | J223: Supplier | K223: Ascendas Panvel FTWZ Private Limited
A224: 2025-06-04 | B224: Sundry Creditors - SLSIPL | C224: 0 | D224: 9844 | E224: -5025860.1 | F224: Purchase Invoice | G224: Purchase Invoice | H224: PU/26/SLS/OT/0358 | I224: Handling Charges - Outbound (Exp) - SLSIPL | J224: Supplier | K224: Ascendas Panvel FTWZ Private Limited | L224: PU/26/SLS/OT/0358 | M224: 256779414165
A225: 2025-06-04 | B225: Sundry Creditors - SLSIPL | C225: 0 | D225: 8407 | E225: -5034267.1 | F225: Purchase Invoice | G225: Purchase Invoice | H225: PU/26/SLS/OT/0360 | I225: Handling Charges - Outbound (Exp) - SLSIPL | J225: Supplier | K225: Ascendas Panvel FTWZ Private Limited | L225: PU/26/SLS/OT/0360 | M225: 256779414216
A226: 2025-06-04 | B226: Sundry Creditors - SLSIPL | C226: 500946.52 | D226: 0 | E226: -4533320.6 | F226: Payment Entry | G226: Pay | H226: BP/25/SLS/1225-1 | I226: 1395250393003 - Punjab National Bank - INR - SLSIPL | J226: Supplier | K226: Ascendas Panvel FTWZ Private Limited | L226: PU/25/SLS/OT/1562, PU/25/SLS/OT/1720, PU/25/SLS/OT/1731, PU/25/SLS/OT/1721, PU/25/SLS/OT/1673 | M226: 246779410117
A227: 2025-06-04 | B227: Sundry Creditors - SLSIPL | C227: 0 | D227: 17313 | E227: -4550633.6 | F227: Purchase Invoice | G227: Purchase Invoice | H227: PU/26/SLS/OT/0585 | I227: Scanning Charges - Inbound - SLSIPL | J227: Supplier | K227: Ascendas Panvel FTWZ Private Limited | L227: PU/26/SLS/OT/0585 | M227: 256779414288
A228: 2025-06-04 | B228: Sundry Creditors - SLSIPL | C228: 0 | D228: 41769 | E228: -4592402.6 | F228: Purchase Invoice | G228: Purchase Invoice | H228: PU/26/SLS/OT/0797 | I228: Handling Charges - Inbound (Exp) - SLSIPL,LCL Movment - Gate in Charge - SLSIPL,Transportation Charges Paid - SLSIPL,Eempty Container Return Charges Paid - SLSIPL | J228: Supplier | K228: Ascendas Panvel FTWZ Private Limited | L228: PU/26/SLS/OT/0797 | M228: 256779414158
A229: 2025-06-07 | B229: Sundry Creditors - SLSIPL | C229: 0 | D229: 352792 | E229: -4945194.6 | F229: Purchase Invoice | G229: Purchase Invoice | H229: PU/26/SLS/OT/0285 | I229: Storage Charges - Cargo - SLSIPL | J229: Supplier | K229: Ascendas Panvel FTWZ Private Limited | L229: PU/26/SLS/OT/0285 | M229: 256779414242
A230: 2025-06-10 | B230: Sundry Creditors - SLSIPL | C230: 0 | D230: 35431 | E230: -4980625.6 | F230: Purchase Invoice | G230: Purchase Invoice | H230: PU/26/SLS/OT/0357-1 | I230: Fixed Storage Charges - ODC (Covered) - SLSIPL | J230: Supplier | K230: Ascendas Panvel FTWZ Private Limited | L230: PU/26/SLS/OT/0357-1 | M230: 256779414386
A231: 2025-06-13 | B231: Sundry Creditors - SLSIPL | C231: 700000 | D231: 0 | E231: -4280625.6 | F231: Payment Entry | G231: Pay | H231: BP/26/SLS/0229 | I231: 1395250393003 - Punjab National Bank - INR - SLSIPL | J231: Supplier | K231: Ascendas Panvel FTWZ Private Limited
A232: 2025-06-21 | B232: Sundry Creditors - SLSIPL | C232: 700000 | D232: 0 | E232: -3580625.6 | F232: Payment Entry | G232: Pay | H232: BP/26/SLS/0259 | I232: 1395250393003 - Punjab National Bank - INR - SLSIPL | J232: Supplier | K232: Ascendas Panvel FTWZ Private Limited
A233: 2025-06-30 | B233: Sundry Creditors - SLSIPL | C233: 700000 | D233: 0 | E233: -2880625.6 | F233: Payment Entry | G233: Pay | H233: BP/26/SLS/0291 | I233: 1395250393003 - Punjab National Bank - INR - SLSIPL | J233: Supplier | K233: Ascendas Panvel FTWZ Private Limited
A234: 2025-07-05 | B234: Sundry Creditors - SLSIPL | C234: 700000 | D234: 0 | E234: -2180625.6 | F234: Payment Entry | G234: Pay | H234: BP/26/SLS/0300 | I234: 1395250393003 - Punjab National Bank - INR - SLSIPL | J234: Supplier | K234: Ascendas Panvel FTWZ Private Limited
A235: 2025-07-11 | B235: Sundry Creditors - SLSIPL | C235: 700000 | D235: 0 | E235: -1480625.6 | F235: Payment Entry | G235: Pay | H235: BP/26/SLS/0311 | I235: 1395250393003 - Punjab National Bank - INR - SLSIPL | J235: Supplier | K235: Ascendas Panvel FTWZ Private Limited
A236: 2025-07-11 | B236: Sundry Creditors - SLSIPL | C236: 0 | D236: 151725 | E236: -1632350.6 | F236: Purchase Invoice | G236: Purchase Invoice | H236: PU/26/SLS/OT/0415-1 | I236: Storage Charges - Cargo - SLSIPL | J236: Supplier | K236: Ascendas Panvel FTWZ Private Limited | L236: PU/26/SLS/OT/0415-1 | M236: 246779410348
A237: 2025-07-16 | B237: Sundry Creditors - SLSIPL | C237: 19430 | D237: 0 | E237: -1612920.6 | F237: Purchase Invoice | G237: Credit Note | H237: SLS26/MF/DN/0006 | I237: Storage Charges - Cargo - SLSIPL | J237: Supplier | K237: Ascendas Panvel FTWZ Private Limited | L237: PU/26/SLS/OT/0590 | M237: 246779413705
A238: 2025-07-16 | B238: Sundry Creditors - SLSIPL | C238: 18611 | D238: 0 | E238: -1594309.6 | F238: Purchase Invoice | G238: Credit Note | H238: SLS26/MF/DN/0008 | I238: Container Scanning Paid - SLSIPL | J238: Supplier | K238: Ascendas Panvel FTWZ Private Limited | L238: PU/25/SLS/OT/1821 | M238: 246779413816
A239: 2025-07-16 | B239: Sundry Creditors - SLSIPL | C239: 31723 | D239: 0 | E239: -1562586.6 | F239: Purchase Invoice | G239: Credit Note | H239: SLS26/MF/DN/0009 | I239: Container Scanning Paid - SLSIPL | J239: Supplier | K239: Ascendas Panvel FTWZ Private Limited | L239: PU/25/SLS/OT/1822 | M239: 246779413827
A240: 2025-07-16 | B240: Sundry Creditors - SLSIPL | C240: 17857 | D240: 0 | E240: -1544729.6 | F240: Purchase Invoice | G240: Credit Note | H240: SLS26/MF/DN/0011 | I240: Container Scanning Paid - SLSIPL | J240: Supplier | K240: Ascendas Panvel FTWZ Private Limited | L240: PU/25/SLS/OT/1854 | M240: 246779411339
A241: 2025-07-16 | B241: Sundry Creditors - SLSIPL | C241: 11798 | D241: 0 | E241: -1532931.6 | F241: Purchase Invoice | G241: Credit Note | H241: SLS26/MF/DN/0013 | I241: Container Scanning Paid - SLSIPL | J241: Supplier | K241: Ascendas Panvel FTWZ Private Limited | L241: PU/26/SLS/OT/0283 | M241: 256779413283
A242: 2025-07-16 | B242: Sundry Creditors - SLSIPL | C242: 20874 | D242: 0 | E242: -1512057.6 | F242: Purchase Invoice | G242: Credit Note | H242: SLS26/MF/DN/0014 | I242: Container Scanning Paid - SLSIPL | J242: Supplier | K242: Ascendas Panvel FTWZ Private Limited | L242: PU/25/SLS/OT/1820 | M242: 246779411326
A243: 2025-07-16 | B243: Sundry Creditors - SLSIPL | C243: 140649 | D243: 0 | E243: -1371408.6 | F243: Purchase Invoice | G243: Credit Note | H243: SLS26/MF/DN/0016 | I243: Storage Charges - Cargo - SLSIPL | J243: Supplier | K243: Ascendas Panvel FTWZ Private Limited | L243: PU/26/SLS/OT/0612 | M243: 256779410010
A244: 2025-07-16 | B244: Sundry Creditors - SLSIPL | C244: 55272 | D244: 0 | E244: -1316136.6 | F244: Purchase Invoice | G244: Credit Note | H244: SLS26/MF/DN/0017 | I244: Storage Charges - Cargo - SLSIPL | J244: Supplier | K244: Ascendas Panvel FTWZ Private Limited | L244: PU/26/SLS/OT/0613 | M244: 256779410004
A245: 2025-07-16 | B245: Sundry Creditors - SLSIPL | C245: 4786 | D245: 0 | E245: -1311350.6 | F245: Purchase Invoice | G245: Credit Note | H245: SLS26/MF/DN/0007-2 | I245: Storage Charges - Cargo - SLSIPL | J245: Supplier | K245: Ascendas Panvel FTWZ Private Limited | L245: SLS26/MF/DN/0007-2 | M245: 256779421381
A246: 2025-07-16 | B246: Sundry Creditors - SLSIPL | C246: 11955 | D246: 0 | E246: -1299395.6 | F246: Purchase Invoice | G246: Credit Note | H246: SLS26/MF/DN/0004-1 | I246: Transportation Charges Paid - SLSIPL | J246: Supplier | K246: Ascendas Panvel FTWZ Private Limited | L246: PU/26/SLS/OT/0588 | M246: 246779413845
A247: 2025-07-16 | B247: Sundry Creditors - SLSIPL | C247: 0 | D247: 163631 | E247: -1463026.6 | F247: Purchase Invoice | G247: Purchase Invoice | H247: PU/26/SLS/OT/0614-1 | I247: Storage Charges - Cargo - SLSIPL | J247: Supplier | K247: Ascendas Panvel FTWZ Private Limited | L247: PU/26/SLS/OT/0614-1 | M247: 246779413796
... A255: 2025-07-16 | B255: Sundry Creditors - SLSIPL | C255: 8696 | D255: 173 | E255: -1292577.6 | F255: Purchase Invoice | G255: Debit Note | H255: SLS26/MF/DN/0010-1 | I255: Container Scanning Paid - SLSIPL | J255: Supplier | K255: Ascendas Panvel FTWZ Private Limited | L255: SLS26/MF/DN/0010-1, SLS26/MF/DN/0010-1 | M255: 256779421373
A256: 2025-07-19 | B256: Sundry Creditors - SLSIPL | C256: 700000 | D256: 0 | E256: -592577.6 | F256: Payment Entry | G256: Pay | H256: BP/26/SLS/0368 | I256: 1395250393003 - Punjab National Bank - INR - SLSIPL | J256: Supplier | K256: Ascendas Panvel FTWZ Private Limited
A257: 2025-07-24 | B257: Sundry Creditors - SLSIPL | C257: 0 | D257: 9368 | E257: -601945.6 | F257: Purchase Invoice | G257: Purchase Invoice | H257: PU/26/SLS/OT/0607 | I257: Handling Charges - Inbound (Exp) - SLSIPL | J257: Supplier | K257: Ascendas Panvel FTWZ Private Limited | L257: PU/26/SLS/OT/0607 | M257: 256779415945
A258: 2025-07-25 | B258: Sundry Creditors - SLSIPL | C258: 350672 | D258: 0 | E258: -251273.6 | F258: Payment Entry | G258: Pay | H258: BP/26/SLS/0394 | I258: 1395250393003 - Punjab National Bank - INR - SLSIPL | J258: Supplier | K258: Ascendas Panvel FTWZ Private Limited
A259: 2025-07-25 | B259: Sundry Creditors - SLSIPL | C259: 0 | D259: 32007 | E259: -283280.6 | F259: Purchase Invoice | G259: Purchase Invoice | H259: PU/26/SLS/OT/0608 | I259: Storage Charges - Cargo - SLSIPL | J259: Supplier | K259: Ascendas Panvel FTWZ Private Limited | L259: PU/26/SLS/OT/0608 | M259: 256779415967
A260: 2025-07-25 | B260: Sundry Creditors - SLSIPL | C260: 0 | D260: 9348 | E260: -292628.6 | F260: Purchase Invoice | G260: Purchase Invoice | H260: PU/26/SLS/OT/0609 | I260: Storage Charges - Cargo - SLSIPL | J260: Supplier | K260: Ascendas Panvel FTWZ Private Limited | L260: PU/26/SLS/OT/0609 | M260: 256779415970
A261: 2025-07-25 | B261: Sundry Creditors - SLSIPL | C261: 0 | D261: 196 | E261: -292824.6 | F261: Purchase Invoice | G261: Purchase Invoice | H261: PU/26/SLS/OT/0610 | I261: VOS Activity Charges Paid - SLSIPL | J261: Supplier | K261: Ascendas Panvel FTWZ Private Limited | L261: PU/26/SLS/OT/0610 | M261: 256779415995
A262: 2025-07-31 | B262: Sundry Creditors - SLSIPL | C262: 33376 | D262: 0 | E262: -259448.6 | F262: Purchase Invoice | G262: Credit Note | H262: SLS26/MF/DN/0019 | I262: Container Scanning Paid - SLSIPL | J262: Supplier | K262: Ascendas Panvel FTWZ Private Limited | L262: PU/25/SLS/OT/1925 | M262: 246779411300
A263: 2025-07-31 | B263: Sundry Creditors - SLSIPL | C263: 15778 | D263: 0 | E263: -243670.6 | F263: Purchase Invoice | G263: Credit Note | H263: SLS26/MF/DN/0020-1 | I263: Storage Charges - Cargo - SLSIPL | J263: Supplier | K263: Ascendas Panvel FTWZ Private Limited | L263: SLS26/MF/DN/0020-1 | M263: 246779410348/256779421380
A264: 2025-07-31 | B264: Sundry Creditors - SLSIPL | C264: 0 | D264: 44602 | E264: -288272.6 | F264: Purchase Invoice | G264: Purchase Invoice | H264: PU/26/SLS/OT/1009-1 | I264: Container Scanning Paid - SLSIPL | J264: Supplier | K264: Ascendas Panvel FTWZ Private Limited | L264: PU/26/SLS/OT/1009-1 | M264: 246779411278
A265: 2025-07-31 | B265: Sundry Creditors - SLSIPL | C265: 36410 | D265: 0 | E265: -251862.6 | F265: Purchase Invoice | G265: Credit Note | H265: SLS26/MF/DN/0022-1 | I265: Container Scanning Paid - SLSIPL | J265: Supplier | K265: Ascendas Panvel FTWZ Private Limited | L265: SLS26/MF/DN/0022-1 | M265: 246779411278/256779421385
A266: 2025-07-31 | B266: Sundry Creditors - SLSIPL | C266: 15401 | D266: 0 | E266: -236461.6 | F266: Purchase Invoice | G266: Credit Note | H266: SLS26/MF/DN/0021-1 | I266: Fixed Storage Charges - ODC (Covered) - SLSIPL | J266: Supplier | K266: Ascendas Panvel FTWZ Private Limited | L266: SLS26/MF/DN/0021-1 | M266: 256779421382/246779413701
A267: 2025-07-31 | B267: Sundry Creditors - SLSIPL | C267: 0 | D267: 18367 | E267: -254828.6 | F267: Purchase Invoice | G267: Purchase Invoice | H267: PU/26/SLS/OT/1008-1 | I267: Fixed Storage Charges - ODC (Covered) - SLSIPL | J267: Supplier | K267: Ascendas Panvel FTWZ Private Limited | L267: PU/26/SLS/OT/1008-1 | M267: 246779413701
A268: 2025-08-08 | B268: Sundry Creditors - SLSIPL | C268: 0 | D268: 9124 | E268: -263952.6 | F268: Purchase Invoice | G268: Purchase Invoice | H268: PU/26/SLS/OT/0798 | I268: Handling Charges - Outbound (Exp) - SLSIPL | J268: Supplier | K268: Ascendas Panvel FTWZ Private Limited | L268: PU/26/SLS/OT/0798 | M268: 256779416223
A269: 2025-08-08 | B269: Sundry Creditors - SLSIPL | C269: 0 | D269: 4755 | E269: -268707.6 | F269: Purchase Invoice | G269: Purchase Invoice | H269: PU/26/SLS/OT/0800 | I269: Handling Charges - Outbound (Exp) - SLSIPL | J269: Supplier | K269: Ascendas Panvel FTWZ Private Limited | L269: PU/26/SLS/OT/0800 | M269: 256779416256
A270: 2025-08-08 | B270: Sundry Creditors - SLSIPL | C270: 0 | D270: 462828 | E270: -731535.6 | F270: Purchase Invoice | G270: Purchase Invoice | H270: PU/26/SLS/OT/0796 | I270: Storage Charges - SLSIPL | J270: Supplier | K270: Ascendas Panvel FTWZ Private Limited | L270: PU/26/SLS/OT/0796 | M270: 256779416088
A271: 2025-08-20 | B271: Sundry Creditors - SLSIPL | C271: 0 | D271: 4790 | E271: -736325.6 | F271: Purchase Invoice | G271: Purchase Invoice | H271: PU/26/SLS/OT/0792 | I271: Handling Charges - Outbound (Exp) - SLSIPL,MHE Charges Paid - SLSIPL | J271: Supplier | K271: Ascendas Panvel FTWZ Private Limited | L271: PU/26/SLS/OT/0792 | M271: 256779416615
A272: 2025-08-20 | B272: Sundry Creditors - SLSIPL | C272: 0 | D272: 6981 | E272: -743306.6 | F272: Purchase Invoice | G272: Purchase Invoice | H272: PU/26/SLS/OT/0793 | I272: VOS Activity Charges Paid - SLSIPL | J272: Supplier | K272: Ascendas Panvel FTWZ Private Limited | L272: PU/26/SLS/OT/0793 | M272: 256779416809
A273: 2025-08-20 | B273: Sundry Creditors - SLSIPL | C273: 0 | D273: 971 | E273: -744277.6 | F273: Purchase Invoice | G273: Purchase Invoice | H273: PU/26/SLS/OT/0801 | I273: Loose Loading Handling - SLSIPL | J273: Supplier | K273: Ascendas Panvel FTWZ Private Limited | L273: PU/26/SLS/OT/0801 | M273: 256779416878
A274: 2025-08-20 | B274: Sundry Creditors - SLSIPL | C274: 0 | D274: 11922 | E274: -756199.6 | F274: Purchase Invoice | G274: Purchase Invoice | H274: PU/26/SLS/OT/0795 | I274: Handling Charges - Inbound (Exp) - SLSIPL,Gate in Charges - Inbound - SLSIPL | J274: Supplier | K274: Ascendas Panvel FTWZ Private Limited | L274: PU/26/SLS/OT/0795 | M274: 256779416844
A275: 2025-08-20 | B275: Sundry Creditors - SLSIPL | C275: 0 | D275: 1463 | E275: -757662.6 | F275: Purchase Invoice | G275: Purchase Invoice | H275: PU/26/SLS/OT/0794 | I275: LCL Movment - Gate in Charge - SLSIPL,Handling Charges - Inbound (Exp) - SLSIPL | J275: Supplier | K275: Ascendas Panvel FTWZ Private Limited | L275: PU/26/SLS/OT/0794 | M275: 256779416603
A276: 2025-10-07 | B276: Sundry Creditors - SLSIPL | C276: 4786 | D276: 4786 | E276: -757662.6 | F276: Journal Entry | G276: Debit Note | H276: SJ/25/GEA/1103 | J276: Supplier | K276: Ascendas Panvel FTWZ Private Limited | L276: PU/26/SLS/OT/0591-1, SLS26/MF/DN/0007-2 | M276: 246779410360
A277: 2025-10-07 | B277: Sundry Creditors - SLSIPL | C277: 15778 | D277: 15778 | E277: -757662.6 | F277: Journal Entry | G277: Debit Note | H277: SJ/25/GEA/1104 | J277: Supplier | K277: Ascendas Panvel FTWZ Private Limited | L277: PU/26/SLS/OT/0415-1, SLS26/MF/DN/0020-1 | M277: 246779410348
A278: 2025-10-07 | B278: Sundry Creditors - SLSIPL | C278: 36410 | D278: 36410 | E278: -757662.6 | F278: Journal Entry | G278: Debit Note | H278: SJ/25/GEA/1105 | J278: Supplier | K278: Ascendas Panvel FTWZ Private Limited | L278: PU/26/SLS/OT/1009-1, SLS26/MF/DN/0022-1 | M278: 246779411278
A279: 2025-10-07 | B279: Sundry Creditors - SLSIPL | C279: 15401 | D279: 15401 | E279: -757662.6 | F279: Journal Entry | G279: Debit Note | H279: SJ/25/GEA/1106 | J279: Supplier | K279: Ascendas Panvel FTWZ Private Limited | L279: PU/26/SLS/OT/1008-1, SLS26/MF/DN/0021-1 | M279: 246779413701
A280: 2025-10-07 | B280: Sundry Creditors - SLSIPL | C280: 12467 | D280: 12467 | E280: -757662.6 | F280: Journal Entry | G280: Debit Note | H280: SJ/25/GEA/1107 | J280: Supplier | K280: Ascendas Panvel FTWZ Private Limited | L280: PU/26/SLS/OT/0614-1, SLS26/MF/DN/0018-1 | M280: 246779413796
A281: 2025-10-07 | B281: Sundry Creditors - SLSIPL | C281: 6084 | D281: 6084 | E281: -757662.6 | F281: Journal Entry | G281: Debit Note | H281: SJ/25/GEA/1108 | J281: Supplier | K281: Ascendas Panvel FTWZ Private Limited | L281: PU/26/SLS/OT/0586-1, SLS26/MF/DN/0002-1 | M281: 256779412692
A282: 2025-10-07 | B282: Sundry Creditors - SLSIPL | C282: 12169 | D282: 12169 | E282: -757662.6 | F282: Journal Entry | G282: Debit Note | H282: SJ/25/GEA/1109 | J282: Supplier | K282: Ascendas Panvel FTWZ Private Limited | L282: PU/26/SLS/OT/0587-1, SLS26/MF/DN/0003-1 | M282: 256779411917
A283: 2025-10-07 | B283: Sundry Creditors - SLSIPL | C283: 114223 | D283: 114223 | E283: -757662.6 | F283: Journal Entry | G283: Debit Note | H283: SJ/25/GEA/1110 | J283: Supplier | K283: Ascendas Panvel FTWZ Private Limited | L283: PU/26/SLS/OT/0611-1, SLS26/MF/DN/0015-1 | M283: 256779410220
A284: 2025-10-07 | B284: Sundry Creditors - SLSIPL | C284: 31577 | D284: 31577 | E284: -757662.6 | F284: Journal Entry | G284: Debit Note | H284: SJ/25/GEA/1111 | J284: Supplier | K284: Ascendas Panvel FTWZ Private Limited | L284: PU/26/SLS/OT/0589-2, SLS26/MF/DN/0005-1 | M284: 246779413702
A285: 2025-10-09 | B285: Sundry Creditors - SLSIPL | C285: 500000 | D285: 0 | E285: -257662.6 | F285: Payment Entry | G285: Pay | H285: BP/26/SLS/0710 | I285: 1395250393003 - Punjab National Bank - INR - SLSIPL | J285: Supplier | K285: Ascendas Panvel FTWZ Private Limited | L285: PU/26/SLS/OT/0797, PU/26/SLS/OT/0357-1, PU/26/SLS/OT/0610, PU/26/SLS/OT/0796, PU/26/SLS/OT/0794 | M285: 256779414158
A286: 2025-10-10 | B286: Sundry Creditors - SLSIPL | C286: 108564 | D286: 0 | E286: -149098.6 | F286: Payment Entry | G286: Pay | H286: BP/26/SLS/0711 | I286: 1395250393003 - Punjab National Bank - INR - SLSIPL | J286: Supplier | K286: Ascendas Panvel FTWZ Private Limited | L286: PU/26/SLS/OT/0797, PU/26/SLS/OT/0607, PU/26/SLS/OT/0608, PU/26/SLS/OT/0609, PU/26/SLS/OT/0798, PU/26/SLS/OT/0800, PU/26/SLS/OT/0792, PU/26/SLS/OT/0793, PU/26/SLS/OT/0795, PU/26/SLS/OT/0801 | M286: 256779414158
A287: 2025-10-18 | B287: Sundry Creditors - SLSIPL | C287: 500000 | D287: 0 | E287: 350901.4 | F287: Payment Entry | G287: Pay | H287: BP/26/SLS/0758 | I287: 1395250393003 - Punjab National Bank - INR - SLSIPL | J287: Supplier | K287: Ascendas Panvel FTWZ Private Limited
A288: 2025-10-29 | B288: Sundry Creditors - SLSIPL | C288: 300000 | D288: 0 | E288: 650901.4 | F288: Payment Entry | G288: Pay | H288: BP/26/SLS/0765 | I288: 1395250393003 - Punjab National Bank - INR - SLSIPL | J288: Supplier | K288: Ascendas Panvel FTWZ Private Limited
A289: 2025-11-01 | B289: Sundry Creditors - SLSIPL | C289: 500000 | D289: 0 | E289: 1150901.4 | F289: Payment Entry | G289: Pay | H289: BP/26/SLS/0801 | I289: 1395250393003 - Punjab National Bank - INR - SLSIPL | J289: Supplier | K289: Ascendas Panvel FTWZ Private Limited
A290: 2025-12-12 | B290: Sundry Creditors - SLSIPL | C290: 0 | D290: 16480.711 | E290: 1134420.7 | F290: Purchase Invoice | G290: Purchase Invoice | H290: PU/26/SLS/OT/1356 | I290: Storage Charges - Cargo - SLSIPL | J290: Supplier | K290: Ascendas Panvel FTWZ Private Limited | L290: PU/26/SLS/OT/1356 | M290: 246779410327
A291: 2025-12-12 | B291: Sundry Creditors - SLSIPL | C291: 0 | D291: 29975.442 | E291: 1104445.2 | F291: Purchase Invoice | G291: Purchase Invoice | H291: PU/26/SLS/OT/1357 | I291: Storage Charges - Cargo - SLSIPL | J291: Supplier | K291: Ascendas Panvel FTWZ Private Limited | L291: PU/26/SLS/OT/1357 | M291: 246779410333
A292: 2025-12-12 | B292: Sundry Creditors - SLSIPL | C292: 0 | D292: 144772.57 | E292: 959672.68 | F292: Purchase Invoice | G292: Purchase Invoice | H292: PU/26/SLS/OT/1358 | I292: Storage Charges - Cargo - SLSIPL | J292: Supplier | K292: Ascendas Panvel FTWZ Private Limited | L292: PU/26/SLS/OT/1358 | M292: 246779410340
A293: 2025-12-12 | B293: Sundry Creditors - SLSIPL | C293: 0 | D293: 102103.26 | E293: 857569.43 | F293: Purchase Invoice | G293: Purchase Invoice | H293: PU/26/SLS/OT/1359 | I293: Storage Charges - Cargo - SLSIPL | J293: Supplier | K293: Ascendas Panvel FTWZ Private Limited | L293: PU/26/SLS/OT/1359 | M293: 246779410352
A294: 2025-12-12 | B294: Sundry Creditors - SLSIPL | C294: 0 | D294: 13859.78 | E294: 843709.65 | F294: Purchase Invoice | G294: Purchase Invoice | H294: PU/26/SLS/OT/1360 | I294: Storage Charges - Cargo - SLSIPL | J294: Supplier | K294: Ascendas Panvel FTWZ Private Limited | L294: PU/26/SLS/OT/1360 | M294: 246779410338
A295: 2025-12-12 | B295: Sundry Creditors - SLSIPL | C295: 0 | D295: 44681.825 | E295: 799027.82 | F295: Purchase Invoice | G295: Purchase Invoice | H295: PU/26/SLS/OT/1361 | I295: Storage Charges - Cargo - SLSIPL | J295: Supplier | K295: Ascendas Panvel FTWZ Private Limited | L295: PU/26/SLS/OT/1361 | M295: 246779410339
A296: 2025-12-12 | B296: Sundry Creditors - SLSIPL | C296: 500000 | D296: 0 | E296: 1299027.8 | F296: Payment Entry | G296: Pay | H296: BP/26/SLS/0958 | I296: 1395250393003 - Punjab National Bank - INR - SLSIPL | J296: Supplier | K296: Ascendas Panvel FTWZ Private Limited
A297: 2025-12-12 | B297: Sundry Creditors - SLSIPL | C297: 0 | D297: 2053.9 | E297: 1296973.9 | F297: Purchase Invoice | G297: Purchase Invoice | H297: PU/26/SLS/OT/1362-1 | I297: Handling Charges - Inbound (Exp) - SLSIPL | J297: Supplier | K297: Ascendas Panvel FTWZ Private Limited | L297: PU/26/SLS/OT/1362-1 | M297: 256779411807
A298: 2025-12-15 | B298: Sundry Creditors - SLSIPL | C298: 0 | D298: 6064.023 | E298: 1290909.9 | F298: Purchase Invoice | G298: Purchase Invoice | H298: PU/26/SLS/OT/1365 | I298: VOS Activity Charges Paid - SLSIPL | J298: Supplier | K298: Ascendas Panvel FTWZ Private Limited | L298: PU/26/SLS/OT/1365 | M298: 256779414743
A299: 2025-12-15 | B299: Sundry Creditors - SLSIPL | C299: 0 | D299: 1800.351 | E299: 1289109.5 | F299: Purchase Invoice | G299: Purchase Invoice | H299: PU/26/SLS/OT/1366-1 | I299: Weightment Charges Paid - SLSIPL | J299: Supplier | K299: Ascendas Panvel FTWZ Private Limited | L299: PU/26/SLS/OT/1366-1 | M299: 256779414748
A300: 2025-12-15 | B300: Sundry Creditors - SLSIPL | C300: 0 | D300: 14610.374 | E300: 1274499.2 | F300: Purchase Invoice | G300: Purchase Invoice | H300: PU/26/SLS/OT/1367 | I300: Handling Charges - Outbound (Exp) - SLSIPL | J300: Supplier | K300: Ascendas Panvel FTWZ Private Limited | L300: PU/26/SLS/OT/1367 | M300: 256779414758
A301: 2025-12-15 | B301: Sundry Creditors - SLSIPL | C301: 0 | D301: 45061.335 | E301: 1229437.8 | F301: Purchase Invoice | G301: Purchase Invoice | H301: PU/26/SLS/OT/1368 | I301: Storage Charges - Cargo - SLSIPL | J301: Supplier | K301: Ascendas Panvel FTWZ Private Limited | L301: PU/26/SLS/OT/1368 | M301: 256779414340
A302: 2025-12-15 | B302: Sundry Creditors - SLSIPL | C302: 0 | D302: 11782.092 | E302: 1217655.7 | F302: Purchase Invoice | G302: Purchase Invoice | H302: PU/26/SLS/OT/1369-1 | I302: Container Scanning Paid - SLSIPL | J302: Supplier | K302: Ascendas Panvel FTWZ Private Limited | L302: PU/26/SLS/OT/1369-1 | M302: 256779415939
A303: 2025-12-15 | B303: Sundry Creditors - SLSIPL | C303: 0 | D303: 2559.3799 | E303: 1215096.4 | F303: Purchase Invoice | G303: Purchase Invoice | H303: PU/26/SLS/OT/1370 | I303: VOS Activity Charges Paid - SLSIPL | J303: Supplier | K303: Ascendas Panvel FTWZ Private Limited | L303: PU/26/SLS/OT/1370 | M303: 256779415771
A304: 2025-12-15 | B304: Sundry Creditors - SLSIPL | C304: 0 | D304: 148540.36 | E304: 1066556 | F304: Purchase Invoice | G304: Purchase Invoice | H304: PU/26/SLS/OT/1371 | I304: Handling Charges - Inbound (Exp) - SLSIPL | J304: Supplier | K304: Ascendas Panvel FTWZ Private Limited | L304: PU/26/SLS/OT/1371 | M304: 256779415801
A305: 2025-12-15 | B305: Sundry Creditors - SLSIPL | C305: 0 | D305: 13522.745 | E305: 1053033.3 | F305: Purchase Invoice | G305: Purchase Invoice | H305: PU/26/SLS/OT/1376 | I305: Handling Charges - Outbound (Exp) - SLSIPL,MHE Charges Paid - SLSIPL | J305: Supplier | K305: Ascendas Panvel FTWZ Private Limited | L305: PU/26/SLS/OT/1376 | M305: 256779415456
A306: 2025-12-15 | B306: Sundry Creditors - SLSIPL | C306: 0 | D306: 8342.065 | E306: 1044691.2 | F306: Purchase Invoice | G306: Purchase Invoice | H306: PU/26/SLS/OT/1378 | I306: Transportation Charges Paid - SLSIPL,Handling Charges - Inbound (Exp) - SLSIPL | J306: Supplier | K306: Ascendas Panvel FTWZ Private Limited | L306: PU/26/SLS/OT/1378 | M306: 256779415444
A307: 2025-12-16 | B307: Sundry Creditors - SLSIPL | C307: 0 | D307: 2629.9005 | E307: 1042061.3 | F307: Purchase Invoice | G307: Purchase Invoice | H307: PU/26/SLS/OT/1379 | I307: MHE Charges Paid - SLSIPL,Handling Charges - Inbound (Exp) - SLSIPL | J307: Supplier | K307: Ascendas Panvel FTWZ Private Limited | L307: PU/26/SLS/OT/1379 | M307: 256779414968
A308: 2025-12-16 | B308: Sundry Creditors - SLSIPL | C308: 0 | D308: 201.2416 | E308: 1041860.1 | F308: Purchase Invoice | G308: Purchase Invoice | H308: PU/26/SLS/OT/1380 | I308: VOS Activity Charges Paid - SLSIPL | J308: Supplier | K308: Ascendas Panvel FTWZ Private Limited | L308: PU/26/SLS/OT/1380 | M308: 256779415263
... A365: 2025-12-29 | B365: Sundry Creditors - SLSIPL | C365: 7320 | D365: 73283.168 | E365: -2311611.1 | F365: Purchase Invoice | G365: Purchase Invoice | H365: PU/26/SLS/OT/1487 | I365: Storage Charges - Cargo - SLSIPL | J365: Supplier | K365: Ascendas Panvel FTWZ Private Limited | L365: PU/26/SLS/OT/1487, PU/26/SLS/OT/1487 | M365: 246779418620
A366: 2025-12-29 | B366: Sundry Creditors - SLSIPL | C366: 500000 | D366: 0 | E366: -1811611.1 | F366: Payment Entry | G366: Pay | H366: BP/26/SLS/1015 | I366: 1395250393003 - Punjab National Bank - INR - SLSIPL | J366: Supplier | K366: Ascendas Panvel FTWZ Private Limited
A367: 2025-12-29 | B367: Sundry Creditors - SLSIPL | C367: 6 | D367: 306 | E367: -1811911.1 | F367: Purchase Invoice | G367: Purchase Invoice | H367: PU/26/SLS/OT/1484-1 | I367: Weightment Charges Paid - SLSIPL | J367: Supplier | K367: Ascendas Panvel FTWZ Private Limited | L367: PU/26/SLS/OT/1484-1, PU/26/SLS/OT/1484-1 | M367: 256779418492
A368: 2025-12-30 | B368: Sundry Creditors - SLSIPL | C368: 176 | D368: 7046.061 | E368: -1818781.2 | F368: Purchase Invoice | G368: Purchase Invoice | H368: PU/26/SLS/OT/1488 | I368: Handling Charges - Outbound (Exp) - SLSIPL | J368: Supplier | K368: Ascendas Panvel FTWZ Private Limited | L368: PU/26/SLS/OT/1488, PU/26/SLS/OT/1488 | M368: 256779418437
A369: 2025-12-30 | B369: Sundry Creditors - SLSIPL | C369: 88 | D369: 2901.2856 | E369: -1821594.5 | F369: Purchase Invoice | G369: Purchase Invoice | H369: PU/26/SLS/OT/1489 | I369: Handling Charges - Inbound (Exp) - SLSIPL | J369: Supplier | K369: Ascendas Panvel FTWZ Private Limited | L369: PU/26/SLS/OT/1489, PU/26/SLS/OT/1489 | M369: 256779418428
A370: 2025-12-30 | B370: Sundry Creditors - SLSIPL | C370: 0 | D370: 1036.08 | E370: -1822630.6 | F370: Purchase Invoice | G370: Purchase Invoice | H370: PU/26/SLS/OT/1490 | I370: Handling Charges - Outbound (Exp) - SLSIPL | J370: Supplier | K370: Ascendas Panvel FTWZ Private Limited | L370: PU/26/SLS/OT/1490 | M370: 256779418351
A371: 2025-12-30 | B371: Sundry Creditors - SLSIPL | C371: 970 | D371: 46651.937 | E371: -1868312.5 | F371: Purchase Invoice | G371: Purchase Invoice | H371: PU/26/SLS/OT/1492 | I371: VOS Activity Charges Paid - SLSIPL | J371: Supplier | K371: Ascendas Panvel FTWZ Private Limited | L371: PU/26/SLS/OT/1492, PU/26/SLS/OT/1492 | M371: 256779418103
...

Sheet Customer Data Pivot
B1: =SUBTOTAL(9,B2:B381) -> 9479044.5 | C1: =SUBTOTAL(9,C2:C381) -> 10968319 | D1: =C1-B1 -> 1489274.5
A2: Posting Date | B2: Debit (INR) | C2: Credit (INR) | D2: Voucher Type | E2: Voucher Subtype | F2: Voucher No | G2: Against Account | H2: Against Voucher | I2: Supplier Invoice No | K2: Supplier Invoice No | L2: Sum of Debit (INR) | M2: Sum of Credit (INR)
A3: 2025-02-20 | B3: 0 | C3: 35554.52 | D3: Purchase Invoice | E3: Purchase Invoice | F3: PU/25/SLS/OT/1560 | G3: Fixed Storage Charges - ODC (Covered) - SLSIPL | H3: PU/25/SLS/OT/1560 | I3: 246779410049 | K3: 256779418075 | L3: 0 | M3: 1972
A4: 2025-02-20 | B4: 0 | C4: 35554.52 | D4: Purchase Invoice | E4: Purchase Invoice | F4: PU/25/SLS/OT/1561 | G4: Fixed Storage Charges - ODC (Covered) - SLSIPL | H4: PU/25/SLS/OT/1561 | I4: 246779410303 | K4: 246779410049 | L4: 0 | M4: 35554.52
A5: 2025-02-20 | B5: 0 | C5: 35554.52 | D5: Purchase Invoice | E5: Purchase Invoice | F5: PU/25/SLS/OT/1562 | G5: Fixed Storage Charges - ODC (Covered) - SLSIPL | H5: PU/25/SLS/OT/1562 | I5: 246779410117 | K5: 246779410072 | L5: 0 | M5: 35477
A6: 2025-02-20 | B6: 0 | C6: 35554.52 | D6: Purchase Invoice | E6: Purchase Invoice | F6: PU/25/SLS/OT/1563 | G6: Fixed Storage Charges - ODC (Covered) - SLSIPL | H6: PU/25/SLS/OT/1563 | I6: 246779410160 | K6: 246779410117 | L6: 0 | M6: 35554.52
A7: 2025-02-20 | B7: 0 | C7: 35554.52 | D7: Purchase Invoice | E7: Purchase Invoice | F7: PU/25/SLS/OT/1564 | G7: Fixed Storage Charges - ODC (Covered) - SLSIPL | H7: PU/25/SLS/OT/1564 | I7: 246779410203 | K7: 246779410160 | L7: 0 | M7: 35554.52
A8: 2025-02-20 | B8: 0 | C8: 35554.52 | D8: Purchase Invoice | E8: Purchase Invoice | F8: PU/25/SLS/OT/1565 | G8: Fixed Storage Charges - ODC (Covered) - SLSIPL | H8: PU/25/SLS/OT/1565 | I8: 246779410246 | K8: 246779410203 | L8: 0 | M8: 35554.52
A9: 2025-03-03 | B9: 0 | C9: 804 | D9: Purchase Invoice | E9: Purchase Invoice | F9: PU/25/SLS/OT/1672 | G9: Handling Charges - Outbound (Exp) - SLSIPL | H9: PU/25/SLS/OT/1672 | I9: 246779410613 | K9: 246779410246 | L9: 0 | M9: 35554.52
A10: 2025-03-03 | B10: 0 | C10: 1004 | D10: Purchase Invoice | E10: Purchase Invoice | F10: PU/25/SLS/OT/1673 | G10: Handling Charges - Outbound (Exp) - SLSIPL | H10: PU/25/SLS/OT/1673 | I10: 246779410612 | K10: 246779410303 | L10: 0 | M10: 35554.52
A11: 2025-03-03 | B11: 0 | C11: 402 | D11: Purchase Invoice | E11: Purchase Invoice | F11: PU/25/SLS/OT/1674 | G11: Handling Charges - Outbound (Exp) - SLSIPL | H11: PU/25/SLS/OT/1674 | I11: 246779410611 | K11: 246779410327 | L11: 0 | M11: 16480.711
A12: 2025-03-03 | B12: 0 | C12: 201 | D12: Purchase Invoice | E12: Purchase Invoice | F12: PU/25/SLS/OT/1675 | G12: Handling Charges - Outbound (Exp) - SLSIPL | H12: PU/25/SLS/OT/1675 | I12: 246779410610 | K12: 246779410333 | L12: 0 | M12: 29975.442
A13: 2025-03-03 | B13: 0 | C13: 804 | D13: Purchase Invoice | E13: Purchase Invoice | F13: PU/25/SLS/OT/1676 | G13: Handling Charges - Outbound (Exp) - SLSIPL | H13: PU/25/SLS/OT/1676 | I13: 246779410608 | K13: 246779410338 | L13: 0 | M13: 13859.78
A14: 2025-03-03 | B14: 0 | C14: 402 | D14: Purchase Invoice | E14: Purchase Invoice | F14: PU/25/SLS/OT/1677 | G14: Handling Charges - Outbound (Exp) - SLSIPL | H14: PU/25/SLS/OT/1677 | I14: 246779410607 | K14: 246779410339 | L14: 0 | M14: 44681.825
... A210: 2025-05-28 | B210: 0 | C210: 333696 | D210: Purchase Invoice | E210: Purchase Invoice | F210: PU/26/SLS/OT/0278 | G210: Storage Charges - Cargo - SLSIPL | H210: PU/26/SLS/OT/0278 | I210: 256779413899 | K210: 256779412461 | L210: 0 | M210: 10809
A211: 2025-05-30 | B211: 177773 | C211: 0 | D211: Payment Entry | E211: Pay | F211: BP/26/SLS/0192 | G211: 1395250393003 - Punjab National Bank - INR - SLSIPL | K211: 256779412468 | L211: 0 | M211: 14119
A212: 2025-06-04 | B212: 0 | C212: 9844 | D212: Purchase Invoice | E212: Purchase Invoice | F212: PU/26/SLS/OT/0358 | G212: Handling Charges - Outbound (Exp) - SLSIPL | H212: PU/26/SLS/OT/0358 | I212: 256779414165 | K212: 256779412613 | L212: 0 | M212: 3922
A213: 2025-06-04 | B213: 0 | C213: 8407 | D213: Purchase Invoice | E213: Purchase Invoice | F213: PU/26/SLS/OT/0360 | G213: Handling Charges - Outbound (Exp) - SLSIPL | H213: PU/26/SLS/OT/0360 | I213: 256779414216 | K213: 256779412655 | L213: 0 | M213: 2085
A214: 2025-06-04 | B214: 500946.52 | C214: 0 | D214: Payment Entry | E214: Pay | F214: BP/25/SLS/1225-1 | G214: 1395250393003 - Punjab National Bank - INR - SLSIPL | H214: PU/25/SLS/OT/1562, PU/25/SLS/OT/1720, PU/25/SLS/OT/1731, PU/25/SLS/OT/1721, PU/25/SLS/OT/1673 | K214: 256779412675 | L214: 0 | M214: 1447
A215: 2025-06-04 | B215: 0 | C215: 17313 | D215: Purchase Invoice | E215: Purchase Invoice | F215: PU/26/SLS/OT/0585 | G215: Scanning Charges - Inbound - SLSIPL | H215: PU/26/SLS/OT/0585 | I215: 256779414288 | K215: 256779412683 | L215: 0 | M215: 43195
A216: 2025-06-04 | B216: 0 | C216: 41769 | D216: Purchase Invoice | E216: Purchase Invoice | F216: PU/26/SLS/OT/0797 | G216: Handling Charges - Inbound (Exp) - SLSIPL,LCL Movment - Gate in Charge - SLSIPL,Transportation Charges Paid - SLSIPL,Eempty Container Return Charges Paid - SLSIPL | H216: PU/26/SLS/OT/0797 | I216: 256779414158 | K216: 256779412692 | L216: 0 | M216: 6084
A217: 2025-06-07 | B217: 0 | C217: 352792 | D217: Purchase Invoice | E217: Purchase Invoice | F217: PU/26/SLS/OT/0285 | G217: Storage Charges - Cargo - SLSIPL | H217: PU/26/SLS/OT/0285 | I217: 256779414242 | K217: 256779412777 | L217: 0 | M217: 7981
A218: 2025-06-10 | B218: 0 | C218: 35431 | D218: Purchase Invoice | E218: Purchase Invoice | F218: PU/26/SLS/OT/0357-1 | G218: Fixed Storage Charges - ODC (Covered) - SLSIPL | H218: PU/26/SLS/OT/0357-1 | I218: 256779414386 | K218: 256779412926 | L218: 0 | M218: 1878
A219: 2025-06-13 | B219: 700000 | C219: 0 | D219: Payment Entry | E219: Pay | F219: BP/26/SLS/0229 | G219: 1395250393003 - Punjab National Bank - INR - SLSIPL | K219: 256779412941 | L219: 0 | M219: 27408
A220: 2025-06-21 | B220: 700000 | C220: 0 | D220: Payment Entry | E220: Pay | F220: BP/26/SLS/0259 | G220: 1395250393003 - Punjab National Bank - INR - SLSIPL | K220: 256779412950 | L220: 0 | M220: 13211
A221: 2025-06-30 | B221: 700000 | C221: 0 | D221: Payment Entry | E221: Pay | F221: BP/26/SLS/0291 | G221: 1395250393003 - Punjab National Bank - INR - SLSIPL | K221: 256779413127 | L221: 0 | M221: 35097
A222: 2025-07-05 | B222: 700000 | C222: 0 | D222: Payment Entry | E222: Pay | F222: BP/26/SLS/0300 | G222: 1395250393003 - Punjab National Bank - INR - SLSIPL | K222: 256779413163 | L222: 0 | M222: 15927
A223: 2025-07-11 | B223: 700000 | C223: 0 | D223: Payment Entry | E223: Pay | F223: BP/26/SLS/0311 | G223: 1395250393003 - Punjab National Bank - INR - SLSIPL | K223: 256779413172 | L223: 0 | M223: 11810
A224: 2025-05-16 | B224: 0 | C224: 11797 | D224: Purchase Invoice | E224: Purchase Invoice | F224: PU/26/SLS/OT/0283 | G224: Container Scanning Paid - SLSIPL | H224: PU/26/SLS/OT/0283 | I224: 256779413283 | K224: 256779413184 | L224: 0 | M224: 11723.018
A225: 2025-07-16 | B225: 11798 | C225: 0 | D225: Purchase Invoice | E225: Credit Note | F225: SLS26/MF/DN/0013 | G225: Container Scanning Paid - SLSIPL | H225: PU/26/SLS/OT/0283 | I225: 256779413283 | K225: 256779413243 | L225: 0 | M225: 3623
A226: 2025-04-23 | B226: 0 | C226: 6084 | D226: Purchase Invoice | E226: Purchase Invoice | F226: PU/26/SLS/OT/0586-1 | G226: Scanning Charges - Inbound - SLSIPL | H226: PU/26/SLS/OT/0586-1 | I226: 256779412692 | K226: 256779413283 | L226: 11798 | M226: 11797
A227: 2025-04-16 | B227: 0 | C227: 12169 | D227: Purchase Invoice | E227: Purchase Invoice | F227: PU/26/SLS/OT/0587-1 | G227: Scanning Charges - Inbound - SLSIPL | H227: PU/26/SLS/OT/0587-1 | I227: 256779411917 | K227: 256779413357 | L227: 0 | M227: 1264
A228: 2025-04-03 | B228: 0 | C228: 114223 | D228: Purchase Invoice | E228: Purchase Invoice | F228: PU/26/SLS/OT/0611-1 | G228: Storage Charges - Cargo - SLSIPL | H228: PU/26/SLS/OT/0611-1 | I228: 256779410220 | K228: 256779413404 | L228: 0 | M228: 7129
A229: 2025-04-03 | B229: 0 | C229: 140649 | D229: Purchase Invoice | E229: Purchase Invoice | F229: PU/26/SLS/OT/0612 | G229: Storage Charges - Cargo - SLSIPL | H229: PU/26/SLS/OT/0612 | I229: 256779410010 | K229: 256779413405 | L229: 0 | M229: 3960
A230: 2025-07-16 | B230: 140649 | C230: 0 | D230: Purchase Invoice | E230: Credit Note | F230: SLS26/MF/DN/0016 | G230: Storage Charges - Cargo - SLSIPL | H230: PU/26/SLS/OT/0612 | I230: 256779410010 | K230: 256779413427 | L230: 0 | M230: 990
A231: 2025-04-03 | B231: 0 | C231: 55272 | D231: Purchase Invoice | E231: Purchase Invoice | F231: PU/26/SLS/OT/0613 | G231: Storage Charges - Cargo - SLSIPL | H231: PU/26/SLS/OT/0613 | I231: 256779410004 | K231: 256779413428 | L231: 0 | M231: 990
A232: 2025-07-16 | B232: 55272 | C232: 0 | D232: Purchase Invoice | E232: Credit Note | F232: SLS26/MF/DN/0017 | G232: Storage Charges - Cargo - SLSIPL | H232: PU/26/SLS/OT/0613 | I232: 256779410004 | K232: 256779413429 | L232: 0 | M232: 601
A233: 2025-07-16 | B233: 4786 | C233: 0 | D233: Purchase Invoice | E233: Credit Note | F233: SLS26/MF/DN/0007-2 | G233: Storage Charges - Cargo - SLSIPL | H233: SLS26/MF/DN/0007-2 | I233: 256779421381 | K233: 256779413430 | L233: 0 | M233: 1201
A234: 2025-04-01 | B234: 0 | C234: 45188 | D234: Purchase Invoice | E234: Purchase Invoice | F234: PU/26/SLS/OT/0588 | G234: Transportation Charges Paid - SLSIPL | H234: PU/26/SLS/OT/0588 | I234: 246779413845 | K234: 256779413486 | L234: 0 | M234: 1054
A235: 2025-07-16 | B235: 11955 | C235: 0 | D235: Purchase Invoice | E235: Credit Note | F235: SLS26/MF/DN/0004-1 | G235: Transportation Charges Paid - SLSIPL | H235: PU/26/SLS/OT/0588 | I235: 246779413845 | K235: 256779413837 | L235: 0 | M235: 12177
... A243: 2025-07-16 | B243: 8696 | C243: 173 | D243: Purchase Invoice | E243: Debit Note | F243: SLS26/MF/DN/0010-1 | G243: Container Scanning Paid - SLSIPL | H243: SLS26/MF/DN/0010-1, SLS26/MF/DN/0010-1 | I243: 256779421373 | K243: 256779414386 | L243: 0 | M243: 35431
A244: 2025-07-19 | B244: 700000 | C244: 0 | D244: Payment Entry | E244: Pay | F244: BP/26/SLS/0368 | G244: 1395250393003 - Punjab National Bank - INR - SLSIPL | K244: 256779414743 | L244: 0 | M244: 6064.023
A245: 2025-07-24 | B245: 0 | C245: 9368 | D245: Purchase Invoice | E245: Purchase Invoice | F245: PU/26/SLS/OT/0607 | G245: Handling Charges - Inbound (Exp) - SLSIPL | H245: PU/26/SLS/OT/0607 | I245: 256779415945 | K245: 256779414748 | L245: 0 | M245: 1800.351
A246: 2025-07-25 | B246: 350672 | C246: 0 | D246: Payment Entry | E246: Pay | F246: BP/26/SLS/0394 | G246: 1395250393003 - Punjab National Bank - INR - SLSIPL | K246: 256779414758 | L246: 0 | M246: 14610.374
A247: 2025-07-25 | B247: 0 | C247: 32007 | D247: Purchase Invoice | E247: Purchase Invoice | F247: PU/26/SLS/OT/0608 | G247: Storage Charges - Cargo - SLSIPL | H247: PU/26/SLS/OT/0608 | I247: 256779415967 | K247: 256779414768 | L247: 0 | M247: 1492.1116
A248: 2025-07-25 | B248: 0 | C248: 9348 | D248: Purchase Invoice | E248: Purchase Invoice | F248: PU/26/SLS/OT/0609 | G248: Storage Charges - Cargo - SLSIPL | H248: PU/26/SLS/OT/0609 | I248: 256779415970 | K248: 256779414829 | L248: 0 | M248: 8595.767
A249: 2025-07-25 | B249: 0 | C249: 196 | D249: Purchase Invoice | E249: Purchase Invoice | F249: PU/26/SLS/OT/0610 | G249: VOS Activity Charges Paid - SLSIPL | H249: PU/26/SLS/OT/0610 | I249: 256779415995 | K249: 256779414878 | L249: 0 | M249: 2642.8006
A250: 2025-07-16 | B250: 31723 | C250: 0 | D250: Purchase Invoice | E250: Credit Note | F250: SLS26/MF/DN/0009 | G250: Container Scanning Paid - SLSIPL | H250: PU/25/SLS/OT/1822 | I250: 246779413827 | K250: 256779414890 | L250: 0 | M250: 91401.512
A251: 2025-07-31 | B251: 15778 | C251: 0 | D251: Purchase Invoice | E251: Credit Note | F251: SLS26/MF/DN/0020-1 | G251: Storage Charges - Cargo - SLSIPL | H251: SLS26/MF/DN/0020-1 | I251: 246779410348/256779421380 | K251: 256779414944 | L251: 0 | M251: 35324.775
A252: 2025-03-31 | B252: 0 | C252: 18610 | D252: Purchase Invoice | E252: Purchase Invoice | F252: PU/25/SLS/OT/1821 | G252: Container Scanning Paid - SLSIPL | H252: PU/25/SLS/OT/1821 | I252: 246779413816 | K252: 256779414968 | L252: 0 | M252: 2629.9005
A253: 2025-07-31 | B253: 36410 | C253: 0 | D253: Purchase Invoice | E253: Credit Note | F253: SLS26/MF/DN/0022-1 | G253: Container Scanning Paid - SLSIPL | H253: SLS26/MF/DN/0022-1 | I253: 246779411278/256779421385 | K253: 256779414975 | L253: 0 | M253: 4562.3355
A254: 2025-07-31 | B254: 15401 | C254: 0 | D254: Purchase Invoice | E254: Credit Note | F254: SLS26/MF/DN/0021-1 | G254: Fixed Storage Charges - ODC (Covered) - SLSIPL | H254: SLS26/MF/DN/0021-1 | I254: 256779421382/246779413701 | K254: 256779415048 | L254: 0 | M254: 552.9843
A255: 2025-07-16 | B255: 18611 | C255: 0 | D255: Purchase Invoice | E255: Credit Note | F255: SLS26/MF/DN/0008 | G255: Container Scanning Paid - SLSIPL | H255: PU/25/SLS/OT/1821 | I255: 246779413816 | K255: 256779415198 | L255: 0 | M255: 257812.81
A256: 2025-08-08 | B256: 0 | C256: 9124 | D256: Purchase Invoice | E256: Purchase Invoice | F256: PU/26/SLS/OT/0798 | G256: Handling Charges - Outbound (Exp) - SLSIPL | H256: PU/26/SLS/OT/0798 | I256: 256779416223 | K256: 256779415263 | L256: 0 | M256: 201.2416
A257: 2025-08-08 | B257: 0 | C257: 4755 | D257: Purchase Invoice | E257: Purchase Invoice | F257: PU/26/SLS/OT/0800 | G257: Handling Charges - Outbound (Exp) - SLSIPL | H257: PU/26/SLS/OT/0800 | I257: 256779416256 | K257: 256779415444 | L257: 0 | M257: 8342.065
A258: 2025-08-08 | B258: 0 | C258: 462828 | D258: Purchase Invoice | E258: Purchase Invoice | F258: PU/26/SLS/OT/0796 | G258: Storage Charges - SLSIPL | H258: PU/26/SLS/OT/0796 | I258: 256779416088 | K258: 256779415456 | L258: 0 | M258: 13522.745
A259: 2025-08-20 | B259: 0 | C259: 4790 | D259: Purchase Invoice | E259: Purchase Invoice | F259: PU/26/SLS/OT/0792 | G259: Handling Charges - Outbound (Exp) - SLSIPL,MHE Charges Paid - SLSIPL | H259: PU/26/SLS/OT/0792 | I259: 256779416615 | K259: 256779415771 | L259: 0 | M259: 2559.3799
A260: 2025-08-20 | B260: 0 | C260: 6981 | D260: Purchase Invoice | E260: Purchase Invoice | F260: PU/26/SLS/OT/0793 | G260: VOS Activity Charges Paid - SLSIPL | H260: PU/26/SLS/OT/0793 | I260: 256779416809 | K260: 256779415801 | L260: 0 | M260: 148540.36
A261: 2025-08-20 | B261: 0 | C261: 971 | D261: Purchase Invoice | E261: Purchase Invoice | F261: PU/26/SLS/OT/0801 | G261: Loose Loading Handling - SLSIPL | H261: PU/26/SLS/OT/0801 | I261: 256779416878 | K261: 256779415939 | L261: 0 | M261: 11782.092
A262: 2025-08-20 | B262: 0 | C262: 11922 | D262: Purchase Invoice | E262: Purchase Invoice | F262: PU/26/SLS/OT/0795 | G262: Handling Charges - Inbound (Exp) - SLSIPL,Gate in Charges - Inbound - SLSIPL | H262: PU/26/SLS/OT/0795 | I262: 256779416844 | K262: 256779415945 | L262: 0 | M262: 9368
A263: 2025-08-20 | B263: 0 | C263: 1463 | D263: Purchase Invoice | E263: Purchase Invoice | F263: PU/26/SLS/OT/0794 | G263: LCL Movment - Gate in Charge - SLSIPL,Handling Charges - Inbound (Exp) - SLSIPL | H263: PU/26/SLS/OT/0794 | I263: 256779416603 | K263: 256779415967 | L263: 0 | M263: 32007
A264: 2025-07-16 | B264: 0 | C264: 163631 | D264: Purchase Invoice | E264: Purchase Invoice | F264: PU/26/SLS/OT/0614-1 | G264: Storage Charges - Cargo - SLSIPL | H264: PU/26/SLS/OT/0614-1 | I264: 246779413796 | K264: 256779415970 | L264: 0 | M264: 9348
A265: 2025-04-01 | B265: 0 | C265: 19429 | D265: Purchase Invoice | E265: Purchase Invoice | F265: PU/26/SLS/OT/0590 | G265: Storage Charges - Cargo - SLSIPL | H265: PU/26/SLS/OT/0590 | I265: 246779413705 | K265: 256779415995 | L265: 0 | M265: 196
A266: 2025-07-16 | B266: 19430 | C266: 0 | D266: Purchase Invoice | E266: Credit Note | F266: SLS26/MF/DN/0006 | G266: Storage Charges - Cargo - SLSIPL | H266: PU/26/SLS/OT/0590 | I266: 246779413705 | K266: 256779416054 | L266: 0 | M266: 35336.872
... A272: 2025-07-16 | B272: 20874 | C272: 0 | D272: Purchase Invoice | E272: Credit Note | F272: SLS26/MF/DN/0014 | G272: Container Scanning Paid - SLSIPL | H272: PU/25/SLS/OT/1820 | I272: 246779411326 | K272: 256779416538 | L272: 0 | M272: 27395.431
A273: 2025-10-09 | B273: 500000 | C273: 0 | D273: Payment Entry | E273: Pay | F273: BP/26/SLS/0710 | G273: 1395250393003 - Punjab National Bank - INR - SLSIPL | H273: PU/26/SLS/OT/0797, PU/26/SLS/OT/0357-1, PU/26/SLS/OT/0610, PU/26/SLS/OT/0796, PU/26/SLS/OT/0794 | K273: 256779416544 | L273: 0 | M273: 23117.154
A274: 2025-10-10 | B274: 108564 | C274: 0 | D274: Payment Entry | E274: Pay | F274: BP/26/SLS/0711 | G274: 1395250393003 - Punjab National Bank - INR - SLSIPL | H274: PU/26/SLS/OT/0797, PU/26/SLS/OT/0607, PU/26/SLS/OT/0608, PU/26/SLS/OT/0609, PU/26/SLS/OT/0798, PU/26/SLS/OT/0800, PU/26/SLS/OT/0792, PU/26/SLS/OT/0793, PU/26/SLS/OT/0795, PU/26/SLS/OT/0801 | K274: 256779416546 | L274: 0 | M274: 21929.078
A275: 2025-10-18 | B275: 500000 | C275: 0 | D275: Payment Entry | E275: Pay | F275: BP/26/SLS/0758 | G275: 1395250393003 - Punjab National Bank - INR - SLSIPL | K275: 256779416603 | L275: 0 | M275: 1463
A276: 2025-10-29 | B276: 300000 | C276: 0 | D276: Payment Entry | E276: Pay | F276: BP/26/SLS/0765 | G276: 1395250393003 - Punjab National Bank - INR - SLSIPL | K276: 256779416615 | L276: 0 | M276: 4790
A277: 2025-11-01 | B277: 500000 | C277: 0 | D277: Payment Entry | E277: Pay | F277: BP/26/SLS/0801 | G277: 1395250393003 - Punjab National Bank - INR - SLSIPL | K277: 256779416809 | L277: 0 | M277: 6981
A278: 2025-12-12 | B278: 0 | C278: 16480.711 | D278: Purchase Invoice | E278: Purchase Invoice | F278: PU/26/SLS/OT/1356 | G278: Storage Charges - Cargo - SLSIPL | H278: PU/26/SLS/OT/1356 | I278: 246779410327 | K278: 256779416844 | L278: 0 | M278: 11922
A279: 2025-12-12 | B279: 0 | C279: 29975.442 | D279: Purchase Invoice | E279: Purchase Invoice | F279: PU/26/SLS/OT/1357 | G279: Storage Charges - Cargo - SLSIPL | H279: PU/26/SLS/OT/1357 | I279: 246779410333 | K279: 256779416878 | L279: 0 | M279: 971
A280: 2025-12-12 | B280: 0 | C280: 144772.57 | D280: Purchase Invoice | E280: Purchase Invoice | F280: PU/26/SLS/OT/1358 | G280: Storage Charges - Cargo - SLSIPL | H280: PU/26/SLS/OT/1358 | I280: 246779410340 | K280: 256779416911 | L280: 0 | M280: 3487.4461
A281: 2025-12-12 | B281: 0 | C281: 102103.26 | D281: Purchase Invoice | E281: Purchase Invoice | F281: PU/26/SLS/OT/1359 | G281: Storage Charges - Cargo - SLSIPL | H281: PU/26/SLS/OT/1359 | I281: 246779410352 | K281: 256779416948 | L281: 0 | M281: 1233.9521
A282: 2025-12-12 | B282: 0 | C282: 13859.78 | D282: Purchase Invoice | E282: Purchase Invoice | F282: PU/26/SLS/OT/1360 | G282: Storage Charges - Cargo - SLSIPL | H282: PU/26/SLS/OT/1360 | I282: 246779410338 | K282: 256779417084 | L282: 0 | M282: 695663.66
A283: 2025-12-12 | B283: 0 | C283: 44681.825 | D283: Purchase Invoice | E283: Purchase Invoice | F283: PU/26/SLS/OT/1361 | G283: Storage Charges - Cargo - SLSIPL | H283: PU/26/SLS/OT/1361 | I283: 246779410339 | K283: 256779417160 | L283: 0 | M283: 1247.0792
A284: 2025-12-12 | B284: 500000 | C284: 0 | D284: Payment Entry | E284: Pay | F284: BP/26/SLS/0958 | G284: 1395250393003 - Punjab National Bank - INR - SLSIPL | K284: 256779417166 | L284: 0 | M284: 59881.68
A285: 2025-12-12 | B285: 0 | C285: 2053.9 | D285: Purchase Invoice | E285: Purchase Invoice | F285: PU/26/SLS/OT/1362-1 | G285: Handling Charges - Inbound (Exp) - SLSIPL | H285: PU/26/SLS/OT/1362-1 | I285: 256779411807 | K285: 256779417173 | L285: 0 | M285: 58594.344
A286: 2025-12-15 | B286: 0 | C286: 6064.023 | D286: Purchase Invoice | E286: Purchase Invoice | F286: PU/26/SLS/OT/1365 | G286: VOS Activity Charges Paid - SLSIPL | H286: PU/26/SLS/OT/1365 | I286: 256779414743 | K286: 256779417261 | L286: 0 | M286: 1992.7012
A287: 2025-12-15 | B287: 0 | C287: 1800.351 | D287: Purchase Invoice | E287: Purchase Invoice | F287: PU/26/SLS/OT/1366-1 | G287: Weightment Charges Paid - SLSIPL | H287: PU/26/SLS/OT/1366-1 | I287: 256779414748 | K287: 256779417286 | L287: 0 | M287: 90131.008
A288: 2025-12-15 | B288: 0 | C288: 14610.374 | D288: Purchase Invoice | E288: Purchase Invoice | F288: PU/26/SLS/OT/1367 | G288: Handling Charges - Outbound (Exp) - SLSIPL | H288: PU/26/SLS/OT/1367 | I288: 256779414758 | K288: 256779417324 | L288: 0 | M288: 4231.3179
A289: 2025-12-15 | B289: 0 | C289: 45061.335 | D289: Purchase Invoice | E289: Purchase Invoice | F289: PU/26/SLS/OT/1368 | G289: Storage Charges - Cargo - SLSIPL | H289: PU/26/SLS/OT/1368 | I289: 256779414340 | K289: 256779417373 | L289: 0 | M289: 33482.011
A290: 2025-12-15 | B290: 0 | C290: 11782.092 | D290: Purchase Invoice | E290: Purchase Invoice | F290: PU/26/SLS/OT/1369-1 | G290: Container Scanning Paid - SLSIPL | H290: PU/26/SLS/OT/1369-1 | I290: 256779415939 | K290: 256779417410 | L290: 0 | M290: 29303.298
A291: 2025-12-15 | B291: 0 | C291: 2559.3799 | D291: Purchase Invoice | E291: Purchase Invoice | F291: PU/26/SLS/OT/1370 | G291: VOS Activity Charges Paid - SLSIPL | H291: PU/26/SLS/OT/1370 | I291: 256779415771 | K291: 256779417442 | L291: 0 | M291: 545.2142
A292: 2025-12-15 | B292: 0 | C292: 148540.36 | D292: Purchase Invoice | E292: Purchase Invoice | F292: PU/26/SLS/OT/1371 | G292: Handling Charges - Inbound (Exp) - SLSIPL | H292: PU/26/SLS/OT/1371 | I292: 256779415801 | K292: 256779417489 | L292: 0 | M292: 42087.392
A293: 2025-12-15 | B293: 0 | C293: 13522.745 | D293: Purchase Invoice | E293: Purchase Invoice | F293: PU/26/SLS/OT/1376 | G293: Handling Charges - Outbound (Exp) - SLSIPL,MHE Charges Paid - SLSIPL | H293: PU/26/SLS/OT/1376 | I293: 256779415456 | K293: 256779417525 | L293: 0 | M293: 26724.251
A294: 2025-12-15 | B294: 0 | C294: 8342.065 | D294: Purchase Invoice | E294: Purchase Invoice | F294: PU/26/SLS/OT/1378 | G294: Transportation Charges Paid - SLSIPL,Handling Charges - Inbound (Exp) - SLSIPL | H294: PU/26/SLS/OT/1378 | I294: 256779415444 | K294: 256779417566 | L294: 0 | M294: 6432.3033
A295: 2025-12-16 | B295: 0 | C295: 2629.9005 | D295: Purchase Invoice | E295: Purchase Invoice | F295: PU/26/SLS/OT/1379 | G295: MHE Charges Paid - SLSIPL,Handling Charges - Inbound (Exp) - SLSIPL | H295: PU/26/SLS/OT/1379 | I295: 256779414968 | K295: 256779417582 | L295: 0 | M295: 6896.1292
A296: 2025-12-16 | B296: 0 | C296: 201.2416 | D296: Purchase Invoice | E296: Purchase Invoice | F296: PU/26/SLS/OT/1380 | G296: VOS Activity Charges Paid - SLSIPL | H296: PU/26/SLS/OT/1380 | I296: 256779415263 | K296: 256779417594 | L296: 0 | M296: 1028.2935
... A337: 2025-12-17 | B337: 0 | C337: 5909.4276 | D337: Purchase Invoice | E337: Purchase Invoice | F337: PU/26/SLS/OT/1435 | G337: Handling Charges - Outbound (Exp) - SLSIPL | H337: PU/26/SLS/OT/1435 | I337: 256779419172 | K337: 256779421383 | L337: 12467 | M337: 0
A338: 2025-12-17 | B338: 0 | C338: 39821.534 | D338: Purchase Invoice | E338: Purchase Invoice | F338: PU/26/SLS/OT/1437 | G338: Storage Charges - Cargo - SLSIPL | H338: PU/26/SLS/OT/1437 | I338: 256779419556 | K338: 256779440041 | L338: 4174 | M338: 41446.745 | N338: =L338/M338 -> 0.10070755
A339: 2025-12-17 | B339: 0 | C339: 29234.726 | D339: Purchase Invoice | E339: Purchase Invoice | F339: PU/26/SLS/OT/1439 | G339: Transportation Charges Paid - SLSIPL,Handling Charges - Inbound (Exp) - SLSIPL | H339: PU/26/SLS/OT/1439 | I339: 256779419588 | K339: 256779440069 | L339: 0 | M339: 1066.231 | N339: =L339/M339 -> 0
A340: 2025-12-17 | B340: 0 | C340: 897.6346 | D340: Purchase Invoice | E340: Purchase Invoice | F340: PU/26/SLS/OT/1440 | G340: Loose Loading Handling - SLSIPL | H340: PU/26/SLS/OT/1440 | I340: 256779419628 | K340: 256779440118 | L340: 181 | M340: 8983.085 | N340: =L340/M340 -> 0.02014898
A341: 2025-12-18 | B341: 0 | C341: 20693.117 | D341: Purchase Invoice | E341: Purchase Invoice | F341: PU/26/SLS/OT/1447 | G341: VOS Activity Charges Paid - SLSIPL | H341: PU/26/SLS/OT/1447 | I341: 256779419465 | K341: 256779440122 | L341: 181 | M341: 11185.421 | N341: =L341/M341 -> 0.016181779
A342: 2025-12-18 | B342: 0 | C342: 14016.3 | D342: Purchase Invoice | E342: Purchase Invoice | F342: PU/26/SLS/OT/1448 | G342: Weightment Charges Paid - SLSIPL | H342: PU/26/SLS/OT/1448 | I342: 256779419476 | K342: 256779440210 | L342: 181 | M342: 7063.8672 | N342: =L342/M342 -> 0.025623358
A343: 2025-12-18 | B343: 0 | C343: 7761.899 | D343: Purchase Invoice | E343: Purchase Invoice | F343: PU/26/SLS/OT/1449 | G343: Transportation Charges Paid - SLSIPL,Handling Charges - Inbound (Exp) - SLSIPL | H343: PU/26/SLS/OT/1449 | I343: 256779419534 | K343: 256779440383 | L343: 90 | M343: 4904.3774 | N343: =L343/M343 -> 0.018350953
A344: 2025-12-18 | B344: 0 | C344: 9417.2428 | D344: Purchase Invoice | E344: Purchase Invoice | F344: PU/26/SLS/OT/1452 | G344: Handling Charges - Outbound (Exp) - SLSIPL,MHE Charges Paid - SLSIPL | H344: PU/26/SLS/OT/1452 | I344: 256779419547 | K344: 256779440392 | L344: 1089 | M344: 11313.937 | N344: =L344/M344 -> 0.096252967
A345: 2025-12-18 | B345: 0 | C345: 27787.07 | D345: Purchase Invoice | E345: Purchase Invoice | F345: PU/26/SLS/OT/1453 | G345: Transportation Charges Paid - SLSIPL,Storage Charges - Cargo - SLSIPL | H345: PU/26/SLS/OT/1453 | I345: 256779419364 | K345: 256779440394 | L345: 1815 | M345: 18211.378 | N345: =L345/M345 -> 0.099662969
A346: 2025-12-18 | B346: 0 | C346: 11723.018 | D346: Purchase Invoice | E346: Purchase Invoice | F346: PU/26/SLS/OT/1455 | G346: Storage Charges - Cargo - SLSIPL | H346: PU/26/SLS/OT/1455 | I346: 256779413184 | K346: 256779440413 | L346: 181 | M346: 8983.0846 | N346: =L346/M346 -> 0.020148981
A347: 2025-12-19 | B347: 0 | C347: 61159.634 | D347: Purchase Invoice | E347: Purchase Invoice | F347: PU/26/SLS/OT/1457 | G347: Transportation Charges Paid - SLSIPL,Handling Charges - Inbound (Exp) - SLSIPL | H347: PU/26/SLS/OT/1457 | I347: 256779419867 | K347: 256779440429 | L347: 91 | M347: 6141.7526 | N347: =L347/M347 -> 0.014816618
...
