Workbook

Sheet Customer Ledger
A1: Posting Date | B1: Debit (INR) | C1: Credit (INR) | D1: Balance (INR) | E1: Voucher Subtype | F1: Voucher No | G1: Against Account | H1: Against Voucher | I1: Supplier Invoice No | K1: Supplier Invoice No | L1: Sum of Debit (INR) | M1: Sum of Credit (INR) | O1: Supplier Invoice No | P1: Sum of Debit (INR) | Q1: Sum of Credit (INR)
A2: 2025-02-20 | B2: 0 | C2: 35554.52 | D2: -35554.52 | E2: Purchase Invoice | F2: PU/25/SLS/OT/1560 | G2: Fixed Storage Charges - ODC (Covered) - SLSIPL | H2: PU/25/SLS/OT/1560 | I2: 246779410049 | K2: 25677941807 | L2: 0 | M2: 1972 | O2: 25677941807 | P2: 0 | Q2: 1972
A3: 2025-02-20 | B3: 0 | C3: 35554.52 | D3: -71109.04 | E3: Purchase Invoice | F3: PU/25/SLS/OT/1561 | G3: Fixed Storage Charges - ODC (Covered) - SLSIPL | H3: PU/25/SLS/OT/1561 | I3: 246779410303 | K3: 246779410049 | L3: 0 | M3: 35554.52 | O3: 246779410049 | P3: 0 | Q3: 35554.52
A4: 2025-02-20 | B4: 0 | C4: 35554.52 | D4: -106663.56 | E4: Purchase Invoice | F4: PU/25/SLS/OT/1562 | G4: Fixed Storage Charges - ODC (Covered) - SLSIPL | H4: PU/25/SLS/OT/1562 | I4: 246779410117 | K4: 246779410072 | L4: 0 | M4: 35477 | O4: 246779410072 | P4: 0 | Q4: 35477
A5: 2025-02-20 | B5: 0 | C5: 35554.52 | D5: -142218.08 | E5: Purchase Invoice | F5: PU/25/SLS/OT/1563 | G5: Fixed Storage Charges - ODC (Covered) - SLSIPL | H5: PU/25/SLS/OT/1563 | I5: 246779410160 | K5: 246779410117 | L5: 0 | M5: 35554.52 | O5: 246779410117 | P5: 0 | Q5: 35554.52
A6: 2025-02-20 | B6: 0 | C6: 35554.52 | D6: -177772.6 | E6: Purchase Invoice | F6: PU/25/SLS/OT/1564 | G6: Fixed Storage Charges - ODC (Covered) - SLSIPL | H6: PU/25/SLS/OT/1564 | I6: 246779410203 | K6: 246779410160 | L6: 0 | M6: 35554.52 | O6: 246779410160 | P6: 0 | Q6: 35554.52
A7: 2025-02-20 | B7: 0 | C7: 35554.52 | D7: -213327.12 | E7: Purchase Invoice | F7: PU/25/SLS/OT/1565 | G7: Fixed Storage Charges - ODC (Covered) - SLSIPL | H7: PU/25/SLS/OT/1565 | I7: 246779410246 | K7: 246779410203 | L7: 0 | M7: 35554.52 | O7: 246779410203 | P7: 0 | Q7: 35554.52
A8: 2025-03-03 | B8: 0 | C8: 804 | D8: -214131.12 | E8: Purchase Invoice | F8: PU/25/SLS/OT/1672 | G8: Handling Charges - Outbound (Exp) - SLSIPL | H8: PU/25/SLS/OT/1672 | I8: 246779410613 | K8: 246779410246 | L8: 0 | M8: 35554.52 | O8: 246779410246 | P8: 0 | Q8: 35554.52
A9: 2025-03-03 | B9: 0 | C9: 1004 | D9: -215135.12 | E9: Purchase Invoice | F9: PU/25/SLS/OT/1673 | G9: Handling Charges - Outbound (Exp) - SLSIPL | H9: PU/25/SLS/OT/1673 | I9: 246779410612 | K9: 246779410303 | L9: 0 | M9: 35554.52 | O9: 246779410303 | P9: 0 | Q9: 35554.52
A10: 2025-03-03 | B10: 0 | C10: 402 | D10: -215537.12 | E10: Purchase Invoice | F10: PU/25/SLS/OT/1674 | G10: Handling Charges - Outbound (Exp) - SLSIPL | H10: PU/25/SLS/OT/1674 | I10: 246779410611 | K10: 246779410327 | L10: 0 | M10: 16480.711 | O10: 246779410327 | P10: 0 | Q10: 16480.711
A11: 2025-03-03 | B11: 0 | C11: 201 | D11: -215738.12 | E11: Purchase Invoice | F11: PU/25/SLS/OT/1675 | G11: Handling Charges - Outbound (Exp) - SLSIPL | H11: PU/25/SLS/OT/1675 | I11: 246779410610 | K11: 246779410333 | L11: 0 | M11: 29975.442 | O11: 246779410333 | P11: 0 | Q11: 29975.442
A12: 2025-03-03 | B12: 0 | C12: 804 | D12: -216542.12 | E12: Purchase Invoice | F12: PU/25/SLS/OT/1676 | G12: Handling Charges - Outbound (Exp) - SLSIPL | H12: PU/25/SLS/OT/1676 | I12: 246779410608 | K12: 246779410338 | L12: 0 | M12: 13859.78 | O12: 246779410338 | P12: 0 | Q12: 13859.78
A13: 2025-03-03 | B13: 0 | C13: 402 | D13: -216944.12 | E13: Purchase Invoice | F13: PU/25/SLS/OT/1677 | G13: Handling Charges - Outbound (Exp) - SLSIPL | H13: PU/25/SLS/OT/1677 | I13: 246779410607 | K13: 246779410339 | L13: 0 | M13: 44681.825 | O13: 246779410339 | P13: 0 | Q13: 44681.825
... A108: 2025-07-11 | B108: 0 | C108: 151725 | D108: -1632350.6 | E108: Purchase Invoice | F108: PU/26/SLS/OT/0415-1 | G108: Storage Charges - Cargo - SLSIPL | H108: PU/26/SLS/OT/0415-1 | I108: 246779410348 | K108: 246779411249 | L108: 0 | M108: 13737 | O108: 246779411249 | P108: 0 | Q108: 13737
A109: 2025-10-07 | B109: 15778 | C109: 15778 | D109: -757662.6 | E109: Debit Note | F109: SJ/25/GEA/1104 | H109: PU/26/SLS/OT/0415-1, SLS26/MF/DN/0020-1 | I109: Debit Note | K109: 246779411250 | L109: 0 | M109: 1599 | O109: 246779411250 | P109: 0 | Q109: 1599
A110: 2025-04-01 | B110: 0 | C110: 59624 | D110: -3015382.1 | E110: Purchase Invoice | F110: PU/26/SLS/OT/0591-1 | G110: Storage Charges - Cargo - SLSIPL | H110: PU/26/SLS/OT/0591-1 | I110: 246779410360 | K110: 246779411251 | L110: 0 | M110: 1599 | O110: 246779411251 | P110: 0 | Q110: 1599
A111: 2025-03-31 | B111: 0 | C111: 31723 | D111: -2522653.1 | E111: Purchase Invoice | F111: PU/25/SLS/OT/1823 | G111: Container Scanning Paid - SLSIPL | H111: PU/25/SLS/OT/1823 | I111: 246779413753 | K111: 246779411252 | L111: 0 | M111: 1907 | O111: 246779411252 | P111: 0 | Q111: 1907
A112: 2025-03-31 | B112: 0 | C112: 191 | D112: -2522844.1 | E112: Purchase Invoice | F112: PU/25/SLS/OT/1824 | G112: Handling Charges - Outbound (Exp) - SLSIPL | H112: PU/25/SLS/OT/1824 | I112: 246779413762 | K112: 246779411278 | L112: 0 | M112: 44602 | O112: 246779411278 | P112: 0 | Q112: 44602
A113: 2025-03-31 | B113: 0 | C113: 3064 | D113: -2525908.1 | E113: Purchase Invoice | F113: PU/25/SLS/OT/1825 | G113: Handling Charges - Outbound (Exp) - SLSIPL | H113: PU/25/SLS/OT/1825 | I113: 246779413745 | K113: 246779411300 | L113: 0 | M113: 33376 | O113: 246779411300 | P113: 0 | Q113: 33376
A114: 2025-03-31 | B114: 0 | C114: 3448 | D114: -2529356.1 | E114: Purchase Invoice | F114: PU/25/SLS/OT/1826 | G114: Handling Charges - Outbound (Exp) - SLSIPL | H114: PU/25/SLS/OT/1826 | I114: 246779413734 | K114: 246779411314 | L114: 0 | M114: 8522 | O114: 246779411314 | P114: 0 | Q114: 8522
A115: 2025-03-31 | B115: 0 | C115: 6513 | D115: -2535869.1 | E115: Purchase Invoice | F115: PU/25/SLS/OT/1827 | G115: Handling Charges - Outbound (Exp) - SLSIPL | H115: PU/25/SLS/OT/1827 | I115: 246779413736 | K115: 246779411326 | L115: 0 | M115: 20874 | O115: 246779411326 | P115: 0 | Q115: 20874
A116: 2025-03-31 | B116: 0 | C116: 1724 | D116: -2537593.1 | E116: Purchase Invoice | F116: PU/25/SLS/OT/1828 | G116: Handling Charges - Outbound (Exp) - SLSIPL | H116: PU/25/SLS/OT/1828 | I116: 246779413739 | K116: 246779411339 | L116: 0 | M116: 17857 | O116: 246779411339 | P116: 0 | Q116: 17857
A117: 2025-03-31 | B117: 0 | C117: 1149 | D117: -2538742.1 | E117: Purchase Invoice | F117: PU/25/SLS/OT/1829 | G117: Handling Charges - Outbound (Exp) - SLSIPL | H117: PU/25/SLS/OT/1829 | I117: 246779413742 | K117: 246779411448 | L117: 0 | M117: 1161 | O117: 246779411448 | P117: 0 | Q117: 1161
A118: 2025-03-31 | B118: 0 | C118: 191 | D118: -2538933.1 | E118: Purchase Invoice | F118: PU/25/SLS/OT/1830 | G118: Handling Charges - Outbound (Exp) - SLSIPL | H118: PU/25/SLS/OT/1830 | I118: 246779413692 | K118: 246779411619 | L118: 0 | M118: 143412 | O118: 246779411619 | P118: 0 | Q118: 143412
A119: 2025-03-31 | B119: 0 | C119: 6896 | D119: -2545829.1 | E119: Purchase Invoice | F119: PU/25/SLS/OT/1831 | G119: Handling Charges - Outbound (Exp) - SLSIPL | H119: PU/25/SLS/OT/1831 | I119: 246779413693 | K119: 246779411620 | L119: 0 | M119: 5816 | O119: 246779411620 | P119: 0 | Q119: 5816
A120: 2025-03-31 | B120: 0 | C120: 3448 | D120: -2549277.1 | E120: Purchase Invoice | F120: PU/25/SLS/OT/1832 | G120: Handling Charges - Outbound (Exp) - SLSIPL | H120: PU/25/SLS/OT/1832 | I120: 246779413694 | K120: 246779411755 | L120: 0 | M120: 5816 | O120: 246779411755 | P120: 0 | Q120: 5816
A121: 2025-03-31 | B121: 0 | C121: 191 | D121: -2549468.1 | E121: Purchase Invoice | F121: PU/25/SLS/OT/1833 | G121: Handling Charges - Outbound (Exp) - SLSIPL | H121: PU/25/SLS/OT/1833 | I121: 246779413695 | K121: 246779411756 | L121: 0 | M121: 4339 | O121: 246779411756 | P121: 0 | Q121: 4339
... A137: 2025-03-31 | B137: 0 | C137: 994 | D137: -2580563.1 | E137: Purchase Invoice | F137: PU/25/SLS/OT/1853 | G137: Handling Charges - Outbound (Exp) - SLSIPL | H137: PU/25/SLS/OT/1853 | I137: 246779413772 | K137: 246779413629 | L137: 0 | M137: 397 | O137: 246779413629 | P137: 0 | Q137: 397
A138: 2025-10-07 | B138: 4786 | C138: 4786 | D138: -757662.6 | E138: Debit Note | F138: SJ/25/GEA/1103 | H138: PU/26/SLS/OT/0591-1, SLS26/MF/DN/0007-2 | I138: Debit Note | K138: 246779413689 | L138: 0 | M138: 1591 | O138: 246779413689 | P138: 0 | Q138: 1591
A139: 2025-07-31 | B139: 0 | C139: 44602 | D139: -288272.6 | E139: Purchase Invoice | F139: PU/26/SLS/OT/1009-1 | G139: Container Scanning Paid - SLSIPL | H139: PU/26/SLS/OT/1009-1 | I139: 246779411278 | K139: 246779413690 | L139: 0 | M139: 198 | O139: 246779413690 | P139: 0 | Q139: 198
A140: 2025-03-31 | B140: 0 | C140: 143412 | D140: -2750354.1 | E140: Purchase Invoice | F140: PU/25/SLS/OT/1857 | G140: VOS Activity Charges Paid - SLSIPL | H140: PU/25/SLS/OT/1857 | I140: 246779411619 | K140: 246779413691 | L140: 0 | M140: 596 | O140: 246779413691 | P140: 0 | Q140: 596
A141: 2025-03-31 | B141: 0 | C141: 5816 | D141: -2756170.1 | E141: Purchase Invoice | F141: PU/25/SLS/OT/1858 | G141: VOS Activity Charges Paid - SLSIPL | H141: PU/25/SLS/OT/1858 | I141: 246779411620 | K141: 246779413692 | L141: 0 | M141: 191 | O141: 246779413692 | P141: 0 | Q141: 191
A142: 2025-03-31 | B142: 0 | C142: 5816 | D142: -2761986.1 | E142: Purchase Invoice | F142: PU/25/SLS/OT/1859 | G142: VOS Activity Charges Paid - SLSIPL | H142: PU/25/SLS/OT/1859 | I142: 246779411755 | K142: 246779413693 | L142: 0 | M142: 6896 | O142: 246779413693 | P142: 0 | Q142: 6896
A143: 2025-03-31 | B143: 0 | C143: 4339 | D143: -2766325.1 | E143: Purchase Invoice | F143: PU/25/SLS/OT/1860 | G143: VOS Activity Charges Paid - SLSIPL | H143: PU/25/SLS/OT/1860 | I143: 246779411756 | K143: 246779413694 | L143: 0 | M143: 3448 | O143: 246779413694 | P143: 0 | Q143: 3448
A144: 2025-03-31 | B144: 0 | C144: 6761 | D144: -2773086.1 | E144: Purchase Invoice | F144: PU/25/SLS/OT/1861 | G144: VOS Activity Charges Paid - SLSIPL | H144: PU/25/SLS/OT/1861 | I144: 246779411759 | K144: 246779413695 | L144: 0 | M144: 191 | O144: 246779413695 | P144: 0 | Q144: 191
A145: 2025-03-31 | B145: 0 | C145: 3110 | D145: -2776196.1 | E145: Purchase Invoice | F145: PU/25/SLS/OT/1862 | G145: VOS Activity Charges Paid - SLSIPL | H145: PU/25/SLS/OT/1862 | I145: 246779411757 | K145: 246779413696 | L145: 0 | M145: 382 | O145: 246779413696 | P145: 0 | Q145: 382
A146: 2025-10-07 | B146: 36410 | C146: 36410 | D146: -757662.6 | E146: Debit Note | F146: SJ/25/GEA/1105 | H146: PU/26/SLS/OT/1009-1, SLS26/MF/DN/0022-1 | I146: Debit Note | K146: 246779413701 | L146: 0 | M146: 18367 | O146: 246779413701 | P146: 0 | Q146: 18367
A147: 2025-04-01 | B147: 0 | C147: 1161 | D147: -2810733.1 | E147: Purchase Invoice | F147: PU/26/SLS/OT/0048 | G147: VOS Activity Charges Paid - SLSIPL | H147: PU/26/SLS/OT/0048 | I147: 246779411448 | K147: 246779413702 | L147: 0 | M147: 31577 | O147: 246779413702 | P147: 0 | Q147: 31577
A148: 2025-04-01 | B148: 0 | C148: 1591 | D148: -2812324.1 | E148: Purchase Invoice | F148: PU/26/SLS/OT/0193 | G148: Handling Charges - Outbound (Exp) - SLSIPL | H148: PU/26/SLS/OT/0193 | I148: 246779413689 | K148: 246779413704 | L148: 0 | M148: 13011 | O148: 246779413704 | P148: 0 | Q148: 13011
A149: 2025-04-01 | B149: 0 | C149: 574 | D149: -2812898.1 | E149: Purchase Invoice | F149: PU/26/SLS/OT/0194 | G149: Handling Charges - Outbound (Exp) - SLSIPL | H149: PU/26/SLS/OT/0194 | I149: 246779413740 | K149: 246779413705 | L149: 0 | M149: 19429 | O149: 246779413705 | P149: 0 | Q149: 19429
A150: 2025-04-01 | B150: 0 | C150: 574 | D150: -2813472.1 | E150: Purchase Invoice | F150: PU/26/SLS/OT/0195 | G150: Handling Charges - Outbound (Exp) - SLSIPL | H150: PU/26/SLS/OT/0195 | I150: 246779413737 | K150: 246779413733 | L150: 0 | M150: 191 | O150: 246779413733 | P150: 0 | Q150: 191
A151: 2025-04-01 | B151: 0 | C151: 6896 | D151: -2820368.1 | E151: Purchase Invoice | F151: PU/26/SLS/OT/0196 | G151: Handling Charges - Outbound (Exp) - SLSIPL | H151: PU/26/SLS/OT/0196 | I151: 246779413735 | K151: 246779413734 | L151: 0 | M151: 3448 | O151: 246779413734 | P151: 0 | Q151: 3448
A152: 2025-04-01 | B152: 0 | C152: 191 | D152: -2820559.1 | E152: Purchase Invoice | F152: PU/26/SLS/OT/0197 | G152: Handling Charges - Outbound (Exp) - SLSIPL | H152: PU/26/SLS/OT/0197 | I152: 246779413744 | K152: 246779413735 | L152: 0 | M152: 6896 | O152: 246779413735 | P152: 0 | Q152: 6896
A153: 2025-04-01 | B153: 0 | C153: 191 | D153: -2820750.1 | E153: Purchase Invoice | F153: PU/26/SLS/OT/0199 | G153: Handling Charges - Outbound (Exp) - SLSIPL | H153: PU/26/SLS/OT/0199 | I153: 246779413733 | K153: 246779413736 | L153: 0 | M153: 6513 | O153: 246779413736 | P153: 0 | Q153: 6513
A154: 2025-04-01 | B154: 0 | C154: 383 | D154: -2821133.1 | E154: Purchase Invoice | F154: PU/26/SLS/OT/0200 | G154: Handling Charges - Outbound (Exp) - SLSIPL | H154: PU/26/SLS/OT/0200 | I154: 246779413743 | K154: 246779413737 | L154: 0 | M154: 574 | O154: 246779413737 | P154: 0 | Q154: 574
A155: 2025-04-01 | B155: 0 | C155: 383 | D155: -2821516.1 | E155: Purchase Invoice | F155: PU/26/SLS/OT/0201 | G155: Handling Charges - Outbound (Exp) - SLSIPL | H155: PU/26/SLS/OT/0201 | I155: 246779414680 | K155: 246779413738 | L155: 0 | M155: 3603 | O155: 246779413738 | P155: 0 | Q155: 3603
A156: 2025-04-01 | B156: 0 | C156: 6895 | D156: -2828411.1 | E156: Purchase Invoice | F156: PU/26/SLS/OT/0202 | G156: Handling Charges - Outbound (Exp) - SLSIPL | H156: PU/26/SLS/OT/0202 | I156: 246779413741 | K156: 246779413739 | L156: 0 | M156: 1724 | O156: 246779413739 | P156: 0 | Q156: 1724
A157: 2025-04-01 | B157: 0 | C157: 846 | D157: -2829257.1 | E157: Purchase Invoice | F157: PU/26/SLS/OT/0191 | G157: Handling Charges - Inbound (Exp) - SLSIPL | H157: PU/26/SLS/OT/0191 | I157: 246779413933 | K157: 246779413740 | L157: 0 | M157: 574 | O157: 246779413740 | P157: 0 | Q157: 574
A158: 2025-04-01 | B158: 0 | C158: 3203 | D158: -2832460.1 | E158: Purchase Invoice | F158: PU/26/SLS/OT/0301-1 | G158: Handling Charges - Outbound (Exp) - SLSIPL | H158: PU/26/SLS/OT/0301-1 | I158: 246779410609 | K158: 246779413741 | L158: 0 | M158: 6895 | O158: 246779413741 | P158: 0 | Q158: 6895
... A163: 2025-03-31 | B163: 0 | C163: 33376 | D163: -2809572.1 | E163: Purchase Invoice | F163: PU/25/SLS/OT/1925 | G163: Container Scanning Paid - SLSIPL | H163: PU/25/SLS/OT/1925 | I163: 246779411300 | K163: 246779413753 | L163: 0 | M163: 31723 | O163: 246779413753 | P163: 0 | Q163: 31723
A164: 2025-12-31 | B164: 8522 | C164: 8522 | D164: -2052708.6 | E164: Debit Note | F164: SJ/25/GEA/1378 | H164: PU/25/SLS/OT/1856, SLS26/MF/DN/0010-1 | I164: Debit Note | K164: 246779413762 | L164: 0 | M164: 191 | O164: 246779413762 | P164: 0 | Q164: 191
A165: 2025-04-01 | B165: 0 | C165: 3594 | D165: -2917685.1 | E165: Purchase Invoice | F165: PU/26/SLS/OT/0790 | G165: Handling Charges - Outbound (Exp) - SLSIPL | H165: PU/26/SLS/OT/0790 | I165: 246779410755 | K165: 246779413772 | L165: 0 | M165: 994 | O165: 246779413772 | P165: 0 | Q165: 994
A166: 2025-04-01 | B166: 0 | C166: 35477 | D166: -2953162.1 | E166: Purchase Invoice | F166: PU/26/SLS/OT/0780-2 | G166: Fixed Storage Charges - ODC (Covered) - SLSIPL | H166: PU/26/SLS/OT/0780-2 | I166: 246779410072 | K166: 246779413782 | L166: 0 | M166: 596 | O166: 246779413782 | P166: 0 | Q166: 596
A167: 2025-04-01 | B167: 0 | C167: 799 | D167: -2953961.1 | E167: Purchase Invoice | F167: PU/26/SLS/OT/0785-1 | G167: Handling Charges - Outbound (Exp) - SLSIPL | H167: PU/26/SLS/OT/0785-1 | I167: 246779410688 | K167: 246779413796 | L167: 0 | M167: 163631 | O167: 246779413796 | P167: 0 | Q167: 163631
A168: 2025-04-01 | B168: 0 | C168: 1797 | D168: -2955758.1 | E168: Purchase Invoice | F168: PU/26/SLS/OT/0784-1 | G168: Handling Charges - Outbound (Exp) - SLSIPL | H168: PU/26/SLS/OT/0784-1 | I168: 246779410687 | K168: 246779413816 | L168: 0 | M168: 18610 | O168: 246779413816 | P168: 0 | Q168: 18610
A169: 2025-03-31 | B169: 0 | C169: 8522 | D169: -2606942.1 | E169: Purchase Invoice | F169: PU/25/SLS/OT/1856 | G169: Container Scanning Paid - SLSIPL | H169: PU/25/SLS/OT/1856 | I169: 246779411314 | K169: 246779413827 | L169: 0 | M169: 31723 | O169: 246779413827 | P169: 0 | Q169: 31723
A170: 2025-04-03 | B170: 0 | C170: 2883 | D170: -3018265.1 | E170: Purchase Invoice | F170: PU/26/SLS/OT/0046 | G170: MHE Charges Paid - SLSIPL | H170: PU/26/SLS/OT/0046 | I170: 256779410157 | K170: 246779413845 | L170: 0 | M170: 45188 | O170: 246779413845 | P170: 0 | Q170: 45188
A171: 2025-04-03 | B171: 0 | C171: 4913 | D171: -3023178.1 | E171: Purchase Invoice | F171: PU/26/SLS/OT/0047 | G171: Handling Charges - Inbound (Exp) - SLSIPL | H171: PU/26/SLS/OT/0047 | I171: 256779410156 | K171: 246779413933 | L171: 0 | M171: 846 | O171: 246779413933 | P171: 0 | Q171: 846
A172: 2025-04-03 | B172: 0 | C172: 13011 | D172: -3036189.1 | E172: Purchase Invoice | F172: PU/26/SLS/OT/0323 | G172: Handling Charges - Outbound (Exp) - SLSIPL | H172: PU/26/SLS/OT/0323 | I172: 256779410166 | K172: 246779414141 | L172: 0 | M172: 4652 | O172: 246779414141 | P172: 0 | Q172: 4652
A173: 2025-04-03 | B173: 0 | C173: 6205 | D173: -3042394.1 | E173: Purchase Invoice | F173: PU/26/SLS/OT/0326 | G173: Handling Charges - Outbound (Exp) - SLSIPL | H173: PU/26/SLS/OT/0326 | I173: 256779410174 | K173: 246779414142 | L173: 0 | M173: 1268 | O173: 246779414142 | P173: 0 | Q173: 1268
A174: 2025-04-03 | B174: 0 | C174: 2937 | D174: -3045331.1 | E174: Purchase Invoice | F174: PU/26/SLS/OT/0332 | G174: VOS Activity Charges Paid - SLSIPL | H174: PU/26/SLS/OT/0332 | I174: 256779410201 | K174: 246779414221 | L174: 0 | M174: 17701 | O174: 246779414221 | P174: 0 | Q174: 17701
A175: 2025-04-03 | B175: 0 | C175: 319 | D175: -3045650.1 | E175: Purchase Invoice | F175: PU/26/SLS/OT/0338 | G175: Gate In Charges Paid - SLSIPL | H175: PU/26/SLS/OT/0338 | I175: 256779410135 | K175: 246779414317 | L175: 0 | M175: 1907 | O175: 246779414317 | P175: 0 | Q175: 1907
A176: 2025-04-03 | B176: 0 | C176: 639 | D176: -3046289.1 | E176: Purchase Invoice | F176: PU/26/SLS/OT/0331 | G176: Handling Charges - Inbound (Exp) - SLSIPL | H176: PU/26/SLS/OT/0331 | I176: 256779410134 | K176: 246779414467 | L176: 0 | M176: 2674 | O176: 246779414467 | P176: 0 | Q176: 2674
A177: 2025-10-07 | B177: 15401 | C177: 15401 | D177: -757662.6 | E177: Debit Note | F177: SJ/25/GEA/1106 | H177: PU/26/SLS/OT/1008-1, SLS26/MF/DN/0021-1 | I177: Debit Note | K177: 246779414603 | L177: 0 | M177: 34760 | O177: 246779414603 | P177: 0 | Q177: 34760
A178: 2025-03-31 | B178: 0 | C178: 20874 | D178: -2440597.1 | E178: Purchase Invoice | F178: PU/25/SLS/OT/1820 | G178: Container Scanning Paid - SLSIPL | H178: PU/25/SLS/OT/1820 | I178: 246779411326 | K178: 246779414680 | L178: 0 | M178: 383 | O178: 246779414680 | P178: 0 | Q178: 383
A179: 2025-07-31 | B179: 0 | C179: 18367 | D179: -254828.6 | E179: Purchase Invoice | F179: PU/26/SLS/OT/1008-1 | G179: Fixed Storage Charges - ODC (Covered) - SLSIPL | H179: PU/26/SLS/OT/1008-1 | I179: 246779413701 | K179: 246779414681 | L179: 0 | M179: 1268 | O179: 246779414681 | P179: 0 | Q179: 1268
A180: 2025-04-04 | B180: 0 | C180: 331566 | D180: -3687999.1 | E180: Purchase Invoice | F180: PU/26/SLS/OT/0044 | G180: Storage Charges - Cargo - SLSIPL | H180: PU/26/SLS/OT/0044 | I180: 256779410812 | K180: 246779414734 | L180: 0 | M180: 211 | O180: 246779414734 | P180: 0 | Q180: 211
A181: 2025-04-04 | B181: 0 | C181: 384955 | D181: -4072954.1 | E181: Purchase Invoice | F181: PU/26/SLS/OT/0045 | G181: Storage Charges - Cargo - SLSIPL | H181: PU/26/SLS/OT/0045 | I181: 256779410795 | K181: 246779414885 | L181: 0 | M181: 211 | O181: 246779414885 | P181: 0 | Q181: 211
A182: 2025-04-15 | B182: 0 | C182: 13328 | D182: -4086282.1 | E182: Purchase Invoice | F182: PU/26/SLS/OT/0205 | G182: Handling Charges - Outbound (Exp) - SLSIPL | H182: PU/26/SLS/OT/0205 | I182: 256779411150 | K182: 246779418620 | L182: 7320 | M182: 73283.168 | O182: 246779418620 | P182: 7320 | Q182: 73283.168
A183: 2025-04-15 | B183: 0 | C183: 25546 | D183: -4111828.1 | E183: Purchase Invoice | F183: PU/26/SLS/OT/0209 | G183: Handling Charges - Inbound (Exp) - SLSIPL,Transportation Charges Paid - SLSIPL | H183: PU/26/SLS/OT/0209 | I183: 256779411148 | K183: 256779410004 | L183: 0 | M183: 55272 | O183: 256779410004 | P183: 0 | Q183: 55272
A184: 2025-04-15 | B184: 0 | C184: 2664 | D184: -4114492.1 | E184: Purchase Invoice | F184: PU/26/SLS/OT/0210 | G184: Handling Charges - Inbound (Exp) - SLSIPL | H184: PU/26/SLS/OT/0210 | I184: 256779411149 | K184: 256779410010 | L184: 0 | M184: 140649 | O184: 256779410010 | P184: 0 | Q184: 140649
A185: 2025-04-15 | B185: 0 | C185: 790 | D185: -4115282.1 | E185: Purchase Invoice | F185: PU/26/SLS/OT/0211 | G185: Handling Charges - Inbound (Exp) - SLSIPL | H185: PU/26/SLS/OT/0211 | I185: 256779411564 | K185: 256779410134 | L185: 0 | M185: 639 | O185: 256779410134 | P185: 0 | Q185: 639
A186: 2025-04-15 | B186: 0 | C186: 198 | D186: -4115480.1 | E186: Purchase Invoice | F186: PU/26/SLS/OT/0212 | G186: Handling Charges - Outbound (Exp) - SLSIPL | H186: PU/26/SLS/OT/0212 | I186: 256779411563 | K186: 256779410135 | L186: 0 | M186: 319 | O186: 256779410135 | P186: 0 | Q186: 319
A187: 2025-04-15 | B187: 0 | C187: 13629 | D187: -4129109.1 | E187: Purchase Invoice | F187: PU/26/SLS/OT/0339 | G187: Gate In Charges Paid - SLSIPL,Handling Charges - Inbound (Exp) - SLSIPL | H187: PU/26/SLS/OT/0339 | I187: 256779411151 | K187: 256779410156 | L187: 0 | M187: 4913 | O187: 256779410156 | P187: 0 | Q187: 4913
A188: 2025-04-16 | B188: 0 | C188: 417286 | D188: -4546395.1 | E188: Purchase Invoice | F188: PU/26/SLS/OT/0043 | G188: Storage Charges - Cargo - SLSIPL | H188: PU/26/SLS/OT/0043 | I188: 256779412117 | K188: 256779410157 | L188: 0 | M188: 2883 | O188: 256779410157 | P188: 0 | Q188: 2883
A189: 2025-04-16 | B189: 0 | C189: 1972 | D189: -4548367.1 | E189: Purchase Invoice | F189: PU/26/SLS/OT/0190 | G189: Handling Charges - Inbound (Exp) - SLSIPL | H189: PU/26/SLS/OT/0190 | I189: 25677941807 | K189: 256779410166 | L189: 0 | M189: 13011 | O189: 256779410166 | P189: 0 | Q189: 13011
... A204: 2025-04-23 | B204: 0 | C204: 27408 | D204: -4738408.1 | E204: Purchase Invoice | F204: PU/26/SLS/OT/0337-1 | G204: Gate In Charges Paid - SLSIPL,Handling Charges - Inbound (Exp) - SLSIPL | H204: PU/26/SLS/OT/0337-1 | I204: 256779412941 | K204: 256779411917 | L204: 0 | M204: 12169 | O204: 256779411917 | P204: 0 | Q204: 12169
A205: 2025-10-07 | B205: 31577 | C205: 31577 | D205: -757662.6 | E205: Debit Note | F205: SJ/25/GEA/1111 | H205: PU/26/SLS/OT/0589-2, SLS26/MF/DN/0005-1 | I205: Debit Note | K205: 256779412065 | L205: 0 | M205: 1584 | O205: 256779412065 | P205: 0 | Q205: 1584
A206: 2025-04-24 | B206: 0 | C206: 7981 | D206: -4752473.1 | E206: Purchase Invoice | F206: PU/26/SLS/OT/0189 | G206: VOS Activity Charges Paid - SLSIPL | H206: PU/26/SLS/OT/0189 | I206: 256779412777 | K206: 256779412100 | L206: 0 | M206: 21549 | O206: 256779412100 | P206: 0 | Q206: 21549
A207: 2025-05-10 | B207: 0 | C207: 15927 | D207: -4768400.1 | E207: Purchase Invoice | F207: PU/26/SLS/OT/0213 | G207: Handling Charges - Inbound (Exp) - SLSIPL | H207: PU/26/SLS/OT/0213 | I207: 256779413163 | K207: 256779412117 | L207: 0 | M207: 417286 | O207: 256779412117 | P207: 0 | Q207: 417286
A208: 2025-05-10 | B208: 0 | C208: 35097 | D208: -4803497.1 | E208: Purchase Invoice | F208: PU/26/SLS/OT/0116 | G208: Fixed Storage Charges - ODC (Covered) - SLSIPL | H208: PU/26/SLS/OT/0116 | I208: 256779413127 | K208: 256779412161 | L208: 0 | M208: 34962 | O208: 256779412161 | P208: 0 | Q208: 34962
A209: 2025-05-10 | B209: 0 | C209: 11810 | D209: -4815307.1 | E209: Purchase Invoice | F209: PU/26/SLS/OT/0340 | G209: Handling Charges - Outbound (Exp) - SLSIPL | H209: PU/26/SLS/OT/0340 | I209: 256779413172 | K209: 256779412461 | L209: 0 | M209: 10809 | O209: 256779412461 | P209: 0 | Q209: 10809
A210: 2025-05-10 | B210: 0 | C210: 3623 | D210: -4818930.1 | E210: Purchase Invoice | F210: PU/26/SLS/OT/0334 | G210: VOS Activity Charges Paid - SLSIPL | H210: PU/26/SLS/OT/0334 | I210: 256779413243 | K210: 256779412468 | L210: 0 | M210: 14119 | O210: 256779412468 | P210: 0 | Q210: 14119
A211: 2025-05-16 | B211: 0 | C211: 1264 | D211: -4820194.1 | E211: Purchase Invoice | F211: PU/26/SLS/OT/0279 | G211: Handling Charges - Outbound (Exp) - SLSIPL | H211: PU/26/SLS/OT/0279 | I211: 256779413357 | K211: 256779412613 | L211: 0 | M211: 3922 | O211: 256779412613 | P211: 0 | Q211: 3922
A212: 2025-07-16 | B212: 0 | C212: 31577 | D212: -1349660.6 | E212: Purchase Invoice | F212: PU/26/SLS/OT/0589-2 | G212: Storage Charges - Cargo - SLSIPL | H212: PU/26/SLS/OT/0589-2 | I212: 246779413702 | K212: 256779412655 | L212: 0 | M212: 2085 | O212: 256779412655 | P212: 0 | Q212: 2085
A213: 2025-05-20 | B213: 0 | C213: 1054 | D213: -4833045.1 | E213: Purchase Invoice | F213: PU/26/SLS/OT/0281 | G213: Handling Charges - Outbound (Exp) - SLSIPL | H213: PU/26/SLS/OT/0281 | I213: 256779413486 | K213: 256779412675 | L213: 0 | M213: 1447 | O213: 256779412675 | P213: 0 | Q213: 1447
A214: 2025-05-20 | B214: 0 | C214: 12177 | D214: -4845222.1 | E214: Purchase Invoice | F214: PU/26/SLS/OT/0284 | G214: VOS Activity Charges Paid - SLSIPL | H214: PU/26/SLS/OT/0284 | I214: 256779413837 | K214: 256779412683 | L214: 0 | M214: 43195 | O214: 256779412683 | P214: 0 | Q214: 43195
A215: 2025-05-21 | B215: 0 | C215: 3960 | D215: -4849182.1 | E215: Purchase Invoice | F215: PU/26/SLS/OT/0187 | G215: Handling Charges - Inbound (Exp) - SLSIPL | H215: PU/26/SLS/OT/0187 | I215: 256779413405 | K215: 256779412692 | L215: 0 | M215: 6084 | O215: 256779412692 | P215: 0 | Q215: 6084
A216: 2025-05-21 | B216: 0 | C216: 7129 | D216: -4856311.1 | E216: Purchase Invoice | F216: PU/26/SLS/OT/0188 | G216: Handling Charges - Inbound (Exp) - SLSIPL | H216: PU/26/SLS/OT/0188 | I216: 256779413404 | K216: 256779412777 | L216: 0 | M216: 7981 | O216: 256779412777 | P216: 0 | Q216: 7981
A217: 2025-05-21 | B217: 0 | C217: 990 | D217: -4857301.1 | E217: Purchase Invoice | F217: PU/26/SLS/OT/0280 | G217: Handling Charges - Outbound (Exp) - SLSIPL | H217: PU/26/SLS/OT/0280 | I217: 256779413427 | K217: 256779412926 | L217: 0 | M217: 1878 | O217: 256779412926 | P217: 0 | Q217: 1878
... A221: 2025-05-28 | B221: 0 | C221: 333696 | D221: -5193789.1 | E221: Purchase Invoice | F221: PU/26/SLS/OT/0278 | G221: Storage Charges - Cargo - SLSIPL | H221: PU/26/SLS/OT/0278 | I221: 256779413899 | K221: 256779413163 | L221: 0 | M221: 15927 | O221: 256779413163 | P221: 0 | Q221: 15927
A222: 2025-05-30 | B222: 177773 | C222: 0 | D222: -5016016.1 | E222: Pay | F222: BP/26/SLS/0192 | G222: 1395250393003 - Punjab National Bank - INR - SLSIPL | I222: Payment | K222: 256779413172 | L222: 0 | M222: 11810 | O222: 256779413172 | P222: 0 | Q222: 11810
A223: 2025-06-04 | B223: 0 | C223: 9844 | D223: -5025860.1 | E223: Purchase Invoice | F223: PU/26/SLS/OT/0358 | G223: Handling Charges - Outbound (Exp) - SLSIPL | H223: PU/26/SLS/OT/0358 | I223: 256779414165 | K223: 256779413184 | L223: 0 | M223: 11723.018 | O223: 256779413184 | P223: 0 | Q223: 11723.018
A224: 2025-06-04 | B224: 0 | C224: 8407 | D224: -5034267.1 | E224: Purchase Invoice | F224: PU/26/SLS/OT/0360 | G224: Handling Charges - Outbound (Exp) - SLSIPL | H224: PU/26/SLS/OT/0360 | I224: 256779414216 | K224: 256779413243 | L224: 0 | M224: 3623 | O224: 256779413243 | P224: 0 | Q224: 3623
A225: 2025-06-04 | B225: 500946.52 | C225: 0 | D225: -4533320.6 | E225: Pay | F225: BP/25/SLS/1225-1 | G225: 1395250393003 - Punjab National Bank - INR - SLSIPL | H225: PU/25/SLS/OT/1562, PU/25/SLS/OT/1720, PU/25/SLS/OT/1731, PU/25/SLS/OT/1721, PU/25/SLS/OT/1673 | I225: Payment | K225: 256779413283 | L225: 0 | M225: 11797 | O225: 256779413283 | P225: 0 | Q225: 11797
A226: 2025-10-07 | B226: 12467 | C226: 12467 | D226: -757662.6 | E226: Debit Note | F226: SJ/25/GEA/1107 | H226: PU/26/SLS/OT/0614-1, SLS26/MF/DN/0018-1 | I226: Debit Note | K226: 256779413357 | L226: 0 | M226: 1264 | O226: 256779413357 | P226: 0 | Q226: 1264
A227: 2025-06-04 | B227: 0 | C227: 41769 | D227: -4592402.6 | E227: Purchase Invoice | F227: PU/26/SLS/OT/0797 | G227: Handling Charges - Inbound (Exp) - SLSIPL,LCL Movment - Gate in Charge - SLSIPL,Transportation Charges Paid - SLSIPL,Eempty Container Return Charges Paid - SLSIPL | H227: PU/26/SLS/OT/0797 | I227: 256779414158 | K227: 256779413404 | L227: 0 | M227: 7129 | O227: 256779413404 | P227: 0 | Q227: 7129
A228: 2025-06-07 | B228: 0 | C228: 352792 | D228: -4945194.6 | E228: Purchase Invoice | F228: PU/26/SLS/OT/0285 | G228: Storage Charges - Cargo - SLSIPL | H228: PU/26/SLS/OT/0285 | I228: 256779414242 | K228: 256779413405 | L228: 0 | M228: 3960 | O228: 256779413405 | P228: 0 | Q228: 3960
A229: 2025-06-10 | B229: 0 | C229: 35431 | D229: -4980625.6 | E229: Purchase Invoice | F229: PU/26/SLS/OT/0357-1 | G229: Fixed Storage Charges - ODC (Covered) - SLSIPL | H229: PU/26/SLS/OT/0357-1 | I229: 256779414386 | K229: 256779413427 | L229: 0 | M229: 990 | O229: 256779413427 | P229: 0 | Q229: 990
A230: 2025-06-13 | B230: 700000 | C230: 0 | D230: -4280625.6 | E230: Pay | F230: BP/26/SLS/0229 | G230: 1395250393003 - Punjab National Bank - INR - SLSIPL | I230: Payment | K230: 256779413428 | L230: 0 | M230: 990 | O230: 256779413428 | P230: 0 | Q230: 990
...

Sheet Ascendus Ledger
A1: Company Code | B1: Customer | C1: Customer Account: Name 1 | D1: Fiscal Year | E1: Posting period | F1: Posting Date | G1: Document Number | H1: Document Type | I1: Document Date | J1: Entry Date | K1: Document Header Text | L1: Reference | M1: G/L Account | N1: G/L Account: Short Text | O1: Special G/L Ind. | P1: Posting Key | Q1: Document Currency Key | R1: Document Currency Value | S1: Company Code Currency Key | T1: Company Code Currency Value | U1: Tax Code | V1: Profit Center | W1: Trading Partner No. | X1: Assignment | Y1: Item | Z1: Debit | AA1: Credit | AB1: Net Amount | AC1: TDS | AD1: Rate | AE1: Text | AF1: Reference Key 1 | AG1: Reference Key 2 | AH1: Reference Key 3 | AI1: Baseline Payment Dte | AJ1: Clearing Date | AK1: Clearing Document
A2: 6779 | B2: 100222332 | C2: SCOPE LOGISTICS SERVICES INDIA PVT. | D2: 2025 | E2: 7 | F2: 45854 | G2: 1600001726 | H2: DG | I2: 45854 | J2: 45854 | K2: NA | L2: 256779421358 | M2: 212100 | N2: Trade Debtors (Ctrl) | P2: 11 | Q2: USD | R2: -1793.99 | S2: INR | T2: -154827.9 | U2: O0 | V2: 6779224500 | X2: NA | Y2: 1 | Z2: {=_xlfn.XLOOKUP(L2,'Customer Ledger'!$O:$O,'Customer Ledger'!$P:$Q,,0)} -> #N/A | AE2: Credit Note raised against INV_246779410348 | AI2: 45854 | AJ2: 45854 | AK2: 1400000285
A3: 6779 | B3: 100222332 | C3: SCOPE LOGISTICS SERVICES INDIA PVT. | D3: 2025 | E3: 7 | F3: 45854 | G3: 1800010646 | H3: DR | I3: 45854 | J3: 45855 | K3: NA | L3: 256779415406 | M3: 212100 | N3: Trade Debtors (Ctrl) | P3: 1 | Q3: USD | R3: 1793.99 | S3: INR | T3: 154827.9 | U3: O0 | V3: 6779224500 | X3: NA | Y3: 1 | Z3: {=_xlfn.XLOOKUP(L3,'Customer Ledger'!$O:$O,'Customer Ledger'!$P:$Q,,0)} -> #N/A | AE3: Debit note Note raised against CN_256779421358 | AI3: 45854 | AJ3: 45854 | AK3: 1400000285
A4: 6779 | B4: 100222332 | C4: SCOPE LOGISTICS SERVICES INDIA PVT. | D4: 2025 | E4: 7 | F4: 45854 | G4: 1600001727 | H4: DG | I4: 45854 | J4: 45854 | K4: NA | L4: 256779421359 | M4: 212100 | N4: Trade Debtors (Ctrl) | P4: 11 | Q4: USD | R4: -705 | S4: INR | T4: -60844.08 | U4: O0 | V4: 6779224500 | X4: NA | Y4: 1 | Z4: {=_xlfn.XLOOKUP(L4,'Customer Ledger'!$O:$O,'Customer Ledger'!$P:$Q,,0)} -> #N/A | AE4: Credit Note raised against INV_246779410360 | AI4: 45854 | AJ4: 45854 | AK4: 1400000286
A5: 6779 | B5: 100222332 | C5: SCOPE LOGISTICS SERVICES INDIA PVT. | D5: 2025 | E5: 7 | F5: 45854 | G5: 1800010647 | H5: DR | I5: 45854 | J5: 45855 | K5: NA | L5: 256779415407 | M5: 212100 | N5: Trade Debtors (Ctrl) | P5: 1 | Q5: USD | R5: 705 | S5: INR | T5: 60844.08 | U5: O0 | V5: 6779224500 | X5: NA | Y5: 1 | Z5: {=_xlfn.XLOOKUP(L5,'Customer Ledger'!$O:$O,'Customer Ledger'!$P:$Q,,0)} -> #N/A | AE5: Debit note Note raised against CN_256779421359 | AI5: 45854 | AJ5: 45854 | AK5: 1400000286
A6: 6779 | B6: 100222332 | C6: SCOPE LOGISTICS SERVICES INDIA PVT. | D6: 2025 | E6: 7 | F6: 45854 | G6: 1600001728 | H6: DG | I6: 45854 | J6: 45854 | K6: NA | L6: 256779421360 | M6: 212100 | N6: Trade Debtors (Ctrl) | P6: 11 | Q6: USD | R6: -216.2 | S6: INR | T6: -18742.65 | U6: O0 | V6: 6779224500 | X6: NA | Y6: 1 | Z6: {=_xlfn.XLOOKUP(L6,'Customer Ledger'!$O:$O,'Customer Ledger'!$P:$Q,,0)} -> #N/A | AE6: Credit Note raised against INV_246779413701 | AI6: 45854 | AJ6: 45854 | AK6: 1400000287
A7: 6779 | B7: 100222332 | C7: SCOPE LOGISTICS SERVICES INDIA PVT. | D7: 2025 | E7: 7 | F7: 45854 | G7: 1800010648 | H7: DR | I7: 45854 | J7: 45855 | K7: NA | L7: 256779415408 | M7: 212100 | N7: Trade Debtors (Ctrl) | P7: 1 | Q7: USD | R7: 216.2 | S7: INR | T7: 18742.65 | U7: O0 | V7: 6779224500 | X7: NA | Y7: 1 | Z7: {=_xlfn.XLOOKUP(L7,'Customer Ledger'!$O:$O,'Customer Ledger'!$P:$Q,,0)} -> #N/A | AE7: Debit note Note raised against CN_256779421360 | AI7: 45854 | AJ7: 45854 | AK7: 1400000287
A8: 6779 | B8: 100222332 | C8: SCOPE LOGISTICS SERVICES INDIA PVT. | D8: 2025 | E8: 7 | F8: 45854 | G8: 1600001731 | H8: DG | I8: 45854 | J8: 45854 | K8: NA | L8: 256779421363 | M8: 212100 | N8: Trade Debtors (Ctrl) | P8: 11 | Q8: USD | R8: -1926.06 | S8: INR | T8: -166972.57 | U8: O0 | V8: 6779224500 | X8: NA | Y8: 1 | Z8: {=_xlfn.XLOOKUP(L8,'Customer Ledger'!$O:$O,'Customer Ledger'!$P:$Q,,0)} -> #N/A | AE8: Credit Note raised against INV_246779413796 | AI8: 45854 | AJ8: 45854 | AK8: 1400000288
A9: 6779 | B9: 100222332 | C9: SCOPE LOGISTICS SERVICES INDIA PVT. | D9: 2025 | E9: 7 | F9: 45854 | G9: 1800010649 | H9: DR | I9: 45854 | J9: 45855 | K9: NA | L9: 256779415409 | M9: 212100 | N9: Trade Debtors (Ctrl) | P9: 1 | Q9: USD | R9: 1926.06 | S9: INR | T9: 166972.57 | U9: O0 | V9: 6779224500 | X9: NA | Y9: 1 | Z9: {=_xlfn.XLOOKUP(L9,'Customer Ledger'!$O:$O,'Customer Ledger'!$P:$Q,,0)} -> #N/A | AE9: Debit note Note raised against CN_256779421363 | AI9: 45854 | AJ9: 45854 | AK9: 1400000288
A10: 6779 | B10: 100222332 | C10: SCOPE LOGISTICS SERVICES INDIA PVT. | D10: 2025 | E10: 7 | F10: 45854 | G10: 1600001734 | H10: DG | I10: 45854 | J10: 45854 | K10: NA | L10: 256779421366 | M10: 212100 | N10: Trade Debtors (Ctrl) | P10: 11 | Q10: USD | R10: -531.9 | S10: INR | T10: -46111.08 | U10: O0 | V10: 6779224500 | X10: NA | Y10: 1 | Z10: {=_xlfn.XLOOKUP(L10,'Customer Ledger'!$O:$O,'Customer Ledger'!$P:$Q,,0)} -> #N/A | AE10: Credit Note raised against INV_246779413845 | AI10: 45854 | AJ10: 45854 | AK10: 1400000289
A11: 6779 | B11: 100222332 | C11: SCOPE LOGISTICS SERVICES INDIA PVT. | D11: 2025 | E11: 7 | F11: 45854 | G11: 1800010650 | H11: DR | I11: 45854 | J11: 45855 | K11: NA | L11: 256779415410 | M11: 212100 | N11: Trade Debtors (Ctrl) | P11: 1 | Q11: USD | R11: 531.9 | S11: INR | T11: 46111.08 | U11: O0 | V11: 6779224500 | X11: NA | Y11: 1 | Z11: {=_xlfn.XLOOKUP(L11,'Customer Ledger'!$O:$O,'Customer Ledger'!$P:$Q,,0)} -> #N/A | AE11: Debit note Note raised against CN_256779421366 | AI11: 45854 | AJ11: 45854 | AK11: 1400000289
A12: 6779 | B12: 100222332 | C12: SCOPE LOGISTICS SERVICES INDIA PVT. | D12: 2025 | E12: 7 | F12: 45854 | G12: 1600001739 | H12: DG | I12: 45854 | J12: 45854 | K12: NA | L12: 256779421371 | M12: 212100 | N12: Trade Debtors (Ctrl) | P12: 11 | Q12: USD | R12: -525 | S12: INR | T12: -45512.91 | U12: O0 | V12: 6779224500 | X12: NA | Y12: 1 | Z12: {=_xlfn.XLOOKUP(L12,'Customer Ledger'!$O:$O,'Customer Ledger'!$P:$Q,,0)} -> #N/A | AE12: Credit Note raised against INV_246779411278 | AI12: 45854 | AJ12: 45854 | AK12: 1400000290
A13: 6779 | B13: 100222332 | C13: SCOPE LOGISTICS SERVICES INDIA PVT. | D13: 2025 | E13: 7 | F13: 45854 | G13: 1800010651 | H13: DR | I13: 45854 | J13: 45855 | K13: NA | L13: 256779415411 | M13: 212100 | N13: Trade Debtors (Ctrl) | P13: 1 | Q13: USD | R13: 525 | S13: INR | T13: 45512.91 | U13: O0 | V13: 6779224500 | X13: NA | Y13: 1 | Z13: {=_xlfn.XLOOKUP(L13,'Customer Ledger'!$O:$O,'Customer Ledger'!$P:$Q,,0)} -> #N/A | AE13: Debit note Note raised against CN_256779421371 | AI13: 45854 | AJ13: 45854 | AK13: 1400000290
A14: 6779 | B14: 100222332 | C14: SCOPE LOGISTICS SERVICES INDIA PVT. | D14: 2025 | E14: 7 | F14: 45854 | G14: 1600001729 | H14: DG | I14: 45854 | J14: 45854 | K14: NA | L14: 256779421361 | M14: 212100 | N14: Trade Debtors (Ctrl) | P14: 11 | Q14: USD | R14: -364.25 | S14: INR | T14: -31577.29 | U14: O0 | V14: 6779224500 | X14: NA | Y14: 1 | Z14: {=_xlfn.XLOOKUP(L14,'Customer Ledger'!$O:$O,'Customer Ledger'!$P:$Q,,0)} -> 31577 | AA14: 0 | AB14: =AA14-Z14 -> -31577 | AC14: =T14-AB14 -> -0.29 | AD14: =AC14/T14 -> 9.1838153e-06 | AE14: Credit Note raised against INV_246779413702 | AI14: 45854 | AJ14: 45976 | AK14: 1400001901
A15: 6779 | B15: 100222332 | C15: SCOPE LOGISTICS SERVICES INDIA PVT. | D15: 2025 | E15: 7 | F15: 45854 | G15: 1600001730 | H15: DG | I15: 45854 | J15: 45854 | K15: NA | L15: 256779421362 | M15: 212100 | N15: Trade Debtors (Ctrl) | P15: 11 | Q15: USD | R15: -237.35 | S15: INR | T15: -20576.17 | U15: O0 | V15: 6779224500 | X15: NA | Y15: 1 | Z15: {=_xlfn.XLOOKUP(L15,'Customer Ledger'!$O:$O,'Customer Ledger'!$P:$Q,,0)} -> 19430 | AA15: 0 | AB15: =AA15-Z15 -> -19430 | AC15: =T15-AB15 -> -1146.17 | AD15: =AC15/T15 -> 0.055703758 | AE15: Credit Note raised against INV_246779413705 | AI15: 45854 | AJ15: 45976 | AK15: 1400001901
A16: 6779 | B16: 100222332 | C16: SCOPE LOGISTICS SERVICES INDIA PVT. | D16: 2025 | E16: 7 | F16: 45854 | G16: 1600001732 | H16: DG | I16: 45854 | J16: 45854 | K16: NA | L16: 256779421364 | M16: 212100 | N16: Trade Debtors (Ctrl) | P16: 11 | Q16: USD | R16: -220 | S16: INR | T16: -19072.08 | U16: O0 | V16: 6779224500 | X16: NA | Y16: 1 | Z16: {=_xlfn.XLOOKUP(L16,'Customer Ledger'!$O:$O,'Customer Ledger'!$P:$Q,,0)} -> 18611 | AA16: 0 | AB16: =AA16-Z16 -> -18611 | AC16: =T16-AB16 -> -461.08 | AD16: =AC16/T16 -> 0.024175654 | AE16: Credit Note raised against INV_246779413816 | AI16: 45854 | AJ16: 45976 | AK16: 1400001901
A17: 6779 | B17: 100222332 | C17: SCOPE LOGISTICS SERVICES INDIA PVT. | D17: 2025 | E17: 7 | F17: 45854 | G17: 1600001733 | H17: DG | I17: 45854 | J17: 45854 | K17: NA | L17: 256779421365 | M17: 212100 | N17: Trade Debtors (Ctrl) | P17: 11 | Q17: USD | R17: -375 | S17: INR | T17: -32509.22 | U17: O0 | V17: 6779224500 | X17: NA | Y17: 1 | Z17: {=_xlfn.XLOOKUP(L17,'Customer Ledger'!$O:$O,'Customer Ledger'!$P:$Q,,0)} -> 31723 | AA17: 0 | AB17: =AA17-Z17 -> -31723 | AC17: =T17-AB17 -> -786.22 | AD17: =AC17/T17 -> 0.024184524 | AE17: Credit Note raised against INV_246779413827 | AI17: 45854 | AJ17: 45976 | AK17: 1400001901
A18: 6779 | B18: 100222332 | C18: SCOPE LOGISTICS SERVICES INDIA PVT. | D18: 2025 | E18: 7 | F18: 45854 | G18: 1600001735 | H18: DG | I18: 45854 | J18: 45854 | K18: NA | L18: 256779421367 | M18: 212100 | N18: Trade Debtors (Ctrl) | P18: 11 | Q18: USD | R18: -1314.12 | S18: INR | T18: -114225.7 | U18: O0 | V18: 6779224500 | X18: NA | Y18: 1 | Z18: {=_xlfn.XLOOKUP(L18,'Customer Ledger'!$O:$O,'Customer Ledger'!$P:$Q,,0)} -> 114223 | AA18: 0 | AB18: =AA18-Z18 -> -114223 | AC18: =T18-AB18 -> -2.7 | AD18: =AC18/T18 -> 2.3637413e-05 | AE18: Credit Note raised against INV_256779410220 | AI18: 45854 | AJ18: 45976 | AK18: 1400001901
A19: 6779 | B19: 100222332 | C19: SCOPE LOGISTICS SERVICES INDIA PVT. | D19: 2025 | E19: 7 | F19: 45854 | G19: 1600001736 | H19: DG | I19: 45854 | J19: 45854 | K19: NA | L19: 256779421368 | M19: 212100 | N19: Trade Debtors (Ctrl) | P19: 11 | Q19: USD | R19: -705 | S19: INR | T19: -61279.88 | U19: O0 | V19: 6779224500 | X19: NA | Y19: 1 | Z19: {=_xlfn.XLOOKUP(L19,'Customer Ledger'!$O:$O,'Customer Ledger'!$P:$Q,,0)} -> 55272 | AA19: 0 | AB19: =AA19-Z19 -> -55272 | AC19: =T19-AB19 -> -6007.88 | AD19: =AC19/T19 -> 0.098040009 | AE19: Credit Note raised against INV_256779410004 | AI19: 45854 | AJ19: 45976 | AK19: 1400001901
A20: 6779 | B20: 100222332 | C20: SCOPE LOGISTICS SERVICES INDIA PVT. | D20: 2025 | E20: 7 | F20: 45854 | G20: 1600001737 | H20: DG | I20: 45854 | J20: 45854 | K20: NA | L20: 256779421369 | M20: 212100 | N20: Trade Debtors (Ctrl) | P20: 11 | Q20: USD | R20: -1793.99 | S20: INR | T20: -155936.88 | U20: O0 | V20: 6779224500 | X20: NA | Y20: 1 | Z20: {=_xlfn.XLOOKUP(L20,'Customer Ledger'!$O:$O,'Customer Ledger'!$P:$Q,,0)} -> 140649 | AA20: 0 | AB20: =AA20-Z20 -> -140649 | AC20: =T20-AB20 -> -15287.88 | AD20: =AC20/T20 -> 0.098038899 | AE20: Credit Note raised against INV_256779410010 | AI20: 45854 | AJ20: 45976 | AK20: 1400001901
A21: 6779 | B21: 100222332 | C21: SCOPE LOGISTICS SERVICES INDIA PVT. | D21: 2025 | E21: 7 | F21: 45854 | G21: 1600001738 | H21: DG | I21: 45854 | J21: 45854 | K21: NA | L21: 256779421370 | M21: 212100 | N21: Trade Debtors (Ctrl) | P21: 11 | Q21: USD | R21: -140 | S21: INR | T21: -12169.05 | U21: O0 | V21: 6779224500 | X21: NA | Y21: 1 | Z21: {=_xlfn.XLOOKUP(L21,'Customer Ledger'!$O:$O,'Customer Ledger'!$P:$Q,,0)} -> 12169 | AA21: 0 | AB21: =AA21-Z21 -> -12169 | AC21: =T21-AB21 -> -0.05 | AD21: =AC21/T21 -> 4.1087842e-06 | AE21: Credit Note raised against INV_256779411917 | AI21: 45854 | AJ21: 45976 | AK21: 1400001901
A22: 6779 | B22: 100222332 | C22: SCOPE LOGISTICS SERVICES INDIA PVT. | D22: 2025 | E22: 7 | F22: 45854 | G22: 1600001740 | H22: DG | I22: 45854 | J22: 45854 | K22: NA | L22: 256779421372 | M22: 212100 | N22: Trade Debtors (Ctrl) | P22: 11 | Q22: USD | R22: -385 | S22: INR | T22: -33376.14 | U22: O0 | V22: 6779224500 | X22: NA | Y22: 1 | Z22: {=_xlfn.XLOOKUP(L22,'Customer Ledger'!$O:$O,'Customer Ledger'!$P:$Q,,0)} -> 33376 | AA22: 0 | AB22: =AA22-Z22 -> -33376 | AC22: =T22-AB22 -> -0.14 | AD22: =AC22/T22 -> 4.1946133e-06 | AE22: Credit Note raised against INV_246779411300 | AI22: 45854 | AJ22: 45976 | AK22: 1400001901
A23: 6779 | B23: 100222332 | C23: SCOPE LOGISTICS SERVICES INDIA PVT. | D23: 2025 | E23: 7 | F23: 45854 | G23: 1600001741 | H23: DG | I23: 45854 | J23: 45854 | K23: NA | L23: 256779421373 | M23: 212100 | N23: Trade Debtors (Ctrl) | P23: 11 | Q23: USD | R23: -105 | S23: INR | T23: -9102.58 | U23: O0 | V23: 6779224500 | X23: NA | Y23: 1 | Z23: {=_xlfn.XLOOKUP(L23,'Customer Ledger'!$O:$O,'Customer Ledger'!$P:$Q,,0)} -> 8696 | AA23: 173 | AB23: =AA23-Z23 -> -8523 | AC23: =T23-AB23 -> -579.58 | AD23: =AC23/T23 -> 0.063672058 | AE23: Credit Note raised against INV_246779411314 | AI23: 45854 | AJ23: 45976 | AK23: 1400001901
A24: 6779 | B24: 100222332 | C24: SCOPE LOGISTICS SERVICES INDIA PVT. | D24: 2025 | E24: 7 | F24: 45854 | G24: 1600001742 | H24: DG | I24: 45854 | J24: 45854 | K24: NA | L24: 256779421374 | M24: 212100 | N24: Trade Debtors (Ctrl) | P24: 11 | Q24: USD | R24: -245 | S24: INR | T24: -21239.36 | U24: O0 | V24: 6779224500 | X24: NA | Y24: 1 | Z24: {=_xlfn.XLOOKUP(L24,'Customer Ledger'!$O:$O,'Customer Ledger'!$P:$Q,,0)} -> 20874 | AA24: 0 | AB24: =AA24-Z24 -> -20874 | AC24: =T24-AB24 -> -365.36 | AD24: =AC24/T24 -> 0.017202025 | AE24: Credit Note raised against INV_246779411326 | AI24: 45854 | AJ24: 45976 | AK24: 1400001901
A25: 6779 | B25: 100222332 | C25: SCOPE LOGISTICS SERVICES INDIA PVT. | D25: 2025 | E25: 7 | F25: 45854 | G25: 1600001743 | H25: DG | I25: 45854 | J25: 45854 | K25: NA | L25: 256779421375 | M25: 212100 | N25: Trade Debtors (Ctrl) | P25: 11 | Q25: USD | R25: -220 | S25: INR | T25: -19072.08 | U25: O0 | V25: 6779224500 | X25: NA | Y25: 1 | Z25: {=_xlfn.XLOOKUP(L25,'Customer Ledger'!$O:$O,'Customer Ledger'!$P:$Q,,0)} -> 17857 | AA25: 0 | AB25: =AA25-Z25 -> -17857 | AC25: =T25-AB25 -> -1215.08 | AD25: =AC25/T25 -> 0.063709884 | AE25: Credit Note raised against INV_246779411339 | AI25: 45854 | AJ25: 45976 | AK25: 1400001901
... A27: 6779 | B27: 100222332 | C27: SCOPE LOGISTICS SERVICES INDIA PVT. | D27: 2025 | E27: 7 | F27: 45854 | G27: 1600001745 | H27: DG | I27: 45854 | J27: 45854 | K27: NA | L27: 256779421377 | M27: 212100 | N27: Trade Debtors (Ctrl) | P27: 11 | Q27: USD | R27: -140 | S27: INR | T27: -12037.72 | U27: O0 | V27: 6779224500 | X27: NA | Y27: 1 | Z27: {=_xlfn.XLOOKUP(L27,'Customer Ledger'!$O:$O,'Customer Ledger'!$P:$Q,,0)} -> 11798 | AA27: 0 | AB27: =AA27-Z27 -> -11798 | AC27: =T27-AB27 -> -239.72 | AD27: =AC27/T27 -> 0.01991407 | AE27: Credit Note raised against INV_256779413283 | AI27: 45854 | AJ27: 45976 | AK27: 1400001901
A28: 6779 | B28: 100222332 | C28: SCOPE LOGISTICS SERVICES INDIA PVT. | D28: 2025 | E28: 7 | F28: 45854 | G28: 1600001746 | H28: DG | I28: 45854 | J28: 45854 | K28: NA | L28: 256779421378 | M28: 212100 | N28: Trade Debtors (Ctrl) | P28: 11 | Q28: USD | R28: -140 | S28: INR | T28: -12037.72 | U28: O0 | V28: 6779224500 | X28: NA | Y28: 1 | Z28: {=_xlfn.XLOOKUP(L28,'Customer Ledger'!$O:$O,'Customer Ledger'!$P:$Q,,0)} -> #N/A | AE28: Credit Note raised against INV_256779413861 | AI28: 45854 | AJ28: 45976 | AK28: 1400001901
A29: 6779 | B29: 100222332 | C29: SCOPE LOGISTICS SERVICES INDIA PVT. | D29: 2025 | E29: 7 | F29: 45854 | G29: 1600001747 | H29: DG | I29: 45854 | J29: 45854 | K29: NA | L29: 256779421379 | M29: 212100 | N29: Trade Debtors (Ctrl) | P29: 11 | Q29: USD | R29: -190 | S29: INR | T29: -16243.25 | U29: O0 | V29: 6779224500 | X29: NA | Y29: 1 | Z29: {=_xlfn.XLOOKUP(L29,'Customer Ledger'!$O:$O,'Customer Ledger'!$P:$Q,,0)} -> 17313 | AA29: 330 | AB29: =AA29-Z29 -> -16983 | AC29: =T29-AB29 -> 739.75 | AD29: =AC29/T29 -> -0.045541994 | AE29: Credit Note raised against INV_256779414288 | AI29: 45854 | AJ29: 45976 | AK29: 1400001901
A30: 6779 | B30: 100222332 | C30: SCOPE LOGISTICS SERVICES INDIA PVT. | D30: 2025 | E30: 7 | F30: 45854 | G30: 1600001748 | H30: DG | I30: 45854 | J30: 45855 | K30: NA | L30: 256779421380 | M30: 212100 | N30: Trade Debtors (Ctrl) | P30: 11 | Q30: USD | R30: -182.83 | S30: INR | T30: -15778.9 | U30: O0 | V30: 6779224500 | X30: NA | Y30: 1 | Z30: {=_xlfn.XLOOKUP(L30,'Customer Ledger'!$O:$O,'Customer Ledger'!$P:$Q,,0)} -> 15778 | AA30: 0 | AB30: =AA30-Z30 -> -15778 | AC30: =T30-AB30 -> -0.9 | AD30: =AC30/T30 -> 5.7038197e-05 | AE30: Credit note Note raised against INV_246779410348 | AI30: 45854 | AJ30: 45976 | AK30: 1400001902
A31: 6779 | B31: 100222332 | C31: SCOPE LOGISTICS SERVICES INDIA PVT. | D31: 2025 | E31: 7 | F31: 45854 | G31: 1600001749 | H31: DG | I31: 45854 | J31: 45855 | K31: NA | L31: 256779421381 | M31: 212100 | N31: Trade Debtors (Ctrl) | P31: 11 | Q31: USD | R31: -55.46 | S31: INR | T31: -4786.4 | U31: O0 | V31: 6779224500 | X31: NA | Y31: 1 | Z31: {=_xlfn.XLOOKUP(L31,'Customer Ledger'!$O:$O,'Customer Ledger'!$P:$Q,,0)} -> 4786 | AA31: 0 | AB31: =AA31-Z31 -> -4786 | AC31: =T31-AB31 -> -0.4 | AD31: =AC31/T31 -> 8.3570115e-05 | AE31: Credit note Note raised against INV_246779410360 | AI31: 45854 | AJ31: 45976 | AK31: 1400001902
A32: 6779 | B32: 100222332 | C32: SCOPE LOGISTICS SERVICES INDIA PVT. | D32: 2025 | E32: 7 | F32: 45854 | G32: 1600001750 | H32: DG | I32: 45854 | J32: 45855 | K32: NA | L32: 256779421382 | M32: 212100 | N32: Trade Debtors (Ctrl) | P32: 11 | Q32: USD | R32: -177.66 | S32: INR | T32: -15401.57 | U32: O0 | V32: 6779224500 | X32: NA | Y32: 1 | Z32: {=_xlfn.XLOOKUP(L32,'Customer Ledger'!$O:$O,'Customer Ledger'!$P:$Q,,0)} -> 15401 | AA32: 0 | AB32: =AA32-Z32 -> -15401 | AC32: =T32-AB32 -> -0.57 | AD32: =AC32/T32 -> 3.7009214e-05 | AE32: Credit note Note raised against INV_246779413701 | AI32: 45854 | AJ32: 45976 | AK32: 1400001902
A33: 6779 | B33: 100222332 | C33: SCOPE LOGISTICS SERVICES INDIA PVT. | D33: 2025 | E33: 7 | F33: 45854 | G33: 1600001751 | H33: DG | I33: 45854 | J33: 45855 | K33: NA | L33: 256779421383 | M33: 212100 | N33: Trade Debtors (Ctrl) | P33: 11 | Q33: USD | R33: -143.81 | S33: INR | T33: -12467.07 | U33: O0 | V33: 6779224500 | X33: NA | Y33: 1 | Z33: {=_xlfn.XLOOKUP(L33,'Customer Ledger'!$O:$O,'Customer Ledger'!$P:$Q,,0)} -> 12467 | AA33: 0 | AB33: =AA33-Z33 -> -12467 | AC33: =T33-AB33 -> -0.07 | AD33: =AC33/T33 -> 5.6147916e-06 | AE33: Credit note Note raised against INV_246779413796 | AI33: 45854 | AJ33: 45976 | AK33: 1400001902
A34: 6779 | B34: 100222332 | C34: SCOPE LOGISTICS SERVICES INDIA PVT. | D34: 2025 | E34: 7 | F34: 45854 | G34: 1600001752 | H34: DG | I34: 45854 | J34: 45855 | K34: NA | L34: 256779421384 | M34: 212100 | N34: Trade Debtors (Ctrl) | P34: 11 | Q34: USD | R34: -137.9 | S34: INR | T34: -11954.72 | U34: O0 | V34: 6779224500 | X34: NA | Y34: 1 | Z34: {=_xlfn.XLOOKUP(L34,'Customer Ledger'!$O:$O,'Customer Ledger'!$P:$Q,,0)} -> 11955 | AA34: 0 | AB34: =AA34-Z34 -> -11955 | AC34: =T34-AB34 -> 0.28 | AD34: =AC34/T34 -> -2.3421711e-05 | AE34: Credit note Note raised against INV_246779413845 | AI34: 45854 | AJ34: 45976 | AK34: 1400001902
A35: 6779 | B35: 100222332 | C35: SCOPE LOGISTICS SERVICES INDIA PVT. | D35: 2025 | E35: 7 | F35: 45854 | G35: 1600001753 | H35: DG | I35: 45854 | J35: 45855 | K35: NA | L35: 256779421385 | M35: 212100 | N35: Trade Debtors (Ctrl) | P35: 11 | Q35: USD | R35: -420 | S35: INR | T35: -36410.33 | U35: O0 | V35: 6779224500 | X35: NA | Y35: 1 | Z35: {=_xlfn.XLOOKUP(L35,'Customer Ledger'!$O:$O,'Customer Ledger'!$P:$Q,,0)} -> 36410 | AA35: 0 | AB35: =AA35-Z35 -> -36410 | AC35: =T35-AB35 -> -0.33 | AD35: =AC35/T35 -> 9.063362e-06 | AE35: Credit note Note raised against INV_246779411278 | AI35: 45854 | AJ35: 45976 | AK35: 1400001902
A36: 6779 | B36: 100222332 | C36: SCOPE LOGISTICS SERVICES INDIA PVT. | D36: 2025 | E36: 5 | F36: 45797 | G36: 1800008722 | H36: DR | I36: 45797 | J36: 45805 | K36: NA | L36: 256779413486 | M36: 212100 | N36: Trade Debtors (Ctrl) | P36: 1 | Q36: USD | R36: 12.5 | S36: INR | T36: 1074.8 | U36: O0 | V36: 6779224500 | X36: NA | Y36: 1 | Z36: {=_xlfn.XLOOKUP(L36,'Customer Ledger'!$O:$O,'Customer Ledger'!$P:$Q,,0)} -> 0 | AA36: 1054 | AB36: =AA36-Z36 -> 1054 | AC36: =T36-AB36 -> 20.8 | AD36: =AC36/T36 -> 0.019352438 | AE36: Outbound chgs - 01 - 15 MAY 25 | AI36: 45797
A37: 6779 | B37: 100222332 | C37: SCOPE LOGISTICS SERVICES INDIA PVT. | D37: 2025 | E37: 5 | F37: 45797 | G37: 1800009073 | H37: DR | I37: 45797 | J37: 45805 | K37: NA | L37: 256779413837 | M37: 212100 | N37: Trade Debtors (Ctrl) | P37: 1 | Q37: USD | R37: 144.52 | S37: INR | T37: 12426.36 | U37: O0 | V37: 6779224500 | Y37: 1 | Z37: {=_xlfn.XLOOKUP(L37,'Customer Ledger'!$O:$O,'Customer Ledger'!$P:$Q,,0)} -> 0 | AA37: 12177 | AB37: =AA37-Z37 -> 12177 | AC37: =T37-AB37 -> 249.36 | AD37: =AC37/T37 -> 0.020067019 | AE37: VAS -1-15 May 25, Ex.rate 85.43 | AI37: 45797
A38: 6779 | B38: 100222332 | C38: SCOPE LOGISTICS SERVICES INDIA PVT. | D38: 2025 | E38: 5 | F38: 45797 | G38: 1600001822 | H38: DG | I38: 45862 | J38: 45862 | K38: NA | L38: 256779421442 | M38: 212100 | N38: Trade Debtors (Ctrl) | P38: 11 | Q38: USD | R38: -111.15 | S38: INR | T38: -9557.09 | U38: O0 | V38: 6779224500 | X38: NA | Y38: 1 | Z38: {=_xlfn.XLOOKUP(L38,'Customer Ledger'!$O:$O,'Customer Ledger'!$P:$Q,,0)} -> #N/A | AE38: Credit Note raised against 256779413885 | AI38: 45862 | AJ38: 45976 | AK38: 1400001901
A39: 6779 | B39: 100222332 | C39: SCOPE LOGISTICS SERVICES INDIA PVT. | D39: 2025 | E39: 4 | F39: 45750 | G39: 1800001031 | H39: DR | I39: 45722 | J39: 45722 | K39: NA | L39: 246779410971 | M39: 212100 | N39: Trade Debtors (Ctrl) | P39: 1 | Q39: USD | R39: 1205.2 | S39: INR | T39: 104480.31 | U39: O0 | V39: 6779224500 | X39: NA | Y39: 1 | Z39: {=_xlfn.XLOOKUP(L39,'Customer Ledger'!$O:$O,'Customer Ledger'!$P:$Q,,0)} -> 0 | AA39: 36538 | AB39: =AA39-Z39 -> 36538 | AC39: =T39-AB39 -> 67942.31 | AD39: =AC39/T39 -> 0.65028817 | AE39: Inbound Handling charges for Aug 2024 | AI39: 45722
A40: 6779 | B40: 100222332 | C40: SCOPE LOGISTICS SERVICES INDIA PVT. | D40: 2025 | E40: 4 | F40: 45750 | G40: 1800007792 | H40: DR | I40: 45769 | J40: 45770 | K40: NA | L40: 256779412683 | M40: 212100 | N40: Trade Debtors (Ctrl) | P40: 1 | Q40: USD | R40: 517.64 | S40: INR | T40: 44994.21 | U40: O0 | V40: 6779224500 | X40: NA | Y40: 1 | Z40: {=_xlfn.XLOOKUP(L40,'Customer Ledger'!$O:$O,'Customer Ledger'!$P:$Q,,0)} -> 0 | AA40: 43195 | AB40: =AA40-Z40 -> 43195 | AC40: =T40-AB40 -> 1799.21 | AD40: =AC40/T40 -> 0.03998759 | AE40: Outbound Handling charges for 31 Mar 25 | AI40: 45769
A41: 6779 | B41: 100222332 | C41: SCOPE LOGISTICS SERVICES INDIA PVT. | D41: 2025 | E41: 4 | F41: 45750 | G41: 1800004735 | H41: DR | I41: 45736 | J41: 45737 | K41: NA | L41: 246779414603 | M41: 212100 | N41: Trade Debtors (Ctrl) | P41: 1 | Q41: USD | R41: 412.38 | S41: INR | T41: 35749.74 | U41: O0 | V41: 6779224500 | X41: NA | Y41: 1 | Z41: {=_xlfn.XLOOKUP(L41,'Customer Ledger'!$O:$O,'Customer Ledger'!$P:$Q,,0)} -> 0 | AA41: 34760 | AB41: =AA41-Z41 -> 34760 | AC41: =T41-AB41 -> 989.74 | AD41: =AC41/T41 -> 0.027685236 | AE41: Outbound Handling charges for Oct 2024 | AI41: 45736
A42: 6779 | B42: 100222332 | C42: SCOPE LOGISTICS SERVICES INDIA PVT. | D42: 2025 | E42: 4 | F42: 45750 | G42: 1800005265 | H42: DR | I42: 45750 | J42: 45752 | K42: NA | L42: 256779410157 | M42: 212100 | N42: Trade Debtors (Ctrl) | P42: 1 | Q42: USD | R42: 34.48 | S42: INR | T42: 2997.06 | U42: O0 | X42: NA | Y42: 1 | Z42: {=_xlfn.XLOOKUP(L42,'Customer Ledger'!$O:$O,'Customer Ledger'!$P:$Q,,0)} -> 0 | AA42: 2883 | AB42: =AA42-Z42 -> 2883 | AC42: =T42-AB42 -> 114.06 | AD42: =AC42/T42 -> 0.038057296 | AE42: MHE Charges for Mar 25 | AI42: 45750
A43: 6779 | B43: 100222332 | C43: SCOPE LOGISTICS SERVICES INDIA PVT. | D43: 2025 | E43: 4 | F43: 45750 | G43: 1800004353 | H43: DR | I43: 45736 | J43: 45737 | K43: NA | L43: 246779414221 | M43: 212100 | N43: Trade Debtors (Ctrl) | P43: 1 | Q43: USD | R43: 209.25 | S43: INR | T43: 18140.15 | U43: O0 | V43: 6779224500 | X43: NA | Y43: 1 | Z43: {=_xlfn.XLOOKUP(L43,'Customer Ledger'!$O:$O,'Customer Ledger'!$P:$Q,,0)} -> 0 | AA43: 17701 | AB43: =AA43-Z43 -> 17701 | AC43: =T43-AB43 -> 439.15 | AD43: =AC43/T43 -> 0.02420873 | AE43: Outbound Handling charges for Sep 2024 | AI43: 45736
A44: 6779 | B44: 100222332 | C44: SCOPE LOGISTICS SERVICES INDIA PVT. | D44: 2025 | E44: 4 | F44: 45750 | G44: 1800007577 | H44: DR | I44: 45769 | J44: 45770 | K44: NA | L44: 256779412468 | M44: 212100 | N44: Trade Debtors (Ctrl) | P44: 1 | Q44: USD | R44: 169.2 | S44: INR | T44: 14707.17 | U44: O0 | V44: 6779224500 | X44: NA | Y44: 1 | Z44: {=_xlfn.XLOOKUP(L44,'Customer Ledger'!$O:$O,'Customer Ledger'!$P:$Q,,0)} -> 0 | AA44: 14119 | AB44: =AA44-Z44 -> 14119 | AC44: =T44-AB44 -> 588.17 | AD44: =AC44/T44 -> 0.039992058 | AE44: Inbound Handling charges for Feb 2025 | AI44: 45769
A45: 6779 | B45: 100222332 | C45: SCOPE LOGISTICS SERVICES INDIA PVT. | D45: 2025 | E45: 4 | F45: 45750 | G45: 1800005309 | H45: DR | I45: 45750 | J45: 45752 | K45: NA | L45: 256779410201 | M45: 212100 | N45: Trade Debtors (Ctrl) | P45: 1 | Q45: USD | R45: 34.48 | S45: INR | T45: 2997.06 | U45: O0 | X45: NA | Y45: 1 | Z45: {=_xlfn.XLOOKUP(L45,'Customer Ledger'!$O:$O,'Customer Ledger'!$P:$Q,,0)} -> 0 | AA45: 2937 | AB45: =AA45-Z45 -> 2937 | AC45: =T45-AB45 -> 60.06 | AD45: =AC45/T45 -> 0.020039639 | AE45: VAS Activity -1 -15 Mar 25, Ex Rate. 87.01 | AI45: 45750
A46: 6779 | B46: 100222332 | C46: SCOPE LOGISTICS SERVICES INDIA PVT. | D46: 2025 | E46: 4 | F46: 45750 | G46: 1800005399 | H46: DR | I46: 45750 | J46: 45752 | K46: NA | L46: 256779410291 | M46: 212100 | N46: Trade Debtors (Ctrl) | P46: 1 | Q46: USD | R46: 456.75 | S46: INR | T46: 39701.54 | U46: O0 | X46: NA | Y46: 1 | Z46: {=_xlfn.XLOOKUP(L46,'Customer Ledger'!$O:$O,'Customer Ledger'!$P:$Q,,0)} -> #N/A | AE46: Fixed Rental charges for Feb 2025 | AI46: 45750 | AJ46: 45842 | AK46: 1400000246
A47: 6779 | B47: 100222332 | C47: SCOPE LOGISTICS SERVICES INDIA PVT. | D47: 2025 | E47: 4 | F47: 45750 | G47: 1800005358 | H47: DR | I47: 45750 | J47: 45752 | K47: NA | L47: 256779410250 | M47: 212100 | N47: Trade Debtors (Ctrl) | P47: 1 | Q47: USD | R47: 456.75 | S47: INR | T47: 39701.54 | U47: O0 | X47: NA | Y47: 1 | Z47: {=_xlfn.XLOOKUP(L47,'Customer Ledger'!$O:$O,'Customer Ledger'!$P:$Q,,0)} -> #N/A | AE47: Fixed Rental charges for Jan 2025 | AI47: 45750 | AJ47: 45842 | AK47: 1400000247
A48: 6779 | B48: 100222332 | C48: SCOPE LOGISTICS SERVICES INDIA PVT. | D48: 2025 | E48: 4 | F48: 45750 | G48: 1600002471 | H48: DG | I48: 45947 | J48: 45953 | K48: NA | L48: 256779422013 | M48: 212100 | N48: Trade Debtors (Ctrl) | P48: 11 | Q48: USD | R48: -582.8 | S48: INR | T48: -51397.58 | U48: O0 | V48: 6779224500 | X48: 2117487 | Y48: 1 | Z48: {=_xlfn.XLOOKUP(L48,'Customer Ledger'!$O:$O,'Customer Ledger'!$P:$Q,,0)} -> #N/A | AE48: Credit note raised against 256779418075 | AI48: 45947 | AJ48: 45976 | AK48: 1400001901
A49: 6779 | B49: 100222332 | C49: SCOPE LOGISTICS SERVICES INDIA PVT. | D49: 2025 | E49: 4 | F49: 45750 | G49: 1800009121 | H49: DR | I49: 45797 | J49: 45805 | K49: NA | L49: 256779413885 | M49: 212100 | N49: Trade Debtors (Ctrl) | P49: 1 | Q49: USD | R49: 111.15 | S49: INR | T49: 9557.09 | U49: O0 | V49: 6779224500 | X49: NA | Y49: 1 | Z49: {=_xlfn.XLOOKUP(L49,'Customer Ledger'!$O:$O,'Customer Ledger'!$P:$Q,,0)} -> #N/A | AE49: Inbound chgs -01-15 MAY 25 | AI49: 45797 | AJ49: 45976 | AK49: 1400001901
A50: 6779 | B50: 100222332 | C50: SCOPE LOGISTICS SERVICES INDIA PVT. | D50: 2025 | E50: 4 | F50: 45750 | G50: 1800005058 | H50: DR | I50: 45750 | J50: 45752 | K50: NA | L50: 256779410004 | M50: 212100 | N50: Trade Debtors (Ctrl) | P50: 1 | Q50: USD | R50: 705 | S50: INR | T50: 61279.88 | U50: O0 | X50: NA | Y50: 1 | Z50: {=_xlfn.XLOOKUP(L50,'Customer Ledger'!$O:$O,'Customer Ledger'!$P:$Q,,0)} -> 0 | AA50: 55272 | AB50: =AA50-Z50 -> 55272 | AC50: =T50-AB50 -> 6007.88 | AD50: =AC50/T50 -> 0.098040009 | AE50: CY Longstanding container Ground Rent charges for | AI50: 45750 | AJ50: 45976 | AK50: 1400001901
A51: 6779 | B51: 100222332 | C51: SCOPE LOGISTICS SERVICES INDIA PVT. | D51: 2025 | E51: 10 | F51: 45950 | G51: 1800013971 | H51: DR | I51: 45950 | J51: 45951 | K51: NA | L51: 256779418614 | M51: 212100 | N51: Trade Debtors (Ctrl) | P51: 1 | Q51: USD | R51: 338.06 | S51: INR | T51: 29813.77 | U51: O0 | V51: 6779224500 | X51: 2114876 | Y51: 1 | Z51: {=_xlfn.XLOOKUP(L51,'Customer Ledger'!$O:$O,'Customer Ledger'!$P:$Q,,0)} -> #N/A | AE51: CY - CY Grd Rent Chgs - 01 - 15 OCT 25 | AI51: 45950
A52: 6779 | B52: 100222332 | C52: SCOPE LOGISTICS SERVICES INDIA PVT. | D52: 2025 | E52: 10 | F52: 45950 | G52: 1800014013 | H52: DR | I52: 45950 | J52: 45951 | K52: NA | L52: 256779418620 | M52: 212100 | N52: Trade Debtors (Ctrl) | P52: 1 | Q52: USD | R52: 830.96 | S52: INR | T52: 73283 | U52: O0 | V52: 6779224500 | X52: 2114877 | Y52: 1 | Z52: {=_xlfn.XLOOKUP(L52,'Customer Ledger'!$O:$O,'Customer Ledger'!$P:$Q,,0)} -> #N/A | AE52: CY Ground rent Chgs - 01 - 15 Oct 25 | AI52: 45950
A53: 6779 | B53: 100222332 | C53: SCOPE LOGISTICS SERVICES INDIA PVT. | D53: 2025 | E53: 10 | F53: 45950 | G53: 1800013843 | H53: DR | I53: 45950 | J53: 45951 | K53: NA | L53: 256779418661 | M53: 212100 | N53: Trade Debtors (Ctrl) | P53: 1 | Q53: USD | R53: 226.3 | S53: INR | T53: 19957.57 | U53: O0 | V53: 6779224500 | X53: 2114881 | Y53: 1 | Z53: {=_xlfn.XLOOKUP(L53,'Customer Ledger'!$O:$O,'Customer Ledger'!$P:$Q,,0)} -> #N/A | AE53: Inbound chgs - 01 - 15 OCT 25 | AI53: 45950
A54: 6779 | B54: 100222332 | C54: SCOPE LOGISTICS SERVICES INDIA PVT. | D54: 2025 | E54: 10 | F54: 45950 | G54: 1800013925 | H54: DR | I54: 45950 | J54: 45951 | K54: NA | L54: 256779418702 | M54: 212100 | N54: Trade Debtors (Ctrl) | P54: 1 | Q54: USD | R54: 182.87 | S54: INR | T54: 16127.45 | U54: O0 | V54: 6779224500 | X54: 2114883 | Y54: 1 | Z54: {=_xlfn.XLOOKUP(L54,'Customer Ledger'!$O:$O,'Customer Ledger'!$P:$Q,,0)} -> #N/A | AE54: Outbound chgs - 01 - 15 Oct 25 | AI54: 45950
A55: 6779 | B55: 100222332 | C55: SCOPE LOGISTICS SERVICES INDIA PVT. | D55: 2025 | E55: 4 | F55: 45768 | G55: 1800007270 | H55: DR | I55: 45768 | J55: 45769 | K55: NA | L55: 256779412161 | M55: 212100 | N55: Trade Debtors (Ctrl) | P55: 1 | Q55: USD | R55: 456.75 | S55: INR | T55: 39193.72 | U55: O0 | V55: 6779224500 | X55: NA | Y55: 1 | Z55: {=_xlfn.XLOOKUP(L55,'Customer Ledger'!$O:$O,'Customer Ledger'!$P:$Q,,0)} -> 0 | AA55: 34962 | AB55: =AA55-Z55 -> 34962 | AC55: =T55-AB55 -> 4231.72 | AD55: =AC55/T55 -> 0.10796934 | AE55: Fixed Storage Charges for April 2025 | AI55: 45768
A56: 6779 | B56: 100222332 | C56: SCOPE LOGISTICS SERVICES INDIA PVT. | D56: 2025 | E56: 7 | F56: 45862 | G56: 1600001816 | H56: DG | I56: 45862 | J56: 45862 | K56: NA | L56: 256779421436 | M56: 212100 | N56: Trade Debtors (Ctrl) | P56: 11 | Q56: USD | R56: -140 | S56: INR | T56: -12037.72 | U56: O0 | V56: 6779224500 | X56: NA | Y56: 1 | Z56: {=_xlfn.XLOOKUP(L56,'Customer Ledger'!$O:$O,'Customer Ledger'!$P:$Q,,0)} -> #N/A | AE56: Credit Note raised against 256779413861 | AI56: 45862
A57: 6779 | B57: 100222332 | C57: SCOPE LOGISTICS SERVICES INDIA PVT. | D57: 2025 | E57: 7 | F57: 45862 | G57: 1800011187 | H57: DR | I57: 45862 | J57: 45862 | K57: NA | L57: 256779415939 | M57: 212100 | N57: Trade Debtors (Ctrl) | P57: 1 | Q57: USD | R57: 140 | S57: INR | T57: 12040.09 | U57: O0 | V57: 6779224500 | X57: NA | Y57: 1 | Z57: {=_xlfn.XLOOKUP(L57,'Customer Ledger'!$O:$O,'Customer Ledger'!$P:$Q,,0)} -> 0 | AA57: 11782.092 | AB57: =AA57-Z57 -> 11782.092 | AC57: =T57-AB57 -> 257.9982 | AD57: =AC57/T57 -> 0.021428262 | AE57: Scanning Chgs - 01 - 15 May 25 | AI57: 45862
A58: 6779 | B58: 100222332 | C58: SCOPE LOGISTICS SERVICES INDIA PVT. | D58: 2025 | E58: 7 | F58: 45862 | G58: 1800011193 | H58: DR | I58: 45862 | J58: 45862 | K58: NA | L58: 256779415945 | M58: 212100 | N58: Trade Debtors (Ctrl) | P58: 1 | Q58: USD | R58: 111.15 | S58: INR | T58: 9558.97 | U58: O0 | V58: 6779224500 | X58: NA | Y58: 1 | Z58: {=_xlfn.XLOOKUP(L58,'Customer Ledger'!$O:$O,'Customer Ledger'!$P:$Q,,0)} -> 0 | AA58: 9368 | AB58: =AA58-Z58 -> 9368 | AC58: =T58-AB58 -> 190.97 | AD58: =AC58/T58 -> 0.019978094 | AE58: Inbound chgs -01-15 MAY 25 | AI58: 45862
A59: 6779 | B59: 100222332 | C59: SCOPE LOGISTICS SERVICES INDIA PVT. | D59: 2025 | E59: 7 | F59: 45862 | G59: 1600001906 | H59: DG | I59: 45862 | J59: 45862 | K59: NA | L59: 256779421526 | M59: 212100 | N59: Trade Debtors (Ctrl) | P59: 11 | Q59: USD | R59: -456.75 | S59: INR | T59: -39280.81 | U59: O0 | V59: 6779224500 | X59: NA | Y59: 1 | Z59: {=_xlfn.XLOOKUP(L59,'Customer Ledger'!$O:$O,'Customer Ledger'!$P:$Q,,0)} -> #N/A | AE59: Credit note raised against 256779414459 | AI59: 45862 | AJ59: 45902 | AK59: 1400001112
A60: 6779 | B60: 100222332 | C60: SCOPE LOGISTICS SERVICES INDIA PVT. | D60: 2025 | E60: 7 | F60: 45862 | G60: 1600001923 | H60: DG | I60: 45862 | J60: 45862 | K60: NA | L60: 256779421543 | M60: 212100 | N60: Trade Debtors (Ctrl) | P60: 11 | Q60: USD | R60: -456.75 | S60: INR | T60: -39280.81 | U60: O0 | V60: 6779224500 | X60: NA | Y60: 1 | Z60: {=_xlfn.XLOOKUP(L60,'Customer Ledger'!$O:$O,'Customer Ledger'!$P:$Q,,0)} -> #N/A | AE60: Credit note raised against 256779414476 | AI60: 45862 | AJ60: 45902 | AK60: 1400001112
A61: 6779 | B61: 100222332 | C61: SCOPE LOGISTICS SERVICES INDIA PVT. | D61: 2025 | E61: 7 | F61: 45862 | G61: 1800005064 | H61: DR | I61: 45750 | J61: 45752 | K61: NA | L61: 256779410010 | M61: 212100 | N61: Trade Debtors (Ctrl) | P61: 1 | Q61: USD | R61: 1793.99 | S61: INR | T61: 155936.88 | U61: O0 | X61: NA | Y61: 1 | Z61: {=_xlfn.XLOOKUP(L61,'Customer Ledger'!$O:$O,'Customer Ledger'!$P:$Q,,0)} -> 0 | AA61: 140649 | AB61: =AA61-Z61 -> 140649 | AC61: =T61-AB61 -> 15287.88 | AD61: =AC61/T61 -> 0.098038899 | AE61: CY Longstanding container Ground Rent charges for | AI61: 45750 | AJ61: 45976 | AK61: 1400001901
A62: 6779 | B62: 100222332 | C62: SCOPE LOGISTICS SERVICES INDIA PVT. | D62: 2025 | E62: 5 | F62: 45798 | G62: 1800008640 | H62: DR | I62: 45798 | J62: 45800 | K62: NA | L62: 256779413404 | M62: 212100 | N62: Trade Debtors (Ctrl) | P62: 1 | Q62: USD | R62: 84.6 | S62: INR | T62: 7274.22 | U62: O0 | V62: 6779224500 | X62: NA | Y62: 1 | Z62: {=_xlfn.XLOOKUP(L62,'Customer Ledger'!$O:$O,'Customer Ledger'!$P:$Q,,0)} -> 0 | AA62: 7129 | AB62: =AA62-Z62 -> 7129 | AC62: =T62-AB62 -> 145.22 | AD62: =AC62/T62 -> 0.019963652 | AE62: InKPI-CODC-1-15 May 25-BOE9790661 | AI62: 45798
A63: 6779 | B63: 100222332 | C63: SCOPE LOGISTICS SERVICES INDIA PVT. | D63: 2025 | E63: 5 | F63: 45798 | G63: 1800008641 | H63: DR | I63: 45798 | J63: 45800 | K63: NA | L63: 256779413405 | M63: 212100 | N63: Trade Debtors (Ctrl) | P63: 1 | Q63: USD | R63: 47 | S63: INR | T63: 4041.23 | U63: O0 | V63: 6779224500 | X63: NA | Y63: 1 | Z63: {=_xlfn.XLOOKUP(L63,'Customer Ledger'!$O:$O,'Customer Ledger'!$P:$Q,,0)} -> 0 | AA63: 3960 | AB63: =AA63-Z63 -> 3960 | AC63: =T63-AB63 -> 81.23 | AD63: =AC63/T63 -> 0.020100316 | AE63: InKPI-CODC-1-15 May 25-BOE9862672 | AI63: 45798
A64: 6779 | B64: 100222332 | C64: SCOPE LOGISTICS SERVICES INDIA PVT. | D64: 2025 | E64: 5 | F64: 45798 | G64: 1800008665 | H64: DR | I64: 45798 | J64: 45800 | K64: NA | L64: 256779413429 | M64: 212100 | N64: Trade Debtors (Ctrl) | P64: 1 | Q64: USD | R64: 7.05 | S64: INR | T64: 606.19 | U64: O0 | V64: 6779224500 | X64: NA | Y64: 1 | Z64: {=_xlfn.XLOOKUP(L64,'Customer Ledger'!$O:$O,'Customer Ledger'!$P:$Q,,0)} -> 0 | AA64: 601 | AB64: =AA64-Z64 -> 601 | AC64: =T64-AB64 -> 5.19 | AD64: =AC64/T64 -> 0.0085616721 | AE64: OutKPI-CODC-1-15-MAY-25-9960786 | AI64: 45798
A65: 6779 | B65: 100222332 | C65: SCOPE LOGISTICS SERVICES INDIA PVT. | D65: 2025 | E65: 5 | F65: 45798 | G65: 1800008666 | H65: DR | I65: 45798 | J65: 45800 | K65: NA | L65: 256779413430 | M65: 212100 | N65: Trade Debtors (Ctrl) | P65: 1 | Q65: USD | R65: 14.1 | S65: INR | T65: 1212.37 | U65: O0 | V65: 6779224500 | X65: NA | Y65: 1 | Z65: {=_xlfn.XLOOKUP(L65,'Customer Ledger'!$O:$O,'Customer Ledger'!$P:$Q,,0)} -> 0 | AA65: 1201 | AB65: =AA65-Z65 -> 1201 | AC65: =T65-AB65 -> 11.37 | AD65: =AC65/T65 -> 0.0093783251 | AE65: OutKPI-CODC-1-15-MAY-25-20045577 | AI65: 45798
A66: 6779 | B66: 100222332 | C66: SCOPE LOGISTICS SERVICES INDIA PVT. | D66: 2025 | E66: 4 | F66: 45771 | G66: 1800007886 | H66: DR | I66: 45771 | J66: 45773 | K66: NA | L66: 256779412777 | M66: 212100 | N66: Trade Debtors (Ctrl) | P66: 1 | Q66: USD | R66: 95.39 | S66: INR | T66: 8291.47 | U66: O0 | V66: 6779224500 | X66: NA | Y66: 1 | Z66: {=_xlfn.XLOOKUP(L66,'Customer Ledger'!$O:$O,'Customer Ledger'!$P:$Q,,0)} -> 0 | AA66: 7981 | AB66: =AA66-Z66 -> 7981 | AC66: =T66-AB66 -> 310.47 | AD66: =AC66/T66 -> 0.037444506 | AE66: VAS 1-15 April-25,Ex.Rate-85.69 | AI66: 45771
A67: 6779 | B67: 100222332 | C67: SCOPE LOGISTICS SERVICES INDIA PVT. | D67: 2025 | E67: 6 | F67: 45826 | G67: 1800009994 | H67: DR | I67: 45826 | J67: 45829 | K67: NA | L67: 256779414758 | M67: 212100 | N67: Trade Debtors (Ctrl) | P67: 1 | Q67: USD | R67: 173.9 | S67: INR | T67: 14866.85 | U67: O0 | V67: 6779224500 | X67: NA | Y67: 1 | Z67: {=_xlfn.XLOOKUP(L67,'Customer Ledger'!$O:$O,'Customer Ledger'!$P:$Q,,0)} -> 0 | AA67: 14610.374 | AB67: =AA67-Z67 -> 14610.374 | AC67: =T67-AB67 -> 256.4757 | AD67: =AC67/T67 -> 0.017251516 | AE67: CODC Out chgs - 01 - 15 Jun 25 | AI67: 45826
A68: 6779 | B68: 100222332 | C68: SCOPE LOGISTICS SERVICES INDIA PVT. | D68: 2025 | E68: 6 | F68: 45826 | G68: 1800009695 | H68: DR | I68: 45826 | J68: 45827 | K68: NA | L68: 256779414459 | M68: 212100 | N68: Trade Debtors (Ctrl) | P68: 1 | Q68: USD | R68: 456.75 | S68: INR | T68: 39047.91 | U68: O0 | V68: 6779224500 | X68: NA | Y68: 1 | Z68: {=_xlfn.XLOOKUP(L68,'Customer Ledger'!$O:$O,'Customer Ledger'!$P:$Q,,0)} -> #N/A | AE68: Fixed Rental charges for Jan 2025 | AI68: 45826 | AJ68: 45902 | AK68: 1400001112
A69: 6779 | B69: 100222332 | C69: SCOPE LOGISTICS SERVICES INDIA PVT. | D69: 2025 | E69: 6 | F69: 45826 | G69: 1800009712 | H69: DR | I69: 45826 | J69: 45827 | K69: NA | L69: 256779414476 | M69: 212100 | N69: Trade Debtors (Ctrl) | P69: 1 | Q69: USD | R69: 456.75 | S69: INR | T69: 39047.91 | U69: O0 | V69: 6779224500 | X69: NA | Y69: 1 | Z69: {=_xlfn.XLOOKUP(L69,'Customer Ledger'!$O:$O,'Customer Ledger'!$P:$Q,,0)} -> #N/A | AE69: Fixed Rental charges for Feb 2025 | AI69: 45826 | AJ69: 45902 | AK69: 1400001112
A70: 6779 | B70: 100222332 | C70: SCOPE LOGISTICS SERVICES INDIA PVT. | D70: 2025 | E70: 10 | F70: 45951 | G70: 1800013945 | H70: DR | I70: 45951 | J70: 45951 | K70: NA | L70: 256779418477 | M70: 212100 | N70: Trade Debtors (Ctrl) | P70: 1 | Q70: USD | R70: 3.4 | S70: INR | T70: 299.85 | U70: O0 | V70: 6779224500 | X70: 2114868 | Y70: 1 | Z70: {=_xlfn.XLOOKUP(L70,'Customer Ledger'!$O:$O,'Customer Ledger'!$P:$Q,,0)} -> 0 | AA70: 299.8486 | AB70: =AA70-Z70 -> 299.8486 | AC70: =T70-AB70 -> 0.0014 | AD70: =AC70/T70 -> 4.6690012e-06 | AE70: VAS -1-15 Oct 2025 | AI70: 45951
A71: 6779 | B71: 100222332 | C71: SCOPE LOGISTICS SERVICES INDIA PVT. | D71: 2025 | E71: 10 | F71: 45951 | G71: 1800013962 | H71: DR | I71: 45951 | J71: 45951 | K71: NA | L71: 256779418492 | M71: 212100 | N71: Trade Debtors (Ctrl) | P71: 1 | Q71: USD | R71: 3.4 | S71: INR | T71: 299.85 | U71: O0 | V71: 6779224500 | X71: 2114868 | Y71: 1 | Z71: {=_xlfn.XLOOKUP(L71,'Customer Ledger'!$O:$O,'Customer Ledger'!$P:$Q,,0)} -> 6 | AA71: 306 | AB71: =AA71-Z71 -> 300 | AC71: =T71-AB71 -> -0.15 | AD71: =AC71/T71 -> -0.00050025013 | AE71: VAS -1-15 Oct 2025 | AI71: 45951
A72: 6779 | B72: 100222332 | C72: SCOPE LOGISTICS SERVICES INDIA PVT. | D72: 2025 | E72: 3 | F72: 45735 | G72: 1800003133 | H72: DR | I72: 45735 | J72: 45736 | K72: NA | L72: 246779413000 | M72: 212100 | N72: Trade Debtors (Ctrl) | P72: 1 | Q72: USD | R72: 456.75 | S72: INR | T72: 39596.23 | U72: O0 | V72: 6779224500 | X72: NA | Y72: 1 | Z72: {=_xlfn.XLOOKUP(L72,'Customer Ledger'!$O:$O,'Customer Ledger'!$P:$Q,,0)} -> 0 | AA72: 35488 | AB72: =AA72-Z72 -> 35488 | AC72: =T72-AB72 -> 4108.23 | AD72: =AC72/T72 -> 0.10375306 | AE72: Fixed Storage Charges for Mar 2025 | AI72: 45735
A73: 6779 | B73: 100222332 | C73: SCOPE LOGISTICS SERVICES INDIA PVT. | D73: 2025 | E73: 3 | F73: 45735 | G73: 1800003342 | H73: DR | I73: 45735 | J73: 45736 | K73: NA | L73: 246779413209 | M73: 212100 | N73: Trade Debtors (Ctrl) | P73: 1 | Q73: USD | R73: 39.06 | S73: INR | T73: 3386.16 | U73: O0 | V73: 6779224500 | X73: NA | Y73: 1 | Z73: {=_xlfn.XLOOKUP(L73,'Customer Ledger'!$O:$O,'Customer Ledger'!$P:$Q,,0)} -> #N/A | AE73: HMMU6832693-Port SSR Shifting Jan 2025. Exch rate | AI73: 45735
A74: 6779 | B74: 100222332 | C74: SCOPE LOGISTICS SERVICES INDIA PVT. | D74: 2025 | E74: 3 | F74: 45735 | G74: 1800003343 | H74: DR | I74: 45735 | J74: 45736 | K74: NA | L74: 246779413210 | M74: 212100 | N74: Trade Debtors (Ctrl) | P74: 1 | Q74: USD | R74: 39.06 | S74: INR | T74: 3386.16 | U74: O0 | V74: 6779224500 | X74: NA | Y74: 1 | Z74: {=_xlfn.XLOOKUP(L74,'Customer Ledger'!$O:$O,'Customer Ledger'!$P:$Q,,0)} -> #N/A | AE74: KOCU4372804-Port SSR Shifting Jan 2025. Exch rate | AI74: 45735
A75: 6779 | B75: 100222332 | C75: SCOPE LOGISTICS SERVICES INDIA PVT. | D75: 2025 | E75: 3 | F75: 45735 | G75: 1800003344 | H75: DR | I75: 45735 | J75: 45736 | K75: NA | L75: 246779413211 | M75: 212100 | N75: Trade Debtors (Ctrl) | P75: 1 | Q75: USD | R75: 78.12 | S75: INR | T75: 6772.32 | U75: O0 | V75: 6779224500 | X75: NA | Y75: 1 | Z75: {=_xlfn.XLOOKUP(L75,'Customer Ledger'!$O:$O,'Customer Ledger'!$P:$Q,,0)} -> #N/A | AE75: TCNU8653352-Port SSR Shifting Jan 2025. Exch rate | AI75: 45735
A76: 6779 | B76: 100222332 | C76: SCOPE LOGISTICS SERVICES INDIA PVT. | D76: 2025 | E76: 3 | F76: 45735 | G76: 1800003345 | H76: DR | I76: 45735 | J76: 45736 | K76: NA | L76: 246779413212 | M76: 212100 | N76: Trade Debtors (Ctrl) | P76: 1 | Q76: USD | R76: 39.06 | S76: INR | T76: 3386.16 | U76: O0 | V76: 6779224500 | X76: NA | Y76: 1 | Z76: {=_xlfn.XLOOKUP(L76,'Customer Ledger'!$O:$O,'Customer Ledger'!$P:$Q,,0)} -> #N/A | AE76: HDMU6860845-Port SSR Shifting Jan 2025. Exch rate | AI76: 45735
A77: 6779 | B77: 100222332 | C77: SCOPE LOGISTICS SERVICES INDIA PVT. | D77: 2025 | E77: 3 | F77: 45735 | G77: 1800003346 | H77: DR | I77: 45735 | J77: 45736 | K77: NA | L77: 246779413213 | M77: 212100 | N77: Trade Debtors (Ctrl) | P77: 1 | Q77: USD | R77: 52.08 | S77: INR | T77: 4514.88 | U77: O0 | V77: 6779224500 | X77: NA | Y77: 1 | Z77: {=_xlfn.XLOOKUP(L77,'Customer Ledger'!$O:$O,'Customer Ledger'!$P:$Q,,0)} -> #N/A | AE77: EOLU8212240-Port SSR Shifting Jan 2025. Exch rate | AI77: 45735
A78: 6779 | B78: 100222332 | C78: SCOPE LOGISTICS SERVICES INDIA PVT. | D78: 2025 | E78: 3 | F78: 45735 | G78: 1800003457 | H78: DR | I78: 45735 | J78: 45736 | K78: NA | L78: 246779413324 | M78: 212100 | N78: Trade Debtors (Ctrl) | P78: 1 | Q78: USD | R78: 4.3 | S78: INR | T78: 372.77 | U78: O0 | V78: 6779224500 | X78: NA | Y78: 1 | Z78: {=_xlfn.XLOOKUP(L78,'Customer Ledger'!$O:$O,'Customer Ledger'!$P:$Q,,0)} -> #N/A | AE78: EOLU8605417-Port SSR Storage Feb 2025. Exch rate - | AI78: 45735
A79: 6779 | B79: 100222332 | C79: SCOPE LOGISTICS SERVICES INDIA PVT. | D79: 2025 | E79: 6 | F79: 45827 | G79: 1800009979 | H79: DR | I79: 45827 | J79: 45829 | K79: NA | L79: 256779414743 | M79: 212100 | N79: Trade Debtors (Ctrl) | P79: 1 | Q79: USD | R79: 71.43 | S79: INR | T79: 6106.61 | U79: O0 | V79: 6779224500 | Y79: 1 | Z79: {=_xlfn.XLOOKUP(L79,'Customer Ledger'!$O:$O,'Customer Ledger'!$P:$Q,,0)} -> 0 | AA79: 6064.023 | AB79: =AA79-Z79 -> 6064.023 | AC79: =T79-AB79 -> 42.587 | AD79: =AC79/T79 -> 0.0069739184 | AE79: VAS 1-15 June 25, Exch 86.10 | AI79: 45827
A80: 6779 | B80: 100222332 | C80: SCOPE LOGISTICS SERVICES INDIA PVT. | D80: 2025 | E80: 6 | F80: 45827 | G80: 1800009984 | H80: DR | I80: 45827 | J80: 45829 | K80: NA | L80: 256779414748 | M80: 212100 | N80: Trade Debtors (Ctrl) | P80: 1 | Q80: USD | R80: 20.91 | S80: INR | T80: 1787.61 | U80: O0 | V80: 6779224500 | Y80: 1 | Z80: {=_xlfn.XLOOKUP(L80,'Customer Ledger'!$O:$O,'Customer Ledger'!$P:$Q,,0)} -> 0 | AA80: 1800.351 | AB80: =AA80-Z80 -> 1800.351 | AC80: =T80-AB80 -> -12.741 | AD80: =AC80/T80 -> -0.0071273936 | AE80: WEIGHMENT 1-15 June 25, Exch 86.10 | AI80: 45827
A81: 6779 | B81: 100222332 | C81: SCOPE LOGISTICS SERVICES INDIA PVT. | D81: 2025 | E81: 11 | F81: 45981 | G81: 1800014964 | H81: DR | I81: 45981 | J81: 45982 | K81: NA | L81: 256779419465 | M81: 212100 | N81: Trade Debtors (Ctrl) | P81: 1 | Q81: USD | R81: 240.14 | S81: INR | T81: 21133.13 | U81: O0 | V81: 6779224500 | X81: 2130555 | Y81: 1 | Z81: {=_xlfn.XLOOKUP(L81,'Customer Ledger'!$O:$O,'Customer Ledger'!$P:$Q,,0)} -> 0 | AA81: 20693.117 | AB81: =AA81-Z81 -> 20693.117 | AC81: =T81-AB81 -> 440.0129 | AD81: =AC81/T81 -> 0.020821 | AE81: VAS-Nov 1-15, 2025 | AI81: 45981
A82: 6779 | B82: 100222332 | C82: SCOPE LOGISTICS SERVICES INDIA PVT. | D82: 2025 | E82: 11 | F82: 45981 | G82: 1800014975 | H82: DR | I82: 45981 | J82: 45982 | K82: NA | L82: 256779419476 | M82: 212100 | N82: Trade Debtors (Ctrl) | P82: 1 | Q82: USD | R82: 162.27 | S82: INR | T82: 14280.31 | U82: O0 | V82: 6779224500 | X82: 2130555 | Y82: 1 | Z82: {=_xlfn.XLOOKUP(L82,'Customer Ledger'!$O:$O,'Customer Ledger'!$P:$Q,,0)} -> 0 | AA82: 14016.3 | AB82: =AA82-Z82 -> 14016.3 | AC82: =T82-AB82 -> 264.0101 | AD82: =AC82/T82 -> 0.018487701 | AE82: Weighment-Nov 1-15, 2025 | AI82: 45981
A83: 6779 | B83: 100222332 | C83: SCOPE LOGISTICS SERVICES INDIA PVT. | D83: 2025 | E83: 11 | F83: 45981 | G83: 1800015033 | H83: DR | I83: 45981 | J83: 45985 | K83: NA | L83: 256779419534 | M83: 212100 | N83: Trade Debtors (Ctrl) | P83: 1 | Q83: USD | R83: 90.2 | S83: INR | T83: 7937.91 | U83: O0 | V83: 6779224500 | X83: NA | Y83: 1 | Z83: {=_xlfn.XLOOKUP(L83,'Customer Ledger'!$O:$O,'Customer Ledger'!$P:$Q,,0)} -> 0 | AA83: 7761.899 | AB83: =AA83-Z83 -> 7761.899 | AC83: =T83-AB83 -> 176.011 | AD83: =AC83/T83 -> 0.022173469 | AE83: CODC LCL Chgs -1-15 Nov 25 | AI83: 45981
A84: 6779 | B84: 100222332 | C84: SCOPE LOGISTICS SERVICES INDIA PVT. | D84: 2025 | E84: 11 | F84: 45981 | G84: 1800015043 | H84: DR | I84: 45981 | J84: 45985 | K84: NA | L84: 256779419556 | M84: 212100 | N84: Trade Debtors (Ctrl) | P84: 1 | Q84: USD | R84: 502.5 | S84: INR | T84: 44221.7 | U84: O0 | V84: 6779224500 | X84: 2130610 | Y84: 1 | Z84: {=_xlfn.XLOOKUP(L84,'Customer Ledger'!$O:$O,'Customer Ledger'!$P:$Q,,0)} -> 0 | AA84: 39821.534 | AB84: =AA84-Z84 -> 39821.534 | AC84: =T84-AB84 -> 4400.166 | AD84: =AC84/T84 -> 0.099502416 | AE84: CY Ground rent Chgs - 01 - 15 Nov 25 | AI84: 45981
A85: 6779 | B85: 100222332 | C85: SCOPE LOGISTICS SERVICES INDIA PVT. | D85: 2025 | E85: 11 | F85: 45981 | G85: 1800015096 | H85: DR | I85: 45981 | J85: 45985 | K85: NA | L85: 256779419547 | M85: 212100 | N85: Trade Debtors (Ctrl) | P85: 1 | Q85: USD | R85: 109.01 | S85: INR | T85: 9593.25 | U85: O0 | V85: 6779224500 | X85: 2130609 | Y85: 1 | Z85: {=_xlfn.XLOOKUP(L85,'Customer Ledger'!$O:$O,'Customer Ledger'!$P:$Q,,0)} -> 0 | AA85: 9417.2428 | AB85: =AA85-Z85 -> 9417.2428 | AC85: =T85-AB85 -> 176.0072 | AD85: =AC85/T85 -> 0.018346984 | AE85: CODC Out chgs -1-15 Nov 25 | AI85: 45981
A86: 6779 | B86: 100222332 | C86: SCOPE LOGISTICS SERVICES INDIA PVT. | D86: 2025 | E86: 11 | F86: 45981 | G86: 1800015075 | H86: DR | I86: 45981 | J86: 45985 | K86: NA | L86: 256779419588 | M86: 212100 | N86: Trade Debtors (Ctrl) | P86: 1 | Q86: USD | R86: 339.2 | S86: INR | T86: 29850.75 | U86: O0 | V86: 6779224500 | X86: 2130611 | Y86: 1 | Z86: {=_xlfn.XLOOKUP(L86,'Customer Ledger'!$O:$O,'Customer Ledger'!$P:$Q,,0)} -> 0 | AA86: 29234.726 | AB86: =AA86-Z86 -> 29234.726 | AC86: =T86-AB86 -> 616.0238 | AD86: =AC86/T86 -> 0.020636795 | AE86: LCL Chgs - 01 - 15 NOV 25 | AI86: 45981
A87: 6779 | B87: 100222332 | C87: SCOPE LOGISTICS SERVICES INDIA PVT. | D87: 2025 | E87: 11 | F87: 45981 | G87: 1800015129 | H87: DR | I87: 45981 | J87: 45985 | K87: NA | L87: 256779419628 | M87: 212100 | N87: Trade Debtors (Ctrl) | P87: 1 | Q87: USD | R87: 10.2 | S87: INR | T87: 897.63 | U87: O0 | V87: 6779224500 | X87: 2130612 | Y87: 1 | Z87: {=_xlfn.XLOOKUP(L87,'Customer Ledger'!$O:$O,'Customer Ledger'!$P:$Q,,0)} -> 0 | AA87: 897.6346 | AB87: =AA87-Z87 -> 897.6346 | AC87: =T87-AB87 -> -0.0046 | AD87: =AC87/T87 -> -5.1246059e-06 | AE87: Loose chgs - 01 - 15 Nov 25 | AI87: 45981
A88: 6779 | B88: 100222332 | C88: SCOPE LOGISTICS SERVICES INDIA PVT. | D88: 2025 | E88: 4 | F88: 45769 | G88: 1800001380 | H88: DR | I88: 45722 | J88: 45723 | K88: NA | L88: 246779411249 | M88: 212100 | N88: Trade Debtors (Ctrl) | P88: 1 | Q88: USD | R88: 169.2 | S88: INR | T88: 14668.16 | U88: O0 | V88: 6779224500 | X88: NA | Y88: 1 | Z88: {=_xlfn.XLOOKUP(L88,'Customer Ledger'!$O:$O,'Customer Ledger'!$P:$Q,,0)} -> 0 | AA88: 13737 | AB88: =AA88-Z88 -> 13737 | AC88: =T88-AB88 -> 931.16 | AD88: =AC88/T88 -> 0.063481718 | AE88: Inbound Handling charges for Dec 2024 | AI88: 45722
A89: 6779 | B89: 100222332 | C89: SCOPE LOGISTICS SERVICES INDIA PVT. | D89: 2025 | E89: 4 | F89: 45769 | G89: 1800006259 | H89: DR | I89: 45762 | J89: 45763 | K89: NA | L89: 256779411150 | M89: 212100 | N89: Trade Debtors (Ctrl) | P89: 1 | Q89: USD | R89: 158.6 | S89: INR | T89: 13785.8 | U89: O0 | X89: NA | Y89: 1 | Z89: {=_xlfn.XLOOKUP(L89,'Customer Ledger'!$O:$O,'Customer Ledger'!$P:$Q,,0)} -> 0 | AA89: 13328 | AB89: =AA89-Z89 -> 13328 | AC89: =T89-AB89 -> 457.8 | AD89: =AC89/T89 -> 0.033208084 | AE89: Inbound Handling for August 24 | AI89: 45762
A90: 6779 | B90: 100222332 | C90: SCOPE LOGISTICS SERVICES INDIA PVT. | D90: 2025 | E90: 4 | F90: 45769 | G90: 1800005274 | H90: DR | I90: 45750 | J90: 45752 | K90: NA | L90: 256779410166 | M90: 212100 | N90: Trade Debtors (Ctrl) | P90: 1 | Q90: USD | R90: 152.75 | S90: INR | T90: 13277.31 | U90: O0 | X90: NA | Y90: 1 | Z90: {=_xlfn.XLOOKUP(L90,'Customer Ledger'!$O:$O,'Customer Ledger'!$P:$Q,,0)} -> 0 | AA90: 13011 | AB90: =AA90-Z90 -> 13011 | AC90: =T90-AB90 -> 266.31 | AD90: =AC90/T90 -> 0.020057527 | AE90: Outbound Handling charges for Mar 25 | AI90: 45750
A91: 6779 | B91: 100222332 | C91: SCOPE LOGISTICS SERVICES INDIA PVT. | D91: 2025 | E91: 4 | F91: 45769 | G91: 1800007570 | H91: DR | I91: 45769 | J91: 45770 | K91: NA | L91: 256779412461 | M91: 212100 | N91: Trade Debtors (Ctrl) | P91: 1 | Q91: USD | R91: 126.9 | S91: INR | T91: 11030.38 | U91: O0 | V91: 6779224500 | X91: NA | Y91: 1 | Z91: {=_xlfn.XLOOKUP(L91,'Customer Ledger'!$O:$O,'Customer Ledger'!$P:$Q,,0)} -> 0 | AA91: 10809 | AB91: =AA91-Z91 -> 10809 | AC91: =T91-AB91 -> 221.38 | AD91: =AC91/T91 -> 0.020070025 | AE91: Inbound Handling charges for Feb 2025 | AI91: 45769
A92: 6779 | B92: 100222332 | C92: SCOPE LOGISTICS SERVICES INDIA PVT. | D92: 2025 | E92: 4 | F92: 45769 | G92: 1800001382 | H92: DR | I92: 45722 | J92: 45723 | K92: NA | L92: 246779411251 | M92: 212100 | N92: Trade Debtors (Ctrl) | P92: 1 | Q92: USD | R92: 126.9 | S92: INR | T92: 11001.12 | U92: O0 | V92: 6779224500 | X92: NA | Y92: 1 | Z92: {=_xlfn.XLOOKUP(L92,'Customer Ledger'!$O:$O,'Customer Ledger'!$P:$Q,,0)} -> 0 | AA92: 1599 | AB92: =AA92-Z92 -> 1599 | AC92: =T92-AB92 -> 9402.12 | AD92: =AC92/T92 -> 0.85465116 | AE92: Inbound Handling charges for Dec 2024 | AI92: 45722
A93: 6779 | B93: 100222332 | C93: SCOPE LOGISTICS SERVICES INDIA PVT. | D93: 2025 | E93: 4 | F93: 45769 | G93: 1800003759 | H93: DR | I93: 45736 | J93: 45736 | K93: NA | L93: 246779413626 | M93: 212100 | N93: Trade Debtors (Ctrl) | P93: 1 | Q93: USD | R93: 84.6 | S93: INR | T93: 7334.08 | U93: O0 | V93: 6779224500 | X93: NA | Y93: 1 | Z93: {=_xlfn.XLOOKUP(L93,'Customer Ledger'!$O:$O,'Customer Ledger'!$P:$Q,,0)} -> 0 | AA93: 7156 | AB93: =AA93-Z93 -> 7156 | AC93: =T93-AB93 -> 178.08 | AD93: =AC93/T93 -> 0.024281164 | AE93: Outbound Handling charges for Jan 2025 | AI93: 45736
A94: 6779 | B94: 100222332 | C94: SCOPE LOGISTICS SERVICES INDIA PVT. | D94: 2025 | E94: 9 | F94: 45918 | G94: 1800012845 | H94: DR | I94: 45918 | J94: 45922 | K94: NA | L94: 256779417410 | M94: 212100 | N94: Trade Debtors (Ctrl) | P94: 1 | Q94: USD | R94: 371.84 | S94: INR | T94: 32541.33 | U94: O0 | V94: 6779224500 | X94: 2102474 | Y94: 1 | Z94: {=_xlfn.XLOOKUP(L94,'Customer Ledger'!$O:$O,'Customer Ledger'!$P:$Q,,0)} -> 0 | AA94: 29303.298 | AB94: =AA94-Z94 -> 29303.298 | AC94: =T94-AB94 -> 3238.0317 | AD94: =AC94/T94 -> 0.099505205 | AE94: CY - CY Grd Rent Chgs - 01 - 15 SEP 25 | AI94: 45918
A95: 6779 | B95: 100222332 | C95: SCOPE LOGISTICS SERVICES INDIA PVT. | D95: 2025 | E95: 9 | F95: 45918 | G95: 1800012871 | H95: DR | I95: 45918 | J95: 45922 | K95: NA | L95: 256779417489 | M95: 212100 | N95: Trade Debtors (Ctrl) | P95: 1 | Q95: USD | R95: 533.92 | S95: INR | T95: 46725.65 | U95: O0 | V95: 6779224500 | X95: 2102476 | Y95: 1 | Z95: {=_xlfn.XLOOKUP(L95,'Customer Ledger'!$O:$O,'Customer Ledger'!$P:$Q,,0)} -> 0 | AA95: 42087.392 | AB95: =AA95-Z95 -> 42087.392 | AC95: =T95-AB95 -> 4638.2584 | AD95: =AC95/T95 -> 0.099265787 | AE95: CY Ground rent Chgs - 01 - 15 Sep 25 | AI95: 45918
A96: 6779 | B96: 100222332 | C96: SCOPE LOGISTICS SERVICES INDIA PVT. | D96: 2025 | E96: 9 | F96: 45918 | G96: 1800012990 | H96: DR | I96: 45918 | J96: 45922 | K96: NA | L96: 256779417525 | M96: 212100 | N96: Trade Debtors (Ctrl) | P96: 1 | Q96: USD | R96: 311.37 | S96: INR | T96: 27249.34 | U96: O0 | V96: 6779224500 | X96: 2102483 | Y96: 1 | Z96: {=_xlfn.XLOOKUP(L96,'Customer Ledger'!$O:$O,'Customer Ledger'!$P:$Q,,0)} -> 0 | AA96: 26724.251 | AB96: =AA96-Z96 -> 26724.251 | AC96: =T96-AB96 -> 525.089 | AD96: =AC96/T96 -> 0.019269788 | AE96: Outbound chgs - 01 - 15 Sep 25 | AI96: 45918
A97: 6779 | B97: 100222332 | C97: SCOPE LOGISTICS SERVICES INDIA PVT. | D97: 2025 | E97: 9 | F97: 45918 | G97: 1800012927 | H97: DR | I97: 45918 | J97: 45922 | K97: NA | L97: 256779417566 | M97: 212100 | N97: Trade Debtors (Ctrl) | P97: 1 | Q97: USD | R97: 75.5 | S97: INR | T97: 6607.33 | U97: O0 | V97: 6779224500 | X97: 2102480 | Y97: 1 | Z97: {=_xlfn.XLOOKUP(L97,'Customer Ledger'!$O:$O,'Customer Ledger'!$P:$Q,,0)} -> 0 | AA97: 6432.3033 | AB97: =AA97-Z97 -> 6432.3033 | AC97: =T97-AB97 -> 175.0267 | AD97: =AC97/T97 -> 0.026489777 | AE97: Inbound chgs - 01 - 15 SEP 25 | AI97: 45918
A98: 6779 | B98: 100222332 | C98: SCOPE LOGISTICS SERVICES INDIA PVT. | D98: 2025 | E98: 9 | F98: 45918 | G98: 1800012943 | H98: DR | I98: 45918 | J98: 45922 | K98: NA | L98: 256779417582 | M98: 212100 | N98: Trade Debtors (Ctrl) | P98: 1 | Q98: USD | R98: 80.8 | S98: INR | T98: 7071.16 | U98: O0 | V98: 6779224500 | X98: 2102527 | Y98: 1 | Z98: {=_xlfn.XLOOKUP(L98,'Customer Ledger'!$O:$O,'Customer Ledger'!$P:$Q,,0)} -> 0 | AA98: 6896.1292 | AB98: =AA98-Z98 -> 6896.1292 | AC98: =T98-AB98 -> 175.0308 | AD98: =AC98/T98 -> 0.02475277 | AE98: CODC LCL Chgs -1-15 Sep 25 | AI98: 45918
A99: 6779 | B99: 100222332 | C99: SCOPE LOGISTICS SERVICES INDIA PVT. | D99: 2025 | E99: 12 | F99: 45996 | G99: 1800015346 | H99: DR | I99: 45996 | J99: 46000 | K99: NA | L99: 256779419795 | M99: 212100 | N99: Trade Debtors (Ctrl) | P99: 1 | Q99: USD | R99: 356.26 | S99: INR | T99: 31600.31 | U99: O0 | V99: 6779224500 | X99: 2140068 | Y99: 1 | Z99: {=_xlfn.XLOOKUP(L99,'Customer Ledger'!$O:$O,'Customer Ledger'!$P:$Q,,0)} -> 0 | AA99: 28407.107 | AB99: =AA99-Z99 -> 28407.107 | AC99: =T99-AB99 -> 3193.2032 | AD99: =AC99/T99 -> 0.10104974 | AE99: CY Ground rent Chgs - 16 - 30 Nov 25 | AI99: 45996
A100: 6779 | B100: 100222332 | C100: SCOPE LOGISTICS SERVICES INDIA PVT. | D100: 2025 | E100: 12 | F100: 45996 | G100: 1800015287 | H100: DR | I100: 45996 | J100: 46000 | K100: NA | L100: 256779419916 | M100: 212100 | N100: Trade Debtors (Ctrl) | P100: 1 | Q100: USD | R100: 128.31 | S100: INR | T100: 11381.11 | U100: O0 | V100: 6779224500 | X100: 2140088 | Y100: 1 | Z100: {=_xlfn.XLOOKUP(L100,'Customer Ledger'!$O:$O,'Customer Ledger'!$P:$Q,,0)} -> 0 | AA100: 11115.014 | AB100: =AA100-Z100 -> 11115.014 | AC100: =T100-AB100 -> 266.0955 | AD100: =AC100/T100 -> 0.023380452 | AE100: Outbound chgs - 16 - 30 Nov 25 | AI100: 45996
A101: 6779 | B101: 100222332 | C101: SCOPE LOGISTICS SERVICES INDIA PVT. | D101: 2025 | E101: 5 | F101: 45799 | G101: 1600001068 | H101: DG | I101: 45799 | J101: 45800 | K101: NA | L101: 256779420756 | M101: 212100 | N101: Trade Debtors (Ctrl) | P101: 11 | Q101: USD | R101: -500.63 | S101: INR | T101: -43400.25 | U101: O0 | V101: 6779224500 | X101: NA | Y101: 1 | Z101: {=_xlfn.XLOOKUP(L101,'Customer Ledger'!$O:$O,'Customer Ledger'!$P:$Q,,0)} -> #N/A | AE101: Credit Note against 246779413088 | AI101: 45799 | AJ101: 45842 | AK101: 1400000248
...

Sheet TDS 

Sheet Invoices not in customers books
A1: Document Number | B1: Document Type | C1: Document Date | D1: Reference | E1: Document Currency Key | F1: Document Currency Value | G1: Company Code Currency Key | H1: Company Code Currency Value | I1: Text | J1: Clearing Document
A2: 1600002697 | B2: DG | C2: 46027 | D2: 256779422167 | E2: USD | F2: -3.4 | G2: INR | H2: -308.53 | I2: Credit note for Duplicate invoice -256779418492 | K2: =IF(H2<0,H2*-1,H2) -> 308.53
A3: 1800003457 | B3: DR | C3: 45735 | D3: 246779413324 | E3: USD | F3: 4.3 | G3: INR | H3: 372.77 | I3: EOLU8605417-Port SSR Storage Feb 2025. Exch rate - | K3: =IF(H3<0,H3*-1,H3) -> 372.77
A4: 1800016637 | B4: DR | C4: 46028 | D4: 256779440257 | E4: USD | F4: 4.7 | G4: INR | H4: 426.49 | I4: CODC Out chgs -16-31 DEC 25 | K4: =IF(H4<0,H4*-1,H4) -> 426.49
A5: 1800016160 | B5: DR | C5: 46031 | D5: 256779440130 | E5: USD | F5: 16.45 | G5: INR | H5: 1492.72 | I5: CODC Out chgs -1-15 Nov 25 | K5: =IF(H5<0,H5*-1,H5) -> 1492.72
A6: 1800007089 | B6: DR | C6: 45763 | D6: 256779411980 | E6: USD | F6: 17.42 | G6: INR | H6: 1514.18 | I6: BEAU2827340-Port SSR Shifting Mar 2025. Exch rate | K6: =IF(H6<0,H6*-1,H6) -> 1514.18
A7: 1800007088 | B7: DR | C7: 45763 | D7: 256779411979 | E7: USD | F7: 37.56 | G7: INR | H7: 3264.78 | I7: GMCU3054416-Port SSR Shifting Mar 2025. Exch rate | K7: =IF(H7<0,H7*-1,H7) -> 3264.78
A8: 1800003342 | B8: DR | C8: 45735 | D8: 246779413209 | E8: USD | F8: 39.06 | G8: INR | H8: 3386.16 | I8: HMMU6832693-Port SSR Shifting Jan 2025. Exch rate | K8: =IF(H8<0,H8*-1,H8) -> 3386.16
A9: 1800003343 | B9: DR | C9: 45735 | D9: 246779413210 | E9: USD | F9: 39.06 | G9: INR | H9: 3386.16 | I9: KOCU4372804-Port SSR Shifting Jan 2025. Exch rate | K9: =IF(H9<0,H9*-1,H9) -> 3386.16
A10: 1800003345 | B10: DR | C10: 45735 | D10: 246779413212 | E10: USD | F10: 39.06 | G10: INR | H10: 3386.16 | I10: HDMU6860845-Port SSR Shifting Jan 2025. Exch rate | K10: =IF(H10<0,H10*-1,H10) -> 3386.16
A11: 1800015963 | B11: DR | C11: 46027 | D11: 256779440080 | E11: USD | F11: 41.46 | G11: INR | H11: 3762.21 | I11: Outbound chgs - 01 - 15 Dec 25 | K11: =IF(H11<0,H11*-1,H11) -> 3762.21
A12: 1800007087 | B12: DR | C12: 45763 | D12: 256779411978 | E12: USD | F12: 46.85 | G12: INR | H12: 4072.29 | I12: GMCU3054268-Port SSR Shifting Mar 2025. Exch rate | K12: =IF(H12<0,H12*-1,H12) -> 4072.29
A13: 1800016321 | B13: DR | C13: 46034 | D13: 256779440174 | E13: USD | F13: 48.8 | G13: INR | H13: 4428.27 | I13: CODC LCL Chgs -16-31 DEC 25 | K13: =IF(H13<0,H13*-1,H13) -> 4428.27
... A16: 1800003344 | B16: DR | C16: 45735 | D16: 246779413211 | E16: USD | F16: 78.12 | G16: INR | H16: 6772.32 | I16: TCNU8653352-Port SSR Shifting Jan 2025. Exch rate | K16: =IF(H16<0,H16*-1,H16) -> 6772.32
A17: 1600001746 | B17: DG | C17: 45854 | D17: 256779421378 | E17: USD | F17: -140 | G17: INR | H17: -12037.72 | I17: Credit Note raised against INV_256779413861 | J17: 1400001901 | K17: =IF(H17<0,H17*-1,H17) -> 12037.72
A18: 1600001816 | B18: DG | C18: 45862 | D18: 256779421436 | E18: USD | F18: -140 | G18: INR | H18: -12037.72 | I18: Credit Note raised against 256779413861 | K18: =IF(H18<0,H18*-1,H18) -> 12037.72
A19: 1800009097 | B19: DR | C19: 45795 | D19: 256779413861 | E19: USD | F19: 140 | G19: INR | H19: 12037.72 | I19: Scanning Chgs - 01 - 15 May 25 | J19: 1400001901 | K19: =IF(H19<0,H19*-1,H19) -> 12037.72
A20: 1800017152 | B20: DR | C20: 46049 | D20: 256779440445 | E20: USD | F20: 137.14 | G20: INR | H20: 12444.51 | I20: VAS-1-15 Jan 2026 | K20: =IF(H20<0,H20*-1,H20) -> 12444.51
A21: 1800010281 | B21: DR | C21: 45842 | D21: 256779415041 | E21: USD | F21: 155.09 | G21: INR | H21: 13337.84 | I21: PORT SSR Chgs June 25 | K21: =IF(H21<0,H21*-1,H21) -> 13337.84
A22: 1800014729 | B22: DR | C22: 45966 | D22: 256779419230 | E22: USD | F22: 179.58 | G22: INR | H22: 15803.65 | I22: PORT SSR Chgs Oct 25 | K22: =IF(H22<0,H22*-1,H22) -> 15803.65
A23: 1800013925 | B23: DR | C23: 45950 | D23: 256779418702 | E23: USD | F23: 182.87 | G23: INR | H23: 16127.45 | I23: Outbound chgs - 01 - 15 Oct 25 | K23: =IF(H23<0,H23*-1,H23) -> 16127.45
A24: 1800016314 | B24: DR | C24: 46034 | D24: 256779440167 | E24: USD | F24: 188 | G24: INR | H24: 17059.71 | I24: CY Ground rent Chgs - 16 - 31 Dec 25 | K24: =IF(H24<0,H24*-1,H24) -> 17059.71
A25: 1800013843 | B25: DR | C25: 45950 | D25: 256779418661 | E25: USD | F25: 226.3 | G25: INR | H25: 19957.57 | I25: Inbound chgs - 01 - 15 OCT 25 | K25: =IF(H25<0,H25*-1,H25) -> 19957.57
A26: 1800016416 | B26: DR | C26: 46034 | D26: 256779440229 | E26: USD | F26: 308.79 | G26: INR | H26: 28020.57 | I26: Outbound chgs - 16 - 31 Dec 25 | K26: =IF(H26<0,H26*-1,H26) -> 28020.57
A27: 1800013971 | B27: DR | C27: 45950 | D27: 256779418614 | E27: USD | F27: 338.06 | G27: INR | H27: 29813.77 | I27: CY - CY Grd Rent Chgs - 01 - 15 OCT 25 | K27: =IF(H27<0,H27*-1,H27) -> 29813.77
A28: 1800010769 | B28: DR | C28: 45856 | D28: 256779415431 | E28: USD | F28: 358.33 | G28: INR | H28: 30816.62 | I28: PORT SSR Chgs Apr & June 25 | K28: =IF(H28<0,H28*-1,H28) -> 30816.62
A29: 1800015801 | B29: DR | C29: 46027 | D29: 256779440051 | E29: USD | F29: 358.14 | G29: INR | H29: 32498.75 | I29: CY Ground rent Chgs - 01 - 15 Dec 25 | K29: =IF(H29<0,H29*-1,H29) -> 32498.75
A30: 1800016202 | B30: DR | C30: 46028 | D30: 256779440143 | E30: USD | F30: 360.75 | G30: INR | H30: 32735.59 | I30: CY - CY Grd Rent Chgs - 16 - 31 Dec 25 | K30: =IF(H30<0,H30*-1,H30) -> 32735.59
A31: 1800015473 | B31: DR | C31: 45997 | D31: 256779419990 | E31: USD | F31: 429.75 | G31: INR | H31: 38118.89 | I31: PORT SSR Chgs Nov 25 | K31: =IF(H31<0,H31*-1,H31) -> 38118.89
... A43: 1800016345 | B43: DR | C43: 46028 | D43: 256779440235 | E43: USD | F43: 7267.85 | G43: INR | H43: 659507.53 | I43: Unit Storage - 1-31 DEC 2025 | K43: =IF(H43<0,H43*-1,H43) -> 659507.53

Sheet Sheet4
A1: Document Number | B1: Document Type | C1: Document Date | D1: Reference | E1: Document Currency Key | F1: Document Currency Value | G1: Company Code Currency Key | H1: Company Code Currency Value | I1: Text | J1: Clearing Document | L1: `
A2: 1600001737 | B2: DG | C2: 45854 | D2: 256779421369 | E2: USD | F2: -1793.99 | G2: INR | H2: -155936.88 | I2: Credit Note raised against INV_256779410010 | J2: 1400001901 | K2: 256779410010 | L2: #N/A
A3: 1600001736 | B3: DG | C3: 45854 | D3: 256779421368 | E3: USD | F3: -705 | G3: INR | H3: -61279.88 | I3: Credit Note raised against INV_256779410004 | J3: 1400001901 | K3: 256779410004 | L3: #N/A
A4: 1600001753 | B4: DG | C4: 45854 | D4: 256779421385 | E4: USD | F4: -420 | G4: INR | H4: -36410.33 | I4: Credit note Note raised against INV_246779411278 | J4: 1400001902 | K4: 246779411278 | L4: #N/A
A5: 1600001740 | B5: DG | C5: 45854 | D5: 256779421372 | E5: USD | F5: -385 | G5: INR | H5: -33376.14 | I5: Credit Note raised against INV_246779411300 | J5: 1400001901 | K5: 246779411300 | L5: #N/A
A6: 1600001733 | B6: DG | C6: 45854 | D6: 256779421365 | E6: USD | F6: -375 | G6: INR | H6: -32509.22 | I6: Credit Note raised against INV_246779413827 | J6: 1400001901 | K6: 246779413827 | L6: #N/A
A7: 1600001742 | B7: DG | C7: 45854 | D7: 256779421374 | E7: USD | F7: -245 | G7: INR | H7: -21239.36 | I7: Credit Note raised against INV_246779411326 | J7: 1400001901 | K7: 246779411326 | L7: #N/A
A8: 1600001730 | B8: DG | C8: 45854 | D8: 256779421362 | E8: USD | F8: -237.35 | G8: INR | H8: -20576.17 | I8: Credit Note raised against INV_246779413705 | J8: 1400001901 | K8: 246779413705 | L8: #N/A
A9: 1600001732 | B9: DG | C9: 45854 | D9: 256779421364 | E9: USD | F9: -220 | G9: INR | H9: -19072.08 | I9: Credit Note raised against INV_246779413816 | J9: 1400001901 | K9: 246779413816 | L9: #N/A
A10: 1600001743 | B10: DG | C10: 45854 | D10: 256779421375 | E10: USD | F10: -220 | G10: INR | H10: -19072.08 | I10: Credit Note raised against INV_246779411339 | J10: 1400001901 | K10: 246779411339 | L10: #N/A
A11: 1600001748 | B11: DG | C11: 45854 | D11: 256779421380 | E11: USD | F11: -182.83 | G11: INR | H11: -15778.9 | I11: Credit note Note raised against INV_246779410348 | J11: 1400001902 | K11: 246779410348 | L11: #N/A
A12: 1600001750 | B12: DG | C12: 45854 | D12: 256779421382 | E12: USD | F12: -177.66 | G12: INR | H12: -15401.57 | I12: Credit note Note raised against INV_246779413701 | J12: 1400001902 | K12: 246779413701 | L12: #N/A
A13: 1600001745 | B13: DG | C13: 45854 | D13: 256779421377 | E13: USD | F13: -140 | G13: INR | H13: -12037.72 | I13: Credit Note raised against INV_256779413283 | J13: 1400001901 | K13: 256779413283 | L13: #N/A
A14: 1600001816 | B14: DG | C14: 45862 | D14: 256779421436 | E14: USD | F14: -140 | G14: INR | H14: -12037.72 | I14: Credit Note raised against 256779413861 | L14: 12037.72
A15: 1600001752 | B15: DG | C15: 45854 | D15: 256779421384 | E15: USD | F15: -137.9 | G15: INR | H15: -11954.72 | I15: Credit note Note raised against INV_246779413845 | J15: 1400001902 | K15: 246779413845 | L15: #N/A
A16: 1600002697 | B16: DG | C16: 46027 | D16: 256779422167 | E16: USD | F16: -3.4 | G16: INR | H16: -308.53 | I16: Credit note for Duplicate invoice -256779418492 | K16: 256779418492 | L16: #N/A
