Workbook

Sheet Summary
A1: Reconciliation of Ledger as on 31st January 2026
A2: Particulars | B2: Amount
A3: Balance as per Scope Chemicals Pvt Ltd | B3: =-'Customer Data'!E389 -> 1489274.5
A4: Add: TDS to be booked in Ascendus books | B4: ='TDS to be recorded '!#REF! -> #REF!
A5: Add: Invoices & CN not recorded in customer books | B5: ='Invoice&DN in Customer''s ledger'!#REF! -> #REF!
A6: Add: Diffrence of invoice value in both Books | B6: ='Diffrence in Invoice value'!M28 -> 0
A7: Add: Knock off entries difference | B7: ='Knock off entries difference'!H1 -> -1093.08
A8: Derived balance | B8: =SUM(B3:B6) -> #REF!
A9: Balance as per Ascent | B9: ='Ascendus Data'!U476 -> 4683369.6
A11: Difference | B11: =B8-B9-B10 -> #REF!

Sheet Payment Reco

Sheet Sheet2
A1: Posting Date | B1: Debit (INR) | C1: Credit (INR) | D1: Balance (INR) | E1: Voucher No | F1: Against Account | G1: Against Voucher | H1: Supplier Invoice No
A2: 45854 | B2: 19430 | C2: 0 | D2: -1612920.6 | E2: SLS26/MF/DN/0006 | F2: Storage Charges - Cargo - SLSIPL | G2: PU/26/SLS/OT/0590 | H2: DN | I2: 246779413705
A3: 45854 | B3: 18611 | C3: 0 | D3: -1594309.6 | E3: SLS26/MF/DN/0008 | F3: Container Scanning Paid - SLSIPL | G3: PU/25/SLS/OT/1821 | H3: DN | I3: 246779413816
A4: 45854 | B4: 31723 | C4: 0 | D4: -1562586.6 | E4: SLS26/MF/DN/0009 | F4: Container Scanning Paid - SLSIPL | G4: PU/25/SLS/OT/1822 | H4: DN | I4: 246779413827
A5: 45854 | B5: 17857 | C5: 0 | D5: -1544729.6 | E5: SLS26/MF/DN/0011 | F5: Container Scanning Paid - SLSIPL | G5: PU/25/SLS/OT/1854 | H5: DN | I5: 246779411339
A6: 45854 | B6: 11798 | C6: 0 | D6: -1532931.6 | E6: SLS26/MF/DN/0013 | F6: Container Scanning Paid - SLSIPL | G6: PU/26/SLS/OT/0283 | H6: DN | I6: 256779413283
A7: 45854 | B7: 20874 | C7: 0 | D7: -1512057.6 | E7: SLS26/MF/DN/0014 | F7: Container Scanning Paid - SLSIPL | G7: PU/25/SLS/OT/1820 | H7: DN | I7: 246779411326
A8: 45854 | B8: 140649 | C8: 0 | D8: -1371408.6 | E8: SLS26/MF/DN/0016 | F8: Storage Charges - Cargo - SLSIPL | G8: PU/26/SLS/OT/0612 | H8: DN | I8: 256779410010
A9: 45854 | B9: 55272 | C9: 0 | D9: -1316136.6 | E9: SLS26/MF/DN/0017 | F9: Storage Charges - Cargo - SLSIPL | G9: PU/26/SLS/OT/0613 | H9: DN | I9: 256779410004
A10: 45854 | B10: 4786 | C10: 0 | D10: -1311350.6 | E10: SLS26/MF/DN/0007-2 | F10: Storage Charges - Cargo - SLSIPL | G10: SLS26/MF/DN/0007-2 | H10: DN | I10: 256779421381
A11: 45854 | B11: 11955 | C11: 0 | D11: -1299395.6 | E11: SLS26/MF/DN/0004-1 | F11: Transportation Charges Paid - SLSIPL | G11: PU/26/SLS/OT/0588 | H11: DN | I11: 246779413845
A12: 45854 | B12: 12467 | C12: 0 | D12: -1450559.6 | E12: SLS26/MF/DN/0018-1 | F12: Storage Charges - Cargo - SLSIPL | G12: SLS26/MF/DN/0018-1 | H12: DN | I12: 256779421383
A13: 45854 | B13: 6084 | C13: 0 | D13: -1444475.6 | E13: SLS26/MF/DN/0002-1 | F13: Scanning Charges - Inbound - SLSIPL | G13: SLS26/MF/DN/0002-1 | H13: DN | I13: 256779421376
... A19: 45869 | B19: 33376 | C19: 0 | D19: -259448.6 | E19: SLS26/MF/DN/0019 | F19: Container Scanning Paid - SLSIPL | G19: PU/25/SLS/OT/1925 | H19: DN | I19: 246779411300
A20: 45869 | B20: 15778 | C20: 0 | D20: -243670.6 | E20: SLS26/MF/DN/0020-1 | F20: Storage Charges - Cargo - SLSIPL | G20: SLS26/MF/DN/0020-1 | H20: DN | I20: 246779410348/256779421380
A21: 45869 | B21: 36410 | C21: 0 | D21: -251862.6 | E21: SLS26/MF/DN/0022-1 | F21: Container Scanning Paid - SLSIPL | G21: SLS26/MF/DN/0022-1 | H21: DN | I21: 246779411278/256779421385
A22: 45869 | B22: 15401 | C22: 0 | D22: -236461.6 | E22: SLS26/MF/DN/0021-1 | F22: Fixed Storage Charges - ODC (Covered) - SLSIPL | G22: SLS26/MF/DN/0021-1 | H22: DN | I22: 256779421382/246779413701

Sheet Customer Data Vlookup
A2: Posting Date | B2: Debit (INR) | C2: Credit (INR) | D2: Balance (INR) | E2: Voucher No | F2: Against Account | G2: Against Voucher | H2: Supplier Invoice No | L2: Row Labels | M2: Sum of Debit (INR) | N2: Sum of Credit (INR) | P2: Row Labels | Q2: Sum of Debit (INR) | R2: Sum of Credit (INR)
A3: 45708 | B3: 0 | C3: 35554.52 | D3: -35554.52 | E3: PU/25/SLS/OT/1560 | F3: Fixed Storage Charges - ODC (Covered) - SLSIPL | G3: PU/25/SLS/OT/1560 | H3: 246779410049 | L3: 25677941807 | M3: 0 | N3: 1972 | P3: 25677941807 | Q3: 0 | R3: 1972
A4: 45708 | B4: 0 | C4: 35554.52 | D4: -71109.04 | E4: PU/25/SLS/OT/1561 | F4: Fixed Storage Charges - ODC (Covered) - SLSIPL | G4: PU/25/SLS/OT/1561 | H4: 246779410303 | L4: 246779410049 | M4: 0 | N4: 35554.52 | P4: 246779410049 | Q4: 0 | R4: 35554.52
A5: 45708 | B5: 0 | C5: 35554.52 | D5: -106663.56 | E5: PU/25/SLS/OT/1562 | F5: Fixed Storage Charges - ODC (Covered) - SLSIPL | G5: PU/25/SLS/OT/1562 | H5: 246779410117 | L5: 246779410072 | M5: 0 | N5: 35477 | P5: 246779410072 | Q5: 0 | R5: 35477
A6: 45708 | B6: 0 | C6: 35554.52 | D6: -142218.08 | E6: PU/25/SLS/OT/1563 | F6: Fixed Storage Charges - ODC (Covered) - SLSIPL | G6: PU/25/SLS/OT/1563 | H6: 246779410160 | L6: 246779410117 | M6: 0 | N6: 35554.52 | P6: 246779410117 | Q6: 0 | R6: 35554.52
A7: 45708 | B7: 0 | C7: 35554.52 | D7: -177772.6 | E7: PU/25/SLS/OT/1564 | F7: Fixed Storage Charges - ODC (Covered) - SLSIPL | G7: PU/25/SLS/OT/1564 | H7: 246779410203 | L7: 246779410160 | M7: 0 | N7: 35554.52 | P7: 246779410160 | Q7: 0 | R7: 35554.52
A8: 45708 | B8: 0 | C8: 35554.52 | D8: -213327.12 | E8: PU/25/SLS/OT/1565 | F8: Fixed Storage Charges - ODC (Covered) - SLSIPL | G8: PU/25/SLS/OT/1565 | H8: 246779410246 | L8: 246779410203 | M8: 0 | N8: 35554.52 | P8: 246779410203 | Q8: 0 | R8: 35554.52
A9: 45719 | B9: 0 | C9: 804 | D9: -214131.12 | E9: PU/25/SLS/OT/1672 | F9: Handling Charges - Outbound (Exp) - SLSIPL | G9: PU/25/SLS/OT/1672 | H9: 246779410613 | L9: 246779410246 | M9: 0 | N9: 35554.52 | P9: 246779410246 | Q9: 0 | R9: 35554.52
A10: 45719 | B10: 0 | C10: 1004 | D10: -215135.12 | E10: PU/25/SLS/OT/1673 | F10: Handling Charges - Outbound (Exp) - SLSIPL | G10: PU/25/SLS/OT/1673 | H10: 246779410612 | L10: 246779410303 | M10: 0 | N10: 35554.52 | P10: 246779410303 | Q10: 0 | R10: 35554.52
A11: 45719 | B11: 0 | C11: 402 | D11: -215537.12 | E11: PU/25/SLS/OT/1674 | F11: Handling Charges - Outbound (Exp) - SLSIPL | G11: PU/25/SLS/OT/1674 | H11: 246779410611 | L11: 246779410327 | M11: 0 | N11: 16480.711 | P11: 246779410327 | Q11: 0 | R11: 16480.711
A12: 45719 | B12: 0 | C12: 201 | D12: -215738.12 | E12: PU/25/SLS/OT/1675 | F12: Handling Charges - Outbound (Exp) - SLSIPL | G12: PU/25/SLS/OT/1675 | H12: 246779410610 | L12: 246779410333 | M12: 0 | N12: 29975.442 | P12: 246779410333 | Q12: 0 | R12: 29975.442
A13: 45719 | B13: 0 | C13: 804 | D13: -216542.12 | E13: PU/25/SLS/OT/1676 | F13: Handling Charges - Outbound (Exp) - SLSIPL | G13: PU/25/SLS/OT/1676 | H13: 246779410608 | L13: 246779410338 | M13: 0 | N13: 13859.78 | P13: 246779410338 | Q13: 0 | R13: 13859.78
A14: 45719 | B14: 0 | C14: 402 | D14: -216944.12 | E14: PU/25/SLS/OT/1677 | F14: Handling Charges - Outbound (Exp) - SLSIPL | G14: PU/25/SLS/OT/1677 | H14: 246779410607 | L14: 246779410339 | M14: 0 | N14: 44681.825 | P14: 246779410339 | Q14: 0 | R14: 44681.825
... A112: 45747 | B112: 0 | C112: 31723 | D112: -2522653.1 | E112: PU/25/SLS/OT/1823 | F112: Container Scanning Paid - SLSIPL | G112: PU/25/SLS/OT/1823 | H112: 246779413753 | L112: 246779411252 | M112: 0 | N112: 1907 | P112: 246779411252 | Q112: 0 | R112: 1907
A113: 45747 | B113: 0 | C113: 191 | D113: -2522844.1 | E113: PU/25/SLS/OT/1824 | F113: Handling Charges - Outbound (Exp) - SLSIPL | G113: PU/25/SLS/OT/1824 | H113: 246779413762 | L113: 246779411278 | P113: 246779411278 | Q113: 0 | R113: 44602
A114: 45747 | B114: 0 | C114: 3064 | D114: -2525908.1 | E114: PU/25/SLS/OT/1825 | F114: Handling Charges - Outbound (Exp) - SLSIPL | G114: PU/25/SLS/OT/1825 | H114: 246779413745 | L114: 246779411300 | M114: 0 | N114: 33376 | P114: 246779411300 | Q114: 33376 | R114: 33376
A115: 45747 | B115: 0 | C115: 3448 | D115: -2529356.1 | E115: PU/25/SLS/OT/1826 | F115: Handling Charges - Outbound (Exp) - SLSIPL | G115: PU/25/SLS/OT/1826 | H115: 246779413734 | L115: 246779411314 | M115: 0 | N115: 8522 | P115: 246779411314 | Q115: 0 | R115: 8522
A116: 45747 | B116: 0 | C116: 6513 | D116: -2535869.1 | E116: PU/25/SLS/OT/1827 | F116: Handling Charges - Outbound (Exp) - SLSIPL | G116: PU/25/SLS/OT/1827 | H116: 246779413736 | L116: 246779411326 | M116: 0 | N116: 20874 | P116: 246779411326 | Q116: 20874 | R116: 20874
A117: 45747 | B117: 0 | C117: 1724 | D117: -2537593.1 | E117: PU/25/SLS/OT/1828 | F117: Handling Charges - Outbound (Exp) - SLSIPL | G117: PU/25/SLS/OT/1828 | H117: 246779413739 | L117: 246779411339 | M117: 0 | N117: 17857 | P117: 246779411339 | Q117: 17857 | R117: 17857
A118: 45747 | B118: 0 | C118: 1149 | D118: -2538742.1 | E118: PU/25/SLS/OT/1829 | F118: Handling Charges - Outbound (Exp) - SLSIPL | G118: PU/25/SLS/OT/1829 | H118: 246779413742 | L118: 246779411448 | M118: 0 | N118: 1161 | P118: 246779411448 | Q118: 0 | R118: 1161
A119: 45747 | B119: 0 | C119: 191 | D119: -2538933.1 | E119: PU/25/SLS/OT/1830 | F119: Handling Charges - Outbound (Exp) - SLSIPL | G119: PU/25/SLS/OT/1830 | H119: 246779413692 | L119: 246779411619 | M119: 0 | N119: 143412 | P119: 246779411619 | Q119: 0 | R119: 143412
A120: 45747 | B120: 0 | C120: 6896 | D120: -2545829.1 | E120: PU/25/SLS/OT/1831 | F120: Handling Charges - Outbound (Exp) - SLSIPL | G120: PU/25/SLS/OT/1831 | H120: 246779413693 | L120: 246779411620 | M120: 0 | N120: 5816 | P120: 246779411620 | Q120: 0 | R120: 5816
A121: 45747 | B121: 0 | C121: 3448 | D121: -2549277.1 | E121: PU/25/SLS/OT/1832 | F121: Handling Charges - Outbound (Exp) - SLSIPL | G121: PU/25/SLS/OT/1832 | H121: 246779413694 | L121: 246779411755 | M121: 0 | N121: 5816 | P121: 246779411755 | Q121: 0 | R121: 5816
A122: 45747 | B122: 0 | C122: 191 | D122: -2549468.1 | E122: PU/25/SLS/OT/1833 | F122: Handling Charges - Outbound (Exp) - SLSIPL | G122: PU/25/SLS/OT/1833 | H122: 246779413695 | L122: 246779411756 | M122: 0 | N122: 4339 | P122: 246779411756 | Q122: 0 | R122: 4339
A123: 45747 | B123: 0 | C123: 382 | D123: -2549850.1 | E123: PU/25/SLS/OT/1834 | F123: Handling Charges - Outbound (Exp) - SLSIPL | G123: PU/25/SLS/OT/1834 | H123: 246779413696 | L123: 246779411757 | M123: 0 | N123: 3110 | P123: 246779411757 | Q123: 0 | R123: 3110
A124: 45747 | B124: 0 | C124: 381 | D124: -2550231.1 | E124: PU/25/SLS/OT/1835 | F124: Handling Charges - Outbound (Exp) - SLSIPL | G124: PU/25/SLS/OT/1835 | H124: 246779410846 | L124: 246779411758 | M124: 0 | N124: 1842 | P124: 246779411758 | Q124: 0 | R124: 1842
A125: 45747 | B125: 0 | C125: 1528 | D125: -2551759.1 | E125: PU/25/SLS/OT/1836 | F125: Handling Charges - Outbound (Exp) - SLSIPL | G125: PU/25/SLS/OT/1836 | H125: 246779410847 | L125: 246779411759 | M125: 0 | N125: 6761 | P125: 246779411759 | Q125: 0 | R125: 6761
... A147: 45747 | B147: 0 | C147: 33376 | D147: -2809572.1 | E147: PU/25/SLS/OT/1925 | F147: Container Scanning Paid - SLSIPL | G147: PU/25/SLS/OT/1925 | H147: 246779411300 | L147: 246779413701 | M147: 0 | N147: 18367 | P147: 246779413701 | Q147: 0 | R147: 18367
A148: 45748 | B148: 0 | C148: 1161 | D148: -2810733.1 | E148: PU/26/SLS/OT/0048 | F148: VOS Activity Charges Paid - SLSIPL | G148: PU/26/SLS/OT/0048 | H148: 246779411448 | L148: 246779413702 | P148: 246779413702 | Q148: 0 | R148: 31577
A149: 45748 | B149: 0 | C149: 1591 | D149: -2812324.1 | E149: PU/26/SLS/OT/0193 | F149: Handling Charges - Outbound (Exp) - SLSIPL | G149: PU/26/SLS/OT/0193 | H149: 246779413689 | L149: 246779413704 | M149: 0 | N149: 13011 | P149: 246779413704 | Q149: 0 | R149: 13011
A150: 45748 | B150: 0 | C150: 574 | D150: -2812898.1 | E150: PU/26/SLS/OT/0194 | F150: Handling Charges - Outbound (Exp) - SLSIPL | G150: PU/26/SLS/OT/0194 | H150: 246779413740 | L150: 246779413705 | M150: 0 | N150: 19429 | P150: 246779413705 | Q150: 19430 | R150: 19429
A151: 45748 | B151: 0 | C151: 574 | D151: -2813472.1 | E151: PU/26/SLS/OT/0195 | F151: Handling Charges - Outbound (Exp) - SLSIPL | G151: PU/26/SLS/OT/0195 | H151: 246779413737 | L151: 246779413733 | M151: 0 | N151: 191 | P151: 246779413733 | Q151: 0 | R151: 191
A152: 45748 | B152: 0 | C152: 6896 | D152: -2820368.1 | E152: PU/26/SLS/OT/0196 | F152: Handling Charges - Outbound (Exp) - SLSIPL | G152: PU/26/SLS/OT/0196 | H152: 246779413735 | L152: 246779413734 | M152: 0 | N152: 3448 | P152: 246779413734 | Q152: 0 | R152: 3448
A153: 45748 | B153: 0 | C153: 191 | D153: -2820559.1 | E153: PU/26/SLS/OT/0197 | F153: Handling Charges - Outbound (Exp) - SLSIPL | G153: PU/26/SLS/OT/0197 | H153: 246779413744 | L153: 246779413735 | M153: 0 | N153: 6896 | P153: 246779413735 | Q153: 0 | R153: 6896
A154: 45748 | B154: 0 | C154: 191 | D154: -2820750.1 | E154: PU/26/SLS/OT/0199 | F154: Handling Charges - Outbound (Exp) - SLSIPL | G154: PU/26/SLS/OT/0199 | H154: 246779413733 | L154: 246779413736 | M154: 0 | N154: 6513 | P154: 246779413736 | Q154: 0 | R154: 6513
A155: 45748 | B155: 0 | C155: 383 | D155: -2821133.1 | E155: PU/26/SLS/OT/0200 | F155: Handling Charges - Outbound (Exp) - SLSIPL | G155: PU/26/SLS/OT/0200 | H155: 246779413743 | L155: 246779413737 | M155: 0 | N155: 574 | P155: 246779413737 | Q155: 0 | R155: 574
A156: 45748 | B156: 0 | C156: 383 | D156: -2821516.1 | E156: PU/26/SLS/OT/0201 | F156: Handling Charges - Outbound (Exp) - SLSIPL | G156: PU/26/SLS/OT/0201 | H156: 246779414680 | L156: 246779413738 | M156: 0 | N156: 3603 | P156: 246779413738 | Q156: 0 | R156: 3603
A157: 45748 | B157: 0 | C157: 6895 | D157: -2828411.1 | E157: PU/26/SLS/OT/0202 | F157: Handling Charges - Outbound (Exp) - SLSIPL | G157: PU/26/SLS/OT/0202 | H157: 246779413741 | L157: 246779413739 | M157: 0 | N157: 1724 | P157: 246779413739 | Q157: 0 | R157: 1724
A158: 45748 | B158: 0 | C158: 846 | D158: -2829257.1 | E158: PU/26/SLS/OT/0191 | F158: Handling Charges - Inbound (Exp) - SLSIPL | G158: PU/26/SLS/OT/0191 | H158: 246779413933 | L158: 246779413740 | M158: 0 | N158: 574 | P158: 246779413740 | Q158: 0 | R158: 574
A159: 45748 | B159: 0 | C159: 3203 | D159: -2832460.1 | E159: PU/26/SLS/OT/0301-1 | F159: Handling Charges - Outbound (Exp) - SLSIPL | G159: PU/26/SLS/OT/0301-1 | H159: 246779410609 | L159: 246779413741 | M159: 0 | N159: 6895 | P159: 246779413741 | Q159: 0 | R159: 6895
A160: 45748 | B160: 0 | C160: 3603 | D160: -2836063.1 | E160: PU/26/SLS/OT/0324 | F160: Handling Charges - Outbound (Exp) - SLSIPL | G160: PU/26/SLS/OT/0324 | H160: 246779413738 | L160: 246779413742 | M160: 0 | N160: 1149 | P160: 246779413742 | Q160: 0 | R160: 1149
... A167: 45748 | B167: 0 | C167: 35477 | D167: -2953162.1 | E167: PU/26/SLS/OT/0780-2 | F167: Fixed Storage Charges - ODC (Covered) - SLSIPL | G167: PU/26/SLS/OT/0780-2 | H167: 246779410072 | L167: 246779413782 | M167: 0 | N167: 596 | P167: 246779413782 | Q167: 0 | R167: 596
A168: 45748 | B168: 0 | C168: 799 | D168: -2953961.1 | E168: PU/26/SLS/OT/0785-1 | F168: Handling Charges - Outbound (Exp) - SLSIPL | G168: PU/26/SLS/OT/0785-1 | H168: 246779410688 | L168: 246779413796 | P168: 246779413796 | Q168: 0 | R168: 163631
A169: 45748 | B169: 0 | C169: 1797 | D169: -2955758.1 | E169: PU/26/SLS/OT/0784-1 | F169: Handling Charges - Outbound (Exp) - SLSIPL | G169: PU/26/SLS/OT/0784-1 | H169: 246779410687 | L169: 246779413816 | M169: 0 | N169: 18610 | P169: 246779413816 | Q169: 18611 | R169: 18610
A170: 45748 | B170: 0 | C170: 59624 | D170: -3015382.1 | E170: PU/26/SLS/OT/0591-1 | F170: Storage Charges - Cargo - SLSIPL | G170: PU/26/SLS/OT/0591-1 | H170: 246779410360 | L170: 246779413827 | M170: 0 | N170: 31723 | P170: 246779413827 | Q170: 31723 | R170: 31723
A171: 45750 | B171: 0 | C171: 2883 | D171: -3018265.1 | E171: PU/26/SLS/OT/0046 | F171: MHE Charges Paid - SLSIPL | G171: PU/26/SLS/OT/0046 | H171: 256779410157 | L171: 246779413845 | M171: 0 | N171: 45188 | P171: 246779413845 | Q171: 11955 | R171: 45188
A172: 45750 | B172: 0 | C172: 4913 | D172: -3023178.1 | E172: PU/26/SLS/OT/0047 | F172: Handling Charges - Inbound (Exp) - SLSIPL | G172: PU/26/SLS/OT/0047 | H172: 256779410156 | L172: 246779413933 | M172: 0 | N172: 846 | P172: 246779413933 | Q172: 0 | R172: 846
A173: 45750 | B173: 0 | C173: 13011 | D173: -3036189.1 | E173: PU/26/SLS/OT/0323 | F173: Handling Charges - Outbound (Exp) - SLSIPL | G173: PU/26/SLS/OT/0323 | H173: 256779410166 | L173: 246779414141 | M173: 0 | N173: 4652 | P173: 246779414141 | Q173: 0 | R173: 4652
A174: 45750 | B174: 0 | C174: 6205 | D174: -3042394.1 | E174: PU/26/SLS/OT/0326 | F174: Handling Charges - Outbound (Exp) - SLSIPL | G174: PU/26/SLS/OT/0326 | H174: 256779410174 | L174: 246779414142 | M174: 0 | N174: 1268 | P174: 246779414142 | Q174: 0 | R174: 1268
A175: 45750 | B175: 0 | C175: 2937 | D175: -3045331.1 | E175: PU/26/SLS/OT/0332 | F175: VOS Activity Charges Paid - SLSIPL | G175: PU/26/SLS/OT/0332 | H175: 256779410201 | L175: 246779414221 | M175: 0 | N175: 17701 | P175: 246779414221 | Q175: 0 | R175: 17701
A176: 45750 | B176: 0 | C176: 319 | D176: -3045650.1 | E176: PU/26/SLS/OT/0338 | F176: Gate In Charges Paid - SLSIPL | G176: PU/26/SLS/OT/0338 | H176: 256779410135 | L176: 246779414317 | M176: 0 | N176: 1907 | P176: 246779414317 | Q176: 0 | R176: 1907
A177: 45750 | B177: 0 | C177: 639 | D177: -3046289.1 | E177: PU/26/SLS/OT/0331 | F177: Handling Charges - Inbound (Exp) - SLSIPL | G177: PU/26/SLS/OT/0331 | H177: 256779410134 | L177: 246779414467 | M177: 0 | N177: 2674 | P177: 246779414467 | Q177: 0 | R177: 2674
A178: 45750 | B178: 0 | C178: 140649 | D178: -3186938.1 | E178: PU/26/SLS/OT/0612 | F178: Storage Charges - Cargo - SLSIPL | G178: PU/26/SLS/OT/0612 | H178: 256779410010 | L178: 246779414603 | M178: 0 | N178: 34760 | P178: 246779414603 | Q178: 0 | R178: 34760
A179: 45750 | B179: 0 | C179: 55272 | D179: -3242210.1 | E179: PU/26/SLS/OT/0613 | F179: Storage Charges - Cargo - SLSIPL | G179: PU/26/SLS/OT/0613 | H179: 256779410004 | L179: 246779414680 | M179: 0 | N179: 383 | P179: 246779414680 | Q179: 0 | R179: 383
A180: 45750 | B180: 0 | C180: 114223 | D180: -3356433.1 | E180: PU/26/SLS/OT/0611-1 | F180: Storage Charges - Cargo - SLSIPL | G180: PU/26/SLS/OT/0611-1 | H180: 256779410220 | L180: 246779414681 | M180: 0 | N180: 1268 | P180: 246779414681 | Q180: 0 | R180: 1268
... A222: 45805 | B222: 0 | C222: 333696 | D222: -5193789.1 | E222: PU/26/SLS/OT/0278 | F222: Storage Charges - Cargo - SLSIPL | G222: PU/26/SLS/OT/0278 | H222: 256779413899 | L222: 256779413163 | M222: 0 | N222: 15927 | P222: 256779413163 | Q222: 0 | R222: 15927
A223: 45807 | B223: 177773 | C223: 0 | D223: -5016016.1 | E223: BP/26/SLS/0192 | F223: 1395250393003 - Punjab National Bank - INR - SLSIPL | L223: 256779413172 | M223: 0 | N223: 11810 | P223: 256779413172 | Q223: 0 | R223: 11810
A224: 45812 | B224: 0 | C224: 9844 | D224: -5025860.1 | E224: PU/26/SLS/OT/0358 | F224: Handling Charges - Outbound (Exp) - SLSIPL | G224: PU/26/SLS/OT/0358 | H224: 256779414165 | L224: 256779413184 | M224: 0 | N224: 11723.018 | P224: 256779413184 | Q224: 0 | R224: 11723.018
A225: 45812 | B225: 0 | C225: 8407 | D225: -5034267.1 | E225: PU/26/SLS/OT/0360 | F225: Handling Charges - Outbound (Exp) - SLSIPL | G225: PU/26/SLS/OT/0360 | H225: 256779414216 | L225: 256779413243 | M225: 0 | N225: 3623 | P225: 256779413243 | Q225: 0 | R225: 3623
A226: 45812 | B226: 500946.52 | C226: 0 | D226: -4533320.6 | E226: BP/25/SLS/1225-1 | F226: 1395250393003 - Punjab National Bank - INR - SLSIPL | G226: PU/25/SLS/OT/1562, PU/25/SLS/OT/1720, PU/25/SLS/OT/1731, PU/25/SLS/OT/1721, PU/25/SLS/OT/1673 | L226: 256779413283 | M226: 0 | N226: 11797 | P226: 256779413283 | Q226: 11798 | R226: 11797
A227: 45812 | B227: 0 | C227: 17313 | D227: -4550633.6 | E227: PU/26/SLS/OT/0585 | F227: Scanning Charges - Inbound - SLSIPL | G227: PU/26/SLS/OT/0585 | H227: 256779414288 | L227: 256779413357 | M227: 0 | N227: 1264 | P227: 256779413357 | Q227: 0 | R227: 1264
A228: 45812 | B228: 0 | C228: 41769 | D228: -4592402.6 | E228: PU/26/SLS/OT/0797 | F228: Handling Charges - Inbound (Exp) - SLSIPL,LCL Movment - Gate in Charge - SLSIPL,Transportation Charges Paid - SLSIPL,Eempty Container Return Charges Paid - SLSIPL | G228: PU/26/SLS/OT/0797 | H228: 256779414158 | L228: 256779413404 | M228: 0 | N228: 7129 | P228: 256779413404 | Q228: 0 | R228: 7129
A229: 45815 | B229: 0 | C229: 352792 | D229: -4945194.6 | E229: PU/26/SLS/OT/0285 | F229: Storage Charges - Cargo - SLSIPL | G229: PU/26/SLS/OT/0285 | H229: 256779414242 | L229: 256779413405 | M229: 0 | N229: 3960 | P229: 256779413405 | Q229: 0 | R229: 3960
A230: 45818 | B230: 0 | C230: 35431 | D230: -4980625.6 | E230: PU/26/SLS/OT/0357-1 | F230: Fixed Storage Charges - ODC (Covered) - SLSIPL | G230: PU/26/SLS/OT/0357-1 | H230: 256779414386 | L230: 256779413427 | M230: 0 | N230: 990 | P230: 256779413427 | Q230: 0 | R230: 990
A231: 45821 | B231: 700000 | C231: 0 | D231: -4280625.6 | E231: BP/26/SLS/0229 | F231: 1395250393003 - Punjab National Bank - INR - SLSIPL | L231: 256779413428 | M231: 0 | N231: 990 | P231: 256779413428 | Q231: 0 | R231: 990
A232: 45829 | B232: 700000 | C232: 0 | D232: -3580625.6 | E232: BP/26/SLS/0259 | F232: 1395250393003 - Punjab National Bank - INR - SLSIPL | L232: 256779413429 | M232: 0 | N232: 601 | P232: 256779413429 | Q232: 0 | R232: 601
A233: 45838 | B233: 700000 | C233: 0 | D233: -2880625.6 | E233: BP/26/SLS/0291 | F233: 1395250393003 - Punjab National Bank - INR - SLSIPL | L233: 256779413430 | M233: 0 | N233: 1201 | P233: 256779413430 | Q233: 0 | R233: 1201
A234: 45843 | B234: 700000 | C234: 0 | D234: -2180625.6 | E234: BP/26/SLS/0300 | F234: 1395250393003 - Punjab National Bank - INR - SLSIPL | L234: 256779413486 | M234: 0 | N234: 1054 | P234: 256779413486 | Q234: 0 | R234: 1054
A235: 45849 | B235: 700000 | C235: 0 | D235: -1480625.6 | E235: BP/26/SLS/0311 | F235: 1395250393003 - Punjab National Bank - INR - SLSIPL | L235: 256779413837 | M235: 0 | N235: 12177 | P235: 256779413837 | Q235: 0 | R235: 12177
A236: 45849 | B236: 0 | C236: 151725 | D236: -1632350.6 | E236: PU/26/SLS/OT/0415-1 | F236: Storage Charges - Cargo - SLSIPL | G236: PU/26/SLS/OT/0415-1 | H236: 246779410348 | L236: 256779413899 | M236: 0 | N236: 333696 | P236: 256779413899 | Q236: 0 | R236: 333696
A237: 45854 | B237: 19430 | C237: 0 | D237: -1612920.6 | E237: SLS26/MF/DN/0006 | F237: Storage Charges - Cargo - SLSIPL | G237: PU/26/SLS/OT/0590 | H237: DN | I237: 246779413705 | L237: 256779414158 | M237: 0 | N237: 41769 | P237: 256779414158 | Q237: 0 | R237: 41769
A238: 45854 | B238: 18611 | C238: 0 | D238: -1594309.6 | E238: SLS26/MF/DN/0008 | F238: Container Scanning Paid - SLSIPL | G238: PU/25/SLS/OT/1821 | H238: DN | I238: 246779413816 | L238: 256779414165 | M238: 0 | N238: 9844 | P238: 256779414165 | Q238: 0 | R238: 9844
A239: 45854 | B239: 31723 | C239: 0 | D239: -1562586.6 | E239: SLS26/MF/DN/0009 | F239: Container Scanning Paid - SLSIPL | G239: PU/25/SLS/OT/1822 | H239: DN | I239: 246779413827 | L239: 256779414216 | M239: 0 | N239: 8407 | P239: 256779414216 | Q239: 0 | R239: 8407
A240: 45854 | B240: 17857 | C240: 0 | D240: -1544729.6 | E240: SLS26/MF/DN/0011 | F240: Container Scanning Paid - SLSIPL | G240: PU/25/SLS/OT/1854 | H240: DN | I240: 246779411339 | L240: 256779414242 | M240: 0 | N240: 352792 | P240: 256779414242 | Q240: 0 | R240: 352792
A241: 45854 | B241: 11798 | C241: 0 | D241: -1532931.6 | E241: SLS26/MF/DN/0013 | F241: Container Scanning Paid - SLSIPL | G241: PU/26/SLS/OT/0283 | H241: DN | I241: 256779413283 | L241: 256779414288 | M241: 0 | N241: 17313 | P241: 256779414288 | Q241: 0 | R241: 17313
A242: 45854 | B242: 20874 | C242: 0 | D242: -1512057.6 | E242: SLS26/MF/DN/0014 | F242: Container Scanning Paid - SLSIPL | G242: PU/25/SLS/OT/1820 | H242: DN | I242: 246779411326 | L242: 256779414340 | M242: 0 | N242: 45061.335 | P242: 256779414340 | Q242: 0 | R242: 45061.335
A243: 45854 | B243: 140649 | C243: 0 | D243: -1371408.6 | E243: SLS26/MF/DN/0016 | F243: Storage Charges - Cargo - SLSIPL | G243: PU/26/SLS/OT/0612 | H243: DN | I243: 256779410010 | L243: 256779414386 | M243: 0 | N243: 35431 | P243: 256779414386 | Q243: 0 | R243: 35431
A244: 45854 | B244: 55272 | C244: 0 | D244: -1316136.6 | E244: SLS26/MF/DN/0017 | F244: Storage Charges - Cargo - SLSIPL | G244: PU/26/SLS/OT/0613 | H244: DN | I244: 256779410004 | L244: 256779414743 | M244: 0 | N244: 6064.023 | P244: 256779414743 | Q244: 0 | R244: 6064.023
A245: 45854 | B245: 4786 | C245: 0 | D245: -1311350.6 | E245: SLS26/MF/DN/0007-2 | F245: Storage Charges - Cargo - SLSIPL | G245: SLS26/MF/DN/0007-2 | H245: DN | I245: 256779421381 | L245: 256779414748 | M245: 0 | N245: 1800.351 | P245: 256779414748 | Q245: 0 | R245: 1800.351
A246: 45854 | B246: 11955 | C246: 0 | D246: -1299395.6 | E246: SLS26/MF/DN/0004-1 | F246: Transportation Charges Paid - SLSIPL | G246: PU/26/SLS/OT/0588 | H246: DN | I246: 246779413845 | L246: 256779414758 | M246: 0 | N246: 14610.374 | P246: 256779414758 | Q246: 0 | R246: 14610.374
A247: 45854 | B247: 0 | C247: 163631 | D247: -1463026.6 | E247: PU/26/SLS/OT/0614-1 | F247: Storage Charges - Cargo - SLSIPL | G247: PU/26/SLS/OT/0614-1 | I247: 246779413796 | L247: 256779414768 | M247: 0 | N247: 1492.1116 | P247: 256779414768 | Q247: 0 | R247: 1492.1116
A248: 45854 | B248: 12467 | C248: 0 | D248: -1450559.6 | E248: SLS26/MF/DN/0018-1 | F248: Storage Charges - Cargo - SLSIPL | G248: SLS26/MF/DN/0018-1 | H248: DN | I248: 256779421383 | L248: 256779414829 | M248: 0 | N248: 8595.767 | P248: 256779414829 | Q248: 0 | R248: 8595.767
A249: 45854 | B249: 6084 | C249: 0 | D249: -1444475.6 | E249: SLS26/MF/DN/0002-1 | F249: Scanning Charges - Inbound - SLSIPL | G249: SLS26/MF/DN/0002-1 | H249: DN | I249: 256779421376 | L249: 256779414878 | M249: 0 | N249: 2642.8006 | P249: 256779414878 | Q249: 0 | R249: 2642.8006
A250: 45854 | B250: 12169 | C250: 0 | D250: -1432306.6 | E250: SLS26/MF/DN/0003-1 | F250: Scanning Charges - Inbound - SLSIPL | G250: SLS26/MF/DN/0003-1 | H250: DN | I250: 256779421370 | L250: 256779414890 | M250: 0 | N250: 91401.512 | P250: 256779414890 | Q250: 0 | R250: 91401.512
A251: 45854 | B251: 114223 | C251: 0 | D251: -1318083.6 | E251: SLS26/MF/DN/0015-1 | F251: Storage Charges - Cargo - SLSIPL | G251: SLS26/MF/DN/0015-1 | H251: DN | I251: 256779421367 | L251: 256779414944 | M251: 0 | N251: 35324.775 | P251: 256779414944 | Q251: 0 | R251: 35324.775
A252: 45854 | B252: 0 | C252: 31577 | D252: -1349660.6 | E252: PU/26/SLS/OT/0589-2 | F252: Storage Charges - Cargo - SLSIPL | G252: PU/26/SLS/OT/0589-2 | I252: 246779413702 | L252: 256779414968 | M252: 0 | N252: 2629.9005 | P252: 256779414968 | Q252: 0 | R252: 2629.9005
A253: 45854 | B253: 31577 | C253: 0 | D253: -1318083.6 | E253: SLS26/MF/DN/0005-1 | F253: Storage Charges - Cargo - SLSIPL | G253: SLS26/MF/DN/0005-1 | H253: DN | I253: 256779421361 | L253: 256779414975 | M253: 0 | N253: 4562.3355 | P253: 256779414975 | Q253: 0 | R253: 4562.3355
A254: 45854 | B254: 17313 | C254: 330 | D254: -1301100.6 | E254: SLS26/MF/DN/0001-2 | F254: Scanning Charges - Inbound - SLSIPL | G254: SLS26/MF/DN/0001-2, SLS26/MF/DN/0001-2 | H254: DN | I254: 256779421379 | L254: 256779415048 | M254: 0 | N254: 552.9843 | P254: 256779415048 | Q254: 0 | R254: 552.9843
A255: 45854 | B255: 8696 | C255: 173 | D255: -1292577.6 | E255: SLS26/MF/DN/0010-1 | F255: Container Scanning Paid - SLSIPL | G255: SLS26/MF/DN/0010-1, SLS26/MF/DN/0010-1 | H255: DN | I255: 256779421373 | L255: 256779415198 | M255: 0 | N255: 257812.81 | P255: 256779415198 | Q255: 0 | R255: 257812.81
A256: 45857 | B256: 700000 | C256: 0 | D256: -592577.6 | E256: BP/26/SLS/0368 | F256: 1395250393003 - Punjab National Bank - INR - SLSIPL | L256: 256779415263 | M256: 0 | N256: 201.2416 | P256: 256779415263 | Q256: 0 | R256: 201.2416
A257: 45862 | B257: 0 | C257: 9368 | D257: -601945.6 | E257: PU/26/SLS/OT/0607 | F257: Handling Charges - Inbound (Exp) - SLSIPL | G257: PU/26/SLS/OT/0607 | I257: 256779415945 | L257: 256779415444 | M257: 0 | N257: 8342.065 | P257: 256779415444 | Q257: 0 | R257: 8342.065
A258: 45863 | B258: 350672 | C258: 0 | D258: -251273.6 | E258: BP/26/SLS/0394 | F258: 1395250393003 - Punjab National Bank - INR - SLSIPL | L258: 256779415456 | M258: 0 | N258: 13522.745 | P258: 256779415456 | Q258: 0 | R258: 13522.745
A259: 45863 | B259: 0 | C259: 32007 | D259: -283280.6 | E259: PU/26/SLS/OT/0608 | F259: Storage Charges - Cargo - SLSIPL | G259: PU/26/SLS/OT/0608 | I259: 256779415967 | L259: 256779415771 | M259: 0 | N259: 2559.3799 | P259: 256779415771 | Q259: 0 | R259: 2559.3799
A260: 45863 | B260: 0 | C260: 9348 | D260: -292628.6 | E260: PU/26/SLS/OT/0609 | F260: Storage Charges - Cargo - SLSIPL | G260: PU/26/SLS/OT/0609 | I260: 256779415970 | L260: 256779415801 | M260: 0 | N260: 148540.36 | P260: 256779415801 | Q260: 0 | R260: 148540.36
A261: 45863 | B261: 0 | C261: 196 | D261: -292824.6 | E261: PU/26/SLS/OT/0610 | F261: VOS Activity Charges Paid - SLSIPL | G261: PU/26/SLS/OT/0610 | I261: 256779415995 | L261: 256779415939 | M261: 0 | N261: 11782.092 | P261: 256779415939 | Q261: 0 | R261: 11782.092
A262: 45869 | B262: 33376 | C262: 0 | D262: -259448.6 | E262: SLS26/MF/DN/0019 | F262: Container Scanning Paid - SLSIPL | G262: PU/25/SLS/OT/1925 | H262: DN | I262: 246779411300 | L262: 256779416054 | M262: 0 | N262: 35336.872 | P262: 256779415945 | Q262: 0 | R262: 9368
A263: 45869 | B263: 15778 | C263: 0 | D263: -243670.6 | E263: SLS26/MF/DN/0020-1 | F263: Storage Charges - Cargo - SLSIPL | G263: SLS26/MF/DN/0020-1 | H263: DN | I263: 246779410348/256779421380 | L263: 256779416088 | M263: 0 | N263: 462828 | P263: 256779415967 | Q263: 0 | R263: 32007
A264: 45869 | B264: 0 | C264: 44602 | D264: -288272.6 | E264: PU/26/SLS/OT/1009-1 | F264: Container Scanning Paid - SLSIPL | G264: PU/26/SLS/OT/1009-1 | I264: 246779411278 | L264: 256779416178 | M264: 1351 | N264: 67557 | P264: 256779415970 | Q264: 0 | R264: 9348
A265: 45869 | B265: 36410 | C265: 0 | D265: -251862.6 | E265: SLS26/MF/DN/0022-1 | F265: Container Scanning Paid - SLSIPL | G265: SLS26/MF/DN/0022-1 | H265: DN | I265: 246779411278/256779421385 | L265: 256779416223 | M265: 0 | N265: 9124 | P265: 256779415995 | Q265: 0 | R265: 196
A266: 45869 | B266: 15401 | C266: 0 | D266: -236461.6 | E266: SLS26/MF/DN/0021-1 | F266: Fixed Storage Charges - ODC (Covered) - SLSIPL | G266: SLS26/MF/DN/0021-1 | H266: DN | I266: 256779421382/246779413701 | L266: 256779416256 | M266: 0 | N266: 4755 | P266: 256779416054 | Q266: 0 | R266: 35336.872
...

Sheet Customer Data
A1: Posting Date | B1: Account | C1: Debit (INR) | D1: Credit (INR) | E1: Balance (INR) | F1: Voucher Type | G1: Voucher Subtype | H1: Voucher No | I1: Against Account | J1: Party Type | K1: Party | L1: Against Voucher | M1: Supplier Invoice No
A2: 45708 | B2: Sundry Creditors - SLSIPL | C2: 0 | D2: 35554.52 | E2: -35554.52 | F2: Purchase Invoice | G2: Purchase Invoice | H2: PU/25/SLS/OT/1560 | I2: Fixed Storage Charges - ODC (Covered) - SLSIPL | J2: Supplier | K2: Ascendas Panvel FTWZ Private Limited | L2: PU/25/SLS/OT/1560 | M2: 246779410049
A3: 45708 | B3: Sundry Creditors - SLSIPL | C3: 0 | D3: 35554.52 | E3: -71109.04 | F3: Purchase Invoice | G3: Purchase Invoice | H3: PU/25/SLS/OT/1561 | I3: Fixed Storage Charges - ODC (Covered) - SLSIPL | J3: Supplier | K3: Ascendas Panvel FTWZ Private Limited | L3: PU/25/SLS/OT/1561 | M3: 246779410303
A4: 45708 | B4: Sundry Creditors - SLSIPL | C4: 0 | D4: 35554.52 | E4: -106663.56 | F4: Purchase Invoice | G4: Purchase Invoice | H4: PU/25/SLS/OT/1562 | I4: Fixed Storage Charges - ODC (Covered) - SLSIPL | J4: Supplier | K4: Ascendas Panvel FTWZ Private Limited | L4: PU/25/SLS/OT/1562 | M4: 246779410117
A5: 45708 | B5: Sundry Creditors - SLSIPL | C5: 0 | D5: 35554.52 | E5: -142218.08 | F5: Purchase Invoice | G5: Purchase Invoice | H5: PU/25/SLS/OT/1563 | I5: Fixed Storage Charges - ODC (Covered) - SLSIPL | J5: Supplier | K5: Ascendas Panvel FTWZ Private Limited | L5: PU/25/SLS/OT/1563 | M5: 246779410160
A6: 45708 | B6: Sundry Creditors - SLSIPL | C6: 0 | D6: 35554.52 | E6: -177772.6 | F6: Purchase Invoice | G6: Purchase Invoice | H6: PU/25/SLS/OT/1564 | I6: Fixed Storage Charges - ODC (Covered) - SLSIPL | J6: Supplier | K6: Ascendas Panvel FTWZ Private Limited | L6: PU/25/SLS/OT/1564 | M6: 246779410203
A7: 45708 | B7: Sundry Creditors - SLSIPL | C7: 0 | D7: 35554.52 | E7: -213327.12 | F7: Purchase Invoice | G7: Purchase Invoice | H7: PU/25/SLS/OT/1565 | I7: Fixed Storage Charges - ODC (Covered) - SLSIPL | J7: Supplier | K7: Ascendas Panvel FTWZ Private Limited | L7: PU/25/SLS/OT/1565 | M7: 246779410246
A8: 45719 | B8: Sundry Creditors - SLSIPL | C8: 0 | D8: 804 | E8: -214131.12 | F8: Purchase Invoice | G8: Purchase Invoice | H8: PU/25/SLS/OT/1672 | I8: Handling Charges - Outbound (Exp) - SLSIPL | J8: Supplier | K8: Ascendas Panvel FTWZ Private Limited | L8: PU/25/SLS/OT/1672 | M8: 246779410613
A9: 45719 | B9: Sundry Creditors - SLSIPL | C9: 0 | D9: 1004 | E9: -215135.12 | F9: Purchase Invoice | G9: Purchase Invoice | H9: PU/25/SLS/OT/1673 | I9: Handling Charges - Outbound (Exp) - SLSIPL | J9: Supplier | K9: Ascendas Panvel FTWZ Private Limited | L9: PU/25/SLS/OT/1673 | M9: 246779410612
A10: 45719 | B10: Sundry Creditors - SLSIPL | C10: 0 | D10: 402 | E10: -215537.12 | F10: Purchase Invoice | G10: Purchase Invoice | H10: PU/25/SLS/OT/1674 | I10: Handling Charges - Outbound (Exp) - SLSIPL | J10: Supplier | K10: Ascendas Panvel FTWZ Private Limited | L10: PU/25/SLS/OT/1674 | M10: 246779410611
A11: 45719 | B11: Sundry Creditors - SLSIPL | C11: 0 | D11: 201 | E11: -215738.12 | F11: Purchase Invoice | G11: Purchase Invoice | H11: PU/25/SLS/OT/1675 | I11: Handling Charges - Outbound (Exp) - SLSIPL | J11: Supplier | K11: Ascendas Panvel FTWZ Private Limited | L11: PU/25/SLS/OT/1675 | M11: 246779410610
A12: 45719 | B12: Sundry Creditors - SLSIPL | C12: 0 | D12: 804 | E12: -216542.12 | F12: Purchase Invoice | G12: Purchase Invoice | H12: PU/25/SLS/OT/1676 | I12: Handling Charges - Outbound (Exp) - SLSIPL | J12: Supplier | K12: Ascendas Panvel FTWZ Private Limited | L12: PU/25/SLS/OT/1676 | M12: 246779410608
A13: 45719 | B13: Sundry Creditors - SLSIPL | C13: 0 | D13: 402 | E13: -216944.12 | F13: Purchase Invoice | G13: Purchase Invoice | H13: PU/25/SLS/OT/1677 | I13: Handling Charges - Outbound (Exp) - SLSIPL | J13: Supplier | K13: Ascendas Panvel FTWZ Private Limited | L13: PU/25/SLS/OT/1677 | M13: 246779410607
... A109: 45849 | B109: Sundry Creditors - SLSIPL | C109: 0 | D109: 151725 | E109: -1632350.6 | F109: Purchase Invoice | G109: Purchase Invoice | H109: PU/26/SLS/OT/0415-1 | I109: Storage Charges - Cargo - SLSIPL | J109: Supplier | K109: Ascendas Panvel FTWZ Private Limited | L109: PU/26/SLS/OT/0415-1 | M109: 246779410348
A110: 45937 | B110: Sundry Creditors - SLSIPL | C110: 15778 | D110: 15778 | E110: -757662.6 | F110: Journal Entry | G110: Debit Note | H110: SJ/25/GEA/1104 | J110: Supplier | K110: Ascendas Panvel FTWZ Private Limited | L110: PU/26/SLS/OT/0415-1, SLS26/MF/DN/0020-1 | M110: 246779410348
A111: 45747 | B111: Sundry Creditors - SLSIPL | C111: 0 | D111: 31723 | E111: -2522653.1 | F111: Purchase Invoice | G111: Purchase Invoice | H111: PU/25/SLS/OT/1823 | I111: Container Scanning Paid - SLSIPL | J111: Supplier | K111: Ascendas Panvel FTWZ Private Limited | L111: PU/25/SLS/OT/1823 | M111: 246779413753
A112: 45747 | B112: Sundry Creditors - SLSIPL | C112: 0 | D112: 191 | E112: -2522844.1 | F112: Purchase Invoice | G112: Purchase Invoice | H112: PU/25/SLS/OT/1824 | I112: Handling Charges - Outbound (Exp) - SLSIPL | J112: Supplier | K112: Ascendas Panvel FTWZ Private Limited | L112: PU/25/SLS/OT/1824 | M112: 246779413762
A113: 45747 | B113: Sundry Creditors - SLSIPL | C113: 0 | D113: 3064 | E113: -2525908.1 | F113: Purchase Invoice | G113: Purchase Invoice | H113: PU/25/SLS/OT/1825 | I113: Handling Charges - Outbound (Exp) - SLSIPL | J113: Supplier | K113: Ascendas Panvel FTWZ Private Limited | L113: PU/25/SLS/OT/1825 | M113: 246779413745
A114: 45747 | B114: Sundry Creditors - SLSIPL | C114: 0 | D114: 3448 | E114: -2529356.1 | F114: Purchase Invoice | G114: Purchase Invoice | H114: PU/25/SLS/OT/1826 | I114: Handling Charges - Outbound (Exp) - SLSIPL | J114: Supplier | K114: Ascendas Panvel FTWZ Private Limited | L114: PU/25/SLS/OT/1826 | M114: 246779413734
A115: 45747 | B115: Sundry Creditors - SLSIPL | C115: 0 | D115: 6513 | E115: -2535869.1 | F115: Purchase Invoice | G115: Purchase Invoice | H115: PU/25/SLS/OT/1827 | I115: Handling Charges - Outbound (Exp) - SLSIPL | J115: Supplier | K115: Ascendas Panvel FTWZ Private Limited | L115: PU/25/SLS/OT/1827 | M115: 246779413736
A116: 45747 | B116: Sundry Creditors - SLSIPL | C116: 0 | D116: 1724 | E116: -2537593.1 | F116: Purchase Invoice | G116: Purchase Invoice | H116: PU/25/SLS/OT/1828 | I116: Handling Charges - Outbound (Exp) - SLSIPL | J116: Supplier | K116: Ascendas Panvel FTWZ Private Limited | L116: PU/25/SLS/OT/1828 | M116: 246779413739
A117: 45747 | B117: Sundry Creditors - SLSIPL | C117: 0 | D117: 1149 | E117: -2538742.1 | F117: Purchase Invoice | G117: Purchase Invoice | H117: PU/25/SLS/OT/1829 | I117: Handling Charges - Outbound (Exp) - SLSIPL | J117: Supplier | K117: Ascendas Panvel FTWZ Private Limited | L117: PU/25/SLS/OT/1829 | M117: 246779413742
A118: 45747 | B118: Sundry Creditors - SLSIPL | C118: 0 | D118: 191 | E118: -2538933.1 | F118: Purchase Invoice | G118: Purchase Invoice | H118: PU/25/SLS/OT/1830 | I118: Handling Charges - Outbound (Exp) - SLSIPL | J118: Supplier | K118: Ascendas Panvel FTWZ Private Limited | L118: PU/25/SLS/OT/1830 | M118: 246779413692
A119: 45747 | B119: Sundry Creditors - SLSIPL | C119: 0 | D119: 6896 | E119: -2545829.1 | F119: Purchase Invoice | G119: Purchase Invoice | H119: PU/25/SLS/OT/1831 | I119: Handling Charges - Outbound (Exp) - SLSIPL | J119: Supplier | K119: Ascendas Panvel FTWZ Private Limited | L119: PU/25/SLS/OT/1831 | M119: 246779413693
A120: 45747 | B120: Sundry Creditors - SLSIPL | C120: 0 | D120: 3448 | E120: -2549277.1 | F120: Purchase Invoice | G120: Purchase Invoice | H120: PU/25/SLS/OT/1832 | I120: Handling Charges - Outbound (Exp) - SLSIPL | J120: Supplier | K120: Ascendas Panvel FTWZ Private Limited | L120: PU/25/SLS/OT/1832 | M120: 246779413694
A121: 45747 | B121: Sundry Creditors - SLSIPL | C121: 0 | D121: 191 | E121: -2549468.1 | F121: Purchase Invoice | G121: Purchase Invoice | H121: PU/25/SLS/OT/1833 | I121: Handling Charges - Outbound (Exp) - SLSIPL | J121: Supplier | K121: Ascendas Panvel FTWZ Private Limited | L121: PU/25/SLS/OT/1833 | M121: 246779413695
A122: 45747 | B122: Sundry Creditors - SLSIPL | C122: 0 | D122: 382 | E122: -2549850.1 | F122: Purchase Invoice | G122: Purchase Invoice | H122: PU/25/SLS/OT/1834 | I122: Handling Charges - Outbound (Exp) - SLSIPL | J122: Supplier | K122: Ascendas Panvel FTWZ Private Limited | L122: PU/25/SLS/OT/1834 | M122: 246779413696
... A138: 45748 | B138: Sundry Creditors - SLSIPL | C138: 0 | D138: 59624 | E138: -3015382.1 | F138: Purchase Invoice | G138: Purchase Invoice | H138: PU/26/SLS/OT/0591-1 | I138: Storage Charges - Cargo - SLSIPL | J138: Supplier | K138: Ascendas Panvel FTWZ Private Limited | L138: PU/26/SLS/OT/0591-1 | M138: 246779410360
A139: 45937 | B139: Sundry Creditors - SLSIPL | C139: 4786 | D139: 4786 | E139: -757662.6 | F139: Journal Entry | G139: Debit Note | H139: SJ/25/GEA/1103 | J139: Supplier | K139: Ascendas Panvel FTWZ Private Limited | L139: PU/26/SLS/OT/0591-1, SLS26/MF/DN/0007-2 | M139: 246779410360
A140: 45747 | B140: Sundry Creditors - SLSIPL | C140: 0 | D140: 143412 | E140: -2750354.1 | F140: Purchase Invoice | G140: Purchase Invoice | H140: PU/25/SLS/OT/1857 | I140: VOS Activity Charges Paid - SLSIPL | J140: Supplier | K140: Ascendas Panvel FTWZ Private Limited | L140: PU/25/SLS/OT/1857 | M140: 246779411619
A141: 45747 | B141: Sundry Creditors - SLSIPL | C141: 0 | D141: 5816 | E141: -2756170.1 | F141: Purchase Invoice | G141: Purchase Invoice | H141: PU/25/SLS/OT/1858 | I141: VOS Activity Charges Paid - SLSIPL | J141: Supplier | K141: Ascendas Panvel FTWZ Private Limited | L141: PU/25/SLS/OT/1858 | M141: 246779411620
A142: 45747 | B142: Sundry Creditors - SLSIPL | C142: 0 | D142: 5816 | E142: -2761986.1 | F142: Purchase Invoice | G142: Purchase Invoice | H142: PU/25/SLS/OT/1859 | I142: VOS Activity Charges Paid - SLSIPL | J142: Supplier | K142: Ascendas Panvel FTWZ Private Limited | L142: PU/25/SLS/OT/1859 | M142: 246779411755
A143: 45747 | B143: Sundry Creditors - SLSIPL | C143: 0 | D143: 4339 | E143: -2766325.1 | F143: Purchase Invoice | G143: Purchase Invoice | H143: PU/25/SLS/OT/1860 | I143: VOS Activity Charges Paid - SLSIPL | J143: Supplier | K143: Ascendas Panvel FTWZ Private Limited | L143: PU/25/SLS/OT/1860 | M143: 246779411756
A144: 45747 | B144: Sundry Creditors - SLSIPL | C144: 0 | D144: 6761 | E144: -2773086.1 | F144: Purchase Invoice | G144: Purchase Invoice | H144: PU/25/SLS/OT/1861 | I144: VOS Activity Charges Paid - SLSIPL | J144: Supplier | K144: Ascendas Panvel FTWZ Private Limited | L144: PU/25/SLS/OT/1861 | M144: 246779411759
A145: 45747 | B145: Sundry Creditors - SLSIPL | C145: 0 | D145: 3110 | E145: -2776196.1 | F145: Purchase Invoice | G145: Purchase Invoice | H145: PU/25/SLS/OT/1862 | I145: VOS Activity Charges Paid - SLSIPL | J145: Supplier | K145: Ascendas Panvel FTWZ Private Limited | L145: PU/25/SLS/OT/1862 | M145: 246779411757
A146: 45869 | B146: Sundry Creditors - SLSIPL | C146: 0 | D146: 44602 | E146: -288272.6 | F146: Purchase Invoice | G146: Purchase Invoice | H146: PU/26/SLS/OT/1009-1 | I146: Container Scanning Paid - SLSIPL | J146: Supplier | K146: Ascendas Panvel FTWZ Private Limited | L146: PU/26/SLS/OT/1009-1 | M146: 246779411278
A147: 45748 | B147: Sundry Creditors - SLSIPL | C147: 0 | D147: 1161 | E147: -2810733.1 | F147: Purchase Invoice | G147: Purchase Invoice | H147: PU/26/SLS/OT/0048 | I147: VOS Activity Charges Paid - SLSIPL | J147: Supplier | K147: Ascendas Panvel FTWZ Private Limited | L147: PU/26/SLS/OT/0048 | M147: 246779411448
A148: 45748 | B148: Sundry Creditors - SLSIPL | C148: 0 | D148: 1591 | E148: -2812324.1 | F148: Purchase Invoice | G148: Purchase Invoice | H148: PU/26/SLS/OT/0193 | I148: Handling Charges - Outbound (Exp) - SLSIPL | J148: Supplier | K148: Ascendas Panvel FTWZ Private Limited | L148: PU/26/SLS/OT/0193 | M148: 246779413689
A149: 45748 | B149: Sundry Creditors - SLSIPL | C149: 0 | D149: 574 | E149: -2812898.1 | F149: Purchase Invoice | G149: Purchase Invoice | H149: PU/26/SLS/OT/0194 | I149: Handling Charges - Outbound (Exp) - SLSIPL | J149: Supplier | K149: Ascendas Panvel FTWZ Private Limited | L149: PU/26/SLS/OT/0194 | M149: 246779413740
A150: 45748 | B150: Sundry Creditors - SLSIPL | C150: 0 | D150: 574 | E150: -2813472.1 | F150: Purchase Invoice | G150: Purchase Invoice | H150: PU/26/SLS/OT/0195 | I150: Handling Charges - Outbound (Exp) - SLSIPL | J150: Supplier | K150: Ascendas Panvel FTWZ Private Limited | L150: PU/26/SLS/OT/0195 | M150: 246779413737
A151: 45748 | B151: Sundry Creditors - SLSIPL | C151: 0 | D151: 6896 | E151: -2820368.1 | F151: Purchase Invoice | G151: Purchase Invoice | H151: PU/26/SLS/OT/0196 | I151: Handling Charges - Outbound (Exp) - SLSIPL | J151: Supplier | K151: Ascendas Panvel FTWZ Private Limited | L151: PU/26/SLS/OT/0196 | M151: 246779413735
... A162: 45748 | B162: Sundry Creditors - SLSIPL | C162: 0 | D162: 200 | E162: -2849474.1 | F162: Purchase Invoice | G162: Purchase Invoice | H162: PU/26/SLS/OT/0359 | I162: Handling Charges - Outbound (Exp) - SLSIPL | J162: Supplier | K162: Ascendas Panvel FTWZ Private Limited | L162: PU/26/SLS/OT/0359 | M162: 246779410848
A163: 45937 | B163: Sundry Creditors - SLSIPL | C163: 36410 | D163: 36410 | E163: -757662.6 | F163: Journal Entry | G163: Debit Note | H163: SJ/25/GEA/1105 | J163: Supplier | K163: Ascendas Panvel FTWZ Private Limited | L163: PU/26/SLS/OT/1009-1, SLS26/MF/DN/0022-1 | M163: 246779411278
A164: 45747 | B164: Sundry Creditors - SLSIPL | C164: 0 | D164: 33376 | E164: -2809572.1 | F164: Purchase Invoice | G164: Purchase Invoice | H164: PU/25/SLS/OT/1925 | I164: Container Scanning Paid - SLSIPL | J164: Supplier | K164: Ascendas Panvel FTWZ Private Limited | L164: PU/25/SLS/OT/1925 | M164: 246779411300
A165: 45748 | B165: Sundry Creditors - SLSIPL | C165: 0 | D165: 3594 | E165: -2917685.1 | F165: Purchase Invoice | G165: Purchase Invoice | H165: PU/26/SLS/OT/0790 | I165: Handling Charges - Outbound (Exp) - SLSIPL | J165: Supplier | K165: Ascendas Panvel FTWZ Private Limited | L165: PU/26/SLS/OT/0790 | M165: 246779410755
A166: 45748 | B166: Sundry Creditors - SLSIPL | C166: 0 | D166: 35477 | E166: -2953162.1 | F166: Purchase Invoice | G166: Purchase Invoice | H166: PU/26/SLS/OT/0780-2 | I166: Fixed Storage Charges - ODC (Covered) - SLSIPL | J166: Supplier | K166: Ascendas Panvel FTWZ Private Limited | L166: PU/26/SLS/OT/0780-2 | M166: 246779410072
A167: 45748 | B167: Sundry Creditors - SLSIPL | C167: 0 | D167: 799 | E167: -2953961.1 | F167: Purchase Invoice | G167: Purchase Invoice | H167: PU/26/SLS/OT/0785-1 | I167: Handling Charges - Outbound (Exp) - SLSIPL | J167: Supplier | K167: Ascendas Panvel FTWZ Private Limited | L167: PU/26/SLS/OT/0785-1 | M167: 246779410688
A168: 45748 | B168: Sundry Creditors - SLSIPL | C168: 0 | D168: 1797 | E168: -2955758.1 | F168: Purchase Invoice | G168: Purchase Invoice | H168: PU/26/SLS/OT/0784-1 | I168: Handling Charges - Outbound (Exp) - SLSIPL | J168: Supplier | K168: Ascendas Panvel FTWZ Private Limited | L168: PU/26/SLS/OT/0784-1 | M168: 246779410687
A169: 45869 | B169: Sundry Creditors - SLSIPL | C169: 33376 | D169: 0 | E169: -259448.6 | F169: Purchase Invoice | G169: Credit Note | H169: SLS26/MF/DN/0019 | I169: Container Scanning Paid - SLSIPL | J169: Supplier | K169: Ascendas Panvel FTWZ Private Limited | L169: PU/25/SLS/OT/1925 | M169: 246779411300
A170: 45750 | B170: Sundry Creditors - SLSIPL | C170: 0 | D170: 2883 | E170: -3018265.1 | F170: Purchase Invoice | G170: Purchase Invoice | H170: PU/26/SLS/OT/0046 | I170: MHE Charges Paid - SLSIPL | J170: Supplier | K170: Ascendas Panvel FTWZ Private Limited | L170: PU/26/SLS/OT/0046 | M170: 256779410157
A171: 45750 | B171: Sundry Creditors - SLSIPL | C171: 0 | D171: 4913 | E171: -3023178.1 | F171: Purchase Invoice | G171: Purchase Invoice | H171: PU/26/SLS/OT/0047 | I171: Handling Charges - Inbound (Exp) - SLSIPL | J171: Supplier | K171: Ascendas Panvel FTWZ Private Limited | L171: PU/26/SLS/OT/0047 | M171: 256779410156
A172: 45750 | B172: Sundry Creditors - SLSIPL | C172: 0 | D172: 13011 | E172: -3036189.1 | F172: Purchase Invoice | G172: Purchase Invoice | H172: PU/26/SLS/OT/0323 | I172: Handling Charges - Outbound (Exp) - SLSIPL | J172: Supplier | K172: Ascendas Panvel FTWZ Private Limited | L172: PU/26/SLS/OT/0323 | M172: 256779410166
A173: 45750 | B173: Sundry Creditors - SLSIPL | C173: 0 | D173: 6205 | E173: -3042394.1 | F173: Purchase Invoice | G173: Purchase Invoice | H173: PU/26/SLS/OT/0326 | I173: Handling Charges - Outbound (Exp) - SLSIPL | J173: Supplier | K173: Ascendas Panvel FTWZ Private Limited | L173: PU/26/SLS/OT/0326 | M173: 256779410174
A174: 45750 | B174: Sundry Creditors - SLSIPL | C174: 0 | D174: 2937 | E174: -3045331.1 | F174: Purchase Invoice | G174: Purchase Invoice | H174: PU/26/SLS/OT/0332 | I174: VOS Activity Charges Paid - SLSIPL | J174: Supplier | K174: Ascendas Panvel FTWZ Private Limited | L174: PU/26/SLS/OT/0332 | M174: 256779410201
A175: 45750 | B175: Sundry Creditors - SLSIPL | C175: 0 | D175: 319 | E175: -3045650.1 | F175: Purchase Invoice | G175: Purchase Invoice | H175: PU/26/SLS/OT/0338 | I175: Gate In Charges Paid - SLSIPL | J175: Supplier | K175: Ascendas Panvel FTWZ Private Limited | L175: PU/26/SLS/OT/0338 | M175: 256779410135
... A177: 45747 | B177: Sundry Creditors - SLSIPL | C177: 0 | D177: 8522 | E177: -2606942.1 | F177: Purchase Invoice | G177: Purchase Invoice | H177: PU/25/SLS/OT/1856 | I177: Container Scanning Paid - SLSIPL | J177: Supplier | K177: Ascendas Panvel FTWZ Private Limited | L177: PU/25/SLS/OT/1856 | M177: 246779411314
A178: 46022 | B178: Sundry Creditors - SLSIPL | C178: 8522 | D178: 8522 | E178: -2052708.6 | F178: Journal Entry | G178: Debit Note | H178: SJ/25/GEA/1378 | J178: Supplier | K178: Ascendas Panvel FTWZ Private Limited | L178: PU/25/SLS/OT/1856, SLS26/MF/DN/0010-1 | M178: 246779411314
A179: 45747 | B179: Sundry Creditors - SLSIPL | C179: 0 | D179: 20874 | E179: -2440597.1 | F179: Purchase Invoice | G179: Purchase Invoice | H179: PU/25/SLS/OT/1820 | I179: Container Scanning Paid - SLSIPL | J179: Supplier | K179: Ascendas Panvel FTWZ Private Limited | L179: PU/25/SLS/OT/1820 | M179: 246779411326
A180: 45751 | B180: Sundry Creditors - SLSIPL | C180: 0 | D180: 331566 | E180: -3687999.1 | F180: Purchase Invoice | G180: Purchase Invoice | H180: PU/26/SLS/OT/0044 | I180: Storage Charges - Cargo - SLSIPL | J180: Supplier | K180: Ascendas Panvel FTWZ Private Limited | L180: PU/26/SLS/OT/0044 | M180: 256779410812
A181: 45751 | B181: Sundry Creditors - SLSIPL | C181: 0 | D181: 384955 | E181: -4072954.1 | F181: Purchase Invoice | G181: Purchase Invoice | H181: PU/26/SLS/OT/0045 | I181: Storage Charges - Cargo - SLSIPL | J181: Supplier | K181: Ascendas Panvel FTWZ Private Limited | L181: PU/26/SLS/OT/0045 | M181: 256779410795
A182: 45762 | B182: Sundry Creditors - SLSIPL | C182: 0 | D182: 13328 | E182: -4086282.1 | F182: Purchase Invoice | G182: Purchase Invoice | H182: PU/26/SLS/OT/0205 | I182: Handling Charges - Outbound (Exp) - SLSIPL | J182: Supplier | K182: Ascendas Panvel FTWZ Private Limited | L182: PU/26/SLS/OT/0205 | M182: 256779411150
A183: 45762 | B183: Sundry Creditors - SLSIPL | C183: 0 | D183: 25546 | E183: -4111828.1 | F183: Purchase Invoice | G183: Purchase Invoice | H183: PU/26/SLS/OT/0209 | I183: Handling Charges - Inbound (Exp) - SLSIPL,Transportation Charges Paid - SLSIPL | J183: Supplier | K183: Ascendas Panvel FTWZ Private Limited | L183: PU/26/SLS/OT/0209 | M183: 256779411148
A184: 45762 | B184: Sundry Creditors - SLSIPL | C184: 0 | D184: 2664 | E184: -4114492.1 | F184: Purchase Invoice | G184: Purchase Invoice | H184: PU/26/SLS/OT/0210 | I184: Handling Charges - Inbound (Exp) - SLSIPL | J184: Supplier | K184: Ascendas Panvel FTWZ Private Limited | L184: PU/26/SLS/OT/0210 | M184: 256779411149
A185: 45762 | B185: Sundry Creditors - SLSIPL | C185: 0 | D185: 790 | E185: -4115282.1 | F185: Purchase Invoice | G185: Purchase Invoice | H185: PU/26/SLS/OT/0211 | I185: Handling Charges - Inbound (Exp) - SLSIPL | J185: Supplier | K185: Ascendas Panvel FTWZ Private Limited | L185: PU/26/SLS/OT/0211 | M185: 256779411564
A186: 45762 | B186: Sundry Creditors - SLSIPL | C186: 0 | D186: 198 | E186: -4115480.1 | F186: Purchase Invoice | G186: Purchase Invoice | H186: PU/26/SLS/OT/0212 | I186: Handling Charges - Outbound (Exp) - SLSIPL | J186: Supplier | K186: Ascendas Panvel FTWZ Private Limited | L186: PU/26/SLS/OT/0212 | M186: 256779411563
A187: 45762 | B187: Sundry Creditors - SLSIPL | C187: 0 | D187: 13629 | E187: -4129109.1 | F187: Purchase Invoice | G187: Purchase Invoice | H187: PU/26/SLS/OT/0339 | I187: Gate In Charges Paid - SLSIPL,Handling Charges - Inbound (Exp) - SLSIPL | J187: Supplier | K187: Ascendas Panvel FTWZ Private Limited | L187: PU/26/SLS/OT/0339 | M187: 256779411151
A188: 45763 | B188: Sundry Creditors - SLSIPL | C188: 0 | D188: 417286 | E188: -4546395.1 | F188: Purchase Invoice | G188: Purchase Invoice | H188: PU/26/SLS/OT/0043 | I188: Storage Charges - Cargo - SLSIPL | J188: Supplier | K188: Ascendas Panvel FTWZ Private Limited | L188: PU/26/SLS/OT/0043 | M188: 256779412117
A189: 45763 | B189: Sundry Creditors - SLSIPL | C189: 0 | D189: 1972 | E189: -4548367.1 | F189: Purchase Invoice | G189: Purchase Invoice | H189: PU/26/SLS/OT/0190 | I189: Handling Charges - Inbound (Exp) - SLSIPL | J189: Supplier | K189: Ascendas Panvel FTWZ Private Limited | L189: PU/26/SLS/OT/0190 | M189: 25677941807
A190: 45763 | B190: Sundry Creditors - SLSIPL | C190: 0 | D190: 1584 | E190: -4549951.1 | F190: Purchase Invoice | G190: Purchase Invoice | H190: PU/26/SLS/OT/0192 | I190: VOS Activity Charges Paid - SLSIPL | J190: Supplier | K190: Ascendas Panvel FTWZ Private Limited | L190: PU/26/SLS/OT/0192 | M190: 256779412065
... A221: 45805 | B221: Sundry Creditors - SLSIPL | C221: 0 | D221: 333696 | E221: -5193789.1 | F221: Purchase Invoice | G221: Purchase Invoice | H221: PU/26/SLS/OT/0278 | I221: Storage Charges - Cargo - SLSIPL | J221: Supplier | K221: Ascendas Panvel FTWZ Private Limited | L221: PU/26/SLS/OT/0278 | M221: 256779413899
A222: 45807 | B222: Sundry Creditors - SLSIPL | C222: 177773 | D222: 0 | E222: -5016016.1 | F222: Payment Entry | G222: Pay | H222: BP/26/SLS/0192 | I222: 1395250393003 - Punjab National Bank - INR - SLSIPL | J222: Supplier | K222: Ascendas Panvel FTWZ Private Limited
A223: 45812 | B223: Sundry Creditors - SLSIPL | C223: 0 | D223: 9844 | E223: -5025860.1 | F223: Purchase Invoice | G223: Purchase Invoice | H223: PU/26/SLS/OT/0358 | I223: Handling Charges - Outbound (Exp) - SLSIPL | J223: Supplier | K223: Ascendas Panvel FTWZ Private Limited | L223: PU/26/SLS/OT/0358 | M223: 256779414165
A224: 45812 | B224: Sundry Creditors - SLSIPL | C224: 0 | D224: 8407 | E224: -5034267.1 | F224: Purchase Invoice | G224: Purchase Invoice | H224: PU/26/SLS/OT/0360 | I224: Handling Charges - Outbound (Exp) - SLSIPL | J224: Supplier | K224: Ascendas Panvel FTWZ Private Limited | L224: PU/26/SLS/OT/0360 | M224: 256779414216
A225: 45869 | B225: Sundry Creditors - SLSIPL | C225: 0 | D225: 18367 | E225: -254828.6 | F225: Purchase Invoice | G225: Purchase Invoice | H225: PU/26/SLS/OT/1008-1 | I225: Fixed Storage Charges - ODC (Covered) - SLSIPL | J225: Supplier | K225: Ascendas Panvel FTWZ Private Limited | L225: PU/26/SLS/OT/1008-1 | M225: 246779413701
A226: 45937 | B226: Sundry Creditors - SLSIPL | C226: 15401 | D226: 15401 | E226: -757662.6 | F226: Journal Entry | G226: Debit Note | H226: SJ/25/GEA/1106 | J226: Supplier | K226: Ascendas Panvel FTWZ Private Limited | L226: PU/26/SLS/OT/1008-1, SLS26/MF/DN/0021-1 | M226: 246779413701
A227: 45854 | B227: Sundry Creditors - SLSIPL | C227: 0 | D227: 31577 | E227: -1349660.6 | F227: Purchase Invoice | G227: Purchase Invoice | H227: PU/26/SLS/OT/0589-2 | I227: Storage Charges - Cargo - SLSIPL | J227: Supplier | K227: Ascendas Panvel FTWZ Private Limited | L227: PU/26/SLS/OT/0589-2 | M227: 246779413702
A228: 45815 | B228: Sundry Creditors - SLSIPL | C228: 0 | D228: 352792 | E228: -4945194.6 | F228: Purchase Invoice | G228: Purchase Invoice | H228: PU/26/SLS/OT/0285 | I228: Storage Charges - Cargo - SLSIPL | J228: Supplier | K228: Ascendas Panvel FTWZ Private Limited | L228: PU/26/SLS/OT/0285 | M228: 256779414242
A229: 45818 | B229: Sundry Creditors - SLSIPL | C229: 0 | D229: 35431 | E229: -4980625.6 | F229: Purchase Invoice | G229: Purchase Invoice | H229: PU/26/SLS/OT/0357-1 | I229: Fixed Storage Charges - ODC (Covered) - SLSIPL | J229: Supplier | K229: Ascendas Panvel FTWZ Private Limited | L229: PU/26/SLS/OT/0357-1 | M229: 256779414386
A230: 45821 | B230: Sundry Creditors - SLSIPL | C230: 700000 | D230: 0 | E230: -4280625.6 | F230: Payment Entry | G230: Pay | H230: BP/26/SLS/0229 | I230: 1395250393003 - Punjab National Bank - INR - SLSIPL | J230: Supplier | K230: Ascendas Panvel FTWZ Private Limited
A231: 45829 | B231: Sundry Creditors - SLSIPL | C231: 700000 | D231: 0 | E231: -3580625.6 | F231: Payment Entry | G231: Pay | H231: BP/26/SLS/0259 | I231: 1395250393003 - Punjab National Bank - INR - SLSIPL | J231: Supplier | K231: Ascendas Panvel FTWZ Private Limited
A232: 45838 | B232: Sundry Creditors - SLSIPL | C232: 700000 | D232: 0 | E232: -2880625.6 | F232: Payment Entry | G232: Pay | H232: BP/26/SLS/0291 | I232: 1395250393003 - Punjab National Bank - INR - SLSIPL | J232: Supplier | K232: Ascendas Panvel FTWZ Private Limited
A233: 45843 | B233: Sundry Creditors - SLSIPL | C233: 700000 | D233: 0 | E233: -2180625.6 | F233: Payment Entry | G233: Pay | H233: BP/26/SLS/0300 | I233: 1395250393003 - Punjab National Bank - INR - SLSIPL | J233: Supplier | K233: Ascendas Panvel FTWZ Private Limited
A234: 45849 | B234: Sundry Creditors - SLSIPL | C234: 700000 | D234: 0 | E234: -1480625.6 | F234: Payment Entry | G234: Pay | H234: BP/26/SLS/0311 | I234: 1395250393003 - Punjab National Bank - INR - SLSIPL | J234: Supplier | K234: Ascendas Panvel FTWZ Private Limited
A235: 45937 | B235: Sundry Creditors - SLSIPL | C235: 31577 | D235: 31577 | E235: -757662.6 | F235: Journal Entry | G235: Debit Note | H235: SJ/25/GEA/1111 | J235: Supplier | K235: Ascendas Panvel FTWZ Private Limited | L235: PU/26/SLS/OT/0589-2, SLS26/MF/DN/0005-1 | M235: 246779413702
A236: 45748 | B236: Sundry Creditors - SLSIPL | C236: 0 | D236: 19429 | E236: -2914091.1 | F236: Purchase Invoice | G236: Purchase Invoice | H236: PU/26/SLS/OT/0590 | I236: Storage Charges - Cargo - SLSIPL | J236: Supplier | K236: Ascendas Panvel FTWZ Private Limited | L236: PU/26/SLS/OT/0590 | M236: 246779413705
A237: 45854 | B237: Sundry Creditors - SLSIPL | C237: 19430 | D237: 0 | E237: -1612920.6 | F237: Purchase Invoice | G237: Credit Note | H237: SLS26/MF/DN/0006 | I237: Storage Charges - Cargo - SLSIPL | J237: Supplier | K237: Ascendas Panvel FTWZ Private Limited | L237: PU/26/SLS/OT/0590 | M237: 246779413705
A238: 45854 | B238: Sundry Creditors - SLSIPL | C238: 0 | D238: 163631 | E238: -1463026.6 | F238: Purchase Invoice | G238: Purchase Invoice | H238: PU/26/SLS/OT/0614-1 | I238: Storage Charges - Cargo - SLSIPL | J238: Supplier | K238: Ascendas Panvel FTWZ Private Limited | L238: PU/26/SLS/OT/0614-1 | M238: 246779413796
A239: 45937 | B239: Sundry Creditors - SLSIPL | C239: 12467 | D239: 12467 | E239: -757662.6 | F239: Journal Entry | G239: Debit Note | H239: SJ/25/GEA/1107 | J239: Supplier | K239: Ascendas Panvel FTWZ Private Limited | L239: PU/26/SLS/OT/0614-1, SLS26/MF/DN/0018-1 | M239: 246779413796
A240: 45747 | B240: Sundry Creditors - SLSIPL | C240: 0 | D240: 18610 | E240: -2459207.1 | F240: Purchase Invoice | G240: Purchase Invoice | H240: PU/25/SLS/OT/1821 | I240: Container Scanning Paid - SLSIPL | J240: Supplier | K240: Ascendas Panvel FTWZ Private Limited | L240: PU/25/SLS/OT/1821 | M240: 246779413816
A241: 45854 | B241: Sundry Creditors - SLSIPL | C241: 18611 | D241: 0 | E241: -1594309.6 | F241: Purchase Invoice | G241: Credit Note | H241: SLS26/MF/DN/0008 | I241: Container Scanning Paid - SLSIPL | J241: Supplier | K241: Ascendas Panvel FTWZ Private Limited | L241: PU/25/SLS/OT/1821 | M241: 246779413816
A242: 45747 | B242: Sundry Creditors - SLSIPL | C242: 0 | D242: 31723 | E242: -2490930.1 | F242: Purchase Invoice | G242: Purchase Invoice | H242: PU/25/SLS/OT/1822 | I242: Container Scanning Paid - SLSIPL | J242: Supplier | K242: Ascendas Panvel FTWZ Private Limited | L242: PU/25/SLS/OT/1822 | M242: 246779413827
A243: 45854 | B243: Sundry Creditors - SLSIPL | C243: 31723 | D243: 0 | E243: -1562586.6 | F243: Purchase Invoice | G243: Credit Note | H243: SLS26/MF/DN/0009 | I243: Container Scanning Paid - SLSIPL | J243: Supplier | K243: Ascendas Panvel FTWZ Private Limited | L243: PU/25/SLS/OT/1822 | M243: 246779413827
A244: 45854 | B244: Sundry Creditors - SLSIPL | C244: 4786 | D244: 0 | E244: -1311350.6 | F244: Purchase Invoice | G244: Credit Note | H244: SLS26/MF/DN/0007-2 | I244: Storage Charges - Cargo - SLSIPL | J244: Supplier | K244: Ascendas Panvel FTWZ Private Limited | L244: SLS26/MF/DN/0007-2 | M244: 256779421381
A245: 45748 | B245: Sundry Creditors - SLSIPL | C245: 0 | D245: 45188 | E245: -2894662.1 | F245: Purchase Invoice | G245: Purchase Invoice | H245: PU/26/SLS/OT/0588 | I245: Transportation Charges Paid - SLSIPL | J245: Supplier | K245: Ascendas Panvel FTWZ Private Limited | L245: PU/26/SLS/OT/0588 | M245: 246779413845
A246: 45854 | B246: Sundry Creditors - SLSIPL | C246: 11955 | D246: 0 | E246: -1299395.6 | F246: Purchase Invoice | G246: Credit Note | H246: SLS26/MF/DN/0004-1 | I246: Transportation Charges Paid - SLSIPL | J246: Supplier | K246: Ascendas Panvel FTWZ Private Limited | L246: PU/26/SLS/OT/0588 | M246: 246779413845
A247: 45854 | B247: Sundry Creditors - SLSIPL | C247: 12467 | D247: 0 | E247: -1450559.6 | F247: Purchase Invoice | G247: Credit Note | H247: SLS26/MF/DN/0018-1 | I247: Storage Charges - Cargo - SLSIPL | J247: Supplier | K247: Ascendas Panvel FTWZ Private Limited | L247: SLS26/MF/DN/0018-1 | M247: 256779421383
A248: 45854 | B248: Sundry Creditors - SLSIPL | C248: 6084 | D248: 0 | E248: -1444475.6 | F248: Purchase Invoice | G248: Credit Note | H248: SLS26/MF/DN/0002-1 | I248: Scanning Charges - Inbound - SLSIPL | J248: Supplier | K248: Ascendas Panvel FTWZ Private Limited | L248: SLS26/MF/DN/0002-1 | M248: 256779421376
A249: 45854 | B249: Sundry Creditors - SLSIPL | C249: 12169 | D249: 0 | E249: -1432306.6 | F249: Purchase Invoice | G249: Credit Note | H249: SLS26/MF/DN/0003-1 | I249: Scanning Charges - Inbound - SLSIPL | J249: Supplier | K249: Ascendas Panvel FTWZ Private Limited | L249: SLS26/MF/DN/0003-1 | M249: 256779421370
A250: 45854 | B250: Sundry Creditors - SLSIPL | C250: 114223 | D250: 0 | E250: -1318083.6 | F250: Purchase Invoice | G250: Credit Note | H250: SLS26/MF/DN/0015-1 | I250: Storage Charges - Cargo - SLSIPL | J250: Supplier | K250: Ascendas Panvel FTWZ Private Limited | L250: SLS26/MF/DN/0015-1 | M250: 256779421367
A251: 45750 | B251: Sundry Creditors - SLSIPL | C251: 0 | D251: 55272 | E251: -3242210.1 | F251: Purchase Invoice | G251: Purchase Invoice | H251: PU/26/SLS/OT/0613 | I251: Storage Charges - Cargo - SLSIPL | J251: Supplier | K251: Ascendas Panvel FTWZ Private Limited | L251: PU/26/SLS/OT/0613 | M251: 256779410004
...

Sheet Ascendus Data
A1: Cleared Item | B1: Company Code | C1: Customer | D1: Customer Account: Name 1 | E1: Fiscal Year | F1: Posting period | G1: Posting Date | H1: Document Number | I1: Document Type | J1: Document Date | K1: Entry Date | L1: Document Header Text | M1: Reference | N1: G/L Account | O1: G/L Account: Short Text | P1: Special G/L Ind. | Q1: Posting Key | R1: Document Currency Key | S1: Document Currency Value | T1: Company Code Currency Key | U1: Company Code Currency Value | V1: Tax Code | W1: Profit Center | X1: Trading Partner No. | Y1: Assignment | Z1: Item | AA1: Text | AB1: Reference Key 1 | AC1: Reference Key 2 | AD1: Reference Key 3 | AE1: Baseline Payment Dte | AF1: Clearing Date | AG1: Clearing Document | AJ1: Debit | AK1: Credit | AL1: Net Amount | AM1: TDS | AN1: Rate
A2: Selected | B2: 6779 | C2: 100222332 | D2: SCOPE LOGISTICS SERVICES INDIA PVT. | E2: 2025 | F2: 7 | G2: 45854 | H2: 1600001726 | I2: DG | J2: 45854 | K2: 45854 | L2: NA | M2: 256779421358 | N2: 212100 | O2: Trade Debtors (Ctrl) | Q2: 11 | R2: USD | S2: -1793.99 | T2: INR | U2: -154827.9 | V2: O0 | W2: 6779224500 | Y2: NA | Z2: 1 | AA2: Credit Note raised against INV_246779410348 | AE2: 45854 | AF2: 45854 | AG2: 1400000285 | AJ2: {=_xlfn.XLOOKUP(M2,'Customer Data Vlookup'!$L:$L,'Customer Data Vlookup'!$M:$N,,0)} -> #N/A
A3: Selected | B3: 6779 | C3: 100222332 | D3: SCOPE LOGISTICS SERVICES INDIA PVT. | E3: 2025 | F3: 7 | G3: 45854 | H3: 1800010646 | I3: DR | J3: 45854 | K3: 45855 | L3: NA | M3: 256779415406 | N3: 212100 | O3: Trade Debtors (Ctrl) | Q3: 01 | R3: USD | S3: 1793.99 | T3: INR | U3: 154827.9 | V3: O0 | W3: 6779224500 | Y3: NA | Z3: 1 | AA3: Debit note Note raised against CN_256779421358 | AE3: 45854 | AF3: 45854 | AG3: 1400000285 | AJ3: {=_xlfn.XLOOKUP(M3,'Customer Data Vlookup'!$L:$L,'Customer Data Vlookup'!$M:$N,,0)} -> #N/A
A4: Selected | B4: 6779 | C4: 100222332 | D4: SCOPE LOGISTICS SERVICES INDIA PVT. | E4: 2025 | F4: 7 | G4: 45854 | H4: 1600001727 | I4: DG | J4: 45854 | K4: 45854 | L4: NA | M4: 256779421359 | N4: 212100 | O4: Trade Debtors (Ctrl) | Q4: 11 | R4: USD | S4: -705 | T4: INR | U4: -60844.08 | V4: O0 | W4: 6779224500 | Y4: NA | Z4: 1 | AA4: Credit Note raised against INV_246779410360 | AE4: 45854 | AF4: 45854 | AG4: 1400000286 | AJ4: {=_xlfn.XLOOKUP(M4,'Customer Data Vlookup'!$L:$L,'Customer Data Vlookup'!$M:$N,,0)} -> #N/A
A5: Selected | B5: 6779 | C5: 100222332 | D5: SCOPE LOGISTICS SERVICES INDIA PVT. | E5: 2025 | F5: 7 | G5: 45854 | H5: 1800010647 | I5: DR | J5: 45854 | K5: 45855 | L5: NA | M5: 256779415407 | N5: 212100 | O5: Trade Debtors (Ctrl) | Q5: 01 | R5: USD | S5: 705 | T5: INR | U5: 60844.08 | V5: O0 | W5: 6779224500 | Y5: NA | Z5: 1 | AA5: Debit note Note raised against CN_256779421359 | AE5: 45854 | AF5: 45854 | AG5: 1400000286 | AJ5: {=_xlfn.XLOOKUP(M5,'Customer Data Vlookup'!$L:$L,'Customer Data Vlookup'!$M:$N,,0)} -> #N/A
A6: Selected | B6: 6779 | C6: 100222332 | D6: SCOPE LOGISTICS SERVICES INDIA PVT. | E6: 2025 | F6: 7 | G6: 45854 | H6: 1600001728 | I6: DG | J6: 45854 | K6: 45854 | L6: NA | M6: 256779421360 | N6: 212100 | O6: Trade Debtors (Ctrl) | Q6: 11 | R6: USD | S6: -216.2 | T6: INR | U6: -18742.65 | V6: O0 | W6: 6779224500 | Y6: NA | Z6: 1 | AA6: Credit Note raised against INV_246779413701 | AE6: 45854 | AF6: 45854 | AG6: 1400000287 | AJ6: {=_xlfn.XLOOKUP(M6,'Customer Data Vlookup'!$L:$L,'Customer Data Vlookup'!$M:$N,,0)} -> #N/A
A7: Selected | B7: 6779 | C7: 100222332 | D7: SCOPE LOGISTICS SERVICES INDIA PVT. | E7: 2025 | F7: 7 | G7: 45854 | H7: 1800010648 | I7: DR | J7: 45854 | K7: 45855 | L7: NA | M7: 256779415408 | N7: 212100 | O7: Trade Debtors (Ctrl) | Q7: 01 | R7: USD | S7: 216.2 | T7: INR | U7: 18742.65 | V7: O0 | W7: 6779224500 | Y7: NA | Z7: 1 | AA7: Debit note Note raised against CN_256779421360 | AE7: 45854 | AF7: 45854 | AG7: 1400000287 | AJ7: {=_xlfn.XLOOKUP(M7,'Customer Data Vlookup'!$L:$L,'Customer Data Vlookup'!$M:$N,,0)} -> #N/A
A8: Selected | B8: 6779 | C8: 100222332 | D8: SCOPE LOGISTICS SERVICES INDIA PVT. | E8: 2025 | F8: 7 | G8: 45854 | H8: 1600001731 | I8: DG | J8: 45854 | K8: 45854 | L8: NA | M8: 256779421363 | N8: 212100 | O8: Trade Debtors (Ctrl) | Q8: 11 | R8: USD | S8: -1926.06 | T8: INR | U8: -166972.57 | V8: O0 | W8: 6779224500 | Y8: NA | Z8: 1 | AA8: Credit Note raised against INV_246779413796 | AE8: 45854 | AF8: 45854 | AG8: 1400000288 | AJ8: {=_xlfn.XLOOKUP(M8,'Customer Data Vlookup'!$L:$L,'Customer Data Vlookup'!$M:$N,,0)} -> #N/A
A9: Selected | B9: 6779 | C9: 100222332 | D9: SCOPE LOGISTICS SERVICES INDIA PVT. | E9: 2025 | F9: 7 | G9: 45854 | H9: 1800010649 | I9: DR | J9: 45854 | K9: 45855 | L9: NA | M9: 256779415409 | N9: 212100 | O9: Trade Debtors (Ctrl) | Q9: 01 | R9: USD | S9: 1926.06 | T9: INR | U9: 166972.57 | V9: O0 | W9: 6779224500 | Y9: NA | Z9: 1 | AA9: Debit note Note raised against CN_256779421363 | AE9: 45854 | AF9: 45854 | AG9: 1400000288 | AJ9: {=_xlfn.XLOOKUP(M9,'Customer Data Vlookup'!$L:$L,'Customer Data Vlookup'!$M:$N,,0)} -> #N/A
A10: Selected | B10: 6779 | C10: 100222332 | D10: SCOPE LOGISTICS SERVICES INDIA PVT. | E10: 2025 | F10: 7 | G10: 45854 | H10: 1600001734 | I10: DG | J10: 45854 | K10: 45854 | L10: NA | M10: 256779421366 | N10: 212100 | O10: Trade Debtors (Ctrl) | Q10: 11 | R10: USD | S10: -531.9 | T10: INR | U10: -46111.08 | V10: O0 | W10: 6779224500 | Y10: NA | Z10: 1 | AA10: Credit Note raised against INV_246779413845 | AE10: 45854 | AF10: 45854 | AG10: 1400000289 | AJ10: {=_xlfn.XLOOKUP(M10,'Customer Data Vlookup'!$L:$L,'Customer Data Vlookup'!$M:$N,,0)} -> #N/A
A11: Selected | B11: 6779 | C11: 100222332 | D11: SCOPE LOGISTICS SERVICES INDIA PVT. | E11: 2025 | F11: 7 | G11: 45854 | H11: 1800010650 | I11: DR | J11: 45854 | K11: 45855 | L11: NA | M11: 256779415410 | N11: 212100 | O11: Trade Debtors (Ctrl) | Q11: 01 | R11: USD | S11: 531.9 | T11: INR | U11: 46111.08 | V11: O0 | W11: 6779224500 | Y11: NA | Z11: 1 | AA11: Debit note Note raised against CN_256779421366 | AE11: 45854 | AF11: 45854 | AG11: 1400000289 | AJ11: {=_xlfn.XLOOKUP(M11,'Customer Data Vlookup'!$L:$L,'Customer Data Vlookup'!$M:$N,,0)} -> #N/A
A12: Selected | B12: 6779 | C12: 100222332 | D12: SCOPE LOGISTICS SERVICES INDIA PVT. | E12: 2025 | F12: 7 | G12: 45854 | H12: 1600001739 | I12: DG | J12: 45854 | K12: 45854 | L12: NA | M12: 256779421371 | N12: 212100 | O12: Trade Debtors (Ctrl) | Q12: 11 | R12: USD | S12: -525 | T12: INR | U12: -45512.91 | V12: O0 | W12: 6779224500 | Y12: NA | Z12: 1 | AA12: Credit Note raised against INV_246779411278 | AE12: 45854 | AF12: 45854 | AG12: 1400000290 | AJ12: {=_xlfn.XLOOKUP(M12,'Customer Data Vlookup'!$L:$L,'Customer Data Vlookup'!$M:$N,,0)} -> #N/A
A13: Selected | B13: 6779 | C13: 100222332 | D13: SCOPE LOGISTICS SERVICES INDIA PVT. | E13: 2025 | F13: 7 | G13: 45854 | H13: 1800010651 | I13: DR | J13: 45854 | K13: 45855 | L13: NA | M13: 256779415411 | N13: 212100 | O13: Trade Debtors (Ctrl) | Q13: 01 | R13: USD | S13: 525 | T13: INR | U13: 45512.91 | V13: O0 | W13: 6779224500 | Y13: NA | Z13: 1 | AA13: Debit note Note raised against CN_256779421371 | AE13: 45854 | AF13: 45854 | AG13: 1400000290 | AJ13: {=_xlfn.XLOOKUP(M13,'Customer Data Vlookup'!$L:$L,'Customer Data Vlookup'!$M:$N,,0)} -> #N/A
... A35: Selected | B35: 6779 | C35: 100222332 | D35: SCOPE LOGISTICS SERVICES INDIA PVT. | E35: 2025 | F35: 7 | G35: 45854 | H35: 1600001753 | I35: DG | J35: 45854 | K35: 45855 | L35: NA | M35: 256779421385 | N35: 212100 | O35: Trade Debtors (Ctrl) | Q35: 11 | R35: USD | S35: -420 | T35: INR | U35: -36410.33 | V35: O0 | W35: 6779224500 | Y35: NA | Z35: 1 | AA35: Credit note Note raised against INV_246779411278 | AE35: 45854 | AF35: 45976 | AG35: 1400001902 | AJ35: {=_xlfn.XLOOKUP(M35,'Customer Data Vlookup'!$L:$L,'Customer Data Vlookup'!$M:$N,,0)} -> #N/A
A36: Not Selected | B36: 6779 | C36: 100222332 | D36: SCOPE LOGISTICS SERVICES INDIA PVT. | E36: 2025 | F36: 5 | G36: 45797 | H36: 1800008722 | I36: DR | J36: 45797 | K36: 45805 | L36: NA | M36: 256779413486 | N36: 212100 | O36: Trade Debtors (Ctrl) | Q36: 01 | R36: USD | S36: 12.5 | T36: INR | U36: 1074.8 | V36: O0 | W36: 6779224500 | Y36: NA | Z36: 1 | AA36: Outbound chgs - 01 - 15 MAY 25 | AE36: 45797 | AJ36: {=_xlfn.XLOOKUP(M36,'Customer Data Vlookup'!$L:$L,'Customer Data Vlookup'!$M:$N,,0)} -> 0 | AK36: 1054 | AL36: =AK36-AJ36 -> 1054 | AM36: =U36-AL36 -> 20.8
A37: Not Selected | B37: 6779 | C37: 100222332 | D37: SCOPE LOGISTICS SERVICES INDIA PVT. | E37: 2025 | F37: 5 | G37: 45797 | H37: 1800009073 | I37: DR | J37: 45797 | K37: 45805 | L37: NA | M37: 256779413837 | N37: 212100 | O37: Trade Debtors (Ctrl) | Q37: 01 | R37: USD | S37: 144.52 | T37: INR | U37: 12426.36 | V37: O0 | W37: 6779224500 | Z37: 1 | AA37: VAS -1-15 May 25, Ex.rate 85.43 | AE37: 45797 | AJ37: {=_xlfn.XLOOKUP(M37,'Customer Data Vlookup'!$L:$L,'Customer Data Vlookup'!$M:$N,,0)} -> 0 | AK37: 12177 | AL37: =AK37-AJ37 -> 12177 | AM37: =U37-AL37 -> 249.36
A38: Selected | B38: 6779 | C38: 100222332 | D38: SCOPE LOGISTICS SERVICES INDIA PVT. | E38: 2025 | F38: 5 | G38: 45797 | H38: 1800009121 | I38: DR | J38: 45797 | K38: 45805 | L38: NA | M38: 256779413885 | N38: 212100 | O38: Trade Debtors (Ctrl) | Q38: 01 | R38: USD | S38: 111.15 | T38: INR | U38: 9557.09 | V38: O0 | W38: 6779224500 | Y38: NA | Z38: 1 | AA38: Inbound chgs -01-15 MAY 25 | AE38: 45797 | AF38: 45976 | AG38: 1400001901 | AJ38: {=_xlfn.XLOOKUP(M38,'Customer Data Vlookup'!$L:$L,'Customer Data Vlookup'!$M:$N,,0)} -> #N/A
A39: Not Selected | B39: 6779 | C39: 100222332 | D39: SCOPE LOGISTICS SERVICES INDIA PVT. | E39: 2025 | F39: 4 | G39: 45750 | H39: 1800005188 | I39: DR | J39: 45750 | K39: 45752 | L39: NA | M39: 256779410134 | N39: 212100 | O39: Trade Debtors (Ctrl) | Q39: 01 | R39: USD | S39: 7.5 | T39: INR | U39: 651.91 | V39: O0 | Y39: NA | Z39: 1 | AA39: Outbound Handling charges for Mar 25 | AE39: 45750 | AJ39: {=_xlfn.XLOOKUP(M39,'Customer Data Vlookup'!$L:$L,'Customer Data Vlookup'!$M:$N,,0)} -> 0 | AK39: 639 | AL39: =AK39-AJ39 -> 639 | AM39: =U39-AL39 -> 12.91
A40: Not Selected | B40: 6779 | C40: 100222332 | D40: SCOPE LOGISTICS SERVICES INDIA PVT. | E40: 2025 | F40: 4 | G40: 45750 | H40: 1800005189 | I40: DR | J40: 45750 | K40: 45752 | L40: NA | M40: 256779410135 | N40: 212100 | O40: Trade Debtors (Ctrl) | Q40: 01 | R40: USD | S40: 3.75 | T40: INR | U40: 325.96 | V40: O0 | Y40: NA | Z40: 1 | AA40: Loose loading Handling charges for Mar 25 | AE40: 45750 | AJ40: {=_xlfn.XLOOKUP(M40,'Customer Data Vlookup'!$L:$L,'Customer Data Vlookup'!$M:$N,,0)} -> 0 | AK40: 319 | AL40: =AK40-AJ40 -> 319 | AM40: =U40-AL40 -> 6.96
A41: Not Selected | B41: 6779 | C41: 100222332 | D41: SCOPE LOGISTICS SERVICES INDIA PVT. | E41: 2025 | F41: 4 | G41: 45750 | H41: 1800005264 | I41: DR | J41: 45750 | K41: 45752 | L41: NA | M41: 256779410156 | N41: 212100 | O41: Trade Debtors (Ctrl) | Q41: 01 | R41: USD | S41: 58.75 | T41: INR | U41: 5106.66 | V41: O0 | Y41: NA | Z41: 1 | AA41: Inbound Handling charges for Mar 25 | AE41: 45750 | AJ41: {=_xlfn.XLOOKUP(M41,'Customer Data Vlookup'!$L:$L,'Customer Data Vlookup'!$M:$N,,0)} -> 0 | AK41: 4913 | AL41: =AK41-AJ41 -> 4913 | AM41: =U41-AL41 -> 193.66
A42: Not Selected | B42: 6779 | C42: 100222332 | D42: SCOPE LOGISTICS SERVICES INDIA PVT. | E42: 2025 | F42: 4 | G42: 45750 | H42: 1800005265 | I42: DR | J42: 45750 | K42: 45752 | L42: NA | M42: 256779410157 | N42: 212100 | O42: Trade Debtors (Ctrl) | Q42: 01 | R42: USD | S42: 34.48 | T42: INR | U42: 2997.06 | V42: O0 | Y42: NA | Z42: 1 | AA42: MHE Charges for Mar 25 | AE42: 45750 | AJ42: {=_xlfn.XLOOKUP(M42,'Customer Data Vlookup'!$L:$L,'Customer Data Vlookup'!$M:$N,,0)} -> 0 | AK42: 2883 | AL42: =AK42-AJ42 -> 2883 | AM42: =U42-AL42 -> 114.06
A43: Not Selected | B43: 6779 | C43: 100222332 | D43: SCOPE LOGISTICS SERVICES INDIA PVT. | E43: 2025 | F43: 4 | G43: 45750 | H43: 1800005274 | I43: DR | J43: 45750 | K43: 45752 | L43: NA | M43: 256779410166 | N43: 212100 | O43: Trade Debtors (Ctrl) | Q43: 01 | R43: USD | S43: 152.75 | T43: INR | U43: 13277.31 | V43: O0 | Y43: NA | Z43: 1 | AA43: Outbound Handling charges for Mar 25 | AE43: 45750 | AJ43: {=_xlfn.XLOOKUP(M43,'Customer Data Vlookup'!$L:$L,'Customer Data Vlookup'!$M:$N,,0)} -> 0 | AK43: 13011 | AL43: =AK43-AJ43 -> 13011 | AM43: =U43-AL43 -> 266.31
A44: Not Selected | B44: 6779 | C44: 100222332 | D44: SCOPE LOGISTICS SERVICES INDIA PVT. | E44: 2025 | F44: 4 | G44: 45750 | H44: 1800005282 | I44: DR | J44: 45750 | K44: 45752 | L44: NA | M44: 256779410174 | N44: 212100 | O44: Trade Debtors (Ctrl) | Q44: 01 | R44: USD | S44: 72.85 | T44: INR | U44: 6332.25 | V44: O0 | Y44: NA | Z44: 1 | AA44: Outbound Handling charges for Feb 2025 | AE44: 45750 | AJ44: {=_xlfn.XLOOKUP(M44,'Customer Data Vlookup'!$L:$L,'Customer Data Vlookup'!$M:$N,,0)} -> 0 | AK44: 6205 | AL44: =AK44-AJ44 -> 6205 | AM44: =U44-AL44 -> 127.25
A45: Not Selected | B45: 6779 | C45: 100222332 | D45: SCOPE LOGISTICS SERVICES INDIA PVT. | E45: 2025 | F45: 4 | G45: 45750 | H45: 1800005309 | I45: DR | J45: 45750 | K45: 45752 | L45: NA | M45: 256779410201 | N45: 212100 | O45: Trade Debtors (Ctrl) | Q45: 01 | R45: USD | S45: 34.48 | T45: INR | U45: 2997.06 | V45: O0 | Y45: NA | Z45: 1 | AA45: VAS Activity -1 -15 Mar 25, Ex Rate. 87.01 | AE45: 45750 | AJ45: {=_xlfn.XLOOKUP(M45,'Customer Data Vlookup'!$L:$L,'Customer Data Vlookup'!$M:$N,,0)} -> 0 | AK45: 2937 | AL45: =AK45-AJ45 -> 2937 | AM45: =U45-AL45 -> 60.06
A46: Selected | B46: 6779 | C46: 100222332 | D46: SCOPE LOGISTICS SERVICES INDIA PVT. | E46: 2025 | F46: 4 | G46: 45750 | H46: 1800005399 | I46: DR | J46: 45750 | K46: 45752 | L46: NA | M46: 256779410291 | N46: 212100 | O46: Trade Debtors (Ctrl) | Q46: 01 | R46: USD | S46: 456.75 | T46: INR | U46: 39701.54 | V46: O0 | Y46: NA | Z46: 1 | AA46: Fixed Rental charges for Feb 2025 | AE46: 45750 | AF46: 45842 | AG46: 1400000246 | AJ46: {=_xlfn.XLOOKUP(M46,'Customer Data Vlookup'!$L:$L,'Customer Data Vlookup'!$M:$N,,0)} -> #N/A
A47: Selected | B47: 6779 | C47: 100222332 | D47: SCOPE LOGISTICS SERVICES INDIA PVT. | E47: 2025 | F47: 4 | G47: 45750 | H47: 1800005358 | I47: DR | J47: 45750 | K47: 45752 | L47: NA | M47: 256779410250 | N47: 212100 | O47: Trade Debtors (Ctrl) | Q47: 01 | R47: USD | S47: 456.75 | T47: INR | U47: 39701.54 | V47: O0 | Y47: NA | Z47: 1 | AA47: Fixed Rental charges for Jan 2025 | AE47: 45750 | AF47: 45842 | AG47: 1400000247 | AJ47: {=_xlfn.XLOOKUP(M47,'Customer Data Vlookup'!$L:$L,'Customer Data Vlookup'!$M:$N,,0)} -> #N/A
A48: Selected | B48: 6779 | C48: 100222332 | D48: SCOPE LOGISTICS SERVICES INDIA PVT. | E48: 2025 | F48: 4 | G48: 45750 | H48: 1800005058 | I48: DR | J48: 45750 | K48: 45752 | L48: NA | M48: 256779410004 | N48: 212100 | O48: Trade Debtors (Ctrl) | Q48: 01 | R48: USD | S48: 705 | T48: INR | U48: 61279.88 | V48: O0 | Y48: NA | Z48: 1 | AA48: CY Longstanding container Ground Rent charges for | AE48: 45750 | AF48: 45976 | AG48: 1400001901 | AJ48: {=_xlfn.XLOOKUP(M48,'Customer Data Vlookup'!$L:$L,'Customer Data Vlookup'!$M:$N,,0)} -> 0 | AK48: 55272 | AL48: =AK48-AJ48 -> 55272 | AM48: =U48-AL48 -> 6007.88
A49: Selected | B49: 6779 | C49: 100222332 | D49: SCOPE LOGISTICS SERVICES INDIA PVT. | E49: 2025 | F49: 4 | G49: 45750 | H49: 1800005064 | I49: DR | J49: 45750 | K49: 45752 | L49: NA | M49: 256779410010 | N49: 212100 | O49: Trade Debtors (Ctrl) | Q49: 01 | R49: USD | S49: 1793.99 | T49: INR | U49: 155936.88 | V49: O0 | Y49: NA | Z49: 1 | AA49: CY Longstanding container Ground Rent charges for | AE49: 45750 | AF49: 45976 | AG49: 1400001901 | AJ49: {=_xlfn.XLOOKUP(M49,'Customer Data Vlookup'!$L:$L,'Customer Data Vlookup'!$M:$N,,0)} -> 0 | AK49: 140649 | AL49: =AK49-AJ49 -> 140649 | AM49: =U49-AL49 -> 15287.88
A50: Selected | B50: 6779 | C50: 100222332 | D50: SCOPE LOGISTICS SERVICES INDIA PVT. | E50: 2025 | F50: 4 | G50: 45750 | H50: 1800005328 | I50: DR | J50: 45750 | K50: 45752 | L50: NA | M50: 256779410220 | N50: 212100 | O50: Trade Debtors (Ctrl) | Q50: 01 | R50: USD | S50: 1314.12 | T50: INR | U50: 114225.7 | V50: O0 | Y50: NA | Z50: 1 | AA50: CY Longstanding container Ground Rent charges for | AE50: 45750 | AF50: 45976 | AG50: 1400001901 | AJ50: {=_xlfn.XLOOKUP(M50,'Customer Data Vlookup'!$L:$L,'Customer Data Vlookup'!$M:$N,,0)} -> 0 | AK50: 114223 | AL50: =AK50-AJ50 -> 114223 | AM50: =U50-AL50 -> 2.7
A51: Not Selected | B51: 6779 | C51: 100222332 | D51: SCOPE LOGISTICS SERVICES INDIA PVT. | E51: 2025 | F51: 10 | G51: 45950 | H51: 1800013971 | I51: DR | J51: 45950 | K51: 45951 | L51: NA | M51: 256779418614 | N51: 212100 | O51: Trade Debtors (Ctrl) | Q51: 01 | R51: USD | S51: 338.06 | T51: INR | U51: 29813.77 | V51: O0 | W51: 6779224500 | Y51: 2114876 | Z51: 1 | AA51: CY - CY Grd Rent Chgs - 01 - 15 OCT 25 | AE51: 45950 | AJ51: {=_xlfn.XLOOKUP(M51,'Customer Data Vlookup'!$L:$L,'Customer Data Vlookup'!$M:$N,,0)} -> #N/A
A52: Not Selected | B52: 6779 | C52: 100222332 | D52: SCOPE LOGISTICS SERVICES INDIA PVT. | E52: 2025 | F52: 10 | G52: 45950 | H52: 1800014013 | I52: DR | J52: 45950 | K52: 45951 | L52: NA | M52: 256779418620 | N52: 212100 | O52: Trade Debtors (Ctrl) | Q52: 01 | R52: USD | S52: 830.96 | T52: INR | U52: 73283 | V52: O0 | W52: 6779224500 | Y52: 2114877 | Z52: 1 | AA52: CY Ground rent Chgs - 01 - 15 Oct 25 | AE52: 45950 | AJ52: {=_xlfn.XLOOKUP(M52,'Customer Data Vlookup'!$L:$L,'Customer Data Vlookup'!$M:$N,,0)} -> #N/A
A53: Not Selected | B53: 6779 | C53: 100222332 | D53: SCOPE LOGISTICS SERVICES INDIA PVT. | E53: 2025 | F53: 10 | G53: 45950 | H53: 1800013843 | I53: DR | J53: 45950 | K53: 45951 | L53: NA | M53: 256779418661 | N53: 212100 | O53: Trade Debtors (Ctrl) | Q53: 01 | R53: USD | S53: 226.3 | T53: INR | U53: 19957.57 | V53: O0 | W53: 6779224500 | Y53: 2114881 | Z53: 1 | AA53: Inbound chgs - 01 - 15 OCT 25 | AE53: 45950 | AJ53: {=_xlfn.XLOOKUP(M53,'Customer Data Vlookup'!$L:$L,'Customer Data Vlookup'!$M:$N,,0)} -> #N/A
A54: Not Selected | B54: 6779 | C54: 100222332 | D54: SCOPE LOGISTICS SERVICES INDIA PVT. | E54: 2025 | F54: 10 | G54: 45950 | H54: 1800013925 | I54: DR | J54: 45950 | K54: 45951 | L54: NA | M54: 256779418702 | N54: 212100 | O54: Trade Debtors (Ctrl) | Q54: 01 | R54: USD | S54: 182.87 | T54: INR | U54: 16127.45 | V54: O0 | W54: 6779224500 | Y54: 2114883 | Z54: 1 | AA54: Outbound chgs - 01 - 15 Oct 25 | AE54: 45950 | AJ54: {=_xlfn.XLOOKUP(M54,'Customer Data Vlookup'!$L:$L,'Customer Data Vlookup'!$M:$N,,0)} -> #N/A
A55: Not Selected | B55: 6779 | C55: 100222332 | D55: SCOPE LOGISTICS SERVICES INDIA PVT. | E55: 2025 | F55: 4 | G55: 45768 | H55: 1800007270 | I55: DR | J55: 45768 | K55: 45769 | L55: NA | M55: 256779412161 | N55: 212100 | O55: Trade Debtors (Ctrl) | Q55: 01 | R55: USD | S55: 456.75 | T55: INR | U55: 39193.72 | V55: O0 | W55: 6779224500 | Y55: NA | Z55: 1 | AA55: Fixed Storage Charges for April 2025 | AE55: 45768 | AJ55: {=_xlfn.XLOOKUP(M55,'Customer Data Vlookup'!$L:$L,'Customer Data Vlookup'!$M:$N,,0)} -> 0 | AK55: 34962 | AL55: =AK55-AJ55 -> 34962 | AM55: =U55-AL55 -> 4231.72
A56: Not Selected | B56: 6779 | C56: 100222332 | D56: SCOPE LOGISTICS SERVICES INDIA PVT. | E56: 2025 | F56: 7 | G56: 45862 | H56: 1600001816 | I56: DG | J56: 45862 | K56: 45862 | L56: NA | M56: 256779421436 | N56: 212100 | O56: Trade Debtors (Ctrl) | Q56: 11 | R56: USD | S56: -140 | T56: INR | U56: -12037.72 | V56: O0 | W56: 6779224500 | Y56: NA | Z56: 1 | AA56: Credit Note raised against 256779413861 | AE56: 45862 | AJ56: {=_xlfn.XLOOKUP(M56,'Customer Data Vlookup'!$L:$L,'Customer Data Vlookup'!$M:$N,,0)} -> #N/A
A57: Not Selected | B57: 6779 | C57: 100222332 | D57: SCOPE LOGISTICS SERVICES INDIA PVT. | E57: 2025 | F57: 7 | G57: 45862 | H57: 1800011187 | I57: DR | J57: 45862 | K57: 45862 | L57: NA | M57: 256779415939 | N57: 212100 | O57: Trade Debtors (Ctrl) | Q57: 01 | R57: USD | S57: 140 | T57: INR | U57: 12040.09 | V57: O0 | W57: 6779224500 | Y57: NA | Z57: 1 | AA57: Scanning Chgs - 01 - 15 May 25 | AE57: 45862 | AJ57: {=_xlfn.XLOOKUP(M57,'Customer Data Vlookup'!$L:$L,'Customer Data Vlookup'!$M:$N,,0)} -> 0 | AK57: 11782.092 | AL57: =AK57-AJ57 -> 11782.092 | AM57: =U57-AL57 -> 257.9982
A58: Not Selected | B58: 6779 | C58: 100222332 | D58: SCOPE LOGISTICS SERVICES INDIA PVT. | E58: 2025 | F58: 7 | G58: 45862 | H58: 1800011193 | I58: DR | J58: 45862 | K58: 45862 | L58: NA | M58: 256779415945 | N58: 212100 | O58: Trade Debtors (Ctrl) | Q58: 01 | R58: USD | S58: 111.15 | T58: INR | U58: 9558.97 | V58: O0 | W58: 6779224500 | Y58: NA | Z58: 1 | AA58: Inbound chgs -01-15 MAY 25 | AE58: 45862 | AJ58: {=_xlfn.XLOOKUP(M58,'Customer Data Vlookup'!$L:$L,'Customer Data Vlookup'!$M:$N,,0)} -> #N/A | AL58: =AK58-AJ58 -> #N/A | AM58: =U58-AL58 -> #N/A
A59: Selected | B59: 6779 | C59: 100222332 | D59: SCOPE LOGISTICS SERVICES INDIA PVT. | E59: 2025 | F59: 7 | G59: 45862 | H59: 1600001906 | I59: DG | J59: 45862 | K59: 45862 | L59: NA | M59: 256779421526 | N59: 212100 | O59: Trade Debtors (Ctrl) | Q59: 11 | R59: USD | S59: -456.75 | T59: INR | U59: -39280.81 | V59: O0 | W59: 6779224500 | Y59: NA | Z59: 1 | AA59: Credit note raised against 256779414459 | AE59: 45862 | AF59: 45902 | AG59: 1400001112 | AJ59: {=_xlfn.XLOOKUP(M59,'Customer Data Vlookup'!$L:$L,'Customer Data Vlookup'!$M:$N,,0)} -> #N/A
A60: Selected | B60: 6779 | C60: 100222332 | D60: SCOPE LOGISTICS SERVICES INDIA PVT. | E60: 2025 | F60: 7 | G60: 45862 | H60: 1600001923 | I60: DG | J60: 45862 | K60: 45862 | L60: NA | M60: 256779421543 | N60: 212100 | O60: Trade Debtors (Ctrl) | Q60: 11 | R60: USD | S60: -456.75 | T60: INR | U60: -39280.81 | V60: O0 | W60: 6779224500 | Y60: NA | Z60: 1 | AA60: Credit note raised against 256779414476 | AE60: 45862 | AF60: 45902 | AG60: 1400001112 | AJ60: {=_xlfn.XLOOKUP(M60,'Customer Data Vlookup'!$L:$L,'Customer Data Vlookup'!$M:$N,,0)} -> #N/A
A61: Selected | B61: 6779 | C61: 100222332 | D61: SCOPE LOGISTICS SERVICES INDIA PVT. | E61: 2025 | F61: 7 | G61: 45862 | H61: 1600001822 | I61: DG | J61: 45862 | K61: 45862 | L61: NA | M61: 256779421442 | N61: 212100 | O61: Trade Debtors (Ctrl) | Q61: 11 | R61: USD | S61: -111.15 | T61: INR | U61: -9557.09 | V61: O0 | W61: 6779224500 | Y61: NA | Z61: 1 | AA61: Credit Note raised against 256779413885 | AE61: 45862 | AF61: 45976 | AG61: 1400001901 | AJ61: {=_xlfn.XLOOKUP(M61,'Customer Data Vlookup'!$L:$L,'Customer Data Vlookup'!$M:$N,,0)} -> #N/A
A62: Not Selected | B62: 6779 | C62: 100222332 | D62: SCOPE LOGISTICS SERVICES INDIA PVT. | E62: 2025 | F62: 5 | G62: 45798 | H62: 1800008640 | I62: DR | J62: 45798 | K62: 45800 | L62: NA | M62: 256779413404 | N62: 212100 | O62: Trade Debtors (Ctrl) | Q62: 01 | R62: USD | S62: 84.6 | T62: INR | U62: 7274.22 | V62: O0 | W62: 6779224500 | Y62: NA | Z62: 1 | AA62: InKPI-CODC-1-15 May 25-BOE9790661 | AE62: 45798 | AJ62: {=_xlfn.XLOOKUP(M62,'Customer Data Vlookup'!$L:$L,'Customer Data Vlookup'!$M:$N,,0)} -> 0 | AK62: 7129 | AL62: =AK62-AJ62 -> 7129 | AM62: =U62-AL62 -> 145.22
A63: Not Selected | B63: 6779 | C63: 100222332 | D63: SCOPE LOGISTICS SERVICES INDIA PVT. | E63: 2025 | F63: 5 | G63: 45798 | H63: 1800008641 | I63: DR | J63: 45798 | K63: 45800 | L63: NA | M63: 256779413405 | N63: 212100 | O63: Trade Debtors (Ctrl) | Q63: 01 | R63: USD | S63: 47 | T63: INR | U63: 4041.23 | V63: O0 | W63: 6779224500 | Y63: NA | Z63: 1 | AA63: InKPI-CODC-1-15 May 25-BOE9862672 | AE63: 45798 | AJ63: {=_xlfn.XLOOKUP(M63,'Customer Data Vlookup'!$L:$L,'Customer Data Vlookup'!$M:$N,,0)} -> 0 | AK63: 3960 | AL63: =AK63-AJ63 -> 3960 | AM63: =U63-AL63 -> 81.23
A64: Not Selected | B64: 6779 | C64: 100222332 | D64: SCOPE LOGISTICS SERVICES INDIA PVT. | E64: 2025 | F64: 5 | G64: 45798 | H64: 1800008665 | I64: DR | J64: 45798 | K64: 45800 | L64: NA | M64: 256779413429 | N64: 212100 | O64: Trade Debtors (Ctrl) | Q64: 01 | R64: USD | S64: 7.05 | T64: INR | U64: 606.19 | V64: O0 | W64: 6779224500 | Y64: NA | Z64: 1 | AA64: OutKPI-CODC-1-15-MAY-25-9960786 | AE64: 45798 | AJ64: {=_xlfn.XLOOKUP(M64,'Customer Data Vlookup'!$L:$L,'Customer Data Vlookup'!$M:$N,,0)} -> 0 | AK64: 601 | AL64: =AK64-AJ64 -> 601 | AM64: =U64-AL64 -> 5.19
A65: Not Selected | B65: 6779 | C65: 100222332 | D65: SCOPE LOGISTICS SERVICES INDIA PVT. | E65: 2025 | F65: 5 | G65: 45798 | H65: 1800008666 | I65: DR | J65: 45798 | K65: 45800 | L65: NA | M65: 256779413430 | N65: 212100 | O65: Trade Debtors (Ctrl) | Q65: 01 | R65: USD | S65: 14.1 | T65: INR | U65: 1212.37 | V65: O0 | W65: 6779224500 | Y65: NA | Z65: 1 | AA65: OutKPI-CODC-1-15-MAY-25-20045577 | AE65: 45798 | AJ65: {=_xlfn.XLOOKUP(M65,'Customer Data Vlookup'!$L:$L,'Customer Data Vlookup'!$M:$N,,0)} -> 0 | AK65: 1201 | AL65: =AK65-AJ65 -> 1201 | AM65: =U65-AL65 -> 11.37
A66: Not Selected | B66: 6779 | C66: 100222332 | D66: SCOPE LOGISTICS SERVICES INDIA PVT. | E66: 2025 | F66: 4 | G66: 45771 | H66: 1800007886 | I66: DR | J66: 45771 | K66: 45773 | L66: NA | M66: 256779412777 | N66: 212100 | O66: Trade Debtors (Ctrl) | Q66: 01 | R66: USD | S66: 95.39 | T66: INR | U66: 8291.47 | V66: O0 | W66: 6779224500 | Y66: NA | Z66: 1 | AA66: VAS 1-15 April-25,Ex.Rate-85.69 | AE66: 45771 | AJ66: {=_xlfn.XLOOKUP(M66,'Customer Data Vlookup'!$L:$L,'Customer Data Vlookup'!$M:$N,,0)} -> 0 | AK66: 7981 | AL66: =AK66-AJ66 -> 7981 | AM66: =U66-AL66 -> 310.47
A67: Not Selected | B67: 6779 | C67: 100222332 | D67: SCOPE LOGISTICS SERVICES INDIA PVT. | E67: 2025 | F67: 6 | G67: 45826 | H67: 1800009994 | I67: DR | J67: 45826 | K67: 45829 | L67: NA | M67: 256779414758 | N67: 212100 | O67: Trade Debtors (Ctrl) | Q67: 01 | R67: USD | S67: 173.9 | T67: INR | U67: 14866.85 | V67: O0 | W67: 6779224500 | Y67: NA | Z67: 1 | AA67: CODC Out chgs - 01 - 15 Jun 25 | AE67: 45826 | AJ67: {=_xlfn.XLOOKUP(M67,'Customer Data Vlookup'!$L:$L,'Customer Data Vlookup'!$M:$N,,0)} -> 0 | AK67: 14610.374 | AL67: =AK67-AJ67 -> 14610.374 | AM67: =U67-AL67 -> 256.4757
A68: Selected | B68: 6779 | C68: 100222332 | D68: SCOPE LOGISTICS SERVICES INDIA PVT. | E68: 2025 | F68: 6 | G68: 45826 | H68: 1800009695 | I68: DR | J68: 45826 | K68: 45827 | L68: NA | M68: 256779414459 | N68: 212100 | O68: Trade Debtors (Ctrl) | Q68: 01 | R68: USD | S68: 456.75 | T68: INR | U68: 39047.91 | V68: O0 | W68: 6779224500 | Y68: NA | Z68: 1 | AA68: Fixed Rental charges for Jan 2025 | AE68: 45826 | AF68: 45902 | AG68: 1400001112 | AJ68: {=_xlfn.XLOOKUP(M68,'Customer Data Vlookup'!$L:$L,'Customer Data Vlookup'!$M:$N,,0)} -> #N/A
A69: Selected | B69: 6779 | C69: 100222332 | D69: SCOPE LOGISTICS SERVICES INDIA PVT. | E69: 2025 | F69: 6 | G69: 45826 | H69: 1800009712 | I69: DR | J69: 45826 | K69: 45827 | L69: NA | M69: 256779414476 | N69: 212100 | O69: Trade Debtors (Ctrl) | Q69: 01 | R69: USD | S69: 456.75 | T69: INR | U69: 39047.91 | V69: O0 | W69: 6779224500 | Y69: NA | Z69: 1 | AA69: Fixed Rental charges for Feb 2025 | AE69: 45826 | AF69: 45902 | AG69: 1400001112 | AJ69: {=_xlfn.XLOOKUP(M69,'Customer Data Vlookup'!$L:$L,'Customer Data Vlookup'!$M:$N,,0)} -> #N/A
A70: Not Selected | B70: 6779 | C70: 100222332 | D70: SCOPE LOGISTICS SERVICES INDIA PVT. | E70: 2025 | F70: 10 | G70: 45951 | H70: 1800013945 | I70: DR | J70: 45951 | K70: 45951 | L70: NA | M70: 256779418477 | N70: 212100 | O70: Trade Debtors (Ctrl) | Q70: 01 | R70: USD | S70: 3.4 | T70: INR | U70: 299.85 | V70: O0 | W70: 6779224500 | Y70: 2114868 | Z70: 1 | AA70: VAS -1-15 Oct 2025 | AE70: 45951 | AJ70: {=_xlfn.XLOOKUP(M70,'Customer Data Vlookup'!$L:$L,'Customer Data Vlookup'!$M:$N,,0)} -> 0 | AK70: 299.8486 | AL70: =AK70-AJ70 -> 299.8486 | AM70: =U70-AL70 -> 0.0014
A71: Not Selected | B71: 6779 | C71: 100222332 | D71: SCOPE LOGISTICS SERVICES INDIA PVT. | E71: 2025 | F71: 10 | G71: 45951 | H71: 1800013962 | I71: DR | J71: 45951 | K71: 45951 | L71: NA | M71: 256779418492 | N71: 212100 | O71: Trade Debtors (Ctrl) | Q71: 01 | R71: USD | S71: 3.4 | T71: INR | U71: 299.85 | V71: O0 | W71: 6779224500 | Y71: 2114868 | Z71: 1 | AA71: VAS -1-15 Oct 2025 | AE71: 45951 | AJ71: {=_xlfn.XLOOKUP(M71,'Customer Data Vlookup'!$L:$L,'Customer Data Vlookup'!$M:$N,,0)} -> 6 | AK71: 306 | AL71: =AK71-AJ71 -> 300 | AM71: =U71-AL71 -> -0.15
A72: Not Selected | B72: 6779 | C72: 100222332 | D72: SCOPE LOGISTICS SERVICES INDIA PVT. | E72: 2025 | F72: 3 | G72: 45735 | H72: 1800003133 | I72: DR | J72: 45735 | K72: 45736 | L72: NA | M72: 246779413000 | N72: 212100 | O72: Trade Debtors (Ctrl) | Q72: 01 | R72: USD | S72: 456.75 | T72: INR | U72: 39596.23 | V72: O0 | W72: 6779224500 | Y72: NA | Z72: 1 | AA72: Fixed Storage Charges for Mar 2025 | AE72: 45735 | AJ72: {=_xlfn.XLOOKUP(M72,'Customer Data Vlookup'!$L:$L,'Customer Data Vlookup'!$M:$N,,0)} -> 0 | AK72: 35488 | AL72: =AK72-AJ72 -> 35488 | AM72: =U72-AL72 -> 4108.23
A73: Not Selected | B73: 6779 | C73: 100222332 | D73: SCOPE LOGISTICS SERVICES INDIA PVT. | E73: 2025 | F73: 3 | G73: 45735 | H73: 1800003342 | I73: DR | J73: 45735 | K73: 45736 | L73: NA | M73: 246779413209 | N73: 212100 | O73: Trade Debtors (Ctrl) | Q73: 01 | R73: USD | S73: 39.06 | T73: INR | U73: 3386.16 | V73: O0 | W73: 6779224500 | Y73: NA | Z73: 1 | AA73: HMMU6832693-Port SSR Shifting Jan 2025. Exch rate | AE73: 45735 | AJ73: {=_xlfn.XLOOKUP(M73,'Customer Data Vlookup'!$L:$L,'Customer Data Vlookup'!$M:$N,,0)} -> #N/A
A74: Not Selected | B74: 6779 | C74: 100222332 | D74: SCOPE LOGISTICS SERVICES INDIA PVT. | E74: 2025 | F74: 3 | G74: 45735 | H74: 1800003343 | I74: DR | J74: 45735 | K74: 45736 | L74: NA | M74: 246779413210 | N74: 212100 | O74: Trade Debtors (Ctrl) | Q74: 01 | R74: USD | S74: 39.06 | T74: INR | U74: 3386.16 | V74: O0 | W74: 6779224500 | Y74: NA | Z74: 1 | AA74: KOCU4372804-Port SSR Shifting Jan 2025. Exch rate | AE74: 45735 | AJ74: {=_xlfn.XLOOKUP(M74,'Customer Data Vlookup'!$L:$L,'Customer Data Vlookup'!$M:$N,,0)} -> #N/A
A75: Not Selected | B75: 6779 | C75: 100222332 | D75: SCOPE LOGISTICS SERVICES INDIA PVT. | E75: 2025 | F75: 3 | G75: 45735 | H75: 1800003344 | I75: DR | J75: 45735 | K75: 45736 | L75: NA | M75: 246779413211 | N75: 212100 | O75: Trade Debtors (Ctrl) | Q75: 01 | R75: USD | S75: 78.12 | T75: INR | U75: 6772.32 | V75: O0 | W75: 6779224500 | Y75: NA | Z75: 1 | AA75: TCNU8653352-Port SSR Shifting Jan 2025. Exch rate | AE75: 45735 | AJ75: {=_xlfn.XLOOKUP(M75,'Customer Data Vlookup'!$L:$L,'Customer Data Vlookup'!$M:$N,,0)} -> #N/A
A76: Not Selected | B76: 6779 | C76: 100222332 | D76: SCOPE LOGISTICS SERVICES INDIA PVT. | E76: 2025 | F76: 3 | G76: 45735 | H76: 1800003345 | I76: DR | J76: 45735 | K76: 45736 | L76: NA | M76: 246779413212 | N76: 212100 | O76: Trade Debtors (Ctrl) | Q76: 01 | R76: USD | S76: 39.06 | T76: INR | U76: 3386.16 | V76: O0 | W76: 6779224500 | Y76: NA | Z76: 1 | AA76: HDMU6860845-Port SSR Shifting Jan 2025. Exch rate | AE76: 45735 | AJ76: {=_xlfn.XLOOKUP(M76,'Customer Data Vlookup'!$L:$L,'Customer Data Vlookup'!$M:$N,,0)} -> #N/A
A77: Not Selected | B77: 6779 | C77: 100222332 | D77: SCOPE LOGISTICS SERVICES INDIA PVT. | E77: 2025 | F77: 3 | G77: 45735 | H77: 1800003346 | I77: DR | J77: 45735 | K77: 45736 | L77: NA | M77: 246779413213 | N77: 212100 | O77: Trade Debtors (Ctrl) | Q77: 01 | R77: USD | S77: 52.08 | T77: INR | U77: 4514.88 | V77: O0 | W77: 6779224500 | Y77: NA | Z77: 1 | AA77: EOLU8212240-Port SSR Shifting Jan 2025. Exch rate | AE77: 45735 | AJ77: {=_xlfn.XLOOKUP(M77,'Customer Data Vlookup'!$L:$L,'Customer Data Vlookup'!$M:$N,,0)} -> #N/A
A78: Not Selected | B78: 6779 | C78: 100222332 | D78: SCOPE LOGISTICS SERVICES INDIA PVT. | E78: 2025 | F78: 3 | G78: 45735 | H78: 1800003457 | I78: DR | J78: 45735 | K78: 45736 | L78: NA | M78: 246779413324 | N78: 212100 | O78: Trade Debtors (Ctrl) | Q78: 01 | R78: USD | S78: 4.3 | T78: INR | U78: 372.77 | V78: O0 | W78: 6779224500 | Y78: NA | Z78: 1 | AA78: EOLU8605417-Port SSR Storage Feb 2025. Exch rate - | AE78: 45735 | AJ78: {=_xlfn.XLOOKUP(M78,'Customer Data Vlookup'!$L:$L,'Customer Data Vlookup'!$M:$N,,0)} -> #N/A
A79: Not Selected | B79: 6779 | C79: 100222332 | D79: SCOPE LOGISTICS SERVICES INDIA PVT. | E79: 2025 | F79: 6 | G79: 45827 | H79: 1800009979 | I79: DR | J79: 45827 | K79: 45829 | L79: NA | M79: 256779414743 | N79: 212100 | O79: Trade Debtors (Ctrl) | Q79: 01 | R79: USD | S79: 71.43 | T79: INR | U79: 6106.61 | V79: O0 | W79: 6779224500 | Z79: 1 | AA79: VAS 1-15 June 25, Exch 86.10 | AE79: 45827 | AJ79: {=_xlfn.XLOOKUP(M79,'Customer Data Vlookup'!$L:$L,'Customer Data Vlookup'!$M:$N,,0)} -> 0 | AK79: 6064.023 | AL79: =AK79-AJ79 -> 6064.023 | AM79: =U79-AL79 -> 42.587
A80: Not Selected | B80: 6779 | C80: 100222332 | D80: SCOPE LOGISTICS SERVICES INDIA PVT. | E80: 2025 | F80: 6 | G80: 45827 | H80: 1800009984 | I80: DR | J80: 45827 | K80: 45829 | L80: NA | M80: 256779414748 | N80: 212100 | O80: Trade Debtors (Ctrl) | Q80: 01 | R80: USD | S80: 20.91 | T80: INR | U80: 1787.61 | V80: O0 | W80: 6779224500 | Z80: 1 | AA80: WEIGHMENT 1-15 June 25, Exch 86.10 | AE80: 45827 | AJ80: {=_xlfn.XLOOKUP(M80,'Customer Data Vlookup'!$L:$L,'Customer Data Vlookup'!$M:$N,,0)} -> 0 | AK80: 1800.351 | AL80: =AK80-AJ80 -> 1800.351 | AM80: =U80-AL80 -> -12.741
A81: Not Selected | B81: 6779 | C81: 100222332 | D81: SCOPE LOGISTICS SERVICES INDIA PVT. | E81: 2025 | F81: 11 | G81: 45981 | H81: 1800014964 | I81: DR | J81: 45981 | K81: 45982 | L81: NA | M81: 256779419465 | N81: 212100 | O81: Trade Debtors (Ctrl) | Q81: 01 | R81: USD | S81: 240.14 | T81: INR | U81: 21133.13 | V81: O0 | W81: 6779224500 | Y81: 2130555 | Z81: 1 | AA81: VAS-Nov 1-15, 2025 | AE81: 45981 | AJ81: {=_xlfn.XLOOKUP(M81,'Customer Data Vlookup'!$L:$L,'Customer Data Vlookup'!$M:$N,,0)} -> 0 | AK81: 20693.117 | AL81: =AK81-AJ81 -> 20693.117 | AM81: =U81-AL81 -> 440.0129
A82: Not Selected | B82: 6779 | C82: 100222332 | D82: SCOPE LOGISTICS SERVICES INDIA PVT. | E82: 2025 | F82: 11 | G82: 45981 | H82: 1800014975 | I82: DR | J82: 45981 | K82: 45982 | L82: NA | M82: 256779419476 | N82: 212100 | O82: Trade Debtors (Ctrl) | Q82: 01 | R82: USD | S82: 162.27 | T82: INR | U82: 14280.31 | V82: O0 | W82: 6779224500 | Y82: 2130555 | Z82: 1 | AA82: Weighment-Nov 1-15, 2025 | AE82: 45981 | AJ82: {=_xlfn.XLOOKUP(M82,'Customer Data Vlookup'!$L:$L,'Customer Data Vlookup'!$M:$N,,0)} -> 0 | AK82: 14016.3 | AL82: =AK82-AJ82 -> 14016.3 | AM82: =U82-AL82 -> 264.0101
A83: Not Selected | B83: 6779 | C83: 100222332 | D83: SCOPE LOGISTICS SERVICES INDIA PVT. | E83: 2025 | F83: 11 | G83: 45981 | H83: 1800015033 | I83: DR | J83: 45981 | K83: 45985 | L83: NA | M83: 256779419534 | N83: 212100 | O83: Trade Debtors (Ctrl) | Q83: 01 | R83: USD | S83: 90.2 | T83: INR | U83: 7937.91 | V83: O0 | W83: 6779224500 | Y83: NA | Z83: 1 | AA83: CODC LCL Chgs -1-15 Nov 25 | AE83: 45981 | AJ83: {=_xlfn.XLOOKUP(M83,'Customer Data Vlookup'!$L:$L,'Customer Data Vlookup'!$M:$N,,0)} -> 0 | AK83: 7761.899 | AL83: =AK83-AJ83 -> 7761.899 | AM83: =U83-AL83 -> 176.011
A84: Not Selected | B84: 6779 | C84: 100222332 | D84: SCOPE LOGISTICS SERVICES INDIA PVT. | E84: 2025 | F84: 11 | G84: 45981 | H84: 1800015043 | I84: DR | J84: 45981 | K84: 45985 | L84: NA | M84: 256779419556 | N84: 212100 | O84: Trade Debtors (Ctrl) | Q84: 01 | R84: USD | S84: 502.5 | T84: INR | U84: 44221.7 | V84: O0 | W84: 6779224500 | Y84: 2130610 | Z84: 1 | AA84: CY Ground rent Chgs - 01 - 15 Nov 25 | AE84: 45981 | AJ84: {=_xlfn.XLOOKUP(M84,'Customer Data Vlookup'!$L:$L,'Customer Data Vlookup'!$M:$N,,0)} -> 0 | AK84: 39821.534 | AL84: =AK84-AJ84 -> 39821.534 | AM84: =U84-AL84 -> 4400.166
A85: Not Selected | B85: 6779 | C85: 100222332 | D85: SCOPE LOGISTICS SERVICES INDIA PVT. | E85: 2025 | F85: 11 | G85: 45981 | H85: 1800015096 | I85: DR | J85: 45981 | K85: 45985 | L85: NA | M85: 256779419547 | N85: 212100 | O85: Trade Debtors (Ctrl) | Q85: 01 | R85: USD | S85: 109.01 | T85: INR | U85: 9593.25 | V85: O0 | W85: 6779224500 | Y85: 2130609 | Z85: 1 | AA85: CODC Out chgs -1-15 Nov 25 | AE85: 45981 | AJ85: {=_xlfn.XLOOKUP(M85,'Customer Data Vlookup'!$L:$L,'Customer Data Vlookup'!$M:$N,,0)} -> 0 | AK85: 9417.2428 | AL85: =AK85-AJ85 -> 9417.2428 | AM85: =U85-AL85 -> 176.0072
A86: Not Selected | B86: 6779 | C86: 100222332 | D86: SCOPE LOGISTICS SERVICES INDIA PVT. | E86: 2025 | F86: 11 | G86: 45981 | H86: 1800015075 | I86: DR | J86: 45981 | K86: 45985 | L86: NA | M86: 256779419588 | N86: 212100 | O86: Trade Debtors (Ctrl) | Q86: 01 | R86: USD | S86: 339.2 | T86: INR | U86: 29850.75 | V86: O0 | W86: 6779224500 | Y86: 2130611 | Z86: 1 | AA86: LCL Chgs - 01 - 15 NOV 25 | AE86: 45981 | AJ86: {=_xlfn.XLOOKUP(M86,'Customer Data Vlookup'!$L:$L,'Customer Data Vlookup'!$M:$N,,0)} -> 0 | AK86: 29234.726 | AL86: =AK86-AJ86 -> 29234.726 | AM86: =U86-AL86 -> 616.0238
A87: Not Selected | B87: 6779 | C87: 100222332 | D87: SCOPE LOGISTICS SERVICES INDIA PVT. | E87: 2025 | F87: 11 | G87: 45981 | H87: 1800015129 | I87: DR | J87: 45981 | K87: 45985 | L87: NA | M87: 256779419628 | N87: 212100 | O87: Trade Debtors (Ctrl) | Q87: 01 | R87: USD | S87: 10.2 | T87: INR | U87: 897.63 | V87: O0 | W87: 6779224500 | Y87: 2130612 | Z87: 1 | AA87: Loose chgs - 01 - 15 Nov 25 | AE87: 45981 | AJ87: {=_xlfn.XLOOKUP(M87,'Customer Data Vlookup'!$L:$L,'Customer Data Vlookup'!$M:$N,,0)} -> 0 | AK87: 897.6346 | AL87: =AK87-AJ87 -> 897.6346 | AM87: =U87-AL87 -> -0.0046
A88: Not Selected | B88: 6779 | C88: 100222332 | D88: SCOPE LOGISTICS SERVICES INDIA PVT. | E88: 2025 | F88: 4 | G88: 45769 | H88: 1800007570 | I88: DR | J88: 45769 | K88: 45770 | L88: NA | M88: 256779412461 | N88: 212100 | O88: Trade Debtors (Ctrl) | Q88: 01 | R88: USD | S88: 126.9 | T88: INR | U88: 11030.38 | V88: O0 | W88: 6779224500 | Y88: NA | Z88: 1 | AA88: Inbound Handling charges for Feb 2025 | AE88: 45769 | AJ88: {=_xlfn.XLOOKUP(M88,'Customer Data Vlookup'!$L:$L,'Customer Data Vlookup'!$M:$N,,0)} -> 0 | AK88: 10809 | AL88: =AK88-AJ88 -> 10809 | AM88: =U88-AL88 -> 221.38
A89: Not Selected | B89: 6779 | C89: 100222332 | D89: SCOPE LOGISTICS SERVICES INDIA PVT. | E89: 2025 | F89: 4 | G89: 45769 | H89: 1800007577 | I89: DR | J89: 45769 | K89: 45770 | L89: NA | M89: 256779412468 | N89: 212100 | O89: Trade Debtors (Ctrl) | Q89: 01 | R89: USD | S89: 169.2 | T89: INR | U89: 14707.17 | V89: O0 | W89: 6779224500 | Y89: NA | Z89: 1 | AA89: Inbound Handling charges for Feb 2025 | AE89: 45769 | AJ89: {=_xlfn.XLOOKUP(M89,'Customer Data Vlookup'!$L:$L,'Customer Data Vlookup'!$M:$N,,0)} -> 0 | AK89: 14119 | AL89: =AK89-AJ89 -> 14119 | AM89: =U89-AL89 -> 588.17
A90: Not Selected | B90: 6779 | C90: 100222332 | D90: SCOPE LOGISTICS SERVICES INDIA PVT. | E90: 2025 | F90: 4 | G90: 45769 | H90: 1800007722 | I90: DR | J90: 45769 | K90: 45770 | L90: NA | M90: 256779412613 | N90: 212100 | O90: Trade Debtors (Ctrl) | Q90: 01 | R90: USD | S90: 47 | T90: INR | U90: 4085.33 | V90: O0 | W90: 6779224500 | Y90: NA | Z90: 1 | AA90: Inbound Handling charges for 31 Mar 2025 | AE90: 45769 | AJ90: {=_xlfn.XLOOKUP(M90,'Customer Data Vlookup'!$L:$L,'Customer Data Vlookup'!$M:$N,,0)} -> 0 | AK90: 3922 | AL90: =AK90-AJ90 -> 3922 | AM90: =U90-AL90 -> 163.33
A91: Not Selected | B91: 6779 | C91: 100222332 | D91: SCOPE LOGISTICS SERVICES INDIA PVT. | E91: 2025 | F91: 4 | G91: 45769 | H91: 1800007764 | I91: DR | J91: 45769 | K91: 45770 | L91: NA | M91: 256779412655 | N91: 212100 | O91: Trade Debtors (Ctrl) | Q91: 01 | R91: USD | S91: 25 | T91: INR | U91: 2173.05 | V91: O0 | W91: 6779224500 | Y91: NA | Z91: 1 | AA91: Outbound Handling charges for 31 Mar 25 | AE91: 45769 | AJ91: {=_xlfn.XLOOKUP(M91,'Customer Data Vlookup'!$L:$L,'Customer Data Vlookup'!$M:$N,,0)} -> 0 | AK91: 2085 | AL91: =AK91-AJ91 -> 2085 | AM91: =U91-AL91 -> 88.05
A92: Not Selected | B92: 6779 | C92: 100222332 | D92: SCOPE LOGISTICS SERVICES INDIA PVT. | E92: 2025 | F92: 4 | G92: 45769 | H92: 1800007784 | I92: DR | J92: 45769 | K92: 45770 | L92: NA | M92: 256779412675 | N92: 212100 | O92: Trade Debtors (Ctrl) | Q92: 01 | R92: USD | S92: 17.35 | T92: INR | U92: 1508.09 | V92: O0 | W92: 6779224500 | Y92: NA | Z92: 1 | AA92: Inbound Handling chgs for 31 Mar 25 | AE92: 45769 | AJ92: {=_xlfn.XLOOKUP(M92,'Customer Data Vlookup'!$L:$L,'Customer Data Vlookup'!$M:$N,,0)} -> 0 | AK92: 1447 | AL92: =AK92-AJ92 -> 1447 | AM92: =U92-AL92 -> 61.09
... A100: Not Selected | B100: 6779 | C100: 100222332 | D100: SCOPE LOGISTICS SERVICES INDIA PVT. | E100: 2025 | F100: 12 | G100: 45996 | H100: 1800015287 | I100: DR | J100: 45996 | K100: 46000 | L100: NA | M100: 256779419916 | N100: 212100 | O100: Trade Debtors (Ctrl) | Q100: 01 | R100: USD | S100: 128.31 | T100: INR | U100: 11381.11 | V100: O0 | W100: 6779224500 | Y100: 2140088 | Z100: 1 | AA100: Outbound chgs - 16 - 30 Nov 25 | AE100: 45996 | AJ100: {=_xlfn.XLOOKUP(M100,'Customer Data Vlookup'!$L:$L,'Customer Data Vlookup'!$M:$N,,0)} -> 0 | AK100: 11115.014 | AL100: =AK100-AJ100 -> 11115.014 | AM100: =U100-AL100 -> 266.0955
A101: Selected | B101: 6779 | C101: 100222332 | D101: SCOPE LOGISTICS SERVICES INDIA PVT. | E101: 2025 | F101: 5 | G101: 45799 | H101: 1600001068 | I101: DG | J101: 45799 | K101: 45800 | L101: NA | M101: 256779420756 | N101: 212100 | O101: Trade Debtors (Ctrl) | Q101: 11 | R101: USD | S101: -500.63 | T101: INR | U101: -43400.25 | V101: O0 | W101: 6779224500 | Y101: NA | Z101: 1 | AA101: Credit Note against 246779413088 | AE101: 45799 | AF101: 45842 | AG101: 1400000248 | AJ101: {=_xlfn.XLOOKUP(M101,'Customer Data Vlookup'!$L:$L,'Customer Data Vlookup'!$M:$N,,0)} -> #N/A
A102: Not Selected | B102: 6779 | C102: 100222332 | D102: SCOPE LOGISTICS SERVICES INDIA PVT. | E102: 2025 | F102: 4 | G102: 45770 | H102: 1800008035 | I102: DR | J102: 45770 | K102: 45776 | L102: NA | M102: 256779412926 | N102: 212100 | O102: Trade Debtors (Ctrl) | Q102: 01 | R102: USD | S102: 22.5 | T102: INR | U102: 1955.74 | V102: O0 | W102: 6779224500 | Y102: NA | Z102: 1 | AA102: Outbound chgs - 01 - 15 Apr 25 | AE102: 45770 | AJ102: {=_xlfn.XLOOKUP(M102,'Customer Data Vlookup'!$L:$L,'Customer Data Vlookup'!$M:$N,,0)} -> 0 | AK102: 1878 | AL102: =AK102-AJ102 -> 1878 | AM102: =U102-AL102 -> 77.74
A103: Not Selected | B103: 6779 | C103: 100222332 | D103: SCOPE LOGISTICS SERVICES INDIA PVT. | E103: 2025 | F103: 4 | G103: 45770 | H103: 1800008050 | I103: DR | J103: 45770 | K103: 45776 | L103: NA | M103: 256779412941 | N103: 212100 | O103: Trade Debtors (Ctrl) | Q103: 01 | R103: USD | S103: 321.75 | T103: INR | U103: 27967.1 | V103: O0 | W103: 6779224500 | Y103: NA | Z103: 1 | AA103: LCL Chgs - 01 - 15 Apr 25 | AE103: 45770 | AJ103: {=_xlfn.XLOOKUP(M103,'Customer Data Vlookup'!$L:$L,'Customer Data Vlookup'!$M:$N,,0)} -> 0 | AK103: 27408 | AL103: =AK103-AJ103 -> 27408 | AM103: =U103-AL103 -> 559.1
A104: Not Selected | B104: 6779 | C104: 100222332 | D104: SCOPE LOGISTICS SERVICES INDIA PVT. | E104: 2025 | F104: 4 | G104: 45770 | H104: 1800008059 | I104: DR | J104: 45770 | K104: 45776 | L104: NA | M104: 256779412950 | N104: 212100 | O104: Trade Debtors (Ctrl) | Q104: 01 | R104: USD | S104: 155.1 | T104: INR | U104: 13481.57 | V104: O0 | W104: 6779224500 | Y104: NA | Z104: 1 | AA104: Outbound chgs - 01 - 15 Apr 25 | AE104: 45770 | AJ104: {=_xlfn.XLOOKUP(M104,'Customer Data Vlookup'!$L:$L,'Customer Data Vlookup'!$M:$N,,0)} -> 0 | AK104: 13211 | AL104: =AK104-AJ104 -> 13211 | AM104: =U104-AL104 -> 270.57
A105: Selected | B105: 6779 | C105: 100222332 | D105: SCOPE LOGISTICS SERVICES INDIA PVT. | E105: 2025 | F105: 4 | G105: 45770 | H105: 1800007801 | I105: DR | J105: 45770 | K105: 45773 | L105: NA | M105: 256779412692 | N105: 212100 | O105: Trade Debtors (Ctrl) | Q105: 01 | R105: USD | S105: 70 | T105: INR | U105: 6084.53 | V105: O0 | W105: 6779224500 | Y105: NA | Z105: 1 | AA105: Scanning Chgs - 01 - 15 Apr 25 | AE105: 45770 | AF105: 45976 | AG105: 1400001901 | AJ105: {=_xlfn.XLOOKUP(M105,'Customer Data Vlookup'!$L:$L,'Customer Data Vlookup'!$M:$N,,0)} -> 0 | AK105: 6084 | AL105: =AK105-AJ105 -> 6084 | AM105: =U105-AL105 -> 0.53
A106: Not Selected | B106: 6779 | C106: 100222332 | D106: SCOPE LOGISTICS SERVICES INDIA PVT. | E106: 2025 | F106: 2 | G106: 45709 | H106: 1800000353 | I106: DR | J106: 45709 | K106: 45716 | L106: NA | M106: 246779410327 | N106: 212100 | O106: Trade Debtors (Ctrl) | Q106: 01 | R106: USD | S106: 211.97 | T106: INR | U106: 18293.79 | V106: O0 | W106: 6779224500 | Y106: NA | Z106: 1 | AA106: CY-CY Ground Rent charges for Aug 2024 | AE106: 45709 | AJ106: {=_xlfn.XLOOKUP(M106,'Customer Data Vlookup'!$L:$L,'Customer Data Vlookup'!$M:$N,,0)} -> 0 | AK106: 16480.711 | AL106: =AK106-AJ106 -> 16480.711 | AM106: =U106-AL106 -> 1813.079
A107: Not Selected | B107: 6779 | C107: 100222332 | D107: SCOPE LOGISTICS SERVICES INDIA PVT. | E107: 2025 | F107: 3 | G107: 45737 | H107: 1800004449 | I107: DR | J107: 45737 | K107: 45737 | L107: NA | M107: 246779414317 | N107: 212100 | O107: Trade Debtors (Ctrl) | Q107: 01 | R107: USD | S107: 25 | T107: INR | U107: 2167.28 | V107: O0 | W107: 6779224500 | Y107: NA | Z107: 1 | AA107: Inbound Handling charges for Oct 2024 | AE107: 45737 | AJ107: {=_xlfn.XLOOKUP(M107,'Customer Data Vlookup'!$L:$L,'Customer Data Vlookup'!$M:$N,,0)} -> 0 | AK107: 1907 | AL107: =AK107-AJ107 -> 1907 | AM107: =U107-AL107 -> 260.28
A108: Not Selected | B108: 6779 | C108: 100222332 | D108: SCOPE LOGISTICS SERVICES INDIA PVT. | E108: 2025 | F108: 10 | G108: 45938 | H108: 1800013487 | I108: DR | J108: 45938 | K108: 45939 | L108: NA | M108: 256779418103 | N108: 212100 | O108: Trade Debtors (Ctrl) | Q108: 01 | R108: USD | S108: 11.26 | T108: INR | U108: 993.03 | V108: O0 | W108: 6779224500 | Y108: 2110497 | Z108: 1 | AA108: Bond Stamp Paper Chgs 01 - 30 Sep 25 | AE108: 45938 | AJ108: {=_xlfn.XLOOKUP(M108,'Customer Data Vlookup'!$L:$L,'Customer Data Vlookup'!$M:$N,,0)} -> 980 | AK108: 47157.937 | AL108: =AK108-AJ108 -> 46177.937 | AM108: =U108-AL108 -> -45184.907
A109: Not Selected | B109: 6779 | C109: 100222332 | D109: SCOPE LOGISTICS SERVICES INDIA PVT. | E109: 2025 | F109: 6 | G109: 45810 | H109: 1800009171 | I109: DR | J109: 45810 | K109: 45810 | L109: NA | M109: 256779413935 | N109: 212100 | O109: Trade Debtors (Ctrl) | Q109: 01 | R109: USD | S109: 590.74 | T109: INR | U109: 50502.82 | V109: O2 | W109: 6779224500 | Y109: NA | Z109: 1 | AA109: Port SSR Charges - Shifting for Aug to D | AE109: 45810 | AJ109: {=_xlfn.XLOOKUP(M109,'Customer Data Vlookup'!$L:$L,'Customer Data Vlookup'!$M:$N,,0)} -> #N/A
A110: Not Selected | B110: 6779 | C110: 100222332 | D110: SCOPE LOGISTICS SERVICES INDIA PVT. | E110: 2025 | F110: 10 | G110: 45937 | H110: 1800013747 | I110: DR | J110: 45937 | K110: 45939 | L110: NA | M110: 256779418168 | N110: 212100 | O110: Trade Debtors (Ctrl) | Q110: 01 | R110: USD | S110: 70 | T110: INR | U110: 6173.35 | V110: O0 | W110: 6779224500 | Y110: 2110802 | Z110: 1 | AA110: Intra - SEZ-16-30 Sept 25 | AE110: 45937 | AJ110: {=_xlfn.XLOOKUP(M110,'Customer Data Vlookup'!$L:$L,'Customer Data Vlookup'!$M:$N,,0)} -> 88 | AK110: 6173.1631 | AL110: =AK110-AJ110 -> 6085.1631 | AM110: =U110-AL110 -> 88.1869
A111: Not Selected | B111: 6779 | C111: 100222332 | D111: SCOPE LOGISTICS SERVICES INDIA PVT. | E111: 2025 | F111: 10 | G111: 45937 | H111: 1800013758 | I111: DR | J111: 45937 | K111: 45939 | L111: NA | M111: 256779418179 | N111: 212100 | O111: Trade Debtors (Ctrl) | Q111: 01 | R111: USD | S111: 528.99 | T111: INR | U111: 46652.04 | V111: O0 | W111: 6779224500 | Y111: 2110802 | Z111: 1 | AA111: VAS-16-30 Sept 25 | AE111: 45937 | AJ111: {=_xlfn.XLOOKUP(M111,'Customer Data Vlookup'!$L:$L,'Customer Data Vlookup'!$M:$N,,0)} -> #N/A
A112: Not Selected | B112: 6779 | C112: 100222332 | D112: SCOPE LOGISTICS SERVICES INDIA PVT. | E112: 2025 | F112: 7 | G112: 45857 | H112: 1800011011 | I112: DR | J112: 45857 | K112: 45859 | L112: NA | M112: 256779415771 | N112: 212100 | O112: Trade Debtors (Ctrl) | Q112: 01 | R112: USD | S112: 30.76 | T112: INR | U112: 2645.38 | V112: O0 | W112: 6779224500 | Y112: NA | Z112: 1 | AA112: VAS - 1-15 July 25 | AE112: 45857 | AJ112: {=_xlfn.XLOOKUP(M112,'Customer Data Vlookup'!$L:$L,'Customer Data Vlookup'!$M:$N,,0)} -> 0 | AK112: 2559.3799 | AL112: =AK112-AJ112 -> 2559.3799 | AM112: =U112-AL112 -> 86.0001
A113: Not Selected | B113: 6779 | C113: 100222332 | D113: SCOPE LOGISTICS SERVICES INDIA PVT. | E113: 2025 | F113: 5 | G113: 45787 | H113: 1800008243 | I113: DR | J113: 45787 | K113: 45791 | L113: NA | M113: 256779413127 | N113: 212100 | O113: Trade Debtors (Ctrl) | Q113: 01 | R113: USD | S113: 456.75 | T113: INR | U113: 39273.05 | V113: O0 | W113: 6779224500 | Y113: NA | Z113: 1 | AA113: Fixed Storage Charges fo MAY 2025 | AE113: 45787 | AJ113: {=_xlfn.XLOOKUP(M113,'Customer Data Vlookup'!$L:$L,'Customer Data Vlookup'!$M:$N,,0)} -> 0 | AK113: 35097 | AL113: =AK113-AJ113 -> 35097 | AM113: =U113-AL113 -> 4176.05
A114: Not Selected | B114: 6779 | C114: 100222332 | D114: SCOPE LOGISTICS SERVICES INDIA PVT. | E114: 2025 | F114: 5 | G114: 45787 | H114: 1800008280 | I114: DR | J114: 45787 | K114: 45792 | L114: NA | M114: 256779413163 | N114: 212100 | O114: Trade Debtors (Ctrl) | Q114: 01 | R114: USD | S114: 190.35 | T114: INR | U114: 16367 | V114: O0 | W114: 6779224500 | Y114: NA | Z114: 1 | AA114: CODC Inbound chgs - 16 - 30 Apr 25 | AE114: 45787 | AJ114: {=_xlfn.XLOOKUP(M114,'Customer Data Vlookup'!$L:$L,'Customer Data Vlookup'!$M:$N,,0)} -> 0 | AK114: 15927 | AL114: =AK114-AJ114 -> 15927 | AM114: =U114-AL114 -> 440
A115: Not Selected | B115: 6779 | C115: 100222332 | D115: SCOPE LOGISTICS SERVICES INDIA PVT. | E115: 2025 | F115: 5 | G115: 45787 | H115: 1800008289 | I115: DR | J115: 45787 | K115: 45792 | L115: NA | M115: 256779413172 | N115: 212100 | O115: Trade Debtors (Ctrl) | Q115: 01 | R115: USD | S115: 138.65 | T115: INR | U115: 11921.64 | V115: O0 | W115: 6779224500 | Y115: NA | Z115: 1 | AA115: CODC Out chgs - 16 - 30 Apr 25 | AE115: 45787 | AJ115: {=_xlfn.XLOOKUP(M115,'Customer Data Vlookup'!$L:$L,'Customer Data Vlookup'!$M:$N,,0)} -> 0 | AK115: 11810 | AL115: =AK115-AJ115 -> 11810 | AM115: =U115-AL115 -> 111.64
A116: Not Selected | B116: 6779 | C116: 100222332 | D116: SCOPE LOGISTICS SERVICES INDIA PVT. | E116: 2025 | F116: 5 | G116: 45787 | H116: 1800008301 | I116: DR | J116: 45787 | K116: 45792 | L116: NA | M116: 256779413184 | N116: 212100 | O116: Trade Debtors (Ctrl) | Q116: 01 | R116: USD | S116: 151.34 | T116: INR | U116: 13012.77 | V116: O0 | W116: 6779224500 | Y116: NA | Z116: 1 | AA116: CY Ground rent Chgs - 01 - 30 Apr 25 | AE116: 45787 | AJ116: {=_xlfn.XLOOKUP(M116,'Customer Data Vlookup'!$L:$L,'Customer Data Vlookup'!$M:$N,,0)} -> 0 | AK116: 11723.018 | AL116: =AK116-AJ116 -> 11723.018 | AM116: =U116-AL116 -> 1289.7523
A117: Not Selected | B117: 6779 | C117: 100222332 | D117: SCOPE LOGISTICS SERVICES INDIA PVT. | E117: 2025 | F117: 5 | G117: 45787 | H117: 1800008360 | I117: DR | J117: 45787 | K117: 45792 | L117: NA | M117: 256779413243 | N117: 212100 | O117: Trade Debtors (Ctrl) | Q117: 01 | R117: USD | S117: 42.53 | T117: INR | U117: 3656.89 | V117: O0 | W117: 6779224500 | Y117: NA | Z117: 1 | AA117: VAS - 16-30 April 25, Ex.Rate-85.05 | AE117: 45787 | AJ117: {=_xlfn.XLOOKUP(M117,'Customer Data Vlookup'!$L:$L,'Customer Data Vlookup'!$M:$N,,0)} -> 0 | AK117: 3623 | AL117: =AK117-AJ117 -> 3623 | AM117: =U117-AL117 -> 33.89
A118: Not Selected | B118: 6779 | C118: 100222332 | D118: SCOPE LOGISTICS SERVICES INDIA PVT. | E118: 2025 | F118: 12 | G118: 45997 | H118: 1800015437 | I118: DR | J118: 45997 | K118: 46000 | L118: NA | M118: 256779419933 | N118: 212100 | O118: Trade Debtors (Ctrl) | Q118: 01 | R118: USD | S118: 131.26 | T118: INR | U118: 11642.78 | V118: O0 | W118: 6779224500 | Y118: 2140454 | Z118: 1 | AA118: CY - CY Grd Rent Chgs - 16 - 30 Nov 25 | AE118: 45997 | AJ118: {=_xlfn.XLOOKUP(M118,'Customer Data Vlookup'!$L:$L,'Customer Data Vlookup'!$M:$N,,0)} -> 0 | AK118: 10489.679 | AL118: =AK118-AJ118 -> 10489.679 | AM118: =U118-AL118 -> 1153.1014
A119: Not Selected | B119: 6779 | C119: 100222332 | D119: SCOPE LOGISTICS SERVICES INDIA PVT. | E119: 2025 | F119: 12 | G119: 45997 | H119: 1800015473 | I119: DR | J119: 45997 | K119: 46000 | L119: NA | M119: 256779419990 | N119: 212100 | O119: Trade Debtors (Ctrl) | Q119: 01 | R119: USD | S119: 429.75 | T119: INR | U119: 38118.89 | V119: O0 | W119: 6779224500 | Y119: 2140458 | Z119: 1 | AA119: PORT SSR Chgs Nov 25 | AE119: 45997 | AJ119: {=_xlfn.XLOOKUP(M119,'Customer Data Vlookup'!$L:$L,'Customer Data Vlookup'!$M:$N,,0)} -> #N/A
A120: Not Selected | B120: 6779 | C120: 100222332 | D120: SCOPE LOGISTICS SERVICES INDIA PVT. | E120: 2025 | F120: 10 | G120: 45948 | H120: 1800014004 | I120: DR | J120: 45948 | K120: 45951 | L120: NA | M120: 256779418428 | N120: 212100 | O120: Trade Debtors (Ctrl) | Q120: 01 | R120: USD | S120: 32.9 | T120: INR | U120: 2901.48 | V120: O0 | W120: 6779224500 | Y120: 2114864 | Z120: 1 | AA120: CODC Inbound chgs - 1-15 Oct 25 | AE120: 45948 | AJ120: {=_xlfn.XLOOKUP(M120,'Customer Data Vlookup'!$L:$L,'Customer Data Vlookup'!$M:$N,,0)} -> 88 | AK120: 2901.2856 | AL120: =AK120-AJ120 -> 2813.2856 | AM120: =U120-AL120 -> 88.1944
A121: Not Selected | B121: 6779 | C121: 100222332 | D121: SCOPE LOGISTICS SERVICES INDIA PVT. | E121: 2025 | F121: 10 | G121: 45948 | H121: 1800014145 | I121: DR | J121: 45948 | K121: 45951 | L121: NA | M121: 256779418437 | N121: 212100 | O121: Trade Debtors (Ctrl) | Q121: 01 | R121: USD | S121: 79.9 | T121: INR | U121: 7046.44 | V121: O0 | W121: 6779224500 | Y121: 2114865 | Z121: 1 | AA121: CODC Out chgs -1-15 Oct 25 | AE121: 45948 | AJ121: {=_xlfn.XLOOKUP(M121,'Customer Data Vlookup'!$L:$L,'Customer Data Vlookup'!$M:$N,,0)} -> 176 | AK121: 7046.061 | AL121: =AK121-AJ121 -> 6870.061 | AM121: =U121-AL121 -> 176.379
A122: Not Selected | B122: 6779 | C122: 100222332 | D122: SCOPE LOGISTICS SERVICES INDIA PVT. | E122: 2025 | F122: 6 | G122: 45815 | H122: 1800009478 | I122: DR | J122: 45815 | K122: 45817 | L122: NA | M122: 256779414242 | N122: 212100 | O122: Trade Debtors (Ctrl) | Q122: 01 | R122: USD | S122: 4585.18 | T122: INR | U122: 391990.61 | V122: O0 | W122: 6779224500 | Y122: NA | Z122: 1 | AA122: Unit storage -1-31 May 25 | AE122: 45815 | AJ122: {=_xlfn.XLOOKUP(M122,'Customer Data Vlookup'!$L:$L,'Customer Data Vlookup'!$M:$N,,0)} -> 0 | AK122: 352792 | AL122: =AK122-AJ122 -> 352792 | AM122: =U122-AL122 -> 39198.61
A123: Not Selected | B123: 6779 | C123: 100222332 | D123: SCOPE LOGISTICS SERVICES INDIA PVT. | E123: 2025 | F123: 10 | G123: 45936 | H123: 1800013274 | I123: DR | J123: 45936 | K123: 45937 | L123: NA | M123: 256779418010 | N123: 212100 | O123: Trade Debtors (Ctrl) | Q123: 01 | R123: USD | S123: 8566.5 | T123: INR | U123: 755486.23 | V123: O0 | W123: 6779224500 | Y123: 2110511 | Z123: 1 | AA123: Unit Storage - 1-30 Sept 2025 | AE123: 45936 | AJ123: {=_xlfn.XLOOKUP(M123,'Customer Data Vlookup'!$L:$L,'Customer Data Vlookup'!$M:$N,,0)} -> 0 | AK123: 679906.74 | AL123: =AK123-AJ123 -> 679906.74 | AM123: =U123-AL123 -> 75579.489
A124: Not Selected | B124: 6779 | C124: 100222332 | D124: SCOPE LOGISTICS SERVICES INDIA PVT. | E124: 2025 | F124: 10 | G124: 45935 | H124: 1800013343 | I124: DR | J124: 45935 | K124: 45937 | L124: NA | M124: 256779417939 | N124: 212100 | O124: Trade Debtors (Ctrl) | Q124: 01 | R124: USD | S124: 445.35 | T124: INR | U124: 39275.76 | V124: O0 | W124: 6779224500 | Y124: NA | Z124: 1 | AA124: Inbound chgs - 16 - 30 SEP 25 | AE124: 45935 | AJ124: {=_xlfn.XLOOKUP(M124,'Customer Data Vlookup'!$L:$L,'Customer Data Vlookup'!$M:$N,,0)} -> 0 | AK124: 38482.043 | AL124: =AK124-AJ124 -> 38482.043 | AM124: =U124-AL124 -> 793.7175
A125: Not Selected | B125: 6779 | C125: 100222332 | D125: SCOPE LOGISTICS SERVICES INDIA PVT. | E125: 2025 | F125: 10 | G125: 45935 | H125: 1800013382 | I125: DR | J125: 45935 | K125: 45937 | L125: NA | M125: 256779417978 | N125: 212100 | O125: Trade Debtors (Ctrl) | Q125: 01 | R125: USD | S125: 582.8 | T125: INR | U125: 51397.58 | V125: O0 | W125: 6779224500 | Y125: 2110504 | Z125: 1 | AA125: Outbound chgs - 16 - 30 Sep 25 | AE125: 45935 | AJ125: {=_xlfn.XLOOKUP(M125,'Customer Data Vlookup'!$L:$L,'Customer Data Vlookup'!$M:$N,,0)} -> 1058 | AK125: 51397.291 | AL125: =AK125-AJ125 -> 50339.291 | AM125: =U125-AL125 -> 1058.2885
A126: Not Selected | B126: 6779 | C126: 100222332 | D126: SCOPE LOGISTICS SERVICES INDIA PVT. | E126: 2025 | F126: 10 | G126: 45935 | H126: 1800013460 | I126: DR | J126: 45935 | K126: 45937 | L126: NA | M126: 256779418036 | N126: 212100 | O126: Trade Debtors (Ctrl) | Q126: 01 | R126: USD | S126: 456.75 | T126: INR | U126: 40281.13 | V126: O0 | W126: 6779224500 | Y126: 2110508 | Z126: 1 | AA126: Fixed Storage Charges for October 2025 | AE126: 45935 | AJ126: {=_xlfn.XLOOKUP(M126,'Customer Data Vlookup'!$L:$L,'Customer Data Vlookup'!$M:$N,,0)} -> 0 | AK126: 36224.359 | AL126: =AK126-AJ126 -> 36224.359 | AM126: =U126-AL126 -> 4056.7712
A127: Not Selected | B127: 6779 | C127: 100222332 | D127: SCOPE LOGISTICS SERVICES INDIA PVT. | E127: 2025 | F127: 10 | G127: 45935 | H127: 1800013478 | I127: DR | J127: 45935 | K127: 45937 | L127: NA | M127: 256779418094 | N127: 212100 | O127: Trade Debtors (Ctrl) | Q127: 01 | R127: USD | S127: 771.74 | T127: INR | U127: 68060.34 | V127: O0 | W127: 6779224500 | Y127: 2110489 | Z127: 1 | AA127: CY Ground rent Chgs - 16 - 30 Sep 25 | AE127: 45935 | AJ127: {=_xlfn.XLOOKUP(M127,'Customer Data Vlookup'!$L:$L,'Customer Data Vlookup'!$M:$N,,0)} -> 6791 | AK127: 68060.655 | AL127: =AK127-AJ127 -> 61269.655 | AM127: =U127-AL127 -> 6790.6845
A128: Not Selected | B128: 6779 | C128: 100222332 | D128: SCOPE LOGISTICS SERVICES INDIA PVT. | E128: 2025 | F128: 10 | G128: 45935 | H128: 1800013509 | I128: DR | J128: 45935 | K128: 45940 | L128: NA | M128: 256779418399 | N128: 212100 | O128: Trade Debtors (Ctrl) | Q128: 01 | R128: USD | S128: 1432.98 | T128: INR | U128: 126375.61 | V128: O0 | W128: 6779224500 | Y128: 2110981 | Z128: 1 | AA128: PORT SSR Chgs Sep 25 | AE128: 45935 | AJ128: {=_xlfn.XLOOKUP(M128,'Customer Data Vlookup'!$L:$L,'Customer Data Vlookup'!$M:$N,,0)} -> #N/A
...

Sheet Knock off entries difference
H1: =SUM(H3:H31) -> -1093.08
A2: Document Number | B2: Document Type | C2: Document Date | D2: Reference | E2: Document Currency Key | F2: Document Currency Value | G2: Company Code Currency Key | H2: Company Code Currency Value
A3: 1400001112 | B3: DY | C3: 45902 | E3: INR | F3: 79944.34 | G3: INR | H3: 78561.62
A4: 1400001112 | B4: DY | C4: 45902 | E4: INR | F4: -79944.34 | G4: INR | H4: -78095.82
A5: 1400000285 | B5: DY | C5: 45854 | E5: USD | F5: 1793.99 | G5: INR | H5: 154827.9
A6: 1400000285 | B6: DY | C6: 45854 | E6: USD | F6: -1793.99 | G6: INR | H6: -154827.9
A7: 1400000286 | B7: DY | C7: 45854 | E7: USD | F7: 705 | G7: INR | H7: 60844.08
A8: 1400000286 | B8: DY | C8: 45854 | E8: USD | F8: -705 | G8: INR | H8: -60844.08
A9: 1400000287 | B9: DY | C9: 45854 | E9: USD | F9: 216.2 | G9: INR | H9: 18742.65
A10: 1400000287 | B10: DY | C10: 45854 | E10: USD | F10: -216.2 | G10: INR | H10: -18742.65
A11: 1400000288 | B11: DY | C11: 45854 | E11: USD | F11: 1926.06 | G11: INR | H11: 166972.57
A12: 1400000288 | B12: DY | C12: 45854 | E12: USD | F12: -1926.06 | G12: INR | H12: -166972.57
A13: 1400000289 | B13: DY | C13: 45854 | E13: USD | F13: 531.9 | G13: INR | H13: 46111.08
A14: 1400000289 | B14: DY | C14: 45854 | E14: USD | F14: -531.9 | G14: INR | H14: -46111.08
A15: 1400000245 | B15: DY | C15: 45842 | D15: KNOCK OFF ENTRY | E15: USD | F15: 0 | G15: INR | H15: 0
A16: 1400000248 | B16: DY | C16: 45842 | D16: KNOCK OFF ENTRY | E16: USD | F16: 0 | G16: INR | H16: 0
A17: 1400000246 | B17: DY | C17: 45842 | D17: KNOCK OFF ENTRY | E17: USD | F17: 456.75 | G17: INR | H17: 39701.54
A18: 1400000246 | B18: DY | C18: 45842 | D18: KNOCK OFF ENTRY | E18: USD | F18: -456.75 | G18: INR | H18: -39701.54
A19: 1400000247 | B19: DY | C19: 45842 | D19: KNOCK OFF ENTRY | E19: USD | F19: 456.75 | G19: INR | H19: 39701.54
A20: 1400000247 | B20: DY | C20: 45842 | D20: KNOCK OFF ENTRY | E20: USD | F20: -456.75 | G20: INR | H20: -39701.54
A21: 1400000290 | B21: DY | C21: 45854 | D21: KNOCK OFF ENTRY | E21: USD | F21: 525 | G21: INR | H21: 45512.91
A22: 1400000290 | B22: DY | C22: 45854 | D22: KNOCK OFF ENTRY | E22: USD | F22: -525 | G22: INR | H22: -45512.91
A23: 1400001901 | B23: DY | C23: 45976 | D23: KNOCK OFF ENTRY | E23: USD | F23: 3813.11 | G23: INR | H23: 331442.46
A24: 1400001901 | B24: DY | C24: 45976 | D24: KNOCK OFF ENTRY | E24: USD | F24: -3813.11 | G24: INR | H24: -331442.46
A25: 1400001902 | B25: DY | C25: 45976 | D25: KNOCK OFF ENTRY | E25: USD | F25: 1117.66 | G25: INR | H25: 96798.99
A26: 1400001902 | B26: DY | C26: 45976 | D26: KNOCK OFF ENTRY | E26: USD | F26: -182.83 | G26: INR | H26: -16089.66
... A31: 1400001902 | B31: DY | C31: 45976 | D31: KNOCK OFF ENTRY | E31: USD | F31: -137.9 | G31: INR | H31: -12135.67

Sheet Diffrence in Invoice value

Sheet TDS to be recorded 
A2: Document Number | B2: Document Type | C2: Document Date | D2: Reference | E2: Document Currency Key | F2: Document Currency Value | G2: Company Code Currency Key | H2: Company Code Currency Value | I2: Text | J2: Debit | K2: Credit | L2: Net Amount
A3: 1800008722 | B3: DR | C3: 45797 | D3: 256779413486 | E3: USD | F3: 12.5 | G3: INR | H3: 1074.8 | I3: Outbound chgs - 01 - 15 MAY 25 | J3: 0 | K3: 1054 | L3: 1054
A4: 1800009073 | B4: DR | C4: 45797 | D4: 256779413837 | E4: USD | F4: 144.52 | G4: INR | H4: 12426.36 | I4: VAS -1-15 May 25, Ex.rate 85.43 | J4: 0 | K4: 12177 | L4: 12177
A5: 1800005188 | B5: DR | C5: 45750 | D5: 256779410134 | E5: USD | F5: 7.5 | G5: INR | H5: 651.91 | I5: Outbound Handling charges for Mar 25 | J5: 0 | K5: 639 | L5: 639
A6: 1800005189 | B6: DR | C6: 45750 | D6: 256779410135 | E6: USD | F6: 3.75 | G6: INR | H6: 325.96 | I6: Loose loading Handling charges for Mar 25 | J6: 0 | K6: 319 | L6: 319
A7: 1800005264 | B7: DR | C7: 45750 | D7: 256779410156 | E7: USD | F7: 58.75 | G7: INR | H7: 5106.66 | I7: Inbound Handling charges for Mar 25 | J7: 0 | K7: 4913 | L7: 4913
A8: 1800005265 | B8: DR | C8: 45750 | D8: 256779410157 | E8: USD | F8: 34.48 | G8: INR | H8: 2997.06 | I8: MHE Charges for Mar 25 | J8: 0 | K8: 2883 | L8: 2883
A9: 1800005274 | B9: DR | C9: 45750 | D9: 256779410166 | E9: USD | F9: 152.75 | G9: INR | H9: 13277.31 | I9: Outbound Handling charges for Mar 25 | J9: 0 | K9: 13011 | L9: 13011
A10: 1800005282 | B10: DR | C10: 45750 | D10: 256779410174 | E10: USD | F10: 72.85 | G10: INR | H10: 6332.25 | I10: Outbound Handling charges for Feb 2025 | J10: 0 | K10: 6205 | L10: 6205
A11: 1800005309 | B11: DR | C11: 45750 | D11: 256779410201 | E11: USD | F11: 34.48 | G11: INR | H11: 2997.06 | I11: VAS Activity -1 -15 Mar 25, Ex Rate. 87.01 | J11: 0 | K11: 2937 | L11: 2937
A12: 1800005058 | B12: DR | C12: 45750 | D12: 256779410004 | E12: USD | F12: 705 | G12: INR | H12: 61279.88 | I12: CY Longstanding container Ground Rent charges for | J12: 0 | K12: 55272 | L12: 55272
A13: 1800005064 | B13: DR | C13: 45750 | D13: 256779410010 | E13: USD | F13: 1793.99 | G13: INR | H13: 155936.88 | I13: CY Longstanding container Ground Rent charges for | J13: 0 | K13: 140649 | L13: 140649
A14: 1800005328 | B14: DR | C14: 45750 | D14: 256779410220 | E14: USD | F14: 1314.12 | G14: INR | H14: 114225.7 | I14: CY Longstanding container Ground Rent charges for | J14: 0 | K14: 114223 | L14: 114223
... A103: 1800011903 | B103: DR | C103: 45880 | D103: 256779416546 | E103: USD | F103: 282.9 | G103: INR | H103: 24337.92 | I103: CY - CY Grd Rent Chgs - 16 - 15 JUL 25 | J103: 0 | K103: 21929.078 | L103: 21929.078
A104: 1800010208 | B104: DR | C104: 45845 | D104: 256779414968 | E104: USD | F104: 31.58 | G104: INR | H104: 2715.9 | J104: 0 | K104: 2629.9005 | L104: 2629.9005
A105: 1800006916 | B105: DR | C105: 45763 | D105: 256779411807 | E105: USD | F105: 23.5 | G105: INR | H105: 2042.66 | I105: Inbound Handling charges for Dec 2024 | J105: 0 | K105: 2053.9 | L105: 2053.9
A106: 1800006994 | B106: DR | C106: 45763 | D106: 256779411885 | E106: USD | F106: 15 | G106: INR | H106: 1303.83 | I106: Outbound Handling charges for Dec 2024 | J106: 0 | K106: 1256 | L106: 1256
A107: 1800006995 | B107: DR | C107: 45763 | D107: 256779411886 | E107: USD | F107: 5.25 | G107: INR | H107: 456.34 | I107: Loose loading Handling charges for Dec 2024 | J107: 0 | K107: 447 | L107: 447
A108: 1800007174 | B108: DR | C108: 45763 | D108: 256779412065 | E108: USD | F108: 18.88 | G108: INR | H108: 1641.08 | I108: VAS Activity - Feb 25, Ex Rate. 87.40 | J108: 0 | K108: 1584 | L108: 1584
A109: 1800007209 | B109: DR | C109: 45763 | D109: 256779412100 | E109: USD | F109: 252.98 | G109: INR | H109: 21989.48 | I109: VAS Activity - Mar 25, 16-31, Ex Rate. 85.58 | J109: 0 | K109: 21549 | L109: 21549
A110: 1800007226 | B110: DR | C110: 45763 | D110: 256779412117 | E110: USD | F110: 5415.85 | G110: INR | H110: 470755.54 | I110: Storage Charges Mar, 25 | J110: 0 | K110: 417286 | L110: 417286
A111: 1800007026 | B111: DR | C111: 45763 | D111: 256779411917 | E111: USD | F111: 140 | G111: INR | H111: 12169.05 | I111: Scanning charges for 01 to 31 Mar 25 | J111: 0 | K111: 12169 | L111: 12169
A112: 1800001783 | B112: DR | C112: 45730 | D112: 246779411448 | E112: USD | F112: 14.31 | G112: INR | H112: 1240.55 | I112: VAS Activity Charges for the month of August, 24 | J112: 0 | K112: 1161 | L112: 1161
A113: 1800012275 | B113: DR | C113: 45904 | D113: 256779416911 | E113: USD | F113: 40.85 | G113: INR | H113: 3574.96 | I113: CODC LCL Chgs - 16-31 Aug 25 | J113: 0 | K113: 3487.4461 | L113: 3487.4461
A114: 1800012286 | B114: DR | C114: 45904 | D114: 256779416948 | E114: USD | F114: 14.1 | G114: INR | H114: 1233.95 | I114: CODC Out chgs -16-31 Aug 25 | J114: 0 | K114: 1233.9521 | L114: 1233.9521
A115: 1800012460 | B115: DR | C115: 45904 | D115: 256779417160 | E115: USD | F115: 14.25 | G115: INR | H115: 1247.08 | I115: VAS -16-31 Aug 25 | J115: 0 | K115: 1247.0792 | L115: 1247.0792
A116: 1800012493 | B116: DR | C116: 45904 | D116: 256779417166 | E116: USD | F116: 760.25 | G116: INR | H116: 66532.77 | I116: CY - CY Grd Rent Chgs - 01 - 31 AUG 25 | J116: 0 | K116: 59881.68 | L116: 59881.68
... A126: 1800010184 | B126: DR | C126: 45842 | D126: 256779414944 | E126: USD | F126: 456.75 | G126: INR | H126: 39280.81 | I126: Fixed Storage Charges fo JULY 2025 | J126: 0 | K126: 35324.775 | L126: 35324.775
A127: 1800010215 | B127: DR | C127: 45842 | D127: 256779414975 | E127: USD | F127: 54.05 | G127: INR | H127: 4648.34 | J127: 0 | K127: 4562.3355 | L127: 4562.3355
A128: 1800010288 | B128: DR | C128: 45842 | D128: 256779415048 | E128: USD | F128: 6.43 | G128: INR | H128: 552.98 | I128: Bond Stamp Paper Chgs | J128: 0 | K128: 552.9843 | L128: 552.9843
A129: 1800010438 | B129: DR | C129: 45842 | D129: 256779415198 | E129: USD | F129: 3330.8 | G129: INR | H129: 286451.03 | I129: Unit Storage - 1-30 June 25 | J129: 0 | K129: 257812.81 | L129: 257812.81
A130: 1800010503 | B130: DR | C130: 45842 | D130: 256779415263 | E130: USD | F130: 2.34 | G130: INR | H130: 201.24 | I130: VAS - 16-30 June 25 | J130: 0 | K130: 201.2416 | L130: 201.2416
A131: 1800014263 | B131: DR | C131: 45966 | D131: 256779418802 | E131: USD | F131: 456.75 | G131: INR | H131: 40195.55 | I131: Fixed Storage Charges for November 2025 | J131: 4048 | K131: 40195.392 | L131: 36147.392
A132: 1800014282 | B132: DR | C132: 45966 | D132: 256779418819 | E132: USD | F132: 32.74 | G132: INR | H132: 2881.23 | I132: VAS-16 -31 Oct 25 | J132: 0 | K132: 2793.2276 | L132: 2793.2276
A133: 1800014537 | B133: DR | C133: 45966 | D133: 256779418869 | E133: USD | F133: 6685.47 | G133: INR | H133: 588344.02 | I133: Unit Storage - 1-31 Oct 2025 | J133: 0 | K133: 529469.76 | L133: 529469.76
A134: 1800014590 | B134: DR | C134: 45966 | D134: 256779418897 | E134: USD | F134: 108.45 | G134: INR | H134: 9543.97 | I134: CODC LCL Chgs -16-31 Oct 25 | J134: 0 | K134: 9367.9609 | L134: 9367.9609
A135: 1800014641 | B135: DR | C135: 45966 | D135: 256779418906 | E135: USD | F135: 35.25 | G135: INR | H135: 3102.12 | I135: CODC Out chgs -16-31 Oct 25 | J135: 0 | K135: 3014.1161 | L135: 3014.1161
A136: 1800014455 | B136: DR | C136: 45966 | D136: 256779419069 | E136: USD | F136: 337.59 | G136: INR | H136: 29709.06 | I136: CY - CY Grd Rent Chgs - 16 - 31 OCT 25 | J136: 0 | K136: 26716.949 | L136: 26716.949
A137: 1800014633 | B137: DR | C137: 45966 | D137: 256779419076 | E137: USD | F137: 799 | G137: INR | H137: 70314.71 | I137: CY Ground rent Chgs - 16 - 31 Oct 25 | J137: 0 | K137: 63274.437 | L137: 63274.437
A138: 1800014523 | B138: DR | C138: 45966 | D138: 256779419172 | E138: USD | F138: 68.15 | G138: INR | H138: 5997.43 | I138: Outbound chgs - 16 - 31 Oct 25 | J138: 0 | K138: 5909.4276 | L138: 5909.4276
A139: 1800014745 | B139: DR | C139: 45966 | D139: 256779419248 | E139: USD | F139: 11.27 | G139: INR | H139: 991.8 | I139: Bond Stamp Paper Chgs Oct 25 | J139: 0 | K139: 991.7982 | L139: 991.7982
... A333: 1800011345 | B333: DR | C333: 45870 | D333: 256779416054 | E333: USD | F333: 456.75 | G333: INR | H333: 39294.26 | I333: Fixed Storage Charges for August 2025 | J333: 0 | K333: 35336.872 | L333: 35336.872

Sheet Invoice&DN in Customer's ledger
A2: Document Number | B2: Document Type | C2: Document Date | D2: Reference | E2: Document Currency Key | F2: Document Currency Value | G2: Company Code Currency Key | H2: Company Code Currency Value | I2: Text | J2: Xlookup
A3: 1600001726 | B3: DG | C3: 45854 | D3: 256779421358 | E3: USD | F3: -1793.99 | G3: INR | H3: -154827.9 | I3: Credit Note raised against INV_246779410348 | J3: #N/A
A4: 1800010646 | B4: DR | C4: 45854 | D4: 256779415406 | E4: USD | F4: 1793.99 | G4: INR | H4: 154827.9 | I4: Debit note Note raised against CN_256779421358 | J4: #N/A
A5: 1600001727 | B5: DG | C5: 45854 | D5: 256779421359 | E5: USD | F5: -705 | G5: INR | H5: -60844.08 | I5: Credit Note raised against INV_246779410360 | J5: #N/A
A6: 1800010647 | B6: DR | C6: 45854 | D6: 256779415407 | E6: USD | F6: 705 | G6: INR | H6: 60844.08 | I6: Debit note Note raised against CN_256779421359 | J6: #N/A
A7: 1600001728 | B7: DG | C7: 45854 | D7: 256779421360 | E7: USD | F7: -216.2 | G7: INR | H7: -18742.65 | I7: Credit Note raised against INV_246779413701 | J7: #N/A
A8: 1800010648 | B8: DR | C8: 45854 | D8: 256779415408 | E8: USD | F8: 216.2 | G8: INR | H8: 18742.65 | I8: Debit note Note raised against CN_256779421360 | J8: #N/A
A9: 1600001731 | B9: DG | C9: 45854 | D9: 256779421363 | E9: USD | F9: -1926.06 | G9: INR | H9: -166972.57 | I9: Credit Note raised against INV_246779413796 | J9: #N/A
A10: 1800010649 | B10: DR | C10: 45854 | D10: 256779415409 | E10: USD | F10: 1926.06 | G10: INR | H10: 166972.57 | I10: Debit note Note raised against CN_256779421363 | J10: #N/A
A11: 1600001734 | B11: DG | C11: 45854 | D11: 256779421366 | E11: USD | F11: -531.9 | G11: INR | H11: -46111.08 | I11: Credit Note raised against INV_246779413845 | J11: #N/A
A12: 1800010650 | B12: DR | C12: 45854 | D12: 256779415410 | E12: USD | F12: 531.9 | G12: INR | H12: 46111.08 | I12: Debit note Note raised against CN_256779421366 | J12: #N/A
A13: 1600001739 | B13: DG | C13: 45854 | D13: 256779421371 | E13: USD | F13: -525 | G13: INR | H13: -45512.91 | I13: Credit Note raised against INV_246779411278 | J13: #N/A
A14: 1800010651 | B14: DR | C14: 45854 | D14: 256779415411 | E14: USD | F14: 525 | G14: INR | H14: 45512.91 | I14: Debit note Note raised against CN_256779421371 | J14: #N/A
... A97: 1800003221 | B97: DR | C97: 45735 | D97: 246779413088 | E97: USD | F97: 500.63 | G97: INR | H97: 43400.25 | I97: Port SSR Charges - Shifting for Aug to Dec,24. | J97: #N/A

Sheet working
O2: Credit Note | P2: Debit Note | R2: Pay | S2: Purchase Invoice
A3: Years | B3: Quarters | C3: Document Date | D3: DA | E3: DG | F3: DR | G3: DY | H3: DZ | I3: XC | J3: Net balance | L3: Years | M3: Quarters | N3: Posting Date | O3: Sum of Debit (INR) | P3: Sum of Debit (INR) | Q3: Sum of Credit (INR) | R3: Sum of Debit (INR) | S3: Sum of Debit (INR) | T3: Sum of Credit (INR) | U3: Net balance
A4: 2025 | B4: Qtr1 | C4: Feb | F4: 882590.45 | I4: -1 | J4: =SUM(D4:I4) -> 882589.45 | L4: 2025 | M4: Qtr1 | N4: Feb | S4: 0 | T4: 213327.12 | U4: =O4+P4-Q4+R4+S4-T4 -> -213327.12
A5: 2025 | B5: Qtr1 | C5: Mar | F5: 3312491.9 | I5: 1 | J5: =SUM(D5:I5) -> 3312492.9 | L5: 2025 | M5: Qtr1 | N5: Mar | S5: 0 | T5: 2596245 | U5: =O5+P5-Q5+R5+S5-T5 -> -2596245
A6: 2025 | B6: Qtr2 | C6: Apr | D6: 0 | F6: 2004959.4 | J6: =SUM(D6:I6) -> 2004959.4 | L6: 2025 | M6: Qtr2 | N6: Apr | S6: 0 | T6: 1942901 | U6: =O6+P6-Q6+R6+S6-T6 -> -1942901
A7: 2025 | B7: Qtr2 | C7: May | E7: -124043.88 | F7: 518581.46 | J7: =SUM(D7:I7) -> 394537.58 | L7: 2025 | M7: Qtr2 | N7: May | R7: 177773 | S7: 0 | T7: 441316 | U7: =O7+P7-Q7+R7+S7-T7 -> -263543
A8: 2025 | B8: Qtr2 | C8: Jun | F8: 750378.21 | H8: -1378720 | J8: =SUM(D8:I8) -> -628341.79 | L8: 2025 | M8: Qtr2 | N8: Jun | R8: 2600946.5 | S8: 0 | T8: 465556 | U8: =O8+P8-Q8+R8+S8-T8 -> 2135390.5
A9: 2025 | B9: Qtr3 | C9: Jul | E9: -1266506.3 | F9: 1226043.9 | G9: 0 | J9: =SUM(D9:I9) -> -40462.36 | L9: 2025 | M9: Qtr3 | N9: Jul | O9: 610440 | P9: 26009 | Q9: 503 | R9: 2450672 | S9: 0 | T9: 460821 | U9: =O9+P9-Q9+R9+S9-T9 -> 2625797
A10: 2025 | B10: Qtr3 | C10: Aug | F10: 906747.15 | H10: -3850672 | J10: =SUM(D10:I10) -> -2943924.9 | L10: 2025 | M10: Qtr3 | N10: Aug | S10: 0 | T10: 502834 | U10: =O10+P10-Q10+R10+S10-T10 -> -502834
A11: 2025 | B11: Qtr3 | C11: Sep | F11: 1230602 | G11: 465.8 | J11: =SUM(D11:I11) -> 1231067.8
A12: 2025 | B12: Qtr4 | C12: Oct | E12: -51397.58 | F12: 1336858.3 | H12: -1108564 | J12: =SUM(D12:I12) -> 176896.72 | L12: 2025 | M12: Qtr4 | N12: Oct | P12: 248895 | Q12: 248895 | R12: 1408564 | U12: =O12+P12-Q12+R12+S12-T12 -> 1408564
A13: 2025 | B13: Qtr4 | C13: Nov | F13: 925665.41 | G13: -1558.88 | H13: -800000 | J13: =SUM(D13:I13) -> 124106.53 | L13: 2025 | M13: Qtr4 | N13: Nov | R13: 500000 | U13: =O13+P13-Q13+R13+S13-T13 -> 500000
A14: 2025 | B14: Qtr4 | C14: Dec | F14: 155144.53 | H14: -500000 | J14: =SUM(D14:I14) -> -344855.47 | L14: 2025 | M14: Qtr4 | N14: Dec | P14: 25505 | Q14: 25505 | R14: 1000000 | S14: 21906 | T14: 4225516 | U14: =O14+P14-Q14+R14+S14-T14 -> -3203610
A15: 2026 | B15: Qtr1 | C15: Jan | E15: -308.53 | F15: 1689363.2 | H15: -500000 | J15: =SUM(D15:I15) -> 1189054.7 | L15: 2026 | M15: Qtr1 | N15: Jan | R15: 674751 | S15: 4355 | T15: 51496.061 | U15: =O15+P15-Q15+R15+S15-T15 -> 627609.94
A16: 2026 | B16: Qtr1 | C16: Feb | H16: -674751 | J16: =SUM(D16:I16) -> -674751 | L16: 2026 | M16: Qtr1 | N16: Feb | S16: 3628 | T16: 67803.817 | U16: =O16+P16-Q16+R16+S16-T16 -> -64175.817
D18: =SUM(D4:D16) -> 0 | E18: =SUM(E4:E16) -> -1442256.3 | F18: =SUM(F4:F16) -> 14939426 | G18: =SUM(G4:G16) -> -1093.08 | H18: =SUM(H4:H16) -> -8812707 | I18: =SUM(I4:I16) -> 0 | J18: =SUM(J4:J16) -> 4683369.6 | O18: =SUM(O4:O16) -> 610440 | P18: =SUM(P4:P16) -> 300409 | Q18: =SUM(Q4:Q16) -> 274903 | R18: =SUM(R4:R16) -> 8812706.5 | S18: =SUM(S4:S16) -> 29889 | T18: =SUM(T4:T16) -> 10967816 | U18: =SUM(U4:U16) -> -1489274.5

Sheet Sheet1
A1: Posting Date | B1: Account | C1: Debit (INR) | D1: Credit (INR) | E1: Balance (INR) | G1: Voucher No | H1: Against Account | I1: File No | J1: Against Voucher | K1: Supplier Invoice No
A2: 2025-02-20 | B2: Sundry Creditors - SLSIPL | C2: 0 | D2: 35554.52 | E2: -35554.52 | F2: Purchase Invoice | G2: PU/25/SLS/OT/1560 | H2: Fixed Storage Charges - ODC (Covered) - SLSIPL | J2: PU/25/SLS/OT/1560 | K2: 246779410049
A3: 2025-02-20 | B3: Sundry Creditors - SLSIPL | C3: 0 | D3: 35554.52 | E3: -71109.04 | F3: Purchase Invoice | G3: PU/25/SLS/OT/1561 | H3: Fixed Storage Charges - ODC (Covered) - SLSIPL | J3: PU/25/SLS/OT/1561 | K3: 246779410303
A4: 2025-02-20 | B4: Sundry Creditors - SLSIPL | C4: 0 | D4: 35554.52 | E4: -106663.56 | F4: Purchase Invoice | G4: PU/25/SLS/OT/1562 | H4: Fixed Storage Charges - ODC (Covered) - SLSIPL | J4: PU/25/SLS/OT/1562 | K4: 246779410117
A5: 2025-02-20 | B5: Sundry Creditors - SLSIPL | C5: 0 | D5: 35554.52 | E5: -142218.08 | F5: Purchase Invoice | G5: PU/25/SLS/OT/1563 | H5: Fixed Storage Charges - ODC (Covered) - SLSIPL | J5: PU/25/SLS/OT/1563 | K5: 246779410160
A6: 2025-02-20 | B6: Sundry Creditors - SLSIPL | C6: 0 | D6: 35554.52 | E6: -177772.6 | F6: Purchase Invoice | G6: PU/25/SLS/OT/1564 | H6: Fixed Storage Charges - ODC (Covered) - SLSIPL | J6: PU/25/SLS/OT/1564 | K6: 246779410203
A7: 2025-02-20 | B7: Sundry Creditors - SLSIPL | C7: 0 | D7: 35554.52 | E7: -213327.12 | F7: Purchase Invoice | G7: PU/25/SLS/OT/1565 | H7: Fixed Storage Charges - ODC (Covered) - SLSIPL | J7: PU/25/SLS/OT/1565 | K7: 246779410246
A8: 2025-03-03 | B8: Sundry Creditors - SLSIPL | C8: 0 | D8: 804 | E8: -214131.12 | F8: Purchase Invoice | G8: PU/25/SLS/OT/1672 | H8: Handling Charges - Outbound (Exp) - SLSIPL | I8: IMP/SLSIPL/0149/24-25 | J8: PU/25/SLS/OT/1672 | K8: 246779410613
A9: 2025-03-03 | B9: Sundry Creditors - SLSIPL | C9: 0 | D9: 1004 | E9: -215135.12 | F9: Purchase Invoice | G9: PU/25/SLS/OT/1673 | H9: Handling Charges - Outbound (Exp) - SLSIPL | I9: IMP/SLSIPL/0149/24-25 | J9: PU/25/SLS/OT/1673 | K9: 246779410612
A10: 2025-03-03 | B10: Sundry Creditors - SLSIPL | C10: 0 | D10: 402 | E10: -215537.12 | F10: Purchase Invoice | G10: PU/25/SLS/OT/1674 | H10: Handling Charges - Outbound (Exp) - SLSIPL | I10: 174/24-25 | J10: PU/25/SLS/OT/1674 | K10: 246779410611
A11: 2025-03-03 | B11: Sundry Creditors - SLSIPL | C11: 0 | D11: 201 | E11: -215738.12 | F11: Purchase Invoice | G11: PU/25/SLS/OT/1675 | H11: Handling Charges - Outbound (Exp) - SLSIPL | I11: 174/24-25 | J11: PU/25/SLS/OT/1675 | K11: 246779410610
A12: 2025-03-03 | B12: Sundry Creditors - SLSIPL | C12: 0 | D12: 804 | E12: -216542.12 | F12: Purchase Invoice | G12: PU/25/SLS/OT/1676 | H12: Handling Charges - Outbound (Exp) - SLSIPL | I12: IMP/SLSIPL/0162/24-25 | J12: PU/25/SLS/OT/1676 | K12: 246779410608
A13: 2025-03-03 | B13: Sundry Creditors - SLSIPL | C13: 0 | D13: 402 | E13: -216944.12 | F13: Purchase Invoice | G13: PU/25/SLS/OT/1677 | H13: Handling Charges - Outbound (Exp) - SLSIPL | I13: 148/24-25 | J13: PU/25/SLS/OT/1677 | K13: 246779410607
A14: 2025-03-03 | B14: Sundry Creditors - SLSIPL | C14: 0 | D14: 580687 | E14: -797631.12 | F14: Purchase Invoice | G14: PU/25/SLS/OT/1718 | H14: Storage Charges - Cargo - SLSIPL | J14: PU/25/SLS/OT/1718 | K14: 246779410404
A15: 2025-03-03 | B15: Sundry Creditors - SLSIPL | C15: 0 | D15: 340227 | E15: -1137858.1 | F15: Purchase Invoice | G15: PU/25/SLS/OT/1719 | H15: Storage Charges - Cargo - SLSIPL | J15: PU/25/SLS/OT/1719 | K15: 246779410428
A16: 2025-03-03 | B16: Sundry Creditors - SLSIPL | C16: 0 | D16: 460370 | E16: -1598228.1 | F16: Purchase Invoice | G16: PU/25/SLS/OT/1720 | H16: Storage Charges - Cargo - SLSIPL | J16: PU/25/SLS/OT/1720 | K16: 246779410379
A17: 2025-03-03 | B17: Sundry Creditors - SLSIPL | C17: 0 | D17: 2009 | E17: -1600237.1 | F17: Purchase Invoice | G17: PU/25/SLS/OT/1721 | H17: Handling Charges - Outbound (Exp) - SLSIPL | I17: 142/24-25 | J17: PU/25/SLS/OT/1721 | K17: 246779410605
A18: 2025-03-03 | B18: Sundry Creditors - SLSIPL | C18: 0 | D18: 402 | E18: -1600639.1 | F18: Purchase Invoice | G18: PU/25/SLS/OT/1722 | H18: Handling Charges - Outbound (Exp) - SLSIPL | I18: IMP/SLSIPL/0147/24-25 | J18: PU/25/SLS/OT/1722 | K18: 246779410606
A19: 2025-03-03 | B19: Sundry Creditors - SLSIPL | C19: 0 | D19: 2009 | E19: -1602648.1 | F19: Purchase Invoice | G19: PU/25/SLS/OT/1731 | H19: Handling Charges - Outbound (Exp) - SLSIPL | I19: IMP/SLSIPL/0101/24-25 | J19: PU/25/SLS/OT/1731 | K19: 246779410495
A20: 2025-03-03 | B20: Sundry Creditors - SLSIPL | C20: 0 | D20: 201 | E20: -1602849.1 | F20: Purchase Invoice | G20: PU/25/SLS/OT/1732 | H20: Handling Charges - Outbound (Exp) - SLSIPL | I20: 106/24-25 | J20: PU/25/SLS/OT/1732 | K20: 246779410494
A21: 2025-03-03 | B21: Sundry Creditors - SLSIPL | C21: 0 | D21: 201 | E21: -1603050.1 | F21: Purchase Invoice | G21: PU/25/SLS/OT/1733 | H21: Handling Charges - Outbound (Exp) - SLSIPL | I21: 095/24-25 | J21: PU/25/SLS/OT/1733 | K21: 246779410496
A22: 2025-03-03 | B22: Sundry Creditors - SLSIPL | C22: 0 | D22: 201 | E22: -1603251.1 | F22: Purchase Invoice | G22: PU/25/SLS/OT/1734 | H22: Handling Charges - Outbound (Exp) - SLSIPL | I22: 117/24-25 | J22: PU/25/SLS/OT/1734 | K22: 246779410497
A23: 2025-03-03 | B23: Sundry Creditors - SLSIPL | C23: 0 | D23: 804 | E23: -1604055.1 | F23: Purchase Invoice | G23: PU/25/SLS/OT/1735 | H23: Handling Charges - Outbound (Exp) - SLSIPL | I23: 107/24-25 | J23: PU/25/SLS/OT/1735 | K23: 246779410499
A24: 2025-03-03 | B24: Sundry Creditors - SLSIPL | C24: 0 | D24: 201 | E24: -1604256.1 | F24: Purchase Invoice | G24: PU/25/SLS/OT/1736 | H24: Handling Charges - Outbound (Exp) - SLSIPL | I24: 118/24-25 | J24: PU/25/SLS/OT/1736 | K24: 246779410500
A25: 2025-03-03 | B25: Sundry Creditors - SLSIPL | C25: 0 | D25: 1607 | E25: -1605863.1 | F25: Purchase Invoice | G25: PU/25/SLS/OT/1737 | H25: Handling Charges - Outbound (Exp) - SLSIPL | I25: 092/24-25 | J25: PU/25/SLS/OT/1737 | K25: 246779410501
A26: 2025-03-03 | B26: Sundry Creditors - SLSIPL | C26: 0 | D26: 2009 | E26: -1607872.1 | F26: Purchase Invoice | G26: PU/25/SLS/OT/1738 | H26: Handling Charges - Outbound (Exp) - SLSIPL | I26: 131/24-25 | J26: PU/25/SLS/OT/1738 | K26: 246779410502
A27: 2025-03-03 | B27: Sundry Creditors - SLSIPL | C27: 0 | D27: 2009 | E27: -1609881.1 | F27: Purchase Invoice | G27: PU/25/SLS/OT/1739 | H27: Handling Charges - Outbound (Exp) - SLSIPL | I27: 129/24-25 | J27: PU/25/SLS/OT/1739 | K27: 246779410503
A28: 2025-03-03 | B28: Sundry Creditors - SLSIPL | C28: 0 | D28: 201 | E28: -1610082.1 | F28: Purchase Invoice | G28: PU/25/SLS/OT/1740 | H28: Handling Charges - Outbound (Exp) - SLSIPL | I28: 135/24-25 | J28: PU/25/SLS/OT/1740 | K28: 246779410504
... A37: 2025-03-04 | B37: Sundry Creditors - SLSIPL | C37: 0 | D37: 1006 | E37: -1614709.1 | F37: Purchase Invoice | G37: PU/25/SLS/OT/1686 | H37: Handling Charges - Outbound (Exp) - SLSIPL | I37: 205 & 206/24-25 | J37: PU/25/SLS/OT/1686 | K37: 246779410760
A38: 2025-03-04 | B38: Sundry Creditors - SLSIPL | C38: 0 | D38: 1207 | E38: -1615916.1 | F38: Purchase Invoice | G38: PU/25/SLS/OT/1687 | H38: Handling Charges - Outbound (Exp) - SLSIPL | J38: PU/25/SLS/OT/1687 | K38: 246779410761
A39: 2025-03-04 | B39: Sundry Creditors - SLSIPL | C39: 0 | D39: 201 | E39: -1616117.1 | F39: Purchase Invoice | G39: PU/25/SLS/OT/1688 | H39: Handling Charges - Outbound (Exp) - SLSIPL | I39: 194/24-25 | J39: PU/25/SLS/OT/1688 | K39: 246779410763
A40: 2025-03-04 | B40: Sundry Creditors - SLSIPL | C40: 0 | D40: 403 | E40: -1616520.1 | F40: Purchase Invoice | G40: PU/25/SLS/OT/1689 | H40: Handling Charges - Outbound (Exp) - SLSIPL | I40: IMP/SLSIPL/0149/24-25 | J40: PU/25/SLS/OT/1689 | K40: 246779410762
A41: 2025-03-04 | B41: Sundry Creditors - SLSIPL | C41: 0 | D41: 403 | E41: -1616923.1 | F41: Purchase Invoice | G41: PU/25/SLS/OT/1690 | H41: Handling Charges - Outbound (Exp) - SLSIPL | I41: 210/24-25 | J41: PU/25/SLS/OT/1690 | K41: 246779410757
A42: 2025-03-04 | B42: Sundry Creditors - SLSIPL | C42: 0 | D42: 201 | E42: -1617124.1 | F42: Purchase Invoice | G42: PU/25/SLS/OT/1691 | H42: Handling Charges - Outbound (Exp) - SLSIPL | I42: 228/24-25 | J42: PU/25/SLS/OT/1691 | K42: 246779410765
A43: 2025-03-04 | B43: Sundry Creditors - SLSIPL | C43: 0 | D43: 201 | E43: -1617325.1 | F43: Purchase Invoice | G43: PU/25/SLS/OT/1692 | H43: Handling Charges - Outbound (Exp) - SLSIPL | I43: 195/24-25 | J43: PU/25/SLS/OT/1692 | K43: 246779410764
A44: 2025-03-04 | B44: Sundry Creditors - SLSIPL | C44: 0 | D44: 403 | E44: -1617728.1 | F44: Purchase Invoice | G44: PU/25/SLS/OT/1693 | H44: Handling Charges - Outbound (Exp) - SLSIPL | I44: 202/24-25 | J44: PU/25/SLS/OT/1693 | K44: 246779410766
A45: 2025-03-04 | B45: Sundry Creditors - SLSIPL | C45: 0 | D45: 403 | E45: -1618131.1 | F45: Purchase Invoice | G45: PU/25/SLS/OT/1694 | H45: Handling Charges - Outbound (Exp) - SLSIPL | I45: IMP/SLSIPL/0171/24-25 | J45: PU/25/SLS/OT/1694 | K45: 246779410756
A46: 2025-03-04 | B46: Sundry Creditors - SLSIPL | C46: 0 | D46: 3219 | E46: -1621350.1 | F46: Purchase Invoice | G46: PU/25/SLS/OT/1695 | H46: Handling Charges - Outbound (Exp) - SLSIPL | I46: 215/24-25 | J46: PU/25/SLS/OT/1695 | K46: 246779410758
A47: 2025-03-04 | B47: Sundry Creditors - SLSIPL | C47: 0 | D47: 403 | E47: -1621753.1 | F47: Purchase Invoice | G47: PU/25/SLS/OT/1696 | H47: Handling Charges - Outbound (Exp) - SLSIPL | I47: 197/24-25 | J47: PU/25/SLS/OT/1696 | K47: 246779410689
A48: 2025-03-04 | B48: Sundry Creditors - SLSIPL | C48: 0 | D48: 805 | E48: -1622558.1 | F48: Purchase Invoice | G48: PU/25/SLS/OT/1697 | H48: Handling Charges - Outbound (Exp) - SLSIPL | I48: 198/24-25 | J48: PU/25/SLS/OT/1697 | K48: 246779410693
A49: 2025-03-04 | B49: Sundry Creditors - SLSIPL | C49: 0 | D49: 604 | E49: -1623162.1 | F49: Purchase Invoice | G49: PU/25/SLS/OT/1698 | H49: Handling Charges - Outbound (Exp) - SLSIPL | I49: 205 & 206/24-25 | J49: PU/25/SLS/OT/1698 | K49: 246779410691
A50: 2025-03-04 | B50: Sundry Creditors - SLSIPL | C50: 0 | D50: 604 | E50: -1623766.1 | F50: Purchase Invoice | G50: PU/25/SLS/OT/1699 | H50: Handling Charges - Outbound (Exp) - SLSIPL | J50: PU/25/SLS/OT/1699 | K50: 246779410684
A51: 2025-03-04 | B51: Sundry Creditors - SLSIPL | C51: 0 | D51: 201 | E51: -1623967.1 | F51: Purchase Invoice | G51: PU/25/SLS/OT/1700 | H51: Handling Charges - Outbound (Exp) - SLSIPL | I51: IMP/SLSIPL/0179/24-25 | J51: PU/25/SLS/OT/1700 | K51: 246779410685
A52: 2025-03-04 | B52: Sundry Creditors - SLSIPL | C52: 0 | D52: 3622 | E52: -1627589.1 | F52: Purchase Invoice | G52: PU/25/SLS/OT/1701 | H52: Handling Charges - Outbound (Exp) - SLSIPL | I52: IMP/SLSIPL/0185/24-25 | J52: PU/25/SLS/OT/1701 | K52: 246779410690
A53: 2025-03-04 | B53: Sundry Creditors - SLSIPL | C53: 0 | D53: 1207 | E53: -1628796.1 | F53: Purchase Invoice | G53: PU/25/SLS/OT/1702 | H53: Handling Charges - Outbound (Exp) - SLSIPL | I53: 170/24-25 | J53: PU/25/SLS/OT/1702 | K53: 246779410680
A54: 2025-03-04 | B54: Sundry Creditors - SLSIPL | C54: 0 | D54: 201 | E54: -1628997.1 | F54: Purchase Invoice | G54: PU/25/SLS/OT/1703 | H54: Handling Charges - Outbound (Exp) - SLSIPL | I54: IMP/SLSIPL/0172/24-25 | J54: PU/25/SLS/OT/1703 | K54: 246779410681
A55: 2025-03-04 | B55: Sundry Creditors - SLSIPL | C55: 0 | D55: 201 | E55: -1629198.1 | F55: Purchase Invoice | G55: PU/25/SLS/OT/1704 | H55: Handling Charges - Outbound (Exp) - SLSIPL | I55: 186/24-25 | J55: PU/25/SLS/OT/1704 | K55: 246779410682
A56: 2025-03-04 | B56: Sundry Creditors - SLSIPL | C56: 0 | D56: 201 | E56: -1629399.1 | F56: Purchase Invoice | G56: PU/25/SLS/OT/1705 | H56: Handling Charges - Outbound (Exp) - SLSIPL | I56: NSDL Job No 173/24-25 | J56: PU/25/SLS/OT/1705 | K56: 246779410678
A57: 2025-03-04 | B57: Sundry Creditors - SLSIPL | C57: 0 | D57: 805 | E57: -1630204.1 | F57: Purchase Invoice | G57: PU/25/SLS/OT/1706 | H57: Handling Charges - Outbound (Exp) - SLSIPL | I57: 253/24-25 | J57: PU/25/SLS/OT/1706 | K57: 246779410845
A58: 2025-03-04 | B58: Sundry Creditors - SLSIPL | C58: 0 | D58: 604 | E58: -1630808.1 | F58: Purchase Invoice | G58: PU/25/SLS/OT/1707 | H58: Handling Charges - Outbound (Exp) - SLSIPL | I58: 93/24-25 | J58: PU/25/SLS/OT/1707 | K58: 246779410841
A59: 2025-03-04 | B59: Sundry Creditors - SLSIPL | C59: 0 | D59: 403 | E59: -1631211.1 | F59: Purchase Invoice | G59: PU/25/SLS/OT/1708 | H59: Handling Charges - Outbound (Exp) - SLSIPL | I59: IMP/SLS/0104/24-25 | J59: PU/25/SLS/OT/1708 | K59: 246779410844
A60: 2025-03-04 | B60: Sundry Creditors - SLSIPL | C60: 0 | D60: 403 | E60: -1631614.1 | F60: Purchase Invoice | G60: PU/25/SLS/OT/1709 | H60: Handling Charges - Outbound (Exp) - SLSIPL | I60: NSDL Job No 244/24-25 | J60: PU/25/SLS/OT/1709 | K60: 246779410842
A61: 2025-03-04 | B61: Sundry Creditors - SLSIPL | C61: 0 | D61: 805 | E61: -1632419.1 | F61: Purchase Invoice | G61: PU/25/SLS/OT/1723 | H61: Handling Charges - Outbound (Exp) - SLSIPL | I61: 199/24-25 | J61: PU/25/SLS/OT/1723 | K61: 246779410692
A62: 2025-03-04 | B62: Sundry Creditors - SLSIPL | C62: 0 | D62: 201 | E62: -1632620.1 | F62: Purchase Invoice | G62: PU/25/SLS/OT/1724 | H62: Handling Charges - Outbound (Exp) - SLSIPL | I62: 167/24-25 | J62: PU/25/SLS/OT/1724 | K62: 246779410679
... A68: 2025-03-06 | B68: Sundry Creditors - SLSIPL | C68: 0 | D68: 2884 | E68: -1678212.1 | F68: Purchase Invoice | G68: PU/25/SLS/OT/1682 | H68: Handling Charges - Inbound (Exp) - SLSIPL,Gate In Charges Paid - SLSIPL | I68: 108/24-25 | J68: PU/25/SLS/OT/1682 | K68: 246779410973
A69: 2025-03-06 | B69: Sundry Creditors - SLSIPL | C69: 0 | D69: 357094 | E69: -2035306.1 | F69: Purchase Invoice | G69: PU/25/SLS/OT/1716 | H69: Storage Charges - Cargo - SLSIPL | J69: PU/25/SLS/OT/1716 | K69: 246779410896
A70: 2025-03-06 | B70: Sundry Creditors - SLSIPL | C70: 0 | D70: 241385 | E70: -2276691.1 | F70: Purchase Invoice | G70: PU/25/SLS/OT/1717 | H70: Storage Charges - Cargo - SLSIPL | J70: PU/25/SLS/OT/1717 | K70: 246779410874
A71: 2025-03-06 | B71: Sundry Creditors - SLSIPL | C71: 0 | D71: 2004 | E71: -2278695.1 | F71: Purchase Invoice | G71: PU/25/SLS/OT/1745 | H71: Handling Charges - Inbound (Exp) - SLSIPL | I71: 226/24-25 | J71: PU/25/SLS/OT/1745 | K71: 246779411189
A72: 2025-03-06 | B72: Sundry Creditors - SLSIPL | C72: 0 | D72: 2004 | E72: -2280699.1 | F72: Purchase Invoice | G72: PU/25/SLS/OT/1746 | H72: Handling Charges - Inbound (Exp) - SLSIPL | I72: 225/24-25 | J72: PU/25/SLS/OT/1746 | K72: 246779411188
A73: 2025-03-06 | B73: Sundry Creditors - SLSIPL | C73: 0 | D73: 2004 | E73: -2282703.1 | F73: Purchase Invoice | G73: PU/25/SLS/OT/1747 | H73: Handling Charges - Inbound (Exp) - SLSIPL | I73: 224/24-25 | J73: PU/25/SLS/OT/1747 | K73: 246779411187
A74: 2025-03-06 | B74: Sundry Creditors - SLSIPL | C74: 0 | D74: 2004 | E74: -2284707.1 | F74: Purchase Invoice | G74: PU/25/SLS/OT/1748 | H74: Handling Charges - Inbound (Exp) - SLSIPL | I74: 196/24-25 | J74: PU/25/SLS/OT/1748 | K74: 246779411186
A75: 2025-03-06 | B75: Sundry Creditors - SLSIPL | C75: 0 | D75: 2004 | E75: -2286711.1 | F75: Purchase Invoice | G75: PU/25/SLS/OT/1749 | H75: Handling Charges - Inbound (Exp) - SLSIPL | I75: 208/24-25 | J75: PU/25/SLS/OT/1749 | K75: 246779411185
A76: 2025-03-17 | B76: Sundry Creditors - SLSIPL | C76: 0 | D76: 1842 | E76: -2288553.1 | F76: Purchase Invoice | G76: PU/25/SLS/OT/1863 | H76: VOS Activity Charges Paid - SLSIPL | J76: PU/25/SLS/OT/1863 | K76: 246779411758
A77: 2025-03-17 | B77: Sundry Creditors - SLSIPL | C77: 0 | D77: 576 | E77: -2289129.1 | F77: Purchase Invoice | G77: PU/25/SLS/OT/1864 | H77: VOS Activity Charges Paid - SLSIPL | J77: PU/25/SLS/OT/1864 | K77: 246779411933
A78: 2025-03-17 | B78: Sundry Creditors - SLSIPL | C78: 0 | D78: 336 | E78: -2289465.1 | F78: Purchase Invoice | G78: PU/25/SLS/OT/1865 | H78: VOS Activity Charges Paid - SLSIPL | J78: PU/25/SLS/OT/1865 | K78: 246779411934
A79: 2025-03-17 | B79: Sundry Creditors - SLSIPL | C79: 0 | D79: 576 | E79: -2290041.1 | F79: Purchase Invoice | G79: PU/25/SLS/OT/1866 | H79: VOS Activity Charges Paid - SLSIPL | J79: PU/25/SLS/OT/1866 | K79: 246779411935
A80: 2025-03-19 | B80: Sundry Creditors - SLSIPL | C80: 0 | D80: 35488 | E80: -2325529.1 | F80: Purchase Invoice | G80: PU/25/SLS/OT/1730 | H80: Fixed Storage Charges - ODC (Covered) - SLSIPL | J80: PU/25/SLS/OT/1730 | K80: 246779413000
A81: 2025-03-20 | B81: Sundry Creditors - SLSIPL | C81: 0 | D81: 1268 | E81: -2326797.1 | F81: Purchase Invoice | G81: PU/25/SLS/OT/1867 | H81: Gate In Charges Paid - SLSIPL | J81: PU/25/SLS/OT/1867 | K81: 246779414142
A82: 2025-03-20 | B82: Sundry Creditors - SLSIPL | C82: 0 | D82: 1408 | E82: -2328205.1 | F82: Purchase Invoice | G82: PU/25/SLS/OT/1868 | H82: Gate In Charges Paid - SLSIPL,Handling Charges - Inbound (Exp) - SLSIPL | J82: PU/25/SLS/OT/1868 | K82: 246779411051
A83: 2025-03-20 | B83: Sundry Creditors - SLSIPL | C83: 0 | D83: 381 | E83: -2328586.1 | F83: Purchase Invoice | G83: PU/25/SLS/OT/1869 | H83: Handling Charges - Inbound (Exp) - SLSIPL | J83: PU/25/SLS/OT/1869 | K83: 246779411052
A84: 2025-03-20 | B84: Sundry Creditors - SLSIPL | C84: 0 | D84: 1981 | E84: -2330567.1 | F84: Purchase Invoice | G84: PU/25/SLS/OT/1870 | H84: Gate In Charges Paid - SLSIPL,Handling Charges - Inbound (Exp) - SLSIPL | J84: PU/25/SLS/OT/1870 | K84: 246779411053
A85: 2025-03-20 | B85: Sundry Creditors - SLSIPL | C85: 0 | D85: 1907 | E85: -2332474.1 | F85: Purchase Invoice | G85: PU/25/SLS/OT/1871 | H85: Handling Charges - Inbound (Exp) - SLSIPL | J85: PU/25/SLS/OT/1871 | K85: 246779411050
A86: 2025-03-20 | B86: Sundry Creditors - SLSIPL | C86: 0 | D86: 596 | E86: -2333070.1 | F86: Purchase Invoice | G86: PU/25/SLS/OT/1872 | H86: Handling Charges - Outbound (Exp) - SLSIPL | J86: PU/25/SLS/OT/1872 | K86: 246779413782
A87: 2025-03-20 | B87: Sundry Creditors - SLSIPL | C87: 0 | D87: 3578 | E87: -2336648.1 | F87: Purchase Invoice | G87: PU/25/SLS/OT/1873 | H87: Handling Charges - Outbound (Exp) - SLSIPL | J87: PU/25/SLS/OT/1873 | K87: 246779413627
... A145: 2025-03-31 | B145: Sundry Creditors - SLSIPL | C145: 0 | D145: 3110 | E145: -2776196.1 | F145: Purchase Invoice | G145: PU/25/SLS/OT/1862 | H145: VOS Activity Charges Paid - SLSIPL | J145: PU/25/SLS/OT/1862 | K145: 246779411757
A146: 2025-03-31 | B146: Sundry Creditors - SLSIPL | C146: 0 | D146: 33376 | E146: -2809572.1 | F146: Purchase Invoice | G146: PU/25/SLS/OT/1925 | H146: Container Scanning Paid - SLSIPL | I146: Ascendas_creditnote | J146: PU/25/SLS/OT/1925 | K146: 246779411300
A147: 2025-04-01 | B147: Sundry Creditors - SLSIPL | C147: 0 | D147: 1161 | E147: -2810733.1 | F147: Purchase Invoice | G147: PU/26/SLS/OT/0048 | H147: VOS Activity Charges Paid - SLSIPL | I147: Supplier | J147: PU/26/SLS/OT/0048 | K147: 246779411448
A148: 2025-04-01 | B148: Sundry Creditors - SLSIPL | C148: 0 | D148: 1591 | E148: -2812324.1 | F148: Purchase Invoice | G148: PU/26/SLS/OT/0193 | H148: Handling Charges - Outbound (Exp) - SLSIPL | I148: Supplier | J148: PU/26/SLS/OT/0193 | K148: 246779413689
A149: 2025-04-01 | B149: Sundry Creditors - SLSIPL | C149: 0 | D149: 574 | E149: -2812898.1 | F149: Purchase Invoice | G149: PU/26/SLS/OT/0194 | H149: Handling Charges - Outbound (Exp) - SLSIPL | I149: Supplier | J149: PU/26/SLS/OT/0194 | K149: 246779413740
A150: 2025-04-01 | B150: Sundry Creditors - SLSIPL | C150: 0 | D150: 574 | E150: -2813472.1 | F150: Purchase Invoice | G150: PU/26/SLS/OT/0195 | H150: Handling Charges - Outbound (Exp) - SLSIPL | I150: Supplier | J150: PU/26/SLS/OT/0195 | K150: 246779413737
A151: 2025-04-01 | B151: Sundry Creditors - SLSIPL | C151: 0 | D151: 6896 | E151: -2820368.1 | F151: Purchase Invoice | G151: PU/26/SLS/OT/0196 | H151: Handling Charges - Outbound (Exp) - SLSIPL | I151: Supplier | J151: PU/26/SLS/OT/0196 | K151: 246779413735
A152: 2025-04-01 | B152: Sundry Creditors - SLSIPL | C152: 0 | D152: 191 | E152: -2820559.1 | F152: Purchase Invoice | G152: PU/26/SLS/OT/0197 | H152: Handling Charges - Outbound (Exp) - SLSIPL | I152: Supplier | J152: PU/26/SLS/OT/0197 | K152: 246779413744
A153: 2025-04-01 | B153: Sundry Creditors - SLSIPL | C153: 0 | D153: 191 | E153: -2820750.1 | F153: Purchase Invoice | G153: PU/26/SLS/OT/0199 | H153: Handling Charges - Outbound (Exp) - SLSIPL | I153: Supplier | J153: PU/26/SLS/OT/0199 | K153: 246779413733
A154: 2025-04-01 | B154: Sundry Creditors - SLSIPL | C154: 0 | D154: 383 | E154: -2821133.1 | F154: Purchase Invoice | G154: PU/26/SLS/OT/0200 | H154: Handling Charges - Outbound (Exp) - SLSIPL | I154: Supplier | J154: PU/26/SLS/OT/0200 | K154: 246779413743
A155: 2025-04-01 | B155: Sundry Creditors - SLSIPL | C155: 0 | D155: 383 | E155: -2821516.1 | F155: Purchase Invoice | G155: PU/26/SLS/OT/0201 | H155: Handling Charges - Outbound (Exp) - SLSIPL | I155: Supplier | J155: PU/26/SLS/OT/0201 | K155: 246779414680
A156: 2025-04-01 | B156: Sundry Creditors - SLSIPL | C156: 0 | D156: 6895 | E156: -2828411.1 | F156: Purchase Invoice | G156: PU/26/SLS/OT/0202 | H156: Handling Charges - Outbound (Exp) - SLSIPL | I156: Supplier | J156: PU/26/SLS/OT/0202 | K156: 246779413741
A157: 2025-04-01 | B157: Sundry Creditors - SLSIPL | C157: 0 | D157: 846 | E157: -2829257.1 | F157: Purchase Invoice | G157: PU/26/SLS/OT/0191 | H157: Handling Charges - Inbound (Exp) - SLSIPL | I157: Supplier | J157: PU/26/SLS/OT/0191 | K157: 246779413933
... A221: 2025-05-28 | B221: Sundry Creditors - SLSIPL | C221: 0 | D221: 333696 | E221: -5193789.1 | F221: Purchase Invoice | G221: PU/26/SLS/OT/0278 | H221: Storage Charges - Cargo - SLSIPL | I221: Supplier | J221: PU/26/SLS/OT/0278 | K221: 256779413899
A222: 2025-05-30 | B222: Sundry Creditors - SLSIPL | C222: 177773 | D222: 0 | E222: -5016016.1 | F222: Pay | G222: BP/26/SLS/0192 | H222: 1395250393003 - Punjab National Bank - INR - SLSIPL | I222: Supplier
A223: 2025-06-04 | B223: Sundry Creditors - SLSIPL | C223: 0 | D223: 9844 | E223: -5025860.1 | F223: Purchase Invoice | G223: PU/26/SLS/OT/0358 | H223: Handling Charges - Outbound (Exp) - SLSIPL | I223: Supplier | J223: PU/26/SLS/OT/0358 | K223: 256779414165
A224: 2025-06-04 | B224: Sundry Creditors - SLSIPL | C224: 0 | D224: 8407 | E224: -5034267.1 | F224: Purchase Invoice | G224: PU/26/SLS/OT/0360 | H224: Handling Charges - Outbound (Exp) - SLSIPL | I224: Supplier | J224: PU/26/SLS/OT/0360 | K224: 256779414216
A225: 2025-06-04 | B225: Sundry Creditors - SLSIPL | C225: 500946.52 | D225: 0 | E225: -4533320.6 | F225: Pay | G225: BP/25/SLS/1225-1 | H225: 1395250393003 - Punjab National Bank - INR - SLSIPL | I225: Supplier | J225: PU/25/SLS/OT/1562, PU/25/SLS/OT/1720, PU/25/SLS/OT/1731, PU/25/SLS/OT/1721, PU/25/SLS/OT/1673 | K225: 246779410117
A226: 2025-06-04 | B226: Sundry Creditors - SLSIPL | C226: 0 | D226: 17313 | E226: -4550633.6 | F226: Purchase Invoice | G226: PU/26/SLS/OT/0585 | H226: Scanning Charges - Inbound - SLSIPL | I226: Supplier | J226: PU/26/SLS/OT/0585 | K226: 256779414288
A227: 2025-06-04 | B227: Sundry Creditors - SLSIPL | C227: 0 | D227: 41769 | E227: -4592402.6 | F227: Purchase Invoice | G227: PU/26/SLS/OT/0797 | H227: Handling Charges - Inbound (Exp) - SLSIPL,LCL Movment - Gate in Charge - SLSIPL,Transportation Charges Paid - SLSIPL,Eempty Container Return Charges Paid - SLSIPL | I227: Supplier | J227: PU/26/SLS/OT/0797 | K227: 256779414158
A228: 2025-06-07 | B228: Sundry Creditors - SLSIPL | C228: 0 | D228: 352792 | E228: -4945194.6 | F228: Purchase Invoice | G228: PU/26/SLS/OT/0285 | H228: Storage Charges - Cargo - SLSIPL | I228: Supplier | J228: PU/26/SLS/OT/0285 | K228: 256779414242
A229: 2025-06-10 | B229: Sundry Creditors - SLSIPL | C229: 0 | D229: 35431 | E229: -4980625.6 | F229: Purchase Invoice | G229: PU/26/SLS/OT/0357-1 | H229: Fixed Storage Charges - ODC (Covered) - SLSIPL | I229: Supplier | J229: PU/26/SLS/OT/0357-1 | K229: 256779414386
A230: 2025-06-13 | B230: Sundry Creditors - SLSIPL | C230: 700000 | D230: 0 | E230: -4280625.6 | F230: Pay | G230: BP/26/SLS/0229 | H230: 1395250393003 - Punjab National Bank - INR - SLSIPL | I230: Supplier
A231: 2025-06-21 | B231: Sundry Creditors - SLSIPL | C231: 700000 | D231: 0 | E231: -3580625.6 | F231: Pay | G231: BP/26/SLS/0259 | H231: 1395250393003 - Punjab National Bank - INR - SLSIPL | I231: Supplier
A232: 2025-06-30 | B232: Sundry Creditors - SLSIPL | C232: 700000 | D232: 0 | E232: -2880625.6 | F232: Pay | G232: BP/26/SLS/0291 | H232: 1395250393003 - Punjab National Bank - INR - SLSIPL | I232: Supplier
A233: 2025-07-05 | B233: Sundry Creditors - SLSIPL | C233: 700000 | D233: 0 | E233: -2180625.6 | F233: Pay | G233: BP/26/SLS/0300 | H233: 1395250393003 - Punjab National Bank - INR - SLSIPL | I233: Supplier
...
