Workbook

Sheet Invoice Not in Customer Boo (2)
A1: Document Number | B1: Document Type | C1: Document Date | D1: Entry Date | E1: Document Header Text | F1: Reference | G1: Document Currency Key | H1: Document Currency Value | I1: Company Code Currency Key | J1: Company Code Currency Value | K1: Text | L1: Remark | M1: Remarks | N1: Action Points
A2: 1800001617 | B2: DR | C2: 45730 | D2: 45735 | E2: NA | F2: 246779412274 | G2: USD | H2: 100 | I2: INR | J2: 8669.13 | K2: Intra Unit Transfer Charges Month Of August,2024 | L2: We had given 2 invoices against BOE No. 7000274, and we accepted invoice 246779411485. | M2: Credit Note to be passed after verification by billing team | N2: Credit Note to be passed as discussed with CL team
A3: 1800000559 | B3: DR | C3: 45719 | D3: 45719 | E3: NA | F3: 246779410509 | G3: USD | H3: 29.25 | I3: INR | J3: 2535.72 | K3: Outbound Handling for Aug 2024 | L3: you have made an Invoice of Handling Charges 13 Plt instead of 4 Plt. | M3: CRM team will handle | N3: to be accounted by siddhartha
A4: 1800006698 | B4: DR | C4: 45762 | D4: 45763 | E4: NA | F4: 256779411589 | G4: USD | H4: 3.38 | I4: INR | J4: 293.8 | K4: Outbound Handling Charges Aug 2024 | L4: Handling Charges CBM Rate is 2.25 but you have Handling Charges CBM Rate is 3.24 | M4: CRM team will handle | N4: To be discussed with customer that the rate is charged as per agreemant for HAZ goods
A5: 1800001791 | B5: DR | C5: 45730 | D5: 45733 | E5: NA | F5: 246779411456 | G5: USD | H5: 4.77 | I5: INR | J5: 413.52 | K5: VAS Activity Charges for the month of August, 24 | L5: Duplicated invoice | M5: Credit Note to be passed after verification by billing team | N5: Credit Note to be passed as discussed with CL team
A6: 1800012462 | B6: DR | C6: 45904 | D6: 45909 | E6: NA | F6: 256779417162 | G6: USD | H6: 44.74 | I6: INR | J6: 3915.39 | K6: VAS -16-31 Aug 25 | L6: The VAS charges are incorrect. | M6: Invoice to changed by CRM team | N6: Credit Note to be passed as discussed with CL team
A7: 1800014290 | B7: DR | C7: 45966 | D7: 45967 | E7: NA | F7: 256779418827 | G7: USD | H7: 60.86 | I7: INR | J7: 5355.89 | K7: WEIGHTMENT-16 -31 Oct 25 | L7: These specific charges are not included in our existing contract. | N7: Credit Note to be passed as discussed with CL team
A8: 1800004532 | B8: DR | C8: 45736 | D8: 45737 | E8: NA | F8: 246779414400 | G8: USD | H8: 80.95 | I8: INR | J8: 7017.66 | K8: Inbound Handling charges for Nov 2024 | L8: Handling Charges CBM Rate is 2.25 but you have Handling Charges CBM Rate is 3.24 | M8: CRM team will handle | N8: To be discussed with customer that the rate is charged as per agreemant for HAZ goods
A9: 1800004533 | B9: DR | C9: 45736 | D9: 45737 | E9: NA | F9: 246779414401 | G9: USD | H9: 15 | I9: INR | J9: 1300.37 | K9: LCL Movement Charges for Nov 2024 | M9: Amount in Invoice to be verified by biling team | N9: to be accounted by siddhartha
A10: 1800013760 | B10: DR | C10: 45937 | D10: 45939 | E10: NA | F10: 256779418181 | G10: USD | H10: 49.33 | I10: INR | J10: 4350.45 | K10: VAS-16-30 Sept 25 | L10: This is to inform you that MHE charges have already been applied in Invoice Nos. 256779418354 and 256779418342. However, the same MHE charges have been included again in Invoice No. 256779418181. | M10: to be accounted by siddhartha after CBM rate issue is solved | N10: Credit Note to be passed as discussed with CL team
A11: 1800009470 | B11: DR | C11: 45815 | D11: 45817 | E11: NA | F11: 256779414234 | G11: USD | H11: 925.23 | I11: INR | J11: 79098.63 | K11: Unit storage -1-31 May 25 | L11: Credit Note Pending | M11: mail summary will be sent by Siddhartha team ,Credit Note to be passed after verification by billing team | N11: Credit Note to be passed as discussed with CL team | O11: 149 | P11: 22.64
A12: 1800013511 | B12: DR | C12: 45935 | D12: 45940 | E12: NA | F12: 256779418401 | G12: USD | H12: 62.52 | I12: INR | J12: 5513.69 | K12: PORT SSR Chgs Sep 25 | L12: These specific charges are not included in our existing contract. | M12: to be accounted by siddhartha | N12: to be accounted by siddhartha
H13: =SUM(H2:H12) -> 1376.03 | J13: =SUBTOTAL(9,J2:J12) -> 118464.25

Sheet Summary
A1: Reconciliation of Ledger as on 31st January 2026
A2: Particulars | B2: Amount in USD
A3: Balance as per Siddhartha Logistics | B3: ='Customer Data'!F151 -> 5221.593
A4: Add: TDS to be booked in Ascendus books | B4: ='TDS To Be Booked'!L146+'Payment Reco'!H4 -> 2462.8459
A5: Add: Invoices & CN not recorded in customer books | B5: ='Invoice Not in Customer Boo (2)'!H13 -> 1376.03
A6: Less: Difference in Payment recorded in both books | B6: 50
A7: Derived balance | B7: =SUM(B3:B6) -> 9110.4689
A8: Balance as per Ascent | B8: ='Ascendus data working'!F202 -> 8974.5146
A10: Difference | B10: =B7-B8-B9 -> 135.95426

Sheet Payment Reco
A2: As per Customer | D2: As per Ascendus
A3: Payment Date | B3: Particulars | C3: Amount | D3: Particulars | E3: Date | G3: Amount | H3: Diffrence
A4: 45800 | B4: Outgoing payment | C4: 7435.89 | D4: DZ | E4: 45862 | F4: USD | G4: -8262.11 | H4: =C4+G4 -> -826.22
A5: 45856 | B5: Outgoing payment | C5: 4602.99 | D5: DZ | E5: 45891 | F5: USD | G5: -4582.99 | H5: =C5+G5 -> 20
A6: 45945 | B6: Outgoing payment | C6: 4875.15 | D6: DZ | E6: 45955 | F6: USD | G6: -4875.15 | H6: =C6+G6 -> 0
B7: Outgoing payment | C7: 10721.42 | D7: DZ | E7: 46050 | F7: USD | G7: -10691.42 | H7: =C7+G7 -> 30
C8: =SUM(C4:C7) -> 27635.45 | G8: =SUM(G4:G7) -> -28411.67 | H8: =SUM(H4:H7) -> -776.22

Sheet CN Not in Customer Books
A1: Document Number | B1: Document Type | C1: Document Date | D1: Entry Date | E1: Document Header Text | F1: Reference | G1: Document Currency Key | H1: Document Currency Value | I1: Company Code Currency Key | J1: Company Code Currency Value | K1: Text | L1: Text | M1: Vlookup
A2: 1600002686 | B2: DG | C2: 46027 | D2: 46027 | E2: NA | F2: 256779422156 | G2: USD | H2: -59.62 | I2: INR | J2: -5410.11 | K2: Credit note for Duplicate invoice -256779418354 | M2: #N/A | O2: 256779418354 | P2: =VLOOKUP(O2,'Invoice Not in Customer Book'!F:H,3,0) -> #N/A | Q2: =H2+P2 -> #N/A
A3: 1600002687 | B3: DG | C3: 46027 | D3: 46027 | E3: NA | F3: 256779422157 | G3: USD | H3: -49.33 | I3: INR | J3: -4476.36 | K3: Credit note for Duplicate invoice -256779418354 | M3: #N/A | O3: 256779418354 | P3: =VLOOKUP(O3,'Invoice Not in Customer Book'!F:H,3,0) -> #N/A | Q3: =H3+P3 -> #N/A
H4: =SUM(H2:H3) -> -108.95

Sheet Invoice Not in Customer Book
A1: Document Number | B1: Document Type | C1: Document Date | D1: Entry Date | E1: Document Header Text | F1: Reference | G1: Document Currency Key | H1: Document Currency Value | I1: Company Code Currency Key | J1: Company Code Currency Value | K1: Text | L1: Text | M1: Vlookup | O1: Action points
A2: 1800001617 | B2: DR | C2: 45730 | D2: 45735 | E2: NA | F2: 246779412274 | G2: USD | H2: 100 | I2: INR | J2: 8669.13 | K2: Intra Unit Transfer Charges Month Of August,2024 | M2: #N/A | N2: =VLOOKUP(F2,'CN Not in Customer Books'!O:O,1,0) -> #N/A | O2: Credit Note to be passed as discussed with CL team
A3: 1800000559 | B3: DR | C3: 45719 | D3: 45719 | E3: NA | F3: 246779410509 | G3: USD | H3: 29.25 | I3: INR | J3: 2535.72 | K3: Outbound Handling for Aug 2024 | M3: #N/A | N3: =VLOOKUP(F3,'CN Not in Customer Books'!O:O,1,0) -> #N/A | O3: to be accounted by siddhartha
A4: 1800006698 | B4: DR | C4: 45762 | D4: 45763 | E4: NA | F4: 256779411589 | G4: USD | H4: 3.38 | I4: INR | J4: 293.8 | K4: Outbound Handling Charges Aug 2024 | M4: #N/A | N4: =VLOOKUP(F4,'CN Not in Customer Books'!O:O,1,0) -> #N/A | O4: To be discussed with customer that the rate is charged as per agreemant for HAZ goods
A5: 1800012462 | B5: DR | C5: 45904 | D5: 45909 | E5: NA | F5: 256779417162 | G5: USD | H5: 44.74 | I5: INR | J5: 3915.39 | K5: VAS -16-31 Aug 25 | M5: #N/A | N5: =VLOOKUP(F5,'CN Not in Customer Books'!O:O,1,0) -> #N/A | O5: Credit Note to be passed as discussed with CL team
A6: 1800014290 | B6: DR | C6: 45966 | D6: 45967 | E6: NA | F6: 256779418827 | G6: USD | H6: 60.86 | I6: INR | J6: 5355.89 | K6: WEIGHTMENT-16 -31 Oct 25 | M6: #N/A | N6: =VLOOKUP(F6,'CN Not in Customer Books'!O:O,1,0) -> #N/A | O6: Credit Note to be passed as discussed with CL team
A7: 1800004532 | B7: DR | C7: 45736 | D7: 45737 | E7: NA | F7: 246779414400 | G7: USD | H7: 80.95 | I7: INR | J7: 7017.66 | K7: Inbound Handling charges for Nov 2024 | M7: #N/A | N7: =VLOOKUP(F7,'CN Not in Customer Books'!O:O,1,0) -> #N/A | O7: To be discussed with customer that the rate is charged as per agreemant for HAZ goods
A8: 1800004533 | B8: DR | C8: 45736 | D8: 45737 | E8: NA | F8: 246779414401 | G8: USD | H8: 15 | I8: INR | J8: 1300.37 | K8: LCL Movement Charges for Nov 2024 | M8: #N/A | N8: =VLOOKUP(F8,'CN Not in Customer Books'!O:O,1,0) -> #N/A | O8: to be accounted by siddhartha
A9: 1800013760 | B9: DR | C9: 45937 | D9: 45939 | E9: NA | F9: 256779418181 | G9: USD | H9: 49.33 | I9: INR | J9: 4350.45 | K9: VAS-16-30 Sept 25 | M9: #N/A | N9: =VLOOKUP(F9,'CN Not in Customer Books'!O:O,1,0) -> #N/A | O9: Credit Note to be passed as discussed with CL team
A10: 1800009470 | B10: DR | C10: 45815 | D10: 45817 | E10: NA | F10: 256779414234 | G10: USD | H10: 925.23 | I10: INR | J10: 79098.63 | K10: Unit storage -1-31 May 25 | M10: #N/A | N10: =VLOOKUP(F10,'CN Not in Customer Books'!O:O,1,0) -> #N/A | O10: Credit Note to be passed as discussed with CL team
A11: 1800013511 | B11: DR | C11: 45935 | D11: 45940 | E11: NA | F11: 256779418401 | G11: USD | H11: 62.52 | I11: INR | J11: 5513.69 | K11: PORT SSR Chgs Sep 25 | M11: #N/A | N11: =VLOOKUP(F11,'CN Not in Customer Books'!O:O,1,0) -> #N/A | O11: to be accounted by siddhartha
H12: =SUM(H2:H11) -> 1371.26
H13: ='CN Not in Customer Books'!H4 -> -108.95
H14: =SUM(H12:H13) -> 1262.31

Sheet TDS To Be Booked
L1: =SUBTOTAL(9,L2:L136) -> 3468.5859 | M1: =L1*85 -> 294829.8
A2: Document Number | B2: Document Type | C2: Document Date | D2: Reference | E2: Document Currency Key | F2: Document Currency Value | G2: Company Code Currency Key | H2: Company Code Currency Value | I2: Text | J2: Vlookup | K2: Converted Value | L2: TDS Deducted | M2: Rate
A3: 1800000035 | B3: DR | C3: 45708 | D3: 246779410007 | E3: USD | F3: 1190.48 | G3: INR | H3: 102742.78 | I3: Fixed Rental charges for Aug 2024 | J3: 1071.43 | K3: =F3 -> 1190.48 | L3: =F3-J3 -> 119.05 | M3: =L3/F3*100 -> 10.000168
A4: 1800000079 | B4: DR | C4: 45708 | D4: 246779410274 | E4: USD | F4: 1190.48 | G4: INR | H4: 102742.78 | I4: Fixed Rental charges for Oct 2024 | J4: 1071.43 | K4: =F4 -> 1190.48 | L4: =F4-J4 -> 119.05 | M4: =L4/F4*100 -> 10.000168
A5: 1800000099 | B5: DR | C5: 45708 | D5: 246779410027 | E5: USD | F5: 1190.48 | G5: INR | H5: 102742.78 | I5: Fixed Rental charges for Sept 2024 | J5: 1071.43 | K5: =F5 -> 1190.48 | L5: =F5-J5 -> 119.05 | M5: =L5/F5*100 -> 10.000168
A6: 1800000168 | B6: DR | C6: 45708 | D6: 246779410095 | E6: USD | F6: 1190.48 | G6: INR | H6: 102742.78 | I6: Fixed Rental charges for Nov 2024 | J6: 1071.43 | K6: =F6 -> 1190.48 | L6: =F6-J6 -> 119.05 | M6: =L6/F6*100 -> 10.000168
A7: 1800000211 | B7: DR | C7: 45708 | D7: 246779410138 | E7: USD | F7: 1190.48 | G7: INR | H7: 102742.78 | I7: Fixed Rental charges for Dec 2024 | J7: 1071.43 | K7: =F7 -> 1190.48 | L7: =F7-J7 -> 119.05 | M7: =L7/F7*100 -> 10.000168
A8: 1800000254 | B8: DR | C8: 45708 | D8: 246779410181 | E8: USD | F8: 1166.59 | G8: INR | H8: 100680.99 | I8: Fixed Rental charges for Jan 2025 | J8: 1049.93 | K8: =F8 -> 1166.59 | L8: =F8-J8 -> 116.66 | M8: =L8/F8*100 -> 10.000086
A9: 1800000297 | B9: DR | C9: 45708 | D9: 246779410224 | E9: USD | F9: 1143.12 | G9: INR | H9: 98655.44 | I9: Fixed Rental charges for Feb 2025 | J9: 1028.81 | K9: =F9 -> 1143.12 | L9: =F9-J9 -> 114.31 | M9: =L9/F9*100 -> 9.999825
A10: 1800000406 | B10: DR | C10: 45719 | D10: 246779410368 | E10: USD | F10: 356.43 | G10: INR | H10: 30899.37 | I10: Storage Charges for the month of August, 2024 | J10: 320.78 | K10: =F10 -> 356.43 | L10: =F10-J10 -> 35.65 | M10: =L10/F10*100 -> 10.001964
A11: 1800000675 | B11: DR | C11: 45719 | D11: 246779410615 | E11: USD | F11: 9 | G11: INR | H11: 780.22 | I11: Outbound Handling for Sep 2024 | J11: 8.81 | K11: =F11 -> 9 | L11: =F11-J11 -> 0.19 | M11: =L11/F11*100 -> 2.1111111
A12: 1800000432 | B12: DR | C12: 45719 | D12: 246779410394 | E12: USD | F12: 505.86 | G12: INR | H12: 43853.64 | I12: Storage for the month of Sep 2024 Exch Rate 83.79 | J12: 455.27 | K12: =F12 -> 505.86 | L12: =F12-J12 -> 50.59 | M12: =L12/F12*100 -> 10.000791
A13: 1800000456 | B13: DR | C13: 45719 | D13: 246779410418 | E13: USD | F13: 562.6 | G13: INR | H13: 48772.5 | I13: Storage for the month of Oct 2024 | J13: 506.34 | K13: =F13 -> 562.6 | L13: =F13-J13 -> 56.26 | M13: =L13/F13*100 -> 10
A14: 1800000560 | B14: DR | C14: 45719 | D14: 246779410510 | E14: USD | F14: 194.9 | G14: INR | H14: 16896.13 | I14: Outbound Handling for Aug 2024 | J14: 191 | K14: =F14 -> 194.9 | L14: =F14-J14 -> 3.9 | M14: =L14/F14*100 -> 2.0010262
... A73: 1800008041 | B73: DR | C73: 45770 | D73: 256779412932 | E73: USD | F73: 66.86 | G73: INR | H73: 5811.59 | I73: Outbound chgs - 01 - 15 Apr 25 | J73: 65.52 | K73: =F73 -> 66.86 | L73: =F73-J73 -> 1.34 | M73: =L73/F73*100 -> 2.0041879
A74: 1800008258 | B74: DR | C74: 45787 | D74: 256779413142 | E74: INR | F74: 100000 | G74: INR | H74: 100000 | I74: Fixed Storage Charges fo MAY 2025 | J74: 1046.71 | K74: =J74/0.9 -> 1163.0111 | L74: =K74-J74 -> 116.30111 | M74: =L74/K74*100 -> 10
A75: 1800008504 | B75: DR | C75: 45793 | D75: 256779413272 | E75: USD | F75: 25.28 | G75: INR | H75: 2173.67 | I75: Empty Lolo Chgs - 01 - 31 Apr 25 | J75: 24.77 | K75: =F75 -> 25.28 | L75: =F75-J75 -> 0.51 | M75: =L75/F75*100 -> 2.0174051
A76: 1800008597 | B76: DR | C76: 45793 | D76: 256779413361 | E76: USD | F76: 3 | G76: INR | H76: 257.95 | I76: Outbound chgs - 16 - 30 Apr 25 | J76: 2.94 | K76: =F76 -> 3 | L76: =F76-J76 -> 0.06 | M76: =L76/F76*100 -> 2
A77: 1800008726 | B77: DR | C77: 45797 | D77: 256779413490 | E77: USD | F77: 3 | G77: INR | H77: 257.95 | I77: Outbound chgs - 01 - 15 MAY 25 | J77: 2.94 | K77: =F77 -> 3 | L77: =F77-J77 -> 0.06 | M77: =L77/F77*100 -> 2
A78: 1800009129 | B78: DR | C78: 45805 | D78: 256779413893 | E78: USD | F78: 797.57 | G78: INR | H78: 68578.02 | I78: Storage Chgs - 01 - 31 Apr 25 | J78: 717.81 | K78: =F78 -> 797.57 | L78: =F78-J78 -> 79.76 | M78: =L78/F78*100 -> 10.000376
A79: 1800009239 | B79: DR | C79: 45812 | D79: 256779414003 | E79: USD | F79: 807.39 | G79: INR | H79: 69024.4 | I79: Storage- Aug-24, | J79: 726.65 | K79: =F79 -> 807.39 | L79: =F79-J79 -> 80.74 | M79: =L79/F79*100 -> 10.000124
A80: 1800009240 | B80: DR | C80: 45812 | D80: 256779414004 | E80: USD | F80: 808.16 | G80: INR | H80: 69090.23 | I80: Storage- Sept-24, | J80: 727.34 | K80: =F80 -> 808.16 | L80: =F80-J80 -> 80.82 | M80: =L80/F80*100 -> 10.000495
A81: 1800009241 | B81: DR | C81: 45812 | D81: 256779414005 | E81: USD | F81: 805.28 | G81: INR | H81: 68844.02 | I81: Storage - Oct-24, | J81: 724.75 | K81: =F81 -> 805.28 | L81: =F81-J81 -> 80.53 | M81: =L81/F81*100 -> 10.000248
A82: 1800009242 | B82: DR | C82: 45812 | D82: 256779414006 | E82: USD | F82: 801.47 | G82: INR | H82: 68518.3 | I82: Storage- Nov-24, | J82: 721.32 | K82: =F82 -> 801.47 | L82: =F82-J82 -> 80.15 | M82: =L82/F82*100 -> 10.000374
A83: 1800009243 | B83: DR | C83: 45812 | D83: 256779414007 | E83: USD | F83: 790.89 | G83: INR | H83: 67613.8 | I83: Storage- Dec-24, | J83: 711.8 | K83: =F83 -> 790.89 | L83: =F83-J83 -> 79.09 | M83: =L83/F83*100 -> 10.000126
A84: 1800009590 | B84: DR | C84: 45818 | D84: 256779414354 | E84: INR | F84: 100000 | G84: INR | H84: 100000 | I84: Fixed Storage Charges fo JUNE 2025 | J84: 1052.75 | K84: =J84/0.9 -> 1169.7222 | L84: =K84-J84 -> 116.97222 | M84: =L84/K84*100 -> 10
A85: 1800010152 | B85: DR | C85: 45842 | D85: 256779414912 | E85: INR | F85: 100000 | G85: INR | H85: 100000 | I85: Fixed Storage Charges fo JULY 2025 | J85: 1046.5 | K85: =J85/0.9 -> 1162.7778 | L85: =K85-J85 -> 116.27778 | M85: =L85/K85*100 -> 10
A86: 1800010069 | B86: DR | C86: 45842 | D86: 256779414833 | E86: USD | F86: 3 | G86: INR | H86: 258 | I86: Outbound chgs - 01 - 15 Jun 25 | J86: 2.94 | K86: =F86 -> 3 | L86: =F86-J86 -> 0.06 | M86: =L86/F86*100 -> 2
A87: 1800010430 | B87: DR | C87: 45842 | D87: 256779415190 | E87: USD | F87: 690.7 | G87: INR | H87: 59400.66 | I87: Unit Storage - 1-30 June 25 | J87: 621.63 | K87: =F87 -> 690.7 | L87: =F87-J87 -> 69.07 | M87: =L87/F87*100 -> 10
A88: 1800010701 | B88: DR | C88: 45856 | D88: 256779415485 | E88: USD | F88: 17.25 | G88: INR | H88: 1483.51 | I88: LCL chgs - 01 - 15 JUL 25 | J88: 16.9 | K88: =F88 -> 17.25 | L88: =F88-J88 -> 0.35 | M88: =L88/F88*100 -> 2.0289855
A89: 1800010749 | B89: DR | C89: 45856 | D89: 256779415533 | E89: USD | F89: 21.75 | G89: INR | H89: 1870.51 | I89: Outbound chgs - 01 - 15 Jul 25 | J89: 21.31 | K89: =F89 -> 21.75 | L89: =F89-J89 -> 0.44 | M89: =L89/F89*100 -> 2.0229885
A90: 1800011012 | B90: DR | C90: 45857 | D90: 256779415772 | E90: USD | F90: 59.43 | G90: INR | H90: 5111.02 | I90: VAS - 1-15 July 25 | J90: 58.24 | K90: =F90 -> 59.43 | L90: =F90-J90 -> 1.19 | M90: =L90/F90*100 -> 2.0023557
A91: 1800011358 | B91: DR | C91: 45870 | D91: 256779416024 | E91: INR | F91: 100000 | G91: INR | H91: 100000 | I91: Fixed Storage Charges for August 2025 | J91: 1046.14 | K91: =J91/0.9 -> 1162.3778 | L91: =K91-J91 -> 116.23778 | M91: =L91/K91*100 -> 10
A92: 1800011652 | B92: DR | C92: 45877 | D92: 256779416082 | E92: USD | F92: 759.67 | G92: INR | H92: 65354.5 | I92: Unit Storage - 1-31 July 25 | J92: 683.7 | K92: =F92 -> 759.67 | L92: =F92-J92 -> 75.97 | M92: =L92/F92*100 -> 10.000395
A93: 1800011791 | B93: DR | C93: 45877 | D93: 256779416182 | E93: USD | F93: 18 | G93: INR | H93: 1548.54 | I93: LCL chgs - 16 - 31 JUL 25 | J93: 17.64 | K93: =F93 -> 18 | L93: =F93-J93 -> 0.36 | M93: =L93/F93*100 -> 2
A94: 1800011710 | B94: DR | C94: 45877 | D94: 256779416228 | E94: USD | F94: 3 | G94: INR | H94: 258.09 | I94: Outbound chgs - 16 - 31 Jul 25 | J94: 2.94 | K94: =F94 -> 3 | L94: =F94-J94 -> 0.06 | M94: =L94/F94*100 -> 2
A95: 1800011396 | B95: DR | C95: 45877 | D95: 256779416246 | E95: USD | F95: 70.95 | G95: INR | H95: 6103.84 | I95: CODC LCL Chgs - 16 - 31 Jul 25 | J95: 69.54 | K95: =F95 -> 70.95 | L95: =F95-J95 -> 1.41 | M95: =L95/F95*100 -> 1.987315
A96: 1800011407 | B96: DR | C96: 45877 | D96: 256779416257 | E96: USD | F96: 22.87 | G96: INR | H96: 1967.51 | I96: CODC Out chgs - 16 - 31 Jul 25 | J96: 22.42 | K96: =F96 -> 22.87 | L96: =F96-J96 -> 0.45 | M96: =L96/F96*100 -> 1.9676432
A97: 1800011596 | B97: DR | C97: 45877 | D97: 256779416446 | E97: USD | F97: 2.28 | G97: INR | H97: 196.15 | I97: VAS 16-31 July 25 | J97: 2.23 | K97: =F97 -> 2.28 | L97: =F97-J97 -> 0.05 | M97: =L97/F97*100 -> 2.1929825
A98: 1800012069 | B98: DR | C98: 45889 | D98: 256779416604 | E98: USD | F98: 17.31 | G98: INR | H98: 1489.18 | I98: CODC LCL Chgs - 1-15 Aug 25 | J98: 16.96 | K98: =F98 -> 17.31 | L98: =F98-J98 -> 0.35 | M98: =L98/F98*100 -> 2.0219526
A99: 1800012178 | B99: DR | C99: 45889 | D99: 256779416616 | E99: USD | F99: 63.65 | G99: INR | H99: 5475.82 | I99: CODC Out chgs - 1-15 Aug 25 | J99: 62.38 | K99: =F99 -> 63.65 | L99: =F99-J99 -> 1.27 | M99: =L99/F99*100 -> 1.9952867
A100: 1800012251 | B100: DR | C100: 45889 | D100: 256779416847 | E100: USD | F100: 27.83 | G100: INR | H100: 2394.22 | I100: LCL chgs - 01 - 15 AUG 25 | J100: 27.27 | K100: =F100 -> 27.83 | L100: =F100-J100 -> 0.56 | M100: =L100/F100*100 -> 2.012217
A101: 1800012220 | B101: DR | C101: 45889 | D101: 256779416882 | E101: USD | F101: 12.83 | G101: INR | H101: 1103.77 | I101: Outbound chgs - 01 - 15 Aug 25 | J101: 12.57 | K101: =F101 -> 12.83 | L101: =F101-J101 -> 0.26 | M101: =L101/F101*100 -> 2.0265004
A102: 1800012710 | B102: DR | C102: 45904 | D102: 256779417344 | E102: INR | F102: 100000 | G102: INR | H102: 100000 | I102: Fixed Storage Charges for September 2025 | J102: 1028.4 | K102: =J102/0.9 -> 1142.6667 | L102: =K102-J102 -> 114.26667 | M102: =L102/K102*100 -> 10
A103: 1800012276 | B103: DR | C103: 45904 | D103: 256779416912 | E103: USD | F103: 44.96 | G103: INR | H103: 3934.64 | I103: CODC LCL Chgs - 16-31 Aug 25 | J103: 44.06 | K103: =F103 -> 44.96 | L103: =F103-J103 -> 0.9 | M103: =L103/F103*100 -> 2.0017794
A104: 1800012287 | B104: DR | C104: 45904 | D104: 256779416949 | E104: USD | F104: 30.16 | G104: INR | H104: 2639.43 | I104: CODC Out chgs -16-31 Aug 25 | J104: 29.55 | K104: =F104 -> 30.16 | L104: =F104-J104 -> 0.61 | M104: =L104/F104*100 -> 2.0225464
A105: 1800012532 | B105: DR | C105: 45904 | D105: 256779417136 | E105: USD | F105: 1.71 | G105: INR | H105: 149.65 | I105: VAS - 16-31 Aug 25 | J105: 1.68 | K105: =F105 -> 1.71 | L105: =F105-J105 -> 0.03 | M105: =L105/F105*100 -> 1.754386
A106: 1800012688 | B106: DR | C106: 45904 | D106: 256779417328 | E106: USD | F106: 2.25 | G106: INR | H106: 196.91 | I106: Outbound chgs - 16 - 31 Aug 25 | J106: 2.2 | K106: =F106 -> 2.25 | L106: =F106-J106 -> 0.05 | M106: =L106/F106*100 -> 2.2222222
A107: 1800012469 | B107: DR | C107: 45906 | D107: 256779417077 | E107: USD | F107: 565.97 | G107: INR | H107: 49530.49 | I107: Unit-Storage-1-31 Aug 25 | J107: 509.36 | K107: =F107 -> 565.97 | L107: =F107-J107 -> 56.61 | M107: =L107/F107*100 -> 10.002297
A108: 1800012993 | B108: DR | C108: 45918 | D108: 256779417528 | E108: USD | F108: 3 | G108: INR | H108: 262.54 | I108: Outbound chgs - 01 - 15 Sep 25 | J108: 2.94 | K108: =F108 -> 3 | L108: =F108-J108 -> 0.06 | M108: =L108/F108*100 -> 2
A109: 1800013251 | B109: DR | C109: 45935 | D109: 256779417871 | E109: INR | F109: 100000 | G109: INR | H109: 100000 | I109: Fixed Storage Charges for October 2025 | J109: 1020.52 | K109: =J109/0.9 -> 1133.9111 | L109: =K109-J109 -> 113.39111 | M109: =L109/K109*100 -> 10
A110: 1800013244 | B110: DR | C110: 45935 | D110: 256779417860 | E110: USD | F110: 50 | G110: INR | H110: 4409.54 | I110: Scanning Chgs - 16 - 30 Sep 25 | J110: 49 | K110: =F110 -> 50 | L110: =F110-J110 -> 1 | M110: =L110/F110*100 -> 2
A111: 1800013774 | B111: DR | C111: 45937 | D111: 256779418342 | E111: USD | F111: 458.95 | G111: INR | H111: 40475.15 | I111: CODC Inbound chgs - 16-30 Sep 25 | J111: 449.77 | K111: =F111 -> 458.95 | L111: =F111-J111 -> 9.18 | M111: =L111/F111*100 -> 2.0002179
A112: 1800013530 | B112: DR | C112: 45937 | D112: 256779418354 | E112: USD | F112: 108.95 | G112: INR | H112: 9608.38 | I112: CODC Out chgs -16-30 Sep 25 | J112: 106.77 | K112: =F112 -> 108.95 | L112: =F112-J112 -> 2.18 | M112: =L112/F112*100 -> 2.0009179
A113: 1800013794 | B113: DR | C113: 45944 | D113: 256779418410 | E113: USD | F113: 480.02 | G113: INR | H113: 42333.33 | I113: Unit Storage - 1-30 Sept 2025 | J113: 432.01 | K113: =F113 -> 480.02 | L113: =F113-J113 -> 48.01 | M113: =L113/F113*100 -> 10.001667
A114: 1800013927 | B114: DR | C114: 45950 | D114: 256779418704 | E114: USD | F114: 2.25 | G114: INR | H114: 198.43 | I114: Outbound chgs - 01 - 15 Oct 25 | J114: 2.2 | K114: =F114 -> 2.25 | L114: =F114-J114 -> 0.05 | M114: =L114/F114*100 -> 2.2222222
A115: 1800013946 | B115: DR | C115: 45951 | D115: 256779418478 | E115: USD | F115: 27.64 | G115: INR | H115: 2437.59 | I115: VAS -1-15 Oct 2025 | J115: 27.09 | K115: =F115 -> 27.64 | L115: =F115-J115 -> 0.55 | M115: =L115/F115*100 -> 1.9898698
A116: 1800014412 | B116: DR | C116: 45964 | D116: 256779419134 | E116: USD | F116: 21.75 | G116: INR | H116: 1914.07 | I116: LCL Chgs - 16 - 31 OCT 25 | J116: 21.31 | K116: =F116 -> 21.75 | L116: =F116-J116 -> 0.44 | M116: =L116/F116*100 -> 2.0229885
A117: 1800014233 | B117: DR | C117: 45966 | D117: 256779418773 | E117: INR | F117: 100000 | G117: INR | H117: 100000 | I117: Fixed Storage Charges for November 2025 | J117: 1022.69 | K117: =J117/0.9 -> 1136.3222 | L117: =K117-J117 -> 113.63222 | M117: =L117/K117*100 -> 10
A118: 1800014284 | B118: DR | C118: 45966 | D118: 256779418821 | E118: USD | F118: 49.59 | G118: INR | H118: 4364.09 | I118: VAS-16 -31 Oct 25 | J118: 48.6 | K118: =F118 -> 49.59 | L118: =F118-J118 -> 0.99 | M118: =L118/F118*100 -> 1.9963702
A119: 1800014538 | B119: DR | C119: 45966 | D119: 256779418870 | E119: USD | F119: 493.91 | G119: INR | H119: 43465.75 | I119: Unit Storage - 1-31 Oct 2025 | J119: 444.51 | K119: =F119 -> 493.91 | L119: =F119-J119 -> 49.4 | M119: =L119/F119*100 -> 10.001822
A120: 1800014271 | B120: DR | C120: 45966 | D120: 256779418946 | E120: USD | F120: 293.04 | G120: INR | H120: 25788.51 | I120: UACU6030817 Without de-stuffing | J120: 287.18 | K120: =F120 -> 293.04 | L120: =F120-J120 -> 5.86 | M120: =L120/F120*100 -> 1.999727
A121: 1800014272 | B121: DR | C121: 45966 | D121: 256779418947 | E121: USD | F121: 293.04 | G121: INR | H121: 25788.51 | I121: GLDU9880607 Without de-stuffing | J121: 287.18 | K121: =F121 -> 293.04 | L121: =F121-J121 -> 5.86 | M121: =L121/F121*100 -> 1.999727
A122: 1800014529 | B122: DR | C122: 45966 | D122: 256779419178 | E122: USD | F122: 2.25 | G122: INR | H122: 198.01 | I122: Outbound chgs - 16 - 31 Oct 25 | J122: 2.2 | K122: =F122 -> 2.25 | L122: =F122-J122 -> 0.05 | M122: =L122/F122*100 -> 2.2222222
A123: 1800014620 | B123: DR | C123: 45966 | D123: 256779419202 | E123: USD | F123: 62.66 | G123: INR | H123: 5514.29 | I123: Empty Lolo Chgs - 01 - 31 OCT 25 | J123: 61.41 | K123: =F123 -> 62.66 | L123: =F123-J123 -> 1.25 | M123: =L123/F123*100 -> 1.9948931
A124: 1800014864 | B124: DR | C124: 45980 | D124: 256779419365 | E124: USD | F124: 292.99 | G124: INR | H124: 25784.11 | I124: MH43CE4486(ONEU1505971) Without de-stuffing Invoic | J124: 287.13 | K124: =F124 -> 292.99 | L124: =F124-J124 -> 5.86 | M124: =L124/F124*100 -> 2.0000683
A125: 1800015079 | B125: DR | C125: 45981 | D125: 256779419592 | E125: USD | F125: 17.62 | G125: INR | H125: 1550.62 | I125: LCL Chgs - 01 - 15 NOV 25 | J125: 17.27 | K125: =F125 -> 17.62 | L125: =F125-J125 -> 0.35 | M125: =L125/F125*100 -> 1.9863791
A126: 1800015134 | B126: DR | C126: 45981 | D126: 256779419633 | E126: USD | F126: 9.37 | G126: INR | H126: 824.59 | I126: Outbound chgs - 01 - 15 Nov 25 | J126: 9.18 | K126: =F126 -> 9.37 | L126: =F126-J126 -> 0.19 | M126: =L126/F126*100 -> 2.0277481
A127: 1800015482 | B127: DR | C127: 45995 | D127: 256779419966 | E127: INR | F127: 100000 | G127: INR | H127: 100000 | I127: Fixed Storage Charges for December 2025 | J127: 1014.65 | K127: =J127/0.9 -> 1127.3889 | L127: =K127-J127 -> 112.73889 | M127: =L127/K127*100 -> 10
A128: 1800015421 | B128: DR | C128: 45999 | D128: 256779419870 | E128: USD | F128: 18.96 | G128: INR | H128: 1681.75 | I128: LCL Chgs - 16 - 30 NOV 25 | J128: 18.58 | K128: =F128 -> 18.96 | L128: =F128-J128 -> 0.38 | M128: =L128/F128*100 -> 2.0042194
A129: 1800015672 | B129: DR | C129: 46024 | D129: 256779440005 | E129: USD | F129: 451.3 | G129: INR | H129: 40952.38 | I129: Unit Storage - 1-30 Nov 2025 | J129: 406.163 | K129: =F129 -> 451.3 | L129: =F129-J129 -> 45.137 | M129: =L129/F129*100 -> 10.001551
A130: 1800015986 | B130: DR | C130: 46027 | D130: 256779440070 | E130: USD | F130: 7.18 | G130: INR | H130: 651.54 | I130: CODC Out chgs -1-15 Dec 25 | J130: 7.04 | K130: =F130 -> 7.18 | L130: =F130-J130 -> 0.14 | M130: =L130/F130*100 -> 1.9498607
A131: 1800015968 | B131: DR | C131: 46027 | D131: 256779440082 | E131: USD | F131: 2.25 | G131: INR | H131: 204.17 | I131: Outbound chgs - 01 - 15 Dec 25 | J131: 2.2 | K131: =F131 -> 2.25 | L131: =F131-J131 -> 0.05 | M131: =L131/F131*100 -> 2.2222222
A132: 1800016055 | B132: DR | C132: 46027 | D132: 256779440102 | E132: USD | F132: 20.39 | G132: INR | H132: 1850.25 | I132: VAS DEC 25 -1-15 | J132: 19.98 | K132: =F132 -> 20.39 | L132: =F132-J132 -> 0.41 | M132: =L132/F132*100 -> 2.0107896
A133: 1800016090 | B133: DR | C133: 46027 | D133: 256779440119 | E133: USD | F133: 17.25 | G133: INR | H133: 1565.32 | I133: LCL Chgs - 01 - 15 DEC 25 | J133: 16.9 | K133: =F133 -> 17.25 | L133: =F133-J133 -> 0.35 | M133: =L133/F133*100 -> 2.0289855
A134: 1800016346 | B134: DR | C134: 46028 | D134: 256779440236 | E134: USD | F134: 505.23 | G134: INR | H134: 45846.16 | I134: Unit Storage - 1-31 DEC 2025 | J134: 454.71 | K134: =F134 -> 505.23 | L134: =F134-J134 -> 50.52 | M134: =L134/F134*100 -> 9.9994062
A135: 1800016543 | B135: DR | C135: 46028 | D135: 256779440305 | E135: INR | F135: 100000 | G135: INR | H135: 100000 | I135: Fixed Storage Charges for January 2026 | J135: 991.81 | K135: =J135/0.9 -> 1102.0111 | L135: =K135-J135 -> 110.20111 | M135: =L135/K135*100 -> 10
A136: 1800017111 | B136: DR | C136: 46045 | D136: 256779440431 | E136: USD | F136: 3 | G136: INR | H136: 272.23 | I136: Outbound chgs - 01 - 15 JAN 26 | J136: 2.94 | K136: =F136 -> 3 | L136: =F136-J136 -> 0.06 | M136: =L136/F136*100 -> 2
A137: 1800014270 | B137: DR | C137: 45966 | D137: 256779418945 | E137: USD | F137: 293.04 | G137: INR | H137: 25788.51 | J137: =VLOOKUP(D137,'Customer Data'!$B$2:$F$149,4,0) -> 287.18 | K137: =F137 -> 293.04 | L137: =F137-J137 -> 5.86 | M137: =L137/F137*100 -> 1.999727
A138: 1600002430 | B138: DG | C138: 45943 | D138: 256779421974 | E138: USD | F138: -435.91 | G138: INR | H138: -38443.24 | I138: CN issued against 246779410865 | J138: -392.32 | K138: =F138 -> -435.91 | L138: -43.59 | M138: 9.9997706
A139: 1600002431 | B139: DG | C139: 45943 | D139: 256779421975 | E139: USD | F139: -447.05 | G139: INR | H139: -39425.68 | I139: CN issued against 246779410888 | J139: -402.34 | K139: =F139 -> -447.05 | L139: -44.71 | M139: 10.001118
A140: 1600002432 | B140: DG | C140: 45943 | D140: 256779421976 | E140: USD | F140: -111.25 | G140: INR | H140: -9811.22 | I140: CN issued against 246779410368 | J140: -100.12 | K140: =F140 -> -111.25 | L140: -11.13 | M140: 10.004494
A141: 1600002433 | B141: DG | C141: 45943 | D141: 256779421977 | E141: USD | F141: -376.4 | G141: INR | H141: -33195.01 | I141: CN issued against 246779410394 | J141: -338.76 | K141: =F141 -> -376.4 | L141: -37.64 | M141: 10
A142: 1600002434 | B142: DG | C142: 45943 | D142: 256779421978 | E142: USD | F142: -391.55 | G142: INR | H142: -34531.1 | I142: CN issued against 246779410418 | J142: -352.39 | K142: =F142 -> -391.55 | L142: -39.16 | M142: 10.001277
A143: 1600002738 | B143: DG | C143: 46035 | D143: 256779422208 | E143: USD | F143: -23.92 | G143: INR | H143: -2170.58 | I143: CN issued against - 256779412113 | J143: -21.53 | K143: =F143 -> -23.92 | L143: -2.39 | M143: 9.9916388
A144: 1600002739 | B144: DG | C144: 46035 | D144: 256779422209 | E144: USD | F144: -45.63 | G144: INR | H144: -4140.61 | I144: CN issued against - 256779413893 | J144: -41.07 | K144: =F144 -> -45.63 | L144: -4.56 | M144: 9.9934254
A145: 1600002741 | B145: DG | C145: 46035 | D145: 256779422211 | E145: USD | F145: -21.96 | G145: INR | H145: -1992.72 | I145: CN issued against - 256779417077 | J145: -19.76 | K145: =F145 -> -21.96 | L145: -2.2 | M145: 10.018215
L146: =SUM(L3:L145) -> 3289.0659

Sheet Ascendus data working
A1: Document Number | B1: Ref | C1: Document Type | D1: Document Date | E1: Document Currency Key | F1: Document Currency Value | G1: Company Code Currency Key | H1: Company Code Currency Value | I1: Text | K1: Ref | L1: Document Type | M1: Sum of Document Currency Value
A2: 1800000035 | B2: 246779410007 | C2: DR | D2: 45708 | E2: USD | F2: 1190.48 | G2: INR | H2: 102742.78 | I2: Fixed Rental charges for Aug 2024 | K2: 2166093 | L2: DZ | M2: -10691.42
A3: 1800000079 | B3: 246779410274 | C3: DR | D3: 45708 | E3: USD | F3: 1190.48 | G3: INR | H3: 102742.78 | I3: Fixed Rental charges for Oct 2024 | K3: 246779410007 | L3: DR | M3: 1190.48
A4: 1800000099 | B4: 246779410027 | C4: DR | D4: 45708 | E4: USD | F4: 1190.48 | G4: INR | H4: 102742.78 | I4: Fixed Rental charges for Sept 2024 | K4: 246779410027 | L4: DR | M4: 1190.48
A5: 1800000168 | B5: 246779410095 | C5: DR | D5: 45708 | E5: USD | F5: 1190.48 | G5: INR | H5: 102742.78 | I5: Fixed Rental charges for Nov 2024 | K5: 246779410095 | L5: DR | M5: 1190.48
A6: 1800000211 | B6: 246779410138 | C6: DR | D6: 45708 | E6: USD | F6: 1190.48 | G6: INR | H6: 102742.78 | I6: Fixed Rental charges for Dec 2024 | K6: 246779410138 | L6: DR | M6: 1190.48
A7: 1800000254 | B7: 246779410181 | C7: DR | D7: 45708 | E7: USD | F7: 1166.59 | G7: INR | H7: 100680.99 | I7: Fixed Rental charges for Jan 2025 | K7: 246779410181 | L7: DR | M7: 1166.59
A8: 1800000297 | B8: 246779410224 | C8: DR | D8: 45708 | E8: USD | F8: 1143.12 | G8: INR | H8: 98655.44 | I8: Fixed Rental charges for Feb 2025 | K8: 246779410224 | L8: DR | M8: 1143.12
A9: 1800000406 | B9: 246779410368 | C9: DR | D9: 45719 | E9: USD | F9: 356.43 | G9: INR | H9: 30899.37 | I9: Storage Charges for the month of August, 2024 | K9: 246779410274 | L9: DR | M9: 1190.48
A10: 1800000675 | B10: 246779410615 | C10: DR | D10: 45719 | E10: USD | F10: 9 | G10: INR | H10: 780.22 | I10: Outbound Handling for Sep 2024 | K10: 246779410368 | L10: DR | M10: 356.43
A11: 1800000432 | B11: 246779410394 | C11: DR | D11: 45719 | E11: USD | F11: 505.86 | G11: INR | H11: 43853.64 | I11: Storage for the month of Sep 2024 Exch Rate 83.79 | K11: 246779410394 | L11: DR | M11: 505.86
A12: 1800000456 | B12: 246779410418 | C12: DR | D12: 45719 | E12: USD | F12: 562.6 | G12: INR | H12: 48772.5 | I12: Storage for the month of Oct 2024 | K12: 246779410418 | L12: DR | M12: 562.6
A13: 1800000559 | B13: 246779410509 | C13: DR | D13: 45719 | E13: USD | F13: 29.25 | G13: INR | H13: 2535.72 | I13: Outbound Handling for Aug 2024 | K13: 246779410509 | L13: DR | M13: 29.25
... A116: 1800011012 | B116: 256779415772 | C116: DR | D116: 45857 | E116: USD | F116: 59.43 | G116: INR | H116: 5111.02 | I116: VAS - 1-15 July 25 | K116: 256779416446 | L116: DR | M116: 2.28
A117: 1400000797 | C117: DY | D117: 45861 | E117: INR | F117: 198636.61 | G117: INR | H117: 200764.2 | K117: 256779416604 | L117: DR | M117: 17.31
A118: 1400000797 | C118: DY | D118: 45861 | E118: INR | F118: -198636.61 | G118: INR | H118: -200764.2 | K118: 256779416616 | L118: DR | M118: 63.65
A119: 1400000805 | C119: DZ | D119: 45862 | E119: USD | F119: -8262.11 | G119: INR | H119: -713050.33 | I119: 0105357143FC | K119: 256779416847 | L119: DR | M119: 27.83
A120: 1600001882 | B120: 256779421502 | C120: DG | D120: 45862 | E120: USD | F120: -1190.48 | G120: INR | H120: -102382.08 | I120: Credit note raised against 256779414435 | K120: 256779416882 | L120: DR | M120: 12.83
A121: 1800011358 | B121: 256779416024 | C121: DR | D121: 45870 | E121: USD | F121: 1162.7907 | G121: INR | H121: 100000 | I121: Fixed Storage Charges for August 2025 | K121: 256779416912 | L121: DR | M121: 44.96
A122: 1600002012 | B122: 256779421588 | C122: DG | D122: 45873 | E122: USD | F122: -17.25 | G122: INR | H122: -1483.51 | I122: Credit note raised against 256779415490 | K122: 256779416949 | L122: DR | M122: 30.16
A123: 1600002057 | B123: 256779421633 | C123: DG | D123: 45873 | E123: USD | F123: -17.25 | G123: INR | H123: -1483.51 | I123: Credit note raised against 256779415805 | K123: 256779417077 | L123: DR | M123: 565.97
A124: 1600002062 | B124: 256779421638 | C124: DG | D124: 45873 | E124: USD | F124: -17.25 | G124: INR | H124: -1483.51 | I124: Credit note raised against 256779415810 | K124: 256779417136 | L124: DR | M124: 1.71
A125: 1800011652 | B125: 256779416082 | C125: DR | D125: 45877 | E125: USD | F125: 759.67 | G125: INR | H125: 65354.5 | I125: Unit Storage - 1-31 July 25 | K125: 256779417162 | L125: DR | M125: 44.74
A126: 1800011791 | B126: 256779416182 | C126: DR | D126: 45877 | E126: USD | F126: 18 | G126: INR | H126: 1548.54 | I126: LCL chgs - 16 - 31 JUL 25 | K126: 256779417328 | L126: DR | M126: 2.25
A127: 1800011710 | B127: 256779416228 | C127: DR | D127: 45877 | E127: USD | F127: 3 | G127: INR | H127: 258.09 | I127: Outbound chgs - 16 - 31 Jul 25 | K127: 256779417344 | L127: DR | M127: 1142.8571
A128: 1800011396 | B128: 256779416246 | C128: DR | D128: 45877 | E128: USD | F128: 70.95 | G128: INR | H128: 6103.84 | I128: CODC LCL Chgs - 16 - 31 Jul 25 | K128: 256779417528 | L128: DR | M128: 3
A129: 1800011407 | B129: 256779416257 | C129: DR | D129: 45877 | E129: USD | F129: 22.87 | G129: INR | H129: 1967.51 | I129: CODC Out chgs - 16 - 31 Jul 25 | K129: 256779417860 | L129: DR | M129: 50
A130: 1800011596 | B130: 256779416446 | C130: DR | D130: 45877 | E130: USD | F130: 2.28 | G130: INR | H130: 196.15 | I130: VAS 16-31 July 25 | K130: 256779417871 | L130: DR | M130: 1136.3636
A131: 1800012069 | B131: 256779416604 | C131: DR | D131: 45889 | E131: USD | F131: 17.31 | G131: INR | H131: 1489.18 | I131: CODC LCL Chgs - 1-15 Aug 25 | K131: 256779418012 | L131: DR | M131: 480.02
... A134: 1800012220 | B134: 256779416882 | C134: DR | D134: 45889 | E134: USD | F134: 12.83 | G134: INR | H134: 1103.77 | I134: Outbound chgs - 01 - 15 Aug 25 | K134: 256779418354 | L134: DR | M134: 108.95
A135: 1400001003 | C135: DZ | D135: 45891 | E135: USD | F135: -4582.99 | G135: INR | H135: -394140.21 | K135: 256779418401 | L135: DR | M135: 62.52
A136: 1400001107 | C136: DY | D136: 45902 | E136: INR | F136: 104184.06 | G136: INR | H136: 102382.08 | K136: 256779418410 | L136: DR | M136: 480.02
A137: 1400001107 | C137: DY | D137: 45902 | E137: INR | F137: -104184.06 | G137: INR | H137: -101775.06 | K137: 256779418440 | L137: DR | M137: 246.92
A138: 1800012710 | B138: 256779417344 | C138: DR | D138: 45904 | E138: USD | F138: 1142.8571 | G138: INR | H138: 100000 | I138: Fixed Storage Charges for September 2025 | K138: 256779418478 | L138: DR | M138: 27.64
A139: 1800012276 | B139: 256779416912 | C139: DR | D139: 45904 | E139: USD | F139: 44.96 | G139: INR | H139: 3934.64 | I139: CODC LCL Chgs - 16-31 Aug 25 | K139: 256779418493 | L139: DR | M139: 27.64
A140: 1800012287 | B140: 256779416949 | C140: DR | D140: 45904 | E140: USD | F140: 30.16 | G140: INR | H140: 2639.43 | I140: CODC Out chgs -16-31 Aug 25 | K140: 256779418704 | L140: DR | M140: 2.25
A141: 1800012532 | B141: 256779417136 | C141: DR | D141: 45904 | E141: USD | F141: 1.71 | G141: INR | H141: 149.65 | I141: VAS - 16-31 Aug 25 | K141: 256779418773 | L141: DR | M141: 1136.3636
A142: 1800012462 | B142: 256779417162 | C142: DR | D142: 45904 | E142: USD | F142: 44.74 | G142: INR | H142: 3915.39 | I142: VAS -16-31 Aug 25 | K142: 256779418821 | L142: DR | M142: 49.59
A143: 1800012688 | B143: 256779417328 | C143: DR | D143: 45904 | E143: USD | F143: 2.25 | G143: INR | H143: 196.91 | I143: Outbound chgs - 16 - 31 Aug 25 | K143: 256779418827 | L143: DR | M143: 60.86
A144: 1800012469 | B144: 256779417077 | C144: DR | D144: 45906 | E144: USD | F144: 565.97 | G144: INR | H144: 49530.49 | I144: Unit-Storage-1-31 Aug 25 | K144: 256779418870 | L144: DR | M144: 493.91
A145: 1800012993 | B145: 256779417528 | C145: DR | D145: 45918 | E145: USD | F145: 3 | G145: INR | H145: 262.54 | I145: Outbound chgs - 01 - 15 Sep 25 | K145: 256779418945 | L145: DR | M145: 293.04
A146: 1800013251 | B146: 256779417871 | C146: DR | D146: 45935 | E146: USD | F146: 1133.9111 | G146: INR | H146: 100000 | I146: Fixed Storage Charges for October 2025 | K146: 256779418946 | L146: DR | M146: 293.04
A147: 1800013244 | B147: 256779417860 | C147: DR | D147: 45935 | E147: USD | F147: 50 | G147: INR | H147: 4409.54 | I147: Scanning Chgs - 16 - 30 Sep 25 | K147: 256779418947 | L147: DR | M147: 293.04
A148: 1800013511 | B148: 256779418401 | C148: DR | D148: 45935 | E148: USD | F148: 62.52 | G148: INR | H148: 5513.69 | I148: PORT SSR Chgs Sep 25 | K148: 256779419134 | L148: DR | M148: 21.75
A149: 1800013276 | B149: 256779418012 | C149: DR | D149: 45936 | E149: USD | F149: 480.02 | G149: INR | H149: 42333.33 | I149: Unit Storage - 1-30 Sept 2025 | K149: 256779419178 | L149: DR | M149: 2.25
... A163: 1800013963 | B163: 256779418493 | C163: DR | D163: 45951 | E163: USD | F163: 27.64 | G163: INR | H163: 2437.59 | I163: VAS -1-15 Oct 2025 | K163: 256779420523 | L163: DG | M163: -1143.12
A164: 1400001512 | C164: DZ | D164: 45955 | E164: USD | F164: -4875.15 | G164: INR | H164: -429943.23 | K164: 256779421502 | L164: DG | M164: -1190.48
A165: 1600002510 | B165: 256779422046 | C165: DG | D165: 45958 | E165: USD | F165: -246.92 | G165: INR | H165: -21776.06 | I165: CN issued against 256779418440 | K165: 256779421588 | L165: DG | M165: -17.25
A166: 1800014412 | B166: 256779419134 | C166: DR | D166: 45964 | E166: USD | F166: 21.75 | G166: INR | H166: 1914.07 | I166: LCL Chgs - 16 - 31 OCT 25 | K166: 256779421633 | L166: DG | M166: -17.25
A167: 1800014233 | B167: 256779418773 | C167: DR | D167: 45966 | E167: USD | F167: 1136.3636 | G167: INR | H167: 100000 | I167: Fixed Storage Charges for November 2025 | K167: 256779421638 | L167: DG | M167: -17.25
A168: 1800014284 | B168: 256779418821 | C168: DR | D168: 45966 | E168: USD | F168: 49.59 | G168: INR | H168: 4364.09 | I168: VAS-16 -31 Oct 25 | K168: 256779421974 | L168: DG | M168: -435.91
A169: 1800014290 | B169: 256779418827 | C169: DR | D169: 45966 | E169: USD | F169: 60.86 | G169: INR | H169: 5355.89 | I169: WEIGHTMENT-16 -31 Oct 25 | K169: 256779421975 | L169: DG | M169: -447.05
A170: 1800014538 | B170: 256779418870 | C170: DR | D170: 45966 | E170: USD | F170: 493.91 | G170: INR | H170: 43465.75 | I170: Unit Storage - 1-31 Oct 2025 | K170: 256779421976 | L170: DG | M170: -111.25
A171: 1800014270 | B171: 256779418945 | C171: DR | D171: 45966 | E171: USD | F171: 293.04 | G171: INR | H171: 25788.51 | I171: ONEU5912276 Without de-stuffing | K171: 256779421977 | L171: DG | M171: -376.4
A172: 1800014271 | B172: 256779418946 | C172: DR | D172: 45966 | E172: USD | F172: 293.04 | G172: INR | H172: 25788.51 | I172: UACU6030817 Without de-stuffing | K172: 256779421978 | L172: DG | M172: -391.55
A173: 1800014272 | B173: 256779418947 | C173: DR | D173: 45966 | E173: USD | F173: 293.04 | G173: INR | H173: 25788.51 | I173: GLDU9880607 Without de-stuffing | K173: 256779421982 | L173: DG | M173: -480.02
A174: 1800014529 | B174: 256779419178 | C174: DR | D174: 45966 | E174: USD | F174: 2.25 | G174: INR | H174: 198.01 | I174: Outbound chgs - 16 - 31 Oct 25 | K174: 256779422046 | L174: DG | M174: -246.92
A175: 1800014620 | B175: 256779419202 | C175: DR | D175: 45966 | E175: USD | F175: 62.66 | G175: INR | H175: 5514.29 | I175: Empty Lolo Chgs - 01 - 31 OCT 25 | K175: 256779422156 | L175: DG | M175: -59.62
A176: 1400001904 | B176: KNOCK OFF ENTRY | C176: DY | D176: 45976 | E176: USD | F176: 0 | G176: INR | H176: 0 | K176: 256779422157 | L176: DG | M176: -49.33
A177: 1400001905 | B177: KNOCK OFF ENTRY | C177: DY | D177: 45976 | E177: USD | F177: 879.2 | G177: INR | H177: 77537.33 | K177: 256779422168 | L177: DG | M177: -27.64
A178: 1400001905 | B178: KNOCK OFF ENTRY | C178: DY | D178: 45976 | E178: USD | F178: -111.25 | G178: INR | H178: -9790.38 | K178: 256779422208 | L178: DG | M178: -23.92
A179: 1400001905 | B179: KNOCK OFF ENTRY | C179: DY | D179: 45976 | E179: USD | F179: -376.4 | G179: INR | H179: -33124.48 | K179: 256779422209 | L179: DG | M179: -45.63
A180: 1400001905 | B180: KNOCK OFF ENTRY | C180: DY | D180: 45976 | E180: USD | F180: -391.55 | G180: INR | H180: -34457.73 | K180: 256779422210 | L180: DG | M180: -22.64
A181: 1800014864 | B181: 256779419365 | C181: DR | D181: 45980 | E181: USD | F181: 292.99 | G181: INR | H181: 25784.11 | I181: MH43CE4486(ONEU1505971) Without de-stuffing Invoic | K181: 256779422211 | L181: DG | M181: -21.96
A182: 1800015079 | B182: 256779419592 | C182: DR | D182: 45981 | E182: USD | F182: 17.62 | G182: INR | H182: 1550.62 | I182: LCL Chgs - 01 - 15 NOV 25 | K182: 256779440005 | L182: DR | M182: 451.3
A183: 1800015134 | B183: 256779419633 | C183: DR | D183: 45981 | E183: USD | F183: 9.37 | G183: INR | H183: 824.59 | I183: Outbound chgs - 01 - 15 Nov 25 | K183: 256779440070 | L183: DR | M183: 7.18
A184: 1800015482 | B184: 256779419966 | C184: DR | D184: 45995 | E184: USD | F184: 1127.3889 | G184: INR | H184: 100000 | I184: Fixed Storage Charges for December 2025 | K184: 256779440082 | L184: DR | M184: 2.25
A185: 1800015421 | B185: 256779419870 | C185: DR | D185: 45999 | E185: USD | F185: 18.96 | G185: INR | H185: 1681.75 | I185: LCL Chgs - 16 - 30 NOV 25 | K185: 256779440102 | L185: DR | M185: 20.39
A186: 1800015672 | B186: 256779440005 | C186: DR | D186: 46024 | E186: USD | F186: 451.3 | G186: INR | H186: 40952.38 | I186: Unit Storage - 1-30 Nov 2025 | K186: 256779440119 | L186: DR | M186: 17.25
A187: 1600002686 | B187: 256779422156 | C187: DG | D187: 46027 | E187: USD | F187: -59.62 | G187: INR | H187: -5410.11 | I187: Credit note for Duplicate invoice -256779418354 | K187: 256779440236 | L187: DR | M187: 505.23
A188: 1600002687 | B188: 256779422157 | C188: DG | D188: 46027 | E188: USD | F188: -49.33 | G188: INR | H188: -4476.36 | I188: Credit note for Duplicate invoice -256779418354 | K188: 256779440305 | L188: DR | M188: 1098.9011
A189: 1600002698 | B189: 256779422168 | C189: DG | D189: 46027 | E189: USD | F189: -27.64 | G189: INR | H189: -2508.14 | I189: Credit note for Duplicate invoice -256779418493 | K189: 256779440431 | L189: DR | M189: 3
A190: 1800015986 | B190: 256779440070 | C190: DR | D190: 46027 | E190: USD | F190: 7.18 | G190: INR | H190: 651.54 | I190: CODC Out chgs -1-15 Dec 25
A191: 1800015968 | B191: 256779440082 | C191: DR | D191: 46027 | E191: USD | F191: 2.25 | G191: INR | H191: 204.17 | I191: Outbound chgs - 01 - 15 Dec 25
A192: 1800016055 | B192: 256779440102 | C192: DR | D192: 46027 | E192: USD | F192: 20.39 | G192: INR | H192: 1850.25 | I192: VAS DEC 25 -1-15
A193: 1800016090 | B193: 256779440119 | C193: DR | D193: 46027 | E193: USD | F193: 17.25 | G193: INR | H193: 1565.32 | I193: LCL Chgs - 01 - 15 DEC 25
A194: 1800016346 | B194: 256779440236 | C194: DR | D194: 46028 | E194: USD | F194: 505.23 | G194: INR | H194: 45846.16 | I194: Unit Storage - 1-31 DEC 2025
A195: 1800016543 | B195: 256779440305 | C195: DR | D195: 46028 | E195: USD | F195: 1102.0111 | G195: INR | H195: 100000 | I195: Fixed Storage Charges for January 2026
A196: 1600002738 | B196: 256779422208 | C196: DG | D196: 46035 | E196: USD | F196: -23.92 | G196: INR | H196: -2170.58 | I196: CN issued against - 256779412113
A197: 1600002739 | B197: 256779422209 | C197: DG | D197: 46035 | E197: USD | F197: -45.63 | G197: INR | H197: -4140.61 | I197: CN issued against - 256779413893
A198: 1600002740 | B198: 256779422210 | C198: DG | D198: 46035 | E198: USD | F198: -22.64 | G198: INR | H198: -2054.42 | I198: CN issued against - 256779414234
A199: 1600002741 | B199: 256779422211 | C199: DG | D199: 46035 | E199: USD | F199: -21.96 | G199: INR | H199: -1992.72 | I199: CN issued against - 256779417077
A200: 1800017111 | B200: 256779440431 | C200: DR | D200: 46045 | E200: USD | F200: 3 | G200: INR | H200: 272.23 | I200: Outbound chgs - 01 - 15 JAN 26
A201: 1400002558 | B201: 2166093 | C201: DZ | D201: 46050 | E201: USD | F201: -10691.42 | G201: INR | H201: -970173.02
F202: =SUM(F2:F201) -> 8974.5146

Sheet Ascendus Data
O1: =SUBTOTAL(9,O3:O202) -> 90064.44 | Q1: =SUBTOTAL(9,Q3:Q202) -> -801583.91 | AH1: =SUBTOTAL(9,AH3:AH202) -> -9.15
A2: Customer | B2: Customer Account: Name 1 | C2: Posting Date | D2: Document Number | E2: Document Type | F2: Document Date | G2: Entry Date | H2: Document Header Text | I2: Reference | J2: G/L Account | K2: G/L Account: Short Text | L2: Special G/L Ind. | M2: Posting Key | N2: Document Currency Key | O2: Document Currency Value | P2: Company Code Currency Key | Q2: Company Code Currency Value | T2: Tax Code | U2: Profit Center | V2: Trading Partner No. | W2: Assignment | X2: Item | Y2: Text | Z2: Reference Key 1 | AA2: Reference Key 2 | AB2: Reference Key 3 | AC2: Baseline Payment Dte | AD2: Clearing Date | AE2: Clearing Document | AF2: Text | AG2: Vlookup
A3: 100222345 | B3: SIDDHARTHA LOGISTICS FTWZ PRIVATE | C3: 45902 | D3: 1400001107 | E3: DY | F3: 45902 | G3: 45902 | J3: 212100 | K3: Trade Debtors (Ctrl) | M3: 08 | N3: INR | O3: 104184.06 | P3: INR | Q3: 102382.08 | U3: 6779224500 | X3: 1 | AC3: 45902 | AD3: 45902 | AE3: 1400001107 | AG3: =VLOOKUP(I3,'Customer Data'!$B$2:$F$149,4,0) -> #N/A
A4: 100222345 | B4: SIDDHARTHA LOGISTICS FTWZ PRIVATE | C4: 45902 | D4: 1400001107 | E4: DY | F4: 45902 | G4: 45902 | J4: 212100 | K4: Trade Debtors (Ctrl) | M4: 15 | N4: INR | O4: -104184.06 | P4: INR | Q4: -101775.06 | U4: 6779224500 | X4: 2 | AC4: 45902 | AD4: 45902 | AE4: 1400001107 | AG4: =VLOOKUP(I4,'Customer Data'!$B$2:$F$149,4,0) -> #N/A
A5: 100222345 | B5: SIDDHARTHA LOGISTICS FTWZ PRIVATE | C5: 45861 | D5: 1400000797 | E5: DY | F5: 45861 | G5: 45861 | J5: 212100 | K5: Trade Debtors (Ctrl) | M5: 08 | N5: INR | O5: 198636.61 | P5: INR | Q5: 200764.2 | U5: 6779224500 | X5: 1 | AC5: 45861 | AD5: 45861 | AE5: 1400000797 | AG5: =VLOOKUP(I5,'Customer Data'!$B$2:$F$149,4,0) -> #N/A
A6: 100222345 | B6: SIDDHARTHA LOGISTICS FTWZ PRIVATE | C6: 45861 | D6: 1400000797 | E6: DY | F6: 45861 | G6: 45861 | J6: 212100 | K6: Trade Debtors (Ctrl) | M6: 15 | N6: INR | O6: -198636.61 | P6: INR | Q6: -200764.2 | U6: 6779224500 | X6: 2 | AC6: 45861 | AD6: 45861 | AE6: 1400000797 | AG6: =VLOOKUP(I6,'Customer Data'!$B$2:$F$149,4,0) -> #N/A
A7: 100222345 | B7: SIDDHARTHA LOGISTICS FTWZ PRIVATE | C7: 45891 | D7: 1400001003 | E7: DZ | F7: 45891 | G7: 45891 | H7: 0099542199FC | J7: 212100 | K7: Trade Debtors (Ctrl) | M7: 15 | N7: USD | O7: -4582.99 | P7: INR | Q7: -394140.21 | U7: 6779220000 | X7: 2 | AC7: 45891 | AG7: =VLOOKUP(I7,'Customer Data'!$B$2:$F$149,4,0) -> #N/A
A8: 100222345 | B8: SIDDHARTHA LOGISTICS FTWZ PRIVATE | C8: 45862 | D8: 1400000805 | E8: DZ | F8: 45862 | G8: 45862 | H8: 0105357143FC | J8: 212100 | K8: Trade Debtors (Ctrl) | M8: 15 | N8: USD | O8: -8262.11 | P8: INR | Q8: -713050.33 | U8: 6779224500 | X8: 3 | Y8: 0105357143FC | AC8: 45862 | AD8: 45862 | AE8: 1400000805 | AG8: =VLOOKUP(I8,'Customer Data'!$B$2:$F$149,4,0) -> #N/A
A9: 100222345 | B9: SIDDHARTHA LOGISTICS FTWZ PRIVATE | C9: 45955 | D9: 1400001512 | E9: DZ | F9: 45955 | G9: 45955 | H9: T54SWIC277314 | J9: 212100 | K9: Trade Debtors (Ctrl) | M9: 15 | N9: USD | O9: -4875.15 | P9: INR | Q9: -429943.23 | U9: 6779220000 | X9: 2 | AC9: 45955 | AG9: =VLOOKUP(I9,'Customer Data'!$B$2:$F$149,4,0) -> #N/A
A10: 100222345 | B10: SIDDHARTHA LOGISTICS FTWZ PRIVATE | C10: 45976 | D10: 1400001904 | E10: DY | F10: 45976 | G10: 45976 | H10: NA | I10: KNOCK OFF ENTRY | J10: 212100 | K10: Trade Debtors (Ctrl) | M10: 08 | N10: USD | O10: 0 | P10: INR | Q10: 0 | U10: 6779224500 | X10: 1 | AC10: 45976 | AD10: 45976 | AE10: 1400001904 | AG10: =VLOOKUP(I10,'Customer Data'!$B$2:$F$149,4,0) -> #N/A
A11: 100222345 | B11: SIDDHARTHA LOGISTICS FTWZ PRIVATE | C11: 45976 | D11: 1400001905 | E11: DY | F11: 45976 | G11: 45976 | H11: NA | I11: KNOCK OFF ENTRY | J11: 212100 | K11: Trade Debtors (Ctrl) | M11: 08 | N11: USD | O11: 879.2 | P11: INR | Q11: 77537.33 | U11: 6779224500 | X11: 4 | AC11: 45976 | AD11: 45976 | AE11: 1400001905 | AG11: =VLOOKUP(I11,'Customer Data'!$B$2:$F$149,4,0) -> #N/A
A12: 100222345 | B12: SIDDHARTHA LOGISTICS FTWZ PRIVATE | C12: 45976 | D12: 1400001905 | E12: DY | F12: 45976 | G12: 45976 | H12: NA | I12: KNOCK OFF ENTRY | J12: 212100 | K12: Trade Debtors (Ctrl) | M12: 15 | N12: USD | O12: -111.25 | P12: INR | Q12: -9790.38 | U12: 6779224500 | W12: NA | X12: 1 | AC12: 45976 | AG12: =VLOOKUP(I12,'Customer Data'!$B$2:$F$149,4,0) -> #N/A
A13: 100222345 | B13: SIDDHARTHA LOGISTICS FTWZ PRIVATE | C13: 45976 | D13: 1400001905 | E13: DY | F13: 45976 | G13: 45976 | H13: NA | I13: KNOCK OFF ENTRY | J13: 212100 | K13: Trade Debtors (Ctrl) | M13: 15 | N13: USD | O13: -376.4 | P13: INR | Q13: -33124.48 | U13: 6779224500 | W13: NA | X13: 2 | AC13: 45976 | AG13: =VLOOKUP(I13,'Customer Data'!$B$2:$F$149,4,0) -> #N/A
A14: 100222345 | B14: SIDDHARTHA LOGISTICS FTWZ PRIVATE | C14: 45976 | D14: 1400001905 | E14: DY | F14: 45976 | G14: 45976 | H14: NA | I14: KNOCK OFF ENTRY | J14: 212100 | K14: Trade Debtors (Ctrl) | M14: 15 | N14: USD | O14: -391.55 | P14: INR | Q14: -34457.73 | U14: 6779224500 | W14: NA | X14: 3 | AC14: 45976 | AG14: =VLOOKUP(I14,'Customer Data'!$B$2:$F$149,4,0) -> #N/A
A15: 100222345 | B15: SIDDHARTHA LOGISTICS FTWZ PRIVATE | C15: 45787 | D15: 1800008258 | E15: DR | F15: 45787 | G15: 45791 | H15: NA | I15: 256779413142 | J15: 212100 | K15: Trade Debtors (Ctrl) | M15: 01 | N15: INR | O15: 100000 | P15: INR | Q15: 100000 | T15: O0 | U15: 6779224500 | W15: NA | X15: 1 | Y15: Fixed Storage Charges fo MAY 2025 | AC15: 45787 | AG15: =VLOOKUP(I15,'Customer Data'!$B$2:$F$149,4,0) -> 1046.71
A16: 100222345 | B16: SIDDHARTHA LOGISTICS FTWZ PRIVATE | C16: 45818 | D16: 1800009590 | E16: DR | F16: 45818 | G16: 45825 | H16: NA | I16: 256779414354 | J16: 212100 | K16: Trade Debtors (Ctrl) | M16: 01 | N16: INR | O16: 100000 | P16: INR | Q16: 100000 | T16: O0 | U16: 6779224500 | W16: NA | X16: 1 | Y16: Fixed Storage Charges fo JUNE 2025 | AC16: 45818 | AG16: =VLOOKUP(I16,'Customer Data'!$B$2:$F$149,4,0) -> 1052.75
A17: 100222345 | B17: SIDDHARTHA LOGISTICS FTWZ PRIVATE | C17: 45842 | D17: 1800010152 | E17: DR | F17: 45842 | G17: 45847 | H17: NA | I17: 256779414912 | J17: 212100 | K17: Trade Debtors (Ctrl) | M17: 01 | N17: INR | O17: 100000 | P17: INR | Q17: 100000 | T17: O0 | U17: 6779224500 | W17: NA | X17: 1 | Y17: Fixed Storage Charges fo JULY 2025 | AC17: 45842 | AG17: =VLOOKUP(I17,'Customer Data'!$B$2:$F$149,4,0) -> 1046.5
A18: 100222345 | B18: SIDDHARTHA LOGISTICS FTWZ PRIVATE | C18: 45870 | D18: 1800011358 | E18: DR | F18: 45870 | G18: 45873 | H18: NA | I18: 256779416024 | J18: 212100 | K18: Trade Debtors (Ctrl) | M18: 01 | N18: INR | O18: 100000 | P18: INR | Q18: 100000 | T18: O0 | U18: 6779224500 | W18: NA | X18: 1 | Y18: Fixed Storage Charges for August 2025 | AC18: 45870 | AG18: =VLOOKUP(I18,'Customer Data'!$B$2:$F$149,4,0) -> 1046.14
A19: 100222345 | B19: SIDDHARTHA LOGISTICS FTWZ PRIVATE | C19: 45904 | D19: 1800012710 | E19: DR | F19: 45904 | G19: 45909 | H19: NA | I19: 256779417344 | J19: 212100 | K19: Trade Debtors (Ctrl) | M19: 01 | N19: INR | O19: 100000 | P19: INR | Q19: 100000 | T19: O0 | U19: 6779224500 | W19: 2097261 | X19: 1 | Y19: Fixed Storage Charges for September 2025 | AC19: 45904 | AG19: =VLOOKUP(I19,'Customer Data'!$B$2:$F$149,4,0) -> 1028.4
A20: 100222345 | B20: SIDDHARTHA LOGISTICS FTWZ PRIVATE | C20: 45935 | D20: 1800013251 | E20: DR | F20: 45935 | G20: 45937 | H20: NA | I20: 256779417871 | J20: 212100 | K20: Trade Debtors (Ctrl) | M20: 01 | N20: INR | O20: 100000 | P20: INR | Q20: 100000 | T20: O0 | U20: 6779224500 | W20: 2110507 | X20: 1 | Y20: Fixed Storage Charges for October 2025 | AC20: 45935 | AG20: =VLOOKUP(I20,'Customer Data'!$B$2:$F$149,4,0) -> 1020.52
A21: 100222345 | B21: SIDDHARTHA LOGISTICS FTWZ PRIVATE | C21: 45966 | D21: 1800014233 | E21: DR | F21: 45966 | G21: 45966 | H21: NA | I21: 256779418773 | J21: 212100 | K21: Trade Debtors (Ctrl) | M21: 01 | N21: INR | O21: 100000 | P21: INR | Q21: 100000 | T21: O0 | U21: 6779224500 | W21: 2123158 | X21: 1 | Y21: Fixed Storage Charges for November 2025 | AC21: 45966 | AG21: =VLOOKUP(I21,'Customer Data'!$B$2:$F$149,4,0) -> 1022.69
A22: 100222345 | B22: SIDDHARTHA LOGISTICS FTWZ PRIVATE | C22: 45995 | D22: 1800015482 | E22: DR | F22: 45995 | G22: 46000 | H22: NA | I22: 256779419966 | J22: 212100 | K22: Trade Debtors (Ctrl) | M22: 01 | N22: INR | O22: 100000 | P22: INR | Q22: 100000 | T22: O0 | U22: 6779224500 | W22: 2139804 | X22: 1 | Y22: Fixed Storage Charges for December 2025 | AC22: 45995 | AG22: =VLOOKUP(I22,'Customer Data'!$B$2:$F$149,4,0) -> 1014.65
A23: 100222345 | B23: SIDDHARTHA LOGISTICS FTWZ PRIVATE | C23: 45730 | D23: 1800001820 | E23: DR | F23: 45730 | G23: 45733 | H23: NA | I23: 246779411485 | J23: 212100 | K23: Trade Debtors (Ctrl) | M23: 01 | N23: USD | O23: 100 | P23: INR | Q23: 8669.13 | T23: O0 | U23: 6779224500 | W23: NA | X23: 1 | Y23: Intra Unit Transfer Charges Month Of August,2024 | AC23: 45730 | AG23: =VLOOKUP(I23,'Customer Data'!$B$2:$F$149,4,0) -> 98
A24: 100222345 | B24: SIDDHARTHA LOGISTICS FTWZ PRIVATE | C24: 45730 | D24: 1800001617 | E24: DR | F24: 45730 | G24: 45735 | H24: NA | I24: 246779412274 | J24: 212100 | K24: Trade Debtors (Ctrl) | M24: 01 | N24: USD | O24: 100 | P24: INR | Q24: 8669.13 | T24: O0 | U24: 6779224500 | W24: NA | X24: 1 | Y24: Intra Unit Transfer Charges Month Of August,2024 | AC24: 45730 | AG24: =VLOOKUP(I24,'Customer Data'!$B$2:$F$149,4,0) -> #N/A
A25: 100222345 | B25: SIDDHARTHA LOGISTICS FTWZ PRIVATE | C25: 45720 | D25: 1800000754 | E25: DR | F25: 45720 | G25: 45720 | H25: NA | I25: 246779410694 | J25: 212100 | K25: Trade Debtors (Ctrl) | M25: 01 | N25: USD | O25: 59.36 | P25: INR | Q25: 5145.99 | T25: O0 | U25: 6779224500 | W25: NA | X25: 1 | Y25: Outbound Handling for Oct 2024 | AC25: 45720 | AG25: =VLOOKUP(I25,'Customer Data'!$B$2:$F$149,4,0) -> 58.17
A26: 100222345 | B26: SIDDHARTHA LOGISTICS FTWZ PRIVATE | C26: 45720 | D26: 1800000915 | E26: DR | F26: 45720 | G26: 45721 | H26: NA | I26: 246779410856 | J26: 212100 | K26: Trade Debtors (Ctrl) | M26: 01 | N26: USD | O26: 18.32 | P26: INR | Q26: 1588.18 | T26: O0 | U26: 6779224500 | W26: NA | X26: 1 | Y26: Outbound Handling for Dec 2024 | AC26: 45720 | AG26: =VLOOKUP(I26,'Customer Data'!$B$2:$F$149,4,0) -> 17.95
A27: 100222345 | B27: SIDDHARTHA LOGISTICS FTWZ PRIVATE | C27: 45751 | D27: 1800005899 | E27: DR | F27: 45751 | G27: 45752 | H27: NA | I27: 256779410791 | J27: 212100 | K27: Trade Debtors (Ctrl) | M27: 01 | N27: USD | O27: 441.2 | P27: INR | Q27: 38349.91 | T27: O0 | W27: NA | X27: 1 | Y27: Storage Charges Feb, 25 Exch Rate 87.4 | AC27: 45751 | AG27: =VLOOKUP(I27,'Customer Data'!$B$2:$F$149,4,0) -> 397.08
A28: 100222345 | B28: SIDDHARTHA LOGISTICS FTWZ PRIVATE | C28: 45751 | D28: 1800005916 | E28: DR | F28: 45751 | G28: 45752 | H28: NA | I28: 256779410807 | J28: 212100 | K28: Trade Debtors (Ctrl) | M28: 01 | N28: USD | O28: 742.7 | P28: INR | Q28: 64556.84 | T28: O0 | W28: NA | X28: 1 | Y28: Storage Charges Jan, 25 Exch Rate 86.64 | AC28: 45751 | AG28: =VLOOKUP(I28,'Customer Data'!$B$2:$F$149,4,0) -> 668.43
A29: 100222345 | B29: SIDDHARTHA LOGISTICS FTWZ PRIVATE | C29: 45722 | D29: 1800000948 | E29: DR | F29: 45722 | G29: 45722 | H29: NA | I29: 246779410888 | J29: 212100 | K29: Trade Debtors (Ctrl) | M29: 01 | N29: USD | O29: 446.38 | P29: INR | Q29: 38697.24 | T29: O0 | U29: 6779224500 | W29: NA | X29: 1 | Y29: Storage Charges for the month of December, 2024 Ex | AC29: 45722 | AG29: =VLOOKUP(I29,'Customer Data'!$B$2:$F$149,4,0) -> 401.74
A30: 100222345 | B30: SIDDHARTHA LOGISTICS FTWZ PRIVATE | C30: 45722 | D30: 1800000925 | E30: DR | F30: 45722 | G30: 45722 | H30: NA | I30: 246779410865 | J30: 212100 | K30: Trade Debtors (Ctrl) | M30: 01 | N30: USD | O30: 412.11 | P30: INR | Q30: 35726.34 | T30: O0 | U30: 6779224500 | W30: NA | X30: 1 | Y30: Storage Charges for the month of November, 2024 Ex | AC30: 45722 | AG30: =VLOOKUP(I30,'Customer Data'!$B$2:$F$149,4,0) -> 370.9
A31: 100222345 | B31: SIDDHARTHA LOGISTICS FTWZ PRIVATE | C31: 45722 | D31: 1800001035 | E31: DR | F31: 45722 | G31: 45722 | H31: NA | I31: 246779410975 | J31: 212100 | K31: Trade Debtors (Ctrl) | M31: 01 | N31: USD | O31: 28.91 | P31: INR | Q31: 2506.24 | T31: O0 | U31: 6779224500 | W31: NA | X31: 1 | Y31: Inbound Handling charges for Aug 2024 | AC31: 45722 | AG31: =VLOOKUP(I31,'Customer Data'!$B$2:$F$149,4,0) -> 28.33
A32: 100222345 | B32: SIDDHARTHA LOGISTICS FTWZ PRIVATE | C32: 45722 | D32: 1800001036 | E32: DR | F32: 45722 | G32: 45722 | H32: NA | I32: 246779410976 | J32: 212100 | K32: Trade Debtors (Ctrl) | M32: 01 | N32: USD | O32: 24 | P32: INR | Q32: 2080.59 | T32: O0 | U32: 6779224500 | W32: NA | X32: 1 | Y32: Inbound Handling charges for Aug 2024 | AC32: 45722 | AG32: =VLOOKUP(I32,'Customer Data'!$B$2:$F$149,4,0) -> 23.51
A33: 100222345 | B33: SIDDHARTHA LOGISTICS FTWZ PRIVATE | C33: 45722 | D33: 1800001120 | E33: DR | F33: 45722 | G33: 45723 | H33: NA | I33: 246779411056 | J33: 212100 | K33: Trade Debtors (Ctrl) | M33: 01 | N33: USD | O33: 59.36 | P33: INR | Q33: 5145.99 | T33: O0 | U33: 6779224500 | W33: NA | X33: 1 | Y33: Inbound Handling charges for Sep 2024 | AC33: 45722 | AG33: =VLOOKUP(I33,'Customer Data'!$B$2:$F$149,4,0) -> 58.17
A34: 100222345 | B34: SIDDHARTHA LOGISTICS FTWZ PRIVATE | C34: 45722 | D34: 1800001121 | E34: DR | F34: 45722 | G34: 45723 | H34: NA | I34: 246779411057 | J34: 212100 | K34: Trade Debtors (Ctrl) | M34: 01 | N34: USD | O34: 67.67 | P34: INR | Q34: 5866.4 | T34: O0 | U34: 6779224500 | W34: NA | X34: 1 | Y34: Inbound Handling charges for Sep 2024 | AC34: 45722 | AG34: =VLOOKUP(I34,'Customer Data'!$B$2:$F$149,4,0) -> 66.32
A35: 100222345 | B35: SIDDHARTHA LOGISTICS FTWZ PRIVATE | C35: 45722 | D35: 1800001321 | E35: DR | F35: 45722 | G35: 45723 | H35: NA | I35: 246779411190 | J35: 212100 | K35: Trade Debtors (Ctrl) | M35: 01 | N35: USD | O35: 17.25 | P35: INR | Q35: 1495.42 | T35: O0 | U35: 6779224500 | W35: NA | X35: 1 | Y35: Inbound Handling charges for Nov 2024 | AC35: 45722 | AG35: =VLOOKUP(I35,'Customer Data'!$B$2:$F$149,4,0) -> 16.9
A36: 100222345 | B36: SIDDHARTHA LOGISTICS FTWZ PRIVATE | C36: 45722 | D36: 1800001322 | E36: DR | F36: 45722 | G36: 45723 | H36: NA | I36: 246779411191 | J36: 212100 | K36: Trade Debtors (Ctrl) | M36: 01 | N36: USD | O36: 26.15 | P36: INR | Q36: 2266.98 | T36: O0 | U36: 6779224500 | W36: NA | X36: 1 | Y36: Inbound Handling charges for Nov 2024 | AC36: 45722 | AG36: =VLOOKUP(I36,'Customer Data'!$B$2:$F$149,4,0) -> 25.63
A37: 100222345 | B37: SIDDHARTHA LOGISTICS FTWZ PRIVATE | C37: 45722 | D37: 1800001384 | E37: DR | F37: 45722 | G37: 45723 | H37: NA | I37: 246779411253 | J37: 212100 | K37: Trade Debtors (Ctrl) | M37: 01 | N37: USD | O37: 20 | P37: INR | Q37: 1733.83 | T37: O0 | U37: 6779224500 | W37: NA | X37: 1 | Y37: Inbound Handling charges for Dec 2024 | AC37: 45722 | AG37: =VLOOKUP(I37,'Customer Data'!$B$2:$F$149,4,0) -> 19.6
A38: 100222345 | B38: SIDDHARTHA LOGISTICS FTWZ PRIVATE | C38: 45943 | D38: 1600002430 | E38: DG | F38: 45943 | G38: 45944 | H38: NA | I38: 256779421974 | J38: 212100 | K38: Trade Debtors (Ctrl) | M38: 11 | N38: USD | O38: -435.91 | P38: INR | Q38: -38443.24 | T38: O0 | U38: 6779224500 | W38: 2112576 | X38: 1 | Y38: CN issued against 246779410865 | AC38: 45943 | AG38: =VLOOKUP(I38,'Customer Data'!$B$2:$F$149,4,0) -> -392.32 | AH38: =O38-AG38 -> -43.59 | AI38: =AH38/O38*100 -> 9.9997706
A39: 100222345 | B39: SIDDHARTHA LOGISTICS FTWZ PRIVATE | C39: 45943 | D39: 1600002431 | E39: DG | F39: 45943 | G39: 45944 | H39: NA | I39: 256779421975 | J39: 212100 | K39: Trade Debtors (Ctrl) | M39: 11 | N39: USD | O39: -447.05 | P39: INR | Q39: -39425.68 | T39: O0 | U39: 6779224500 | W39: 2112576 | X39: 1 | Y39: CN issued against 246779410888 | AC39: 45943 | AG39: =VLOOKUP(I39,'Customer Data'!$B$2:$F$149,4,0) -> -402.34 | AH39: =O39-AG39 -> -44.71 | AI39: =AH39/O39*100 -> 10.001118
A40: 100222345 | B40: SIDDHARTHA LOGISTICS FTWZ PRIVATE | C40: 45943 | D40: 1600002438 | E40: DG | F40: 45943 | G40: 45944 | H40: NA | I40: 256779421982 | J40: 212100 | K40: Trade Debtors (Ctrl) | M40: 11 | N40: USD | O40: -480.02 | P40: INR | Q40: -42333.33 | T40: O0 | U40: 6779224500 | W40: 2112591 | X40: 1 | Y40: CN issued against 256779418012 | AC40: 45943 | AD40: 45976 | AE40: 1400001904 | AG40: =VLOOKUP(I40,'Customer Data'!$B$2:$F$149,4,0) -> #N/A
A41: 100222345 | B41: SIDDHARTHA LOGISTICS FTWZ PRIVATE | C41: 45943 | D41: 1600002432 | E41: DG | F41: 45943 | G41: 45944 | H41: NA | I41: 256779421976 | J41: 212100 | K41: Trade Debtors (Ctrl) | M41: 11 | N41: USD | O41: -111.25 | P41: INR | Q41: -9811.22 | T41: O0 | U41: 6779224500 | W41: 2112576 | X41: 1 | Y41: CN issued against 246779410368 | AC41: 45943 | AD41: 45976 | AE41: 1400001905 | AG41: =VLOOKUP(I41,'Customer Data'!$B$2:$F$149,4,0) -> -100.12 | AH41: =O41-AG41 -> -11.13 | AI41: =AH41/O41*100 -> 10.004494
A42: 100222345 | B42: SIDDHARTHA LOGISTICS FTWZ PRIVATE | C42: 45943 | D42: 1600002433 | E42: DG | F42: 45943 | G42: 45944 | H42: NA | I42: 256779421977 | J42: 212100 | K42: Trade Debtors (Ctrl) | M42: 11 | N42: USD | O42: -376.4 | P42: INR | Q42: -33195.01 | T42: O0 | U42: 6779224500 | W42: 2112576 | X42: 1 | Y42: CN issued against 246779410394 | AC42: 45943 | AD42: 45976 | AE42: 1400001905 | AG42: =VLOOKUP(I42,'Customer Data'!$B$2:$F$149,4,0) -> -338.76 | AH42: =O42-AG42 -> -37.64 | AI42: =AH42/O42*100 -> 10
A43: 100222345 | B43: SIDDHARTHA LOGISTICS FTWZ PRIVATE | C43: 45943 | D43: 1600002434 | E43: DG | F43: 45943 | G43: 45944 | H43: NA | I43: 256779421978 | J43: 212100 | K43: Trade Debtors (Ctrl) | M43: 11 | N43: USD | O43: -391.55 | P43: INR | Q43: -34531.1 | T43: O0 | U43: 6779224500 | W43: 2112576 | X43: 1 | Y43: CN issued against 246779410418 | AC43: 45943 | AD43: 45976 | AE43: 1400001905 | AG43: =VLOOKUP(I43,'Customer Data'!$B$2:$F$149,4,0) -> -352.39 | AH43: =O43-AG43 -> -39.16 | AI43: =AH43/O43*100 -> 10.001277
A44: 100222345 | B44: SIDDHARTHA LOGISTICS FTWZ PRIVATE | C44: 45719 | D44: 1800000406 | E44: DR | F44: 45719 | G44: 45719 | H44: NA | I44: 246779410368 | J44: 212100 | K44: Trade Debtors (Ctrl) | M44: 01 | N44: USD | O44: 356.43 | P44: INR | Q44: 30899.37 | T44: O0 | U44: 6779224500 | W44: NA | X44: 1 | Y44: Storage Charges for the month of August, 2024 | AC44: 45719 | AG44: =VLOOKUP(I44,'Customer Data'!$B$2:$F$149,4,0) -> 320.78
A45: 100222345 | B45: SIDDHARTHA LOGISTICS FTWZ PRIVATE | C45: 45719 | D45: 1800000675 | E45: DR | F45: 45719 | G45: 45720 | H45: NA | I45: 246779410615 | J45: 212100 | K45: Trade Debtors (Ctrl) | M45: 01 | N45: USD | O45: 9 | P45: INR | Q45: 780.22 | T45: O0 | U45: 6779224500 | W45: NA | X45: 1 | Y45: Outbound Handling for Sep 2024 | AC45: 45719 | AG45: =VLOOKUP(I45,'Customer Data'!$B$2:$F$149,4,0) -> 8.81
A46: 100222345 | B46: SIDDHARTHA LOGISTICS FTWZ PRIVATE | C46: 45719 | D46: 1800000432 | E46: DR | F46: 45719 | G46: 45719 | H46: NA | I46: 246779410394 | J46: 212100 | K46: Trade Debtors (Ctrl) | M46: 01 | N46: USD | O46: 505.86 | P46: INR | Q46: 43853.64 | T46: O0 | U46: 6779224500 | W46: NA | X46: 1 | Y46: Storage for the month of Sep 2024 Exch Rate 83.79 | AC46: 45719 | AG46: =VLOOKUP(I46,'Customer Data'!$B$2:$F$149,4,0) -> 455.27
A47: 100222345 | B47: SIDDHARTHA LOGISTICS FTWZ PRIVATE | C47: 45719 | D47: 1800000456 | E47: DR | F47: 45719 | G47: 45719 | H47: NA | I47: 246779410418 | J47: 212100 | K47: Trade Debtors (Ctrl) | M47: 01 | N47: USD | O47: 562.6 | P47: INR | Q47: 48772.5 | T47: O0 | U47: 6779224500 | W47: NA | X47: 1 | Y47: Storage for the month of Oct 2024 | AC47: 45719 | AG47: =VLOOKUP(I47,'Customer Data'!$B$2:$F$149,4,0) -> 506.34
A48: 100222345 | B48: SIDDHARTHA LOGISTICS FTWZ PRIVATE | C48: 45719 | D48: 1800000559 | E48: DR | F48: 45719 | G48: 45719 | H48: NA | I48: 246779410509 | J48: 212100 | K48: Trade Debtors (Ctrl) | M48: 01 | N48: USD | O48: 29.25 | P48: INR | Q48: 2535.72 | T48: O0 | U48: 6779224500 | W48: NA | X48: 1 | Y48: Outbound Handling for Aug 2024 | AC48: 45719 | AG48: =VLOOKUP(I48,'Customer Data'!$B$2:$F$149,4,0) -> #N/A
A49: 100222345 | B49: SIDDHARTHA LOGISTICS FTWZ PRIVATE | C49: 45719 | D49: 1800000560 | E49: DR | F49: 45719 | G49: 45719 | H49: NA | I49: 246779410510 | J49: 212100 | K49: Trade Debtors (Ctrl) | M49: 01 | N49: USD | O49: 194.9 | P49: INR | Q49: 16896.13 | T49: O0 | U49: 6779224500 | W49: NA | X49: 1 | Y49: Outbound Handling for Aug 2024 | AC49: 45719 | AG49: =VLOOKUP(I49,'Customer Data'!$B$2:$F$149,4,0) -> 191
A50: 100222345 | B50: SIDDHARTHA LOGISTICS FTWZ PRIVATE | C50: 45719 | D50: 1800000561 | E50: DR | F50: 45719 | G50: 45719 | H50: NA | I50: 246779410511 | J50: 212100 | K50: Trade Debtors (Ctrl) | M50: 01 | N50: USD | O50: 13.91 | P50: INR | Q50: 1205.88 | T50: O0 | U50: 6779224500 | W50: NA | X50: 1 | Y50: Outbound Handling for Aug 2024 | AC50: 45719 | AG50: =VLOOKUP(I50,'Customer Data'!$B$2:$F$149,4,0) -> 13.63
A51: 100222345 | B51: SIDDHARTHA LOGISTICS FTWZ PRIVATE | C51: 45719 | D51: 1800000674 | E51: DR | F51: 45719 | G51: 45720 | H51: NA | I51: 246779410614 | J51: 212100 | K51: Trade Debtors (Ctrl) | M51: 01 | N51: USD | O51: 2.25 | P51: INR | Q51: 195.06 | T51: O0 | U51: 6779224500 | W51: NA | X51: 1 | Y51: Outbound Handling for Sep 2024 | AC51: 45719 | AG51: =VLOOKUP(I51,'Customer Data'!$B$2:$F$149,4,0) -> 2.2
A52: 100222345 | B52: SIDDHARTHA LOGISTICS FTWZ PRIVATE | C52: 45733 | D52: 1800001957 | E52: DR | F52: 45733 | G52: 45733 | H52: NA | I52: 246779411622 | J52: 212100 | K52: Trade Debtors (Ctrl) | M52: 01 | N52: USD | O52: 3.82 | P52: INR | Q52: 331.16 | T52: O0 | U52: 6779224500 | W52: NA | X52: 1 | Y52: VAS Activity Charges for the month of September, 2 | AC52: 45733 | AG52: =VLOOKUP(I52,'Customer Data'!$B$2:$F$149,4,0) -> 3.74
A53: 100222345 | B53: SIDDHARTHA LOGISTICS FTWZ PRIVATE | C53: 45733 | D53: 1800001958 | E53: DR | F53: 45733 | G53: 45733 | H53: NA | I53: 246779411623 | J53: 212100 | K53: Trade Debtors (Ctrl) | M53: 01 | N53: USD | O53: 1.91 | P53: INR | Q53: 165.58 | T53: O0 | U53: 6779224500 | W53: NA | X53: 1 | Y53: VAS Activity Charges for the month of September, 2 | AC53: 45733 | AG53: =VLOOKUP(I53,'Customer Data'!$B$2:$F$149,4,0) -> 1.87
A54: 100222345 | B54: SIDDHARTHA LOGISTICS FTWZ PRIVATE | C54: 45980 | D54: 1800014864 | E54: DR | F54: 45980 | G54: 45982 | H54: NA | I54: 256779419365 | J54: 212100 | K54: Trade Debtors (Ctrl) | M54: 01 | N54: USD | O54: 292.99 | P54: INR | Q54: 25784.11 | T54: O0 | U54: 6779224500 | W54: 2128982 | X54: 1 | Y54: MH43CE4486(ONEU1505971) Without de-stuffing Invoic | AC54: 45980 | AG54: =VLOOKUP(I54,'Customer Data'!$B$2:$F$149,4,0) -> 287.13
A55: 100222345 | B55: SIDDHARTHA LOGISTICS FTWZ PRIVATE | C55: 45762 | D55: 1800006269 | E55: DR | F55: 45762 | G55: 45763 | H55: NA | I55: 256779411160 | J55: 212100 | K55: Trade Debtors (Ctrl) | M55: 01 | N55: USD | O55: 18.38 | P55: INR | Q55: 1597.62 | T55: O0 | W55: NA | X55: 1 | Y55: LCL Charges August 2024 | AC55: 45762 | AG55: =VLOOKUP(I55,'Customer Data'!$B$2:$F$149,4,0) -> 18.01
A56: 100222345 | B56: SIDDHARTHA LOGISTICS FTWZ PRIVATE | C56: 45762 | D56: 1800006270 | E56: DR | F56: 45762 | G56: 45763 | H56: NA | I56: 256779411161 | J56: 212100 | K56: Trade Debtors (Ctrl) | M56: 01 | N56: USD | O56: 46.76 | P56: INR | Q56: 4064.46 | T56: O0 | W56: NA | X56: 1 | Y56: Inbound Handling for August 24 | AC56: 45762 | AG56: =VLOOKUP(I56,'Customer Data'!$B$2:$F$149,4,0) -> 45.82
A57: 100222345 | B57: SIDDHARTHA LOGISTICS FTWZ PRIVATE | C57: 45762 | D57: 1800006271 | E57: DR | F57: 45762 | G57: 45763 | H57: NA | I57: 256779411162 | J57: 212100 | K57: Trade Debtors (Ctrl) | M57: 01 | N57: USD | O57: 35.25 | P57: INR | Q57: 3063.99 | T57: O0 | W57: NA | X57: 1 | Y57: LCL Charges August 2024 | AC57: 45762 | AG57: =VLOOKUP(I57,'Customer Data'!$B$2:$F$149,4,0) -> 34.54
A58: 100222345 | B58: SIDDHARTHA LOGISTICS FTWZ PRIVATE | C58: 45762 | D58: 1800006272 | E58: DR | F58: 45762 | G58: 45763 | H58: NA | I58: 256779411163 | J58: 212100 | K58: Trade Debtors (Ctrl) | M58: 01 | N58: USD | O58: 24 | P58: INR | Q58: 2086.12 | T58: O0 | W58: NA | X58: 1 | Y58: LCL Charges August 2024 | AC58: 45762 | AG58: =VLOOKUP(I58,'Customer Data'!$B$2:$F$149,4,0) -> 23.52
A59: 100222345 | B59: SIDDHARTHA LOGISTICS FTWZ PRIVATE | C59: 45762 | D59: 1800006273 | E59: DR | F59: 45762 | G59: 45763 | H59: NA | I59: 256779411164 | J59: 212100 | K59: Trade Debtors (Ctrl) | M59: 01 | N59: USD | O59: 33 | P59: INR | Q59: 2868.42 | T59: O0 | W59: NA | X59: 1 | Y59: LCL Charges August 2024 | AC59: 45762 | AG59: =VLOOKUP(I59,'Customer Data'!$B$2:$F$149,4,0) -> 32.34
A60: 100222345 | B60: SIDDHARTHA LOGISTICS FTWZ PRIVATE | C60: 45762 | D60: 1800006696 | E60: DR | F60: 45762 | G60: 45763 | H60: NA | I60: 256779411587 | J60: 212100 | K60: Trade Debtors (Ctrl) | M60: 01 | N60: USD | O60: 2.25 | P60: INR | Q60: 195.57 | T60: O0 | W60: NA | X60: 1 | Y60: Outbound Handling Charges Aug 2024 | AC60: 45762 | AG60: =VLOOKUP(I60,'Customer Data'!$B$2:$F$149,4,0) -> 2.2
A61: 100222345 | B61: SIDDHARTHA LOGISTICS FTWZ PRIVATE | C61: 45762 | D61: 1800006697 | E61: DR | F61: 45762 | G61: 45763 | H61: NA | I61: 256779411588 | J61: 212100 | K61: Trade Debtors (Ctrl) | M61: 01 | N61: USD | O61: 2.25 | P61: INR | Q61: 195.57 | T61: O0 | W61: NA | X61: 1 | Y61: Outbound Handling Charges Aug 2024 | AC61: 45762 | AG61: =VLOOKUP(I61,'Customer Data'!$B$2:$F$149,4,0) -> 2.2
A62: 100222345 | B62: SIDDHARTHA LOGISTICS FTWZ PRIVATE | C62: 45762 | D62: 1800006698 | E62: DR | F62: 45762 | G62: 45763 | H62: NA | I62: 256779411589 | J62: 212100 | K62: Trade Debtors (Ctrl) | M62: 01 | N62: USD | O62: 3.38 | P62: INR | Q62: 293.8 | T62: O0 | W62: NA | X62: 1 | Y62: Outbound Handling Charges Aug 2024 | AC62: 45762 | AG62: =VLOOKUP(I62,'Customer Data'!$B$2:$F$149,4,0) -> #N/A
A63: 100222345 | B63: SIDDHARTHA LOGISTICS FTWZ PRIVATE | C63: 45762 | D63: 1800006699 | E63: DR | F63: 45762 | G63: 45763 | H63: NA | I63: 256779411590 | J63: 212100 | K63: Trade Debtors (Ctrl) | M63: 01 | N63: USD | O63: 2.25 | P63: INR | Q63: 195.57 | T63: O0 | W63: NA | X63: 1 | Y63: Outbound Handling Charges Aug 2024 | AC63: 45762 | AG63: =VLOOKUP(I63,'Customer Data'!$B$2:$F$149,4,0) -> 2.2
A64: 100222345 | B64: SIDDHARTHA LOGISTICS FTWZ PRIVATE | C64: 45762 | D64: 1800006700 | E64: DR | F64: 45762 | G64: 45763 | H64: NA | I64: 256779411591 | J64: 212100 | K64: Trade Debtors (Ctrl) | M64: 01 | N64: USD | O64: 3 | P64: INR | Q64: 260.77 | T64: O0 | W64: NA | X64: 1 | Y64: Outbound Handling Charges Aug 2024 | AC64: 45762 | AG64: =VLOOKUP(I64,'Customer Data'!$B$2:$F$149,4,0) -> 2.94
A65: 100222345 | B65: SIDDHARTHA LOGISTICS FTWZ PRIVATE | C65: 45762 | D65: 1800006701 | E65: DR | F65: 45762 | G65: 45763 | H65: NA | I65: 256779411592 | J65: 212100 | K65: Trade Debtors (Ctrl) | M65: 01 | N65: USD | O65: 9.59 | P65: INR | Q65: 833.58 | T65: O0 | W65: NA | X65: 1 | Y65: Outbound Handling Charges Aug 2024 | AC65: 45762 | AG65: =VLOOKUP(I65,'Customer Data'!$B$2:$F$149,4,0) -> 9.4
A66: 100222345 | B66: SIDDHARTHA LOGISTICS FTWZ PRIVATE | C66: 45762 | D66: 1800006702 | E66: DR | F66: 45762 | G66: 45763 | H66: NA | I66: 256779411593 | J66: 212100 | K66: Trade Debtors (Ctrl) | M66: 01 | N66: USD | O66: 3 | P66: INR | Q66: 260.77 | T66: O0 | W66: NA | X66: 1 | Y66: Outbound Handling Charges Aug 2024 | AC66: 45762 | AG66: =VLOOKUP(I66,'Customer Data'!$B$2:$F$149,4,0) -> 2.94
... A70: 100222345 | B70: SIDDHARTHA LOGISTICS FTWZ PRIVATE | C70: 45762 | D70: 1800006706 | E70: DR | F70: 45762 | G70: 45763 | H70: NA | I70: 256779411597 | J70: 212100 | K70: Trade Debtors (Ctrl) | M70: 01 | N70: USD | O70: 19.95 | P70: INR | Q70: 1734.09 | T70: O0 | W70: NA | X70: 1 | Y70: Outbound Handling Charges Aug 2024 | AC70: 45762 | AG70: =VLOOKUP(I70,'Customer Data'!$B$2:$F$149,4,0) -> 19.55
A71: 100222345 | B71: SIDDHARTHA LOGISTICS FTWZ PRIVATE | C71: 45763 | D71: 1800006920 | E71: DR | F71: 45763 | G71: 45764 | H71: NA | I71: 256779411811 | J71: 212100 | K71: Trade Debtors (Ctrl) | M71: 01 | N71: USD | O71: 3.24 | P71: INR | Q71: 281.63 | T71: O0 | U71: 6779224500 | W71: NA | X71: 1 | Y71: Inbound Handling charges for Dec 2024 | AC71: 45763 | AG71: =VLOOKUP(I71,'Customer Data'!$B$2:$F$149,4,0) -> 3.18
A72: 100222345 | B72: SIDDHARTHA LOGISTICS FTWZ PRIVATE | C72: 45763 | D72: 1800006921 | E72: DR | F72: 45763 | G72: 45764 | H72: NA | I72: 256779411812 | J72: 212100 | K72: Trade Debtors (Ctrl) | M72: 01 | N72: USD | O72: 15 | P72: INR | Q72: 1303.83 | T72: O0 | U72: 6779224500 | W72: NA | X72: 1 | Y72: LCL charges for Dec 2024 | AC72: 45763 | AG72: =VLOOKUP(I72,'Customer Data'!$B$2:$F$149,4,0) -> 14.7
A73: 100222345 | B73: SIDDHARTHA LOGISTICS FTWZ PRIVATE | C73: 45763 | D73: 1800006999 | E73: DR | F73: 45763 | G73: 45764 | H73: NA | I73: 256779411890 | J73: 212100 | K73: Trade Debtors (Ctrl) | M73: 01 | N73: USD | O73: 24.75 | P73: INR | Q73: 2151.32 | T73: O0 | U73: 6779224500 | W73: NA | X73: 1 | Y73: Outbound Handling charges for Dec 2024 | AC73: 45763 | AG73: =VLOOKUP(I73,'Customer Data'!$B$2:$F$149,4,0) -> 24.25
A74: 100222345 | B74: SIDDHARTHA LOGISTICS FTWZ PRIVATE | C74: 45763 | D74: 1800007000 | E74: DR | F74: 45763 | G74: 45764 | H74: NA | I74: 256779411891 | J74: 212100 | K74: Trade Debtors (Ctrl) | M74: 01 | N74: USD | O74: 2.25 | P74: INR | Q74: 195.57 | T74: O0 | U74: 6779224500 | W74: NA | X74: 1 | Y74: Loose loading Handling charges for Dec 2024 | AC74: 45763 | AG74: =VLOOKUP(I74,'Customer Data'!$B$2:$F$149,4,0) -> 2.2
A75: 100222345 | B75: SIDDHARTHA LOGISTICS FTWZ PRIVATE | C75: 45763 | D75: 1800007212 | E75: DR | F75: 45763 | G75: 45764 | H75: NA | I75: 256779412103 | J75: 212100 | K75: Trade Debtors (Ctrl) | M75: 01 | N75: USD | O75: 42.53 | P75: INR | Q75: 3696.79 | T75: O0 | U75: 6779224500 | W75: NA | X75: 1 | Y75: VAS Activity - Mar 25, 16-31, Ex Rate. 85.58 | AC75: 45763 | AG75: =VLOOKUP(I75,'Customer Data'!$B$2:$F$149,4,0) -> 41.67
A76: 100222345 | B76: SIDDHARTHA LOGISTICS FTWZ PRIVATE | C76: 45763 | D76: 1800007222 | E76: DR | F76: 45763 | G76: 45764 | H76: NA | I76: 256779412113 | J76: 212100 | K76: Trade Debtors (Ctrl) | M76: 01 | N76: USD | O76: 827.48 | P76: INR | Q76: 71926.07 | T76: O0 | U76: 6779224500 | W76: NA | X76: 1 | Y76: Storage Charges Mar, 25 Exch Rate 85.58 | AC76: 45763 | AG76: =VLOOKUP(I76,'Customer Data'!$B$2:$F$149,4,0) -> 744.73
A77: 100222345 | B77: SIDDHARTHA LOGISTICS FTWZ PRIVATE | C77: 45730 | D77: 1800001786 | E77: DR | F77: 45730 | G77: 45733 | H77: NA | I77: 246779411451 | J77: 212100 | K77: Trade Debtors (Ctrl) | M77: 01 | N77: USD | O77: 2.86 | P77: INR | Q77: 247.94 | T77: O0 | U77: 6779224500 | W77: NA | X77: 1 | Y77: VAS Activity Charges for the month of August, 24 | AC77: 45730 | AG77: =VLOOKUP(I77,'Customer Data'!$B$2:$F$149,4,0) -> #N/A
A78: 100222345 | B78: SIDDHARTHA LOGISTICS FTWZ PRIVATE | C78: 45730 | D78: 1800001787 | E78: DR | F78: 45730 | G78: 45733 | H78: NA | I78: 246779411452 | J78: 212100 | K78: Trade Debtors (Ctrl) | M78: 01 | N78: USD | O78: 0.95 | P78: INR | Q78: 82.36 | T78: O0 | U78: 6779224500 | W78: NA | X78: 1 | Y78: VAS Activity Charges for the month of August, 24 | AC78: 45730 | AG78: =VLOOKUP(I78,'Customer Data'!$B$2:$F$149,4,0) -> 0.93
A79: 100222345 | B79: SIDDHARTHA LOGISTICS FTWZ PRIVATE | C79: 45730 | D79: 1800001788 | E79: DR | F79: 45730 | G79: 45733 | H79: NA | I79: 246779411453 | J79: 212100 | K79: Trade Debtors (Ctrl) | M79: 01 | N79: USD | O79: 4.77 | P79: INR | Q79: 413.52 | T79: O0 | U79: 6779224500 | W79: NA | X79: 1 | Y79: VAS Activity Charges for the month of August, 24 | AC79: 45730 | AG79: =VLOOKUP(I79,'Customer Data'!$B$2:$F$149,4,0) -> #N/A
A80: 100222345 | B80: SIDDHARTHA LOGISTICS FTWZ PRIVATE | C80: 45730 | D80: 1800001789 | E80: DR | F80: 45730 | G80: 45733 | H80: NA | I80: 246779411454 | J80: 212100 | K80: Trade Debtors (Ctrl) | M80: 01 | N80: USD | O80: 1.91 | P80: INR | Q80: 165.58 | T80: O0 | U80: 6779224500 | W80: NA | X80: 1 | Y80: VAS Activity Charges for the month of August, 24 | AC80: 45730 | AG80: =VLOOKUP(I80,'Customer Data'!$B$2:$F$149,4,0) -> #N/A
A81: 100222345 | B81: SIDDHARTHA LOGISTICS FTWZ PRIVATE | C81: 45730 | D81: 1800001790 | E81: DR | F81: 45730 | G81: 45733 | H81: NA | I81: 246779411455 | J81: 212100 | K81: Trade Debtors (Ctrl) | M81: 01 | N81: USD | O81: 1.91 | P81: INR | Q81: 165.58 | T81: O0 | U81: 6779224500 | W81: NA | X81: 1 | Y81: VAS Activity Charges for the month of August, 24 | AC81: 45730 | AG81: =VLOOKUP(I81,'Customer Data'!$B$2:$F$149,4,0) -> #N/A
A82: 100222345 | B82: SIDDHARTHA LOGISTICS FTWZ PRIVATE | C82: 45730 | D82: 1800001791 | E82: DR | F82: 45730 | G82: 45733 | H82: NA | I82: 246779411456 | J82: 212100 | K82: Trade Debtors (Ctrl) | M82: 01 | N82: USD | O82: 4.77 | P82: INR | Q82: 413.52 | T82: O0 | U82: 6779224500 | W82: NA | X82: 1 | Y82: VAS Activity Charges for the month of August, 24 | AC82: 45730 | AG82: =VLOOKUP(I82,'Customer Data'!$B$2:$F$149,4,0) -> #N/A
A83: 100222345 | B83: SIDDHARTHA LOGISTICS FTWZ PRIVATE | C83: 45730 | D83: 1800001583 | E83: DR | F83: 45730 | G83: 45735 | H83: NA | I83: 246779412240 | J83: 212100 | K83: Trade Debtors (Ctrl) | M83: 01 | N83: USD | O83: 2.86 | P83: INR | Q83: 247.94 | T83: O0 | U83: 6779224500 | W83: NA | X83: 1 | Y83: VAS Activity Charges for the month of August, 24 | AC83: 45730 | AD83: 45861 | AE83: 1400000797 | AG83: =VLOOKUP(I83,'Customer Data'!$B$2:$F$149,4,0) -> 2.8
A84: 100222345 | B84: SIDDHARTHA LOGISTICS FTWZ PRIVATE | C84: 45730 | D84: 1800001584 | E84: DR | F84: 45730 | G84: 45735 | H84: NA | I84: 246779412241 | J84: 212100 | K84: Trade Debtors (Ctrl) | M84: 01 | N84: USD | O84: 0.95 | P84: INR | Q84: 82.36 | T84: O0 | U84: 6779224500 | W84: NA | X84: 1 | Y84: VAS Activity Charges for the month of August, 24 | AC84: 45730 | AD84: 45861 | AE84: 1400000797 | AG84: =VLOOKUP(I84,'Customer Data'!$B$2:$F$149,4,0) -> #N/A
A85: 100222345 | B85: SIDDHARTHA LOGISTICS FTWZ PRIVATE | C85: 45730 | D85: 1800001585 | E85: DR | F85: 45730 | G85: 45735 | H85: NA | I85: 246779412242 | J85: 212100 | K85: Trade Debtors (Ctrl) | M85: 01 | N85: USD | O85: 4.77 | P85: INR | Q85: 413.52 | T85: O0 | U85: 6779224500 | W85: NA | X85: 1 | Y85: VAS Activity Charges for the month of August, 24 | AC85: 45730 | AD85: 45861 | AE85: 1400000797 | AG85: =VLOOKUP(I85,'Customer Data'!$B$2:$F$149,4,0) -> 4.67
A86: 100222345 | B86: SIDDHARTHA LOGISTICS FTWZ PRIVATE | C86: 45730 | D86: 1800001586 | E86: DR | F86: 45730 | G86: 45735 | H86: NA | I86: 246779412243 | J86: 212100 | K86: Trade Debtors (Ctrl) | M86: 01 | N86: USD | O86: 1.91 | P86: INR | Q86: 165.58 | T86: O0 | U86: 6779224500 | W86: NA | X86: 1 | Y86: VAS Activity Charges for the month of August, 24 | AC86: 45730 | AD86: 45861 | AE86: 1400000797 | AG86: =VLOOKUP(I86,'Customer Data'!$B$2:$F$149,4,0) -> 1.87
A87: 100222345 | B87: SIDDHARTHA LOGISTICS FTWZ PRIVATE | C87: 45730 | D87: 1800001587 | E87: DR | F87: 45730 | G87: 45735 | H87: NA | I87: 246779412244 | J87: 212100 | K87: Trade Debtors (Ctrl) | M87: 01 | N87: USD | O87: 1.91 | P87: INR | Q87: 165.58 | T87: O0 | U87: 6779224500 | W87: NA | X87: 1 | Y87: VAS Activity Charges for the month of August, 24 | AC87: 45730 | AD87: 45861 | AE87: 1400000797 | AG87: =VLOOKUP(I87,'Customer Data'!$B$2:$F$149,4,0) -> 1.87
A88: 100222345 | B88: SIDDHARTHA LOGISTICS FTWZ PRIVATE | C88: 45730 | D88: 1800001588 | E88: DR | F88: 45730 | G88: 45735 | H88: NA | I88: 246779412245 | J88: 212100 | K88: Trade Debtors (Ctrl) | M88: 01 | N88: USD | O88: 4.77 | P88: INR | Q88: 413.52 | T88: O0 | U88: 6779224500 | W88: NA | X88: 1 | Y88: VAS Activity Charges for the month of August, 24 | AC88: 45730 | AD88: 45861 | AE88: 1400000797 | AG88: =VLOOKUP(I88,'Customer Data'!$B$2:$F$149,4,0) -> 4.68
A89: 100222345 | B89: SIDDHARTHA LOGISTICS FTWZ PRIVATE | C89: 45904 | D89: 1800012276 | E89: DR | F89: 45904 | G89: 45908 | H89: NA | I89: 256779416912 | J89: 212100 | K89: Trade Debtors (Ctrl) | M89: 01 | N89: USD | O89: 44.96 | P89: INR | Q89: 3934.64 | T89: O0 | U89: 6779224500 | W89: NA | X89: 1 | Y89: CODC LCL Chgs - 16-31 Aug 25 | AC89: 45904 | AG89: =VLOOKUP(I89,'Customer Data'!$B$2:$F$149,4,0) -> 44.06
A90: 100222345 | B90: SIDDHARTHA LOGISTICS FTWZ PRIVATE | C90: 45904 | D90: 1800012287 | E90: DR | F90: 45904 | G90: 45908 | H90: NA | I90: 256779416949 | J90: 212100 | K90: Trade Debtors (Ctrl) | M90: 01 | N90: USD | O90: 30.16 | P90: INR | Q90: 2639.43 | T90: O0 | U90: 6779224500 | W90: NA | X90: 1 | Y90: CODC Out chgs -16-31 Aug 25 | AC90: 45904 | AG90: =VLOOKUP(I90,'Customer Data'!$B$2:$F$149,4,0) -> 29.55
A91: 100222345 | B91: SIDDHARTHA LOGISTICS FTWZ PRIVATE | C91: 45904 | D91: 1800012532 | E91: DR | F91: 45904 | G91: 45909 | H91: NA | I91: 256779417136 | J91: 212100 | K91: Trade Debtors (Ctrl) | M91: 01 | N91: USD | O91: 1.71 | P91: INR | Q91: 149.65 | T91: O0 | U91: 6779224500 | W91: NA | X91: 1 | Y91: VAS - 16-31 Aug 25 | AC91: 45904 | AG91: =VLOOKUP(I91,'Customer Data'!$B$2:$F$149,4,0) -> 1.68
A92: 100222345 | B92: SIDDHARTHA LOGISTICS FTWZ PRIVATE | C92: 45904 | D92: 1800012462 | E92: DR | F92: 45904 | G92: 45909 | H92: NA | I92: 256779417162 | J92: 212100 | K92: Trade Debtors (Ctrl) | M92: 01 | N92: USD | O92: 44.74 | P92: INR | Q92: 3915.39 | T92: O0 | U92: 6779224500 | W92: NA | X92: 1 | Y92: VAS -16-31 Aug 25 | AC92: 45904 | AG92: =VLOOKUP(I92,'Customer Data'!$B$2:$F$149,4,0) -> #N/A
A93: 100222345 | B93: SIDDHARTHA LOGISTICS FTWZ PRIVATE | C93: 45904 | D93: 1800012688 | E93: DR | F93: 45904 | G93: 45909 | H93: NA | I93: 256779417328 | J93: 212100 | K93: Trade Debtors (Ctrl) | M93: 01 | N93: USD | O93: 2.25 | P93: INR | Q93: 196.91 | T93: O0 | U93: 6779224500 | W93: 2096996 | X93: 1 | Y93: Outbound chgs - 16 - 31 Aug 25 | AC93: 45904 | AG93: =VLOOKUP(I93,'Customer Data'!$B$2:$F$149,4,0) -> 2.2
A94: 100222345 | B94: SIDDHARTHA LOGISTICS FTWZ PRIVATE | C94: 45842 | D94: 1800010069 | E94: DR | F94: 45842 | G94: 45845 | H94: NA | I94: 256779414833 | J94: 212100 | K94: Trade Debtors (Ctrl) | M94: 01 | N94: USD | O94: 3 | P94: INR | Q94: 258 | T94: O0 | U94: 6779224500 | W94: NA | X94: 1 | Y94: Outbound chgs - 01 - 15 Jun 25 | AC94: 45842 | AG94: =VLOOKUP(I94,'Customer Data'!$B$2:$F$149,4,0) -> 2.94
A95: 100222345 | B95: SIDDHARTHA LOGISTICS FTWZ PRIVATE | C95: 45842 | D95: 1800010430 | E95: DR | F95: 45842 | G95: 45847 | H95: NA | I95: 256779415190 | J95: 212100 | K95: Trade Debtors (Ctrl) | M95: 01 | N95: USD | O95: 690.7 | P95: INR | Q95: 59400.66 | T95: O0 | U95: 6779224500 | W95: NA | X95: 1 | Y95: Unit Storage - 1-30 June 25 | AC95: 45842 | AG95: =VLOOKUP(I95,'Customer Data'!$B$2:$F$149,4,0) -> 621.63
A96: 100222345 | B96: SIDDHARTHA LOGISTICS FTWZ PRIVATE | C96: 45966 | D96: 1800014284 | E96: DR | F96: 45966 | G96: 45967 | H96: NA | I96: 256779418821 | J96: 212100 | K96: Trade Debtors (Ctrl) | M96: 01 | N96: USD | O96: 49.59 | P96: INR | Q96: 4364.09 | T96: O0 | U96: 6779224500 | W96: 2123387 | X96: 1 | Y96: VAS-16 -31 Oct 25 | AC96: 45966 | AG96: =VLOOKUP(I96,'Customer Data'!$B$2:$F$149,4,0) -> 48.6
A97: 100222345 | B97: SIDDHARTHA LOGISTICS FTWZ PRIVATE | C97: 45966 | D97: 1800014290 | E97: DR | F97: 45966 | G97: 45967 | H97: NA | I97: 256779418827 | J97: 212100 | K97: Trade Debtors (Ctrl) | M97: 01 | N97: USD | O97: 60.86 | P97: INR | Q97: 5355.89 | T97: O0 | U97: 6779224500 | W97: 2123387 | X97: 1 | Y97: WEIGHTMENT-16 -31 Oct 25 | AC97: 45966 | AG97: =VLOOKUP(I97,'Customer Data'!$B$2:$F$149,4,0) -> #N/A
A98: 100222345 | B98: SIDDHARTHA LOGISTICS FTWZ PRIVATE | C98: 45966 | D98: 1800014538 | E98: DR | F98: 45966 | G98: 45967 | H98: NA | I98: 256779418870 | J98: 212100 | K98: Trade Debtors (Ctrl) | M98: 01 | N98: USD | O98: 493.91 | P98: INR | Q98: 43465.75 | T98: O0 | U98: 6779224500 | W98: 2123390 | X98: 1 | Y98: Unit Storage - 1-31 Oct 2025 | AC98: 45966 | AG98: =VLOOKUP(I98,'Customer Data'!$B$2:$F$149,4,0) -> 444.51
A99: 100222345 | B99: SIDDHARTHA LOGISTICS FTWZ PRIVATE | C99: 45966 | D99: 1800014270 | E99: DR | F99: 45966 | G99: 45967 | H99: NA | I99: 256779418945 | J99: 212100 | K99: Trade Debtors (Ctrl) | M99: 01 | N99: USD | O99: 293.04 | P99: INR | Q99: 25788.51 | T99: O0 | U99: 6779224500 | W99: NA | X99: 1 | Y99: ONEU5912276 Without de-stuffing | AC99: 45966 | AG99: =VLOOKUP(I99,'Customer Data'!$B$2:$F$149,4,0) -> 287.18
A100: 100222345 | B100: SIDDHARTHA LOGISTICS FTWZ PRIVATE | C100: 45966 | D100: 1800014271 | E100: DR | F100: 45966 | G100: 45967 | H100: NA | I100: 256779418946 | J100: 212100 | K100: Trade Debtors (Ctrl) | M100: 01 | N100: USD | O100: 293.04 | P100: INR | Q100: 25788.51 | T100: O0 | U100: 6779224500 | W100: NA | X100: 1 | Y100: UACU6030817 Without de-stuffing | AC100: 45966 | AG100: =VLOOKUP(I100,'Customer Data'!$B$2:$F$149,4,0) -> 287.18
... A115: 100222345 | B115: SIDDHARTHA LOGISTICS FTWZ PRIVATE | C115: 45812 | D115: 1800009243 | E115: DR | F115: 45812 | G115: 45817 | H115: NA | I115: 256779414007 | J115: 212100 | K115: Trade Debtors (Ctrl) | M115: 01 | N115: USD | O115: 790.89 | P115: INR | Q115: 67613.8 | T115: O0 | U115: 6779224500 | W115: NA | X115: 1 | Y115: Storage- Dec-24, | AC115: 45812 | AG115: =VLOOKUP(I115,'Customer Data'!$B$2:$F$149,4,0) -> 711.8
A116: 100222345 | B116: SIDDHARTHA LOGISTICS FTWZ PRIVATE | C116: 45791 | D116: 1600000602 | E116: DG | F116: 45791 | G116: 45793 | H116: NA | I116: 256779420311 | J116: 212100 | K116: Trade Debtors (Ctrl) | M116: 11 | N116: USD | O116: -1.91 | P116: INR | Q116: -165.58 | T116: O0 | U116: 6779224500 | W116: NA | X116: 1 | Y116: Credit note against 246779412244 | AC116: 45791 | AD116: 45861 | AE116: 1400000797 | AG116: =VLOOKUP(I116,'Customer Data'!$B$2:$F$149,4,0) -> #N/A
A117: 100222345 | B117: SIDDHARTHA LOGISTICS FTWZ PRIVATE | C117: 45791 | D117: 1600000598 | E117: DG | F117: 45791 | G117: 45793 | H117: NA | I117: 256779420307 | J117: 212100 | K117: Trade Debtors (Ctrl) | M117: 11 | N117: USD | O117: -2.86 | P117: INR | Q117: -247.94 | T117: O0 | U117: 6779224500 | W117: NA | X117: 1 | Y117: Credit note against 246779412240 | AC117: 45791 | AD117: 45861 | AE117: 1400000797 | AG117: =VLOOKUP(I117,'Customer Data'!$B$2:$F$149,4,0) -> #N/A
...

Sheet Customer Data
A1: Payment Date | B1: Invoice No | C1: Invoice Dt | D1: Debit (USD) | E1: Credit (USD) | H1: Inv No | I1: Sum of Debit (USD) | J1: Sum of Credit (USD)
B2: 246779410007 | C2: 45708 | E2: 1071.43 | F2: =VLOOKUP(B2,'Ascendus data working'!$B$2:$F$201,5,0) -> 1190.48 | G2: =F2-E2 -> 119.05 | H2: 246779410007 | J2: 1071.43 | K2: =VLOOKUP(H2,'Ascendus data working'!$K$1:$M$189,3,0) -> 1190.48
B3: 246779410138 | C3: 45708 | E3: 1071.43 | F3: =VLOOKUP(B3,'Ascendus data working'!$B$2:$F$201,5,0) -> 1190.48 | G3: =F3-E3 -> 119.05 | H3: 246779410027 | J3: 1071.43 | K3: =VLOOKUP(H3,'Ascendus data working'!$K$1:$M$189,3,0) -> 1190.48
B4: 246779410095 | C4: 45708 | E4: 1071.43 | F4: =VLOOKUP(B4,'Ascendus data working'!$B$2:$F$201,5,0) -> 1190.48 | G4: =F4-E4 -> 119.05 | H4: 246779410095 | J4: 1071.43 | K4: =VLOOKUP(H4,'Ascendus data working'!$K$1:$M$189,3,0) -> 1190.48
B5: 246779410274 | C5: 45708 | E5: 1071.43 | F5: =VLOOKUP(B5,'Ascendus data working'!$B$2:$F$201,5,0) -> 1190.48 | G5: =F5-E5 -> 119.05 | H5: 246779410138 | J5: 1071.43 | K5: =VLOOKUP(H5,'Ascendus data working'!$K$1:$M$189,3,0) -> 1190.48
B6: 246779410027 | C6: 45708 | E6: 1071.43 | F6: =VLOOKUP(B6,'Ascendus data working'!$B$2:$F$201,5,0) -> 1190.48 | G6: =F6-E6 -> 119.05 | H6: 246779410181 | J6: 1049.93 | K6: =VLOOKUP(H6,'Ascendus data working'!$K$1:$M$189,3,0) -> 1166.59
B7: 246779410181 | C7: 45708 | E7: 1049.93 | F7: =VLOOKUP(B7,'Ascendus data working'!$B$2:$F$201,5,0) -> 1166.59 | G7: =F7-E7 -> 116.66 | H7: 246779410224 | J7: 1028.81 | K7: =VLOOKUP(H7,'Ascendus data working'!$K$1:$M$189,3,0) -> 1143.12
B8: 246779410224 | C8: 45708 | E8: 1028.81 | F8: =VLOOKUP(B8,'Ascendus data working'!$B$2:$F$201,5,0) -> 1143.12 | G8: =F8-E8 -> 114.31 | H8: 246779410274 | J8: 1071.43 | K8: =VLOOKUP(H8,'Ascendus data working'!$K$1:$M$189,3,0) -> 1190.48
A9: 45800 | B9: Outgoing payment | C9: 45800 | D9: 7435.89 | F9: =VLOOKUP(B9,'Ascendus data working'!$B$2:$F$201,5,0) -> #N/A | H9: 246779410368 | J9: 320.78 | K9: =VLOOKUP(H9,'Ascendus data working'!$K$1:$M$189,3,0) -> 356.43
B10: 246779410694 | C10: 45720 | E10: 58.17 | F10: =VLOOKUP(B10,'Ascendus data working'!$B$2:$F$201,5,0) -> 59.36 | G10: =F10-E10 -> 1.19 | H10: 246779410394 | J10: 455.27 | K10: =VLOOKUP(H10,'Ascendus data working'!$K$1:$M$189,3,0) -> 505.86
B11: 246779410614 | C11: 45719 | E11: 2.2 | F11: =VLOOKUP(B11,'Ascendus data working'!$B$2:$F$201,5,0) -> 2.25 | G11: =F11-E11 -> 0.05 | H11: 246779410418 | J11: 506.34 | K11: =VLOOKUP(H11,'Ascendus data working'!$K$1:$M$189,3,0) -> 562.6
B12: 246779410615 | C12: 45719 | E12: 8.81 | F12: =VLOOKUP(B12,'Ascendus data working'!$B$2:$F$201,5,0) -> 9 | G12: =F12-E12 -> 0.19 | H12: 246779410510 | J12: 191 | K12: =VLOOKUP(H12,'Ascendus data working'!$K$1:$M$189,3,0) -> 194.9
B13: 246779410975 | C13: 45722 | E13: 28.33 | F13: =VLOOKUP(B13,'Ascendus data working'!$B$2:$F$201,5,0) -> 28.91 | G13: =F13-E13 -> 0.58 | H13: 246779410511 | J13: 13.63 | K13: =VLOOKUP(H13,'Ascendus data working'!$K$1:$M$189,3,0) -> 13.91
B14: 246779410976 | C14: 45722 | E14: 23.51 | F14: =VLOOKUP(B14,'Ascendus data working'!$B$2:$F$201,5,0) -> 24 | G14: =F14-E14 -> 0.49 | H14: 246779410614 | J14: 2.2 | K14: =VLOOKUP(H14,'Ascendus data working'!$K$1:$M$189,3,0) -> 2.25
B15: 246779411190 | C15: 45722 | E15: 16.9 | F15: =VLOOKUP(B15,'Ascendus data working'!$B$2:$F$201,5,0) -> 17.25 | G15: =F15-E15 -> 0.35 | H15: 246779410615 | J15: 8.81 | K15: =VLOOKUP(H15,'Ascendus data working'!$K$1:$M$189,3,0) -> 9
B16: 246779411191 | C16: 45722 | E16: 25.63 | F16: =VLOOKUP(B16,'Ascendus data working'!$B$2:$F$201,5,0) -> 26.15 | G16: =F16-E16 -> 0.52 | H16: 246779410694 | J16: 58.17 | K16: =VLOOKUP(H16,'Ascendus data working'!$K$1:$M$189,3,0) -> 59.36
B17: 246779410511 | C17: 45719 | E17: 13.63 | F17: =VLOOKUP(B17,'Ascendus data working'!$B$2:$F$201,5,0) -> 13.91 | G17: =F17-E17 -> 0.28 | H17: 246779410856 | J17: 17.95 | K17: =VLOOKUP(H17,'Ascendus data working'!$K$1:$M$189,3,0) -> 18.32
B18: 246779412992 | C18: 45735 | E18: 1033.77 | F18: =VLOOKUP(B18,'Ascendus data working'!$B$2:$F$201,5,0) -> 1148.63 | G18: =F18-E18 -> 114.86 | H18: 246779410865 | J18: 370.9 | K18: =VLOOKUP(H18,'Ascendus data working'!$K$1:$M$189,3,0) -> 412.11
B19: 246779410510 | C19: 45719 | E19: 191 | F19: =VLOOKUP(B19,'Ascendus data working'!$B$2:$F$201,5,0) -> 194.9 | G19: =F19-E19 -> 3.9 | H19: 246779410888 | J19: 401.74 | K19: =VLOOKUP(H19,'Ascendus data working'!$K$1:$M$189,3,0) -> 446.38
B20: 246779412240 | C20: 45747 | E20: 2.8 | F20: =VLOOKUP(B20,'Ascendus data working'!$B$2:$F$201,5,0) -> 2.86 | G20: =F20-E20 -> 0.06 | H20: 246779410975 | J20: 28.33 | K20: =VLOOKUP(H20,'Ascendus data working'!$K$1:$M$189,3,0) -> 28.91
B21: 246779411452 | C21: 45747 | E21: 0.93 | F21: =VLOOKUP(B21,'Ascendus data working'!$B$2:$F$201,5,0) -> 0.95 | G21: =F21-E21 -> 0.02 | H21: 246779410976 | J21: 23.51 | K21: =VLOOKUP(H21,'Ascendus data working'!$K$1:$M$189,3,0) -> 24
B22: 246779412242 | C22: 45730 | E22: 4.67 | F22: =VLOOKUP(B22,'Ascendus data working'!$B$2:$F$201,5,0) -> 4.77 | H22: 246779411056 | J22: 58.17 | K22: =VLOOKUP(H22,'Ascendus data working'!$K$1:$M$189,3,0) -> 59.36
B23: 246779412243 | C23: 45730 | E23: 1.87 | F23: =VLOOKUP(B23,'Ascendus data working'!$B$2:$F$201,5,0) -> 1.91 | G23: =F23-E23 -> 0.04 | H23: 246779411057 | J23: 66.32 | K23: =VLOOKUP(H23,'Ascendus data working'!$K$1:$M$189,3,0) -> 67.67
B24: 246779412244 | C24: 45730 | E24: 1.87 | F24: =VLOOKUP(B24,'Ascendus data working'!$B$2:$F$201,5,0) -> 1.91 | G24: =F24-E24 -> 0.04 | H24: 246779411190 | J24: 16.9 | K24: =VLOOKUP(H24,'Ascendus data working'!$K$1:$M$189,3,0) -> 17.25
B25: 246779412245 | C25: 45730 | E25: 4.68 | F25: =VLOOKUP(B25,'Ascendus data working'!$B$2:$F$201,5,0) -> 4.77 | G25: =F25-E25 -> 0.09 | H25: 246779411191 | J25: 25.63 | K25: =VLOOKUP(H25,'Ascendus data working'!$K$1:$M$189,3,0) -> 26.15
B26: 246779411622 | C26: 45733 | E26: 3.74 | F26: =VLOOKUP(B26,'Ascendus data working'!$B$2:$F$201,5,0) -> 3.82 | G26: =F26-E26 -> 0.08 | H26: 246779411253 | J26: 19.6 | K26: =VLOOKUP(H26,'Ascendus data working'!$K$1:$M$189,3,0) -> 20
B27: 246779411623 | C27: 45733 | E27: 1.87 | F27: =VLOOKUP(B27,'Ascendus data working'!$B$2:$F$201,5,0) -> 1.91 | G27: =F27-E27 -> 0.04 | H27: 246779411452 | J27: 0.93 | K27: =VLOOKUP(H27,'Ascendus data working'!$K$1:$M$189,3,0) -> 0.95
B28: 246779410856 | C28: 45748 | E28: 17.95 | F28: =VLOOKUP(B28,'Ascendus data working'!$B$2:$F$201,5,0) -> 18.32 | G28: =F28-E28 -> 0.37 | H28: 246779411485 | J28: 98 | K28: =VLOOKUP(H28,'Ascendus data working'!$K$1:$M$189,3,0) -> 100
B29: 246779411253 | C29: 45748 | E29: 19.6 | F29: =VLOOKUP(B29,'Ascendus data working'!$B$2:$F$201,5,0) -> 20 | G29: =F29-E29 -> 0.4 | H29: 246779411622 | J29: 3.74 | K29: =VLOOKUP(H29,'Ascendus data working'!$K$1:$M$189,3,0) -> 3.82
B30: 246779411056 | C30: 45748 | E30: 58.17 | F30: =VLOOKUP(B30,'Ascendus data working'!$B$2:$F$201,5,0) -> 59.36 | G30: =F30-E30 -> 1.19 | H30: 246779411623 | J30: 1.87 | K30: =VLOOKUP(H30,'Ascendus data working'!$K$1:$M$189,3,0) -> 1.91
B31: 246779411485 | C31: 45748 | E31: 98 | F31: =VLOOKUP(B31,'Ascendus data working'!$B$2:$F$201,5,0) -> 100 | G31: =F31-E31 -> 2 | H31: 246779412240 | J31: 2.8 | K31: =VLOOKUP(H31,'Ascendus data working'!$K$1:$M$189,3,0) -> 2.86
B32: 246779414225 | C32: 45748 | E32: 13.23 | F32: =VLOOKUP(B32,'Ascendus data working'!$B$2:$F$201,5,0) -> 13.5 | G32: =F32-E32 -> 0.27 | H32: 246779412243 | J32: 1.87 | K32: =VLOOKUP(H32,'Ascendus data working'!$K$1:$M$189,3,0) -> 1.91
B33: 246779414607 | C33: 45748 | E33: 2.2 | F33: =VLOOKUP(B33,'Ascendus data working'!$B$2:$F$201,5,0) -> 2.25 | G33: =F33-E33 -> 0.05 | H33: 246779412244 | J33: 1.87 | K33: =VLOOKUP(H33,'Ascendus data working'!$K$1:$M$189,3,0) -> 1.91
B34: 246779414738 | C34: 45748 | E34: 2.2 | F34: =VLOOKUP(B34,'Ascendus data working'!$B$2:$F$201,5,0) -> 2.25 | G34: =F34-E34 -> 0.05 | H34: 246779412245 | J34: 4.68 | K34: =VLOOKUP(H34,'Ascendus data working'!$K$1:$M$189,3,0) -> 4.77
... B68: 256779413490 | C68: 45797 | E68: 2.94 | F68: =VLOOKUP(B68,'Ascendus data working'!$B$2:$F$201,5,0) -> 3 | G68: =F68-E68 -> 0.06 | H68: 256779411891 | J68: 2.2 | K68: =VLOOKUP(H68,'Ascendus data working'!$K$1:$M$189,3,0) -> 2.25
A69: 45856 | B69: Outgoing payment | C69: 45856 | D69: 4602.99 | F69: =VLOOKUP(B69,'Ascendus data working'!$B$2:$F$201,5,0) -> #N/A | H69: 256779412103 | J69: 41.67 | K69: =VLOOKUP(H69,'Ascendus data working'!$K$1:$M$189,3,0) -> 42.53
B70: 256779414354 | C70: 45818 | E70: 1052.75 | F70: =VLOOKUP(B70,'Ascendus data working'!$B$2:$F$201,5,0) -> 1169.5906 | G70: =F70-E70 -> 116.84064 | H70: 256779412113 | J70: 744.73 | K70: =VLOOKUP(H70,'Ascendus data working'!$K$1:$M$189,3,0) -> 827.48
B71: 246779411057 | C71: 45748 | E71: 66.32 | F71: =VLOOKUP(B71,'Ascendus data working'!$B$2:$F$201,5,0) -> 67.67 | G71: =F71-E71 -> 1.35 | H71: 256779412153 | J71: 1048.83 | K71: =VLOOKUP(H71,'Ascendus data working'!$K$1:$M$189,3,0) -> 1165.37
B72: 256779414912 | C72: 45842 | E72: 1046.5 | F72: =VLOOKUP(B72,'Ascendus data working'!$B$2:$F$201,5,0) -> 1162.7907 | G72: =F72-E72 -> 116.2907 | H72: 256779412617 | J72: 376.93 | K72: =VLOOKUP(H72,'Ascendus data working'!$K$1:$M$189,3,0) -> 384.63
B73: 256779415190 | C73: 45842 | E73: 621.63 | F73: =VLOOKUP(B73,'Ascendus data working'!$B$2:$F$201,5,0) -> 690.7 | G73: =F73-E73 -> 69.07 | H73: 256779412660 | J73: 7.34 | K73: =VLOOKUP(H73,'Ascendus data working'!$K$1:$M$189,3,0) -> 7.5
B74: 256779414833 | C74: 45842 | E74: 2.94 | F74: =VLOOKUP(B74,'Ascendus data working'!$B$2:$F$201,5,0) -> 3 | G74: =F74-E74 -> 0.06 | H74: 256779412932 | J74: 65.52 | K74: =VLOOKUP(H74,'Ascendus data working'!$K$1:$M$189,3,0) -> 66.86
B75: 256779415485 | C75: 45856 | E75: 16.9 | F75: =VLOOKUP(B75,'Ascendus data working'!$B$2:$F$201,5,0) -> 17.25 | G75: =F75-E75 -> 0.35 | H75: 256779413142 | J75: 1046.71 | K75: =VLOOKUP(H75,'Ascendus data working'!$K$1:$M$189,3,0) -> 1162.7907
B76: 256779415533 | C76: 45856 | E76: 21.31 | F76: =VLOOKUP(B76,'Ascendus data working'!$B$2:$F$201,5,0) -> 21.75 | G76: =F76-E76 -> 0.44 | H76: 256779413272 | J76: 24.77 | K76: =VLOOKUP(H76,'Ascendus data working'!$K$1:$M$189,3,0) -> 25.28
B77: 256779415772 | C77: 45857 | E77: 58.24 | F77: =VLOOKUP(B77,'Ascendus data working'!$B$2:$F$201,5,0) -> 59.43 | G77: =F77-E77 -> 1.19 | H77: 256779413361 | J77: 2.94 | K77: =VLOOKUP(H77,'Ascendus data working'!$K$1:$M$189,3,0) -> 3
B78: 256779416024 | C78: 45870 | E78: 1046.14 | F78: =VLOOKUP(B78,'Ascendus data working'!$B$2:$F$201,5,0) -> 1162.7907 | G78: =F78-E78 -> 116.6507 | H78: 256779413490 | J78: 2.94 | K78: =VLOOKUP(H78,'Ascendus data working'!$K$1:$M$189,3,0) -> 3
B79: 256779416082 | C79: 45877 | E79: 683.7 | F79: =VLOOKUP(B79,'Ascendus data working'!$B$2:$F$201,5,0) -> 759.67 | G79: =F79-E79 -> 75.97 | H79: 256779413893 | J79: 717.81 | K79: =VLOOKUP(H79,'Ascendus data working'!$K$1:$M$189,3,0) -> 797.57
B80: 256779416446 | C80: 45877 | E80: 2.23 | F80: =VLOOKUP(B80,'Ascendus data working'!$B$2:$F$201,5,0) -> 2.28 | G80: =F80-E80 -> 0.05 | H80: 256779414003 | J80: 726.65 | K80: =VLOOKUP(H80,'Ascendus data working'!$K$1:$M$189,3,0) -> 807.39
B81: 256779416257 | C81: 45877 | E81: 22.42 | F81: =VLOOKUP(B81,'Ascendus data working'!$B$2:$F$201,5,0) -> 22.87 | G81: =F81-E81 -> 0.45 | H81: 256779414004 | J81: 727.34 | K81: =VLOOKUP(H81,'Ascendus data working'!$K$1:$M$189,3,0) -> 808.16
... B89: 256779416616 | C89: 45889 | E89: 62.38 | F89: =VLOOKUP(B89,'Ascendus data working'!$B$2:$F$201,5,0) -> 63.65 | G89: =F89-E89 -> 1.27 | H89: 256779415485 | J89: 16.9 | K89: =VLOOKUP(H89,'Ascendus data working'!$K$1:$M$189,3,0) -> 17.25
A90: 45945 | B90: Outgoing payment | C90: 45945 | D90: 4875.15 | F90: =VLOOKUP(B90,'Ascendus data working'!$B$2:$F$201,5,0) -> #N/A | H90: 256779415533 | J90: 21.31 | K90: =VLOOKUP(H90,'Ascendus data working'!$K$1:$M$189,3,0) -> 21.75
B91: 256779417344 | C91: 45904 | E91: 1028.4 | F91: =VLOOKUP(B91,'Ascendus data working'!$B$2:$F$201,5,0) -> 1142.8571 | G91: =F91-E91 -> 114.45714 | H91: 256779415772 | J91: 58.24 | K91: =VLOOKUP(H91,'Ascendus data working'!$K$1:$M$189,3,0) -> 59.43
B92: 256779417328 | C92: 45904 | E92: 2.2 | F92: =VLOOKUP(B92,'Ascendus data working'!$B$2:$F$201,5,0) -> 2.25 | G92: =F92-E92 -> 0.05 | H92: 256779416024 | J92: 1046.14 | K92: =VLOOKUP(H92,'Ascendus data working'!$K$1:$M$189,3,0) -> 1162.7907
B93: 256779416912 | C93: 45904 | E93: 44.06 | F93: =VLOOKUP(B93,'Ascendus data working'!$B$2:$F$201,5,0) -> 44.96 | G93: =F93-E93 -> 0.9 | H93: 256779416082 | J93: 683.7 | K93: =VLOOKUP(H93,'Ascendus data working'!$K$1:$M$189,3,0) -> 759.67
B94: 256779417136 | C94: 45904 | E94: 1.68 | F94: =VLOOKUP(B94,'Ascendus data working'!$B$2:$F$201,5,0) -> 1.71 | G94: =F94-E94 -> 0.03 | H94: 256779416182 | J94: 17.64 | K94: =VLOOKUP(H94,'Ascendus data working'!$K$1:$M$189,3,0) -> 18
B95: 256779416949 | C95: 45904 | E95: 29.55 | F95: =VLOOKUP(B95,'Ascendus data working'!$B$2:$F$201,5,0) -> 30.16 | G95: =F95-E95 -> 0.61 | H95: 256779416228 | J95: 2.94 | K95: =VLOOKUP(H95,'Ascendus data working'!$K$1:$M$189,3,0) -> 3
B96: 256779417528 | C96: 45918 | E96: 2.94 | F96: =VLOOKUP(B96,'Ascendus data working'!$B$2:$F$201,5,0) -> 3 | G96: =F96-E96 -> 0.06 | H96: 256779416246 | J96: 69.54 | K96: =VLOOKUP(H96,'Ascendus data working'!$K$1:$M$189,3,0) -> 70.95
B97: 256779417871 | C97: 45935 | E97: 1020.52 | F97: =VLOOKUP(B97,'Ascendus data working'!$B$2:$F$201,5,0) -> 1133.9111 | G97: =F97-E97 -> 113.39111 | H97: 256779416257 | J97: 22.42 | K97: =VLOOKUP(H97,'Ascendus data working'!$K$1:$M$189,3,0) -> 22.87
B98: 256779417860 | C98: 45967 | E98: 49 | F98: =VLOOKUP(B98,'Ascendus data working'!$B$2:$F$201,5,0) -> 50 | G98: =F98-E98 -> 1 | H98: 256779416446 | J98: 2.23 | K98: =VLOOKUP(H98,'Ascendus data working'!$K$1:$M$189,3,0) -> 2.28
B99: 256779418704 | C99: 45935 | E99: 2.2 | F99: =VLOOKUP(B99,'Ascendus data working'!$B$2:$F$201,5,0) -> 2.25 | G99: =F99-E99 -> 0.05 | H99: 256779416604 | J99: 16.96 | K99: =VLOOKUP(H99,'Ascendus data working'!$K$1:$M$189,3,0) -> 17.31
B100: 256779418478 | C100: 45935 | E100: 27.09 | F100: =VLOOKUP(B100,'Ascendus data working'!$B$2:$F$201,5,0) -> 27.64 | G100: =F100-E100 -> 0.55 | H100: 256779416616 | J100: 62.38 | K100: =VLOOKUP(H100,'Ascendus data working'!$K$1:$M$189,3,0) -> 63.65
B101: 256779418354 | C101: 45935 | E101: 106.77 | F101: =VLOOKUP(B101,'Ascendus data working'!$B$2:$F$201,5,0) -> 108.95 | G101: =F101-E101 -> 2.18 | H101: 256779416847 | J101: 27.27 | K101: =VLOOKUP(H101,'Ascendus data working'!$K$1:$M$189,3,0) -> 27.83
B102: 256779418342 | C102: 45937 | E102: 449.77 | F102: =VLOOKUP(B102,'Ascendus data working'!$B$2:$F$201,5,0) -> 458.95 | G102: =F102-E102 -> 9.18 | H102: 256779416882 | J102: 12.57 | K102: =VLOOKUP(H102,'Ascendus data working'!$K$1:$M$189,3,0) -> 12.83
... B131: 256779421975 | C131: 45943 | E131: -402.34 | F131: =VLOOKUP(B131,'Ascendus data working'!$B$2:$F$201,5,0) -> -447.05 | G131: =F131-E131 -> -44.71 | H131: 256779421975 | J131: -402.34 | K131: =VLOOKUP(H131,'Ascendus data working'!$K$1:$M$189,3,0) -> -447.05
B132: Outgoing payment | C132: 46050 | D132: 10721.42 | F132: =VLOOKUP(B132,'Ascendus data working'!$B$2:$F$201,5,0) -> #N/A | H132: 256779421976 | J132: -100.12 | K132: =VLOOKUP(H132,'Ascendus data working'!$K$1:$M$189,3,0) -> -111.25
B133: 256779419966 | C133: 45995 | E133: 1014.65 | F133: =VLOOKUP(B133,'Ascendus data working'!$B$2:$F$201,5,0) -> 1127.3889 | G133: =F133-E133 -> 112.73889 | H133: 256779421977 | J133: -338.76 | K133: =VLOOKUP(H133,'Ascendus data working'!$K$1:$M$189,3,0) -> -376.4
B134: 256779419870 | C134: 45999 | E134: 18.58 | F134: =VLOOKUP(B134,'Ascendus data working'!$B$2:$F$201,5,0) -> 18.96 | G134: =F134-E134 -> 0.38 | H134: 256779421978 | J134: -352.39 | K134: =VLOOKUP(H134,'Ascendus data working'!$K$1:$M$189,3,0) -> -391.55
B135: 256779440005 | C135: 46024 | E135: 406.163 | F135: =VLOOKUP(B135,'Ascendus data working'!$B$2:$F$201,5,0) -> 451.3 | G135: =F135-E135 -> 45.137 | H135: 256779422208 | J135: -21.53 | K135: =VLOOKUP(H135,'Ascendus data working'!$K$1:$M$189,3,0) -> -23.92
B136: 256779440119 | C136: 46027 | E136: 16.9 | F136: =VLOOKUP(B136,'Ascendus data working'!$B$2:$F$201,5,0) -> 17.25 | G136: =F136-E136 -> 0.35 | H136: 256779422209 | J136: -41.07 | K136: =VLOOKUP(H136,'Ascendus data working'!$K$1:$M$189,3,0) -> -45.63
B137: 256779440082 | C137: 46027 | E137: 2.2 | F137: =VLOOKUP(B137,'Ascendus data working'!$B$2:$F$201,5,0) -> 2.25 | G137: =F137-E137 -> 0.05 | H137: 256779422211 | J137: -19.76 | K137: =VLOOKUP(H137,'Ascendus data working'!$K$1:$M$189,3,0) -> -21.96
B138: 256779440070 | C138: 46027 | E138: 7.04 | F138: =VLOOKUP(B138,'Ascendus data working'!$B$2:$F$201,5,0) -> 7.18 | G138: =F138-E138 -> 0.14 | H138: 256779440005 | J138: 406.163 | K138: =VLOOKUP(H138,'Ascendus data working'!$K$1:$M$189,3,0) -> 451.3
B139: 256779440102 | C139: 46027 | E139: 19.98 | F139: =VLOOKUP(B139,'Ascendus data working'!$B$2:$F$201,5,0) -> 20.39 | G139: =F139-E139 -> 0.41 | H139: 256779440070 | J139: 7.04 | K139: =VLOOKUP(H139,'Ascendus data working'!$K$1:$M$189,3,0) -> 7.18
B140: 256779440305 | C140: 46028 | E140: 991.81 | F140: =VLOOKUP(B140,'Ascendus data working'!$B$2:$F$201,5,0) -> 1102.0111 | G140: =F140-E140 -> 110.20111 | H140: 256779440082 | J140: 2.2 | K140: =VLOOKUP(H140,'Ascendus data working'!$K$1:$M$189,3,0) -> 2.25
B141: 256779440431 | C141: 46045 | E141: 2.94 | F141: =VLOOKUP(B141,'Ascendus data working'!$B$2:$F$201,5,0) -> 3 | G141: =F141-E141 -> 0.06 | H141: 256779440102 | J141: 19.98 | K141: =VLOOKUP(H141,'Ascendus data working'!$K$1:$M$189,3,0) -> 20.39
B142: 256779440236 | C142: 46028 | E142: 454.71 | F142: =VLOOKUP(B142,'Ascendus data working'!$B$2:$F$201,5,0) -> 505.23 | G142: =F142-E142 -> 50.52 | H142: 256779440119 | J142: 16.9 | K142: =VLOOKUP(H142,'Ascendus data working'!$K$1:$M$189,3,0) -> 17.25
B143: 256779410791 | C143: 45751 | E143: 397.08 | F143: =VLOOKUP(B143,'Ascendus data working'!$B$2:$F$201,5,0) -> 441.2 | G143: =F143-E143 -> 44.12 | H143: 256779440236 | J143: 454.71 | K143: =VLOOKUP(H143,'Ascendus data working'!$K$1:$M$189,3,0) -> 505.23
B144: 256779412113 | C144: 45763 | E144: 744.73 | F144: =VLOOKUP(B144,'Ascendus data working'!$B$2:$F$201,5,0) -> 827.48 | G144: =F144-E144 -> 82.75 | H144: 256779440305 | J144: 991.81 | K144: =VLOOKUP(H144,'Ascendus data working'!$K$1:$M$189,3,0) -> 1098.9011
B145: 256779413893 | C145: 45805 | E145: 717.81 | F145: =VLOOKUP(B145,'Ascendus data working'!$B$2:$F$201,5,0) -> 797.57 | G145: =F145-E145 -> 79.76 | H145: 256779440431 | J145: 2.94 | K145: =VLOOKUP(H145,'Ascendus data working'!$K$1:$M$189,3,0) -> 3
B146: 256779417077 | C146: 45906 | E146: 509.36 | F146: =VLOOKUP(B146,'Ascendus data working'!$B$2:$F$201,5,0) -> 565.97 | G146: =F146-E146 -> 56.61 | H146: Outgoing payment | I146: 27635.45
B147: 256779422208 | C147: 46035 | E147: -21.53 | F147: =VLOOKUP(B147,'Ascendus data working'!$B$2:$F$201,5,0) -> -23.92 | G147: =F147-E147 -> -2.39
B148: 256779422209 | C148: 46035 | E148: -41.07 | F148: =VLOOKUP(B148,'Ascendus data working'!$B$2:$F$201,5,0) -> -45.63 | G148: =F148-E148 -> -4.56
B149: 256779422211 | C149: 46035 | E149: -19.76 | F149: =VLOOKUP(B149,'Ascendus data working'!$B$2:$F$201,5,0) -> -21.96 | G149: =F149-E149 -> -2.2
A151: Total | D151: =SUM(D2:D149) -> 27635.45 | E151: =SUM(E2:E149) -> 32857.043 | F151: =E151-D151 -> 5221.593
